import com.whatsapp.App;
import java.io.IOException;
import java.io.InputStream;
import java.io.InputStreamReader;
import java.io.Reader;
import java.util.Hashtable;
import org.xmlpull.v1.XmlPullParser;
import org.xmlpull.v1.XmlPullParserException;

public class zb
  implements XmlPullParser
{
  public static int I;
  private static final String[] J;
  private String[] A;
  private int B;
  private String C;
  private int[] D;
  private int E;
  private boolean F;
  private boolean G;
  private boolean H;
  private Object a;
  private String b;
  private Boolean c;
  private boolean d;
  private boolean e;
  private Hashtable f;
  private int g;
  private String[] h = new String[16];
  private String[] i = new String[8];
  private int[] j = new int[4];
  private Reader k;
  private String l;
  private char[] m;
  private int n;
  private int o;
  private int p;
  private int q;
  private char[] r;
  private int s;
  private int t;
  private boolean u;
  private String v;
  private String w;
  private String x;
  private boolean y;
  private int z;

  // ERROR //
  static
  {
    // Byte code:
    //   0: bipush 74
    //   2: anewarray 55	java/lang/String
    //   5: astore_0
    //   6: ldc 57
    //   8: invokevirtual 61	java/lang/String:toCharArray	()[C
    //   11: astore_1
    //   12: aload_1
    //   13: arraylength
    //   14: istore_2
    //   15: iconst_0
    //   16: istore_3
    //   17: iload_2
    //   18: iload_3
    //   19: if_icmpgt +3113 -> 3132
    //   22: aload_0
    //   23: iconst_0
    //   24: new 55	java/lang/String
    //   27: dup
    //   28: aload_1
    //   29: invokespecial 65	java/lang/String:<init>	([C)V
    //   32: invokevirtual 69	java/lang/String:intern	()Ljava/lang/String;
    //   35: aastore
    //   36: ldc 71
    //   38: invokevirtual 61	java/lang/String:toCharArray	()[C
    //   41: astore 6
    //   43: aload 6
    //   45: arraylength
    //   46: istore 7
    //   48: iconst_0
    //   49: istore 8
    //   51: iload 7
    //   53: iload 8
    //   55: if_icmpgt +3164 -> 3219
    //   58: aload_0
    //   59: iconst_1
    //   60: new 55	java/lang/String
    //   63: dup
    //   64: aload 6
    //   66: invokespecial 65	java/lang/String:<init>	([C)V
    //   69: invokevirtual 69	java/lang/String:intern	()Ljava/lang/String;
    //   72: aastore
    //   73: ldc 73
    //   75: invokevirtual 61	java/lang/String:toCharArray	()[C
    //   78: astore 11
    //   80: aload 11
    //   82: arraylength
    //   83: istore 12
    //   85: iconst_0
    //   86: istore 13
    //   88: iload 12
    //   90: iload 13
    //   92: if_icmpgt +3217 -> 3309
    //   95: aload_0
    //   96: iconst_2
    //   97: new 55	java/lang/String
    //   100: dup
    //   101: aload 11
    //   103: invokespecial 65	java/lang/String:<init>	([C)V
    //   106: invokevirtual 69	java/lang/String:intern	()Ljava/lang/String;
    //   109: aastore
    //   110: ldc 75
    //   112: invokevirtual 61	java/lang/String:toCharArray	()[C
    //   115: astore 16
    //   117: aload 16
    //   119: arraylength
    //   120: istore 17
    //   122: iconst_0
    //   123: istore 18
    //   125: iload 17
    //   127: iload 18
    //   129: if_icmpgt +3272 -> 3401
    //   132: aload_0
    //   133: iconst_3
    //   134: new 55	java/lang/String
    //   137: dup
    //   138: aload 16
    //   140: invokespecial 65	java/lang/String:<init>	([C)V
    //   143: invokevirtual 69	java/lang/String:intern	()Ljava/lang/String;
    //   146: aastore
    //   147: ldc 77
    //   149: invokevirtual 61	java/lang/String:toCharArray	()[C
    //   152: astore 21
    //   154: aload 21
    //   156: arraylength
    //   157: istore 22
    //   159: iconst_0
    //   160: istore 23
    //   162: iload 22
    //   164: iload 23
    //   166: if_icmpgt +3327 -> 3493
    //   169: aload_0
    //   170: iconst_4
    //   171: new 55	java/lang/String
    //   174: dup
    //   175: aload 21
    //   177: invokespecial 65	java/lang/String:<init>	([C)V
    //   180: invokevirtual 69	java/lang/String:intern	()Ljava/lang/String;
    //   183: aastore
    //   184: ldc 79
    //   186: invokevirtual 61	java/lang/String:toCharArray	()[C
    //   189: astore 26
    //   191: aload 26
    //   193: arraylength
    //   194: istore 27
    //   196: iconst_0
    //   197: istore 28
    //   199: iload 27
    //   201: iload 28
    //   203: if_icmpgt +3382 -> 3585
    //   206: aload_0
    //   207: iconst_5
    //   208: new 55	java/lang/String
    //   211: dup
    //   212: aload 26
    //   214: invokespecial 65	java/lang/String:<init>	([C)V
    //   217: invokevirtual 69	java/lang/String:intern	()Ljava/lang/String;
    //   220: aastore
    //   221: ldc 81
    //   223: invokevirtual 61	java/lang/String:toCharArray	()[C
    //   226: astore 31
    //   228: aload 31
    //   230: arraylength
    //   231: istore 32
    //   233: iconst_0
    //   234: istore 33
    //   236: iload 32
    //   238: iload 33
    //   240: if_icmpgt +3437 -> 3677
    //   243: aload_0
    //   244: bipush 6
    //   246: new 55	java/lang/String
    //   249: dup
    //   250: aload 31
    //   252: invokespecial 65	java/lang/String:<init>	([C)V
    //   255: invokevirtual 69	java/lang/String:intern	()Ljava/lang/String;
    //   258: aastore
    //   259: ldc 83
    //   261: invokevirtual 61	java/lang/String:toCharArray	()[C
    //   264: astore 36
    //   266: aload 36
    //   268: arraylength
    //   269: istore 37
    //   271: iconst_0
    //   272: istore 38
    //   274: iload 37
    //   276: iload 38
    //   278: if_icmpgt +3491 -> 3769
    //   281: aload_0
    //   282: bipush 7
    //   284: new 55	java/lang/String
    //   287: dup
    //   288: aload 36
    //   290: invokespecial 65	java/lang/String:<init>	([C)V
    //   293: invokevirtual 69	java/lang/String:intern	()Ljava/lang/String;
    //   296: aastore
    //   297: ldc 85
    //   299: invokevirtual 61	java/lang/String:toCharArray	()[C
    //   302: astore 41
    //   304: aload 41
    //   306: arraylength
    //   307: istore 42
    //   309: iconst_0
    //   310: istore 43
    //   312: iload 42
    //   314: iload 43
    //   316: if_icmpgt +3545 -> 3861
    //   319: aload_0
    //   320: bipush 8
    //   322: new 55	java/lang/String
    //   325: dup
    //   326: aload 41
    //   328: invokespecial 65	java/lang/String:<init>	([C)V
    //   331: invokevirtual 69	java/lang/String:intern	()Ljava/lang/String;
    //   334: aastore
    //   335: ldc 87
    //   337: invokevirtual 61	java/lang/String:toCharArray	()[C
    //   340: astore 46
    //   342: aload 46
    //   344: arraylength
    //   345: istore 47
    //   347: iconst_0
    //   348: istore 48
    //   350: iload 47
    //   352: iload 48
    //   354: if_icmpgt +3599 -> 3953
    //   357: aload_0
    //   358: bipush 9
    //   360: new 55	java/lang/String
    //   363: dup
    //   364: aload 46
    //   366: invokespecial 65	java/lang/String:<init>	([C)V
    //   369: invokevirtual 69	java/lang/String:intern	()Ljava/lang/String;
    //   372: aastore
    //   373: ldc 89
    //   375: invokevirtual 61	java/lang/String:toCharArray	()[C
    //   378: astore 51
    //   380: aload 51
    //   382: arraylength
    //   383: istore 52
    //   385: iconst_0
    //   386: istore 53
    //   388: iload 52
    //   390: iload 53
    //   392: if_icmpgt +3653 -> 4045
    //   395: aload_0
    //   396: bipush 10
    //   398: new 55	java/lang/String
    //   401: dup
    //   402: aload 51
    //   404: invokespecial 65	java/lang/String:<init>	([C)V
    //   407: invokevirtual 69	java/lang/String:intern	()Ljava/lang/String;
    //   410: aastore
    //   411: ldc 91
    //   413: invokevirtual 61	java/lang/String:toCharArray	()[C
    //   416: astore 56
    //   418: aload 56
    //   420: arraylength
    //   421: istore 57
    //   423: iconst_0
    //   424: istore 58
    //   426: iload 57
    //   428: iload 58
    //   430: if_icmpgt +3707 -> 4137
    //   433: aload_0
    //   434: bipush 11
    //   436: new 55	java/lang/String
    //   439: dup
    //   440: aload 56
    //   442: invokespecial 65	java/lang/String:<init>	([C)V
    //   445: invokevirtual 69	java/lang/String:intern	()Ljava/lang/String;
    //   448: aastore
    //   449: ldc 93
    //   451: invokevirtual 61	java/lang/String:toCharArray	()[C
    //   454: astore 61
    //   456: aload 61
    //   458: arraylength
    //   459: istore 62
    //   461: iconst_0
    //   462: istore 63
    //   464: iload 62
    //   466: iload 63
    //   468: if_icmpgt +3761 -> 4229
    //   471: aload_0
    //   472: bipush 12
    //   474: new 55	java/lang/String
    //   477: dup
    //   478: aload 61
    //   480: invokespecial 65	java/lang/String:<init>	([C)V
    //   483: invokevirtual 69	java/lang/String:intern	()Ljava/lang/String;
    //   486: aastore
    //   487: ldc 95
    //   489: invokevirtual 61	java/lang/String:toCharArray	()[C
    //   492: astore 66
    //   494: aload 66
    //   496: arraylength
    //   497: istore 67
    //   499: iconst_0
    //   500: istore 68
    //   502: iload 67
    //   504: iload 68
    //   506: if_icmpgt +3815 -> 4321
    //   509: aload_0
    //   510: bipush 13
    //   512: new 55	java/lang/String
    //   515: dup
    //   516: aload 66
    //   518: invokespecial 65	java/lang/String:<init>	([C)V
    //   521: invokevirtual 69	java/lang/String:intern	()Ljava/lang/String;
    //   524: aastore
    //   525: ldc 97
    //   527: invokevirtual 61	java/lang/String:toCharArray	()[C
    //   530: astore 71
    //   532: aload 71
    //   534: arraylength
    //   535: istore 72
    //   537: iconst_0
    //   538: istore 73
    //   540: iload 72
    //   542: iload 73
    //   544: if_icmpgt +3869 -> 4413
    //   547: aload_0
    //   548: bipush 14
    //   550: new 55	java/lang/String
    //   553: dup
    //   554: aload 71
    //   556: invokespecial 65	java/lang/String:<init>	([C)V
    //   559: invokevirtual 69	java/lang/String:intern	()Ljava/lang/String;
    //   562: aastore
    //   563: ldc 99
    //   565: invokevirtual 61	java/lang/String:toCharArray	()[C
    //   568: astore 76
    //   570: aload 76
    //   572: arraylength
    //   573: istore 77
    //   575: iconst_0
    //   576: istore 78
    //   578: iload 77
    //   580: iload 78
    //   582: if_icmpgt +3923 -> 4505
    //   585: aload_0
    //   586: bipush 15
    //   588: new 55	java/lang/String
    //   591: dup
    //   592: aload 76
    //   594: invokespecial 65	java/lang/String:<init>	([C)V
    //   597: invokevirtual 69	java/lang/String:intern	()Ljava/lang/String;
    //   600: aastore
    //   601: ldc 101
    //   603: invokevirtual 61	java/lang/String:toCharArray	()[C
    //   606: astore 81
    //   608: aload 81
    //   610: arraylength
    //   611: istore 82
    //   613: iconst_0
    //   614: istore 83
    //   616: iload 82
    //   618: iload 83
    //   620: if_icmpgt +3977 -> 4597
    //   623: aload_0
    //   624: bipush 16
    //   626: new 55	java/lang/String
    //   629: dup
    //   630: aload 81
    //   632: invokespecial 65	java/lang/String:<init>	([C)V
    //   635: invokevirtual 69	java/lang/String:intern	()Ljava/lang/String;
    //   638: aastore
    //   639: ldc 103
    //   641: invokevirtual 61	java/lang/String:toCharArray	()[C
    //   644: astore 86
    //   646: aload 86
    //   648: arraylength
    //   649: istore 87
    //   651: iconst_0
    //   652: istore 88
    //   654: iload 87
    //   656: iload 88
    //   658: if_icmpgt +4031 -> 4689
    //   661: aload_0
    //   662: bipush 17
    //   664: new 55	java/lang/String
    //   667: dup
    //   668: aload 86
    //   670: invokespecial 65	java/lang/String:<init>	([C)V
    //   673: invokevirtual 69	java/lang/String:intern	()Ljava/lang/String;
    //   676: aastore
    //   677: ldc 105
    //   679: invokevirtual 61	java/lang/String:toCharArray	()[C
    //   682: astore 91
    //   684: aload 91
    //   686: arraylength
    //   687: istore 92
    //   689: iconst_0
    //   690: istore 93
    //   692: iload 92
    //   694: iload 93
    //   696: if_icmpgt +4085 -> 4781
    //   699: aload_0
    //   700: bipush 18
    //   702: new 55	java/lang/String
    //   705: dup
    //   706: aload 91
    //   708: invokespecial 65	java/lang/String:<init>	([C)V
    //   711: invokevirtual 69	java/lang/String:intern	()Ljava/lang/String;
    //   714: aastore
    //   715: ldc 107
    //   717: invokevirtual 61	java/lang/String:toCharArray	()[C
    //   720: astore 96
    //   722: aload 96
    //   724: arraylength
    //   725: istore 97
    //   727: iconst_0
    //   728: istore 98
    //   730: iload 97
    //   732: iload 98
    //   734: if_icmpgt +4139 -> 4873
    //   737: aload_0
    //   738: bipush 19
    //   740: new 55	java/lang/String
    //   743: dup
    //   744: aload 96
    //   746: invokespecial 65	java/lang/String:<init>	([C)V
    //   749: invokevirtual 69	java/lang/String:intern	()Ljava/lang/String;
    //   752: aastore
    //   753: ldc 109
    //   755: invokevirtual 61	java/lang/String:toCharArray	()[C
    //   758: astore 101
    //   760: aload 101
    //   762: arraylength
    //   763: istore 102
    //   765: iconst_0
    //   766: istore 103
    //   768: iload 102
    //   770: iload 103
    //   772: if_icmpgt +4193 -> 4965
    //   775: aload_0
    //   776: bipush 20
    //   778: new 55	java/lang/String
    //   781: dup
    //   782: aload 101
    //   784: invokespecial 65	java/lang/String:<init>	([C)V
    //   787: invokevirtual 69	java/lang/String:intern	()Ljava/lang/String;
    //   790: aastore
    //   791: ldc 111
    //   793: invokevirtual 61	java/lang/String:toCharArray	()[C
    //   796: astore 106
    //   798: aload 106
    //   800: arraylength
    //   801: istore 107
    //   803: iconst_0
    //   804: istore 108
    //   806: iload 107
    //   808: iload 108
    //   810: if_icmpgt +4247 -> 5057
    //   813: aload_0
    //   814: bipush 21
    //   816: new 55	java/lang/String
    //   819: dup
    //   820: aload 106
    //   822: invokespecial 65	java/lang/String:<init>	([C)V
    //   825: invokevirtual 69	java/lang/String:intern	()Ljava/lang/String;
    //   828: aastore
    //   829: ldc 113
    //   831: invokevirtual 61	java/lang/String:toCharArray	()[C
    //   834: astore 111
    //   836: aload 111
    //   838: arraylength
    //   839: istore 112
    //   841: iconst_0
    //   842: istore 113
    //   844: iload 112
    //   846: iload 113
    //   848: if_icmpgt +4301 -> 5149
    //   851: aload_0
    //   852: bipush 22
    //   854: new 55	java/lang/String
    //   857: dup
    //   858: aload 111
    //   860: invokespecial 65	java/lang/String:<init>	([C)V
    //   863: invokevirtual 69	java/lang/String:intern	()Ljava/lang/String;
    //   866: aastore
    //   867: ldc 115
    //   869: invokevirtual 61	java/lang/String:toCharArray	()[C
    //   872: astore 116
    //   874: aload 116
    //   876: arraylength
    //   877: istore 117
    //   879: iconst_0
    //   880: istore 118
    //   882: iload 117
    //   884: iload 118
    //   886: if_icmpgt +4355 -> 5241
    //   889: aload_0
    //   890: bipush 23
    //   892: new 55	java/lang/String
    //   895: dup
    //   896: aload 116
    //   898: invokespecial 65	java/lang/String:<init>	([C)V
    //   901: invokevirtual 69	java/lang/String:intern	()Ljava/lang/String;
    //   904: aastore
    //   905: ldc 117
    //   907: invokevirtual 61	java/lang/String:toCharArray	()[C
    //   910: astore 121
    //   912: aload 121
    //   914: arraylength
    //   915: istore 122
    //   917: iconst_0
    //   918: istore 123
    //   920: iload 122
    //   922: iload 123
    //   924: if_icmpgt +4409 -> 5333
    //   927: aload_0
    //   928: bipush 24
    //   930: new 55	java/lang/String
    //   933: dup
    //   934: aload 121
    //   936: invokespecial 65	java/lang/String:<init>	([C)V
    //   939: invokevirtual 69	java/lang/String:intern	()Ljava/lang/String;
    //   942: aastore
    //   943: ldc 119
    //   945: invokevirtual 61	java/lang/String:toCharArray	()[C
    //   948: astore 126
    //   950: aload 126
    //   952: arraylength
    //   953: istore 127
    //   955: iconst_0
    //   956: istore 128
    //   958: iload 127
    //   960: iload 128
    //   962: if_icmpgt +4463 -> 5425
    //   965: aload_0
    //   966: bipush 25
    //   968: new 55	java/lang/String
    //   971: dup
    //   972: aload 126
    //   974: invokespecial 65	java/lang/String:<init>	([C)V
    //   977: invokevirtual 69	java/lang/String:intern	()Ljava/lang/String;
    //   980: aastore
    //   981: ldc 121
    //   983: invokevirtual 61	java/lang/String:toCharArray	()[C
    //   986: astore 131
    //   988: aload 131
    //   990: arraylength
    //   991: istore 132
    //   993: iconst_0
    //   994: istore 133
    //   996: iload 132
    //   998: iload 133
    //   1000: if_icmpgt +4517 -> 5517
    //   1003: aload_0
    //   1004: bipush 26
    //   1006: new 55	java/lang/String
    //   1009: dup
    //   1010: aload 131
    //   1012: invokespecial 65	java/lang/String:<init>	([C)V
    //   1015: invokevirtual 69	java/lang/String:intern	()Ljava/lang/String;
    //   1018: aastore
    //   1019: ldc 123
    //   1021: invokevirtual 61	java/lang/String:toCharArray	()[C
    //   1024: astore 136
    //   1026: aload 136
    //   1028: arraylength
    //   1029: istore 137
    //   1031: iconst_0
    //   1032: istore 138
    //   1034: iload 137
    //   1036: iload 138
    //   1038: if_icmpgt +4571 -> 5609
    //   1041: aload_0
    //   1042: bipush 27
    //   1044: new 55	java/lang/String
    //   1047: dup
    //   1048: aload 136
    //   1050: invokespecial 65	java/lang/String:<init>	([C)V
    //   1053: invokevirtual 69	java/lang/String:intern	()Ljava/lang/String;
    //   1056: aastore
    //   1057: ldc 125
    //   1059: invokevirtual 61	java/lang/String:toCharArray	()[C
    //   1062: astore 141
    //   1064: aload 141
    //   1066: arraylength
    //   1067: istore 142
    //   1069: iconst_0
    //   1070: istore 143
    //   1072: iload 142
    //   1074: iload 143
    //   1076: if_icmpgt +4625 -> 5701
    //   1079: aload_0
    //   1080: bipush 28
    //   1082: new 55	java/lang/String
    //   1085: dup
    //   1086: aload 141
    //   1088: invokespecial 65	java/lang/String:<init>	([C)V
    //   1091: invokevirtual 69	java/lang/String:intern	()Ljava/lang/String;
    //   1094: aastore
    //   1095: ldc 127
    //   1097: invokevirtual 61	java/lang/String:toCharArray	()[C
    //   1100: astore 146
    //   1102: aload 146
    //   1104: arraylength
    //   1105: istore 147
    //   1107: iconst_0
    //   1108: istore 148
    //   1110: iload 147
    //   1112: iload 148
    //   1114: if_icmpgt +4679 -> 5793
    //   1117: aload_0
    //   1118: bipush 29
    //   1120: new 55	java/lang/String
    //   1123: dup
    //   1124: aload 146
    //   1126: invokespecial 65	java/lang/String:<init>	([C)V
    //   1129: invokevirtual 69	java/lang/String:intern	()Ljava/lang/String;
    //   1132: aastore
    //   1133: ldc 129
    //   1135: invokevirtual 61	java/lang/String:toCharArray	()[C
    //   1138: astore 151
    //   1140: aload 151
    //   1142: arraylength
    //   1143: istore 152
    //   1145: iconst_0
    //   1146: istore 153
    //   1148: iload 152
    //   1150: iload 153
    //   1152: if_icmpgt +4733 -> 5885
    //   1155: aload_0
    //   1156: bipush 30
    //   1158: new 55	java/lang/String
    //   1161: dup
    //   1162: aload 151
    //   1164: invokespecial 65	java/lang/String:<init>	([C)V
    //   1167: invokevirtual 69	java/lang/String:intern	()Ljava/lang/String;
    //   1170: aastore
    //   1171: ldc 131
    //   1173: invokevirtual 61	java/lang/String:toCharArray	()[C
    //   1176: astore 156
    //   1178: aload 156
    //   1180: arraylength
    //   1181: istore 157
    //   1183: iconst_0
    //   1184: istore 158
    //   1186: iload 157
    //   1188: iload 158
    //   1190: if_icmpgt +4787 -> 5977
    //   1193: aload_0
    //   1194: bipush 31
    //   1196: new 55	java/lang/String
    //   1199: dup
    //   1200: aload 156
    //   1202: invokespecial 65	java/lang/String:<init>	([C)V
    //   1205: invokevirtual 69	java/lang/String:intern	()Ljava/lang/String;
    //   1208: aastore
    //   1209: ldc 133
    //   1211: invokevirtual 61	java/lang/String:toCharArray	()[C
    //   1214: astore 161
    //   1216: aload 161
    //   1218: arraylength
    //   1219: istore 162
    //   1221: iconst_0
    //   1222: istore 163
    //   1224: iload 162
    //   1226: iload 163
    //   1228: if_icmpgt +4841 -> 6069
    //   1231: aload_0
    //   1232: bipush 32
    //   1234: new 55	java/lang/String
    //   1237: dup
    //   1238: aload 161
    //   1240: invokespecial 65	java/lang/String:<init>	([C)V
    //   1243: invokevirtual 69	java/lang/String:intern	()Ljava/lang/String;
    //   1246: aastore
    //   1247: ldc 135
    //   1249: invokevirtual 61	java/lang/String:toCharArray	()[C
    //   1252: astore 166
    //   1254: aload 166
    //   1256: arraylength
    //   1257: istore 167
    //   1259: iconst_0
    //   1260: istore 168
    //   1262: iload 167
    //   1264: iload 168
    //   1266: if_icmpgt +4895 -> 6161
    //   1269: aload_0
    //   1270: bipush 33
    //   1272: new 55	java/lang/String
    //   1275: dup
    //   1276: aload 166
    //   1278: invokespecial 65	java/lang/String:<init>	([C)V
    //   1281: invokevirtual 69	java/lang/String:intern	()Ljava/lang/String;
    //   1284: aastore
    //   1285: ldc 137
    //   1287: invokevirtual 61	java/lang/String:toCharArray	()[C
    //   1290: astore 171
    //   1292: aload 171
    //   1294: arraylength
    //   1295: istore 172
    //   1297: iconst_0
    //   1298: istore 173
    //   1300: iload 172
    //   1302: iload 173
    //   1304: if_icmpgt +4949 -> 6253
    //   1307: aload_0
    //   1308: bipush 34
    //   1310: new 55	java/lang/String
    //   1313: dup
    //   1314: aload 171
    //   1316: invokespecial 65	java/lang/String:<init>	([C)V
    //   1319: invokevirtual 69	java/lang/String:intern	()Ljava/lang/String;
    //   1322: aastore
    //   1323: ldc 139
    //   1325: invokevirtual 61	java/lang/String:toCharArray	()[C
    //   1328: astore 176
    //   1330: aload 176
    //   1332: arraylength
    //   1333: istore 177
    //   1335: iconst_0
    //   1336: istore 178
    //   1338: iload 177
    //   1340: iload 178
    //   1342: if_icmpgt +5003 -> 6345
    //   1345: aload_0
    //   1346: bipush 35
    //   1348: new 55	java/lang/String
    //   1351: dup
    //   1352: aload 176
    //   1354: invokespecial 65	java/lang/String:<init>	([C)V
    //   1357: invokevirtual 69	java/lang/String:intern	()Ljava/lang/String;
    //   1360: aastore
    //   1361: ldc 141
    //   1363: invokevirtual 61	java/lang/String:toCharArray	()[C
    //   1366: astore 181
    //   1368: aload 181
    //   1370: arraylength
    //   1371: istore 182
    //   1373: iconst_0
    //   1374: istore 183
    //   1376: iload 182
    //   1378: iload 183
    //   1380: if_icmpgt +5057 -> 6437
    //   1383: aload_0
    //   1384: bipush 36
    //   1386: new 55	java/lang/String
    //   1389: dup
    //   1390: aload 181
    //   1392: invokespecial 65	java/lang/String:<init>	([C)V
    //   1395: invokevirtual 69	java/lang/String:intern	()Ljava/lang/String;
    //   1398: aastore
    //   1399: ldc 143
    //   1401: invokevirtual 61	java/lang/String:toCharArray	()[C
    //   1404: astore 186
    //   1406: aload 186
    //   1408: arraylength
    //   1409: istore 187
    //   1411: iconst_0
    //   1412: istore 188
    //   1414: iload 187
    //   1416: iload 188
    //   1418: if_icmpgt +5111 -> 6529
    //   1421: aload_0
    //   1422: bipush 37
    //   1424: new 55	java/lang/String
    //   1427: dup
    //   1428: aload 186
    //   1430: invokespecial 65	java/lang/String:<init>	([C)V
    //   1433: invokevirtual 69	java/lang/String:intern	()Ljava/lang/String;
    //   1436: aastore
    //   1437: ldc 145
    //   1439: invokevirtual 61	java/lang/String:toCharArray	()[C
    //   1442: astore 191
    //   1444: aload 191
    //   1446: arraylength
    //   1447: istore 192
    //   1449: iconst_0
    //   1450: istore 193
    //   1452: iload 192
    //   1454: iload 193
    //   1456: if_icmpgt +5165 -> 6621
    //   1459: aload_0
    //   1460: bipush 38
    //   1462: new 55	java/lang/String
    //   1465: dup
    //   1466: aload 191
    //   1468: invokespecial 65	java/lang/String:<init>	([C)V
    //   1471: invokevirtual 69	java/lang/String:intern	()Ljava/lang/String;
    //   1474: aastore
    //   1475: ldc 147
    //   1477: invokevirtual 61	java/lang/String:toCharArray	()[C
    //   1480: astore 196
    //   1482: aload 196
    //   1484: arraylength
    //   1485: istore 197
    //   1487: iconst_0
    //   1488: istore 198
    //   1490: iload 197
    //   1492: iload 198
    //   1494: if_icmpgt +5219 -> 6713
    //   1497: aload_0
    //   1498: bipush 39
    //   1500: new 55	java/lang/String
    //   1503: dup
    //   1504: aload 196
    //   1506: invokespecial 65	java/lang/String:<init>	([C)V
    //   1509: invokevirtual 69	java/lang/String:intern	()Ljava/lang/String;
    //   1512: aastore
    //   1513: ldc 149
    //   1515: invokevirtual 61	java/lang/String:toCharArray	()[C
    //   1518: astore 201
    //   1520: aload 201
    //   1522: arraylength
    //   1523: istore 202
    //   1525: iconst_0
    //   1526: istore 203
    //   1528: iload 202
    //   1530: iload 203
    //   1532: if_icmpgt +5273 -> 6805
    //   1535: aload_0
    //   1536: bipush 40
    //   1538: new 55	java/lang/String
    //   1541: dup
    //   1542: aload 201
    //   1544: invokespecial 65	java/lang/String:<init>	([C)V
    //   1547: invokevirtual 69	java/lang/String:intern	()Ljava/lang/String;
    //   1550: aastore
    //   1551: ldc 151
    //   1553: invokevirtual 61	java/lang/String:toCharArray	()[C
    //   1556: astore 206
    //   1558: aload 206
    //   1560: arraylength
    //   1561: istore 207
    //   1563: iconst_0
    //   1564: istore 208
    //   1566: iload 207
    //   1568: iload 208
    //   1570: if_icmpgt +5327 -> 6897
    //   1573: aload_0
    //   1574: bipush 41
    //   1576: new 55	java/lang/String
    //   1579: dup
    //   1580: aload 206
    //   1582: invokespecial 65	java/lang/String:<init>	([C)V
    //   1585: invokevirtual 69	java/lang/String:intern	()Ljava/lang/String;
    //   1588: aastore
    //   1589: ldc 153
    //   1591: invokevirtual 61	java/lang/String:toCharArray	()[C
    //   1594: astore 211
    //   1596: aload 211
    //   1598: arraylength
    //   1599: istore 212
    //   1601: iconst_0
    //   1602: istore 213
    //   1604: iload 212
    //   1606: iload 213
    //   1608: if_icmpgt +5381 -> 6989
    //   1611: aload_0
    //   1612: bipush 42
    //   1614: new 55	java/lang/String
    //   1617: dup
    //   1618: aload 211
    //   1620: invokespecial 65	java/lang/String:<init>	([C)V
    //   1623: invokevirtual 69	java/lang/String:intern	()Ljava/lang/String;
    //   1626: aastore
    //   1627: ldc 155
    //   1629: invokevirtual 61	java/lang/String:toCharArray	()[C
    //   1632: astore 216
    //   1634: aload 216
    //   1636: arraylength
    //   1637: istore 217
    //   1639: iconst_0
    //   1640: istore 218
    //   1642: iload 217
    //   1644: iload 218
    //   1646: if_icmpgt +5435 -> 7081
    //   1649: aload_0
    //   1650: bipush 43
    //   1652: new 55	java/lang/String
    //   1655: dup
    //   1656: aload 216
    //   1658: invokespecial 65	java/lang/String:<init>	([C)V
    //   1661: invokevirtual 69	java/lang/String:intern	()Ljava/lang/String;
    //   1664: aastore
    //   1665: ldc 157
    //   1667: invokevirtual 61	java/lang/String:toCharArray	()[C
    //   1670: astore 221
    //   1672: aload 221
    //   1674: arraylength
    //   1675: istore 222
    //   1677: iconst_0
    //   1678: istore 223
    //   1680: iload 222
    //   1682: iload 223
    //   1684: if_icmpgt +5489 -> 7173
    //   1687: aload_0
    //   1688: bipush 44
    //   1690: new 55	java/lang/String
    //   1693: dup
    //   1694: aload 221
    //   1696: invokespecial 65	java/lang/String:<init>	([C)V
    //   1699: invokevirtual 69	java/lang/String:intern	()Ljava/lang/String;
    //   1702: aastore
    //   1703: ldc 159
    //   1705: invokevirtual 61	java/lang/String:toCharArray	()[C
    //   1708: astore 226
    //   1710: aload 226
    //   1712: arraylength
    //   1713: istore 227
    //   1715: iconst_0
    //   1716: istore 228
    //   1718: iload 227
    //   1720: iload 228
    //   1722: if_icmpgt +5543 -> 7265
    //   1725: aload_0
    //   1726: bipush 45
    //   1728: new 55	java/lang/String
    //   1731: dup
    //   1732: aload 226
    //   1734: invokespecial 65	java/lang/String:<init>	([C)V
    //   1737: invokevirtual 69	java/lang/String:intern	()Ljava/lang/String;
    //   1740: aastore
    //   1741: ldc 161
    //   1743: invokevirtual 61	java/lang/String:toCharArray	()[C
    //   1746: astore 231
    //   1748: aload 231
    //   1750: arraylength
    //   1751: istore 232
    //   1753: iconst_0
    //   1754: istore 233
    //   1756: iload 232
    //   1758: iload 233
    //   1760: if_icmpgt +5597 -> 7357
    //   1763: aload_0
    //   1764: bipush 46
    //   1766: new 55	java/lang/String
    //   1769: dup
    //   1770: aload 231
    //   1772: invokespecial 65	java/lang/String:<init>	([C)V
    //   1775: invokevirtual 69	java/lang/String:intern	()Ljava/lang/String;
    //   1778: aastore
    //   1779: ldc 163
    //   1781: invokevirtual 61	java/lang/String:toCharArray	()[C
    //   1784: astore 236
    //   1786: aload 236
    //   1788: arraylength
    //   1789: istore 237
    //   1791: iconst_0
    //   1792: istore 238
    //   1794: iload 237
    //   1796: iload 238
    //   1798: if_icmpgt +5651 -> 7449
    //   1801: aload_0
    //   1802: bipush 47
    //   1804: new 55	java/lang/String
    //   1807: dup
    //   1808: aload 236
    //   1810: invokespecial 65	java/lang/String:<init>	([C)V
    //   1813: invokevirtual 69	java/lang/String:intern	()Ljava/lang/String;
    //   1816: aastore
    //   1817: ldc 165
    //   1819: invokevirtual 61	java/lang/String:toCharArray	()[C
    //   1822: astore 241
    //   1824: aload 241
    //   1826: arraylength
    //   1827: istore 242
    //   1829: iconst_0
    //   1830: istore 243
    //   1832: iload 242
    //   1834: iload 243
    //   1836: if_icmpgt +5705 -> 7541
    //   1839: aload_0
    //   1840: bipush 48
    //   1842: new 55	java/lang/String
    //   1845: dup
    //   1846: aload 241
    //   1848: invokespecial 65	java/lang/String:<init>	([C)V
    //   1851: invokevirtual 69	java/lang/String:intern	()Ljava/lang/String;
    //   1854: aastore
    //   1855: ldc 167
    //   1857: invokevirtual 61	java/lang/String:toCharArray	()[C
    //   1860: astore 246
    //   1862: aload 246
    //   1864: arraylength
    //   1865: istore 247
    //   1867: iconst_0
    //   1868: istore 248
    //   1870: iload 247
    //   1872: iload 248
    //   1874: if_icmpgt +5759 -> 7633
    //   1877: aload_0
    //   1878: bipush 49
    //   1880: new 55	java/lang/String
    //   1883: dup
    //   1884: aload 246
    //   1886: invokespecial 65	java/lang/String:<init>	([C)V
    //   1889: invokevirtual 69	java/lang/String:intern	()Ljava/lang/String;
    //   1892: aastore
    //   1893: ldc 169
    //   1895: invokevirtual 61	java/lang/String:toCharArray	()[C
    //   1898: astore 251
    //   1900: aload 251
    //   1902: arraylength
    //   1903: istore 252
    //   1905: iconst_0
    //   1906: istore 253
    //   1908: iload 252
    //   1910: iload 253
    //   1912: if_icmpgt +5813 -> 7725
    //   1915: aload_0
    //   1916: bipush 50
    //   1918: new 55	java/lang/String
    //   1921: dup
    //   1922: aload 251
    //   1924: invokespecial 65	java/lang/String:<init>	([C)V
    //   1927: invokevirtual 69	java/lang/String:intern	()Ljava/lang/String;
    //   1930: aastore
    //   1931: ldc 171
    //   1933: invokevirtual 61	java/lang/String:toCharArray	()[C
    //   1936: wide
    //   1940: wide
    //   1944: arraylength
    //   1945: wide
    //   1949: iconst_0
    //   1950: wide
    //   1954: wide
    //   1958: wide
    //   1962: if_icmpgt +5855 -> 7817
    //   1965: aload_0
    //   1966: bipush 51
    //   1968: new 55	java/lang/String
    //   1971: dup
    //   1972: wide
    //   1976: invokespecial 65	java/lang/String:<init>	([C)V
    //   1979: invokevirtual 69	java/lang/String:intern	()Ljava/lang/String;
    //   1982: aastore
    //   1983: ldc 173
    //   1985: invokevirtual 61	java/lang/String:toCharArray	()[C
    //   1988: wide
    //   1992: wide
    //   1996: arraylength
    //   1997: wide
    //   2001: iconst_0
    //   2002: wide
    //   2006: wide
    //   2010: wide
    //   2014: if_icmpgt +5924 -> 7938
    //   2017: aload_0
    //   2018: bipush 52
    //   2020: new 55	java/lang/String
    //   2023: dup
    //   2024: wide
    //   2028: invokespecial 65	java/lang/String:<init>	([C)V
    //   2031: invokevirtual 69	java/lang/String:intern	()Ljava/lang/String;
    //   2034: aastore
    //   2035: ldc 175
    //   2037: invokevirtual 61	java/lang/String:toCharArray	()[C
    //   2040: wide
    //   2044: wide
    //   2048: arraylength
    //   2049: wide
    //   2053: iconst_0
    //   2054: wide
    //   2058: wide
    //   2062: wide
    //   2066: if_icmpgt +5992 -> 8058
    //   2069: aload_0
    //   2070: bipush 53
    //   2072: new 55	java/lang/String
    //   2075: dup
    //   2076: wide
    //   2080: invokespecial 65	java/lang/String:<init>	([C)V
    //   2083: invokevirtual 69	java/lang/String:intern	()Ljava/lang/String;
    //   2086: aastore
    //   2087: ldc 177
    //   2089: invokevirtual 61	java/lang/String:toCharArray	()[C
    //   2092: wide
    //   2096: wide
    //   2100: arraylength
    //   2101: wide
    //   2105: iconst_0
    //   2106: wide
    //   2110: wide
    //   2114: wide
    //   2118: if_icmpgt +6060 -> 8178
    //   2121: aload_0
    //   2122: bipush 54
    //   2124: new 55	java/lang/String
    //   2127: dup
    //   2128: wide
    //   2132: invokespecial 65	java/lang/String:<init>	([C)V
    //   2135: invokevirtual 69	java/lang/String:intern	()Ljava/lang/String;
    //   2138: aastore
    //   2139: ldc 179
    //   2141: invokevirtual 61	java/lang/String:toCharArray	()[C
    //   2144: wide
    //   2148: wide
    //   2152: arraylength
    //   2153: wide
    //   2157: iconst_0
    //   2158: wide
    //   2162: wide
    //   2166: wide
    //   2170: if_icmpgt +6128 -> 8298
    //   2173: aload_0
    //   2174: bipush 55
    //   2176: new 55	java/lang/String
    //   2179: dup
    //   2180: wide
    //   2184: invokespecial 65	java/lang/String:<init>	([C)V
    //   2187: invokevirtual 69	java/lang/String:intern	()Ljava/lang/String;
    //   2190: aastore
    //   2191: ldc 181
    //   2193: invokevirtual 61	java/lang/String:toCharArray	()[C
    //   2196: wide
    //   2200: wide
    //   2204: arraylength
    //   2205: wide
    //   2209: iconst_0
    //   2210: wide
    //   2214: wide
    //   2218: wide
    //   2222: if_icmpgt +6196 -> 8418
    //   2225: aload_0
    //   2226: bipush 56
    //   2228: new 55	java/lang/String
    //   2231: dup
    //   2232: wide
    //   2236: invokespecial 65	java/lang/String:<init>	([C)V
    //   2239: invokevirtual 69	java/lang/String:intern	()Ljava/lang/String;
    //   2242: aastore
    //   2243: ldc 183
    //   2245: invokevirtual 61	java/lang/String:toCharArray	()[C
    //   2248: wide
    //   2252: wide
    //   2256: arraylength
    //   2257: wide
    //   2261: iconst_0
    //   2262: wide
    //   2266: wide
    //   2270: wide
    //   2274: if_icmpgt +6264 -> 8538
    //   2277: aload_0
    //   2278: bipush 57
    //   2280: new 55	java/lang/String
    //   2283: dup
    //   2284: wide
    //   2288: invokespecial 65	java/lang/String:<init>	([C)V
    //   2291: invokevirtual 69	java/lang/String:intern	()Ljava/lang/String;
    //   2294: aastore
    //   2295: ldc 185
    //   2297: invokevirtual 61	java/lang/String:toCharArray	()[C
    //   2300: wide
    //   2304: wide
    //   2308: arraylength
    //   2309: wide
    //   2313: iconst_0
    //   2314: wide
    //   2318: wide
    //   2322: wide
    //   2326: if_icmpgt +6332 -> 8658
    //   2329: aload_0
    //   2330: bipush 58
    //   2332: new 55	java/lang/String
    //   2335: dup
    //   2336: wide
    //   2340: invokespecial 65	java/lang/String:<init>	([C)V
    //   2343: invokevirtual 69	java/lang/String:intern	()Ljava/lang/String;
    //   2346: aastore
    //   2347: ldc 187
    //   2349: invokevirtual 61	java/lang/String:toCharArray	()[C
    //   2352: wide
    //   2356: wide
    //   2360: arraylength
    //   2361: wide
    //   2365: iconst_0
    //   2366: wide
    //   2370: wide
    //   2374: wide
    //   2378: if_icmpgt +6400 -> 8778
    //   2381: aload_0
    //   2382: bipush 59
    //   2384: new 55	java/lang/String
    //   2387: dup
    //   2388: wide
    //   2392: invokespecial 65	java/lang/String:<init>	([C)V
    //   2395: invokevirtual 69	java/lang/String:intern	()Ljava/lang/String;
    //   2398: aastore
    //   2399: ldc 189
    //   2401: invokevirtual 61	java/lang/String:toCharArray	()[C
    //   2404: wide
    //   2408: wide
    //   2412: arraylength
    //   2413: wide
    //   2417: iconst_0
    //   2418: wide
    //   2422: wide
    //   2426: wide
    //   2430: if_icmpgt +6468 -> 8898
    //   2433: aload_0
    //   2434: bipush 60
    //   2436: new 55	java/lang/String
    //   2439: dup
    //   2440: wide
    //   2444: invokespecial 65	java/lang/String:<init>	([C)V
    //   2447: invokevirtual 69	java/lang/String:intern	()Ljava/lang/String;
    //   2450: aastore
    //   2451: ldc 191
    //   2453: invokevirtual 61	java/lang/String:toCharArray	()[C
    //   2456: wide
    //   2460: wide
    //   2464: arraylength
    //   2465: wide
    //   2469: iconst_0
    //   2470: wide
    //   2474: wide
    //   2478: wide
    //   2482: if_icmpgt +6536 -> 9018
    //   2485: aload_0
    //   2486: bipush 61
    //   2488: new 55	java/lang/String
    //   2491: dup
    //   2492: wide
    //   2496: invokespecial 65	java/lang/String:<init>	([C)V
    //   2499: invokevirtual 69	java/lang/String:intern	()Ljava/lang/String;
    //   2502: aastore
    //   2503: ldc 193
    //   2505: invokevirtual 61	java/lang/String:toCharArray	()[C
    //   2508: wide
    //   2512: wide
    //   2516: arraylength
    //   2517: wide
    //   2521: iconst_0
    //   2522: wide
    //   2526: wide
    //   2530: wide
    //   2534: if_icmpgt +6604 -> 9138
    //   2537: aload_0
    //   2538: bipush 62
    //   2540: new 55	java/lang/String
    //   2543: dup
    //   2544: wide
    //   2548: invokespecial 65	java/lang/String:<init>	([C)V
    //   2551: invokevirtual 69	java/lang/String:intern	()Ljava/lang/String;
    //   2554: aastore
    //   2555: ldc 195
    //   2557: invokevirtual 61	java/lang/String:toCharArray	()[C
    //   2560: wide
    //   2564: wide
    //   2568: arraylength
    //   2569: wide
    //   2573: iconst_0
    //   2574: wide
    //   2578: wide
    //   2582: wide
    //   2586: if_icmpgt +6672 -> 9258
    //   2589: aload_0
    //   2590: bipush 63
    //   2592: new 55	java/lang/String
    //   2595: dup
    //   2596: wide
    //   2600: invokespecial 65	java/lang/String:<init>	([C)V
    //   2603: invokevirtual 69	java/lang/String:intern	()Ljava/lang/String;
    //   2606: aastore
    //   2607: ldc 197
    //   2609: invokevirtual 61	java/lang/String:toCharArray	()[C
    //   2612: wide
    //   2616: wide
    //   2620: arraylength
    //   2621: wide
    //   2625: iconst_0
    //   2626: wide
    //   2630: wide
    //   2634: wide
    //   2638: if_icmpgt +6740 -> 9378
    //   2641: aload_0
    //   2642: bipush 64
    //   2644: new 55	java/lang/String
    //   2647: dup
    //   2648: wide
    //   2652: invokespecial 65	java/lang/String:<init>	([C)V
    //   2655: invokevirtual 69	java/lang/String:intern	()Ljava/lang/String;
    //   2658: aastore
    //   2659: ldc 199
    //   2661: invokevirtual 61	java/lang/String:toCharArray	()[C
    //   2664: wide
    //   2668: wide
    //   2672: arraylength
    //   2673: wide
    //   2677: iconst_0
    //   2678: wide
    //   2682: wide
    //   2686: wide
    //   2690: if_icmpgt +6808 -> 9498
    //   2693: aload_0
    //   2694: bipush 65
    //   2696: new 55	java/lang/String
    //   2699: dup
    //   2700: wide
    //   2704: invokespecial 65	java/lang/String:<init>	([C)V
    //   2707: invokevirtual 69	java/lang/String:intern	()Ljava/lang/String;
    //   2710: aastore
    //   2711: ldc 201
    //   2713: invokevirtual 61	java/lang/String:toCharArray	()[C
    //   2716: wide
    //   2720: wide
    //   2724: arraylength
    //   2725: wide
    //   2729: iconst_0
    //   2730: wide
    //   2734: wide
    //   2738: wide
    //   2742: if_icmpgt +6876 -> 9618
    //   2745: aload_0
    //   2746: bipush 66
    //   2748: new 55	java/lang/String
    //   2751: dup
    //   2752: wide
    //   2756: invokespecial 65	java/lang/String:<init>	([C)V
    //   2759: invokevirtual 69	java/lang/String:intern	()Ljava/lang/String;
    //   2762: aastore
    //   2763: ldc 203
    //   2765: invokevirtual 61	java/lang/String:toCharArray	()[C
    //   2768: wide
    //   2772: wide
    //   2776: arraylength
    //   2777: wide
    //   2781: iconst_0
    //   2782: wide
    //   2786: wide
    //   2790: wide
    //   2794: if_icmpgt +6944 -> 9738
    //   2797: aload_0
    //   2798: bipush 67
    //   2800: new 55	java/lang/String
    //   2803: dup
    //   2804: wide
    //   2808: invokespecial 65	java/lang/String:<init>	([C)V
    //   2811: invokevirtual 69	java/lang/String:intern	()Ljava/lang/String;
    //   2814: aastore
    //   2815: ldc 205
    //   2817: invokevirtual 61	java/lang/String:toCharArray	()[C
    //   2820: wide
    //   2824: wide
    //   2828: arraylength
    //   2829: wide
    //   2833: iconst_0
    //   2834: wide
    //   2838: wide
    //   2842: wide
    //   2846: if_icmpgt +7012 -> 9858
    //   2849: aload_0
    //   2850: bipush 68
    //   2852: new 55	java/lang/String
    //   2855: dup
    //   2856: wide
    //   2860: invokespecial 65	java/lang/String:<init>	([C)V
    //   2863: invokevirtual 69	java/lang/String:intern	()Ljava/lang/String;
    //   2866: aastore
    //   2867: ldc 207
    //   2869: invokevirtual 61	java/lang/String:toCharArray	()[C
    //   2872: wide
    //   2876: wide
    //   2880: arraylength
    //   2881: wide
    //   2885: iconst_0
    //   2886: wide
    //   2890: wide
    //   2894: wide
    //   2898: if_icmpgt +7080 -> 9978
    //   2901: aload_0
    //   2902: bipush 69
    //   2904: new 55	java/lang/String
    //   2907: dup
    //   2908: wide
    //   2912: invokespecial 65	java/lang/String:<init>	([C)V
    //   2915: invokevirtual 69	java/lang/String:intern	()Ljava/lang/String;
    //   2918: aastore
    //   2919: ldc 209
    //   2921: invokevirtual 61	java/lang/String:toCharArray	()[C
    //   2924: wide
    //   2928: wide
    //   2932: arraylength
    //   2933: wide
    //   2937: iconst_0
    //   2938: wide
    //   2942: wide
    //   2946: wide
    //   2950: if_icmpgt +7148 -> 10098
    //   2953: aload_0
    //   2954: bipush 70
    //   2956: new 55	java/lang/String
    //   2959: dup
    //   2960: wide
    //   2964: invokespecial 65	java/lang/String:<init>	([C)V
    //   2967: invokevirtual 69	java/lang/String:intern	()Ljava/lang/String;
    //   2970: aastore
    //   2971: ldc 211
    //   2973: invokevirtual 61	java/lang/String:toCharArray	()[C
    //   2976: wide
    //   2980: wide
    //   2984: arraylength
    //   2985: wide
    //   2989: iconst_0
    //   2990: wide
    //   2994: wide
    //   2998: wide
    //   3002: if_icmpgt +7216 -> 10218
    //   3005: aload_0
    //   3006: bipush 71
    //   3008: new 55	java/lang/String
    //   3011: dup
    //   3012: wide
    //   3016: invokespecial 65	java/lang/String:<init>	([C)V
    //   3019: invokevirtual 69	java/lang/String:intern	()Ljava/lang/String;
    //   3022: aastore
    //   3023: ldc 213
    //   3025: invokevirtual 61	java/lang/String:toCharArray	()[C
    //   3028: wide
    //   3032: wide
    //   3036: arraylength
    //   3037: wide
    //   3041: iconst_0
    //   3042: wide
    //   3046: wide
    //   3050: wide
    //   3054: if_icmpgt +7284 -> 10338
    //   3057: aload_0
    //   3058: bipush 72
    //   3060: new 55	java/lang/String
    //   3063: dup
    //   3064: wide
    //   3068: invokespecial 65	java/lang/String:<init>	([C)V
    //   3071: invokevirtual 69	java/lang/String:intern	()Ljava/lang/String;
    //   3074: aastore
    //   3075: ldc 215
    //   3077: invokevirtual 61	java/lang/String:toCharArray	()[C
    //   3080: wide
    //   3084: wide
    //   3088: arraylength
    //   3089: wide
    //   3093: iconst_0
    //   3094: wide
    //   3098: wide
    //   3102: wide
    //   3106: if_icmpgt +7352 -> 10458
    //   3109: aload_0
    //   3110: bipush 73
    //   3112: new 55	java/lang/String
    //   3115: dup
    //   3116: wide
    //   3120: invokespecial 65	java/lang/String:<init>	([C)V
    //   3123: invokevirtual 69	java/lang/String:intern	()Ljava/lang/String;
    //   3126: aastore
    //   3127: aload_0
    //   3128: putstatic 217	zb:J	[Ljava/lang/String;
    //   3131: return
    //   3132: aload_1
    //   3133: iload_3
    //   3134: caload
    //   3135: istore 4
    //   3137: iload_3
    //   3138: iconst_5
    //   3139: irem
    //   3140: tableswitch	default:+32 -> 3172, 0:+51->3191, 1:+58->3198, 2:+65->3205, 3:+72->3212
    //   3173: fstore_0
    //   3174: istore 5
    //   3176: aload_1
    //   3177: iload_3
    //   3178: iload 5
    //   3180: iload 4
    //   3182: ixor
    //   3183: i2c
    //   3184: castore
    //   3185: iinc 3 1
    //   3188: goto -3171 -> 17
    //   3191: bipush 30
    //   3193: istore 5
    //   3195: goto -19 -> 3176
    //   3198: bipush 62
    //   3200: istore 5
    //   3202: goto -26 -> 3176
    //   3205: bipush 54
    //   3207: istore 5
    //   3209: goto -33 -> 3176
    //   3212: bipush 41
    //   3214: istore 5
    //   3216: goto -40 -> 3176
    //   3219: aload 6
    //   3221: iload 8
    //   3223: caload
    //   3224: istore 9
    //   3226: iload 8
    //   3228: iconst_5
    //   3229: irem
    //   3230: tableswitch	default:+30 -> 3260, 0:+51->3281, 1:+58->3288, 2:+65->3295, 3:+72->3302
    //   3261: fstore_0
    //   3262: istore 10
    //   3264: aload 6
    //   3266: iload 8
    //   3268: iload 10
    //   3270: iload 9
    //   3272: ixor
    //   3273: i2c
    //   3274: castore
    //   3275: iinc 8 1
    //   3278: goto -3227 -> 51
    //   3281: bipush 30
    //   3283: istore 10
    //   3285: goto -21 -> 3264
    //   3288: bipush 62
    //   3290: istore 10
    //   3292: goto -28 -> 3264
    //   3295: bipush 54
    //   3297: istore 10
    //   3299: goto -35 -> 3264
    //   3302: bipush 41
    //   3304: istore 10
    //   3306: goto -42 -> 3264
    //   3309: aload 11
    //   3311: iload 13
    //   3313: caload
    //   3314: istore 14
    //   3316: iload 13
    //   3318: iconst_5
    //   3319: irem
    //   3320: tableswitch	default:+32 -> 3352, 0:+53->3373, 1:+60->3380, 2:+67->3387, 3:+74->3394
    //   3353: fstore_0
    //   3354: istore 15
    //   3356: aload 11
    //   3358: iload 13
    //   3360: iload 15
    //   3362: iload 14
    //   3364: ixor
    //   3365: i2c
    //   3366: castore
    //   3367: iinc 13 1
    //   3370: goto -3282 -> 88
    //   3373: bipush 30
    //   3375: istore 15
    //   3377: goto -21 -> 3356
    //   3380: bipush 62
    //   3382: istore 15
    //   3384: goto -28 -> 3356
    //   3387: bipush 54
    //   3389: istore 15
    //   3391: goto -35 -> 3356
    //   3394: bipush 41
    //   3396: istore 15
    //   3398: goto -42 -> 3356
    //   3401: aload 16
    //   3403: iload 18
    //   3405: caload
    //   3406: istore 19
    //   3408: iload 18
    //   3410: iconst_5
    //   3411: irem
    //   3412: tableswitch	default:+32 -> 3444, 0:+53->3465, 1:+60->3472, 2:+67->3479, 3:+74->3486
    //   3445: fstore_0
    //   3446: istore 20
    //   3448: aload 16
    //   3450: iload 18
    //   3452: iload 20
    //   3454: iload 19
    //   3456: ixor
    //   3457: i2c
    //   3458: castore
    //   3459: iinc 18 1
    //   3462: goto -3337 -> 125
    //   3465: bipush 30
    //   3467: istore 20
    //   3469: goto -21 -> 3448
    //   3472: bipush 62
    //   3474: istore 20
    //   3476: goto -28 -> 3448
    //   3479: bipush 54
    //   3481: istore 20
    //   3483: goto -35 -> 3448
    //   3486: bipush 41
    //   3488: istore 20
    //   3490: goto -42 -> 3448
    //   3493: aload 21
    //   3495: iload 23
    //   3497: caload
    //   3498: istore 24
    //   3500: iload 23
    //   3502: iconst_5
    //   3503: irem
    //   3504: tableswitch	default:+32 -> 3536, 0:+53->3557, 1:+60->3564, 2:+67->3571, 3:+74->3578
    //   3537: fstore_0
    //   3538: istore 25
    //   3540: aload 21
    //   3542: iload 23
    //   3544: iload 25
    //   3546: iload 24
    //   3548: ixor
    //   3549: i2c
    //   3550: castore
    //   3551: iinc 23 1
    //   3554: goto -3392 -> 162
    //   3557: bipush 30
    //   3559: istore 25
    //   3561: goto -21 -> 3540
    //   3564: bipush 62
    //   3566: istore 25
    //   3568: goto -28 -> 3540
    //   3571: bipush 54
    //   3573: istore 25
    //   3575: goto -35 -> 3540
    //   3578: bipush 41
    //   3580: istore 25
    //   3582: goto -42 -> 3540
    //   3585: aload 26
    //   3587: iload 28
    //   3589: caload
    //   3590: istore 29
    //   3592: iload 28
    //   3594: iconst_5
    //   3595: irem
    //   3596: tableswitch	default:+32 -> 3628, 0:+53->3649, 1:+60->3656, 2:+67->3663, 3:+74->3670
    //   3629: fstore_0
    //   3630: istore 30
    //   3632: aload 26
    //   3634: iload 28
    //   3636: iload 30
    //   3638: iload 29
    //   3640: ixor
    //   3641: i2c
    //   3642: castore
    //   3643: iinc 28 1
    //   3646: goto -3447 -> 199
    //   3649: bipush 30
    //   3651: istore 30
    //   3653: goto -21 -> 3632
    //   3656: bipush 62
    //   3658: istore 30
    //   3660: goto -28 -> 3632
    //   3663: bipush 54
    //   3665: istore 30
    //   3667: goto -35 -> 3632
    //   3670: bipush 41
    //   3672: istore 30
    //   3674: goto -42 -> 3632
    //   3677: aload 31
    //   3679: iload 33
    //   3681: caload
    //   3682: istore 34
    //   3684: iload 33
    //   3686: iconst_5
    //   3687: irem
    //   3688: tableswitch	default:+32 -> 3720, 0:+53->3741, 1:+60->3748, 2:+67->3755, 3:+74->3762
    //   3721: fstore_0
    //   3722: istore 35
    //   3724: aload 31
    //   3726: iload 33
    //   3728: iload 35
    //   3730: iload 34
    //   3732: ixor
    //   3733: i2c
    //   3734: castore
    //   3735: iinc 33 1
    //   3738: goto -3502 -> 236
    //   3741: bipush 30
    //   3743: istore 35
    //   3745: goto -21 -> 3724
    //   3748: bipush 62
    //   3750: istore 35
    //   3752: goto -28 -> 3724
    //   3755: bipush 54
    //   3757: istore 35
    //   3759: goto -35 -> 3724
    //   3762: bipush 41
    //   3764: istore 35
    //   3766: goto -42 -> 3724
    //   3769: aload 36
    //   3771: iload 38
    //   3773: caload
    //   3774: istore 39
    //   3776: iload 38
    //   3778: iconst_5
    //   3779: irem
    //   3780: tableswitch	default:+32 -> 3812, 0:+53->3833, 1:+60->3840, 2:+67->3847, 3:+74->3854
    //   3813: fstore_0
    //   3814: istore 40
    //   3816: aload 36
    //   3818: iload 38
    //   3820: iload 40
    //   3822: iload 39
    //   3824: ixor
    //   3825: i2c
    //   3826: castore
    //   3827: iinc 38 1
    //   3830: goto -3556 -> 274
    //   3833: bipush 30
    //   3835: istore 40
    //   3837: goto -21 -> 3816
    //   3840: bipush 62
    //   3842: istore 40
    //   3844: goto -28 -> 3816
    //   3847: bipush 54
    //   3849: istore 40
    //   3851: goto -35 -> 3816
    //   3854: bipush 41
    //   3856: istore 40
    //   3858: goto -42 -> 3816
    //   3861: aload 41
    //   3863: iload 43
    //   3865: caload
    //   3866: istore 44
    //   3868: iload 43
    //   3870: iconst_5
    //   3871: irem
    //   3872: tableswitch	default:+32 -> 3904, 0:+53->3925, 1:+60->3932, 2:+67->3939, 3:+74->3946
    //   3905: fstore_0
    //   3906: istore 45
    //   3908: aload 41
    //   3910: iload 43
    //   3912: iload 45
    //   3914: iload 44
    //   3916: ixor
    //   3917: i2c
    //   3918: castore
    //   3919: iinc 43 1
    //   3922: goto -3610 -> 312
    //   3925: bipush 30
    //   3927: istore 45
    //   3929: goto -21 -> 3908
    //   3932: bipush 62
    //   3934: istore 45
    //   3936: goto -28 -> 3908
    //   3939: bipush 54
    //   3941: istore 45
    //   3943: goto -35 -> 3908
    //   3946: bipush 41
    //   3948: istore 45
    //   3950: goto -42 -> 3908
    //   3953: aload 46
    //   3955: iload 48
    //   3957: caload
    //   3958: istore 49
    //   3960: iload 48
    //   3962: iconst_5
    //   3963: irem
    //   3964: tableswitch	default:+32 -> 3996, 0:+53->4017, 1:+60->4024, 2:+67->4031, 3:+74->4038
    //   3997: fstore_0
    //   3998: istore 50
    //   4000: aload 46
    //   4002: iload 48
    //   4004: iload 50
    //   4006: iload 49
    //   4008: ixor
    //   4009: i2c
    //   4010: castore
    //   4011: iinc 48 1
    //   4014: goto -3664 -> 350
    //   4017: bipush 30
    //   4019: istore 50
    //   4021: goto -21 -> 4000
    //   4024: bipush 62
    //   4026: istore 50
    //   4028: goto -28 -> 4000
    //   4031: bipush 54
    //   4033: istore 50
    //   4035: goto -35 -> 4000
    //   4038: bipush 41
    //   4040: istore 50
    //   4042: goto -42 -> 4000
    //   4045: aload 51
    //   4047: iload 53
    //   4049: caload
    //   4050: istore 54
    //   4052: iload 53
    //   4054: iconst_5
    //   4055: irem
    //   4056: tableswitch	default:+32 -> 4088, 0:+53->4109, 1:+60->4116, 2:+67->4123, 3:+74->4130
    //   4089: fstore_0
    //   4090: istore 55
    //   4092: aload 51
    //   4094: iload 53
    //   4096: iload 55
    //   4098: iload 54
    //   4100: ixor
    //   4101: i2c
    //   4102: castore
    //   4103: iinc 53 1
    //   4106: goto -3718 -> 388
    //   4109: bipush 30
    //   4111: istore 55
    //   4113: goto -21 -> 4092
    //   4116: bipush 62
    //   4118: istore 55
    //   4120: goto -28 -> 4092
    //   4123: bipush 54
    //   4125: istore 55
    //   4127: goto -35 -> 4092
    //   4130: bipush 41
    //   4132: istore 55
    //   4134: goto -42 -> 4092
    //   4137: aload 56
    //   4139: iload 58
    //   4141: caload
    //   4142: istore 59
    //   4144: iload 58
    //   4146: iconst_5
    //   4147: irem
    //   4148: tableswitch	default:+32 -> 4180, 0:+53->4201, 1:+60->4208, 2:+67->4215, 3:+74->4222
    //   4181: fstore_0
    //   4182: istore 60
    //   4184: aload 56
    //   4186: iload 58
    //   4188: iload 60
    //   4190: iload 59
    //   4192: ixor
    //   4193: i2c
    //   4194: castore
    //   4195: iinc 58 1
    //   4198: goto -3772 -> 426
    //   4201: bipush 30
    //   4203: istore 60
    //   4205: goto -21 -> 4184
    //   4208: bipush 62
    //   4210: istore 60
    //   4212: goto -28 -> 4184
    //   4215: bipush 54
    //   4217: istore 60
    //   4219: goto -35 -> 4184
    //   4222: bipush 41
    //   4224: istore 60
    //   4226: goto -42 -> 4184
    //   4229: aload 61
    //   4231: iload 63
    //   4233: caload
    //   4234: istore 64
    //   4236: iload 63
    //   4238: iconst_5
    //   4239: irem
    //   4240: tableswitch	default:+32 -> 4272, 0:+53->4293, 1:+60->4300, 2:+67->4307, 3:+74->4314
    //   4273: fstore_0
    //   4274: istore 65
    //   4276: aload 61
    //   4278: iload 63
    //   4280: iload 65
    //   4282: iload 64
    //   4284: ixor
    //   4285: i2c
    //   4286: castore
    //   4287: iinc 63 1
    //   4290: goto -3826 -> 464
    //   4293: bipush 30
    //   4295: istore 65
    //   4297: goto -21 -> 4276
    //   4300: bipush 62
    //   4302: istore 65
    //   4304: goto -28 -> 4276
    //   4307: bipush 54
    //   4309: istore 65
    //   4311: goto -35 -> 4276
    //   4314: bipush 41
    //   4316: istore 65
    //   4318: goto -42 -> 4276
    //   4321: aload 66
    //   4323: iload 68
    //   4325: caload
    //   4326: istore 69
    //   4328: iload 68
    //   4330: iconst_5
    //   4331: irem
    //   4332: tableswitch	default:+32 -> 4364, 0:+53->4385, 1:+60->4392, 2:+67->4399, 3:+74->4406
    //   4365: fstore_0
    //   4366: istore 70
    //   4368: aload 66
    //   4370: iload 68
    //   4372: iload 70
    //   4374: iload 69
    //   4376: ixor
    //   4377: i2c
    //   4378: castore
    //   4379: iinc 68 1
    //   4382: goto -3880 -> 502
    //   4385: bipush 30
    //   4387: istore 70
    //   4389: goto -21 -> 4368
    //   4392: bipush 62
    //   4394: istore 70
    //   4396: goto -28 -> 4368
    //   4399: bipush 54
    //   4401: istore 70
    //   4403: goto -35 -> 4368
    //   4406: bipush 41
    //   4408: istore 70
    //   4410: goto -42 -> 4368
    //   4413: aload 71
    //   4415: iload 73
    //   4417: caload
    //   4418: istore 74
    //   4420: iload 73
    //   4422: iconst_5
    //   4423: irem
    //   4424: tableswitch	default:+32 -> 4456, 0:+53->4477, 1:+60->4484, 2:+67->4491, 3:+74->4498
    //   4457: fstore_0
    //   4458: istore 75
    //   4460: aload 71
    //   4462: iload 73
    //   4464: iload 75
    //   4466: iload 74
    //   4468: ixor
    //   4469: i2c
    //   4470: castore
    //   4471: iinc 73 1
    //   4474: goto -3934 -> 540
    //   4477: bipush 30
    //   4479: istore 75
    //   4481: goto -21 -> 4460
    //   4484: bipush 62
    //   4486: istore 75
    //   4488: goto -28 -> 4460
    //   4491: bipush 54
    //   4493: istore 75
    //   4495: goto -35 -> 4460
    //   4498: bipush 41
    //   4500: istore 75
    //   4502: goto -42 -> 4460
    //   4505: aload 76
    //   4507: iload 78
    //   4509: caload
    //   4510: istore 79
    //   4512: iload 78
    //   4514: iconst_5
    //   4515: irem
    //   4516: tableswitch	default:+32 -> 4548, 0:+53->4569, 1:+60->4576, 2:+67->4583, 3:+74->4590
    //   4549: fstore_0
    //   4550: istore 80
    //   4552: aload 76
    //   4554: iload 78
    //   4556: iload 80
    //   4558: iload 79
    //   4560: ixor
    //   4561: i2c
    //   4562: castore
    //   4563: iinc 78 1
    //   4566: goto -3988 -> 578
    //   4569: bipush 30
    //   4571: istore 80
    //   4573: goto -21 -> 4552
    //   4576: bipush 62
    //   4578: istore 80
    //   4580: goto -28 -> 4552
    //   4583: bipush 54
    //   4585: istore 80
    //   4587: goto -35 -> 4552
    //   4590: bipush 41
    //   4592: istore 80
    //   4594: goto -42 -> 4552
    //   4597: aload 81
    //   4599: iload 83
    //   4601: caload
    //   4602: istore 84
    //   4604: iload 83
    //   4606: iconst_5
    //   4607: irem
    //   4608: tableswitch	default:+32 -> 4640, 0:+53->4661, 1:+60->4668, 2:+67->4675, 3:+74->4682
    //   4641: fstore_0
    //   4642: istore 85
    //   4644: aload 81
    //   4646: iload 83
    //   4648: iload 85
    //   4650: iload 84
    //   4652: ixor
    //   4653: i2c
    //   4654: castore
    //   4655: iinc 83 1
    //   4658: goto -4042 -> 616
    //   4661: bipush 30
    //   4663: istore 85
    //   4665: goto -21 -> 4644
    //   4668: bipush 62
    //   4670: istore 85
    //   4672: goto -28 -> 4644
    //   4675: bipush 54
    //   4677: istore 85
    //   4679: goto -35 -> 4644
    //   4682: bipush 41
    //   4684: istore 85
    //   4686: goto -42 -> 4644
    //   4689: aload 86
    //   4691: iload 88
    //   4693: caload
    //   4694: istore 89
    //   4696: iload 88
    //   4698: iconst_5
    //   4699: irem
    //   4700: tableswitch	default:+32 -> 4732, 0:+53->4753, 1:+60->4760, 2:+67->4767, 3:+74->4774
    //   4733: fstore_0
    //   4734: istore 90
    //   4736: aload 86
    //   4738: iload 88
    //   4740: iload 90
    //   4742: iload 89
    //   4744: ixor
    //   4745: i2c
    //   4746: castore
    //   4747: iinc 88 1
    //   4750: goto -4096 -> 654
    //   4753: bipush 30
    //   4755: istore 90
    //   4757: goto -21 -> 4736
    //   4760: bipush 62
    //   4762: istore 90
    //   4764: goto -28 -> 4736
    //   4767: bipush 54
    //   4769: istore 90
    //   4771: goto -35 -> 4736
    //   4774: bipush 41
    //   4776: istore 90
    //   4778: goto -42 -> 4736
    //   4781: aload 91
    //   4783: iload 93
    //   4785: caload
    //   4786: istore 94
    //   4788: iload 93
    //   4790: iconst_5
    //   4791: irem
    //   4792: tableswitch	default:+32 -> 4824, 0:+53->4845, 1:+60->4852, 2:+67->4859, 3:+74->4866
    //   4825: fstore_0
    //   4826: istore 95
    //   4828: aload 91
    //   4830: iload 93
    //   4832: iload 95
    //   4834: iload 94
    //   4836: ixor
    //   4837: i2c
    //   4838: castore
    //   4839: iinc 93 1
    //   4842: goto -4150 -> 692
    //   4845: bipush 30
    //   4847: istore 95
    //   4849: goto -21 -> 4828
    //   4852: bipush 62
    //   4854: istore 95
    //   4856: goto -28 -> 4828
    //   4859: bipush 54
    //   4861: istore 95
    //   4863: goto -35 -> 4828
    //   4866: bipush 41
    //   4868: istore 95
    //   4870: goto -42 -> 4828
    //   4873: aload 96
    //   4875: iload 98
    //   4877: caload
    //   4878: istore 99
    //   4880: iload 98
    //   4882: iconst_5
    //   4883: irem
    //   4884: tableswitch	default:+32 -> 4916, 0:+53->4937, 1:+60->4944, 2:+67->4951, 3:+74->4958
    //   4917: fstore_0
    //   4918: istore 100
    //   4920: aload 96
    //   4922: iload 98
    //   4924: iload 100
    //   4926: iload 99
    //   4928: ixor
    //   4929: i2c
    //   4930: castore
    //   4931: iinc 98 1
    //   4934: goto -4204 -> 730
    //   4937: bipush 30
    //   4939: istore 100
    //   4941: goto -21 -> 4920
    //   4944: bipush 62
    //   4946: istore 100
    //   4948: goto -28 -> 4920
    //   4951: bipush 54
    //   4953: istore 100
    //   4955: goto -35 -> 4920
    //   4958: bipush 41
    //   4960: istore 100
    //   4962: goto -42 -> 4920
    //   4965: aload 101
    //   4967: iload 103
    //   4969: caload
    //   4970: istore 104
    //   4972: iload 103
    //   4974: iconst_5
    //   4975: irem
    //   4976: tableswitch	default:+32 -> 5008, 0:+53->5029, 1:+60->5036, 2:+67->5043, 3:+74->5050
    //   5009: fstore_0
    //   5010: istore 105
    //   5012: aload 101
    //   5014: iload 103
    //   5016: iload 105
    //   5018: iload 104
    //   5020: ixor
    //   5021: i2c
    //   5022: castore
    //   5023: iinc 103 1
    //   5026: goto -4258 -> 768
    //   5029: bipush 30
    //   5031: istore 105
    //   5033: goto -21 -> 5012
    //   5036: bipush 62
    //   5038: istore 105
    //   5040: goto -28 -> 5012
    //   5043: bipush 54
    //   5045: istore 105
    //   5047: goto -35 -> 5012
    //   5050: bipush 41
    //   5052: istore 105
    //   5054: goto -42 -> 5012
    //   5057: aload 106
    //   5059: iload 108
    //   5061: caload
    //   5062: istore 109
    //   5064: iload 108
    //   5066: iconst_5
    //   5067: irem
    //   5068: tableswitch	default:+32 -> 5100, 0:+53->5121, 1:+60->5128, 2:+67->5135, 3:+74->5142
    //   5101: fstore_0
    //   5102: istore 110
    //   5104: aload 106
    //   5106: iload 108
    //   5108: iload 110
    //   5110: iload 109
    //   5112: ixor
    //   5113: i2c
    //   5114: castore
    //   5115: iinc 108 1
    //   5118: goto -4312 -> 806
    //   5121: bipush 30
    //   5123: istore 110
    //   5125: goto -21 -> 5104
    //   5128: bipush 62
    //   5130: istore 110
    //   5132: goto -28 -> 5104
    //   5135: bipush 54
    //   5137: istore 110
    //   5139: goto -35 -> 5104
    //   5142: bipush 41
    //   5144: istore 110
    //   5146: goto -42 -> 5104
    //   5149: aload 111
    //   5151: iload 113
    //   5153: caload
    //   5154: istore 114
    //   5156: iload 113
    //   5158: iconst_5
    //   5159: irem
    //   5160: tableswitch	default:+32 -> 5192, 0:+53->5213, 1:+60->5220, 2:+67->5227, 3:+74->5234
    //   5193: fstore_0
    //   5194: istore 115
    //   5196: aload 111
    //   5198: iload 113
    //   5200: iload 115
    //   5202: iload 114
    //   5204: ixor
    //   5205: i2c
    //   5206: castore
    //   5207: iinc 113 1
    //   5210: goto -4366 -> 844
    //   5213: bipush 30
    //   5215: istore 115
    //   5217: goto -21 -> 5196
    //   5220: bipush 62
    //   5222: istore 115
    //   5224: goto -28 -> 5196
    //   5227: bipush 54
    //   5229: istore 115
    //   5231: goto -35 -> 5196
    //   5234: bipush 41
    //   5236: istore 115
    //   5238: goto -42 -> 5196
    //   5241: aload 116
    //   5243: iload 118
    //   5245: caload
    //   5246: istore 119
    //   5248: iload 118
    //   5250: iconst_5
    //   5251: irem
    //   5252: tableswitch	default:+32 -> 5284, 0:+53->5305, 1:+60->5312, 2:+67->5319, 3:+74->5326
    //   5285: fstore_0
    //   5286: istore 120
    //   5288: aload 116
    //   5290: iload 118
    //   5292: iload 120
    //   5294: iload 119
    //   5296: ixor
    //   5297: i2c
    //   5298: castore
    //   5299: iinc 118 1
    //   5302: goto -4420 -> 882
    //   5305: bipush 30
    //   5307: istore 120
    //   5309: goto -21 -> 5288
    //   5312: bipush 62
    //   5314: istore 120
    //   5316: goto -28 -> 5288
    //   5319: bipush 54
    //   5321: istore 120
    //   5323: goto -35 -> 5288
    //   5326: bipush 41
    //   5328: istore 120
    //   5330: goto -42 -> 5288
    //   5333: aload 121
    //   5335: iload 123
    //   5337: caload
    //   5338: istore 124
    //   5340: iload 123
    //   5342: iconst_5
    //   5343: irem
    //   5344: tableswitch	default:+32 -> 5376, 0:+53->5397, 1:+60->5404, 2:+67->5411, 3:+74->5418
    //   5377: fstore_0
    //   5378: istore 125
    //   5380: aload 121
    //   5382: iload 123
    //   5384: iload 125
    //   5386: iload 124
    //   5388: ixor
    //   5389: i2c
    //   5390: castore
    //   5391: iinc 123 1
    //   5394: goto -4474 -> 920
    //   5397: bipush 30
    //   5399: istore 125
    //   5401: goto -21 -> 5380
    //   5404: bipush 62
    //   5406: istore 125
    //   5408: goto -28 -> 5380
    //   5411: bipush 54
    //   5413: istore 125
    //   5415: goto -35 -> 5380
    //   5418: bipush 41
    //   5420: istore 125
    //   5422: goto -42 -> 5380
    //   5425: aload 126
    //   5427: iload 128
    //   5429: caload
    //   5430: istore 129
    //   5432: iload 128
    //   5434: iconst_5
    //   5435: irem
    //   5436: tableswitch	default:+32 -> 5468, 0:+53->5489, 1:+60->5496, 2:+67->5503, 3:+74->5510
    //   5469: fstore_0
    //   5470: istore 130
    //   5472: aload 126
    //   5474: iload 128
    //   5476: iload 130
    //   5478: iload 129
    //   5480: ixor
    //   5481: i2c
    //   5482: castore
    //   5483: iinc 128 1
    //   5486: goto -4528 -> 958
    //   5489: bipush 30
    //   5491: istore 130
    //   5493: goto -21 -> 5472
    //   5496: bipush 62
    //   5498: istore 130
    //   5500: goto -28 -> 5472
    //   5503: bipush 54
    //   5505: istore 130
    //   5507: goto -35 -> 5472
    //   5510: bipush 41
    //   5512: istore 130
    //   5514: goto -42 -> 5472
    //   5517: aload 131
    //   5519: iload 133
    //   5521: caload
    //   5522: istore 134
    //   5524: iload 133
    //   5526: iconst_5
    //   5527: irem
    //   5528: tableswitch	default:+32 -> 5560, 0:+53->5581, 1:+60->5588, 2:+67->5595, 3:+74->5602
    //   5561: fstore_0
    //   5562: istore 135
    //   5564: aload 131
    //   5566: iload 133
    //   5568: iload 135
    //   5570: iload 134
    //   5572: ixor
    //   5573: i2c
    //   5574: castore
    //   5575: iinc 133 1
    //   5578: goto -4582 -> 996
    //   5581: bipush 30
    //   5583: istore 135
    //   5585: goto -21 -> 5564
    //   5588: bipush 62
    //   5590: istore 135
    //   5592: goto -28 -> 5564
    //   5595: bipush 54
    //   5597: istore 135
    //   5599: goto -35 -> 5564
    //   5602: bipush 41
    //   5604: istore 135
    //   5606: goto -42 -> 5564
    //   5609: aload 136
    //   5611: iload 138
    //   5613: caload
    //   5614: istore 139
    //   5616: iload 138
    //   5618: iconst_5
    //   5619: irem
    //   5620: tableswitch	default:+32 -> 5652, 0:+53->5673, 1:+60->5680, 2:+67->5687, 3:+74->5694
    //   5653: fstore_0
    //   5654: istore 140
    //   5656: aload 136
    //   5658: iload 138
    //   5660: iload 140
    //   5662: iload 139
    //   5664: ixor
    //   5665: i2c
    //   5666: castore
    //   5667: iinc 138 1
    //   5670: goto -4636 -> 1034
    //   5673: bipush 30
    //   5675: istore 140
    //   5677: goto -21 -> 5656
    //   5680: bipush 62
    //   5682: istore 140
    //   5684: goto -28 -> 5656
    //   5687: bipush 54
    //   5689: istore 140
    //   5691: goto -35 -> 5656
    //   5694: bipush 41
    //   5696: istore 140
    //   5698: goto -42 -> 5656
    //   5701: aload 141
    //   5703: iload 143
    //   5705: caload
    //   5706: istore 144
    //   5708: iload 143
    //   5710: iconst_5
    //   5711: irem
    //   5712: tableswitch	default:+32 -> 5744, 0:+53->5765, 1:+60->5772, 2:+67->5779, 3:+74->5786
    //   5745: fstore_0
    //   5746: istore 145
    //   5748: aload 141
    //   5750: iload 143
    //   5752: iload 145
    //   5754: iload 144
    //   5756: ixor
    //   5757: i2c
    //   5758: castore
    //   5759: iinc 143 1
    //   5762: goto -4690 -> 1072
    //   5765: bipush 30
    //   5767: istore 145
    //   5769: goto -21 -> 5748
    //   5772: bipush 62
    //   5774: istore 145
    //   5776: goto -28 -> 5748
    //   5779: bipush 54
    //   5781: istore 145
    //   5783: goto -35 -> 5748
    //   5786: bipush 41
    //   5788: istore 145
    //   5790: goto -42 -> 5748
    //   5793: aload 146
    //   5795: iload 148
    //   5797: caload
    //   5798: istore 149
    //   5800: iload 148
    //   5802: iconst_5
    //   5803: irem
    //   5804: tableswitch	default:+32 -> 5836, 0:+53->5857, 1:+60->5864, 2:+67->5871, 3:+74->5878
    //   5837: fstore_0
    //   5838: istore 150
    //   5840: aload 146
    //   5842: iload 148
    //   5844: iload 150
    //   5846: iload 149
    //   5848: ixor
    //   5849: i2c
    //   5850: castore
    //   5851: iinc 148 1
    //   5854: goto -4744 -> 1110
    //   5857: bipush 30
    //   5859: istore 150
    //   5861: goto -21 -> 5840
    //   5864: bipush 62
    //   5866: istore 150
    //   5868: goto -28 -> 5840
    //   5871: bipush 54
    //   5873: istore 150
    //   5875: goto -35 -> 5840
    //   5878: bipush 41
    //   5880: istore 150
    //   5882: goto -42 -> 5840
    //   5885: aload 151
    //   5887: iload 153
    //   5889: caload
    //   5890: istore 154
    //   5892: iload 153
    //   5894: iconst_5
    //   5895: irem
    //   5896: tableswitch	default:+32 -> 5928, 0:+53->5949, 1:+60->5956, 2:+67->5963, 3:+74->5970
    //   5929: fstore_0
    //   5930: istore 155
    //   5932: aload 151
    //   5934: iload 153
    //   5936: iload 155
    //   5938: iload 154
    //   5940: ixor
    //   5941: i2c
    //   5942: castore
    //   5943: iinc 153 1
    //   5946: goto -4798 -> 1148
    //   5949: bipush 30
    //   5951: istore 155
    //   5953: goto -21 -> 5932
    //   5956: bipush 62
    //   5958: istore 155
    //   5960: goto -28 -> 5932
    //   5963: bipush 54
    //   5965: istore 155
    //   5967: goto -35 -> 5932
    //   5970: bipush 41
    //   5972: istore 155
    //   5974: goto -42 -> 5932
    //   5977: aload 156
    //   5979: iload 158
    //   5981: caload
    //   5982: istore 159
    //   5984: iload 158
    //   5986: iconst_5
    //   5987: irem
    //   5988: tableswitch	default:+32 -> 6020, 0:+53->6041, 1:+60->6048, 2:+67->6055, 3:+74->6062
    //   6021: fstore_0
    //   6022: istore 160
    //   6024: aload 156
    //   6026: iload 158
    //   6028: iload 160
    //   6030: iload 159
    //   6032: ixor
    //   6033: i2c
    //   6034: castore
    //   6035: iinc 158 1
    //   6038: goto -4852 -> 1186
    //   6041: bipush 30
    //   6043: istore 160
    //   6045: goto -21 -> 6024
    //   6048: bipush 62
    //   6050: istore 160
    //   6052: goto -28 -> 6024
    //   6055: bipush 54
    //   6057: istore 160
    //   6059: goto -35 -> 6024
    //   6062: bipush 41
    //   6064: istore 160
    //   6066: goto -42 -> 6024
    //   6069: aload 161
    //   6071: iload 163
    //   6073: caload
    //   6074: istore 164
    //   6076: iload 163
    //   6078: iconst_5
    //   6079: irem
    //   6080: tableswitch	default:+32 -> 6112, 0:+53->6133, 1:+60->6140, 2:+67->6147, 3:+74->6154
    //   6113: fstore_0
    //   6114: istore 165
    //   6116: aload 161
    //   6118: iload 163
    //   6120: iload 165
    //   6122: iload 164
    //   6124: ixor
    //   6125: i2c
    //   6126: castore
    //   6127: iinc 163 1
    //   6130: goto -4906 -> 1224
    //   6133: bipush 30
    //   6135: istore 165
    //   6137: goto -21 -> 6116
    //   6140: bipush 62
    //   6142: istore 165
    //   6144: goto -28 -> 6116
    //   6147: bipush 54
    //   6149: istore 165
    //   6151: goto -35 -> 6116
    //   6154: bipush 41
    //   6156: istore 165
    //   6158: goto -42 -> 6116
    //   6161: aload 166
    //   6163: iload 168
    //   6165: caload
    //   6166: istore 169
    //   6168: iload 168
    //   6170: iconst_5
    //   6171: irem
    //   6172: tableswitch	default:+32 -> 6204, 0:+53->6225, 1:+60->6232, 2:+67->6239, 3:+74->6246
    //   6205: fstore_0
    //   6206: istore 170
    //   6208: aload 166
    //   6210: iload 168
    //   6212: iload 170
    //   6214: iload 169
    //   6216: ixor
    //   6217: i2c
    //   6218: castore
    //   6219: iinc 168 1
    //   6222: goto -4960 -> 1262
    //   6225: bipush 30
    //   6227: istore 170
    //   6229: goto -21 -> 6208
    //   6232: bipush 62
    //   6234: istore 170
    //   6236: goto -28 -> 6208
    //   6239: bipush 54
    //   6241: istore 170
    //   6243: goto -35 -> 6208
    //   6246: bipush 41
    //   6248: istore 170
    //   6250: goto -42 -> 6208
    //   6253: aload 171
    //   6255: iload 173
    //   6257: caload
    //   6258: istore 174
    //   6260: iload 173
    //   6262: iconst_5
    //   6263: irem
    //   6264: tableswitch	default:+32 -> 6296, 0:+53->6317, 1:+60->6324, 2:+67->6331, 3:+74->6338
    //   6297: fstore_0
    //   6298: istore 175
    //   6300: aload 171
    //   6302: iload 173
    //   6304: iload 175
    //   6306: iload 174
    //   6308: ixor
    //   6309: i2c
    //   6310: castore
    //   6311: iinc 173 1
    //   6314: goto -5014 -> 1300
    //   6317: bipush 30
    //   6319: istore 175
    //   6321: goto -21 -> 6300
    //   6324: bipush 62
    //   6326: istore 175
    //   6328: goto -28 -> 6300
    //   6331: bipush 54
    //   6333: istore 175
    //   6335: goto -35 -> 6300
    //   6338: bipush 41
    //   6340: istore 175
    //   6342: goto -42 -> 6300
    //   6345: aload 176
    //   6347: iload 178
    //   6349: caload
    //   6350: istore 179
    //   6352: iload 178
    //   6354: iconst_5
    //   6355: irem
    //   6356: tableswitch	default:+32 -> 6388, 0:+53->6409, 1:+60->6416, 2:+67->6423, 3:+74->6430
    //   6389: fstore_0
    //   6390: istore 180
    //   6392: aload 176
    //   6394: iload 178
    //   6396: iload 180
    //   6398: iload 179
    //   6400: ixor
    //   6401: i2c
    //   6402: castore
    //   6403: iinc 178 1
    //   6406: goto -5068 -> 1338
    //   6409: bipush 30
    //   6411: istore 180
    //   6413: goto -21 -> 6392
    //   6416: bipush 62
    //   6418: istore 180
    //   6420: goto -28 -> 6392
    //   6423: bipush 54
    //   6425: istore 180
    //   6427: goto -35 -> 6392
    //   6430: bipush 41
    //   6432: istore 180
    //   6434: goto -42 -> 6392
    //   6437: aload 181
    //   6439: iload 183
    //   6441: caload
    //   6442: istore 184
    //   6444: iload 183
    //   6446: iconst_5
    //   6447: irem
    //   6448: tableswitch	default:+32 -> 6480, 0:+53->6501, 1:+60->6508, 2:+67->6515, 3:+74->6522
    //   6481: fstore_0
    //   6482: istore 185
    //   6484: aload 181
    //   6486: iload 183
    //   6488: iload 185
    //   6490: iload 184
    //   6492: ixor
    //   6493: i2c
    //   6494: castore
    //   6495: iinc 183 1
    //   6498: goto -5122 -> 1376
    //   6501: bipush 30
    //   6503: istore 185
    //   6505: goto -21 -> 6484
    //   6508: bipush 62
    //   6510: istore 185
    //   6512: goto -28 -> 6484
    //   6515: bipush 54
    //   6517: istore 185
    //   6519: goto -35 -> 6484
    //   6522: bipush 41
    //   6524: istore 185
    //   6526: goto -42 -> 6484
    //   6529: aload 186
    //   6531: iload 188
    //   6533: caload
    //   6534: istore 189
    //   6536: iload 188
    //   6538: iconst_5
    //   6539: irem
    //   6540: tableswitch	default:+32 -> 6572, 0:+53->6593, 1:+60->6600, 2:+67->6607, 3:+74->6614
    //   6573: fstore_0
    //   6574: istore 190
    //   6576: aload 186
    //   6578: iload 188
    //   6580: iload 190
    //   6582: iload 189
    //   6584: ixor
    //   6585: i2c
    //   6586: castore
    //   6587: iinc 188 1
    //   6590: goto -5176 -> 1414
    //   6593: bipush 30
    //   6595: istore 190
    //   6597: goto -21 -> 6576
    //   6600: bipush 62
    //   6602: istore 190
    //   6604: goto -28 -> 6576
    //   6607: bipush 54
    //   6609: istore 190
    //   6611: goto -35 -> 6576
    //   6614: bipush 41
    //   6616: istore 190
    //   6618: goto -42 -> 6576
    //   6621: aload 191
    //   6623: iload 193
    //   6625: caload
    //   6626: istore 194
    //   6628: iload 193
    //   6630: iconst_5
    //   6631: irem
    //   6632: tableswitch	default:+32 -> 6664, 0:+53->6685, 1:+60->6692, 2:+67->6699, 3:+74->6706
    //   6665: fstore_0
    //   6666: istore 195
    //   6668: aload 191
    //   6670: iload 193
    //   6672: iload 195
    //   6674: iload 194
    //   6676: ixor
    //   6677: i2c
    //   6678: castore
    //   6679: iinc 193 1
    //   6682: goto -5230 -> 1452
    //   6685: bipush 30
    //   6687: istore 195
    //   6689: goto -21 -> 6668
    //   6692: bipush 62
    //   6694: istore 195
    //   6696: goto -28 -> 6668
    //   6699: bipush 54
    //   6701: istore 195
    //   6703: goto -35 -> 6668
    //   6706: bipush 41
    //   6708: istore 195
    //   6710: goto -42 -> 6668
    //   6713: aload 196
    //   6715: iload 198
    //   6717: caload
    //   6718: istore 199
    //   6720: iload 198
    //   6722: iconst_5
    //   6723: irem
    //   6724: tableswitch	default:+32 -> 6756, 0:+53->6777, 1:+60->6784, 2:+67->6791, 3:+74->6798
    //   6757: fstore_0
    //   6758: istore 200
    //   6760: aload 196
    //   6762: iload 198
    //   6764: iload 200
    //   6766: iload 199
    //   6768: ixor
    //   6769: i2c
    //   6770: castore
    //   6771: iinc 198 1
    //   6774: goto -5284 -> 1490
    //   6777: bipush 30
    //   6779: istore 200
    //   6781: goto -21 -> 6760
    //   6784: bipush 62
    //   6786: istore 200
    //   6788: goto -28 -> 6760
    //   6791: bipush 54
    //   6793: istore 200
    //   6795: goto -35 -> 6760
    //   6798: bipush 41
    //   6800: istore 200
    //   6802: goto -42 -> 6760
    //   6805: aload 201
    //   6807: iload 203
    //   6809: caload
    //   6810: istore 204
    //   6812: iload 203
    //   6814: iconst_5
    //   6815: irem
    //   6816: tableswitch	default:+32 -> 6848, 0:+53->6869, 1:+60->6876, 2:+67->6883, 3:+74->6890
    //   6849: fstore_0
    //   6850: istore 205
    //   6852: aload 201
    //   6854: iload 203
    //   6856: iload 205
    //   6858: iload 204
    //   6860: ixor
    //   6861: i2c
    //   6862: castore
    //   6863: iinc 203 1
    //   6866: goto -5338 -> 1528
    //   6869: bipush 30
    //   6871: istore 205
    //   6873: goto -21 -> 6852
    //   6876: bipush 62
    //   6878: istore 205
    //   6880: goto -28 -> 6852
    //   6883: bipush 54
    //   6885: istore 205
    //   6887: goto -35 -> 6852
    //   6890: bipush 41
    //   6892: istore 205
    //   6894: goto -42 -> 6852
    //   6897: aload 206
    //   6899: iload 208
    //   6901: caload
    //   6902: istore 209
    //   6904: iload 208
    //   6906: iconst_5
    //   6907: irem
    //   6908: tableswitch	default:+32 -> 6940, 0:+53->6961, 1:+60->6968, 2:+67->6975, 3:+74->6982
    //   6941: fstore_0
    //   6942: istore 210
    //   6944: aload 206
    //   6946: iload 208
    //   6948: iload 210
    //   6950: iload 209
    //   6952: ixor
    //   6953: i2c
    //   6954: castore
    //   6955: iinc 208 1
    //   6958: goto -5392 -> 1566
    //   6961: bipush 30
    //   6963: istore 210
    //   6965: goto -21 -> 6944
    //   6968: bipush 62
    //   6970: istore 210
    //   6972: goto -28 -> 6944
    //   6975: bipush 54
    //   6977: istore 210
    //   6979: goto -35 -> 6944
    //   6982: bipush 41
    //   6984: istore 210
    //   6986: goto -42 -> 6944
    //   6989: aload 211
    //   6991: iload 213
    //   6993: caload
    //   6994: istore 214
    //   6996: iload 213
    //   6998: iconst_5
    //   6999: irem
    //   7000: tableswitch	default:+32 -> 7032, 0:+53->7053, 1:+60->7060, 2:+67->7067, 3:+74->7074
    //   7033: fstore_0
    //   7034: istore 215
    //   7036: aload 211
    //   7038: iload 213
    //   7040: iload 215
    //   7042: iload 214
    //   7044: ixor
    //   7045: i2c
    //   7046: castore
    //   7047: iinc 213 1
    //   7050: goto -5446 -> 1604
    //   7053: bipush 30
    //   7055: istore 215
    //   7057: goto -21 -> 7036
    //   7060: bipush 62
    //   7062: istore 215
    //   7064: goto -28 -> 7036
    //   7067: bipush 54
    //   7069: istore 215
    //   7071: goto -35 -> 7036
    //   7074: bipush 41
    //   7076: istore 215
    //   7078: goto -42 -> 7036
    //   7081: aload 216
    //   7083: iload 218
    //   7085: caload
    //   7086: istore 219
    //   7088: iload 218
    //   7090: iconst_5
    //   7091: irem
    //   7092: tableswitch	default:+32 -> 7124, 0:+53->7145, 1:+60->7152, 2:+67->7159, 3:+74->7166
    //   7125: fstore_0
    //   7126: istore 220
    //   7128: aload 216
    //   7130: iload 218
    //   7132: iload 220
    //   7134: iload 219
    //   7136: ixor
    //   7137: i2c
    //   7138: castore
    //   7139: iinc 218 1
    //   7142: goto -5500 -> 1642
    //   7145: bipush 30
    //   7147: istore 220
    //   7149: goto -21 -> 7128
    //   7152: bipush 62
    //   7154: istore 220
    //   7156: goto -28 -> 7128
    //   7159: bipush 54
    //   7161: istore 220
    //   7163: goto -35 -> 7128
    //   7166: bipush 41
    //   7168: istore 220
    //   7170: goto -42 -> 7128
    //   7173: aload 221
    //   7175: iload 223
    //   7177: caload
    //   7178: istore 224
    //   7180: iload 223
    //   7182: iconst_5
    //   7183: irem
    //   7184: tableswitch	default:+32 -> 7216, 0:+53->7237, 1:+60->7244, 2:+67->7251, 3:+74->7258
    //   7217: fstore_0
    //   7218: istore 225
    //   7220: aload 221
    //   7222: iload 223
    //   7224: iload 225
    //   7226: iload 224
    //   7228: ixor
    //   7229: i2c
    //   7230: castore
    //   7231: iinc 223 1
    //   7234: goto -5554 -> 1680
    //   7237: bipush 30
    //   7239: istore 225
    //   7241: goto -21 -> 7220
    //   7244: bipush 62
    //   7246: istore 225
    //   7248: goto -28 -> 7220
    //   7251: bipush 54
    //   7253: istore 225
    //   7255: goto -35 -> 7220
    //   7258: bipush 41
    //   7260: istore 225
    //   7262: goto -42 -> 7220
    //   7265: aload 226
    //   7267: iload 228
    //   7269: caload
    //   7270: istore 229
    //   7272: iload 228
    //   7274: iconst_5
    //   7275: irem
    //   7276: tableswitch	default:+32 -> 7308, 0:+53->7329, 1:+60->7336, 2:+67->7343, 3:+74->7350
    //   7309: fstore_0
    //   7310: istore 230
    //   7312: aload 226
    //   7314: iload 228
    //   7316: iload 230
    //   7318: iload 229
    //   7320: ixor
    //   7321: i2c
    //   7322: castore
    //   7323: iinc 228 1
    //   7326: goto -5608 -> 1718
    //   7329: bipush 30
    //   7331: istore 230
    //   7333: goto -21 -> 7312
    //   7336: bipush 62
    //   7338: istore 230
    //   7340: goto -28 -> 7312
    //   7343: bipush 54
    //   7345: istore 230
    //   7347: goto -35 -> 7312
    //   7350: bipush 41
    //   7352: istore 230
    //   7354: goto -42 -> 7312
    //   7357: aload 231
    //   7359: iload 233
    //   7361: caload
    //   7362: istore 234
    //   7364: iload 233
    //   7366: iconst_5
    //   7367: irem
    //   7368: tableswitch	default:+32 -> 7400, 0:+53->7421, 1:+60->7428, 2:+67->7435, 3:+74->7442
    //   7401: fstore_0
    //   7402: istore 235
    //   7404: aload 231
    //   7406: iload 233
    //   7408: iload 235
    //   7410: iload 234
    //   7412: ixor
    //   7413: i2c
    //   7414: castore
    //   7415: iinc 233 1
    //   7418: goto -5662 -> 1756
    //   7421: bipush 30
    //   7423: istore 235
    //   7425: goto -21 -> 7404
    //   7428: bipush 62
    //   7430: istore 235
    //   7432: goto -28 -> 7404
    //   7435: bipush 54
    //   7437: istore 235
    //   7439: goto -35 -> 7404
    //   7442: bipush 41
    //   7444: istore 235
    //   7446: goto -42 -> 7404
    //   7449: aload 236
    //   7451: iload 238
    //   7453: caload
    //   7454: istore 239
    //   7456: iload 238
    //   7458: iconst_5
    //   7459: irem
    //   7460: tableswitch	default:+32 -> 7492, 0:+53->7513, 1:+60->7520, 2:+67->7527, 3:+74->7534
    //   7493: fstore_0
    //   7494: istore 240
    //   7496: aload 236
    //   7498: iload 238
    //   7500: iload 240
    //   7502: iload 239
    //   7504: ixor
    //   7505: i2c
    //   7506: castore
    //   7507: iinc 238 1
    //   7510: goto -5716 -> 1794
    //   7513: bipush 30
    //   7515: istore 240
    //   7517: goto -21 -> 7496
    //   7520: bipush 62
    //   7522: istore 240
    //   7524: goto -28 -> 7496
    //   7527: bipush 54
    //   7529: istore 240
    //   7531: goto -35 -> 7496
    //   7534: bipush 41
    //   7536: istore 240
    //   7538: goto -42 -> 7496
    //   7541: aload 241
    //   7543: iload 243
    //   7545: caload
    //   7546: istore 244
    //   7548: iload 243
    //   7550: iconst_5
    //   7551: irem
    //   7552: tableswitch	default:+32 -> 7584, 0:+53->7605, 1:+60->7612, 2:+67->7619, 3:+74->7626
    //   7585: fstore_0
    //   7586: istore 245
    //   7588: aload 241
    //   7590: iload 243
    //   7592: iload 245
    //   7594: iload 244
    //   7596: ixor
    //   7597: i2c
    //   7598: castore
    //   7599: iinc 243 1
    //   7602: goto -5770 -> 1832
    //   7605: bipush 30
    //   7607: istore 245
    //   7609: goto -21 -> 7588
    //   7612: bipush 62
    //   7614: istore 245
    //   7616: goto -28 -> 7588
    //   7619: bipush 54
    //   7621: istore 245
    //   7623: goto -35 -> 7588
    //   7626: bipush 41
    //   7628: istore 245
    //   7630: goto -42 -> 7588
    //   7633: aload 246
    //   7635: iload 248
    //   7637: caload
    //   7638: istore 249
    //   7640: iload 248
    //   7642: iconst_5
    //   7643: irem
    //   7644: tableswitch	default:+32 -> 7676, 0:+53->7697, 1:+60->7704, 2:+67->7711, 3:+74->7718
    //   7677: fstore_0
    //   7678: istore 250
    //   7680: aload 246
    //   7682: iload 248
    //   7684: iload 250
    //   7686: iload 249
    //   7688: ixor
    //   7689: i2c
    //   7690: castore
    //   7691: iinc 248 1
    //   7694: goto -5824 -> 1870
    //   7697: bipush 30
    //   7699: istore 250
    //   7701: goto -21 -> 7680
    //   7704: bipush 62
    //   7706: istore 250
    //   7708: goto -28 -> 7680
    //   7711: bipush 54
    //   7713: istore 250
    //   7715: goto -35 -> 7680
    //   7718: bipush 41
    //   7720: istore 250
    //   7722: goto -42 -> 7680
    //   7725: aload 251
    //   7727: iload 253
    //   7729: caload
    //   7730: istore 254
    //   7732: iload 253
    //   7734: iconst_5
    //   7735: irem
    //   7736: tableswitch	default:+32 -> 7768, 0:+53->7789, 1:+60->7796, 2:+67->7803, 3:+74->7810
    //   7769: fstore_0
    //   7770: istore 255
    //   7772: aload 251
    //   7774: iload 253
    //   7776: iload 255
    //   7778: iload 254
    //   7780: ixor
    //   7781: i2c
    //   7782: castore
    //   7783: iinc 253 1
    //   7786: goto -5878 -> 1908
    //   7789: bipush 30
    //   7791: istore 255
    //   7793: goto -21 -> 7772
    //   7796: bipush 62
    //   7798: istore 255
    //   7800: goto -28 -> 7772
    //   7803: bipush 54
    //   7805: istore 255
    //   7807: goto -35 -> 7772
    //   7810: bipush 41
    //   7812: istore 255
    //   7814: goto -42 -> 7772
    //   7817: wide
    //   7821: wide
    //   7825: caload
    //   7826: wide
    //   7830: wide
    //   7834: iconst_5
    //   7835: irem
    //   7836: tableswitch	default:+32 -> 7868, 0:+66->7902, 1:+75->7911, 2:+84->7920, 3:+93->7929
    //   7869: fstore_0
    //   7870: wide
    //   7874: wide
    //   7878: wide
    //   7882: wide
    //   7886: wide
    //   7890: ixor
    //   7891: i2c
    //   7892: castore
    //   7893: wide
    //   7899: goto -5945 -> 1954
    //   7902: bipush 30
    //   7904: wide
    //   7908: goto -34 -> 7874
    //   7911: bipush 62
    //   7913: wide
    //   7917: goto -43 -> 7874
    //   7920: bipush 54
    //   7922: wide
    //   7926: goto -52 -> 7874
    //   7929: bipush 41
    //   7931: wide
    //   7935: goto -61 -> 7874
    //   7938: wide
    //   7942: wide
    //   7946: caload
    //   7947: wide
    //   7951: wide
    //   7955: iconst_5
    //   7956: irem
    //   7957: tableswitch	default:+31 -> 7988, 0:+65->8022, 1:+74->8031, 2:+83->8040, 3:+92->8049
    //   7989: fstore_0
    //   7990: wide
    //   7994: wide
    //   7998: wide
    //   8002: wide
    //   8006: wide
    //   8010: ixor
    //   8011: i2c
    //   8012: castore
    //   8013: wide
    //   8019: goto -6013 -> 2006
    //   8022: bipush 30
    //   8024: wide
    //   8028: goto -34 -> 7994
    //   8031: bipush 62
    //   8033: wide
    //   8037: goto -43 -> 7994
    //   8040: bipush 54
    //   8042: wide
    //   8046: goto -52 -> 7994
    //   8049: bipush 41
    //   8051: wide
    //   8055: goto -61 -> 7994
    //   8058: wide
    //   8062: wide
    //   8066: caload
    //   8067: wide
    //   8071: wide
    //   8075: iconst_5
    //   8076: irem
    //   8077: tableswitch	default:+31 -> 8108, 0:+65->8142, 1:+74->8151, 2:+83->8160, 3:+92->8169
    //   8109: fstore_0
    //   8110: wide
    //   8114: wide
    //   8118: wide
    //   8122: wide
    //   8126: wide
    //   8130: ixor
    //   8131: i2c
    //   8132: castore
    //   8133: wide
    //   8139: goto -6081 -> 2058
    //   8142: bipush 30
    //   8144: wide
    //   8148: goto -34 -> 8114
    //   8151: bipush 62
    //   8153: wide
    //   8157: goto -43 -> 8114
    //   8160: bipush 54
    //   8162: wide
    //   8166: goto -52 -> 8114
    //   8169: bipush 41
    //   8171: wide
    //   8175: goto -61 -> 8114
    //   8178: wide
    //   8182: wide
    //   8186: caload
    //   8187: wide
    //   8191: wide
    //   8195: iconst_5
    //   8196: irem
    //   8197: tableswitch	default:+31 -> 8228, 0:+65->8262, 1:+74->8271, 2:+83->8280, 3:+92->8289
    //   8229: fstore_0
    //   8230: wide
    //   8234: wide
    //   8238: wide
    //   8242: wide
    //   8246: wide
    //   8250: ixor
    //   8251: i2c
    //   8252: castore
    //   8253: wide
    //   8259: goto -6149 -> 2110
    //   8262: bipush 30
    //   8264: wide
    //   8268: goto -34 -> 8234
    //   8271: bipush 62
    //   8273: wide
    //   8277: goto -43 -> 8234
    //   8280: bipush 54
    //   8282: wide
    //   8286: goto -52 -> 8234
    //   8289: bipush 41
    //   8291: wide
    //   8295: goto -61 -> 8234
    //   8298: wide
    //   8302: wide
    //   8306: caload
    //   8307: wide
    //   8311: wide
    //   8315: iconst_5
    //   8316: irem
    //   8317: tableswitch	default:+31 -> 8348, 0:+65->8382, 1:+74->8391, 2:+83->8400, 3:+92->8409
    //   8349: fstore_0
    //   8350: wide
    //   8354: wide
    //   8358: wide
    //   8362: wide
    //   8366: wide
    //   8370: ixor
    //   8371: i2c
    //   8372: castore
    //   8373: wide
    //   8379: goto -6217 -> 2162
    //   8382: bipush 30
    //   8384: wide
    //   8388: goto -34 -> 8354
    //   8391: bipush 62
    //   8393: wide
    //   8397: goto -43 -> 8354
    //   8400: bipush 54
    //   8402: wide
    //   8406: goto -52 -> 8354
    //   8409: bipush 41
    //   8411: wide
    //   8415: goto -61 -> 8354
    //   8418: wide
    //   8422: wide
    //   8426: caload
    //   8427: wide
    //   8431: wide
    //   8435: iconst_5
    //   8436: irem
    //   8437: tableswitch	default:+31 -> 8468, 0:+65->8502, 1:+74->8511, 2:+83->8520, 3:+92->8529
    //   8469: fstore_0
    //   8470: wide
    //   8474: wide
    //   8478: wide
    //   8482: wide
    //   8486: wide
    //   8490: ixor
    //   8491: i2c
    //   8492: castore
    //   8493: wide
    //   8499: goto -6285 -> 2214
    //   8502: bipush 30
    //   8504: wide
    //   8508: goto -34 -> 8474
    //   8511: bipush 62
    //   8513: wide
    //   8517: goto -43 -> 8474
    //   8520: bipush 54
    //   8522: wide
    //   8526: goto -52 -> 8474
    //   8529: bipush 41
    //   8531: wide
    //   8535: goto -61 -> 8474
    //   8538: wide
    //   8542: wide
    //   8546: caload
    //   8547: wide
    //   8551: wide
    //   8555: iconst_5
    //   8556: irem
    //   8557: tableswitch	default:+31 -> 8588, 0:+65->8622, 1:+74->8631, 2:+83->8640, 3:+92->8649
    //   8589: fstore_0
    //   8590: wide
    //   8594: wide
    //   8598: wide
    //   8602: wide
    //   8606: wide
    //   8610: ixor
    //   8611: i2c
    //   8612: castore
    //   8613: wide
    //   8619: goto -6353 -> 2266
    //   8622: bipush 30
    //   8624: wide
    //   8628: goto -34 -> 8594
    //   8631: bipush 62
    //   8633: wide
    //   8637: goto -43 -> 8594
    //   8640: bipush 54
    //   8642: wide
    //   8646: goto -52 -> 8594
    //   8649: bipush 41
    //   8651: wide
    //   8655: goto -61 -> 8594
    //   8658: wide
    //   8662: wide
    //   8666: caload
    //   8667: wide
    //   8671: wide
    //   8675: iconst_5
    //   8676: irem
    //   8677: tableswitch	default:+31 -> 8708, 0:+65->8742, 1:+74->8751, 2:+83->8760, 3:+92->8769
    //   8709: fstore_0
    //   8710: wide
    //   8714: wide
    //   8718: wide
    //   8722: wide
    //   8726: wide
    //   8730: ixor
    //   8731: i2c
    //   8732: castore
    //   8733: wide
    //   8739: goto -6421 -> 2318
    //   8742: bipush 30
    //   8744: wide
    //   8748: goto -34 -> 8714
    //   8751: bipush 62
    //   8753: wide
    //   8757: goto -43 -> 8714
    //   8760: bipush 54
    //   8762: wide
    //   8766: goto -52 -> 8714
    //   8769: bipush 41
    //   8771: wide
    //   8775: goto -61 -> 8714
    //   8778: wide
    //   8782: wide
    //   8786: caload
    //   8787: wide
    //   8791: wide
    //   8795: iconst_5
    //   8796: irem
    //   8797: tableswitch	default:+31 -> 8828, 0:+65->8862, 1:+74->8871, 2:+83->8880, 3:+92->8889
    //   8829: fstore_0
    //   8830: wide
    //   8834: wide
    //   8838: wide
    //   8842: wide
    //   8846: wide
    //   8850: ixor
    //   8851: i2c
    //   8852: castore
    //   8853: wide
    //   8859: goto -6489 -> 2370
    //   8862: bipush 30
    //   8864: wide
    //   8868: goto -34 -> 8834
    //   8871: bipush 62
    //   8873: wide
    //   8877: goto -43 -> 8834
    //   8880: bipush 54
    //   8882: wide
    //   8886: goto -52 -> 8834
    //   8889: bipush 41
    //   8891: wide
    //   8895: goto -61 -> 8834
    //   8898: wide
    //   8902: wide
    //   8906: caload
    //   8907: wide
    //   8911: wide
    //   8915: iconst_5
    //   8916: irem
    //   8917: tableswitch	default:+31 -> 8948, 0:+65->8982, 1:+74->8991, 2:+83->9000, 3:+92->9009
    //   8949: fstore_0
    //   8950: wide
    //   8954: wide
    //   8958: wide
    //   8962: wide
    //   8966: wide
    //   8970: ixor
    //   8971: i2c
    //   8972: castore
    //   8973: wide
    //   8979: goto -6557 -> 2422
    //   8982: bipush 30
    //   8984: wide
    //   8988: goto -34 -> 8954
    //   8991: bipush 62
    //   8993: wide
    //   8997: goto -43 -> 8954
    //   9000: bipush 54
    //   9002: wide
    //   9006: goto -52 -> 8954
    //   9009: bipush 41
    //   9011: wide
    //   9015: goto -61 -> 8954
    //   9018: wide
    //   9022: wide
    //   9026: caload
    //   9027: wide
    //   9031: wide
    //   9035: iconst_5
    //   9036: irem
    //   9037: tableswitch	default:+31 -> 9068, 0:+65->9102, 1:+74->9111, 2:+83->9120, 3:+92->9129
    //   9069: fstore_0
    //   9070: wide
    //   9074: wide
    //   9078: wide
    //   9082: wide
    //   9086: wide
    //   9090: ixor
    //   9091: i2c
    //   9092: castore
    //   9093: wide
    //   9099: goto -6625 -> 2474
    //   9102: bipush 30
    //   9104: wide
    //   9108: goto -34 -> 9074
    //   9111: bipush 62
    //   9113: wide
    //   9117: goto -43 -> 9074
    //   9120: bipush 54
    //   9122: wide
    //   9126: goto -52 -> 9074
    //   9129: bipush 41
    //   9131: wide
    //   9135: goto -61 -> 9074
    //   9138: wide
    //   9142: wide
    //   9146: caload
    //   9147: wide
    //   9151: wide
    //   9155: iconst_5
    //   9156: irem
    //   9157: tableswitch	default:+31 -> 9188, 0:+65->9222, 1:+74->9231, 2:+83->9240, 3:+92->9249
    //   9189: fstore_0
    //   9190: wide
    //   9194: wide
    //   9198: wide
    //   9202: wide
    //   9206: wide
    //   9210: ixor
    //   9211: i2c
    //   9212: castore
    //   9213: wide
    //   9219: goto -6693 -> 2526
    //   9222: bipush 30
    //   9224: wide
    //   9228: goto -34 -> 9194
    //   9231: bipush 62
    //   9233: wide
    //   9237: goto -43 -> 9194
    //   9240: bipush 54
    //   9242: wide
    //   9246: goto -52 -> 9194
    //   9249: bipush 41
    //   9251: wide
    //   9255: goto -61 -> 9194
    //   9258: wide
    //   9262: wide
    //   9266: caload
    //   9267: wide
    //   9271: wide
    //   9275: iconst_5
    //   9276: irem
    //   9277: tableswitch	default:+31 -> 9308, 0:+65->9342, 1:+74->9351, 2:+83->9360, 3:+92->9369
    //   9309: fstore_0
    //   9310: wide
    //   9314: wide
    //   9318: wide
    //   9322: wide
    //   9326: wide
    //   9330: ixor
    //   9331: i2c
    //   9332: castore
    //   9333: wide
    //   9339: goto -6761 -> 2578
    //   9342: bipush 30
    //   9344: wide
    //   9348: goto -34 -> 9314
    //   9351: bipush 62
    //   9353: wide
    //   9357: goto -43 -> 9314
    //   9360: bipush 54
    //   9362: wide
    //   9366: goto -52 -> 9314
    //   9369: bipush 41
    //   9371: wide
    //   9375: goto -61 -> 9314
    //   9378: wide
    //   9382: wide
    //   9386: caload
    //   9387: wide
    //   9391: wide
    //   9395: iconst_5
    //   9396: irem
    //   9397: tableswitch	default:+31 -> 9428, 0:+65->9462, 1:+74->9471, 2:+83->9480, 3:+92->9489
    //   9429: fstore_0
    //   9430: wide
    //   9434: wide
    //   9438: wide
    //   9442: wide
    //   9446: wide
    //   9450: ixor
    //   9451: i2c
    //   9452: castore
    //   9453: wide
    //   9459: goto -6829 -> 2630
    //   9462: bipush 30
    //   9464: wide
    //   9468: goto -34 -> 9434
    //   9471: bipush 62
    //   9473: wide
    //   9477: goto -43 -> 9434
    //   9480: bipush 54
    //   9482: wide
    //   9486: goto -52 -> 9434
    //   9489: bipush 41
    //   9491: wide
    //   9495: goto -61 -> 9434
    //   9498: wide
    //   9502: wide
    //   9506: caload
    //   9507: wide
    //   9511: wide
    //   9515: iconst_5
    //   9516: irem
    //   9517: tableswitch	default:+31 -> 9548, 0:+65->9582, 1:+74->9591, 2:+83->9600, 3:+92->9609
    //   9549: fstore_0
    //   9550: wide
    //   9554: wide
    //   9558: wide
    //   9562: wide
    //   9566: wide
    //   9570: ixor
    //   9571: i2c
    //   9572: castore
    //   9573: wide
    //   9579: goto -6897 -> 2682
    //   9582: bipush 30
    //   9584: wide
    //   9588: goto -34 -> 9554
    //   9591: bipush 62
    //   9593: wide
    //   9597: goto -43 -> 9554
    //   9600: bipush 54
    //   9602: wide
    //   9606: goto -52 -> 9554
    //   9609: bipush 41
    //   9611: wide
    //   9615: goto -61 -> 9554
    //   9618: wide
    //   9622: wide
    //   9626: caload
    //   9627: wide
    //   9631: wide
    //   9635: iconst_5
    //   9636: irem
    //   9637: tableswitch	default:+31 -> 9668, 0:+65->9702, 1:+74->9711, 2:+83->9720, 3:+92->9729
    //   9669: fstore_0
    //   9670: wide
    //   9674: wide
    //   9678: wide
    //   9682: wide
    //   9686: wide
    //   9690: ixor
    //   9691: i2c
    //   9692: castore
    //   9693: wide
    //   9699: goto -6965 -> 2734
    //   9702: bipush 30
    //   9704: wide
    //   9708: goto -34 -> 9674
    //   9711: bipush 62
    //   9713: wide
    //   9717: goto -43 -> 9674
    //   9720: bipush 54
    //   9722: wide
    //   9726: goto -52 -> 9674
    //   9729: bipush 41
    //   9731: wide
    //   9735: goto -61 -> 9674
    //   9738: wide
    //   9742: wide
    //   9746: caload
    //   9747: wide
    //   9751: wide
    //   9755: iconst_5
    //   9756: irem
    //   9757: tableswitch	default:+31 -> 9788, 0:+65->9822, 1:+74->9831, 2:+83->9840, 3:+92->9849
    //   9789: fstore_0
    //   9790: wide
    //   9794: wide
    //   9798: wide
    //   9802: wide
    //   9806: wide
    //   9810: ixor
    //   9811: i2c
    //   9812: castore
    //   9813: wide
    //   9819: goto -7033 -> 2786
    //   9822: bipush 30
    //   9824: wide
    //   9828: goto -34 -> 9794
    //   9831: bipush 62
    //   9833: wide
    //   9837: goto -43 -> 9794
    //   9840: bipush 54
    //   9842: wide
    //   9846: goto -52 -> 9794
    //   9849: bipush 41
    //   9851: wide
    //   9855: goto -61 -> 9794
    //   9858: wide
    //   9862: wide
    //   9866: caload
    //   9867: wide
    //   9871: wide
    //   9875: iconst_5
    //   9876: irem
    //   9877: tableswitch	default:+31 -> 9908, 0:+65->9942, 1:+74->9951, 2:+83->9960, 3:+92->9969
    //   9909: fstore_0
    //   9910: wide
    //   9914: wide
    //   9918: wide
    //   9922: wide
    //   9926: wide
    //   9930: ixor
    //   9931: i2c
    //   9932: castore
    //   9933: wide
    //   9939: goto -7101 -> 2838
    //   9942: bipush 30
    //   9944: wide
    //   9948: goto -34 -> 9914
    //   9951: bipush 62
    //   9953: wide
    //   9957: goto -43 -> 9914
    //   9960: bipush 54
    //   9962: wide
    //   9966: goto -52 -> 9914
    //   9969: bipush 41
    //   9971: wide
    //   9975: goto -61 -> 9914
    //   9978: wide
    //   9982: wide
    //   9986: caload
    //   9987: wide
    //   9991: wide
    //   9995: iconst_5
    //   9996: irem
    //   9997: tableswitch	default:+31 -> 10028, 0:+65->10062, 1:+74->10071, 2:+83->10080, 3:+92->10089
    //   10029: fstore_0
    //   10030: wide
    //   10034: wide
    //   10038: wide
    //   10042: wide
    //   10046: wide
    //   10050: ixor
    //   10051: i2c
    //   10052: castore
    //   10053: wide
    //   10059: goto -7169 -> 2890
    //   10062: bipush 30
    //   10064: wide
    //   10068: goto -34 -> 10034
    //   10071: bipush 62
    //   10073: wide
    //   10077: goto -43 -> 10034
    //   10080: bipush 54
    //   10082: wide
    //   10086: goto -52 -> 10034
    //   10089: bipush 41
    //   10091: wide
    //   10095: goto -61 -> 10034
    //   10098: wide
    //   10102: wide
    //   10106: caload
    //   10107: wide
    //   10111: wide
    //   10115: iconst_5
    //   10116: irem
    //   10117: tableswitch	default:+31 -> 10148, 0:+65->10182, 1:+74->10191, 2:+83->10200, 3:+92->10209
    //   10149: fstore_0
    //   10150: wide
    //   10154: wide
    //   10158: wide
    //   10162: wide
    //   10166: wide
    //   10170: ixor
    //   10171: i2c
    //   10172: castore
    //   10173: wide
    //   10179: goto -7237 -> 2942
    //   10182: bipush 30
    //   10184: wide
    //   10188: goto -34 -> 10154
    //   10191: bipush 62
    //   10193: wide
    //   10197: goto -43 -> 10154
    //   10200: bipush 54
    //   10202: wide
    //   10206: goto -52 -> 10154
    //   10209: bipush 41
    //   10211: wide
    //   10215: goto -61 -> 10154
    //   10218: wide
    //   10222: wide
    //   10226: caload
    //   10227: wide
    //   10231: wide
    //   10235: iconst_5
    //   10236: irem
    //   10237: tableswitch	default:+31 -> 10268, 0:+65->10302, 1:+74->10311, 2:+83->10320, 3:+92->10329
    //   10269: fstore_0
    //   10270: wide
    //   10274: wide
    //   10278: wide
    //   10282: wide
    //   10286: wide
    //   10290: ixor
    //   10291: i2c
    //   10292: castore
    //   10293: wide
    //   10299: goto -7305 -> 2994
    //   10302: bipush 30
    //   10304: wide
    //   10308: goto -34 -> 10274
    //   10311: bipush 62
    //   10313: wide
    //   10317: goto -43 -> 10274
    //   10320: bipush 54
    //   10322: wide
    //   10326: goto -52 -> 10274
    //   10329: bipush 41
    //   10331: wide
    //   10335: goto -61 -> 10274
    //   10338: wide
    //   10342: wide
    //   10346: caload
    //   10347: wide
    //   10351: wide
    //   10355: iconst_5
    //   10356: irem
    //   10357: tableswitch	default:+31 -> 10388, 0:+65->10422, 1:+74->10431, 2:+83->10440, 3:+92->10449
    //   10389: fstore_0
    //   10390: wide
    //   10394: wide
    //   10398: wide
    //   10402: wide
    //   10406: wide
    //   10410: ixor
    //   10411: i2c
    //   10412: castore
    //   10413: wide
    //   10419: goto -7373 -> 3046
    //   10422: bipush 30
    //   10424: wide
    //   10428: goto -34 -> 10394
    //   10431: bipush 62
    //   10433: wide
    //   10437: goto -43 -> 10394
    //   10440: bipush 54
    //   10442: wide
    //   10446: goto -52 -> 10394
    //   10449: bipush 41
    //   10451: wide
    //   10455: goto -61 -> 10394
    //   10458: wide
    //   10462: wide
    //   10466: caload
    //   10467: wide
    //   10471: wide
    //   10475: iconst_5
    //   10476: irem
    //   10477: tableswitch	default:+31 -> 10508, 0:+65->10542, 1:+74->10551, 2:+83->10560, 3:+92->10569
    //   10509: fstore_0
    //   10510: wide
    //   10514: wide
    //   10518: wide
    //   10522: wide
    //   10526: wide
    //   10530: ixor
    //   10531: i2c
    //   10532: castore
    //   10533: wide
    //   10539: goto -7441 -> 3098
    //   10542: bipush 30
    //   10544: wide
    //   10548: goto -34 -> 10514
    //   10551: bipush 62
    //   10553: wide
    //   10557: goto -43 -> 10514
    //   10560: bipush 54
    //   10562: wide
    //   10566: goto -52 -> 10514
    //   10569: bipush 41
    //   10571: wide
    //   10575: goto -61 -> 10514
  }

  public zb()
  {
    this.r = new char[i1];
    this.A = new String[16];
    this.B = 0;
    this.D = new int[2];
    if (Runtime.getRuntime().freeMemory() >= 1048576L)
      i1 = 8192;
    this.m = new char[i1];
    if (App.wc != 0)
      I = i2 + 1;
  }

  private final int a(boolean paramBoolean)
    throws IOException, XmlPullParserException
  {
    int i1 = 9;
    int i2 = I;
    f();
    int i3 = f();
    if (i3 == 63)
      if (((c(0) == 120) || (c(0) == 88)) && ((c(1) == 109) || (c(1) == 77)))
      {
        if (paramBoolean)
        {
          b(c(0));
          b(c(1));
        }
        f();
        f();
        if (((c(0) == 108) || (c(0) == 76)) && (c(1) <= 32))
        {
          if ((this.p != 1) || (this.q > 4))
            a(J[58]);
          c(true);
          if ((this.z < 1) || (!J[56].equals(this.A[2])))
            a(J[59]);
          this.b = this.A[3];
          if ((1 >= this.z) || (!J[61].equals(this.A[6])))
            break label763;
          this.l = this.A[7];
        }
      }
    label537: label724: label737: label751: label763: for (int i9 = 2; ; i9 = 1)
    {
      if ((i9 < this.z) && (J[62].equals(this.A[(2 + i9 * 4)])))
      {
        String str3 = this.A[(3 + i9 * 4)];
        if (J[52].equals(str3))
        {
          this.c = new Boolean(true);
          if (i2 == 0);
        }
        else if (J[54].equals(str3))
        {
          this.c = new Boolean(false);
          if (i2 == 0);
        }
        else
        {
          a(J[51] + str3);
        }
        i9++;
      }
      if (i9 != this.z)
        a(J[55]);
      this.u = true;
      this.s = 0;
      i1 = 998;
      int i4;
      String str2;
      String str1;
      int i5;
      while (true)
      {
        return i1;
        i4 = 8;
        if (i2 == 0)
          break label751;
        if (i3 == 33)
        {
          if (c(0) == 45)
          {
            str2 = J[60];
            if (i2 == 0)
              break label737;
          }
          if (c(0) == 91)
          {
            i4 = 5;
            str1 = J[50];
            i5 = 93;
            if (i2 == 0)
              break;
            paramBoolean = true;
          }
          i4 = 10;
          str1 = J[57];
          i5 = -1;
          if (i2 == 0)
            break label537;
        }
        a(J[53] + i3);
      }
      paramBoolean = true;
      while (true)
      {
        int i6 = 0;
        do
        {
          if (i6 >= str1.length())
            break;
          a(str1.charAt(i6));
          i6++;
        }
        while (i2 == 0);
        if (i4 == 10)
        {
          b(paramBoolean);
          if (i2 == 0)
            break label724;
        }
        int i8;
        for (int i7 = 0; ; i7 = i8)
        {
          i8 = f();
          if (i8 == -1)
          {
            a(J[3]);
            break;
          }
          if (paramBoolean)
            b(i8);
          if (((i5 != 63) && (i8 != i5)) || (c(0) != i5) || (c(1) != 62) || (i2 != 0))
          {
            if (i2 != 0)
              i7 = i8;
          }
          else
          {
            if ((i5 == 45) && (i7 == 45))
              a(J[49]);
            f();
            f();
            if ((paramBoolean) && (i5 != 63))
              this.s = (-1 + this.s);
            i1 = i4;
            break;
          }
        }
        i5 = 45;
        str1 = str2;
        i4 = i1;
        continue;
        str1 = "";
        i5 = 63;
      }
    }
  }

  private final String a(int paramInt)
  {
    return new String(this.r, paramInt, this.s - paramInt);
  }

  private final void a(char paramChar)
    throws IOException, XmlPullParserException
  {
    char c1 = f();
    if (c1 != paramChar)
      a(J[66] + paramChar + J[67] + (char)c1 + "'");
  }

  private final void a(int paramInt, boolean paramBoolean)
    throws IOException, XmlPullParserException
  {
    int i1 = I;
    int i2 = c(0);
    int i3 = 0;
    do
    {
      if ((i2 == -1) || (i2 == paramInt) || ((paramInt == 32) && ((i2 <= 32) || ((i2 == 62) && (i1 == 0)))))
        break;
      if (i2 == 38)
      {
        if ((!paramBoolean) && (i1 == 0))
          break;
        e();
        if (i1 == 0);
      }
      else if ((i2 == 10) && (this.t == 2))
      {
        f();
        b(32);
        if (i1 == 0);
      }
      else
      {
        b(f());
      }
      if ((i2 == 62) && (i3 >= 2) && (paramInt != 93))
        a(J[31]);
      if (i2 == 93)
      {
        i3++;
        if (i1 == 0);
      }
      else
      {
        i3 = 0;
      }
      i2 = c(0);
    }
    while (i1 == 0);
  }

  private final void a(String paramString)
    throws XmlPullParserException
  {
    if (this.e)
    {
      if (this.C == null)
      {
        this.C = (J[64] + paramString);
        if (I == 0);
      }
    }
    else
      b(paramString);
  }

  private final boolean a()
    throws XmlPullParserException
  {
    int i1 = I;
    int i2 = 0;
    boolean bool = false;
    Object localObject1;
    String str5;
    Object localObject2;
    if (i2 < this.z << 2)
    {
      localObject1 = this.A[(i2 + 2)];
      int i6 = ((String)localObject1).indexOf(':');
      if (i6 != -1)
      {
        str5 = ((String)localObject1).substring(0, i6);
        localObject1 = ((String)localObject1).substring(i6 + 1);
        if (i1 == 0)
          break label647;
      }
      if (((String)localObject1).equals(J[9]))
        localObject2 = null;
    }
    while (true)
    {
      if (!((String)localObject1).equals(J[9]))
      {
        bool = true;
        if (i1 == 0);
      }
      else
      {
        int[] arrayOfInt = this.j;
        int i7 = this.g;
        int i8 = arrayOfInt[i7];
        arrayOfInt[i7] = (i8 + 1);
        int i9 = i8 << 1;
        this.i = a(this.i, i9 + 2);
        this.i[i9] = localObject2;
        this.i[(i9 + 1)] = this.A[(i2 + 3)];
        if ((localObject2 != null) && (this.A[(i2 + 3)].equals("")))
          a(J[15]);
        String[] arrayOfString1 = this.A;
        int i10 = i2 + 4;
        String[] arrayOfString2 = this.A;
        int i11 = -1 + this.z;
        this.z = i11;
        System.arraycopy(arrayOfString1, i10, arrayOfString2, i2, (i11 << 2) - i2);
        i2 -= 4;
      }
      i2 += 4;
      if (i1 == 0)
        break;
      if (bool)
      {
        int i4 = -4 + (this.z << 2);
        do
        {
          if (i4 < 0)
            break;
          String str1 = this.A[(i4 + 2)];
          int i5 = str1.indexOf(':');
          if ((i5 == 0) && (!this.e))
            throw new RuntimeException(J[13] + str1 + J[10] + this);
          if (i5 != -1)
          {
            String str2 = str1.substring(0, i5);
            String str3 = str1.substring(i5 + 1);
            String str4 = getNamespace(str2);
            if ((str4 == null) && (!this.e))
              throw new RuntimeException(J[14] + str2 + J[12] + this);
            this.A[i4] = str4;
            this.A[(i4 + 1)] = str2;
            this.A[(i4 + 2)] = str3;
          }
          i4 -= 4;
        }
        while (i1 == 0);
      }
      int i3 = this.x.indexOf(':');
      if (i3 == 0)
        a(J[8] + this.x);
      if (i3 != -1)
      {
        this.w = this.x.substring(0, i3);
        this.x = this.x.substring(i3 + 1);
      }
      this.v = getNamespace(this.w);
      if (this.v == null)
      {
        if (this.w != null)
          a(J[11] + this.w);
        this.v = "";
      }
      return bool;
      label647: localObject2 = localObject1;
      localObject1 = str5;
    }
  }

  private final boolean a(String paramString1, boolean paramBoolean, String paramString2)
  {
    boolean bool;
    if (!paramString1.startsWith(J[32]))
      bool = false;
    while (true)
    {
      return bool;
      if (paramBoolean)
        bool = paramString1.substring(42).equals(paramString2);
      else
        bool = paramString1.substring(40).equals(paramString2);
    }
  }

  private final String[] a(String[] paramArrayOfString, int paramInt)
  {
    if (paramArrayOfString.length >= paramInt);
    while (true)
    {
      return paramArrayOfString;
      String[] arrayOfString = new String[paramInt + 16];
      System.arraycopy(paramArrayOfString, 0, arrayOfString, 0, paramArrayOfString.length);
      paramArrayOfString = arrayOfString;
    }
  }

  private final void b()
    throws IOException, XmlPullParserException
  {
    int i1 = 0;
    int i2 = I;
    if (this.k == null)
      b(J[19]);
    if (this.t == 3)
      this.g = (-1 + this.g);
    this.z = -1;
    if (this.y)
    {
      this.y = false;
      this.t = 3;
    }
    while (true)
    {
      return;
      if (this.C != null)
      {
        do
        {
          if (i1 >= this.C.length())
            break;
          b(this.C.charAt(i1));
          i1++;
        }
        while (i2 == 0);
        this.C = null;
        this.t = 9;
      }
      else if ((this.e) && ((this.B > 0) || ((c(0) == -1) && (this.g > 0))))
      {
        int i3 = -1 + this.g << 2;
        this.t = 3;
        this.v = this.h[i3];
        this.w = this.h[(i3 + 1)];
        this.x = this.h[(i3 + 2)];
        if (this.B != 1)
          this.C = (J[21] + this.x + J[20]);
        if (this.B > 0)
          this.B = (-1 + this.B);
      }
      else
      {
        this.w = null;
        this.x = null;
        this.v = null;
        this.t = d();
        switch (this.t)
        {
        case 1:
        case 5:
        default:
          this.t = a(this.H);
          if (this.t == 998)
            break;
          break;
        case 6:
          e();
          break;
        case 2:
          c(false);
          break;
        case 3:
          c();
          break;
        case 4:
          if (!this.H)
            i1 = 1;
          a(60, i1);
          if ((this.g == 0) && (this.u))
            this.t = 7;
          break;
        }
      }
    }
  }

  private final void b(int paramInt)
  {
    boolean bool1 = this.u;
    if (paramInt <= 32);
    for (boolean bool2 = true; ; bool2 = false)
    {
      this.u = (bool2 & bool1);
      if (this.s == this.r.length)
      {
        char[] arrayOfChar2 = new char[4 + 4 * this.s / 3];
        System.arraycopy(this.r, 0, arrayOfChar2, 0, this.s);
        this.r = arrayOfChar2;
      }
      char[] arrayOfChar1 = this.r;
      int i1 = this.s;
      this.s = (i1 + 1);
      arrayOfChar1[i1] = (char)paramInt;
      return;
    }
  }

  private final void b(String paramString)
    throws XmlPullParserException
  {
    if (paramString.length() < 100);
    while (true)
    {
      throw new XmlPullParserException(paramString, this, null);
      paramString = paramString.substring(0, 100) + "\n";
    }
  }

  private final void b(boolean paramBoolean)
    throws IOException, XmlPullParserException
  {
    int i1 = I;
    int i2 = 0;
    int i3 = 1;
    break label60;
    while (true)
    {
      int i4 = f();
      switch (i4)
      {
      default:
        label60: if (paramBoolean)
          b(i4);
        break;
      case -1:
      case 39:
      case 60:
      case 62:
      }
    }
    a(J[3]);
    label82: return;
    if (i2 == 0);
    for (i2 = 1; (i1 != 0) && (i2 == 0); i2 = 0)
    {
      i3++;
      if ((i1 == 0) || (i2 != 0))
        break;
      i3--;
      if (i3 != 0)
        break;
      break label82;
    }
  }

  private final int c(int paramInt)
    throws IOException
  {
    int i1 = I;
    do
    {
      if (paramInt < this.E)
        break;
      int i2;
      if (this.m.length <= 1)
      {
        i2 = this.k.read();
        if (i1 == 0);
      }
      else if (this.n < this.o)
      {
        char[] arrayOfChar = this.m;
        int i6 = this.n;
        this.n = (i6 + 1);
        i2 = arrayOfChar[i6];
        if (i1 == 0);
      }
      else
      {
        this.o = this.k.read(this.m, 0, this.m.length);
        if (this.o <= 0)
        {
          i2 = -1;
          if (i1 == 0);
        }
        else
        {
          i2 = this.m[0];
        }
        this.n = 1;
      }
      if (i2 == 13)
      {
        this.F = true;
        int[] arrayOfInt3 = this.D;
        int i5 = this.E;
        this.E = (i5 + 1);
        arrayOfInt3[i5] = 10;
        if (i1 == 0);
      }
      else
      {
        if (i2 == 10)
        {
          if (!this.F)
          {
            int[] arrayOfInt2 = this.D;
            int i4 = this.E;
            this.E = (i4 + 1);
            arrayOfInt2[i4] = 10;
            if (i1 == 0);
          }
        }
        else
        {
          int[] arrayOfInt1 = this.D;
          int i3 = this.E;
          this.E = (i3 + 1);
          arrayOfInt1[i3] = i2;
        }
        this.F = false;
      }
    }
    while (i1 == 0);
    return this.D[paramInt];
  }

  private final void c()
    throws IOException, XmlPullParserException
  {
    int i1 = I;
    f();
    f();
    this.x = g();
    h();
    a('>');
    int i2 = -1 + this.g << 2;
    if (this.g == 0)
    {
      a(J[45]);
      this.t = 9;
    }
    while (true)
    {
      return;
      if (!this.x.equals(this.h[(i2 + 3)]))
      {
        a(J[46] + this.h[(i2 + 3)] + J[47] + this.x);
        int i3 = i2;
        do
        {
          if ((i3 < 0) || (this.x.toLowerCase().equals(this.h[(i3 + 3)].toLowerCase())))
            break;
          this.B = (1 + this.B);
          i3 -= 4;
        }
        while (i1 == 0);
        if (i3 < 0)
        {
          this.B = 0;
          this.t = 9;
        }
      }
      else
      {
        this.v = this.h[i2];
        this.w = this.h[(i2 + 1)];
        this.x = this.h[(i2 + 2)];
      }
    }
  }

  private final void c(boolean paramBoolean)
    throws IOException, XmlPullParserException
  {
    int i1 = I;
    if (!paramBoolean)
      f();
    this.x = g();
    this.z = 0;
    h();
    int i2 = c(0);
    if (paramBoolean)
    {
      if (i2 != 63)
        break label107;
      f();
      a('>');
    }
    while (true)
    {
      label57: return;
      if (i2 == 47)
      {
        this.y = true;
        f();
        h();
        a('>');
        if (i1 == 0)
          break label401;
      }
      if ((i2 == 62) && (!paramBoolean))
      {
        f();
        if (i1 == 0)
          break label401;
      }
      label107: if (i2 != -1)
        break;
      a(J[3]);
    }
    String str = g();
    int i7;
    int i8;
    if (str.length() == 0)
    {
      a(J[1]);
      if (i1 == 0);
    }
    else
    {
      int i3 = this.z;
      this.z = (i3 + 1);
      int i4 = i3 << 2;
      this.A = a(this.A, i4 + 4);
      String[] arrayOfString1 = this.A;
      int i5 = i4 + 1;
      arrayOfString1[i4] = "";
      String[] arrayOfString2 = this.A;
      int i6 = i5 + 1;
      arrayOfString2[i5] = null;
      String[] arrayOfString3 = this.A;
      i7 = i6 + 1;
      arrayOfString3[i6] = str;
      h();
      if (c(0) != 61)
      {
        a(J[0] + str);
        this.A[i7] = "1";
        if (i1 == 0);
      }
      else
      {
        a('=');
        h();
        i8 = c(0);
        if ((i8 != 39) && (i8 != 34))
        {
          a(J[2]);
          if (i1 == 0)
            break label578;
          i8 = 32;
        }
        f();
      }
    }
    while (true)
    {
      int i9 = this.s;
      a(i8, true);
      this.A[i7] = a(i9);
      this.s = i9;
      if (i8 != 32)
        f();
      if (i1 == 0)
        break;
      label401: int i10 = this.g;
      this.g = (i10 + 1);
      int i11 = i10 << 2;
      this.h = a(this.h, i11 + 4);
      this.h[(i11 + 3)] = this.x;
      if (this.g >= this.j.length)
      {
        int[] arrayOfInt = new int[4 + this.g];
        System.arraycopy(this.j, 0, arrayOfInt, 0, this.j.length);
        this.j = arrayOfInt;
      }
      this.j[this.g] = this.j[(-1 + this.g)];
      if (this.d)
      {
        a();
        if (i1 == 0);
      }
      else
      {
        this.v = "";
      }
      this.h[i11] = this.v;
      this.h[(i11 + 1)] = this.w;
      this.h[(i11 + 2)] = this.x;
      break label57;
      label578: i8 = 32;
    }
  }

  private final int d()
    throws IOException
  {
    int i1 = 1;
    switch (c(0))
    {
    default:
      i1 = 4;
    case -1:
    case 38:
    case 60:
    }
    while (true)
    {
      return i1;
      i1 = 6;
      continue;
      switch (c(i1))
      {
      default:
        i1 = 2;
        break;
      case 47:
        i1 = 3;
        break;
      case 33:
      case 63:
        i1 = 999;
      }
    }
  }

  private final void e()
    throws IOException, XmlPullParserException
  {
    int i1 = 1;
    int i2 = 0;
    int i3 = I;
    b(f());
    int i4 = this.s;
    label140: 
    do
    {
      int i5 = f();
      if ((i5 == 59) && (i3 == 0))
        break;
      if ((i5 < 128) && ((i5 < 48) || (i5 > 57)) && ((i5 < 97) || (i5 > 122)) && ((i5 < 65) || (i5 > 90)) && (i5 != 95) && (i5 != 45) && (i5 != 35))
      {
        if (!this.e)
          a(J[23]);
        if (i5 != -1)
          b(i5);
        return;
        break label323;
      }
      b(i5);
    }
    while (i3 == 0);
    String str1 = a(i4);
    this.s = (i4 - 1);
    if ((this.H) && (this.t == 6))
      this.x = str1;
    if (str1.charAt(0) == '#')
    {
      if (str1.charAt(i1) == 'x');
      for (int i6 = Integer.parseInt(str1.substring(2), 16); ; i6 = Integer.parseInt(str1.substring(i1)))
      {
        b(i6);
        break;
      }
    }
    String str2 = (String)this.f.get(str1);
    if (str2 == null);
    while (true)
    {
      this.G = i1;
      if (this.G)
      {
        if (this.H)
          break label140;
        a(J[22] + str1 + ";");
        if (i3 == 0)
          break label140;
      }
      label323: if (i2 >= str2.length())
        break label140;
      b(str2.charAt(i2));
      i2++;
      if (i3 == 0)
        break;
      break label140;
      i1 = 0;
    }
  }

  private final int f()
    throws IOException
  {
    int i1;
    if (this.E == 0)
    {
      i1 = c(0);
      if (I == 0);
    }
    else
    {
      i1 = this.D[0];
      this.D[0] = this.D[1];
    }
    this.E = (-1 + this.E);
    this.q = (1 + this.q);
    if (i1 == 10)
    {
      this.p = (1 + this.p);
      this.q = 1;
    }
    return i1;
  }

  private final String g()
    throws IOException, XmlPullParserException
  {
    int i1 = this.s;
    int i2 = c(0);
    if (((i2 < 97) || (i2 > 122)) && ((i2 < 65) || (i2 > 90)) && (i2 != 95) && (i2 != 58) && (i2 < 192) && (!this.e))
      a(J[63]);
    int i3;
    do
    {
      b(f());
      i3 = c(0);
    }
    while (((i3 >= 97) && (i3 <= 122)) || ((i3 >= 65) && (i3 <= 90)) || ((i3 >= 48) && (i3 <= 57)) || (i3 == 95) || (i3 == 45) || (i3 == 58) || (i3 == 46) || (i3 >= 183));
    String str = a(i1);
    this.s = i1;
    return str;
  }

  private final void h()
    throws IOException
  {
    int i1 = I;
    do
    {
      int i2 = c(0);
      if ((i2 > 32) || ((i2 == -1) && (i1 == 0)))
        break;
      f();
    }
    while (i1 == 0);
  }

  public void defineEntityReplacementText(String paramString1, String paramString2)
    throws XmlPullParserException
  {
    if (this.f == null)
      throw new RuntimeException(J[4]);
    this.f.put(paramString1, paramString2);
  }

  public int getAttributeCount()
  {
    return this.z;
  }

  public String getAttributeName(int paramInt)
  {
    if (paramInt >= this.z)
      throw new IndexOutOfBoundsException();
    return this.A[(2 + (paramInt << 2))];
  }

  public String getAttributeNamespace(int paramInt)
  {
    if (paramInt >= this.z)
      throw new IndexOutOfBoundsException();
    return this.A[(paramInt << 2)];
  }

  public String getAttributePrefix(int paramInt)
  {
    if (paramInt >= this.z)
      throw new IndexOutOfBoundsException();
    return this.A[(1 + (paramInt << 2))];
  }

  public String getAttributeType(int paramInt)
  {
    return J[48];
  }

  public String getAttributeValue(int paramInt)
  {
    if (paramInt >= this.z)
      throw new IndexOutOfBoundsException();
    return this.A[(3 + (paramInt << 2))];
  }

  public String getAttributeValue(String paramString1, String paramString2)
  {
    int i1 = I;
    int i2 = -4 + (this.z << 2);
    if (i2 >= 0)
      if ((!this.A[(i2 + 2)].equals(paramString2)) || ((paramString1 != null) && (!this.A[i2].equals(paramString1))));
    for (String str = this.A[(i2 + 3)]; ; str = null)
    {
      return str;
      i2 -= 4;
      if (i1 == 0)
        break;
    }
  }

  public int getColumnNumber()
  {
    return this.q;
  }

  public int getDepth()
  {
    return this.g;
  }

  public int getEventType()
    throws XmlPullParserException
  {
    return this.t;
  }

  public boolean getFeature(String paramString)
  {
    boolean bool = false;
    if (J[6].equals(paramString))
      bool = this.d;
    while (true)
    {
      return bool;
      if (a(paramString, false, J[5]))
        bool = this.e;
    }
  }

  public String getInputEncoding()
  {
    return this.l;
  }

  public int getLineNumber()
  {
    return this.p;
  }

  public String getName()
  {
    return this.x;
  }

  public String getNamespace()
  {
    return this.v;
  }

  public String getNamespace(String paramString)
  {
    int i1 = I;
    String str;
    if (J[25].equals(paramString))
      str = J[26];
    while (true)
    {
      return str;
      if (J[9].equals(paramString))
      {
        str = J[24];
      }
      else
      {
        int i2 = -2 + (getNamespaceCount(this.g) << 1);
        label122: 
        do
        {
          if (i2 < 0)
            break label129;
          if (paramString == null)
          {
            if (this.i[i2] != null)
              break label122;
            str = this.i[(i2 + 1)];
            break;
          }
          if (paramString.equals(this.i[i2]))
          {
            str = this.i[(i2 + 1)];
            break;
          }
          i2 -= 2;
        }
        while (i1 == 0);
        label129: str = null;
      }
    }
  }

  public int getNamespaceCount(int paramInt)
  {
    if (paramInt > this.g)
      throw new IndexOutOfBoundsException();
    return this.j[paramInt];
  }

  public String getNamespacePrefix(int paramInt)
  {
    return this.i[(paramInt << 1)];
  }

  public String getNamespaceUri(int paramInt)
  {
    return this.i[(1 + (paramInt << 1))];
  }

  public String getPositionDescription()
  {
    int i1 = I;
    String str1;
    StringBuffer localStringBuffer;
    if (this.t < TYPES.length)
    {
      str1 = TYPES[this.t];
      localStringBuffer = new StringBuffer(str1);
      localStringBuffer.append(' ');
      if ((this.t == 2) || (this.t == 3))
      {
        if (this.y)
          localStringBuffer.append(J[39]);
        localStringBuffer.append('<');
        if (this.t == 3)
          localStringBuffer.append('/');
        if (this.w != null)
          localStringBuffer.append("{" + this.v + "}" + this.w + ":");
        localStringBuffer.append(this.x);
        int i2 = this.z << 2;
        int i3 = 0;
        while (i3 < i2)
        {
          localStringBuffer.append(' ');
          if (this.A[(i3 + 1)] != null)
            localStringBuffer.append("{" + this.A[i3] + "}" + this.A[(i3 + 1)] + ":");
          localStringBuffer.append(this.A[(i3 + 2)] + J[41] + this.A[(i3 + 3)] + "'");
          i3 += 4;
          if (i1 != 0)
            App.wc = 1 + App.wc;
        }
        localStringBuffer.append('>');
        if (i1 == 0);
      }
      else
      {
        if (this.t != 7)
          break label457;
      }
    }
    while (true)
    {
      localStringBuffer.append("@" + this.p + ":" + this.q);
      if (this.a != null)
      {
        localStringBuffer.append(J[12]);
        localStringBuffer.append(this.a);
        if (i1 == 0);
      }
      else if (this.k != null)
      {
        localStringBuffer.append(J[12]);
        localStringBuffer.append(this.k.toString());
      }
      return localStringBuffer.toString();
      str1 = J[42];
      break;
      label457: if (this.t != 4)
      {
        localStringBuffer.append(getText());
        if (i1 == 0);
      }
      else if (this.u)
      {
        localStringBuffer.append(J[40]);
        if (i1 == 0);
      }
      else
      {
        String str2 = getText();
        if (str2.length() > 16)
          str2 = str2.substring(0, 16) + J[38];
        localStringBuffer.append(str2);
      }
    }
  }

  public String getPrefix()
  {
    return this.w;
  }

  public Object getProperty(String paramString)
  {
    Object localObject;
    if (a(paramString, true, J[27]))
      localObject = this.b;
    while (true)
    {
      return localObject;
      if (a(paramString, true, J[28]))
        localObject = this.c;
      else if (a(paramString, true, J[16]))
      {
        if (this.a != null)
          localObject = this.a;
        else
          localObject = this.k.toString();
      }
      else
        localObject = null;
    }
  }

  public String getText()
  {
    if ((this.t < 4) || ((this.t == 6) && (this.G)));
    for (String str = null; ; str = a(0))
      return str;
  }

  public char[] getTextCharacters(int[] paramArrayOfInt)
  {
    char[] arrayOfChar;
    if (this.t >= 4)
      if (this.t == 6)
      {
        paramArrayOfInt[0] = 0;
        paramArrayOfInt[1] = this.x.length();
        arrayOfChar = this.x.toCharArray();
      }
    while (true)
    {
      return arrayOfChar;
      paramArrayOfInt[0] = 0;
      paramArrayOfInt[1] = this.s;
      arrayOfChar = this.r;
      continue;
      paramArrayOfInt[0] = -1;
      paramArrayOfInt[1] = -1;
      arrayOfChar = null;
    }
  }

  public boolean isAttributeDefault(int paramInt)
  {
    return false;
  }

  public boolean isEmptyElementTag()
    throws XmlPullParserException
  {
    if (this.t != 2)
      b(J[18]);
    return this.y;
  }

  public boolean isWhitespace()
    throws XmlPullParserException
  {
    if ((this.t != 4) && (this.t != 7) && (this.t != 5))
      b(J[18]);
    return this.u;
  }

  public int next()
    throws XmlPullParserException, IOException
  {
    this.s = 0;
    this.u = true;
    int i1 = 9999;
    this.H = false;
    do
    {
      b();
      if (this.t < i1)
        i1 = this.t;
    }
    while ((i1 > 6) || ((i1 >= 4) && (d() >= 4)));
    this.t = i1;
    if (this.t > 4)
      this.t = 4;
    return this.t;
  }

  public int nextTag()
    throws XmlPullParserException, IOException
  {
    next();
    if ((this.t == 4) && (this.u))
      next();
    if ((this.t != 3) && (this.t != 2))
      b(J[65]);
    return this.t;
  }

  public String nextText()
    throws XmlPullParserException, IOException
  {
    if (this.t != 2)
      b(J[44]);
    next();
    String str;
    if (this.t == 4)
    {
      str = getText();
      next();
      if (I == 0);
    }
    else
    {
      str = "";
    }
    if (this.t != 3)
      b(J[43]);
    return str;
  }

  public int nextToken()
    throws XmlPullParserException, IOException
  {
    this.u = true;
    this.s = 0;
    this.H = true;
    b();
    return this.t;
  }

  public void require(int paramInt, String paramString1, String paramString2)
    throws XmlPullParserException, IOException
  {
    if ((paramInt != this.t) || ((paramString1 != null) && (!paramString1.equals(getNamespace()))) || ((paramString2 != null) && (!paramString2.equals(getName()))))
      b(J[30] + TYPES[paramInt] + J[29] + paramString1 + "}" + paramString2);
  }

  public void setFeature(String paramString, boolean paramBoolean)
    throws XmlPullParserException
  {
    int i1 = I;
    if (J[6].equals(paramString))
    {
      this.d = paramBoolean;
      if (i1 == 0);
    }
    else if (a(paramString, false, J[5]))
    {
      this.e = paramBoolean;
      if (i1 == 0);
    }
    else
    {
      b(J[7] + paramString);
    }
  }

  public void setInput(InputStream paramInputStream, String paramString)
    throws XmlPullParserException
  {
    int i1 = 0;
    int i2 = I;
    this.n = 0;
    this.o = 0;
    if (paramInputStream == null)
      throw new IllegalArgumentException();
    if (paramString == null);
    while (true)
    {
      try
      {
        if (this.o < 4)
        {
          int i10 = paramInputStream.read();
          if ((i10 != -1) || (i2 != 0))
          {
            i1 = i10 | i1 << 8;
            char[] arrayOfChar2 = this.m;
            int i11 = this.o;
            this.o = (i11 + 1);
            arrayOfChar2[i11] = (char)i10;
            if (i2 == 0)
              continue;
          }
        }
        int i4 = i1;
        if (this.o != 4)
          break label743;
        switch (i4)
        {
        case 65279:
          if ((0xFFFF0000 & i4) == -16842752)
          {
            localObject = J[72];
            this.m[0] = (char)(this.m[2] << '\b' | this.m[3]);
            this.o = 1;
            if (i2 == 0)
              break;
          }
          else if ((0xFFFF0000 & i4) == -131072)
          {
            localObject = J[71];
            this.m[0] = (char)(this.m[3] << '\b' | this.m[2]);
            this.o = 1;
            if (i2 == 0)
              break;
          }
          else if ((i4 & 0xFFFFFF00) == -272908544)
          {
            localObject = J[68];
            this.m[0] = this.m[3];
            this.o = 1;
          }
          if (localObject == null)
            localObject = J[68];
          int i3 = this.o;
          setInput(new InputStreamReader(paramInputStream, (String)localObject));
          this.l = paramString;
          this.o = i3;
          return;
          localObject = J[70];
          this.o = 0;
          if (i2 == 0)
            continue;
        case -131072:
          localObject = J[73];
          this.o = 0;
          if (i2 == 0)
            continue;
        case 60:
          localObject = J[70];
          this.m[0] = '<';
          this.o = 1;
          if (i2 == 0)
            continue;
        case 1006632960:
          localObject = J[73];
          this.m[0] = '<';
          this.o = 1;
          if (i2 == 0)
            continue;
        case 3932223:
          localObject = J[72];
          this.m[0] = '<';
          this.m[1] = '?';
          this.o = 2;
          if (i2 == 0)
            continue;
        case 1006649088:
          localObject = J[71];
          this.m[0] = '<';
          this.m[1] = '?';
          this.o = 2;
          if (i2 == 0)
            continue;
          int i5 = paramInputStream.read();
          if ((i5 == -1) && (i2 == 0))
            continue;
          char[] arrayOfChar1 = this.m;
          int i6 = this.o;
          this.o = (i6 + 1);
          arrayOfChar1[i6] = (char)i5;
          if (i5 == 62)
          {
            String str1 = new String(this.m, 0, this.o);
            int i7 = str1.indexOf(J[61]);
            if (i7 == -1)
              continue;
            int i8 = i7;
            if ((str1.charAt(i8) != '"') && (str1.charAt(i8) != '\''))
            {
              i8++;
              if (i2 == 0)
                continue;
            }
            int i9 = i8 + 1;
            String str2 = str1.substring(i9, str1.indexOf(str1.charAt(i8), i9));
            localObject = str2;
            if (i2 == 0)
              continue;
          }
          if (i2 == 0)
            continue;
          continue;
        case 1010792557:
        }
      }
      catch (Exception localException)
      {
        throw new XmlPullParserException(J[69] + localException.toString(), this, localException);
      }
      Object localObject = paramString;
      continue;
      label743: localObject = paramString;
      continue;
      localObject = paramString;
    }
  }

  public void setInput(Reader paramReader)
    throws XmlPullParserException
  {
    this.k = paramReader;
    this.p = 1;
    this.q = 0;
    this.t = 0;
    this.x = null;
    this.v = null;
    this.y = false;
    this.z = -1;
    this.l = null;
    this.b = null;
    this.c = null;
    if (paramReader == null);
    while (true)
    {
      return;
      this.n = 0;
      this.o = 0;
      this.E = 0;
      this.g = 0;
      this.f = new Hashtable();
      this.f.put(J[35], "&");
      this.f.put(J[34], "'");
      this.f.put(J[37], ">");
      this.f.put(J[33], "<");
      this.f.put(J[36], "\"");
    }
  }

  public void setProperty(String paramString, Object paramObject)
    throws XmlPullParserException
  {
    if (a(paramString, true, J[16]))
    {
      this.a = paramObject;
      if (I == 0);
    }
    else
    {
      throw new XmlPullParserException(J[17] + paramString);
    }
  }
}