// #######################################################
// Decompiled by   : coddec 
// Module          : WhatsApp-5.cod
// Module version  : 2.8.1914
// Class ID        : 7
// ########################################################


package com.whatsapp.client;


abstract final class AuthSelfSMSScreen$SelfSMSImpl$2 extends Object
implements Runnable

{

	// @@@@@@@@@@@@@ Fields 
	private final String /*java.lang.String*/  field_59814 ; // ofs = 59814 addr = 0)
	private final com.whatsapp.client.AuthSelfSMSScreen$SelfSMSImpl /*com.whatsapp.client.AuthSelfSMSScreen$SelfSMSImpl*/  field_59818 ; // ofs = 59818 addr = 0)

	// @@@@@@@@@@@@@ Static routines 

<init>( com.whatsapp.client.AuthSelfSMSScreen$SelfSMSImpl$2, com.whatsapp.client.AuthSelfSMSScreen$SelfSMSImpl, java.lang.String ); // address: 0
	{
	enter_narrow 
	aload_0 
	invokespecial_lib java.lang.Object.<init> // pc=1
	aload_0 
	aload_1 
	putfield .field_1_1   // get_name_1:  .field_1_1   // get_name_2:  .field_1_1   // get_Name:    .field_1_1   // getName->1:  null   // getName->2:  null   // getName->N:  null   // ofs = -1 ord = 0 addr = 1
	aload_0 
	aload_2 
	putfield .field_0_   // get_name_1:  .field_0_   // get_name_2:  .field_0_   // get_Name:    .field_0_   // getName->1:  null   // getName->2:  null   // getName->N:  null   // ofs = -1 ord = 0 addr = 0
	return 
	}

	// @@@@@@@@@@@@@ Virtual routines 

public final run( com.whatsapp.client.AuthSelfSMSScreen$SelfSMSImpl$2 ); // address: 0
	{
	enter 
	new_lib StringBuffer//java.lang.StringBuffer java.lang.StringBuffer java.lang.StringBuffer
	dup 
	invokespecial_lib java.lang.StringBuffer.<init> // pc=1
	astore_1 
	iconst_0 
	istore_2 
Label7:
	aload_0_getfield .field_0_   // get_name_1:  .field_0_   // get_name_2:  .field_0_   // get_Name:    .field_0_   // getName->1:  null   // getName->2:  null   // getName->N:  null   // ofs = -1 ord = 0 addr = 0
	stringlength 
	iload_2 
	if_icmple Label18
	aload_0_getfield .field_0_   // get_name_1:  .field_0_   // get_name_2:  .field_0_   // get_Name:    .field_0_   // getName->1:  null   // getName->2:  null   // getName->N:  null   // ofs = -1 ord = 0 addr = 0
	iload_2 
	stringaload 
	invokestatic_lib boolean isDigit( char ) // Character
	ifeq Label18
	iinc 2 1
	goto Label7
Label18:
	aload_0_getfield .field_0_   // get_name_1:  .field_0_   // get_name_2:  .field_0_   // get_Name:    .field_0_   // getName->1:  null   // getName->2:  null   // getName->N:  null   // ofs = -1 ord = 0 addr = 0
	iconst_0 
	iload_2 
	invokenonvirtual_lib java.lang.String.substring // pc=3
	astore_3 
	aload_3 
	stringlength 
	ifne Label34
	aload_0_getfield .field_0_   // get_name_1:  .field_0_   // get_name_2:  .field_0_   // get_Name:    .field_0_   // getName->1:  null   // getName->2:  null   // getName->N:  null   // ofs = -1 ord = 0 addr = 0
	iconst_0 
	aload_0_getfield .field_0_   // get_name_1:  .field_0_   // get_name_2:  .field_0_   // get_Name:    .field_0_   // getName->1:  null   // getName->2:  null   // getName->N:  null   // ofs = -1 ord = 0 addr = 0
	stringlength 
	bipush 10
	invokestatic_lib int min( int, int ) // Math
	invokenonvirtual_lib java.lang.String.substring // pc=3
	astore_3 
Label34:
	aload_3 
	invokestatic_lib module:WhatsApp-79.class#39.routine_23917(  ) // class#39
	invokestatic_lib module:WhatsApp-45.class#0.routine_2835(  ) // class#0
	astore_4 
	ldc literal_237:"mismatch"
	aload_4 
	invokevirtual_short .equals // idx=1 pc=2
	ifeq Label78
	aconst_null 
	astore_5 
	aload_0_getfield .field_0_   // get_name_1:  .field_0_   // get_name_2:  .field_0_   // get_Name:    .field_0_   // getName->1:  null   // getName->2:  null   // getName->N:  null   // ofs = -1 ord = 0 addr = 0
	astore_5 
	new_lib StringBuffer//java.lang.StringBuffer java.lang.StringBuffer java.lang.StringBuffer
	dup 
	ldc literal_238:"couldnt match code in "
	invokespecial_lib java.lang.StringBuffer.<init> // pc=2
	aload_5 
	invokevirtual java.lang.StringBuffer append( java.lang.StringBuffer, java.lang.String ) // pc=2
	invokevirtual_short .toString // idx=2 pc=1
	invokestatic_lib module:WhatsApp-79.class#39.routine_24694(  ) // class#39
	aload_0_getfield .field_1_1   // get_name_1:  .field_1_1   // get_name_2:  .field_1_1   // get_Name:    .field_1_1   // getName->1:  null   // getName->2:  null   // getName->N:  null   // ofs = -1 ord = 0 addr = 1
	getfield .field_1_1   // get_name_1:  .field_1_1   // get_name_2:  .field_1_1   // get_Name:    .field_1_1   // getName->1:  null   // getName->2:  null   // getName->N:  null   // ofs = -1 ord = 0 addr = 1
	new_lib StringBuffer//java.lang.StringBuffer java.lang.StringBuffer java.lang.StringBuffer
	dup 
	ldc literal_238:"couldnt match code in "
	invokespecial_lib java.lang.StringBuffer.<init> // pc=2
	aload_5 
	invokevirtual java.lang.StringBuffer append( java.lang.StringBuffer, java.lang.String ) // pc=2
	ldc literal_215:"?"
	invokevirtual java.lang.StringBuffer append( java.lang.StringBuffer, java.lang.String ) // pc=2
	invokevirtual_short .toString // idx=2 pc=1
	invokevirtual java.lang.StringBuffer append( java.lang.StringBuffer, java.lang.String ) // pc=2
	pop 
	aload_0_getfield .field_1_1   // get_name_1:  .field_1_1   // get_name_2:  .field_1_1   // get_Name:    .field_1_1   // getName->1:  null   // getName->2:  null   // getName->N:  null   // ofs = -1 ord = 0 addr = 1
	getfield .field_0_   // get_name_1:  .field_0_   // get_name_2:  .field_0_   // get_Name:    .field_0_   // getName->1:  null   // getName->2:  null   // getName->N:  null   // ofs = -1 ord = 0 addr = 0
	ifnull Label115
	aload_0_getfield .field_1_1   // get_name_1:  .field_1_1   // get_name_2:  .field_1_1   // get_Name:    .field_1_1   // getName->1:  null   // getName->2:  null   // getName->N:  null   // ofs = -1 ord = 0 addr = 1
	getfield .field_0_   // get_name_1:  .field_0_   // get_name_2:  .field_0_   // get_Name:    .field_0_   // getName->1:  null   // getName->2:  null   // getName->N:  null   // ofs = -1 ord = 0 addr = 0
	sipush 670
	getstatic_lib module:WhatsApp-19.class#0.static_133 // class#0
	aload_5 
	invokestatic_lib module:WhatsApp-47.class#11.routine_4492(  ) // class#11
	invokeinterface interfacemethodref_15 // pc=2 guess=15
	goto Label115
Label78:
	ldc literal_239:"ok"
	aload_4 
	invokevirtual_short .equals // idx=1 pc=2
	ifeq Label106
	new_lib StringBuffer//java.lang.StringBuffer java.lang.StringBuffer java.lang.StringBuffer
	dup 
	ldc literal_240:"match completed for "
	invokespecial_lib java.lang.StringBuffer.<init> // pc=2
	aload_3 
	invokevirtual java.lang.StringBuffer append( java.lang.StringBuffer, java.lang.String ) // pc=2
	invokevirtual_short .toString // idx=2 pc=1
	invokestatic_lib module:WhatsApp-79.class#39.routine_24694(  ) // class#39
	aload_0_getfield .field_1_1   // get_name_1:  .field_1_1   // get_name_2:  .field_1_1   // get_Name:    .field_1_1   // getName->1:  null   // getName->2:  null   // getName->N:  null   // ofs = -1 ord = 0 addr = 1
	getfield .field_1_1   // get_name_1:  .field_1_1   // get_name_2:  .field_1_1   // get_Name:    .field_1_1   // getName->1:  null   // getName->2:  null   // getName->N:  null   // ofs = -1 ord = 0 addr = 1
	new_lib StringBuffer//java.lang.StringBuffer java.lang.StringBuffer java.lang.StringBuffer
	dup 
	ldc literal_240:"match completed for "
	invokespecial_lib java.lang.StringBuffer.<init> // pc=2
	aload_3 
	invokevirtual java.lang.StringBuffer append( java.lang.StringBuffer, java.lang.String ) // pc=2
	ldc literal_215:"?"
	invokevirtual java.lang.StringBuffer append( java.lang.StringBuffer, java.lang.String ) // pc=2
	invokevirtual_short .toString // idx=2 pc=1
	invokevirtual java.lang.StringBuffer append( java.lang.StringBuffer, java.lang.String ) // pc=2
	pop 
	aload_0_getfield .field_1_1   // get_name_1:  .field_1_1   // get_name_2:  .field_1_1   // get_Name:    .field_1_1   // getName->1:  null   // getName->2:  null   // getName->N:  null   // ofs = -1 ord = 0 addr = 1
	invokevirtual_short .virtual_6 // idx=6 pc=1
	goto Label115
Label106:
	aload_0_getfield .field_1_1   // get_name_1:  .field_1_1   // get_name_2:  .field_1_1   // get_Name:    .field_1_1   // getName->1:  null   // getName->2:  null   // getName->N:  null   // ofs = -1 ord = 0 addr = 1
	getfield .field_0_   // get_name_1:  .field_0_   // get_name_2:  .field_0_   // get_Name:    .field_0_   // getName->1:  null   // getName->2:  null   // getName->N:  null   // ofs = -1 ord = 0 addr = 0
	ifnull Label115
	aload_0_getfield .field_1_1   // get_name_1:  .field_1_1   // get_name_2:  .field_1_1   // get_Name:    .field_1_1   // getName->1:  null   // getName->2:  null   // getName->N:  null   // ofs = -1 ord = 0 addr = 1
	getfield .field_0_   // get_name_1:  .field_0_   // get_name_2:  .field_0_   // get_Name:    .field_0_   // getName->1:  null   // getName->2:  null   // getName->N:  null   // ofs = -1 ord = 0 addr = 0
	sipush 862
	aload_4 
	invokestatic_lib module:WhatsApp-47.class#11.routine_4463(  ) // class#11
	invokeinterface interfacemethodref_15 // pc=2 guess=15
Label115:
	aload_0_getfield .field_1_1   // get_name_1:  .field_1_1   // get_name_2:  .field_1_1   // get_Name:    .field_1_1   // getName->1:  null   // getName->2:  null   // getName->N:  null   // ofs = -1 ord = 0 addr = 1
	getfield .field_0_   // get_name_1:  .field_0_   // get_name_2:  .field_0_   // get_Name:    .field_0_   // getName->1:  null   // getName->2:  null   // getName->N:  null   // ofs = -1 ord = 0 addr = 0
	ifnull Label122
	aload_0_getfield .field_1_1   // get_name_1:  .field_1_1   // get_name_2:  .field_1_1   // get_Name:    .field_1_1   // getName->1:  null   // getName->2:  null   // getName->N:  null   // ofs = -1 ord = 0 addr = 1
	getfield .field_0_   // get_name_1:  .field_0_   // get_name_2:  .field_0_   // get_Name:    .field_0_   // getName->1:  null   // getName->2:  null   // getName->N:  null   // ofs = -1 ord = 0 addr = 0
	aload_4 
	invokeinterface interfacemethodref_28 // pc=2 guess=16
Label122:
	return 
	}

}
