// #######################################################
// Decompiled by   : coddec 
// Module          : WhatsApp-6.cod
// Module version  : 2.8.1914
// Class ID        : 0
// ########################################################


package com.whatsapp.client;


abstract final class AuthSelfSMSScreen$SelfSMSImpl$SendThread extends Thread

{

	// @@@@@@@@@@@@@ Fields 
	private String /*java.lang.String*/  field_58970 ; // ofs = 58970 addr = 0)
	private final com.whatsapp.client. /*module:WhatsApp-5.class#4*/  field_58974 ; // ofs = 58974 addr = 0)

	// @@@@@@@@@@@@@ Static routines 

public <init>( com.whatsapp.client.AuthSelfSMSScreen$SelfSMSImpl$SendThread, module:WhatsApp-5.class#4, java.lang.String ); // address: 0
	{
	enter_narrow 
	aload_0 
	invokespecial_lib java.lang.Thread.<init> // pc=1
	aload_0 
	aload_1 
	putfield com.whatsapp.client.AuthSelfSMSScreen$SelfSMSImpl$SendThread.field_58974   // get_name_1:  com.whatsapp.client.AuthSelfSMSScreen$SelfSMSImpl$SendThread.field_58974   // get_name_2:  com.whatsapp.client.AuthSelfSMSScreen$SelfSMSImpl$SendThread.field_58974   // get_Name:    com.whatsapp.client.AuthSelfSMSScreen$SelfSMSImpl$SendThread.field_58974   // getName->1:     // getName->2:     // getName->N:     // ofs = 58974 ord = 1 addr = 0
	aload_0 
	aload_2 
	putfield com.whatsapp.client.AuthSelfSMSScreen$SelfSMSImpl$SendThread.field_58970   // get_name_1:  com.whatsapp.client.AuthSelfSMSScreen$SelfSMSImpl$SendThread.field_58970   // get_name_2:  com.whatsapp.client.AuthSelfSMSScreen$SelfSMSImpl$SendThread.field_58970   // get_Name:    com.whatsapp.client.AuthSelfSMSScreen$SelfSMSImpl$SendThread.field_58970   // getName->1:     // getName->2:     // getName->N:     // ofs = 58970 ord = 0 addr = 0
	return 
	}

	// @@@@@@@@@@@@@ Non-virtual routines 

private final com.whatsapp.client.AuthSelfSMSScreen$SelfSMSImpl$SendThread.routine_338( com.whatsapp.client.AuthSelfSMSScreen$SelfSMSImpl$SendThread, java.lang.String ); // address: 0
	{
	enter_narrow 
	aload_0_getfield com.whatsapp.client.AuthSelfSMSScreen$SelfSMSImpl$SendThread.field_58974   // get_name_1:  com.whatsapp.client.AuthSelfSMSScreen$SelfSMSImpl$SendThread.field_58974   // get_name_2:  com.whatsapp.client.AuthSelfSMSScreen$SelfSMSImpl$SendThread.field_58974   // get_Name:    com.whatsapp.client.AuthSelfSMSScreen$SelfSMSImpl$SendThread.field_58974   // getName->1:     // getName->2:     // getName->N:     // ofs = 58974 ord = 1 addr = 0
	getfield .field_5_5   // get_name_1:  .field_5_5   // get_name_2:  .field_5_5   // get_Name:    .field_5_5   // getName->1:  null   // getName->2:  null   // getName->N:  null   // ofs = -1 ord = 0 addr = 5
	ldc literal_97:"text"
	aload_1 
	invokeinterface interfacemethodref_3 // pc=3 guess=1
	checkcast_lib javax.wireless.messaging.Message//javax.wireless.messaging.Message javax.wireless.messaging.Message javax.wireless.messaging.Message
	astore_2 
	aload_2 
	aload_0_getfield com.whatsapp.client.AuthSelfSMSScreen$SelfSMSImpl$SendThread.field_58970   // get_name_1:  com.whatsapp.client.AuthSelfSMSScreen$SelfSMSImpl$SendThread.field_58970   // get_name_2:  com.whatsapp.client.AuthSelfSMSScreen$SelfSMSImpl$SendThread.field_58970   // get_Name:    com.whatsapp.client.AuthSelfSMSScreen$SelfSMSImpl$SendThread.field_58970   // getName->1:     // getName->2:     // getName->N:     // ofs = 58970 ord = 0 addr = 0
	invokeinterface interfacemethodref_4 // pc=2 guess=2
	aload_0_getfield com.whatsapp.client.AuthSelfSMSScreen$SelfSMSImpl$SendThread.field_58974   // get_name_1:  com.whatsapp.client.AuthSelfSMSScreen$SelfSMSImpl$SendThread.field_58974   // get_name_2:  com.whatsapp.client.AuthSelfSMSScreen$SelfSMSImpl$SendThread.field_58974   // get_Name:    com.whatsapp.client.AuthSelfSMSScreen$SelfSMSImpl$SendThread.field_58974   // getName->1:     // getName->2:     // getName->N:     // ofs = 58974 ord = 1 addr = 0
	getfield .field_5_5   // get_name_1:  .field_5_5   // get_name_2:  .field_5_5   // get_Name:    .field_5_5   // getName->1:  null   // getName->2:  null   // getName->N:  null   // ofs = -1 ord = 0 addr = 5
	aload_2 
	invokeinterface interfacemethodref_5 // pc=2 guess=3
	return 
	}


private final com.whatsapp.client.AuthSelfSMSScreen$SelfSMSImpl$SendThread.routine_392( com.whatsapp.client.AuthSelfSMSScreen$SelfSMSImpl$SendThread, boolean ); // address: 0
	{
	enter 
	new_lib Thread//java.lang.Thread java.lang.Thread java.lang.Thread
	dup 
	invokespecial_lib java.lang.StringBuffer.<init> // pc=1
	getstatic_lib module:WhatsApp-19.class#0.static_124 // class#0
	invokevirtual java.lang.StringBuffer append( java.lang.StringBuffer, java.lang.String ) // pc=2
	aload_0_getfield com.whatsapp.client.AuthSelfSMSScreen$SelfSMSImpl$SendThread.field_58974   // get_name_1:  com.whatsapp.client.AuthSelfSMSScreen$SelfSMSImpl$SendThread.field_58974   // get_name_2:  com.whatsapp.client.AuthSelfSMSScreen$SelfSMSImpl$SendThread.field_58974   // get_Name:    com.whatsapp.client.AuthSelfSMSScreen$SelfSMSImpl$SendThread.field_58974   // getName->1:     // getName->2:     // getName->N:     // ofs = 58974 ord = 1 addr = 0
	invokevirtual_short .virtual_10 // idx=10 pc=1
	invokevirtual java.lang.StringBuffer append( java.lang.StringBuffer, java.lang.String ) // pc=2
	iload_1 
	ifeq Label13
	ldc_nullstr 
	goto Label21
Label13:
	new_lib Thread//java.lang.Thread java.lang.Thread java.lang.Thread
	dup 
	ldc literal_85:":"
	invokespecial_lib java.lang.StringBuffer.<init> // pc=2
	aload_0_getfield com.whatsapp.client.AuthSelfSMSScreen$SelfSMSImpl$SendThread.field_58974   // get_name_1:  com.whatsapp.client.AuthSelfSMSScreen$SelfSMSImpl$SendThread.field_58974   // get_name_2:  com.whatsapp.client.AuthSelfSMSScreen$SelfSMSImpl$SendThread.field_58974   // get_Name:    com.whatsapp.client.AuthSelfSMSScreen$SelfSMSImpl$SendThread.field_58974   // getName->1:     // getName->2:     // getName->N:     // ofs = 58974 ord = 1 addr = 0
	invokevirtual_short .virtual_3 // idx=3 pc=1
	invokevirtual java.lang.StringBuffer append( java.lang.StringBuffer, int ) // pc=2
	invokevirtual_short .toString // idx=2 pc=1
Label21:
	invokevirtual java.lang.StringBuffer append( java.lang.StringBuffer, java.lang.String ) // pc=2
	invokevirtual_short .toString // idx=2 pc=1
	astore_2 
	aload_2 
	invokestatic_lib javax.microedition.io.Connection open( java.lang.String ) // Connector
	checkcast_lib javax.wireless.messaging.TextMessage//javax.wireless.messaging.TextMessage javax.wireless.messaging.TextMessage javax.wireless.messaging.TextMessage
	astore_3 
	aload_0_getfield com.whatsapp.client.AuthSelfSMSScreen$SelfSMSImpl$SendThread.field_58970   // get_name_1:  com.whatsapp.client.AuthSelfSMSScreen$SelfSMSImpl$SendThread.field_58970   // get_name_2:  com.whatsapp.client.AuthSelfSMSScreen$SelfSMSImpl$SendThread.field_58970   // get_Name:    com.whatsapp.client.AuthSelfSMSScreen$SelfSMSImpl$SendThread.field_58970   // getName->1:     // getName->2:     // getName->N:     // ofs = 58970 ord = 0 addr = 0
	getstatic_lib module:WhatsApp-19.class#0.static_2 // class#0
	invokenonvirtual_lib java.lang.String.getBytes // pc=2
	astore_4 
	iload_1 
	ifeq Label41
	aload_3 
	aload_4 
	aload_4 
	arraylength 
	invokeinterface interfacemethodref_6 // pc=3 guess=4
	astore_5 
	goto_w Label118
Label41:
	new_lib javax.microedition.io.Datagram//javax.microedition.io.Datagram javax.microedition.io.Datagram javax.microedition.io.Datagram
	dup 
	new_lib Thread//java.lang.Thread java.lang.Thread java.lang.Thread
	dup 
	ldc literal_84:"//"
	invokespecial_lib java.lang.StringBuffer.<init> // pc=2
	aload_0_getfield com.whatsapp.client.AuthSelfSMSScreen$SelfSMSImpl$SendThread.field_58974   // get_name_1:  com.whatsapp.client.AuthSelfSMSScreen$SelfSMSImpl$SendThread.field_58974   // get_name_2:  com.whatsapp.client.AuthSelfSMSScreen$SelfSMSImpl$SendThread.field_58974   // get_Name:    com.whatsapp.client.AuthSelfSMSScreen$SelfSMSImpl$SendThread.field_58974   // getName->1:     // getName->2:     // getName->N:     // ofs = 58974 ord = 1 addr = 0
	invokevirtual_short .virtual_10 // idx=10 pc=1
	invokevirtual java.lang.StringBuffer append( java.lang.StringBuffer, java.lang.String ) // pc=2
	ldc literal_85:":"
	invokevirtual java.lang.StringBuffer append( java.lang.StringBuffer, java.lang.String ) // pc=2
	aload_0_getfield com.whatsapp.client.AuthSelfSMSScreen$SelfSMSImpl$SendThread.field_58974   // get_name_1:  com.whatsapp.client.AuthSelfSMSScreen$SelfSMSImpl$SendThread.field_58974   // get_name_2:  com.whatsapp.client.AuthSelfSMSScreen$SelfSMSImpl$SendThread.field_58974   // get_Name:    com.whatsapp.client.AuthSelfSMSScreen$SelfSMSImpl$SendThread.field_58974   // getName->1:     // getName->2:     // getName->N:     // ofs = 58974 ord = 1 addr = 0
	invokevirtual_short .virtual_3 // idx=3 pc=1
	invokevirtual java.lang.StringBuffer append( java.lang.StringBuffer, int ) // pc=2
	invokevirtual_short .toString // idx=2 pc=1
	invokespecial_lib net.rim.device.api.io.SmsAddress.<init> // pc=2
	astore_6 
	aload_6 
	invokevirtual net.rim.device.api.system.SMSPacketHeader getHeader( net.rim.device.api.io.SmsAddress ) // pc=1
	astore_7 
	aload_7 
	iconst_0 
	invokevirtual setStatusReportRequest( net.rim.device.api.system.SMSPacketHeader, boolean ) // pc=2
	aload_7 
	iconst_1 
	invokevirtual setUserDataHeaderPresent( net.rim.device.api.system.SMSPacketHeader, boolean ) // pc=2
	aload_7 
	bipush -1
	invokevirtual setValidityPeriod( net.rim.device.api.system.SMSPacketHeader, int ) // pc=2
	aload_7 
	bipush -1
	invokevirtual setDeliveryPeriod( net.rim.device.api.system.SMSPacketHeader, int ) // pc=2
	aload_7 
	iconst_1 
	invokevirtual setMessageClass( net.rim.device.api.system.SMSPacketHeader, int ) // pc=2
	aload_7 
	iconst_1 
	invokevirtual setMessageCoding( net.rim.device.api.system.SMSPacketHeader, int ) // pc=2
	arrayinit [6, 5, 4, 7, -6, 7, -6]
	astore 8
	aload 8
	arraylength 
	aload_4 
	arraylength 
	iadd 
	newarray 2
	astore 9
	aload 8
	iconst_0 
	aload 9
	iconst_0 
	aload 8
	arraylength 
	invokestatic_lib arraycopy( java.lang.Object, int, java.lang.Object, int, int ) // System
	aload_4 
	iconst_0 
	aload 9
	aload 8
	arraylength 
	aload_4 
	arraylength 
	invokestatic_lib arraycopy( java.lang.Object, int, java.lang.Object, int, int ) // System
	aload_3 
	aload 9
	arraylength 
	invokeinterface interfacemethodref_7 // pc=2 guess=5
	astore_5 
	aload_5 
	checkcast_lib net.rim.device.api.system.SMSPacketHeader//net.rim.device.api.system.SMSPacketHeader net.rim.device.api.system.SMSPacketHeader net.rim.device.api.system.SMSPacketHeader
	aload_6 
	invokevirtual setAddressBase( net.rim.device.api.io.DatagramBase, net.rim.device.api.io.DatagramAddressBase ) // pc=2
	aload_5 
	aload 9
	iconst_0 
	aload 9
	arraylength 
	invokeinterface interfacemethodref_8 // pc=4 guess=6
Label118:
	aload_3 
	aload_5 
	invokeinterface interfacemethodref_9 // pc=2 guess=7
	aload_3 
	invokeinterface interfacemethodref_10 // pc=1 guess=8
	return 
	}

	// @@@@@@@@@@@@@ Virtual routines 

public final run( com.whatsapp.client.AuthSelfSMSScreen$SelfSMSImpl$SendThread ); // address: 0
	{
	enter 
	new_lib Thread//java.lang.Thread java.lang.Thread java.lang.Thread
	dup 
	ldc literal_84:"//"
	invokespecial_lib java.lang.StringBuffer.<init> // pc=2
	aload_0_getfield com.whatsapp.client.AuthSelfSMSScreen$SelfSMSImpl$SendThread.field_58974   // get_name_1:  com.whatsapp.client.AuthSelfSMSScreen$SelfSMSImpl$SendThread.field_58974   // get_name_2:  com.whatsapp.client.AuthSelfSMSScreen$SelfSMSImpl$SendThread.field_58974   // get_Name:    com.whatsapp.client.AuthSelfSMSScreen$SelfSMSImpl$SendThread.field_58974   // getName->1:     // getName->2:     // getName->N:     // ofs = 58974 ord = 1 addr = 0
	invokevirtual_short .virtual_10 // idx=10 pc=1
	invokevirtual java.lang.StringBuffer append( java.lang.StringBuffer, java.lang.String ) // pc=2
	ldc literal_85:":"
	invokevirtual java.lang.StringBuffer append( java.lang.StringBuffer, java.lang.String ) // pc=2
	aload_0_getfield com.whatsapp.client.AuthSelfSMSScreen$SelfSMSImpl$SendThread.field_58974   // get_name_1:  com.whatsapp.client.AuthSelfSMSScreen$SelfSMSImpl$SendThread.field_58974   // get_name_2:  com.whatsapp.client.AuthSelfSMSScreen$SelfSMSImpl$SendThread.field_58974   // get_Name:    com.whatsapp.client.AuthSelfSMSScreen$SelfSMSImpl$SendThread.field_58974   // getName->1:     // getName->2:     // getName->N:     // ofs = 58974 ord = 1 addr = 0
	invokevirtual_short .virtual_3 // idx=3 pc=1
	invokevirtual java.lang.StringBuffer append( java.lang.StringBuffer, int ) // pc=2
	invokevirtual_short .toString // idx=2 pc=1
	astore_1 
	aload_0_getfield com.whatsapp.client.AuthSelfSMSScreen$SelfSMSImpl$SendThread.field_58974   // get_name_1:  com.whatsapp.client.AuthSelfSMSScreen$SelfSMSImpl$SendThread.field_58974   // get_name_2:  com.whatsapp.client.AuthSelfSMSScreen$SelfSMSImpl$SendThread.field_58974   // get_Name:    com.whatsapp.client.AuthSelfSMSScreen$SelfSMSImpl$SendThread.field_58974   // getName->1:     // getName->2:     // getName->N:     // ofs = 58974 ord = 1 addr = 0
	getfield .field_3_3   // get_name_1:  .field_3_3   // get_name_2:  .field_3_3   // get_Name:    .field_3_3   // getName->1:  null   // getName->2:  null   // getName->N:  null   // ofs = -1 ord = 0 addr = 3
	ifeq Label27
	aload_0 
	invokestatic_lib int getNetworkType(  ) // RadioInfo
	bipush 4
	if_icmpne Label24
	iconst_1 
	goto Label25
Label24:
	iconst_0 
Label25:
	invokespecial com.whatsapp.client.AuthSelfSMSScreen$SelfSMSImpl$SendThread.routine_392 // pc=2
	goto_w Label113
Label27:
	aload_0 
	aload_1 
	invokespecial com.whatsapp.client.AuthSelfSMSScreen$SelfSMSImpl$SendThread.routine_338 // pc=2
	aload_0_getfield com.whatsapp.client.AuthSelfSMSScreen$SelfSMSImpl$SendThread.field_58974   // get_name_1:  com.whatsapp.client.AuthSelfSMSScreen$SelfSMSImpl$SendThread.field_58974   // get_name_2:  com.whatsapp.client.AuthSelfSMSScreen$SelfSMSImpl$SendThread.field_58974   // get_Name:    com.whatsapp.client.AuthSelfSMSScreen$SelfSMSImpl$SendThread.field_58974   // getName->1:     // getName->2:     // getName->N:     // ofs = 58974 ord = 1 addr = 0
	getfield .field_1_1   // get_name_1:  .field_1_1   // get_name_2:  .field_1_1   // get_Name:    .field_1_1   // getName->1:  null   // getName->2:  null   // getName->N:  null   // ofs = -1 ord = 0 addr = 1
	new_lib Thread//java.lang.Thread java.lang.Thread java.lang.Thread
	dup 
	ldc literal_86:"sent text message "
	invokespecial_lib java.lang.StringBuffer.<init> // pc=2
	aload_0_getfield com.whatsapp.client.AuthSelfSMSScreen$SelfSMSImpl$SendThread.field_58970   // get_name_1:  com.whatsapp.client.AuthSelfSMSScreen$SelfSMSImpl$SendThread.field_58970   // get_name_2:  com.whatsapp.client.AuthSelfSMSScreen$SelfSMSImpl$SendThread.field_58970   // get_Name:    com.whatsapp.client.AuthSelfSMSScreen$SelfSMSImpl$SendThread.field_58970   // getName->1:     // getName->2:     // getName->N:     // ofs = 58970 ord = 0 addr = 0
	invokevirtual java.lang.StringBuffer append( java.lang.StringBuffer, java.lang.String ) // pc=2
	ldc literal_87:" to "
	invokevirtual java.lang.StringBuffer append( java.lang.StringBuffer, java.lang.String ) // pc=2
	aload_1 
	invokevirtual java.lang.StringBuffer append( java.lang.StringBuffer, java.lang.String ) // pc=2
	invokevirtual_short .toString // idx=2 pc=1
	invokevirtual java.lang.StringBuffer append( java.lang.StringBuffer, java.lang.String ) // pc=2
	pop 
	return 
	astore_1 
	aload_0_getfield com.whatsapp.client.AuthSelfSMSScreen$SelfSMSImpl$SendThread.field_58974   // get_name_1:  com.whatsapp.client.AuthSelfSMSScreen$SelfSMSImpl$SendThread.field_58974   // get_name_2:  com.whatsapp.client.AuthSelfSMSScreen$SelfSMSImpl$SendThread.field_58974   // get_Name:    com.whatsapp.client.AuthSelfSMSScreen$SelfSMSImpl$SendThread.field_58974   // getName->1:     // getName->2:     // getName->N:     // ofs = 58974 ord = 1 addr = 0
	getfield .field_3_3   // get_name_1:  .field_3_3   // get_name_2:  .field_3_3   // get_Name:    .field_3_3   // getName->1:  null   // getName->2:  null   // getName->N:  null   // ofs = -1 ord = 0 addr = 3
	ifeq Label52
	ldc literal_88:"datagram"
	goto Label53
Label52:
	ldc literal_89:"TextMessage"
Label53:
	astore_2 
	new_lib Thread//java.lang.Thread java.lang.Thread java.lang.Thread
	dup 
	ldc literal_90:"failed sending "
	invokespecial_lib java.lang.StringBuffer.<init> // pc=2
	aload_2 
	invokevirtual java.lang.StringBuffer append( java.lang.StringBuffer, java.lang.String ) // pc=2
	ldc literal_91:" mode text message"
	invokevirtual java.lang.StringBuffer append( java.lang.StringBuffer, java.lang.String ) // pc=2
	invokevirtual_short .toString // idx=2 pc=1
	invokestatic_lib module:WhatsApp-79.class#39.routine_24694(  ) // class#39
	aload_0_getfield com.whatsapp.client.AuthSelfSMSScreen$SelfSMSImpl$SendThread.field_58974   // get_name_1:  com.whatsapp.client.AuthSelfSMSScreen$SelfSMSImpl$SendThread.field_58974   // get_name_2:  com.whatsapp.client.AuthSelfSMSScreen$SelfSMSImpl$SendThread.field_58974   // get_Name:    com.whatsapp.client.AuthSelfSMSScreen$SelfSMSImpl$SendThread.field_58974   // getName->1:     // getName->2:     // getName->N:     // ofs = 58974 ord = 1 addr = 0
	getfield .field_1_1   // get_name_1:  .field_1_1   // get_name_2:  .field_1_1   // get_Name:    .field_1_1   // getName->1:  null   // getName->2:  null   // getName->N:  null   // ofs = -1 ord = 0 addr = 1
	new_lib Thread//java.lang.Thread java.lang.Thread java.lang.Thread
	dup 
	ldc literal_90:"failed sending "
	invokespecial_lib java.lang.StringBuffer.<init> // pc=2
	aload_2 
	invokevirtual java.lang.StringBuffer append( java.lang.StringBuffer, java.lang.String ) // pc=2
	ldc literal_92:" text "
	invokevirtual java.lang.StringBuffer append( java.lang.StringBuffer, java.lang.String ) // pc=2
	aload_1 
	invokevirtual_short .toString // idx=2 pc=1
	invokevirtual java.lang.StringBuffer append( java.lang.StringBuffer, java.lang.String ) // pc=2
	ldc literal_93:": "
	invokevirtual java.lang.StringBuffer append( java.lang.StringBuffer, java.lang.String ) // pc=2
	aload_1 
	invokevirtual java.lang.String getMessage( java.lang.Throwable ) // pc=1
	invokevirtual java.lang.StringBuffer append( java.lang.StringBuffer, java.lang.String ) // pc=2
	ldc literal_94:"?"
	invokevirtual java.lang.StringBuffer append( java.lang.StringBuffer, java.lang.String ) // pc=2
	invokevirtual_short .toString // idx=2 pc=1
	invokevirtual java.lang.StringBuffer append( java.lang.StringBuffer, java.lang.String ) // pc=2
	pop 
	aload_0_getfield com.whatsapp.client.AuthSelfSMSScreen$SelfSMSImpl$SendThread.field_58974   // get_name_1:  com.whatsapp.client.AuthSelfSMSScreen$SelfSMSImpl$SendThread.field_58974   // get_name_2:  com.whatsapp.client.AuthSelfSMSScreen$SelfSMSImpl$SendThread.field_58974   // get_Name:    com.whatsapp.client.AuthSelfSMSScreen$SelfSMSImpl$SendThread.field_58974   // getName->1:     // getName->2:     // getName->N:     // ofs = 58974 ord = 1 addr = 0
	getfield .field_0_   // get_name_1:  .field_0_   // get_name_2:  .field_0_   // get_Name:    .field_0_   // getName->1:  null   // getName->2:  null   // getName->N:  null   // ofs = -1 ord = 0 addr = 0
	ifnull Label113
	aload_1 
	invokenonvirtual_lib java.lang.Object.getClass // pc=1
	invokevirtual java.lang.String getName( java.lang.Class ) // pc=1
	astore_3 
	aload_0_getfield com.whatsapp.client.AuthSelfSMSScreen$SelfSMSImpl$SendThread.field_58974   // get_name_1:  com.whatsapp.client.AuthSelfSMSScreen$SelfSMSImpl$SendThread.field_58974   // get_name_2:  com.whatsapp.client.AuthSelfSMSScreen$SelfSMSImpl$SendThread.field_58974   // get_Name:    com.whatsapp.client.AuthSelfSMSScreen$SelfSMSImpl$SendThread.field_58974   // getName->1:     // getName->2:     // getName->N:     // ofs = 58974 ord = 1 addr = 0
	getfield .field_0_   // get_name_1:  .field_0_   // get_name_2:  .field_0_   // get_Name:    .field_0_   // getName->1:  null   // getName->2:  null   // getName->N:  null   // ofs = -1 ord = 0 addr = 0
	new_lib Thread//java.lang.Thread java.lang.Thread java.lang.Thread
	dup 
	ldc literal_95:"local-error-send-"
	invokespecial_lib java.lang.StringBuffer.<init> // pc=2
	aload_3 
	invokevirtual java.lang.StringBuffer append( java.lang.StringBuffer, java.lang.String ) // pc=2
	ldc literal_96:"-"
	invokevirtual java.lang.StringBuffer append( java.lang.StringBuffer, java.lang.String ) // pc=2
	aload_1 
	invokevirtual java.lang.String getMessage( java.lang.Throwable ) // pc=1
	invokevirtual java.lang.StringBuffer append( java.lang.StringBuffer, java.lang.String ) // pc=2
	invokevirtual_short .toString // idx=2 pc=1
	sipush 671
	aload_0_getfield com.whatsapp.client.AuthSelfSMSScreen$SelfSMSImpl$SendThread.field_58974   // get_name_1:  com.whatsapp.client.AuthSelfSMSScreen$SelfSMSImpl$SendThread.field_58974   // get_name_2:  com.whatsapp.client.AuthSelfSMSScreen$SelfSMSImpl$SendThread.field_58974   // get_Name:    com.whatsapp.client.AuthSelfSMSScreen$SelfSMSImpl$SendThread.field_58974   // getName->1:     // getName->2:     // getName->N:     // ofs = 58974 ord = 1 addr = 0
	invokevirtual_short .virtual_10 // idx=10 pc=1
	invokestatic_lib module:WhatsApp-47.class#11.routine_4463(  ) // class#11
	invokeinterface interfacemethodref_2 // pc=3 guess=0
Label113:
	return 
	}

}
