// #######################################################
// Decompiled by   : coddec 
// Module          : WhatsApp-9.cod
// Module version  : 2.8.1914
// Class ID        : 1
// ########################################################


package com.whatsapp.client;


abstract public final class BitmapButtonField$SpinnerDrawableImage extends Object
implements com.whatsapp.client.

{

	// @@@@@@@@@@@@@ Fields 
	private com.whatsapp.client.BitmapButtonField /*module:WhatsApp-8.class#1*/  field_59378 ; // ofs = 59378 addr = 0)
	private final net.rim.device.api.system.Bitmap /*net.rim.device.api.system.Bitmap*/  field_59382 ; // ofs = 59382 addr = 0)
	private final net.rim.device.api.system.Bitmap /*net.rim.device.api.system.Bitmap*/  field_59386 ; // ofs = 59386 addr = 0)
	private final int /*int*/  field_59390 ; // ofs = 59390 addr = 0)
	private final int /*int*/  field_59394 ; // ofs = 59394 addr = 0)
	private final int /*int*/  field_59398 ; // ofs = 59398 addr = 0)
	private int /*int*/  field_59402 ; // ofs = 59402 addr = 0)
	private int /*int*/  field_59406 ; // ofs = 59406 addr = 0)

	// @@@@@@@@@@@@@ Static routines 

public <init>( com.whatsapp.client.BitmapButtonField$SpinnerDrawableImage, net.rim.device.api.system.Bitmap, net.rim.device.api.system.Bitmap, int ); // address: 0
	{
	enter 
	aload_0 
	invokespecial_lib java.lang.Object.<init> // pc=1
	aload_0 
	bipush -1
	putfield .field_7_7   // get_name_1:  .field_7_7   // get_name_2:  .field_7_7   // get_Name:    .field_7_7   // getName->1:  null   // getName->2:  null   // getName->N:  null   // ofs = -1 ord = 0 addr = 7
	aload_0 
	aload_1 
	putfield .field_1_1   // get_name_1:  .field_1_1   // get_name_2:  .field_1_1   // get_Name:    .field_1_1   // getName->1:  null   // getName->2:  null   // getName->N:  null   // ofs = -1 ord = 0 addr = 1
	aload_0 
	aload_2 
	putfield .field_2_2   // get_name_1:  .field_2_2   // get_name_2:  .field_2_2   // get_Name:    .field_2_2   // getName->1:  null   // getName->2:  null   // getName->N:  null   // ofs = -1 ord = 0 addr = 2
	aload_0 
	iload_3 
	putfield .field_3_3   // get_name_1:  .field_3_3   // get_name_2:  .field_3_3   // get_Name:    .field_3_3   // getName->1:  null   // getName->2:  null   // getName->N:  null   // ofs = -1 ord = 0 addr = 3
	aload_0 
	aload_0_getfield .field_2_2   // get_name_1:  .field_2_2   // get_name_2:  .field_2_2   // get_Name:    .field_2_2   // getName->1:  null   // getName->2:  null   // getName->N:  null   // ofs = -1 ord = 0 addr = 2
	invokevirtual int getWidth( net.rim.device.api.system.Bitmap ) // pc=1
	aload_0_getfield .field_3_3   // get_name_1:  .field_3_3   // get_name_2:  .field_3_3   // get_Name:    .field_3_3   // getName->1:  null   // getName->2:  null   // getName->N:  null   // ofs = -1 ord = 0 addr = 3
	idiv 
	putfield .field_4_4   // get_name_1:  .field_4_4   // get_name_2:  .field_4_4   // get_Name:    .field_4_4   // getName->1:  null   // getName->2:  null   // getName->N:  null   // ofs = -1 ord = 0 addr = 4
	aload_0 
	aload_0_getfield .field_2_2   // get_name_1:  .field_2_2   // get_name_2:  .field_2_2   // get_Name:    .field_2_2   // getName->1:  null   // getName->2:  null   // getName->N:  null   // ofs = -1 ord = 0 addr = 2
	invokevirtual int getHeight( net.rim.device.api.system.Bitmap ) // pc=1
	putfield .field_5_5   // get_name_1:  .field_5_5   // get_name_2:  .field_5_5   // get_Name:    .field_5_5   // getName->1:  null   // getName->2:  null   // getName->N:  null   // ofs = -1 ord = 0 addr = 5
	return 
	}

	// @@@@@@@@@@@@@ Non-virtual routines 

private final advanceFrame( com.whatsapp.client.BitmapButtonField$SpinnerDrawableImage ); // address: 0
	{
	enter 
	aload_0 
	aload_0_getfield .field_6_6   // get_name_1:  .field_6_6   // get_name_2:  .field_6_6   // get_Name:    .field_6_6   // getName->1:  null   // getName->2:  null   // getName->N:  null   // ofs = -1 ord = 0 addr = 6
	iconst_1 
	iadd 
	putfield .field_6_6   // get_name_1:  .field_6_6   // get_name_2:  .field_6_6   // get_Name:    .field_6_6   // getName->1:  null   // getName->2:  null   // getName->N:  null   // ofs = -1 ord = 0 addr = 6
	aload_0_getfield .field_6_6   // get_name_1:  .field_6_6   // get_name_2:  .field_6_6   // get_Name:    .field_6_6   // getName->1:  null   // getName->2:  null   // getName->N:  null   // ofs = -1 ord = 0 addr = 6
	aload_0_getfield .field_3_3   // get_name_1:  .field_3_3   // get_name_2:  .field_3_3   // get_Name:    .field_3_3   // getName->1:  null   // getName->2:  null   // getName->N:  null   // ofs = -1 ord = 0 addr = 3
	if_icmplt Label12
	aload_0 
	iconst_0 
	putfield .field_6_6   // get_name_1:  .field_6_6   // get_name_2:  .field_6_6   // get_Name:    .field_6_6   // getName->1:  null   // getName->2:  null   // getName->N:  null   // ofs = -1 ord = 0 addr = 6
Label12:
	aload_0_getfield .field_0_   // get_name_1:  .field_0_   // get_name_2:  .field_0_   // get_Name:    .field_0_   // getName->1:  null   // getName->2:  null   // getName->N:  null   // ofs = -1 ord = 0 addr = 0
	ifnull Label16
	aload_0_getfield .field_0_   // get_name_1:  .field_0_   // get_name_2:  .field_0_   // get_Name:    .field_0_   // getName->1:  null   // getName->2:  null   // getName->N:  null   // ofs = -1 ord = 0 addr = 0
	invokestatic_lib module:WhatsApp-8.class#1.routine_3122(  ) // class#1
Label16:
	return 
	}

	// @@@@@@@@@@@@@ Virtual routines 

public final int getWidth( com.whatsapp.client.BitmapButtonField$SpinnerDrawableImage ); // address: 0
	{
	enter_narrow 
	aload_0_getfield .field_1_1   // get_name_1:  .field_1_1   // get_name_2:  .field_1_1   // get_Name:    .field_1_1   // getName->1:  null   // getName->2:  null   // getName->N:  null   // ofs = -1 ord = 0 addr = 1
	invokevirtual int getWidth( net.rim.device.api.system.Bitmap ) // pc=1
	ireturn 
	}


public final int getHeight( com.whatsapp.client.BitmapButtonField$SpinnerDrawableImage ); // address: 0
	{
	enter_narrow 
	aload_0_getfield .field_1_1   // get_name_1:  .field_1_1   // get_name_2:  .field_1_1   // get_Name:    .field_1_1   // getName->1:  null   // getName->2:  null   // getName->N:  null   // ofs = -1 ord = 0 addr = 1
	invokevirtual int getHeight( net.rim.device.api.system.Bitmap ) // pc=1
	ireturn 
	}


public final setParent( com.whatsapp.client.BitmapButtonField$SpinnerDrawableImage, module:WhatsApp-8.class#1 ); // address: 0
	{
	putfield_return .field_0_   // get_name_1:  .field_0_   // get_name_2:  .field_0_   // get_Name:    .field_0_   // getName->1:  null   // getName->2:  null   // getName->N:  null   // ofs = -1 ord = 0 addr = 0
	}


public final onDisplay( com.whatsapp.client.BitmapButtonField$SpinnerDrawableImage ); // address: 0
	{
	enter 
	aload_0_getfield .field_7_7   // get_name_1:  .field_7_7   // get_name_2:  .field_7_7   // get_Name:    .field_7_7   // getName->1:  null   // getName->2:  null   // getName->N:  null   // ofs = -1 ord = 0 addr = 7
	bipush -1
	if_icmpne Label15
	aload_0 
	invokestatic_lib com.whatsapp.client.UiApp.routine_7787(  ) // UiApp
	new BitmapButtonField$SpinnerDrawableImage$1
	dup 
	aload_0 
	invokespecial com.whatsapp.client.BitmapButtonField$SpinnerDrawableImage$1.<init> // pc=2
	sipush 200
	i2l 
	iconst_1 
	invokevirtual int invokeLater( net.rim.device.api.system.Application, java.lang.Runnable, long, boolean ) // pc=5
	putfield .field_7_7   // get_name_1:  .field_7_7   // get_name_2:  .field_7_7   // get_Name:    .field_7_7   // getName->1:  null   // getName->2:  null   // getName->N:  null   // ofs = -1 ord = 0 addr = 7
Label15:
	return 
	}


public final onUndisplay( com.whatsapp.client.BitmapButtonField$SpinnerDrawableImage ); // address: 0
	{
	enter_narrow 
	aload_0_getfield .field_7_7   // get_name_1:  .field_7_7   // get_name_2:  .field_7_7   // get_Name:    .field_7_7   // getName->1:  null   // getName->2:  null   // getName->N:  null   // ofs = -1 ord = 0 addr = 7
	bipush -1
	if_icmpeq Label10
	invokestatic_lib com.whatsapp.client.UiApp.routine_7787(  ) // UiApp
	aload_0_getfield .field_7_7   // get_name_1:  .field_7_7   // get_name_2:  .field_7_7   // get_Name:    .field_7_7   // getName->1:  null   // getName->2:  null   // getName->N:  null   // ofs = -1 ord = 0 addr = 7
	invokevirtual cancelInvokeLater( net.rim.device.api.system.Application, int ) // pc=2
	aload_0 
	bipush -1
	putfield .field_7_7   // get_name_1:  .field_7_7   // get_name_2:  .field_7_7   // get_Name:    .field_7_7   // getName->1:  null   // getName->2:  null   // getName->N:  null   // ofs = -1 ord = 0 addr = 7
Label10:
	return 
	}


public final paint( com.whatsapp.client.BitmapButtonField$SpinnerDrawableImage, net.rim.device.api.ui.Graphics ); // address: 0
	{
	enter 
	aload_1 
	iconst_0 
	iconst_0 
	aload_0_getfield .field_1_1   // get_name_1:  .field_1_1   // get_name_2:  .field_1_1   // get_Name:    .field_1_1   // getName->1:  null   // getName->2:  null   // getName->N:  null   // ofs = -1 ord = 0 addr = 1
	invokevirtual int getWidth( net.rim.device.api.system.Bitmap ) // pc=1
	aload_0_getfield .field_1_1   // get_name_1:  .field_1_1   // get_name_2:  .field_1_1   // get_Name:    .field_1_1   // getName->1:  null   // getName->2:  null   // getName->N:  null   // ofs = -1 ord = 0 addr = 1
	invokevirtual int getHeight( net.rim.device.api.system.Bitmap ) // pc=1
	aload_0_getfield .field_1_1   // get_name_1:  .field_1_1   // get_name_2:  .field_1_1   // get_Name:    .field_1_1   // getName->1:  null   // getName->2:  null   // getName->N:  null   // ofs = -1 ord = 0 addr = 1
	iconst_0 
	iconst_0 
	invokevirtual drawBitmap( net.rim.device.api.ui.Graphics, int, int, int, int, net.rim.device.api.system.Bitmap, int, int ) // pc=8
	aload_1 
	aload_0 
	invokevirtual_short .virtual_3 // idx=3 pc=1
	aload_0_getfield .field_4_4   // get_name_1:  .field_4_4   // get_name_2:  .field_4_4   // get_Name:    .field_4_4   // getName->1:  null   // getName->2:  null   // getName->N:  null   // ofs = -1 ord = 0 addr = 4
	isub 
	bipush 2
	idiv 
	aload_0 
	invokevirtual_short .virtual_4 // idx=4 pc=1
	aload_0_getfield .field_5_5   // get_name_1:  .field_5_5   // get_name_2:  .field_5_5   // get_Name:    .field_5_5   // getName->1:  null   // getName->2:  null   // getName->N:  null   // ofs = -1 ord = 0 addr = 5
	isub 
	bipush 2
	idiv 
	aload_0_getfield .field_4_4   // get_name_1:  .field_4_4   // get_name_2:  .field_4_4   // get_Name:    .field_4_4   // getName->1:  null   // getName->2:  null   // getName->N:  null   // ofs = -1 ord = 0 addr = 4
	aload_0_getfield .field_5_5   // get_name_1:  .field_5_5   // get_name_2:  .field_5_5   // get_Name:    .field_5_5   // getName->1:  null   // getName->2:  null   // getName->N:  null   // ofs = -1 ord = 0 addr = 5
	aload_0_getfield .field_2_2   // get_name_1:  .field_2_2   // get_name_2:  .field_2_2   // get_Name:    .field_2_2   // getName->1:  null   // getName->2:  null   // getName->N:  null   // ofs = -1 ord = 0 addr = 2
	aload_0_getfield .field_4_4   // get_name_1:  .field_4_4   // get_name_2:  .field_4_4   // get_Name:    .field_4_4   // getName->1:  null   // getName->2:  null   // getName->N:  null   // ofs = -1 ord = 0 addr = 4
	aload_0_getfield .field_6_6   // get_name_1:  .field_6_6   // get_name_2:  .field_6_6   // get_Name:    .field_6_6   // getName->1:  null   // getName->2:  null   // getName->N:  null   // ofs = -1 ord = 0 addr = 6
	imul 
	iconst_0 
	invokevirtual drawBitmap( net.rim.device.api.ui.Graphics, int, int, int, int, net.rim.device.api.system.Bitmap, int, int ) // pc=8
	return 
	}

}
