import com.whatsapp.g5;
import java.io.BufferedReader;
import java.io.IOException;
import java.io.InputStream;
import java.io.InputStreamReader;
import java.util.ArrayList;
import java.util.HashSet;

public class o
{
  private static final String[] A;
  private static final HashSet<String> a;
  private static final HashSet<String> b;
  private static final HashSet<String> c;
  private static final HashSet<String> d;
  static boolean y;
  static String z;
  private String e;
  protected f f = null;
  protected String g = null;
  protected final String h = A[2];
  protected BufferedReader i;
  private boolean j;
  private int k;
  protected HashSet<String> l = new HashSet();
  private long m;
  private long n;
  private long o;
  private long p;
  private long q;
  private long r;
  private long s;
  private long t;
  private long u;
  private long v;
  private long w;
  private long x;

  // ERROR //
  static
  {
    // Byte code:
    //   0: bipush 119
    //   2: anewarray 43	java/lang/String
    //   5: astore_0
    //   6: ldc 45
    //   8: invokevirtual 49	java/lang/String:toCharArray	()[C
    //   11: astore_1
    //   12: aload_1
    //   13: arraylength
    //   14: istore_2
    //   15: iconst_0
    //   16: istore_3
    //   17: iload_2
    //   18: iload_3
    //   19: if_icmpgt +6578 -> 6597
    //   22: aload_0
    //   23: iconst_0
    //   24: new 43	java/lang/String
    //   27: dup
    //   28: aload_1
    //   29: invokespecial 53	java/lang/String:<init>	([C)V
    //   32: invokevirtual 57	java/lang/String:intern	()Ljava/lang/String;
    //   35: aastore
    //   36: ldc 59
    //   38: invokevirtual 49	java/lang/String:toCharArray	()[C
    //   41: astore 6
    //   43: aload 6
    //   45: arraylength
    //   46: istore 7
    //   48: iconst_0
    //   49: istore 8
    //   51: iload 7
    //   53: iload 8
    //   55: if_icmpgt +6628 -> 6683
    //   58: aload_0
    //   59: iconst_1
    //   60: new 43	java/lang/String
    //   63: dup
    //   64: aload 6
    //   66: invokespecial 53	java/lang/String:<init>	([C)V
    //   69: invokevirtual 57	java/lang/String:intern	()Ljava/lang/String;
    //   72: aastore
    //   73: ldc 61
    //   75: invokevirtual 49	java/lang/String:toCharArray	()[C
    //   78: astore 11
    //   80: aload 11
    //   82: arraylength
    //   83: istore 12
    //   85: iconst_0
    //   86: istore 13
    //   88: iload 12
    //   90: iload 13
    //   92: if_icmpgt +6681 -> 6773
    //   95: aload_0
    //   96: iconst_2
    //   97: new 43	java/lang/String
    //   100: dup
    //   101: aload 11
    //   103: invokespecial 53	java/lang/String:<init>	([C)V
    //   106: invokevirtual 57	java/lang/String:intern	()Ljava/lang/String;
    //   109: aastore
    //   110: ldc 63
    //   112: invokevirtual 49	java/lang/String:toCharArray	()[C
    //   115: astore 16
    //   117: aload 16
    //   119: arraylength
    //   120: istore 17
    //   122: iconst_0
    //   123: istore 18
    //   125: iload 17
    //   127: iload 18
    //   129: if_icmpgt +6736 -> 6865
    //   132: aload_0
    //   133: iconst_3
    //   134: new 43	java/lang/String
    //   137: dup
    //   138: aload 16
    //   140: invokespecial 53	java/lang/String:<init>	([C)V
    //   143: invokevirtual 57	java/lang/String:intern	()Ljava/lang/String;
    //   146: aastore
    //   147: ldc 65
    //   149: invokevirtual 49	java/lang/String:toCharArray	()[C
    //   152: astore 21
    //   154: aload 21
    //   156: arraylength
    //   157: istore 22
    //   159: iconst_0
    //   160: istore 23
    //   162: iload 22
    //   164: iload 23
    //   166: if_icmpgt +6791 -> 6957
    //   169: aload_0
    //   170: iconst_4
    //   171: new 43	java/lang/String
    //   174: dup
    //   175: aload 21
    //   177: invokespecial 53	java/lang/String:<init>	([C)V
    //   180: invokevirtual 57	java/lang/String:intern	()Ljava/lang/String;
    //   183: aastore
    //   184: ldc 67
    //   186: invokevirtual 49	java/lang/String:toCharArray	()[C
    //   189: astore 26
    //   191: aload 26
    //   193: arraylength
    //   194: istore 27
    //   196: iconst_0
    //   197: istore 28
    //   199: iload 27
    //   201: iload 28
    //   203: if_icmpgt +6846 -> 7049
    //   206: aload_0
    //   207: iconst_5
    //   208: new 43	java/lang/String
    //   211: dup
    //   212: aload 26
    //   214: invokespecial 53	java/lang/String:<init>	([C)V
    //   217: invokevirtual 57	java/lang/String:intern	()Ljava/lang/String;
    //   220: aastore
    //   221: ldc 69
    //   223: invokevirtual 49	java/lang/String:toCharArray	()[C
    //   226: astore 31
    //   228: aload 31
    //   230: arraylength
    //   231: istore 32
    //   233: iconst_0
    //   234: istore 33
    //   236: iload 32
    //   238: iload 33
    //   240: if_icmpgt +6901 -> 7141
    //   243: aload_0
    //   244: bipush 6
    //   246: new 43	java/lang/String
    //   249: dup
    //   250: aload 31
    //   252: invokespecial 53	java/lang/String:<init>	([C)V
    //   255: invokevirtual 57	java/lang/String:intern	()Ljava/lang/String;
    //   258: aastore
    //   259: ldc 71
    //   261: invokevirtual 49	java/lang/String:toCharArray	()[C
    //   264: astore 36
    //   266: aload 36
    //   268: arraylength
    //   269: istore 37
    //   271: iconst_0
    //   272: istore 38
    //   274: iload 37
    //   276: iload 38
    //   278: if_icmpgt +6955 -> 7233
    //   281: aload_0
    //   282: bipush 7
    //   284: new 43	java/lang/String
    //   287: dup
    //   288: aload 36
    //   290: invokespecial 53	java/lang/String:<init>	([C)V
    //   293: invokevirtual 57	java/lang/String:intern	()Ljava/lang/String;
    //   296: aastore
    //   297: ldc 73
    //   299: invokevirtual 49	java/lang/String:toCharArray	()[C
    //   302: astore 41
    //   304: aload 41
    //   306: arraylength
    //   307: istore 42
    //   309: iconst_0
    //   310: istore 43
    //   312: iload 42
    //   314: iload 43
    //   316: if_icmpgt +7009 -> 7325
    //   319: aload_0
    //   320: bipush 8
    //   322: new 43	java/lang/String
    //   325: dup
    //   326: aload 41
    //   328: invokespecial 53	java/lang/String:<init>	([C)V
    //   331: invokevirtual 57	java/lang/String:intern	()Ljava/lang/String;
    //   334: aastore
    //   335: ldc 75
    //   337: invokevirtual 49	java/lang/String:toCharArray	()[C
    //   340: astore 46
    //   342: aload 46
    //   344: arraylength
    //   345: istore 47
    //   347: iconst_0
    //   348: istore 48
    //   350: iload 47
    //   352: iload 48
    //   354: if_icmpgt +7063 -> 7417
    //   357: aload_0
    //   358: bipush 9
    //   360: new 43	java/lang/String
    //   363: dup
    //   364: aload 46
    //   366: invokespecial 53	java/lang/String:<init>	([C)V
    //   369: invokevirtual 57	java/lang/String:intern	()Ljava/lang/String;
    //   372: aastore
    //   373: ldc 77
    //   375: invokevirtual 49	java/lang/String:toCharArray	()[C
    //   378: astore 51
    //   380: aload 51
    //   382: arraylength
    //   383: istore 52
    //   385: iconst_0
    //   386: istore 53
    //   388: iload 52
    //   390: iload 53
    //   392: if_icmpgt +7117 -> 7509
    //   395: aload_0
    //   396: bipush 10
    //   398: new 43	java/lang/String
    //   401: dup
    //   402: aload 51
    //   404: invokespecial 53	java/lang/String:<init>	([C)V
    //   407: invokevirtual 57	java/lang/String:intern	()Ljava/lang/String;
    //   410: aastore
    //   411: ldc 79
    //   413: invokevirtual 49	java/lang/String:toCharArray	()[C
    //   416: astore 56
    //   418: aload 56
    //   420: arraylength
    //   421: istore 57
    //   423: iconst_0
    //   424: istore 58
    //   426: iload 57
    //   428: iload 58
    //   430: if_icmpgt +7171 -> 7601
    //   433: aload_0
    //   434: bipush 11
    //   436: new 43	java/lang/String
    //   439: dup
    //   440: aload 56
    //   442: invokespecial 53	java/lang/String:<init>	([C)V
    //   445: invokevirtual 57	java/lang/String:intern	()Ljava/lang/String;
    //   448: aastore
    //   449: ldc 81
    //   451: invokevirtual 49	java/lang/String:toCharArray	()[C
    //   454: astore 61
    //   456: aload 61
    //   458: arraylength
    //   459: istore 62
    //   461: iconst_0
    //   462: istore 63
    //   464: iload 62
    //   466: iload 63
    //   468: if_icmpgt +7225 -> 7693
    //   471: aload_0
    //   472: bipush 12
    //   474: new 43	java/lang/String
    //   477: dup
    //   478: aload 61
    //   480: invokespecial 53	java/lang/String:<init>	([C)V
    //   483: invokevirtual 57	java/lang/String:intern	()Ljava/lang/String;
    //   486: aastore
    //   487: ldc 83
    //   489: invokevirtual 49	java/lang/String:toCharArray	()[C
    //   492: astore 66
    //   494: aload 66
    //   496: arraylength
    //   497: istore 67
    //   499: iconst_0
    //   500: istore 68
    //   502: iload 67
    //   504: iload 68
    //   506: if_icmpgt +7279 -> 7785
    //   509: aload_0
    //   510: bipush 13
    //   512: new 43	java/lang/String
    //   515: dup
    //   516: aload 66
    //   518: invokespecial 53	java/lang/String:<init>	([C)V
    //   521: invokevirtual 57	java/lang/String:intern	()Ljava/lang/String;
    //   524: aastore
    //   525: ldc 85
    //   527: invokevirtual 49	java/lang/String:toCharArray	()[C
    //   530: astore 71
    //   532: aload 71
    //   534: arraylength
    //   535: istore 72
    //   537: iconst_0
    //   538: istore 73
    //   540: iload 72
    //   542: iload 73
    //   544: if_icmpgt +7333 -> 7877
    //   547: aload_0
    //   548: bipush 14
    //   550: new 43	java/lang/String
    //   553: dup
    //   554: aload 71
    //   556: invokespecial 53	java/lang/String:<init>	([C)V
    //   559: invokevirtual 57	java/lang/String:intern	()Ljava/lang/String;
    //   562: aastore
    //   563: ldc 87
    //   565: invokevirtual 49	java/lang/String:toCharArray	()[C
    //   568: astore 76
    //   570: aload 76
    //   572: arraylength
    //   573: istore 77
    //   575: iconst_0
    //   576: istore 78
    //   578: iload 77
    //   580: iload 78
    //   582: if_icmpgt +7387 -> 7969
    //   585: aload_0
    //   586: bipush 15
    //   588: new 43	java/lang/String
    //   591: dup
    //   592: aload 76
    //   594: invokespecial 53	java/lang/String:<init>	([C)V
    //   597: invokevirtual 57	java/lang/String:intern	()Ljava/lang/String;
    //   600: aastore
    //   601: ldc 89
    //   603: invokevirtual 49	java/lang/String:toCharArray	()[C
    //   606: astore 81
    //   608: aload 81
    //   610: arraylength
    //   611: istore 82
    //   613: iconst_0
    //   614: istore 83
    //   616: iload 82
    //   618: iload 83
    //   620: if_icmpgt +7441 -> 8061
    //   623: aload_0
    //   624: bipush 16
    //   626: new 43	java/lang/String
    //   629: dup
    //   630: aload 81
    //   632: invokespecial 53	java/lang/String:<init>	([C)V
    //   635: invokevirtual 57	java/lang/String:intern	()Ljava/lang/String;
    //   638: aastore
    //   639: ldc 91
    //   641: invokevirtual 49	java/lang/String:toCharArray	()[C
    //   644: astore 86
    //   646: aload 86
    //   648: arraylength
    //   649: istore 87
    //   651: iconst_0
    //   652: istore 88
    //   654: iload 87
    //   656: iload 88
    //   658: if_icmpgt +7495 -> 8153
    //   661: aload_0
    //   662: bipush 17
    //   664: new 43	java/lang/String
    //   667: dup
    //   668: aload 86
    //   670: invokespecial 53	java/lang/String:<init>	([C)V
    //   673: invokevirtual 57	java/lang/String:intern	()Ljava/lang/String;
    //   676: aastore
    //   677: ldc 93
    //   679: invokevirtual 49	java/lang/String:toCharArray	()[C
    //   682: astore 91
    //   684: aload 91
    //   686: arraylength
    //   687: istore 92
    //   689: iconst_0
    //   690: istore 93
    //   692: iload 92
    //   694: iload 93
    //   696: if_icmpgt +7549 -> 8245
    //   699: aload_0
    //   700: bipush 18
    //   702: new 43	java/lang/String
    //   705: dup
    //   706: aload 91
    //   708: invokespecial 53	java/lang/String:<init>	([C)V
    //   711: invokevirtual 57	java/lang/String:intern	()Ljava/lang/String;
    //   714: aastore
    //   715: ldc 95
    //   717: invokevirtual 49	java/lang/String:toCharArray	()[C
    //   720: astore 96
    //   722: aload 96
    //   724: arraylength
    //   725: istore 97
    //   727: iconst_0
    //   728: istore 98
    //   730: iload 97
    //   732: iload 98
    //   734: if_icmpgt +7603 -> 8337
    //   737: aload_0
    //   738: bipush 19
    //   740: new 43	java/lang/String
    //   743: dup
    //   744: aload 96
    //   746: invokespecial 53	java/lang/String:<init>	([C)V
    //   749: invokevirtual 57	java/lang/String:intern	()Ljava/lang/String;
    //   752: aastore
    //   753: ldc 97
    //   755: invokevirtual 49	java/lang/String:toCharArray	()[C
    //   758: astore 101
    //   760: aload 101
    //   762: arraylength
    //   763: istore 102
    //   765: iconst_0
    //   766: istore 103
    //   768: iload 102
    //   770: iload 103
    //   772: if_icmpgt +7657 -> 8429
    //   775: aload_0
    //   776: bipush 20
    //   778: new 43	java/lang/String
    //   781: dup
    //   782: aload 101
    //   784: invokespecial 53	java/lang/String:<init>	([C)V
    //   787: invokevirtual 57	java/lang/String:intern	()Ljava/lang/String;
    //   790: aastore
    //   791: ldc 99
    //   793: invokevirtual 49	java/lang/String:toCharArray	()[C
    //   796: astore 106
    //   798: aload 106
    //   800: arraylength
    //   801: istore 107
    //   803: iconst_0
    //   804: istore 108
    //   806: iload 107
    //   808: iload 108
    //   810: if_icmpgt +7711 -> 8521
    //   813: aload_0
    //   814: bipush 21
    //   816: new 43	java/lang/String
    //   819: dup
    //   820: aload 106
    //   822: invokespecial 53	java/lang/String:<init>	([C)V
    //   825: invokevirtual 57	java/lang/String:intern	()Ljava/lang/String;
    //   828: aastore
    //   829: ldc 101
    //   831: invokevirtual 49	java/lang/String:toCharArray	()[C
    //   834: astore 111
    //   836: aload 111
    //   838: arraylength
    //   839: istore 112
    //   841: iconst_0
    //   842: istore 113
    //   844: iload 112
    //   846: iload 113
    //   848: if_icmpgt +7765 -> 8613
    //   851: aload_0
    //   852: bipush 22
    //   854: new 43	java/lang/String
    //   857: dup
    //   858: aload 111
    //   860: invokespecial 53	java/lang/String:<init>	([C)V
    //   863: invokevirtual 57	java/lang/String:intern	()Ljava/lang/String;
    //   866: aastore
    //   867: ldc 103
    //   869: invokevirtual 49	java/lang/String:toCharArray	()[C
    //   872: astore 116
    //   874: aload 116
    //   876: arraylength
    //   877: istore 117
    //   879: iconst_0
    //   880: istore 118
    //   882: iload 117
    //   884: iload 118
    //   886: if_icmpgt +7819 -> 8705
    //   889: aload_0
    //   890: bipush 23
    //   892: new 43	java/lang/String
    //   895: dup
    //   896: aload 116
    //   898: invokespecial 53	java/lang/String:<init>	([C)V
    //   901: invokevirtual 57	java/lang/String:intern	()Ljava/lang/String;
    //   904: aastore
    //   905: ldc 105
    //   907: invokevirtual 49	java/lang/String:toCharArray	()[C
    //   910: astore 121
    //   912: aload 121
    //   914: arraylength
    //   915: istore 122
    //   917: iconst_0
    //   918: istore 123
    //   920: iload 122
    //   922: iload 123
    //   924: if_icmpgt +7873 -> 8797
    //   927: aload_0
    //   928: bipush 24
    //   930: new 43	java/lang/String
    //   933: dup
    //   934: aload 121
    //   936: invokespecial 53	java/lang/String:<init>	([C)V
    //   939: invokevirtual 57	java/lang/String:intern	()Ljava/lang/String;
    //   942: aastore
    //   943: ldc 107
    //   945: invokevirtual 49	java/lang/String:toCharArray	()[C
    //   948: astore 126
    //   950: aload 126
    //   952: arraylength
    //   953: istore 127
    //   955: iconst_0
    //   956: istore 128
    //   958: iload 127
    //   960: iload 128
    //   962: if_icmpgt +7927 -> 8889
    //   965: aload_0
    //   966: bipush 25
    //   968: new 43	java/lang/String
    //   971: dup
    //   972: aload 126
    //   974: invokespecial 53	java/lang/String:<init>	([C)V
    //   977: invokevirtual 57	java/lang/String:intern	()Ljava/lang/String;
    //   980: aastore
    //   981: ldc 109
    //   983: invokevirtual 49	java/lang/String:toCharArray	()[C
    //   986: astore 131
    //   988: aload 131
    //   990: arraylength
    //   991: istore 132
    //   993: iconst_0
    //   994: istore 133
    //   996: iload 132
    //   998: iload 133
    //   1000: if_icmpgt +7981 -> 8981
    //   1003: aload_0
    //   1004: bipush 26
    //   1006: new 43	java/lang/String
    //   1009: dup
    //   1010: aload 131
    //   1012: invokespecial 53	java/lang/String:<init>	([C)V
    //   1015: invokevirtual 57	java/lang/String:intern	()Ljava/lang/String;
    //   1018: aastore
    //   1019: ldc 111
    //   1021: invokevirtual 49	java/lang/String:toCharArray	()[C
    //   1024: astore 136
    //   1026: aload 136
    //   1028: arraylength
    //   1029: istore 137
    //   1031: iconst_0
    //   1032: istore 138
    //   1034: iload 137
    //   1036: iload 138
    //   1038: if_icmpgt +8035 -> 9073
    //   1041: aload_0
    //   1042: bipush 27
    //   1044: new 43	java/lang/String
    //   1047: dup
    //   1048: aload 136
    //   1050: invokespecial 53	java/lang/String:<init>	([C)V
    //   1053: invokevirtual 57	java/lang/String:intern	()Ljava/lang/String;
    //   1056: aastore
    //   1057: ldc 113
    //   1059: invokevirtual 49	java/lang/String:toCharArray	()[C
    //   1062: astore 141
    //   1064: aload 141
    //   1066: arraylength
    //   1067: istore 142
    //   1069: iconst_0
    //   1070: istore 143
    //   1072: iload 142
    //   1074: iload 143
    //   1076: if_icmpgt +8089 -> 9165
    //   1079: aload_0
    //   1080: bipush 28
    //   1082: new 43	java/lang/String
    //   1085: dup
    //   1086: aload 141
    //   1088: invokespecial 53	java/lang/String:<init>	([C)V
    //   1091: invokevirtual 57	java/lang/String:intern	()Ljava/lang/String;
    //   1094: aastore
    //   1095: ldc 115
    //   1097: invokevirtual 49	java/lang/String:toCharArray	()[C
    //   1100: astore 146
    //   1102: aload 146
    //   1104: arraylength
    //   1105: istore 147
    //   1107: iconst_0
    //   1108: istore 148
    //   1110: iload 147
    //   1112: iload 148
    //   1114: if_icmpgt +8143 -> 9257
    //   1117: aload_0
    //   1118: bipush 29
    //   1120: new 43	java/lang/String
    //   1123: dup
    //   1124: aload 146
    //   1126: invokespecial 53	java/lang/String:<init>	([C)V
    //   1129: invokevirtual 57	java/lang/String:intern	()Ljava/lang/String;
    //   1132: aastore
    //   1133: ldc 117
    //   1135: invokevirtual 49	java/lang/String:toCharArray	()[C
    //   1138: astore 151
    //   1140: aload 151
    //   1142: arraylength
    //   1143: istore 152
    //   1145: iconst_0
    //   1146: istore 153
    //   1148: iload 152
    //   1150: iload 153
    //   1152: if_icmpgt +8197 -> 9349
    //   1155: aload_0
    //   1156: bipush 30
    //   1158: new 43	java/lang/String
    //   1161: dup
    //   1162: aload 151
    //   1164: invokespecial 53	java/lang/String:<init>	([C)V
    //   1167: invokevirtual 57	java/lang/String:intern	()Ljava/lang/String;
    //   1170: aastore
    //   1171: ldc 119
    //   1173: invokevirtual 49	java/lang/String:toCharArray	()[C
    //   1176: astore 156
    //   1178: aload 156
    //   1180: arraylength
    //   1181: istore 157
    //   1183: iconst_0
    //   1184: istore 158
    //   1186: iload 157
    //   1188: iload 158
    //   1190: if_icmpgt +8251 -> 9441
    //   1193: aload_0
    //   1194: bipush 31
    //   1196: new 43	java/lang/String
    //   1199: dup
    //   1200: aload 156
    //   1202: invokespecial 53	java/lang/String:<init>	([C)V
    //   1205: invokevirtual 57	java/lang/String:intern	()Ljava/lang/String;
    //   1208: aastore
    //   1209: ldc 121
    //   1211: invokevirtual 49	java/lang/String:toCharArray	()[C
    //   1214: astore 161
    //   1216: aload 161
    //   1218: arraylength
    //   1219: istore 162
    //   1221: iconst_0
    //   1222: istore 163
    //   1224: iload 162
    //   1226: iload 163
    //   1228: if_icmpgt +8305 -> 9533
    //   1231: aload_0
    //   1232: bipush 32
    //   1234: new 43	java/lang/String
    //   1237: dup
    //   1238: aload 161
    //   1240: invokespecial 53	java/lang/String:<init>	([C)V
    //   1243: invokevirtual 57	java/lang/String:intern	()Ljava/lang/String;
    //   1246: aastore
    //   1247: ldc 123
    //   1249: invokevirtual 49	java/lang/String:toCharArray	()[C
    //   1252: astore 166
    //   1254: aload 166
    //   1256: arraylength
    //   1257: istore 167
    //   1259: iconst_0
    //   1260: istore 168
    //   1262: iload 167
    //   1264: iload 168
    //   1266: if_icmpgt +8359 -> 9625
    //   1269: aload_0
    //   1270: bipush 33
    //   1272: new 43	java/lang/String
    //   1275: dup
    //   1276: aload 166
    //   1278: invokespecial 53	java/lang/String:<init>	([C)V
    //   1281: invokevirtual 57	java/lang/String:intern	()Ljava/lang/String;
    //   1284: aastore
    //   1285: ldc 125
    //   1287: invokevirtual 49	java/lang/String:toCharArray	()[C
    //   1290: astore 171
    //   1292: aload 171
    //   1294: arraylength
    //   1295: istore 172
    //   1297: iconst_0
    //   1298: istore 173
    //   1300: iload 172
    //   1302: iload 173
    //   1304: if_icmpgt +8413 -> 9717
    //   1307: aload_0
    //   1308: bipush 34
    //   1310: new 43	java/lang/String
    //   1313: dup
    //   1314: aload 171
    //   1316: invokespecial 53	java/lang/String:<init>	([C)V
    //   1319: invokevirtual 57	java/lang/String:intern	()Ljava/lang/String;
    //   1322: aastore
    //   1323: ldc 127
    //   1325: invokevirtual 49	java/lang/String:toCharArray	()[C
    //   1328: astore 176
    //   1330: aload 176
    //   1332: arraylength
    //   1333: istore 177
    //   1335: iconst_0
    //   1336: istore 178
    //   1338: iload 177
    //   1340: iload 178
    //   1342: if_icmpgt +8467 -> 9809
    //   1345: aload_0
    //   1346: bipush 35
    //   1348: new 43	java/lang/String
    //   1351: dup
    //   1352: aload 176
    //   1354: invokespecial 53	java/lang/String:<init>	([C)V
    //   1357: invokevirtual 57	java/lang/String:intern	()Ljava/lang/String;
    //   1360: aastore
    //   1361: ldc 129
    //   1363: invokevirtual 49	java/lang/String:toCharArray	()[C
    //   1366: astore 181
    //   1368: aload 181
    //   1370: arraylength
    //   1371: istore 182
    //   1373: iconst_0
    //   1374: istore 183
    //   1376: iload 182
    //   1378: iload 183
    //   1380: if_icmpgt +8521 -> 9901
    //   1383: aload_0
    //   1384: bipush 36
    //   1386: new 43	java/lang/String
    //   1389: dup
    //   1390: aload 181
    //   1392: invokespecial 53	java/lang/String:<init>	([C)V
    //   1395: invokevirtual 57	java/lang/String:intern	()Ljava/lang/String;
    //   1398: aastore
    //   1399: ldc 131
    //   1401: invokevirtual 49	java/lang/String:toCharArray	()[C
    //   1404: astore 186
    //   1406: aload 186
    //   1408: arraylength
    //   1409: istore 187
    //   1411: iconst_0
    //   1412: istore 188
    //   1414: iload 187
    //   1416: iload 188
    //   1418: if_icmpgt +8575 -> 9993
    //   1421: aload_0
    //   1422: bipush 37
    //   1424: new 43	java/lang/String
    //   1427: dup
    //   1428: aload 186
    //   1430: invokespecial 53	java/lang/String:<init>	([C)V
    //   1433: invokevirtual 57	java/lang/String:intern	()Ljava/lang/String;
    //   1436: aastore
    //   1437: ldc 133
    //   1439: invokevirtual 49	java/lang/String:toCharArray	()[C
    //   1442: astore 191
    //   1444: aload 191
    //   1446: arraylength
    //   1447: istore 192
    //   1449: iconst_0
    //   1450: istore 193
    //   1452: iload 192
    //   1454: iload 193
    //   1456: if_icmpgt +8629 -> 10085
    //   1459: aload_0
    //   1460: bipush 38
    //   1462: new 43	java/lang/String
    //   1465: dup
    //   1466: aload 191
    //   1468: invokespecial 53	java/lang/String:<init>	([C)V
    //   1471: invokevirtual 57	java/lang/String:intern	()Ljava/lang/String;
    //   1474: aastore
    //   1475: ldc 135
    //   1477: invokevirtual 49	java/lang/String:toCharArray	()[C
    //   1480: astore 196
    //   1482: aload 196
    //   1484: arraylength
    //   1485: istore 197
    //   1487: iconst_0
    //   1488: istore 198
    //   1490: iload 197
    //   1492: iload 198
    //   1494: if_icmpgt +8683 -> 10177
    //   1497: aload_0
    //   1498: bipush 39
    //   1500: new 43	java/lang/String
    //   1503: dup
    //   1504: aload 196
    //   1506: invokespecial 53	java/lang/String:<init>	([C)V
    //   1509: invokevirtual 57	java/lang/String:intern	()Ljava/lang/String;
    //   1512: aastore
    //   1513: ldc 137
    //   1515: invokevirtual 49	java/lang/String:toCharArray	()[C
    //   1518: astore 201
    //   1520: aload 201
    //   1522: arraylength
    //   1523: istore 202
    //   1525: iconst_0
    //   1526: istore 203
    //   1528: iload 202
    //   1530: iload 203
    //   1532: if_icmpgt +8737 -> 10269
    //   1535: aload_0
    //   1536: bipush 40
    //   1538: new 43	java/lang/String
    //   1541: dup
    //   1542: aload 201
    //   1544: invokespecial 53	java/lang/String:<init>	([C)V
    //   1547: invokevirtual 57	java/lang/String:intern	()Ljava/lang/String;
    //   1550: aastore
    //   1551: ldc 139
    //   1553: invokevirtual 49	java/lang/String:toCharArray	()[C
    //   1556: astore 206
    //   1558: aload 206
    //   1560: arraylength
    //   1561: istore 207
    //   1563: iconst_0
    //   1564: istore 208
    //   1566: iload 207
    //   1568: iload 208
    //   1570: if_icmpgt +8791 -> 10361
    //   1573: aload_0
    //   1574: bipush 41
    //   1576: new 43	java/lang/String
    //   1579: dup
    //   1580: aload 206
    //   1582: invokespecial 53	java/lang/String:<init>	([C)V
    //   1585: invokevirtual 57	java/lang/String:intern	()Ljava/lang/String;
    //   1588: aastore
    //   1589: ldc 141
    //   1591: invokevirtual 49	java/lang/String:toCharArray	()[C
    //   1594: astore 211
    //   1596: aload 211
    //   1598: arraylength
    //   1599: istore 212
    //   1601: iconst_0
    //   1602: istore 213
    //   1604: iload 212
    //   1606: iload 213
    //   1608: if_icmpgt +8845 -> 10453
    //   1611: aload_0
    //   1612: bipush 42
    //   1614: new 43	java/lang/String
    //   1617: dup
    //   1618: aload 211
    //   1620: invokespecial 53	java/lang/String:<init>	([C)V
    //   1623: invokevirtual 57	java/lang/String:intern	()Ljava/lang/String;
    //   1626: aastore
    //   1627: ldc 143
    //   1629: invokevirtual 49	java/lang/String:toCharArray	()[C
    //   1632: astore 216
    //   1634: aload 216
    //   1636: arraylength
    //   1637: istore 217
    //   1639: iconst_0
    //   1640: istore 218
    //   1642: iload 217
    //   1644: iload 218
    //   1646: if_icmpgt +8899 -> 10545
    //   1649: aload_0
    //   1650: bipush 43
    //   1652: new 43	java/lang/String
    //   1655: dup
    //   1656: aload 216
    //   1658: invokespecial 53	java/lang/String:<init>	([C)V
    //   1661: invokevirtual 57	java/lang/String:intern	()Ljava/lang/String;
    //   1664: aastore
    //   1665: ldc 145
    //   1667: invokevirtual 49	java/lang/String:toCharArray	()[C
    //   1670: astore 221
    //   1672: aload 221
    //   1674: arraylength
    //   1675: istore 222
    //   1677: iconst_0
    //   1678: istore 223
    //   1680: iload 222
    //   1682: iload 223
    //   1684: if_icmpgt +8953 -> 10637
    //   1687: aload_0
    //   1688: bipush 44
    //   1690: new 43	java/lang/String
    //   1693: dup
    //   1694: aload 221
    //   1696: invokespecial 53	java/lang/String:<init>	([C)V
    //   1699: invokevirtual 57	java/lang/String:intern	()Ljava/lang/String;
    //   1702: aastore
    //   1703: ldc 147
    //   1705: invokevirtual 49	java/lang/String:toCharArray	()[C
    //   1708: astore 226
    //   1710: aload 226
    //   1712: arraylength
    //   1713: istore 227
    //   1715: iconst_0
    //   1716: istore 228
    //   1718: iload 227
    //   1720: iload 228
    //   1722: if_icmpgt +9007 -> 10729
    //   1725: aload_0
    //   1726: bipush 45
    //   1728: new 43	java/lang/String
    //   1731: dup
    //   1732: aload 226
    //   1734: invokespecial 53	java/lang/String:<init>	([C)V
    //   1737: invokevirtual 57	java/lang/String:intern	()Ljava/lang/String;
    //   1740: aastore
    //   1741: ldc 149
    //   1743: invokevirtual 49	java/lang/String:toCharArray	()[C
    //   1746: astore 231
    //   1748: aload 231
    //   1750: arraylength
    //   1751: istore 232
    //   1753: iconst_0
    //   1754: istore 233
    //   1756: iload 232
    //   1758: iload 233
    //   1760: if_icmpgt +9061 -> 10821
    //   1763: aload_0
    //   1764: bipush 46
    //   1766: new 43	java/lang/String
    //   1769: dup
    //   1770: aload 231
    //   1772: invokespecial 53	java/lang/String:<init>	([C)V
    //   1775: invokevirtual 57	java/lang/String:intern	()Ljava/lang/String;
    //   1778: aastore
    //   1779: ldc 151
    //   1781: invokevirtual 49	java/lang/String:toCharArray	()[C
    //   1784: astore 236
    //   1786: aload 236
    //   1788: arraylength
    //   1789: istore 237
    //   1791: iconst_0
    //   1792: istore 238
    //   1794: iload 237
    //   1796: iload 238
    //   1798: if_icmpgt +9115 -> 10913
    //   1801: aload_0
    //   1802: bipush 47
    //   1804: new 43	java/lang/String
    //   1807: dup
    //   1808: aload 236
    //   1810: invokespecial 53	java/lang/String:<init>	([C)V
    //   1813: invokevirtual 57	java/lang/String:intern	()Ljava/lang/String;
    //   1816: aastore
    //   1817: ldc 153
    //   1819: invokevirtual 49	java/lang/String:toCharArray	()[C
    //   1822: astore 241
    //   1824: aload 241
    //   1826: arraylength
    //   1827: istore 242
    //   1829: iconst_0
    //   1830: istore 243
    //   1832: iload 242
    //   1834: iload 243
    //   1836: if_icmpgt +9169 -> 11005
    //   1839: aload_0
    //   1840: bipush 48
    //   1842: new 43	java/lang/String
    //   1845: dup
    //   1846: aload 241
    //   1848: invokespecial 53	java/lang/String:<init>	([C)V
    //   1851: invokevirtual 57	java/lang/String:intern	()Ljava/lang/String;
    //   1854: aastore
    //   1855: ldc 155
    //   1857: invokevirtual 49	java/lang/String:toCharArray	()[C
    //   1860: astore 246
    //   1862: aload 246
    //   1864: arraylength
    //   1865: istore 247
    //   1867: iconst_0
    //   1868: istore 248
    //   1870: iload 247
    //   1872: iload 248
    //   1874: if_icmpgt +9223 -> 11097
    //   1877: aload_0
    //   1878: bipush 49
    //   1880: new 43	java/lang/String
    //   1883: dup
    //   1884: aload 246
    //   1886: invokespecial 53	java/lang/String:<init>	([C)V
    //   1889: invokevirtual 57	java/lang/String:intern	()Ljava/lang/String;
    //   1892: aastore
    //   1893: ldc 157
    //   1895: invokevirtual 49	java/lang/String:toCharArray	()[C
    //   1898: astore 251
    //   1900: aload 251
    //   1902: arraylength
    //   1903: istore 252
    //   1905: iconst_0
    //   1906: istore 253
    //   1908: iload 252
    //   1910: iload 253
    //   1912: if_icmpgt +9277 -> 11189
    //   1915: aload_0
    //   1916: bipush 50
    //   1918: new 43	java/lang/String
    //   1921: dup
    //   1922: aload 251
    //   1924: invokespecial 53	java/lang/String:<init>	([C)V
    //   1927: invokevirtual 57	java/lang/String:intern	()Ljava/lang/String;
    //   1930: aastore
    //   1931: ldc 159
    //   1933: invokevirtual 49	java/lang/String:toCharArray	()[C
    //   1936: wide
    //   1940: wide
    //   1944: arraylength
    //   1945: wide
    //   1949: iconst_0
    //   1950: wide
    //   1954: wide
    //   1958: wide
    //   1962: if_icmpgt +9319 -> 11281
    //   1965: aload_0
    //   1966: bipush 51
    //   1968: new 43	java/lang/String
    //   1971: dup
    //   1972: wide
    //   1976: invokespecial 53	java/lang/String:<init>	([C)V
    //   1979: invokevirtual 57	java/lang/String:intern	()Ljava/lang/String;
    //   1982: aastore
    //   1983: ldc 161
    //   1985: invokevirtual 49	java/lang/String:toCharArray	()[C
    //   1988: wide
    //   1992: wide
    //   1996: arraylength
    //   1997: wide
    //   2001: iconst_0
    //   2002: wide
    //   2006: wide
    //   2010: wide
    //   2014: if_icmpgt +9388 -> 11402
    //   2017: aload_0
    //   2018: bipush 52
    //   2020: new 43	java/lang/String
    //   2023: dup
    //   2024: wide
    //   2028: invokespecial 53	java/lang/String:<init>	([C)V
    //   2031: invokevirtual 57	java/lang/String:intern	()Ljava/lang/String;
    //   2034: aastore
    //   2035: ldc 163
    //   2037: invokevirtual 49	java/lang/String:toCharArray	()[C
    //   2040: wide
    //   2044: wide
    //   2048: arraylength
    //   2049: wide
    //   2053: iconst_0
    //   2054: wide
    //   2058: wide
    //   2062: wide
    //   2066: if_icmpgt +9456 -> 11522
    //   2069: aload_0
    //   2070: bipush 53
    //   2072: new 43	java/lang/String
    //   2075: dup
    //   2076: wide
    //   2080: invokespecial 53	java/lang/String:<init>	([C)V
    //   2083: invokevirtual 57	java/lang/String:intern	()Ljava/lang/String;
    //   2086: aastore
    //   2087: ldc 165
    //   2089: invokevirtual 49	java/lang/String:toCharArray	()[C
    //   2092: wide
    //   2096: wide
    //   2100: arraylength
    //   2101: wide
    //   2105: iconst_0
    //   2106: wide
    //   2110: wide
    //   2114: wide
    //   2118: if_icmpgt +9524 -> 11642
    //   2121: aload_0
    //   2122: bipush 54
    //   2124: new 43	java/lang/String
    //   2127: dup
    //   2128: wide
    //   2132: invokespecial 53	java/lang/String:<init>	([C)V
    //   2135: invokevirtual 57	java/lang/String:intern	()Ljava/lang/String;
    //   2138: aastore
    //   2139: ldc 167
    //   2141: invokevirtual 49	java/lang/String:toCharArray	()[C
    //   2144: wide
    //   2148: wide
    //   2152: arraylength
    //   2153: wide
    //   2157: iconst_0
    //   2158: wide
    //   2162: wide
    //   2166: wide
    //   2170: if_icmpgt +9592 -> 11762
    //   2173: aload_0
    //   2174: bipush 55
    //   2176: new 43	java/lang/String
    //   2179: dup
    //   2180: wide
    //   2184: invokespecial 53	java/lang/String:<init>	([C)V
    //   2187: invokevirtual 57	java/lang/String:intern	()Ljava/lang/String;
    //   2190: aastore
    //   2191: ldc 169
    //   2193: invokevirtual 49	java/lang/String:toCharArray	()[C
    //   2196: wide
    //   2200: wide
    //   2204: arraylength
    //   2205: wide
    //   2209: iconst_0
    //   2210: wide
    //   2214: wide
    //   2218: wide
    //   2222: if_icmpgt +9660 -> 11882
    //   2225: aload_0
    //   2226: bipush 56
    //   2228: new 43	java/lang/String
    //   2231: dup
    //   2232: wide
    //   2236: invokespecial 53	java/lang/String:<init>	([C)V
    //   2239: invokevirtual 57	java/lang/String:intern	()Ljava/lang/String;
    //   2242: aastore
    //   2243: ldc 171
    //   2245: invokevirtual 49	java/lang/String:toCharArray	()[C
    //   2248: wide
    //   2252: wide
    //   2256: arraylength
    //   2257: wide
    //   2261: iconst_0
    //   2262: wide
    //   2266: wide
    //   2270: wide
    //   2274: if_icmpgt +9728 -> 12002
    //   2277: aload_0
    //   2278: bipush 57
    //   2280: new 43	java/lang/String
    //   2283: dup
    //   2284: wide
    //   2288: invokespecial 53	java/lang/String:<init>	([C)V
    //   2291: invokevirtual 57	java/lang/String:intern	()Ljava/lang/String;
    //   2294: aastore
    //   2295: ldc 173
    //   2297: invokevirtual 49	java/lang/String:toCharArray	()[C
    //   2300: wide
    //   2304: wide
    //   2308: arraylength
    //   2309: wide
    //   2313: iconst_0
    //   2314: wide
    //   2318: wide
    //   2322: wide
    //   2326: if_icmpgt +9796 -> 12122
    //   2329: aload_0
    //   2330: bipush 58
    //   2332: new 43	java/lang/String
    //   2335: dup
    //   2336: wide
    //   2340: invokespecial 53	java/lang/String:<init>	([C)V
    //   2343: invokevirtual 57	java/lang/String:intern	()Ljava/lang/String;
    //   2346: aastore
    //   2347: ldc 175
    //   2349: invokevirtual 49	java/lang/String:toCharArray	()[C
    //   2352: wide
    //   2356: wide
    //   2360: arraylength
    //   2361: wide
    //   2365: iconst_0
    //   2366: wide
    //   2370: wide
    //   2374: wide
    //   2378: if_icmpgt +9864 -> 12242
    //   2381: aload_0
    //   2382: bipush 59
    //   2384: new 43	java/lang/String
    //   2387: dup
    //   2388: wide
    //   2392: invokespecial 53	java/lang/String:<init>	([C)V
    //   2395: invokevirtual 57	java/lang/String:intern	()Ljava/lang/String;
    //   2398: aastore
    //   2399: ldc 177
    //   2401: invokevirtual 49	java/lang/String:toCharArray	()[C
    //   2404: wide
    //   2408: wide
    //   2412: arraylength
    //   2413: wide
    //   2417: iconst_0
    //   2418: wide
    //   2422: wide
    //   2426: wide
    //   2430: if_icmpgt +9932 -> 12362
    //   2433: aload_0
    //   2434: bipush 60
    //   2436: new 43	java/lang/String
    //   2439: dup
    //   2440: wide
    //   2444: invokespecial 53	java/lang/String:<init>	([C)V
    //   2447: invokevirtual 57	java/lang/String:intern	()Ljava/lang/String;
    //   2450: aastore
    //   2451: ldc 179
    //   2453: invokevirtual 49	java/lang/String:toCharArray	()[C
    //   2456: wide
    //   2460: wide
    //   2464: arraylength
    //   2465: wide
    //   2469: iconst_0
    //   2470: wide
    //   2474: wide
    //   2478: wide
    //   2482: if_icmpgt +10000 -> 12482
    //   2485: aload_0
    //   2486: bipush 61
    //   2488: new 43	java/lang/String
    //   2491: dup
    //   2492: wide
    //   2496: invokespecial 53	java/lang/String:<init>	([C)V
    //   2499: invokevirtual 57	java/lang/String:intern	()Ljava/lang/String;
    //   2502: aastore
    //   2503: ldc 181
    //   2505: invokevirtual 49	java/lang/String:toCharArray	()[C
    //   2508: wide
    //   2512: wide
    //   2516: arraylength
    //   2517: wide
    //   2521: iconst_0
    //   2522: wide
    //   2526: wide
    //   2530: wide
    //   2534: if_icmpgt +10068 -> 12602
    //   2537: aload_0
    //   2538: bipush 62
    //   2540: new 43	java/lang/String
    //   2543: dup
    //   2544: wide
    //   2548: invokespecial 53	java/lang/String:<init>	([C)V
    //   2551: invokevirtual 57	java/lang/String:intern	()Ljava/lang/String;
    //   2554: aastore
    //   2555: ldc 183
    //   2557: invokevirtual 49	java/lang/String:toCharArray	()[C
    //   2560: wide
    //   2564: wide
    //   2568: arraylength
    //   2569: wide
    //   2573: iconst_0
    //   2574: wide
    //   2578: wide
    //   2582: wide
    //   2586: if_icmpgt +10136 -> 12722
    //   2589: aload_0
    //   2590: bipush 63
    //   2592: new 43	java/lang/String
    //   2595: dup
    //   2596: wide
    //   2600: invokespecial 53	java/lang/String:<init>	([C)V
    //   2603: invokevirtual 57	java/lang/String:intern	()Ljava/lang/String;
    //   2606: aastore
    //   2607: ldc 185
    //   2609: invokevirtual 49	java/lang/String:toCharArray	()[C
    //   2612: wide
    //   2616: wide
    //   2620: arraylength
    //   2621: wide
    //   2625: iconst_0
    //   2626: wide
    //   2630: wide
    //   2634: wide
    //   2638: if_icmpgt +10204 -> 12842
    //   2641: aload_0
    //   2642: bipush 64
    //   2644: new 43	java/lang/String
    //   2647: dup
    //   2648: wide
    //   2652: invokespecial 53	java/lang/String:<init>	([C)V
    //   2655: invokevirtual 57	java/lang/String:intern	()Ljava/lang/String;
    //   2658: aastore
    //   2659: ldc 187
    //   2661: invokevirtual 49	java/lang/String:toCharArray	()[C
    //   2664: wide
    //   2668: wide
    //   2672: arraylength
    //   2673: wide
    //   2677: iconst_0
    //   2678: wide
    //   2682: wide
    //   2686: wide
    //   2690: if_icmpgt +10272 -> 12962
    //   2693: aload_0
    //   2694: bipush 65
    //   2696: new 43	java/lang/String
    //   2699: dup
    //   2700: wide
    //   2704: invokespecial 53	java/lang/String:<init>	([C)V
    //   2707: invokevirtual 57	java/lang/String:intern	()Ljava/lang/String;
    //   2710: aastore
    //   2711: ldc 189
    //   2713: invokevirtual 49	java/lang/String:toCharArray	()[C
    //   2716: wide
    //   2720: wide
    //   2724: arraylength
    //   2725: wide
    //   2729: iconst_0
    //   2730: wide
    //   2734: wide
    //   2738: wide
    //   2742: if_icmpgt +10340 -> 13082
    //   2745: aload_0
    //   2746: bipush 66
    //   2748: new 43	java/lang/String
    //   2751: dup
    //   2752: wide
    //   2756: invokespecial 53	java/lang/String:<init>	([C)V
    //   2759: invokevirtual 57	java/lang/String:intern	()Ljava/lang/String;
    //   2762: aastore
    //   2763: ldc 191
    //   2765: invokevirtual 49	java/lang/String:toCharArray	()[C
    //   2768: wide
    //   2772: wide
    //   2776: arraylength
    //   2777: wide
    //   2781: iconst_0
    //   2782: wide
    //   2786: wide
    //   2790: wide
    //   2794: if_icmpgt +10408 -> 13202
    //   2797: aload_0
    //   2798: bipush 67
    //   2800: new 43	java/lang/String
    //   2803: dup
    //   2804: wide
    //   2808: invokespecial 53	java/lang/String:<init>	([C)V
    //   2811: invokevirtual 57	java/lang/String:intern	()Ljava/lang/String;
    //   2814: aastore
    //   2815: ldc 193
    //   2817: invokevirtual 49	java/lang/String:toCharArray	()[C
    //   2820: wide
    //   2824: wide
    //   2828: arraylength
    //   2829: wide
    //   2833: iconst_0
    //   2834: wide
    //   2838: wide
    //   2842: wide
    //   2846: if_icmpgt +10476 -> 13322
    //   2849: aload_0
    //   2850: bipush 68
    //   2852: new 43	java/lang/String
    //   2855: dup
    //   2856: wide
    //   2860: invokespecial 53	java/lang/String:<init>	([C)V
    //   2863: invokevirtual 57	java/lang/String:intern	()Ljava/lang/String;
    //   2866: aastore
    //   2867: ldc 195
    //   2869: invokevirtual 49	java/lang/String:toCharArray	()[C
    //   2872: wide
    //   2876: wide
    //   2880: arraylength
    //   2881: wide
    //   2885: iconst_0
    //   2886: wide
    //   2890: wide
    //   2894: wide
    //   2898: if_icmpgt +10544 -> 13442
    //   2901: aload_0
    //   2902: bipush 69
    //   2904: new 43	java/lang/String
    //   2907: dup
    //   2908: wide
    //   2912: invokespecial 53	java/lang/String:<init>	([C)V
    //   2915: invokevirtual 57	java/lang/String:intern	()Ljava/lang/String;
    //   2918: aastore
    //   2919: ldc 197
    //   2921: invokevirtual 49	java/lang/String:toCharArray	()[C
    //   2924: wide
    //   2928: wide
    //   2932: arraylength
    //   2933: wide
    //   2937: iconst_0
    //   2938: wide
    //   2942: wide
    //   2946: wide
    //   2950: if_icmpgt +10612 -> 13562
    //   2953: aload_0
    //   2954: bipush 70
    //   2956: new 43	java/lang/String
    //   2959: dup
    //   2960: wide
    //   2964: invokespecial 53	java/lang/String:<init>	([C)V
    //   2967: invokevirtual 57	java/lang/String:intern	()Ljava/lang/String;
    //   2970: aastore
    //   2971: ldc 199
    //   2973: invokevirtual 49	java/lang/String:toCharArray	()[C
    //   2976: wide
    //   2980: wide
    //   2984: arraylength
    //   2985: wide
    //   2989: iconst_0
    //   2990: wide
    //   2994: wide
    //   2998: wide
    //   3002: if_icmpgt +10680 -> 13682
    //   3005: aload_0
    //   3006: bipush 71
    //   3008: new 43	java/lang/String
    //   3011: dup
    //   3012: wide
    //   3016: invokespecial 53	java/lang/String:<init>	([C)V
    //   3019: invokevirtual 57	java/lang/String:intern	()Ljava/lang/String;
    //   3022: aastore
    //   3023: ldc 201
    //   3025: invokevirtual 49	java/lang/String:toCharArray	()[C
    //   3028: wide
    //   3032: wide
    //   3036: arraylength
    //   3037: wide
    //   3041: iconst_0
    //   3042: wide
    //   3046: wide
    //   3050: wide
    //   3054: if_icmpgt +10748 -> 13802
    //   3057: aload_0
    //   3058: bipush 72
    //   3060: new 43	java/lang/String
    //   3063: dup
    //   3064: wide
    //   3068: invokespecial 53	java/lang/String:<init>	([C)V
    //   3071: invokevirtual 57	java/lang/String:intern	()Ljava/lang/String;
    //   3074: aastore
    //   3075: ldc 203
    //   3077: invokevirtual 49	java/lang/String:toCharArray	()[C
    //   3080: wide
    //   3084: wide
    //   3088: arraylength
    //   3089: wide
    //   3093: iconst_0
    //   3094: wide
    //   3098: wide
    //   3102: wide
    //   3106: if_icmpgt +10816 -> 13922
    //   3109: aload_0
    //   3110: bipush 73
    //   3112: new 43	java/lang/String
    //   3115: dup
    //   3116: wide
    //   3120: invokespecial 53	java/lang/String:<init>	([C)V
    //   3123: invokevirtual 57	java/lang/String:intern	()Ljava/lang/String;
    //   3126: aastore
    //   3127: ldc 205
    //   3129: invokevirtual 49	java/lang/String:toCharArray	()[C
    //   3132: wide
    //   3136: wide
    //   3140: arraylength
    //   3141: wide
    //   3145: iconst_0
    //   3146: wide
    //   3150: wide
    //   3154: wide
    //   3158: if_icmpgt +10884 -> 14042
    //   3161: aload_0
    //   3162: bipush 74
    //   3164: new 43	java/lang/String
    //   3167: dup
    //   3168: wide
    //   3172: invokespecial 53	java/lang/String:<init>	([C)V
    //   3175: invokevirtual 57	java/lang/String:intern	()Ljava/lang/String;
    //   3178: aastore
    //   3179: ldc 207
    //   3181: invokevirtual 49	java/lang/String:toCharArray	()[C
    //   3184: wide
    //   3188: wide
    //   3192: arraylength
    //   3193: wide
    //   3197: iconst_0
    //   3198: wide
    //   3202: wide
    //   3206: wide
    //   3210: if_icmpgt +10952 -> 14162
    //   3213: aload_0
    //   3214: bipush 75
    //   3216: new 43	java/lang/String
    //   3219: dup
    //   3220: wide
    //   3224: invokespecial 53	java/lang/String:<init>	([C)V
    //   3227: invokevirtual 57	java/lang/String:intern	()Ljava/lang/String;
    //   3230: aastore
    //   3231: ldc 209
    //   3233: invokevirtual 49	java/lang/String:toCharArray	()[C
    //   3236: wide
    //   3240: wide
    //   3244: arraylength
    //   3245: wide
    //   3249: iconst_0
    //   3250: wide
    //   3254: wide
    //   3258: wide
    //   3262: if_icmpgt +11020 -> 14282
    //   3265: aload_0
    //   3266: bipush 76
    //   3268: new 43	java/lang/String
    //   3271: dup
    //   3272: wide
    //   3276: invokespecial 53	java/lang/String:<init>	([C)V
    //   3279: invokevirtual 57	java/lang/String:intern	()Ljava/lang/String;
    //   3282: aastore
    //   3283: ldc 211
    //   3285: invokevirtual 49	java/lang/String:toCharArray	()[C
    //   3288: wide
    //   3292: wide
    //   3296: arraylength
    //   3297: wide
    //   3301: iconst_0
    //   3302: wide
    //   3306: wide
    //   3310: wide
    //   3314: if_icmpgt +11088 -> 14402
    //   3317: aload_0
    //   3318: bipush 77
    //   3320: new 43	java/lang/String
    //   3323: dup
    //   3324: wide
    //   3328: invokespecial 53	java/lang/String:<init>	([C)V
    //   3331: invokevirtual 57	java/lang/String:intern	()Ljava/lang/String;
    //   3334: aastore
    //   3335: ldc 213
    //   3337: invokevirtual 49	java/lang/String:toCharArray	()[C
    //   3340: wide
    //   3344: wide
    //   3348: arraylength
    //   3349: wide
    //   3353: iconst_0
    //   3354: wide
    //   3358: wide
    //   3362: wide
    //   3366: if_icmpgt +11156 -> 14522
    //   3369: aload_0
    //   3370: bipush 78
    //   3372: new 43	java/lang/String
    //   3375: dup
    //   3376: wide
    //   3380: invokespecial 53	java/lang/String:<init>	([C)V
    //   3383: invokevirtual 57	java/lang/String:intern	()Ljava/lang/String;
    //   3386: aastore
    //   3387: ldc 215
    //   3389: invokevirtual 49	java/lang/String:toCharArray	()[C
    //   3392: wide
    //   3396: wide
    //   3400: arraylength
    //   3401: wide
    //   3405: iconst_0
    //   3406: wide
    //   3410: wide
    //   3414: wide
    //   3418: if_icmpgt +11224 -> 14642
    //   3421: aload_0
    //   3422: bipush 79
    //   3424: new 43	java/lang/String
    //   3427: dup
    //   3428: wide
    //   3432: invokespecial 53	java/lang/String:<init>	([C)V
    //   3435: invokevirtual 57	java/lang/String:intern	()Ljava/lang/String;
    //   3438: aastore
    //   3439: ldc 217
    //   3441: invokevirtual 49	java/lang/String:toCharArray	()[C
    //   3444: wide
    //   3448: wide
    //   3452: arraylength
    //   3453: wide
    //   3457: iconst_0
    //   3458: wide
    //   3462: wide
    //   3466: wide
    //   3470: if_icmpgt +11292 -> 14762
    //   3473: aload_0
    //   3474: bipush 80
    //   3476: new 43	java/lang/String
    //   3479: dup
    //   3480: wide
    //   3484: invokespecial 53	java/lang/String:<init>	([C)V
    //   3487: invokevirtual 57	java/lang/String:intern	()Ljava/lang/String;
    //   3490: aastore
    //   3491: ldc 219
    //   3493: invokevirtual 49	java/lang/String:toCharArray	()[C
    //   3496: wide
    //   3500: wide
    //   3504: arraylength
    //   3505: wide
    //   3509: iconst_0
    //   3510: wide
    //   3514: wide
    //   3518: wide
    //   3522: if_icmpgt +11360 -> 14882
    //   3525: aload_0
    //   3526: bipush 81
    //   3528: new 43	java/lang/String
    //   3531: dup
    //   3532: wide
    //   3536: invokespecial 53	java/lang/String:<init>	([C)V
    //   3539: invokevirtual 57	java/lang/String:intern	()Ljava/lang/String;
    //   3542: aastore
    //   3543: ldc 221
    //   3545: invokevirtual 49	java/lang/String:toCharArray	()[C
    //   3548: wide
    //   3552: wide
    //   3556: arraylength
    //   3557: wide
    //   3561: iconst_0
    //   3562: wide
    //   3566: wide
    //   3570: wide
    //   3574: if_icmpgt +11428 -> 15002
    //   3577: aload_0
    //   3578: bipush 82
    //   3580: new 43	java/lang/String
    //   3583: dup
    //   3584: wide
    //   3588: invokespecial 53	java/lang/String:<init>	([C)V
    //   3591: invokevirtual 57	java/lang/String:intern	()Ljava/lang/String;
    //   3594: aastore
    //   3595: ldc 223
    //   3597: invokevirtual 49	java/lang/String:toCharArray	()[C
    //   3600: wide
    //   3604: wide
    //   3608: arraylength
    //   3609: wide
    //   3613: iconst_0
    //   3614: wide
    //   3618: wide
    //   3622: wide
    //   3626: if_icmpgt +11496 -> 15122
    //   3629: aload_0
    //   3630: bipush 83
    //   3632: new 43	java/lang/String
    //   3635: dup
    //   3636: wide
    //   3640: invokespecial 53	java/lang/String:<init>	([C)V
    //   3643: invokevirtual 57	java/lang/String:intern	()Ljava/lang/String;
    //   3646: aastore
    //   3647: ldc 225
    //   3649: invokevirtual 49	java/lang/String:toCharArray	()[C
    //   3652: wide
    //   3656: wide
    //   3660: arraylength
    //   3661: wide
    //   3665: iconst_0
    //   3666: wide
    //   3670: wide
    //   3674: wide
    //   3678: if_icmpgt +11564 -> 15242
    //   3681: aload_0
    //   3682: bipush 84
    //   3684: new 43	java/lang/String
    //   3687: dup
    //   3688: wide
    //   3692: invokespecial 53	java/lang/String:<init>	([C)V
    //   3695: invokevirtual 57	java/lang/String:intern	()Ljava/lang/String;
    //   3698: aastore
    //   3699: ldc 227
    //   3701: invokevirtual 49	java/lang/String:toCharArray	()[C
    //   3704: wide
    //   3708: wide
    //   3712: arraylength
    //   3713: wide
    //   3717: iconst_0
    //   3718: wide
    //   3722: wide
    //   3726: wide
    //   3730: if_icmpgt +11632 -> 15362
    //   3733: aload_0
    //   3734: bipush 85
    //   3736: new 43	java/lang/String
    //   3739: dup
    //   3740: wide
    //   3744: invokespecial 53	java/lang/String:<init>	([C)V
    //   3747: invokevirtual 57	java/lang/String:intern	()Ljava/lang/String;
    //   3750: aastore
    //   3751: ldc 229
    //   3753: invokevirtual 49	java/lang/String:toCharArray	()[C
    //   3756: wide
    //   3760: wide
    //   3764: arraylength
    //   3765: wide
    //   3769: iconst_0
    //   3770: wide
    //   3774: wide
    //   3778: wide
    //   3782: if_icmpgt +11700 -> 15482
    //   3785: aload_0
    //   3786: bipush 86
    //   3788: new 43	java/lang/String
    //   3791: dup
    //   3792: wide
    //   3796: invokespecial 53	java/lang/String:<init>	([C)V
    //   3799: invokevirtual 57	java/lang/String:intern	()Ljava/lang/String;
    //   3802: aastore
    //   3803: ldc 231
    //   3805: invokevirtual 49	java/lang/String:toCharArray	()[C
    //   3808: wide
    //   3812: wide
    //   3816: arraylength
    //   3817: wide
    //   3821: iconst_0
    //   3822: wide
    //   3826: wide
    //   3830: wide
    //   3834: if_icmpgt +11768 -> 15602
    //   3837: aload_0
    //   3838: bipush 87
    //   3840: new 43	java/lang/String
    //   3843: dup
    //   3844: wide
    //   3848: invokespecial 53	java/lang/String:<init>	([C)V
    //   3851: invokevirtual 57	java/lang/String:intern	()Ljava/lang/String;
    //   3854: aastore
    //   3855: ldc 233
    //   3857: invokevirtual 49	java/lang/String:toCharArray	()[C
    //   3860: wide
    //   3864: wide
    //   3868: arraylength
    //   3869: wide
    //   3873: iconst_0
    //   3874: wide
    //   3878: wide
    //   3882: wide
    //   3886: if_icmpgt +11836 -> 15722
    //   3889: aload_0
    //   3890: bipush 88
    //   3892: new 43	java/lang/String
    //   3895: dup
    //   3896: wide
    //   3900: invokespecial 53	java/lang/String:<init>	([C)V
    //   3903: invokevirtual 57	java/lang/String:intern	()Ljava/lang/String;
    //   3906: aastore
    //   3907: ldc 235
    //   3909: invokevirtual 49	java/lang/String:toCharArray	()[C
    //   3912: wide
    //   3916: wide
    //   3920: arraylength
    //   3921: wide
    //   3925: iconst_0
    //   3926: wide
    //   3930: wide
    //   3934: wide
    //   3938: if_icmpgt +11904 -> 15842
    //   3941: aload_0
    //   3942: bipush 89
    //   3944: new 43	java/lang/String
    //   3947: dup
    //   3948: wide
    //   3952: invokespecial 53	java/lang/String:<init>	([C)V
    //   3955: invokevirtual 57	java/lang/String:intern	()Ljava/lang/String;
    //   3958: aastore
    //   3959: ldc 237
    //   3961: invokevirtual 49	java/lang/String:toCharArray	()[C
    //   3964: wide
    //   3968: wide
    //   3972: arraylength
    //   3973: wide
    //   3977: iconst_0
    //   3978: wide
    //   3982: wide
    //   3986: wide
    //   3990: if_icmpgt +11972 -> 15962
    //   3993: aload_0
    //   3994: bipush 90
    //   3996: new 43	java/lang/String
    //   3999: dup
    //   4000: wide
    //   4004: invokespecial 53	java/lang/String:<init>	([C)V
    //   4007: invokevirtual 57	java/lang/String:intern	()Ljava/lang/String;
    //   4010: aastore
    //   4011: ldc 239
    //   4013: invokevirtual 49	java/lang/String:toCharArray	()[C
    //   4016: wide
    //   4020: wide
    //   4024: arraylength
    //   4025: wide
    //   4029: iconst_0
    //   4030: wide
    //   4034: wide
    //   4038: wide
    //   4042: if_icmpgt +12040 -> 16082
    //   4045: aload_0
    //   4046: bipush 91
    //   4048: new 43	java/lang/String
    //   4051: dup
    //   4052: wide
    //   4056: invokespecial 53	java/lang/String:<init>	([C)V
    //   4059: invokevirtual 57	java/lang/String:intern	()Ljava/lang/String;
    //   4062: aastore
    //   4063: ldc 241
    //   4065: invokevirtual 49	java/lang/String:toCharArray	()[C
    //   4068: wide
    //   4072: wide
    //   4076: arraylength
    //   4077: wide
    //   4081: iconst_0
    //   4082: wide
    //   4086: wide
    //   4090: wide
    //   4094: if_icmpgt +12108 -> 16202
    //   4097: aload_0
    //   4098: bipush 92
    //   4100: new 43	java/lang/String
    //   4103: dup
    //   4104: wide
    //   4108: invokespecial 53	java/lang/String:<init>	([C)V
    //   4111: invokevirtual 57	java/lang/String:intern	()Ljava/lang/String;
    //   4114: aastore
    //   4115: ldc 243
    //   4117: invokevirtual 49	java/lang/String:toCharArray	()[C
    //   4120: wide
    //   4124: wide
    //   4128: arraylength
    //   4129: wide
    //   4133: iconst_0
    //   4134: wide
    //   4138: wide
    //   4142: wide
    //   4146: if_icmpgt +12176 -> 16322
    //   4149: aload_0
    //   4150: bipush 93
    //   4152: new 43	java/lang/String
    //   4155: dup
    //   4156: wide
    //   4160: invokespecial 53	java/lang/String:<init>	([C)V
    //   4163: invokevirtual 57	java/lang/String:intern	()Ljava/lang/String;
    //   4166: aastore
    //   4167: ldc 245
    //   4169: invokevirtual 49	java/lang/String:toCharArray	()[C
    //   4172: wide
    //   4176: wide
    //   4180: arraylength
    //   4181: wide
    //   4185: iconst_0
    //   4186: wide
    //   4190: wide
    //   4194: wide
    //   4198: if_icmpgt +12244 -> 16442
    //   4201: aload_0
    //   4202: bipush 94
    //   4204: new 43	java/lang/String
    //   4207: dup
    //   4208: wide
    //   4212: invokespecial 53	java/lang/String:<init>	([C)V
    //   4215: invokevirtual 57	java/lang/String:intern	()Ljava/lang/String;
    //   4218: aastore
    //   4219: ldc 247
    //   4221: invokevirtual 49	java/lang/String:toCharArray	()[C
    //   4224: wide
    //   4228: wide
    //   4232: arraylength
    //   4233: wide
    //   4237: iconst_0
    //   4238: wide
    //   4242: wide
    //   4246: wide
    //   4250: if_icmpgt +12312 -> 16562
    //   4253: aload_0
    //   4254: bipush 95
    //   4256: new 43	java/lang/String
    //   4259: dup
    //   4260: wide
    //   4264: invokespecial 53	java/lang/String:<init>	([C)V
    //   4267: invokevirtual 57	java/lang/String:intern	()Ljava/lang/String;
    //   4270: aastore
    //   4271: ldc 249
    //   4273: invokevirtual 49	java/lang/String:toCharArray	()[C
    //   4276: wide
    //   4280: wide
    //   4284: arraylength
    //   4285: wide
    //   4289: iconst_0
    //   4290: wide
    //   4294: wide
    //   4298: wide
    //   4302: if_icmpgt +12380 -> 16682
    //   4305: aload_0
    //   4306: bipush 96
    //   4308: new 43	java/lang/String
    //   4311: dup
    //   4312: wide
    //   4316: invokespecial 53	java/lang/String:<init>	([C)V
    //   4319: invokevirtual 57	java/lang/String:intern	()Ljava/lang/String;
    //   4322: aastore
    //   4323: ldc 251
    //   4325: invokevirtual 49	java/lang/String:toCharArray	()[C
    //   4328: wide
    //   4332: wide
    //   4336: arraylength
    //   4337: wide
    //   4341: iconst_0
    //   4342: wide
    //   4346: wide
    //   4350: wide
    //   4354: if_icmpgt +12448 -> 16802
    //   4357: aload_0
    //   4358: bipush 97
    //   4360: new 43	java/lang/String
    //   4363: dup
    //   4364: wide
    //   4368: invokespecial 53	java/lang/String:<init>	([C)V
    //   4371: invokevirtual 57	java/lang/String:intern	()Ljava/lang/String;
    //   4374: aastore
    //   4375: ldc 253
    //   4377: invokevirtual 49	java/lang/String:toCharArray	()[C
    //   4380: wide
    //   4384: wide
    //   4388: arraylength
    //   4389: wide
    //   4393: iconst_0
    //   4394: wide
    //   4398: wide
    //   4402: wide
    //   4406: if_icmpgt +12516 -> 16922
    //   4409: aload_0
    //   4410: bipush 98
    //   4412: new 43	java/lang/String
    //   4415: dup
    //   4416: wide
    //   4420: invokespecial 53	java/lang/String:<init>	([C)V
    //   4423: invokevirtual 57	java/lang/String:intern	()Ljava/lang/String;
    //   4426: aastore
    //   4427: ldc 255
    //   4429: invokevirtual 49	java/lang/String:toCharArray	()[C
    //   4432: wide
    //   4436: wide
    //   4440: arraylength
    //   4441: wide
    //   4445: iconst_0
    //   4446: wide
    //   4450: wide
    //   4454: wide
    //   4458: if_icmpgt +12584 -> 17042
    //   4461: aload_0
    //   4462: bipush 99
    //   4464: new 43	java/lang/String
    //   4467: dup
    //   4468: wide
    //   4472: invokespecial 53	java/lang/String:<init>	([C)V
    //   4475: invokevirtual 57	java/lang/String:intern	()Ljava/lang/String;
    //   4478: aastore
    //   4479: ldc_w 257
    //   4482: invokevirtual 49	java/lang/String:toCharArray	()[C
    //   4485: wide
    //   4489: wide
    //   4493: arraylength
    //   4494: wide
    //   4498: iconst_0
    //   4499: wide
    //   4503: wide
    //   4507: wide
    //   4511: if_icmpgt +12651 -> 17162
    //   4514: aload_0
    //   4515: bipush 100
    //   4517: new 43	java/lang/String
    //   4520: dup
    //   4521: wide
    //   4525: invokespecial 53	java/lang/String:<init>	([C)V
    //   4528: invokevirtual 57	java/lang/String:intern	()Ljava/lang/String;
    //   4531: aastore
    //   4532: ldc_w 259
    //   4535: invokevirtual 49	java/lang/String:toCharArray	()[C
    //   4538: wide
    //   4542: wide
    //   4546: arraylength
    //   4547: wide
    //   4551: iconst_0
    //   4552: wide
    //   4556: wide
    //   4560: wide
    //   4564: if_icmpgt +12718 -> 17282
    //   4567: aload_0
    //   4568: bipush 101
    //   4570: new 43	java/lang/String
    //   4573: dup
    //   4574: wide
    //   4578: invokespecial 53	java/lang/String:<init>	([C)V
    //   4581: invokevirtual 57	java/lang/String:intern	()Ljava/lang/String;
    //   4584: aastore
    //   4585: ldc_w 261
    //   4588: invokevirtual 49	java/lang/String:toCharArray	()[C
    //   4591: wide
    //   4595: wide
    //   4599: arraylength
    //   4600: wide
    //   4604: iconst_0
    //   4605: wide
    //   4609: wide
    //   4613: wide
    //   4617: if_icmpgt +12785 -> 17402
    //   4620: aload_0
    //   4621: bipush 102
    //   4623: new 43	java/lang/String
    //   4626: dup
    //   4627: wide
    //   4631: invokespecial 53	java/lang/String:<init>	([C)V
    //   4634: invokevirtual 57	java/lang/String:intern	()Ljava/lang/String;
    //   4637: aastore
    //   4638: ldc_w 263
    //   4641: invokevirtual 49	java/lang/String:toCharArray	()[C
    //   4644: wide
    //   4648: wide
    //   4652: arraylength
    //   4653: wide
    //   4657: iconst_0
    //   4658: wide
    //   4662: wide
    //   4666: wide
    //   4670: if_icmpgt +12852 -> 17522
    //   4673: aload_0
    //   4674: bipush 103
    //   4676: new 43	java/lang/String
    //   4679: dup
    //   4680: wide
    //   4684: invokespecial 53	java/lang/String:<init>	([C)V
    //   4687: invokevirtual 57	java/lang/String:intern	()Ljava/lang/String;
    //   4690: aastore
    //   4691: ldc_w 265
    //   4694: invokevirtual 49	java/lang/String:toCharArray	()[C
    //   4697: wide
    //   4701: wide
    //   4705: arraylength
    //   4706: wide
    //   4710: iconst_0
    //   4711: wide
    //   4715: wide
    //   4719: wide
    //   4723: if_icmpgt +12919 -> 17642
    //   4726: aload_0
    //   4727: bipush 104
    //   4729: new 43	java/lang/String
    //   4732: dup
    //   4733: wide
    //   4737: invokespecial 53	java/lang/String:<init>	([C)V
    //   4740: invokevirtual 57	java/lang/String:intern	()Ljava/lang/String;
    //   4743: aastore
    //   4744: ldc_w 267
    //   4747: invokevirtual 49	java/lang/String:toCharArray	()[C
    //   4750: wide
    //   4754: wide
    //   4758: arraylength
    //   4759: wide
    //   4763: iconst_0
    //   4764: wide
    //   4768: wide
    //   4772: wide
    //   4776: if_icmpgt +12986 -> 17762
    //   4779: aload_0
    //   4780: bipush 105
    //   4782: new 43	java/lang/String
    //   4785: dup
    //   4786: wide
    //   4790: invokespecial 53	java/lang/String:<init>	([C)V
    //   4793: invokevirtual 57	java/lang/String:intern	()Ljava/lang/String;
    //   4796: aastore
    //   4797: ldc_w 269
    //   4800: invokevirtual 49	java/lang/String:toCharArray	()[C
    //   4803: wide
    //   4807: wide
    //   4811: arraylength
    //   4812: wide
    //   4816: iconst_0
    //   4817: wide
    //   4821: wide
    //   4825: wide
    //   4829: if_icmpgt +13053 -> 17882
    //   4832: aload_0
    //   4833: bipush 106
    //   4835: new 43	java/lang/String
    //   4838: dup
    //   4839: wide
    //   4843: invokespecial 53	java/lang/String:<init>	([C)V
    //   4846: invokevirtual 57	java/lang/String:intern	()Ljava/lang/String;
    //   4849: aastore
    //   4850: ldc_w 271
    //   4853: invokevirtual 49	java/lang/String:toCharArray	()[C
    //   4856: wide
    //   4860: wide
    //   4864: arraylength
    //   4865: wide
    //   4869: iconst_0
    //   4870: wide
    //   4874: wide
    //   4878: wide
    //   4882: if_icmpgt +13120 -> 18002
    //   4885: aload_0
    //   4886: bipush 107
    //   4888: new 43	java/lang/String
    //   4891: dup
    //   4892: wide
    //   4896: invokespecial 53	java/lang/String:<init>	([C)V
    //   4899: invokevirtual 57	java/lang/String:intern	()Ljava/lang/String;
    //   4902: aastore
    //   4903: ldc_w 273
    //   4906: invokevirtual 49	java/lang/String:toCharArray	()[C
    //   4909: wide
    //   4913: wide
    //   4917: arraylength
    //   4918: wide
    //   4922: iconst_0
    //   4923: wide
    //   4927: wide
    //   4931: wide
    //   4935: if_icmpgt +13187 -> 18122
    //   4938: aload_0
    //   4939: bipush 108
    //   4941: new 43	java/lang/String
    //   4944: dup
    //   4945: wide
    //   4949: invokespecial 53	java/lang/String:<init>	([C)V
    //   4952: invokevirtual 57	java/lang/String:intern	()Ljava/lang/String;
    //   4955: aastore
    //   4956: ldc_w 275
    //   4959: invokevirtual 49	java/lang/String:toCharArray	()[C
    //   4962: wide
    //   4966: wide
    //   4970: arraylength
    //   4971: wide
    //   4975: iconst_0
    //   4976: wide
    //   4980: wide
    //   4984: wide
    //   4988: if_icmpgt +13254 -> 18242
    //   4991: aload_0
    //   4992: bipush 109
    //   4994: new 43	java/lang/String
    //   4997: dup
    //   4998: wide
    //   5002: invokespecial 53	java/lang/String:<init>	([C)V
    //   5005: invokevirtual 57	java/lang/String:intern	()Ljava/lang/String;
    //   5008: aastore
    //   5009: ldc_w 277
    //   5012: invokevirtual 49	java/lang/String:toCharArray	()[C
    //   5015: wide
    //   5019: wide
    //   5023: arraylength
    //   5024: wide
    //   5028: iconst_0
    //   5029: wide
    //   5033: wide
    //   5037: wide
    //   5041: if_icmpgt +13321 -> 18362
    //   5044: aload_0
    //   5045: bipush 110
    //   5047: new 43	java/lang/String
    //   5050: dup
    //   5051: wide
    //   5055: invokespecial 53	java/lang/String:<init>	([C)V
    //   5058: invokevirtual 57	java/lang/String:intern	()Ljava/lang/String;
    //   5061: aastore
    //   5062: ldc_w 279
    //   5065: invokevirtual 49	java/lang/String:toCharArray	()[C
    //   5068: wide
    //   5072: wide
    //   5076: arraylength
    //   5077: wide
    //   5081: iconst_0
    //   5082: wide
    //   5086: wide
    //   5090: wide
    //   5094: if_icmpgt +13388 -> 18482
    //   5097: aload_0
    //   5098: bipush 111
    //   5100: new 43	java/lang/String
    //   5103: dup
    //   5104: wide
    //   5108: invokespecial 53	java/lang/String:<init>	([C)V
    //   5111: invokevirtual 57	java/lang/String:intern	()Ljava/lang/String;
    //   5114: aastore
    //   5115: ldc_w 281
    //   5118: invokevirtual 49	java/lang/String:toCharArray	()[C
    //   5121: wide
    //   5125: wide
    //   5129: arraylength
    //   5130: wide
    //   5134: iconst_0
    //   5135: wide
    //   5139: wide
    //   5143: wide
    //   5147: if_icmpgt +13455 -> 18602
    //   5150: aload_0
    //   5151: bipush 112
    //   5153: new 43	java/lang/String
    //   5156: dup
    //   5157: wide
    //   5161: invokespecial 53	java/lang/String:<init>	([C)V
    //   5164: invokevirtual 57	java/lang/String:intern	()Ljava/lang/String;
    //   5167: aastore
    //   5168: ldc_w 283
    //   5171: invokevirtual 49	java/lang/String:toCharArray	()[C
    //   5174: wide
    //   5178: wide
    //   5182: arraylength
    //   5183: wide
    //   5187: iconst_0
    //   5188: wide
    //   5192: wide
    //   5196: wide
    //   5200: if_icmpgt +13522 -> 18722
    //   5203: aload_0
    //   5204: bipush 113
    //   5206: new 43	java/lang/String
    //   5209: dup
    //   5210: wide
    //   5214: invokespecial 53	java/lang/String:<init>	([C)V
    //   5217: invokevirtual 57	java/lang/String:intern	()Ljava/lang/String;
    //   5220: aastore
    //   5221: ldc_w 285
    //   5224: invokevirtual 49	java/lang/String:toCharArray	()[C
    //   5227: wide
    //   5231: wide
    //   5235: arraylength
    //   5236: wide
    //   5240: iconst_0
    //   5241: wide
    //   5245: wide
    //   5249: wide
    //   5253: if_icmpgt +13589 -> 18842
    //   5256: aload_0
    //   5257: bipush 114
    //   5259: new 43	java/lang/String
    //   5262: dup
    //   5263: wide
    //   5267: invokespecial 53	java/lang/String:<init>	([C)V
    //   5270: invokevirtual 57	java/lang/String:intern	()Ljava/lang/String;
    //   5273: aastore
    //   5274: ldc_w 287
    //   5277: invokevirtual 49	java/lang/String:toCharArray	()[C
    //   5280: wide
    //   5284: wide
    //   5288: arraylength
    //   5289: wide
    //   5293: iconst_0
    //   5294: wide
    //   5298: wide
    //   5302: wide
    //   5306: if_icmpgt +13656 -> 18962
    //   5309: aload_0
    //   5310: bipush 115
    //   5312: new 43	java/lang/String
    //   5315: dup
    //   5316: wide
    //   5320: invokespecial 53	java/lang/String:<init>	([C)V
    //   5323: invokevirtual 57	java/lang/String:intern	()Ljava/lang/String;
    //   5326: aastore
    //   5327: ldc_w 289
    //   5330: invokevirtual 49	java/lang/String:toCharArray	()[C
    //   5333: wide
    //   5337: wide
    //   5341: arraylength
    //   5342: wide
    //   5346: iconst_0
    //   5347: wide
    //   5351: wide
    //   5355: wide
    //   5359: if_icmpgt +13723 -> 19082
    //   5362: aload_0
    //   5363: bipush 116
    //   5365: new 43	java/lang/String
    //   5368: dup
    //   5369: wide
    //   5373: invokespecial 53	java/lang/String:<init>	([C)V
    //   5376: invokevirtual 57	java/lang/String:intern	()Ljava/lang/String;
    //   5379: aastore
    //   5380: ldc_w 291
    //   5383: invokevirtual 49	java/lang/String:toCharArray	()[C
    //   5386: wide
    //   5390: wide
    //   5394: arraylength
    //   5395: wide
    //   5399: iconst_0
    //   5400: wide
    //   5404: wide
    //   5408: wide
    //   5412: if_icmpgt +13790 -> 19202
    //   5415: aload_0
    //   5416: bipush 117
    //   5418: new 43	java/lang/String
    //   5421: dup
    //   5422: wide
    //   5426: invokespecial 53	java/lang/String:<init>	([C)V
    //   5429: invokevirtual 57	java/lang/String:intern	()Ljava/lang/String;
    //   5432: aastore
    //   5433: ldc_w 293
    //   5436: invokevirtual 49	java/lang/String:toCharArray	()[C
    //   5439: wide
    //   5443: wide
    //   5447: arraylength
    //   5448: wide
    //   5452: iconst_0
    //   5453: wide
    //   5457: wide
    //   5461: wide
    //   5465: if_icmpgt +13857 -> 19322
    //   5468: aload_0
    //   5469: bipush 118
    //   5471: new 43	java/lang/String
    //   5474: dup
    //   5475: wide
    //   5479: invokespecial 53	java/lang/String:<init>	([C)V
    //   5482: invokevirtual 57	java/lang/String:intern	()Ljava/lang/String;
    //   5485: aastore
    //   5486: aload_0
    //   5487: putstatic 295	o:A	[Ljava/lang/String;
    //   5490: bipush 50
    //   5492: anewarray 43	java/lang/String
    //   5495: wide
    //   5499: wide
    //   5503: iconst_0
    //   5504: getstatic 295	o:A	[Ljava/lang/String;
    //   5507: bipush 96
    //   5509: aaload
    //   5510: aastore
    //   5511: wide
    //   5515: iconst_1
    //   5516: getstatic 295	o:A	[Ljava/lang/String;
    //   5519: bipush 102
    //   5521: aaload
    //   5522: aastore
    //   5523: wide
    //   5527: iconst_2
    //   5528: getstatic 295	o:A	[Ljava/lang/String;
    //   5531: bipush 101
    //   5533: aaload
    //   5534: aastore
    //   5535: wide
    //   5539: iconst_3
    //   5540: getstatic 295	o:A	[Ljava/lang/String;
    //   5543: bipush 92
    //   5545: aaload
    //   5546: aastore
    //   5547: wide
    //   5551: iconst_4
    //   5552: getstatic 295	o:A	[Ljava/lang/String;
    //   5555: bipush 68
    //   5557: aaload
    //   5558: aastore
    //   5559: wide
    //   5563: iconst_5
    //   5564: getstatic 295	o:A	[Ljava/lang/String;
    //   5567: bipush 110
    //   5569: aaload
    //   5570: aastore
    //   5571: wide
    //   5575: bipush 6
    //   5577: getstatic 295	o:A	[Ljava/lang/String;
    //   5580: bipush 65
    //   5582: aaload
    //   5583: aastore
    //   5584: wide
    //   5588: bipush 7
    //   5590: getstatic 295	o:A	[Ljava/lang/String;
    //   5593: bipush 94
    //   5595: aaload
    //   5596: aastore
    //   5597: wide
    //   5601: bipush 8
    //   5603: getstatic 295	o:A	[Ljava/lang/String;
    //   5606: bipush 108
    //   5608: aaload
    //   5609: aastore
    //   5610: wide
    //   5614: bipush 9
    //   5616: getstatic 295	o:A	[Ljava/lang/String;
    //   5619: bipush 69
    //   5621: aaload
    //   5622: aastore
    //   5623: wide
    //   5627: bipush 10
    //   5629: getstatic 295	o:A	[Ljava/lang/String;
    //   5632: bipush 61
    //   5634: aaload
    //   5635: aastore
    //   5636: wide
    //   5640: bipush 11
    //   5642: getstatic 295	o:A	[Ljava/lang/String;
    //   5645: bipush 85
    //   5647: aaload
    //   5648: aastore
    //   5649: wide
    //   5653: bipush 12
    //   5655: getstatic 295	o:A	[Ljava/lang/String;
    //   5658: bipush 107
    //   5660: aaload
    //   5661: aastore
    //   5662: wide
    //   5666: bipush 13
    //   5668: getstatic 295	o:A	[Ljava/lang/String;
    //   5671: bipush 48
    //   5673: aaload
    //   5674: aastore
    //   5675: wide
    //   5679: bipush 14
    //   5681: getstatic 295	o:A	[Ljava/lang/String;
    //   5684: bipush 51
    //   5686: aaload
    //   5687: aastore
    //   5688: wide
    //   5692: bipush 15
    //   5694: getstatic 295	o:A	[Ljava/lang/String;
    //   5697: bipush 87
    //   5699: aaload
    //   5700: aastore
    //   5701: wide
    //   5705: bipush 16
    //   5707: getstatic 295	o:A	[Ljava/lang/String;
    //   5710: bipush 86
    //   5712: aaload
    //   5713: aastore
    //   5714: wide
    //   5718: bipush 17
    //   5720: getstatic 295	o:A	[Ljava/lang/String;
    //   5723: bipush 67
    //   5725: aaload
    //   5726: aastore
    //   5727: wide
    //   5731: bipush 18
    //   5733: getstatic 295	o:A	[Ljava/lang/String;
    //   5736: bipush 75
    //   5738: aaload
    //   5739: aastore
    //   5740: wide
    //   5744: bipush 19
    //   5746: getstatic 295	o:A	[Ljava/lang/String;
    //   5749: bipush 112
    //   5751: aaload
    //   5752: aastore
    //   5753: wide
    //   5757: bipush 20
    //   5759: getstatic 295	o:A	[Ljava/lang/String;
    //   5762: bipush 118
    //   5764: aaload
    //   5765: aastore
    //   5766: wide
    //   5770: bipush 21
    //   5772: getstatic 295	o:A	[Ljava/lang/String;
    //   5775: bipush 83
    //   5777: aaload
    //   5778: aastore
    //   5779: wide
    //   5783: bipush 22
    //   5785: getstatic 295	o:A	[Ljava/lang/String;
    //   5788: bipush 84
    //   5790: aaload
    //   5791: aastore
    //   5792: wide
    //   5796: bipush 23
    //   5798: getstatic 295	o:A	[Ljava/lang/String;
    //   5801: bipush 116
    //   5803: aaload
    //   5804: aastore
    //   5805: wide
    //   5809: bipush 24
    //   5811: getstatic 295	o:A	[Ljava/lang/String;
    //   5814: bipush 52
    //   5816: aaload
    //   5817: aastore
    //   5818: wide
    //   5822: bipush 25
    //   5824: getstatic 295	o:A	[Ljava/lang/String;
    //   5827: bipush 72
    //   5829: aaload
    //   5830: aastore
    //   5831: wide
    //   5835: bipush 26
    //   5837: getstatic 295	o:A	[Ljava/lang/String;
    //   5840: bipush 80
    //   5842: aaload
    //   5843: aastore
    //   5844: wide
    //   5848: bipush 27
    //   5850: getstatic 295	o:A	[Ljava/lang/String;
    //   5853: bipush 89
    //   5855: aaload
    //   5856: aastore
    //   5857: wide
    //   5861: bipush 28
    //   5863: getstatic 295	o:A	[Ljava/lang/String;
    //   5866: bipush 98
    //   5868: aaload
    //   5869: aastore
    //   5870: wide
    //   5874: bipush 29
    //   5876: getstatic 295	o:A	[Ljava/lang/String;
    //   5879: bipush 64
    //   5881: aaload
    //   5882: aastore
    //   5883: wide
    //   5887: bipush 30
    //   5889: getstatic 295	o:A	[Ljava/lang/String;
    //   5892: bipush 79
    //   5894: aaload
    //   5895: aastore
    //   5896: wide
    //   5900: bipush 31
    //   5902: getstatic 295	o:A	[Ljava/lang/String;
    //   5905: bipush 73
    //   5907: aaload
    //   5908: aastore
    //   5909: wide
    //   5913: bipush 32
    //   5915: getstatic 295	o:A	[Ljava/lang/String;
    //   5918: bipush 55
    //   5920: aaload
    //   5921: aastore
    //   5922: wide
    //   5926: bipush 33
    //   5928: getstatic 295	o:A	[Ljava/lang/String;
    //   5931: bipush 115
    //   5933: aaload
    //   5934: aastore
    //   5935: wide
    //   5939: bipush 34
    //   5941: getstatic 295	o:A	[Ljava/lang/String;
    //   5944: bipush 93
    //   5946: aaload
    //   5947: aastore
    //   5948: wide
    //   5952: bipush 35
    //   5954: getstatic 295	o:A	[Ljava/lang/String;
    //   5957: bipush 111
    //   5959: aaload
    //   5960: aastore
    //   5961: wide
    //   5965: bipush 36
    //   5967: getstatic 295	o:A	[Ljava/lang/String;
    //   5970: bipush 58
    //   5972: aaload
    //   5973: aastore
    //   5974: wide
    //   5978: bipush 37
    //   5980: getstatic 295	o:A	[Ljava/lang/String;
    //   5983: bipush 78
    //   5985: aaload
    //   5986: aastore
    //   5987: wide
    //   5991: bipush 38
    //   5993: getstatic 295	o:A	[Ljava/lang/String;
    //   5996: bipush 56
    //   5998: aaload
    //   5999: aastore
    //   6000: wide
    //   6004: bipush 39
    //   6006: getstatic 295	o:A	[Ljava/lang/String;
    //   6009: bipush 50
    //   6011: aaload
    //   6012: aastore
    //   6013: wide
    //   6017: bipush 40
    //   6019: getstatic 295	o:A	[Ljava/lang/String;
    //   6022: bipush 59
    //   6024: aaload
    //   6025: aastore
    //   6026: wide
    //   6030: bipush 41
    //   6032: getstatic 295	o:A	[Ljava/lang/String;
    //   6035: bipush 106
    //   6037: aaload
    //   6038: aastore
    //   6039: wide
    //   6043: bipush 42
    //   6045: getstatic 295	o:A	[Ljava/lang/String;
    //   6048: bipush 66
    //   6050: aaload
    //   6051: aastore
    //   6052: wide
    //   6056: bipush 43
    //   6058: getstatic 295	o:A	[Ljava/lang/String;
    //   6061: bipush 82
    //   6063: aaload
    //   6064: aastore
    //   6065: wide
    //   6069: bipush 44
    //   6071: getstatic 295	o:A	[Ljava/lang/String;
    //   6074: bipush 117
    //   6076: aaload
    //   6077: aastore
    //   6078: wide
    //   6082: bipush 45
    //   6084: getstatic 295	o:A	[Ljava/lang/String;
    //   6087: bipush 95
    //   6089: aaload
    //   6090: aastore
    //   6091: wide
    //   6095: bipush 46
    //   6097: getstatic 295	o:A	[Ljava/lang/String;
    //   6100: bipush 77
    //   6102: aaload
    //   6103: aastore
    //   6104: wide
    //   6108: bipush 47
    //   6110: getstatic 295	o:A	[Ljava/lang/String;
    //   6113: bipush 53
    //   6115: aaload
    //   6116: aastore
    //   6117: wide
    //   6121: bipush 48
    //   6123: getstatic 295	o:A	[Ljava/lang/String;
    //   6126: bipush 71
    //   6128: aaload
    //   6129: aastore
    //   6130: wide
    //   6134: bipush 49
    //   6136: getstatic 295	o:A	[Ljava/lang/String;
    //   6139: bipush 114
    //   6141: aaload
    //   6142: aastore
    //   6143: new 297	java/util/HashSet
    //   6146: dup
    //   6147: wide
    //   6151: invokestatic 303	java/util/Arrays:asList	([Ljava/lang/Object;)Ljava/util/List;
    //   6154: invokespecial 306	java/util/HashSet:<init>	(Ljava/util/Collection;)V
    //   6157: putstatic 308	o:a	Ljava/util/HashSet;
    //   6160: iconst_4
    //   6161: anewarray 43	java/lang/String
    //   6164: wide
    //   6168: wide
    //   6172: iconst_0
    //   6173: getstatic 295	o:A	[Ljava/lang/String;
    //   6176: bipush 49
    //   6178: aaload
    //   6179: aastore
    //   6180: wide
    //   6184: iconst_1
    //   6185: getstatic 295	o:A	[Ljava/lang/String;
    //   6188: bipush 90
    //   6190: aaload
    //   6191: aastore
    //   6192: wide
    //   6196: iconst_2
    //   6197: getstatic 295	o:A	[Ljava/lang/String;
    //   6200: bipush 105
    //   6202: aaload
    //   6203: aastore
    //   6204: wide
    //   6208: iconst_3
    //   6209: getstatic 295	o:A	[Ljava/lang/String;
    //   6212: bipush 54
    //   6214: aaload
    //   6215: aastore
    //   6216: new 297	java/util/HashSet
    //   6219: dup
    //   6220: wide
    //   6224: invokestatic 303	java/util/Arrays:asList	([Ljava/lang/Object;)Ljava/util/List;
    //   6227: invokespecial 306	java/util/HashSet:<init>	(Ljava/util/Collection;)V
    //   6230: putstatic 310	o:b	Ljava/util/HashSet;
    //   6233: bipush 20
    //   6235: anewarray 43	java/lang/String
    //   6238: wide
    //   6242: wide
    //   6246: iconst_0
    //   6247: getstatic 295	o:A	[Ljava/lang/String;
    //   6250: bipush 18
    //   6252: aaload
    //   6253: aastore
    //   6254: wide
    //   6258: iconst_1
    //   6259: getstatic 295	o:A	[Ljava/lang/String;
    //   6262: bipush 103
    //   6264: aaload
    //   6265: aastore
    //   6266: wide
    //   6270: iconst_2
    //   6271: getstatic 295	o:A	[Ljava/lang/String;
    //   6274: bipush 81
    //   6276: aaload
    //   6277: aastore
    //   6278: wide
    //   6282: iconst_3
    //   6283: getstatic 295	o:A	[Ljava/lang/String;
    //   6286: bipush 74
    //   6288: aaload
    //   6289: aastore
    //   6290: wide
    //   6294: iconst_4
    //   6295: getstatic 295	o:A	[Ljava/lang/String;
    //   6298: bipush 100
    //   6300: aaload
    //   6301: aastore
    //   6302: wide
    //   6306: iconst_5
    //   6307: getstatic 295	o:A	[Ljava/lang/String;
    //   6310: bipush 88
    //   6312: aaload
    //   6313: aastore
    //   6314: wide
    //   6318: bipush 6
    //   6320: getstatic 295	o:A	[Ljava/lang/String;
    //   6323: bipush 57
    //   6325: aaload
    //   6326: aastore
    //   6327: wide
    //   6331: bipush 7
    //   6333: getstatic 295	o:A	[Ljava/lang/String;
    //   6336: bipush 35
    //   6338: aaload
    //   6339: aastore
    //   6340: wide
    //   6344: bipush 8
    //   6346: getstatic 295	o:A	[Ljava/lang/String;
    //   6349: bipush 70
    //   6351: aaload
    //   6352: aastore
    //   6353: wide
    //   6357: bipush 9
    //   6359: getstatic 295	o:A	[Ljava/lang/String;
    //   6362: bipush 104
    //   6364: aaload
    //   6365: aastore
    //   6366: wide
    //   6370: bipush 10
    //   6372: getstatic 295	o:A	[Ljava/lang/String;
    //   6375: bipush 97
    //   6377: aaload
    //   6378: aastore
    //   6379: wide
    //   6383: bipush 11
    //   6385: getstatic 295	o:A	[Ljava/lang/String;
    //   6388: bipush 99
    //   6390: aaload
    //   6391: aastore
    //   6392: wide
    //   6396: bipush 12
    //   6398: getstatic 295	o:A	[Ljava/lang/String;
    //   6401: bipush 109
    //   6403: aaload
    //   6404: aastore
    //   6405: wide
    //   6409: bipush 13
    //   6411: getstatic 295	o:A	[Ljava/lang/String;
    //   6414: bipush 90
    //   6416: aaload
    //   6417: aastore
    //   6418: wide
    //   6422: bipush 14
    //   6424: getstatic 295	o:A	[Ljava/lang/String;
    //   6427: bipush 76
    //   6429: aaload
    //   6430: aastore
    //   6431: wide
    //   6435: bipush 15
    //   6437: getstatic 295	o:A	[Ljava/lang/String;
    //   6440: bipush 63
    //   6442: aaload
    //   6443: aastore
    //   6444: wide
    //   6448: bipush 16
    //   6450: getstatic 295	o:A	[Ljava/lang/String;
    //   6453: bipush 91
    //   6455: aaload
    //   6456: aastore
    //   6457: wide
    //   6461: bipush 17
    //   6463: getstatic 295	o:A	[Ljava/lang/String;
    //   6466: bipush 62
    //   6468: aaload
    //   6469: aastore
    //   6470: wide
    //   6474: bipush 18
    //   6476: getstatic 295	o:A	[Ljava/lang/String;
    //   6479: bipush 113
    //   6481: aaload
    //   6482: aastore
    //   6483: wide
    //   6487: bipush 19
    //   6489: getstatic 295	o:A	[Ljava/lang/String;
    //   6492: bipush 60
    //   6494: aaload
    //   6495: aastore
    //   6496: new 297	java/util/HashSet
    //   6499: dup
    //   6500: wide
    //   6504: invokestatic 303	java/util/Arrays:asList	([Ljava/lang/Object;)Ljava/util/List;
    //   6507: invokespecial 306	java/util/HashSet:<init>	(Ljava/util/Collection;)V
    //   6510: putstatic 312	o:c	Ljava/util/HashSet;
    //   6513: iconst_5
    //   6514: anewarray 43	java/lang/String
    //   6517: wide
    //   6521: wide
    //   6525: iconst_0
    //   6526: getstatic 295	o:A	[Ljava/lang/String;
    //   6529: bipush 6
    //   6531: aaload
    //   6532: aastore
    //   6533: wide
    //   6537: iconst_1
    //   6538: getstatic 295	o:A	[Ljava/lang/String;
    //   6541: iconst_2
    //   6542: aaload
    //   6543: aastore
    //   6544: wide
    //   6548: iconst_2
    //   6549: getstatic 295	o:A	[Ljava/lang/String;
    //   6552: iconst_4
    //   6553: aaload
    //   6554: aastore
    //   6555: wide
    //   6559: iconst_3
    //   6560: getstatic 295	o:A	[Ljava/lang/String;
    //   6563: iconst_0
    //   6564: aaload
    //   6565: aastore
    //   6566: wide
    //   6570: iconst_4
    //   6571: ldc_w 314
    //   6574: aastore
    //   6575: new 297	java/util/HashSet
    //   6578: dup
    //   6579: wide
    //   6583: invokestatic 303	java/util/Arrays:asList	([Ljava/lang/Object;)Ljava/util/List;
    //   6586: invokespecial 306	java/util/HashSet:<init>	(Ljava/util/Collection;)V
    //   6589: putstatic 316	o:d	Ljava/util/HashSet;
    //   6592: iconst_0
    //   6593: putstatic 318	o:y	Z
    //   6596: return
    //   6597: aload_1
    //   6598: iload_3
    //   6599: caload
    //   6600: istore 4
    //   6602: iload_3
    //   6603: iconst_5
    //   6604: irem
    //   6605: tableswitch	default:+31 -> 6636, 0:+50->6655, 1:+57->6662, 2:+64->6669, 3:+71->6676
    //   6637: pop
    //   6638: istore 5
    //   6640: aload_1
    //   6641: iload_3
    //   6642: iload 5
    //   6644: iload 4
    //   6646: ixor
    //   6647: i2c
    //   6648: castore
    //   6649: iinc 3 1
    //   6652: goto -6635 -> 17
    //   6655: bipush 77
    //   6657: istore 5
    //   6659: goto -19 -> 6640
    //   6662: bipush 73
    //   6664: istore 5
    //   6666: goto -26 -> 6640
    //   6669: bipush 99
    //   6671: istore 5
    //   6673: goto -33 -> 6640
    //   6676: bipush 59
    //   6678: istore 5
    //   6680: goto -40 -> 6640
    //   6683: aload 6
    //   6685: iload 8
    //   6687: caload
    //   6688: istore 9
    //   6690: iload 8
    //   6692: iconst_5
    //   6693: irem
    //   6694: tableswitch	default:+30 -> 6724, 0:+51->6745, 1:+58->6752, 2:+65->6759, 3:+72->6766
    //   6725: pop
    //   6726: istore 10
    //   6728: aload 6
    //   6730: iload 8
    //   6732: iload 10
    //   6734: iload 9
    //   6736: ixor
    //   6737: i2c
    //   6738: castore
    //   6739: iinc 8 1
    //   6742: goto -6691 -> 51
    //   6745: bipush 77
    //   6747: istore 10
    //   6749: goto -21 -> 6728
    //   6752: bipush 73
    //   6754: istore 10
    //   6756: goto -28 -> 6728
    //   6759: bipush 99
    //   6761: istore 10
    //   6763: goto -35 -> 6728
    //   6766: bipush 59
    //   6768: istore 10
    //   6770: goto -42 -> 6728
    //   6773: aload 11
    //   6775: iload 13
    //   6777: caload
    //   6778: istore 14
    //   6780: iload 13
    //   6782: iconst_5
    //   6783: irem
    //   6784: tableswitch	default:+32 -> 6816, 0:+53->6837, 1:+60->6844, 2:+67->6851, 3:+74->6858
    //   6817: pop
    //   6818: istore 15
    //   6820: aload 11
    //   6822: iload 13
    //   6824: iload 15
    //   6826: iload 14
    //   6828: ixor
    //   6829: i2c
    //   6830: castore
    //   6831: iinc 13 1
    //   6834: goto -6746 -> 88
    //   6837: bipush 77
    //   6839: istore 15
    //   6841: goto -21 -> 6820
    //   6844: bipush 73
    //   6846: istore 15
    //   6848: goto -28 -> 6820
    //   6851: bipush 99
    //   6853: istore 15
    //   6855: goto -35 -> 6820
    //   6858: bipush 59
    //   6860: istore 15
    //   6862: goto -42 -> 6820
    //   6865: aload 16
    //   6867: iload 18
    //   6869: caload
    //   6870: istore 19
    //   6872: iload 18
    //   6874: iconst_5
    //   6875: irem
    //   6876: tableswitch	default:+32 -> 6908, 0:+53->6929, 1:+60->6936, 2:+67->6943, 3:+74->6950
    //   6909: pop
    //   6910: istore 20
    //   6912: aload 16
    //   6914: iload 18
    //   6916: iload 20
    //   6918: iload 19
    //   6920: ixor
    //   6921: i2c
    //   6922: castore
    //   6923: iinc 18 1
    //   6926: goto -6801 -> 125
    //   6929: bipush 77
    //   6931: istore 20
    //   6933: goto -21 -> 6912
    //   6936: bipush 73
    //   6938: istore 20
    //   6940: goto -28 -> 6912
    //   6943: bipush 99
    //   6945: istore 20
    //   6947: goto -35 -> 6912
    //   6950: bipush 59
    //   6952: istore 20
    //   6954: goto -42 -> 6912
    //   6957: aload 21
    //   6959: iload 23
    //   6961: caload
    //   6962: istore 24
    //   6964: iload 23
    //   6966: iconst_5
    //   6967: irem
    //   6968: tableswitch	default:+32 -> 7000, 0:+53->7021, 1:+60->7028, 2:+67->7035, 3:+74->7042
    //   7001: pop
    //   7002: istore 25
    //   7004: aload 21
    //   7006: iload 23
    //   7008: iload 25
    //   7010: iload 24
    //   7012: ixor
    //   7013: i2c
    //   7014: castore
    //   7015: iinc 23 1
    //   7018: goto -6856 -> 162
    //   7021: bipush 77
    //   7023: istore 25
    //   7025: goto -21 -> 7004
    //   7028: bipush 73
    //   7030: istore 25
    //   7032: goto -28 -> 7004
    //   7035: bipush 99
    //   7037: istore 25
    //   7039: goto -35 -> 7004
    //   7042: bipush 59
    //   7044: istore 25
    //   7046: goto -42 -> 7004
    //   7049: aload 26
    //   7051: iload 28
    //   7053: caload
    //   7054: istore 29
    //   7056: iload 28
    //   7058: iconst_5
    //   7059: irem
    //   7060: tableswitch	default:+32 -> 7092, 0:+53->7113, 1:+60->7120, 2:+67->7127, 3:+74->7134
    //   7093: pop
    //   7094: istore 30
    //   7096: aload 26
    //   7098: iload 28
    //   7100: iload 30
    //   7102: iload 29
    //   7104: ixor
    //   7105: i2c
    //   7106: castore
    //   7107: iinc 28 1
    //   7110: goto -6911 -> 199
    //   7113: bipush 77
    //   7115: istore 30
    //   7117: goto -21 -> 7096
    //   7120: bipush 73
    //   7122: istore 30
    //   7124: goto -28 -> 7096
    //   7127: bipush 99
    //   7129: istore 30
    //   7131: goto -35 -> 7096
    //   7134: bipush 59
    //   7136: istore 30
    //   7138: goto -42 -> 7096
    //   7141: aload 31
    //   7143: iload 33
    //   7145: caload
    //   7146: istore 34
    //   7148: iload 33
    //   7150: iconst_5
    //   7151: irem
    //   7152: tableswitch	default:+32 -> 7184, 0:+53->7205, 1:+60->7212, 2:+67->7219, 3:+74->7226
    //   7185: pop
    //   7186: istore 35
    //   7188: aload 31
    //   7190: iload 33
    //   7192: iload 35
    //   7194: iload 34
    //   7196: ixor
    //   7197: i2c
    //   7198: castore
    //   7199: iinc 33 1
    //   7202: goto -6966 -> 236
    //   7205: bipush 77
    //   7207: istore 35
    //   7209: goto -21 -> 7188
    //   7212: bipush 73
    //   7214: istore 35
    //   7216: goto -28 -> 7188
    //   7219: bipush 99
    //   7221: istore 35
    //   7223: goto -35 -> 7188
    //   7226: bipush 59
    //   7228: istore 35
    //   7230: goto -42 -> 7188
    //   7233: aload 36
    //   7235: iload 38
    //   7237: caload
    //   7238: istore 39
    //   7240: iload 38
    //   7242: iconst_5
    //   7243: irem
    //   7244: tableswitch	default:+32 -> 7276, 0:+53->7297, 1:+60->7304, 2:+67->7311, 3:+74->7318
    //   7277: pop
    //   7278: istore 40
    //   7280: aload 36
    //   7282: iload 38
    //   7284: iload 40
    //   7286: iload 39
    //   7288: ixor
    //   7289: i2c
    //   7290: castore
    //   7291: iinc 38 1
    //   7294: goto -7020 -> 274
    //   7297: bipush 77
    //   7299: istore 40
    //   7301: goto -21 -> 7280
    //   7304: bipush 73
    //   7306: istore 40
    //   7308: goto -28 -> 7280
    //   7311: bipush 99
    //   7313: istore 40
    //   7315: goto -35 -> 7280
    //   7318: bipush 59
    //   7320: istore 40
    //   7322: goto -42 -> 7280
    //   7325: aload 41
    //   7327: iload 43
    //   7329: caload
    //   7330: istore 44
    //   7332: iload 43
    //   7334: iconst_5
    //   7335: irem
    //   7336: tableswitch	default:+32 -> 7368, 0:+53->7389, 1:+60->7396, 2:+67->7403, 3:+74->7410
    //   7369: pop
    //   7370: istore 45
    //   7372: aload 41
    //   7374: iload 43
    //   7376: iload 45
    //   7378: iload 44
    //   7380: ixor
    //   7381: i2c
    //   7382: castore
    //   7383: iinc 43 1
    //   7386: goto -7074 -> 312
    //   7389: bipush 77
    //   7391: istore 45
    //   7393: goto -21 -> 7372
    //   7396: bipush 73
    //   7398: istore 45
    //   7400: goto -28 -> 7372
    //   7403: bipush 99
    //   7405: istore 45
    //   7407: goto -35 -> 7372
    //   7410: bipush 59
    //   7412: istore 45
    //   7414: goto -42 -> 7372
    //   7417: aload 46
    //   7419: iload 48
    //   7421: caload
    //   7422: istore 49
    //   7424: iload 48
    //   7426: iconst_5
    //   7427: irem
    //   7428: tableswitch	default:+32 -> 7460, 0:+53->7481, 1:+60->7488, 2:+67->7495, 3:+74->7502
    //   7461: pop
    //   7462: istore 50
    //   7464: aload 46
    //   7466: iload 48
    //   7468: iload 50
    //   7470: iload 49
    //   7472: ixor
    //   7473: i2c
    //   7474: castore
    //   7475: iinc 48 1
    //   7478: goto -7128 -> 350
    //   7481: bipush 77
    //   7483: istore 50
    //   7485: goto -21 -> 7464
    //   7488: bipush 73
    //   7490: istore 50
    //   7492: goto -28 -> 7464
    //   7495: bipush 99
    //   7497: istore 50
    //   7499: goto -35 -> 7464
    //   7502: bipush 59
    //   7504: istore 50
    //   7506: goto -42 -> 7464
    //   7509: aload 51
    //   7511: iload 53
    //   7513: caload
    //   7514: istore 54
    //   7516: iload 53
    //   7518: iconst_5
    //   7519: irem
    //   7520: tableswitch	default:+32 -> 7552, 0:+53->7573, 1:+60->7580, 2:+67->7587, 3:+74->7594
    //   7553: pop
    //   7554: istore 55
    //   7556: aload 51
    //   7558: iload 53
    //   7560: iload 55
    //   7562: iload 54
    //   7564: ixor
    //   7565: i2c
    //   7566: castore
    //   7567: iinc 53 1
    //   7570: goto -7182 -> 388
    //   7573: bipush 77
    //   7575: istore 55
    //   7577: goto -21 -> 7556
    //   7580: bipush 73
    //   7582: istore 55
    //   7584: goto -28 -> 7556
    //   7587: bipush 99
    //   7589: istore 55
    //   7591: goto -35 -> 7556
    //   7594: bipush 59
    //   7596: istore 55
    //   7598: goto -42 -> 7556
    //   7601: aload 56
    //   7603: iload 58
    //   7605: caload
    //   7606: istore 59
    //   7608: iload 58
    //   7610: iconst_5
    //   7611: irem
    //   7612: tableswitch	default:+32 -> 7644, 0:+53->7665, 1:+60->7672, 2:+67->7679, 3:+74->7686
    //   7645: pop
    //   7646: istore 60
    //   7648: aload 56
    //   7650: iload 58
    //   7652: iload 60
    //   7654: iload 59
    //   7656: ixor
    //   7657: i2c
    //   7658: castore
    //   7659: iinc 58 1
    //   7662: goto -7236 -> 426
    //   7665: bipush 77
    //   7667: istore 60
    //   7669: goto -21 -> 7648
    //   7672: bipush 73
    //   7674: istore 60
    //   7676: goto -28 -> 7648
    //   7679: bipush 99
    //   7681: istore 60
    //   7683: goto -35 -> 7648
    //   7686: bipush 59
    //   7688: istore 60
    //   7690: goto -42 -> 7648
    //   7693: aload 61
    //   7695: iload 63
    //   7697: caload
    //   7698: istore 64
    //   7700: iload 63
    //   7702: iconst_5
    //   7703: irem
    //   7704: tableswitch	default:+32 -> 7736, 0:+53->7757, 1:+60->7764, 2:+67->7771, 3:+74->7778
    //   7737: pop
    //   7738: istore 65
    //   7740: aload 61
    //   7742: iload 63
    //   7744: iload 65
    //   7746: iload 64
    //   7748: ixor
    //   7749: i2c
    //   7750: castore
    //   7751: iinc 63 1
    //   7754: goto -7290 -> 464
    //   7757: bipush 77
    //   7759: istore 65
    //   7761: goto -21 -> 7740
    //   7764: bipush 73
    //   7766: istore 65
    //   7768: goto -28 -> 7740
    //   7771: bipush 99
    //   7773: istore 65
    //   7775: goto -35 -> 7740
    //   7778: bipush 59
    //   7780: istore 65
    //   7782: goto -42 -> 7740
    //   7785: aload 66
    //   7787: iload 68
    //   7789: caload
    //   7790: istore 69
    //   7792: iload 68
    //   7794: iconst_5
    //   7795: irem
    //   7796: tableswitch	default:+32 -> 7828, 0:+53->7849, 1:+60->7856, 2:+67->7863, 3:+74->7870
    //   7829: pop
    //   7830: istore 70
    //   7832: aload 66
    //   7834: iload 68
    //   7836: iload 70
    //   7838: iload 69
    //   7840: ixor
    //   7841: i2c
    //   7842: castore
    //   7843: iinc 68 1
    //   7846: goto -7344 -> 502
    //   7849: bipush 77
    //   7851: istore 70
    //   7853: goto -21 -> 7832
    //   7856: bipush 73
    //   7858: istore 70
    //   7860: goto -28 -> 7832
    //   7863: bipush 99
    //   7865: istore 70
    //   7867: goto -35 -> 7832
    //   7870: bipush 59
    //   7872: istore 70
    //   7874: goto -42 -> 7832
    //   7877: aload 71
    //   7879: iload 73
    //   7881: caload
    //   7882: istore 74
    //   7884: iload 73
    //   7886: iconst_5
    //   7887: irem
    //   7888: tableswitch	default:+32 -> 7920, 0:+53->7941, 1:+60->7948, 2:+67->7955, 3:+74->7962
    //   7921: pop
    //   7922: istore 75
    //   7924: aload 71
    //   7926: iload 73
    //   7928: iload 75
    //   7930: iload 74
    //   7932: ixor
    //   7933: i2c
    //   7934: castore
    //   7935: iinc 73 1
    //   7938: goto -7398 -> 540
    //   7941: bipush 77
    //   7943: istore 75
    //   7945: goto -21 -> 7924
    //   7948: bipush 73
    //   7950: istore 75
    //   7952: goto -28 -> 7924
    //   7955: bipush 99
    //   7957: istore 75
    //   7959: goto -35 -> 7924
    //   7962: bipush 59
    //   7964: istore 75
    //   7966: goto -42 -> 7924
    //   7969: aload 76
    //   7971: iload 78
    //   7973: caload
    //   7974: istore 79
    //   7976: iload 78
    //   7978: iconst_5
    //   7979: irem
    //   7980: tableswitch	default:+32 -> 8012, 0:+53->8033, 1:+60->8040, 2:+67->8047, 3:+74->8054
    //   8013: pop
    //   8014: istore 80
    //   8016: aload 76
    //   8018: iload 78
    //   8020: iload 80
    //   8022: iload 79
    //   8024: ixor
    //   8025: i2c
    //   8026: castore
    //   8027: iinc 78 1
    //   8030: goto -7452 -> 578
    //   8033: bipush 77
    //   8035: istore 80
    //   8037: goto -21 -> 8016
    //   8040: bipush 73
    //   8042: istore 80
    //   8044: goto -28 -> 8016
    //   8047: bipush 99
    //   8049: istore 80
    //   8051: goto -35 -> 8016
    //   8054: bipush 59
    //   8056: istore 80
    //   8058: goto -42 -> 8016
    //   8061: aload 81
    //   8063: iload 83
    //   8065: caload
    //   8066: istore 84
    //   8068: iload 83
    //   8070: iconst_5
    //   8071: irem
    //   8072: tableswitch	default:+32 -> 8104, 0:+53->8125, 1:+60->8132, 2:+67->8139, 3:+74->8146
    //   8105: pop
    //   8106: istore 85
    //   8108: aload 81
    //   8110: iload 83
    //   8112: iload 85
    //   8114: iload 84
    //   8116: ixor
    //   8117: i2c
    //   8118: castore
    //   8119: iinc 83 1
    //   8122: goto -7506 -> 616
    //   8125: bipush 77
    //   8127: istore 85
    //   8129: goto -21 -> 8108
    //   8132: bipush 73
    //   8134: istore 85
    //   8136: goto -28 -> 8108
    //   8139: bipush 99
    //   8141: istore 85
    //   8143: goto -35 -> 8108
    //   8146: bipush 59
    //   8148: istore 85
    //   8150: goto -42 -> 8108
    //   8153: aload 86
    //   8155: iload 88
    //   8157: caload
    //   8158: istore 89
    //   8160: iload 88
    //   8162: iconst_5
    //   8163: irem
    //   8164: tableswitch	default:+32 -> 8196, 0:+53->8217, 1:+60->8224, 2:+67->8231, 3:+74->8238
    //   8197: pop
    //   8198: istore 90
    //   8200: aload 86
    //   8202: iload 88
    //   8204: iload 90
    //   8206: iload 89
    //   8208: ixor
    //   8209: i2c
    //   8210: castore
    //   8211: iinc 88 1
    //   8214: goto -7560 -> 654
    //   8217: bipush 77
    //   8219: istore 90
    //   8221: goto -21 -> 8200
    //   8224: bipush 73
    //   8226: istore 90
    //   8228: goto -28 -> 8200
    //   8231: bipush 99
    //   8233: istore 90
    //   8235: goto -35 -> 8200
    //   8238: bipush 59
    //   8240: istore 90
    //   8242: goto -42 -> 8200
    //   8245: aload 91
    //   8247: iload 93
    //   8249: caload
    //   8250: istore 94
    //   8252: iload 93
    //   8254: iconst_5
    //   8255: irem
    //   8256: tableswitch	default:+32 -> 8288, 0:+53->8309, 1:+60->8316, 2:+67->8323, 3:+74->8330
    //   8289: pop
    //   8290: istore 95
    //   8292: aload 91
    //   8294: iload 93
    //   8296: iload 95
    //   8298: iload 94
    //   8300: ixor
    //   8301: i2c
    //   8302: castore
    //   8303: iinc 93 1
    //   8306: goto -7614 -> 692
    //   8309: bipush 77
    //   8311: istore 95
    //   8313: goto -21 -> 8292
    //   8316: bipush 73
    //   8318: istore 95
    //   8320: goto -28 -> 8292
    //   8323: bipush 99
    //   8325: istore 95
    //   8327: goto -35 -> 8292
    //   8330: bipush 59
    //   8332: istore 95
    //   8334: goto -42 -> 8292
    //   8337: aload 96
    //   8339: iload 98
    //   8341: caload
    //   8342: istore 99
    //   8344: iload 98
    //   8346: iconst_5
    //   8347: irem
    //   8348: tableswitch	default:+32 -> 8380, 0:+53->8401, 1:+60->8408, 2:+67->8415, 3:+74->8422
    //   8381: pop
    //   8382: istore 100
    //   8384: aload 96
    //   8386: iload 98
    //   8388: iload 100
    //   8390: iload 99
    //   8392: ixor
    //   8393: i2c
    //   8394: castore
    //   8395: iinc 98 1
    //   8398: goto -7668 -> 730
    //   8401: bipush 77
    //   8403: istore 100
    //   8405: goto -21 -> 8384
    //   8408: bipush 73
    //   8410: istore 100
    //   8412: goto -28 -> 8384
    //   8415: bipush 99
    //   8417: istore 100
    //   8419: goto -35 -> 8384
    //   8422: bipush 59
    //   8424: istore 100
    //   8426: goto -42 -> 8384
    //   8429: aload 101
    //   8431: iload 103
    //   8433: caload
    //   8434: istore 104
    //   8436: iload 103
    //   8438: iconst_5
    //   8439: irem
    //   8440: tableswitch	default:+32 -> 8472, 0:+53->8493, 1:+60->8500, 2:+67->8507, 3:+74->8514
    //   8473: pop
    //   8474: istore 105
    //   8476: aload 101
    //   8478: iload 103
    //   8480: iload 105
    //   8482: iload 104
    //   8484: ixor
    //   8485: i2c
    //   8486: castore
    //   8487: iinc 103 1
    //   8490: goto -7722 -> 768
    //   8493: bipush 77
    //   8495: istore 105
    //   8497: goto -21 -> 8476
    //   8500: bipush 73
    //   8502: istore 105
    //   8504: goto -28 -> 8476
    //   8507: bipush 99
    //   8509: istore 105
    //   8511: goto -35 -> 8476
    //   8514: bipush 59
    //   8516: istore 105
    //   8518: goto -42 -> 8476
    //   8521: aload 106
    //   8523: iload 108
    //   8525: caload
    //   8526: istore 109
    //   8528: iload 108
    //   8530: iconst_5
    //   8531: irem
    //   8532: tableswitch	default:+32 -> 8564, 0:+53->8585, 1:+60->8592, 2:+67->8599, 3:+74->8606
    //   8565: pop
    //   8566: istore 110
    //   8568: aload 106
    //   8570: iload 108
    //   8572: iload 110
    //   8574: iload 109
    //   8576: ixor
    //   8577: i2c
    //   8578: castore
    //   8579: iinc 108 1
    //   8582: goto -7776 -> 806
    //   8585: bipush 77
    //   8587: istore 110
    //   8589: goto -21 -> 8568
    //   8592: bipush 73
    //   8594: istore 110
    //   8596: goto -28 -> 8568
    //   8599: bipush 99
    //   8601: istore 110
    //   8603: goto -35 -> 8568
    //   8606: bipush 59
    //   8608: istore 110
    //   8610: goto -42 -> 8568
    //   8613: aload 111
    //   8615: iload 113
    //   8617: caload
    //   8618: istore 114
    //   8620: iload 113
    //   8622: iconst_5
    //   8623: irem
    //   8624: tableswitch	default:+32 -> 8656, 0:+53->8677, 1:+60->8684, 2:+67->8691, 3:+74->8698
    //   8657: pop
    //   8658: istore 115
    //   8660: aload 111
    //   8662: iload 113
    //   8664: iload 115
    //   8666: iload 114
    //   8668: ixor
    //   8669: i2c
    //   8670: castore
    //   8671: iinc 113 1
    //   8674: goto -7830 -> 844
    //   8677: bipush 77
    //   8679: istore 115
    //   8681: goto -21 -> 8660
    //   8684: bipush 73
    //   8686: istore 115
    //   8688: goto -28 -> 8660
    //   8691: bipush 99
    //   8693: istore 115
    //   8695: goto -35 -> 8660
    //   8698: bipush 59
    //   8700: istore 115
    //   8702: goto -42 -> 8660
    //   8705: aload 116
    //   8707: iload 118
    //   8709: caload
    //   8710: istore 119
    //   8712: iload 118
    //   8714: iconst_5
    //   8715: irem
    //   8716: tableswitch	default:+32 -> 8748, 0:+53->8769, 1:+60->8776, 2:+67->8783, 3:+74->8790
    //   8749: pop
    //   8750: istore 120
    //   8752: aload 116
    //   8754: iload 118
    //   8756: iload 120
    //   8758: iload 119
    //   8760: ixor
    //   8761: i2c
    //   8762: castore
    //   8763: iinc 118 1
    //   8766: goto -7884 -> 882
    //   8769: bipush 77
    //   8771: istore 120
    //   8773: goto -21 -> 8752
    //   8776: bipush 73
    //   8778: istore 120
    //   8780: goto -28 -> 8752
    //   8783: bipush 99
    //   8785: istore 120
    //   8787: goto -35 -> 8752
    //   8790: bipush 59
    //   8792: istore 120
    //   8794: goto -42 -> 8752
    //   8797: aload 121
    //   8799: iload 123
    //   8801: caload
    //   8802: istore 124
    //   8804: iload 123
    //   8806: iconst_5
    //   8807: irem
    //   8808: tableswitch	default:+32 -> 8840, 0:+53->8861, 1:+60->8868, 2:+67->8875, 3:+74->8882
    //   8841: pop
    //   8842: istore 125
    //   8844: aload 121
    //   8846: iload 123
    //   8848: iload 125
    //   8850: iload 124
    //   8852: ixor
    //   8853: i2c
    //   8854: castore
    //   8855: iinc 123 1
    //   8858: goto -7938 -> 920
    //   8861: bipush 77
    //   8863: istore 125
    //   8865: goto -21 -> 8844
    //   8868: bipush 73
    //   8870: istore 125
    //   8872: goto -28 -> 8844
    //   8875: bipush 99
    //   8877: istore 125
    //   8879: goto -35 -> 8844
    //   8882: bipush 59
    //   8884: istore 125
    //   8886: goto -42 -> 8844
    //   8889: aload 126
    //   8891: iload 128
    //   8893: caload
    //   8894: istore 129
    //   8896: iload 128
    //   8898: iconst_5
    //   8899: irem
    //   8900: tableswitch	default:+32 -> 8932, 0:+53->8953, 1:+60->8960, 2:+67->8967, 3:+74->8974
    //   8933: pop
    //   8934: istore 130
    //   8936: aload 126
    //   8938: iload 128
    //   8940: iload 130
    //   8942: iload 129
    //   8944: ixor
    //   8945: i2c
    //   8946: castore
    //   8947: iinc 128 1
    //   8950: goto -7992 -> 958
    //   8953: bipush 77
    //   8955: istore 130
    //   8957: goto -21 -> 8936
    //   8960: bipush 73
    //   8962: istore 130
    //   8964: goto -28 -> 8936
    //   8967: bipush 99
    //   8969: istore 130
    //   8971: goto -35 -> 8936
    //   8974: bipush 59
    //   8976: istore 130
    //   8978: goto -42 -> 8936
    //   8981: aload 131
    //   8983: iload 133
    //   8985: caload
    //   8986: istore 134
    //   8988: iload 133
    //   8990: iconst_5
    //   8991: irem
    //   8992: tableswitch	default:+32 -> 9024, 0:+53->9045, 1:+60->9052, 2:+67->9059, 3:+74->9066
    //   9025: pop
    //   9026: istore 135
    //   9028: aload 131
    //   9030: iload 133
    //   9032: iload 135
    //   9034: iload 134
    //   9036: ixor
    //   9037: i2c
    //   9038: castore
    //   9039: iinc 133 1
    //   9042: goto -8046 -> 996
    //   9045: bipush 77
    //   9047: istore 135
    //   9049: goto -21 -> 9028
    //   9052: bipush 73
    //   9054: istore 135
    //   9056: goto -28 -> 9028
    //   9059: bipush 99
    //   9061: istore 135
    //   9063: goto -35 -> 9028
    //   9066: bipush 59
    //   9068: istore 135
    //   9070: goto -42 -> 9028
    //   9073: aload 136
    //   9075: iload 138
    //   9077: caload
    //   9078: istore 139
    //   9080: iload 138
    //   9082: iconst_5
    //   9083: irem
    //   9084: tableswitch	default:+32 -> 9116, 0:+53->9137, 1:+60->9144, 2:+67->9151, 3:+74->9158
    //   9117: pop
    //   9118: istore 140
    //   9120: aload 136
    //   9122: iload 138
    //   9124: iload 140
    //   9126: iload 139
    //   9128: ixor
    //   9129: i2c
    //   9130: castore
    //   9131: iinc 138 1
    //   9134: goto -8100 -> 1034
    //   9137: bipush 77
    //   9139: istore 140
    //   9141: goto -21 -> 9120
    //   9144: bipush 73
    //   9146: istore 140
    //   9148: goto -28 -> 9120
    //   9151: bipush 99
    //   9153: istore 140
    //   9155: goto -35 -> 9120
    //   9158: bipush 59
    //   9160: istore 140
    //   9162: goto -42 -> 9120
    //   9165: aload 141
    //   9167: iload 143
    //   9169: caload
    //   9170: istore 144
    //   9172: iload 143
    //   9174: iconst_5
    //   9175: irem
    //   9176: tableswitch	default:+32 -> 9208, 0:+53->9229, 1:+60->9236, 2:+67->9243, 3:+74->9250
    //   9209: pop
    //   9210: istore 145
    //   9212: aload 141
    //   9214: iload 143
    //   9216: iload 145
    //   9218: iload 144
    //   9220: ixor
    //   9221: i2c
    //   9222: castore
    //   9223: iinc 143 1
    //   9226: goto -8154 -> 1072
    //   9229: bipush 77
    //   9231: istore 145
    //   9233: goto -21 -> 9212
    //   9236: bipush 73
    //   9238: istore 145
    //   9240: goto -28 -> 9212
    //   9243: bipush 99
    //   9245: istore 145
    //   9247: goto -35 -> 9212
    //   9250: bipush 59
    //   9252: istore 145
    //   9254: goto -42 -> 9212
    //   9257: aload 146
    //   9259: iload 148
    //   9261: caload
    //   9262: istore 149
    //   9264: iload 148
    //   9266: iconst_5
    //   9267: irem
    //   9268: tableswitch	default:+32 -> 9300, 0:+53->9321, 1:+60->9328, 2:+67->9335, 3:+74->9342
    //   9301: pop
    //   9302: istore 150
    //   9304: aload 146
    //   9306: iload 148
    //   9308: iload 150
    //   9310: iload 149
    //   9312: ixor
    //   9313: i2c
    //   9314: castore
    //   9315: iinc 148 1
    //   9318: goto -8208 -> 1110
    //   9321: bipush 77
    //   9323: istore 150
    //   9325: goto -21 -> 9304
    //   9328: bipush 73
    //   9330: istore 150
    //   9332: goto -28 -> 9304
    //   9335: bipush 99
    //   9337: istore 150
    //   9339: goto -35 -> 9304
    //   9342: bipush 59
    //   9344: istore 150
    //   9346: goto -42 -> 9304
    //   9349: aload 151
    //   9351: iload 153
    //   9353: caload
    //   9354: istore 154
    //   9356: iload 153
    //   9358: iconst_5
    //   9359: irem
    //   9360: tableswitch	default:+32 -> 9392, 0:+53->9413, 1:+60->9420, 2:+67->9427, 3:+74->9434
    //   9393: pop
    //   9394: istore 155
    //   9396: aload 151
    //   9398: iload 153
    //   9400: iload 155
    //   9402: iload 154
    //   9404: ixor
    //   9405: i2c
    //   9406: castore
    //   9407: iinc 153 1
    //   9410: goto -8262 -> 1148
    //   9413: bipush 77
    //   9415: istore 155
    //   9417: goto -21 -> 9396
    //   9420: bipush 73
    //   9422: istore 155
    //   9424: goto -28 -> 9396
    //   9427: bipush 99
    //   9429: istore 155
    //   9431: goto -35 -> 9396
    //   9434: bipush 59
    //   9436: istore 155
    //   9438: goto -42 -> 9396
    //   9441: aload 156
    //   9443: iload 158
    //   9445: caload
    //   9446: istore 159
    //   9448: iload 158
    //   9450: iconst_5
    //   9451: irem
    //   9452: tableswitch	default:+32 -> 9484, 0:+53->9505, 1:+60->9512, 2:+67->9519, 3:+74->9526
    //   9485: pop
    //   9486: istore 160
    //   9488: aload 156
    //   9490: iload 158
    //   9492: iload 160
    //   9494: iload 159
    //   9496: ixor
    //   9497: i2c
    //   9498: castore
    //   9499: iinc 158 1
    //   9502: goto -8316 -> 1186
    //   9505: bipush 77
    //   9507: istore 160
    //   9509: goto -21 -> 9488
    //   9512: bipush 73
    //   9514: istore 160
    //   9516: goto -28 -> 9488
    //   9519: bipush 99
    //   9521: istore 160
    //   9523: goto -35 -> 9488
    //   9526: bipush 59
    //   9528: istore 160
    //   9530: goto -42 -> 9488
    //   9533: aload 161
    //   9535: iload 163
    //   9537: caload
    //   9538: istore 164
    //   9540: iload 163
    //   9542: iconst_5
    //   9543: irem
    //   9544: tableswitch	default:+32 -> 9576, 0:+53->9597, 1:+60->9604, 2:+67->9611, 3:+74->9618
    //   9577: pop
    //   9578: istore 165
    //   9580: aload 161
    //   9582: iload 163
    //   9584: iload 165
    //   9586: iload 164
    //   9588: ixor
    //   9589: i2c
    //   9590: castore
    //   9591: iinc 163 1
    //   9594: goto -8370 -> 1224
    //   9597: bipush 77
    //   9599: istore 165
    //   9601: goto -21 -> 9580
    //   9604: bipush 73
    //   9606: istore 165
    //   9608: goto -28 -> 9580
    //   9611: bipush 99
    //   9613: istore 165
    //   9615: goto -35 -> 9580
    //   9618: bipush 59
    //   9620: istore 165
    //   9622: goto -42 -> 9580
    //   9625: aload 166
    //   9627: iload 168
    //   9629: caload
    //   9630: istore 169
    //   9632: iload 168
    //   9634: iconst_5
    //   9635: irem
    //   9636: tableswitch	default:+32 -> 9668, 0:+53->9689, 1:+60->9696, 2:+67->9703, 3:+74->9710
    //   9669: pop
    //   9670: istore 170
    //   9672: aload 166
    //   9674: iload 168
    //   9676: iload 170
    //   9678: iload 169
    //   9680: ixor
    //   9681: i2c
    //   9682: castore
    //   9683: iinc 168 1
    //   9686: goto -8424 -> 1262
    //   9689: bipush 77
    //   9691: istore 170
    //   9693: goto -21 -> 9672
    //   9696: bipush 73
    //   9698: istore 170
    //   9700: goto -28 -> 9672
    //   9703: bipush 99
    //   9705: istore 170
    //   9707: goto -35 -> 9672
    //   9710: bipush 59
    //   9712: istore 170
    //   9714: goto -42 -> 9672
    //   9717: aload 171
    //   9719: iload 173
    //   9721: caload
    //   9722: istore 174
    //   9724: iload 173
    //   9726: iconst_5
    //   9727: irem
    //   9728: tableswitch	default:+32 -> 9760, 0:+53->9781, 1:+60->9788, 2:+67->9795, 3:+74->9802
    //   9761: pop
    //   9762: istore 175
    //   9764: aload 171
    //   9766: iload 173
    //   9768: iload 175
    //   9770: iload 174
    //   9772: ixor
    //   9773: i2c
    //   9774: castore
    //   9775: iinc 173 1
    //   9778: goto -8478 -> 1300
    //   9781: bipush 77
    //   9783: istore 175
    //   9785: goto -21 -> 9764
    //   9788: bipush 73
    //   9790: istore 175
    //   9792: goto -28 -> 9764
    //   9795: bipush 99
    //   9797: istore 175
    //   9799: goto -35 -> 9764
    //   9802: bipush 59
    //   9804: istore 175
    //   9806: goto -42 -> 9764
    //   9809: aload 176
    //   9811: iload 178
    //   9813: caload
    //   9814: istore 179
    //   9816: iload 178
    //   9818: iconst_5
    //   9819: irem
    //   9820: tableswitch	default:+32 -> 9852, 0:+53->9873, 1:+60->9880, 2:+67->9887, 3:+74->9894
    //   9853: pop
    //   9854: istore 180
    //   9856: aload 176
    //   9858: iload 178
    //   9860: iload 180
    //   9862: iload 179
    //   9864: ixor
    //   9865: i2c
    //   9866: castore
    //   9867: iinc 178 1
    //   9870: goto -8532 -> 1338
    //   9873: bipush 77
    //   9875: istore 180
    //   9877: goto -21 -> 9856
    //   9880: bipush 73
    //   9882: istore 180
    //   9884: goto -28 -> 9856
    //   9887: bipush 99
    //   9889: istore 180
    //   9891: goto -35 -> 9856
    //   9894: bipush 59
    //   9896: istore 180
    //   9898: goto -42 -> 9856
    //   9901: aload 181
    //   9903: iload 183
    //   9905: caload
    //   9906: istore 184
    //   9908: iload 183
    //   9910: iconst_5
    //   9911: irem
    //   9912: tableswitch	default:+32 -> 9944, 0:+53->9965, 1:+60->9972, 2:+67->9979, 3:+74->9986
    //   9945: pop
    //   9946: istore 185
    //   9948: aload 181
    //   9950: iload 183
    //   9952: iload 185
    //   9954: iload 184
    //   9956: ixor
    //   9957: i2c
    //   9958: castore
    //   9959: iinc 183 1
    //   9962: goto -8586 -> 1376
    //   9965: bipush 77
    //   9967: istore 185
    //   9969: goto -21 -> 9948
    //   9972: bipush 73
    //   9974: istore 185
    //   9976: goto -28 -> 9948
    //   9979: bipush 99
    //   9981: istore 185
    //   9983: goto -35 -> 9948
    //   9986: bipush 59
    //   9988: istore 185
    //   9990: goto -42 -> 9948
    //   9993: aload 186
    //   9995: iload 188
    //   9997: caload
    //   9998: istore 189
    //   10000: iload 188
    //   10002: iconst_5
    //   10003: irem
    //   10004: tableswitch	default:+32 -> 10036, 0:+53->10057, 1:+60->10064, 2:+67->10071, 3:+74->10078
    //   10037: pop
    //   10038: istore 190
    //   10040: aload 186
    //   10042: iload 188
    //   10044: iload 190
    //   10046: iload 189
    //   10048: ixor
    //   10049: i2c
    //   10050: castore
    //   10051: iinc 188 1
    //   10054: goto -8640 -> 1414
    //   10057: bipush 77
    //   10059: istore 190
    //   10061: goto -21 -> 10040
    //   10064: bipush 73
    //   10066: istore 190
    //   10068: goto -28 -> 10040
    //   10071: bipush 99
    //   10073: istore 190
    //   10075: goto -35 -> 10040
    //   10078: bipush 59
    //   10080: istore 190
    //   10082: goto -42 -> 10040
    //   10085: aload 191
    //   10087: iload 193
    //   10089: caload
    //   10090: istore 194
    //   10092: iload 193
    //   10094: iconst_5
    //   10095: irem
    //   10096: tableswitch	default:+32 -> 10128, 0:+53->10149, 1:+60->10156, 2:+67->10163, 3:+74->10170
    //   10129: pop
    //   10130: istore 195
    //   10132: aload 191
    //   10134: iload 193
    //   10136: iload 195
    //   10138: iload 194
    //   10140: ixor
    //   10141: i2c
    //   10142: castore
    //   10143: iinc 193 1
    //   10146: goto -8694 -> 1452
    //   10149: bipush 77
    //   10151: istore 195
    //   10153: goto -21 -> 10132
    //   10156: bipush 73
    //   10158: istore 195
    //   10160: goto -28 -> 10132
    //   10163: bipush 99
    //   10165: istore 195
    //   10167: goto -35 -> 10132
    //   10170: bipush 59
    //   10172: istore 195
    //   10174: goto -42 -> 10132
    //   10177: aload 196
    //   10179: iload 198
    //   10181: caload
    //   10182: istore 199
    //   10184: iload 198
    //   10186: iconst_5
    //   10187: irem
    //   10188: tableswitch	default:+32 -> 10220, 0:+53->10241, 1:+60->10248, 2:+67->10255, 3:+74->10262
    //   10221: pop
    //   10222: istore 200
    //   10224: aload 196
    //   10226: iload 198
    //   10228: iload 200
    //   10230: iload 199
    //   10232: ixor
    //   10233: i2c
    //   10234: castore
    //   10235: iinc 198 1
    //   10238: goto -8748 -> 1490
    //   10241: bipush 77
    //   10243: istore 200
    //   10245: goto -21 -> 10224
    //   10248: bipush 73
    //   10250: istore 200
    //   10252: goto -28 -> 10224
    //   10255: bipush 99
    //   10257: istore 200
    //   10259: goto -35 -> 10224
    //   10262: bipush 59
    //   10264: istore 200
    //   10266: goto -42 -> 10224
    //   10269: aload 201
    //   10271: iload 203
    //   10273: caload
    //   10274: istore 204
    //   10276: iload 203
    //   10278: iconst_5
    //   10279: irem
    //   10280: tableswitch	default:+32 -> 10312, 0:+53->10333, 1:+60->10340, 2:+67->10347, 3:+74->10354
    //   10313: pop
    //   10314: istore 205
    //   10316: aload 201
    //   10318: iload 203
    //   10320: iload 205
    //   10322: iload 204
    //   10324: ixor
    //   10325: i2c
    //   10326: castore
    //   10327: iinc 203 1
    //   10330: goto -8802 -> 1528
    //   10333: bipush 77
    //   10335: istore 205
    //   10337: goto -21 -> 10316
    //   10340: bipush 73
    //   10342: istore 205
    //   10344: goto -28 -> 10316
    //   10347: bipush 99
    //   10349: istore 205
    //   10351: goto -35 -> 10316
    //   10354: bipush 59
    //   10356: istore 205
    //   10358: goto -42 -> 10316
    //   10361: aload 206
    //   10363: iload 208
    //   10365: caload
    //   10366: istore 209
    //   10368: iload 208
    //   10370: iconst_5
    //   10371: irem
    //   10372: tableswitch	default:+32 -> 10404, 0:+53->10425, 1:+60->10432, 2:+67->10439, 3:+74->10446
    //   10405: pop
    //   10406: istore 210
    //   10408: aload 206
    //   10410: iload 208
    //   10412: iload 210
    //   10414: iload 209
    //   10416: ixor
    //   10417: i2c
    //   10418: castore
    //   10419: iinc 208 1
    //   10422: goto -8856 -> 1566
    //   10425: bipush 77
    //   10427: istore 210
    //   10429: goto -21 -> 10408
    //   10432: bipush 73
    //   10434: istore 210
    //   10436: goto -28 -> 10408
    //   10439: bipush 99
    //   10441: istore 210
    //   10443: goto -35 -> 10408
    //   10446: bipush 59
    //   10448: istore 210
    //   10450: goto -42 -> 10408
    //   10453: aload 211
    //   10455: iload 213
    //   10457: caload
    //   10458: istore 214
    //   10460: iload 213
    //   10462: iconst_5
    //   10463: irem
    //   10464: tableswitch	default:+32 -> 10496, 0:+53->10517, 1:+60->10524, 2:+67->10531, 3:+74->10538
    //   10497: pop
    //   10498: istore 215
    //   10500: aload 211
    //   10502: iload 213
    //   10504: iload 215
    //   10506: iload 214
    //   10508: ixor
    //   10509: i2c
    //   10510: castore
    //   10511: iinc 213 1
    //   10514: goto -8910 -> 1604
    //   10517: bipush 77
    //   10519: istore 215
    //   10521: goto -21 -> 10500
    //   10524: bipush 73
    //   10526: istore 215
    //   10528: goto -28 -> 10500
    //   10531: bipush 99
    //   10533: istore 215
    //   10535: goto -35 -> 10500
    //   10538: bipush 59
    //   10540: istore 215
    //   10542: goto -42 -> 10500
    //   10545: aload 216
    //   10547: iload 218
    //   10549: caload
    //   10550: istore 219
    //   10552: iload 218
    //   10554: iconst_5
    //   10555: irem
    //   10556: tableswitch	default:+32 -> 10588, 0:+53->10609, 1:+60->10616, 2:+67->10623, 3:+74->10630
    //   10589: pop
    //   10590: istore 220
    //   10592: aload 216
    //   10594: iload 218
    //   10596: iload 220
    //   10598: iload 219
    //   10600: ixor
    //   10601: i2c
    //   10602: castore
    //   10603: iinc 218 1
    //   10606: goto -8964 -> 1642
    //   10609: bipush 77
    //   10611: istore 220
    //   10613: goto -21 -> 10592
    //   10616: bipush 73
    //   10618: istore 220
    //   10620: goto -28 -> 10592
    //   10623: bipush 99
    //   10625: istore 220
    //   10627: goto -35 -> 10592
    //   10630: bipush 59
    //   10632: istore 220
    //   10634: goto -42 -> 10592
    //   10637: aload 221
    //   10639: iload 223
    //   10641: caload
    //   10642: istore 224
    //   10644: iload 223
    //   10646: iconst_5
    //   10647: irem
    //   10648: tableswitch	default:+32 -> 10680, 0:+53->10701, 1:+60->10708, 2:+67->10715, 3:+74->10722
    //   10681: pop
    //   10682: istore 225
    //   10684: aload 221
    //   10686: iload 223
    //   10688: iload 225
    //   10690: iload 224
    //   10692: ixor
    //   10693: i2c
    //   10694: castore
    //   10695: iinc 223 1
    //   10698: goto -9018 -> 1680
    //   10701: bipush 77
    //   10703: istore 225
    //   10705: goto -21 -> 10684
    //   10708: bipush 73
    //   10710: istore 225
    //   10712: goto -28 -> 10684
    //   10715: bipush 99
    //   10717: istore 225
    //   10719: goto -35 -> 10684
    //   10722: bipush 59
    //   10724: istore 225
    //   10726: goto -42 -> 10684
    //   10729: aload 226
    //   10731: iload 228
    //   10733: caload
    //   10734: istore 229
    //   10736: iload 228
    //   10738: iconst_5
    //   10739: irem
    //   10740: tableswitch	default:+32 -> 10772, 0:+53->10793, 1:+60->10800, 2:+67->10807, 3:+74->10814
    //   10773: pop
    //   10774: istore 230
    //   10776: aload 226
    //   10778: iload 228
    //   10780: iload 230
    //   10782: iload 229
    //   10784: ixor
    //   10785: i2c
    //   10786: castore
    //   10787: iinc 228 1
    //   10790: goto -9072 -> 1718
    //   10793: bipush 77
    //   10795: istore 230
    //   10797: goto -21 -> 10776
    //   10800: bipush 73
    //   10802: istore 230
    //   10804: goto -28 -> 10776
    //   10807: bipush 99
    //   10809: istore 230
    //   10811: goto -35 -> 10776
    //   10814: bipush 59
    //   10816: istore 230
    //   10818: goto -42 -> 10776
    //   10821: aload 231
    //   10823: iload 233
    //   10825: caload
    //   10826: istore 234
    //   10828: iload 233
    //   10830: iconst_5
    //   10831: irem
    //   10832: tableswitch	default:+32 -> 10864, 0:+53->10885, 1:+60->10892, 2:+67->10899, 3:+74->10906
    //   10865: pop
    //   10866: istore 235
    //   10868: aload 231
    //   10870: iload 233
    //   10872: iload 235
    //   10874: iload 234
    //   10876: ixor
    //   10877: i2c
    //   10878: castore
    //   10879: iinc 233 1
    //   10882: goto -9126 -> 1756
    //   10885: bipush 77
    //   10887: istore 235
    //   10889: goto -21 -> 10868
    //   10892: bipush 73
    //   10894: istore 235
    //   10896: goto -28 -> 10868
    //   10899: bipush 99
    //   10901: istore 235
    //   10903: goto -35 -> 10868
    //   10906: bipush 59
    //   10908: istore 235
    //   10910: goto -42 -> 10868
    //   10913: aload 236
    //   10915: iload 238
    //   10917: caload
    //   10918: istore 239
    //   10920: iload 238
    //   10922: iconst_5
    //   10923: irem
    //   10924: tableswitch	default:+32 -> 10956, 0:+53->10977, 1:+60->10984, 2:+67->10991, 3:+74->10998
    //   10957: pop
    //   10958: istore 240
    //   10960: aload 236
    //   10962: iload 238
    //   10964: iload 240
    //   10966: iload 239
    //   10968: ixor
    //   10969: i2c
    //   10970: castore
    //   10971: iinc 238 1
    //   10974: goto -9180 -> 1794
    //   10977: bipush 77
    //   10979: istore 240
    //   10981: goto -21 -> 10960
    //   10984: bipush 73
    //   10986: istore 240
    //   10988: goto -28 -> 10960
    //   10991: bipush 99
    //   10993: istore 240
    //   10995: goto -35 -> 10960
    //   10998: bipush 59
    //   11000: istore 240
    //   11002: goto -42 -> 10960
    //   11005: aload 241
    //   11007: iload 243
    //   11009: caload
    //   11010: istore 244
    //   11012: iload 243
    //   11014: iconst_5
    //   11015: irem
    //   11016: tableswitch	default:+32 -> 11048, 0:+53->11069, 1:+60->11076, 2:+67->11083, 3:+74->11090
    //   11049: pop
    //   11050: istore 245
    //   11052: aload 241
    //   11054: iload 243
    //   11056: iload 245
    //   11058: iload 244
    //   11060: ixor
    //   11061: i2c
    //   11062: castore
    //   11063: iinc 243 1
    //   11066: goto -9234 -> 1832
    //   11069: bipush 77
    //   11071: istore 245
    //   11073: goto -21 -> 11052
    //   11076: bipush 73
    //   11078: istore 245
    //   11080: goto -28 -> 11052
    //   11083: bipush 99
    //   11085: istore 245
    //   11087: goto -35 -> 11052
    //   11090: bipush 59
    //   11092: istore 245
    //   11094: goto -42 -> 11052
    //   11097: aload 246
    //   11099: iload 248
    //   11101: caload
    //   11102: istore 249
    //   11104: iload 248
    //   11106: iconst_5
    //   11107: irem
    //   11108: tableswitch	default:+32 -> 11140, 0:+53->11161, 1:+60->11168, 2:+67->11175, 3:+74->11182
    //   11141: pop
    //   11142: istore 250
    //   11144: aload 246
    //   11146: iload 248
    //   11148: iload 250
    //   11150: iload 249
    //   11152: ixor
    //   11153: i2c
    //   11154: castore
    //   11155: iinc 248 1
    //   11158: goto -9288 -> 1870
    //   11161: bipush 77
    //   11163: istore 250
    //   11165: goto -21 -> 11144
    //   11168: bipush 73
    //   11170: istore 250
    //   11172: goto -28 -> 11144
    //   11175: bipush 99
    //   11177: istore 250
    //   11179: goto -35 -> 11144
    //   11182: bipush 59
    //   11184: istore 250
    //   11186: goto -42 -> 11144
    //   11189: aload 251
    //   11191: iload 253
    //   11193: caload
    //   11194: istore 254
    //   11196: iload 253
    //   11198: iconst_5
    //   11199: irem
    //   11200: tableswitch	default:+32 -> 11232, 0:+53->11253, 1:+60->11260, 2:+67->11267, 3:+74->11274
    //   11233: pop
    //   11234: istore 255
    //   11236: aload 251
    //   11238: iload 253
    //   11240: iload 255
    //   11242: iload 254
    //   11244: ixor
    //   11245: i2c
    //   11246: castore
    //   11247: iinc 253 1
    //   11250: goto -9342 -> 1908
    //   11253: bipush 77
    //   11255: istore 255
    //   11257: goto -21 -> 11236
    //   11260: bipush 73
    //   11262: istore 255
    //   11264: goto -28 -> 11236
    //   11267: bipush 99
    //   11269: istore 255
    //   11271: goto -35 -> 11236
    //   11274: bipush 59
    //   11276: istore 255
    //   11278: goto -42 -> 11236
    //   11281: wide
    //   11285: wide
    //   11289: caload
    //   11290: wide
    //   11294: wide
    //   11298: iconst_5
    //   11299: irem
    //   11300: tableswitch	default:+32 -> 11332, 0:+66->11366, 1:+75->11375, 2:+84->11384, 3:+93->11393
    //   11333: pop
    //   11334: wide
    //   11338: wide
    //   11342: wide
    //   11346: wide
    //   11350: wide
    //   11354: ixor
    //   11355: i2c
    //   11356: castore
    //   11357: wide
    //   11363: goto -9409 -> 1954
    //   11366: bipush 77
    //   11368: wide
    //   11372: goto -34 -> 11338
    //   11375: bipush 73
    //   11377: wide
    //   11381: goto -43 -> 11338
    //   11384: bipush 99
    //   11386: wide
    //   11390: goto -52 -> 11338
    //   11393: bipush 59
    //   11395: wide
    //   11399: goto -61 -> 11338
    //   11402: wide
    //   11406: wide
    //   11410: caload
    //   11411: wide
    //   11415: wide
    //   11419: iconst_5
    //   11420: irem
    //   11421: tableswitch	default:+31 -> 11452, 0:+65->11486, 1:+74->11495, 2:+83->11504, 3:+92->11513
    //   11453: pop
    //   11454: wide
    //   11458: wide
    //   11462: wide
    //   11466: wide
    //   11470: wide
    //   11474: ixor
    //   11475: i2c
    //   11476: castore
    //   11477: wide
    //   11483: goto -9477 -> 2006
    //   11486: bipush 77
    //   11488: wide
    //   11492: goto -34 -> 11458
    //   11495: bipush 73
    //   11497: wide
    //   11501: goto -43 -> 11458
    //   11504: bipush 99
    //   11506: wide
    //   11510: goto -52 -> 11458
    //   11513: bipush 59
    //   11515: wide
    //   11519: goto -61 -> 11458
    //   11522: wide
    //   11526: wide
    //   11530: caload
    //   11531: wide
    //   11535: wide
    //   11539: iconst_5
    //   11540: irem
    //   11541: tableswitch	default:+31 -> 11572, 0:+65->11606, 1:+74->11615, 2:+83->11624, 3:+92->11633
    //   11573: pop
    //   11574: wide
    //   11578: wide
    //   11582: wide
    //   11586: wide
    //   11590: wide
    //   11594: ixor
    //   11595: i2c
    //   11596: castore
    //   11597: wide
    //   11603: goto -9545 -> 2058
    //   11606: bipush 77
    //   11608: wide
    //   11612: goto -34 -> 11578
    //   11615: bipush 73
    //   11617: wide
    //   11621: goto -43 -> 11578
    //   11624: bipush 99
    //   11626: wide
    //   11630: goto -52 -> 11578
    //   11633: bipush 59
    //   11635: wide
    //   11639: goto -61 -> 11578
    //   11642: wide
    //   11646: wide
    //   11650: caload
    //   11651: wide
    //   11655: wide
    //   11659: iconst_5
    //   11660: irem
    //   11661: tableswitch	default:+31 -> 11692, 0:+65->11726, 1:+74->11735, 2:+83->11744, 3:+92->11753
    //   11693: pop
    //   11694: wide
    //   11698: wide
    //   11702: wide
    //   11706: wide
    //   11710: wide
    //   11714: ixor
    //   11715: i2c
    //   11716: castore
    //   11717: wide
    //   11723: goto -9613 -> 2110
    //   11726: bipush 77
    //   11728: wide
    //   11732: goto -34 -> 11698
    //   11735: bipush 73
    //   11737: wide
    //   11741: goto -43 -> 11698
    //   11744: bipush 99
    //   11746: wide
    //   11750: goto -52 -> 11698
    //   11753: bipush 59
    //   11755: wide
    //   11759: goto -61 -> 11698
    //   11762: wide
    //   11766: wide
    //   11770: caload
    //   11771: wide
    //   11775: wide
    //   11779: iconst_5
    //   11780: irem
    //   11781: tableswitch	default:+31 -> 11812, 0:+65->11846, 1:+74->11855, 2:+83->11864, 3:+92->11873
    //   11813: pop
    //   11814: wide
    //   11818: wide
    //   11822: wide
    //   11826: wide
    //   11830: wide
    //   11834: ixor
    //   11835: i2c
    //   11836: castore
    //   11837: wide
    //   11843: goto -9681 -> 2162
    //   11846: bipush 77
    //   11848: wide
    //   11852: goto -34 -> 11818
    //   11855: bipush 73
    //   11857: wide
    //   11861: goto -43 -> 11818
    //   11864: bipush 99
    //   11866: wide
    //   11870: goto -52 -> 11818
    //   11873: bipush 59
    //   11875: wide
    //   11879: goto -61 -> 11818
    //   11882: wide
    //   11886: wide
    //   11890: caload
    //   11891: wide
    //   11895: wide
    //   11899: iconst_5
    //   11900: irem
    //   11901: tableswitch	default:+31 -> 11932, 0:+65->11966, 1:+74->11975, 2:+83->11984, 3:+92->11993
    //   11933: pop
    //   11934: wide
    //   11938: wide
    //   11942: wide
    //   11946: wide
    //   11950: wide
    //   11954: ixor
    //   11955: i2c
    //   11956: castore
    //   11957: wide
    //   11963: goto -9749 -> 2214
    //   11966: bipush 77
    //   11968: wide
    //   11972: goto -34 -> 11938
    //   11975: bipush 73
    //   11977: wide
    //   11981: goto -43 -> 11938
    //   11984: bipush 99
    //   11986: wide
    //   11990: goto -52 -> 11938
    //   11993: bipush 59
    //   11995: wide
    //   11999: goto -61 -> 11938
    //   12002: wide
    //   12006: wide
    //   12010: caload
    //   12011: wide
    //   12015: wide
    //   12019: iconst_5
    //   12020: irem
    //   12021: tableswitch	default:+31 -> 12052, 0:+65->12086, 1:+74->12095, 2:+83->12104, 3:+92->12113
    //   12053: pop
    //   12054: wide
    //   12058: wide
    //   12062: wide
    //   12066: wide
    //   12070: wide
    //   12074: ixor
    //   12075: i2c
    //   12076: castore
    //   12077: wide
    //   12083: goto -9817 -> 2266
    //   12086: bipush 77
    //   12088: wide
    //   12092: goto -34 -> 12058
    //   12095: bipush 73
    //   12097: wide
    //   12101: goto -43 -> 12058
    //   12104: bipush 99
    //   12106: wide
    //   12110: goto -52 -> 12058
    //   12113: bipush 59
    //   12115: wide
    //   12119: goto -61 -> 12058
    //   12122: wide
    //   12126: wide
    //   12130: caload
    //   12131: wide
    //   12135: wide
    //   12139: iconst_5
    //   12140: irem
    //   12141: tableswitch	default:+31 -> 12172, 0:+65->12206, 1:+74->12215, 2:+83->12224, 3:+92->12233
    //   12173: pop
    //   12174: wide
    //   12178: wide
    //   12182: wide
    //   12186: wide
    //   12190: wide
    //   12194: ixor
    //   12195: i2c
    //   12196: castore
    //   12197: wide
    //   12203: goto -9885 -> 2318
    //   12206: bipush 77
    //   12208: wide
    //   12212: goto -34 -> 12178
    //   12215: bipush 73
    //   12217: wide
    //   12221: goto -43 -> 12178
    //   12224: bipush 99
    //   12226: wide
    //   12230: goto -52 -> 12178
    //   12233: bipush 59
    //   12235: wide
    //   12239: goto -61 -> 12178
    //   12242: wide
    //   12246: wide
    //   12250: caload
    //   12251: wide
    //   12255: wide
    //   12259: iconst_5
    //   12260: irem
    //   12261: tableswitch	default:+31 -> 12292, 0:+65->12326, 1:+74->12335, 2:+83->12344, 3:+92->12353
    //   12293: pop
    //   12294: wide
    //   12298: wide
    //   12302: wide
    //   12306: wide
    //   12310: wide
    //   12314: ixor
    //   12315: i2c
    //   12316: castore
    //   12317: wide
    //   12323: goto -9953 -> 2370
    //   12326: bipush 77
    //   12328: wide
    //   12332: goto -34 -> 12298
    //   12335: bipush 73
    //   12337: wide
    //   12341: goto -43 -> 12298
    //   12344: bipush 99
    //   12346: wide
    //   12350: goto -52 -> 12298
    //   12353: bipush 59
    //   12355: wide
    //   12359: goto -61 -> 12298
    //   12362: wide
    //   12366: wide
    //   12370: caload
    //   12371: wide
    //   12375: wide
    //   12379: iconst_5
    //   12380: irem
    //   12381: tableswitch	default:+31 -> 12412, 0:+65->12446, 1:+74->12455, 2:+83->12464, 3:+92->12473
    //   12413: pop
    //   12414: wide
    //   12418: wide
    //   12422: wide
    //   12426: wide
    //   12430: wide
    //   12434: ixor
    //   12435: i2c
    //   12436: castore
    //   12437: wide
    //   12443: goto -10021 -> 2422
    //   12446: bipush 77
    //   12448: wide
    //   12452: goto -34 -> 12418
    //   12455: bipush 73
    //   12457: wide
    //   12461: goto -43 -> 12418
    //   12464: bipush 99
    //   12466: wide
    //   12470: goto -52 -> 12418
    //   12473: bipush 59
    //   12475: wide
    //   12479: goto -61 -> 12418
    //   12482: wide
    //   12486: wide
    //   12490: caload
    //   12491: wide
    //   12495: wide
    //   12499: iconst_5
    //   12500: irem
    //   12501: tableswitch	default:+31 -> 12532, 0:+65->12566, 1:+74->12575, 2:+83->12584, 3:+92->12593
    //   12533: pop
    //   12534: wide
    //   12538: wide
    //   12542: wide
    //   12546: wide
    //   12550: wide
    //   12554: ixor
    //   12555: i2c
    //   12556: castore
    //   12557: wide
    //   12563: goto -10089 -> 2474
    //   12566: bipush 77
    //   12568: wide
    //   12572: goto -34 -> 12538
    //   12575: bipush 73
    //   12577: wide
    //   12581: goto -43 -> 12538
    //   12584: bipush 99
    //   12586: wide
    //   12590: goto -52 -> 12538
    //   12593: bipush 59
    //   12595: wide
    //   12599: goto -61 -> 12538
    //   12602: wide
    //   12606: wide
    //   12610: caload
    //   12611: wide
    //   12615: wide
    //   12619: iconst_5
    //   12620: irem
    //   12621: tableswitch	default:+31 -> 12652, 0:+65->12686, 1:+74->12695, 2:+83->12704, 3:+92->12713
    //   12653: pop
    //   12654: wide
    //   12658: wide
    //   12662: wide
    //   12666: wide
    //   12670: wide
    //   12674: ixor
    //   12675: i2c
    //   12676: castore
    //   12677: wide
    //   12683: goto -10157 -> 2526
    //   12686: bipush 77
    //   12688: wide
    //   12692: goto -34 -> 12658
    //   12695: bipush 73
    //   12697: wide
    //   12701: goto -43 -> 12658
    //   12704: bipush 99
    //   12706: wide
    //   12710: goto -52 -> 12658
    //   12713: bipush 59
    //   12715: wide
    //   12719: goto -61 -> 12658
    //   12722: wide
    //   12726: wide
    //   12730: caload
    //   12731: wide
    //   12735: wide
    //   12739: iconst_5
    //   12740: irem
    //   12741: tableswitch	default:+31 -> 12772, 0:+65->12806, 1:+74->12815, 2:+83->12824, 3:+92->12833
    //   12773: pop
    //   12774: wide
    //   12778: wide
    //   12782: wide
    //   12786: wide
    //   12790: wide
    //   12794: ixor
    //   12795: i2c
    //   12796: castore
    //   12797: wide
    //   12803: goto -10225 -> 2578
    //   12806: bipush 77
    //   12808: wide
    //   12812: goto -34 -> 12778
    //   12815: bipush 73
    //   12817: wide
    //   12821: goto -43 -> 12778
    //   12824: bipush 99
    //   12826: wide
    //   12830: goto -52 -> 12778
    //   12833: bipush 59
    //   12835: wide
    //   12839: goto -61 -> 12778
    //   12842: wide
    //   12846: wide
    //   12850: caload
    //   12851: wide
    //   12855: wide
    //   12859: iconst_5
    //   12860: irem
    //   12861: tableswitch	default:+31 -> 12892, 0:+65->12926, 1:+74->12935, 2:+83->12944, 3:+92->12953
    //   12893: pop
    //   12894: wide
    //   12898: wide
    //   12902: wide
    //   12906: wide
    //   12910: wide
    //   12914: ixor
    //   12915: i2c
    //   12916: castore
    //   12917: wide
    //   12923: goto -10293 -> 2630
    //   12926: bipush 77
    //   12928: wide
    //   12932: goto -34 -> 12898
    //   12935: bipush 73
    //   12937: wide
    //   12941: goto -43 -> 12898
    //   12944: bipush 99
    //   12946: wide
    //   12950: goto -52 -> 12898
    //   12953: bipush 59
    //   12955: wide
    //   12959: goto -61 -> 12898
    //   12962: wide
    //   12966: wide
    //   12970: caload
    //   12971: wide
    //   12975: wide
    //   12979: iconst_5
    //   12980: irem
    //   12981: tableswitch	default:+31 -> 13012, 0:+65->13046, 1:+74->13055, 2:+83->13064, 3:+92->13073
    //   13013: pop
    //   13014: wide
    //   13018: wide
    //   13022: wide
    //   13026: wide
    //   13030: wide
    //   13034: ixor
    //   13035: i2c
    //   13036: castore
    //   13037: wide
    //   13043: goto -10361 -> 2682
    //   13046: bipush 77
    //   13048: wide
    //   13052: goto -34 -> 13018
    //   13055: bipush 73
    //   13057: wide
    //   13061: goto -43 -> 13018
    //   13064: bipush 99
    //   13066: wide
    //   13070: goto -52 -> 13018
    //   13073: bipush 59
    //   13075: wide
    //   13079: goto -61 -> 13018
    //   13082: wide
    //   13086: wide
    //   13090: caload
    //   13091: wide
    //   13095: wide
    //   13099: iconst_5
    //   13100: irem
    //   13101: tableswitch	default:+31 -> 13132, 0:+65->13166, 1:+74->13175, 2:+83->13184, 3:+92->13193
    //   13133: pop
    //   13134: wide
    //   13138: wide
    //   13142: wide
    //   13146: wide
    //   13150: wide
    //   13154: ixor
    //   13155: i2c
    //   13156: castore
    //   13157: wide
    //   13163: goto -10429 -> 2734
    //   13166: bipush 77
    //   13168: wide
    //   13172: goto -34 -> 13138
    //   13175: bipush 73
    //   13177: wide
    //   13181: goto -43 -> 13138
    //   13184: bipush 99
    //   13186: wide
    //   13190: goto -52 -> 13138
    //   13193: bipush 59
    //   13195: wide
    //   13199: goto -61 -> 13138
    //   13202: wide
    //   13206: wide
    //   13210: caload
    //   13211: wide
    //   13215: wide
    //   13219: iconst_5
    //   13220: irem
    //   13221: tableswitch	default:+31 -> 13252, 0:+65->13286, 1:+74->13295, 2:+83->13304, 3:+92->13313
    //   13253: pop
    //   13254: wide
    //   13258: wide
    //   13262: wide
    //   13266: wide
    //   13270: wide
    //   13274: ixor
    //   13275: i2c
    //   13276: castore
    //   13277: wide
    //   13283: goto -10497 -> 2786
    //   13286: bipush 77
    //   13288: wide
    //   13292: goto -34 -> 13258
    //   13295: bipush 73
    //   13297: wide
    //   13301: goto -43 -> 13258
    //   13304: bipush 99
    //   13306: wide
    //   13310: goto -52 -> 13258
    //   13313: bipush 59
    //   13315: wide
    //   13319: goto -61 -> 13258
    //   13322: wide
    //   13326: wide
    //   13330: caload
    //   13331: wide
    //   13335: wide
    //   13339: iconst_5
    //   13340: irem
    //   13341: tableswitch	default:+31 -> 13372, 0:+65->13406, 1:+74->13415, 2:+83->13424, 3:+92->13433
    //   13373: pop
    //   13374: wide
    //   13378: wide
    //   13382: wide
    //   13386: wide
    //   13390: wide
    //   13394: ixor
    //   13395: i2c
    //   13396: castore
    //   13397: wide
    //   13403: goto -10565 -> 2838
    //   13406: bipush 77
    //   13408: wide
    //   13412: goto -34 -> 13378
    //   13415: bipush 73
    //   13417: wide
    //   13421: goto -43 -> 13378
    //   13424: bipush 99
    //   13426: wide
    //   13430: goto -52 -> 13378
    //   13433: bipush 59
    //   13435: wide
    //   13439: goto -61 -> 13378
    //   13442: wide
    //   13446: wide
    //   13450: caload
    //   13451: wide
    //   13455: wide
    //   13459: iconst_5
    //   13460: irem
    //   13461: tableswitch	default:+31 -> 13492, 0:+65->13526, 1:+74->13535, 2:+83->13544, 3:+92->13553
    //   13493: pop
    //   13494: wide
    //   13498: wide
    //   13502: wide
    //   13506: wide
    //   13510: wide
    //   13514: ixor
    //   13515: i2c
    //   13516: castore
    //   13517: wide
    //   13523: goto -10633 -> 2890
    //   13526: bipush 77
    //   13528: wide
    //   13532: goto -34 -> 13498
    //   13535: bipush 73
    //   13537: wide
    //   13541: goto -43 -> 13498
    //   13544: bipush 99
    //   13546: wide
    //   13550: goto -52 -> 13498
    //   13553: bipush 59
    //   13555: wide
    //   13559: goto -61 -> 13498
    //   13562: wide
    //   13566: wide
    //   13570: caload
    //   13571: wide
    //   13575: wide
    //   13579: iconst_5
    //   13580: irem
    //   13581: tableswitch	default:+31 -> 13612, 0:+65->13646, 1:+74->13655, 2:+83->13664, 3:+92->13673
    //   13613: pop
    //   13614: wide
    //   13618: wide
    //   13622: wide
    //   13626: wide
    //   13630: wide
    //   13634: ixor
    //   13635: i2c
    //   13636: castore
    //   13637: wide
    //   13643: goto -10701 -> 2942
    //   13646: bipush 77
    //   13648: wide
    //   13652: goto -34 -> 13618
    //   13655: bipush 73
    //   13657: wide
    //   13661: goto -43 -> 13618
    //   13664: bipush 99
    //   13666: wide
    //   13670: goto -52 -> 13618
    //   13673: bipush 59
    //   13675: wide
    //   13679: goto -61 -> 13618
    //   13682: wide
    //   13686: wide
    //   13690: caload
    //   13691: wide
    //   13695: wide
    //   13699: iconst_5
    //   13700: irem
    //   13701: tableswitch	default:+31 -> 13732, 0:+65->13766, 1:+74->13775, 2:+83->13784, 3:+92->13793
    //   13733: pop
    //   13734: wide
    //   13738: wide
    //   13742: wide
    //   13746: wide
    //   13750: wide
    //   13754: ixor
    //   13755: i2c
    //   13756: castore
    //   13757: wide
    //   13763: goto -10769 -> 2994
    //   13766: bipush 77
    //   13768: wide
    //   13772: goto -34 -> 13738
    //   13775: bipush 73
    //   13777: wide
    //   13781: goto -43 -> 13738
    //   13784: bipush 99
    //   13786: wide
    //   13790: goto -52 -> 13738
    //   13793: bipush 59
    //   13795: wide
    //   13799: goto -61 -> 13738
    //   13802: wide
    //   13806: wide
    //   13810: caload
    //   13811: wide
    //   13815: wide
    //   13819: iconst_5
    //   13820: irem
    //   13821: tableswitch	default:+31 -> 13852, 0:+65->13886, 1:+74->13895, 2:+83->13904, 3:+92->13913
    //   13853: pop
    //   13854: wide
    //   13858: wide
    //   13862: wide
    //   13866: wide
    //   13870: wide
    //   13874: ixor
    //   13875: i2c
    //   13876: castore
    //   13877: wide
    //   13883: goto -10837 -> 3046
    //   13886: bipush 77
    //   13888: wide
    //   13892: goto -34 -> 13858
    //   13895: bipush 73
    //   13897: wide
    //   13901: goto -43 -> 13858
    //   13904: bipush 99
    //   13906: wide
    //   13910: goto -52 -> 13858
    //   13913: bipush 59
    //   13915: wide
    //   13919: goto -61 -> 13858
    //   13922: wide
    //   13926: wide
    //   13930: caload
    //   13931: wide
    //   13935: wide
    //   13939: iconst_5
    //   13940: irem
    //   13941: tableswitch	default:+31 -> 13972, 0:+65->14006, 1:+74->14015, 2:+83->14024, 3:+92->14033
    //   13973: pop
    //   13974: wide
    //   13978: wide
    //   13982: wide
    //   13986: wide
    //   13990: wide
    //   13994: ixor
    //   13995: i2c
    //   13996: castore
    //   13997: wide
    //   14003: goto -10905 -> 3098
    //   14006: bipush 77
    //   14008: wide
    //   14012: goto -34 -> 13978
    //   14015: bipush 73
    //   14017: wide
    //   14021: goto -43 -> 13978
    //   14024: bipush 99
    //   14026: wide
    //   14030: goto -52 -> 13978
    //   14033: bipush 59
    //   14035: wide
    //   14039: goto -61 -> 13978
    //   14042: wide
    //   14046: wide
    //   14050: caload
    //   14051: wide
    //   14055: wide
    //   14059: iconst_5
    //   14060: irem
    //   14061: tableswitch	default:+31 -> 14092, 0:+65->14126, 1:+74->14135, 2:+83->14144, 3:+92->14153
    //   14093: pop
    //   14094: wide
    //   14098: wide
    //   14102: wide
    //   14106: wide
    //   14110: wide
    //   14114: ixor
    //   14115: i2c
    //   14116: castore
    //   14117: wide
    //   14123: goto -10973 -> 3150
    //   14126: bipush 77
    //   14128: wide
    //   14132: goto -34 -> 14098
    //   14135: bipush 73
    //   14137: wide
    //   14141: goto -43 -> 14098
    //   14144: bipush 99
    //   14146: wide
    //   14150: goto -52 -> 14098
    //   14153: bipush 59
    //   14155: wide
    //   14159: goto -61 -> 14098
    //   14162: wide
    //   14166: wide
    //   14170: caload
    //   14171: wide
    //   14175: wide
    //   14179: iconst_5
    //   14180: irem
    //   14181: tableswitch	default:+31 -> 14212, 0:+65->14246, 1:+74->14255, 2:+83->14264, 3:+92->14273
    //   14213: pop
    //   14214: wide
    //   14218: wide
    //   14222: wide
    //   14226: wide
    //   14230: wide
    //   14234: ixor
    //   14235: i2c
    //   14236: castore
    //   14237: wide
    //   14243: goto -11041 -> 3202
    //   14246: bipush 77
    //   14248: wide
    //   14252: goto -34 -> 14218
    //   14255: bipush 73
    //   14257: wide
    //   14261: goto -43 -> 14218
    //   14264: bipush 99
    //   14266: wide
    //   14270: goto -52 -> 14218
    //   14273: bipush 59
    //   14275: wide
    //   14279: goto -61 -> 14218
    //   14282: wide
    //   14286: wide
    //   14290: caload
    //   14291: wide
    //   14295: wide
    //   14299: iconst_5
    //   14300: irem
    //   14301: tableswitch	default:+31 -> 14332, 0:+65->14366, 1:+74->14375, 2:+83->14384, 3:+92->14393
    //   14333: pop
    //   14334: wide
    //   14338: wide
    //   14342: wide
    //   14346: wide
    //   14350: wide
    //   14354: ixor
    //   14355: i2c
    //   14356: castore
    //   14357: wide
    //   14363: goto -11109 -> 3254
    //   14366: bipush 77
    //   14368: wide
    //   14372: goto -34 -> 14338
    //   14375: bipush 73
    //   14377: wide
    //   14381: goto -43 -> 14338
    //   14384: bipush 99
    //   14386: wide
    //   14390: goto -52 -> 14338
    //   14393: bipush 59
    //   14395: wide
    //   14399: goto -61 -> 14338
    //   14402: wide
    //   14406: wide
    //   14410: caload
    //   14411: wide
    //   14415: wide
    //   14419: iconst_5
    //   14420: irem
    //   14421: tableswitch	default:+31 -> 14452, 0:+65->14486, 1:+74->14495, 2:+83->14504, 3:+92->14513
    //   14453: pop
    //   14454: wide
    //   14458: wide
    //   14462: wide
    //   14466: wide
    //   14470: wide
    //   14474: ixor
    //   14475: i2c
    //   14476: castore
    //   14477: wide
    //   14483: goto -11177 -> 3306
    //   14486: bipush 77
    //   14488: wide
    //   14492: goto -34 -> 14458
    //   14495: bipush 73
    //   14497: wide
    //   14501: goto -43 -> 14458
    //   14504: bipush 99
    //   14506: wide
    //   14510: goto -52 -> 14458
    //   14513: bipush 59
    //   14515: wide
    //   14519: goto -61 -> 14458
    //   14522: wide
    //   14526: wide
    //   14530: caload
    //   14531: wide
    //   14535: wide
    //   14539: iconst_5
    //   14540: irem
    //   14541: tableswitch	default:+31 -> 14572, 0:+65->14606, 1:+74->14615, 2:+83->14624, 3:+92->14633
    //   14573: pop
    //   14574: wide
    //   14578: wide
    //   14582: wide
    //   14586: wide
    //   14590: wide
    //   14594: ixor
    //   14595: i2c
    //   14596: castore
    //   14597: wide
    //   14603: goto -11245 -> 3358
    //   14606: bipush 77
    //   14608: wide
    //   14612: goto -34 -> 14578
    //   14615: bipush 73
    //   14617: wide
    //   14621: goto -43 -> 14578
    //   14624: bipush 99
    //   14626: wide
    //   14630: goto -52 -> 14578
    //   14633: bipush 59
    //   14635: wide
    //   14639: goto -61 -> 14578
    //   14642: wide
    //   14646: wide
    //   14650: caload
    //   14651: wide
    //   14655: wide
    //   14659: iconst_5
    //   14660: irem
    //   14661: tableswitch	default:+31 -> 14692, 0:+65->14726, 1:+74->14735, 2:+83->14744, 3:+92->14753
    //   14693: pop
    //   14694: wide
    //   14698: wide
    //   14702: wide
    //   14706: wide
    //   14710: wide
    //   14714: ixor
    //   14715: i2c
    //   14716: castore
    //   14717: wide
    //   14723: goto -11313 -> 3410
    //   14726: bipush 77
    //   14728: wide
    //   14732: goto -34 -> 14698
    //   14735: bipush 73
    //   14737: wide
    //   14741: goto -43 -> 14698
    //   14744: bipush 99
    //   14746: wide
    //   14750: goto -52 -> 14698
    //   14753: bipush 59
    //   14755: wide
    //   14759: goto -61 -> 14698
    //   14762: wide
    //   14766: wide
    //   14770: caload
    //   14771: wide
    //   14775: wide
    //   14779: iconst_5
    //   14780: irem
    //   14781: tableswitch	default:+31 -> 14812, 0:+65->14846, 1:+74->14855, 2:+83->14864, 3:+92->14873
    //   14813: pop
    //   14814: wide
    //   14818: wide
    //   14822: wide
    //   14826: wide
    //   14830: wide
    //   14834: ixor
    //   14835: i2c
    //   14836: castore
    //   14837: wide
    //   14843: goto -11381 -> 3462
    //   14846: bipush 77
    //   14848: wide
    //   14852: goto -34 -> 14818
    //   14855: bipush 73
    //   14857: wide
    //   14861: goto -43 -> 14818
    //   14864: bipush 99
    //   14866: wide
    //   14870: goto -52 -> 14818
    //   14873: bipush 59
    //   14875: wide
    //   14879: goto -61 -> 14818
    //   14882: wide
    //   14886: wide
    //   14890: caload
    //   14891: wide
    //   14895: wide
    //   14899: iconst_5
    //   14900: irem
    //   14901: tableswitch	default:+31 -> 14932, 0:+65->14966, 1:+74->14975, 2:+83->14984, 3:+92->14993
    //   14933: pop
    //   14934: wide
    //   14938: wide
    //   14942: wide
    //   14946: wide
    //   14950: wide
    //   14954: ixor
    //   14955: i2c
    //   14956: castore
    //   14957: wide
    //   14963: goto -11449 -> 3514
    //   14966: bipush 77
    //   14968: wide
    //   14972: goto -34 -> 14938
    //   14975: bipush 73
    //   14977: wide
    //   14981: goto -43 -> 14938
    //   14984: bipush 99
    //   14986: wide
    //   14990: goto -52 -> 14938
    //   14993: bipush 59
    //   14995: wide
    //   14999: goto -61 -> 14938
    //   15002: wide
    //   15006: wide
    //   15010: caload
    //   15011: wide
    //   15015: wide
    //   15019: iconst_5
    //   15020: irem
    //   15021: tableswitch	default:+31 -> 15052, 0:+65->15086, 1:+74->15095, 2:+83->15104, 3:+92->15113
    //   15053: pop
    //   15054: wide
    //   15058: wide
    //   15062: wide
    //   15066: wide
    //   15070: wide
    //   15074: ixor
    //   15075: i2c
    //   15076: castore
    //   15077: wide
    //   15083: goto -11517 -> 3566
    //   15086: bipush 77
    //   15088: wide
    //   15092: goto -34 -> 15058
    //   15095: bipush 73
    //   15097: wide
    //   15101: goto -43 -> 15058
    //   15104: bipush 99
    //   15106: wide
    //   15110: goto -52 -> 15058
    //   15113: bipush 59
    //   15115: wide
    //   15119: goto -61 -> 15058
    //   15122: wide
    //   15126: wide
    //   15130: caload
    //   15131: wide
    //   15135: wide
    //   15139: iconst_5
    //   15140: irem
    //   15141: tableswitch	default:+31 -> 15172, 0:+65->15206, 1:+74->15215, 2:+83->15224, 3:+92->15233
    //   15173: pop
    //   15174: wide
    //   15178: wide
    //   15182: wide
    //   15186: wide
    //   15190: wide
    //   15194: ixor
    //   15195: i2c
    //   15196: castore
    //   15197: wide
    //   15203: goto -11585 -> 3618
    //   15206: bipush 77
    //   15208: wide
    //   15212: goto -34 -> 15178
    //   15215: bipush 73
    //   15217: wide
    //   15221: goto -43 -> 15178
    //   15224: bipush 99
    //   15226: wide
    //   15230: goto -52 -> 15178
    //   15233: bipush 59
    //   15235: wide
    //   15239: goto -61 -> 15178
    //   15242: wide
    //   15246: wide
    //   15250: caload
    //   15251: wide
    //   15255: wide
    //   15259: iconst_5
    //   15260: irem
    //   15261: tableswitch	default:+31 -> 15292, 0:+65->15326, 1:+74->15335, 2:+83->15344, 3:+92->15353
    //   15293: pop
    //   15294: wide
    //   15298: wide
    //   15302: wide
    //   15306: wide
    //   15310: wide
    //   15314: ixor
    //   15315: i2c
    //   15316: castore
    //   15317: wide
    //   15323: goto -11653 -> 3670
    //   15326: bipush 77
    //   15328: wide
    //   15332: goto -34 -> 15298
    //   15335: bipush 73
    //   15337: wide
    //   15341: goto -43 -> 15298
    //   15344: bipush 99
    //   15346: wide
    //   15350: goto -52 -> 15298
    //   15353: bipush 59
    //   15355: wide
    //   15359: goto -61 -> 15298
    //   15362: wide
    //   15366: wide
    //   15370: caload
    //   15371: wide
    //   15375: wide
    //   15379: iconst_5
    //   15380: irem
    //   15381: tableswitch	default:+31 -> 15412, 0:+65->15446, 1:+74->15455, 2:+83->15464, 3:+92->15473
    //   15413: pop
    //   15414: wide
    //   15418: wide
    //   15422: wide
    //   15426: wide
    //   15430: wide
    //   15434: ixor
    //   15435: i2c
    //   15436: castore
    //   15437: wide
    //   15443: goto -11721 -> 3722
    //   15446: bipush 77
    //   15448: wide
    //   15452: goto -34 -> 15418
    //   15455: bipush 73
    //   15457: wide
    //   15461: goto -43 -> 15418
    //   15464: bipush 99
    //   15466: wide
    //   15470: goto -52 -> 15418
    //   15473: bipush 59
    //   15475: wide
    //   15479: goto -61 -> 15418
    //   15482: wide
    //   15486: wide
    //   15490: caload
    //   15491: wide
    //   15495: wide
    //   15499: iconst_5
    //   15500: irem
    //   15501: tableswitch	default:+31 -> 15532, 0:+65->15566, 1:+74->15575, 2:+83->15584, 3:+92->15593
    //   15533: pop
    //   15534: wide
    //   15538: wide
    //   15542: wide
    //   15546: wide
    //   15550: wide
    //   15554: ixor
    //   15555: i2c
    //   15556: castore
    //   15557: wide
    //   15563: goto -11789 -> 3774
    //   15566: bipush 77
    //   15568: wide
    //   15572: goto -34 -> 15538
    //   15575: bipush 73
    //   15577: wide
    //   15581: goto -43 -> 15538
    //   15584: bipush 99
    //   15586: wide
    //   15590: goto -52 -> 15538
    //   15593: bipush 59
    //   15595: wide
    //   15599: goto -61 -> 15538
    //   15602: wide
    //   15606: wide
    //   15610: caload
    //   15611: wide
    //   15615: wide
    //   15619: iconst_5
    //   15620: irem
    //   15621: tableswitch	default:+31 -> 15652, 0:+65->15686, 1:+74->15695, 2:+83->15704, 3:+92->15713
    //   15653: pop
    //   15654: wide
    //   15658: wide
    //   15662: wide
    //   15666: wide
    //   15670: wide
    //   15674: ixor
    //   15675: i2c
    //   15676: castore
    //   15677: wide
    //   15683: goto -11857 -> 3826
    //   15686: bipush 77
    //   15688: wide
    //   15692: goto -34 -> 15658
    //   15695: bipush 73
    //   15697: wide
    //   15701: goto -43 -> 15658
    //   15704: bipush 99
    //   15706: wide
    //   15710: goto -52 -> 15658
    //   15713: bipush 59
    //   15715: wide
    //   15719: goto -61 -> 15658
    //   15722: wide
    //   15726: wide
    //   15730: caload
    //   15731: wide
    //   15735: wide
    //   15739: iconst_5
    //   15740: irem
    //   15741: tableswitch	default:+31 -> 15772, 0:+65->15806, 1:+74->15815, 2:+83->15824, 3:+92->15833
    //   15773: pop
    //   15774: wide
    //   15778: wide
    //   15782: wide
    //   15786: wide
    //   15790: wide
    //   15794: ixor
    //   15795: i2c
    //   15796: castore
    //   15797: wide
    //   15803: goto -11925 -> 3878
    //   15806: bipush 77
    //   15808: wide
    //   15812: goto -34 -> 15778
    //   15815: bipush 73
    //   15817: wide
    //   15821: goto -43 -> 15778
    //   15824: bipush 99
    //   15826: wide
    //   15830: goto -52 -> 15778
    //   15833: bipush 59
    //   15835: wide
    //   15839: goto -61 -> 15778
    //   15842: wide
    //   15846: wide
    //   15850: caload
    //   15851: wide
    //   15855: wide
    //   15859: iconst_5
    //   15860: irem
    //   15861: tableswitch	default:+31 -> 15892, 0:+65->15926, 1:+74->15935, 2:+83->15944, 3:+92->15953
    //   15893: pop
    //   15894: wide
    //   15898: wide
    //   15902: wide
    //   15906: wide
    //   15910: wide
    //   15914: ixor
    //   15915: i2c
    //   15916: castore
    //   15917: wide
    //   15923: goto -11993 -> 3930
    //   15926: bipush 77
    //   15928: wide
    //   15932: goto -34 -> 15898
    //   15935: bipush 73
    //   15937: wide
    //   15941: goto -43 -> 15898
    //   15944: bipush 99
    //   15946: wide
    //   15950: goto -52 -> 15898
    //   15953: bipush 59
    //   15955: wide
    //   15959: goto -61 -> 15898
    //   15962: wide
    //   15966: wide
    //   15970: caload
    //   15971: wide
    //   15975: wide
    //   15979: iconst_5
    //   15980: irem
    //   15981: tableswitch	default:+31 -> 16012, 0:+65->16046, 1:+74->16055, 2:+83->16064, 3:+92->16073
    //   16013: pop
    //   16014: wide
    //   16018: wide
    //   16022: wide
    //   16026: wide
    //   16030: wide
    //   16034: ixor
    //   16035: i2c
    //   16036: castore
    //   16037: wide
    //   16043: goto -12061 -> 3982
    //   16046: bipush 77
    //   16048: wide
    //   16052: goto -34 -> 16018
    //   16055: bipush 73
    //   16057: wide
    //   16061: goto -43 -> 16018
    //   16064: bipush 99
    //   16066: wide
    //   16070: goto -52 -> 16018
    //   16073: bipush 59
    //   16075: wide
    //   16079: goto -61 -> 16018
    //   16082: wide
    //   16086: wide
    //   16090: caload
    //   16091: wide
    //   16095: wide
    //   16099: iconst_5
    //   16100: irem
    //   16101: tableswitch	default:+31 -> 16132, 0:+65->16166, 1:+74->16175, 2:+83->16184, 3:+92->16193
    //   16133: pop
    //   16134: wide
    //   16138: wide
    //   16142: wide
    //   16146: wide
    //   16150: wide
    //   16154: ixor
    //   16155: i2c
    //   16156: castore
    //   16157: wide
    //   16163: goto -12129 -> 4034
    //   16166: bipush 77
    //   16168: wide
    //   16172: goto -34 -> 16138
    //   16175: bipush 73
    //   16177: wide
    //   16181: goto -43 -> 16138
    //   16184: bipush 99
    //   16186: wide
    //   16190: goto -52 -> 16138
    //   16193: bipush 59
    //   16195: wide
    //   16199: goto -61 -> 16138
    //   16202: wide
    //   16206: wide
    //   16210: caload
    //   16211: wide
    //   16215: wide
    //   16219: iconst_5
    //   16220: irem
    //   16221: tableswitch	default:+31 -> 16252, 0:+65->16286, 1:+74->16295, 2:+83->16304, 3:+92->16313
    //   16253: pop
    //   16254: wide
    //   16258: wide
    //   16262: wide
    //   16266: wide
    //   16270: wide
    //   16274: ixor
    //   16275: i2c
    //   16276: castore
    //   16277: wide
    //   16283: goto -12197 -> 4086
    //   16286: bipush 77
    //   16288: wide
    //   16292: goto -34 -> 16258
    //   16295: bipush 73
    //   16297: wide
    //   16301: goto -43 -> 16258
    //   16304: bipush 99
    //   16306: wide
    //   16310: goto -52 -> 16258
    //   16313: bipush 59
    //   16315: wide
    //   16319: goto -61 -> 16258
    //   16322: wide
    //   16326: wide
    //   16330: caload
    //   16331: wide
    //   16335: wide
    //   16339: iconst_5
    //   16340: irem
    //   16341: tableswitch	default:+31 -> 16372, 0:+65->16406, 1:+74->16415, 2:+83->16424, 3:+92->16433
    //   16373: pop
    //   16374: wide
    //   16378: wide
    //   16382: wide
    //   16386: wide
    //   16390: wide
    //   16394: ixor
    //   16395: i2c
    //   16396: castore
    //   16397: wide
    //   16403: goto -12265 -> 4138
    //   16406: bipush 77
    //   16408: wide
    //   16412: goto -34 -> 16378
    //   16415: bipush 73
    //   16417: wide
    //   16421: goto -43 -> 16378
    //   16424: bipush 99
    //   16426: wide
    //   16430: goto -52 -> 16378
    //   16433: bipush 59
    //   16435: wide
    //   16439: goto -61 -> 16378
    //   16442: wide
    //   16446: wide
    //   16450: caload
    //   16451: wide
    //   16455: wide
    //   16459: iconst_5
    //   16460: irem
    //   16461: tableswitch	default:+31 -> 16492, 0:+65->16526, 1:+74->16535, 2:+83->16544, 3:+92->16553
    //   16493: pop
    //   16494: wide
    //   16498: wide
    //   16502: wide
    //   16506: wide
    //   16510: wide
    //   16514: ixor
    //   16515: i2c
    //   16516: castore
    //   16517: wide
    //   16523: goto -12333 -> 4190
    //   16526: bipush 77
    //   16528: wide
    //   16532: goto -34 -> 16498
    //   16535: bipush 73
    //   16537: wide
    //   16541: goto -43 -> 16498
    //   16544: bipush 99
    //   16546: wide
    //   16550: goto -52 -> 16498
    //   16553: bipush 59
    //   16555: wide
    //   16559: goto -61 -> 16498
    //   16562: wide
    //   16566: wide
    //   16570: caload
    //   16571: wide
    //   16575: wide
    //   16579: iconst_5
    //   16580: irem
    //   16581: tableswitch	default:+31 -> 16612, 0:+65->16646, 1:+74->16655, 2:+83->16664, 3:+92->16673
    //   16613: pop
    //   16614: wide
    //   16618: wide
    //   16622: wide
    //   16626: wide
    //   16630: wide
    //   16634: ixor
    //   16635: i2c
    //   16636: castore
    //   16637: wide
    //   16643: goto -12401 -> 4242
    //   16646: bipush 77
    //   16648: wide
    //   16652: goto -34 -> 16618
    //   16655: bipush 73
    //   16657: wide
    //   16661: goto -43 -> 16618
    //   16664: bipush 99
    //   16666: wide
    //   16670: goto -52 -> 16618
    //   16673: bipush 59
    //   16675: wide
    //   16679: goto -61 -> 16618
    //   16682: wide
    //   16686: wide
    //   16690: caload
    //   16691: wide
    //   16695: wide
    //   16699: iconst_5
    //   16700: irem
    //   16701: tableswitch	default:+31 -> 16732, 0:+65->16766, 1:+74->16775, 2:+83->16784, 3:+92->16793
    //   16733: pop
    //   16734: wide
    //   16738: wide
    //   16742: wide
    //   16746: wide
    //   16750: wide
    //   16754: ixor
    //   16755: i2c
    //   16756: castore
    //   16757: wide
    //   16763: goto -12469 -> 4294
    //   16766: bipush 77
    //   16768: wide
    //   16772: goto -34 -> 16738
    //   16775: bipush 73
    //   16777: wide
    //   16781: goto -43 -> 16738
    //   16784: bipush 99
    //   16786: wide
    //   16790: goto -52 -> 16738
    //   16793: bipush 59
    //   16795: wide
    //   16799: goto -61 -> 16738
    //   16802: wide
    //   16806: wide
    //   16810: caload
    //   16811: wide
    //   16815: wide
    //   16819: iconst_5
    //   16820: irem
    //   16821: tableswitch	default:+31 -> 16852, 0:+65->16886, 1:+74->16895, 2:+83->16904, 3:+92->16913
    //   16853: pop
    //   16854: wide
    //   16858: wide
    //   16862: wide
    //   16866: wide
    //   16870: wide
    //   16874: ixor
    //   16875: i2c
    //   16876: castore
    //   16877: wide
    //   16883: goto -12537 -> 4346
    //   16886: bipush 77
    //   16888: wide
    //   16892: goto -34 -> 16858
    //   16895: bipush 73
    //   16897: wide
    //   16901: goto -43 -> 16858
    //   16904: bipush 99
    //   16906: wide
    //   16910: goto -52 -> 16858
    //   16913: bipush 59
    //   16915: wide
    //   16919: goto -61 -> 16858
    //   16922: wide
    //   16926: wide
    //   16930: caload
    //   16931: wide
    //   16935: wide
    //   16939: iconst_5
    //   16940: irem
    //   16941: tableswitch	default:+31 -> 16972, 0:+65->17006, 1:+74->17015, 2:+83->17024, 3:+92->17033
    //   16973: pop
    //   16974: wide
    //   16978: wide
    //   16982: wide
    //   16986: wide
    //   16990: wide
    //   16994: ixor
    //   16995: i2c
    //   16996: castore
    //   16997: wide
    //   17003: goto -12605 -> 4398
    //   17006: bipush 77
    //   17008: wide
    //   17012: goto -34 -> 16978
    //   17015: bipush 73
    //   17017: wide
    //   17021: goto -43 -> 16978
    //   17024: bipush 99
    //   17026: wide
    //   17030: goto -52 -> 16978
    //   17033: bipush 59
    //   17035: wide
    //   17039: goto -61 -> 16978
    //   17042: wide
    //   17046: wide
    //   17050: caload
    //   17051: wide
    //   17055: wide
    //   17059: iconst_5
    //   17060: irem
    //   17061: tableswitch	default:+31 -> 17092, 0:+65->17126, 1:+74->17135, 2:+83->17144, 3:+92->17153
    //   17093: pop
    //   17094: wide
    //   17098: wide
    //   17102: wide
    //   17106: wide
    //   17110: wide
    //   17114: ixor
    //   17115: i2c
    //   17116: castore
    //   17117: wide
    //   17123: goto -12673 -> 4450
    //   17126: bipush 77
    //   17128: wide
    //   17132: goto -34 -> 17098
    //   17135: bipush 73
    //   17137: wide
    //   17141: goto -43 -> 17098
    //   17144: bipush 99
    //   17146: wide
    //   17150: goto -52 -> 17098
    //   17153: bipush 59
    //   17155: wide
    //   17159: goto -61 -> 17098
    //   17162: wide
    //   17166: wide
    //   17170: caload
    //   17171: wide
    //   17175: wide
    //   17179: iconst_5
    //   17180: irem
    //   17181: tableswitch	default:+31 -> 17212, 0:+65->17246, 1:+74->17255, 2:+83->17264, 3:+92->17273
    //   17213: pop
    //   17214: wide
    //   17218: wide
    //   17222: wide
    //   17226: wide
    //   17230: wide
    //   17234: ixor
    //   17235: i2c
    //   17236: castore
    //   17237: wide
    //   17243: goto -12740 -> 4503
    //   17246: bipush 77
    //   17248: wide
    //   17252: goto -34 -> 17218
    //   17255: bipush 73
    //   17257: wide
    //   17261: goto -43 -> 17218
    //   17264: bipush 99
    //   17266: wide
    //   17270: goto -52 -> 17218
    //   17273: bipush 59
    //   17275: wide
    //   17279: goto -61 -> 17218
    //   17282: wide
    //   17286: wide
    //   17290: caload
    //   17291: wide
    //   17295: wide
    //   17299: iconst_5
    //   17300: irem
    //   17301: tableswitch	default:+31 -> 17332, 0:+65->17366, 1:+74->17375, 2:+83->17384, 3:+92->17393
    //   17333: pop
    //   17334: wide
    //   17338: wide
    //   17342: wide
    //   17346: wide
    //   17350: wide
    //   17354: ixor
    //   17355: i2c
    //   17356: castore
    //   17357: wide
    //   17363: goto -12807 -> 4556
    //   17366: bipush 77
    //   17368: wide
    //   17372: goto -34 -> 17338
    //   17375: bipush 73
    //   17377: wide
    //   17381: goto -43 -> 17338
    //   17384: bipush 99
    //   17386: wide
    //   17390: goto -52 -> 17338
    //   17393: bipush 59
    //   17395: wide
    //   17399: goto -61 -> 17338
    //   17402: wide
    //   17406: wide
    //   17410: caload
    //   17411: wide
    //   17415: wide
    //   17419: iconst_5
    //   17420: irem
    //   17421: tableswitch	default:+31 -> 17452, 0:+65->17486, 1:+74->17495, 2:+83->17504, 3:+92->17513
    //   17453: pop
    //   17454: wide
    //   17458: wide
    //   17462: wide
    //   17466: wide
    //   17470: wide
    //   17474: ixor
    //   17475: i2c
    //   17476: castore
    //   17477: wide
    //   17483: goto -12874 -> 4609
    //   17486: bipush 77
    //   17488: wide
    //   17492: goto -34 -> 17458
    //   17495: bipush 73
    //   17497: wide
    //   17501: goto -43 -> 17458
    //   17504: bipush 99
    //   17506: wide
    //   17510: goto -52 -> 17458
    //   17513: bipush 59
    //   17515: wide
    //   17519: goto -61 -> 17458
    //   17522: wide
    //   17526: wide
    //   17530: caload
    //   17531: wide
    //   17535: wide
    //   17539: iconst_5
    //   17540: irem
    //   17541: tableswitch	default:+31 -> 17572, 0:+65->17606, 1:+74->17615, 2:+83->17624, 3:+92->17633
    //   17573: pop
    //   17574: wide
    //   17578: wide
    //   17582: wide
    //   17586: wide
    //   17590: wide
    //   17594: ixor
    //   17595: i2c
    //   17596: castore
    //   17597: wide
    //   17603: goto -12941 -> 4662
    //   17606: bipush 77
    //   17608: wide
    //   17612: goto -34 -> 17578
    //   17615: bipush 73
    //   17617: wide
    //   17621: goto -43 -> 17578
    //   17624: bipush 99
    //   17626: wide
    //   17630: goto -52 -> 17578
    //   17633: bipush 59
    //   17635: wide
    //   17639: goto -61 -> 17578
    //   17642: wide
    //   17646: wide
    //   17650: caload
    //   17651: wide
    //   17655: wide
    //   17659: iconst_5
    //   17660: irem
    //   17661: tableswitch	default:+31 -> 17692, 0:+65->17726, 1:+74->17735, 2:+83->17744, 3:+92->17753
    //   17693: pop
    //   17694: wide
    //   17698: wide
    //   17702: wide
    //   17706: wide
    //   17710: wide
    //   17714: ixor
    //   17715: i2c
    //   17716: castore
    //   17717: wide
    //   17723: goto -13008 -> 4715
    //   17726: bipush 77
    //   17728: wide
    //   17732: goto -34 -> 17698
    //   17735: bipush 73
    //   17737: wide
    //   17741: goto -43 -> 17698
    //   17744: bipush 99
    //   17746: wide
    //   17750: goto -52 -> 17698
    //   17753: bipush 59
    //   17755: wide
    //   17759: goto -61 -> 17698
    //   17762: wide
    //   17766: wide
    //   17770: caload
    //   17771: wide
    //   17775: wide
    //   17779: iconst_5
    //   17780: irem
    //   17781: tableswitch	default:+31 -> 17812, 0:+65->17846, 1:+74->17855, 2:+83->17864, 3:+92->17873
    //   17813: pop
    //   17814: wide
    //   17818: wide
    //   17822: wide
    //   17826: wide
    //   17830: wide
    //   17834: ixor
    //   17835: i2c
    //   17836: castore
    //   17837: wide
    //   17843: goto -13075 -> 4768
    //   17846: bipush 77
    //   17848: wide
    //   17852: goto -34 -> 17818
    //   17855: bipush 73
    //   17857: wide
    //   17861: goto -43 -> 17818
    //   17864: bipush 99
    //   17866: wide
    //   17870: goto -52 -> 17818
    //   17873: bipush 59
    //   17875: wide
    //   17879: goto -61 -> 17818
    //   17882: wide
    //   17886: wide
    //   17890: caload
    //   17891: wide
    //   17895: wide
    //   17899: iconst_5
    //   17900: irem
    //   17901: tableswitch	default:+31 -> 17932, 0:+65->17966, 1:+74->17975, 2:+83->17984, 3:+92->17993
    //   17933: pop
    //   17934: wide
    //   17938: wide
    //   17942: wide
    //   17946: wide
    //   17950: wide
    //   17954: ixor
    //   17955: i2c
    //   17956: castore
    //   17957: wide
    //   17963: goto -13142 -> 4821
    //   17966: bipush 77
    //   17968: wide
    //   17972: goto -34 -> 17938
    //   17975: bipush 73
    //   17977: wide
    //   17981: goto -43 -> 17938
    //   17984: bipush 99
    //   17986: wide
    //   17990: goto -52 -> 17938
    //   17993: bipush 59
    //   17995: wide
    //   17999: goto -61 -> 17938
    //   18002: wide
    //   18006: wide
    //   18010: caload
    //   18011: wide
    //   18015: wide
    //   18019: iconst_5
    //   18020: irem
    //   18021: tableswitch	default:+31 -> 18052, 0:+65->18086, 1:+74->18095, 2:+83->18104, 3:+92->18113
    //   18053: pop
    //   18054: wide
    //   18058: wide
    //   18062: wide
    //   18066: wide
    //   18070: wide
    //   18074: ixor
    //   18075: i2c
    //   18076: castore
    //   18077: wide
    //   18083: goto -13209 -> 4874
    //   18086: bipush 77
    //   18088: wide
    //   18092: goto -34 -> 18058
    //   18095: bipush 73
    //   18097: wide
    //   18101: goto -43 -> 18058
    //   18104: bipush 99
    //   18106: wide
    //   18110: goto -52 -> 18058
    //   18113: bipush 59
    //   18115: wide
    //   18119: goto -61 -> 18058
    //   18122: wide
    //   18126: wide
    //   18130: caload
    //   18131: wide
    //   18135: wide
    //   18139: iconst_5
    //   18140: irem
    //   18141: tableswitch	default:+31 -> 18172, 0:+65->18206, 1:+74->18215, 2:+83->18224, 3:+92->18233
    //   18173: pop
    //   18174: wide
    //   18178: wide
    //   18182: wide
    //   18186: wide
    //   18190: wide
    //   18194: ixor
    //   18195: i2c
    //   18196: castore
    //   18197: wide
    //   18203: goto -13276 -> 4927
    //   18206: bipush 77
    //   18208: wide
    //   18212: goto -34 -> 18178
    //   18215: bipush 73
    //   18217: wide
    //   18221: goto -43 -> 18178
    //   18224: bipush 99
    //   18226: wide
    //   18230: goto -52 -> 18178
    //   18233: bipush 59
    //   18235: wide
    //   18239: goto -61 -> 18178
    //   18242: wide
    //   18246: wide
    //   18250: caload
    //   18251: wide
    //   18255: wide
    //   18259: iconst_5
    //   18260: irem
    //   18261: tableswitch	default:+31 -> 18292, 0:+65->18326, 1:+74->18335, 2:+83->18344, 3:+92->18353
    //   18293: pop
    //   18294: wide
    //   18298: wide
    //   18302: wide
    //   18306: wide
    //   18310: wide
    //   18314: ixor
    //   18315: i2c
    //   18316: castore
    //   18317: wide
    //   18323: goto -13343 -> 4980
    //   18326: bipush 77
    //   18328: wide
    //   18332: goto -34 -> 18298
    //   18335: bipush 73
    //   18337: wide
    //   18341: goto -43 -> 18298
    //   18344: bipush 99
    //   18346: wide
    //   18350: goto -52 -> 18298
    //   18353: bipush 59
    //   18355: wide
    //   18359: goto -61 -> 18298
    //   18362: wide
    //   18366: wide
    //   18370: caload
    //   18371: wide
    //   18375: wide
    //   18379: iconst_5
    //   18380: irem
    //   18381: tableswitch	default:+31 -> 18412, 0:+65->18446, 1:+74->18455, 2:+83->18464, 3:+92->18473
    //   18413: pop
    //   18414: wide
    //   18418: wide
    //   18422: wide
    //   18426: wide
    //   18430: wide
    //   18434: ixor
    //   18435: i2c
    //   18436: castore
    //   18437: wide
    //   18443: goto -13410 -> 5033
    //   18446: bipush 77
    //   18448: wide
    //   18452: goto -34 -> 18418
    //   18455: bipush 73
    //   18457: wide
    //   18461: goto -43 -> 18418
    //   18464: bipush 99
    //   18466: wide
    //   18470: goto -52 -> 18418
    //   18473: bipush 59
    //   18475: wide
    //   18479: goto -61 -> 18418
    //   18482: wide
    //   18486: wide
    //   18490: caload
    //   18491: wide
    //   18495: wide
    //   18499: iconst_5
    //   18500: irem
    //   18501: tableswitch	default:+31 -> 18532, 0:+65->18566, 1:+74->18575, 2:+83->18584, 3:+92->18593
    //   18533: pop
    //   18534: wide
    //   18538: wide
    //   18542: wide
    //   18546: wide
    //   18550: wide
    //   18554: ixor
    //   18555: i2c
    //   18556: castore
    //   18557: wide
    //   18563: goto -13477 -> 5086
    //   18566: bipush 77
    //   18568: wide
    //   18572: goto -34 -> 18538
    //   18575: bipush 73
    //   18577: wide
    //   18581: goto -43 -> 18538
    //   18584: bipush 99
    //   18586: wide
    //   18590: goto -52 -> 18538
    //   18593: bipush 59
    //   18595: wide
    //   18599: goto -61 -> 18538
    //   18602: wide
    //   18606: wide
    //   18610: caload
    //   18611: wide
    //   18615: wide
    //   18619: iconst_5
    //   18620: irem
    //   18621: tableswitch	default:+31 -> 18652, 0:+65->18686, 1:+74->18695, 2:+83->18704, 3:+92->18713
    //   18653: pop
    //   18654: wide
    //   18658: wide
    //   18662: wide
    //   18666: wide
    //   18670: wide
    //   18674: ixor
    //   18675: i2c
    //   18676: castore
    //   18677: wide
    //   18683: goto -13544 -> 5139
    //   18686: bipush 77
    //   18688: wide
    //   18692: goto -34 -> 18658
    //   18695: bipush 73
    //   18697: wide
    //   18701: goto -43 -> 18658
    //   18704: bipush 99
    //   18706: wide
    //   18710: goto -52 -> 18658
    //   18713: bipush 59
    //   18715: wide
    //   18719: goto -61 -> 18658
    //   18722: wide
    //   18726: wide
    //   18730: caload
    //   18731: wide
    //   18735: wide
    //   18739: iconst_5
    //   18740: irem
    //   18741: tableswitch	default:+31 -> 18772, 0:+65->18806, 1:+74->18815, 2:+83->18824, 3:+92->18833
    //   18773: pop
    //   18774: wide
    //   18778: wide
    //   18782: wide
    //   18786: wide
    //   18790: wide
    //   18794: ixor
    //   18795: i2c
    //   18796: castore
    //   18797: wide
    //   18803: goto -13611 -> 5192
    //   18806: bipush 77
    //   18808: wide
    //   18812: goto -34 -> 18778
    //   18815: bipush 73
    //   18817: wide
    //   18821: goto -43 -> 18778
    //   18824: bipush 99
    //   18826: wide
    //   18830: goto -52 -> 18778
    //   18833: bipush 59
    //   18835: wide
    //   18839: goto -61 -> 18778
    //   18842: wide
    //   18846: wide
    //   18850: caload
    //   18851: wide
    //   18855: wide
    //   18859: iconst_5
    //   18860: irem
    //   18861: tableswitch	default:+31 -> 18892, 0:+65->18926, 1:+74->18935, 2:+83->18944, 3:+92->18953
    //   18893: pop
    //   18894: wide
    //   18898: wide
    //   18902: wide
    //   18906: wide
    //   18910: wide
    //   18914: ixor
    //   18915: i2c
    //   18916: castore
    //   18917: wide
    //   18923: goto -13678 -> 5245
    //   18926: bipush 77
    //   18928: wide
    //   18932: goto -34 -> 18898
    //   18935: bipush 73
    //   18937: wide
    //   18941: goto -43 -> 18898
    //   18944: bipush 99
    //   18946: wide
    //   18950: goto -52 -> 18898
    //   18953: bipush 59
    //   18955: wide
    //   18959: goto -61 -> 18898
    //   18962: wide
    //   18966: wide
    //   18970: caload
    //   18971: wide
    //   18975: wide
    //   18979: iconst_5
    //   18980: irem
    //   18981: tableswitch	default:+31 -> 19012, 0:+65->19046, 1:+74->19055, 2:+83->19064, 3:+92->19073
    //   19013: pop
    //   19014: wide
    //   19018: wide
    //   19022: wide
    //   19026: wide
    //   19030: wide
    //   19034: ixor
    //   19035: i2c
    //   19036: castore
    //   19037: wide
    //   19043: goto -13745 -> 5298
    //   19046: bipush 77
    //   19048: wide
    //   19052: goto -34 -> 19018
    //   19055: bipush 73
    //   19057: wide
    //   19061: goto -43 -> 19018
    //   19064: bipush 99
    //   19066: wide
    //   19070: goto -52 -> 19018
    //   19073: bipush 59
    //   19075: wide
    //   19079: goto -61 -> 19018
    //   19082: wide
    //   19086: wide
    //   19090: caload
    //   19091: wide
    //   19095: wide
    //   19099: iconst_5
    //   19100: irem
    //   19101: tableswitch	default:+31 -> 19132, 0:+65->19166, 1:+74->19175, 2:+83->19184, 3:+92->19193
    //   19133: pop
    //   19134: wide
    //   19138: wide
    //   19142: wide
    //   19146: wide
    //   19150: wide
    //   19154: ixor
    //   19155: i2c
    //   19156: castore
    //   19157: wide
    //   19163: goto -13812 -> 5351
    //   19166: bipush 77
    //   19168: wide
    //   19172: goto -34 -> 19138
    //   19175: bipush 73
    //   19177: wide
    //   19181: goto -43 -> 19138
    //   19184: bipush 99
    //   19186: wide
    //   19190: goto -52 -> 19138
    //   19193: bipush 59
    //   19195: wide
    //   19199: goto -61 -> 19138
    //   19202: wide
    //   19206: wide
    //   19210: caload
    //   19211: wide
    //   19215: wide
    //   19219: iconst_5
    //   19220: irem
    //   19221: tableswitch	default:+31 -> 19252, 0:+65->19286, 1:+74->19295, 2:+83->19304, 3:+92->19313
    //   19253: pop
    //   19254: wide
    //   19258: wide
    //   19262: wide
    //   19266: wide
    //   19270: wide
    //   19274: ixor
    //   19275: i2c
    //   19276: castore
    //   19277: wide
    //   19283: goto -13879 -> 5404
    //   19286: bipush 77
    //   19288: wide
    //   19292: goto -34 -> 19258
    //   19295: bipush 73
    //   19297: wide
    //   19301: goto -43 -> 19258
    //   19304: bipush 99
    //   19306: wide
    //   19310: goto -52 -> 19258
    //   19313: bipush 59
    //   19315: wide
    //   19319: goto -61 -> 19258
    //   19322: wide
    //   19326: wide
    //   19330: caload
    //   19331: wide
    //   19335: wide
    //   19339: iconst_5
    //   19340: irem
    //   19341: tableswitch	default:+31 -> 19372, 0:+65->19406, 1:+74->19415, 2:+83->19424, 3:+92->19433
    //   19373: pop
    //   19374: wide
    //   19378: wide
    //   19382: wide
    //   19386: wide
    //   19390: wide
    //   19394: ixor
    //   19395: i2c
    //   19396: castore
    //   19397: wide
    //   19403: goto -13946 -> 5457
    //   19406: bipush 77
    //   19408: wide
    //   19412: goto -34 -> 19378
    //   19415: bipush 73
    //   19417: wide
    //   19421: goto -43 -> 19378
    //   19424: bipush 99
    //   19426: wide
    //   19430: goto -52 -> 19378
    //   19433: bipush 59
    //   19435: wide
    //   19439: goto -61 -> 19378
  }

  private boolean a(boolean paramBoolean)
    throws IOException, b
  {
    boolean bool1 = false;
    boolean bool2 = b.a;
    int i1;
    boolean bool3;
    if ((paramBoolean) && (this.k > 0))
    {
      i1 = 0;
      bool3 = false;
      if (i1 < this.k)
        if (b(bool3));
    }
    label41: label185: 
    while (true)
    {
      return bool1;
      i1++;
      if (bool2);
      for (bool3 = true; ; bool3 = false)
      {
        if (!b(bool3))
          break label185;
        if (this.f != null)
        {
          long l3 = System.currentTimeMillis();
          this.f.a(A[17]);
          this.n += System.currentTimeMillis() - l3;
        }
        long l1 = System.currentTimeMillis();
        f();
        this.r += System.currentTimeMillis() - l1;
        a(true, false);
        if (this.f != null)
        {
          long l2 = System.currentTimeMillis();
          this.f.c();
          this.o += System.currentTimeMillis() - l2;
        }
        bool1 = true;
        break label41;
        bool3 = true;
        break;
      }
    }
  }

  private boolean b(char paramChar)
  {
    if (((paramChar >= 'a') && (paramChar <= 'z')) || ((paramChar >= 'A') && (paramChar <= 'Z')));
    for (boolean bool = true; ; bool = false)
      return bool;
  }

  private String c(String paramString)
  {
    boolean bool = b.a;
    StringBuilder localStringBuilder = new StringBuilder();
    int i1 = 64;
    int i2 = 1 + paramString.indexOf(".");
    do
    {
      if (i2 >= paramString.length())
        break;
      if ((paramString.charAt(i2) >= 'A') && (paramString.charAt(i2) <= 'Z'))
      {
        localStringBuilder.append(paramString.charAt(i2));
        i1 = paramString.charAt(i2);
        if (!bool);
      }
      else
      {
        if ((paramString.charAt(i2) != '-') || (i1 != 88))
          break;
        localStringBuilder.append(paramString.charAt(i2));
      }
      i2++;
    }
    while (!bool);
    return localStringBuilder.toString();
  }

  protected String a(char paramChar)
  {
    if ((paramChar == '\\') || (paramChar == ';') || (paramChar == ':') || (paramChar == ','));
    for (String str = String.valueOf(paramChar); ; str = null)
      return str;
  }

  protected void a()
    throws IOException, b
  {
    boolean bool1 = b.a;
    for (boolean bool2 = true; ; bool2 = false)
      if (((this.j) && (!bool1)) || ((!a(bool2)) && (!bool1)) || (bool1))
      {
        int i1;
        if (this.k > 0)
          i1 = 0;
        for (boolean bool3 = true; ; bool3 = false)
          if (i1 < this.k)
          {
            a(bool3, true);
            i1++;
            if (!bool1);
          }
          else
          {
            return;
          }
      }
  }

  protected void a(String paramString1, String paramString2)
  {
    if (this.f != null)
    {
      this.f.d(paramString1);
      this.f.e(paramString2);
    }
  }

  protected void a(boolean paramBoolean1, boolean paramBoolean2)
    throws IOException, b
  {
    boolean bool = b.a;
    while (true)
    {
      String str;
      if (paramBoolean1)
      {
        str = this.e;
        if (!bool);
      }
      else
      {
        do
        {
          str = c();
          if (str == null)
            throw new b(A[32]);
        }
        while (str.trim().length() <= 0);
      }
      String[] arrayOfString = str.split(":", 2);
      if ((arrayOfString.length == 2) && (arrayOfString[0].trim().equalsIgnoreCase(A[24])) && (arrayOfString[1].trim().equalsIgnoreCase(A[17])));
      do
      {
        return;
        if (!paramBoolean2)
          throw new b(A[31] + this.e + "\"");
      }
      while (!paramBoolean2);
      paramBoolean1 = false;
    }
  }

  public boolean a(InputStream paramInputStream, String paramString, f paramf)
    throws IOException, b
  {
    this.i = new a(new InputStreamReader(paramInputStream, paramString));
    this.f = paramf;
    long l1 = System.currentTimeMillis();
    if (this.f != null)
      this.f.a();
    a();
    if (this.f != null)
      this.f.b();
    this.m += System.currentTimeMillis() - l1;
    return true;
  }

  protected boolean a(String paramString)
  {
    if ((!c.contains(paramString.toUpperCase())) && (!paramString.startsWith(A[3])) && (!this.l.contains(paramString)))
    {
      this.l.add(paramString);
      g5.c(A[44] + paramString);
    }
    return true;
  }

  protected String b()
  {
    return A[21];
  }

  protected void b(String paramString1, String paramString2)
    throws IOException, b
  {
    boolean bool = b.a;
    long l1;
    if (this.g.equalsIgnoreCase(A[4]))
    {
      long l3 = System.currentTimeMillis();
      String str2 = k(paramString2);
      if (this.f != null)
      {
        ArrayList localArrayList3 = new ArrayList();
        localArrayList3.add(str2);
        this.f.a(localArrayList3);
      }
      this.w += System.currentTimeMillis() - l3;
      if (!bool);
    }
    else if ((this.g.equalsIgnoreCase(A[0])) || (this.g.equalsIgnoreCase("B")))
    {
      l1 = System.currentTimeMillis();
    }
    try
    {
      String str1 = l(paramString2);
      if (this.f != null)
      {
        ArrayList localArrayList2 = new ArrayList();
        localArrayList2.add(str1);
        this.f.a(localArrayList2);
      }
      this.x += System.currentTimeMillis() - l1;
      if (bool)
      {
        if ((this.g != null) && (!this.g.equalsIgnoreCase(A[6])) && (!this.g.equalsIgnoreCase(A[2])) && (!this.g.toUpperCase().startsWith(A[3])))
          g5.c(A[5] + this.g + A[1]);
        long l2 = System.currentTimeMillis();
        if (this.f != null)
        {
          ArrayList localArrayList1 = new ArrayList();
          localArrayList1.add(n(paramString2));
          this.f.a(localArrayList1);
        }
        this.v += System.currentTimeMillis() - l2;
      }
      return;
    }
    catch (OutOfMemoryError localOutOfMemoryError)
    {
      while (true)
      {
        g5.d(A[7] + localOutOfMemoryError.toString());
        if (this.f != null)
          this.f.a(null);
      }
    }
  }

  protected boolean b(String paramString)
  {
    return d.contains(paramString.toUpperCase());
  }

  protected boolean b(boolean paramBoolean)
    throws IOException, b
  {
    boolean bool = false;
    label102: 
    do
    {
      String str = c();
      if (str == null);
      while (true)
      {
        return bool;
        if (str.trim().length() <= 0)
          break;
        String[] arrayOfString = str.split(":", 2);
        if ((arrayOfString.length == 2) && (arrayOfString[0].trim().equalsIgnoreCase(A[18])) && (arrayOfString[1].trim().equalsIgnoreCase(A[17])))
        {
          bool = true;
        }
        else
        {
          if (paramBoolean)
            break label142;
          if (this.k <= 0)
            break label102;
          this.e = str;
        }
      }
      throw new b(A[20] + str + A[19]);
    }
    while (paramBoolean);
    label142: throw new b(A[16]);
  }

  protected String c()
    throws IOException
  {
    return this.i.readLine();
  }

  protected void c(String paramString1, String paramString2)
    throws IOException, b
  {
    boolean bool = b.a;
    if (this.g.equalsIgnoreCase(A[4]))
      paramString2 = k(paramString2);
    Object localObject1;
    ArrayList localArrayList;
    int i2;
    char c1;
    int i3;
    Object localObject2;
    if (this.f != null)
    {
      localObject1 = new StringBuilder();
      localArrayList = new ArrayList();
      int i1 = paramString2.length();
      i2 = 0;
      if (i2 < i1)
      {
        c1 = paramString2.charAt(i2);
        if ((c1 == '\\') && (i2 < i1 - 1) && (!paramString1.equals(A[28])))
        {
          String str = a(paramString2.charAt(i2 + 1));
          if (str != null)
          {
            ((StringBuilder)localObject1).append(str);
            i2++;
            if (!bool);
          }
          else
          {
            ((StringBuilder)localObject1).append(c1);
          }
          if (!bool);
        }
        else
        {
          i3 = i2;
          if (c1 != ';')
            break label241;
          localArrayList.add(((StringBuilder)localObject1).toString());
          localObject2 = new StringBuilder();
          if (!bool)
            break label230;
        }
      }
    }
    while (true)
    {
      ((StringBuilder)localObject2).append(c1);
      localObject1 = localObject2;
      for (i2 = i3; ; i2 = i3)
      {
        i2++;
        if (!bool)
          break;
        localArrayList.add(((StringBuilder)localObject1).toString());
        this.f.a(localArrayList);
        return;
        label230: localObject1 = localObject2;
      }
      break;
      label241: localObject2 = localObject1;
    }
  }

  protected String d()
    throws IOException, b
  {
    String str;
    if (y)
    {
      y = false;
      str = z;
    }
    while (true)
    {
      return str;
      str = c();
      if (str == null)
        throw new b(A[9]);
      if (str.trim().length() <= 0)
        str = null;
    }
  }

  protected String[] d(String paramString)
    throws b, IOException
  {
    Object localObject = null;
    boolean bool = b.a;
    int i1 = paramString.length();
    String[] arrayOfString1 = new String[2];
    if (paramString.startsWith(A[26]))
    {
      String[] arrayOfString2 = paramString.split(":");
      if (arrayOfString2.length < 2)
        return localObject;
      arrayOfString1[0] = c(arrayOfString2[0]);
      arrayOfString1[1] = arrayOfString2[1].replaceAll(A[27], "");
      if (arrayOfString1[0].equals(A[28]))
      {
        if (!paramString.contains(A[25]))
          break label336;
        f(paramString.substring(1 + paramString.indexOf("="), paramString.indexOf(":")));
      }
      label336: for (int i7 = 0; ; i7 = 1)
      {
        String str5 = e();
        if ((str5 != null) && (str5.contains(A[22])))
        {
          arrayOfString1[1] = (arrayOfString1[1] + ";" + str5.substring(1 + str5.lastIndexOf(":")));
          y = false;
        }
        if (i7 != 0)
        {
          String str6 = d();
          f(str6.substring(1 + str6.lastIndexOf(":")));
        }
        if (bool)
        {
          if (arrayOfString2.length > 2)
          {
            int i6 = 2;
            do
            {
              if (i6 >= arrayOfString2.length)
                break;
              arrayOfString1[1] = (arrayOfString1[1] + ":" + arrayOfString2[i6]);
              i6++;
            }
            while (!bool);
          }
          String str4 = d();
          f(str4.substring(1 + str4.lastIndexOf(":")));
        }
        localObject = arrayOfString1;
        break;
      }
    }
    int i2 = 0;
    int i3 = 0;
    int i4 = 0;
    label351: int i5;
    if (i2 < i1)
    {
      i5 = paramString.charAt(i2);
      switch (i4)
      {
      default:
      case 0:
      case 1:
      case 2:
      }
    }
    while (true)
    {
      i2++;
      if (!bool)
        break label351;
      throw new b(A[23] + paramString + "\"");
      if (i5 == 58)
      {
        String str3 = paramString.substring(i3, i2);
        if (str3.equalsIgnoreCase(A[24]))
        {
          this.e = paramString;
          break;
        }
        arrayOfString1[0] = str3;
        if (i2 < i1 - 1)
        {
          arrayOfString1[1] = paramString.substring(i2 + 1);
          if (!bool);
        }
        else
        {
          arrayOfString1[1] = "";
        }
        localObject = arrayOfString1;
        break;
      }
      if (i5 == 46)
      {
        String str2 = paramString.substring(i3, i2);
        if (this.f != null)
          this.f.b(str2);
        i3 = i2 + 1;
        if (!bool);
      }
      else if (i5 == 59)
      {
        String str1 = paramString.substring(i3, i2);
        if (str1.equalsIgnoreCase(A[24]))
        {
          this.e = paramString;
          break;
        }
        arrayOfString1[0] = str1;
        i3 = i2 + 1;
        if (bool)
        {
          i4 = 1;
          if (i5 == 34)
          {
            if (bool)
              i4 = 2;
          }
          else
          {
            if (i5 == 59)
            {
              e(paramString.substring(i3, i2));
              i3 = i2 + 1;
              if (!bool)
                continue;
            }
            if (i5 != 58)
              continue;
            e(paramString.substring(i3, i2));
            if (i2 < i1 - 1)
            {
              arrayOfString1[1] = paramString.substring(i2 + 1);
              if (!bool);
            }
            else
            {
              arrayOfString1[1] = "";
            }
            localObject = arrayOfString1;
            break;
            if (i5 != 34)
              continue;
            i4 = 1;
            continue;
          }
          i4 = 2;
          continue;
        }
        i4 = 1;
      }
    }
  }

  protected String e()
    throws IOException, b
  {
    String str = null;
    z = null;
    z = c();
    if (z == null)
      throw new b(A[9]);
    if (z.trim().length() > 0)
    {
      y = true;
      str = z;
    }
    return str;
  }

  protected void e(String paramString)
    throws b
  {
    boolean bool = b.a;
    String[] arrayOfString = paramString.split("=", 2);
    if (arrayOfString.length == 2)
    {
      String str1 = arrayOfString[0].trim();
      String str2 = arrayOfString[1].trim();
      if (str1.equalsIgnoreCase(A[10]))
      {
        f(str2);
        if (!bool);
      }
      else if (str1.equals(A[15]))
      {
        g(str2);
        if (!bool);
      }
      else if (str1.equals(A[12]))
      {
        h(str2);
        if (!bool);
      }
      else if (str1.equals(A[8]))
      {
        i(str2);
        if (!bool);
      }
      else if (str1.equals(A[13]))
      {
        j(str2);
        if (!bool);
      }
      else if (str1.startsWith(A[3]))
      {
        a(str1, str2);
        if (!bool);
      }
      else
      {
        throw new b(A[14] + str1 + "\"");
      }
      if (!bool);
    }
    else
    {
      f(arrayOfString[0]);
    }
  }

  protected void f()
    throws IOException, b
  {
    boolean bool1 = b.a;
    if (this.f != null)
    {
      long l4 = System.currentTimeMillis();
      this.f.d();
      this.p += System.currentTimeMillis() - l4;
    }
    boolean bool2 = g();
    if ((this.f != null) && (!bool2))
    {
      long l3 = System.currentTimeMillis();
      this.f.e();
      this.q += System.currentTimeMillis() - l3;
    }
    do
    {
      do
      {
        if (bool2)
          break;
        if (this.f != null)
        {
          long l2 = System.currentTimeMillis();
          this.f.d();
          this.p += System.currentTimeMillis() - l2;
        }
        bool2 = g();
      }
      while ((this.f == null) || (bool2));
      long l1 = System.currentTimeMillis();
      this.f.e();
      this.q += System.currentTimeMillis() - l1;
    }
    while (!bool1);
  }

  protected void f(String paramString)
  {
    if ((!a.contains(paramString)) && (!paramString.startsWith(A[3])) && (!this.l.contains(paramString)))
    {
      this.l.add(paramString);
      g5.c(A[11] + paramString);
    }
    if (this.f != null)
    {
      this.f.d(A[10]);
      this.f.e(paramString);
    }
  }

  protected void g(String paramString)
    throws b
  {
    if ((b.contains(paramString.toUpperCase())) || (paramString.startsWith(A[3])))
    {
      if (this.f != null)
      {
        this.f.d(A[15]);
        this.f.e(paramString);
        if (!b.a);
      }
    }
    else
      throw new b(A[47] + paramString + "\"");
  }

  protected boolean g()
    throws IOException, b
  {
    boolean bool = true;
    this.g = A[2];
    String str1 = d();
    long l1 = System.currentTimeMillis();
    String[] arrayOfString = d(str1);
    if (arrayOfString == null);
    String str2;
    while (true)
    {
      return bool;
      if (arrayOfString.length != 2)
        throw new b(A[42] + str1 + "\"");
      str2 = arrayOfString[0].toUpperCase();
      String str3 = arrayOfString[bool];
      this.s += System.currentTimeMillis() - l1;
      if (this.f != null)
        this.f.c(str2);
      if ((str2.equals(A[28])) || (str2.equals(A[41])) || (str2.equals("N")))
      {
        long l2 = System.currentTimeMillis();
        c(str2, str3);
        this.u += System.currentTimeMillis() - l2;
        bool = false;
      }
      else if (str2.equals(A[39]))
      {
        m(str3);
        bool = false;
      }
      else
      {
        if (!a(str2))
          break;
        if (str2.equals(A[18]))
        {
          if (str3.equals(A[17]))
            throw new c(A[37]);
          throw new b(A[40] + str3);
        }
        if ((str2.equals(A[35])) && (!str3.equals(b())))
          throw new d(A[36] + str3 + A[38] + b());
        long l3 = System.currentTimeMillis();
        b(str2, str3);
        this.t += System.currentTimeMillis() - l3;
        bool = false;
      }
    }
    throw new b(A[43] + str2 + "\"");
  }

  protected void h(String paramString)
    throws b
  {
    if ((b(paramString)) || (paramString.startsWith(A[3])))
    {
      if (this.f != null)
      {
        this.f.d(A[12]);
        this.f.e(paramString);
      }
      this.g = paramString;
      if (!b.a);
    }
    else
    {
      throw new b(A[30] + paramString + "\"");
    }
  }

  protected void i(String paramString)
  {
    if (this.f != null)
    {
      this.f.d(A[8]);
      this.f.e(paramString);
    }
  }

  protected void j(String paramString)
    throws b
  {
    int i1 = 0;
    boolean bool = b.a;
    String[] arrayOfString = paramString.split("-");
    if (arrayOfString.length > 2)
      throw new b(A[29] + paramString + "\"");
    String str1 = arrayOfString[0];
    int i2 = str1.length();
    int i3 = 0;
    do
    {
      if (i3 >= i2)
        break;
      if (!b(str1.charAt(i3)))
        throw new b(A[29] + paramString + "\"");
      i3++;
    }
    while (!bool);
    if (arrayOfString.length > 1)
    {
      String str2 = arrayOfString[1];
      int i4 = str2.length();
      do
      {
        if (i1 >= i4)
          break;
        if (!b(str2.charAt(i1)))
          throw new b(A[29] + paramString + "\"");
        i1++;
      }
      while (!bool);
    }
    if (this.f != null)
    {
      this.f.d(A[13]);
      this.f.e(paramString);
    }
  }

  protected String k(String paramString)
    throws IOException, b
  {
    boolean bool = b.a;
    if (paramString.trim().endsWith("="))
    {
      int i1 = -1 + paramString.length();
      while (paramString.charAt(i1) != '=');
      StringBuilder localStringBuilder = new StringBuilder();
      localStringBuilder.append(paramString.substring(0, i1 + 1));
      localStringBuilder.append(A[46]);
      String str;
      do
      {
        str = c();
        if (str == null)
          throw new b(A[45]);
        if (!str.trim().endsWith("="))
          break;
        int i2 = -1 + str.length();
        while (str.charAt(i2) != '=');
        localStringBuilder.append(str.substring(0, i2 + 1));
        localStringBuilder.append(A[46]);
      }
      while (!bool);
      localStringBuilder.append(str);
      paramString = localStringBuilder.toString();
    }
    return paramString;
  }

  protected String l(String paramString)
    throws IOException, b
  {
    boolean bool = b.a;
    StringBuilder localStringBuilder = new StringBuilder();
    localStringBuilder.append(paramString);
    do
    {
      String str = c();
      if (str == null)
        throw new b(A[34]);
      if ((str.length() == 0) && (!bool))
        break;
      localStringBuilder.append(str);
    }
    while (!bool);
    return localStringBuilder.toString();
  }

  protected void m(String paramString)
    throws b
  {
    throw new b(A[33]);
  }

  protected String n(String paramString)
  {
    return paramString;
  }
}

/* Location:           C:\Users\Jaap\Downloads\Code\WhatsApp-2.8.4278_dex2jar.jar
 * Qualified Name:     o
 * JD-Core Version:    0.6.1
 */