// #######################################################
// Decompiled by   : coddec 
// Module          : WhatsApp-7.cod
// Module version  : 2.7.3204
// Class ID        : 17
// ########################################################


package com.whatsapp.client;


abstract final class AuthVoiceScreen$6$1 extends Object
implements Runnable

{

	// @@@@@@@@@@@@@ Fields 
	private final String /*java.lang.String[]*/  field_55496 ; // ofs = 55496 addr = 0)
	private final com.whatsapp.client.AuthVoiceScreen$6 /*com.whatsapp.client.AuthVoiceScreen$6*/  field_55500 ; // ofs = 55500 addr = 0)

	// @@@@@@@@@@@@@ Static routines 

<init>( com.whatsapp.client.AuthVoiceScreen$6$1, com.whatsapp.client.AuthVoiceScreen$6, java.lang.String[] ); // address: 0
	{
	enter_narrow 
	aload_0 
	invokespecial_lib java.lang.Object.<init> // pc=1
	aload_0 
	aload_1 
	putfield .field_1_1   // get_name_1:  .field_1_1   // get_name_2:  .field_1_1   // get_Name:    .field_1_1   // getName->1:  null   // getName->2:  null   // getName->N:  null   // ofs = -1 ord = 0 addr = 1
	aload_0 
	aload_2 
	putfield .field_0_   // get_name_1:  .field_0_   // get_name_2:  .field_0_   // get_Name:    .field_0_   // getName->1:  null   // getName->2:  null   // getName->N:  null   // ofs = -1 ord = 0 addr = 0
	return 
	}

	// @@@@@@@@@@@@@ Virtual routines 

public final run( com.whatsapp.client.AuthVoiceScreen$6$1 ); // address: 0
	{
	enter_narrow 
	aload_0_getfield .field_0_   // get_name_1:  .field_0_   // get_name_2:  .field_0_   // get_Name:    .field_0_   // getName->1:  null   // getName->2:  null   // getName->N:  null   // ofs = -1 ord = 0 addr = 0
	ifnonnull Label8
	sipush 821
	ldc literal_67:"local"
	invokestatic_lib module:WhatsApp-28.class#18.routine_4751(  ) // class#18
	invokestatic_lib alert( java.lang.String ) // Dialog
	goto Label47
Label8:
	aload_0_getfield .field_0_   // get_name_1:  .field_0_   // get_name_2:  .field_0_   // get_Name:    .field_0_   // getName->1:  null   // getName->2:  null   // getName->N:  null   // ofs = -1 ord = 0 addr = 0
	iconst_0 
	aaload 
	astore_1 
	aload_0_getfield .field_0_   // get_name_1:  .field_0_   // get_name_2:  .field_0_   // get_Name:    .field_0_   // getName->1:  null   // getName->2:  null   // getName->N:  null   // ofs = -1 ord = 0 addr = 0
	iconst_1 
	aaload 
	astore_2 
	ldc literal_68:"success-sent"
	aload_1 
	invokevirtual_short .equals // idx=1 pc=2
	ifeq Label25
	aload_0_getfield .field_1_1   // get_name_1:  .field_1_1   // get_name_2:  .field_1_1   // get_Name:    .field_1_1   // getName->1:  null   // getName->2:  null   // getName->N:  null   // ofs = -1 ord = 0 addr = 1
	getfield .field_1_1   // get_name_1:  .field_1_1   // get_name_2:  .field_1_1   // get_Name:    .field_1_1   // getName->1:  null   // getName->2:  null   // getName->N:  null   // ofs = -1 ord = 0 addr = 1
	getfield _codeEditField   // get_name_1:  _codeEditField   // get_name_2:  _codeEditField   // get_Name:    _codeEditField   // getName->1:  _codeEditField   // getName->2:  _codeEditField   // getName->N:  _codeEditField   // ofs = 55094 ord = 5 addr = 0
	invokevirtual setFocus( net.rim.device.api.ui.Field ) // pc=1
	goto Label47
Label25:
	ldc literal_55:"success-attached"
	aload_1 
	invokevirtual_short .equals // idx=1 pc=2
	ifeq Label34
	aload_0_getfield .field_1_1   // get_name_1:  .field_1_1   // get_name_2:  .field_1_1   // get_Name:    .field_1_1   // getName->1:  null   // getName->2:  null   // getName->N:  null   // ofs = -1 ord = 0 addr = 1
	getfield .field_1_1   // get_name_1:  .field_1_1   // get_name_2:  .field_1_1   // get_Name:    .field_1_1   // getName->1:  null   // getName->2:  null   // getName->N:  null   // ofs = -1 ord = 0 addr = 1
	aload_2 
	invokespecial com.whatsapp.client.AuthVoiceScreen.checkCodeAsync // pc=2
	goto Label47
Label34:
	ldc literal_69:"fail-too-recent"
	aload_1 
	invokevirtual_short .equals // idx=1 pc=2
	ifeq Label43
	sipush 864
	aload_2 
	invokestatic_lib module:WhatsApp-28.class#18.routine_4751(  ) // class#18
	invokestatic_lib inform( java.lang.String ) // Dialog
	goto Label47
Label43:
	sipush 821
	aload_1 
	invokestatic_lib module:WhatsApp-28.class#18.routine_4751(  ) // class#18
	invokestatic_lib alert( java.lang.String ) // Dialog
Label47:
	aload_0_getfield .field_1_1   // get_name_1:  .field_1_1   // get_name_2:  .field_1_1   // get_Name:    .field_1_1   // getName->1:  null   // getName->2:  null   // getName->N:  null   // ofs = -1 ord = 0 addr = 1
	getfield .field_1_1   // get_name_1:  .field_1_1   // get_name_2:  .field_1_1   // get_Name:    .field_1_1   // getName->1:  null   // getName->2:  null   // getName->N:  null   // ofs = -1 ord = 0 addr = 1
	invokespecial com.whatsapp.client.AuthVoiceScreen.showCallButton // pc=1
	aload_0_getfield .field_1_1   // get_name_1:  .field_1_1   // get_name_2:  .field_1_1   // get_Name:    .field_1_1   // getName->1:  null   // getName->2:  null   // getName->N:  null   // ofs = -1 ord = 0 addr = 1
	getfield .field_1_1   // get_name_1:  .field_1_1   // get_name_2:  .field_1_1   // get_Name:    .field_1_1   // getName->1:  null   // getName->2:  null   // getName->N:  null   // ofs = -1 ord = 0 addr = 1
	aconst_null 
	putfield _fetchDataThread   // get_name_1:  _fetchDataThread   // get_name_2:  _fetchDataThread   // get_Name:    _fetchDataThread   // getName->1:  _fetchDataThread   // getName->2:  _fetchDataThread   // getName->N:  _fetchDataThread   // ofs = 55114 ord = 10 addr = 0
	return 
	}

}
