// #######################################################
// Decompiled by   : coddec 
// Module          : WhatsApp.cod
// Module version  : 2.7.3204
// Class ID        : 15
// ########################################################


package com.whatsapp.client;


abstract public final class UIDPhone extends Object
implements net.rim.device.api.util.Persistable

{

	// @@@@@@@@@@@@@ Fields 
	public String /*java.lang.String*/  _uid ; // ofs = 55268 addr = 0)
	public String /*java.lang.String*/  _phone ; // ofs = 55272 addr = 0)

	// @@@@@@@@@@@@@ Static routines 

public <init>( com.whatsapp.client.UIDPhone, java.lang.String, java.lang.String ); // address: 0
	{
	enter_narrow 
	aload_0 
	invokespecial_lib java.lang.Object.<init> // pc=1
	aload_0 
	aload_1 
	putfield .field_0_   // get_name_1:  .field_0_   // get_name_2:  .field_0_   // get_Name:    .field_0_   // getName->1:  null   // getName->2:  null   // getName->N:  null   // ofs = -1 ord = 0 addr = 0
	aload_0 
	aload_2 
	putfield .field_1_1   // get_name_1:  .field_1_1   // get_name_2:  .field_1_1   // get_Name:    .field_1_1   // getName->1:  null   // getName->2:  null   // getName->N:  null   // ofs = -1 ord = 0 addr = 1
	return 
	}

	// @@@@@@@@@@@@@ Virtual routines 

public final boolean equals( com.whatsapp.client.UIDPhone, java.lang.Object ); // address: 0
	{
	enter_narrow 
	aload_1 
	ifnull Label20
	aload_1 
	checkcastbranch 
	astore_2 
	aload_0_getfield .field_0_   // get_name_1:  .field_0_   // get_name_2:  .field_0_   // get_Name:    .field_0_   // getName->1:  null   // getName->2:  null   // getName->N:  null   // ofs = -1 ord = 0 addr = 0
	aload_2 
	getfield .field_0_   // get_name_1:  .field_0_   // get_name_2:  .field_0_   // get_Name:    .field_0_   // getName->1:  null   // getName->2:  null   // getName->N:  null   // ofs = -1 ord = 0 addr = 0
	invokevirtual_short .equals // idx=1 pc=2
	ifeq Label18
	aload_0_getfield .field_1_1   // get_name_1:  .field_1_1   // get_name_2:  .field_1_1   // get_Name:    .field_1_1   // getName->1:  null   // getName->2:  null   // getName->N:  null   // ofs = -1 ord = 0 addr = 1
	aload_2 
	getfield .field_1_1   // get_name_1:  .field_1_1   // get_name_2:  .field_1_1   // get_Name:    .field_1_1   // getName->1:  null   // getName->2:  null   // getName->N:  null   // ofs = -1 ord = 0 addr = 1
	invokevirtual_short .equals // idx=1 pc=2
	ifeq Label18
	iconst_1 
	ireturn 
Label18:
	iconst_0 
	ireturn 
Label20:
	iconst_0 
	ireturn 
	}


public final java.lang.String toString( com.whatsapp.client.UIDPhone ); // address: 0
	{
	enter_narrow 
	new_lib net.rim.device.api.ui.Screen//net.rim.device.api.ui.Screen net.rim.device.api.ui.Screen net.rim.device.api.ui.Screen
	dup 
	invokespecial_lib java.lang.StringBuffer.<init> // pc=1
	aload_0_getfield .field_0_   // get_name_1:  .field_0_   // get_name_2:  .field_0_   // get_Name:    .field_0_   // getName->1:  null   // getName->2:  null   // getName->N:  null   // ofs = -1 ord = 0 addr = 0
	invokevirtual java.lang.StringBuffer append( java.lang.StringBuffer, java.lang.String ) // pc=2
	ldc literal_383:"."
	invokevirtual java.lang.StringBuffer append( java.lang.StringBuffer, java.lang.String ) // pc=2
	aload_0_getfield .field_1_1   // get_name_1:  .field_1_1   // get_name_2:  .field_1_1   // get_Name:    .field_1_1   // getName->1:  null   // getName->2:  null   // getName->N:  null   // ofs = -1 ord = 0 addr = 1
	invokevirtual java.lang.StringBuffer append( java.lang.StringBuffer, java.lang.String ) // pc=2
	invokevirtual_short .toString // idx=2 pc=1
	areturn 
	}


public final int hashCode( com.whatsapp.client.UIDPhone ); // address: 0
	{
	enter_narrow 
	aload_0 
	invokevirtual_short .toString // idx=2 pc=1
	invokevirtual_short .virtual_ // idx=0 pc=1
	ireturn 
	}

}
