// #######################################################
// Decompiled by   : coddec 
// Module          : WhatsApp.cod
// Module version  : 2.8.1914
// Class ID        : 20
// ########################################################


package com.whatsapp.client;


abstract final class ContactInfoDetails extends Object
implements net.rim.device.api.util.Persistable

{
	// @@@@@@@@@@@@@ Static fields 
	private static String /*java.lang.String*/  field_50728 ; // ofs = 50728 addr = 48)
	private static String /*java.lang.String*/  field_50734 ; // ofs = 50734 addr = 49)
	private static String /*java.lang.String*/  field_50740 ; // ofs = 50740 addr = 50)
	private static String /*java.lang.String*/  field_50746 ; // ofs = 50746 addr = 51)
	private static String /*java.lang.String*/  field_50752 ; // ofs = 50752 addr = 52)
	private static String /*java.lang.String*/  field_50758 ; // ofs = 50758 addr = 53)
	private static String /*java.lang.String*/  field_50764 ; // ofs = 50764 addr = 54)
	private static String /*java.lang.String*/  field_50770 ; // ofs = 50770 addr = 55)

	// @@@@@@@@@@@@@ Fields 

	// @@@@@@@@@@@@@ Static routines 

<init>( com.whatsapp.client.ContactInfoDetails ); // address: 0
	{
	enter_narrow 
	aload_0 
	invokespecial_lib java.lang.Object.<init> // pc=1
	aload_0 
	new_lib Boolean//java.lang.Boolean java.lang.Boolean java.lang.Boolean
	dup 
	invokespecial_lib java.util.Vector.<init> // pc=1
	putfield .field_6_6   // get_name_1:  .field_6_6   // get_name_2:  .field_6_6   // get_Name:    .field_6_6   // getName->1:  null   // getName->2:  null   // getName->N:  null   // ofs = -1 ord = 0 addr = 6
	aload_0 
	iconst_0 
	newarray_object_lib String//java.lang.String java.lang.String java.lang.String
	putfield .field_36_36   // get_name_1:  .field_36_36   // get_name_2:  .field_36_36   // get_Name:    .field_36_36   // getName->1:  null   // getName->2:  null   // getName->N:  null   // ofs = -1 ord = 0 addr = 36
	return 
	}


static protected final net.rim.device.api.system.EncodedImage loadImage( net.rim.blackberry.api.pdap.BlackBerryContact ); // address: 0
	{
	enter_narrow 
	aload_0 
	bipush 110
	iconst_0 
	invokeinterface interfacemethodref_15 // pc=3 guess=13
	astore_1 
	aload_1 
	ifnull Label38
	aload_1 
	arraylength 
	ifle Label38
	aload_1 
	iconst_0 
	aload_1 
	arraylength 
	invokestatic_lib byte[] decode( byte[], int, int ) // Base64InputStream
	astore_2 
	aload_2 
	ifnull Label38
	aload_2 
	arraylength 
	ifle Label38
	aload_2 
	iconst_0 
	aload_2 
	arraylength 
	invokestatic_lib net.rim.device.api.system.EncodedImage createEncodedImage( byte[], int, int ) // EncodedImage
	areturn 
	astore_1 
	new_lib net.rim.device.api.ui.decor.Background//net.rim.device.api.ui.decor.Background net.rim.device.api.ui.decor.Background net.rim.device.api.ui.decor.Background
	dup 
	ldc literal_152:"error creating photo from contact: "
	invokespecial_lib java.lang.StringBuffer.<init> // pc=2
	aload_1 
	invokevirtual_short .toString // idx=2 pc=1
	invokevirtual java.lang.StringBuffer append( java.lang.StringBuffer, java.lang.String ) // pc=2
	invokevirtual_short .toString // idx=2 pc=1
	invokestatic_lib module:WhatsApp-79.class#39.routine_24694(  ) // class#39
Label38:
	aconst_null 
	areturn 
	}


static final <clinit>(  ); // address: 0
	{
	enter 
	synch_static ContactInfoDetails
	clinit_wait 
	ldc literal_153:";"
	putstatic com.whatsapp.client.ContactInfoDetails.field_50728 // ContactInfoDetails
	ldc literal_154:"\r\n"
	putstatic com.whatsapp.client.ContactInfoDetails.field_50734 // ContactInfoDetails
	ldc literal_155:"BEGIN:VCARD??VERSION:3.0??"
	putstatic com.whatsapp.client.ContactInfoDetails.field_50740 // ContactInfoDetails
	ldc literal_156:"FN:"
	putstatic com.whatsapp.client.ContactInfoDetails.field_50746 // ContactInfoDetails
	ldc literal_157:"N:"
	putstatic com.whatsapp.client.ContactInfoDetails.field_50752 // ContactInfoDetails
	ldc literal_158:"ORG:"
	putstatic com.whatsapp.client.ContactInfoDetails.field_50758 // ContactInfoDetails
	ldc literal_159:"TITLE:"
	putstatic com.whatsapp.client.ContactInfoDetails.field_50764 // ContactInfoDetails
	ldc literal_160:"END:VCARD"
	putstatic com.whatsapp.client.ContactInfoDetails.field_50770 // ContactInfoDetails
	clinit_return 
	}

	// @@@@@@@@@@@@@ Non-virtual routines 

private final com.whatsapp.client.ContactInfoDetails.routine_11753( com.whatsapp.client.ContactInfoDetails, module:WhatsApp-21.class#0, java.lang.String, int, module:WhatsApp-12.class#30[] ); // address: 0
	{
	enter 
	aload_2 
	ifnull Label18
	aload_1 
	aload_2 
	invokenonvirtual_lib .routine_478 // pc=2
	astore_5 
	aload_5 
	ifnull Label18
	aload_4 
	new_lib com.whatsapp.client.//module:WhatsApp-12.class#30 module:WhatsApp-12.class#30 module:WhatsApp-12.class#30
	dup 
	aload_0 
	aload_5 
	iload_3 
	invokestatic_lib module:WhatsApp-47.class#11.routine_4387(  ) // class#11
	invokespecial_lib .routine_5658 // pc=4
	invokestatic_lib add( java.lang.Object[], java.lang.Object ) // Arrays
Label18:
	return 
	}


private final module:WhatsApp-18.class#1 com.whatsapp.client.ContactInfoDetails.routine_11806( com.whatsapp.client.ContactInfoDetails, int, int ); // address: 0
	{
	enter 
	new_lib com.whatsapp.client.//module:WhatsApp-18.class#1 module:WhatsApp-18.class#1 module:WhatsApp-18.class#1
	dup 
	iload_2 
	invokespecial_lib .routine_3660 // pc=2
	astore_3 
	aload_3 
	iconst_0 
	putfield .field_4_4   // get_name_1:  .field_4_4   // get_name_2:  .field_4_4   // get_Name:    .field_4_4   // getName->1:  null   // getName->2:  null   // getName->N:  null   // ofs = -1 ord = 0 addr = 4
	aload_3 
	aload_0 
	iload_1 
	invokenonvirtual com.whatsapp.client.ContactInfoDetails.getFullName // pc=2
	putfield .field_3_3   // get_name_1:  .field_3_3   // get_name_2:  .field_3_3   // get_Name:    .field_3_3   // getName->1:  null   // getName->2:  null   // getName->N:  null   // ofs = -1 ord = 0 addr = 3
	aload_3 
	aload_3 
	getfield .field_3_3   // get_name_1:  .field_3_3   // get_name_2:  .field_3_3   // get_Name:    .field_3_3   // getName->1:  null   // getName->2:  null   // getName->N:  null   // ofs = -1 ord = 0 addr = 3
	putfield .field_2_2   // get_name_1:  .field_2_2   // get_name_2:  .field_2_2   // get_Name:    .field_2_2   // getName->1:  null   // getName->2:  null   // getName->N:  null   // ofs = -1 ord = 0 addr = 2
	aload_3 
	aload_0_getfield .field_0_   // get_name_1:  .field_0_   // get_name_2:  .field_0_   // get_Name:    .field_0_   // getName->1:  null   // getName->2:  null   // getName->N:  null   // ofs = -1 ord = 0 addr = 0
	putfield .field_1_1   // get_name_1:  .field_1_1   // get_name_2:  .field_1_1   // get_Name:    .field_1_1   // getName->1:  null   // getName->2:  null   // getName->N:  null   // ofs = -1 ord = 0 addr = 1
	aload_3 
	areturn 
	}


private final com.whatsapp.client.ContactInfoDetails.routine_11858( com.whatsapp.client.ContactInfoDetails, java.util.Vector, java.lang.String, int, java.lang.String, int ); // address: 0
	{
	enter 
	aload_2 
	ifnull Label26
	new_lib com.whatsapp.client.ContactInfoDetailsListItem//module:WhatsApp-18.class#1 module:WhatsApp-18.class#1 module:WhatsApp-18.class#1
	dup 
	iload_5 
	invokespecial_lib .routine_3660 // pc=2
	astore_6 
	aload_6 
	iload_3 
	putfield .field_4_4   // get_name_1:  .field_4_4   // get_name_2:  .field_4_4   // get_Name:    .field_4_4   // getName->1:  null   // getName->2:  null   // getName->N:  null   // ofs = -1 ord = 0 addr = 4
	aload_6 
	aload_2 
	putfield .field_3_3   // get_name_1:  .field_3_3   // get_name_2:  .field_3_3   // get_Name:    .field_3_3   // getName->1:  null   // getName->2:  null   // getName->N:  null   // ofs = -1 ord = 0 addr = 3
	aload_6 
	sipush 334
	aload_2 
	aload_4 
	invokestatic_lib module:WhatsApp-47.class#11.routine_4492(  ) // class#11
	putfield .field_2_2   // get_name_1:  .field_2_2   // get_name_2:  .field_2_2   // get_Name:    .field_2_2   // getName->1:  null   // getName->2:  null   // getName->N:  null   // ofs = -1 ord = 0 addr = 2
	aload_6 
	aload_0_getfield .field_0_   // get_name_1:  .field_0_   // get_name_2:  .field_0_   // get_Name:    .field_0_   // getName->1:  null   // getName->2:  null   // getName->N:  null   // ofs = -1 ord = 0 addr = 0
	putfield .field_1_1   // get_name_1:  .field_1_1   // get_name_2:  .field_1_1   // get_Name:    .field_1_1   // getName->1:  null   // getName->2:  null   // getName->N:  null   // ofs = -1 ord = 0 addr = 1
	aload_1 
	aload_6 
	invokevirtual addElement( java.util.Vector, java.lang.Object ) // pc=2
Label26:
	return 
	}


private final java.lang.String com.whatsapp.client.ContactInfoDetails.routine_11920( com.whatsapp.client.ContactInfoDetails, java.lang.String ); // address: 0
	{
	enter 
	aload_1 
	bipush 59
	invokenonvirtual_lib java.lang.String.indexOf // pc=2
	istore_2 
	iload_2 
	bipush -1
	if_icmpne Label10
	aload_1 
	areturn 
Label10:
	new_lib net.rim.device.api.ui.decor.Background//net.rim.device.api.ui.decor.Background net.rim.device.api.ui.decor.Background net.rim.device.api.ui.decor.Background
	dup 
	invokespecial_lib java.lang.StringBuffer.<init> // pc=1
	aload_1 
	iconst_0 
	iload_2 
	invokenonvirtual_lib java.lang.String.substring // pc=3
	invokevirtual java.lang.StringBuffer append( java.lang.StringBuffer, java.lang.String ) // pc=2
	ldc literal_151:"\;"
	invokevirtual java.lang.StringBuffer append( java.lang.StringBuffer, java.lang.String ) // pc=2
	aload_0 
	aload_1 
	iload_2 
	iconst_1 
	iadd 
	invokenonvirtual_lib java.lang.String.substring // pc=2
	invokespecial com.whatsapp.client.ContactInfoDetails.routine_11920 // pc=2
	invokevirtual java.lang.StringBuffer append( java.lang.StringBuffer, java.lang.String ) // pc=2
	invokevirtual_short .toString // idx=2 pc=1
	areturn 
	}

	// @@@@@@@@@@@@@ Virtual routines 

final clearDetails( com.whatsapp.client.ContactInfoDetails ); // address: 0
	{
	enter_narrow 
	aload_0 
	aconst_null 
	putfield .field_0_   // get_name_1:  .field_0_   // get_name_2:  .field_0_   // get_Name:    .field_0_   // getName->1:  null   // getName->2:  null   // getName->N:  null   // ofs = -1 ord = 0 addr = 0
	aload_0 
	aconst_null 
	putfield .field_1_1   // get_name_1:  .field_1_1   // get_name_2:  .field_1_1   // get_Name:    .field_1_1   // getName->1:  null   // getName->2:  null   // getName->N:  null   // ofs = -1 ord = 0 addr = 1
	aload_0 
	aconst_null 
	putfield .field_2_2   // get_name_1:  .field_2_2   // get_name_2:  .field_2_2   // get_Name:    .field_2_2   // getName->1:  null   // getName->2:  null   // getName->N:  null   // ofs = -1 ord = 0 addr = 2
	aload_0 
	aconst_null 
	putfield .field_3_3   // get_name_1:  .field_3_3   // get_name_2:  .field_3_3   // get_Name:    .field_3_3   // getName->1:  null   // getName->2:  null   // getName->N:  null   // ofs = -1 ord = 0 addr = 3
	aload_0 
	aconst_null 
	putfield .field_4_4   // get_name_1:  .field_4_4   // get_name_2:  .field_4_4   // get_Name:    .field_4_4   // getName->1:  null   // getName->2:  null   // getName->N:  null   // ofs = -1 ord = 0 addr = 4
	aload_0 
	aconst_null 
	putfield .field_5_5   // get_name_1:  .field_5_5   // get_name_2:  .field_5_5   // get_Name:    .field_5_5   // getName->1:  null   // getName->2:  null   // getName->N:  null   // ofs = -1 ord = 0 addr = 5
	aload_0_getfield .field_6_6   // get_name_1:  .field_6_6   // get_name_2:  .field_6_6   // get_Name:    .field_6_6   // getName->1:  null   // getName->2:  null   // getName->N:  null   // ofs = -1 ord = 0 addr = 6
	invokevirtual removeAllElements( java.util.Vector ) // pc=1
	aload_0 
	aconst_null 
	putfield .field_7_7   // get_name_1:  .field_7_7   // get_name_2:  .field_7_7   // get_Name:    .field_7_7   // getName->1:  null   // getName->2:  null   // getName->N:  null   // ofs = -1 ord = 0 addr = 7
	aload_0 
	aconst_null 
	putfield .field_8_8   // get_name_1:  .field_8_8   // get_name_2:  .field_8_8   // get_Name:    .field_8_8   // getName->1:  null   // getName->2:  null   // getName->N:  null   // ofs = -1 ord = 0 addr = 8
	aload_0 
	aconst_null 
	putfield .field_9_9   // get_name_1:  .field_9_9   // get_name_2:  .field_9_9   // get_Name:    .field_9_9   // getName->1:  null   // getName->2:  null   // getName->N:  null   // ofs = -1 ord = 0 addr = 9
	aload_0 
	aconst_null 
	putfield .field_10_10   // get_name_1:  .field_10_10   // get_name_2:  .field_10_10   // get_Name:    .field_10_10   // getName->1:  null   // getName->2:  null   // getName->N:  null   // ofs = -1 ord = 0 addr = 10
	aload_0 
	aconst_null 
	putfield .field_11_11   // get_name_1:  .field_11_11   // get_name_2:  .field_11_11   // get_Name:    .field_11_11   // getName->1:  null   // getName->2:  null   // getName->N:  null   // ofs = -1 ord = 0 addr = 11
	aload_0 
	aconst_null 
	putfield .field_13_13   // get_name_1:  .field_13_13   // get_name_2:  .field_13_13   // get_Name:    .field_13_13   // getName->1:  null   // getName->2:  null   // getName->N:  null   // ofs = -1 ord = 0 addr = 13
	aload_0 
	aconst_null 
	putfield .field_14_14   // get_name_1:  .field_14_14   // get_name_2:  .field_14_14   // get_Name:    .field_14_14   // getName->1:  null   // getName->2:  null   // getName->N:  null   // ofs = -1 ord = 0 addr = 14
	aload_0 
	aconst_null 
	putfield .field_16_16   // get_name_1:  .field_16_16   // get_name_2:  .field_16_16   // get_Name:    .field_16_16   // getName->1:  null   // getName->2:  null   // getName->N:  null   // ofs = -1 ord = 0 addr = 16
	aload_0 
	aconst_null 
	putfield .field_17_17   // get_name_1:  .field_17_17   // get_name_2:  .field_17_17   // get_Name:    .field_17_17   // getName->1:  null   // getName->2:  null   // getName->N:  null   // ofs = -1 ord = 0 addr = 17
	aload_0 
	aconst_null 
	putfield .field_18_18   // get_name_1:  .field_18_18   // get_name_2:  .field_18_18   // get_Name:    .field_18_18   // getName->1:  null   // getName->2:  null   // getName->N:  null   // ofs = -1 ord = 0 addr = 18
	aload_0 
	aconst_null 
	putfield .field_19_19   // get_name_1:  .field_19_19   // get_name_2:  .field_19_19   // get_Name:    .field_19_19   // getName->1:  null   // getName->2:  null   // getName->N:  null   // ofs = -1 ord = 0 addr = 19
	aload_0 
	aconst_null 
	putfield .field_20_20   // get_name_1:  .field_20_20   // get_name_2:  .field_20_20   // get_Name:    .field_20_20   // getName->1:  null   // getName->2:  null   // getName->N:  null   // ofs = -1 ord = 0 addr = 20
	aload_0 
	aconst_null 
	putfield .field_21_21   // get_name_1:  .field_21_21   // get_name_2:  .field_21_21   // get_Name:    .field_21_21   // getName->1:  null   // getName->2:  null   // getName->N:  null   // ofs = -1 ord = 0 addr = 21
	aload_0 
	aconst_null 
	putfield .field_22_22   // get_name_1:  .field_22_22   // get_name_2:  .field_22_22   // get_Name:    .field_22_22   // getName->1:  null   // getName->2:  null   // getName->N:  null   // ofs = -1 ord = 0 addr = 22
	aload_0 
	aconst_null 
	putfield .field_23_23   // get_name_1:  .field_23_23   // get_name_2:  .field_23_23   // get_Name:    .field_23_23   // getName->1:  null   // getName->2:  null   // getName->N:  null   // ofs = -1 ord = 0 addr = 23
	aload_0 
	aconst_null 
	putfield .field_24_24   // get_name_1:  .field_24_24   // get_name_2:  .field_24_24   // get_Name:    .field_24_24   // getName->1:  null   // getName->2:  null   // getName->N:  null   // ofs = -1 ord = 0 addr = 24
	aload_0 
	aconst_null 
	putfield .field_25_25   // get_name_1:  .field_25_25   // get_name_2:  .field_25_25   // get_Name:    .field_25_25   // getName->1:  null   // getName->2:  null   // getName->N:  null   // ofs = -1 ord = 0 addr = 25
	aload_0 
	aconst_null 
	putfield .field_26_26   // get_name_1:  .field_26_26   // get_name_2:  .field_26_26   // get_Name:    .field_26_26   // getName->1:  null   // getName->2:  null   // getName->N:  null   // ofs = -1 ord = 0 addr = 26
	aload_0 
	aconst_null 
	putfield .field_27_27   // get_name_1:  .field_27_27   // get_name_2:  .field_27_27   // get_Name:    .field_27_27   // getName->1:  null   // getName->2:  null   // getName->N:  null   // ofs = -1 ord = 0 addr = 27
	aload_0 
	aconst_null 
	putfield .field_28_28   // get_name_1:  .field_28_28   // get_name_2:  .field_28_28   // get_Name:    .field_28_28   // getName->1:  null   // getName->2:  null   // getName->N:  null   // ofs = -1 ord = 0 addr = 28
	aload_0 
	aconst_null 
	putfield .field_29_29   // get_name_1:  .field_29_29   // get_name_2:  .field_29_29   // get_Name:    .field_29_29   // getName->1:  null   // getName->2:  null   // getName->N:  null   // ofs = -1 ord = 0 addr = 29
	aload_0 
	iconst_0 
	i2l 
	lputfield .field_30_30   // get_name_1:  .field_30_30   // get_name_2:  .field_30_30   // get_Name:    .field_30_30   // getName->1:  null   // getName->2:  null   // getName->N:  null   // ofs = -1 ord = 0 addr = 30
	aload_0 
	iconst_0 
	putfield .field_32_32   // get_name_1:  .field_32_32   // get_name_2:  .field_32_32   // get_Name:    .field_32_32   // getName->1:  null   // getName->2:  null   // getName->N:  null   // ofs = -1 ord = 0 addr = 32
	aload_0 
	iconst_0 
	i2l 
	lputfield .field_33_33   // get_name_1:  .field_33_33   // get_name_2:  .field_33_33   // get_Name:    .field_33_33   // getName->1:  null   // getName->2:  null   // getName->N:  null   // ofs = -1 ord = 0 addr = 33
	aload_0 
	iconst_0 
	putfield .field_35_35   // get_name_1:  .field_35_35   // get_name_2:  .field_35_35   // get_Name:    .field_35_35   // getName->1:  null   // getName->2:  null   // getName->N:  null   // ofs = -1 ord = 0 addr = 35
	aload_0 
	iconst_0 
	newarray_object_lib String//java.lang.String java.lang.String java.lang.String
	putfield .field_36_36   // get_name_1:  .field_36_36   // get_name_2:  .field_36_36   // get_Name:    .field_36_36   // getName->1:  null   // getName->2:  null   // getName->N:  null   // ofs = -1 ord = 0 addr = 36
	aload_0 
	aconst_null 
	putfield .field_37_37   // get_name_1:  .field_37_37   // get_name_2:  .field_37_37   // get_Name:    .field_37_37   // getName->1:  null   // getName->2:  null   // getName->N:  null   // ofs = -1 ord = 0 addr = 37
	aload_0 
	aconst_null 
	putfield .field_38_38   // get_name_1:  .field_38_38   // get_name_2:  .field_38_38   // get_Name:    .field_38_38   // getName->1:  null   // getName->2:  null   // getName->N:  null   // ofs = -1 ord = 0 addr = 38
	aload_0 
	aconst_null 
	putfield .field_39_39   // get_name_1:  .field_39_39   // get_name_2:  .field_39_39   // get_Name:    .field_39_39   // getName->1:  null   // getName->2:  null   // getName->N:  null   // ofs = -1 ord = 0 addr = 39
	aload_0 
	aconst_null 
	putfield .field_40_40   // get_name_1:  .field_40_40   // get_name_2:  .field_40_40   // get_Name:    .field_40_40   // getName->1:  null   // getName->2:  null   // getName->N:  null   // ofs = -1 ord = 0 addr = 40
	aload_0 
	aconst_null 
	putfield .field_41_41   // get_name_1:  .field_41_41   // get_name_2:  .field_41_41   // get_Name:    .field_41_41   // getName->1:  null   // getName->2:  null   // getName->N:  null   // ofs = -1 ord = 0 addr = 41
	aload_0 
	aconst_null 
	putfield .field_42_42   // get_name_1:  .field_42_42   // get_name_2:  .field_42_42   // get_Name:    .field_42_42   // getName->1:  null   // getName->2:  null   // getName->N:  null   // ofs = -1 ord = 0 addr = 42
	return 
	}


public final boolean equals( com.whatsapp.client.ContactInfoDetails, java.lang.Object ); // address: 0
	{
	enter 
	aload_1 
	checkcastbranch 
	astore_2 
	aload_0_getfield .field_0_   // get_name_1:  .field_0_   // get_name_2:  .field_0_   // get_Name:    .field_0_   // getName->1:  null   // getName->2:  null   // getName->N:  null   // ofs = -1 ord = 0 addr = 0
	aload_2 
	getfield .field_0_   // get_name_1:  .field_0_   // get_name_2:  .field_0_   // get_Name:    .field_0_   // getName->1:  null   // getName->2:  null   // getName->N:  null   // ofs = -1 ord = 0 addr = 0
	invokestatic_lib boolean strEqual( java.lang.String, java.lang.String ) // StringUtilities
	ifne Label11
	iconst_0 
	ireturn 
Label11:
	aload_0_getfield .field_1_1   // get_name_1:  .field_1_1   // get_name_2:  .field_1_1   // get_Name:    .field_1_1   // getName->1:  null   // getName->2:  null   // getName->N:  null   // ofs = -1 ord = 0 addr = 1
	aload_2 
	getfield .field_1_1   // get_name_1:  .field_1_1   // get_name_2:  .field_1_1   // get_Name:    .field_1_1   // getName->1:  null   // getName->2:  null   // getName->N:  null   // ofs = -1 ord = 0 addr = 1
	invokestatic_lib boolean strEqual( java.lang.String, java.lang.String ) // StringUtilities
	ifne Label18
	iconst_0 
	ireturn 
Label18:
	aload_0_getfield .field_2_2   // get_name_1:  .field_2_2   // get_name_2:  .field_2_2   // get_Name:    .field_2_2   // getName->1:  null   // getName->2:  null   // getName->N:  null   // ofs = -1 ord = 0 addr = 2
	aload_2 
	getfield .field_2_2   // get_name_1:  .field_2_2   // get_name_2:  .field_2_2   // get_Name:    .field_2_2   // getName->1:  null   // getName->2:  null   // getName->N:  null   // ofs = -1 ord = 0 addr = 2
	invokestatic_lib boolean strEqual( java.lang.String, java.lang.String ) // StringUtilities
	ifne Label25
	iconst_0 
	ireturn 
Label25:
	aload_0_getfield .field_3_3   // get_name_1:  .field_3_3   // get_name_2:  .field_3_3   // get_Name:    .field_3_3   // getName->1:  null   // getName->2:  null   // getName->N:  null   // ofs = -1 ord = 0 addr = 3
	aload_2 
	getfield .field_3_3   // get_name_1:  .field_3_3   // get_name_2:  .field_3_3   // get_Name:    .field_3_3   // getName->1:  null   // getName->2:  null   // getName->N:  null   // ofs = -1 ord = 0 addr = 3
	invokestatic_lib boolean strEqual( java.lang.String, java.lang.String ) // StringUtilities
	ifne Label32
	iconst_0 
	ireturn 
Label32:
	aload_0_getfield .field_4_4   // get_name_1:  .field_4_4   // get_name_2:  .field_4_4   // get_Name:    .field_4_4   // getName->1:  null   // getName->2:  null   // getName->N:  null   // ofs = -1 ord = 0 addr = 4
	aload_2 
	getfield .field_4_4   // get_name_1:  .field_4_4   // get_name_2:  .field_4_4   // get_Name:    .field_4_4   // getName->1:  null   // getName->2:  null   // getName->N:  null   // ofs = -1 ord = 0 addr = 4
	invokestatic_lib boolean strEqual( java.lang.String, java.lang.String ) // StringUtilities
	ifne Label39
	iconst_0 
	ireturn 
Label39:
	aload_0_getfield .field_5_5   // get_name_1:  .field_5_5   // get_name_2:  .field_5_5   // get_Name:    .field_5_5   // getName->1:  null   // getName->2:  null   // getName->N:  null   // ofs = -1 ord = 0 addr = 5
	aload_2 
	getfield .field_5_5   // get_name_1:  .field_5_5   // get_name_2:  .field_5_5   // get_Name:    .field_5_5   // getName->1:  null   // getName->2:  null   // getName->N:  null   // ofs = -1 ord = 0 addr = 5
	invokestatic_lib boolean strEqual( java.lang.String, java.lang.String ) // StringUtilities
	ifne Label46
	iconst_0 
	ireturn 
Label46:
	aload_2 
	getfield .field_6_6   // get_name_1:  .field_6_6   // get_name_2:  .field_6_6   // get_Name:    .field_6_6   // getName->1:  null   // getName->2:  null   // getName->N:  null   // ofs = -1 ord = 0 addr = 6
	astore_3 
	aload_3 
	invokevirtual int size( java.util.Vector ) // pc=1
	aload_0_getfield .field_6_6   // get_name_1:  .field_6_6   // get_name_2:  .field_6_6   // get_Name:    .field_6_6   // getName->1:  null   // getName->2:  null   // getName->N:  null   // ofs = -1 ord = 0 addr = 6
	invokevirtual int size( java.util.Vector ) // pc=1
	if_icmpeq Label56
	iconst_0 
	ireturn 
Label56:
	aload_0_getfield .field_6_6   // get_name_1:  .field_6_6   // get_name_2:  .field_6_6   // get_Name:    .field_6_6   // getName->1:  null   // getName->2:  null   // getName->N:  null   // ofs = -1 ord = 0 addr = 6
	invokevirtual int size( java.util.Vector ) // pc=1
	istore_4 
	iload_4 
	iconst_1 
	isub 
	istore_5 
Label63:
	iload_5 
	iflt Label79
	aload_0_getfield .field_6_6   // get_name_1:  .field_6_6   // get_name_2:  .field_6_6   // get_Name:    .field_6_6   // getName->1:  null   // getName->2:  null   // getName->N:  null   // ofs = -1 ord = 0 addr = 6
	iload_5 
	invokevirtual java.lang.Object elementAt( java.util.Vector, int ) // pc=2
	checkcast_lib String//java.lang.String java.lang.String java.lang.String
	aload_3 
	iload_5 
	invokevirtual java.lang.Object elementAt( java.util.Vector, int ) // pc=2
	checkcast_lib String//java.lang.String java.lang.String java.lang.String
	invokestatic_lib boolean strEqual( java.lang.String, java.lang.String ) // StringUtilities
	ifne Label77
	iconst_0 
	ireturn 
Label77:
	iinc 5 -1
	goto Label63
Label79:
	aload_0 
	aload_2 
	invokenonvirtual com.whatsapp.client.ContactInfoDetails.equalPhones // pc=2
	ifne Label85
	iconst_0 
	ireturn 
Label85:
	aload_0_getfield .field_17_17   // get_name_1:  .field_17_17   // get_name_2:  .field_17_17   // get_Name:    .field_17_17   // getName->1:  null   // getName->2:  null   // getName->N:  null   // ofs = -1 ord = 0 addr = 17
	aload_2 
	getfield .field_17_17   // get_name_1:  .field_17_17   // get_name_2:  .field_17_17   // get_Name:    .field_17_17   // getName->1:  null   // getName->2:  null   // getName->N:  null   // ofs = -1 ord = 0 addr = 17
	invokestatic_lib boolean strEqual( java.lang.String, java.lang.String ) // StringUtilities
	ifne Label92
	iconst_0 
	ireturn 
Label92:
	aload_0_getfield .field_18_18   // get_name_1:  .field_18_18   // get_name_2:  .field_18_18   // get_Name:    .field_18_18   // getName->1:  null   // getName->2:  null   // getName->N:  null   // ofs = -1 ord = 0 addr = 18
	aload_2 
	getfield .field_18_18   // get_name_1:  .field_18_18   // get_name_2:  .field_18_18   // get_Name:    .field_18_18   // getName->1:  null   // getName->2:  null   // getName->N:  null   // ofs = -1 ord = 0 addr = 18
	invokestatic_lib boolean strEqual( java.lang.String, java.lang.String ) // StringUtilities
	ifne Label99
	iconst_0 
	ireturn 
Label99:
	aload_0_getfield .field_19_19   // get_name_1:  .field_19_19   // get_name_2:  .field_19_19   // get_Name:    .field_19_19   // getName->1:  null   // getName->2:  null   // getName->N:  null   // ofs = -1 ord = 0 addr = 19
	aload_2 
	getfield .field_19_19   // get_name_1:  .field_19_19   // get_name_2:  .field_19_19   // get_Name:    .field_19_19   // getName->1:  null   // getName->2:  null   // getName->N:  null   // ofs = -1 ord = 0 addr = 19
	invokestatic_lib boolean strEqual( java.lang.String, java.lang.String ) // StringUtilities
	ifne Label106
	iconst_0 
	ireturn 
Label106:
	aload_0_getfield .field_20_20   // get_name_1:  .field_20_20   // get_name_2:  .field_20_20   // get_Name:    .field_20_20   // getName->1:  null   // getName->2:  null   // getName->N:  null   // ofs = -1 ord = 0 addr = 20
	aload_2 
	getfield .field_20_20   // get_name_1:  .field_20_20   // get_name_2:  .field_20_20   // get_Name:    .field_20_20   // getName->1:  null   // getName->2:  null   // getName->N:  null   // ofs = -1 ord = 0 addr = 20
	invokestatic_lib boolean strEqual( java.lang.String, java.lang.String ) // StringUtilities
	ifne Label113
	iconst_0 
	ireturn 
Label113:
	aload_0_getfield .field_21_21   // get_name_1:  .field_21_21   // get_name_2:  .field_21_21   // get_Name:    .field_21_21   // getName->1:  null   // getName->2:  null   // getName->N:  null   // ofs = -1 ord = 0 addr = 21
	aload_2 
	getfield .field_21_21   // get_name_1:  .field_21_21   // get_name_2:  .field_21_21   // get_Name:    .field_21_21   // getName->1:  null   // getName->2:  null   // getName->N:  null   // ofs = -1 ord = 0 addr = 21
	invokestatic_lib boolean strEqual( java.lang.String, java.lang.String ) // StringUtilities
	ifne Label120
	iconst_0 
	ireturn 
Label120:
	aload_0_getfield .field_22_22   // get_name_1:  .field_22_22   // get_name_2:  .field_22_22   // get_Name:    .field_22_22   // getName->1:  null   // getName->2:  null   // getName->N:  null   // ofs = -1 ord = 0 addr = 22
	aload_2 
	getfield .field_22_22   // get_name_1:  .field_22_22   // get_name_2:  .field_22_22   // get_Name:    .field_22_22   // getName->1:  null   // getName->2:  null   // getName->N:  null   // ofs = -1 ord = 0 addr = 22
	invokestatic_lib boolean strEqual( java.lang.String, java.lang.String ) // StringUtilities
	ifne Label127
	iconst_0 
	ireturn 
Label127:
	aload_0_getfield .field_23_23   // get_name_1:  .field_23_23   // get_name_2:  .field_23_23   // get_Name:    .field_23_23   // getName->1:  null   // getName->2:  null   // getName->N:  null   // ofs = -1 ord = 0 addr = 23
	aload_2 
	getfield .field_23_23   // get_name_1:  .field_23_23   // get_name_2:  .field_23_23   // get_Name:    .field_23_23   // getName->1:  null   // getName->2:  null   // getName->N:  null   // ofs = -1 ord = 0 addr = 23
	invokestatic_lib boolean strEqual( java.lang.String, java.lang.String ) // StringUtilities
	ifne Label134
	iconst_0 
	ireturn 
Label134:
	aload_0_getfield .field_24_24   // get_name_1:  .field_24_24   // get_name_2:  .field_24_24   // get_Name:    .field_24_24   // getName->1:  null   // getName->2:  null   // getName->N:  null   // ofs = -1 ord = 0 addr = 24
	aload_2 
	getfield .field_24_24   // get_name_1:  .field_24_24   // get_name_2:  .field_24_24   // get_Name:    .field_24_24   // getName->1:  null   // getName->2:  null   // getName->N:  null   // ofs = -1 ord = 0 addr = 24
	invokestatic_lib boolean strEqual( java.lang.String, java.lang.String ) // StringUtilities
	ifne Label141
	iconst_0 
	ireturn 
Label141:
	aload_0_getfield .field_25_25   // get_name_1:  .field_25_25   // get_name_2:  .field_25_25   // get_Name:    .field_25_25   // getName->1:  null   // getName->2:  null   // getName->N:  null   // ofs = -1 ord = 0 addr = 25
	aload_2 
	getfield .field_25_25   // get_name_1:  .field_25_25   // get_name_2:  .field_25_25   // get_Name:    .field_25_25   // getName->1:  null   // getName->2:  null   // getName->N:  null   // ofs = -1 ord = 0 addr = 25
	invokestatic_lib boolean strEqual( java.lang.String, java.lang.String ) // StringUtilities
	ifne Label148
	iconst_0 
	ireturn 
Label148:
	aload_0_getfield .field_26_26   // get_name_1:  .field_26_26   // get_name_2:  .field_26_26   // get_Name:    .field_26_26   // getName->1:  null   // getName->2:  null   // getName->N:  null   // ofs = -1 ord = 0 addr = 26
	aload_2 
	getfield .field_26_26   // get_name_1:  .field_26_26   // get_name_2:  .field_26_26   // get_Name:    .field_26_26   // getName->1:  null   // getName->2:  null   // getName->N:  null   // ofs = -1 ord = 0 addr = 26
	invokestatic_lib boolean strEqual( java.lang.String, java.lang.String ) // StringUtilities
	ifne Label155
	iconst_0 
	ireturn 
Label155:
	aload_0_getfield .field_27_27   // get_name_1:  .field_27_27   // get_name_2:  .field_27_27   // get_Name:    .field_27_27   // getName->1:  null   // getName->2:  null   // getName->N:  null   // ofs = -1 ord = 0 addr = 27
	aload_2 
	getfield .field_27_27   // get_name_1:  .field_27_27   // get_name_2:  .field_27_27   // get_Name:    .field_27_27   // getName->1:  null   // getName->2:  null   // getName->N:  null   // ofs = -1 ord = 0 addr = 27
	invokestatic_lib boolean strEqual( java.lang.String, java.lang.String ) // StringUtilities
	ifne Label162
	iconst_0 
	ireturn 
Label162:
	aload_0_getfield .field_28_28   // get_name_1:  .field_28_28   // get_name_2:  .field_28_28   // get_Name:    .field_28_28   // getName->1:  null   // getName->2:  null   // getName->N:  null   // ofs = -1 ord = 0 addr = 28
	aload_2 
	getfield .field_28_28   // get_name_1:  .field_28_28   // get_name_2:  .field_28_28   // get_Name:    .field_28_28   // getName->1:  null   // getName->2:  null   // getName->N:  null   // ofs = -1 ord = 0 addr = 28
	invokestatic_lib boolean strEqual( java.lang.String, java.lang.String ) // StringUtilities
	ifne Label169
	iconst_0 
	ireturn 
Label169:
	aload_0_getfield .field_29_29   // get_name_1:  .field_29_29   // get_name_2:  .field_29_29   // get_Name:    .field_29_29   // getName->1:  null   // getName->2:  null   // getName->N:  null   // ofs = -1 ord = 0 addr = 29
	aload_2 
	getfield .field_29_29   // get_name_1:  .field_29_29   // get_name_2:  .field_29_29   // get_Name:    .field_29_29   // getName->1:  null   // getName->2:  null   // getName->N:  null   // ofs = -1 ord = 0 addr = 29
	invokestatic_lib boolean strEqual( java.lang.String, java.lang.String ) // StringUtilities
	ifne Label176
	iconst_0 
	ireturn 
Label176:
	aload_0_getfield .field_32_32   // get_name_1:  .field_32_32   // get_name_2:  .field_32_32   // get_Name:    .field_32_32   // getName->1:  null   // getName->2:  null   // getName->N:  null   // ofs = -1 ord = 0 addr = 32
	ifeq Label189
	aload_2 
	getfield .field_32_32   // get_name_1:  .field_32_32   // get_name_2:  .field_32_32   // get_Name:    .field_32_32   // getName->1:  null   // getName->2:  null   // getName->N:  null   // ofs = -1 ord = 0 addr = 32
	ifeq Label189
	aload_0 
	lgetfield .field_30_30   // get_name_1:  .field_30_30   // get_name_2:  .field_30_30   // get_Name:    .field_30_30   // getName->1:  null   // getName->2:  null   // getName->N:  null   // ofs = -1 ord = 0 addr = 30
	aload_2 
	lgetfield .field_30_30   // get_name_1:  .field_30_30   // get_name_2:  .field_30_30   // get_Name:    .field_30_30   // getName->1:  null   // getName->2:  null   // getName->N:  null   // ofs = -1 ord = 0 addr = 30
	lcmp 
	ifeq Label189
	iconst_0 
	ireturn 
Label189:
	aload_0_getfield .field_35_35   // get_name_1:  .field_35_35   // get_name_2:  .field_35_35   // get_Name:    .field_35_35   // getName->1:  null   // getName->2:  null   // getName->N:  null   // ofs = -1 ord = 0 addr = 35
	ifeq Label202
	aload_2 
	getfield .field_35_35   // get_name_1:  .field_35_35   // get_name_2:  .field_35_35   // get_Name:    .field_35_35   // getName->1:  null   // getName->2:  null   // getName->N:  null   // ofs = -1 ord = 0 addr = 35
	ifeq Label202
	aload_0 
	lgetfield .field_33_33   // get_name_1:  .field_33_33   // get_name_2:  .field_33_33   // get_Name:    .field_33_33   // getName->1:  null   // getName->2:  null   // getName->N:  null   // ofs = -1 ord = 0 addr = 33
	aload_2 
	lgetfield .field_33_33   // get_name_1:  .field_33_33   // get_name_2:  .field_33_33   // get_Name:    .field_33_33   // getName->1:  null   // getName->2:  null   // getName->N:  null   // ofs = -1 ord = 0 addr = 33
	lcmp 
	ifeq Label202
	iconst_0 
	ireturn 
Label202:
	aload_2 
	getfield .field_36_36   // get_name_1:  .field_36_36   // get_name_2:  .field_36_36   // get_Name:    .field_36_36   // getName->1:  null   // getName->2:  null   // getName->N:  null   // ofs = -1 ord = 0 addr = 36
	arraylength 
	aload_0_getfield .field_36_36   // get_name_1:  .field_36_36   // get_name_2:  .field_36_36   // get_Name:    .field_36_36   // getName->1:  null   // getName->2:  null   // getName->N:  null   // ofs = -1 ord = 0 addr = 36
	arraylength 
	if_icmpeq Label210
	iconst_0 
	ireturn 
Label210:
	aload_0_getfield .field_36_36   // get_name_1:  .field_36_36   // get_name_2:  .field_36_36   // get_Name:    .field_36_36   // getName->1:  null   // getName->2:  null   // getName->N:  null   // ofs = -1 ord = 0 addr = 36
	arraylength 
	istore_5 
	iconst_0 
	istore_6 
Label215:
	iload_6 
	iload_5 
	if_icmpge Label235
	aload_0_getfield .field_36_36   // get_name_1:  .field_36_36   // get_name_2:  .field_36_36   // get_Name:    .field_36_36   // getName->1:  null   // getName->2:  null   // getName->N:  null   // ofs = -1 ord = 0 addr = 36
	iload_6 
	aaload 
	astore_7 
	aload_2 
	getfield .field_36_36   // get_name_1:  .field_36_36   // get_name_2:  .field_36_36   // get_Name:    .field_36_36   // getName->1:  null   // getName->2:  null   // getName->N:  null   // ofs = -1 ord = 0 addr = 36
	iload_6 
	aaload 
	astore 8
	aload_7 
	aload 8
	invokestatic_lib boolean strEqual( java.lang.String, java.lang.String ) // StringUtilities
	ifne Label233
	iconst_0 
	ireturn 
Label233:
	iinc 6 1
	goto Label215
Label235:
	aload_0_getfield .field_37_37   // get_name_1:  .field_37_37   // get_name_2:  .field_37_37   // get_Name:    .field_37_37   // getName->1:  null   // getName->2:  null   // getName->N:  null   // ofs = -1 ord = 0 addr = 37
	aload_2 
	getfield .field_37_37   // get_name_1:  .field_37_37   // get_name_2:  .field_37_37   // get_Name:    .field_37_37   // getName->1:  null   // getName->2:  null   // getName->N:  null   // ofs = -1 ord = 0 addr = 37
	invokestatic_lib boolean strEqual( java.lang.String, java.lang.String ) // StringUtilities
	ifne Label242
	iconst_0 
	ireturn 
Label242:
	aload_0_getfield .field_38_38   // get_name_1:  .field_38_38   // get_name_2:  .field_38_38   // get_Name:    .field_38_38   // getName->1:  null   // getName->2:  null   // getName->N:  null   // ofs = -1 ord = 0 addr = 38
	aload_2 
	getfield .field_38_38   // get_name_1:  .field_38_38   // get_name_2:  .field_38_38   // get_Name:    .field_38_38   // getName->1:  null   // getName->2:  null   // getName->N:  null   // ofs = -1 ord = 0 addr = 38
	invokestatic_lib boolean strEqual( java.lang.String, java.lang.String ) // StringUtilities
	ifne Label249
	iconst_0 
	ireturn 
Label249:
	aload_0_getfield .field_39_39   // get_name_1:  .field_39_39   // get_name_2:  .field_39_39   // get_Name:    .field_39_39   // getName->1:  null   // getName->2:  null   // getName->N:  null   // ofs = -1 ord = 0 addr = 39
	aload_2 
	getfield .field_39_39   // get_name_1:  .field_39_39   // get_name_2:  .field_39_39   // get_Name:    .field_39_39   // getName->1:  null   // getName->2:  null   // getName->N:  null   // ofs = -1 ord = 0 addr = 39
	invokestatic_lib boolean strEqual( java.lang.String, java.lang.String ) // StringUtilities
	ifne Label256
	iconst_0 
	ireturn 
Label256:
	aload_0_getfield .field_40_40   // get_name_1:  .field_40_40   // get_name_2:  .field_40_40   // get_Name:    .field_40_40   // getName->1:  null   // getName->2:  null   // getName->N:  null   // ofs = -1 ord = 0 addr = 40
	aload_2 
	getfield .field_40_40   // get_name_1:  .field_40_40   // get_name_2:  .field_40_40   // get_Name:    .field_40_40   // getName->1:  null   // getName->2:  null   // getName->N:  null   // ofs = -1 ord = 0 addr = 40
	invokestatic_lib boolean strEqual( java.lang.String, java.lang.String ) // StringUtilities
	ifne Label263
	iconst_0 
	ireturn 
Label263:
	aload_0_getfield .field_41_41   // get_name_1:  .field_41_41   // get_name_2:  .field_41_41   // get_Name:    .field_41_41   // getName->1:  null   // getName->2:  null   // getName->N:  null   // ofs = -1 ord = 0 addr = 41
	aload_2 
	getfield .field_41_41   // get_name_1:  .field_41_41   // get_name_2:  .field_41_41   // get_Name:    .field_41_41   // getName->1:  null   // getName->2:  null   // getName->N:  null   // ofs = -1 ord = 0 addr = 41
	invokestatic_lib boolean strEqual( java.lang.String, java.lang.String ) // StringUtilities
	ifne Label270
	iconst_0 
	ireturn 
Label270:
	aload_0_getfield .field_42_42   // get_name_1:  .field_42_42   // get_name_2:  .field_42_42   // get_Name:    .field_42_42   // getName->1:  null   // getName->2:  null   // getName->N:  null   // ofs = -1 ord = 0 addr = 42
	aload_2 
	getfield .field_42_42   // get_name_1:  .field_42_42   // get_name_2:  .field_42_42   // get_Name:    .field_42_42   // getName->1:  null   // getName->2:  null   // getName->N:  null   // ofs = -1 ord = 0 addr = 42
	invokestatic_lib boolean strEqual( java.lang.String, java.lang.String ) // StringUtilities
	ifne Label277
	iconst_0 
	ireturn 
Label277:
	iconst_1 
	ireturn 
Label279:
	iconst_0 
	ireturn 
	}


public final boolean equalPhones( com.whatsapp.client.ContactInfoDetails, com.whatsapp.client.ContactInfoDetails ); // address: 0
	{
	enter_narrow 
	aload_0_getfield .field_7_7   // get_name_1:  .field_7_7   // get_name_2:  .field_7_7   // get_Name:    .field_7_7   // getName->1:  null   // getName->2:  null   // getName->N:  null   // ofs = -1 ord = 0 addr = 7
	aload_1 
	getfield .field_7_7   // get_name_1:  .field_7_7   // get_name_2:  .field_7_7   // get_Name:    .field_7_7   // getName->1:  null   // getName->2:  null   // getName->N:  null   // ofs = -1 ord = 0 addr = 7
	invokestatic_lib boolean strEqual( java.lang.String, java.lang.String ) // StringUtilities
	ifne Label8
	iconst_0 
	ireturn 
Label8:
	aload_0_getfield .field_8_8   // get_name_1:  .field_8_8   // get_name_2:  .field_8_8   // get_Name:    .field_8_8   // getName->1:  null   // getName->2:  null   // getName->N:  null   // ofs = -1 ord = 0 addr = 8
	aload_1 
	getfield .field_8_8   // get_name_1:  .field_8_8   // get_name_2:  .field_8_8   // get_Name:    .field_8_8   // getName->1:  null   // getName->2:  null   // getName->N:  null   // ofs = -1 ord = 0 addr = 8
	invokestatic_lib boolean strEqual( java.lang.String, java.lang.String ) // StringUtilities
	ifne Label15
	iconst_0 
	ireturn 
Label15:
	aload_0_getfield .field_9_9   // get_name_1:  .field_9_9   // get_name_2:  .field_9_9   // get_Name:    .field_9_9   // getName->1:  null   // getName->2:  null   // getName->N:  null   // ofs = -1 ord = 0 addr = 9
	aload_1 
	getfield .field_9_9   // get_name_1:  .field_9_9   // get_name_2:  .field_9_9   // get_Name:    .field_9_9   // getName->1:  null   // getName->2:  null   // getName->N:  null   // ofs = -1 ord = 0 addr = 9
	invokestatic_lib boolean strEqual( java.lang.String, java.lang.String ) // StringUtilities
	ifne Label22
	iconst_0 
	ireturn 
Label22:
	aload_0_getfield .field_10_10   // get_name_1:  .field_10_10   // get_name_2:  .field_10_10   // get_Name:    .field_10_10   // getName->1:  null   // getName->2:  null   // getName->N:  null   // ofs = -1 ord = 0 addr = 10
	aload_1 
	getfield .field_10_10   // get_name_1:  .field_10_10   // get_name_2:  .field_10_10   // get_Name:    .field_10_10   // getName->1:  null   // getName->2:  null   // getName->N:  null   // ofs = -1 ord = 0 addr = 10
	invokestatic_lib boolean strEqual( java.lang.String, java.lang.String ) // StringUtilities
	ifne Label29
	iconst_0 
	ireturn 
Label29:
	aload_0_getfield .field_11_11   // get_name_1:  .field_11_11   // get_name_2:  .field_11_11   // get_Name:    .field_11_11   // getName->1:  null   // getName->2:  null   // getName->N:  null   // ofs = -1 ord = 0 addr = 11
	aload_1 
	getfield .field_11_11   // get_name_1:  .field_11_11   // get_name_2:  .field_11_11   // get_Name:    .field_11_11   // getName->1:  null   // getName->2:  null   // getName->N:  null   // ofs = -1 ord = 0 addr = 11
	invokestatic_lib boolean strEqual( java.lang.String, java.lang.String ) // StringUtilities
	ifne Label36
	iconst_0 
	ireturn 
Label36:
	aload_0_getfield .field_12_12   // get_name_1:  .field_12_12   // get_name_2:  .field_12_12   // get_Name:    .field_12_12   // getName->1:  null   // getName->2:  null   // getName->N:  null   // ofs = -1 ord = 0 addr = 12
	aload_1 
	getfield .field_12_12   // get_name_1:  .field_12_12   // get_name_2:  .field_12_12   // get_Name:    .field_12_12   // getName->1:  null   // getName->2:  null   // getName->N:  null   // ofs = -1 ord = 0 addr = 12
	invokestatic_lib boolean strEqual( java.lang.String, java.lang.String ) // StringUtilities
	ifne Label43
	iconst_0 
	ireturn 
Label43:
	aload_0_getfield .field_13_13   // get_name_1:  .field_13_13   // get_name_2:  .field_13_13   // get_Name:    .field_13_13   // getName->1:  null   // getName->2:  null   // getName->N:  null   // ofs = -1 ord = 0 addr = 13
	aload_1 
	getfield .field_13_13   // get_name_1:  .field_13_13   // get_name_2:  .field_13_13   // get_Name:    .field_13_13   // getName->1:  null   // getName->2:  null   // getName->N:  null   // ofs = -1 ord = 0 addr = 13
	invokestatic_lib boolean strEqual( java.lang.String, java.lang.String ) // StringUtilities
	ifne Label50
	iconst_0 
	ireturn 
Label50:
	aload_0_getfield .field_14_14   // get_name_1:  .field_14_14   // get_name_2:  .field_14_14   // get_Name:    .field_14_14   // getName->1:  null   // getName->2:  null   // getName->N:  null   // ofs = -1 ord = 0 addr = 14
	aload_1 
	getfield .field_14_14   // get_name_1:  .field_14_14   // get_name_2:  .field_14_14   // get_Name:    .field_14_14   // getName->1:  null   // getName->2:  null   // getName->N:  null   // ofs = -1 ord = 0 addr = 14
	invokestatic_lib boolean strEqual( java.lang.String, java.lang.String ) // StringUtilities
	ifne Label57
	iconst_0 
	ireturn 
Label57:
	aload_0_getfield .field_15_15   // get_name_1:  .field_15_15   // get_name_2:  .field_15_15   // get_Name:    .field_15_15   // getName->1:  null   // getName->2:  null   // getName->N:  null   // ofs = -1 ord = 0 addr = 15
	aload_1 
	getfield .field_15_15   // get_name_1:  .field_15_15   // get_name_2:  .field_15_15   // get_Name:    .field_15_15   // getName->1:  null   // getName->2:  null   // getName->N:  null   // ofs = -1 ord = 0 addr = 15
	invokestatic_lib boolean strEqual( java.lang.String, java.lang.String ) // StringUtilities
	ifne Label64
	iconst_0 
	ireturn 
Label64:
	aload_0_getfield .field_16_16   // get_name_1:  .field_16_16   // get_name_2:  .field_16_16   // get_Name:    .field_16_16   // getName->1:  null   // getName->2:  null   // getName->N:  null   // ofs = -1 ord = 0 addr = 16
	aload_1 
	getfield .field_16_16   // get_name_1:  .field_16_16   // get_name_2:  .field_16_16   // get_Name:    .field_16_16   // getName->1:  null   // getName->2:  null   // getName->N:  null   // ofs = -1 ord = 0 addr = 16
	invokestatic_lib boolean strEqual( java.lang.String, java.lang.String ) // StringUtilities
	ifne Label71
	iconst_0 
	ireturn 
Label71:
	iconst_1 
	ireturn 
	}


public final boolean equalNames( com.whatsapp.client.ContactInfoDetails, com.whatsapp.client.ContactInfoDetails ); // address: 0
	{
	enter_narrow 
	aload_0_getfield .field_1_1   // get_name_1:  .field_1_1   // get_name_2:  .field_1_1   // get_Name:    .field_1_1   // getName->1:  null   // getName->2:  null   // getName->N:  null   // ofs = -1 ord = 0 addr = 1
	aload_1 
	getfield .field_1_1   // get_name_1:  .field_1_1   // get_name_2:  .field_1_1   // get_Name:    .field_1_1   // getName->1:  null   // getName->2:  null   // getName->N:  null   // ofs = -1 ord = 0 addr = 1
	invokestatic_lib boolean strEqual( java.lang.String, java.lang.String ) // StringUtilities
	ifne Label8
	iconst_0 
	ireturn 
Label8:
	aload_0_getfield .field_2_2   // get_name_1:  .field_2_2   // get_name_2:  .field_2_2   // get_Name:    .field_2_2   // getName->1:  null   // getName->2:  null   // getName->N:  null   // ofs = -1 ord = 0 addr = 2
	aload_1 
	getfield .field_2_2   // get_name_1:  .field_2_2   // get_name_2:  .field_2_2   // get_Name:    .field_2_2   // getName->1:  null   // getName->2:  null   // getName->N:  null   // ofs = -1 ord = 0 addr = 2
	invokestatic_lib boolean strEqual( java.lang.String, java.lang.String ) // StringUtilities
	ifne Label15
	iconst_0 
	ireturn 
Label15:
	aload_0_getfield .field_3_3   // get_name_1:  .field_3_3   // get_name_2:  .field_3_3   // get_Name:    .field_3_3   // getName->1:  null   // getName->2:  null   // getName->N:  null   // ofs = -1 ord = 0 addr = 3
	aload_1 
	getfield .field_3_3   // get_name_1:  .field_3_3   // get_name_2:  .field_3_3   // get_Name:    .field_3_3   // getName->1:  null   // getName->2:  null   // getName->N:  null   // ofs = -1 ord = 0 addr = 3
	invokestatic_lib boolean strEqual( java.lang.String, java.lang.String ) // StringUtilities
	ifne Label22
	iconst_0 
	ireturn 
Label22:
	iconst_1 
	ireturn 
	}


final loadDetails( com.whatsapp.client.ContactInfoDetails, net.rim.blackberry.api.pdap.BlackBerryContact ); // address: 0
	{
	enter_narrow 
	invokestatic_lib module:WhatsApp-18.class#0.routine_2419(  ) // class#0
	astore_2 
	aload_0 
	aload_1 
	aload_2 
	invokenonvirtual com.whatsapp.client.ContactInfoDetails.loadDetails // pc=3
	return 
	}


final loadDetails( com.whatsapp.client.ContactInfoDetails, net.rim.blackberry.api.pdap.BlackBerryContact, module:WhatsApp-18.class#0 ); // address: 0
	{
	enter 
	aload_0 
	invokenonvirtual com.whatsapp.client.ContactInfoDetails.clearDetails // pc=1
	aload_1 
	invokeinterface interfacemethodref_6 // pc=1 guess=4
	checkcast_lib net.rim.blackberry.api.pdap.BlackBerryContactList//net.rim.blackberry.api.pdap.BlackBerryContactList net.rim.blackberry.api.pdap.BlackBerryContactList net.rim.blackberry.api.pdap.BlackBerryContactList
	astore_3 
	aload_3 
	ifnonnull Label15
	invokestatic_lib javax.microedition.pim.PIM getInstance(  ) // PIM
	iconst_1 
	iconst_1 
	invokevirtual javax.microedition.pim.PIMList openPIMList( javax.microedition.pim.PIM, int, int ) // pc=3
	checkcast_lib net.rim.blackberry.api.pdap.BlackBerryContactList//net.rim.blackberry.api.pdap.BlackBerryContactList net.rim.blackberry.api.pdap.BlackBerryContactList net.rim.blackberry.api.pdap.BlackBerryContactList
	astore_3 
Label15:
	aload_3 
	bipush 117
	invokeinterface interfacemethodref_7 // pc=2 guess=5
	ifeq Label30
	aload_1 
	bipush 117
	invokeinterface interfacemethodref_8 // pc=2 guess=6
	ifle Label30
	aload_0 
	aload_1 
	bipush 117
	iconst_0 
	invokeinterface interfacemethodref_9 // pc=3 guess=7
	putfield .field_0_   // get_name_1:  .field_0_   // get_name_2:  .field_0_   // get_Name:    .field_0_   // getName->1:  null   // getName->2:  null   // getName->N:  null   // ofs = -1 ord = 0 addr = 0
	goto Label39
Label30:
	aload_0 
	new_lib net.rim.device.api.ui.decor.Background//net.rim.device.api.ui.decor.Background net.rim.device.api.ui.decor.Background net.rim.device.api.ui.decor.Background
	dup 
	ldc literal_123:"fake_"
	invokespecial_lib java.lang.StringBuffer.<init> // pc=2
	invokestatic_lib long currentTimeMillis(  ) // System
	invokevirtual java.lang.StringBuffer append( java.lang.StringBuffer, long ) // pc=3
	invokevirtual_short .toString // idx=2 pc=1
	putfield .field_0_   // get_name_1:  .field_0_   // get_name_2:  .field_0_   // get_Name:    .field_0_   // getName->1:  null   // getName->2:  null   // getName->N:  null   // ofs = -1 ord = 0 addr = 0
Label39:
	aload_3 
	bipush 106
	invokeinterface interfacemethodref_7 // pc=2 guess=5
	ifeq Label95
	aload_1 
	bipush 106
	invokeinterface interfacemethodref_8 // pc=2 guess=6
	ifle Label95
	aload_1 
	bipush 106
	iconst_0 
	invokeinterface interfacemethodref_10 // pc=3 guess=8
	astore_4 
	aload_3 
	bipush 106
	bipush 3
	invokeinterface interfacemethodref_11 // pc=3 guess=9
	ifeq Label66
	aload_4 
	bipush 3
	aaload 
	ifnull Label66
	aload_0 
	aload_4 
	bipush 3
	aaload 
	putfield .field_1_1   // get_name_1:  .field_1_1   // get_name_2:  .field_1_1   // get_Name:    .field_1_1   // getName->1:  null   // getName->2:  null   // getName->N:  null   // ofs = -1 ord = 0 addr = 1
Label66:
	aload_3 
	bipush 106
	iconst_1 
	invokeinterface interfacemethodref_11 // pc=3 guess=9
	ifeq Label80
	aload_4 
	iconst_1 
	aaload 
	ifnull Label80
	aload_0 
	aload_4 
	iconst_1 
	aaload 
	putfield .field_2_2   // get_name_1:  .field_2_2   // get_name_2:  .field_2_2   // get_Name:    .field_2_2   // getName->1:  null   // getName->2:  null   // getName->N:  null   // ofs = -1 ord = 0 addr = 2
Label80:
	aload_3 
	bipush 106
	iconst_0 
	invokeinterface interfacemethodref_11 // pc=3 guess=9
	ifeq Label103
	aload_4 
	iconst_0 
	aaload 
	ifnull Label103
	aload_0 
	aload_4 
	iconst_0 
	aaload 
	putfield .field_3_3   // get_name_1:  .field_3_3   // get_name_2:  .field_3_3   // get_Name:    .field_3_3   // getName->1:  null   // getName->2:  null   // getName->N:  null   // ofs = -1 ord = 0 addr = 3
	goto Label103
Label95:
	new_lib net.rim.device.api.ui.decor.Background//net.rim.device.api.ui.decor.Background net.rim.device.api.ui.decor.Background net.rim.device.api.ui.decor.Background
	dup 
	ldc literal_124:"NNN no values associated with NAME in contact "
	invokespecial_lib java.lang.StringBuffer.<init> // pc=2
	aload_0_getfield .field_0_   // get_name_1:  .field_0_   // get_name_2:  .field_0_   // get_Name:    .field_0_   // getName->1:  null   // getName->2:  null   // getName->N:  null   // ofs = -1 ord = 0 addr = 0
	invokevirtual java.lang.StringBuffer append( java.lang.StringBuffer, java.lang.String ) // pc=2
	invokevirtual_short .toString // idx=2 pc=1
	invokestatic_lib module:WhatsApp-79.class#39.routine_24694(  ) // class#39
Label103:
	aload_3 
	bipush 109
	invokeinterface interfacemethodref_7 // pc=2 guess=5
	ifeq Label117
	aload_1 
	bipush 109
	invokeinterface interfacemethodref_8 // pc=2 guess=6
	ifle Label117
	aload_0 
	aload_1 
	bipush 109
	iconst_0 
	invokeinterface interfacemethodref_9 // pc=3 guess=7
	putfield .field_4_4   // get_name_1:  .field_4_4   // get_name_2:  .field_4_4   // get_Name:    .field_4_4   // getName->1:  null   // getName->2:  null   // getName->N:  null   // ofs = -1 ord = 0 addr = 4
Label117:
	aload_3 
	bipush 116
	invokeinterface interfacemethodref_7 // pc=2 guess=5
	ifeq Label131
	aload_1 
	bipush 116
	invokeinterface interfacemethodref_8 // pc=2 guess=6
	ifle Label131
	aload_0 
	aload_1 
	bipush 116
	iconst_0 
	invokeinterface interfacemethodref_9 // pc=3 guess=7
	putfield .field_5_5   // get_name_1:  .field_5_5   // get_name_2:  .field_5_5   // get_Name:    .field_5_5   // getName->1:  null   // getName->2:  null   // getName->N:  null   // ofs = -1 ord = 0 addr = 5
Label131:
	aload_3 
	bipush 103
	invokeinterface interfacemethodref_7 // pc=2 guess=5
	ifeq Label157
	aload_1 
	bipush 103
	invokeinterface interfacemethodref_8 // pc=2 guess=6
	istore_4 
	iconst_0 
	istore_5 
Label141:
	iload_5 
	iload_4 
	if_icmpge Label157
	aload_1 
	bipush 103
	iload_5 
	invokeinterface interfacemethodref_9 // pc=3 guess=7
	astore_6 
	aload_6 
	ifnull Label155
	aload_0_getfield .field_6_6   // get_name_1:  .field_6_6   // get_name_2:  .field_6_6   // get_Name:    .field_6_6   // getName->1:  null   // getName->2:  null   // getName->N:  null   // ofs = -1 ord = 0 addr = 6
	aload_6 
	invokenonvirtual_lib java.lang.String.trim // pc=1
	invokevirtual addElement( java.util.Vector, java.lang.Object ) // pc=2
Label155:
	iinc 5 1
	goto Label141
Label157:
	aload_3 
	bipush 115
	invokeinterface interfacemethodref_7 // pc=2 guess=5
	ifne Label162
	goto_w Label262
Label162:
	aload_1 
	bipush 115
	invokeinterface interfacemethodref_8 // pc=2 guess=6
	istore_4 
	iconst_0 
	istore_5 
Label168:
	iload_5 
	iload_4 
	if_icmplt Label172
	goto_w Label262
Label172:
	aload_1 
	bipush 115
	iload_5 
	invokeinterface interfacemethodref_12 // pc=3 guess=10
	istore_6 
	aload_1 
	bipush 115
	iload_5 
	invokeinterface interfacemethodref_9 // pc=3 guess=7
	astore_7 
	aload_7 
	ifnonnull Label185
	goto_w Label260
Label185:
	aload_7 
	invokenonvirtual_lib java.lang.String.trim // pc=1
	invokestatic_lib module:WhatsApp-79.class#39.routine_27263(  ) // class#39
	astore 8
	iload_6 
Label191:
	aload_0_getfield .field_11_11   // get_name_1:  .field_11_11   // get_name_2:  .field_11_11   // get_Name:    .field_11_11   // getName->1:  null   // getName->2:  null   // getName->N:  null   // ofs = -1 ord = 0 addr = 11
	ifnonnull Label197
	aload_0 
	aload 8
	putfield .field_11_11   // get_name_1:  .field_11_11   // get_name_2:  .field_11_11   // get_Name:    .field_11_11   // getName->1:  null   // getName->2:  null   // getName->N:  null   // ofs = -1 ord = 0 addr = 11
	goto_w Label260
Label197:
	aload_0 
	aload 8
	putfield .field_12_12   // get_name_1:  .field_12_12   // get_name_2:  .field_12_12   // get_Name:    .field_12_12   // getName->1:  null   // getName->2:  null   // getName->N:  null   // ofs = -1 ord = 0 addr = 12
	goto_w Label260
Label201:
	aload_0 
	aload 8
	putfield .field_9_9   // get_name_1:  .field_9_9   // get_name_2:  .field_9_9   // get_Name:    .field_9_9   // getName->1:  null   // getName->2:  null   // getName->N:  null   // ofs = -1 ord = 0 addr = 9
	goto Label260
Label205:
	aload_0 
	aload 8
	putfield .field_10_10   // get_name_1:  .field_10_10   // get_name_2:  .field_10_10   // get_Name:    .field_10_10   // getName->1:  null   // getName->2:  null   // getName->N:  null   // ofs = -1 ord = 0 addr = 10
	goto Label260
Label209:
	aload_0 
	aload 8
	putfield .field_7_7   // get_name_1:  .field_7_7   // get_name_2:  .field_7_7   // get_Name:    .field_7_7   // getName->1:  null   // getName->2:  null   // getName->N:  null   // ofs = -1 ord = 0 addr = 7
	goto Label260
Label213:
	aload_0 
	aload 8
	putfield .field_8_8   // get_name_1:  .field_8_8   // get_name_2:  .field_8_8   // get_Name:    .field_8_8   // getName->1:  null   // getName->2:  null   // getName->N:  null   // ofs = -1 ord = 0 addr = 8
	goto Label260
Label217:
	aload_0 
	aload 8
	putfield .field_13_13   // get_name_1:  .field_13_13   // get_name_2:  .field_13_13   // get_Name:    .field_13_13   // getName->1:  null   // getName->2:  null   // getName->N:  null   // ofs = -1 ord = 0 addr = 13
	goto Label260
Label221:
	aload_0_getfield .field_14_14   // get_name_1:  .field_14_14   // get_name_2:  .field_14_14   // get_Name:    .field_14_14   // getName->1:  null   // getName->2:  null   // getName->N:  null   // ofs = -1 ord = 0 addr = 14
	ifnonnull Label227
	aload_0 
	aload 8
	putfield .field_14_14   // get_name_1:  .field_14_14   // get_name_2:  .field_14_14   // get_Name:    .field_14_14   // getName->1:  null   // getName->2:  null   // getName->N:  null   // ofs = -1 ord = 0 addr = 14
	goto Label260
Label227:
	aload_0 
	aload 8
	putfield .field_15_15   // get_name_1:  .field_15_15   // get_name_2:  .field_15_15   // get_Name:    .field_15_15   // getName->1:  null   // getName->2:  null   // getName->N:  null   // ofs = -1 ord = 0 addr = 15
	goto Label260
Label231:
	aload_0 
	aload 8
	putfield .field_15_15   // get_name_1:  .field_15_15   // get_name_2:  .field_15_15   // get_Name:    .field_15_15   // getName->1:  null   // getName->2:  null   // getName->N:  null   // ofs = -1 ord = 0 addr = 15
	goto Label260
Label235:
	aload_0 
	aload 8
	putfield .field_12_12   // get_name_1:  .field_12_12   // get_name_2:  .field_12_12   // get_Name:    .field_12_12   // getName->1:  null   // getName->2:  null   // getName->N:  null   // ofs = -1 ord = 0 addr = 12
	goto Label260
Label239:
	aload_0 
	aload 8
	putfield .field_16_16   // get_name_1:  .field_16_16   // get_name_2:  .field_16_16   // get_Name:    .field_16_16   // getName->1:  null   // getName->2:  null   // getName->N:  null   // ofs = -1 ord = 0 addr = 16
	goto Label260
Label243:
	new_lib net.rim.device.api.ui.decor.Background//net.rim.device.api.ui.decor.Background net.rim.device.api.ui.decor.Background net.rim.device.api.ui.decor.Background
	dup 
	ldc literal_125:"phone "
	invokespecial_lib java.lang.StringBuffer.<init> // pc=2
	iload_5 
	invokevirtual java.lang.StringBuffer append( java.lang.StringBuffer, int ) // pc=2
	ldc literal_126:" has unknown attr "
	invokevirtual java.lang.StringBuffer append( java.lang.StringBuffer, java.lang.String ) // pc=2
	iload_6 
	invokevirtual java.lang.StringBuffer append( java.lang.StringBuffer, int ) // pc=2
	ldc literal_127:" with value "
	invokevirtual java.lang.StringBuffer append( java.lang.StringBuffer, java.lang.String ) // pc=2
	aload 8
	invokestatic_lib module:WhatsApp-79.class#39.routine_24526(  ) // class#39
	invokevirtual java.lang.StringBuffer append( java.lang.StringBuffer, java.lang.String ) // pc=2
	invokevirtual_short .toString // idx=2 pc=1
	invokestatic_lib module:WhatsApp-79.class#39.routine_24694(  ) // class#39
Label260:
	iinc 5 1
	goto_w Label168
Label262:
	aload_3 
	iipush 20000927
	invokeinterface interfacemethodref_7 // pc=2 guess=5
	ifeq Label276
	aload_1 
	iipush 20000927
	invokeinterface interfacemethodref_8 // pc=2 guess=6
	ifle Label276
	aload_0 
	aload_1 
	iipush 20000927
	iconst_0 
	invokeinterface interfacemethodref_9 // pc=3 guess=7
	putfield .field_17_17   // get_name_1:  .field_17_17   // get_name_2:  .field_17_17   // get_Name:    .field_17_17   // getName->1:  null   // getName->2:  null   // getName->N:  null   // ofs = -1 ord = 0 addr = 17
Label276:
	aload_3 
	bipush 100
	invokeinterface interfacemethodref_7 // pc=2 guess=5
	ifne Label281
	goto_w Label449
Label281:
	aload_1 
	bipush 100
	invokeinterface interfacemethodref_8 // pc=2 guess=6
	istore_4 
	iload_4 
	iconst_1 
	isub 
	istore_5 
Label289:
	iload_5 
	ifge Label292
	goto_w Label449
Label292:
	aload_1 
	bipush 100
	iload_5 
	invokeinterface interfacemethodref_12 // pc=3 guess=10
	istore_6 
	iload_6 
	bipush 8
	if_icmpeq Label304
	iload_6 
	sipush 512
	if_icmpeq Label304
	goto_w Label447
Label304:
	aload_1 
	bipush 100
	iload_5 
	invokeinterface interfacemethodref_10 // pc=3 guess=8
	astore_7 
	aload_3 
	bipush 100
	bipush 2
	invokeinterface interfacemethodref_11 // pc=3 guess=9
	ifeq Label332
	aload_7 
	bipush 2
	aaload 
	ifnull Label332
	iload_6 
	bipush 8
	if_icmpne Label327
	aload_0 
	aload_7 
	bipush 2
	aaload 
	putfield .field_24_24   // get_name_1:  .field_24_24   // get_name_2:  .field_24_24   // get_Name:    .field_24_24   // getName->1:  null   // getName->2:  null   // getName->N:  null   // ofs = -1 ord = 0 addr = 24
	goto Label332
Label327:
	aload_0 
	aload_7 
	bipush 2
	aaload 
	putfield .field_18_18   // get_name_1:  .field_18_18   // get_name_2:  .field_18_18   // get_Name:    .field_18_18   // getName->1:  null   // getName->2:  null   // getName->N:  null   // ofs = -1 ord = 0 addr = 18
Label332:
	aload_3 
	bipush 100
	iconst_1 
	invokeinterface interfacemethodref_11 // pc=3 guess=9
	ifeq Label355
	aload_7 
	iconst_1 
	aaload 
	ifnull Label355
	iload_6 
	bipush 8
	if_icmpne Label350
	aload_0 
	aload_7 
	iconst_1 
	aaload 
	putfield .field_25_25   // get_name_1:  .field_25_25   // get_name_2:  .field_25_25   // get_Name:    .field_25_25   // getName->1:  null   // getName->2:  null   // getName->N:  null   // ofs = -1 ord = 0 addr = 25
	goto Label355
Label350:
	aload_0 
	aload_7 
	iconst_1 
	aaload 
	putfield .field_19_19   // get_name_1:  .field_19_19   // get_name_2:  .field_19_19   // get_Name:    .field_19_19   // getName->1:  null   // getName->2:  null   // getName->N:  null   // ofs = -1 ord = 0 addr = 19
Label355:
	aload_3 
	bipush 100
	bipush 3
	invokeinterface interfacemethodref_11 // pc=3 guess=9
	ifeq Label378
	aload_7 
	bipush 3
	aaload 
	ifnull Label378
	iload_6 
	bipush 8
	if_icmpne Label373
	aload_0 
	aload_7 
	bipush 3
	aaload 
	putfield .field_26_26   // get_name_1:  .field_26_26   // get_name_2:  .field_26_26   // get_Name:    .field_26_26   // getName->1:  null   // getName->2:  null   // getName->N:  null   // ofs = -1 ord = 0 addr = 26
	goto Label378
Label373:
	aload_0 
	aload_7 
	bipush 3
	aaload 
	putfield .field_20_20   // get_name_1:  .field_20_20   // get_name_2:  .field_20_20   // get_Name:    .field_20_20   // getName->1:  null   // getName->2:  null   // getName->N:  null   // ofs = -1 ord = 0 addr = 20
Label378:
	aload_3 
	bipush 100
	bipush 6
	invokeinterface interfacemethodref_11 // pc=3 guess=9
	ifeq Label401
	aload_7 
	bipush 6
	aaload 
	ifnull Label401
	iload_6 
	bipush 8
	if_icmpne Label396
	aload_0 
	aload_7 
	bipush 6
	aaload 
	putfield .field_29_29   // get_name_1:  .field_29_29   // get_name_2:  .field_29_29   // get_Name:    .field_29_29   // getName->1:  null   // getName->2:  null   // getName->N:  null   // ofs = -1 ord = 0 addr = 29
	goto Label401
Label396:
	aload_0 
	aload_7 
	bipush 6
	aaload 
	putfield .field_23_23   // get_name_1:  .field_23_23   // get_name_2:  .field_23_23   // get_Name:    .field_23_23   // getName->1:  null   // getName->2:  null   // getName->N:  null   // ofs = -1 ord = 0 addr = 23
Label401:
	aload_3 
	bipush 100
	bipush 5
	invokeinterface interfacemethodref_11 // pc=3 guess=9
	ifeq Label424
	aload_7 
	bipush 5
	aaload 
	ifnull Label424
	iload_6 
	bipush 8
	if_icmpne Label419
	aload_0 
	aload_7 
	bipush 5
	aaload 
	putfield .field_28_28   // get_name_1:  .field_28_28   // get_name_2:  .field_28_28   // get_Name:    .field_28_28   // getName->1:  null   // getName->2:  null   // getName->N:  null   // ofs = -1 ord = 0 addr = 28
	goto Label424
Label419:
	aload_0 
	aload_7 
	bipush 5
	aaload 
	putfield .field_22_22   // get_name_1:  .field_22_22   // get_name_2:  .field_22_22   // get_Name:    .field_22_22   // getName->1:  null   // getName->2:  null   // getName->N:  null   // ofs = -1 ord = 0 addr = 22
Label424:
	aload_3 
	bipush 100
	bipush 4
	invokeinterface interfacemethodref_11 // pc=3 guess=9
	ifeq Label447
	aload_7 
	bipush 4
	aaload 
	ifnull Label447
	iload_6 
	bipush 8
	if_icmpne Label442
	aload_0 
	aload_7 
	bipush 4
	aaload 
	putfield .field_27_27   // get_name_1:  .field_27_27   // get_name_2:  .field_27_27   // get_Name:    .field_27_27   // getName->1:  null   // getName->2:  null   // getName->N:  null   // ofs = -1 ord = 0 addr = 27
	goto Label447
Label442:
	aload_0 
	aload_7 
	bipush 4
	aaload 
	putfield .field_21_21   // get_name_1:  .field_21_21   // get_name_2:  .field_21_21   // get_Name:    .field_21_21   // getName->1:  null   // getName->2:  null   // getName->N:  null   // ofs = -1 ord = 0 addr = 21
Label447:
	iinc 5 -1
	goto_w Label289
Label449:
	aload_3 
	bipush 101
	invokeinterface interfacemethodref_7 // pc=2 guess=5
	ifeq Label470
	aload_1 
	bipush 101
	invokeinterface interfacemethodref_8 // pc=2 guess=6
	ifle Label470
	aload_0 
	aload_1 
	bipush 101
	iconst_0 
	invokeinterface interfacemethodref_13 // pc=3 guess=11
	invokestatic_lib java.util.TimeZone getDefault(  ) // TimeZone
	invokevirtual int getRawOffset( java.util.TimeZone ) // pc=1
	i2l 
	lsub 
	lputfield .field_30_30   // get_name_1:  .field_30_30   // get_name_2:  .field_30_30   // get_Name:    .field_30_30   // getName->1:  null   // getName->2:  null   // getName->N:  null   // ofs = -1 ord = 0 addr = 30
	aload_0 
	iconst_1 
	putfield .field_32_32   // get_name_1:  .field_32_32   // get_name_2:  .field_32_32   // get_Name:    .field_32_32   // getName->1:  null   // getName->2:  null   // getName->N:  null   // ofs = -1 ord = 0 addr = 32
Label470:
	aload_3 
	iipush 20000933
	invokeinterface interfacemethodref_7 // pc=2 guess=5
	ifeq Label491
	aload_1 
	iipush 20000933
	invokeinterface interfacemethodref_8 // pc=2 guess=6
	ifle Label491
	aload_0 
	aload_1 
	iipush 20000933
	iconst_0 
	invokeinterface interfacemethodref_13 // pc=3 guess=11
	invokestatic_lib java.util.TimeZone getDefault(  ) // TimeZone
	invokevirtual int getRawOffset( java.util.TimeZone ) // pc=1
	i2l 
	lsub 
	lputfield .field_33_33   // get_name_1:  .field_33_33   // get_name_2:  .field_33_33   // get_Name:    .field_33_33   // getName->1:  null   // getName->2:  null   // getName->N:  null   // ofs = -1 ord = 0 addr = 33
	aload_0 
	iconst_1 
	putfield .field_35_35   // get_name_1:  .field_35_35   // get_name_2:  .field_35_35   // get_Name:    .field_35_35   // getName->1:  null   // getName->2:  null   // getName->N:  null   // ofs = -1 ord = 0 addr = 35
Label491:
	aload_0 
	aload_1 
	invokeinterface interfacemethodref_14 // pc=1 guess=12
	putfield .field_36_36   // get_name_1:  .field_36_36   // get_name_2:  .field_36_36   // get_Name:    .field_36_36   // getName->1:  null   // getName->2:  null   // getName->N:  null   // ofs = -1 ord = 0 addr = 36
	aload_3 
	bipush 118
	invokeinterface interfacemethodref_7 // pc=2 guess=5
	ifeq Label509
	aload_1 
	bipush 118
	invokeinterface interfacemethodref_8 // pc=2 guess=6
	ifle Label509
	aload_0 
	aload_1 
	bipush 118
	iconst_0 
	invokeinterface interfacemethodref_9 // pc=3 guess=7
	putfield .field_37_37   // get_name_1:  .field_37_37   // get_name_2:  .field_37_37   // get_Name:    .field_37_37   // getName->1:  null   // getName->2:  null   // getName->N:  null   // ofs = -1 ord = 0 addr = 37
Label509:
	aload_3 
	iipush 20000928
	invokeinterface interfacemethodref_7 // pc=2 guess=5
	ifeq Label523
	aload_1 
	iipush 20000928
	invokeinterface interfacemethodref_8 // pc=2 guess=6
	ifle Label523
	aload_0 
	aload_1 
	iipush 20000928
	iconst_0 
	invokeinterface interfacemethodref_9 // pc=3 guess=7
	putfield .field_38_38   // get_name_1:  .field_38_38   // get_name_2:  .field_38_38   // get_Name:    .field_38_38   // getName->1:  null   // getName->2:  null   // getName->N:  null   // ofs = -1 ord = 0 addr = 38
Label523:
	aload_3 
	iipush 20000929
	invokeinterface interfacemethodref_7 // pc=2 guess=5
	ifeq Label537
	aload_1 
	iipush 20000929
	invokeinterface interfacemethodref_8 // pc=2 guess=6
	ifle Label537
	aload_0 
	aload_1 
	iipush 20000929
	iconst_0 
	invokeinterface interfacemethodref_9 // pc=3 guess=7
	putfield .field_39_39   // get_name_1:  .field_39_39   // get_name_2:  .field_39_39   // get_Name:    .field_39_39   // getName->1:  null   // getName->2:  null   // getName->N:  null   // ofs = -1 ord = 0 addr = 39
Label537:
	aload_3 
	iipush 20000930
	invokeinterface interfacemethodref_7 // pc=2 guess=5
	ifeq Label551
	aload_1 
	iipush 20000930
	invokeinterface interfacemethodref_8 // pc=2 guess=6
	ifle Label551
	aload_0 
	aload_1 
	iipush 20000930
	iconst_0 
	invokeinterface interfacemethodref_9 // pc=3 guess=7
	putfield .field_40_40   // get_name_1:  .field_40_40   // get_name_2:  .field_40_40   // get_Name:    .field_40_40   // getName->1:  null   // getName->2:  null   // getName->N:  null   // ofs = -1 ord = 0 addr = 40
Label551:
	aload_3 
	iipush 20000931
	invokeinterface interfacemethodref_7 // pc=2 guess=5
	ifeq Label565
	aload_1 
	iipush 20000931
	invokeinterface interfacemethodref_8 // pc=2 guess=6
	ifle Label565
	aload_0 
	aload_1 
	iipush 20000931
	iconst_0 
	invokeinterface interfacemethodref_9 // pc=3 guess=7
	putfield .field_41_41   // get_name_1:  .field_41_41   // get_name_2:  .field_41_41   // get_Name:    .field_41_41   // getName->1:  null   // getName->2:  null   // getName->N:  null   // ofs = -1 ord = 0 addr = 41
Label565:
	aload_3 
	bipush 108
	invokeinterface interfacemethodref_7 // pc=2 guess=5
	ifeq Label579
	aload_1 
	bipush 108
	invokeinterface interfacemethodref_8 // pc=2 guess=6
	ifle Label579
	aload_0 
	aload_1 
	bipush 108
	iconst_0 
	invokeinterface interfacemethodref_9 // pc=3 guess=7
	putfield .field_42_42   // get_name_1:  .field_42_42   // get_name_2:  .field_42_42   // get_Name:    .field_42_42   // getName->1:  null   // getName->2:  null   // getName->N:  null   // ofs = -1 ord = 0 addr = 42
Label579:
	aload_3 
	bipush 110
	invokeinterface interfacemethodref_7 // pc=2 guess=5
	ifeq Label611
	aload_1 
	bipush 110
	invokeinterface interfacemethodref_8 // pc=2 guess=6
	ifle Label611
	aload_1 
	invokestatic net.rim.device.api.system.EncodedImage loadImage( net.rim.blackberry.api.pdap.BlackBerryContact ) // ContactInfoDetails
	astore_4 
	aload_4 
	ifnull Label611
	aload_2 
	aload_0_getfield .field_0_   // get_name_1:  .field_0_   // get_name_2:  .field_0_   // get_Name:    .field_0_   // getName->1:  null   // getName->2:  null   // getName->N:  null   // ofs = -1 ord = 0 addr = 0
	aload_4 
	invokenonvirtual_lib .routine_385 // pc=3
	return 
	astore_3 
	new_lib net.rim.device.api.ui.decor.Background//net.rim.device.api.ui.decor.Background net.rim.device.api.ui.decor.Background net.rim.device.api.ui.decor.Background
	dup 
	ldc literal_128:"error loading contact details for uid "
	invokespecial_lib java.lang.StringBuffer.<init> // pc=2
	aload_0_getfield .field_0_   // get_name_1:  .field_0_   // get_name_2:  .field_0_   // get_Name:    .field_0_   // getName->1:  null   // getName->2:  null   // getName->N:  null   // ofs = -1 ord = 0 addr = 0
	invokevirtual java.lang.StringBuffer append( java.lang.StringBuffer, java.lang.String ) // pc=2
	ldc literal_129:": "
	invokevirtual java.lang.StringBuffer append( java.lang.StringBuffer, java.lang.String ) // pc=2
	aload_3 
	invokevirtual_short .toString // idx=2 pc=1
	invokevirtual java.lang.StringBuffer append( java.lang.StringBuffer, java.lang.String ) // pc=2
	invokevirtual_short .toString // idx=2 pc=1
	invokestatic_lib module:WhatsApp-79.class#39.routine_24694(  ) // class#39
Label611:
	return 
	}


public final java.lang.String getShortName( com.whatsapp.client.ContactInfoDetails ); // address: 0
	{
	enter_narrow 
	aload_0_getfield .field_2_2   // get_name_1:  .field_2_2   // get_name_2:  .field_2_2   // get_Name:    .field_2_2   // getName->1:  null   // getName->2:  null   // getName->N:  null   // ofs = -1 ord = 0 addr = 2
	ifnull Label8
	aload_0_getfield .field_2_2   // get_name_1:  .field_2_2   // get_name_2:  .field_2_2   // get_Name:    .field_2_2   // getName->1:  null   // getName->2:  null   // getName->N:  null   // ofs = -1 ord = 0 addr = 2
	stringlength 
	ifle Label8
	aload_0_getfield .field_2_2   // get_name_1:  .field_2_2   // get_name_2:  .field_2_2   // get_Name:    .field_2_2   // getName->1:  null   // getName->2:  null   // getName->N:  null   // ofs = -1 ord = 0 addr = 2
	areturn 
Label8:
	aload_0_getfield .field_3_3   // get_name_1:  .field_3_3   // get_name_2:  .field_3_3   // get_Name:    .field_3_3   // getName->1:  null   // getName->2:  null   // getName->N:  null   // ofs = -1 ord = 0 addr = 3
	ifnull Label15
	aload_0_getfield .field_3_3   // get_name_1:  .field_3_3   // get_name_2:  .field_3_3   // get_Name:    .field_3_3   // getName->1:  null   // getName->2:  null   // getName->N:  null   // ofs = -1 ord = 0 addr = 3
	stringlength 
	ifle Label15
	aload_0_getfield .field_3_3   // get_name_1:  .field_3_3   // get_name_2:  .field_3_3   // get_Name:    .field_3_3   // getName->1:  null   // getName->2:  null   // getName->N:  null   // ofs = -1 ord = 0 addr = 3
	areturn 
Label15:
	aload_0_getfield .field_4_4   // get_name_1:  .field_4_4   // get_name_2:  .field_4_4   // get_Name:    .field_4_4   // getName->1:  null   // getName->2:  null   // getName->N:  null   // ofs = -1 ord = 0 addr = 4
	ifnull Label22
	aload_0_getfield .field_4_4   // get_name_1:  .field_4_4   // get_name_2:  .field_4_4   // get_Name:    .field_4_4   // getName->1:  null   // getName->2:  null   // getName->N:  null   // ofs = -1 ord = 0 addr = 4
	stringlength 
	ifle Label22
	aload_0_getfield .field_4_4   // get_name_1:  .field_4_4   // get_name_2:  .field_4_4   // get_Name:    .field_4_4   // getName->1:  null   // getName->2:  null   // getName->N:  null   // ofs = -1 ord = 0 addr = 4
	areturn 
Label22:
	aload_0 
	invokenonvirtual com.whatsapp.client.ContactInfoDetails.getAllPhones // pc=1
	astore_1 
	iconst_0 
	istore_2 
Label27:
	iload_2 
	aload_1 
	invokevirtual int size( java.util.Vector ) // pc=1
	if_icmpge Label44
	aload_1 
	iload_2 
	invokevirtual java.lang.Object elementAt( java.util.Vector, int ) // pc=2
	checkcast_lib String//java.lang.String java.lang.String java.lang.String
	stringlength 
	ifle Label42
	aload_1 
	iload_2 
	invokevirtual java.lang.Object elementAt( java.util.Vector, int ) // pc=2
	checkcast_lib String//java.lang.String java.lang.String java.lang.String
	areturn 
Label42:
	iinc 2 1
	goto Label27
Label44:
	getstatic_lib module:WhatsApp-19.class#0.static_131 // class#0
	areturn 
	}


final java.lang.String getFullName( com.whatsapp.client.ContactInfoDetails, int ); // address: 0
	{
	enter 
	new_lib net.rim.device.api.ui.decor.Background//net.rim.device.api.ui.decor.Background net.rim.device.api.ui.decor.Background net.rim.device.api.ui.decor.Background
	dup 
	invokespecial_lib java.lang.StringBuffer.<init> // pc=1
	astore_2 
	iload_1 
Label7:
	aload_0_getfield .field_1_1   // get_name_1:  .field_1_1   // get_name_2:  .field_1_1   // get_Name:    .field_1_1   // getName->1:  null   // getName->2:  null   // getName->N:  null   // ofs = -1 ord = 0 addr = 1
	ifnull Label13
	aload_2 
	aload_0_getfield .field_1_1   // get_name_1:  .field_1_1   // get_name_2:  .field_1_1   // get_Name:    .field_1_1   // getName->1:  null   // getName->2:  null   // getName->N:  null   // ofs = -1 ord = 0 addr = 1
	invokevirtual java.lang.StringBuffer append( java.lang.StringBuffer, java.lang.String ) // pc=2
	pop 
Label13:
	aload_0_getfield .field_2_2   // get_name_1:  .field_2_2   // get_name_2:  .field_2_2   // get_Name:    .field_2_2   // getName->1:  null   // getName->2:  null   // getName->N:  null   // ofs = -1 ord = 0 addr = 2
	ifnull Label26
	aload_2 
	invokevirtual int length( java.lang.StringBuffer ) // pc=1
	ifle Label22
	aload_2 
	bipush 32
	invokevirtual java.lang.StringBuffer append( java.lang.StringBuffer, char ) // pc=2
	pop 
Label22:
	aload_2 
	aload_0_getfield .field_2_2   // get_name_1:  .field_2_2   // get_name_2:  .field_2_2   // get_Name:    .field_2_2   // getName->1:  null   // getName->2:  null   // getName->N:  null   // ofs = -1 ord = 0 addr = 2
	invokevirtual java.lang.StringBuffer append( java.lang.StringBuffer, java.lang.String ) // pc=2
	pop 
Label26:
	aload_0_getfield .field_3_3   // get_name_1:  .field_3_3   // get_name_2:  .field_3_3   // get_Name:    .field_3_3   // getName->1:  null   // getName->2:  null   // getName->N:  null   // ofs = -1 ord = 0 addr = 3
	ifnull Label83
	aload_2 
	invokevirtual int length( java.lang.StringBuffer ) // pc=1
	ifle Label35
	aload_2 
	bipush 32
	invokevirtual java.lang.StringBuffer append( java.lang.StringBuffer, char ) // pc=2
	pop 
Label35:
	aload_2 
	aload_0_getfield .field_3_3   // get_name_1:  .field_3_3   // get_name_2:  .field_3_3   // get_Name:    .field_3_3   // getName->1:  null   // getName->2:  null   // getName->N:  null   // ofs = -1 ord = 0 addr = 3
	invokevirtual java.lang.StringBuffer append( java.lang.StringBuffer, java.lang.String ) // pc=2
	pop 
	goto Label83
Label40:
	aload_0_getfield .field_3_3   // get_name_1:  .field_3_3   // get_name_2:  .field_3_3   // get_Name:    .field_3_3   // getName->1:  null   // getName->2:  null   // getName->N:  null   // ofs = -1 ord = 0 addr = 3
	ifnull Label46
	aload_2 
	aload_0_getfield .field_3_3   // get_name_1:  .field_3_3   // get_name_2:  .field_3_3   // get_Name:    .field_3_3   // getName->1:  null   // getName->2:  null   // getName->N:  null   // ofs = -1 ord = 0 addr = 3
	invokevirtual java.lang.StringBuffer append( java.lang.StringBuffer, java.lang.String ) // pc=2
	pop 
Label46:
	aload_2 
	invokevirtual int length( java.lang.StringBuffer ) // pc=1
	ifle Label57
	aload_0_getfield .field_1_1   // get_name_1:  .field_1_1   // get_name_2:  .field_1_1   // get_Name:    .field_1_1   // getName->1:  null   // getName->2:  null   // getName->N:  null   // ofs = -1 ord = 0 addr = 1
	ifnonnull Label53
	aload_0_getfield .field_2_2   // get_name_1:  .field_2_2   // get_name_2:  .field_2_2   // get_Name:    .field_2_2   // getName->1:  null   // getName->2:  null   // getName->N:  null   // ofs = -1 ord = 0 addr = 2
	ifnull Label57
Label53:
	aload_2 
	bipush 44
	invokevirtual java.lang.StringBuffer append( java.lang.StringBuffer, char ) // pc=2
	pop 
Label57:
	aload_0_getfield .field_1_1   // get_name_1:  .field_1_1   // get_name_2:  .field_1_1   // get_Name:    .field_1_1   // getName->1:  null   // getName->2:  null   // getName->N:  null   // ofs = -1 ord = 0 addr = 1
	ifnull Label70
	aload_2 
	invokevirtual int length( java.lang.StringBuffer ) // pc=1
	ifle Label66
	aload_2 
	bipush 32
	invokevirtual java.lang.StringBuffer append( java.lang.StringBuffer, char ) // pc=2
	pop 
Label66:
	aload_2 
	aload_0_getfield .field_1_1   // get_name_1:  .field_1_1   // get_name_2:  .field_1_1   // get_Name:    .field_1_1   // getName->1:  null   // getName->2:  null   // getName->N:  null   // ofs = -1 ord = 0 addr = 1
	invokevirtual java.lang.StringBuffer append( java.lang.StringBuffer, java.lang.String ) // pc=2
	pop 
Label70:
	aload_0_getfield .field_2_2   // get_name_1:  .field_2_2   // get_name_2:  .field_2_2   // get_Name:    .field_2_2   // getName->1:  null   // getName->2:  null   // getName->N:  null   // ofs = -1 ord = 0 addr = 2
	ifnull Label83
	aload_2 
	invokevirtual int length( java.lang.StringBuffer ) // pc=1
	ifle Label79
	aload_2 
	bipush 32
	invokevirtual java.lang.StringBuffer append( java.lang.StringBuffer, char ) // pc=2
	pop 
Label79:
	aload_2 
	aload_0_getfield .field_2_2   // get_name_1:  .field_2_2   // get_name_2:  .field_2_2   // get_Name:    .field_2_2   // getName->1:  null   // getName->2:  null   // getName->N:  null   // ofs = -1 ord = 0 addr = 2
	invokevirtual java.lang.StringBuffer append( java.lang.StringBuffer, java.lang.String ) // pc=2
	pop 
Label83:
	aload_2 
	invokevirtual int length( java.lang.StringBuffer ) // pc=1
	ifne Label92
	aload_0_getfield .field_4_4   // get_name_1:  .field_4_4   // get_name_2:  .field_4_4   // get_Name:    .field_4_4   // getName->1:  null   // getName->2:  null   // getName->N:  null   // ofs = -1 ord = 0 addr = 4
	ifnull Label92
	aload_2 
	aload_0_getfield .field_4_4   // get_name_1:  .field_4_4   // get_name_2:  .field_4_4   // get_Name:    .field_4_4   // getName->1:  null   // getName->2:  null   // getName->N:  null   // ofs = -1 ord = 0 addr = 4
	invokevirtual java.lang.StringBuffer append( java.lang.StringBuffer, java.lang.String ) // pc=2
	pop 
Label92:
	aload_2 
	invokevirtual int length( java.lang.StringBuffer ) // pc=1
	ifne Label108
	aload_0 
	invokenonvirtual com.whatsapp.client.ContactInfoDetails.getAllPhones // pc=1
	astore_3 
	aload_3 
	invokevirtual int size( java.util.Vector ) // pc=1
	ifle Label108
	aload_2 
	aload_3 
	iconst_0 
	invokevirtual java.lang.Object elementAt( java.util.Vector, int ) // pc=2
	checkcast_lib String//java.lang.String java.lang.String java.lang.String
	invokevirtual java.lang.StringBuffer append( java.lang.StringBuffer, java.lang.String ) // pc=2
	pop 
Label108:
	aload_2 
	invokevirtual int length( java.lang.StringBuffer ) // pc=1
	ifne Label117
	aload_2 
	sipush 732
	aload_0_getfield .field_0_   // get_name_1:  .field_0_   // get_name_2:  .field_0_   // get_Name:    .field_0_   // getName->1:  null   // getName->2:  null   // getName->N:  null   // ofs = -1 ord = 0 addr = 0
	invokestatic_lib module:WhatsApp-47.class#11.routine_4463(  ) // class#11
	invokevirtual java.lang.StringBuffer append( java.lang.StringBuffer, java.lang.String ) // pc=2
	pop 
Label117:
	aload_2 
	invokevirtual_short .toString // idx=2 pc=1
	areturn 
	}


public final module:WhatsApp-12.class#30[] getStatuses( com.whatsapp.client.ContactInfoDetails ); // address: 0
	{
	enter 
	invokestatic_lib module:WhatsApp-21.class#0.routine_1491(  ) // class#0
	astore_1 
	iconst_0 
	newarray_object_lib com.whatsapp.client.ChatableNumber//module:WhatsApp-12.class#30 module:WhatsApp-12.class#30 module:WhatsApp-12.class#30
	astore_2 
	aload_1 
	ifnonnull Label10
	aload_2 
	areturn 
Label10:
	aload_0 
	aload_1 
	aload_0_getfield .field_11_11   // get_name_1:  .field_11_11   // get_name_2:  .field_11_11   // get_Name:    .field_11_11   // getName->1:  null   // getName->2:  null   // getName->N:  null   // ofs = -1 ord = 0 addr = 11
	bipush 61
	aload_2 
	invokespecial com.whatsapp.client.ContactInfoDetails.routine_11753 // pc=5
	aload_0 
	aload_1 
	aload_0_getfield .field_12_12   // get_name_1:  .field_12_12   // get_name_2:  .field_12_12   // get_Name:    .field_12_12   // getName->1:  null   // getName->2:  null   // getName->N:  null   // ofs = -1 ord = 0 addr = 12
	sipush 354
	aload_2 
	invokespecial com.whatsapp.client.ContactInfoDetails.routine_11753 // pc=5
	aload_0 
	aload_1 
	aload_0_getfield .field_9_9   // get_name_1:  .field_9_9   // get_name_2:  .field_9_9   // get_Name:    .field_9_9   // getName->1:  null   // getName->2:  null   // getName->N:  null   // ofs = -1 ord = 0 addr = 9
	bipush 59
	aload_2 
	invokespecial com.whatsapp.client.ContactInfoDetails.routine_11753 // pc=5
	aload_0 
	aload_1 
	aload_0_getfield .field_10_10   // get_name_1:  .field_10_10   // get_name_2:  .field_10_10   // get_Name:    .field_10_10   // getName->1:  null   // getName->2:  null   // getName->N:  null   // ofs = -1 ord = 0 addr = 10
	bipush 60
	aload_2 
	invokespecial com.whatsapp.client.ContactInfoDetails.routine_11753 // pc=5
	aload_0 
	aload_1 
	aload_0_getfield .field_13_13   // get_name_1:  .field_13_13   // get_name_2:  .field_13_13   // get_Name:    .field_13_13   // getName->1:  null   // getName->2:  null   // getName->N:  null   // ofs = -1 ord = 0 addr = 13
	bipush 62
	aload_2 
	invokespecial com.whatsapp.client.ContactInfoDetails.routine_11753 // pc=5
	aload_0 
	aload_1 
	aload_0_getfield .field_16_16   // get_name_1:  .field_16_16   // get_name_2:  .field_16_16   // get_Name:    .field_16_16   // getName->1:  null   // getName->2:  null   // getName->N:  null   // ofs = -1 ord = 0 addr = 16
	bipush 64
	aload_2 
	invokespecial com.whatsapp.client.ContactInfoDetails.routine_11753 // pc=5
	aload_0 
	aload_1 
	aload_0_getfield .field_7_7   // get_name_1:  .field_7_7   // get_name_2:  .field_7_7   // get_Name:    .field_7_7   // getName->1:  null   // getName->2:  null   // getName->N:  null   // ofs = -1 ord = 0 addr = 7
	bipush 57
	aload_2 
	invokespecial com.whatsapp.client.ContactInfoDetails.routine_11753 // pc=5
	aload_0 
	aload_1 
	aload_0_getfield .field_8_8   // get_name_1:  .field_8_8   // get_name_2:  .field_8_8   // get_Name:    .field_8_8   // getName->1:  null   // getName->2:  null   // getName->N:  null   // ofs = -1 ord = 0 addr = 8
	bipush 58
	aload_2 
	invokespecial com.whatsapp.client.ContactInfoDetails.routine_11753 // pc=5
	aload_0 
	aload_1 
	aload_0_getfield .field_14_14   // get_name_1:  .field_14_14   // get_name_2:  .field_14_14   // get_Name:    .field_14_14   // getName->1:  null   // getName->2:  null   // getName->N:  null   // ofs = -1 ord = 0 addr = 14
	bipush 63
	aload_2 
	invokespecial com.whatsapp.client.ContactInfoDetails.routine_11753 // pc=5
	aload_0 
	aload_1 
	aload_0_getfield .field_15_15   // get_name_1:  .field_15_15   // get_name_2:  .field_15_15   // get_Name:    .field_15_15   // getName->1:  null   // getName->2:  null   // getName->N:  null   // ofs = -1 ord = 0 addr = 15
	sipush 355
	aload_2 
	invokespecial com.whatsapp.client.ContactInfoDetails.routine_11753 // pc=5
	aload_2 
	areturn 
	}


public final java.lang.String getPhoneLabel( com.whatsapp.client.ContactInfoDetails, java.lang.String[] ); // address: 0
	{
	enter 
	iconst_0 
	istore_2 
Label3:
	iload_2 
	aload_1 
	arraylength 
	if_icmpge Label24
	aload_1 
	iload_2 
	aaload 
	astore_3 
	aload_3 
	ifnonnull Label14
	goto Label22
Label14:
	aload_0 
	aload_3 
	invokenonvirtual com.whatsapp.client.ContactInfoDetails.getPhoneLabel // pc=2
	astore_4 
	aload_4 
	ifnull Label22
	aload_4 
	areturn 
Label22:
	iinc 2 1
	goto Label3
Label24:
	aconst_null 
	areturn 
	}


public final java.lang.String getPhoneLabel( com.whatsapp.client.ContactInfoDetails, java.lang.String ); // address: 0
	{
	enter_narrow 
	aload_1 
	aload_0_getfield .field_11_11   // get_name_1:  .field_11_11   // get_name_2:  .field_11_11   // get_Name:    .field_11_11   // getName->1:  null   // getName->2:  null   // getName->N:  null   // ofs = -1 ord = 0 addr = 11
	invokevirtual_short .equals // idx=1 pc=2
	ifeq Label8
	bipush 61
	invokestatic_lib module:WhatsApp-47.class#11.routine_4387(  ) // class#11
	areturn 
Label8:
	aload_1 
	aload_0_getfield .field_12_12   // get_name_1:  .field_12_12   // get_name_2:  .field_12_12   // get_Name:    .field_12_12   // getName->1:  null   // getName->2:  null   // getName->N:  null   // ofs = -1 ord = 0 addr = 12
	invokevirtual_short .equals // idx=1 pc=2
	ifeq Label15
	sipush 354
	invokestatic_lib module:WhatsApp-47.class#11.routine_4387(  ) // class#11
	areturn 
Label15:
	aload_1 
	aload_0_getfield .field_9_9   // get_name_1:  .field_9_9   // get_name_2:  .field_9_9   // get_Name:    .field_9_9   // getName->1:  null   // getName->2:  null   // getName->N:  null   // ofs = -1 ord = 0 addr = 9
	invokevirtual_short .equals // idx=1 pc=2
	ifeq Label22
	bipush 59
	invokestatic_lib module:WhatsApp-47.class#11.routine_4387(  ) // class#11
	areturn 
Label22:
	aload_1 
	aload_0_getfield .field_10_10   // get_name_1:  .field_10_10   // get_name_2:  .field_10_10   // get_Name:    .field_10_10   // getName->1:  null   // getName->2:  null   // getName->N:  null   // ofs = -1 ord = 0 addr = 10
	invokevirtual_short .equals // idx=1 pc=2
	ifeq Label29
	bipush 60
	invokestatic_lib module:WhatsApp-47.class#11.routine_4387(  ) // class#11
	areturn 
Label29:
	aload_1 
	aload_0_getfield .field_13_13   // get_name_1:  .field_13_13   // get_name_2:  .field_13_13   // get_Name:    .field_13_13   // getName->1:  null   // getName->2:  null   // getName->N:  null   // ofs = -1 ord = 0 addr = 13
	invokevirtual_short .equals // idx=1 pc=2
	ifeq Label36
	bipush 62
	invokestatic_lib module:WhatsApp-47.class#11.routine_4387(  ) // class#11
	areturn 
Label36:
	aload_1 
	aload_0_getfield .field_16_16   // get_name_1:  .field_16_16   // get_name_2:  .field_16_16   // get_Name:    .field_16_16   // getName->1:  null   // getName->2:  null   // getName->N:  null   // ofs = -1 ord = 0 addr = 16
	invokevirtual_short .equals // idx=1 pc=2
	ifeq Label43
	bipush 64
	invokestatic_lib module:WhatsApp-47.class#11.routine_4387(  ) // class#11
	areturn 
Label43:
	aload_1 
	aload_0_getfield .field_7_7   // get_name_1:  .field_7_7   // get_name_2:  .field_7_7   // get_Name:    .field_7_7   // getName->1:  null   // getName->2:  null   // getName->N:  null   // ofs = -1 ord = 0 addr = 7
	invokevirtual_short .equals // idx=1 pc=2
	ifeq Label50
	bipush 57
	invokestatic_lib module:WhatsApp-47.class#11.routine_4387(  ) // class#11
	areturn 
Label50:
	aload_1 
	aload_0_getfield .field_8_8   // get_name_1:  .field_8_8   // get_name_2:  .field_8_8   // get_Name:    .field_8_8   // getName->1:  null   // getName->2:  null   // getName->N:  null   // ofs = -1 ord = 0 addr = 8
	invokevirtual_short .equals // idx=1 pc=2
	ifeq Label57
	bipush 58
	invokestatic_lib module:WhatsApp-47.class#11.routine_4387(  ) // class#11
	areturn 
Label57:
	aload_1 
	aload_0_getfield .field_14_14   // get_name_1:  .field_14_14   // get_name_2:  .field_14_14   // get_Name:    .field_14_14   // getName->1:  null   // getName->2:  null   // getName->N:  null   // ofs = -1 ord = 0 addr = 14
	invokevirtual_short .equals // idx=1 pc=2
	ifeq Label64
	bipush 63
	invokestatic_lib module:WhatsApp-47.class#11.routine_4387(  ) // class#11
	areturn 
Label64:
	aload_1 
	aload_0_getfield .field_15_15   // get_name_1:  .field_15_15   // get_name_2:  .field_15_15   // get_Name:    .field_15_15   // getName->1:  null   // getName->2:  null   // getName->N:  null   // ofs = -1 ord = 0 addr = 15
	invokevirtual_short .equals // idx=1 pc=2
	ifeq Label71
	sipush 355
	invokestatic_lib module:WhatsApp-47.class#11.routine_4387(  ) // class#11
	areturn 
Label71:
	aconst_null 
	areturn 
	}


public final java.util.Vector getAllPhones( com.whatsapp.client.ContactInfoDetails ); // address: 0
	{
	enter_narrow 
	new_lib Boolean//java.lang.Boolean java.lang.Boolean java.lang.Boolean
	dup 
	bipush 10
	invokespecial_lib java.util.Vector.<init> // pc=2
	astore_1 
	aload_0_getfield .field_11_11   // get_name_1:  .field_11_11   // get_name_2:  .field_11_11   // get_Name:    .field_11_11   // getName->1:  null   // getName->2:  null   // getName->N:  null   // ofs = -1 ord = 0 addr = 11
	ifnull Label11
	aload_1 
	aload_0_getfield .field_11_11   // get_name_1:  .field_11_11   // get_name_2:  .field_11_11   // get_Name:    .field_11_11   // getName->1:  null   // getName->2:  null   // getName->N:  null   // ofs = -1 ord = 0 addr = 11
	invokevirtual addElement( java.util.Vector, java.lang.Object ) // pc=2
Label11:
	aload_0_getfield .field_12_12   // get_name_1:  .field_12_12   // get_name_2:  .field_12_12   // get_Name:    .field_12_12   // getName->1:  null   // getName->2:  null   // getName->N:  null   // ofs = -1 ord = 0 addr = 12
	ifnull Label16
	aload_1 
	aload_0_getfield .field_12_12   // get_name_1:  .field_12_12   // get_name_2:  .field_12_12   // get_Name:    .field_12_12   // getName->1:  null   // getName->2:  null   // getName->N:  null   // ofs = -1 ord = 0 addr = 12
	invokevirtual addElement( java.util.Vector, java.lang.Object ) // pc=2
Label16:
	aload_0_getfield .field_14_14   // get_name_1:  .field_14_14   // get_name_2:  .field_14_14   // get_Name:    .field_14_14   // getName->1:  null   // getName->2:  null   // getName->N:  null   // ofs = -1 ord = 0 addr = 14
	ifnull Label21
	aload_1 
	aload_0_getfield .field_14_14   // get_name_1:  .field_14_14   // get_name_2:  .field_14_14   // get_Name:    .field_14_14   // getName->1:  null   // getName->2:  null   // getName->N:  null   // ofs = -1 ord = 0 addr = 14
	invokevirtual addElement( java.util.Vector, java.lang.Object ) // pc=2
Label21:
	aload_0_getfield .field_15_15   // get_name_1:  .field_15_15   // get_name_2:  .field_15_15   // get_Name:    .field_15_15   // getName->1:  null   // getName->2:  null   // getName->N:  null   // ofs = -1 ord = 0 addr = 15
	ifnull Label26
	aload_1 
	aload_0_getfield .field_15_15   // get_name_1:  .field_15_15   // get_name_2:  .field_15_15   // get_Name:    .field_15_15   // getName->1:  null   // getName->2:  null   // getName->N:  null   // ofs = -1 ord = 0 addr = 15
	invokevirtual addElement( java.util.Vector, java.lang.Object ) // pc=2
Label26:
	aload_0_getfield .field_9_9   // get_name_1:  .field_9_9   // get_name_2:  .field_9_9   // get_Name:    .field_9_9   // getName->1:  null   // getName->2:  null   // getName->N:  null   // ofs = -1 ord = 0 addr = 9
	ifnull Label31
	aload_1 
	aload_0_getfield .field_9_9   // get_name_1:  .field_9_9   // get_name_2:  .field_9_9   // get_Name:    .field_9_9   // getName->1:  null   // getName->2:  null   // getName->N:  null   // ofs = -1 ord = 0 addr = 9
	invokevirtual addElement( java.util.Vector, java.lang.Object ) // pc=2
Label31:
	aload_0_getfield .field_10_10   // get_name_1:  .field_10_10   // get_name_2:  .field_10_10   // get_Name:    .field_10_10   // getName->1:  null   // getName->2:  null   // getName->N:  null   // ofs = -1 ord = 0 addr = 10
	ifnull Label36
	aload_1 
	aload_0_getfield .field_10_10   // get_name_1:  .field_10_10   // get_name_2:  .field_10_10   // get_Name:    .field_10_10   // getName->1:  null   // getName->2:  null   // getName->N:  null   // ofs = -1 ord = 0 addr = 10
	invokevirtual addElement( java.util.Vector, java.lang.Object ) // pc=2
Label36:
	aload_0_getfield .field_13_13   // get_name_1:  .field_13_13   // get_name_2:  .field_13_13   // get_Name:    .field_13_13   // getName->1:  null   // getName->2:  null   // getName->N:  null   // ofs = -1 ord = 0 addr = 13
	ifnull Label41
	aload_1 
	aload_0_getfield .field_13_13   // get_name_1:  .field_13_13   // get_name_2:  .field_13_13   // get_Name:    .field_13_13   // getName->1:  null   // getName->2:  null   // getName->N:  null   // ofs = -1 ord = 0 addr = 13
	invokevirtual addElement( java.util.Vector, java.lang.Object ) // pc=2
Label41:
	aload_0_getfield .field_16_16   // get_name_1:  .field_16_16   // get_name_2:  .field_16_16   // get_Name:    .field_16_16   // getName->1:  null   // getName->2:  null   // getName->N:  null   // ofs = -1 ord = 0 addr = 16
	ifnull Label46
	aload_1 
	aload_0_getfield .field_16_16   // get_name_1:  .field_16_16   // get_name_2:  .field_16_16   // get_Name:    .field_16_16   // getName->1:  null   // getName->2:  null   // getName->N:  null   // ofs = -1 ord = 0 addr = 16
	invokevirtual addElement( java.util.Vector, java.lang.Object ) // pc=2
Label46:
	aload_0_getfield .field_7_7   // get_name_1:  .field_7_7   // get_name_2:  .field_7_7   // get_Name:    .field_7_7   // getName->1:  null   // getName->2:  null   // getName->N:  null   // ofs = -1 ord = 0 addr = 7
	ifnull Label51
	aload_1 
	aload_0_getfield .field_7_7   // get_name_1:  .field_7_7   // get_name_2:  .field_7_7   // get_Name:    .field_7_7   // getName->1:  null   // getName->2:  null   // getName->N:  null   // ofs = -1 ord = 0 addr = 7
	invokevirtual addElement( java.util.Vector, java.lang.Object ) // pc=2
Label51:
	aload_0_getfield .field_8_8   // get_name_1:  .field_8_8   // get_name_2:  .field_8_8   // get_Name:    .field_8_8   // getName->1:  null   // getName->2:  null   // getName->N:  null   // ofs = -1 ord = 0 addr = 8
	ifnull Label56
	aload_1 
	aload_0_getfield .field_8_8   // get_name_1:  .field_8_8   // get_name_2:  .field_8_8   // get_Name:    .field_8_8   // getName->1:  null   // getName->2:  null   // getName->N:  null   // ofs = -1 ord = 0 addr = 8
	invokevirtual addElement( java.util.Vector, java.lang.Object ) // pc=2
Label56:
	aload_1 
	areturn 
	}


public final net.rim.device.api.util.IntVector getAllPhoneIds( com.whatsapp.client.ContactInfoDetails ); // address: 0
	{
	enter_narrow 
	new_lib java.util.Vector//java.util.Vector java.util.Vector java.util.Vector
	dup 
	bipush 10
	invokespecial_lib net.rim.device.api.util.IntVector.<init> // pc=2
	astore_1 
	aload_0_getfield .field_11_11   // get_name_1:  .field_11_11   // get_name_2:  .field_11_11   // get_Name:    .field_11_11   // getName->1:  null   // getName->2:  null   // getName->N:  null   // ofs = -1 ord = 0 addr = 11
	ifnull Label11
	aload_1 
	iconst_0 
	invokevirtual addElement( net.rim.device.api.util.IntVector, int ) // pc=2
Label11:
	aload_0_getfield .field_12_12   // get_name_1:  .field_12_12   // get_name_2:  .field_12_12   // get_Name:    .field_12_12   // getName->1:  null   // getName->2:  null   // getName->N:  null   // ofs = -1 ord = 0 addr = 12
	ifnull Label16
	aload_1 
	bipush 8
	invokevirtual addElement( net.rim.device.api.util.IntVector, int ) // pc=2
Label16:
	aload_0_getfield .field_14_14   // get_name_1:  .field_14_14   // get_name_2:  .field_14_14   // get_Name:    .field_14_14   // getName->1:  null   // getName->2:  null   // getName->N:  null   // ofs = -1 ord = 0 addr = 14
	ifnull Label21
	aload_1 
	bipush 6
	invokevirtual addElement( net.rim.device.api.util.IntVector, int ) // pc=2
Label21:
	aload_0_getfield .field_15_15   // get_name_1:  .field_15_15   // get_name_2:  .field_15_15   // get_Name:    .field_15_15   // getName->1:  null   // getName->2:  null   // getName->N:  null   // ofs = -1 ord = 0 addr = 15
	ifnull Label26
	aload_1 
	bipush 9
	invokevirtual addElement( net.rim.device.api.util.IntVector, int ) // pc=2
Label26:
	aload_0_getfield .field_9_9   // get_name_1:  .field_9_9   // get_name_2:  .field_9_9   // get_Name:    .field_9_9   // getName->1:  null   // getName->2:  null   // getName->N:  null   // ofs = -1 ord = 0 addr = 9
	ifnull Label31
	aload_1 
	iconst_1 
	invokevirtual addElement( net.rim.device.api.util.IntVector, int ) // pc=2
Label31:
	aload_0_getfield .field_10_10   // get_name_1:  .field_10_10   // get_name_2:  .field_10_10   // get_Name:    .field_10_10   // getName->1:  null   // getName->2:  null   // getName->N:  null   // ofs = -1 ord = 0 addr = 10
	ifnull Label36
	aload_1 
	bipush 2
	invokevirtual addElement( net.rim.device.api.util.IntVector, int ) // pc=2
Label36:
	aload_0_getfield .field_13_13   // get_name_1:  .field_13_13   // get_name_2:  .field_13_13   // get_Name:    .field_13_13   // getName->1:  null   // getName->2:  null   // getName->N:  null   // ofs = -1 ord = 0 addr = 13
	ifnull Label41
	aload_1 
	bipush 5
	invokevirtual addElement( net.rim.device.api.util.IntVector, int ) // pc=2
Label41:
	aload_0_getfield .field_16_16   // get_name_1:  .field_16_16   // get_name_2:  .field_16_16   // get_Name:    .field_16_16   // getName->1:  null   // getName->2:  null   // getName->N:  null   // ofs = -1 ord = 0 addr = 16
	ifnull Label46
	aload_1 
	bipush 7
	invokevirtual addElement( net.rim.device.api.util.IntVector, int ) // pc=2
Label46:
	aload_0_getfield .field_7_7   // get_name_1:  .field_7_7   // get_name_2:  .field_7_7   // get_Name:    .field_7_7   // getName->1:  null   // getName->2:  null   // getName->N:  null   // ofs = -1 ord = 0 addr = 7
	ifnull Label51
	aload_1 
	bipush 3
	invokevirtual addElement( net.rim.device.api.util.IntVector, int ) // pc=2
Label51:
	aload_0_getfield .field_8_8   // get_name_1:  .field_8_8   // get_name_2:  .field_8_8   // get_Name:    .field_8_8   // getName->1:  null   // getName->2:  null   // getName->N:  null   // ofs = -1 ord = 0 addr = 8
	ifnull Label56
	aload_1 
	bipush 4
	invokevirtual addElement( net.rim.device.api.util.IntVector, int ) // pc=2
Label56:
	aload_1 
	areturn 
	}


public final java.lang.String[] fastAllPhones( com.whatsapp.client.ContactInfoDetails ); // address: 0
	{
	enter 
	bipush 10
	newarray_object_lib String//java.lang.String java.lang.String java.lang.String
	dup 
	iconst_0 
	aload_0_getfield .field_11_11   // get_name_1:  .field_11_11   // get_name_2:  .field_11_11   // get_Name:    .field_11_11   // getName->1:  null   // getName->2:  null   // getName->N:  null   // ofs = -1 ord = 0 addr = 11
	aastore 
	dup 
	iconst_1 
	aload_0_getfield .field_12_12   // get_name_1:  .field_12_12   // get_name_2:  .field_12_12   // get_Name:    .field_12_12   // getName->1:  null   // getName->2:  null   // getName->N:  null   // ofs = -1 ord = 0 addr = 12
	aastore 
	dup 
	bipush 2
	aload_0_getfield .field_14_14   // get_name_1:  .field_14_14   // get_name_2:  .field_14_14   // get_Name:    .field_14_14   // getName->1:  null   // getName->2:  null   // getName->N:  null   // ofs = -1 ord = 0 addr = 14
	aastore 
	dup 
	bipush 3
	aload_0_getfield .field_15_15   // get_name_1:  .field_15_15   // get_name_2:  .field_15_15   // get_Name:    .field_15_15   // getName->1:  null   // getName->2:  null   // getName->N:  null   // ofs = -1 ord = 0 addr = 15
	aastore 
	dup 
	bipush 4
	aload_0_getfield .field_9_9   // get_name_1:  .field_9_9   // get_name_2:  .field_9_9   // get_Name:    .field_9_9   // getName->1:  null   // getName->2:  null   // getName->N:  null   // ofs = -1 ord = 0 addr = 9
	aastore 
	dup 
	bipush 5
	aload_0_getfield .field_10_10   // get_name_1:  .field_10_10   // get_name_2:  .field_10_10   // get_Name:    .field_10_10   // getName->1:  null   // getName->2:  null   // getName->N:  null   // ofs = -1 ord = 0 addr = 10
	aastore 
	dup 
	bipush 6
	aload_0_getfield .field_13_13   // get_name_1:  .field_13_13   // get_name_2:  .field_13_13   // get_Name:    .field_13_13   // getName->1:  null   // getName->2:  null   // getName->N:  null   // ofs = -1 ord = 0 addr = 13
	aastore 
	dup 
	bipush 7
	aload_0_getfield .field_16_16   // get_name_1:  .field_16_16   // get_name_2:  .field_16_16   // get_Name:    .field_16_16   // getName->1:  null   // getName->2:  null   // getName->N:  null   // ofs = -1 ord = 0 addr = 16
	aastore 
	dup 
	bipush 8
	aload_0_getfield .field_7_7   // get_name_1:  .field_7_7   // get_name_2:  .field_7_7   // get_Name:    .field_7_7   // getName->1:  null   // getName->2:  null   // getName->N:  null   // ofs = -1 ord = 0 addr = 7
	aastore 
	dup 
	bipush 9
	aload_0_getfield .field_8_8   // get_name_1:  .field_8_8   // get_name_2:  .field_8_8   // get_Name:    .field_8_8   // getName->1:  null   // getName->2:  null   // getName->N:  null   // ofs = -1 ord = 0 addr = 8
	aastore 
	areturn 
	}


public final addListItems( com.whatsapp.client.ContactInfoDetails, java.util.Vector, int, int ); // address: 0
	{
	enter 
	aload_0_getfield .field_6_6   // get_name_1:  .field_6_6   // get_name_2:  .field_6_6   // get_Name:    .field_6_6   // getName->1:  null   // getName->2:  null   // getName->N:  null   // ofs = -1 ord = 0 addr = 6
	invokevirtual int size( java.util.Vector ) // pc=1
	ifle Label47
	aload_1 
	aload_0 
	iload_2 
	iload_3 
	invokespecial com.whatsapp.client.ContactInfoDetails.routine_11806 // pc=3
	invokevirtual addElement( java.util.Vector, java.lang.Object ) // pc=2
	iconst_1 
	istore_5 
	aload_0_getfield .field_6_6   // get_name_1:  .field_6_6   // get_name_2:  .field_6_6   // get_Name:    .field_6_6   // getName->1:  null   // getName->2:  null   // getName->N:  null   // ofs = -1 ord = 0 addr = 6
	invokevirtual int size( java.util.Vector ) // pc=1
	istore_6 
	iconst_0 
	istore_7 
Label17:
	iload_7 
	iload_6 
	if_icmpge Label49
	aload_0_getfield .field_6_6   // get_name_1:  .field_6_6   // get_name_2:  .field_6_6   // get_Name:    .field_6_6   // getName->1:  null   // getName->2:  null   // getName->N:  null   // ofs = -1 ord = 0 addr = 6
	iload_7 
	invokevirtual java.lang.Object elementAt( java.util.Vector, int ) // pc=2
	checkcast_lib String//java.lang.String java.lang.String java.lang.String
	astore 8
	new_lib com.whatsapp.client.ContactInfoDetailsListItem//module:WhatsApp-18.class#1 module:WhatsApp-18.class#1 module:WhatsApp-18.class#1
	dup 
	iload_3 
	invokespecial_lib .routine_3660 // pc=2
	astore_4 
	aload_4 
	bipush 9
	putfield .field_4_4   // get_name_1:  .field_4_4   // get_name_2:  .field_4_4   // get_Name:    .field_4_4   // getName->1:  null   // getName->2:  null   // getName->N:  null   // ofs = -1 ord = 0 addr = 4
	aload_4 
	aload 8
	putfield .field_3_3   // get_name_1:  .field_3_3   // get_name_2:  .field_3_3   // get_Name:    .field_3_3   // getName->1:  null   // getName->2:  null   // getName->N:  null   // ofs = -1 ord = 0 addr = 3
	aload_4 
	aload 8
	putfield .field_2_2   // get_name_1:  .field_2_2   // get_name_2:  .field_2_2   // get_Name:    .field_2_2   // getName->1:  null   // getName->2:  null   // getName->N:  null   // ofs = -1 ord = 0 addr = 2
	aload_4 
	aload_0_getfield .field_0_   // get_name_1:  .field_0_   // get_name_2:  .field_0_   // get_Name:    .field_0_   // getName->1:  null   // getName->2:  null   // getName->N:  null   // ofs = -1 ord = 0 addr = 0
	putfield .field_1_1   // get_name_1:  .field_1_1   // get_name_2:  .field_1_1   // get_Name:    .field_1_1   // getName->1:  null   // getName->2:  null   // getName->N:  null   // ofs = -1 ord = 0 addr = 1
	aload_1 
	aload_4 
	invokevirtual addElement( java.util.Vector, java.lang.Object ) // pc=2
	iinc 7 1
	goto Label17
Label47:
	iconst_0 
	istore_5 
Label49:
	aload_0_getfield .field_9_9   // get_name_1:  .field_9_9   // get_name_2:  .field_9_9   // get_Name:    .field_9_9   // getName->1:  null   // getName->2:  null   // getName->N:  null   // ofs = -1 ord = 0 addr = 9
	ifnonnull Label66
	aload_0_getfield .field_10_10   // get_name_1:  .field_10_10   // get_name_2:  .field_10_10   // get_Name:    .field_10_10   // getName->1:  null   // getName->2:  null   // getName->N:  null   // ofs = -1 ord = 0 addr = 10
	ifnonnull Label66
	aload_0_getfield .field_7_7   // get_name_1:  .field_7_7   // get_name_2:  .field_7_7   // get_Name:    .field_7_7   // getName->1:  null   // getName->2:  null   // getName->N:  null   // ofs = -1 ord = 0 addr = 7
	ifnonnull Label66
	aload_0_getfield .field_8_8   // get_name_1:  .field_8_8   // get_name_2:  .field_8_8   // get_Name:    .field_8_8   // getName->1:  null   // getName->2:  null   // getName->N:  null   // ofs = -1 ord = 0 addr = 8
	ifnonnull Label66
	aload_0_getfield .field_11_11   // get_name_1:  .field_11_11   // get_name_2:  .field_11_11   // get_Name:    .field_11_11   // getName->1:  null   // getName->2:  null   // getName->N:  null   // ofs = -1 ord = 0 addr = 11
	ifnonnull Label66
	aload_0_getfield .field_13_13   // get_name_1:  .field_13_13   // get_name_2:  .field_13_13   // get_Name:    .field_13_13   // getName->1:  null   // getName->2:  null   // getName->N:  null   // ofs = -1 ord = 0 addr = 13
	ifnonnull Label66
	aload_0_getfield .field_14_14   // get_name_1:  .field_14_14   // get_name_2:  .field_14_14   // get_Name:    .field_14_14   // getName->1:  null   // getName->2:  null   // getName->N:  null   // ofs = -1 ord = 0 addr = 14
	ifnonnull Label66
	aload_0_getfield .field_16_16   // get_name_1:  .field_16_16   // get_name_2:  .field_16_16   // get_Name:    .field_16_16   // getName->1:  null   // getName->2:  null   // getName->N:  null   // ofs = -1 ord = 0 addr = 16
	ifnonnull Label66
	goto_w Label138
Label66:
	iload_5 
	ifne Label74
	aload_1 
	aload_0 
	iload_2 
	iload_3 
	invokespecial com.whatsapp.client.ContactInfoDetails.routine_11806 // pc=3
	invokevirtual addElement( java.util.Vector, java.lang.Object ) // pc=2
Label74:
	aload_0 
	aload_1 
	aload_0_getfield .field_11_11   // get_name_1:  .field_11_11   // get_name_2:  .field_11_11   // get_Name:    .field_11_11   // getName->1:  null   // getName->2:  null   // getName->N:  null   // ofs = -1 ord = 0 addr = 11
	bipush 5
	bipush 61
	invokestatic_lib module:WhatsApp-47.class#11.routine_4387(  ) // class#11
	iload_3 
	invokespecial com.whatsapp.client.ContactInfoDetails.routine_11858 // pc=6
	aload_0 
	aload_1 
	aload_0_getfield .field_9_9   // get_name_1:  .field_9_9   // get_name_2:  .field_9_9   // get_Name:    .field_9_9   // getName->1:  null   // getName->2:  null   // getName->N:  null   // ofs = -1 ord = 0 addr = 9
	iconst_1 
	bipush 59
	invokestatic_lib module:WhatsApp-47.class#11.routine_4387(  ) // class#11
	iload_3 
	invokespecial com.whatsapp.client.ContactInfoDetails.routine_11858 // pc=6
	aload_0 
	aload_1 
	aload_0_getfield .field_10_10   // get_name_1:  .field_10_10   // get_name_2:  .field_10_10   // get_Name:    .field_10_10   // getName->1:  null   // getName->2:  null   // getName->N:  null   // ofs = -1 ord = 0 addr = 10
	bipush 2
	bipush 60
	invokestatic_lib module:WhatsApp-47.class#11.routine_4387(  ) // class#11
	iload_3 
	invokespecial com.whatsapp.client.ContactInfoDetails.routine_11858 // pc=6
	aload_0 
	aload_1 
	aload_0_getfield .field_7_7   // get_name_1:  .field_7_7   // get_name_2:  .field_7_7   // get_Name:    .field_7_7   // getName->1:  null   // getName->2:  null   // getName->N:  null   // ofs = -1 ord = 0 addr = 7
	bipush 3
	bipush 57
	invokestatic_lib module:WhatsApp-47.class#11.routine_4387(  ) // class#11
	iload_3 
	invokespecial com.whatsapp.client.ContactInfoDetails.routine_11858 // pc=6
	aload_0 
	aload_1 
	aload_0_getfield .field_8_8   // get_name_1:  .field_8_8   // get_name_2:  .field_8_8   // get_Name:    .field_8_8   // getName->1:  null   // getName->2:  null   // getName->N:  null   // ofs = -1 ord = 0 addr = 8
	bipush 4
	bipush 58
	invokestatic_lib module:WhatsApp-47.class#11.routine_4387(  ) // class#11
	iload_3 
	invokespecial com.whatsapp.client.ContactInfoDetails.routine_11858 // pc=6
	aload_0 
	aload_1 
	aload_0_getfield .field_13_13   // get_name_1:  .field_13_13   // get_name_2:  .field_13_13   // get_Name:    .field_13_13   // getName->1:  null   // getName->2:  null   // getName->N:  null   // ofs = -1 ord = 0 addr = 13
	bipush 6
	bipush 62
	invokestatic_lib module:WhatsApp-47.class#11.routine_4387(  ) // class#11
	iload_3 
	invokespecial com.whatsapp.client.ContactInfoDetails.routine_11858 // pc=6
	aload_0 
	aload_1 
	aload_0_getfield .field_14_14   // get_name_1:  .field_14_14   // get_name_2:  .field_14_14   // get_Name:    .field_14_14   // getName->1:  null   // getName->2:  null   // getName->N:  null   // ofs = -1 ord = 0 addr = 14
	bipush 7
	bipush 63
	invokestatic_lib module:WhatsApp-47.class#11.routine_4387(  ) // class#11
	iload_3 
	invokespecial com.whatsapp.client.ContactInfoDetails.routine_11858 // pc=6
	aload_0 
	aload_1 
	aload_0_getfield .field_16_16   // get_name_1:  .field_16_16   // get_name_2:  .field_16_16   // get_Name:    .field_16_16   // getName->1:  null   // getName->2:  null   // getName->N:  null   // ofs = -1 ord = 0 addr = 16
	bipush 8
	bipush 64
	invokestatic_lib module:WhatsApp-47.class#11.routine_4387(  ) // class#11
	iload_3 
	invokespecial com.whatsapp.client.ContactInfoDetails.routine_11858 // pc=6
Label138:
	return 
	}


public final java.lang.String toString( com.whatsapp.client.ContactInfoDetails ); // address: 0
	{
	enter 
	new_lib net.rim.device.api.ui.decor.Background//net.rim.device.api.ui.decor.Background net.rim.device.api.ui.decor.Background net.rim.device.api.ui.decor.Background
	dup 
	invokespecial_lib java.lang.StringBuffer.<init> // pc=1
	astore_1 
	aload_1 
	aload_0 
	iconst_0 
	invokenonvirtual com.whatsapp.client.ContactInfoDetails.getFullName // pc=2
	invokevirtual java.lang.StringBuffer append( java.lang.StringBuffer, java.lang.String ) // pc=2
	pop 
	aload_1 
	ldc literal_130:" phones: "
	invokevirtual java.lang.StringBuffer append( java.lang.StringBuffer, java.lang.String ) // pc=2
	pop 
	aload_0_getfield .field_11_11   // get_name_1:  .field_11_11   // get_name_2:  .field_11_11   // get_Name:    .field_11_11   // getName->1:  null   // getName->2:  null   // getName->N:  null   // ofs = -1 ord = 0 addr = 11
	ifnull Label27
	aload_1 
	new_lib net.rim.device.api.ui.decor.Background//net.rim.device.api.ui.decor.Background net.rim.device.api.ui.decor.Background net.rim.device.api.ui.decor.Background
	dup 
	ldc literal_131:" mobilePhone="
	invokespecial_lib java.lang.StringBuffer.<init> // pc=2
	aload_0_getfield .field_11_11   // get_name_1:  .field_11_11   // get_name_2:  .field_11_11   // get_Name:    .field_11_11   // getName->1:  null   // getName->2:  null   // getName->N:  null   // ofs = -1 ord = 0 addr = 11
	invokevirtual java.lang.StringBuffer append( java.lang.StringBuffer, java.lang.String ) // pc=2
	invokevirtual_short .toString // idx=2 pc=1
	invokevirtual java.lang.StringBuffer append( java.lang.StringBuffer, java.lang.String ) // pc=2
	pop 
Label27:
	aload_0_getfield .field_12_12   // get_name_1:  .field_12_12   // get_name_2:  .field_12_12   // get_Name:    .field_12_12   // getName->1:  null   // getName->2:  null   // getName->N:  null   // ofs = -1 ord = 0 addr = 12
	ifnull Label39
	aload_1 
	new_lib net.rim.device.api.ui.decor.Background//net.rim.device.api.ui.decor.Background net.rim.device.api.ui.decor.Background net.rim.device.api.ui.decor.Background
	dup 
	ldc literal_132:" mobilePhone2="
	invokespecial_lib java.lang.StringBuffer.<init> // pc=2
	aload_0_getfield .field_12_12   // get_name_1:  .field_12_12   // get_name_2:  .field_12_12   // get_Name:    .field_12_12   // getName->1:  null   // getName->2:  null   // getName->N:  null   // ofs = -1 ord = 0 addr = 12
	invokevirtual java.lang.StringBuffer append( java.lang.StringBuffer, java.lang.String ) // pc=2
	invokevirtual_short .toString // idx=2 pc=1
	invokevirtual java.lang.StringBuffer append( java.lang.StringBuffer, java.lang.String ) // pc=2
	pop 
Label39:
	aload_0_getfield .field_14_14   // get_name_1:  .field_14_14   // get_name_2:  .field_14_14   // get_Name:    .field_14_14   // getName->1:  null   // getName->2:  null   // getName->N:  null   // ofs = -1 ord = 0 addr = 14
	ifnull Label51
	aload_1 
	new_lib net.rim.device.api.ui.decor.Background//net.rim.device.api.ui.decor.Background net.rim.device.api.ui.decor.Background net.rim.device.api.ui.decor.Background
	dup 
	ldc literal_133:" fax="
	invokespecial_lib java.lang.StringBuffer.<init> // pc=2
	aload_0_getfield .field_14_14   // get_name_1:  .field_14_14   // get_name_2:  .field_14_14   // get_Name:    .field_14_14   // getName->1:  null   // getName->2:  null   // getName->N:  null   // ofs = -1 ord = 0 addr = 14
	invokevirtual java.lang.StringBuffer append( java.lang.StringBuffer, java.lang.String ) // pc=2
	invokevirtual_short .toString // idx=2 pc=1
	invokevirtual java.lang.StringBuffer append( java.lang.StringBuffer, java.lang.String ) // pc=2
	pop 
Label51:
	aload_0_getfield .field_15_15   // get_name_1:  .field_15_15   // get_name_2:  .field_15_15   // get_Name:    .field_15_15   // getName->1:  null   // getName->2:  null   // getName->N:  null   // ofs = -1 ord = 0 addr = 15
	ifnull Label63
	aload_1 
	new_lib net.rim.device.api.ui.decor.Background//net.rim.device.api.ui.decor.Background net.rim.device.api.ui.decor.Background net.rim.device.api.ui.decor.Background
	dup 
	ldc literal_134:" fax2="
	invokespecial_lib java.lang.StringBuffer.<init> // pc=2
	aload_0_getfield .field_15_15   // get_name_1:  .field_15_15   // get_name_2:  .field_15_15   // get_Name:    .field_15_15   // getName->1:  null   // getName->2:  null   // getName->N:  null   // ofs = -1 ord = 0 addr = 15
	invokevirtual java.lang.StringBuffer append( java.lang.StringBuffer, java.lang.String ) // pc=2
	invokevirtual_short .toString // idx=2 pc=1
	invokevirtual java.lang.StringBuffer append( java.lang.StringBuffer, java.lang.String ) // pc=2
	pop 
Label63:
	aload_0_getfield .field_9_9   // get_name_1:  .field_9_9   // get_name_2:  .field_9_9   // get_Name:    .field_9_9   // getName->1:  null   // getName->2:  null   // getName->N:  null   // ofs = -1 ord = 0 addr = 9
	ifnull Label75
	aload_1 
	new_lib net.rim.device.api.ui.decor.Background//net.rim.device.api.ui.decor.Background net.rim.device.api.ui.decor.Background net.rim.device.api.ui.decor.Background
	dup 
	ldc literal_135:" homePhone1="
	invokespecial_lib java.lang.StringBuffer.<init> // pc=2
	aload_0_getfield .field_9_9   // get_name_1:  .field_9_9   // get_name_2:  .field_9_9   // get_Name:    .field_9_9   // getName->1:  null   // getName->2:  null   // getName->N:  null   // ofs = -1 ord = 0 addr = 9
	invokevirtual java.lang.StringBuffer append( java.lang.StringBuffer, java.lang.String ) // pc=2
	invokevirtual_short .toString // idx=2 pc=1
	invokevirtual java.lang.StringBuffer append( java.lang.StringBuffer, java.lang.String ) // pc=2
	pop 
Label75:
	aload_0_getfield .field_10_10   // get_name_1:  .field_10_10   // get_name_2:  .field_10_10   // get_Name:    .field_10_10   // getName->1:  null   // getName->2:  null   // getName->N:  null   // ofs = -1 ord = 0 addr = 10
	ifnull Label87
	aload_1 
	new_lib net.rim.device.api.ui.decor.Background//net.rim.device.api.ui.decor.Background net.rim.device.api.ui.decor.Background net.rim.device.api.ui.decor.Background
	dup 
	ldc literal_136:" homePhone2="
	invokespecial_lib java.lang.StringBuffer.<init> // pc=2
	aload_0_getfield .field_10_10   // get_name_1:  .field_10_10   // get_name_2:  .field_10_10   // get_Name:    .field_10_10   // getName->1:  null   // getName->2:  null   // getName->N:  null   // ofs = -1 ord = 0 addr = 10
	invokevirtual java.lang.StringBuffer append( java.lang.StringBuffer, java.lang.String ) // pc=2
	invokevirtual_short .toString // idx=2 pc=1
	invokevirtual java.lang.StringBuffer append( java.lang.StringBuffer, java.lang.String ) // pc=2
	pop 
Label87:
	aload_0_getfield .field_13_13   // get_name_1:  .field_13_13   // get_name_2:  .field_13_13   // get_Name:    .field_13_13   // getName->1:  null   // getName->2:  null   // getName->N:  null   // ofs = -1 ord = 0 addr = 13
	ifnull Label99
	aload_1 
	new_lib net.rim.device.api.ui.decor.Background//net.rim.device.api.ui.decor.Background net.rim.device.api.ui.decor.Background net.rim.device.api.ui.decor.Background
	dup 
	ldc literal_137:" pager="
	invokespecial_lib java.lang.StringBuffer.<init> // pc=2
	aload_0_getfield .field_13_13   // get_name_1:  .field_13_13   // get_name_2:  .field_13_13   // get_Name:    .field_13_13   // getName->1:  null   // getName->2:  null   // getName->N:  null   // ofs = -1 ord = 0 addr = 13
	invokevirtual java.lang.StringBuffer append( java.lang.StringBuffer, java.lang.String ) // pc=2
	invokevirtual_short .toString // idx=2 pc=1
	invokevirtual java.lang.StringBuffer append( java.lang.StringBuffer, java.lang.String ) // pc=2
	pop 
Label99:
	aload_0_getfield .field_16_16   // get_name_1:  .field_16_16   // get_name_2:  .field_16_16   // get_Name:    .field_16_16   // getName->1:  null   // getName->2:  null   // getName->N:  null   // ofs = -1 ord = 0 addr = 16
	ifnull Label111
	aload_1 
	new_lib net.rim.device.api.ui.decor.Background//net.rim.device.api.ui.decor.Background net.rim.device.api.ui.decor.Background net.rim.device.api.ui.decor.Background
	dup 
	ldc literal_138:" otherPhone="
	invokespecial_lib java.lang.StringBuffer.<init> // pc=2
	aload_0_getfield .field_16_16   // get_name_1:  .field_16_16   // get_name_2:  .field_16_16   // get_Name:    .field_16_16   // getName->1:  null   // getName->2:  null   // getName->N:  null   // ofs = -1 ord = 0 addr = 16
	invokevirtual java.lang.StringBuffer append( java.lang.StringBuffer, java.lang.String ) // pc=2
	invokevirtual_short .toString // idx=2 pc=1
	invokevirtual java.lang.StringBuffer append( java.lang.StringBuffer, java.lang.String ) // pc=2
	pop 
Label111:
	aload_0_getfield .field_7_7   // get_name_1:  .field_7_7   // get_name_2:  .field_7_7   // get_Name:    .field_7_7   // getName->1:  null   // getName->2:  null   // getName->N:  null   // ofs = -1 ord = 0 addr = 7
	ifnull Label123
	aload_1 
	new_lib net.rim.device.api.ui.decor.Background//net.rim.device.api.ui.decor.Background net.rim.device.api.ui.decor.Background net.rim.device.api.ui.decor.Background
	dup 
	ldc literal_139:" workPhone1="
	invokespecial_lib java.lang.StringBuffer.<init> // pc=2
	aload_0_getfield .field_7_7   // get_name_1:  .field_7_7   // get_name_2:  .field_7_7   // get_Name:    .field_7_7   // getName->1:  null   // getName->2:  null   // getName->N:  null   // ofs = -1 ord = 0 addr = 7
	invokevirtual java.lang.StringBuffer append( java.lang.StringBuffer, java.lang.String ) // pc=2
	invokevirtual_short .toString // idx=2 pc=1
	invokevirtual java.lang.StringBuffer append( java.lang.StringBuffer, java.lang.String ) // pc=2
	pop 
Label123:
	aload_0_getfield .field_8_8   // get_name_1:  .field_8_8   // get_name_2:  .field_8_8   // get_Name:    .field_8_8   // getName->1:  null   // getName->2:  null   // getName->N:  null   // ofs = -1 ord = 0 addr = 8
	ifnull Label135
	aload_1 
	new_lib net.rim.device.api.ui.decor.Background//net.rim.device.api.ui.decor.Background net.rim.device.api.ui.decor.Background net.rim.device.api.ui.decor.Background
	dup 
	ldc literal_140:" workPhone2="
	invokespecial_lib java.lang.StringBuffer.<init> // pc=2
	aload_0_getfield .field_8_8   // get_name_1:  .field_8_8   // get_name_2:  .field_8_8   // get_Name:    .field_8_8   // getName->1:  null   // getName->2:  null   // getName->N:  null   // ofs = -1 ord = 0 addr = 8
	invokevirtual java.lang.StringBuffer append( java.lang.StringBuffer, java.lang.String ) // pc=2
	invokevirtual_short .toString // idx=2 pc=1
	invokevirtual java.lang.StringBuffer append( java.lang.StringBuffer, java.lang.String ) // pc=2
	pop 
Label135:
	aload_1 
	invokevirtual_short .toString // idx=2 pc=1
	areturn 
	}


public final java.lang.String toVCard( com.whatsapp.client.ContactInfoDetails ); // address: 0
	{
	enter 
	new_lib net.rim.device.api.ui.decor.Background//net.rim.device.api.ui.decor.Background net.rim.device.api.ui.decor.Background net.rim.device.api.ui.decor.Background
	dup 
	getstatic com.whatsapp.client.ContactInfoDetails.field_50740 // ContactInfoDetails
	invokespecial_lib java.lang.StringBuffer.<init> // pc=2
	astore_1 
	aload_1 
	getstatic com.whatsapp.client.ContactInfoDetails.field_50752 // ContactInfoDetails
	invokevirtual java.lang.StringBuffer append( java.lang.StringBuffer, java.lang.String ) // pc=2
	pop 
	aload_0_getfield .field_3_3   // get_name_1:  .field_3_3   // get_name_2:  .field_3_3   // get_Name:    .field_3_3   // getName->1:  null   // getName->2:  null   // getName->N:  null   // ofs = -1 ord = 0 addr = 3
	ifnull Label18
	aload_1 
	aload_0 
	aload_0_getfield .field_3_3   // get_name_1:  .field_3_3   // get_name_2:  .field_3_3   // get_Name:    .field_3_3   // getName->1:  null   // getName->2:  null   // getName->N:  null   // ofs = -1 ord = 0 addr = 3
	invokespecial com.whatsapp.client.ContactInfoDetails.routine_11920 // pc=2
	invokevirtual java.lang.StringBuffer append( java.lang.StringBuffer, java.lang.String ) // pc=2
	pop 
Label18:
	aload_1 
	getstatic com.whatsapp.client.ContactInfoDetails.field_50728 // ContactInfoDetails
	invokevirtual java.lang.StringBuffer append( java.lang.StringBuffer, java.lang.String ) // pc=2
	pop 
	aload_0_getfield .field_2_2   // get_name_1:  .field_2_2   // get_name_2:  .field_2_2   // get_Name:    .field_2_2   // getName->1:  null   // getName->2:  null   // getName->N:  null   // ofs = -1 ord = 0 addr = 2
	ifnull Label30
	aload_1 
	aload_0 
	aload_0_getfield .field_2_2   // get_name_1:  .field_2_2   // get_name_2:  .field_2_2   // get_Name:    .field_2_2   // getName->1:  null   // getName->2:  null   // getName->N:  null   // ofs = -1 ord = 0 addr = 2
	invokespecial com.whatsapp.client.ContactInfoDetails.routine_11920 // pc=2
	invokevirtual java.lang.StringBuffer append( java.lang.StringBuffer, java.lang.String ) // pc=2
	pop 
Label30:
	aload_1 
	getstatic com.whatsapp.client.ContactInfoDetails.field_50728 // ContactInfoDetails
	invokevirtual java.lang.StringBuffer append( java.lang.StringBuffer, java.lang.String ) // pc=2
	pop 
	aload_1 
	getstatic com.whatsapp.client.ContactInfoDetails.field_50728 // ContactInfoDetails
	invokevirtual java.lang.StringBuffer append( java.lang.StringBuffer, java.lang.String ) // pc=2
	pop 
	aload_0_getfield .field_1_1   // get_name_1:  .field_1_1   // get_name_2:  .field_1_1   // get_Name:    .field_1_1   // getName->1:  null   // getName->2:  null   // getName->N:  null   // ofs = -1 ord = 0 addr = 1
	ifnull Label46
	aload_1 
	aload_0 
	aload_0_getfield .field_1_1   // get_name_1:  .field_1_1   // get_name_2:  .field_1_1   // get_Name:    .field_1_1   // getName->1:  null   // getName->2:  null   // getName->N:  null   // ofs = -1 ord = 0 addr = 1
	invokespecial com.whatsapp.client.ContactInfoDetails.routine_11920 // pc=2
	invokevirtual java.lang.StringBuffer append( java.lang.StringBuffer, java.lang.String ) // pc=2
	pop 
Label46:
	aload_1 
	getstatic_lib module:WhatsApp-19.class#0.static_4 // class#0
	invokevirtual java.lang.StringBuffer append( java.lang.StringBuffer, java.lang.String ) // pc=2
	pop 
	aload_1 
	getstatic com.whatsapp.client.ContactInfoDetails.field_50746 // ContactInfoDetails
	invokevirtual java.lang.StringBuffer append( java.lang.StringBuffer, java.lang.String ) // pc=2
	pop 
	aload_1 
	aload_0 
	aload_0 
	iconst_0 
	invokenonvirtual com.whatsapp.client.ContactInfoDetails.getFullName // pc=2
	invokespecial com.whatsapp.client.ContactInfoDetails.routine_11920 // pc=2
	invokevirtual java.lang.StringBuffer append( java.lang.StringBuffer, java.lang.String ) // pc=2
	pop 
	aload_1 
	getstatic_lib module:WhatsApp-19.class#0.static_4 // class#0
	invokevirtual java.lang.StringBuffer append( java.lang.StringBuffer, java.lang.String ) // pc=2
	pop 
	aload_0_getfield .field_4_4   // get_name_1:  .field_4_4   // get_name_2:  .field_4_4   // get_Name:    .field_4_4   // getName->1:  null   // getName->2:  null   // getName->N:  null   // ofs = -1 ord = 0 addr = 4
	ifnull Label82
	aload_1 
	getstatic com.whatsapp.client.ContactInfoDetails.field_50758 // ContactInfoDetails
	invokevirtual java.lang.StringBuffer append( java.lang.StringBuffer, java.lang.String ) // pc=2
	pop 
	aload_1 
	aload_0 
	aload_0_getfield .field_4_4   // get_name_1:  .field_4_4   // get_name_2:  .field_4_4   // get_Name:    .field_4_4   // getName->1:  null   // getName->2:  null   // getName->N:  null   // ofs = -1 ord = 0 addr = 4
	invokespecial com.whatsapp.client.ContactInfoDetails.routine_11920 // pc=2
	invokevirtual java.lang.StringBuffer append( java.lang.StringBuffer, java.lang.String ) // pc=2
	pop 
	aload_1 
	getstatic_lib module:WhatsApp-19.class#0.static_4 // class#0
	invokevirtual java.lang.StringBuffer append( java.lang.StringBuffer, java.lang.String ) // pc=2
	pop 
Label82:
	aload_0_getfield .field_5_5   // get_name_1:  .field_5_5   // get_name_2:  .field_5_5   // get_Name:    .field_5_5   // getName->1:  null   // getName->2:  null   // getName->N:  null   // ofs = -1 ord = 0 addr = 5
	ifnull Label98
	aload_1 
	getstatic com.whatsapp.client.ContactInfoDetails.field_50764 // ContactInfoDetails
	invokevirtual java.lang.StringBuffer append( java.lang.StringBuffer, java.lang.String ) // pc=2
	pop 
	aload_1 
	aload_0 
	aload_0_getfield .field_5_5   // get_name_1:  .field_5_5   // get_name_2:  .field_5_5   // get_Name:    .field_5_5   // getName->1:  null   // getName->2:  null   // getName->N:  null   // ofs = -1 ord = 0 addr = 5
	invokespecial com.whatsapp.client.ContactInfoDetails.routine_11920 // pc=2
	invokevirtual java.lang.StringBuffer append( java.lang.StringBuffer, java.lang.String ) // pc=2
	pop 
	aload_1 
	getstatic_lib module:WhatsApp-19.class#0.static_4 // class#0
	invokevirtual java.lang.StringBuffer append( java.lang.StringBuffer, java.lang.String ) // pc=2
	pop 
Label98:
	aload_0_getfield .field_11_11   // get_name_1:  .field_11_11   // get_name_2:  .field_11_11   // get_Name:    .field_11_11   // getName->1:  null   // getName->2:  null   // getName->N:  null   // ofs = -1 ord = 0 addr = 11
	ifnull Label114
	aload_1 
	new_lib net.rim.device.api.ui.decor.Background//net.rim.device.api.ui.decor.Background net.rim.device.api.ui.decor.Background net.rim.device.api.ui.decor.Background
	dup 
	ldc literal_141:"TEL;type=CELL:"
	invokespecial_lib java.lang.StringBuffer.<init> // pc=2
	aload_0 
	aload_0_getfield .field_11_11   // get_name_1:  .field_11_11   // get_name_2:  .field_11_11   // get_Name:    .field_11_11   // getName->1:  null   // getName->2:  null   // getName->N:  null   // ofs = -1 ord = 0 addr = 11
	invokespecial com.whatsapp.client.ContactInfoDetails.routine_11920 // pc=2
	invokevirtual java.lang.StringBuffer append( java.lang.StringBuffer, java.lang.String ) // pc=2
	getstatic_lib module:WhatsApp-19.class#0.static_4 // class#0
	invokevirtual java.lang.StringBuffer append( java.lang.StringBuffer, java.lang.String ) // pc=2
	invokevirtual_short .toString // idx=2 pc=1
	invokevirtual java.lang.StringBuffer append( java.lang.StringBuffer, java.lang.String ) // pc=2
	pop 
Label114:
	aload_0_getfield .field_12_12   // get_name_1:  .field_12_12   // get_name_2:  .field_12_12   // get_Name:    .field_12_12   // getName->1:  null   // getName->2:  null   // getName->N:  null   // ofs = -1 ord = 0 addr = 12
	ifnull Label130
	aload_1 
	new_lib net.rim.device.api.ui.decor.Background//net.rim.device.api.ui.decor.Background net.rim.device.api.ui.decor.Background net.rim.device.api.ui.decor.Background
	dup 
	ldc literal_141:"TEL;type=CELL:"
	invokespecial_lib java.lang.StringBuffer.<init> // pc=2
	aload_0 
	aload_0_getfield .field_12_12   // get_name_1:  .field_12_12   // get_name_2:  .field_12_12   // get_Name:    .field_12_12   // getName->1:  null   // getName->2:  null   // getName->N:  null   // ofs = -1 ord = 0 addr = 12
	invokespecial com.whatsapp.client.ContactInfoDetails.routine_11920 // pc=2
	invokevirtual java.lang.StringBuffer append( java.lang.StringBuffer, java.lang.String ) // pc=2
	getstatic_lib module:WhatsApp-19.class#0.static_4 // class#0
	invokevirtual java.lang.StringBuffer append( java.lang.StringBuffer, java.lang.String ) // pc=2
	invokevirtual_short .toString // idx=2 pc=1
	invokevirtual java.lang.StringBuffer append( java.lang.StringBuffer, java.lang.String ) // pc=2
	pop 
Label130:
	aload_0_getfield .field_14_14   // get_name_1:  .field_14_14   // get_name_2:  .field_14_14   // get_Name:    .field_14_14   // getName->1:  null   // getName->2:  null   // getName->N:  null   // ofs = -1 ord = 0 addr = 14
	ifnull Label146
	aload_1 
	new_lib net.rim.device.api.ui.decor.Background//net.rim.device.api.ui.decor.Background net.rim.device.api.ui.decor.Background net.rim.device.api.ui.decor.Background
	dup 
	ldc literal_142:"TEL;type=FAX:"
	invokespecial_lib java.lang.StringBuffer.<init> // pc=2
	aload_0 
	aload_0_getfield .field_14_14   // get_name_1:  .field_14_14   // get_name_2:  .field_14_14   // get_Name:    .field_14_14   // getName->1:  null   // getName->2:  null   // getName->N:  null   // ofs = -1 ord = 0 addr = 14
	invokespecial com.whatsapp.client.ContactInfoDetails.routine_11920 // pc=2
	invokevirtual java.lang.StringBuffer append( java.lang.StringBuffer, java.lang.String ) // pc=2
	getstatic_lib module:WhatsApp-19.class#0.static_4 // class#0
	invokevirtual java.lang.StringBuffer append( java.lang.StringBuffer, java.lang.String ) // pc=2
	invokevirtual_short .toString // idx=2 pc=1
	invokevirtual java.lang.StringBuffer append( java.lang.StringBuffer, java.lang.String ) // pc=2
	pop 
Label146:
	aload_0_getfield .field_15_15   // get_name_1:  .field_15_15   // get_name_2:  .field_15_15   // get_Name:    .field_15_15   // getName->1:  null   // getName->2:  null   // getName->N:  null   // ofs = -1 ord = 0 addr = 15
	ifnull Label162
	aload_1 
	new_lib net.rim.device.api.ui.decor.Background//net.rim.device.api.ui.decor.Background net.rim.device.api.ui.decor.Background net.rim.device.api.ui.decor.Background
	dup 
	ldc literal_142:"TEL;type=FAX:"
	invokespecial_lib java.lang.StringBuffer.<init> // pc=2
	aload_0 
	aload_0_getfield .field_15_15   // get_name_1:  .field_15_15   // get_name_2:  .field_15_15   // get_Name:    .field_15_15   // getName->1:  null   // getName->2:  null   // getName->N:  null   // ofs = -1 ord = 0 addr = 15
	invokespecial com.whatsapp.client.ContactInfoDetails.routine_11920 // pc=2
	invokevirtual java.lang.StringBuffer append( java.lang.StringBuffer, java.lang.String ) // pc=2
	getstatic_lib module:WhatsApp-19.class#0.static_4 // class#0
	invokevirtual java.lang.StringBuffer append( java.lang.StringBuffer, java.lang.String ) // pc=2
	invokevirtual_short .toString // idx=2 pc=1
	invokevirtual java.lang.StringBuffer append( java.lang.StringBuffer, java.lang.String ) // pc=2
	pop 
Label162:
	aload_0_getfield .field_9_9   // get_name_1:  .field_9_9   // get_name_2:  .field_9_9   // get_Name:    .field_9_9   // getName->1:  null   // getName->2:  null   // getName->N:  null   // ofs = -1 ord = 0 addr = 9
	ifnull Label178
	aload_1 
	new_lib net.rim.device.api.ui.decor.Background//net.rim.device.api.ui.decor.Background net.rim.device.api.ui.decor.Background net.rim.device.api.ui.decor.Background
	dup 
	ldc literal_143:"TEL;type=HOME:"
	invokespecial_lib java.lang.StringBuffer.<init> // pc=2
	aload_0 
	aload_0_getfield .field_9_9   // get_name_1:  .field_9_9   // get_name_2:  .field_9_9   // get_Name:    .field_9_9   // getName->1:  null   // getName->2:  null   // getName->N:  null   // ofs = -1 ord = 0 addr = 9
	invokespecial com.whatsapp.client.ContactInfoDetails.routine_11920 // pc=2
	invokevirtual java.lang.StringBuffer append( java.lang.StringBuffer, java.lang.String ) // pc=2
	getstatic_lib module:WhatsApp-19.class#0.static_4 // class#0
	invokevirtual java.lang.StringBuffer append( java.lang.StringBuffer, java.lang.String ) // pc=2
	invokevirtual_short .toString // idx=2 pc=1
	invokevirtual java.lang.StringBuffer append( java.lang.StringBuffer, java.lang.String ) // pc=2
	pop 
Label178:
	aload_0_getfield .field_10_10   // get_name_1:  .field_10_10   // get_name_2:  .field_10_10   // get_Name:    .field_10_10   // getName->1:  null   // getName->2:  null   // getName->N:  null   // ofs = -1 ord = 0 addr = 10
	ifnull Label194
	aload_1 
	new_lib net.rim.device.api.ui.decor.Background//net.rim.device.api.ui.decor.Background net.rim.device.api.ui.decor.Background net.rim.device.api.ui.decor.Background
	dup 
	ldc literal_143:"TEL;type=HOME:"
	invokespecial_lib java.lang.StringBuffer.<init> // pc=2
	aload_0 
	aload_0_getfield .field_10_10   // get_name_1:  .field_10_10   // get_name_2:  .field_10_10   // get_Name:    .field_10_10   // getName->1:  null   // getName->2:  null   // getName->N:  null   // ofs = -1 ord = 0 addr = 10
	invokespecial com.whatsapp.client.ContactInfoDetails.routine_11920 // pc=2
	invokevirtual java.lang.StringBuffer append( java.lang.StringBuffer, java.lang.String ) // pc=2
	getstatic_lib module:WhatsApp-19.class#0.static_4 // class#0
	invokevirtual java.lang.StringBuffer append( java.lang.StringBuffer, java.lang.String ) // pc=2
	invokevirtual_short .toString // idx=2 pc=1
	invokevirtual java.lang.StringBuffer append( java.lang.StringBuffer, java.lang.String ) // pc=2
	pop 
Label194:
	aload_0_getfield .field_13_13   // get_name_1:  .field_13_13   // get_name_2:  .field_13_13   // get_Name:    .field_13_13   // getName->1:  null   // getName->2:  null   // getName->N:  null   // ofs = -1 ord = 0 addr = 13
	ifnull Label210
	aload_1 
	new_lib net.rim.device.api.ui.decor.Background//net.rim.device.api.ui.decor.Background net.rim.device.api.ui.decor.Background net.rim.device.api.ui.decor.Background
	dup 
	ldc literal_144:"TEL;type=PAGER:"
	invokespecial_lib java.lang.StringBuffer.<init> // pc=2
	aload_0 
	aload_0_getfield .field_13_13   // get_name_1:  .field_13_13   // get_name_2:  .field_13_13   // get_Name:    .field_13_13   // getName->1:  null   // getName->2:  null   // getName->N:  null   // ofs = -1 ord = 0 addr = 13
	invokespecial com.whatsapp.client.ContactInfoDetails.routine_11920 // pc=2
	invokevirtual java.lang.StringBuffer append( java.lang.StringBuffer, java.lang.String ) // pc=2
	getstatic_lib module:WhatsApp-19.class#0.static_4 // class#0
	invokevirtual java.lang.StringBuffer append( java.lang.StringBuffer, java.lang.String ) // pc=2
	invokevirtual_short .toString // idx=2 pc=1
	invokevirtual java.lang.StringBuffer append( java.lang.StringBuffer, java.lang.String ) // pc=2
	pop 
Label210:
	aload_0_getfield .field_16_16   // get_name_1:  .field_16_16   // get_name_2:  .field_16_16   // get_Name:    .field_16_16   // getName->1:  null   // getName->2:  null   // getName->N:  null   // ofs = -1 ord = 0 addr = 16
	ifnull Label226
	aload_1 
	new_lib net.rim.device.api.ui.decor.Background//net.rim.device.api.ui.decor.Background net.rim.device.api.ui.decor.Background net.rim.device.api.ui.decor.Background
	dup 
	ldc literal_145:"TEL;type=OTHER:"
	invokespecial_lib java.lang.StringBuffer.<init> // pc=2
	aload_0 
	aload_0_getfield .field_16_16   // get_name_1:  .field_16_16   // get_name_2:  .field_16_16   // get_Name:    .field_16_16   // getName->1:  null   // getName->2:  null   // getName->N:  null   // ofs = -1 ord = 0 addr = 16
	invokespecial com.whatsapp.client.ContactInfoDetails.routine_11920 // pc=2
	invokevirtual java.lang.StringBuffer append( java.lang.StringBuffer, java.lang.String ) // pc=2
	getstatic_lib module:WhatsApp-19.class#0.static_4 // class#0
	invokevirtual java.lang.StringBuffer append( java.lang.StringBuffer, java.lang.String ) // pc=2
	invokevirtual_short .toString // idx=2 pc=1
	invokevirtual java.lang.StringBuffer append( java.lang.StringBuffer, java.lang.String ) // pc=2
	pop 
Label226:
	aload_0_getfield .field_7_7   // get_name_1:  .field_7_7   // get_name_2:  .field_7_7   // get_Name:    .field_7_7   // getName->1:  null   // getName->2:  null   // getName->N:  null   // ofs = -1 ord = 0 addr = 7
	ifnull Label242
	aload_1 
	new_lib net.rim.device.api.ui.decor.Background//net.rim.device.api.ui.decor.Background net.rim.device.api.ui.decor.Background net.rim.device.api.ui.decor.Background
	dup 
	ldc literal_146:"TEL;type=WORK:"
	invokespecial_lib java.lang.StringBuffer.<init> // pc=2
	aload_0 
	aload_0_getfield .field_7_7   // get_name_1:  .field_7_7   // get_name_2:  .field_7_7   // get_Name:    .field_7_7   // getName->1:  null   // getName->2:  null   // getName->N:  null   // ofs = -1 ord = 0 addr = 7
	invokespecial com.whatsapp.client.ContactInfoDetails.routine_11920 // pc=2
	invokevirtual java.lang.StringBuffer append( java.lang.StringBuffer, java.lang.String ) // pc=2
	getstatic_lib module:WhatsApp-19.class#0.static_4 // class#0
	invokevirtual java.lang.StringBuffer append( java.lang.StringBuffer, java.lang.String ) // pc=2
	invokevirtual_short .toString // idx=2 pc=1
	invokevirtual java.lang.StringBuffer append( java.lang.StringBuffer, java.lang.String ) // pc=2
	pop 
Label242:
	aload_0_getfield .field_8_8   // get_name_1:  .field_8_8   // get_name_2:  .field_8_8   // get_Name:    .field_8_8   // getName->1:  null   // getName->2:  null   // getName->N:  null   // ofs = -1 ord = 0 addr = 8
	ifnull Label258
	aload_1 
	new_lib net.rim.device.api.ui.decor.Background//net.rim.device.api.ui.decor.Background net.rim.device.api.ui.decor.Background net.rim.device.api.ui.decor.Background
	dup 
	ldc literal_146:"TEL;type=WORK:"
	invokespecial_lib java.lang.StringBuffer.<init> // pc=2
	aload_0 
	aload_0_getfield .field_8_8   // get_name_1:  .field_8_8   // get_name_2:  .field_8_8   // get_Name:    .field_8_8   // getName->1:  null   // getName->2:  null   // getName->N:  null   // ofs = -1 ord = 0 addr = 8
	invokespecial com.whatsapp.client.ContactInfoDetails.routine_11920 // pc=2
	invokevirtual java.lang.StringBuffer append( java.lang.StringBuffer, java.lang.String ) // pc=2
	getstatic_lib module:WhatsApp-19.class#0.static_4 // class#0
	invokevirtual java.lang.StringBuffer append( java.lang.StringBuffer, java.lang.String ) // pc=2
	invokevirtual_short .toString // idx=2 pc=1
	invokevirtual java.lang.StringBuffer append( java.lang.StringBuffer, java.lang.String ) // pc=2
	pop 
Label258:
	iconst_0 
	istore_2 
Label260:
	iload_2 
	aload_0_getfield .field_6_6   // get_name_1:  .field_6_6   // get_name_2:  .field_6_6   // get_Name:    .field_6_6   // getName->1:  null   // getName->2:  null   // getName->N:  null   // ofs = -1 ord = 0 addr = 6
	invokevirtual int size( java.util.Vector ) // pc=1
	if_icmpge Label281
	aload_1 
	new_lib net.rim.device.api.ui.decor.Background//net.rim.device.api.ui.decor.Background net.rim.device.api.ui.decor.Background net.rim.device.api.ui.decor.Background
	dup 
	ldc literal_147:"EMAIL;type=INTERNET:"
	invokespecial_lib java.lang.StringBuffer.<init> // pc=2
	aload_0_getfield .field_6_6   // get_name_1:  .field_6_6   // get_name_2:  .field_6_6   // get_Name:    .field_6_6   // getName->1:  null   // getName->2:  null   // getName->N:  null   // ofs = -1 ord = 0 addr = 6
	iload_2 
	invokevirtual java.lang.Object elementAt( java.util.Vector, int ) // pc=2
	checkcast_lib String//java.lang.String java.lang.String java.lang.String
	invokevirtual java.lang.StringBuffer append( java.lang.StringBuffer, java.lang.String ) // pc=2
	getstatic_lib module:WhatsApp-19.class#0.static_4 // class#0
	invokevirtual java.lang.StringBuffer append( java.lang.StringBuffer, java.lang.String ) // pc=2
	invokevirtual_short .toString // idx=2 pc=1
	invokevirtual java.lang.StringBuffer append( java.lang.StringBuffer, java.lang.String ) // pc=2
	pop 
	iinc 2 1
	goto Label260
Label281:
	aload_0_getfield .field_18_18   // get_name_1:  .field_18_18   // get_name_2:  .field_18_18   // get_Name:    .field_18_18   // getName->1:  null   // getName->2:  null   // getName->N:  null   // ofs = -1 ord = 0 addr = 18
	ifnonnull Label294
	aload_0_getfield .field_19_19   // get_name_1:  .field_19_19   // get_name_2:  .field_19_19   // get_Name:    .field_19_19   // getName->1:  null   // getName->2:  null   // getName->N:  null   // ofs = -1 ord = 0 addr = 19
	ifnonnull Label294
	aload_0_getfield .field_20_20   // get_name_1:  .field_20_20   // get_name_2:  .field_20_20   // get_Name:    .field_20_20   // getName->1:  null   // getName->2:  null   // getName->N:  null   // ofs = -1 ord = 0 addr = 20
	ifnonnull Label294
	aload_0_getfield .field_21_21   // get_name_1:  .field_21_21   // get_name_2:  .field_21_21   // get_Name:    .field_21_21   // getName->1:  null   // getName->2:  null   // getName->N:  null   // ofs = -1 ord = 0 addr = 21
	ifnonnull Label294
	aload_0_getfield .field_22_22   // get_name_1:  .field_22_22   // get_name_2:  .field_22_22   // get_Name:    .field_22_22   // getName->1:  null   // getName->2:  null   // getName->N:  null   // ofs = -1 ord = 0 addr = 22
	ifnonnull Label294
	aload_0_getfield .field_23_23   // get_name_1:  .field_23_23   // get_name_2:  .field_23_23   // get_Name:    .field_23_23   // getName->1:  null   // getName->2:  null   // getName->N:  null   // ofs = -1 ord = 0 addr = 23
	ifnonnull Label294
	goto_w Label372
Label294:
	aload_1 
	ldc literal_148:"ADR;type=WORK:;;"
	invokevirtual java.lang.StringBuffer append( java.lang.StringBuffer, java.lang.String ) // pc=2
	pop 
	aload_0_getfield .field_18_18   // get_name_1:  .field_18_18   // get_name_2:  .field_18_18   // get_Name:    .field_18_18   // getName->1:  null   // getName->2:  null   // getName->N:  null   // ofs = -1 ord = 0 addr = 18
	ifnull Label312
	aload_1 
	aload_0 
	aload_0_getfield .field_18_18   // get_name_1:  .field_18_18   // get_name_2:  .field_18_18   // get_Name:    .field_18_18   // getName->1:  null   // getName->2:  null   // getName->N:  null   // ofs = -1 ord = 0 addr = 18
	invokespecial com.whatsapp.client.ContactInfoDetails.routine_11920 // pc=2
	invokevirtual java.lang.StringBuffer append( java.lang.StringBuffer, java.lang.String ) // pc=2
	pop 
	aload_0_getfield .field_19_19   // get_name_1:  .field_19_19   // get_name_2:  .field_19_19   // get_Name:    .field_19_19   // getName->1:  null   // getName->2:  null   // getName->N:  null   // ofs = -1 ord = 0 addr = 19
	ifnull Label312
	aload_1 
	getstatic com.whatsapp.client.ContactInfoDetails.field_50734 // ContactInfoDetails
	invokevirtual java.lang.StringBuffer append( java.lang.StringBuffer, java.lang.String ) // pc=2
	pop 
Label312:
	aload_0_getfield .field_19_19   // get_name_1:  .field_19_19   // get_name_2:  .field_19_19   // get_Name:    .field_19_19   // getName->1:  null   // getName->2:  null   // getName->N:  null   // ofs = -1 ord = 0 addr = 19
	ifnull Label320
	aload_1 
	aload_0 
	aload_0_getfield .field_19_19   // get_name_1:  .field_19_19   // get_name_2:  .field_19_19   // get_Name:    .field_19_19   // getName->1:  null   // getName->2:  null   // getName->N:  null   // ofs = -1 ord = 0 addr = 19
	invokespecial com.whatsapp.client.ContactInfoDetails.routine_11920 // pc=2
	invokevirtual java.lang.StringBuffer append( java.lang.StringBuffer, java.lang.String ) // pc=2
	pop 
Label320:
	aload_1 
	getstatic com.whatsapp.client.ContactInfoDetails.field_50728 // ContactInfoDetails
	invokevirtual java.lang.StringBuffer append( java.lang.StringBuffer, java.lang.String ) // pc=2
	pop 
	aload_0_getfield .field_20_20   // get_name_1:  .field_20_20   // get_name_2:  .field_20_20   // get_Name:    .field_20_20   // getName->1:  null   // getName->2:  null   // getName->N:  null   // ofs = -1 ord = 0 addr = 20
	ifnull Label332
	aload_1 
	aload_0 
	aload_0_getfield .field_20_20   // get_name_1:  .field_20_20   // get_name_2:  .field_20_20   // get_Name:    .field_20_20   // getName->1:  null   // getName->2:  null   // getName->N:  null   // ofs = -1 ord = 0 addr = 20
	invokespecial com.whatsapp.client.ContactInfoDetails.routine_11920 // pc=2
	invokevirtual java.lang.StringBuffer append( java.lang.StringBuffer, java.lang.String ) // pc=2
	pop 
Label332:
	aload_1 
	getstatic com.whatsapp.client.ContactInfoDetails.field_50728 // ContactInfoDetails
	invokevirtual java.lang.StringBuffer append( java.lang.StringBuffer, java.lang.String ) // pc=2
	pop 
	aload_0_getfield .field_21_21   // get_name_1:  .field_21_21   // get_name_2:  .field_21_21   // get_Name:    .field_21_21   // getName->1:  null   // getName->2:  null   // getName->N:  null   // ofs = -1 ord = 0 addr = 21
	ifnull Label344
	aload_1 
	aload_0 
	aload_0_getfield .field_21_21   // get_name_1:  .field_21_21   // get_name_2:  .field_21_21   // get_Name:    .field_21_21   // getName->1:  null   // getName->2:  null   // getName->N:  null   // ofs = -1 ord = 0 addr = 21
	invokespecial com.whatsapp.client.ContactInfoDetails.routine_11920 // pc=2
	invokevirtual java.lang.StringBuffer append( java.lang.StringBuffer, java.lang.String ) // pc=2
	pop 
Label344:
	aload_1 
	getstatic com.whatsapp.client.ContactInfoDetails.field_50728 // ContactInfoDetails
	invokevirtual java.lang.StringBuffer append( java.lang.StringBuffer, java.lang.String ) // pc=2
	pop 
	aload_0_getfield .field_22_22   // get_name_1:  .field_22_22   // get_name_2:  .field_22_22   // get_Name:    .field_22_22   // getName->1:  null   // getName->2:  null   // getName->N:  null   // ofs = -1 ord = 0 addr = 22
	ifnull Label356
	aload_1 
	aload_0 
	aload_0_getfield .field_22_22   // get_name_1:  .field_22_22   // get_name_2:  .field_22_22   // get_Name:    .field_22_22   // getName->1:  null   // getName->2:  null   // getName->N:  null   // ofs = -1 ord = 0 addr = 22
	invokespecial com.whatsapp.client.ContactInfoDetails.routine_11920 // pc=2
	invokevirtual java.lang.StringBuffer append( java.lang.StringBuffer, java.lang.String ) // pc=2
	pop 
Label356:
	aload_1 
	getstatic com.whatsapp.client.ContactInfoDetails.field_50728 // ContactInfoDetails
	invokevirtual java.lang.StringBuffer append( java.lang.StringBuffer, java.lang.String ) // pc=2
	pop 
	aload_0_getfield .field_23_23   // get_name_1:  .field_23_23   // get_name_2:  .field_23_23   // get_Name:    .field_23_23   // getName->1:  null   // getName->2:  null   // getName->N:  null   // ofs = -1 ord = 0 addr = 23
	ifnull Label368
	aload_1 
	aload_0 
	aload_0_getfield .field_23_23   // get_name_1:  .field_23_23   // get_name_2:  .field_23_23   // get_Name:    .field_23_23   // getName->1:  null   // getName->2:  null   // getName->N:  null   // ofs = -1 ord = 0 addr = 23
	invokespecial com.whatsapp.client.ContactInfoDetails.routine_11920 // pc=2
	invokevirtual java.lang.StringBuffer append( java.lang.StringBuffer, java.lang.String ) // pc=2
	pop 
Label368:
	aload_1 
	getstatic_lib module:WhatsApp-19.class#0.static_4 // class#0
	invokevirtual java.lang.StringBuffer append( java.lang.StringBuffer, java.lang.String ) // pc=2
	pop 
Label372:
	aload_0_getfield .field_24_24   // get_name_1:  .field_24_24   // get_name_2:  .field_24_24   // get_Name:    .field_24_24   // getName->1:  null   // getName->2:  null   // getName->N:  null   // ofs = -1 ord = 0 addr = 24
	ifnonnull Label385
	aload_0_getfield .field_25_25   // get_name_1:  .field_25_25   // get_name_2:  .field_25_25   // get_Name:    .field_25_25   // getName->1:  null   // getName->2:  null   // getName->N:  null   // ofs = -1 ord = 0 addr = 25
	ifnonnull Label385
	aload_0_getfield .field_26_26   // get_name_1:  .field_26_26   // get_name_2:  .field_26_26   // get_Name:    .field_26_26   // getName->1:  null   // getName->2:  null   // getName->N:  null   // ofs = -1 ord = 0 addr = 26
	ifnonnull Label385
	aload_0_getfield .field_27_27   // get_name_1:  .field_27_27   // get_name_2:  .field_27_27   // get_Name:    .field_27_27   // getName->1:  null   // getName->2:  null   // getName->N:  null   // ofs = -1 ord = 0 addr = 27
	ifnonnull Label385
	aload_0_getfield .field_28_28   // get_name_1:  .field_28_28   // get_name_2:  .field_28_28   // get_Name:    .field_28_28   // getName->1:  null   // getName->2:  null   // getName->N:  null   // ofs = -1 ord = 0 addr = 28
	ifnonnull Label385
	aload_0_getfield .field_29_29   // get_name_1:  .field_29_29   // get_name_2:  .field_29_29   // get_Name:    .field_29_29   // getName->1:  null   // getName->2:  null   // getName->N:  null   // ofs = -1 ord = 0 addr = 29
	ifnonnull Label385
	goto_w Label463
Label385:
	aload_1 
	ldc literal_149:"ADR;type=HOME:;;"
	invokevirtual java.lang.StringBuffer append( java.lang.StringBuffer, java.lang.String ) // pc=2
	pop 
	aload_0_getfield .field_24_24   // get_name_1:  .field_24_24   // get_name_2:  .field_24_24   // get_Name:    .field_24_24   // getName->1:  null   // getName->2:  null   // getName->N:  null   // ofs = -1 ord = 0 addr = 24
	ifnull Label403
	aload_1 
	aload_0 
	aload_0_getfield .field_24_24   // get_name_1:  .field_24_24   // get_name_2:  .field_24_24   // get_Name:    .field_24_24   // getName->1:  null   // getName->2:  null   // getName->N:  null   // ofs = -1 ord = 0 addr = 24
	invokespecial com.whatsapp.client.ContactInfoDetails.routine_11920 // pc=2
	invokevirtual java.lang.StringBuffer append( java.lang.StringBuffer, java.lang.String ) // pc=2
	pop 
	aload_0_getfield .field_25_25   // get_name_1:  .field_25_25   // get_name_2:  .field_25_25   // get_Name:    .field_25_25   // getName->1:  null   // getName->2:  null   // getName->N:  null   // ofs = -1 ord = 0 addr = 25
	ifnull Label403
	aload_1 
	getstatic com.whatsapp.client.ContactInfoDetails.field_50734 // ContactInfoDetails
	invokevirtual java.lang.StringBuffer append( java.lang.StringBuffer, java.lang.String ) // pc=2
	pop 
Label403:
	aload_0_getfield .field_25_25   // get_name_1:  .field_25_25   // get_name_2:  .field_25_25   // get_Name:    .field_25_25   // getName->1:  null   // getName->2:  null   // getName->N:  null   // ofs = -1 ord = 0 addr = 25
	ifnull Label411
	aload_1 
	aload_0 
	aload_0_getfield .field_25_25   // get_name_1:  .field_25_25   // get_name_2:  .field_25_25   // get_Name:    .field_25_25   // getName->1:  null   // getName->2:  null   // getName->N:  null   // ofs = -1 ord = 0 addr = 25
	invokespecial com.whatsapp.client.ContactInfoDetails.routine_11920 // pc=2
	invokevirtual java.lang.StringBuffer append( java.lang.StringBuffer, java.lang.String ) // pc=2
	pop 
Label411:
	aload_1 
	getstatic com.whatsapp.client.ContactInfoDetails.field_50728 // ContactInfoDetails
	invokevirtual java.lang.StringBuffer append( java.lang.StringBuffer, java.lang.String ) // pc=2
	pop 
	aload_0_getfield .field_26_26   // get_name_1:  .field_26_26   // get_name_2:  .field_26_26   // get_Name:    .field_26_26   // getName->1:  null   // getName->2:  null   // getName->N:  null   // ofs = -1 ord = 0 addr = 26
	ifnull Label423
	aload_1 
	aload_0 
	aload_0_getfield .field_26_26   // get_name_1:  .field_26_26   // get_name_2:  .field_26_26   // get_Name:    .field_26_26   // getName->1:  null   // getName->2:  null   // getName->N:  null   // ofs = -1 ord = 0 addr = 26
	invokespecial com.whatsapp.client.ContactInfoDetails.routine_11920 // pc=2
	invokevirtual java.lang.StringBuffer append( java.lang.StringBuffer, java.lang.String ) // pc=2
	pop 
Label423:
	aload_1 
	getstatic com.whatsapp.client.ContactInfoDetails.field_50728 // ContactInfoDetails
	invokevirtual java.lang.StringBuffer append( java.lang.StringBuffer, java.lang.String ) // pc=2
	pop 
	aload_0_getfield .field_27_27   // get_name_1:  .field_27_27   // get_name_2:  .field_27_27   // get_Name:    .field_27_27   // getName->1:  null   // getName->2:  null   // getName->N:  null   // ofs = -1 ord = 0 addr = 27
	ifnull Label435
	aload_1 
	aload_0 
	aload_0_getfield .field_27_27   // get_name_1:  .field_27_27   // get_name_2:  .field_27_27   // get_Name:    .field_27_27   // getName->1:  null   // getName->2:  null   // getName->N:  null   // ofs = -1 ord = 0 addr = 27
	invokespecial com.whatsapp.client.ContactInfoDetails.routine_11920 // pc=2
	invokevirtual java.lang.StringBuffer append( java.lang.StringBuffer, java.lang.String ) // pc=2
	pop 
Label435:
	aload_1 
	getstatic com.whatsapp.client.ContactInfoDetails.field_50728 // ContactInfoDetails
	invokevirtual java.lang.StringBuffer append( java.lang.StringBuffer, java.lang.String ) // pc=2
	pop 
	aload_0_getfield .field_28_28   // get_name_1:  .field_28_28   // get_name_2:  .field_28_28   // get_Name:    .field_28_28   // getName->1:  null   // getName->2:  null   // getName->N:  null   // ofs = -1 ord = 0 addr = 28
	ifnull Label447
	aload_1 
	aload_0 
	aload_0_getfield .field_28_28   // get_name_1:  .field_28_28   // get_name_2:  .field_28_28   // get_Name:    .field_28_28   // getName->1:  null   // getName->2:  null   // getName->N:  null   // ofs = -1 ord = 0 addr = 28
	invokespecial com.whatsapp.client.ContactInfoDetails.routine_11920 // pc=2
	invokevirtual java.lang.StringBuffer append( java.lang.StringBuffer, java.lang.String ) // pc=2
	pop 
Label447:
	aload_1 
	getstatic com.whatsapp.client.ContactInfoDetails.field_50728 // ContactInfoDetails
	invokevirtual java.lang.StringBuffer append( java.lang.StringBuffer, java.lang.String ) // pc=2
	pop 
	aload_0_getfield .field_29_29   // get_name_1:  .field_29_29   // get_name_2:  .field_29_29   // get_Name:    .field_29_29   // getName->1:  null   // getName->2:  null   // getName->N:  null   // ofs = -1 ord = 0 addr = 29
	ifnull Label459
	aload_1 
	aload_0 
	aload_0_getfield .field_29_29   // get_name_1:  .field_29_29   // get_name_2:  .field_29_29   // get_Name:    .field_29_29   // getName->1:  null   // getName->2:  null   // getName->N:  null   // ofs = -1 ord = 0 addr = 29
	invokespecial com.whatsapp.client.ContactInfoDetails.routine_11920 // pc=2
	invokevirtual java.lang.StringBuffer append( java.lang.StringBuffer, java.lang.String ) // pc=2
	pop 
Label459:
	aload_1 
	getstatic_lib module:WhatsApp-19.class#0.static_4 // class#0
	invokevirtual java.lang.StringBuffer append( java.lang.StringBuffer, java.lang.String ) // pc=2
	pop 
Label463:
	aconst_null 
	astore_2 
	invokestatic_lib module:WhatsApp-18.class#0.routine_2419(  ) // class#0
	astore_3 
	aload_3 
	aload_0_getfield .field_0_   // get_name_1:  .field_0_   // get_name_2:  .field_0_   // get_Name:    .field_0_   // getName->1:  null   // getName->2:  null   // getName->N:  null   // ofs = -1 ord = 0 addr = 0
	getstatic_lib module:WhatsApp-20.class#0.static_2 // class#0
	getstatic_lib module:WhatsApp-20.class#0.static_2 // class#0
	invokenonvirtual_lib .routine_282 // pc=4
	astore_4 
	aload_4 
	ifnull Label490
	aload_4 
	invokestatic_lib net.rim.device.api.system.PNGEncodedImage encode( net.rim.device.api.system.Bitmap ) // PNGEncodedImage
	astore_5 
	aload_5 
	invokevirtual byte[] getData( net.rim.device.api.system.EncodedImage ) // pc=1
	aload_5 
	invokevirtual int getOffset( net.rim.device.api.system.EncodedImage ) // pc=1
	aload_5 
	invokevirtual int getLength( net.rim.device.api.system.EncodedImage ) // pc=1
	iconst_0 
	iconst_0 
	invokestatic_lib java.lang.String encodeAsString( byte[], int, int, boolean, boolean ) // Base64OutputStream
	astore_2 
	goto Label490
	astore_6 
Label490:
	aload_2 
	ifnull Label504
	aload_1 
	ldc literal_150:"PHOTO;BASE64:"
	invokevirtual java.lang.StringBuffer append( java.lang.StringBuffer, java.lang.String ) // pc=2
	pop 
	aload_1 
	aload_2 
	invokevirtual java.lang.StringBuffer append( java.lang.StringBuffer, java.lang.String ) // pc=2
	pop 
	aload_1 
	getstatic_lib module:WhatsApp-19.class#0.static_4 // class#0
	invokevirtual java.lang.StringBuffer append( java.lang.StringBuffer, java.lang.String ) // pc=2
	pop 
Label504:
	aload_1 
	getstatic com.whatsapp.client.ContactInfoDetails.field_50770 // ContactInfoDetails
	invokevirtual java.lang.StringBuffer append( java.lang.StringBuffer, java.lang.String ) // pc=2
	pop 
	aload_1 
	invokevirtual_short .toString // idx=2 pc=1
	areturn 
	}

}
