package com.whatsapp;

import android.content.Context;
import android.content.SharedPreferences;
import android.content.SharedPreferences.Editor;
import android.os.Handler;
import android.os.Message;
import android.os.Process;
import hb;
import java.io.File;
import java.util.ArrayList;
import java.util.Arrays;
import java.util.Collection;
import java.util.Collections;
import java.util.Date;
import java.util.HashMap;
import java.util.Hashtable;
import java.util.Iterator;
import java.util.Set;
import java.util.Vector;

public class eu
  implements vz
{
  public static int a;
  public static int b;
  public static int c;
  public static boolean d;
  public static HashMap<String, gu> e;
  public static boolean f;
  private static Vector g;
  public static boolean h;
  public static boolean i;
  public static boolean j;
  public static boolean k;
  public static boolean l;
  public static HashMap<String, String> m;
  private static final j n;
  public static Handler o;
  public static HashMap<String, ju> p;
  private static SharedPreferences q;
  public static final int[] r;
  private static final String[] z;

  // ERROR //
  static
  {
    // Byte code:
    //   0: bipush 64
    //   2: anewarray 41	java/lang/String
    //   5: astore_0
    //   6: ldc 43
    //   8: invokevirtual 47	java/lang/String:toCharArray	()[C
    //   11: astore_1
    //   12: aload_1
    //   13: arraylength
    //   14: istore_2
    //   15: iconst_0
    //   16: istore_3
    //   17: iload_2
    //   18: iload_3
    //   19: if_icmpgt +2936 -> 2955
    //   22: aload_0
    //   23: iconst_0
    //   24: new 41	java/lang/String
    //   27: dup
    //   28: aload_1
    //   29: invokespecial 51	java/lang/String:<init>	([C)V
    //   32: invokevirtual 55	java/lang/String:intern	()Ljava/lang/String;
    //   35: aastore
    //   36: ldc 57
    //   38: invokevirtual 47	java/lang/String:toCharArray	()[C
    //   41: astore 6
    //   43: aload 6
    //   45: arraylength
    //   46: istore 7
    //   48: iconst_0
    //   49: istore 8
    //   51: iload 7
    //   53: iload 8
    //   55: if_icmpgt +2984 -> 3039
    //   58: aload_0
    //   59: iconst_1
    //   60: new 41	java/lang/String
    //   63: dup
    //   64: aload 6
    //   66: invokespecial 51	java/lang/String:<init>	([C)V
    //   69: invokevirtual 55	java/lang/String:intern	()Ljava/lang/String;
    //   72: aastore
    //   73: ldc 59
    //   75: invokevirtual 47	java/lang/String:toCharArray	()[C
    //   78: astore 11
    //   80: aload 11
    //   82: arraylength
    //   83: istore 12
    //   85: iconst_0
    //   86: istore 13
    //   88: iload 12
    //   90: iload 13
    //   92: if_icmpgt +3037 -> 3129
    //   95: aload_0
    //   96: iconst_2
    //   97: new 41	java/lang/String
    //   100: dup
    //   101: aload 11
    //   103: invokespecial 51	java/lang/String:<init>	([C)V
    //   106: invokevirtual 55	java/lang/String:intern	()Ljava/lang/String;
    //   109: aastore
    //   110: ldc 61
    //   112: invokevirtual 47	java/lang/String:toCharArray	()[C
    //   115: astore 16
    //   117: aload 16
    //   119: arraylength
    //   120: istore 17
    //   122: iconst_0
    //   123: istore 18
    //   125: iload 17
    //   127: iload 18
    //   129: if_icmpgt +3092 -> 3221
    //   132: aload_0
    //   133: iconst_3
    //   134: new 41	java/lang/String
    //   137: dup
    //   138: aload 16
    //   140: invokespecial 51	java/lang/String:<init>	([C)V
    //   143: invokevirtual 55	java/lang/String:intern	()Ljava/lang/String;
    //   146: aastore
    //   147: ldc 63
    //   149: invokevirtual 47	java/lang/String:toCharArray	()[C
    //   152: astore 21
    //   154: aload 21
    //   156: arraylength
    //   157: istore 22
    //   159: iconst_0
    //   160: istore 23
    //   162: iload 22
    //   164: iload 23
    //   166: if_icmpgt +3147 -> 3313
    //   169: aload_0
    //   170: iconst_4
    //   171: new 41	java/lang/String
    //   174: dup
    //   175: aload 21
    //   177: invokespecial 51	java/lang/String:<init>	([C)V
    //   180: invokevirtual 55	java/lang/String:intern	()Ljava/lang/String;
    //   183: aastore
    //   184: ldc 65
    //   186: invokevirtual 47	java/lang/String:toCharArray	()[C
    //   189: astore 26
    //   191: aload 26
    //   193: arraylength
    //   194: istore 27
    //   196: iconst_0
    //   197: istore 28
    //   199: iload 27
    //   201: iload 28
    //   203: if_icmpgt +3202 -> 3405
    //   206: aload_0
    //   207: iconst_5
    //   208: new 41	java/lang/String
    //   211: dup
    //   212: aload 26
    //   214: invokespecial 51	java/lang/String:<init>	([C)V
    //   217: invokevirtual 55	java/lang/String:intern	()Ljava/lang/String;
    //   220: aastore
    //   221: ldc 67
    //   223: invokevirtual 47	java/lang/String:toCharArray	()[C
    //   226: astore 31
    //   228: aload 31
    //   230: arraylength
    //   231: istore 32
    //   233: iconst_0
    //   234: istore 33
    //   236: iload 32
    //   238: iload 33
    //   240: if_icmpgt +3257 -> 3497
    //   243: aload_0
    //   244: bipush 6
    //   246: new 41	java/lang/String
    //   249: dup
    //   250: aload 31
    //   252: invokespecial 51	java/lang/String:<init>	([C)V
    //   255: invokevirtual 55	java/lang/String:intern	()Ljava/lang/String;
    //   258: aastore
    //   259: ldc 69
    //   261: invokevirtual 47	java/lang/String:toCharArray	()[C
    //   264: astore 36
    //   266: aload 36
    //   268: arraylength
    //   269: istore 37
    //   271: iconst_0
    //   272: istore 38
    //   274: iload 37
    //   276: iload 38
    //   278: if_icmpgt +3311 -> 3589
    //   281: aload_0
    //   282: bipush 7
    //   284: new 41	java/lang/String
    //   287: dup
    //   288: aload 36
    //   290: invokespecial 51	java/lang/String:<init>	([C)V
    //   293: invokevirtual 55	java/lang/String:intern	()Ljava/lang/String;
    //   296: aastore
    //   297: ldc 71
    //   299: invokevirtual 47	java/lang/String:toCharArray	()[C
    //   302: astore 41
    //   304: aload 41
    //   306: arraylength
    //   307: istore 42
    //   309: iconst_0
    //   310: istore 43
    //   312: iload 42
    //   314: iload 43
    //   316: if_icmpgt +3365 -> 3681
    //   319: aload_0
    //   320: bipush 8
    //   322: new 41	java/lang/String
    //   325: dup
    //   326: aload 41
    //   328: invokespecial 51	java/lang/String:<init>	([C)V
    //   331: invokevirtual 55	java/lang/String:intern	()Ljava/lang/String;
    //   334: aastore
    //   335: ldc 73
    //   337: invokevirtual 47	java/lang/String:toCharArray	()[C
    //   340: astore 46
    //   342: aload 46
    //   344: arraylength
    //   345: istore 47
    //   347: iconst_0
    //   348: istore 48
    //   350: iload 47
    //   352: iload 48
    //   354: if_icmpgt +3419 -> 3773
    //   357: aload_0
    //   358: bipush 9
    //   360: new 41	java/lang/String
    //   363: dup
    //   364: aload 46
    //   366: invokespecial 51	java/lang/String:<init>	([C)V
    //   369: invokevirtual 55	java/lang/String:intern	()Ljava/lang/String;
    //   372: aastore
    //   373: ldc 75
    //   375: invokevirtual 47	java/lang/String:toCharArray	()[C
    //   378: astore 51
    //   380: aload 51
    //   382: arraylength
    //   383: istore 52
    //   385: iconst_0
    //   386: istore 53
    //   388: iload 52
    //   390: iload 53
    //   392: if_icmpgt +3473 -> 3865
    //   395: aload_0
    //   396: bipush 10
    //   398: new 41	java/lang/String
    //   401: dup
    //   402: aload 51
    //   404: invokespecial 51	java/lang/String:<init>	([C)V
    //   407: invokevirtual 55	java/lang/String:intern	()Ljava/lang/String;
    //   410: aastore
    //   411: ldc 77
    //   413: invokevirtual 47	java/lang/String:toCharArray	()[C
    //   416: astore 56
    //   418: aload 56
    //   420: arraylength
    //   421: istore 57
    //   423: iconst_0
    //   424: istore 58
    //   426: iload 57
    //   428: iload 58
    //   430: if_icmpgt +3527 -> 3957
    //   433: aload_0
    //   434: bipush 11
    //   436: new 41	java/lang/String
    //   439: dup
    //   440: aload 56
    //   442: invokespecial 51	java/lang/String:<init>	([C)V
    //   445: invokevirtual 55	java/lang/String:intern	()Ljava/lang/String;
    //   448: aastore
    //   449: ldc 79
    //   451: invokevirtual 47	java/lang/String:toCharArray	()[C
    //   454: astore 61
    //   456: aload 61
    //   458: arraylength
    //   459: istore 62
    //   461: iconst_0
    //   462: istore 63
    //   464: iload 62
    //   466: iload 63
    //   468: if_icmpgt +3581 -> 4049
    //   471: aload_0
    //   472: bipush 12
    //   474: new 41	java/lang/String
    //   477: dup
    //   478: aload 61
    //   480: invokespecial 51	java/lang/String:<init>	([C)V
    //   483: invokevirtual 55	java/lang/String:intern	()Ljava/lang/String;
    //   486: aastore
    //   487: ldc 81
    //   489: invokevirtual 47	java/lang/String:toCharArray	()[C
    //   492: astore 66
    //   494: aload 66
    //   496: arraylength
    //   497: istore 67
    //   499: iconst_0
    //   500: istore 68
    //   502: iload 67
    //   504: iload 68
    //   506: if_icmpgt +3635 -> 4141
    //   509: aload_0
    //   510: bipush 13
    //   512: new 41	java/lang/String
    //   515: dup
    //   516: aload 66
    //   518: invokespecial 51	java/lang/String:<init>	([C)V
    //   521: invokevirtual 55	java/lang/String:intern	()Ljava/lang/String;
    //   524: aastore
    //   525: ldc 83
    //   527: invokevirtual 47	java/lang/String:toCharArray	()[C
    //   530: astore 71
    //   532: aload 71
    //   534: arraylength
    //   535: istore 72
    //   537: iconst_0
    //   538: istore 73
    //   540: iload 72
    //   542: iload 73
    //   544: if_icmpgt +3689 -> 4233
    //   547: aload_0
    //   548: bipush 14
    //   550: new 41	java/lang/String
    //   553: dup
    //   554: aload 71
    //   556: invokespecial 51	java/lang/String:<init>	([C)V
    //   559: invokevirtual 55	java/lang/String:intern	()Ljava/lang/String;
    //   562: aastore
    //   563: ldc 85
    //   565: invokevirtual 47	java/lang/String:toCharArray	()[C
    //   568: astore 76
    //   570: aload 76
    //   572: arraylength
    //   573: istore 77
    //   575: iconst_0
    //   576: istore 78
    //   578: iload 77
    //   580: iload 78
    //   582: if_icmpgt +3743 -> 4325
    //   585: aload_0
    //   586: bipush 15
    //   588: new 41	java/lang/String
    //   591: dup
    //   592: aload 76
    //   594: invokespecial 51	java/lang/String:<init>	([C)V
    //   597: invokevirtual 55	java/lang/String:intern	()Ljava/lang/String;
    //   600: aastore
    //   601: ldc 87
    //   603: invokevirtual 47	java/lang/String:toCharArray	()[C
    //   606: astore 81
    //   608: aload 81
    //   610: arraylength
    //   611: istore 82
    //   613: iconst_0
    //   614: istore 83
    //   616: iload 82
    //   618: iload 83
    //   620: if_icmpgt +3797 -> 4417
    //   623: aload_0
    //   624: bipush 16
    //   626: new 41	java/lang/String
    //   629: dup
    //   630: aload 81
    //   632: invokespecial 51	java/lang/String:<init>	([C)V
    //   635: invokevirtual 55	java/lang/String:intern	()Ljava/lang/String;
    //   638: aastore
    //   639: ldc 89
    //   641: invokevirtual 47	java/lang/String:toCharArray	()[C
    //   644: astore 86
    //   646: aload 86
    //   648: arraylength
    //   649: istore 87
    //   651: iconst_0
    //   652: istore 88
    //   654: iload 87
    //   656: iload 88
    //   658: if_icmpgt +3851 -> 4509
    //   661: aload_0
    //   662: bipush 17
    //   664: new 41	java/lang/String
    //   667: dup
    //   668: aload 86
    //   670: invokespecial 51	java/lang/String:<init>	([C)V
    //   673: invokevirtual 55	java/lang/String:intern	()Ljava/lang/String;
    //   676: aastore
    //   677: ldc 91
    //   679: invokevirtual 47	java/lang/String:toCharArray	()[C
    //   682: astore 91
    //   684: aload 91
    //   686: arraylength
    //   687: istore 92
    //   689: iconst_0
    //   690: istore 93
    //   692: iload 92
    //   694: iload 93
    //   696: if_icmpgt +3905 -> 4601
    //   699: aload_0
    //   700: bipush 18
    //   702: new 41	java/lang/String
    //   705: dup
    //   706: aload 91
    //   708: invokespecial 51	java/lang/String:<init>	([C)V
    //   711: invokevirtual 55	java/lang/String:intern	()Ljava/lang/String;
    //   714: aastore
    //   715: ldc 93
    //   717: invokevirtual 47	java/lang/String:toCharArray	()[C
    //   720: astore 96
    //   722: aload 96
    //   724: arraylength
    //   725: istore 97
    //   727: iconst_0
    //   728: istore 98
    //   730: iload 97
    //   732: iload 98
    //   734: if_icmpgt +3959 -> 4693
    //   737: aload_0
    //   738: bipush 19
    //   740: new 41	java/lang/String
    //   743: dup
    //   744: aload 96
    //   746: invokespecial 51	java/lang/String:<init>	([C)V
    //   749: invokevirtual 55	java/lang/String:intern	()Ljava/lang/String;
    //   752: aastore
    //   753: ldc 95
    //   755: invokevirtual 47	java/lang/String:toCharArray	()[C
    //   758: astore 101
    //   760: aload 101
    //   762: arraylength
    //   763: istore 102
    //   765: iconst_0
    //   766: istore 103
    //   768: iload 102
    //   770: iload 103
    //   772: if_icmpgt +4013 -> 4785
    //   775: aload_0
    //   776: bipush 20
    //   778: new 41	java/lang/String
    //   781: dup
    //   782: aload 101
    //   784: invokespecial 51	java/lang/String:<init>	([C)V
    //   787: invokevirtual 55	java/lang/String:intern	()Ljava/lang/String;
    //   790: aastore
    //   791: ldc 97
    //   793: invokevirtual 47	java/lang/String:toCharArray	()[C
    //   796: astore 106
    //   798: aload 106
    //   800: arraylength
    //   801: istore 107
    //   803: iconst_0
    //   804: istore 108
    //   806: iload 107
    //   808: iload 108
    //   810: if_icmpgt +4067 -> 4877
    //   813: aload_0
    //   814: bipush 21
    //   816: new 41	java/lang/String
    //   819: dup
    //   820: aload 106
    //   822: invokespecial 51	java/lang/String:<init>	([C)V
    //   825: invokevirtual 55	java/lang/String:intern	()Ljava/lang/String;
    //   828: aastore
    //   829: ldc 99
    //   831: invokevirtual 47	java/lang/String:toCharArray	()[C
    //   834: astore 111
    //   836: aload 111
    //   838: arraylength
    //   839: istore 112
    //   841: iconst_0
    //   842: istore 113
    //   844: iload 112
    //   846: iload 113
    //   848: if_icmpgt +4121 -> 4969
    //   851: aload_0
    //   852: bipush 22
    //   854: new 41	java/lang/String
    //   857: dup
    //   858: aload 111
    //   860: invokespecial 51	java/lang/String:<init>	([C)V
    //   863: invokevirtual 55	java/lang/String:intern	()Ljava/lang/String;
    //   866: aastore
    //   867: ldc 101
    //   869: invokevirtual 47	java/lang/String:toCharArray	()[C
    //   872: astore 116
    //   874: aload 116
    //   876: arraylength
    //   877: istore 117
    //   879: iconst_0
    //   880: istore 118
    //   882: iload 117
    //   884: iload 118
    //   886: if_icmpgt +4175 -> 5061
    //   889: aload_0
    //   890: bipush 23
    //   892: new 41	java/lang/String
    //   895: dup
    //   896: aload 116
    //   898: invokespecial 51	java/lang/String:<init>	([C)V
    //   901: invokevirtual 55	java/lang/String:intern	()Ljava/lang/String;
    //   904: aastore
    //   905: ldc 103
    //   907: invokevirtual 47	java/lang/String:toCharArray	()[C
    //   910: astore 121
    //   912: aload 121
    //   914: arraylength
    //   915: istore 122
    //   917: iconst_0
    //   918: istore 123
    //   920: iload 122
    //   922: iload 123
    //   924: if_icmpgt +4229 -> 5153
    //   927: aload_0
    //   928: bipush 24
    //   930: new 41	java/lang/String
    //   933: dup
    //   934: aload 121
    //   936: invokespecial 51	java/lang/String:<init>	([C)V
    //   939: invokevirtual 55	java/lang/String:intern	()Ljava/lang/String;
    //   942: aastore
    //   943: ldc 105
    //   945: invokevirtual 47	java/lang/String:toCharArray	()[C
    //   948: astore 126
    //   950: aload 126
    //   952: arraylength
    //   953: istore 127
    //   955: iconst_0
    //   956: istore 128
    //   958: iload 127
    //   960: iload 128
    //   962: if_icmpgt +4283 -> 5245
    //   965: aload_0
    //   966: bipush 25
    //   968: new 41	java/lang/String
    //   971: dup
    //   972: aload 126
    //   974: invokespecial 51	java/lang/String:<init>	([C)V
    //   977: invokevirtual 55	java/lang/String:intern	()Ljava/lang/String;
    //   980: aastore
    //   981: ldc 107
    //   983: invokevirtual 47	java/lang/String:toCharArray	()[C
    //   986: astore 131
    //   988: aload 131
    //   990: arraylength
    //   991: istore 132
    //   993: iconst_0
    //   994: istore 133
    //   996: iload 132
    //   998: iload 133
    //   1000: if_icmpgt +4337 -> 5337
    //   1003: aload_0
    //   1004: bipush 26
    //   1006: new 41	java/lang/String
    //   1009: dup
    //   1010: aload 131
    //   1012: invokespecial 51	java/lang/String:<init>	([C)V
    //   1015: invokevirtual 55	java/lang/String:intern	()Ljava/lang/String;
    //   1018: aastore
    //   1019: ldc 109
    //   1021: invokevirtual 47	java/lang/String:toCharArray	()[C
    //   1024: astore 136
    //   1026: aload 136
    //   1028: arraylength
    //   1029: istore 137
    //   1031: iconst_0
    //   1032: istore 138
    //   1034: iload 137
    //   1036: iload 138
    //   1038: if_icmpgt +4391 -> 5429
    //   1041: aload_0
    //   1042: bipush 27
    //   1044: new 41	java/lang/String
    //   1047: dup
    //   1048: aload 136
    //   1050: invokespecial 51	java/lang/String:<init>	([C)V
    //   1053: invokevirtual 55	java/lang/String:intern	()Ljava/lang/String;
    //   1056: aastore
    //   1057: ldc 111
    //   1059: invokevirtual 47	java/lang/String:toCharArray	()[C
    //   1062: astore 141
    //   1064: aload 141
    //   1066: arraylength
    //   1067: istore 142
    //   1069: iconst_0
    //   1070: istore 143
    //   1072: iload 142
    //   1074: iload 143
    //   1076: if_icmpgt +4445 -> 5521
    //   1079: aload_0
    //   1080: bipush 28
    //   1082: new 41	java/lang/String
    //   1085: dup
    //   1086: aload 141
    //   1088: invokespecial 51	java/lang/String:<init>	([C)V
    //   1091: invokevirtual 55	java/lang/String:intern	()Ljava/lang/String;
    //   1094: aastore
    //   1095: ldc 113
    //   1097: invokevirtual 47	java/lang/String:toCharArray	()[C
    //   1100: astore 146
    //   1102: aload 146
    //   1104: arraylength
    //   1105: istore 147
    //   1107: iconst_0
    //   1108: istore 148
    //   1110: iload 147
    //   1112: iload 148
    //   1114: if_icmpgt +4499 -> 5613
    //   1117: aload_0
    //   1118: bipush 29
    //   1120: new 41	java/lang/String
    //   1123: dup
    //   1124: aload 146
    //   1126: invokespecial 51	java/lang/String:<init>	([C)V
    //   1129: invokevirtual 55	java/lang/String:intern	()Ljava/lang/String;
    //   1132: aastore
    //   1133: ldc 115
    //   1135: invokevirtual 47	java/lang/String:toCharArray	()[C
    //   1138: astore 151
    //   1140: aload 151
    //   1142: arraylength
    //   1143: istore 152
    //   1145: iconst_0
    //   1146: istore 153
    //   1148: iload 152
    //   1150: iload 153
    //   1152: if_icmpgt +4553 -> 5705
    //   1155: aload_0
    //   1156: bipush 30
    //   1158: new 41	java/lang/String
    //   1161: dup
    //   1162: aload 151
    //   1164: invokespecial 51	java/lang/String:<init>	([C)V
    //   1167: invokevirtual 55	java/lang/String:intern	()Ljava/lang/String;
    //   1170: aastore
    //   1171: ldc 117
    //   1173: invokevirtual 47	java/lang/String:toCharArray	()[C
    //   1176: astore 156
    //   1178: aload 156
    //   1180: arraylength
    //   1181: istore 157
    //   1183: iconst_0
    //   1184: istore 158
    //   1186: iload 157
    //   1188: iload 158
    //   1190: if_icmpgt +4607 -> 5797
    //   1193: aload_0
    //   1194: bipush 31
    //   1196: new 41	java/lang/String
    //   1199: dup
    //   1200: aload 156
    //   1202: invokespecial 51	java/lang/String:<init>	([C)V
    //   1205: invokevirtual 55	java/lang/String:intern	()Ljava/lang/String;
    //   1208: aastore
    //   1209: ldc 119
    //   1211: invokevirtual 47	java/lang/String:toCharArray	()[C
    //   1214: astore 161
    //   1216: aload 161
    //   1218: arraylength
    //   1219: istore 162
    //   1221: iconst_0
    //   1222: istore 163
    //   1224: iload 162
    //   1226: iload 163
    //   1228: if_icmpgt +4661 -> 5889
    //   1231: aload_0
    //   1232: bipush 32
    //   1234: new 41	java/lang/String
    //   1237: dup
    //   1238: aload 161
    //   1240: invokespecial 51	java/lang/String:<init>	([C)V
    //   1243: invokevirtual 55	java/lang/String:intern	()Ljava/lang/String;
    //   1246: aastore
    //   1247: ldc 121
    //   1249: invokevirtual 47	java/lang/String:toCharArray	()[C
    //   1252: astore 166
    //   1254: aload 166
    //   1256: arraylength
    //   1257: istore 167
    //   1259: iconst_0
    //   1260: istore 168
    //   1262: iload 167
    //   1264: iload 168
    //   1266: if_icmpgt +4715 -> 5981
    //   1269: aload_0
    //   1270: bipush 33
    //   1272: new 41	java/lang/String
    //   1275: dup
    //   1276: aload 166
    //   1278: invokespecial 51	java/lang/String:<init>	([C)V
    //   1281: invokevirtual 55	java/lang/String:intern	()Ljava/lang/String;
    //   1284: aastore
    //   1285: ldc 123
    //   1287: invokevirtual 47	java/lang/String:toCharArray	()[C
    //   1290: astore 171
    //   1292: aload 171
    //   1294: arraylength
    //   1295: istore 172
    //   1297: iconst_0
    //   1298: istore 173
    //   1300: iload 172
    //   1302: iload 173
    //   1304: if_icmpgt +4769 -> 6073
    //   1307: aload_0
    //   1308: bipush 34
    //   1310: new 41	java/lang/String
    //   1313: dup
    //   1314: aload 171
    //   1316: invokespecial 51	java/lang/String:<init>	([C)V
    //   1319: invokevirtual 55	java/lang/String:intern	()Ljava/lang/String;
    //   1322: aastore
    //   1323: ldc 125
    //   1325: invokevirtual 47	java/lang/String:toCharArray	()[C
    //   1328: astore 176
    //   1330: aload 176
    //   1332: arraylength
    //   1333: istore 177
    //   1335: iconst_0
    //   1336: istore 178
    //   1338: iload 177
    //   1340: iload 178
    //   1342: if_icmpgt +4823 -> 6165
    //   1345: aload_0
    //   1346: bipush 35
    //   1348: new 41	java/lang/String
    //   1351: dup
    //   1352: aload 176
    //   1354: invokespecial 51	java/lang/String:<init>	([C)V
    //   1357: invokevirtual 55	java/lang/String:intern	()Ljava/lang/String;
    //   1360: aastore
    //   1361: ldc 127
    //   1363: invokevirtual 47	java/lang/String:toCharArray	()[C
    //   1366: astore 181
    //   1368: aload 181
    //   1370: arraylength
    //   1371: istore 182
    //   1373: iconst_0
    //   1374: istore 183
    //   1376: iload 182
    //   1378: iload 183
    //   1380: if_icmpgt +4877 -> 6257
    //   1383: aload_0
    //   1384: bipush 36
    //   1386: new 41	java/lang/String
    //   1389: dup
    //   1390: aload 181
    //   1392: invokespecial 51	java/lang/String:<init>	([C)V
    //   1395: invokevirtual 55	java/lang/String:intern	()Ljava/lang/String;
    //   1398: aastore
    //   1399: ldc 129
    //   1401: invokevirtual 47	java/lang/String:toCharArray	()[C
    //   1404: astore 186
    //   1406: aload 186
    //   1408: arraylength
    //   1409: istore 187
    //   1411: iconst_0
    //   1412: istore 188
    //   1414: iload 187
    //   1416: iload 188
    //   1418: if_icmpgt +4931 -> 6349
    //   1421: aload_0
    //   1422: bipush 37
    //   1424: new 41	java/lang/String
    //   1427: dup
    //   1428: aload 186
    //   1430: invokespecial 51	java/lang/String:<init>	([C)V
    //   1433: invokevirtual 55	java/lang/String:intern	()Ljava/lang/String;
    //   1436: aastore
    //   1437: ldc 131
    //   1439: invokevirtual 47	java/lang/String:toCharArray	()[C
    //   1442: astore 191
    //   1444: aload 191
    //   1446: arraylength
    //   1447: istore 192
    //   1449: iconst_0
    //   1450: istore 193
    //   1452: iload 192
    //   1454: iload 193
    //   1456: if_icmpgt +4985 -> 6441
    //   1459: aload_0
    //   1460: bipush 38
    //   1462: new 41	java/lang/String
    //   1465: dup
    //   1466: aload 191
    //   1468: invokespecial 51	java/lang/String:<init>	([C)V
    //   1471: invokevirtual 55	java/lang/String:intern	()Ljava/lang/String;
    //   1474: aastore
    //   1475: ldc 133
    //   1477: invokevirtual 47	java/lang/String:toCharArray	()[C
    //   1480: astore 196
    //   1482: aload 196
    //   1484: arraylength
    //   1485: istore 197
    //   1487: iconst_0
    //   1488: istore 198
    //   1490: iload 197
    //   1492: iload 198
    //   1494: if_icmpgt +5039 -> 6533
    //   1497: aload_0
    //   1498: bipush 39
    //   1500: new 41	java/lang/String
    //   1503: dup
    //   1504: aload 196
    //   1506: invokespecial 51	java/lang/String:<init>	([C)V
    //   1509: invokevirtual 55	java/lang/String:intern	()Ljava/lang/String;
    //   1512: aastore
    //   1513: ldc 135
    //   1515: invokevirtual 47	java/lang/String:toCharArray	()[C
    //   1518: astore 201
    //   1520: aload 201
    //   1522: arraylength
    //   1523: istore 202
    //   1525: iconst_0
    //   1526: istore 203
    //   1528: iload 202
    //   1530: iload 203
    //   1532: if_icmpgt +5093 -> 6625
    //   1535: aload_0
    //   1536: bipush 40
    //   1538: new 41	java/lang/String
    //   1541: dup
    //   1542: aload 201
    //   1544: invokespecial 51	java/lang/String:<init>	([C)V
    //   1547: invokevirtual 55	java/lang/String:intern	()Ljava/lang/String;
    //   1550: aastore
    //   1551: ldc 137
    //   1553: invokevirtual 47	java/lang/String:toCharArray	()[C
    //   1556: astore 206
    //   1558: aload 206
    //   1560: arraylength
    //   1561: istore 207
    //   1563: iconst_0
    //   1564: istore 208
    //   1566: iload 207
    //   1568: iload 208
    //   1570: if_icmpgt +5147 -> 6717
    //   1573: aload_0
    //   1574: bipush 41
    //   1576: new 41	java/lang/String
    //   1579: dup
    //   1580: aload 206
    //   1582: invokespecial 51	java/lang/String:<init>	([C)V
    //   1585: invokevirtual 55	java/lang/String:intern	()Ljava/lang/String;
    //   1588: aastore
    //   1589: ldc 139
    //   1591: invokevirtual 47	java/lang/String:toCharArray	()[C
    //   1594: astore 211
    //   1596: aload 211
    //   1598: arraylength
    //   1599: istore 212
    //   1601: iconst_0
    //   1602: istore 213
    //   1604: iload 212
    //   1606: iload 213
    //   1608: if_icmpgt +5201 -> 6809
    //   1611: aload_0
    //   1612: bipush 42
    //   1614: new 41	java/lang/String
    //   1617: dup
    //   1618: aload 211
    //   1620: invokespecial 51	java/lang/String:<init>	([C)V
    //   1623: invokevirtual 55	java/lang/String:intern	()Ljava/lang/String;
    //   1626: aastore
    //   1627: ldc 141
    //   1629: invokevirtual 47	java/lang/String:toCharArray	()[C
    //   1632: astore 216
    //   1634: aload 216
    //   1636: arraylength
    //   1637: istore 217
    //   1639: iconst_0
    //   1640: istore 218
    //   1642: iload 217
    //   1644: iload 218
    //   1646: if_icmpgt +5255 -> 6901
    //   1649: aload_0
    //   1650: bipush 43
    //   1652: new 41	java/lang/String
    //   1655: dup
    //   1656: aload 216
    //   1658: invokespecial 51	java/lang/String:<init>	([C)V
    //   1661: invokevirtual 55	java/lang/String:intern	()Ljava/lang/String;
    //   1664: aastore
    //   1665: ldc 143
    //   1667: invokevirtual 47	java/lang/String:toCharArray	()[C
    //   1670: astore 221
    //   1672: aload 221
    //   1674: arraylength
    //   1675: istore 222
    //   1677: iconst_0
    //   1678: istore 223
    //   1680: iload 222
    //   1682: iload 223
    //   1684: if_icmpgt +5309 -> 6993
    //   1687: aload_0
    //   1688: bipush 44
    //   1690: new 41	java/lang/String
    //   1693: dup
    //   1694: aload 221
    //   1696: invokespecial 51	java/lang/String:<init>	([C)V
    //   1699: invokevirtual 55	java/lang/String:intern	()Ljava/lang/String;
    //   1702: aastore
    //   1703: ldc 145
    //   1705: invokevirtual 47	java/lang/String:toCharArray	()[C
    //   1708: astore 226
    //   1710: aload 226
    //   1712: arraylength
    //   1713: istore 227
    //   1715: iconst_0
    //   1716: istore 228
    //   1718: iload 227
    //   1720: iload 228
    //   1722: if_icmpgt +5363 -> 7085
    //   1725: aload_0
    //   1726: bipush 45
    //   1728: new 41	java/lang/String
    //   1731: dup
    //   1732: aload 226
    //   1734: invokespecial 51	java/lang/String:<init>	([C)V
    //   1737: invokevirtual 55	java/lang/String:intern	()Ljava/lang/String;
    //   1740: aastore
    //   1741: ldc 147
    //   1743: invokevirtual 47	java/lang/String:toCharArray	()[C
    //   1746: astore 231
    //   1748: aload 231
    //   1750: arraylength
    //   1751: istore 232
    //   1753: iconst_0
    //   1754: istore 233
    //   1756: iload 232
    //   1758: iload 233
    //   1760: if_icmpgt +5417 -> 7177
    //   1763: aload_0
    //   1764: bipush 46
    //   1766: new 41	java/lang/String
    //   1769: dup
    //   1770: aload 231
    //   1772: invokespecial 51	java/lang/String:<init>	([C)V
    //   1775: invokevirtual 55	java/lang/String:intern	()Ljava/lang/String;
    //   1778: aastore
    //   1779: ldc 149
    //   1781: invokevirtual 47	java/lang/String:toCharArray	()[C
    //   1784: astore 236
    //   1786: aload 236
    //   1788: arraylength
    //   1789: istore 237
    //   1791: iconst_0
    //   1792: istore 238
    //   1794: iload 237
    //   1796: iload 238
    //   1798: if_icmpgt +5471 -> 7269
    //   1801: aload_0
    //   1802: bipush 47
    //   1804: new 41	java/lang/String
    //   1807: dup
    //   1808: aload 236
    //   1810: invokespecial 51	java/lang/String:<init>	([C)V
    //   1813: invokevirtual 55	java/lang/String:intern	()Ljava/lang/String;
    //   1816: aastore
    //   1817: ldc 151
    //   1819: invokevirtual 47	java/lang/String:toCharArray	()[C
    //   1822: astore 241
    //   1824: aload 241
    //   1826: arraylength
    //   1827: istore 242
    //   1829: iconst_0
    //   1830: istore 243
    //   1832: iload 242
    //   1834: iload 243
    //   1836: if_icmpgt +5525 -> 7361
    //   1839: aload_0
    //   1840: bipush 48
    //   1842: new 41	java/lang/String
    //   1845: dup
    //   1846: aload 241
    //   1848: invokespecial 51	java/lang/String:<init>	([C)V
    //   1851: invokevirtual 55	java/lang/String:intern	()Ljava/lang/String;
    //   1854: aastore
    //   1855: ldc 153
    //   1857: invokevirtual 47	java/lang/String:toCharArray	()[C
    //   1860: astore 246
    //   1862: aload 246
    //   1864: arraylength
    //   1865: istore 247
    //   1867: iconst_0
    //   1868: istore 248
    //   1870: iload 247
    //   1872: iload 248
    //   1874: if_icmpgt +5579 -> 7453
    //   1877: aload_0
    //   1878: bipush 49
    //   1880: new 41	java/lang/String
    //   1883: dup
    //   1884: aload 246
    //   1886: invokespecial 51	java/lang/String:<init>	([C)V
    //   1889: invokevirtual 55	java/lang/String:intern	()Ljava/lang/String;
    //   1892: aastore
    //   1893: ldc 155
    //   1895: invokevirtual 47	java/lang/String:toCharArray	()[C
    //   1898: astore 251
    //   1900: aload 251
    //   1902: arraylength
    //   1903: istore 252
    //   1905: iconst_0
    //   1906: istore 253
    //   1908: iload 252
    //   1910: iload 253
    //   1912: if_icmpgt +5633 -> 7545
    //   1915: aload_0
    //   1916: bipush 50
    //   1918: new 41	java/lang/String
    //   1921: dup
    //   1922: aload 251
    //   1924: invokespecial 51	java/lang/String:<init>	([C)V
    //   1927: invokevirtual 55	java/lang/String:intern	()Ljava/lang/String;
    //   1930: aastore
    //   1931: ldc 157
    //   1933: invokevirtual 47	java/lang/String:toCharArray	()[C
    //   1936: wide
    //   1940: wide
    //   1944: arraylength
    //   1945: wide
    //   1949: iconst_0
    //   1950: wide
    //   1954: wide
    //   1958: wide
    //   1962: if_icmpgt +5675 -> 7637
    //   1965: aload_0
    //   1966: bipush 51
    //   1968: new 41	java/lang/String
    //   1971: dup
    //   1972: wide
    //   1976: invokespecial 51	java/lang/String:<init>	([C)V
    //   1979: invokevirtual 55	java/lang/String:intern	()Ljava/lang/String;
    //   1982: aastore
    //   1983: ldc 159
    //   1985: invokevirtual 47	java/lang/String:toCharArray	()[C
    //   1988: wide
    //   1992: wide
    //   1996: arraylength
    //   1997: wide
    //   2001: iconst_0
    //   2002: wide
    //   2006: wide
    //   2010: wide
    //   2014: if_icmpgt +5744 -> 7758
    //   2017: aload_0
    //   2018: bipush 52
    //   2020: new 41	java/lang/String
    //   2023: dup
    //   2024: wide
    //   2028: invokespecial 51	java/lang/String:<init>	([C)V
    //   2031: invokevirtual 55	java/lang/String:intern	()Ljava/lang/String;
    //   2034: aastore
    //   2035: ldc 161
    //   2037: invokevirtual 47	java/lang/String:toCharArray	()[C
    //   2040: wide
    //   2044: wide
    //   2048: arraylength
    //   2049: wide
    //   2053: iconst_0
    //   2054: wide
    //   2058: wide
    //   2062: wide
    //   2066: if_icmpgt +5812 -> 7878
    //   2069: aload_0
    //   2070: bipush 53
    //   2072: new 41	java/lang/String
    //   2075: dup
    //   2076: wide
    //   2080: invokespecial 51	java/lang/String:<init>	([C)V
    //   2083: invokevirtual 55	java/lang/String:intern	()Ljava/lang/String;
    //   2086: aastore
    //   2087: ldc 163
    //   2089: invokevirtual 47	java/lang/String:toCharArray	()[C
    //   2092: wide
    //   2096: wide
    //   2100: arraylength
    //   2101: wide
    //   2105: iconst_0
    //   2106: wide
    //   2110: wide
    //   2114: wide
    //   2118: if_icmpgt +5880 -> 7998
    //   2121: aload_0
    //   2122: bipush 54
    //   2124: new 41	java/lang/String
    //   2127: dup
    //   2128: wide
    //   2132: invokespecial 51	java/lang/String:<init>	([C)V
    //   2135: invokevirtual 55	java/lang/String:intern	()Ljava/lang/String;
    //   2138: aastore
    //   2139: ldc 165
    //   2141: invokevirtual 47	java/lang/String:toCharArray	()[C
    //   2144: wide
    //   2148: wide
    //   2152: arraylength
    //   2153: wide
    //   2157: iconst_0
    //   2158: wide
    //   2162: wide
    //   2166: wide
    //   2170: if_icmpgt +5948 -> 8118
    //   2173: aload_0
    //   2174: bipush 55
    //   2176: new 41	java/lang/String
    //   2179: dup
    //   2180: wide
    //   2184: invokespecial 51	java/lang/String:<init>	([C)V
    //   2187: invokevirtual 55	java/lang/String:intern	()Ljava/lang/String;
    //   2190: aastore
    //   2191: ldc 167
    //   2193: invokevirtual 47	java/lang/String:toCharArray	()[C
    //   2196: wide
    //   2200: wide
    //   2204: arraylength
    //   2205: wide
    //   2209: iconst_0
    //   2210: wide
    //   2214: wide
    //   2218: wide
    //   2222: if_icmpgt +6016 -> 8238
    //   2225: aload_0
    //   2226: bipush 56
    //   2228: new 41	java/lang/String
    //   2231: dup
    //   2232: wide
    //   2236: invokespecial 51	java/lang/String:<init>	([C)V
    //   2239: invokevirtual 55	java/lang/String:intern	()Ljava/lang/String;
    //   2242: aastore
    //   2243: ldc 169
    //   2245: invokevirtual 47	java/lang/String:toCharArray	()[C
    //   2248: wide
    //   2252: wide
    //   2256: arraylength
    //   2257: wide
    //   2261: iconst_0
    //   2262: wide
    //   2266: wide
    //   2270: wide
    //   2274: if_icmpgt +6084 -> 8358
    //   2277: aload_0
    //   2278: bipush 57
    //   2280: new 41	java/lang/String
    //   2283: dup
    //   2284: wide
    //   2288: invokespecial 51	java/lang/String:<init>	([C)V
    //   2291: invokevirtual 55	java/lang/String:intern	()Ljava/lang/String;
    //   2294: aastore
    //   2295: ldc 171
    //   2297: invokevirtual 47	java/lang/String:toCharArray	()[C
    //   2300: wide
    //   2304: wide
    //   2308: arraylength
    //   2309: wide
    //   2313: iconst_0
    //   2314: wide
    //   2318: wide
    //   2322: wide
    //   2326: if_icmpgt +6152 -> 8478
    //   2329: aload_0
    //   2330: bipush 58
    //   2332: new 41	java/lang/String
    //   2335: dup
    //   2336: wide
    //   2340: invokespecial 51	java/lang/String:<init>	([C)V
    //   2343: invokevirtual 55	java/lang/String:intern	()Ljava/lang/String;
    //   2346: aastore
    //   2347: ldc 173
    //   2349: invokevirtual 47	java/lang/String:toCharArray	()[C
    //   2352: wide
    //   2356: wide
    //   2360: arraylength
    //   2361: wide
    //   2365: iconst_0
    //   2366: wide
    //   2370: wide
    //   2374: wide
    //   2378: if_icmpgt +6220 -> 8598
    //   2381: aload_0
    //   2382: bipush 59
    //   2384: new 41	java/lang/String
    //   2387: dup
    //   2388: wide
    //   2392: invokespecial 51	java/lang/String:<init>	([C)V
    //   2395: invokevirtual 55	java/lang/String:intern	()Ljava/lang/String;
    //   2398: aastore
    //   2399: ldc 175
    //   2401: invokevirtual 47	java/lang/String:toCharArray	()[C
    //   2404: wide
    //   2408: wide
    //   2412: arraylength
    //   2413: wide
    //   2417: iconst_0
    //   2418: wide
    //   2422: wide
    //   2426: wide
    //   2430: if_icmpgt +6288 -> 8718
    //   2433: aload_0
    //   2434: bipush 60
    //   2436: new 41	java/lang/String
    //   2439: dup
    //   2440: wide
    //   2444: invokespecial 51	java/lang/String:<init>	([C)V
    //   2447: invokevirtual 55	java/lang/String:intern	()Ljava/lang/String;
    //   2450: aastore
    //   2451: ldc 177
    //   2453: invokevirtual 47	java/lang/String:toCharArray	()[C
    //   2456: wide
    //   2460: wide
    //   2464: arraylength
    //   2465: wide
    //   2469: iconst_0
    //   2470: wide
    //   2474: wide
    //   2478: wide
    //   2482: if_icmpgt +6356 -> 8838
    //   2485: aload_0
    //   2486: bipush 61
    //   2488: new 41	java/lang/String
    //   2491: dup
    //   2492: wide
    //   2496: invokespecial 51	java/lang/String:<init>	([C)V
    //   2499: invokevirtual 55	java/lang/String:intern	()Ljava/lang/String;
    //   2502: aastore
    //   2503: ldc 179
    //   2505: invokevirtual 47	java/lang/String:toCharArray	()[C
    //   2508: wide
    //   2512: wide
    //   2516: arraylength
    //   2517: wide
    //   2521: iconst_0
    //   2522: wide
    //   2526: wide
    //   2530: wide
    //   2534: if_icmpgt +6424 -> 8958
    //   2537: aload_0
    //   2538: bipush 62
    //   2540: new 41	java/lang/String
    //   2543: dup
    //   2544: wide
    //   2548: invokespecial 51	java/lang/String:<init>	([C)V
    //   2551: invokevirtual 55	java/lang/String:intern	()Ljava/lang/String;
    //   2554: aastore
    //   2555: ldc 181
    //   2557: invokevirtual 47	java/lang/String:toCharArray	()[C
    //   2560: wide
    //   2564: wide
    //   2568: arraylength
    //   2569: wide
    //   2573: iconst_0
    //   2574: wide
    //   2578: wide
    //   2582: wide
    //   2586: if_icmpgt +6492 -> 9078
    //   2589: aload_0
    //   2590: bipush 63
    //   2592: new 41	java/lang/String
    //   2595: dup
    //   2596: wide
    //   2600: invokespecial 51	java/lang/String:<init>	([C)V
    //   2603: invokevirtual 55	java/lang/String:intern	()Ljava/lang/String;
    //   2606: aastore
    //   2607: aload_0
    //   2608: putstatic 183	com/whatsapp/eu:z	[Ljava/lang/String;
    //   2611: bipush 30
    //   2613: putstatic 185	com/whatsapp/eu:a	I
    //   2616: bipush 30
    //   2618: putstatic 187	com/whatsapp/eu:b	I
    //   2621: bipush 25
    //   2623: putstatic 189	com/whatsapp/eu:c	I
    //   2626: iconst_0
    //   2627: putstatic 191	com/whatsapp/eu:d	Z
    //   2630: new 193	java/util/HashMap
    //   2633: dup
    //   2634: invokespecial 195	java/util/HashMap:<init>	()V
    //   2637: putstatic 197	com/whatsapp/eu:e	Ljava/util/HashMap;
    //   2640: new 199	java/util/Vector
    //   2643: dup
    //   2644: invokespecial 200	java/util/Vector:<init>	()V
    //   2647: putstatic 202	com/whatsapp/eu:g	Ljava/util/Vector;
    //   2650: iconst_0
    //   2651: putstatic 204	com/whatsapp/eu:h	Z
    //   2654: iconst_0
    //   2655: putstatic 206	com/whatsapp/eu:i	Z
    //   2658: iconst_0
    //   2659: putstatic 208	com/whatsapp/eu:j	Z
    //   2662: iconst_0
    //   2663: putstatic 210	com/whatsapp/eu:k	Z
    //   2666: iconst_0
    //   2667: putstatic 212	com/whatsapp/eu:l	Z
    //   2670: new 193	java/util/HashMap
    //   2673: dup
    //   2674: invokespecial 195	java/util/HashMap:<init>	()V
    //   2677: putstatic 214	com/whatsapp/eu:m	Ljava/util/HashMap;
    //   2680: new 216	com/whatsapp/j
    //   2683: dup
    //   2684: invokespecial 217	com/whatsapp/j:<init>	()V
    //   2687: putstatic 219	com/whatsapp/eu:n	Lcom/whatsapp/j;
    //   2690: new 221	com/whatsapp/jd
    //   2693: dup
    //   2694: invokespecial 222	com/whatsapp/jd:<init>	()V
    //   2697: putstatic 224	com/whatsapp/eu:o	Landroid/os/Handler;
    //   2700: new 193	java/util/HashMap
    //   2703: dup
    //   2704: invokespecial 195	java/util/HashMap:<init>	()V
    //   2707: putstatic 226	com/whatsapp/eu:p	Ljava/util/HashMap;
    //   2710: getstatic 232	com/whatsapp/App:Mb	Lcom/whatsapp/App;
    //   2713: getstatic 232	com/whatsapp/App:Mb	Lcom/whatsapp/App;
    //   2716: ldc 233
    //   2718: invokevirtual 237	com/whatsapp/App:getString	(I)Ljava/lang/String;
    //   2721: iconst_0
    //   2722: invokevirtual 241	com/whatsapp/App:getSharedPreferences	(Ljava/lang/String;I)Landroid/content/SharedPreferences;
    //   2725: putstatic 243	com/whatsapp/eu:q	Landroid/content/SharedPreferences;
    //   2728: bipush 13
    //   2730: newarray int
    //   2732: wide
    //   2736: wide
    //   2740: iconst_0
    //   2741: sipush 153
    //   2744: sipush 196
    //   2747: bipush 10
    //   2749: invokestatic 249	android/graphics/Color:rgb	(III)I
    //   2752: iastore
    //   2753: wide
    //   2757: iconst_1
    //   2758: bipush 54
    //   2760: bipush 61
    //   2762: sipush 155
    //   2765: invokestatic 249	android/graphics/Color:rgb	(III)I
    //   2768: iastore
    //   2769: wide
    //   2773: iconst_2
    //   2774: sipush 217
    //   2777: iconst_0
    //   2778: bipush 106
    //   2780: invokestatic 249	android/graphics/Color:rgb	(III)I
    //   2783: iastore
    //   2784: wide
    //   2788: iconst_3
    //   2789: sipush 221
    //   2792: sipush 204
    //   2795: bipush 11
    //   2797: invokestatic 249	android/graphics/Color:rgb	(III)I
    //   2800: iastore
    //   2801: wide
    //   2805: iconst_4
    //   2806: iconst_3
    //   2807: bipush 68
    //   2809: iconst_2
    //   2810: invokestatic 249	android/graphics/Color:rgb	(III)I
    //   2813: iastore
    //   2814: wide
    //   2818: iconst_5
    //   2819: bipush 50
    //   2821: sipush 148
    //   2824: sipush 138
    //   2827: invokestatic 249	android/graphics/Color:rgb	(III)I
    //   2830: iastore
    //   2831: wide
    //   2835: bipush 6
    //   2837: bipush 84
    //   2839: bipush 71
    //   2841: bipush 89
    //   2843: invokestatic 249	android/graphics/Color:rgb	(III)I
    //   2846: iastore
    //   2847: wide
    //   2851: bipush 7
    //   2853: sipush 152
    //   2856: bipush 116
    //   2858: iconst_5
    //   2859: invokestatic 249	android/graphics/Color:rgb	(III)I
    //   2862: iastore
    //   2863: wide
    //   2867: bipush 8
    //   2869: sipush 178
    //   2872: bipush 50
    //   2874: iconst_3
    //   2875: invokestatic 249	android/graphics/Color:rgb	(III)I
    //   2878: iastore
    //   2879: wide
    //   2883: bipush 9
    //   2885: bipush 117
    //   2887: bipush 57
    //   2889: bipush 77
    //   2891: invokestatic 249	android/graphics/Color:rgb	(III)I
    //   2894: iastore
    //   2895: wide
    //   2899: bipush 10
    //   2901: bipush 103
    //   2903: bipush 59
    //   2905: bipush 126
    //   2907: invokestatic 249	android/graphics/Color:rgb	(III)I
    //   2910: iastore
    //   2911: wide
    //   2915: bipush 11
    //   2917: bipush 28
    //   2919: sipush 185
    //   2922: sipush 213
    //   2925: invokestatic 249	android/graphics/Color:rgb	(III)I
    //   2928: iastore
    //   2929: wide
    //   2933: bipush 12
    //   2935: sipush 186
    //   2938: bipush 51
    //   2940: sipush 220
    //   2943: invokestatic 249	android/graphics/Color:rgb	(III)I
    //   2946: iastore
    //   2947: wide
    //   2951: putstatic 251	com/whatsapp/eu:r	[I
    //   2954: return
    //   2955: aload_1
    //   2956: iload_3
    //   2957: caload
    //   2958: istore 4
    //   2960: iload_3
    //   2961: iconst_5
    //   2962: irem
    //   2963: tableswitch	default:+29 -> 2992, 0:+48->3011, 1:+55->3018, 2:+62->3025, 3:+69->3032
    //   2993: castore
    //   2994: istore 5
    //   2996: aload_1
    //   2997: iload_3
    //   2998: iload 5
    //   3000: iload 4
    //   3002: ixor
    //   3003: i2c
    //   3004: castore
    //   3005: iinc 3 1
    //   3008: goto -2991 -> 17
    //   3011: bipush 56
    //   3013: istore 5
    //   3015: goto -19 -> 2996
    //   3018: bipush 120
    //   3020: istore 5
    //   3022: goto -26 -> 2996
    //   3025: bipush 79
    //   3027: istore 5
    //   3029: goto -33 -> 2996
    //   3032: bipush 71
    //   3034: istore 5
    //   3036: goto -40 -> 2996
    //   3039: aload 6
    //   3041: iload 8
    //   3043: caload
    //   3044: istore 9
    //   3046: iload 8
    //   3048: iconst_5
    //   3049: irem
    //   3050: tableswitch	default:+30 -> 3080, 0:+51->3101, 1:+58->3108, 2:+65->3115, 3:+72->3122
    //   3081: castore
    //   3082: istore 10
    //   3084: aload 6
    //   3086: iload 8
    //   3088: iload 10
    //   3090: iload 9
    //   3092: ixor
    //   3093: i2c
    //   3094: castore
    //   3095: iinc 8 1
    //   3098: goto -3047 -> 51
    //   3101: bipush 56
    //   3103: istore 10
    //   3105: goto -21 -> 3084
    //   3108: bipush 120
    //   3110: istore 10
    //   3112: goto -28 -> 3084
    //   3115: bipush 79
    //   3117: istore 10
    //   3119: goto -35 -> 3084
    //   3122: bipush 71
    //   3124: istore 10
    //   3126: goto -42 -> 3084
    //   3129: aload 11
    //   3131: iload 13
    //   3133: caload
    //   3134: istore 14
    //   3136: iload 13
    //   3138: iconst_5
    //   3139: irem
    //   3140: tableswitch	default:+32 -> 3172, 0:+53->3193, 1:+60->3200, 2:+67->3207, 3:+74->3214
    //   3173: castore
    //   3174: istore 15
    //   3176: aload 11
    //   3178: iload 13
    //   3180: iload 15
    //   3182: iload 14
    //   3184: ixor
    //   3185: i2c
    //   3186: castore
    //   3187: iinc 13 1
    //   3190: goto -3102 -> 88
    //   3193: bipush 56
    //   3195: istore 15
    //   3197: goto -21 -> 3176
    //   3200: bipush 120
    //   3202: istore 15
    //   3204: goto -28 -> 3176
    //   3207: bipush 79
    //   3209: istore 15
    //   3211: goto -35 -> 3176
    //   3214: bipush 71
    //   3216: istore 15
    //   3218: goto -42 -> 3176
    //   3221: aload 16
    //   3223: iload 18
    //   3225: caload
    //   3226: istore 19
    //   3228: iload 18
    //   3230: iconst_5
    //   3231: irem
    //   3232: tableswitch	default:+32 -> 3264, 0:+53->3285, 1:+60->3292, 2:+67->3299, 3:+74->3306
    //   3265: castore
    //   3266: istore 20
    //   3268: aload 16
    //   3270: iload 18
    //   3272: iload 20
    //   3274: iload 19
    //   3276: ixor
    //   3277: i2c
    //   3278: castore
    //   3279: iinc 18 1
    //   3282: goto -3157 -> 125
    //   3285: bipush 56
    //   3287: istore 20
    //   3289: goto -21 -> 3268
    //   3292: bipush 120
    //   3294: istore 20
    //   3296: goto -28 -> 3268
    //   3299: bipush 79
    //   3301: istore 20
    //   3303: goto -35 -> 3268
    //   3306: bipush 71
    //   3308: istore 20
    //   3310: goto -42 -> 3268
    //   3313: aload 21
    //   3315: iload 23
    //   3317: caload
    //   3318: istore 24
    //   3320: iload 23
    //   3322: iconst_5
    //   3323: irem
    //   3324: tableswitch	default:+32 -> 3356, 0:+53->3377, 1:+60->3384, 2:+67->3391, 3:+74->3398
    //   3357: castore
    //   3358: istore 25
    //   3360: aload 21
    //   3362: iload 23
    //   3364: iload 25
    //   3366: iload 24
    //   3368: ixor
    //   3369: i2c
    //   3370: castore
    //   3371: iinc 23 1
    //   3374: goto -3212 -> 162
    //   3377: bipush 56
    //   3379: istore 25
    //   3381: goto -21 -> 3360
    //   3384: bipush 120
    //   3386: istore 25
    //   3388: goto -28 -> 3360
    //   3391: bipush 79
    //   3393: istore 25
    //   3395: goto -35 -> 3360
    //   3398: bipush 71
    //   3400: istore 25
    //   3402: goto -42 -> 3360
    //   3405: aload 26
    //   3407: iload 28
    //   3409: caload
    //   3410: istore 29
    //   3412: iload 28
    //   3414: iconst_5
    //   3415: irem
    //   3416: tableswitch	default:+32 -> 3448, 0:+53->3469, 1:+60->3476, 2:+67->3483, 3:+74->3490
    //   3449: castore
    //   3450: istore 30
    //   3452: aload 26
    //   3454: iload 28
    //   3456: iload 30
    //   3458: iload 29
    //   3460: ixor
    //   3461: i2c
    //   3462: castore
    //   3463: iinc 28 1
    //   3466: goto -3267 -> 199
    //   3469: bipush 56
    //   3471: istore 30
    //   3473: goto -21 -> 3452
    //   3476: bipush 120
    //   3478: istore 30
    //   3480: goto -28 -> 3452
    //   3483: bipush 79
    //   3485: istore 30
    //   3487: goto -35 -> 3452
    //   3490: bipush 71
    //   3492: istore 30
    //   3494: goto -42 -> 3452
    //   3497: aload 31
    //   3499: iload 33
    //   3501: caload
    //   3502: istore 34
    //   3504: iload 33
    //   3506: iconst_5
    //   3507: irem
    //   3508: tableswitch	default:+32 -> 3540, 0:+53->3561, 1:+60->3568, 2:+67->3575, 3:+74->3582
    //   3541: castore
    //   3542: istore 35
    //   3544: aload 31
    //   3546: iload 33
    //   3548: iload 35
    //   3550: iload 34
    //   3552: ixor
    //   3553: i2c
    //   3554: castore
    //   3555: iinc 33 1
    //   3558: goto -3322 -> 236
    //   3561: bipush 56
    //   3563: istore 35
    //   3565: goto -21 -> 3544
    //   3568: bipush 120
    //   3570: istore 35
    //   3572: goto -28 -> 3544
    //   3575: bipush 79
    //   3577: istore 35
    //   3579: goto -35 -> 3544
    //   3582: bipush 71
    //   3584: istore 35
    //   3586: goto -42 -> 3544
    //   3589: aload 36
    //   3591: iload 38
    //   3593: caload
    //   3594: istore 39
    //   3596: iload 38
    //   3598: iconst_5
    //   3599: irem
    //   3600: tableswitch	default:+32 -> 3632, 0:+53->3653, 1:+60->3660, 2:+67->3667, 3:+74->3674
    //   3633: castore
    //   3634: istore 40
    //   3636: aload 36
    //   3638: iload 38
    //   3640: iload 40
    //   3642: iload 39
    //   3644: ixor
    //   3645: i2c
    //   3646: castore
    //   3647: iinc 38 1
    //   3650: goto -3376 -> 274
    //   3653: bipush 56
    //   3655: istore 40
    //   3657: goto -21 -> 3636
    //   3660: bipush 120
    //   3662: istore 40
    //   3664: goto -28 -> 3636
    //   3667: bipush 79
    //   3669: istore 40
    //   3671: goto -35 -> 3636
    //   3674: bipush 71
    //   3676: istore 40
    //   3678: goto -42 -> 3636
    //   3681: aload 41
    //   3683: iload 43
    //   3685: caload
    //   3686: istore 44
    //   3688: iload 43
    //   3690: iconst_5
    //   3691: irem
    //   3692: tableswitch	default:+32 -> 3724, 0:+53->3745, 1:+60->3752, 2:+67->3759, 3:+74->3766
    //   3725: castore
    //   3726: istore 45
    //   3728: aload 41
    //   3730: iload 43
    //   3732: iload 45
    //   3734: iload 44
    //   3736: ixor
    //   3737: i2c
    //   3738: castore
    //   3739: iinc 43 1
    //   3742: goto -3430 -> 312
    //   3745: bipush 56
    //   3747: istore 45
    //   3749: goto -21 -> 3728
    //   3752: bipush 120
    //   3754: istore 45
    //   3756: goto -28 -> 3728
    //   3759: bipush 79
    //   3761: istore 45
    //   3763: goto -35 -> 3728
    //   3766: bipush 71
    //   3768: istore 45
    //   3770: goto -42 -> 3728
    //   3773: aload 46
    //   3775: iload 48
    //   3777: caload
    //   3778: istore 49
    //   3780: iload 48
    //   3782: iconst_5
    //   3783: irem
    //   3784: tableswitch	default:+32 -> 3816, 0:+53->3837, 1:+60->3844, 2:+67->3851, 3:+74->3858
    //   3817: castore
    //   3818: istore 50
    //   3820: aload 46
    //   3822: iload 48
    //   3824: iload 50
    //   3826: iload 49
    //   3828: ixor
    //   3829: i2c
    //   3830: castore
    //   3831: iinc 48 1
    //   3834: goto -3484 -> 350
    //   3837: bipush 56
    //   3839: istore 50
    //   3841: goto -21 -> 3820
    //   3844: bipush 120
    //   3846: istore 50
    //   3848: goto -28 -> 3820
    //   3851: bipush 79
    //   3853: istore 50
    //   3855: goto -35 -> 3820
    //   3858: bipush 71
    //   3860: istore 50
    //   3862: goto -42 -> 3820
    //   3865: aload 51
    //   3867: iload 53
    //   3869: caload
    //   3870: istore 54
    //   3872: iload 53
    //   3874: iconst_5
    //   3875: irem
    //   3876: tableswitch	default:+32 -> 3908, 0:+53->3929, 1:+60->3936, 2:+67->3943, 3:+74->3950
    //   3909: castore
    //   3910: istore 55
    //   3912: aload 51
    //   3914: iload 53
    //   3916: iload 55
    //   3918: iload 54
    //   3920: ixor
    //   3921: i2c
    //   3922: castore
    //   3923: iinc 53 1
    //   3926: goto -3538 -> 388
    //   3929: bipush 56
    //   3931: istore 55
    //   3933: goto -21 -> 3912
    //   3936: bipush 120
    //   3938: istore 55
    //   3940: goto -28 -> 3912
    //   3943: bipush 79
    //   3945: istore 55
    //   3947: goto -35 -> 3912
    //   3950: bipush 71
    //   3952: istore 55
    //   3954: goto -42 -> 3912
    //   3957: aload 56
    //   3959: iload 58
    //   3961: caload
    //   3962: istore 59
    //   3964: iload 58
    //   3966: iconst_5
    //   3967: irem
    //   3968: tableswitch	default:+32 -> 4000, 0:+53->4021, 1:+60->4028, 2:+67->4035, 3:+74->4042
    //   4001: castore
    //   4002: istore 60
    //   4004: aload 56
    //   4006: iload 58
    //   4008: iload 60
    //   4010: iload 59
    //   4012: ixor
    //   4013: i2c
    //   4014: castore
    //   4015: iinc 58 1
    //   4018: goto -3592 -> 426
    //   4021: bipush 56
    //   4023: istore 60
    //   4025: goto -21 -> 4004
    //   4028: bipush 120
    //   4030: istore 60
    //   4032: goto -28 -> 4004
    //   4035: bipush 79
    //   4037: istore 60
    //   4039: goto -35 -> 4004
    //   4042: bipush 71
    //   4044: istore 60
    //   4046: goto -42 -> 4004
    //   4049: aload 61
    //   4051: iload 63
    //   4053: caload
    //   4054: istore 64
    //   4056: iload 63
    //   4058: iconst_5
    //   4059: irem
    //   4060: tableswitch	default:+32 -> 4092, 0:+53->4113, 1:+60->4120, 2:+67->4127, 3:+74->4134
    //   4093: castore
    //   4094: istore 65
    //   4096: aload 61
    //   4098: iload 63
    //   4100: iload 65
    //   4102: iload 64
    //   4104: ixor
    //   4105: i2c
    //   4106: castore
    //   4107: iinc 63 1
    //   4110: goto -3646 -> 464
    //   4113: bipush 56
    //   4115: istore 65
    //   4117: goto -21 -> 4096
    //   4120: bipush 120
    //   4122: istore 65
    //   4124: goto -28 -> 4096
    //   4127: bipush 79
    //   4129: istore 65
    //   4131: goto -35 -> 4096
    //   4134: bipush 71
    //   4136: istore 65
    //   4138: goto -42 -> 4096
    //   4141: aload 66
    //   4143: iload 68
    //   4145: caload
    //   4146: istore 69
    //   4148: iload 68
    //   4150: iconst_5
    //   4151: irem
    //   4152: tableswitch	default:+32 -> 4184, 0:+53->4205, 1:+60->4212, 2:+67->4219, 3:+74->4226
    //   4185: castore
    //   4186: istore 70
    //   4188: aload 66
    //   4190: iload 68
    //   4192: iload 70
    //   4194: iload 69
    //   4196: ixor
    //   4197: i2c
    //   4198: castore
    //   4199: iinc 68 1
    //   4202: goto -3700 -> 502
    //   4205: bipush 56
    //   4207: istore 70
    //   4209: goto -21 -> 4188
    //   4212: bipush 120
    //   4214: istore 70
    //   4216: goto -28 -> 4188
    //   4219: bipush 79
    //   4221: istore 70
    //   4223: goto -35 -> 4188
    //   4226: bipush 71
    //   4228: istore 70
    //   4230: goto -42 -> 4188
    //   4233: aload 71
    //   4235: iload 73
    //   4237: caload
    //   4238: istore 74
    //   4240: iload 73
    //   4242: iconst_5
    //   4243: irem
    //   4244: tableswitch	default:+32 -> 4276, 0:+53->4297, 1:+60->4304, 2:+67->4311, 3:+74->4318
    //   4277: castore
    //   4278: istore 75
    //   4280: aload 71
    //   4282: iload 73
    //   4284: iload 75
    //   4286: iload 74
    //   4288: ixor
    //   4289: i2c
    //   4290: castore
    //   4291: iinc 73 1
    //   4294: goto -3754 -> 540
    //   4297: bipush 56
    //   4299: istore 75
    //   4301: goto -21 -> 4280
    //   4304: bipush 120
    //   4306: istore 75
    //   4308: goto -28 -> 4280
    //   4311: bipush 79
    //   4313: istore 75
    //   4315: goto -35 -> 4280
    //   4318: bipush 71
    //   4320: istore 75
    //   4322: goto -42 -> 4280
    //   4325: aload 76
    //   4327: iload 78
    //   4329: caload
    //   4330: istore 79
    //   4332: iload 78
    //   4334: iconst_5
    //   4335: irem
    //   4336: tableswitch	default:+32 -> 4368, 0:+53->4389, 1:+60->4396, 2:+67->4403, 3:+74->4410
    //   4369: castore
    //   4370: istore 80
    //   4372: aload 76
    //   4374: iload 78
    //   4376: iload 80
    //   4378: iload 79
    //   4380: ixor
    //   4381: i2c
    //   4382: castore
    //   4383: iinc 78 1
    //   4386: goto -3808 -> 578
    //   4389: bipush 56
    //   4391: istore 80
    //   4393: goto -21 -> 4372
    //   4396: bipush 120
    //   4398: istore 80
    //   4400: goto -28 -> 4372
    //   4403: bipush 79
    //   4405: istore 80
    //   4407: goto -35 -> 4372
    //   4410: bipush 71
    //   4412: istore 80
    //   4414: goto -42 -> 4372
    //   4417: aload 81
    //   4419: iload 83
    //   4421: caload
    //   4422: istore 84
    //   4424: iload 83
    //   4426: iconst_5
    //   4427: irem
    //   4428: tableswitch	default:+32 -> 4460, 0:+53->4481, 1:+60->4488, 2:+67->4495, 3:+74->4502
    //   4461: castore
    //   4462: istore 85
    //   4464: aload 81
    //   4466: iload 83
    //   4468: iload 85
    //   4470: iload 84
    //   4472: ixor
    //   4473: i2c
    //   4474: castore
    //   4475: iinc 83 1
    //   4478: goto -3862 -> 616
    //   4481: bipush 56
    //   4483: istore 85
    //   4485: goto -21 -> 4464
    //   4488: bipush 120
    //   4490: istore 85
    //   4492: goto -28 -> 4464
    //   4495: bipush 79
    //   4497: istore 85
    //   4499: goto -35 -> 4464
    //   4502: bipush 71
    //   4504: istore 85
    //   4506: goto -42 -> 4464
    //   4509: aload 86
    //   4511: iload 88
    //   4513: caload
    //   4514: istore 89
    //   4516: iload 88
    //   4518: iconst_5
    //   4519: irem
    //   4520: tableswitch	default:+32 -> 4552, 0:+53->4573, 1:+60->4580, 2:+67->4587, 3:+74->4594
    //   4553: castore
    //   4554: istore 90
    //   4556: aload 86
    //   4558: iload 88
    //   4560: iload 90
    //   4562: iload 89
    //   4564: ixor
    //   4565: i2c
    //   4566: castore
    //   4567: iinc 88 1
    //   4570: goto -3916 -> 654
    //   4573: bipush 56
    //   4575: istore 90
    //   4577: goto -21 -> 4556
    //   4580: bipush 120
    //   4582: istore 90
    //   4584: goto -28 -> 4556
    //   4587: bipush 79
    //   4589: istore 90
    //   4591: goto -35 -> 4556
    //   4594: bipush 71
    //   4596: istore 90
    //   4598: goto -42 -> 4556
    //   4601: aload 91
    //   4603: iload 93
    //   4605: caload
    //   4606: istore 94
    //   4608: iload 93
    //   4610: iconst_5
    //   4611: irem
    //   4612: tableswitch	default:+32 -> 4644, 0:+53->4665, 1:+60->4672, 2:+67->4679, 3:+74->4686
    //   4645: castore
    //   4646: istore 95
    //   4648: aload 91
    //   4650: iload 93
    //   4652: iload 95
    //   4654: iload 94
    //   4656: ixor
    //   4657: i2c
    //   4658: castore
    //   4659: iinc 93 1
    //   4662: goto -3970 -> 692
    //   4665: bipush 56
    //   4667: istore 95
    //   4669: goto -21 -> 4648
    //   4672: bipush 120
    //   4674: istore 95
    //   4676: goto -28 -> 4648
    //   4679: bipush 79
    //   4681: istore 95
    //   4683: goto -35 -> 4648
    //   4686: bipush 71
    //   4688: istore 95
    //   4690: goto -42 -> 4648
    //   4693: aload 96
    //   4695: iload 98
    //   4697: caload
    //   4698: istore 99
    //   4700: iload 98
    //   4702: iconst_5
    //   4703: irem
    //   4704: tableswitch	default:+32 -> 4736, 0:+53->4757, 1:+60->4764, 2:+67->4771, 3:+74->4778
    //   4737: castore
    //   4738: istore 100
    //   4740: aload 96
    //   4742: iload 98
    //   4744: iload 100
    //   4746: iload 99
    //   4748: ixor
    //   4749: i2c
    //   4750: castore
    //   4751: iinc 98 1
    //   4754: goto -4024 -> 730
    //   4757: bipush 56
    //   4759: istore 100
    //   4761: goto -21 -> 4740
    //   4764: bipush 120
    //   4766: istore 100
    //   4768: goto -28 -> 4740
    //   4771: bipush 79
    //   4773: istore 100
    //   4775: goto -35 -> 4740
    //   4778: bipush 71
    //   4780: istore 100
    //   4782: goto -42 -> 4740
    //   4785: aload 101
    //   4787: iload 103
    //   4789: caload
    //   4790: istore 104
    //   4792: iload 103
    //   4794: iconst_5
    //   4795: irem
    //   4796: tableswitch	default:+32 -> 4828, 0:+53->4849, 1:+60->4856, 2:+67->4863, 3:+74->4870
    //   4829: castore
    //   4830: istore 105
    //   4832: aload 101
    //   4834: iload 103
    //   4836: iload 105
    //   4838: iload 104
    //   4840: ixor
    //   4841: i2c
    //   4842: castore
    //   4843: iinc 103 1
    //   4846: goto -4078 -> 768
    //   4849: bipush 56
    //   4851: istore 105
    //   4853: goto -21 -> 4832
    //   4856: bipush 120
    //   4858: istore 105
    //   4860: goto -28 -> 4832
    //   4863: bipush 79
    //   4865: istore 105
    //   4867: goto -35 -> 4832
    //   4870: bipush 71
    //   4872: istore 105
    //   4874: goto -42 -> 4832
    //   4877: aload 106
    //   4879: iload 108
    //   4881: caload
    //   4882: istore 109
    //   4884: iload 108
    //   4886: iconst_5
    //   4887: irem
    //   4888: tableswitch	default:+32 -> 4920, 0:+53->4941, 1:+60->4948, 2:+67->4955, 3:+74->4962
    //   4921: castore
    //   4922: istore 110
    //   4924: aload 106
    //   4926: iload 108
    //   4928: iload 110
    //   4930: iload 109
    //   4932: ixor
    //   4933: i2c
    //   4934: castore
    //   4935: iinc 108 1
    //   4938: goto -4132 -> 806
    //   4941: bipush 56
    //   4943: istore 110
    //   4945: goto -21 -> 4924
    //   4948: bipush 120
    //   4950: istore 110
    //   4952: goto -28 -> 4924
    //   4955: bipush 79
    //   4957: istore 110
    //   4959: goto -35 -> 4924
    //   4962: bipush 71
    //   4964: istore 110
    //   4966: goto -42 -> 4924
    //   4969: aload 111
    //   4971: iload 113
    //   4973: caload
    //   4974: istore 114
    //   4976: iload 113
    //   4978: iconst_5
    //   4979: irem
    //   4980: tableswitch	default:+32 -> 5012, 0:+53->5033, 1:+60->5040, 2:+67->5047, 3:+74->5054
    //   5013: castore
    //   5014: istore 115
    //   5016: aload 111
    //   5018: iload 113
    //   5020: iload 115
    //   5022: iload 114
    //   5024: ixor
    //   5025: i2c
    //   5026: castore
    //   5027: iinc 113 1
    //   5030: goto -4186 -> 844
    //   5033: bipush 56
    //   5035: istore 115
    //   5037: goto -21 -> 5016
    //   5040: bipush 120
    //   5042: istore 115
    //   5044: goto -28 -> 5016
    //   5047: bipush 79
    //   5049: istore 115
    //   5051: goto -35 -> 5016
    //   5054: bipush 71
    //   5056: istore 115
    //   5058: goto -42 -> 5016
    //   5061: aload 116
    //   5063: iload 118
    //   5065: caload
    //   5066: istore 119
    //   5068: iload 118
    //   5070: iconst_5
    //   5071: irem
    //   5072: tableswitch	default:+32 -> 5104, 0:+53->5125, 1:+60->5132, 2:+67->5139, 3:+74->5146
    //   5105: castore
    //   5106: istore 120
    //   5108: aload 116
    //   5110: iload 118
    //   5112: iload 120
    //   5114: iload 119
    //   5116: ixor
    //   5117: i2c
    //   5118: castore
    //   5119: iinc 118 1
    //   5122: goto -4240 -> 882
    //   5125: bipush 56
    //   5127: istore 120
    //   5129: goto -21 -> 5108
    //   5132: bipush 120
    //   5134: istore 120
    //   5136: goto -28 -> 5108
    //   5139: bipush 79
    //   5141: istore 120
    //   5143: goto -35 -> 5108
    //   5146: bipush 71
    //   5148: istore 120
    //   5150: goto -42 -> 5108
    //   5153: aload 121
    //   5155: iload 123
    //   5157: caload
    //   5158: istore 124
    //   5160: iload 123
    //   5162: iconst_5
    //   5163: irem
    //   5164: tableswitch	default:+32 -> 5196, 0:+53->5217, 1:+60->5224, 2:+67->5231, 3:+74->5238
    //   5197: castore
    //   5198: istore 125
    //   5200: aload 121
    //   5202: iload 123
    //   5204: iload 125
    //   5206: iload 124
    //   5208: ixor
    //   5209: i2c
    //   5210: castore
    //   5211: iinc 123 1
    //   5214: goto -4294 -> 920
    //   5217: bipush 56
    //   5219: istore 125
    //   5221: goto -21 -> 5200
    //   5224: bipush 120
    //   5226: istore 125
    //   5228: goto -28 -> 5200
    //   5231: bipush 79
    //   5233: istore 125
    //   5235: goto -35 -> 5200
    //   5238: bipush 71
    //   5240: istore 125
    //   5242: goto -42 -> 5200
    //   5245: aload 126
    //   5247: iload 128
    //   5249: caload
    //   5250: istore 129
    //   5252: iload 128
    //   5254: iconst_5
    //   5255: irem
    //   5256: tableswitch	default:+32 -> 5288, 0:+53->5309, 1:+60->5316, 2:+67->5323, 3:+74->5330
    //   5289: castore
    //   5290: istore 130
    //   5292: aload 126
    //   5294: iload 128
    //   5296: iload 130
    //   5298: iload 129
    //   5300: ixor
    //   5301: i2c
    //   5302: castore
    //   5303: iinc 128 1
    //   5306: goto -4348 -> 958
    //   5309: bipush 56
    //   5311: istore 130
    //   5313: goto -21 -> 5292
    //   5316: bipush 120
    //   5318: istore 130
    //   5320: goto -28 -> 5292
    //   5323: bipush 79
    //   5325: istore 130
    //   5327: goto -35 -> 5292
    //   5330: bipush 71
    //   5332: istore 130
    //   5334: goto -42 -> 5292
    //   5337: aload 131
    //   5339: iload 133
    //   5341: caload
    //   5342: istore 134
    //   5344: iload 133
    //   5346: iconst_5
    //   5347: irem
    //   5348: tableswitch	default:+32 -> 5380, 0:+53->5401, 1:+60->5408, 2:+67->5415, 3:+74->5422
    //   5381: castore
    //   5382: istore 135
    //   5384: aload 131
    //   5386: iload 133
    //   5388: iload 135
    //   5390: iload 134
    //   5392: ixor
    //   5393: i2c
    //   5394: castore
    //   5395: iinc 133 1
    //   5398: goto -4402 -> 996
    //   5401: bipush 56
    //   5403: istore 135
    //   5405: goto -21 -> 5384
    //   5408: bipush 120
    //   5410: istore 135
    //   5412: goto -28 -> 5384
    //   5415: bipush 79
    //   5417: istore 135
    //   5419: goto -35 -> 5384
    //   5422: bipush 71
    //   5424: istore 135
    //   5426: goto -42 -> 5384
    //   5429: aload 136
    //   5431: iload 138
    //   5433: caload
    //   5434: istore 139
    //   5436: iload 138
    //   5438: iconst_5
    //   5439: irem
    //   5440: tableswitch	default:+32 -> 5472, 0:+53->5493, 1:+60->5500, 2:+67->5507, 3:+74->5514
    //   5473: castore
    //   5474: istore 140
    //   5476: aload 136
    //   5478: iload 138
    //   5480: iload 140
    //   5482: iload 139
    //   5484: ixor
    //   5485: i2c
    //   5486: castore
    //   5487: iinc 138 1
    //   5490: goto -4456 -> 1034
    //   5493: bipush 56
    //   5495: istore 140
    //   5497: goto -21 -> 5476
    //   5500: bipush 120
    //   5502: istore 140
    //   5504: goto -28 -> 5476
    //   5507: bipush 79
    //   5509: istore 140
    //   5511: goto -35 -> 5476
    //   5514: bipush 71
    //   5516: istore 140
    //   5518: goto -42 -> 5476
    //   5521: aload 141
    //   5523: iload 143
    //   5525: caload
    //   5526: istore 144
    //   5528: iload 143
    //   5530: iconst_5
    //   5531: irem
    //   5532: tableswitch	default:+32 -> 5564, 0:+53->5585, 1:+60->5592, 2:+67->5599, 3:+74->5606
    //   5565: castore
    //   5566: istore 145
    //   5568: aload 141
    //   5570: iload 143
    //   5572: iload 145
    //   5574: iload 144
    //   5576: ixor
    //   5577: i2c
    //   5578: castore
    //   5579: iinc 143 1
    //   5582: goto -4510 -> 1072
    //   5585: bipush 56
    //   5587: istore 145
    //   5589: goto -21 -> 5568
    //   5592: bipush 120
    //   5594: istore 145
    //   5596: goto -28 -> 5568
    //   5599: bipush 79
    //   5601: istore 145
    //   5603: goto -35 -> 5568
    //   5606: bipush 71
    //   5608: istore 145
    //   5610: goto -42 -> 5568
    //   5613: aload 146
    //   5615: iload 148
    //   5617: caload
    //   5618: istore 149
    //   5620: iload 148
    //   5622: iconst_5
    //   5623: irem
    //   5624: tableswitch	default:+32 -> 5656, 0:+53->5677, 1:+60->5684, 2:+67->5691, 3:+74->5698
    //   5657: castore
    //   5658: istore 150
    //   5660: aload 146
    //   5662: iload 148
    //   5664: iload 150
    //   5666: iload 149
    //   5668: ixor
    //   5669: i2c
    //   5670: castore
    //   5671: iinc 148 1
    //   5674: goto -4564 -> 1110
    //   5677: bipush 56
    //   5679: istore 150
    //   5681: goto -21 -> 5660
    //   5684: bipush 120
    //   5686: istore 150
    //   5688: goto -28 -> 5660
    //   5691: bipush 79
    //   5693: istore 150
    //   5695: goto -35 -> 5660
    //   5698: bipush 71
    //   5700: istore 150
    //   5702: goto -42 -> 5660
    //   5705: aload 151
    //   5707: iload 153
    //   5709: caload
    //   5710: istore 154
    //   5712: iload 153
    //   5714: iconst_5
    //   5715: irem
    //   5716: tableswitch	default:+32 -> 5748, 0:+53->5769, 1:+60->5776, 2:+67->5783, 3:+74->5790
    //   5749: castore
    //   5750: istore 155
    //   5752: aload 151
    //   5754: iload 153
    //   5756: iload 155
    //   5758: iload 154
    //   5760: ixor
    //   5761: i2c
    //   5762: castore
    //   5763: iinc 153 1
    //   5766: goto -4618 -> 1148
    //   5769: bipush 56
    //   5771: istore 155
    //   5773: goto -21 -> 5752
    //   5776: bipush 120
    //   5778: istore 155
    //   5780: goto -28 -> 5752
    //   5783: bipush 79
    //   5785: istore 155
    //   5787: goto -35 -> 5752
    //   5790: bipush 71
    //   5792: istore 155
    //   5794: goto -42 -> 5752
    //   5797: aload 156
    //   5799: iload 158
    //   5801: caload
    //   5802: istore 159
    //   5804: iload 158
    //   5806: iconst_5
    //   5807: irem
    //   5808: tableswitch	default:+32 -> 5840, 0:+53->5861, 1:+60->5868, 2:+67->5875, 3:+74->5882
    //   5841: castore
    //   5842: istore 160
    //   5844: aload 156
    //   5846: iload 158
    //   5848: iload 160
    //   5850: iload 159
    //   5852: ixor
    //   5853: i2c
    //   5854: castore
    //   5855: iinc 158 1
    //   5858: goto -4672 -> 1186
    //   5861: bipush 56
    //   5863: istore 160
    //   5865: goto -21 -> 5844
    //   5868: bipush 120
    //   5870: istore 160
    //   5872: goto -28 -> 5844
    //   5875: bipush 79
    //   5877: istore 160
    //   5879: goto -35 -> 5844
    //   5882: bipush 71
    //   5884: istore 160
    //   5886: goto -42 -> 5844
    //   5889: aload 161
    //   5891: iload 163
    //   5893: caload
    //   5894: istore 164
    //   5896: iload 163
    //   5898: iconst_5
    //   5899: irem
    //   5900: tableswitch	default:+32 -> 5932, 0:+53->5953, 1:+60->5960, 2:+67->5967, 3:+74->5974
    //   5933: castore
    //   5934: istore 165
    //   5936: aload 161
    //   5938: iload 163
    //   5940: iload 165
    //   5942: iload 164
    //   5944: ixor
    //   5945: i2c
    //   5946: castore
    //   5947: iinc 163 1
    //   5950: goto -4726 -> 1224
    //   5953: bipush 56
    //   5955: istore 165
    //   5957: goto -21 -> 5936
    //   5960: bipush 120
    //   5962: istore 165
    //   5964: goto -28 -> 5936
    //   5967: bipush 79
    //   5969: istore 165
    //   5971: goto -35 -> 5936
    //   5974: bipush 71
    //   5976: istore 165
    //   5978: goto -42 -> 5936
    //   5981: aload 166
    //   5983: iload 168
    //   5985: caload
    //   5986: istore 169
    //   5988: iload 168
    //   5990: iconst_5
    //   5991: irem
    //   5992: tableswitch	default:+32 -> 6024, 0:+53->6045, 1:+60->6052, 2:+67->6059, 3:+74->6066
    //   6025: castore
    //   6026: istore 170
    //   6028: aload 166
    //   6030: iload 168
    //   6032: iload 170
    //   6034: iload 169
    //   6036: ixor
    //   6037: i2c
    //   6038: castore
    //   6039: iinc 168 1
    //   6042: goto -4780 -> 1262
    //   6045: bipush 56
    //   6047: istore 170
    //   6049: goto -21 -> 6028
    //   6052: bipush 120
    //   6054: istore 170
    //   6056: goto -28 -> 6028
    //   6059: bipush 79
    //   6061: istore 170
    //   6063: goto -35 -> 6028
    //   6066: bipush 71
    //   6068: istore 170
    //   6070: goto -42 -> 6028
    //   6073: aload 171
    //   6075: iload 173
    //   6077: caload
    //   6078: istore 174
    //   6080: iload 173
    //   6082: iconst_5
    //   6083: irem
    //   6084: tableswitch	default:+32 -> 6116, 0:+53->6137, 1:+60->6144, 2:+67->6151, 3:+74->6158
    //   6117: castore
    //   6118: istore 175
    //   6120: aload 171
    //   6122: iload 173
    //   6124: iload 175
    //   6126: iload 174
    //   6128: ixor
    //   6129: i2c
    //   6130: castore
    //   6131: iinc 173 1
    //   6134: goto -4834 -> 1300
    //   6137: bipush 56
    //   6139: istore 175
    //   6141: goto -21 -> 6120
    //   6144: bipush 120
    //   6146: istore 175
    //   6148: goto -28 -> 6120
    //   6151: bipush 79
    //   6153: istore 175
    //   6155: goto -35 -> 6120
    //   6158: bipush 71
    //   6160: istore 175
    //   6162: goto -42 -> 6120
    //   6165: aload 176
    //   6167: iload 178
    //   6169: caload
    //   6170: istore 179
    //   6172: iload 178
    //   6174: iconst_5
    //   6175: irem
    //   6176: tableswitch	default:+32 -> 6208, 0:+53->6229, 1:+60->6236, 2:+67->6243, 3:+74->6250
    //   6209: castore
    //   6210: istore 180
    //   6212: aload 176
    //   6214: iload 178
    //   6216: iload 180
    //   6218: iload 179
    //   6220: ixor
    //   6221: i2c
    //   6222: castore
    //   6223: iinc 178 1
    //   6226: goto -4888 -> 1338
    //   6229: bipush 56
    //   6231: istore 180
    //   6233: goto -21 -> 6212
    //   6236: bipush 120
    //   6238: istore 180
    //   6240: goto -28 -> 6212
    //   6243: bipush 79
    //   6245: istore 180
    //   6247: goto -35 -> 6212
    //   6250: bipush 71
    //   6252: istore 180
    //   6254: goto -42 -> 6212
    //   6257: aload 181
    //   6259: iload 183
    //   6261: caload
    //   6262: istore 184
    //   6264: iload 183
    //   6266: iconst_5
    //   6267: irem
    //   6268: tableswitch	default:+32 -> 6300, 0:+53->6321, 1:+60->6328, 2:+67->6335, 3:+74->6342
    //   6301: castore
    //   6302: istore 185
    //   6304: aload 181
    //   6306: iload 183
    //   6308: iload 185
    //   6310: iload 184
    //   6312: ixor
    //   6313: i2c
    //   6314: castore
    //   6315: iinc 183 1
    //   6318: goto -4942 -> 1376
    //   6321: bipush 56
    //   6323: istore 185
    //   6325: goto -21 -> 6304
    //   6328: bipush 120
    //   6330: istore 185
    //   6332: goto -28 -> 6304
    //   6335: bipush 79
    //   6337: istore 185
    //   6339: goto -35 -> 6304
    //   6342: bipush 71
    //   6344: istore 185
    //   6346: goto -42 -> 6304
    //   6349: aload 186
    //   6351: iload 188
    //   6353: caload
    //   6354: istore 189
    //   6356: iload 188
    //   6358: iconst_5
    //   6359: irem
    //   6360: tableswitch	default:+32 -> 6392, 0:+53->6413, 1:+60->6420, 2:+67->6427, 3:+74->6434
    //   6393: castore
    //   6394: istore 190
    //   6396: aload 186
    //   6398: iload 188
    //   6400: iload 190
    //   6402: iload 189
    //   6404: ixor
    //   6405: i2c
    //   6406: castore
    //   6407: iinc 188 1
    //   6410: goto -4996 -> 1414
    //   6413: bipush 56
    //   6415: istore 190
    //   6417: goto -21 -> 6396
    //   6420: bipush 120
    //   6422: istore 190
    //   6424: goto -28 -> 6396
    //   6427: bipush 79
    //   6429: istore 190
    //   6431: goto -35 -> 6396
    //   6434: bipush 71
    //   6436: istore 190
    //   6438: goto -42 -> 6396
    //   6441: aload 191
    //   6443: iload 193
    //   6445: caload
    //   6446: istore 194
    //   6448: iload 193
    //   6450: iconst_5
    //   6451: irem
    //   6452: tableswitch	default:+32 -> 6484, 0:+53->6505, 1:+60->6512, 2:+67->6519, 3:+74->6526
    //   6485: castore
    //   6486: istore 195
    //   6488: aload 191
    //   6490: iload 193
    //   6492: iload 195
    //   6494: iload 194
    //   6496: ixor
    //   6497: i2c
    //   6498: castore
    //   6499: iinc 193 1
    //   6502: goto -5050 -> 1452
    //   6505: bipush 56
    //   6507: istore 195
    //   6509: goto -21 -> 6488
    //   6512: bipush 120
    //   6514: istore 195
    //   6516: goto -28 -> 6488
    //   6519: bipush 79
    //   6521: istore 195
    //   6523: goto -35 -> 6488
    //   6526: bipush 71
    //   6528: istore 195
    //   6530: goto -42 -> 6488
    //   6533: aload 196
    //   6535: iload 198
    //   6537: caload
    //   6538: istore 199
    //   6540: iload 198
    //   6542: iconst_5
    //   6543: irem
    //   6544: tableswitch	default:+32 -> 6576, 0:+53->6597, 1:+60->6604, 2:+67->6611, 3:+74->6618
    //   6577: castore
    //   6578: istore 200
    //   6580: aload 196
    //   6582: iload 198
    //   6584: iload 200
    //   6586: iload 199
    //   6588: ixor
    //   6589: i2c
    //   6590: castore
    //   6591: iinc 198 1
    //   6594: goto -5104 -> 1490
    //   6597: bipush 56
    //   6599: istore 200
    //   6601: goto -21 -> 6580
    //   6604: bipush 120
    //   6606: istore 200
    //   6608: goto -28 -> 6580
    //   6611: bipush 79
    //   6613: istore 200
    //   6615: goto -35 -> 6580
    //   6618: bipush 71
    //   6620: istore 200
    //   6622: goto -42 -> 6580
    //   6625: aload 201
    //   6627: iload 203
    //   6629: caload
    //   6630: istore 204
    //   6632: iload 203
    //   6634: iconst_5
    //   6635: irem
    //   6636: tableswitch	default:+32 -> 6668, 0:+53->6689, 1:+60->6696, 2:+67->6703, 3:+74->6710
    //   6669: castore
    //   6670: istore 205
    //   6672: aload 201
    //   6674: iload 203
    //   6676: iload 205
    //   6678: iload 204
    //   6680: ixor
    //   6681: i2c
    //   6682: castore
    //   6683: iinc 203 1
    //   6686: goto -5158 -> 1528
    //   6689: bipush 56
    //   6691: istore 205
    //   6693: goto -21 -> 6672
    //   6696: bipush 120
    //   6698: istore 205
    //   6700: goto -28 -> 6672
    //   6703: bipush 79
    //   6705: istore 205
    //   6707: goto -35 -> 6672
    //   6710: bipush 71
    //   6712: istore 205
    //   6714: goto -42 -> 6672
    //   6717: aload 206
    //   6719: iload 208
    //   6721: caload
    //   6722: istore 209
    //   6724: iload 208
    //   6726: iconst_5
    //   6727: irem
    //   6728: tableswitch	default:+32 -> 6760, 0:+53->6781, 1:+60->6788, 2:+67->6795, 3:+74->6802
    //   6761: castore
    //   6762: istore 210
    //   6764: aload 206
    //   6766: iload 208
    //   6768: iload 210
    //   6770: iload 209
    //   6772: ixor
    //   6773: i2c
    //   6774: castore
    //   6775: iinc 208 1
    //   6778: goto -5212 -> 1566
    //   6781: bipush 56
    //   6783: istore 210
    //   6785: goto -21 -> 6764
    //   6788: bipush 120
    //   6790: istore 210
    //   6792: goto -28 -> 6764
    //   6795: bipush 79
    //   6797: istore 210
    //   6799: goto -35 -> 6764
    //   6802: bipush 71
    //   6804: istore 210
    //   6806: goto -42 -> 6764
    //   6809: aload 211
    //   6811: iload 213
    //   6813: caload
    //   6814: istore 214
    //   6816: iload 213
    //   6818: iconst_5
    //   6819: irem
    //   6820: tableswitch	default:+32 -> 6852, 0:+53->6873, 1:+60->6880, 2:+67->6887, 3:+74->6894
    //   6853: castore
    //   6854: istore 215
    //   6856: aload 211
    //   6858: iload 213
    //   6860: iload 215
    //   6862: iload 214
    //   6864: ixor
    //   6865: i2c
    //   6866: castore
    //   6867: iinc 213 1
    //   6870: goto -5266 -> 1604
    //   6873: bipush 56
    //   6875: istore 215
    //   6877: goto -21 -> 6856
    //   6880: bipush 120
    //   6882: istore 215
    //   6884: goto -28 -> 6856
    //   6887: bipush 79
    //   6889: istore 215
    //   6891: goto -35 -> 6856
    //   6894: bipush 71
    //   6896: istore 215
    //   6898: goto -42 -> 6856
    //   6901: aload 216
    //   6903: iload 218
    //   6905: caload
    //   6906: istore 219
    //   6908: iload 218
    //   6910: iconst_5
    //   6911: irem
    //   6912: tableswitch	default:+32 -> 6944, 0:+53->6965, 1:+60->6972, 2:+67->6979, 3:+74->6986
    //   6945: castore
    //   6946: istore 220
    //   6948: aload 216
    //   6950: iload 218
    //   6952: iload 220
    //   6954: iload 219
    //   6956: ixor
    //   6957: i2c
    //   6958: castore
    //   6959: iinc 218 1
    //   6962: goto -5320 -> 1642
    //   6965: bipush 56
    //   6967: istore 220
    //   6969: goto -21 -> 6948
    //   6972: bipush 120
    //   6974: istore 220
    //   6976: goto -28 -> 6948
    //   6979: bipush 79
    //   6981: istore 220
    //   6983: goto -35 -> 6948
    //   6986: bipush 71
    //   6988: istore 220
    //   6990: goto -42 -> 6948
    //   6993: aload 221
    //   6995: iload 223
    //   6997: caload
    //   6998: istore 224
    //   7000: iload 223
    //   7002: iconst_5
    //   7003: irem
    //   7004: tableswitch	default:+32 -> 7036, 0:+53->7057, 1:+60->7064, 2:+67->7071, 3:+74->7078
    //   7037: castore
    //   7038: istore 225
    //   7040: aload 221
    //   7042: iload 223
    //   7044: iload 225
    //   7046: iload 224
    //   7048: ixor
    //   7049: i2c
    //   7050: castore
    //   7051: iinc 223 1
    //   7054: goto -5374 -> 1680
    //   7057: bipush 56
    //   7059: istore 225
    //   7061: goto -21 -> 7040
    //   7064: bipush 120
    //   7066: istore 225
    //   7068: goto -28 -> 7040
    //   7071: bipush 79
    //   7073: istore 225
    //   7075: goto -35 -> 7040
    //   7078: bipush 71
    //   7080: istore 225
    //   7082: goto -42 -> 7040
    //   7085: aload 226
    //   7087: iload 228
    //   7089: caload
    //   7090: istore 229
    //   7092: iload 228
    //   7094: iconst_5
    //   7095: irem
    //   7096: tableswitch	default:+32 -> 7128, 0:+53->7149, 1:+60->7156, 2:+67->7163, 3:+74->7170
    //   7129: castore
    //   7130: istore 230
    //   7132: aload 226
    //   7134: iload 228
    //   7136: iload 230
    //   7138: iload 229
    //   7140: ixor
    //   7141: i2c
    //   7142: castore
    //   7143: iinc 228 1
    //   7146: goto -5428 -> 1718
    //   7149: bipush 56
    //   7151: istore 230
    //   7153: goto -21 -> 7132
    //   7156: bipush 120
    //   7158: istore 230
    //   7160: goto -28 -> 7132
    //   7163: bipush 79
    //   7165: istore 230
    //   7167: goto -35 -> 7132
    //   7170: bipush 71
    //   7172: istore 230
    //   7174: goto -42 -> 7132
    //   7177: aload 231
    //   7179: iload 233
    //   7181: caload
    //   7182: istore 234
    //   7184: iload 233
    //   7186: iconst_5
    //   7187: irem
    //   7188: tableswitch	default:+32 -> 7220, 0:+53->7241, 1:+60->7248, 2:+67->7255, 3:+74->7262
    //   7221: castore
    //   7222: istore 235
    //   7224: aload 231
    //   7226: iload 233
    //   7228: iload 235
    //   7230: iload 234
    //   7232: ixor
    //   7233: i2c
    //   7234: castore
    //   7235: iinc 233 1
    //   7238: goto -5482 -> 1756
    //   7241: bipush 56
    //   7243: istore 235
    //   7245: goto -21 -> 7224
    //   7248: bipush 120
    //   7250: istore 235
    //   7252: goto -28 -> 7224
    //   7255: bipush 79
    //   7257: istore 235
    //   7259: goto -35 -> 7224
    //   7262: bipush 71
    //   7264: istore 235
    //   7266: goto -42 -> 7224
    //   7269: aload 236
    //   7271: iload 238
    //   7273: caload
    //   7274: istore 239
    //   7276: iload 238
    //   7278: iconst_5
    //   7279: irem
    //   7280: tableswitch	default:+32 -> 7312, 0:+53->7333, 1:+60->7340, 2:+67->7347, 3:+74->7354
    //   7313: castore
    //   7314: istore 240
    //   7316: aload 236
    //   7318: iload 238
    //   7320: iload 240
    //   7322: iload 239
    //   7324: ixor
    //   7325: i2c
    //   7326: castore
    //   7327: iinc 238 1
    //   7330: goto -5536 -> 1794
    //   7333: bipush 56
    //   7335: istore 240
    //   7337: goto -21 -> 7316
    //   7340: bipush 120
    //   7342: istore 240
    //   7344: goto -28 -> 7316
    //   7347: bipush 79
    //   7349: istore 240
    //   7351: goto -35 -> 7316
    //   7354: bipush 71
    //   7356: istore 240
    //   7358: goto -42 -> 7316
    //   7361: aload 241
    //   7363: iload 243
    //   7365: caload
    //   7366: istore 244
    //   7368: iload 243
    //   7370: iconst_5
    //   7371: irem
    //   7372: tableswitch	default:+32 -> 7404, 0:+53->7425, 1:+60->7432, 2:+67->7439, 3:+74->7446
    //   7405: castore
    //   7406: istore 245
    //   7408: aload 241
    //   7410: iload 243
    //   7412: iload 245
    //   7414: iload 244
    //   7416: ixor
    //   7417: i2c
    //   7418: castore
    //   7419: iinc 243 1
    //   7422: goto -5590 -> 1832
    //   7425: bipush 56
    //   7427: istore 245
    //   7429: goto -21 -> 7408
    //   7432: bipush 120
    //   7434: istore 245
    //   7436: goto -28 -> 7408
    //   7439: bipush 79
    //   7441: istore 245
    //   7443: goto -35 -> 7408
    //   7446: bipush 71
    //   7448: istore 245
    //   7450: goto -42 -> 7408
    //   7453: aload 246
    //   7455: iload 248
    //   7457: caload
    //   7458: istore 249
    //   7460: iload 248
    //   7462: iconst_5
    //   7463: irem
    //   7464: tableswitch	default:+32 -> 7496, 0:+53->7517, 1:+60->7524, 2:+67->7531, 3:+74->7538
    //   7497: castore
    //   7498: istore 250
    //   7500: aload 246
    //   7502: iload 248
    //   7504: iload 250
    //   7506: iload 249
    //   7508: ixor
    //   7509: i2c
    //   7510: castore
    //   7511: iinc 248 1
    //   7514: goto -5644 -> 1870
    //   7517: bipush 56
    //   7519: istore 250
    //   7521: goto -21 -> 7500
    //   7524: bipush 120
    //   7526: istore 250
    //   7528: goto -28 -> 7500
    //   7531: bipush 79
    //   7533: istore 250
    //   7535: goto -35 -> 7500
    //   7538: bipush 71
    //   7540: istore 250
    //   7542: goto -42 -> 7500
    //   7545: aload 251
    //   7547: iload 253
    //   7549: caload
    //   7550: istore 254
    //   7552: iload 253
    //   7554: iconst_5
    //   7555: irem
    //   7556: tableswitch	default:+32 -> 7588, 0:+53->7609, 1:+60->7616, 2:+67->7623, 3:+74->7630
    //   7589: castore
    //   7590: istore 255
    //   7592: aload 251
    //   7594: iload 253
    //   7596: iload 255
    //   7598: iload 254
    //   7600: ixor
    //   7601: i2c
    //   7602: castore
    //   7603: iinc 253 1
    //   7606: goto -5698 -> 1908
    //   7609: bipush 56
    //   7611: istore 255
    //   7613: goto -21 -> 7592
    //   7616: bipush 120
    //   7618: istore 255
    //   7620: goto -28 -> 7592
    //   7623: bipush 79
    //   7625: istore 255
    //   7627: goto -35 -> 7592
    //   7630: bipush 71
    //   7632: istore 255
    //   7634: goto -42 -> 7592
    //   7637: wide
    //   7641: wide
    //   7645: caload
    //   7646: wide
    //   7650: wide
    //   7654: iconst_5
    //   7655: irem
    //   7656: tableswitch	default:+32 -> 7688, 0:+66->7722, 1:+75->7731, 2:+84->7740, 3:+93->7749
    //   7689: castore
    //   7690: wide
    //   7694: wide
    //   7698: wide
    //   7702: wide
    //   7706: wide
    //   7710: ixor
    //   7711: i2c
    //   7712: castore
    //   7713: wide
    //   7719: goto -5765 -> 1954
    //   7722: bipush 56
    //   7724: wide
    //   7728: goto -34 -> 7694
    //   7731: bipush 120
    //   7733: wide
    //   7737: goto -43 -> 7694
    //   7740: bipush 79
    //   7742: wide
    //   7746: goto -52 -> 7694
    //   7749: bipush 71
    //   7751: wide
    //   7755: goto -61 -> 7694
    //   7758: wide
    //   7762: wide
    //   7766: caload
    //   7767: wide
    //   7771: wide
    //   7775: iconst_5
    //   7776: irem
    //   7777: tableswitch	default:+31 -> 7808, 0:+65->7842, 1:+74->7851, 2:+83->7860, 3:+92->7869
    //   7809: castore
    //   7810: wide
    //   7814: wide
    //   7818: wide
    //   7822: wide
    //   7826: wide
    //   7830: ixor
    //   7831: i2c
    //   7832: castore
    //   7833: wide
    //   7839: goto -5833 -> 2006
    //   7842: bipush 56
    //   7844: wide
    //   7848: goto -34 -> 7814
    //   7851: bipush 120
    //   7853: wide
    //   7857: goto -43 -> 7814
    //   7860: bipush 79
    //   7862: wide
    //   7866: goto -52 -> 7814
    //   7869: bipush 71
    //   7871: wide
    //   7875: goto -61 -> 7814
    //   7878: wide
    //   7882: wide
    //   7886: caload
    //   7887: wide
    //   7891: wide
    //   7895: iconst_5
    //   7896: irem
    //   7897: tableswitch	default:+31 -> 7928, 0:+65->7962, 1:+74->7971, 2:+83->7980, 3:+92->7989
    //   7929: castore
    //   7930: wide
    //   7934: wide
    //   7938: wide
    //   7942: wide
    //   7946: wide
    //   7950: ixor
    //   7951: i2c
    //   7952: castore
    //   7953: wide
    //   7959: goto -5901 -> 2058
    //   7962: bipush 56
    //   7964: wide
    //   7968: goto -34 -> 7934
    //   7971: bipush 120
    //   7973: wide
    //   7977: goto -43 -> 7934
    //   7980: bipush 79
    //   7982: wide
    //   7986: goto -52 -> 7934
    //   7989: bipush 71
    //   7991: wide
    //   7995: goto -61 -> 7934
    //   7998: wide
    //   8002: wide
    //   8006: caload
    //   8007: wide
    //   8011: wide
    //   8015: iconst_5
    //   8016: irem
    //   8017: tableswitch	default:+31 -> 8048, 0:+65->8082, 1:+74->8091, 2:+83->8100, 3:+92->8109
    //   8049: castore
    //   8050: wide
    //   8054: wide
    //   8058: wide
    //   8062: wide
    //   8066: wide
    //   8070: ixor
    //   8071: i2c
    //   8072: castore
    //   8073: wide
    //   8079: goto -5969 -> 2110
    //   8082: bipush 56
    //   8084: wide
    //   8088: goto -34 -> 8054
    //   8091: bipush 120
    //   8093: wide
    //   8097: goto -43 -> 8054
    //   8100: bipush 79
    //   8102: wide
    //   8106: goto -52 -> 8054
    //   8109: bipush 71
    //   8111: wide
    //   8115: goto -61 -> 8054
    //   8118: wide
    //   8122: wide
    //   8126: caload
    //   8127: wide
    //   8131: wide
    //   8135: iconst_5
    //   8136: irem
    //   8137: tableswitch	default:+31 -> 8168, 0:+65->8202, 1:+74->8211, 2:+83->8220, 3:+92->8229
    //   8169: castore
    //   8170: wide
    //   8174: wide
    //   8178: wide
    //   8182: wide
    //   8186: wide
    //   8190: ixor
    //   8191: i2c
    //   8192: castore
    //   8193: wide
    //   8199: goto -6037 -> 2162
    //   8202: bipush 56
    //   8204: wide
    //   8208: goto -34 -> 8174
    //   8211: bipush 120
    //   8213: wide
    //   8217: goto -43 -> 8174
    //   8220: bipush 79
    //   8222: wide
    //   8226: goto -52 -> 8174
    //   8229: bipush 71
    //   8231: wide
    //   8235: goto -61 -> 8174
    //   8238: wide
    //   8242: wide
    //   8246: caload
    //   8247: wide
    //   8251: wide
    //   8255: iconst_5
    //   8256: irem
    //   8257: tableswitch	default:+31 -> 8288, 0:+65->8322, 1:+74->8331, 2:+83->8340, 3:+92->8349
    //   8289: castore
    //   8290: wide
    //   8294: wide
    //   8298: wide
    //   8302: wide
    //   8306: wide
    //   8310: ixor
    //   8311: i2c
    //   8312: castore
    //   8313: wide
    //   8319: goto -6105 -> 2214
    //   8322: bipush 56
    //   8324: wide
    //   8328: goto -34 -> 8294
    //   8331: bipush 120
    //   8333: wide
    //   8337: goto -43 -> 8294
    //   8340: bipush 79
    //   8342: wide
    //   8346: goto -52 -> 8294
    //   8349: bipush 71
    //   8351: wide
    //   8355: goto -61 -> 8294
    //   8358: wide
    //   8362: wide
    //   8366: caload
    //   8367: wide
    //   8371: wide
    //   8375: iconst_5
    //   8376: irem
    //   8377: tableswitch	default:+31 -> 8408, 0:+65->8442, 1:+74->8451, 2:+83->8460, 3:+92->8469
    //   8409: castore
    //   8410: wide
    //   8414: wide
    //   8418: wide
    //   8422: wide
    //   8426: wide
    //   8430: ixor
    //   8431: i2c
    //   8432: castore
    //   8433: wide
    //   8439: goto -6173 -> 2266
    //   8442: bipush 56
    //   8444: wide
    //   8448: goto -34 -> 8414
    //   8451: bipush 120
    //   8453: wide
    //   8457: goto -43 -> 8414
    //   8460: bipush 79
    //   8462: wide
    //   8466: goto -52 -> 8414
    //   8469: bipush 71
    //   8471: wide
    //   8475: goto -61 -> 8414
    //   8478: wide
    //   8482: wide
    //   8486: caload
    //   8487: wide
    //   8491: wide
    //   8495: iconst_5
    //   8496: irem
    //   8497: tableswitch	default:+31 -> 8528, 0:+65->8562, 1:+74->8571, 2:+83->8580, 3:+92->8589
    //   8529: castore
    //   8530: wide
    //   8534: wide
    //   8538: wide
    //   8542: wide
    //   8546: wide
    //   8550: ixor
    //   8551: i2c
    //   8552: castore
    //   8553: wide
    //   8559: goto -6241 -> 2318
    //   8562: bipush 56
    //   8564: wide
    //   8568: goto -34 -> 8534
    //   8571: bipush 120
    //   8573: wide
    //   8577: goto -43 -> 8534
    //   8580: bipush 79
    //   8582: wide
    //   8586: goto -52 -> 8534
    //   8589: bipush 71
    //   8591: wide
    //   8595: goto -61 -> 8534
    //   8598: wide
    //   8602: wide
    //   8606: caload
    //   8607: wide
    //   8611: wide
    //   8615: iconst_5
    //   8616: irem
    //   8617: tableswitch	default:+31 -> 8648, 0:+65->8682, 1:+74->8691, 2:+83->8700, 3:+92->8709
    //   8649: castore
    //   8650: wide
    //   8654: wide
    //   8658: wide
    //   8662: wide
    //   8666: wide
    //   8670: ixor
    //   8671: i2c
    //   8672: castore
    //   8673: wide
    //   8679: goto -6309 -> 2370
    //   8682: bipush 56
    //   8684: wide
    //   8688: goto -34 -> 8654
    //   8691: bipush 120
    //   8693: wide
    //   8697: goto -43 -> 8654
    //   8700: bipush 79
    //   8702: wide
    //   8706: goto -52 -> 8654
    //   8709: bipush 71
    //   8711: wide
    //   8715: goto -61 -> 8654
    //   8718: wide
    //   8722: wide
    //   8726: caload
    //   8727: wide
    //   8731: wide
    //   8735: iconst_5
    //   8736: irem
    //   8737: tableswitch	default:+31 -> 8768, 0:+65->8802, 1:+74->8811, 2:+83->8820, 3:+92->8829
    //   8769: castore
    //   8770: wide
    //   8774: wide
    //   8778: wide
    //   8782: wide
    //   8786: wide
    //   8790: ixor
    //   8791: i2c
    //   8792: castore
    //   8793: wide
    //   8799: goto -6377 -> 2422
    //   8802: bipush 56
    //   8804: wide
    //   8808: goto -34 -> 8774
    //   8811: bipush 120
    //   8813: wide
    //   8817: goto -43 -> 8774
    //   8820: bipush 79
    //   8822: wide
    //   8826: goto -52 -> 8774
    //   8829: bipush 71
    //   8831: wide
    //   8835: goto -61 -> 8774
    //   8838: wide
    //   8842: wide
    //   8846: caload
    //   8847: wide
    //   8851: wide
    //   8855: iconst_5
    //   8856: irem
    //   8857: tableswitch	default:+31 -> 8888, 0:+65->8922, 1:+74->8931, 2:+83->8940, 3:+92->8949
    //   8889: castore
    //   8890: wide
    //   8894: wide
    //   8898: wide
    //   8902: wide
    //   8906: wide
    //   8910: ixor
    //   8911: i2c
    //   8912: castore
    //   8913: wide
    //   8919: goto -6445 -> 2474
    //   8922: bipush 56
    //   8924: wide
    //   8928: goto -34 -> 8894
    //   8931: bipush 120
    //   8933: wide
    //   8937: goto -43 -> 8894
    //   8940: bipush 79
    //   8942: wide
    //   8946: goto -52 -> 8894
    //   8949: bipush 71
    //   8951: wide
    //   8955: goto -61 -> 8894
    //   8958: wide
    //   8962: wide
    //   8966: caload
    //   8967: wide
    //   8971: wide
    //   8975: iconst_5
    //   8976: irem
    //   8977: tableswitch	default:+31 -> 9008, 0:+65->9042, 1:+74->9051, 2:+83->9060, 3:+92->9069
    //   9009: castore
    //   9010: wide
    //   9014: wide
    //   9018: wide
    //   9022: wide
    //   9026: wide
    //   9030: ixor
    //   9031: i2c
    //   9032: castore
    //   9033: wide
    //   9039: goto -6513 -> 2526
    //   9042: bipush 56
    //   9044: wide
    //   9048: goto -34 -> 9014
    //   9051: bipush 120
    //   9053: wide
    //   9057: goto -43 -> 9014
    //   9060: bipush 79
    //   9062: wide
    //   9066: goto -52 -> 9014
    //   9069: bipush 71
    //   9071: wide
    //   9075: goto -61 -> 9014
    //   9078: wide
    //   9082: wide
    //   9086: caload
    //   9087: wide
    //   9091: wide
    //   9095: iconst_5
    //   9096: irem
    //   9097: tableswitch	default:+31 -> 9128, 0:+65->9162, 1:+74->9171, 2:+83->9180, 3:+92->9189
    //   9129: castore
    //   9130: wide
    //   9134: wide
    //   9138: wide
    //   9142: wide
    //   9146: wide
    //   9150: ixor
    //   9151: i2c
    //   9152: castore
    //   9153: wide
    //   9159: goto -6581 -> 2578
    //   9162: bipush 56
    //   9164: wide
    //   9168: goto -34 -> 9134
    //   9171: bipush 120
    //   9173: wide
    //   9177: goto -43 -> 9134
    //   9180: bipush 79
    //   9182: wide
    //   9186: goto -52 -> 9134
    //   9189: bipush 71
    //   9191: wide
    //   9195: goto -61 -> 9134
  }

  public eu(Context paramContext)
  {
    SharedPreferences localSharedPreferences = paramContext.getSharedPreferences(paramContext.getString(2131296258), 0);
    a = localSharedPreferences.getInt(z[3], a);
    b = localSharedPreferences.getInt(z[4], b);
    c = localSharedPreferences.getInt(z[5], c);
  }

  private static sz a(int paramInt, String paramString1, String paramString2, String paramString3, boolean paramBoolean)
  {
    boolean bool = DialogToastListActivity.f;
    sz localsz1;
    if (paramString1 != null)
    {
      localsz1 = new sz(new uz(paramString2, true, paramString1));
      localsz1.e = true;
      if (!bool);
    }
    else
    {
      localsz1 = new sz(paramString2, (byte[])null, null);
    }
    localsz1.a = 6;
    localsz1.m = paramInt;
    localsz1.c = paramString3;
    if (paramBoolean)
    {
      sz localsz2 = App.z.j(paramString2);
      if (localsz2 != null)
      {
        localsz1.i = localsz2.i;
        if (!bool);
      }
      else
      {
        localsz1.i = System.currentTimeMillis();
      }
      if (!bool);
    }
    else
    {
      localsz1.i = System.currentTimeMillis();
    }
    if (paramInt == 4)
    {
      c(paramString2, paramString3);
      if (!bool);
    }
    else if ((paramInt == 5) || (paramInt == 7))
    {
      d(paramString2, paramString3);
    }
    return localsz1;
  }

  private static sz a(String paramString1, String paramString2, String paramString3, String paramString4, Long paramLong)
  {
    sz localsz;
    if (paramString1 != null)
    {
      localsz = new sz(new uz(paramString2, true, paramString1));
      localsz.e = true;
      if (!DialogToastListActivity.f);
    }
    else
    {
      localsz = new sz(paramString2, (byte[])null, null);
    }
    localsz.b(paramString3);
    localsz.a = 6;
    localsz.m = 1L;
    localsz.c = paramString4;
    localsz.i = paramLong.longValue();
    return localsz;
  }

  public static sz a(String paramString1, String paramString2, Vector paramVector, int paramInt)
  {
    sz localsz = new sz(paramString1, paramString2, null);
    localsz.a = 6;
    localsz.m = paramInt;
    localsz.t = paramVector;
    return localsz;
  }

  public static void a()
  {
    App.z.a(a(c(), null, null, -2));
  }

  public static void a(int paramInt)
  {
    o9 localo9 = new o9();
    localo9.setPriority(1);
    localo9.start();
  }

  public static void a(String paramString, HashMap<String, String> paramHashMap)
  {
    boolean bool = DialogToastListActivity.f;
    g5.b(z[38] + Arrays.deepToString(paramHashMap.values().toArray()));
    StringBuffer localStringBuffer = new StringBuffer();
    Iterator localIterator = paramHashMap.values().iterator();
    do
    {
      if (!localIterator.hasNext())
        break;
      localStringBuffer.append((String)localIterator.next()).append(",");
    }
    while (!bool);
    if (localStringBuffer.length() > 0)
      localStringBuffer.delete(-1 + localStringBuffer.length(), localStringBuffer.length());
    SharedPreferences.Editor localEditor = q.edit();
    localEditor.putString(z[14] + paramString, localStringBuffer.toString());
    localEditor.commit();
  }

  public static void a(boolean paramBoolean)
  {
    g5.b(z[19]);
    h = false;
    j = false;
    i = false;
    f = false;
    a();
    if (k)
    {
      k = false;
      if (!DialogToastListActivity.f);
    }
    else
    {
      o.sendEmptyMessage(6);
      g5.b(z[18] + paramBoolean);
    }
    if (l)
      l = false;
  }

  static sz b(int paramInt, String paramString1, String paramString2, String paramString3, boolean paramBoolean)
  {
    return a(paramInt, paramString1, paramString2, paramString3, paramBoolean);
  }

  public static void b()
  {
    g5.b(z[56]);
    App.z.a(a(c(), null, null, -1));
  }

  public static void b(String paramString1, String paramString2)
  {
    g5.b(z[6] + paramString2);
    String str = q.getString(z[9] + paramString1, "");
    SharedPreferences.Editor localEditor = q.edit();
    g5.b(z[7] + str);
    if ((str.length() > 0) && (!str.contains(paramString2)))
    {
      str = str + "," + paramString2;
      localEditor.putString(z[9] + paramString1, str);
      if (!DialogToastListActivity.f);
    }
    else
    {
      localEditor.putString(z[9] + paramString1, paramString2);
    }
    g5.b(z[8] + str);
    localEditor.commit();
  }

  public static void b(String paramString, Vector paramVector)
  {
    boolean bool = DialogToastListActivity.f;
    g5.c(z[39] + Arrays.deepToString(paramVector.toArray()));
    StringBuffer localStringBuffer = new StringBuffer();
    Iterator localIterator = paramVector.iterator();
    do
    {
      if (!localIterator.hasNext())
        break;
      localStringBuffer.append(localIterator.next()).append(",");
    }
    while (!bool);
    if (localStringBuffer.length() > 0)
      localStringBuffer.delete(-1 + localStringBuffer.length(), localStringBuffer.length());
    SharedPreferences.Editor localEditor = q.edit();
    localEditor.putString(z[9] + paramString, localStringBuffer.toString());
    localEditor.commit();
  }

  public static String c()
  {
    return App.c() + "-" + App.E;
  }

  public static void c(String paramString)
  {
    boolean bool = DialogToastListActivity.f;
    g.clear();
    String[] arrayOfString = paramString.split(",");
    int i1 = arrayOfString.length;
    int i2 = 0;
    do
    {
      if (i2 >= i1)
        break;
      String str = arrayOfString[i2];
      g5.b(z[54] + str);
      g.add(str);
      i2++;
    }
    while (!bool);
  }

  public static void c(String paramString1, String paramString2)
  {
    String str = q.getString(z[14] + paramString1, "");
    g5.b(z[35] + paramString1 + z[16] + paramString2 + z[33] + str);
    if (!str.contains(paramString2))
    {
      if (str.length() == 0)
      {
        if (DialogToastListActivity.f)
          str = paramString2;
      }
      else
        paramString2 = str + "," + paramString2;
      g5.b(z[34] + paramString2);
      SharedPreferences.Editor localEditor = q.edit();
      localEditor.putString(z[14] + paramString1, paramString2);
      localEditor.commit();
    }
  }

  public static void c(String paramString, Vector paramVector)
  {
    boolean bool = DialogToastListActivity.f;
    String str1 = q.getString(z[9] + paramString, "");
    g5.b(z[21] + Arrays.deepToString(paramVector.toArray()) + z[22] + str1);
    StringBuffer localStringBuffer = new StringBuffer();
    int i2;
    String str2;
    int i3;
    label140: int i4;
    if (str1.length() > 0)
    {
      String[] arrayOfString = str1.split(",");
      int i1 = arrayOfString.length;
      i2 = 0;
      if (i2 < i1)
      {
        str2 = arrayOfString[i2];
        Iterator localIterator = paramVector.iterator();
        i3 = 0;
        if (!localIterator.hasNext())
          break label384;
        if (!((String)localIterator.next()).equals(str2))
          break label377;
        i4 = 1;
        label171: if (!bool)
          break label370;
      }
    }
    while (true)
    {
      if (i4 == 0)
        localStringBuffer.append(str2).append(",");
      int i5 = i2 + 1;
      if (bool)
      {
        if (localStringBuffer.length() > 0)
          localStringBuffer.delete(-1 + localStringBuffer.length(), localStringBuffer.length());
        SharedPreferences.Editor localEditor = q.edit();
        if (localStringBuffer.length() > 0)
        {
          localEditor.putString(z[9] + paramString, localStringBuffer.toString());
          if (!bool);
        }
        else
        {
          localEditor.putString(z[9] + paramString, "");
          localEditor.remove(z[9] + paramString);
        }
        localEditor.commit();
        return;
      }
      i2 = i5;
      break;
      label370: i3 = i4;
      break label140;
      label377: i4 = i3;
      break label171;
      label384: i4 = i3;
    }
  }

  public static void d()
  {
    boolean bool = DialogToastListActivity.f;
    g5.b(z[36]);
    Iterator localIterator = m.values().iterator();
    do
    {
      if (!localIterator.hasNext())
        break;
      String str = (String)localIterator.next();
      App.z.g(str);
    }
    while (!bool);
  }

  public static void d(String paramString1, String paramString2)
  {
    String str = q.getString(z[14] + paramString1, "");
    g5.b(z[15] + str + "[" + paramString1 + z[16] + paramString2 + "]");
    if (str.contains(paramString2))
    {
      if (str.lastIndexOf(paramString2) + paramString2.length() == str.length())
      {
        str = str.replace(paramString2, "");
        if (!DialogToastListActivity.f);
      }
      else
      {
        str = str.replace(paramString2 + ",", "");
      }
      g5.b(z[17] + str);
      SharedPreferences.Editor localEditor = q.edit();
      localEditor.putString(z[14] + paramString1, str);
      localEditor.commit();
    }
  }

  public static sz e(String paramString)
  {
    sz localsz = new sz(paramString, (byte[])null, null);
    localsz.a = 6;
    localsz.m = 8L;
    return localsz;
  }

  public static boolean f(String paramString)
  {
    return paramString.contains("-");
  }

  public static String g(String paramString)
  {
    return App.c() + "-" + paramString + z[25];
  }

  public static Vector h(String paramString)
  {
    boolean bool = DialogToastListActivity.f;
    String str1 = q.getString(z[9] + paramString, "");
    g5.b(z[50] + str1);
    String[] arrayOfString = str1.split(",");
    Vector localVector = new Vector();
    int i1 = arrayOfString.length;
    int i2 = 0;
    do
    {
      if (i2 >= i1)
        break;
      String str2 = arrayOfString[i2];
      if (str2.length() > 0)
        localVector.add(str2);
      i2++;
    }
    while (!bool);
    return localVector;
  }

  public static HashMap<String, String> i(String paramString)
  {
    boolean bool = DialogToastListActivity.f;
    String[] arrayOfString = q.getString(z[14] + paramString, "").split(",");
    HashMap localHashMap = new HashMap();
    int i1 = arrayOfString.length;
    int i2 = 0;
    do
    {
      if (i2 >= i1)
        break;
      String str = arrayOfString[i2];
      if (str.length() > 0)
        localHashMap.put(str, str);
      i2++;
    }
    while (!bool);
    return localHashMap;
  }

  public static String j(String paramString)
  {
    boolean bool = DialogToastListActivity.f;
    ArrayList localArrayList1 = new ArrayList();
    Iterator localIterator1 = i(paramString).values().iterator();
    do
    {
      if (!localIterator1.hasNext())
        break;
      String str3 = (String)localIterator1.next();
      if ((str3.length() > 0) && (!str3.contains(App.c())))
      {
        zq localzq3 = App.w.a(str3, null);
        if (!localArrayList1.contains(localzq3))
          localArrayList1.add(localzq3);
      }
    }
    while (!bool);
    ArrayList localArrayList2 = new ArrayList();
    ArrayList localArrayList3 = new ArrayList();
    Iterator localIterator2 = localArrayList1.iterator();
    do
    {
      if (!localIterator2.hasNext())
        break;
      zq localzq2 = (zq)localIterator2.next();
      String str2 = localzq2.d();
      if (str2 != null)
        if (str2.equals(localzq2.a()))
        {
          localArrayList3.add(str2);
          if (!bool);
        }
        else
        {
          localArrayList2.add(str2);
        }
    }
    while (!bool);
    Collections.sort(localArrayList2);
    Collections.sort(localArrayList3);
    localArrayList2.addAll(localArrayList3);
    zq localzq1 = App.w.c(paramString);
    if ((localzq1 != null) && (localzq1.k))
      localArrayList2.add(App.Mb.getString(2131296866));
    StringBuilder localStringBuilder = new StringBuilder();
    Iterator localIterator3 = localArrayList2.iterator();
    do
    {
      if (!localIterator3.hasNext())
        break;
      String str1 = (String)localIterator3.next();
      if (localStringBuilder.length() > 0)
        localStringBuilder.append(z[0]);
      localStringBuilder.append(str1);
    }
    while (!bool);
    return localStringBuilder.toString();
  }

  public static void k(String paramString)
  {
    SharedPreferences.Editor localEditor = q.edit();
    localEditor.putString(z[14] + paramString, "");
    localEditor.remove(z[14] + paramString);
    localEditor.commit();
  }

  public hu a(String paramString1, String paramString2)
  {
    gu localgu = (gu)e.get(paramString1);
    if ((hu)localgu.b.get(paramString2) != null);
    for (hu localhu = (hu)localgu.b.get(paramString2); ; localhu = (hu)localgu.b.get(paramString2))
    {
      return localhu;
      g5.b(z[2] + paramString2);
      localgu.a(paramString2, true);
    }
  }

  public void a(int paramInt, Hashtable paramHashtable)
  {
    boolean bool = DialogToastListActivity.f;
    g5.b(z[29]);
    String str = App.Mb.getString(2131296258);
    SharedPreferences.Editor localEditor = App.Mb.getSharedPreferences(str, 0).edit();
    Iterator localIterator = paramHashtable.keySet().iterator();
    do
    {
      if (!localIterator.hasNext())
        break;
      Object localObject = localIterator.next();
      g5.b(z[26] + localObject + ":" + paramHashtable.get(localObject));
      if (localObject.toString().contains(z[28]))
      {
        c = Integer.parseInt(paramHashtable.get(localObject).toString());
        localEditor.putInt(z[5], c);
      }
      if (localObject.toString().contains(z[31]))
      {
        a = Integer.parseInt(paramHashtable.get(localObject).toString());
        localEditor.putInt(z[3], a);
      }
      if (localObject.toString().contains(z[32]))
      {
        b = -1 + Integer.parseInt(paramHashtable.get(localObject).toString());
        localEditor.putInt(z[4], b);
      }
    }
    while (!bool);
    localEditor.putLong(z[27], System.currentTimeMillis());
    if (!localEditor.commit())
      g5.d(z[30]);
    if (d)
    {
      GroupChatInfo.g();
      d = false;
    }
  }

  public void a(hq paramhq)
  {
    try
    {
      n.registerObserver(paramhq);
      g5.b(z[12] + Process.myPid());
      return;
    }
    catch (IllegalStateException localIllegalStateException)
    {
      while (true)
        g5.b(z[13] + Process.myPid() + localIllegalStateException);
    }
  }

  public void a(String paramString)
  {
    g5.b(z[20] + paramString);
  }

  public void a(String paramString1, String paramString2)
  {
    long l1 = 1000L * Long.parseLong(paramString1.substring(1 + paramString1.indexOf("-"), paramString1.lastIndexOf("@")));
    g5.c(z[49] + paramString1 + "/" + paramString2 + "/" + l1);
    gu localgu = new gu(paramString1);
    e.put(paramString1, localgu);
    String str = App.c() + "-" + paramString2 + z[25];
    sz localsz = App.z.j(str);
    App.w.a(App.w.a(str, null), paramString1, paramString2, "" + l1);
    if ((localsz != null) && (localsz.t != null));
    for (ju localju = new ju(paramString1, null, (Vector)localsz.t, 14); ; localju = new ju(paramString1, null, h(g(paramString2)), 14))
    {
      if (Conversations.a())
      {
        App.z.h(str);
        Conversations.b().a(str, paramString1, paramString2, new fu(this, str));
        if (!DialogToastListActivity.f);
      }
      else
      {
        App.m(str);
      }
      Message localMessage = o.obtainMessage(0, a(null, paramString1, paramString2, App.c(), Long.valueOf(l1)));
      o.sendMessage(localMessage);
      App.b(localju);
      return;
    }
  }

  public void a(String paramString1, String paramString2, String paramString3)
  {
    boolean bool = DialogToastListActivity.f;
    g5.b(z[10] + paramString3 + z[11] + paramString2);
    if (App.c().equals(paramString3.substring(0, paramString3.lastIndexOf("@"))))
    {
      zq localzq = App.w.c(paramString2);
      if ((localzq == null) || (localzq.k))
        break label191;
      localzq.k = true;
      App.w.c(localzq);
      App.Ib.sendEmptyMessage(0);
      App.l(paramString2);
      App.c(paramString2, false);
      App.a(paramString2, localzq.p, 2);
    }
    label191: for (int i1 = 1; ; i1 = 0)
    {
      if (bool)
        i1 = 1;
      if (i1 != 0)
      {
        d(paramString2).a(paramString3, false);
        Message localMessage = o.obtainMessage(1, a(4, paramString1, paramString2, paramString3, false));
        o.sendMessage(localMessage);
        if (!bool);
      }
      else
      {
        App.a(paramString1, paramString2);
      }
      return;
    }
  }

  public void a(String paramString1, String paramString2, String paramString3, String paramString4)
  {
    g5.b(z[24] + paramString3 + z[11] + paramString2 + z[23] + paramString4);
    Handler localHandler;
    if ((!App.c().equals(paramString3.substring(0, paramString3.lastIndexOf("@")))) || (paramString4 != null))
    {
      d(paramString2).b(paramString3, false);
      localHandler = o;
      if (paramString4 != null)
        break label210;
    }
    label210: for (int i1 = 5; ; i1 = 7)
    {
      Message localMessage = localHandler.obtainMessage(1, a(i1, paramString1, paramString2, paramString3, false));
      o.sendMessage(localMessage);
      if ((App.c().equals(paramString3.substring(0, paramString3.lastIndexOf("@")))) && (paramString4 != null))
      {
        zq localzq = App.w.c(paramString2);
        if ((localzq != null) && (localzq.k))
        {
          localzq.k = false;
          App.w.c(localzq);
          App.Ib.sendEmptyMessage(0);
        }
      }
      if (DialogToastListActivity.f)
        App.a(paramString1, paramString2);
      return;
    }
  }

  public void a(String paramString1, String paramString2, String paramString3, String paramString4, int paramInt)
  {
    boolean bool = DialogToastListActivity.f;
    g5.c(z[62] + paramString4 + z[11] + paramString2 + z[63] + 1000L * paramInt);
    zq localzq = App.w.c(paramString2);
    g5.b(z[60] + q.getString(new StringBuilder().append(z[14]).append(paramString2).toString(), ""));
    if ((q.getString(z[14] + paramString2, "").length() > 0) || ((localzq != null) && (localzq.h != null) && (localzq.h.length() > 0)))
    {
      if ((localzq == null) || (!localzq.b().equals(paramString4)))
      {
        App.w.a(paramString2, paramString3, paramString4, null);
        Message localMessage1 = o.obtainMessage(3, a(paramString1, paramString2, paramString4, paramString3, Long.valueOf(1000L * paramInt)));
        o.sendMessage(localMessage1);
        if (!bool);
      }
      else
      {
        g5.b(z[59]);
        App.c(a(paramString1, paramString2, paramString4, paramString3, Long.valueOf(1000L * paramInt)));
        if (!bool);
      }
    }
    else
    {
      gu localgu = new gu(paramString2);
      gp.b(paramString2, paramString4, "" + 1000L * paramInt);
      localgu.a(paramString2.substring(0, paramString2.indexOf("-")) + z[58], false);
      e.put(paramString2, localgu);
      Message localMessage2 = o.obtainMessage(3, a(paramString1, paramString2, paramString4, paramString3, Long.valueOf(1000L * paramInt)));
      o.sendMessage(localMessage2);
      Message localMessage3 = o.obtainMessage(1, a(4, null, paramString2, paramString2.substring(0, paramString2.indexOf("-")) + z[58], false));
      o.sendMessage(localMessage3);
      g5.b(z[61] + paramString2);
      App.c(paramString2, false);
    }
  }

  public void a(String paramString1, String paramString2, String paramString3, String paramString4, int paramInt1, int paramInt2)
  {
    g5.b(z[55] + paramString1 + "/" + paramString3 + "/" + paramString2 + "/" + new Date(1000L * paramInt2));
    qp localqp = App.w;
    if (hb.a(paramString3))
      paramString3 = "-";
    localqp.b(paramString1, paramString2, paramString3, "" + 1000L * paramInt2);
    Message localMessage = o.obtainMessage(5, paramString1);
    o.sendMessage(localMessage);
    App.S.b(paramString1);
  }

  public void a(String paramString, Vector paramVector)
  {
    g5.b(z[40] + paramString + "/" + Arrays.deepToString(paramVector.toArray()));
    gu localgu = (gu)e.get(paramString);
    if (localgu == null)
    {
      localgu = new gu(paramString);
      e.put(paramString, localgu);
    }
    localgu.a(paramVector);
    Message localMessage = o.obtainMessage(4, paramString);
    o.sendMessage(localMessage);
  }

  public void a(String paramString, Vector paramVector, Hashtable paramHashtable)
  {
    g5.b(z[1] + paramString + "/" + Arrays.deepToString(paramVector.toArray()));
    ju localju = (ju)p.remove(paramString);
    if (localju != null)
      ju.a(localju).cancel();
    if ((paramHashtable != null) && (paramHashtable.size() > 0))
    {
      Message localMessage = o.obtainMessage(11, paramString);
      localju.i = paramHashtable;
      localMessage.obj = localju;
      o.sendMessage(localMessage);
    }
    c(paramString, paramVector);
  }

  public void a(Vector paramVector)
  {
    g5.b(z[57] + Arrays.deepToString(paramVector.toArray()));
  }

  public void b(String paramString)
  {
    g5.b(z[37] + paramString);
    ju localju = (ju)p.remove(paramString);
    if (localju != null)
      ju.a(localju).cancel();
    Message localMessage = o.obtainMessage(2, paramString);
    o.sendMessage(localMessage);
    n5.b(paramString);
    k(paramString);
    zq.b(paramString).delete();
    zq.a(paramString).delete();
  }

  public void b(String paramString1, String paramString2, String paramString3, String paramString4, int paramInt1, int paramInt2)
  {
    g5.b(z[45] + paramString1 + z[44] + paramString2 + z[42] + paramString4 + z[47] + paramString3 + z[48] + paramInt1 + z[41] + 1000L * paramInt2);
    zq localzq = App.w.a(paramString1, null);
    localzq.h = paramString3;
    localzq.j = ("" + 1000L * paramInt2);
    localzq.m = paramString2;
    App.w.c(localzq);
    if (App.z.a(paramString1, paramString3, 1000L * paramInt1))
    {
      g5.b(z[43] + paramString3);
      Message localMessage = o.obtainMessage(8, a(null, paramString1, paramString3, paramString4, Long.valueOf(1000L * paramInt1)));
      o.sendMessage(localMessage);
    }
    if ((j) || (k))
    {
      g5.b(z[46] + paramString1);
      m.remove(paramString1);
    }
    App.c(paramString1, true);
  }

  public void b(String paramString, Vector paramVector, Hashtable paramHashtable)
  {
    g5.b(z[53] + paramString);
    ju localju = (ju)p.remove(paramString);
    if (localju != null)
      ju.a(localju).cancel();
    if ((paramHashtable != null) && (paramHashtable.size() > 0))
    {
      Message localMessage2 = o.obtainMessage(15, paramString);
      localju.i = paramHashtable;
      localMessage2.obj = localju;
      o.sendMessage(localMessage2);
      if (!DialogToastListActivity.f);
    }
    else
    {
      Message localMessage1 = o.obtainMessage(16, paramString);
      o.sendMessage(localMessage1);
    }
  }

  public void b(Vector paramVector)
  {
    boolean bool = DialogToastListActivity.f;
    g5.b(z[52] + Arrays.deepToString(paramVector.toArray()));
    f = false;
    h = false;
    i = false;
    if ((j) || (k) || (l))
    {
      Iterator localIterator = m.values().iterator();
      do
      {
        if (!localIterator.hasNext())
          break;
        String str = (String)localIterator.next();
        Message localMessage2 = o.obtainMessage(12, str);
        o.sendMessage(localMessage2);
      }
      while (!bool);
      if (k)
      {
        g5.b(z[51]);
        Message localMessage1 = o.obtainMessage(7, paramVector);
        o.sendMessage(localMessage1);
      }
      if (l)
        l = false;
      k = false;
      j = false;
      App.Ib.sendEmptyMessage(0);
    }
    App.Ib.sendEmptyMessage(0);
    App.s();
  }

  public gu d(String paramString)
  {
    gu localgu = (gu)e.get(paramString);
    if (localgu == null)
    {
      localgu = new gu(paramString);
      e.put(paramString, localgu);
    }
    return localgu;
  }
}