package com.whatsapp;

import android.app.Application;
import android.content.pm.PackageInfo;
import android.content.pm.PackageManager;
import android.content.pm.PackageManager.NameNotFoundException;
import android.content.pm.Signature;
import android.os.Build;
import android.os.Build.VERSION;
import android.os.Debug;
import android.provider.Settings.Secure;
import android.telephony.TelephonyManager;
import java.io.IOException;
import java.io.InputStream;
import java.security.MessageDigest;
import java.security.NoSuchAlgorithmException;
import java.util.Locale;
import java.util.zip.ZipFile;

public class mh
{
  private static String a;
  private static boolean b;
  private static boolean c;
  private static boolean d;
  private static String e;
  private static boolean f;
  private static final String[] z;

  // ERROR //
  static
  {
    // Byte code:
    //   0: bipush 69
    //   2: anewarray 18	java/lang/String
    //   5: astore_0
    //   6: ldc 20
    //   8: invokevirtual 24	java/lang/String:toCharArray	()[C
    //   11: astore_1
    //   12: aload_1
    //   13: arraylength
    //   14: istore_2
    //   15: iconst_0
    //   16: istore_3
    //   17: iload_2
    //   18: iload_3
    //   19: if_icmpgt +2877 -> 2896
    //   22: aload_0
    //   23: iconst_0
    //   24: new 18	java/lang/String
    //   27: dup
    //   28: aload_1
    //   29: invokespecial 28	java/lang/String:<init>	([C)V
    //   32: invokevirtual 32	java/lang/String:intern	()Ljava/lang/String;
    //   35: aastore
    //   36: ldc 34
    //   38: invokevirtual 24	java/lang/String:toCharArray	()[C
    //   41: astore 6
    //   43: aload 6
    //   45: arraylength
    //   46: istore 7
    //   48: iconst_0
    //   49: istore 8
    //   51: iload 7
    //   53: iload 8
    //   55: if_icmpgt +2928 -> 2983
    //   58: aload_0
    //   59: iconst_1
    //   60: new 18	java/lang/String
    //   63: dup
    //   64: aload 6
    //   66: invokespecial 28	java/lang/String:<init>	([C)V
    //   69: invokevirtual 32	java/lang/String:intern	()Ljava/lang/String;
    //   72: aastore
    //   73: ldc 36
    //   75: invokevirtual 24	java/lang/String:toCharArray	()[C
    //   78: astore 11
    //   80: aload 11
    //   82: arraylength
    //   83: istore 12
    //   85: iconst_0
    //   86: istore 13
    //   88: iload 12
    //   90: iload 13
    //   92: if_icmpgt +2981 -> 3073
    //   95: aload_0
    //   96: iconst_2
    //   97: new 18	java/lang/String
    //   100: dup
    //   101: aload 11
    //   103: invokespecial 28	java/lang/String:<init>	([C)V
    //   106: invokevirtual 32	java/lang/String:intern	()Ljava/lang/String;
    //   109: aastore
    //   110: ldc 38
    //   112: invokevirtual 24	java/lang/String:toCharArray	()[C
    //   115: astore 16
    //   117: aload 16
    //   119: arraylength
    //   120: istore 17
    //   122: iconst_0
    //   123: istore 18
    //   125: iload 17
    //   127: iload 18
    //   129: if_icmpgt +3036 -> 3165
    //   132: aload_0
    //   133: iconst_3
    //   134: new 18	java/lang/String
    //   137: dup
    //   138: aload 16
    //   140: invokespecial 28	java/lang/String:<init>	([C)V
    //   143: invokevirtual 32	java/lang/String:intern	()Ljava/lang/String;
    //   146: aastore
    //   147: ldc 40
    //   149: invokevirtual 24	java/lang/String:toCharArray	()[C
    //   152: astore 21
    //   154: aload 21
    //   156: arraylength
    //   157: istore 22
    //   159: iconst_0
    //   160: istore 23
    //   162: iload 22
    //   164: iload 23
    //   166: if_icmpgt +3091 -> 3257
    //   169: aload_0
    //   170: iconst_4
    //   171: new 18	java/lang/String
    //   174: dup
    //   175: aload 21
    //   177: invokespecial 28	java/lang/String:<init>	([C)V
    //   180: invokevirtual 32	java/lang/String:intern	()Ljava/lang/String;
    //   183: aastore
    //   184: ldc 42
    //   186: invokevirtual 24	java/lang/String:toCharArray	()[C
    //   189: astore 26
    //   191: aload 26
    //   193: arraylength
    //   194: istore 27
    //   196: iconst_0
    //   197: istore 28
    //   199: iload 27
    //   201: iload 28
    //   203: if_icmpgt +3146 -> 3349
    //   206: aload_0
    //   207: iconst_5
    //   208: new 18	java/lang/String
    //   211: dup
    //   212: aload 26
    //   214: invokespecial 28	java/lang/String:<init>	([C)V
    //   217: invokevirtual 32	java/lang/String:intern	()Ljava/lang/String;
    //   220: aastore
    //   221: ldc 44
    //   223: invokevirtual 24	java/lang/String:toCharArray	()[C
    //   226: astore 31
    //   228: aload 31
    //   230: arraylength
    //   231: istore 32
    //   233: iconst_0
    //   234: istore 33
    //   236: iload 32
    //   238: iload 33
    //   240: if_icmpgt +3201 -> 3441
    //   243: aload_0
    //   244: bipush 6
    //   246: new 18	java/lang/String
    //   249: dup
    //   250: aload 31
    //   252: invokespecial 28	java/lang/String:<init>	([C)V
    //   255: invokevirtual 32	java/lang/String:intern	()Ljava/lang/String;
    //   258: aastore
    //   259: ldc 46
    //   261: invokevirtual 24	java/lang/String:toCharArray	()[C
    //   264: astore 36
    //   266: aload 36
    //   268: arraylength
    //   269: istore 37
    //   271: iconst_0
    //   272: istore 38
    //   274: iload 37
    //   276: iload 38
    //   278: if_icmpgt +3255 -> 3533
    //   281: aload_0
    //   282: bipush 7
    //   284: new 18	java/lang/String
    //   287: dup
    //   288: aload 36
    //   290: invokespecial 28	java/lang/String:<init>	([C)V
    //   293: invokevirtual 32	java/lang/String:intern	()Ljava/lang/String;
    //   296: aastore
    //   297: ldc 48
    //   299: invokevirtual 24	java/lang/String:toCharArray	()[C
    //   302: astore 41
    //   304: aload 41
    //   306: arraylength
    //   307: istore 42
    //   309: iconst_0
    //   310: istore 43
    //   312: iload 42
    //   314: iload 43
    //   316: if_icmpgt +3309 -> 3625
    //   319: aload_0
    //   320: bipush 8
    //   322: new 18	java/lang/String
    //   325: dup
    //   326: aload 41
    //   328: invokespecial 28	java/lang/String:<init>	([C)V
    //   331: invokevirtual 32	java/lang/String:intern	()Ljava/lang/String;
    //   334: aastore
    //   335: ldc 50
    //   337: invokevirtual 24	java/lang/String:toCharArray	()[C
    //   340: astore 46
    //   342: aload 46
    //   344: arraylength
    //   345: istore 47
    //   347: iconst_0
    //   348: istore 48
    //   350: iload 47
    //   352: iload 48
    //   354: if_icmpgt +3363 -> 3717
    //   357: aload_0
    //   358: bipush 9
    //   360: new 18	java/lang/String
    //   363: dup
    //   364: aload 46
    //   366: invokespecial 28	java/lang/String:<init>	([C)V
    //   369: invokevirtual 32	java/lang/String:intern	()Ljava/lang/String;
    //   372: aastore
    //   373: ldc 52
    //   375: invokevirtual 24	java/lang/String:toCharArray	()[C
    //   378: astore 51
    //   380: aload 51
    //   382: arraylength
    //   383: istore 52
    //   385: iconst_0
    //   386: istore 53
    //   388: iload 52
    //   390: iload 53
    //   392: if_icmpgt +3417 -> 3809
    //   395: aload_0
    //   396: bipush 10
    //   398: new 18	java/lang/String
    //   401: dup
    //   402: aload 51
    //   404: invokespecial 28	java/lang/String:<init>	([C)V
    //   407: invokevirtual 32	java/lang/String:intern	()Ljava/lang/String;
    //   410: aastore
    //   411: ldc 54
    //   413: invokevirtual 24	java/lang/String:toCharArray	()[C
    //   416: astore 56
    //   418: aload 56
    //   420: arraylength
    //   421: istore 57
    //   423: iconst_0
    //   424: istore 58
    //   426: iload 57
    //   428: iload 58
    //   430: if_icmpgt +3471 -> 3901
    //   433: aload_0
    //   434: bipush 11
    //   436: new 18	java/lang/String
    //   439: dup
    //   440: aload 56
    //   442: invokespecial 28	java/lang/String:<init>	([C)V
    //   445: invokevirtual 32	java/lang/String:intern	()Ljava/lang/String;
    //   448: aastore
    //   449: ldc 56
    //   451: invokevirtual 24	java/lang/String:toCharArray	()[C
    //   454: astore 61
    //   456: aload 61
    //   458: arraylength
    //   459: istore 62
    //   461: iconst_0
    //   462: istore 63
    //   464: iload 62
    //   466: iload 63
    //   468: if_icmpgt +3525 -> 3993
    //   471: aload_0
    //   472: bipush 12
    //   474: new 18	java/lang/String
    //   477: dup
    //   478: aload 61
    //   480: invokespecial 28	java/lang/String:<init>	([C)V
    //   483: invokevirtual 32	java/lang/String:intern	()Ljava/lang/String;
    //   486: aastore
    //   487: ldc 58
    //   489: invokevirtual 24	java/lang/String:toCharArray	()[C
    //   492: astore 66
    //   494: aload 66
    //   496: arraylength
    //   497: istore 67
    //   499: iconst_0
    //   500: istore 68
    //   502: iload 67
    //   504: iload 68
    //   506: if_icmpgt +3579 -> 4085
    //   509: aload_0
    //   510: bipush 13
    //   512: new 18	java/lang/String
    //   515: dup
    //   516: aload 66
    //   518: invokespecial 28	java/lang/String:<init>	([C)V
    //   521: invokevirtual 32	java/lang/String:intern	()Ljava/lang/String;
    //   524: aastore
    //   525: ldc 60
    //   527: invokevirtual 24	java/lang/String:toCharArray	()[C
    //   530: astore 71
    //   532: aload 71
    //   534: arraylength
    //   535: istore 72
    //   537: iconst_0
    //   538: istore 73
    //   540: iload 72
    //   542: iload 73
    //   544: if_icmpgt +3633 -> 4177
    //   547: aload_0
    //   548: bipush 14
    //   550: new 18	java/lang/String
    //   553: dup
    //   554: aload 71
    //   556: invokespecial 28	java/lang/String:<init>	([C)V
    //   559: invokevirtual 32	java/lang/String:intern	()Ljava/lang/String;
    //   562: aastore
    //   563: ldc 62
    //   565: invokevirtual 24	java/lang/String:toCharArray	()[C
    //   568: astore 76
    //   570: aload 76
    //   572: arraylength
    //   573: istore 77
    //   575: iconst_0
    //   576: istore 78
    //   578: iload 77
    //   580: iload 78
    //   582: if_icmpgt +3687 -> 4269
    //   585: aload_0
    //   586: bipush 15
    //   588: new 18	java/lang/String
    //   591: dup
    //   592: aload 76
    //   594: invokespecial 28	java/lang/String:<init>	([C)V
    //   597: invokevirtual 32	java/lang/String:intern	()Ljava/lang/String;
    //   600: aastore
    //   601: ldc 64
    //   603: invokevirtual 24	java/lang/String:toCharArray	()[C
    //   606: astore 81
    //   608: aload 81
    //   610: arraylength
    //   611: istore 82
    //   613: iconst_0
    //   614: istore 83
    //   616: iload 82
    //   618: iload 83
    //   620: if_icmpgt +3741 -> 4361
    //   623: aload_0
    //   624: bipush 16
    //   626: new 18	java/lang/String
    //   629: dup
    //   630: aload 81
    //   632: invokespecial 28	java/lang/String:<init>	([C)V
    //   635: invokevirtual 32	java/lang/String:intern	()Ljava/lang/String;
    //   638: aastore
    //   639: ldc 66
    //   641: invokevirtual 24	java/lang/String:toCharArray	()[C
    //   644: astore 86
    //   646: aload 86
    //   648: arraylength
    //   649: istore 87
    //   651: iconst_0
    //   652: istore 88
    //   654: iload 87
    //   656: iload 88
    //   658: if_icmpgt +3795 -> 4453
    //   661: aload_0
    //   662: bipush 17
    //   664: new 18	java/lang/String
    //   667: dup
    //   668: aload 86
    //   670: invokespecial 28	java/lang/String:<init>	([C)V
    //   673: invokevirtual 32	java/lang/String:intern	()Ljava/lang/String;
    //   676: aastore
    //   677: ldc 68
    //   679: invokevirtual 24	java/lang/String:toCharArray	()[C
    //   682: astore 91
    //   684: aload 91
    //   686: arraylength
    //   687: istore 92
    //   689: iconst_0
    //   690: istore 93
    //   692: iload 92
    //   694: iload 93
    //   696: if_icmpgt +3849 -> 4545
    //   699: aload_0
    //   700: bipush 18
    //   702: new 18	java/lang/String
    //   705: dup
    //   706: aload 91
    //   708: invokespecial 28	java/lang/String:<init>	([C)V
    //   711: invokevirtual 32	java/lang/String:intern	()Ljava/lang/String;
    //   714: aastore
    //   715: ldc 70
    //   717: invokevirtual 24	java/lang/String:toCharArray	()[C
    //   720: astore 96
    //   722: aload 96
    //   724: arraylength
    //   725: istore 97
    //   727: iconst_0
    //   728: istore 98
    //   730: iload 97
    //   732: iload 98
    //   734: if_icmpgt +3903 -> 4637
    //   737: aload_0
    //   738: bipush 19
    //   740: new 18	java/lang/String
    //   743: dup
    //   744: aload 96
    //   746: invokespecial 28	java/lang/String:<init>	([C)V
    //   749: invokevirtual 32	java/lang/String:intern	()Ljava/lang/String;
    //   752: aastore
    //   753: ldc 72
    //   755: invokevirtual 24	java/lang/String:toCharArray	()[C
    //   758: astore 101
    //   760: aload 101
    //   762: arraylength
    //   763: istore 102
    //   765: iconst_0
    //   766: istore 103
    //   768: iload 102
    //   770: iload 103
    //   772: if_icmpgt +3957 -> 4729
    //   775: aload_0
    //   776: bipush 20
    //   778: new 18	java/lang/String
    //   781: dup
    //   782: aload 101
    //   784: invokespecial 28	java/lang/String:<init>	([C)V
    //   787: invokevirtual 32	java/lang/String:intern	()Ljava/lang/String;
    //   790: aastore
    //   791: ldc 74
    //   793: invokevirtual 24	java/lang/String:toCharArray	()[C
    //   796: astore 106
    //   798: aload 106
    //   800: arraylength
    //   801: istore 107
    //   803: iconst_0
    //   804: istore 108
    //   806: iload 107
    //   808: iload 108
    //   810: if_icmpgt +4011 -> 4821
    //   813: aload_0
    //   814: bipush 21
    //   816: new 18	java/lang/String
    //   819: dup
    //   820: aload 106
    //   822: invokespecial 28	java/lang/String:<init>	([C)V
    //   825: invokevirtual 32	java/lang/String:intern	()Ljava/lang/String;
    //   828: aastore
    //   829: ldc 76
    //   831: invokevirtual 24	java/lang/String:toCharArray	()[C
    //   834: astore 111
    //   836: aload 111
    //   838: arraylength
    //   839: istore 112
    //   841: iconst_0
    //   842: istore 113
    //   844: iload 112
    //   846: iload 113
    //   848: if_icmpgt +4065 -> 4913
    //   851: aload_0
    //   852: bipush 22
    //   854: new 18	java/lang/String
    //   857: dup
    //   858: aload 111
    //   860: invokespecial 28	java/lang/String:<init>	([C)V
    //   863: invokevirtual 32	java/lang/String:intern	()Ljava/lang/String;
    //   866: aastore
    //   867: ldc 78
    //   869: invokevirtual 24	java/lang/String:toCharArray	()[C
    //   872: astore 116
    //   874: aload 116
    //   876: arraylength
    //   877: istore 117
    //   879: iconst_0
    //   880: istore 118
    //   882: iload 117
    //   884: iload 118
    //   886: if_icmpgt +4119 -> 5005
    //   889: aload_0
    //   890: bipush 23
    //   892: new 18	java/lang/String
    //   895: dup
    //   896: aload 116
    //   898: invokespecial 28	java/lang/String:<init>	([C)V
    //   901: invokevirtual 32	java/lang/String:intern	()Ljava/lang/String;
    //   904: aastore
    //   905: ldc 80
    //   907: invokevirtual 24	java/lang/String:toCharArray	()[C
    //   910: astore 121
    //   912: aload 121
    //   914: arraylength
    //   915: istore 122
    //   917: iconst_0
    //   918: istore 123
    //   920: iload 122
    //   922: iload 123
    //   924: if_icmpgt +4173 -> 5097
    //   927: aload_0
    //   928: bipush 24
    //   930: new 18	java/lang/String
    //   933: dup
    //   934: aload 121
    //   936: invokespecial 28	java/lang/String:<init>	([C)V
    //   939: invokevirtual 32	java/lang/String:intern	()Ljava/lang/String;
    //   942: aastore
    //   943: ldc 82
    //   945: invokevirtual 24	java/lang/String:toCharArray	()[C
    //   948: astore 126
    //   950: aload 126
    //   952: arraylength
    //   953: istore 127
    //   955: iconst_0
    //   956: istore 128
    //   958: iload 127
    //   960: iload 128
    //   962: if_icmpgt +4227 -> 5189
    //   965: aload_0
    //   966: bipush 25
    //   968: new 18	java/lang/String
    //   971: dup
    //   972: aload 126
    //   974: invokespecial 28	java/lang/String:<init>	([C)V
    //   977: invokevirtual 32	java/lang/String:intern	()Ljava/lang/String;
    //   980: aastore
    //   981: ldc 84
    //   983: invokevirtual 24	java/lang/String:toCharArray	()[C
    //   986: astore 131
    //   988: aload 131
    //   990: arraylength
    //   991: istore 132
    //   993: iconst_0
    //   994: istore 133
    //   996: iload 132
    //   998: iload 133
    //   1000: if_icmpgt +4281 -> 5281
    //   1003: aload_0
    //   1004: bipush 26
    //   1006: new 18	java/lang/String
    //   1009: dup
    //   1010: aload 131
    //   1012: invokespecial 28	java/lang/String:<init>	([C)V
    //   1015: invokevirtual 32	java/lang/String:intern	()Ljava/lang/String;
    //   1018: aastore
    //   1019: ldc 86
    //   1021: invokevirtual 24	java/lang/String:toCharArray	()[C
    //   1024: astore 136
    //   1026: aload 136
    //   1028: arraylength
    //   1029: istore 137
    //   1031: iconst_0
    //   1032: istore 138
    //   1034: iload 137
    //   1036: iload 138
    //   1038: if_icmpgt +4335 -> 5373
    //   1041: aload_0
    //   1042: bipush 27
    //   1044: new 18	java/lang/String
    //   1047: dup
    //   1048: aload 136
    //   1050: invokespecial 28	java/lang/String:<init>	([C)V
    //   1053: invokevirtual 32	java/lang/String:intern	()Ljava/lang/String;
    //   1056: aastore
    //   1057: ldc 88
    //   1059: invokevirtual 24	java/lang/String:toCharArray	()[C
    //   1062: astore 141
    //   1064: aload 141
    //   1066: arraylength
    //   1067: istore 142
    //   1069: iconst_0
    //   1070: istore 143
    //   1072: iload 142
    //   1074: iload 143
    //   1076: if_icmpgt +4389 -> 5465
    //   1079: aload_0
    //   1080: bipush 28
    //   1082: new 18	java/lang/String
    //   1085: dup
    //   1086: aload 141
    //   1088: invokespecial 28	java/lang/String:<init>	([C)V
    //   1091: invokevirtual 32	java/lang/String:intern	()Ljava/lang/String;
    //   1094: aastore
    //   1095: ldc 90
    //   1097: invokevirtual 24	java/lang/String:toCharArray	()[C
    //   1100: astore 146
    //   1102: aload 146
    //   1104: arraylength
    //   1105: istore 147
    //   1107: iconst_0
    //   1108: istore 148
    //   1110: iload 147
    //   1112: iload 148
    //   1114: if_icmpgt +4443 -> 5557
    //   1117: aload_0
    //   1118: bipush 29
    //   1120: new 18	java/lang/String
    //   1123: dup
    //   1124: aload 146
    //   1126: invokespecial 28	java/lang/String:<init>	([C)V
    //   1129: invokevirtual 32	java/lang/String:intern	()Ljava/lang/String;
    //   1132: aastore
    //   1133: ldc 92
    //   1135: invokevirtual 24	java/lang/String:toCharArray	()[C
    //   1138: astore 151
    //   1140: aload 151
    //   1142: arraylength
    //   1143: istore 152
    //   1145: iconst_0
    //   1146: istore 153
    //   1148: iload 152
    //   1150: iload 153
    //   1152: if_icmpgt +4497 -> 5649
    //   1155: aload_0
    //   1156: bipush 30
    //   1158: new 18	java/lang/String
    //   1161: dup
    //   1162: aload 151
    //   1164: invokespecial 28	java/lang/String:<init>	([C)V
    //   1167: invokevirtual 32	java/lang/String:intern	()Ljava/lang/String;
    //   1170: aastore
    //   1171: ldc 94
    //   1173: invokevirtual 24	java/lang/String:toCharArray	()[C
    //   1176: astore 156
    //   1178: aload 156
    //   1180: arraylength
    //   1181: istore 157
    //   1183: iconst_0
    //   1184: istore 158
    //   1186: iload 157
    //   1188: iload 158
    //   1190: if_icmpgt +4551 -> 5741
    //   1193: aload_0
    //   1194: bipush 31
    //   1196: new 18	java/lang/String
    //   1199: dup
    //   1200: aload 156
    //   1202: invokespecial 28	java/lang/String:<init>	([C)V
    //   1205: invokevirtual 32	java/lang/String:intern	()Ljava/lang/String;
    //   1208: aastore
    //   1209: ldc 96
    //   1211: invokevirtual 24	java/lang/String:toCharArray	()[C
    //   1214: astore 161
    //   1216: aload 161
    //   1218: arraylength
    //   1219: istore 162
    //   1221: iconst_0
    //   1222: istore 163
    //   1224: iload 162
    //   1226: iload 163
    //   1228: if_icmpgt +4605 -> 5833
    //   1231: aload_0
    //   1232: bipush 32
    //   1234: new 18	java/lang/String
    //   1237: dup
    //   1238: aload 161
    //   1240: invokespecial 28	java/lang/String:<init>	([C)V
    //   1243: invokevirtual 32	java/lang/String:intern	()Ljava/lang/String;
    //   1246: aastore
    //   1247: ldc 98
    //   1249: invokevirtual 24	java/lang/String:toCharArray	()[C
    //   1252: astore 166
    //   1254: aload 166
    //   1256: arraylength
    //   1257: istore 167
    //   1259: iconst_0
    //   1260: istore 168
    //   1262: iload 167
    //   1264: iload 168
    //   1266: if_icmpgt +4659 -> 5925
    //   1269: aload_0
    //   1270: bipush 33
    //   1272: new 18	java/lang/String
    //   1275: dup
    //   1276: aload 166
    //   1278: invokespecial 28	java/lang/String:<init>	([C)V
    //   1281: invokevirtual 32	java/lang/String:intern	()Ljava/lang/String;
    //   1284: aastore
    //   1285: ldc 100
    //   1287: invokevirtual 24	java/lang/String:toCharArray	()[C
    //   1290: astore 171
    //   1292: aload 171
    //   1294: arraylength
    //   1295: istore 172
    //   1297: iconst_0
    //   1298: istore 173
    //   1300: iload 172
    //   1302: iload 173
    //   1304: if_icmpgt +4713 -> 6017
    //   1307: aload_0
    //   1308: bipush 34
    //   1310: new 18	java/lang/String
    //   1313: dup
    //   1314: aload 171
    //   1316: invokespecial 28	java/lang/String:<init>	([C)V
    //   1319: invokevirtual 32	java/lang/String:intern	()Ljava/lang/String;
    //   1322: aastore
    //   1323: ldc 102
    //   1325: invokevirtual 24	java/lang/String:toCharArray	()[C
    //   1328: astore 176
    //   1330: aload 176
    //   1332: arraylength
    //   1333: istore 177
    //   1335: iconst_0
    //   1336: istore 178
    //   1338: iload 177
    //   1340: iload 178
    //   1342: if_icmpgt +4767 -> 6109
    //   1345: aload_0
    //   1346: bipush 35
    //   1348: new 18	java/lang/String
    //   1351: dup
    //   1352: aload 176
    //   1354: invokespecial 28	java/lang/String:<init>	([C)V
    //   1357: invokevirtual 32	java/lang/String:intern	()Ljava/lang/String;
    //   1360: aastore
    //   1361: ldc 104
    //   1363: invokevirtual 24	java/lang/String:toCharArray	()[C
    //   1366: astore 181
    //   1368: aload 181
    //   1370: arraylength
    //   1371: istore 182
    //   1373: iconst_0
    //   1374: istore 183
    //   1376: iload 182
    //   1378: iload 183
    //   1380: if_icmpgt +4821 -> 6201
    //   1383: aload_0
    //   1384: bipush 36
    //   1386: new 18	java/lang/String
    //   1389: dup
    //   1390: aload 181
    //   1392: invokespecial 28	java/lang/String:<init>	([C)V
    //   1395: invokevirtual 32	java/lang/String:intern	()Ljava/lang/String;
    //   1398: aastore
    //   1399: ldc 106
    //   1401: invokevirtual 24	java/lang/String:toCharArray	()[C
    //   1404: astore 186
    //   1406: aload 186
    //   1408: arraylength
    //   1409: istore 187
    //   1411: iconst_0
    //   1412: istore 188
    //   1414: iload 187
    //   1416: iload 188
    //   1418: if_icmpgt +4875 -> 6293
    //   1421: aload_0
    //   1422: bipush 37
    //   1424: new 18	java/lang/String
    //   1427: dup
    //   1428: aload 186
    //   1430: invokespecial 28	java/lang/String:<init>	([C)V
    //   1433: invokevirtual 32	java/lang/String:intern	()Ljava/lang/String;
    //   1436: aastore
    //   1437: ldc 108
    //   1439: invokevirtual 24	java/lang/String:toCharArray	()[C
    //   1442: astore 191
    //   1444: aload 191
    //   1446: arraylength
    //   1447: istore 192
    //   1449: iconst_0
    //   1450: istore 193
    //   1452: iload 192
    //   1454: iload 193
    //   1456: if_icmpgt +4929 -> 6385
    //   1459: aload_0
    //   1460: bipush 38
    //   1462: new 18	java/lang/String
    //   1465: dup
    //   1466: aload 191
    //   1468: invokespecial 28	java/lang/String:<init>	([C)V
    //   1471: invokevirtual 32	java/lang/String:intern	()Ljava/lang/String;
    //   1474: aastore
    //   1475: ldc 110
    //   1477: invokevirtual 24	java/lang/String:toCharArray	()[C
    //   1480: astore 196
    //   1482: aload 196
    //   1484: arraylength
    //   1485: istore 197
    //   1487: iconst_0
    //   1488: istore 198
    //   1490: iload 197
    //   1492: iload 198
    //   1494: if_icmpgt +4983 -> 6477
    //   1497: aload_0
    //   1498: bipush 39
    //   1500: new 18	java/lang/String
    //   1503: dup
    //   1504: aload 196
    //   1506: invokespecial 28	java/lang/String:<init>	([C)V
    //   1509: invokevirtual 32	java/lang/String:intern	()Ljava/lang/String;
    //   1512: aastore
    //   1513: ldc 112
    //   1515: invokevirtual 24	java/lang/String:toCharArray	()[C
    //   1518: astore 201
    //   1520: aload 201
    //   1522: arraylength
    //   1523: istore 202
    //   1525: iconst_0
    //   1526: istore 203
    //   1528: iload 202
    //   1530: iload 203
    //   1532: if_icmpgt +5037 -> 6569
    //   1535: aload_0
    //   1536: bipush 40
    //   1538: new 18	java/lang/String
    //   1541: dup
    //   1542: aload 201
    //   1544: invokespecial 28	java/lang/String:<init>	([C)V
    //   1547: invokevirtual 32	java/lang/String:intern	()Ljava/lang/String;
    //   1550: aastore
    //   1551: ldc 114
    //   1553: invokevirtual 24	java/lang/String:toCharArray	()[C
    //   1556: astore 206
    //   1558: aload 206
    //   1560: arraylength
    //   1561: istore 207
    //   1563: iconst_0
    //   1564: istore 208
    //   1566: iload 207
    //   1568: iload 208
    //   1570: if_icmpgt +5091 -> 6661
    //   1573: aload_0
    //   1574: bipush 41
    //   1576: new 18	java/lang/String
    //   1579: dup
    //   1580: aload 206
    //   1582: invokespecial 28	java/lang/String:<init>	([C)V
    //   1585: invokevirtual 32	java/lang/String:intern	()Ljava/lang/String;
    //   1588: aastore
    //   1589: ldc 116
    //   1591: invokevirtual 24	java/lang/String:toCharArray	()[C
    //   1594: astore 211
    //   1596: aload 211
    //   1598: arraylength
    //   1599: istore 212
    //   1601: iconst_0
    //   1602: istore 213
    //   1604: iload 212
    //   1606: iload 213
    //   1608: if_icmpgt +5145 -> 6753
    //   1611: aload_0
    //   1612: bipush 42
    //   1614: new 18	java/lang/String
    //   1617: dup
    //   1618: aload 211
    //   1620: invokespecial 28	java/lang/String:<init>	([C)V
    //   1623: invokevirtual 32	java/lang/String:intern	()Ljava/lang/String;
    //   1626: aastore
    //   1627: ldc 118
    //   1629: invokevirtual 24	java/lang/String:toCharArray	()[C
    //   1632: astore 216
    //   1634: aload 216
    //   1636: arraylength
    //   1637: istore 217
    //   1639: iconst_0
    //   1640: istore 218
    //   1642: iload 217
    //   1644: iload 218
    //   1646: if_icmpgt +5199 -> 6845
    //   1649: aload_0
    //   1650: bipush 43
    //   1652: new 18	java/lang/String
    //   1655: dup
    //   1656: aload 216
    //   1658: invokespecial 28	java/lang/String:<init>	([C)V
    //   1661: invokevirtual 32	java/lang/String:intern	()Ljava/lang/String;
    //   1664: aastore
    //   1665: ldc 120
    //   1667: invokevirtual 24	java/lang/String:toCharArray	()[C
    //   1670: astore 221
    //   1672: aload 221
    //   1674: arraylength
    //   1675: istore 222
    //   1677: iconst_0
    //   1678: istore 223
    //   1680: iload 222
    //   1682: iload 223
    //   1684: if_icmpgt +5253 -> 6937
    //   1687: aload_0
    //   1688: bipush 44
    //   1690: new 18	java/lang/String
    //   1693: dup
    //   1694: aload 221
    //   1696: invokespecial 28	java/lang/String:<init>	([C)V
    //   1699: invokevirtual 32	java/lang/String:intern	()Ljava/lang/String;
    //   1702: aastore
    //   1703: ldc 122
    //   1705: invokevirtual 24	java/lang/String:toCharArray	()[C
    //   1708: astore 226
    //   1710: aload 226
    //   1712: arraylength
    //   1713: istore 227
    //   1715: iconst_0
    //   1716: istore 228
    //   1718: iload 227
    //   1720: iload 228
    //   1722: if_icmpgt +5307 -> 7029
    //   1725: aload_0
    //   1726: bipush 45
    //   1728: new 18	java/lang/String
    //   1731: dup
    //   1732: aload 226
    //   1734: invokespecial 28	java/lang/String:<init>	([C)V
    //   1737: invokevirtual 32	java/lang/String:intern	()Ljava/lang/String;
    //   1740: aastore
    //   1741: ldc 124
    //   1743: invokevirtual 24	java/lang/String:toCharArray	()[C
    //   1746: astore 231
    //   1748: aload 231
    //   1750: arraylength
    //   1751: istore 232
    //   1753: iconst_0
    //   1754: istore 233
    //   1756: iload 232
    //   1758: iload 233
    //   1760: if_icmpgt +5361 -> 7121
    //   1763: aload_0
    //   1764: bipush 46
    //   1766: new 18	java/lang/String
    //   1769: dup
    //   1770: aload 231
    //   1772: invokespecial 28	java/lang/String:<init>	([C)V
    //   1775: invokevirtual 32	java/lang/String:intern	()Ljava/lang/String;
    //   1778: aastore
    //   1779: ldc 126
    //   1781: invokevirtual 24	java/lang/String:toCharArray	()[C
    //   1784: astore 236
    //   1786: aload 236
    //   1788: arraylength
    //   1789: istore 237
    //   1791: iconst_0
    //   1792: istore 238
    //   1794: iload 237
    //   1796: iload 238
    //   1798: if_icmpgt +5415 -> 7213
    //   1801: aload_0
    //   1802: bipush 47
    //   1804: new 18	java/lang/String
    //   1807: dup
    //   1808: aload 236
    //   1810: invokespecial 28	java/lang/String:<init>	([C)V
    //   1813: invokevirtual 32	java/lang/String:intern	()Ljava/lang/String;
    //   1816: aastore
    //   1817: ldc 128
    //   1819: invokevirtual 24	java/lang/String:toCharArray	()[C
    //   1822: astore 241
    //   1824: aload 241
    //   1826: arraylength
    //   1827: istore 242
    //   1829: iconst_0
    //   1830: istore 243
    //   1832: iload 242
    //   1834: iload 243
    //   1836: if_icmpgt +5469 -> 7305
    //   1839: aload_0
    //   1840: bipush 48
    //   1842: new 18	java/lang/String
    //   1845: dup
    //   1846: aload 241
    //   1848: invokespecial 28	java/lang/String:<init>	([C)V
    //   1851: invokevirtual 32	java/lang/String:intern	()Ljava/lang/String;
    //   1854: aastore
    //   1855: ldc 130
    //   1857: invokevirtual 24	java/lang/String:toCharArray	()[C
    //   1860: astore 246
    //   1862: aload 246
    //   1864: arraylength
    //   1865: istore 247
    //   1867: iconst_0
    //   1868: istore 248
    //   1870: iload 247
    //   1872: iload 248
    //   1874: if_icmpgt +5523 -> 7397
    //   1877: aload_0
    //   1878: bipush 49
    //   1880: new 18	java/lang/String
    //   1883: dup
    //   1884: aload 246
    //   1886: invokespecial 28	java/lang/String:<init>	([C)V
    //   1889: invokevirtual 32	java/lang/String:intern	()Ljava/lang/String;
    //   1892: aastore
    //   1893: ldc 132
    //   1895: invokevirtual 24	java/lang/String:toCharArray	()[C
    //   1898: astore 251
    //   1900: aload 251
    //   1902: arraylength
    //   1903: istore 252
    //   1905: iconst_0
    //   1906: istore 253
    //   1908: iload 252
    //   1910: iload 253
    //   1912: if_icmpgt +5577 -> 7489
    //   1915: aload_0
    //   1916: bipush 50
    //   1918: new 18	java/lang/String
    //   1921: dup
    //   1922: aload 251
    //   1924: invokespecial 28	java/lang/String:<init>	([C)V
    //   1927: invokevirtual 32	java/lang/String:intern	()Ljava/lang/String;
    //   1930: aastore
    //   1931: ldc 134
    //   1933: invokevirtual 24	java/lang/String:toCharArray	()[C
    //   1936: wide
    //   1940: wide
    //   1944: arraylength
    //   1945: wide
    //   1949: iconst_0
    //   1950: wide
    //   1954: wide
    //   1958: wide
    //   1962: if_icmpgt +5619 -> 7581
    //   1965: aload_0
    //   1966: bipush 51
    //   1968: new 18	java/lang/String
    //   1971: dup
    //   1972: wide
    //   1976: invokespecial 28	java/lang/String:<init>	([C)V
    //   1979: invokevirtual 32	java/lang/String:intern	()Ljava/lang/String;
    //   1982: aastore
    //   1983: ldc 136
    //   1985: invokevirtual 24	java/lang/String:toCharArray	()[C
    //   1988: wide
    //   1992: wide
    //   1996: arraylength
    //   1997: wide
    //   2001: iconst_0
    //   2002: wide
    //   2006: wide
    //   2010: wide
    //   2014: if_icmpgt +5688 -> 7702
    //   2017: aload_0
    //   2018: bipush 52
    //   2020: new 18	java/lang/String
    //   2023: dup
    //   2024: wide
    //   2028: invokespecial 28	java/lang/String:<init>	([C)V
    //   2031: invokevirtual 32	java/lang/String:intern	()Ljava/lang/String;
    //   2034: aastore
    //   2035: ldc 138
    //   2037: invokevirtual 24	java/lang/String:toCharArray	()[C
    //   2040: wide
    //   2044: wide
    //   2048: arraylength
    //   2049: wide
    //   2053: iconst_0
    //   2054: wide
    //   2058: wide
    //   2062: wide
    //   2066: if_icmpgt +5756 -> 7822
    //   2069: aload_0
    //   2070: bipush 53
    //   2072: new 18	java/lang/String
    //   2075: dup
    //   2076: wide
    //   2080: invokespecial 28	java/lang/String:<init>	([C)V
    //   2083: invokevirtual 32	java/lang/String:intern	()Ljava/lang/String;
    //   2086: aastore
    //   2087: ldc 140
    //   2089: invokevirtual 24	java/lang/String:toCharArray	()[C
    //   2092: wide
    //   2096: wide
    //   2100: arraylength
    //   2101: wide
    //   2105: iconst_0
    //   2106: wide
    //   2110: wide
    //   2114: wide
    //   2118: if_icmpgt +5824 -> 7942
    //   2121: aload_0
    //   2122: bipush 54
    //   2124: new 18	java/lang/String
    //   2127: dup
    //   2128: wide
    //   2132: invokespecial 28	java/lang/String:<init>	([C)V
    //   2135: invokevirtual 32	java/lang/String:intern	()Ljava/lang/String;
    //   2138: aastore
    //   2139: ldc 142
    //   2141: invokevirtual 24	java/lang/String:toCharArray	()[C
    //   2144: wide
    //   2148: wide
    //   2152: arraylength
    //   2153: wide
    //   2157: iconst_0
    //   2158: wide
    //   2162: wide
    //   2166: wide
    //   2170: if_icmpgt +5892 -> 8062
    //   2173: aload_0
    //   2174: bipush 55
    //   2176: new 18	java/lang/String
    //   2179: dup
    //   2180: wide
    //   2184: invokespecial 28	java/lang/String:<init>	([C)V
    //   2187: invokevirtual 32	java/lang/String:intern	()Ljava/lang/String;
    //   2190: aastore
    //   2191: ldc 144
    //   2193: invokevirtual 24	java/lang/String:toCharArray	()[C
    //   2196: wide
    //   2200: wide
    //   2204: arraylength
    //   2205: wide
    //   2209: iconst_0
    //   2210: wide
    //   2214: wide
    //   2218: wide
    //   2222: if_icmpgt +5960 -> 8182
    //   2225: aload_0
    //   2226: bipush 56
    //   2228: new 18	java/lang/String
    //   2231: dup
    //   2232: wide
    //   2236: invokespecial 28	java/lang/String:<init>	([C)V
    //   2239: invokevirtual 32	java/lang/String:intern	()Ljava/lang/String;
    //   2242: aastore
    //   2243: ldc 146
    //   2245: invokevirtual 24	java/lang/String:toCharArray	()[C
    //   2248: wide
    //   2252: wide
    //   2256: arraylength
    //   2257: wide
    //   2261: iconst_0
    //   2262: wide
    //   2266: wide
    //   2270: wide
    //   2274: if_icmpgt +6028 -> 8302
    //   2277: aload_0
    //   2278: bipush 57
    //   2280: new 18	java/lang/String
    //   2283: dup
    //   2284: wide
    //   2288: invokespecial 28	java/lang/String:<init>	([C)V
    //   2291: invokevirtual 32	java/lang/String:intern	()Ljava/lang/String;
    //   2294: aastore
    //   2295: ldc 148
    //   2297: invokevirtual 24	java/lang/String:toCharArray	()[C
    //   2300: wide
    //   2304: wide
    //   2308: arraylength
    //   2309: wide
    //   2313: iconst_0
    //   2314: wide
    //   2318: wide
    //   2322: wide
    //   2326: if_icmpgt +6096 -> 8422
    //   2329: aload_0
    //   2330: bipush 58
    //   2332: new 18	java/lang/String
    //   2335: dup
    //   2336: wide
    //   2340: invokespecial 28	java/lang/String:<init>	([C)V
    //   2343: invokevirtual 32	java/lang/String:intern	()Ljava/lang/String;
    //   2346: aastore
    //   2347: ldc 150
    //   2349: invokevirtual 24	java/lang/String:toCharArray	()[C
    //   2352: wide
    //   2356: wide
    //   2360: arraylength
    //   2361: wide
    //   2365: iconst_0
    //   2366: wide
    //   2370: wide
    //   2374: wide
    //   2378: if_icmpgt +6164 -> 8542
    //   2381: aload_0
    //   2382: bipush 59
    //   2384: new 18	java/lang/String
    //   2387: dup
    //   2388: wide
    //   2392: invokespecial 28	java/lang/String:<init>	([C)V
    //   2395: invokevirtual 32	java/lang/String:intern	()Ljava/lang/String;
    //   2398: aastore
    //   2399: ldc 152
    //   2401: invokevirtual 24	java/lang/String:toCharArray	()[C
    //   2404: wide
    //   2408: wide
    //   2412: arraylength
    //   2413: wide
    //   2417: iconst_0
    //   2418: wide
    //   2422: wide
    //   2426: wide
    //   2430: if_icmpgt +6232 -> 8662
    //   2433: aload_0
    //   2434: bipush 60
    //   2436: new 18	java/lang/String
    //   2439: dup
    //   2440: wide
    //   2444: invokespecial 28	java/lang/String:<init>	([C)V
    //   2447: invokevirtual 32	java/lang/String:intern	()Ljava/lang/String;
    //   2450: aastore
    //   2451: ldc 154
    //   2453: invokevirtual 24	java/lang/String:toCharArray	()[C
    //   2456: wide
    //   2460: wide
    //   2464: arraylength
    //   2465: wide
    //   2469: iconst_0
    //   2470: wide
    //   2474: wide
    //   2478: wide
    //   2482: if_icmpgt +6300 -> 8782
    //   2485: aload_0
    //   2486: bipush 61
    //   2488: new 18	java/lang/String
    //   2491: dup
    //   2492: wide
    //   2496: invokespecial 28	java/lang/String:<init>	([C)V
    //   2499: invokevirtual 32	java/lang/String:intern	()Ljava/lang/String;
    //   2502: aastore
    //   2503: ldc 156
    //   2505: invokevirtual 24	java/lang/String:toCharArray	()[C
    //   2508: wide
    //   2512: wide
    //   2516: arraylength
    //   2517: wide
    //   2521: iconst_0
    //   2522: wide
    //   2526: wide
    //   2530: wide
    //   2534: if_icmpgt +6368 -> 8902
    //   2537: aload_0
    //   2538: bipush 62
    //   2540: new 18	java/lang/String
    //   2543: dup
    //   2544: wide
    //   2548: invokespecial 28	java/lang/String:<init>	([C)V
    //   2551: invokevirtual 32	java/lang/String:intern	()Ljava/lang/String;
    //   2554: aastore
    //   2555: ldc 158
    //   2557: invokevirtual 24	java/lang/String:toCharArray	()[C
    //   2560: wide
    //   2564: wide
    //   2568: arraylength
    //   2569: wide
    //   2573: iconst_0
    //   2574: wide
    //   2578: wide
    //   2582: wide
    //   2586: if_icmpgt +6436 -> 9022
    //   2589: aload_0
    //   2590: bipush 63
    //   2592: new 18	java/lang/String
    //   2595: dup
    //   2596: wide
    //   2600: invokespecial 28	java/lang/String:<init>	([C)V
    //   2603: invokevirtual 32	java/lang/String:intern	()Ljava/lang/String;
    //   2606: aastore
    //   2607: ldc 160
    //   2609: invokevirtual 24	java/lang/String:toCharArray	()[C
    //   2612: wide
    //   2616: wide
    //   2620: arraylength
    //   2621: wide
    //   2625: iconst_0
    //   2626: wide
    //   2630: wide
    //   2634: wide
    //   2638: if_icmpgt +6504 -> 9142
    //   2641: aload_0
    //   2642: bipush 64
    //   2644: new 18	java/lang/String
    //   2647: dup
    //   2648: wide
    //   2652: invokespecial 28	java/lang/String:<init>	([C)V
    //   2655: invokevirtual 32	java/lang/String:intern	()Ljava/lang/String;
    //   2658: aastore
    //   2659: ldc 162
    //   2661: invokevirtual 24	java/lang/String:toCharArray	()[C
    //   2664: wide
    //   2668: wide
    //   2672: arraylength
    //   2673: wide
    //   2677: iconst_0
    //   2678: wide
    //   2682: wide
    //   2686: wide
    //   2690: if_icmpgt +6572 -> 9262
    //   2693: aload_0
    //   2694: bipush 65
    //   2696: new 18	java/lang/String
    //   2699: dup
    //   2700: wide
    //   2704: invokespecial 28	java/lang/String:<init>	([C)V
    //   2707: invokevirtual 32	java/lang/String:intern	()Ljava/lang/String;
    //   2710: aastore
    //   2711: ldc 164
    //   2713: invokevirtual 24	java/lang/String:toCharArray	()[C
    //   2716: wide
    //   2720: wide
    //   2724: arraylength
    //   2725: wide
    //   2729: iconst_0
    //   2730: wide
    //   2734: wide
    //   2738: wide
    //   2742: if_icmpgt +6640 -> 9382
    //   2745: aload_0
    //   2746: bipush 66
    //   2748: new 18	java/lang/String
    //   2751: dup
    //   2752: wide
    //   2756: invokespecial 28	java/lang/String:<init>	([C)V
    //   2759: invokevirtual 32	java/lang/String:intern	()Ljava/lang/String;
    //   2762: aastore
    //   2763: ldc 166
    //   2765: invokevirtual 24	java/lang/String:toCharArray	()[C
    //   2768: wide
    //   2772: wide
    //   2776: arraylength
    //   2777: wide
    //   2781: iconst_0
    //   2782: wide
    //   2786: wide
    //   2790: wide
    //   2794: if_icmpgt +6708 -> 9502
    //   2797: aload_0
    //   2798: bipush 67
    //   2800: new 18	java/lang/String
    //   2803: dup
    //   2804: wide
    //   2808: invokespecial 28	java/lang/String:<init>	([C)V
    //   2811: invokevirtual 32	java/lang/String:intern	()Ljava/lang/String;
    //   2814: aastore
    //   2815: ldc 168
    //   2817: invokevirtual 24	java/lang/String:toCharArray	()[C
    //   2820: wide
    //   2824: wide
    //   2828: arraylength
    //   2829: wide
    //   2833: iconst_0
    //   2834: wide
    //   2838: wide
    //   2842: wide
    //   2846: if_icmpgt +6776 -> 9622
    //   2849: aload_0
    //   2850: bipush 68
    //   2852: new 18	java/lang/String
    //   2855: dup
    //   2856: wide
    //   2860: invokespecial 28	java/lang/String:<init>	([C)V
    //   2863: invokevirtual 32	java/lang/String:intern	()Ljava/lang/String;
    //   2866: aastore
    //   2867: aload_0
    //   2868: putstatic 170	com/whatsapp/mh:z	[Ljava/lang/String;
    //   2871: aconst_null
    //   2872: putstatic 172	com/whatsapp/mh:a	Ljava/lang/String;
    //   2875: iconst_0
    //   2876: putstatic 174	com/whatsapp/mh:b	Z
    //   2879: iconst_0
    //   2880: putstatic 176	com/whatsapp/mh:c	Z
    //   2883: iconst_0
    //   2884: putstatic 178	com/whatsapp/mh:d	Z
    //   2887: aconst_null
    //   2888: putstatic 180	com/whatsapp/mh:e	Ljava/lang/String;
    //   2891: iconst_0
    //   2892: putstatic 182	com/whatsapp/mh:f	Z
    //   2895: return
    //   2896: aload_1
    //   2897: iload_3
    //   2898: caload
    //   2899: istore 4
    //   2901: iload_3
    //   2902: iconst_5
    //   2903: irem
    //   2904: tableswitch	default:+32 -> 2936, 0:+51->2955, 1:+58->2962, 2:+65->2969, 3:+72->2976
    //   2937: dup2
    //   2938: istore 5
    //   2940: aload_1
    //   2941: iload_3
    //   2942: iload 5
    //   2944: iload 4
    //   2946: ixor
    //   2947: i2c
    //   2948: castore
    //   2949: iinc 3 1
    //   2952: goto -2935 -> 17
    //   2955: bipush 100
    //   2957: istore 5
    //   2959: goto -19 -> 2940
    //   2962: bipush 14
    //   2964: istore 5
    //   2966: goto -26 -> 2940
    //   2969: bipush 68
    //   2971: istore 5
    //   2973: goto -33 -> 2940
    //   2976: bipush 111
    //   2978: istore 5
    //   2980: goto -40 -> 2940
    //   2983: aload 6
    //   2985: iload 8
    //   2987: caload
    //   2988: istore 9
    //   2990: iload 8
    //   2992: iconst_5
    //   2993: irem
    //   2994: tableswitch	default:+30 -> 3024, 0:+51->3045, 1:+58->3052, 2:+65->3059, 3:+72->3066
    //   3025: dup2
    //   3026: istore 10
    //   3028: aload 6
    //   3030: iload 8
    //   3032: iload 10
    //   3034: iload 9
    //   3036: ixor
    //   3037: i2c
    //   3038: castore
    //   3039: iinc 8 1
    //   3042: goto -2991 -> 51
    //   3045: bipush 100
    //   3047: istore 10
    //   3049: goto -21 -> 3028
    //   3052: bipush 14
    //   3054: istore 10
    //   3056: goto -28 -> 3028
    //   3059: bipush 68
    //   3061: istore 10
    //   3063: goto -35 -> 3028
    //   3066: bipush 111
    //   3068: istore 10
    //   3070: goto -42 -> 3028
    //   3073: aload 11
    //   3075: iload 13
    //   3077: caload
    //   3078: istore 14
    //   3080: iload 13
    //   3082: iconst_5
    //   3083: irem
    //   3084: tableswitch	default:+32 -> 3116, 0:+53->3137, 1:+60->3144, 2:+67->3151, 3:+74->3158
    //   3117: dup2
    //   3118: istore 15
    //   3120: aload 11
    //   3122: iload 13
    //   3124: iload 15
    //   3126: iload 14
    //   3128: ixor
    //   3129: i2c
    //   3130: castore
    //   3131: iinc 13 1
    //   3134: goto -3046 -> 88
    //   3137: bipush 100
    //   3139: istore 15
    //   3141: goto -21 -> 3120
    //   3144: bipush 14
    //   3146: istore 15
    //   3148: goto -28 -> 3120
    //   3151: bipush 68
    //   3153: istore 15
    //   3155: goto -35 -> 3120
    //   3158: bipush 111
    //   3160: istore 15
    //   3162: goto -42 -> 3120
    //   3165: aload 16
    //   3167: iload 18
    //   3169: caload
    //   3170: istore 19
    //   3172: iload 18
    //   3174: iconst_5
    //   3175: irem
    //   3176: tableswitch	default:+32 -> 3208, 0:+53->3229, 1:+60->3236, 2:+67->3243, 3:+74->3250
    //   3209: dup2
    //   3210: istore 20
    //   3212: aload 16
    //   3214: iload 18
    //   3216: iload 20
    //   3218: iload 19
    //   3220: ixor
    //   3221: i2c
    //   3222: castore
    //   3223: iinc 18 1
    //   3226: goto -3101 -> 125
    //   3229: bipush 100
    //   3231: istore 20
    //   3233: goto -21 -> 3212
    //   3236: bipush 14
    //   3238: istore 20
    //   3240: goto -28 -> 3212
    //   3243: bipush 68
    //   3245: istore 20
    //   3247: goto -35 -> 3212
    //   3250: bipush 111
    //   3252: istore 20
    //   3254: goto -42 -> 3212
    //   3257: aload 21
    //   3259: iload 23
    //   3261: caload
    //   3262: istore 24
    //   3264: iload 23
    //   3266: iconst_5
    //   3267: irem
    //   3268: tableswitch	default:+32 -> 3300, 0:+53->3321, 1:+60->3328, 2:+67->3335, 3:+74->3342
    //   3301: dup2
    //   3302: istore 25
    //   3304: aload 21
    //   3306: iload 23
    //   3308: iload 25
    //   3310: iload 24
    //   3312: ixor
    //   3313: i2c
    //   3314: castore
    //   3315: iinc 23 1
    //   3318: goto -3156 -> 162
    //   3321: bipush 100
    //   3323: istore 25
    //   3325: goto -21 -> 3304
    //   3328: bipush 14
    //   3330: istore 25
    //   3332: goto -28 -> 3304
    //   3335: bipush 68
    //   3337: istore 25
    //   3339: goto -35 -> 3304
    //   3342: bipush 111
    //   3344: istore 25
    //   3346: goto -42 -> 3304
    //   3349: aload 26
    //   3351: iload 28
    //   3353: caload
    //   3354: istore 29
    //   3356: iload 28
    //   3358: iconst_5
    //   3359: irem
    //   3360: tableswitch	default:+32 -> 3392, 0:+53->3413, 1:+60->3420, 2:+67->3427, 3:+74->3434
    //   3393: dup2
    //   3394: istore 30
    //   3396: aload 26
    //   3398: iload 28
    //   3400: iload 30
    //   3402: iload 29
    //   3404: ixor
    //   3405: i2c
    //   3406: castore
    //   3407: iinc 28 1
    //   3410: goto -3211 -> 199
    //   3413: bipush 100
    //   3415: istore 30
    //   3417: goto -21 -> 3396
    //   3420: bipush 14
    //   3422: istore 30
    //   3424: goto -28 -> 3396
    //   3427: bipush 68
    //   3429: istore 30
    //   3431: goto -35 -> 3396
    //   3434: bipush 111
    //   3436: istore 30
    //   3438: goto -42 -> 3396
    //   3441: aload 31
    //   3443: iload 33
    //   3445: caload
    //   3446: istore 34
    //   3448: iload 33
    //   3450: iconst_5
    //   3451: irem
    //   3452: tableswitch	default:+32 -> 3484, 0:+53->3505, 1:+60->3512, 2:+67->3519, 3:+74->3526
    //   3485: dup2
    //   3486: istore 35
    //   3488: aload 31
    //   3490: iload 33
    //   3492: iload 35
    //   3494: iload 34
    //   3496: ixor
    //   3497: i2c
    //   3498: castore
    //   3499: iinc 33 1
    //   3502: goto -3266 -> 236
    //   3505: bipush 100
    //   3507: istore 35
    //   3509: goto -21 -> 3488
    //   3512: bipush 14
    //   3514: istore 35
    //   3516: goto -28 -> 3488
    //   3519: bipush 68
    //   3521: istore 35
    //   3523: goto -35 -> 3488
    //   3526: bipush 111
    //   3528: istore 35
    //   3530: goto -42 -> 3488
    //   3533: aload 36
    //   3535: iload 38
    //   3537: caload
    //   3538: istore 39
    //   3540: iload 38
    //   3542: iconst_5
    //   3543: irem
    //   3544: tableswitch	default:+32 -> 3576, 0:+53->3597, 1:+60->3604, 2:+67->3611, 3:+74->3618
    //   3577: dup2
    //   3578: istore 40
    //   3580: aload 36
    //   3582: iload 38
    //   3584: iload 40
    //   3586: iload 39
    //   3588: ixor
    //   3589: i2c
    //   3590: castore
    //   3591: iinc 38 1
    //   3594: goto -3320 -> 274
    //   3597: bipush 100
    //   3599: istore 40
    //   3601: goto -21 -> 3580
    //   3604: bipush 14
    //   3606: istore 40
    //   3608: goto -28 -> 3580
    //   3611: bipush 68
    //   3613: istore 40
    //   3615: goto -35 -> 3580
    //   3618: bipush 111
    //   3620: istore 40
    //   3622: goto -42 -> 3580
    //   3625: aload 41
    //   3627: iload 43
    //   3629: caload
    //   3630: istore 44
    //   3632: iload 43
    //   3634: iconst_5
    //   3635: irem
    //   3636: tableswitch	default:+32 -> 3668, 0:+53->3689, 1:+60->3696, 2:+67->3703, 3:+74->3710
    //   3669: dup2
    //   3670: istore 45
    //   3672: aload 41
    //   3674: iload 43
    //   3676: iload 45
    //   3678: iload 44
    //   3680: ixor
    //   3681: i2c
    //   3682: castore
    //   3683: iinc 43 1
    //   3686: goto -3374 -> 312
    //   3689: bipush 100
    //   3691: istore 45
    //   3693: goto -21 -> 3672
    //   3696: bipush 14
    //   3698: istore 45
    //   3700: goto -28 -> 3672
    //   3703: bipush 68
    //   3705: istore 45
    //   3707: goto -35 -> 3672
    //   3710: bipush 111
    //   3712: istore 45
    //   3714: goto -42 -> 3672
    //   3717: aload 46
    //   3719: iload 48
    //   3721: caload
    //   3722: istore 49
    //   3724: iload 48
    //   3726: iconst_5
    //   3727: irem
    //   3728: tableswitch	default:+32 -> 3760, 0:+53->3781, 1:+60->3788, 2:+67->3795, 3:+74->3802
    //   3761: dup2
    //   3762: istore 50
    //   3764: aload 46
    //   3766: iload 48
    //   3768: iload 50
    //   3770: iload 49
    //   3772: ixor
    //   3773: i2c
    //   3774: castore
    //   3775: iinc 48 1
    //   3778: goto -3428 -> 350
    //   3781: bipush 100
    //   3783: istore 50
    //   3785: goto -21 -> 3764
    //   3788: bipush 14
    //   3790: istore 50
    //   3792: goto -28 -> 3764
    //   3795: bipush 68
    //   3797: istore 50
    //   3799: goto -35 -> 3764
    //   3802: bipush 111
    //   3804: istore 50
    //   3806: goto -42 -> 3764
    //   3809: aload 51
    //   3811: iload 53
    //   3813: caload
    //   3814: istore 54
    //   3816: iload 53
    //   3818: iconst_5
    //   3819: irem
    //   3820: tableswitch	default:+32 -> 3852, 0:+53->3873, 1:+60->3880, 2:+67->3887, 3:+74->3894
    //   3853: dup2
    //   3854: istore 55
    //   3856: aload 51
    //   3858: iload 53
    //   3860: iload 55
    //   3862: iload 54
    //   3864: ixor
    //   3865: i2c
    //   3866: castore
    //   3867: iinc 53 1
    //   3870: goto -3482 -> 388
    //   3873: bipush 100
    //   3875: istore 55
    //   3877: goto -21 -> 3856
    //   3880: bipush 14
    //   3882: istore 55
    //   3884: goto -28 -> 3856
    //   3887: bipush 68
    //   3889: istore 55
    //   3891: goto -35 -> 3856
    //   3894: bipush 111
    //   3896: istore 55
    //   3898: goto -42 -> 3856
    //   3901: aload 56
    //   3903: iload 58
    //   3905: caload
    //   3906: istore 59
    //   3908: iload 58
    //   3910: iconst_5
    //   3911: irem
    //   3912: tableswitch	default:+32 -> 3944, 0:+53->3965, 1:+60->3972, 2:+67->3979, 3:+74->3986
    //   3945: dup2
    //   3946: istore 60
    //   3948: aload 56
    //   3950: iload 58
    //   3952: iload 60
    //   3954: iload 59
    //   3956: ixor
    //   3957: i2c
    //   3958: castore
    //   3959: iinc 58 1
    //   3962: goto -3536 -> 426
    //   3965: bipush 100
    //   3967: istore 60
    //   3969: goto -21 -> 3948
    //   3972: bipush 14
    //   3974: istore 60
    //   3976: goto -28 -> 3948
    //   3979: bipush 68
    //   3981: istore 60
    //   3983: goto -35 -> 3948
    //   3986: bipush 111
    //   3988: istore 60
    //   3990: goto -42 -> 3948
    //   3993: aload 61
    //   3995: iload 63
    //   3997: caload
    //   3998: istore 64
    //   4000: iload 63
    //   4002: iconst_5
    //   4003: irem
    //   4004: tableswitch	default:+32 -> 4036, 0:+53->4057, 1:+60->4064, 2:+67->4071, 3:+74->4078
    //   4037: dup2
    //   4038: istore 65
    //   4040: aload 61
    //   4042: iload 63
    //   4044: iload 65
    //   4046: iload 64
    //   4048: ixor
    //   4049: i2c
    //   4050: castore
    //   4051: iinc 63 1
    //   4054: goto -3590 -> 464
    //   4057: bipush 100
    //   4059: istore 65
    //   4061: goto -21 -> 4040
    //   4064: bipush 14
    //   4066: istore 65
    //   4068: goto -28 -> 4040
    //   4071: bipush 68
    //   4073: istore 65
    //   4075: goto -35 -> 4040
    //   4078: bipush 111
    //   4080: istore 65
    //   4082: goto -42 -> 4040
    //   4085: aload 66
    //   4087: iload 68
    //   4089: caload
    //   4090: istore 69
    //   4092: iload 68
    //   4094: iconst_5
    //   4095: irem
    //   4096: tableswitch	default:+32 -> 4128, 0:+53->4149, 1:+60->4156, 2:+67->4163, 3:+74->4170
    //   4129: dup2
    //   4130: istore 70
    //   4132: aload 66
    //   4134: iload 68
    //   4136: iload 70
    //   4138: iload 69
    //   4140: ixor
    //   4141: i2c
    //   4142: castore
    //   4143: iinc 68 1
    //   4146: goto -3644 -> 502
    //   4149: bipush 100
    //   4151: istore 70
    //   4153: goto -21 -> 4132
    //   4156: bipush 14
    //   4158: istore 70
    //   4160: goto -28 -> 4132
    //   4163: bipush 68
    //   4165: istore 70
    //   4167: goto -35 -> 4132
    //   4170: bipush 111
    //   4172: istore 70
    //   4174: goto -42 -> 4132
    //   4177: aload 71
    //   4179: iload 73
    //   4181: caload
    //   4182: istore 74
    //   4184: iload 73
    //   4186: iconst_5
    //   4187: irem
    //   4188: tableswitch	default:+32 -> 4220, 0:+53->4241, 1:+60->4248, 2:+67->4255, 3:+74->4262
    //   4221: dup2
    //   4222: istore 75
    //   4224: aload 71
    //   4226: iload 73
    //   4228: iload 75
    //   4230: iload 74
    //   4232: ixor
    //   4233: i2c
    //   4234: castore
    //   4235: iinc 73 1
    //   4238: goto -3698 -> 540
    //   4241: bipush 100
    //   4243: istore 75
    //   4245: goto -21 -> 4224
    //   4248: bipush 14
    //   4250: istore 75
    //   4252: goto -28 -> 4224
    //   4255: bipush 68
    //   4257: istore 75
    //   4259: goto -35 -> 4224
    //   4262: bipush 111
    //   4264: istore 75
    //   4266: goto -42 -> 4224
    //   4269: aload 76
    //   4271: iload 78
    //   4273: caload
    //   4274: istore 79
    //   4276: iload 78
    //   4278: iconst_5
    //   4279: irem
    //   4280: tableswitch	default:+32 -> 4312, 0:+53->4333, 1:+60->4340, 2:+67->4347, 3:+74->4354
    //   4313: dup2
    //   4314: istore 80
    //   4316: aload 76
    //   4318: iload 78
    //   4320: iload 80
    //   4322: iload 79
    //   4324: ixor
    //   4325: i2c
    //   4326: castore
    //   4327: iinc 78 1
    //   4330: goto -3752 -> 578
    //   4333: bipush 100
    //   4335: istore 80
    //   4337: goto -21 -> 4316
    //   4340: bipush 14
    //   4342: istore 80
    //   4344: goto -28 -> 4316
    //   4347: bipush 68
    //   4349: istore 80
    //   4351: goto -35 -> 4316
    //   4354: bipush 111
    //   4356: istore 80
    //   4358: goto -42 -> 4316
    //   4361: aload 81
    //   4363: iload 83
    //   4365: caload
    //   4366: istore 84
    //   4368: iload 83
    //   4370: iconst_5
    //   4371: irem
    //   4372: tableswitch	default:+32 -> 4404, 0:+53->4425, 1:+60->4432, 2:+67->4439, 3:+74->4446
    //   4405: dup2
    //   4406: istore 85
    //   4408: aload 81
    //   4410: iload 83
    //   4412: iload 85
    //   4414: iload 84
    //   4416: ixor
    //   4417: i2c
    //   4418: castore
    //   4419: iinc 83 1
    //   4422: goto -3806 -> 616
    //   4425: bipush 100
    //   4427: istore 85
    //   4429: goto -21 -> 4408
    //   4432: bipush 14
    //   4434: istore 85
    //   4436: goto -28 -> 4408
    //   4439: bipush 68
    //   4441: istore 85
    //   4443: goto -35 -> 4408
    //   4446: bipush 111
    //   4448: istore 85
    //   4450: goto -42 -> 4408
    //   4453: aload 86
    //   4455: iload 88
    //   4457: caload
    //   4458: istore 89
    //   4460: iload 88
    //   4462: iconst_5
    //   4463: irem
    //   4464: tableswitch	default:+32 -> 4496, 0:+53->4517, 1:+60->4524, 2:+67->4531, 3:+74->4538
    //   4497: dup2
    //   4498: istore 90
    //   4500: aload 86
    //   4502: iload 88
    //   4504: iload 90
    //   4506: iload 89
    //   4508: ixor
    //   4509: i2c
    //   4510: castore
    //   4511: iinc 88 1
    //   4514: goto -3860 -> 654
    //   4517: bipush 100
    //   4519: istore 90
    //   4521: goto -21 -> 4500
    //   4524: bipush 14
    //   4526: istore 90
    //   4528: goto -28 -> 4500
    //   4531: bipush 68
    //   4533: istore 90
    //   4535: goto -35 -> 4500
    //   4538: bipush 111
    //   4540: istore 90
    //   4542: goto -42 -> 4500
    //   4545: aload 91
    //   4547: iload 93
    //   4549: caload
    //   4550: istore 94
    //   4552: iload 93
    //   4554: iconst_5
    //   4555: irem
    //   4556: tableswitch	default:+32 -> 4588, 0:+53->4609, 1:+60->4616, 2:+67->4623, 3:+74->4630
    //   4589: dup2
    //   4590: istore 95
    //   4592: aload 91
    //   4594: iload 93
    //   4596: iload 95
    //   4598: iload 94
    //   4600: ixor
    //   4601: i2c
    //   4602: castore
    //   4603: iinc 93 1
    //   4606: goto -3914 -> 692
    //   4609: bipush 100
    //   4611: istore 95
    //   4613: goto -21 -> 4592
    //   4616: bipush 14
    //   4618: istore 95
    //   4620: goto -28 -> 4592
    //   4623: bipush 68
    //   4625: istore 95
    //   4627: goto -35 -> 4592
    //   4630: bipush 111
    //   4632: istore 95
    //   4634: goto -42 -> 4592
    //   4637: aload 96
    //   4639: iload 98
    //   4641: caload
    //   4642: istore 99
    //   4644: iload 98
    //   4646: iconst_5
    //   4647: irem
    //   4648: tableswitch	default:+32 -> 4680, 0:+53->4701, 1:+60->4708, 2:+67->4715, 3:+74->4722
    //   4681: dup2
    //   4682: istore 100
    //   4684: aload 96
    //   4686: iload 98
    //   4688: iload 100
    //   4690: iload 99
    //   4692: ixor
    //   4693: i2c
    //   4694: castore
    //   4695: iinc 98 1
    //   4698: goto -3968 -> 730
    //   4701: bipush 100
    //   4703: istore 100
    //   4705: goto -21 -> 4684
    //   4708: bipush 14
    //   4710: istore 100
    //   4712: goto -28 -> 4684
    //   4715: bipush 68
    //   4717: istore 100
    //   4719: goto -35 -> 4684
    //   4722: bipush 111
    //   4724: istore 100
    //   4726: goto -42 -> 4684
    //   4729: aload 101
    //   4731: iload 103
    //   4733: caload
    //   4734: istore 104
    //   4736: iload 103
    //   4738: iconst_5
    //   4739: irem
    //   4740: tableswitch	default:+32 -> 4772, 0:+53->4793, 1:+60->4800, 2:+67->4807, 3:+74->4814
    //   4773: dup2
    //   4774: istore 105
    //   4776: aload 101
    //   4778: iload 103
    //   4780: iload 105
    //   4782: iload 104
    //   4784: ixor
    //   4785: i2c
    //   4786: castore
    //   4787: iinc 103 1
    //   4790: goto -4022 -> 768
    //   4793: bipush 100
    //   4795: istore 105
    //   4797: goto -21 -> 4776
    //   4800: bipush 14
    //   4802: istore 105
    //   4804: goto -28 -> 4776
    //   4807: bipush 68
    //   4809: istore 105
    //   4811: goto -35 -> 4776
    //   4814: bipush 111
    //   4816: istore 105
    //   4818: goto -42 -> 4776
    //   4821: aload 106
    //   4823: iload 108
    //   4825: caload
    //   4826: istore 109
    //   4828: iload 108
    //   4830: iconst_5
    //   4831: irem
    //   4832: tableswitch	default:+32 -> 4864, 0:+53->4885, 1:+60->4892, 2:+67->4899, 3:+74->4906
    //   4865: dup2
    //   4866: istore 110
    //   4868: aload 106
    //   4870: iload 108
    //   4872: iload 110
    //   4874: iload 109
    //   4876: ixor
    //   4877: i2c
    //   4878: castore
    //   4879: iinc 108 1
    //   4882: goto -4076 -> 806
    //   4885: bipush 100
    //   4887: istore 110
    //   4889: goto -21 -> 4868
    //   4892: bipush 14
    //   4894: istore 110
    //   4896: goto -28 -> 4868
    //   4899: bipush 68
    //   4901: istore 110
    //   4903: goto -35 -> 4868
    //   4906: bipush 111
    //   4908: istore 110
    //   4910: goto -42 -> 4868
    //   4913: aload 111
    //   4915: iload 113
    //   4917: caload
    //   4918: istore 114
    //   4920: iload 113
    //   4922: iconst_5
    //   4923: irem
    //   4924: tableswitch	default:+32 -> 4956, 0:+53->4977, 1:+60->4984, 2:+67->4991, 3:+74->4998
    //   4957: dup2
    //   4958: istore 115
    //   4960: aload 111
    //   4962: iload 113
    //   4964: iload 115
    //   4966: iload 114
    //   4968: ixor
    //   4969: i2c
    //   4970: castore
    //   4971: iinc 113 1
    //   4974: goto -4130 -> 844
    //   4977: bipush 100
    //   4979: istore 115
    //   4981: goto -21 -> 4960
    //   4984: bipush 14
    //   4986: istore 115
    //   4988: goto -28 -> 4960
    //   4991: bipush 68
    //   4993: istore 115
    //   4995: goto -35 -> 4960
    //   4998: bipush 111
    //   5000: istore 115
    //   5002: goto -42 -> 4960
    //   5005: aload 116
    //   5007: iload 118
    //   5009: caload
    //   5010: istore 119
    //   5012: iload 118
    //   5014: iconst_5
    //   5015: irem
    //   5016: tableswitch	default:+32 -> 5048, 0:+53->5069, 1:+60->5076, 2:+67->5083, 3:+74->5090
    //   5049: dup2
    //   5050: istore 120
    //   5052: aload 116
    //   5054: iload 118
    //   5056: iload 120
    //   5058: iload 119
    //   5060: ixor
    //   5061: i2c
    //   5062: castore
    //   5063: iinc 118 1
    //   5066: goto -4184 -> 882
    //   5069: bipush 100
    //   5071: istore 120
    //   5073: goto -21 -> 5052
    //   5076: bipush 14
    //   5078: istore 120
    //   5080: goto -28 -> 5052
    //   5083: bipush 68
    //   5085: istore 120
    //   5087: goto -35 -> 5052
    //   5090: bipush 111
    //   5092: istore 120
    //   5094: goto -42 -> 5052
    //   5097: aload 121
    //   5099: iload 123
    //   5101: caload
    //   5102: istore 124
    //   5104: iload 123
    //   5106: iconst_5
    //   5107: irem
    //   5108: tableswitch	default:+32 -> 5140, 0:+53->5161, 1:+60->5168, 2:+67->5175, 3:+74->5182
    //   5141: dup2
    //   5142: istore 125
    //   5144: aload 121
    //   5146: iload 123
    //   5148: iload 125
    //   5150: iload 124
    //   5152: ixor
    //   5153: i2c
    //   5154: castore
    //   5155: iinc 123 1
    //   5158: goto -4238 -> 920
    //   5161: bipush 100
    //   5163: istore 125
    //   5165: goto -21 -> 5144
    //   5168: bipush 14
    //   5170: istore 125
    //   5172: goto -28 -> 5144
    //   5175: bipush 68
    //   5177: istore 125
    //   5179: goto -35 -> 5144
    //   5182: bipush 111
    //   5184: istore 125
    //   5186: goto -42 -> 5144
    //   5189: aload 126
    //   5191: iload 128
    //   5193: caload
    //   5194: istore 129
    //   5196: iload 128
    //   5198: iconst_5
    //   5199: irem
    //   5200: tableswitch	default:+32 -> 5232, 0:+53->5253, 1:+60->5260, 2:+67->5267, 3:+74->5274
    //   5233: dup2
    //   5234: istore 130
    //   5236: aload 126
    //   5238: iload 128
    //   5240: iload 130
    //   5242: iload 129
    //   5244: ixor
    //   5245: i2c
    //   5246: castore
    //   5247: iinc 128 1
    //   5250: goto -4292 -> 958
    //   5253: bipush 100
    //   5255: istore 130
    //   5257: goto -21 -> 5236
    //   5260: bipush 14
    //   5262: istore 130
    //   5264: goto -28 -> 5236
    //   5267: bipush 68
    //   5269: istore 130
    //   5271: goto -35 -> 5236
    //   5274: bipush 111
    //   5276: istore 130
    //   5278: goto -42 -> 5236
    //   5281: aload 131
    //   5283: iload 133
    //   5285: caload
    //   5286: istore 134
    //   5288: iload 133
    //   5290: iconst_5
    //   5291: irem
    //   5292: tableswitch	default:+32 -> 5324, 0:+53->5345, 1:+60->5352, 2:+67->5359, 3:+74->5366
    //   5325: dup2
    //   5326: istore 135
    //   5328: aload 131
    //   5330: iload 133
    //   5332: iload 135
    //   5334: iload 134
    //   5336: ixor
    //   5337: i2c
    //   5338: castore
    //   5339: iinc 133 1
    //   5342: goto -4346 -> 996
    //   5345: bipush 100
    //   5347: istore 135
    //   5349: goto -21 -> 5328
    //   5352: bipush 14
    //   5354: istore 135
    //   5356: goto -28 -> 5328
    //   5359: bipush 68
    //   5361: istore 135
    //   5363: goto -35 -> 5328
    //   5366: bipush 111
    //   5368: istore 135
    //   5370: goto -42 -> 5328
    //   5373: aload 136
    //   5375: iload 138
    //   5377: caload
    //   5378: istore 139
    //   5380: iload 138
    //   5382: iconst_5
    //   5383: irem
    //   5384: tableswitch	default:+32 -> 5416, 0:+53->5437, 1:+60->5444, 2:+67->5451, 3:+74->5458
    //   5417: dup2
    //   5418: istore 140
    //   5420: aload 136
    //   5422: iload 138
    //   5424: iload 140
    //   5426: iload 139
    //   5428: ixor
    //   5429: i2c
    //   5430: castore
    //   5431: iinc 138 1
    //   5434: goto -4400 -> 1034
    //   5437: bipush 100
    //   5439: istore 140
    //   5441: goto -21 -> 5420
    //   5444: bipush 14
    //   5446: istore 140
    //   5448: goto -28 -> 5420
    //   5451: bipush 68
    //   5453: istore 140
    //   5455: goto -35 -> 5420
    //   5458: bipush 111
    //   5460: istore 140
    //   5462: goto -42 -> 5420
    //   5465: aload 141
    //   5467: iload 143
    //   5469: caload
    //   5470: istore 144
    //   5472: iload 143
    //   5474: iconst_5
    //   5475: irem
    //   5476: tableswitch	default:+32 -> 5508, 0:+53->5529, 1:+60->5536, 2:+67->5543, 3:+74->5550
    //   5509: dup2
    //   5510: istore 145
    //   5512: aload 141
    //   5514: iload 143
    //   5516: iload 145
    //   5518: iload 144
    //   5520: ixor
    //   5521: i2c
    //   5522: castore
    //   5523: iinc 143 1
    //   5526: goto -4454 -> 1072
    //   5529: bipush 100
    //   5531: istore 145
    //   5533: goto -21 -> 5512
    //   5536: bipush 14
    //   5538: istore 145
    //   5540: goto -28 -> 5512
    //   5543: bipush 68
    //   5545: istore 145
    //   5547: goto -35 -> 5512
    //   5550: bipush 111
    //   5552: istore 145
    //   5554: goto -42 -> 5512
    //   5557: aload 146
    //   5559: iload 148
    //   5561: caload
    //   5562: istore 149
    //   5564: iload 148
    //   5566: iconst_5
    //   5567: irem
    //   5568: tableswitch	default:+32 -> 5600, 0:+53->5621, 1:+60->5628, 2:+67->5635, 3:+74->5642
    //   5601: dup2
    //   5602: istore 150
    //   5604: aload 146
    //   5606: iload 148
    //   5608: iload 150
    //   5610: iload 149
    //   5612: ixor
    //   5613: i2c
    //   5614: castore
    //   5615: iinc 148 1
    //   5618: goto -4508 -> 1110
    //   5621: bipush 100
    //   5623: istore 150
    //   5625: goto -21 -> 5604
    //   5628: bipush 14
    //   5630: istore 150
    //   5632: goto -28 -> 5604
    //   5635: bipush 68
    //   5637: istore 150
    //   5639: goto -35 -> 5604
    //   5642: bipush 111
    //   5644: istore 150
    //   5646: goto -42 -> 5604
    //   5649: aload 151
    //   5651: iload 153
    //   5653: caload
    //   5654: istore 154
    //   5656: iload 153
    //   5658: iconst_5
    //   5659: irem
    //   5660: tableswitch	default:+32 -> 5692, 0:+53->5713, 1:+60->5720, 2:+67->5727, 3:+74->5734
    //   5693: dup2
    //   5694: istore 155
    //   5696: aload 151
    //   5698: iload 153
    //   5700: iload 155
    //   5702: iload 154
    //   5704: ixor
    //   5705: i2c
    //   5706: castore
    //   5707: iinc 153 1
    //   5710: goto -4562 -> 1148
    //   5713: bipush 100
    //   5715: istore 155
    //   5717: goto -21 -> 5696
    //   5720: bipush 14
    //   5722: istore 155
    //   5724: goto -28 -> 5696
    //   5727: bipush 68
    //   5729: istore 155
    //   5731: goto -35 -> 5696
    //   5734: bipush 111
    //   5736: istore 155
    //   5738: goto -42 -> 5696
    //   5741: aload 156
    //   5743: iload 158
    //   5745: caload
    //   5746: istore 159
    //   5748: iload 158
    //   5750: iconst_5
    //   5751: irem
    //   5752: tableswitch	default:+32 -> 5784, 0:+53->5805, 1:+60->5812, 2:+67->5819, 3:+74->5826
    //   5785: dup2
    //   5786: istore 160
    //   5788: aload 156
    //   5790: iload 158
    //   5792: iload 160
    //   5794: iload 159
    //   5796: ixor
    //   5797: i2c
    //   5798: castore
    //   5799: iinc 158 1
    //   5802: goto -4616 -> 1186
    //   5805: bipush 100
    //   5807: istore 160
    //   5809: goto -21 -> 5788
    //   5812: bipush 14
    //   5814: istore 160
    //   5816: goto -28 -> 5788
    //   5819: bipush 68
    //   5821: istore 160
    //   5823: goto -35 -> 5788
    //   5826: bipush 111
    //   5828: istore 160
    //   5830: goto -42 -> 5788
    //   5833: aload 161
    //   5835: iload 163
    //   5837: caload
    //   5838: istore 164
    //   5840: iload 163
    //   5842: iconst_5
    //   5843: irem
    //   5844: tableswitch	default:+32 -> 5876, 0:+53->5897, 1:+60->5904, 2:+67->5911, 3:+74->5918
    //   5877: dup2
    //   5878: istore 165
    //   5880: aload 161
    //   5882: iload 163
    //   5884: iload 165
    //   5886: iload 164
    //   5888: ixor
    //   5889: i2c
    //   5890: castore
    //   5891: iinc 163 1
    //   5894: goto -4670 -> 1224
    //   5897: bipush 100
    //   5899: istore 165
    //   5901: goto -21 -> 5880
    //   5904: bipush 14
    //   5906: istore 165
    //   5908: goto -28 -> 5880
    //   5911: bipush 68
    //   5913: istore 165
    //   5915: goto -35 -> 5880
    //   5918: bipush 111
    //   5920: istore 165
    //   5922: goto -42 -> 5880
    //   5925: aload 166
    //   5927: iload 168
    //   5929: caload
    //   5930: istore 169
    //   5932: iload 168
    //   5934: iconst_5
    //   5935: irem
    //   5936: tableswitch	default:+32 -> 5968, 0:+53->5989, 1:+60->5996, 2:+67->6003, 3:+74->6010
    //   5969: dup2
    //   5970: istore 170
    //   5972: aload 166
    //   5974: iload 168
    //   5976: iload 170
    //   5978: iload 169
    //   5980: ixor
    //   5981: i2c
    //   5982: castore
    //   5983: iinc 168 1
    //   5986: goto -4724 -> 1262
    //   5989: bipush 100
    //   5991: istore 170
    //   5993: goto -21 -> 5972
    //   5996: bipush 14
    //   5998: istore 170
    //   6000: goto -28 -> 5972
    //   6003: bipush 68
    //   6005: istore 170
    //   6007: goto -35 -> 5972
    //   6010: bipush 111
    //   6012: istore 170
    //   6014: goto -42 -> 5972
    //   6017: aload 171
    //   6019: iload 173
    //   6021: caload
    //   6022: istore 174
    //   6024: iload 173
    //   6026: iconst_5
    //   6027: irem
    //   6028: tableswitch	default:+32 -> 6060, 0:+53->6081, 1:+60->6088, 2:+67->6095, 3:+74->6102
    //   6061: dup2
    //   6062: istore 175
    //   6064: aload 171
    //   6066: iload 173
    //   6068: iload 175
    //   6070: iload 174
    //   6072: ixor
    //   6073: i2c
    //   6074: castore
    //   6075: iinc 173 1
    //   6078: goto -4778 -> 1300
    //   6081: bipush 100
    //   6083: istore 175
    //   6085: goto -21 -> 6064
    //   6088: bipush 14
    //   6090: istore 175
    //   6092: goto -28 -> 6064
    //   6095: bipush 68
    //   6097: istore 175
    //   6099: goto -35 -> 6064
    //   6102: bipush 111
    //   6104: istore 175
    //   6106: goto -42 -> 6064
    //   6109: aload 176
    //   6111: iload 178
    //   6113: caload
    //   6114: istore 179
    //   6116: iload 178
    //   6118: iconst_5
    //   6119: irem
    //   6120: tableswitch	default:+32 -> 6152, 0:+53->6173, 1:+60->6180, 2:+67->6187, 3:+74->6194
    //   6153: dup2
    //   6154: istore 180
    //   6156: aload 176
    //   6158: iload 178
    //   6160: iload 180
    //   6162: iload 179
    //   6164: ixor
    //   6165: i2c
    //   6166: castore
    //   6167: iinc 178 1
    //   6170: goto -4832 -> 1338
    //   6173: bipush 100
    //   6175: istore 180
    //   6177: goto -21 -> 6156
    //   6180: bipush 14
    //   6182: istore 180
    //   6184: goto -28 -> 6156
    //   6187: bipush 68
    //   6189: istore 180
    //   6191: goto -35 -> 6156
    //   6194: bipush 111
    //   6196: istore 180
    //   6198: goto -42 -> 6156
    //   6201: aload 181
    //   6203: iload 183
    //   6205: caload
    //   6206: istore 184
    //   6208: iload 183
    //   6210: iconst_5
    //   6211: irem
    //   6212: tableswitch	default:+32 -> 6244, 0:+53->6265, 1:+60->6272, 2:+67->6279, 3:+74->6286
    //   6245: dup2
    //   6246: istore 185
    //   6248: aload 181
    //   6250: iload 183
    //   6252: iload 185
    //   6254: iload 184
    //   6256: ixor
    //   6257: i2c
    //   6258: castore
    //   6259: iinc 183 1
    //   6262: goto -4886 -> 1376
    //   6265: bipush 100
    //   6267: istore 185
    //   6269: goto -21 -> 6248
    //   6272: bipush 14
    //   6274: istore 185
    //   6276: goto -28 -> 6248
    //   6279: bipush 68
    //   6281: istore 185
    //   6283: goto -35 -> 6248
    //   6286: bipush 111
    //   6288: istore 185
    //   6290: goto -42 -> 6248
    //   6293: aload 186
    //   6295: iload 188
    //   6297: caload
    //   6298: istore 189
    //   6300: iload 188
    //   6302: iconst_5
    //   6303: irem
    //   6304: tableswitch	default:+32 -> 6336, 0:+53->6357, 1:+60->6364, 2:+67->6371, 3:+74->6378
    //   6337: dup2
    //   6338: istore 190
    //   6340: aload 186
    //   6342: iload 188
    //   6344: iload 190
    //   6346: iload 189
    //   6348: ixor
    //   6349: i2c
    //   6350: castore
    //   6351: iinc 188 1
    //   6354: goto -4940 -> 1414
    //   6357: bipush 100
    //   6359: istore 190
    //   6361: goto -21 -> 6340
    //   6364: bipush 14
    //   6366: istore 190
    //   6368: goto -28 -> 6340
    //   6371: bipush 68
    //   6373: istore 190
    //   6375: goto -35 -> 6340
    //   6378: bipush 111
    //   6380: istore 190
    //   6382: goto -42 -> 6340
    //   6385: aload 191
    //   6387: iload 193
    //   6389: caload
    //   6390: istore 194
    //   6392: iload 193
    //   6394: iconst_5
    //   6395: irem
    //   6396: tableswitch	default:+32 -> 6428, 0:+53->6449, 1:+60->6456, 2:+67->6463, 3:+74->6470
    //   6429: dup2
    //   6430: istore 195
    //   6432: aload 191
    //   6434: iload 193
    //   6436: iload 195
    //   6438: iload 194
    //   6440: ixor
    //   6441: i2c
    //   6442: castore
    //   6443: iinc 193 1
    //   6446: goto -4994 -> 1452
    //   6449: bipush 100
    //   6451: istore 195
    //   6453: goto -21 -> 6432
    //   6456: bipush 14
    //   6458: istore 195
    //   6460: goto -28 -> 6432
    //   6463: bipush 68
    //   6465: istore 195
    //   6467: goto -35 -> 6432
    //   6470: bipush 111
    //   6472: istore 195
    //   6474: goto -42 -> 6432
    //   6477: aload 196
    //   6479: iload 198
    //   6481: caload
    //   6482: istore 199
    //   6484: iload 198
    //   6486: iconst_5
    //   6487: irem
    //   6488: tableswitch	default:+32 -> 6520, 0:+53->6541, 1:+60->6548, 2:+67->6555, 3:+74->6562
    //   6521: dup2
    //   6522: istore 200
    //   6524: aload 196
    //   6526: iload 198
    //   6528: iload 200
    //   6530: iload 199
    //   6532: ixor
    //   6533: i2c
    //   6534: castore
    //   6535: iinc 198 1
    //   6538: goto -5048 -> 1490
    //   6541: bipush 100
    //   6543: istore 200
    //   6545: goto -21 -> 6524
    //   6548: bipush 14
    //   6550: istore 200
    //   6552: goto -28 -> 6524
    //   6555: bipush 68
    //   6557: istore 200
    //   6559: goto -35 -> 6524
    //   6562: bipush 111
    //   6564: istore 200
    //   6566: goto -42 -> 6524
    //   6569: aload 201
    //   6571: iload 203
    //   6573: caload
    //   6574: istore 204
    //   6576: iload 203
    //   6578: iconst_5
    //   6579: irem
    //   6580: tableswitch	default:+32 -> 6612, 0:+53->6633, 1:+60->6640, 2:+67->6647, 3:+74->6654
    //   6613: dup2
    //   6614: istore 205
    //   6616: aload 201
    //   6618: iload 203
    //   6620: iload 205
    //   6622: iload 204
    //   6624: ixor
    //   6625: i2c
    //   6626: castore
    //   6627: iinc 203 1
    //   6630: goto -5102 -> 1528
    //   6633: bipush 100
    //   6635: istore 205
    //   6637: goto -21 -> 6616
    //   6640: bipush 14
    //   6642: istore 205
    //   6644: goto -28 -> 6616
    //   6647: bipush 68
    //   6649: istore 205
    //   6651: goto -35 -> 6616
    //   6654: bipush 111
    //   6656: istore 205
    //   6658: goto -42 -> 6616
    //   6661: aload 206
    //   6663: iload 208
    //   6665: caload
    //   6666: istore 209
    //   6668: iload 208
    //   6670: iconst_5
    //   6671: irem
    //   6672: tableswitch	default:+32 -> 6704, 0:+53->6725, 1:+60->6732, 2:+67->6739, 3:+74->6746
    //   6705: dup2
    //   6706: istore 210
    //   6708: aload 206
    //   6710: iload 208
    //   6712: iload 210
    //   6714: iload 209
    //   6716: ixor
    //   6717: i2c
    //   6718: castore
    //   6719: iinc 208 1
    //   6722: goto -5156 -> 1566
    //   6725: bipush 100
    //   6727: istore 210
    //   6729: goto -21 -> 6708
    //   6732: bipush 14
    //   6734: istore 210
    //   6736: goto -28 -> 6708
    //   6739: bipush 68
    //   6741: istore 210
    //   6743: goto -35 -> 6708
    //   6746: bipush 111
    //   6748: istore 210
    //   6750: goto -42 -> 6708
    //   6753: aload 211
    //   6755: iload 213
    //   6757: caload
    //   6758: istore 214
    //   6760: iload 213
    //   6762: iconst_5
    //   6763: irem
    //   6764: tableswitch	default:+32 -> 6796, 0:+53->6817, 1:+60->6824, 2:+67->6831, 3:+74->6838
    //   6797: dup2
    //   6798: istore 215
    //   6800: aload 211
    //   6802: iload 213
    //   6804: iload 215
    //   6806: iload 214
    //   6808: ixor
    //   6809: i2c
    //   6810: castore
    //   6811: iinc 213 1
    //   6814: goto -5210 -> 1604
    //   6817: bipush 100
    //   6819: istore 215
    //   6821: goto -21 -> 6800
    //   6824: bipush 14
    //   6826: istore 215
    //   6828: goto -28 -> 6800
    //   6831: bipush 68
    //   6833: istore 215
    //   6835: goto -35 -> 6800
    //   6838: bipush 111
    //   6840: istore 215
    //   6842: goto -42 -> 6800
    //   6845: aload 216
    //   6847: iload 218
    //   6849: caload
    //   6850: istore 219
    //   6852: iload 218
    //   6854: iconst_5
    //   6855: irem
    //   6856: tableswitch	default:+32 -> 6888, 0:+53->6909, 1:+60->6916, 2:+67->6923, 3:+74->6930
    //   6889: dup2
    //   6890: istore 220
    //   6892: aload 216
    //   6894: iload 218
    //   6896: iload 220
    //   6898: iload 219
    //   6900: ixor
    //   6901: i2c
    //   6902: castore
    //   6903: iinc 218 1
    //   6906: goto -5264 -> 1642
    //   6909: bipush 100
    //   6911: istore 220
    //   6913: goto -21 -> 6892
    //   6916: bipush 14
    //   6918: istore 220
    //   6920: goto -28 -> 6892
    //   6923: bipush 68
    //   6925: istore 220
    //   6927: goto -35 -> 6892
    //   6930: bipush 111
    //   6932: istore 220
    //   6934: goto -42 -> 6892
    //   6937: aload 221
    //   6939: iload 223
    //   6941: caload
    //   6942: istore 224
    //   6944: iload 223
    //   6946: iconst_5
    //   6947: irem
    //   6948: tableswitch	default:+32 -> 6980, 0:+53->7001, 1:+60->7008, 2:+67->7015, 3:+74->7022
    //   6981: dup2
    //   6982: istore 225
    //   6984: aload 221
    //   6986: iload 223
    //   6988: iload 225
    //   6990: iload 224
    //   6992: ixor
    //   6993: i2c
    //   6994: castore
    //   6995: iinc 223 1
    //   6998: goto -5318 -> 1680
    //   7001: bipush 100
    //   7003: istore 225
    //   7005: goto -21 -> 6984
    //   7008: bipush 14
    //   7010: istore 225
    //   7012: goto -28 -> 6984
    //   7015: bipush 68
    //   7017: istore 225
    //   7019: goto -35 -> 6984
    //   7022: bipush 111
    //   7024: istore 225
    //   7026: goto -42 -> 6984
    //   7029: aload 226
    //   7031: iload 228
    //   7033: caload
    //   7034: istore 229
    //   7036: iload 228
    //   7038: iconst_5
    //   7039: irem
    //   7040: tableswitch	default:+32 -> 7072, 0:+53->7093, 1:+60->7100, 2:+67->7107, 3:+74->7114
    //   7073: dup2
    //   7074: istore 230
    //   7076: aload 226
    //   7078: iload 228
    //   7080: iload 230
    //   7082: iload 229
    //   7084: ixor
    //   7085: i2c
    //   7086: castore
    //   7087: iinc 228 1
    //   7090: goto -5372 -> 1718
    //   7093: bipush 100
    //   7095: istore 230
    //   7097: goto -21 -> 7076
    //   7100: bipush 14
    //   7102: istore 230
    //   7104: goto -28 -> 7076
    //   7107: bipush 68
    //   7109: istore 230
    //   7111: goto -35 -> 7076
    //   7114: bipush 111
    //   7116: istore 230
    //   7118: goto -42 -> 7076
    //   7121: aload 231
    //   7123: iload 233
    //   7125: caload
    //   7126: istore 234
    //   7128: iload 233
    //   7130: iconst_5
    //   7131: irem
    //   7132: tableswitch	default:+32 -> 7164, 0:+53->7185, 1:+60->7192, 2:+67->7199, 3:+74->7206
    //   7165: dup2
    //   7166: istore 235
    //   7168: aload 231
    //   7170: iload 233
    //   7172: iload 235
    //   7174: iload 234
    //   7176: ixor
    //   7177: i2c
    //   7178: castore
    //   7179: iinc 233 1
    //   7182: goto -5426 -> 1756
    //   7185: bipush 100
    //   7187: istore 235
    //   7189: goto -21 -> 7168
    //   7192: bipush 14
    //   7194: istore 235
    //   7196: goto -28 -> 7168
    //   7199: bipush 68
    //   7201: istore 235
    //   7203: goto -35 -> 7168
    //   7206: bipush 111
    //   7208: istore 235
    //   7210: goto -42 -> 7168
    //   7213: aload 236
    //   7215: iload 238
    //   7217: caload
    //   7218: istore 239
    //   7220: iload 238
    //   7222: iconst_5
    //   7223: irem
    //   7224: tableswitch	default:+32 -> 7256, 0:+53->7277, 1:+60->7284, 2:+67->7291, 3:+74->7298
    //   7257: dup2
    //   7258: istore 240
    //   7260: aload 236
    //   7262: iload 238
    //   7264: iload 240
    //   7266: iload 239
    //   7268: ixor
    //   7269: i2c
    //   7270: castore
    //   7271: iinc 238 1
    //   7274: goto -5480 -> 1794
    //   7277: bipush 100
    //   7279: istore 240
    //   7281: goto -21 -> 7260
    //   7284: bipush 14
    //   7286: istore 240
    //   7288: goto -28 -> 7260
    //   7291: bipush 68
    //   7293: istore 240
    //   7295: goto -35 -> 7260
    //   7298: bipush 111
    //   7300: istore 240
    //   7302: goto -42 -> 7260
    //   7305: aload 241
    //   7307: iload 243
    //   7309: caload
    //   7310: istore 244
    //   7312: iload 243
    //   7314: iconst_5
    //   7315: irem
    //   7316: tableswitch	default:+32 -> 7348, 0:+53->7369, 1:+60->7376, 2:+67->7383, 3:+74->7390
    //   7349: dup2
    //   7350: istore 245
    //   7352: aload 241
    //   7354: iload 243
    //   7356: iload 245
    //   7358: iload 244
    //   7360: ixor
    //   7361: i2c
    //   7362: castore
    //   7363: iinc 243 1
    //   7366: goto -5534 -> 1832
    //   7369: bipush 100
    //   7371: istore 245
    //   7373: goto -21 -> 7352
    //   7376: bipush 14
    //   7378: istore 245
    //   7380: goto -28 -> 7352
    //   7383: bipush 68
    //   7385: istore 245
    //   7387: goto -35 -> 7352
    //   7390: bipush 111
    //   7392: istore 245
    //   7394: goto -42 -> 7352
    //   7397: aload 246
    //   7399: iload 248
    //   7401: caload
    //   7402: istore 249
    //   7404: iload 248
    //   7406: iconst_5
    //   7407: irem
    //   7408: tableswitch	default:+32 -> 7440, 0:+53->7461, 1:+60->7468, 2:+67->7475, 3:+74->7482
    //   7441: dup2
    //   7442: istore 250
    //   7444: aload 246
    //   7446: iload 248
    //   7448: iload 250
    //   7450: iload 249
    //   7452: ixor
    //   7453: i2c
    //   7454: castore
    //   7455: iinc 248 1
    //   7458: goto -5588 -> 1870
    //   7461: bipush 100
    //   7463: istore 250
    //   7465: goto -21 -> 7444
    //   7468: bipush 14
    //   7470: istore 250
    //   7472: goto -28 -> 7444
    //   7475: bipush 68
    //   7477: istore 250
    //   7479: goto -35 -> 7444
    //   7482: bipush 111
    //   7484: istore 250
    //   7486: goto -42 -> 7444
    //   7489: aload 251
    //   7491: iload 253
    //   7493: caload
    //   7494: istore 254
    //   7496: iload 253
    //   7498: iconst_5
    //   7499: irem
    //   7500: tableswitch	default:+32 -> 7532, 0:+53->7553, 1:+60->7560, 2:+67->7567, 3:+74->7574
    //   7533: dup2
    //   7534: istore 255
    //   7536: aload 251
    //   7538: iload 253
    //   7540: iload 255
    //   7542: iload 254
    //   7544: ixor
    //   7545: i2c
    //   7546: castore
    //   7547: iinc 253 1
    //   7550: goto -5642 -> 1908
    //   7553: bipush 100
    //   7555: istore 255
    //   7557: goto -21 -> 7536
    //   7560: bipush 14
    //   7562: istore 255
    //   7564: goto -28 -> 7536
    //   7567: bipush 68
    //   7569: istore 255
    //   7571: goto -35 -> 7536
    //   7574: bipush 111
    //   7576: istore 255
    //   7578: goto -42 -> 7536
    //   7581: wide
    //   7585: wide
    //   7589: caload
    //   7590: wide
    //   7594: wide
    //   7598: iconst_5
    //   7599: irem
    //   7600: tableswitch	default:+32 -> 7632, 0:+66->7666, 1:+75->7675, 2:+84->7684, 3:+93->7693
    //   7633: dup2
    //   7634: wide
    //   7638: wide
    //   7642: wide
    //   7646: wide
    //   7650: wide
    //   7654: ixor
    //   7655: i2c
    //   7656: castore
    //   7657: wide
    //   7663: goto -5709 -> 1954
    //   7666: bipush 100
    //   7668: wide
    //   7672: goto -34 -> 7638
    //   7675: bipush 14
    //   7677: wide
    //   7681: goto -43 -> 7638
    //   7684: bipush 68
    //   7686: wide
    //   7690: goto -52 -> 7638
    //   7693: bipush 111
    //   7695: wide
    //   7699: goto -61 -> 7638
    //   7702: wide
    //   7706: wide
    //   7710: caload
    //   7711: wide
    //   7715: wide
    //   7719: iconst_5
    //   7720: irem
    //   7721: tableswitch	default:+31 -> 7752, 0:+65->7786, 1:+74->7795, 2:+83->7804, 3:+92->7813
    //   7753: dup2
    //   7754: wide
    //   7758: wide
    //   7762: wide
    //   7766: wide
    //   7770: wide
    //   7774: ixor
    //   7775: i2c
    //   7776: castore
    //   7777: wide
    //   7783: goto -5777 -> 2006
    //   7786: bipush 100
    //   7788: wide
    //   7792: goto -34 -> 7758
    //   7795: bipush 14
    //   7797: wide
    //   7801: goto -43 -> 7758
    //   7804: bipush 68
    //   7806: wide
    //   7810: goto -52 -> 7758
    //   7813: bipush 111
    //   7815: wide
    //   7819: goto -61 -> 7758
    //   7822: wide
    //   7826: wide
    //   7830: caload
    //   7831: wide
    //   7835: wide
    //   7839: iconst_5
    //   7840: irem
    //   7841: tableswitch	default:+31 -> 7872, 0:+65->7906, 1:+74->7915, 2:+83->7924, 3:+92->7933
    //   7873: dup2
    //   7874: wide
    //   7878: wide
    //   7882: wide
    //   7886: wide
    //   7890: wide
    //   7894: ixor
    //   7895: i2c
    //   7896: castore
    //   7897: wide
    //   7903: goto -5845 -> 2058
    //   7906: bipush 100
    //   7908: wide
    //   7912: goto -34 -> 7878
    //   7915: bipush 14
    //   7917: wide
    //   7921: goto -43 -> 7878
    //   7924: bipush 68
    //   7926: wide
    //   7930: goto -52 -> 7878
    //   7933: bipush 111
    //   7935: wide
    //   7939: goto -61 -> 7878
    //   7942: wide
    //   7946: wide
    //   7950: caload
    //   7951: wide
    //   7955: wide
    //   7959: iconst_5
    //   7960: irem
    //   7961: tableswitch	default:+31 -> 7992, 0:+65->8026, 1:+74->8035, 2:+83->8044, 3:+92->8053
    //   7993: dup2
    //   7994: wide
    //   7998: wide
    //   8002: wide
    //   8006: wide
    //   8010: wide
    //   8014: ixor
    //   8015: i2c
    //   8016: castore
    //   8017: wide
    //   8023: goto -5913 -> 2110
    //   8026: bipush 100
    //   8028: wide
    //   8032: goto -34 -> 7998
    //   8035: bipush 14
    //   8037: wide
    //   8041: goto -43 -> 7998
    //   8044: bipush 68
    //   8046: wide
    //   8050: goto -52 -> 7998
    //   8053: bipush 111
    //   8055: wide
    //   8059: goto -61 -> 7998
    //   8062: wide
    //   8066: wide
    //   8070: caload
    //   8071: wide
    //   8075: wide
    //   8079: iconst_5
    //   8080: irem
    //   8081: tableswitch	default:+31 -> 8112, 0:+65->8146, 1:+74->8155, 2:+83->8164, 3:+92->8173
    //   8113: dup2
    //   8114: wide
    //   8118: wide
    //   8122: wide
    //   8126: wide
    //   8130: wide
    //   8134: ixor
    //   8135: i2c
    //   8136: castore
    //   8137: wide
    //   8143: goto -5981 -> 2162
    //   8146: bipush 100
    //   8148: wide
    //   8152: goto -34 -> 8118
    //   8155: bipush 14
    //   8157: wide
    //   8161: goto -43 -> 8118
    //   8164: bipush 68
    //   8166: wide
    //   8170: goto -52 -> 8118
    //   8173: bipush 111
    //   8175: wide
    //   8179: goto -61 -> 8118
    //   8182: wide
    //   8186: wide
    //   8190: caload
    //   8191: wide
    //   8195: wide
    //   8199: iconst_5
    //   8200: irem
    //   8201: tableswitch	default:+31 -> 8232, 0:+65->8266, 1:+74->8275, 2:+83->8284, 3:+92->8293
    //   8233: dup2
    //   8234: wide
    //   8238: wide
    //   8242: wide
    //   8246: wide
    //   8250: wide
    //   8254: ixor
    //   8255: i2c
    //   8256: castore
    //   8257: wide
    //   8263: goto -6049 -> 2214
    //   8266: bipush 100
    //   8268: wide
    //   8272: goto -34 -> 8238
    //   8275: bipush 14
    //   8277: wide
    //   8281: goto -43 -> 8238
    //   8284: bipush 68
    //   8286: wide
    //   8290: goto -52 -> 8238
    //   8293: bipush 111
    //   8295: wide
    //   8299: goto -61 -> 8238
    //   8302: wide
    //   8306: wide
    //   8310: caload
    //   8311: wide
    //   8315: wide
    //   8319: iconst_5
    //   8320: irem
    //   8321: tableswitch	default:+31 -> 8352, 0:+65->8386, 1:+74->8395, 2:+83->8404, 3:+92->8413
    //   8353: dup2
    //   8354: wide
    //   8358: wide
    //   8362: wide
    //   8366: wide
    //   8370: wide
    //   8374: ixor
    //   8375: i2c
    //   8376: castore
    //   8377: wide
    //   8383: goto -6117 -> 2266
    //   8386: bipush 100
    //   8388: wide
    //   8392: goto -34 -> 8358
    //   8395: bipush 14
    //   8397: wide
    //   8401: goto -43 -> 8358
    //   8404: bipush 68
    //   8406: wide
    //   8410: goto -52 -> 8358
    //   8413: bipush 111
    //   8415: wide
    //   8419: goto -61 -> 8358
    //   8422: wide
    //   8426: wide
    //   8430: caload
    //   8431: wide
    //   8435: wide
    //   8439: iconst_5
    //   8440: irem
    //   8441: tableswitch	default:+31 -> 8472, 0:+65->8506, 1:+74->8515, 2:+83->8524, 3:+92->8533
    //   8473: dup2
    //   8474: wide
    //   8478: wide
    //   8482: wide
    //   8486: wide
    //   8490: wide
    //   8494: ixor
    //   8495: i2c
    //   8496: castore
    //   8497: wide
    //   8503: goto -6185 -> 2318
    //   8506: bipush 100
    //   8508: wide
    //   8512: goto -34 -> 8478
    //   8515: bipush 14
    //   8517: wide
    //   8521: goto -43 -> 8478
    //   8524: bipush 68
    //   8526: wide
    //   8530: goto -52 -> 8478
    //   8533: bipush 111
    //   8535: wide
    //   8539: goto -61 -> 8478
    //   8542: wide
    //   8546: wide
    //   8550: caload
    //   8551: wide
    //   8555: wide
    //   8559: iconst_5
    //   8560: irem
    //   8561: tableswitch	default:+31 -> 8592, 0:+65->8626, 1:+74->8635, 2:+83->8644, 3:+92->8653
    //   8593: dup2
    //   8594: wide
    //   8598: wide
    //   8602: wide
    //   8606: wide
    //   8610: wide
    //   8614: ixor
    //   8615: i2c
    //   8616: castore
    //   8617: wide
    //   8623: goto -6253 -> 2370
    //   8626: bipush 100
    //   8628: wide
    //   8632: goto -34 -> 8598
    //   8635: bipush 14
    //   8637: wide
    //   8641: goto -43 -> 8598
    //   8644: bipush 68
    //   8646: wide
    //   8650: goto -52 -> 8598
    //   8653: bipush 111
    //   8655: wide
    //   8659: goto -61 -> 8598
    //   8662: wide
    //   8666: wide
    //   8670: caload
    //   8671: wide
    //   8675: wide
    //   8679: iconst_5
    //   8680: irem
    //   8681: tableswitch	default:+31 -> 8712, 0:+65->8746, 1:+74->8755, 2:+83->8764, 3:+92->8773
    //   8713: dup2
    //   8714: wide
    //   8718: wide
    //   8722: wide
    //   8726: wide
    //   8730: wide
    //   8734: ixor
    //   8735: i2c
    //   8736: castore
    //   8737: wide
    //   8743: goto -6321 -> 2422
    //   8746: bipush 100
    //   8748: wide
    //   8752: goto -34 -> 8718
    //   8755: bipush 14
    //   8757: wide
    //   8761: goto -43 -> 8718
    //   8764: bipush 68
    //   8766: wide
    //   8770: goto -52 -> 8718
    //   8773: bipush 111
    //   8775: wide
    //   8779: goto -61 -> 8718
    //   8782: wide
    //   8786: wide
    //   8790: caload
    //   8791: wide
    //   8795: wide
    //   8799: iconst_5
    //   8800: irem
    //   8801: tableswitch	default:+31 -> 8832, 0:+65->8866, 1:+74->8875, 2:+83->8884, 3:+92->8893
    //   8833: dup2
    //   8834: wide
    //   8838: wide
    //   8842: wide
    //   8846: wide
    //   8850: wide
    //   8854: ixor
    //   8855: i2c
    //   8856: castore
    //   8857: wide
    //   8863: goto -6389 -> 2474
    //   8866: bipush 100
    //   8868: wide
    //   8872: goto -34 -> 8838
    //   8875: bipush 14
    //   8877: wide
    //   8881: goto -43 -> 8838
    //   8884: bipush 68
    //   8886: wide
    //   8890: goto -52 -> 8838
    //   8893: bipush 111
    //   8895: wide
    //   8899: goto -61 -> 8838
    //   8902: wide
    //   8906: wide
    //   8910: caload
    //   8911: wide
    //   8915: wide
    //   8919: iconst_5
    //   8920: irem
    //   8921: tableswitch	default:+31 -> 8952, 0:+65->8986, 1:+74->8995, 2:+83->9004, 3:+92->9013
    //   8953: dup2
    //   8954: wide
    //   8958: wide
    //   8962: wide
    //   8966: wide
    //   8970: wide
    //   8974: ixor
    //   8975: i2c
    //   8976: castore
    //   8977: wide
    //   8983: goto -6457 -> 2526
    //   8986: bipush 100
    //   8988: wide
    //   8992: goto -34 -> 8958
    //   8995: bipush 14
    //   8997: wide
    //   9001: goto -43 -> 8958
    //   9004: bipush 68
    //   9006: wide
    //   9010: goto -52 -> 8958
    //   9013: bipush 111
    //   9015: wide
    //   9019: goto -61 -> 8958
    //   9022: wide
    //   9026: wide
    //   9030: caload
    //   9031: wide
    //   9035: wide
    //   9039: iconst_5
    //   9040: irem
    //   9041: tableswitch	default:+31 -> 9072, 0:+65->9106, 1:+74->9115, 2:+83->9124, 3:+92->9133
    //   9073: dup2
    //   9074: wide
    //   9078: wide
    //   9082: wide
    //   9086: wide
    //   9090: wide
    //   9094: ixor
    //   9095: i2c
    //   9096: castore
    //   9097: wide
    //   9103: goto -6525 -> 2578
    //   9106: bipush 100
    //   9108: wide
    //   9112: goto -34 -> 9078
    //   9115: bipush 14
    //   9117: wide
    //   9121: goto -43 -> 9078
    //   9124: bipush 68
    //   9126: wide
    //   9130: goto -52 -> 9078
    //   9133: bipush 111
    //   9135: wide
    //   9139: goto -61 -> 9078
    //   9142: wide
    //   9146: wide
    //   9150: caload
    //   9151: wide
    //   9155: wide
    //   9159: iconst_5
    //   9160: irem
    //   9161: tableswitch	default:+31 -> 9192, 0:+65->9226, 1:+74->9235, 2:+83->9244, 3:+92->9253
    //   9193: dup2
    //   9194: wide
    //   9198: wide
    //   9202: wide
    //   9206: wide
    //   9210: wide
    //   9214: ixor
    //   9215: i2c
    //   9216: castore
    //   9217: wide
    //   9223: goto -6593 -> 2630
    //   9226: bipush 100
    //   9228: wide
    //   9232: goto -34 -> 9198
    //   9235: bipush 14
    //   9237: wide
    //   9241: goto -43 -> 9198
    //   9244: bipush 68
    //   9246: wide
    //   9250: goto -52 -> 9198
    //   9253: bipush 111
    //   9255: wide
    //   9259: goto -61 -> 9198
    //   9262: wide
    //   9266: wide
    //   9270: caload
    //   9271: wide
    //   9275: wide
    //   9279: iconst_5
    //   9280: irem
    //   9281: tableswitch	default:+31 -> 9312, 0:+65->9346, 1:+74->9355, 2:+83->9364, 3:+92->9373
    //   9313: dup2
    //   9314: wide
    //   9318: wide
    //   9322: wide
    //   9326: wide
    //   9330: wide
    //   9334: ixor
    //   9335: i2c
    //   9336: castore
    //   9337: wide
    //   9343: goto -6661 -> 2682
    //   9346: bipush 100
    //   9348: wide
    //   9352: goto -34 -> 9318
    //   9355: bipush 14
    //   9357: wide
    //   9361: goto -43 -> 9318
    //   9364: bipush 68
    //   9366: wide
    //   9370: goto -52 -> 9318
    //   9373: bipush 111
    //   9375: wide
    //   9379: goto -61 -> 9318
    //   9382: wide
    //   9386: wide
    //   9390: caload
    //   9391: wide
    //   9395: wide
    //   9399: iconst_5
    //   9400: irem
    //   9401: tableswitch	default:+31 -> 9432, 0:+65->9466, 1:+74->9475, 2:+83->9484, 3:+92->9493
    //   9433: dup2
    //   9434: wide
    //   9438: wide
    //   9442: wide
    //   9446: wide
    //   9450: wide
    //   9454: ixor
    //   9455: i2c
    //   9456: castore
    //   9457: wide
    //   9463: goto -6729 -> 2734
    //   9466: bipush 100
    //   9468: wide
    //   9472: goto -34 -> 9438
    //   9475: bipush 14
    //   9477: wide
    //   9481: goto -43 -> 9438
    //   9484: bipush 68
    //   9486: wide
    //   9490: goto -52 -> 9438
    //   9493: bipush 111
    //   9495: wide
    //   9499: goto -61 -> 9438
    //   9502: wide
    //   9506: wide
    //   9510: caload
    //   9511: wide
    //   9515: wide
    //   9519: iconst_5
    //   9520: irem
    //   9521: tableswitch	default:+31 -> 9552, 0:+65->9586, 1:+74->9595, 2:+83->9604, 3:+92->9613
    //   9553: dup2
    //   9554: wide
    //   9558: wide
    //   9562: wide
    //   9566: wide
    //   9570: wide
    //   9574: ixor
    //   9575: i2c
    //   9576: castore
    //   9577: wide
    //   9583: goto -6797 -> 2786
    //   9586: bipush 100
    //   9588: wide
    //   9592: goto -34 -> 9558
    //   9595: bipush 14
    //   9597: wide
    //   9601: goto -43 -> 9558
    //   9604: bipush 68
    //   9606: wide
    //   9610: goto -52 -> 9558
    //   9613: bipush 111
    //   9615: wide
    //   9619: goto -61 -> 9558
    //   9622: wide
    //   9626: wide
    //   9630: caload
    //   9631: wide
    //   9635: wide
    //   9639: iconst_5
    //   9640: irem
    //   9641: tableswitch	default:+31 -> 9672, 0:+65->9706, 1:+74->9715, 2:+83->9724, 3:+92->9733
    //   9673: dup2
    //   9674: wide
    //   9678: wide
    //   9682: wide
    //   9686: wide
    //   9690: wide
    //   9694: ixor
    //   9695: i2c
    //   9696: castore
    //   9697: wide
    //   9703: goto -6865 -> 2838
    //   9706: bipush 100
    //   9708: wide
    //   9712: goto -34 -> 9678
    //   9715: bipush 14
    //   9717: wide
    //   9721: goto -43 -> 9678
    //   9724: bipush 68
    //   9726: wide
    //   9730: goto -52 -> 9678
    //   9733: bipush 111
    //   9735: wide
    //   9739: goto -61 -> 9678
  }

  private static String a()
  {
    if (App.f == 3);
    for (String str = f8.l; ; str = f8.m)
      return str;
  }

  static String a(String paramString)
  {
    return b(e + paramString);
  }

  static void a(Application paramApplication)
  {
    f = false;
    a = b();
    b = d();
    c = e();
    d = c(paramApplication);
    String str1 = b(paramApplication);
    String str2 = a();
    if (App.f == 3);
    while (true)
    {
      e = str2;
      f = true;
      return;
      str2 = str2 + str1;
    }
  }

  private static boolean a(Application paramApplication, String paramString)
  {
    boolean bool1 = false;
    boolean bool2 = DialogToastListActivity.f;
    if (f)
      bool1 = d;
    while (true)
    {
      return bool1;
      String str = paramApplication.getPackageName();
      if ((str != null) && (str.equals(z[4])))
      {
        PackageManager localPackageManager = paramApplication.getPackageManager();
        if (localPackageManager != null)
          try
          {
            PackageInfo localPackageInfo = localPackageManager.getPackageInfo(str, 64);
            if ((localPackageInfo != null) && (localPackageInfo.signatures != null))
            {
              Signature[] arrayOfSignature = localPackageInfo.signatures;
              int i = arrayOfSignature.length;
              int j = 0;
              do
              {
                if (j >= i)
                  break;
                Signature localSignature = arrayOfSignature[j];
                if ((localSignature != null) && (localSignature.toCharsString().equals(paramString)))
                {
                  bool1 = true;
                  break;
                }
                j++;
              }
              while (!bool2);
            }
          }
          catch (PackageManager.NameNotFoundException localNameNotFoundException)
          {
          }
      }
    }
  }

  static String b()
  {
    String str6;
    if (f)
    {
      str6 = a;
      return str6;
    }
    String str1;
    label24: String str2;
    label34: String str3;
    label44: String str4;
    label54: String str5;
    if (Build.MANUFACTURER == null)
    {
      str1 = "";
      if (Build.VERSION.RELEASE != null)
        break label124;
      str2 = "";
      if (Build.DISPLAY != null)
        break label131;
      str3 = "";
      if (Build.MODEL != null)
        break label138;
      str4 = "";
      str5 = ds.a();
      if (!str5.toLowerCase(Locale.US).contains(z[15]))
        break label145;
      str6 = z[15];
    }
    while (true)
    {
      g5.b(z[49] + str6);
      break;
      str1 = Build.MANUFACTURER;
      break label24;
      label124: str2 = Build.VERSION.RELEASE;
      break label34;
      label131: str3 = Build.DISPLAY;
      break label44;
      label138: str4 = Build.MODEL;
      break label54;
      label145: if (str1.toLowerCase(Locale.US).contains(z[57]))
        str6 = z[57];
      else if (str2.toLowerCase(Locale.US).contains(z[57]))
        str6 = z[57];
      else if (str3.toLowerCase(Locale.US).contains(z[57]))
        str6 = z[57];
      else if (str4.toLowerCase(Locale.US).contains(z[57]))
        str6 = z[57];
      else if (str5.toLowerCase(Locale.US).contains(z[57]))
        str6 = z[57];
      else if (str3.startsWith(z[6]))
        str6 = z[9];
      else if (str1.startsWith(z[8]))
        str6 = z[62];
      else if (str2.startsWith(z[20]))
        str6 = z[35];
      else if ((str2.startsWith(z[10])) || (str3.startsWith(z[10])))
        str6 = z[12];
      else if (str2.startsWith(z[52]))
        str6 = z[7];
      else if (str3.startsWith(z[61]))
        str6 = z[41];
      else if (str3.startsWith(z[26]))
        str6 = z[45];
      else if (str3.startsWith(z[22]))
        str6 = z[60];
      else if (str3.startsWith(z[13]))
        str6 = z[30];
      else if (str3.startsWith(z[56]))
        str6 = z[16];
      else if (str3.startsWith(z[64]))
        str6 = z[36];
      else if (str3.startsWith(z[24]))
        str6 = z[32];
      else if (str3.startsWith(z[40]))
        str6 = z[33];
      else if (str3.startsWith(z[31]))
        str6 = z[29];
      else if (str3.startsWith(z[50]))
        str6 = z[46];
      else if (str4.startsWith(z[39]))
        str6 = z[59];
      else if (str3.startsWith(z[23]))
        str6 = z[53];
      else if (str3.startsWith(z[21]))
        str6 = z[18];
      else if (str3.startsWith(z[63]))
        str6 = z[44];
      else if (str3.startsWith(z[17]))
        str6 = z[19];
      else if (str3.startsWith(z[42]))
        str6 = z[48];
      else if (str3.startsWith(z[43]))
        str6 = z[54];
      else if (str3.startsWith(z[34]))
        str6 = z[55];
      else if (str5.contains(z[28]))
        str6 = z[25];
      else if (str5.contains(z[58]))
        str6 = z[47];
      else if (str5.contains(z[37]))
        str6 = z[27];
      else if (str5.contains(z[51]))
        str6 = z[11];
      else if (str3.contains(z[38]))
        str6 = z[14];
      else
        str6 = null;
    }
  }

  private static String b(Application paramApplication)
  {
    boolean bool = DialogToastListActivity.f;
    String str;
    try
    {
      ZipFile localZipFile = new ZipFile(paramApplication.getPackageCodePath());
      InputStream localInputStream = localZipFile.getInputStream(localZipFile.getEntry(z[68]));
      MessageDigest localMessageDigest = MessageDigest.getInstance(z[5]);
      byte[] arrayOfByte1 = new byte[8192];
      do
      {
        int i = localInputStream.read(arrayOfByte1);
        if (i <= 0)
          break;
        localMessageDigest.update(arrayOfByte1, 0, i);
      }
      while (!bool);
      byte[] arrayOfByte2 = localMessageDigest.digest();
      StringBuffer localStringBuffer = new StringBuffer();
      j = 0;
      if (j < arrayOfByte2.length)
        if (arrayOfByte2[j] >= 0)
          break label174;
      label174: for (int k = 256 + arrayOfByte2[j]; ; k = arrayOfByte2[j])
      {
        localStringBuffer.append(Character.forDigit(k >> 4, 16));
        localStringBuffer.append(Character.forDigit(k % 16, 16));
        m = j + 1;
        if (!bool)
          break;
        str = localStringBuffer.toString();
        break label208;
      }
    }
    catch (Exception localException)
    {
      str = null;
    }
    catch (NoSuchAlgorithmException localNoSuchAlgorithmException)
    {
      break label186;
    }
    catch (IOException localIOException)
    {
      while (true)
      {
        int m;
        label186: continue;
        int j = m;
      }
    }
    label208: return str;
  }

  public static String b(String paramString)
  {
    boolean bool = DialogToastListActivity.f;
    try
    {
      MessageDigest localMessageDigest = MessageDigest.getInstance(z[5]);
      localMessageDigest.update(paramString.getBytes());
      byte[] arrayOfByte = localMessageDigest.digest();
      StringBuilder localStringBuilder = new StringBuilder();
      i = 0;
      if (i < arrayOfByte.length)
      {
        int j = arrayOfByte[i];
        if (j < 0)
          j += 256;
        localStringBuilder.append(Character.forDigit(j >> 4, 16));
        localStringBuilder.append(Character.forDigit(j % 16, 16));
        k = i + 1;
        if (!bool);
      }
      else
      {
        String str2 = localStringBuilder.toString();
        str1 = str2;
        return str1;
      }
    }
    catch (NoSuchAlgorithmException localNoSuchAlgorithmException)
    {
      while (true)
      {
        int k;
        String str1 = null;
        continue;
        int i = k;
      }
    }
  }

  public static String c(String paramString)
  {
    return b(new StringBuffer(paramString).reverse().toString());
  }

  static boolean c()
  {
    boolean bool = true;
    String str1 = Build.PRODUCT;
    if (App.r(str1));
    while (true)
    {
      return bool;
      if (!str1.toLowerCase(Locale.US).contains(z[65]))
      {
        String str2 = Build.MODEL;
        if ((!App.r(str2)) && (!str2.toLowerCase(Locale.US).contains(z[65])))
        {
          String str3 = Build.MANUFACTURER;
          if ((!App.r(str3)) && (!str3.toLowerCase(Locale.US).contains(z[65])) && (App.ib != null) && (!App.r(Settings.Secure.getString(App.ib, z[67]))) && (App.db != null))
          {
            String str4 = App.db.getSubscriberId();
            if ((!App.r(str4)) && (!str4.contains(z[66])))
              bool = false;
          }
        }
      }
    }
  }

  static boolean c(Application paramApplication)
  {
    if (f);
    for (boolean bool = d; ; bool = a(paramApplication, a()))
      return bool;
  }

  // ERROR //
  static boolean d()
  {
    // Byte code:
    //   0: iconst_2
    //   1: istore_0
    //   2: iconst_1
    //   3: istore_1
    //   4: getstatic 182	com/whatsapp/mh:f	Z
    //   7: ifeq +9 -> 16
    //   10: getstatic 174	com/whatsapp/mh:b	Z
    //   13: istore_1
    //   14: iload_1
    //   15: ireturn
    //   16: new 404	java/io/File
    //   19: dup
    //   20: getstatic 170	com/whatsapp/mh:z	[Ljava/lang/String;
    //   23: iconst_3
    //   24: aaload
    //   25: invokespecial 405	java/io/File:<init>	(Ljava/lang/String;)V
    //   28: astore_2
    //   29: getstatic 408	android/os/Build$VERSION:SDK_INT	I
    //   32: bipush 9
    //   34: if_icmplt +16 -> 50
    //   37: aload_2
    //   38: invokevirtual 411	java/io/File:canExecute	()Z
    //   41: istore 16
    //   43: iload 16
    //   45: ifeq +141 -> 186
    //   48: iload_1
    //   49: istore_0
    //   50: new 198	java/lang/StringBuilder
    //   53: dup
    //   54: invokespecial 200	java/lang/StringBuilder:<init>	()V
    //   57: getstatic 170	com/whatsapp/mh:z	[Ljava/lang/String;
    //   60: iload_1
    //   61: aaload
    //   62: invokevirtual 204	java/lang/StringBuilder:append	(Ljava/lang/String;)Ljava/lang/StringBuilder;
    //   65: astore 4
    //   67: aload_2
    //   68: invokevirtual 414	java/io/File:exists	()Z
    //   71: ifeq +152 -> 223
    //   74: iload_1
    //   75: istore 5
    //   77: aload 4
    //   79: iload 5
    //   81: invokevirtual 417	java/lang/StringBuilder:append	(I)Ljava/lang/StringBuilder;
    //   84: astore 6
    //   86: aload_2
    //   87: invokevirtual 420	java/io/File:canRead	()Z
    //   90: ifeq +139 -> 229
    //   93: iload_1
    //   94: istore 7
    //   96: aload 6
    //   98: iload 7
    //   100: invokevirtual 417	java/lang/StringBuilder:append	(I)Ljava/lang/StringBuilder;
    //   103: astore 8
    //   105: aload_2
    //   106: invokevirtual 423	java/io/File:canWrite	()Z
    //   109: ifeq +126 -> 235
    //   112: iload_1
    //   113: istore 9
    //   115: aload 8
    //   117: iload 9
    //   119: invokevirtual 417	java/lang/StringBuilder:append	(I)Ljava/lang/StringBuilder;
    //   122: iload_0
    //   123: invokevirtual 417	java/lang/StringBuilder:append	(I)Ljava/lang/StringBuilder;
    //   126: astore 10
    //   128: invokestatic 425	com/whatsapp/mh:c	()Z
    //   131: ifeq +110 -> 241
    //   134: getstatic 170	com/whatsapp/mh:z	[Ljava/lang/String;
    //   137: iconst_0
    //   138: aaload
    //   139: astore 11
    //   141: aload 10
    //   143: aload 11
    //   145: invokevirtual 204	java/lang/StringBuilder:append	(Ljava/lang/String;)Ljava/lang/StringBuilder;
    //   148: invokevirtual 207	java/lang/StringBuilder:toString	()Ljava/lang/String;
    //   151: invokestatic 301	com/whatsapp/g5:b	(Ljava/lang/String;)V
    //   154: aload_2
    //   155: invokevirtual 414	java/io/File:exists	()Z
    //   158: ifne -144 -> 14
    //   161: new 427	java/io/FileInputStream
    //   164: dup
    //   165: aload_2
    //   166: invokespecial 430	java/io/FileInputStream:<init>	(Ljava/io/File;)V
    //   169: astore 12
    //   171: aload 12
    //   173: invokevirtual 433	java/io/FileInputStream:close	()V
    //   176: aload 12
    //   178: ifnonnull -164 -> 14
    //   181: iconst_0
    //   182: istore_1
    //   183: goto -169 -> 14
    //   186: iconst_0
    //   187: istore_0
    //   188: goto -138 -> 50
    //   191: astore 15
    //   193: new 198	java/lang/StringBuilder
    //   196: dup
    //   197: invokespecial 200	java/lang/StringBuilder:<init>	()V
    //   200: getstatic 170	com/whatsapp/mh:z	[Ljava/lang/String;
    //   203: iload_0
    //   204: aaload
    //   205: invokevirtual 204	java/lang/StringBuilder:append	(Ljava/lang/String;)Ljava/lang/StringBuilder;
    //   208: getstatic 408	android/os/Build$VERSION:SDK_INT	I
    //   211: invokevirtual 417	java/lang/StringBuilder:append	(I)Ljava/lang/StringBuilder;
    //   214: invokevirtual 207	java/lang/StringBuilder:toString	()Ljava/lang/String;
    //   217: invokestatic 301	com/whatsapp/g5:b	(Ljava/lang/String;)V
    //   220: goto -170 -> 50
    //   223: iconst_0
    //   224: istore 5
    //   226: goto -149 -> 77
    //   229: iconst_0
    //   230: istore 7
    //   232: goto -136 -> 96
    //   235: iconst_0
    //   236: istore 9
    //   238: goto -123 -> 115
    //   241: ldc_w 268
    //   244: astore 11
    //   246: goto -105 -> 141
    //   249: astore 14
    //   251: aconst_null
    //   252: astore 12
    //   254: goto -78 -> 176
    //   257: astore 13
    //   259: goto -83 -> 176
    //   262: astore_3
    //   263: goto -213 -> 50
    //
    // Exception table:
    //   from	to	target	type
    //   29	43	191	java/lang/NoSuchMethodError
    //   161	171	249	java/lang/Exception
    //   171	176	257	java/lang/Exception
    //   29	43	262	java/lang/Exception
  }

  static boolean e()
  {
    if (f);
    for (boolean bool = c; ; bool = Debug.isDebuggerConnected())
      return bool;
  }
}