// #######################################################
// Decompiled by   : coddec 
// Module          : WhatsApp.cod
// Module version  : 2.7.3204
// Class ID        : 16
// ########################################################


package com.whatsapp.client;


abstract public final class UsageStats extends Object
implements net.rim.device.api.util.Persistable

{

	// @@@@@@@@@@@@@ Fields 

	// @@@@@@@@@@@@@ Static routines 

public <init>( com.whatsapp.client.UsageStats ); // address: 0
	{
	enter_narrow 
	aload_0 
	iconst_0 
	invokespecial com.whatsapp.client.UsageStats.<init> // pc=2
	return 
	}


public <init>( com.whatsapp.client.UsageStats, boolean ); // address: 0
	{
	enter_narrow 
	aload_0 
	invokespecial_lib java.lang.Object.<init> // pc=1
	aload_0 
	iconst_0 
	i2l 
	lputfield .field_0_   // get_name_1:  .field_0_   // get_name_2:  .field_0_   // get_Name:    .field_0_   // getName->1:  null   // getName->2:  null   // getName->N:  null   // ofs = -1 ord = 0 addr = 0
	aload_0 
	iconst_0 
	i2l 
	lputfield .field_2_2   // get_name_1:  .field_2_2   // get_name_2:  .field_2_2   // get_Name:    .field_2_2   // getName->1:  null   // getName->2:  null   // getName->N:  null   // ofs = -1 ord = 0 addr = 2
	aload_0 
	iconst_0 
	i2l 
	lputfield .field_4_4   // get_name_1:  .field_4_4   // get_name_2:  .field_4_4   // get_Name:    .field_4_4   // getName->1:  null   // getName->2:  null   // getName->N:  null   // ofs = -1 ord = 0 addr = 4
	aload_0 
	iconst_0 
	i2l 
	lputfield .field_6_6   // get_name_1:  .field_6_6   // get_name_2:  .field_6_6   // get_Name:    .field_6_6   // getName->1:  null   // getName->2:  null   // getName->N:  null   // ofs = -1 ord = 0 addr = 6
	aload_0 
	iconst_0 
	i2l 
	lputfield .field_8_8   // get_name_1:  .field_8_8   // get_name_2:  .field_8_8   // get_Name:    .field_8_8   // getName->1:  null   // getName->2:  null   // getName->N:  null   // ofs = -1 ord = 0 addr = 8
	aload_0 
	iconst_0 
	i2l 
	lputfield .field_10_10   // get_name_1:  .field_10_10   // get_name_2:  .field_10_10   // get_Name:    .field_10_10   // getName->1:  null   // getName->2:  null   // getName->N:  null   // ofs = -1 ord = 0 addr = 10
	aload_0 
	iconst_0 
	i2l 
	lputfield .field_12_12   // get_name_1:  .field_12_12   // get_name_2:  .field_12_12   // get_Name:    .field_12_12   // getName->1:  null   // getName->2:  null   // getName->N:  null   // ofs = -1 ord = 0 addr = 12
	aload_0 
	iconst_0 
	i2l 
	lputfield .field_14_14   // get_name_1:  .field_14_14   // get_name_2:  .field_14_14   // get_Name:    .field_14_14   // getName->1:  null   // getName->2:  null   // getName->N:  null   // ofs = -1 ord = 0 addr = 14
	aload_0 
	iconst_0 
	i2l 
	lputfield .field_16_16   // get_name_1:  .field_16_16   // get_name_2:  .field_16_16   // get_Name:    .field_16_16   // getName->1:  null   // getName->2:  null   // getName->N:  null   // ofs = -1 ord = 0 addr = 16
	aload_0 
	iconst_0 
	i2l 
	lputfield .field_18_18   // get_name_1:  .field_18_18   // get_name_2:  .field_18_18   // get_Name:    .field_18_18   // getName->1:  null   // getName->2:  null   // getName->N:  null   // ofs = -1 ord = 0 addr = 18
	aload_0 
	iconst_0 
	i2l 
	lputfield .field_20_20   // get_name_1:  .field_20_20   // get_name_2:  .field_20_20   // get_Name:    .field_20_20   // getName->1:  null   // getName->2:  null   // getName->N:  null   // ofs = -1 ord = 0 addr = 20
	aload_0 
	iconst_0 
	i2l 
	lputfield .field_22_22   // get_name_1:  .field_22_22   // get_name_2:  .field_22_22   // get_Name:    .field_22_22   // getName->1:  null   // getName->2:  null   // getName->N:  null   // ofs = -1 ord = 0 addr = 22
	iload_1 
	ifeq Label57
	aload_0 
	invokestatic_lib long currentTimeMillis(  ) // System
	lputfield .field_24_24   // get_name_1:  .field_24_24   // get_name_2:  .field_24_24   // get_Name:    .field_24_24   // getName->1:  null   // getName->2:  null   // getName->N:  null   // ofs = -1 ord = 0 addr = 24
	return 
Label57:
	aload_0 
	lipush -9223372036854775808
	lputfield .field_24_24   // get_name_1:  .field_24_24   // get_name_2:  .field_24_24   // get_Name:    .field_24_24   // getName->1:  null   // getName->2:  null   // getName->N:  null   // ofs = -1 ord = 0 addr = 24
	return 
	}


static public final reset(  ); // address: 0
	{
	enter_narrow 
	new UsageStats
	dup 
	iconst_1 
	invokespecial com.whatsapp.client.UsageStats.<init> // pc=2
	astore_0 
	invokestatic_lib module:WhatsApp-10.class#29.routine_5442(  ) // class#29
	aload_0 
	putfield .field_38_38   // get_name_1:  .field_38_38   // get_name_2:  .field_38_38   // get_Name:    .field_38_38   // getName->1:  null   // getName->2:  null   // getName->N:  null   // ofs = -1 ord = 0 addr = 38
	invokestatic_lib module:WhatsApp-26.class#11.routine_3571(  ) // class#11
	astore_1 
	aload_1 
	aload_0 
	invokenonvirtual_lib .routine_3377 // pc=2
	return 
	}

	// @@@@@@@@@@@@@ Non-virtual routines 

private final com.whatsapp.client.UsageStats.routine_10358( com.whatsapp.client.UsageStats ); // address: 0
	{
	enter 
	invokestatic_lib long currentTimeMillis(  ) // System
	aload_0 
	lgetfield .field_26_26   // get_name_1:  .field_26_26   // get_name_2:  .field_26_26   // get_Name:    .field_26_26   // getName->1:  null   // getName->2:  null   // getName->N:  null   // ofs = -1 ord = 0 addr = 26
	lsub 
	iipush 1800000
	i2l 
	lcmp 
	ifle Label17
	new_lib net.rim.device.api.system.Bitmap//net.rim.device.api.system.Bitmap net.rim.device.api.system.Bitmap net.rim.device.api.system.Bitmap
	dup 
	new_lib com.whatsapp.client.//module:WhatsApp-30.class#10 module:WhatsApp-30.class#10 module:WhatsApp-30.class#10
	dup 
	aload_0 
	invokespecial_lib .routine_12160 // pc=2
	invokespecial_lib java.lang.Thread.<init> // pc=2
	invokevirtual start( java.lang.Thread ) // pc=1
Label17:
	return 
	}

	// @@@@@@@@@@@@@ Virtual routines 

public final recordMessageReceived( com.whatsapp.client.UsageStats, module:WhatsApp-17.class#15 ); // address: 0
	{
	enter 
	synch 
	invokestatic_lib long currentTimeMillis(  ) // System
	aload_1 
	lgetfield .field_6_6   // get_name_1:  .field_6_6   // get_name_2:  .field_6_6   // get_Name:    .field_6_6   // getName->1:  null   // getName->2:  null   // getName->N:  null   // ofs = -1 ord = 0 addr = 6
	lsub 
	lstore 2
	aload_1 
	getfield .field_21_21   // get_name_1:  .field_21_21   // get_name_2:  .field_21_21   // get_Name:    .field_21_21   // getName->1:  null   // getName->2:  null   // getName->N:  null   // ofs = -1 ord = 0 addr = 21
	ifeq Label28
	aload_0 
	aload_0 
	lgetfield .field_10_10   // get_name_1:  .field_10_10   // get_name_2:  .field_10_10   // get_Name:    .field_10_10   // getName->1:  null   // getName->2:  null   // getName->N:  null   // ofs = -1 ord = 0 addr = 10
	aload_0 
	lgetfield .field_8_8   // get_name_1:  .field_8_8   // get_name_2:  .field_8_8   // get_Name:    .field_8_8   // getName->1:  null   // getName->2:  null   // getName->N:  null   // ofs = -1 ord = 0 addr = 8
	lmul 
	lload 2
	ladd 
	aload_0 
	aload_0 
	lgetfield .field_8_8   // get_name_1:  .field_8_8   // get_name_2:  .field_8_8   // get_Name:    .field_8_8   // getName->1:  null   // getName->2:  null   // getName->N:  null   // ofs = -1 ord = 0 addr = 8
	iconst_1 
	i2l 
	ladd 
	dup2_x1 
	lputfield .field_8_8   // get_name_1:  .field_8_8   // get_name_2:  .field_8_8   // get_Name:    .field_8_8   // getName->1:  null   // getName->2:  null   // getName->N:  null   // ofs = -1 ord = 0 addr = 8
	ldiv 
	lputfield .field_10_10   // get_name_1:  .field_10_10   // get_name_2:  .field_10_10   // get_Name:    .field_10_10   // getName->1:  null   // getName->2:  null   // getName->N:  null   // ofs = -1 ord = 0 addr = 10
Label28:
	aload_1 
	getfield .field_10_10   // get_name_1:  .field_10_10   // get_name_2:  .field_10_10   // get_Name:    .field_10_10   // getName->1:  null   // getName->2:  null   // getName->N:  null   // ofs = -1 ord = 0 addr = 10
	ifne Label39
	aload_0 
	aload_0 
	lgetfield .field_0_   // get_name_1:  .field_0_   // get_name_2:  .field_0_   // get_Name:    .field_0_   // getName->1:  null   // getName->2:  null   // getName->N:  null   // ofs = -1 ord = 0 addr = 0
	iconst_1 
	i2l 
	ladd 
	lputfield .field_0_   // get_name_1:  .field_0_   // get_name_2:  .field_0_   // get_Name:    .field_0_   // getName->1:  null   // getName->2:  null   // getName->N:  null   // ofs = -1 ord = 0 addr = 0
	goto Label46
Label39:
	aload_0 
	aload_0 
	lgetfield .field_4_4   // get_name_1:  .field_4_4   // get_name_2:  .field_4_4   // get_Name:    .field_4_4   // getName->1:  null   // getName->2:  null   // getName->N:  null   // ofs = -1 ord = 0 addr = 4
	iconst_1 
	i2l 
	ladd 
	lputfield .field_4_4   // get_name_1:  .field_4_4   // get_name_2:  .field_4_4   // get_Name:    .field_4_4   // getName->1:  null   // getName->2:  null   // getName->N:  null   // ofs = -1 ord = 0 addr = 4
Label46:
	aload_0 
	invokespecial com.whatsapp.client.UsageStats.routine_10358 // pc=1
	return 
	}


public final recordMessageSent( com.whatsapp.client.UsageStats, module:WhatsApp-17.class#15 ); // address: 0
	{
	enter 
	synch 
	aload_1 
	getfield .field_10_10   // get_name_1:  .field_10_10   // get_name_2:  .field_10_10   // get_Name:    .field_10_10   // getName->1:  null   // getName->2:  null   // getName->N:  null   // ofs = -1 ord = 0 addr = 10
	ifne Label13
	aload_0 
	aload_0 
	lgetfield .field_2_2   // get_name_1:  .field_2_2   // get_name_2:  .field_2_2   // get_Name:    .field_2_2   // getName->1:  null   // getName->2:  null   // getName->N:  null   // ofs = -1 ord = 0 addr = 2
	iconst_1 
	i2l 
	ladd 
	lputfield .field_2_2   // get_name_1:  .field_2_2   // get_name_2:  .field_2_2   // get_Name:    .field_2_2   // getName->1:  null   // getName->2:  null   // getName->N:  null   // ofs = -1 ord = 0 addr = 2
	goto Label20
Label13:
	aload_0 
	aload_0 
	lgetfield .field_6_6   // get_name_1:  .field_6_6   // get_name_2:  .field_6_6   // get_Name:    .field_6_6   // getName->1:  null   // getName->2:  null   // getName->N:  null   // ofs = -1 ord = 0 addr = 6
	iconst_1 
	i2l 
	ladd 
	lputfield .field_6_6   // get_name_1:  .field_6_6   // get_name_2:  .field_6_6   // get_Name:    .field_6_6   // getName->1:  null   // getName->2:  null   // getName->N:  null   // ofs = -1 ord = 0 addr = 6
Label20:
	aload_0 
	invokespecial com.whatsapp.client.UsageStats.routine_10358 // pc=1
	return 
	}


public final recordBytesReceived( com.whatsapp.client.UsageStats, long, int ); // address: 0
	{
	enter 
	synch 
	iload_3 
	tableswitch  :
		
		
		
		

Label4:
	aload_0 
	aload_0 
	lgetfield .field_12_12   // get_name_1:  .field_12_12   // get_name_2:  .field_12_12   // get_Name:    .field_12_12   // getName->1:  null   // getName->2:  null   // getName->N:  null   // ofs = -1 ord = 0 addr = 12
	lload 1
	ladd 
	lputfield .field_12_12   // get_name_1:  .field_12_12   // get_name_2:  .field_12_12   // get_Name:    .field_12_12   // getName->1:  null   // getName->2:  null   // getName->N:  null   // ofs = -1 ord = 0 addr = 12
	return 
Label11:
	aload_0 
	aload_0 
	lgetfield .field_20_20   // get_name_1:  .field_20_20   // get_name_2:  .field_20_20   // get_Name:    .field_20_20   // getName->1:  null   // getName->2:  null   // getName->N:  null   // ofs = -1 ord = 0 addr = 20
	lload 1
	ladd 
	lputfield .field_20_20   // get_name_1:  .field_20_20   // get_name_2:  .field_20_20   // get_Name:    .field_20_20   // getName->1:  null   // getName->2:  null   // getName->N:  null   // ofs = -1 ord = 0 addr = 20
	return 
Label18:
	aload_0 
	aload_0 
	lgetfield .field_16_16   // get_name_1:  .field_16_16   // get_name_2:  .field_16_16   // get_Name:    .field_16_16   // getName->1:  null   // getName->2:  null   // getName->N:  null   // ofs = -1 ord = 0 addr = 16
	lload 1
	ladd 
	lputfield .field_16_16   // get_name_1:  .field_16_16   // get_name_2:  .field_16_16   // get_Name:    .field_16_16   // getName->1:  null   // getName->2:  null   // getName->N:  null   // ofs = -1 ord = 0 addr = 16
Label24:
	return 
	}


public final recordBytesSent( com.whatsapp.client.UsageStats, long, int ); // address: 0
	{
	enter 
	synch 
	iload_3 
	tableswitch  :
		
		
		
		

Label4:
	aload_0 
	aload_0 
	lgetfield .field_14_14   // get_name_1:  .field_14_14   // get_name_2:  .field_14_14   // get_Name:    .field_14_14   // getName->1:  null   // getName->2:  null   // getName->N:  null   // ofs = -1 ord = 0 addr = 14
	lload 1
	ladd 
	lputfield .field_14_14   // get_name_1:  .field_14_14   // get_name_2:  .field_14_14   // get_Name:    .field_14_14   // getName->1:  null   // getName->2:  null   // getName->N:  null   // ofs = -1 ord = 0 addr = 14
	return 
Label11:
	aload_0 
	aload_0 
	lgetfield .field_22_22   // get_name_1:  .field_22_22   // get_name_2:  .field_22_22   // get_Name:    .field_22_22   // getName->1:  null   // getName->2:  null   // getName->N:  null   // ofs = -1 ord = 0 addr = 22
	lload 1
	ladd 
	lputfield .field_22_22   // get_name_1:  .field_22_22   // get_name_2:  .field_22_22   // get_Name:    .field_22_22   // getName->1:  null   // getName->2:  null   // getName->N:  null   // ofs = -1 ord = 0 addr = 22
	return 
Label18:
	aload_0 
	aload_0 
	lgetfield .field_18_18   // get_name_1:  .field_18_18   // get_name_2:  .field_18_18   // get_Name:    .field_18_18   // getName->1:  null   // getName->2:  null   // getName->N:  null   // ofs = -1 ord = 0 addr = 18
	lload 1
	ladd 
	lputfield .field_18_18   // get_name_1:  .field_18_18   // get_name_2:  .field_18_18   // get_Name:    .field_18_18   // getName->1:  null   // getName->2:  null   // getName->N:  null   // ofs = -1 ord = 0 addr = 18
Label24:
	return 
	}

}
