// #######################################################
// Decompiled by   : coddec 
// Module          : WhatsApp-25.cod
// Module version  : 2.8.1914
// Class ID        : 4
// ########################################################


package com.whatsapp.client;


abstract final class FMessageActions$8 extends Object
implements com.whatsapp.client.ChatablePickerScreen$Listener

{

	// @@@@@@@@@@@@@ Fields 
	private final com.whatsapp.client.FunXMPP$FMessage /*module:WhatsApp-26.class#23*/  field_53998 ; // ofs = 53998 addr = 0)
	private final com.whatsapp.client.NewChatScreen /*module:WhatsApp-42.class#0*/  field_54002 ; // ofs = 54002 addr = 0)
	private final com.whatsapp.client.ChatablePickerScreen /*module:WhatsApp-14.class#0*/  field_54006 ; // ofs = 54006 addr = 0)

	// @@@@@@@@@@@@@ Static routines 

<init>( com.whatsapp.client.FMessageActions$8, module:WhatsApp-26.class#23, module:WhatsApp-42.class#0, module:WhatsApp-14.class#0 ); // address: 0
	{
	enter 
	aload_0 
	invokespecial_lib java.lang.Object.<init> // pc=1
	aload_0 
	aload_1 
	putfield .field_0_   // get_name_1:  .field_0_   // get_name_2:  .field_0_   // get_Name:    .field_0_   // getName->1:  null   // getName->2:  null   // getName->N:  null   // ofs = -1 ord = 0 addr = 0
	aload_0 
	aload_2 
	putfield .field_1_1   // get_name_1:  .field_1_1   // get_name_2:  .field_1_1   // get_Name:    .field_1_1   // getName->1:  null   // getName->2:  null   // getName->N:  null   // ofs = -1 ord = 0 addr = 1
	aload_0 
	aload_3 
	putfield .field_2_2   // get_name_1:  .field_2_2   // get_name_2:  .field_2_2   // get_Name:    .field_2_2   // getName->1:  null   // getName->2:  null   // getName->N:  null   // ofs = -1 ord = 0 addr = 2
	return 
	}

	// @@@@@@@@@@@@@ Virtual routines 

public final boolean selectionDone( com.whatsapp.client.FMessageActions$8, module:WhatsApp-12.class#30 ); // address: 0
	{
	enter 
	aload_1 
	getfield .field_0_   // get_name_1:  .field_0_   // get_name_2:  .field_0_   // get_Name:    .field_0_   // getName->1:  null   // getName->2:  null   // getName->N:  null   // ofs = -1 ord = 0 addr = 0
	iconst_0 
	invokenonvirtual_lib .routine_8839 // pc=2
	astore_2 
	aload_2 
	invokestatic boolean showForwardPrompt( java.lang.String ) // FMessageActions
	ifne Label11
	iconst_0 
	ireturn 
Label11:
	invokestatic_lib com.whatsapp.client.UiApp.routine_7787(  ) // UiApp
	astore_3 
	aload_3 
	getfield _fromSystemFolder   // get_name_1:  _fromSystemFolder   // get_name_2:  _fromSystemFolder   // get_Name:    _fromSystemFolder   // getName->1:  _fromSystemFolder   // getName->2:  _fromSystemFolder   // getName->N:  _fromSystemFolder   // ofs = -1 ord = 0 addr = -1
	istore_4 
	aload_0_getfield .field_0_   // get_name_1:  .field_0_   // get_name_2:  .field_0_   // get_Name:    .field_0_   // getName->1:  null   // getName->2:  null   // getName->N:  null   // ofs = -1 ord = 0 addr = 0
	getfield .field_12_12   // get_name_1:  .field_12_12   // get_name_2:  .field_12_12   // get_Name:    .field_12_12   // getName->1:  null   // getName->2:  null   // getName->N:  null   // ofs = -1 ord = 0 addr = 12
	ifne Label27
	lipush 7375980026338060110
	aload_1 
	getfield .field_2_2   // get_name_1:  .field_2_2   // get_name_2:  .field_2_2   // get_Name:    .field_2_2   // getName->1:  null   // getName->2:  null   // getName->N:  null   // ofs = -1 ord = 0 addr = 2
	invokenonvirtual_lib .routine_12254 // pc=1
	aload_0_getfield .field_0_   // get_name_1:  .field_0_   // get_name_2:  .field_0_   // get_Name:    .field_0_   // getName->1:  null   // getName->2:  null   // getName->N:  null   // ofs = -1 ord = 0 addr = 0
	invokenonvirtual_lib .routine_5941 // pc=1
	invokestatic_lib module:WhatsApp-79.class#39.routine_26776(  ) // class#39
	goto Label49
Label27:
	aload_1 
	getfield .field_2_2   // get_name_1:  .field_2_2   // get_name_2:  .field_2_2   // get_Name:    .field_2_2   // getName->1:  null   // getName->2:  null   // getName->N:  null   // ofs = -1 ord = 0 addr = 2
	invokenonvirtual_lib .routine_12254 // pc=1
	aload_0_getfield .field_0_   // get_name_1:  .field_0_   // get_name_2:  .field_0_   // get_Name:    .field_0_   // getName->1:  null   // getName->2:  null   // getName->N:  null   // ofs = -1 ord = 0 addr = 0
	invokestatic module:WhatsApp-26.class#23 copyMessage( java.lang.String, module:WhatsApp-26.class#23 ) // FMessageActions
	astore_5 
	aload_5 
	getfield .field_12_12   // get_name_1:  .field_12_12   // get_name_2:  .field_12_12   // get_Name:    .field_12_12   // getName->1:  null   // getName->2:  null   // getName->N:  null   // ofs = -1 ord = 0 addr = 12
	bipush 5
	if_icmpne Label43
	aload_5 
	getfield .field_10_10   // get_name_1:  .field_10_10   // get_name_2:  .field_10_10   // get_Name:    .field_10_10   // getName->1:  null   // getName->2:  null   // getName->N:  null   // ofs = -1 ord = 0 addr = 10
	ifnonnull Label43
	aload_5 
	getstatic_lib module:WhatsApp-19.class#0.static_131 // class#0
	putfield .field_10_10   // get_name_1:  .field_10_10   // get_name_2:  .field_10_10   // get_Name:    .field_10_10   // getName->1:  null   // getName->2:  null   // getName->N:  null   // ofs = -1 ord = 0 addr = 10
Label43:
	lipush 7375980026338060110
	aload_1 
	getfield .field_2_2   // get_name_1:  .field_2_2   // get_name_2:  .field_2_2   // get_Name:    .field_2_2   // getName->1:  null   // getName->2:  null   // getName->N:  null   // ofs = -1 ord = 0 addr = 2
	invokenonvirtual_lib .routine_12254 // pc=1
	aload_5 
	invokestatic_lib module:WhatsApp-79.class#39.routine_26776(  ) // class#39
Label49:
	aload_1 
	aconst_null 
	invokestatic_lib com.whatsapp.client.TabButton.routine_7301(  ) // TabButton
	ifnull Label63
	aload_0_getfield .field_1_1   // get_name_1:  .field_1_1   // get_name_2:  .field_1_1   // get_Name:    .field_1_1   // getName->1:  null   // getName->2:  null   // getName->N:  null   // ofs = -1 ord = 0 addr = 1
	aload_0_getfield .field_2_2   // get_name_1:  .field_2_2   // get_name_2:  .field_2_2   // get_Name:    .field_2_2   // getName->1:  null   // getName->2:  null   // getName->N:  null   // ofs = -1 ord = 0 addr = 2
	invokestatic closeScreensUnder( net.rim.device.api.ui.Screen, net.rim.device.api.ui.Screen ) // FMessageActions
	iload_4 
	ifeq Label61
	aload_3 
	iconst_1 
	putfield _fromSystemFolder   // get_name_1:  _fromSystemFolder   // get_name_2:  _fromSystemFolder   // get_Name:    _fromSystemFolder   // getName->1:  _fromSystemFolder   // getName->2:  _fromSystemFolder   // getName->N:  _fromSystemFolder   // ofs = -1 ord = 0 addr = -1
Label61:
	iconst_1 
	ireturn 
Label63:
	iconst_0 
	ireturn 
	}


public final boolean selectionDone( com.whatsapp.client.FMessageActions$8, module:WhatsApp-11.class#1 ); // address: 0
	{
	enter 
	aload_1 
	getfield .field_8_8   // get_name_1:  .field_8_8   // get_name_2:  .field_8_8   // get_Name:    .field_8_8   // getName->1:  null   // getName->2:  null   // getName->N:  null   // ofs = -1 ord = 0 addr = 8
	ifnull Label17
	new_lib java.util.Vector//java.util.Vector java.util.Vector java.util.Vector
	dup 
	invokespecial_lib java.lang.StringBuffer.<init> // pc=1
	getstatic_lib module:WhatsApp-19.class#0.static_6 // class#0
	invokevirtual java.lang.StringBuffer append( java.lang.StringBuffer, java.lang.String ) // pc=2
	aload_1 
	invokenonvirtual_lib .routine_1673 // pc=1
	invokevirtual java.lang.StringBuffer append( java.lang.StringBuffer, java.lang.String ) // pc=2
	getstatic_lib module:WhatsApp-19.class#0.static_6 // class#0
	invokevirtual java.lang.StringBuffer append( java.lang.StringBuffer, java.lang.String ) // pc=2
	invokevirtual_short .toString // idx=2 pc=1
	astore_2 
	goto Label20
Label17:
	aload_1 
	invokenonvirtual_lib .routine_1673 // pc=1
	astore_2 
Label20:
	aload_2 
	invokestatic boolean showForwardPrompt( java.lang.String ) // FMessageActions
	ifne Label25
	iconst_0 
	ireturn 
Label25:
	aload_0_getfield .field_0_   // get_name_1:  .field_0_   // get_name_2:  .field_0_   // get_Name:    .field_0_   // getName->1:  null   // getName->2:  null   // getName->N:  null   // ofs = -1 ord = 0 addr = 0
	getfield .field_12_12   // get_name_1:  .field_12_12   // get_name_2:  .field_12_12   // get_Name:    .field_12_12   // getName->1:  null   // getName->2:  null   // getName->N:  null   // ofs = -1 ord = 0 addr = 12
	ifne Label35
	lipush 7375980026338060110
	aload_1 
	getfield .field_0_   // get_name_1:  .field_0_   // get_name_2:  .field_0_   // get_Name:    .field_0_   // getName->1:  null   // getName->2:  null   // getName->N:  null   // ofs = -1 ord = 0 addr = 0
	aload_0_getfield .field_0_   // get_name_1:  .field_0_   // get_name_2:  .field_0_   // get_Name:    .field_0_   // getName->1:  null   // getName->2:  null   // getName->N:  null   // ofs = -1 ord = 0 addr = 0
	invokenonvirtual_lib .routine_5941 // pc=1
	invokestatic_lib module:WhatsApp-79.class#39.routine_26776(  ) // class#39
	goto Label55
Label35:
	aload_1 
	getfield .field_0_   // get_name_1:  .field_0_   // get_name_2:  .field_0_   // get_Name:    .field_0_   // getName->1:  null   // getName->2:  null   // getName->N:  null   // ofs = -1 ord = 0 addr = 0
	aload_0_getfield .field_0_   // get_name_1:  .field_0_   // get_name_2:  .field_0_   // get_Name:    .field_0_   // getName->1:  null   // getName->2:  null   // getName->N:  null   // ofs = -1 ord = 0 addr = 0
	invokestatic module:WhatsApp-26.class#23 copyMessage( java.lang.String, module:WhatsApp-26.class#23 ) // FMessageActions
	astore_3 
	aload_3 
	getfield .field_12_12   // get_name_1:  .field_12_12   // get_name_2:  .field_12_12   // get_Name:    .field_12_12   // getName->1:  null   // getName->2:  null   // getName->N:  null   // ofs = -1 ord = 0 addr = 12
	bipush 5
	if_icmpne Label50
	aload_3 
	getfield .field_10_10   // get_name_1:  .field_10_10   // get_name_2:  .field_10_10   // get_Name:    .field_10_10   // getName->1:  null   // getName->2:  null   // getName->N:  null   // ofs = -1 ord = 0 addr = 10
	ifnonnull Label50
	aload_3 
	getstatic_lib module:WhatsApp-19.class#0.static_131 // class#0
	putfield .field_10_10   // get_name_1:  .field_10_10   // get_name_2:  .field_10_10   // get_Name:    .field_10_10   // getName->1:  null   // getName->2:  null   // getName->N:  null   // ofs = -1 ord = 0 addr = 10
Label50:
	lipush 7375980026338060110
	aload_1 
	getfield .field_0_   // get_name_1:  .field_0_   // get_name_2:  .field_0_   // get_Name:    .field_0_   // getName->1:  null   // getName->2:  null   // getName->N:  null   // ofs = -1 ord = 0 addr = 0
	aload_3 
	invokestatic_lib module:WhatsApp-79.class#39.routine_26776(  ) // class#39
Label55:
	aload_1 
	invokestatic_lib com.whatsapp.client.TabButton.routine_7124(  ) // TabButton
	pop 
	aload_1 
	invokestatic_lib com.whatsapp.client.TabButton.routine_7124(  ) // TabButton
	ifeq Label66
	aload_0_getfield .field_1_1   // get_name_1:  .field_1_1   // get_name_2:  .field_1_1   // get_Name:    .field_1_1   // getName->1:  null   // getName->2:  null   // getName->N:  null   // ofs = -1 ord = 0 addr = 1
	aload_0_getfield .field_2_2   // get_name_1:  .field_2_2   // get_name_2:  .field_2_2   // get_Name:    .field_2_2   // getName->1:  null   // getName->2:  null   // getName->N:  null   // ofs = -1 ord = 0 addr = 2
	invokestatic closeScreensUnder( net.rim.device.api.ui.Screen, net.rim.device.api.ui.Screen ) // FMessageActions
	iconst_1 
	ireturn 
Label66:
	iconst_0 
	ireturn 
	}

}
