// #######################################################
// Decompiled by   : coddec 
// Module          : WhatsApp-32.cod
// Module version  : 2.7.3204
// Class ID        : 19
// ########################################################


package com.whatsapp.client;


abstract final class TransferRunner$2 extends Object
implements Runnable

{

	// @@@@@@@@@@@@@ Fields 
	private final com.whatsapp.client.TransferRunner /*com.whatsapp.client.TransferRunner*/  field_54422 ; // ofs = 54422 addr = 0)

	// @@@@@@@@@@@@@ Static routines 

<init>( com.whatsapp.client.TransferRunner$2, com.whatsapp.client.TransferRunner ); // address: 0
	{
	enter_narrow 
	aload_0 
	invokespecial_lib java.lang.Object.<init> // pc=1
	aload_0 
	aload_1 
	putfield .field_0_   // get_name_1:  .field_0_   // get_name_2:  .field_0_   // get_Name:    .field_0_   // getName->1:  null   // getName->2:  null   // getName->N:  null   // ofs = -1 ord = 0 addr = 0
	return 
	}

	// @@@@@@@@@@@@@ Virtual routines 

public final run( com.whatsapp.client.TransferRunner$2 ); // address: 0
	{
	enter 
Label1:
	aload_0_getfield .field_0_   // get_name_1:  .field_0_   // get_name_2:  .field_0_   // get_Name:    .field_0_   // getName->1:  null   // getName->2:  null   // getName->N:  null   // ofs = -1 ord = 0 addr = 0
	getfield .field_0_   // get_name_1:  .field_0_   // get_name_2:  .field_0_   // get_Name:    .field_0_   // getName->1:  null   // getName->2:  null   // getName->N:  null   // ofs = -1 ord = 0 addr = 0
	dup 
	astore_2 
	monitorenter 
	aload_0_getfield .field_0_   // get_name_1:  .field_0_   // get_name_2:  .field_0_   // get_Name:    .field_0_   // getName->1:  null   // getName->2:  null   // getName->N:  null   // ofs = -1 ord = 0 addr = 0
	getfield .field_0_   // get_name_1:  .field_0_   // get_name_2:  .field_0_   // get_Name:    .field_0_   // getName->1:  null   // getName->2:  null   // getName->N:  null   // ofs = -1 ord = 0 addr = 0
	invokenonvirtual_lib .routine_4401 // pc=1
	ifeq Label16
	aload_0_getfield .field_0_   // get_name_1:  .field_0_   // get_name_2:  .field_0_   // get_Name:    .field_0_   // getName->1:  null   // getName->2:  null   // getName->N:  null   // ofs = -1 ord = 0 addr = 0
	iconst_0 
	putfield .field_2_2   // get_name_1:  .field_2_2   // get_name_2:  .field_2_2   // get_Name:    .field_2_2   // getName->1:  null   // getName->2:  null   // getName->N:  null   // ofs = -1 ord = 0 addr = 2
	aconst_null 
	astore_1 
	goto Label31
Label16:
	aload_0_getfield .field_0_   // get_name_1:  .field_0_   // get_name_2:  .field_0_   // get_Name:    .field_0_   // getName->1:  null   // getName->2:  null   // getName->N:  null   // ofs = -1 ord = 0 addr = 0
	getfield .field_0_   // get_name_1:  .field_0_   // get_name_2:  .field_0_   // get_Name:    .field_0_   // getName->1:  null   // getName->2:  null   // getName->N:  null   // ofs = -1 ord = 0 addr = 0
	invokenonvirtual_lib .routine_4351 // pc=1
	checkcast TransferItem
	astore_1 
	aload_0_getfield .field_0_   // get_name_1:  .field_0_   // get_name_2:  .field_0_   // get_Name:    .field_0_   // getName->1:  null   // getName->2:  null   // getName->N:  null   // ofs = -1 ord = 0 addr = 0
	invokespecial com.whatsapp.client.TransferRunner.copyQueue // pc=1
	astore_3 
	invokestatic com.whatsapp.client.UiApp getInstance(  ) // UiApp
	new TransferRunner$2$1
	dup 
	aload_0 
	aload_3 
	invokespecial com.whatsapp.client.TransferRunner$2$1.<init> // pc=3
	invokevirtual invokeAndWait( net.rim.device.api.system.Application, java.lang.Runnable ) // pc=2
Label31:
	aload_2 
	monitorexit 
	goto Label39
	astore_4 
	aload_2 
	monitorexit 
	aload_4 
	athrow 
Label39:
	aload_1 
	ifnull Label79
	aload_1 
	invokenonvirtual com.whatsapp.client.TransferItem.startTransfer // pc=1
	aload_0_getfield .field_0_   // get_name_1:  .field_0_   // get_name_2:  .field_0_   // get_Name:    .field_0_   // getName->1:  null   // getName->2:  null   // getName->N:  null   // ofs = -1 ord = 0 addr = 0
	getfield .field_0_   // get_name_1:  .field_0_   // get_name_2:  .field_0_   // get_Name:    .field_0_   // getName->1:  null   // getName->2:  null   // getName->N:  null   // ofs = -1 ord = 0 addr = 0
	dup 
	astore_2 
	monitorenter 
	aload_0_getfield .field_0_   // get_name_1:  .field_0_   // get_name_2:  .field_0_   // get_Name:    .field_0_   // getName->1:  null   // getName->2:  null   // getName->N:  null   // ofs = -1 ord = 0 addr = 0
	getfield .field_1_1   // get_name_1:  .field_1_1   // get_name_2:  .field_1_1   // get_Name:    .field_1_1   // getName->1:  null   // getName->2:  null   // getName->N:  null   // ofs = -1 ord = 0 addr = 1
	aload_1 
	invokenonvirtual com.whatsapp.client.TransferItem.getKey // pc=1
	invokevirtual java.lang.Object remove( java.util.Hashtable, java.lang.Object ) // pc=2
	pop 
	aload_2 
	monitorexit 
	goto Label1
	astore_5 
	aload_2 
	monitorexit 
	aload_5 
	athrow 
	astore_1 
	aload_0_getfield .field_0_   // get_name_1:  .field_0_   // get_name_2:  .field_0_   // get_Name:    .field_0_   // getName->1:  null   // getName->2:  null   // getName->N:  null   // ofs = -1 ord = 0 addr = 0
	getfield .field_0_   // get_name_1:  .field_0_   // get_name_2:  .field_0_   // get_Name:    .field_0_   // getName->1:  null   // getName->2:  null   // getName->N:  null   // ofs = -1 ord = 0 addr = 0
	dup 
	astore_2 
	monitorenter 
	aload_0_getfield .field_0_   // get_name_1:  .field_0_   // get_name_2:  .field_0_   // get_Name:    .field_0_   // getName->1:  null   // getName->2:  null   // getName->N:  null   // ofs = -1 ord = 0 addr = 0
	iconst_0 
	putfield .field_2_2   // get_name_1:  .field_2_2   // get_name_2:  .field_2_2   // get_Name:    .field_2_2   // getName->1:  null   // getName->2:  null   // getName->N:  null   // ofs = -1 ord = 0 addr = 2
	aload_2 
	monitorexit 
	return 
	astore_6 
	aload_2 
	monitorexit 
	aload_6 
	athrow 
Label79:
	return 
	}

}
