// #######################################################
// Decompiled by   : coddec 
// Module          : WhatsApp-36.cod
// Module version  : 2.7.3204
// Class ID        : 24
// ########################################################


package com.whatsapp.client;


abstract public final class Worklist extends Object

{

	// @@@@@@@@@@@@@ Fields 
	private Thread /*java.lang.Thread*/  _worker ; // ofs = 54968 addr = 0)
	private java.util.Vector /*java.util.Vector*/  _work ; // ofs = 54972 addr = 0)
	private Object /*java.lang.Object*/  _workLock ; // ofs = 54976 addr = 0)

	// @@@@@@@@@@@@@ Static routines 

public <init>( com.whatsapp.client.Worklist ); // address: 0
	{
	enter_narrow 
	aload_0 
	invokespecial_lib java.lang.Object.<init> // pc=1
	aload_0 
	new_lib StringBuffer//java.lang.StringBuffer java.lang.StringBuffer java.lang.StringBuffer
	dup 
	invokespecial_lib java.util.Vector.<init> // pc=1
	putfield .field_1_1   // get_name_1:  .field_1_1   // get_name_2:  .field_1_1   // get_Name:    .field_1_1   // getName->1:  null   // getName->2:  null   // getName->N:  null   // ofs = -1 ord = 0 addr = 1
	aload_0 
	new_lib java.io.Reader//java.io.Reader java.io.Reader java.io.Reader
	dup 
	invokespecial_lib java.lang.Object.<init> // pc=1
	putfield .field_2_2   // get_name_1:  .field_2_2   // get_name_2:  .field_2_2   // get_Name:    .field_2_2   // getName->1:  null   // getName->2:  null   // getName->N:  null   // ofs = -1 ord = 0 addr = 2
	return 
	}

	// @@@@@@@@@@@@@ Non-virtual routines 

public final add( com.whatsapp.client.Worklist, java.lang.Runnable ); // address: 0
	{
	enter 
	aload_0_getfield .field_2_2   // get_name_1:  .field_2_2   // get_name_2:  .field_2_2   // get_Name:    .field_2_2   // getName->1:  null   // getName->2:  null   // getName->N:  null   // ofs = -1 ord = 0 addr = 2
	dup 
	astore_2 
	monitorenter 
	aload_0_getfield .field_1_1   // get_name_1:  .field_1_1   // get_name_2:  .field_1_1   // get_Name:    .field_1_1   // getName->1:  null   // getName->2:  null   // getName->N:  null   // ofs = -1 ord = 0 addr = 1
	aload_1 
	invokevirtual addElement( java.util.Vector, java.lang.Object ) // pc=2
	aload_0_getfield .field_0_   // get_name_1:  .field_0_   // get_name_2:  .field_0_   // get_Name:    .field_0_   // getName->1:  null   // getName->2:  null   // getName->N:  null   // ofs = -1 ord = 0 addr = 0
	ifnull Label13
	aload_0_getfield .field_0_   // get_name_1:  .field_0_   // get_name_2:  .field_0_   // get_Name:    .field_0_   // getName->1:  null   // getName->2:  null   // getName->N:  null   // ofs = -1 ord = 0 addr = 0
	invokevirtual boolean isAlive( java.lang.Thread ) // pc=1
	ifne Label21
Label13:
	aload_0 
	new Worklist$1
	dup 
	aload_0 
	invokespecial com.whatsapp.client.Worklist$1.<init> // pc=2
	putfield .field_0_   // get_name_1:  .field_0_   // get_name_2:  .field_0_   // get_Name:    .field_0_   // getName->1:  null   // getName->2:  null   // getName->N:  null   // ofs = -1 ord = 0 addr = 0
	aload_0_getfield .field_0_   // get_name_1:  .field_0_   // get_name_2:  .field_0_   // get_Name:    .field_0_   // getName->1:  null   // getName->2:  null   // getName->N:  null   // ofs = -1 ord = 0 addr = 0
	invokevirtual start( java.lang.Thread ) // pc=1
Label21:
	aload_2 
	monitorexit 
	return 
	astore_3 
	aload_2 
	monitorexit 
	aload_3 
	athrow 
	}

}
