// #######################################################
// Decompiled by   : coddec 
// Module          : WhatsApp-12.cod
// Module version  : 2.8.1914
// Class ID        : 23
// ########################################################


package com.whatsapp.client;


abstract final class ChatServerOperation$SetPhotoGroup$1 extends Object
implements com.whatsapp.client.FunXMPP$StringRunnable

{

	// @@@@@@@@@@@@@ Fields 
	private final com.whatsapp.client.ChatServerOperation$SetPhotoGroup /*com.whatsapp.client.ChatServerOperation$SetPhotoGroup*/  field_56452 ; // ofs = 56452 addr = 0)

	// @@@@@@@@@@@@@ Static routines 

<init>( com.whatsapp.client.ChatServerOperation$SetPhotoGroup$1, com.whatsapp.client.ChatServerOperation$SetPhotoGroup ); // address: 0
	{
	enter_narrow 
	aload_0 
	invokespecial_lib java.lang.Object.<init> // pc=1
	aload_0 
	aload_1 
	putfield .field_0_   // get_name_1:  .field_0_   // get_name_2:  .field_0_   // get_Name:    .field_0_   // getName->1:  null   // getName->2:  null   // getName->N:  null   // ofs = -1 ord = 0 addr = 0
	return 
	}

	// @@@@@@@@@@@@@ Virtual routines 

public final run( com.whatsapp.client.ChatServerOperation$SetPhotoGroup$1, java.lang.String ); // address: 0
	{
	enter 
	aload_0_getfield .field_0_   // get_name_1:  .field_0_   // get_name_2:  .field_0_   // get_Name:    .field_0_   // getName->1:  null   // getName->2:  null   // getName->N:  null   // ofs = -1 ord = 0 addr = 0
	iconst_1 
	putfield .field_3_3   // get_name_1:  .field_3_3   // get_name_2:  .field_3_3   // get_Name:    .field_3_3   // getName->1:  null   // getName->2:  null   // getName->N:  null   // ofs = -1 ord = 0 addr = 3
	aload_0_getfield .field_0_   // get_name_1:  .field_0_   // get_name_2:  .field_0_   // get_Name:    .field_0_   // getName->1:  null   // getName->2:  null   // getName->N:  null   // ofs = -1 ord = 0 addr = 0
	getfield .field_7_7   // get_name_1:  .field_7_7   // get_name_2:  .field_7_7   // get_Name:    .field_7_7   // getName->1:  null   // getName->2:  null   // getName->N:  null   // ofs = -1 ord = 0 addr = 7
	ifeq Label53
	invokestatic java.util.Hashtable getChats(  ) // ChatMessageStore
	aload_0_getfield .field_0_   // get_name_1:  .field_0_   // get_name_2:  .field_0_   // get_Name:    .field_0_   // getName->1:  null   // getName->2:  null   // getName->N:  null   // ofs = -1 ord = 0 addr = 0
	getfield .field_4_4   // get_name_1:  .field_4_4   // get_name_2:  .field_4_4   // get_Name:    .field_4_4   // getName->1:  null   // getName->2:  null   // getName->N:  null   // ofs = -1 ord = 0 addr = 4
	invokevirtual java.lang.Object get( java.util.Hashtable, java.lang.Object ) // pc=2
	checkcast_lib com.whatsapp.client.ChatHistory//module:WhatsApp-11.class#1 module:WhatsApp-11.class#1 module:WhatsApp-11.class#1
	astore_2 
	aload_2 
	ifnonnull Label16
	goto_w Label68
Label16:
	aconst_null 
	astore_3 
	aload_0_getfield .field_0_   // get_name_1:  .field_0_   // get_name_2:  .field_0_   // get_Name:    .field_0_   // getName->1:  null   // getName->2:  null   // getName->N:  null   // ofs = -1 ord = 0 addr = 0
	getfield .field_6_6   // get_name_1:  .field_6_6   // get_name_2:  .field_6_6   // get_Name:    .field_6_6   // getName->1:  null   // getName->2:  null   // getName->N:  null   // ofs = -1 ord = 0 addr = 6
	ifnull Label29
	aload_0_getfield .field_0_   // get_name_1:  .field_0_   // get_name_2:  .field_0_   // get_Name:    .field_0_   // getName->1:  null   // getName->2:  null   // getName->N:  null   // ofs = -1 ord = 0 addr = 0
	getfield .field_6_6   // get_name_1:  .field_6_6   // get_name_2:  .field_6_6   // get_Name:    .field_6_6   // getName->1:  null   // getName->2:  null   // getName->N:  null   // ofs = -1 ord = 0 addr = 6
	iconst_0 
	aload_0_getfield .field_0_   // get_name_1:  .field_0_   // get_name_2:  .field_0_   // get_Name:    .field_0_   // getName->1:  null   // getName->2:  null   // getName->N:  null   // ofs = -1 ord = 0 addr = 0
	getfield .field_6_6   // get_name_1:  .field_6_6   // get_name_2:  .field_6_6   // get_Name:    .field_6_6   // getName->1:  null   // getName->2:  null   // getName->N:  null   // ofs = -1 ord = 0 addr = 6
	arraylength 
	invokestatic_lib net.rim.device.api.system.EncodedImage createEncodedImage( byte[], int, int ) // EncodedImage
	astore_3 
Label29:
	aload_2 
	getfield .field_8_8   // get_name_1:  .field_8_8   // get_name_2:  .field_8_8   // get_Name:    .field_8_8   // getName->1:  null   // getName->2:  null   // getName->N:  null   // ofs = -1 ord = 0 addr = 8
	aload_1 
	aload_3 
	invokenonvirtual com.whatsapp.client.ChatHistory$Group.setPreviewPhoto // pc=3
	invokestatic_lib module:WhatsApp-44.class#7.routine_3329(  ) // class#7
	invokenonvirtual_lib .routine_2609 // pc=1
	astore_4 
	aload_4 
	aload_0_getfield .field_0_   // get_name_1:  .field_0_   // get_name_2:  .field_0_   // get_Name:    .field_0_   // getName->1:  null   // getName->2:  null   // getName->N:  null   // ofs = -1 ord = 0 addr = 0
	getfield .field_4_4   // get_name_1:  .field_4_4   // get_name_2:  .field_4_4   // get_Name:    .field_4_4   // getName->1:  null   // getName->2:  null   // getName->N:  null   // ofs = -1 ord = 0 addr = 4
	aload_1 
	aload_0_getfield .field_0_   // get_name_1:  .field_0_   // get_name_2:  .field_0_   // get_Name:    .field_0_   // getName->1:  null   // getName->2:  null   // getName->N:  null   // ofs = -1 ord = 0 addr = 0
	getfield .field_5_5   // get_name_1:  .field_5_5   // get_name_2:  .field_5_5   // get_Name:    .field_5_5   // getName->1:  null   // getName->2:  null   // getName->N:  null   // ofs = -1 ord = 0 addr = 5
	invokenonvirtual_lib .routine_14089 // pc=4
	invokestatic_lib module:WhatsApp-44.class#7.routine_3329(  ) // class#7
	aload_4 
	invokenonvirtual_lib .routine_2655 // pc=2
	lipush 3980180135159314637
	aload_0_getfield .field_0_   // get_name_1:  .field_0_   // get_name_2:  .field_0_   // get_Name:    .field_0_   // getName->1:  null   // getName->2:  null   // getName->N:  null   // ofs = -1 ord = 0 addr = 0
	getfield .field_4_4   // get_name_1:  .field_4_4   // get_name_2:  .field_4_4   // get_Name:    .field_4_4   // getName->1:  null   // getName->2:  null   // getName->N:  null   // ofs = -1 ord = 0 addr = 4
	invokestatic_lib module:WhatsApp-79.class#39.routine_26966(  ) // class#39
	pop 
	return 
Label53:
	invokestatic_lib module:WhatsApp-21.class#0.routine_1491(  ) // class#0
	aload_0_getfield .field_0_   // get_name_1:  .field_0_   // get_name_2:  .field_0_   // get_Name:    .field_0_   // getName->1:  null   // getName->2:  null   // getName->N:  null   // ofs = -1 ord = 0 addr = 0
	getfield .field_4_4   // get_name_1:  .field_4_4   // get_name_2:  .field_4_4   // get_Name:    .field_4_4   // getName->1:  null   // getName->2:  null   // getName->N:  null   // ofs = -1 ord = 0 addr = 4
	aload_1 
	aload_0_getfield .field_0_   // get_name_1:  .field_0_   // get_name_2:  .field_0_   // get_Name:    .field_0_   // getName->1:  null   // getName->2:  null   // getName->N:  null   // ofs = -1 ord = 0 addr = 0
	getfield .field_6_6   // get_name_1:  .field_6_6   // get_name_2:  .field_6_6   // get_Name:    .field_6_6   // getName->1:  null   // getName->2:  null   // getName->N:  null   // ofs = -1 ord = 0 addr = 6
	aload_0_getfield .field_0_   // get_name_1:  .field_0_   // get_name_2:  .field_0_   // get_Name:    .field_0_   // getName->1:  null   // getName->2:  null   // getName->N:  null   // ofs = -1 ord = 0 addr = 0
	getfield .field_5_5   // get_name_1:  .field_5_5   // get_name_2:  .field_5_5   // get_Name:    .field_5_5   // getName->1:  null   // getName->2:  null   // getName->N:  null   // ofs = -1 ord = 0 addr = 5
	invokenonvirtual_lib .routine_1073 // pc=5
	invokestatic_lib module:WhatsApp-21.class#0.routine_1676(  ) // class#0
	lipush 4105952464837359382
	aload_0_getfield .field_0_   // get_name_1:  .field_0_   // get_name_2:  .field_0_   // get_Name:    .field_0_   // getName->1:  null   // getName->2:  null   // getName->N:  null   // ofs = -1 ord = 0 addr = 0
	getfield .field_4_4   // get_name_1:  .field_4_4   // get_name_2:  .field_4_4   // get_Name:    .field_4_4   // getName->1:  null   // getName->2:  null   // getName->N:  null   // ofs = -1 ord = 0 addr = 4
	invokestatic_lib module:WhatsApp-79.class#39.routine_26966(  ) // class#39
	pop 
Label68:
	return 
	}

}
