package com.whatsapp.billing;

import android.content.ContentValues;
import android.content.Context;
import android.database.sqlite.SQLiteDatabase;

public class j
{
  private static final String[] a;
  private static final String[] b;
  private static final String[] z;
  private SQLiteDatabase c;
  private a d;

  static
  {
    String[] arrayOfString1 = new String[10];
    char[] arrayOfChar1 = "ZL\026,:IJ0,r\025".toCharArray();
    int i = arrayOfChar1.length;
    int j = 0;
    char[] arrayOfChar2;
    int i1;
    char[] arrayOfChar3;
    int i5;
    char[] arrayOfChar4;
    int i9;
    char[] arrayOfChar5;
    int i13;
    char[] arrayOfChar6;
    int i17;
    char[] arrayOfChar7;
    int i21;
    char[] arrayOfChar8;
    int i25;
    char[] arrayOfChar9;
    int i29;
    char[] arrayOfChar10;
    int i33;
    if (i <= j)
    {
      arrayOfString1[0] = new String(arrayOfChar1).intern();
      arrayOfChar2 = "BW\n< XG".toCharArray();
      int n = arrayOfChar2.length;
      i1 = 0;
      if (n <= i1)
      {
        arrayOfString1[1] = new String(arrayOfChar2).intern();
        arrayOfChar3 = "uW\035up".toCharArray();
        int i4 = arrayOfChar3.length;
        i5 = 0;
        if (i4 > i5)
          break label641;
        arrayOfString1[2] = new String(arrayOfChar3).intern();
        arrayOfChar4 = "ZK\013+'KM\034,".toCharArray();
        int i8 = arrayOfChar4.length;
        i9 = 0;
        if (i8 > i9)
          break label733;
        arrayOfString1[3] = new String(arrayOfChar4).intern();
        arrayOfChar5 = "[K\030&;CJ��".toCharArray();
        int i12 = arrayOfChar5.length;
        i13 = 0;
        if (i12 > i13)
          break label825;
        arrayOfString1[4] = new String(arrayOfChar5).intern();
        arrayOfChar6 = "uW\035".toCharArray();
        int i16 = arrayOfChar6.length;
        i17 = 0;
        if (i16 > i17)
          break label917;
        arrayOfString1[5] = new String(arrayOfChar6).intern();
        arrayOfChar7 = "N[\017-#EN\034:\037KG\025'.N".toCharArray();
        int i20 = arrayOfChar7.length;
        i21 = 0;
        if (i20 > i21)
          break label1009;
        arrayOfString1[6] = new String(arrayOfChar7).intern();
        arrayOfChar8 = "YJ\030<*".toCharArray();
        int i24 = arrayOfChar8.length;
        i25 = 0;
        if (i24 > i25)
          break label1101;
        arrayOfString1[7] = new String(arrayOfChar8).intern();
        arrayOfChar9 = "ZK\013+'KM\034\034&G[".toCharArray();
        int i28 = arrayOfChar9.length;
        i29 = 0;
        if (i28 > i29)
          break label1193;
        arrayOfString1[8] = new String(arrayOfChar9).intern();
        arrayOfChar10 = "ZL\026,:IJ0,".toCharArray();
        int i32 = arrayOfChar10.length;
        i33 = 0;
        if (i32 > i33)
          break label1285;
        arrayOfString1[9] = new String(arrayOfChar10).intern();
        z = arrayOfString1;
        String[] arrayOfString2 = new String[5];
        arrayOfString2[0] = z[5];
        arrayOfString2[1] = z[9];
        arrayOfString2[2] = z[7];
        arrayOfString2[3] = z[8];
        arrayOfString2[4] = z[6];
        a = arrayOfString2;
        String[] arrayOfString3 = new String[2];
        arrayOfString3[0] = z[5];
        arrayOfString3[1] = z[4];
        b = arrayOfString3;
      }
    }
    else
    {
      int k = arrayOfChar1[j];
      int m;
      switch (j % 5)
      {
      default:
        m = 79;
      case 0:
      case 1:
      case 2:
      case 3:
      }
      while (true)
      {
        arrayOfChar1[j] = (char)(m ^ k);
        j++;
        break;
        m = 42;
        continue;
        m = 62;
        continue;
        m = 121;
        continue;
        m = 72;
      }
    }
    int i2 = arrayOfChar2[i1];
    int i3;
    switch (i1 % 5)
    {
    default:
      i3 = 79;
    case 0:
    case 1:
    case 2:
    case 3:
    }
    while (true)
    {
      arrayOfChar2[i1] = (char)(i3 ^ i2);
      i1++;
      break;
      i3 = 42;
      continue;
      i3 = 62;
      continue;
      i3 = 121;
      continue;
      i3 = 72;
    }
    label641: int i6 = arrayOfChar3[i5];
    int i7;
    switch (i5 % 5)
    {
    default:
      i7 = 79;
    case 0:
    case 1:
    case 2:
    case 3:
    }
    while (true)
    {
      arrayOfChar3[i5] = (char)(i7 ^ i6);
      i5++;
      break;
      i7 = 42;
      continue;
      i7 = 62;
      continue;
      i7 = 121;
      continue;
      i7 = 72;
    }
    label733: int i10 = arrayOfChar4[i9];
    int i11;
    switch (i9 % 5)
    {
    default:
      i11 = 79;
    case 0:
    case 1:
    case 2:
    case 3:
    }
    while (true)
    {
      arrayOfChar4[i9] = (char)(i11 ^ i10);
      i9++;
      break;
      i11 = 42;
      continue;
      i11 = 62;
      continue;
      i11 = 121;
      continue;
      i11 = 72;
    }
    label825: int i14 = arrayOfChar5[i13];
    int i15;
    switch (i13 % 5)
    {
    default:
      i15 = 79;
    case 0:
    case 1:
    case 2:
    case 3:
    }
    while (true)
    {
      arrayOfChar5[i13] = (char)(i15 ^ i14);
      i13++;
      break;
      i15 = 42;
      continue;
      i15 = 62;
      continue;
      i15 = 121;
      continue;
      i15 = 72;
    }
    label917: int i18 = arrayOfChar6[i17];
    int i19;
    switch (i17 % 5)
    {
    default:
      i19 = 79;
    case 0:
    case 1:
    case 2:
    case 3:
    }
    while (true)
    {
      arrayOfChar6[i17] = (char)(i19 ^ i18);
      i17++;
      break;
      i19 = 42;
      continue;
      i19 = 62;
      continue;
      i19 = 121;
      continue;
      i19 = 72;
    }
    label1009: int i22 = arrayOfChar7[i21];
    int i23;
    switch (i21 % 5)
    {
    default:
      i23 = 79;
    case 0:
    case 1:
    case 2:
    case 3:
    }
    while (true)
    {
      arrayOfChar7[i21] = (char)(i23 ^ i22);
      i21++;
      break;
      i23 = 42;
      continue;
      i23 = 62;
      continue;
      i23 = 121;
      continue;
      i23 = 72;
    }
    label1101: int i26 = arrayOfChar8[i25];
    int i27;
    switch (i25 % 5)
    {
    default:
      i27 = 79;
    case 0:
    case 1:
    case 2:
    case 3:
    }
    while (true)
    {
      arrayOfChar8[i25] = (char)(i27 ^ i26);
      i25++;
      break;
      i27 = 42;
      continue;
      i27 = 62;
      continue;
      i27 = 121;
      continue;
      i27 = 72;
    }
    label1193: int i30 = arrayOfChar9[i29];
    int i31;
    switch (i29 % 5)
    {
    default:
      i31 = 79;
    case 0:
    case 1:
    case 2:
    case 3:
    }
    while (true)
    {
      arrayOfChar9[i29] = (char)(i31 ^ i30);
      i29++;
      break;
      i31 = 42;
      continue;
      i31 = 62;
      continue;
      i31 = 121;
      continue;
      i31 = 72;
    }
    label1285: int i34 = arrayOfChar10[i33];
    int i35;
    switch (i33 % 5)
    {
    default:
      i35 = 79;
    case 0:
    case 1:
    case 2:
    case 3:
    }
    while (true)
    {
      arrayOfChar10[i33] = (char)(i35 ^ i34);
      i33++;
      break;
      i35 = 42;
      continue;
      i35 = 62;
      continue;
      i35 = 121;
      continue;
      i35 = 72;
    }
  }

  public j(Context paramContext)
  {
    this.d = new a(this, paramContext);
    this.c = this.d.getWritableDatabase();
  }

  private void a(String paramString, int paramInt)
  {
    if (paramInt == 0)
    {
      SQLiteDatabase localSQLiteDatabase = this.c;
      String str1 = z[3];
      String str2 = z[2];
      String[] arrayOfString = new String[1];
      arrayOfString[0] = paramString;
      localSQLiteDatabase.delete(str1, str2, arrayOfString);
    }
    while (true)
    {
      return;
      ContentValues localContentValues = new ContentValues();
      localContentValues.put(z[5], paramString);
      localContentValues.put(z[4], Integer.valueOf(paramInt));
      this.c.replace(z[3], null, localContentValues);
    }
  }

  private void a(String paramString1, String paramString2, b paramb, long paramLong, String paramString3)
  {
    ContentValues localContentValues = new ContentValues();
    localContentValues.put(z[5], paramString1);
    localContentValues.put(z[9], paramString2);
    localContentValues.put(z[7], Integer.valueOf(paramb.ordinal()));
    localContentValues.put(z[8], Long.valueOf(paramLong));
    localContentValues.put(z[6], paramString3);
    this.c.replace(z[1], null, localContentValues);
  }

  public void a()
  {
    this.d.close();
  }

  // ERROR //
  public int b(String paramString1, String paramString2, b paramb, long paramLong, String paramString3)
  {
    // Byte code:
    //   0: aload_0
    //   1: monitorenter
    //   2: getstatic 121	com/whatsapp/billing/i:b	I
    //   5: istore 8
    //   7: aload_0
    //   8: aload_1
    //   9: aload_2
    //   10: aload_3
    //   11: lload 4
    //   13: aload 6
    //   15: invokespecial 123	com/whatsapp/billing/j:a	(Ljava/lang/String;Ljava/lang/String;Lcom/whatsapp/billing/b;JLjava/lang/String;)V
    //   18: aload_0
    //   19: getfield 70	com/whatsapp/billing/j:c	Landroid/database/sqlite/SQLiteDatabase;
    //   22: astore 9
    //   24: getstatic 50	com/whatsapp/billing/j:z	[Ljava/lang/String;
    //   27: iconst_1
    //   28: aaload
    //   29: astore 10
    //   31: getstatic 52	com/whatsapp/billing/j:a	[Ljava/lang/String;
    //   34: astore 11
    //   36: getstatic 50	com/whatsapp/billing/j:z	[Ljava/lang/String;
    //   39: iconst_0
    //   40: aaload
    //   41: astore 12
    //   43: iconst_1
    //   44: anewarray 16	java/lang/String
    //   47: astore 13
    //   49: aload 13
    //   51: iconst_0
    //   52: aload_2
    //   53: aastore
    //   54: aload 9
    //   56: aload 10
    //   58: aload 11
    //   60: aload 12
    //   62: aload 13
    //   64: aconst_null
    //   65: aconst_null
    //   66: aconst_null
    //   67: aconst_null
    //   68: invokevirtual 127	android/database/sqlite/SQLiteDatabase:query	(Ljava/lang/String;[Ljava/lang/String;Ljava/lang/String;[Ljava/lang/String;Ljava/lang/String;Ljava/lang/String;Ljava/lang/String;Ljava/lang/String;)Landroid/database/Cursor;
    //   71: astore 14
    //   73: aload 14
    //   75: ifnonnull +11 -> 86
    //   78: iconst_0
    //   79: istore 15
    //   81: aload_0
    //   82: monitorexit
    //   83: iload 15
    //   85: ireturn
    //   86: iconst_0
    //   87: istore 15
    //   89: aload 14
    //   91: invokeinterface 133 1 0
    //   96: ifeq +35 -> 131
    //   99: aload 14
    //   101: iconst_2
    //   102: invokeinterface 137 2 0
    //   107: invokestatic 140	com/whatsapp/billing/b:a	(I)Lcom/whatsapp/billing/b;
    //   110: astore 17
    //   112: aload 17
    //   114: getstatic 143	com/whatsapp/billing/b:a	Lcom/whatsapp/billing/b;
    //   117: if_acmpeq +60 -> 177
    //   120: aload 17
    //   122: getstatic 145	com/whatsapp/billing/b:c	Lcom/whatsapp/billing/b;
    //   125: if_acmpne +55 -> 180
    //   128: goto +49 -> 177
    //   131: aload_0
    //   132: aload_2
    //   133: iload 15
    //   135: invokespecial 147	com/whatsapp/billing/j:a	(Ljava/lang/String;I)V
    //   138: aload 14
    //   140: ifnull -59 -> 81
    //   143: aload 14
    //   145: invokeinterface 148 1 0
    //   150: goto -69 -> 81
    //   153: astore 7
    //   155: aload_0
    //   156: monitorexit
    //   157: aload 7
    //   159: athrow
    //   160: astore 16
    //   162: aload 14
    //   164: ifnull +10 -> 174
    //   167: aload 14
    //   169: invokeinterface 148 1 0
    //   174: aload 16
    //   176: athrow
    //   177: iinc 15 1
    //   180: iload 8
    //   182: ifeq -93 -> 89
    //   185: goto -54 -> 131
    //
    // Exception table:
    //   from	to	target	type
    //   2	73	153	finally
    //   143	150	153	finally
    //   167	177	153	finally
    //   89	138	160	finally
  }
}

/* Location:           C:\Users\Jaap\Downloads\Code\WhatsApp-2.8.4278_dex2jar.jar
 * Qualified Name:     com.whatsapp.billing.j
 * JD-Core Version:    0.6.1
 */