package com.whatsapp;

import android.app.Activity;
import android.content.ContentResolver;
import android.content.Context;
import android.content.Intent;
import android.content.SharedPreferences;
import android.content.SharedPreferences.Editor;
import android.content.pm.ActivityInfo;
import android.content.pm.ApplicationInfo;
import android.content.pm.PackageManager;
import android.content.pm.ResolveInfo;
import android.content.res.Resources;
import android.database.Cursor;
import android.graphics.Bitmap;
import android.graphics.Bitmap.CompressFormat;
import android.graphics.Bitmap.Config;
import android.graphics.BitmapFactory.Options;
import android.graphics.Canvas;
import android.graphics.Matrix;
import android.graphics.Paint;
import android.graphics.Paint.Align;
import android.graphics.Paint.Style;
import android.graphics.Path;
import android.graphics.PorterDuff.Mode;
import android.graphics.PorterDuffXfermode;
import android.graphics.Rect;
import android.graphics.RectF;
import android.graphics.Typeface;
import android.media.MediaMetadataRetriever;
import android.net.Uri;
import android.os.Build.VERSION;
import android.os.Debug;
import android.os.Parcelable;
import android.provider.MediaStore.Images.Media;
import android.provider.MediaStore.Video.Media;
import android.text.TextPaint;
import android.text.TextUtils;
import android.text.TextUtils.TruncateAt;
import android.util.Pair;
import android.widget.ImageView;
import android.widget.ImageView.ScaleType;
import java.io.ByteArrayOutputStream;
import java.io.File;
import java.io.FileNotFoundException;
import java.io.FileOutputStream;
import java.io.IOException;
import java.io.OutputStream;
import java.lang.ref.SoftReference;
import java.text.DecimalFormat;
import java.util.ArrayList;
import java.util.Date;
import java.util.HashMap;
import java.util.Iterator;
import java.util.List;
import java.util.Set;

public class j5
{
  private static File a;
  public static Intent b;
  public static int c;
  public static int d;
  private static int e;
  private static long f;
  private static int g;
  private static int h;
  public static BitmapFactory.Options i;
  private static final String[] z;

  // ERROR //
  static
  {
    // Byte code:
    //   0: bipush 78
    //   2: anewarray 24	java/lang/String
    //   5: astore_0
    //   6: ldc 26
    //   8: invokevirtual 30	java/lang/String:toCharArray	()[C
    //   11: astore_1
    //   12: aload_1
    //   13: arraylength
    //   14: istore_2
    //   15: iconst_0
    //   16: istore_3
    //   17: iload_2
    //   18: iload_3
    //   19: if_icmpgt +3346 -> 3365
    //   22: aload_0
    //   23: iconst_0
    //   24: new 24	java/lang/String
    //   27: dup
    //   28: aload_1
    //   29: invokespecial 34	java/lang/String:<init>	([C)V
    //   32: invokevirtual 38	java/lang/String:intern	()Ljava/lang/String;
    //   35: aastore
    //   36: ldc 40
    //   38: invokevirtual 30	java/lang/String:toCharArray	()[C
    //   41: astore 6
    //   43: aload 6
    //   45: arraylength
    //   46: istore 7
    //   48: iconst_0
    //   49: istore 8
    //   51: iload 7
    //   53: iload 8
    //   55: if_icmpgt +3396 -> 3451
    //   58: aload_0
    //   59: iconst_1
    //   60: new 24	java/lang/String
    //   63: dup
    //   64: aload 6
    //   66: invokespecial 34	java/lang/String:<init>	([C)V
    //   69: invokevirtual 38	java/lang/String:intern	()Ljava/lang/String;
    //   72: aastore
    //   73: ldc 42
    //   75: invokevirtual 30	java/lang/String:toCharArray	()[C
    //   78: astore 11
    //   80: aload 11
    //   82: arraylength
    //   83: istore 12
    //   85: iconst_0
    //   86: istore 13
    //   88: iload 12
    //   90: iload 13
    //   92: if_icmpgt +3449 -> 3541
    //   95: aload_0
    //   96: iconst_2
    //   97: new 24	java/lang/String
    //   100: dup
    //   101: aload 11
    //   103: invokespecial 34	java/lang/String:<init>	([C)V
    //   106: invokevirtual 38	java/lang/String:intern	()Ljava/lang/String;
    //   109: aastore
    //   110: ldc 44
    //   112: invokevirtual 30	java/lang/String:toCharArray	()[C
    //   115: astore 16
    //   117: aload 16
    //   119: arraylength
    //   120: istore 17
    //   122: iconst_0
    //   123: istore 18
    //   125: iload 17
    //   127: iload 18
    //   129: if_icmpgt +3504 -> 3633
    //   132: aload_0
    //   133: iconst_3
    //   134: new 24	java/lang/String
    //   137: dup
    //   138: aload 16
    //   140: invokespecial 34	java/lang/String:<init>	([C)V
    //   143: invokevirtual 38	java/lang/String:intern	()Ljava/lang/String;
    //   146: aastore
    //   147: ldc 46
    //   149: invokevirtual 30	java/lang/String:toCharArray	()[C
    //   152: astore 21
    //   154: aload 21
    //   156: arraylength
    //   157: istore 22
    //   159: iconst_0
    //   160: istore 23
    //   162: iload 22
    //   164: iload 23
    //   166: if_icmpgt +3559 -> 3725
    //   169: aload_0
    //   170: iconst_4
    //   171: new 24	java/lang/String
    //   174: dup
    //   175: aload 21
    //   177: invokespecial 34	java/lang/String:<init>	([C)V
    //   180: invokevirtual 38	java/lang/String:intern	()Ljava/lang/String;
    //   183: aastore
    //   184: ldc 48
    //   186: invokevirtual 30	java/lang/String:toCharArray	()[C
    //   189: astore 26
    //   191: aload 26
    //   193: arraylength
    //   194: istore 27
    //   196: iconst_0
    //   197: istore 28
    //   199: iload 27
    //   201: iload 28
    //   203: if_icmpgt +3614 -> 3817
    //   206: aload_0
    //   207: iconst_5
    //   208: new 24	java/lang/String
    //   211: dup
    //   212: aload 26
    //   214: invokespecial 34	java/lang/String:<init>	([C)V
    //   217: invokevirtual 38	java/lang/String:intern	()Ljava/lang/String;
    //   220: aastore
    //   221: ldc 50
    //   223: invokevirtual 30	java/lang/String:toCharArray	()[C
    //   226: astore 31
    //   228: aload 31
    //   230: arraylength
    //   231: istore 32
    //   233: iconst_0
    //   234: istore 33
    //   236: iload 32
    //   238: iload 33
    //   240: if_icmpgt +3669 -> 3909
    //   243: aload_0
    //   244: bipush 6
    //   246: new 24	java/lang/String
    //   249: dup
    //   250: aload 31
    //   252: invokespecial 34	java/lang/String:<init>	([C)V
    //   255: invokevirtual 38	java/lang/String:intern	()Ljava/lang/String;
    //   258: aastore
    //   259: ldc 52
    //   261: invokevirtual 30	java/lang/String:toCharArray	()[C
    //   264: astore 36
    //   266: aload 36
    //   268: arraylength
    //   269: istore 37
    //   271: iconst_0
    //   272: istore 38
    //   274: iload 37
    //   276: iload 38
    //   278: if_icmpgt +3723 -> 4001
    //   281: aload_0
    //   282: bipush 7
    //   284: new 24	java/lang/String
    //   287: dup
    //   288: aload 36
    //   290: invokespecial 34	java/lang/String:<init>	([C)V
    //   293: invokevirtual 38	java/lang/String:intern	()Ljava/lang/String;
    //   296: aastore
    //   297: ldc 54
    //   299: invokevirtual 30	java/lang/String:toCharArray	()[C
    //   302: astore 41
    //   304: aload 41
    //   306: arraylength
    //   307: istore 42
    //   309: iconst_0
    //   310: istore 43
    //   312: iload 42
    //   314: iload 43
    //   316: if_icmpgt +3777 -> 4093
    //   319: aload_0
    //   320: bipush 8
    //   322: new 24	java/lang/String
    //   325: dup
    //   326: aload 41
    //   328: invokespecial 34	java/lang/String:<init>	([C)V
    //   331: invokevirtual 38	java/lang/String:intern	()Ljava/lang/String;
    //   334: aastore
    //   335: ldc 56
    //   337: invokevirtual 30	java/lang/String:toCharArray	()[C
    //   340: astore 46
    //   342: aload 46
    //   344: arraylength
    //   345: istore 47
    //   347: iconst_0
    //   348: istore 48
    //   350: iload 47
    //   352: iload 48
    //   354: if_icmpgt +3831 -> 4185
    //   357: aload_0
    //   358: bipush 9
    //   360: new 24	java/lang/String
    //   363: dup
    //   364: aload 46
    //   366: invokespecial 34	java/lang/String:<init>	([C)V
    //   369: invokevirtual 38	java/lang/String:intern	()Ljava/lang/String;
    //   372: aastore
    //   373: ldc 58
    //   375: invokevirtual 30	java/lang/String:toCharArray	()[C
    //   378: astore 51
    //   380: aload 51
    //   382: arraylength
    //   383: istore 52
    //   385: iconst_0
    //   386: istore 53
    //   388: iload 52
    //   390: iload 53
    //   392: if_icmpgt +3885 -> 4277
    //   395: aload_0
    //   396: bipush 10
    //   398: new 24	java/lang/String
    //   401: dup
    //   402: aload 51
    //   404: invokespecial 34	java/lang/String:<init>	([C)V
    //   407: invokevirtual 38	java/lang/String:intern	()Ljava/lang/String;
    //   410: aastore
    //   411: ldc 60
    //   413: invokevirtual 30	java/lang/String:toCharArray	()[C
    //   416: astore 56
    //   418: aload 56
    //   420: arraylength
    //   421: istore 57
    //   423: iconst_0
    //   424: istore 58
    //   426: iload 57
    //   428: iload 58
    //   430: if_icmpgt +3939 -> 4369
    //   433: aload_0
    //   434: bipush 11
    //   436: new 24	java/lang/String
    //   439: dup
    //   440: aload 56
    //   442: invokespecial 34	java/lang/String:<init>	([C)V
    //   445: invokevirtual 38	java/lang/String:intern	()Ljava/lang/String;
    //   448: aastore
    //   449: ldc 62
    //   451: invokevirtual 30	java/lang/String:toCharArray	()[C
    //   454: astore 61
    //   456: aload 61
    //   458: arraylength
    //   459: istore 62
    //   461: iconst_0
    //   462: istore 63
    //   464: iload 62
    //   466: iload 63
    //   468: if_icmpgt +3993 -> 4461
    //   471: aload_0
    //   472: bipush 12
    //   474: new 24	java/lang/String
    //   477: dup
    //   478: aload 61
    //   480: invokespecial 34	java/lang/String:<init>	([C)V
    //   483: invokevirtual 38	java/lang/String:intern	()Ljava/lang/String;
    //   486: aastore
    //   487: ldc 64
    //   489: invokevirtual 30	java/lang/String:toCharArray	()[C
    //   492: astore 66
    //   494: aload 66
    //   496: arraylength
    //   497: istore 67
    //   499: iconst_0
    //   500: istore 68
    //   502: iload 67
    //   504: iload 68
    //   506: if_icmpgt +4047 -> 4553
    //   509: aload_0
    //   510: bipush 13
    //   512: new 24	java/lang/String
    //   515: dup
    //   516: aload 66
    //   518: invokespecial 34	java/lang/String:<init>	([C)V
    //   521: invokevirtual 38	java/lang/String:intern	()Ljava/lang/String;
    //   524: aastore
    //   525: ldc 66
    //   527: invokevirtual 30	java/lang/String:toCharArray	()[C
    //   530: astore 71
    //   532: aload 71
    //   534: arraylength
    //   535: istore 72
    //   537: iconst_0
    //   538: istore 73
    //   540: iload 72
    //   542: iload 73
    //   544: if_icmpgt +4101 -> 4645
    //   547: aload_0
    //   548: bipush 14
    //   550: new 24	java/lang/String
    //   553: dup
    //   554: aload 71
    //   556: invokespecial 34	java/lang/String:<init>	([C)V
    //   559: invokevirtual 38	java/lang/String:intern	()Ljava/lang/String;
    //   562: aastore
    //   563: ldc 68
    //   565: invokevirtual 30	java/lang/String:toCharArray	()[C
    //   568: astore 76
    //   570: aload 76
    //   572: arraylength
    //   573: istore 77
    //   575: iconst_0
    //   576: istore 78
    //   578: iload 77
    //   580: iload 78
    //   582: if_icmpgt +4155 -> 4737
    //   585: aload_0
    //   586: bipush 15
    //   588: new 24	java/lang/String
    //   591: dup
    //   592: aload 76
    //   594: invokespecial 34	java/lang/String:<init>	([C)V
    //   597: invokevirtual 38	java/lang/String:intern	()Ljava/lang/String;
    //   600: aastore
    //   601: ldc 70
    //   603: invokevirtual 30	java/lang/String:toCharArray	()[C
    //   606: astore 81
    //   608: aload 81
    //   610: arraylength
    //   611: istore 82
    //   613: iconst_0
    //   614: istore 83
    //   616: iload 82
    //   618: iload 83
    //   620: if_icmpgt +4209 -> 4829
    //   623: aload_0
    //   624: bipush 16
    //   626: new 24	java/lang/String
    //   629: dup
    //   630: aload 81
    //   632: invokespecial 34	java/lang/String:<init>	([C)V
    //   635: invokevirtual 38	java/lang/String:intern	()Ljava/lang/String;
    //   638: aastore
    //   639: ldc 72
    //   641: invokevirtual 30	java/lang/String:toCharArray	()[C
    //   644: astore 86
    //   646: aload 86
    //   648: arraylength
    //   649: istore 87
    //   651: iconst_0
    //   652: istore 88
    //   654: iload 87
    //   656: iload 88
    //   658: if_icmpgt +4263 -> 4921
    //   661: aload_0
    //   662: bipush 17
    //   664: new 24	java/lang/String
    //   667: dup
    //   668: aload 86
    //   670: invokespecial 34	java/lang/String:<init>	([C)V
    //   673: invokevirtual 38	java/lang/String:intern	()Ljava/lang/String;
    //   676: aastore
    //   677: ldc 74
    //   679: invokevirtual 30	java/lang/String:toCharArray	()[C
    //   682: astore 91
    //   684: aload 91
    //   686: arraylength
    //   687: istore 92
    //   689: iconst_0
    //   690: istore 93
    //   692: iload 92
    //   694: iload 93
    //   696: if_icmpgt +4317 -> 5013
    //   699: aload_0
    //   700: bipush 18
    //   702: new 24	java/lang/String
    //   705: dup
    //   706: aload 91
    //   708: invokespecial 34	java/lang/String:<init>	([C)V
    //   711: invokevirtual 38	java/lang/String:intern	()Ljava/lang/String;
    //   714: aastore
    //   715: ldc 76
    //   717: invokevirtual 30	java/lang/String:toCharArray	()[C
    //   720: astore 96
    //   722: aload 96
    //   724: arraylength
    //   725: istore 97
    //   727: iconst_0
    //   728: istore 98
    //   730: iload 97
    //   732: iload 98
    //   734: if_icmpgt +4371 -> 5105
    //   737: aload_0
    //   738: bipush 19
    //   740: new 24	java/lang/String
    //   743: dup
    //   744: aload 96
    //   746: invokespecial 34	java/lang/String:<init>	([C)V
    //   749: invokevirtual 38	java/lang/String:intern	()Ljava/lang/String;
    //   752: aastore
    //   753: ldc 78
    //   755: invokevirtual 30	java/lang/String:toCharArray	()[C
    //   758: astore 101
    //   760: aload 101
    //   762: arraylength
    //   763: istore 102
    //   765: iconst_0
    //   766: istore 103
    //   768: iload 102
    //   770: iload 103
    //   772: if_icmpgt +4425 -> 5197
    //   775: aload_0
    //   776: bipush 20
    //   778: new 24	java/lang/String
    //   781: dup
    //   782: aload 101
    //   784: invokespecial 34	java/lang/String:<init>	([C)V
    //   787: invokevirtual 38	java/lang/String:intern	()Ljava/lang/String;
    //   790: aastore
    //   791: ldc 80
    //   793: invokevirtual 30	java/lang/String:toCharArray	()[C
    //   796: astore 106
    //   798: aload 106
    //   800: arraylength
    //   801: istore 107
    //   803: iconst_0
    //   804: istore 108
    //   806: iload 107
    //   808: iload 108
    //   810: if_icmpgt +4479 -> 5289
    //   813: aload_0
    //   814: bipush 21
    //   816: new 24	java/lang/String
    //   819: dup
    //   820: aload 106
    //   822: invokespecial 34	java/lang/String:<init>	([C)V
    //   825: invokevirtual 38	java/lang/String:intern	()Ljava/lang/String;
    //   828: aastore
    //   829: ldc 82
    //   831: invokevirtual 30	java/lang/String:toCharArray	()[C
    //   834: astore 111
    //   836: aload 111
    //   838: arraylength
    //   839: istore 112
    //   841: iconst_0
    //   842: istore 113
    //   844: iload 112
    //   846: iload 113
    //   848: if_icmpgt +4533 -> 5381
    //   851: aload_0
    //   852: bipush 22
    //   854: new 24	java/lang/String
    //   857: dup
    //   858: aload 111
    //   860: invokespecial 34	java/lang/String:<init>	([C)V
    //   863: invokevirtual 38	java/lang/String:intern	()Ljava/lang/String;
    //   866: aastore
    //   867: ldc 84
    //   869: invokevirtual 30	java/lang/String:toCharArray	()[C
    //   872: astore 116
    //   874: aload 116
    //   876: arraylength
    //   877: istore 117
    //   879: iconst_0
    //   880: istore 118
    //   882: iload 117
    //   884: iload 118
    //   886: if_icmpgt +4587 -> 5473
    //   889: aload_0
    //   890: bipush 23
    //   892: new 24	java/lang/String
    //   895: dup
    //   896: aload 116
    //   898: invokespecial 34	java/lang/String:<init>	([C)V
    //   901: invokevirtual 38	java/lang/String:intern	()Ljava/lang/String;
    //   904: aastore
    //   905: ldc 86
    //   907: invokevirtual 30	java/lang/String:toCharArray	()[C
    //   910: astore 121
    //   912: aload 121
    //   914: arraylength
    //   915: istore 122
    //   917: iconst_0
    //   918: istore 123
    //   920: iload 122
    //   922: iload 123
    //   924: if_icmpgt +4641 -> 5565
    //   927: aload_0
    //   928: bipush 24
    //   930: new 24	java/lang/String
    //   933: dup
    //   934: aload 121
    //   936: invokespecial 34	java/lang/String:<init>	([C)V
    //   939: invokevirtual 38	java/lang/String:intern	()Ljava/lang/String;
    //   942: aastore
    //   943: ldc 88
    //   945: invokevirtual 30	java/lang/String:toCharArray	()[C
    //   948: astore 126
    //   950: aload 126
    //   952: arraylength
    //   953: istore 127
    //   955: iconst_0
    //   956: istore 128
    //   958: iload 127
    //   960: iload 128
    //   962: if_icmpgt +4695 -> 5657
    //   965: aload_0
    //   966: bipush 25
    //   968: new 24	java/lang/String
    //   971: dup
    //   972: aload 126
    //   974: invokespecial 34	java/lang/String:<init>	([C)V
    //   977: invokevirtual 38	java/lang/String:intern	()Ljava/lang/String;
    //   980: aastore
    //   981: ldc 90
    //   983: invokevirtual 30	java/lang/String:toCharArray	()[C
    //   986: astore 131
    //   988: aload 131
    //   990: arraylength
    //   991: istore 132
    //   993: iconst_0
    //   994: istore 133
    //   996: iload 132
    //   998: iload 133
    //   1000: if_icmpgt +4749 -> 5749
    //   1003: aload_0
    //   1004: bipush 26
    //   1006: new 24	java/lang/String
    //   1009: dup
    //   1010: aload 131
    //   1012: invokespecial 34	java/lang/String:<init>	([C)V
    //   1015: invokevirtual 38	java/lang/String:intern	()Ljava/lang/String;
    //   1018: aastore
    //   1019: ldc 92
    //   1021: invokevirtual 30	java/lang/String:toCharArray	()[C
    //   1024: astore 136
    //   1026: aload 136
    //   1028: arraylength
    //   1029: istore 137
    //   1031: iconst_0
    //   1032: istore 138
    //   1034: iload 137
    //   1036: iload 138
    //   1038: if_icmpgt +4803 -> 5841
    //   1041: aload_0
    //   1042: bipush 27
    //   1044: new 24	java/lang/String
    //   1047: dup
    //   1048: aload 136
    //   1050: invokespecial 34	java/lang/String:<init>	([C)V
    //   1053: invokevirtual 38	java/lang/String:intern	()Ljava/lang/String;
    //   1056: aastore
    //   1057: ldc 94
    //   1059: invokevirtual 30	java/lang/String:toCharArray	()[C
    //   1062: astore 141
    //   1064: aload 141
    //   1066: arraylength
    //   1067: istore 142
    //   1069: iconst_0
    //   1070: istore 143
    //   1072: iload 142
    //   1074: iload 143
    //   1076: if_icmpgt +4857 -> 5933
    //   1079: aload_0
    //   1080: bipush 28
    //   1082: new 24	java/lang/String
    //   1085: dup
    //   1086: aload 141
    //   1088: invokespecial 34	java/lang/String:<init>	([C)V
    //   1091: invokevirtual 38	java/lang/String:intern	()Ljava/lang/String;
    //   1094: aastore
    //   1095: ldc 96
    //   1097: invokevirtual 30	java/lang/String:toCharArray	()[C
    //   1100: astore 146
    //   1102: aload 146
    //   1104: arraylength
    //   1105: istore 147
    //   1107: iconst_0
    //   1108: istore 148
    //   1110: iload 147
    //   1112: iload 148
    //   1114: if_icmpgt +4911 -> 6025
    //   1117: aload_0
    //   1118: bipush 29
    //   1120: new 24	java/lang/String
    //   1123: dup
    //   1124: aload 146
    //   1126: invokespecial 34	java/lang/String:<init>	([C)V
    //   1129: invokevirtual 38	java/lang/String:intern	()Ljava/lang/String;
    //   1132: aastore
    //   1133: ldc 98
    //   1135: invokevirtual 30	java/lang/String:toCharArray	()[C
    //   1138: astore 151
    //   1140: aload 151
    //   1142: arraylength
    //   1143: istore 152
    //   1145: iconst_0
    //   1146: istore 153
    //   1148: iload 152
    //   1150: iload 153
    //   1152: if_icmpgt +4965 -> 6117
    //   1155: aload_0
    //   1156: bipush 30
    //   1158: new 24	java/lang/String
    //   1161: dup
    //   1162: aload 151
    //   1164: invokespecial 34	java/lang/String:<init>	([C)V
    //   1167: invokevirtual 38	java/lang/String:intern	()Ljava/lang/String;
    //   1170: aastore
    //   1171: ldc 100
    //   1173: invokevirtual 30	java/lang/String:toCharArray	()[C
    //   1176: astore 156
    //   1178: aload 156
    //   1180: arraylength
    //   1181: istore 157
    //   1183: iconst_0
    //   1184: istore 158
    //   1186: iload 157
    //   1188: iload 158
    //   1190: if_icmpgt +5019 -> 6209
    //   1193: aload_0
    //   1194: bipush 31
    //   1196: new 24	java/lang/String
    //   1199: dup
    //   1200: aload 156
    //   1202: invokespecial 34	java/lang/String:<init>	([C)V
    //   1205: invokevirtual 38	java/lang/String:intern	()Ljava/lang/String;
    //   1208: aastore
    //   1209: ldc 102
    //   1211: invokevirtual 30	java/lang/String:toCharArray	()[C
    //   1214: astore 161
    //   1216: aload 161
    //   1218: arraylength
    //   1219: istore 162
    //   1221: iconst_0
    //   1222: istore 163
    //   1224: iload 162
    //   1226: iload 163
    //   1228: if_icmpgt +5073 -> 6301
    //   1231: aload_0
    //   1232: bipush 32
    //   1234: new 24	java/lang/String
    //   1237: dup
    //   1238: aload 161
    //   1240: invokespecial 34	java/lang/String:<init>	([C)V
    //   1243: invokevirtual 38	java/lang/String:intern	()Ljava/lang/String;
    //   1246: aastore
    //   1247: ldc 104
    //   1249: invokevirtual 30	java/lang/String:toCharArray	()[C
    //   1252: astore 166
    //   1254: aload 166
    //   1256: arraylength
    //   1257: istore 167
    //   1259: iconst_0
    //   1260: istore 168
    //   1262: iload 167
    //   1264: iload 168
    //   1266: if_icmpgt +5127 -> 6393
    //   1269: aload_0
    //   1270: bipush 33
    //   1272: new 24	java/lang/String
    //   1275: dup
    //   1276: aload 166
    //   1278: invokespecial 34	java/lang/String:<init>	([C)V
    //   1281: invokevirtual 38	java/lang/String:intern	()Ljava/lang/String;
    //   1284: aastore
    //   1285: ldc 106
    //   1287: invokevirtual 30	java/lang/String:toCharArray	()[C
    //   1290: astore 171
    //   1292: aload 171
    //   1294: arraylength
    //   1295: istore 172
    //   1297: iconst_0
    //   1298: istore 173
    //   1300: iload 172
    //   1302: iload 173
    //   1304: if_icmpgt +5181 -> 6485
    //   1307: aload_0
    //   1308: bipush 34
    //   1310: new 24	java/lang/String
    //   1313: dup
    //   1314: aload 171
    //   1316: invokespecial 34	java/lang/String:<init>	([C)V
    //   1319: invokevirtual 38	java/lang/String:intern	()Ljava/lang/String;
    //   1322: aastore
    //   1323: ldc 108
    //   1325: invokevirtual 30	java/lang/String:toCharArray	()[C
    //   1328: astore 176
    //   1330: aload 176
    //   1332: arraylength
    //   1333: istore 177
    //   1335: iconst_0
    //   1336: istore 178
    //   1338: iload 177
    //   1340: iload 178
    //   1342: if_icmpgt +5235 -> 6577
    //   1345: aload_0
    //   1346: bipush 35
    //   1348: new 24	java/lang/String
    //   1351: dup
    //   1352: aload 176
    //   1354: invokespecial 34	java/lang/String:<init>	([C)V
    //   1357: invokevirtual 38	java/lang/String:intern	()Ljava/lang/String;
    //   1360: aastore
    //   1361: ldc 110
    //   1363: invokevirtual 30	java/lang/String:toCharArray	()[C
    //   1366: astore 181
    //   1368: aload 181
    //   1370: arraylength
    //   1371: istore 182
    //   1373: iconst_0
    //   1374: istore 183
    //   1376: iload 182
    //   1378: iload 183
    //   1380: if_icmpgt +5289 -> 6669
    //   1383: aload_0
    //   1384: bipush 36
    //   1386: new 24	java/lang/String
    //   1389: dup
    //   1390: aload 181
    //   1392: invokespecial 34	java/lang/String:<init>	([C)V
    //   1395: invokevirtual 38	java/lang/String:intern	()Ljava/lang/String;
    //   1398: aastore
    //   1399: ldc 112
    //   1401: invokevirtual 30	java/lang/String:toCharArray	()[C
    //   1404: astore 186
    //   1406: aload 186
    //   1408: arraylength
    //   1409: istore 187
    //   1411: iconst_0
    //   1412: istore 188
    //   1414: iload 187
    //   1416: iload 188
    //   1418: if_icmpgt +5343 -> 6761
    //   1421: aload_0
    //   1422: bipush 37
    //   1424: new 24	java/lang/String
    //   1427: dup
    //   1428: aload 186
    //   1430: invokespecial 34	java/lang/String:<init>	([C)V
    //   1433: invokevirtual 38	java/lang/String:intern	()Ljava/lang/String;
    //   1436: aastore
    //   1437: ldc 114
    //   1439: invokevirtual 30	java/lang/String:toCharArray	()[C
    //   1442: astore 191
    //   1444: aload 191
    //   1446: arraylength
    //   1447: istore 192
    //   1449: iconst_0
    //   1450: istore 193
    //   1452: iload 192
    //   1454: iload 193
    //   1456: if_icmpgt +5397 -> 6853
    //   1459: aload_0
    //   1460: bipush 38
    //   1462: new 24	java/lang/String
    //   1465: dup
    //   1466: aload 191
    //   1468: invokespecial 34	java/lang/String:<init>	([C)V
    //   1471: invokevirtual 38	java/lang/String:intern	()Ljava/lang/String;
    //   1474: aastore
    //   1475: ldc 116
    //   1477: invokevirtual 30	java/lang/String:toCharArray	()[C
    //   1480: astore 196
    //   1482: aload 196
    //   1484: arraylength
    //   1485: istore 197
    //   1487: iconst_0
    //   1488: istore 198
    //   1490: iload 197
    //   1492: iload 198
    //   1494: if_icmpgt +5451 -> 6945
    //   1497: aload_0
    //   1498: bipush 39
    //   1500: new 24	java/lang/String
    //   1503: dup
    //   1504: aload 196
    //   1506: invokespecial 34	java/lang/String:<init>	([C)V
    //   1509: invokevirtual 38	java/lang/String:intern	()Ljava/lang/String;
    //   1512: aastore
    //   1513: ldc 118
    //   1515: invokevirtual 30	java/lang/String:toCharArray	()[C
    //   1518: astore 201
    //   1520: aload 201
    //   1522: arraylength
    //   1523: istore 202
    //   1525: iconst_0
    //   1526: istore 203
    //   1528: iload 202
    //   1530: iload 203
    //   1532: if_icmpgt +5505 -> 7037
    //   1535: aload_0
    //   1536: bipush 40
    //   1538: new 24	java/lang/String
    //   1541: dup
    //   1542: aload 201
    //   1544: invokespecial 34	java/lang/String:<init>	([C)V
    //   1547: invokevirtual 38	java/lang/String:intern	()Ljava/lang/String;
    //   1550: aastore
    //   1551: ldc 120
    //   1553: invokevirtual 30	java/lang/String:toCharArray	()[C
    //   1556: astore 206
    //   1558: aload 206
    //   1560: arraylength
    //   1561: istore 207
    //   1563: iconst_0
    //   1564: istore 208
    //   1566: iload 207
    //   1568: iload 208
    //   1570: if_icmpgt +5559 -> 7129
    //   1573: aload_0
    //   1574: bipush 41
    //   1576: new 24	java/lang/String
    //   1579: dup
    //   1580: aload 206
    //   1582: invokespecial 34	java/lang/String:<init>	([C)V
    //   1585: invokevirtual 38	java/lang/String:intern	()Ljava/lang/String;
    //   1588: aastore
    //   1589: ldc 122
    //   1591: invokevirtual 30	java/lang/String:toCharArray	()[C
    //   1594: astore 211
    //   1596: aload 211
    //   1598: arraylength
    //   1599: istore 212
    //   1601: iconst_0
    //   1602: istore 213
    //   1604: iload 212
    //   1606: iload 213
    //   1608: if_icmpgt +5613 -> 7221
    //   1611: aload_0
    //   1612: bipush 42
    //   1614: new 24	java/lang/String
    //   1617: dup
    //   1618: aload 211
    //   1620: invokespecial 34	java/lang/String:<init>	([C)V
    //   1623: invokevirtual 38	java/lang/String:intern	()Ljava/lang/String;
    //   1626: aastore
    //   1627: ldc 124
    //   1629: invokevirtual 30	java/lang/String:toCharArray	()[C
    //   1632: astore 216
    //   1634: aload 216
    //   1636: arraylength
    //   1637: istore 217
    //   1639: iconst_0
    //   1640: istore 218
    //   1642: iload 217
    //   1644: iload 218
    //   1646: if_icmpgt +5667 -> 7313
    //   1649: aload_0
    //   1650: bipush 43
    //   1652: new 24	java/lang/String
    //   1655: dup
    //   1656: aload 216
    //   1658: invokespecial 34	java/lang/String:<init>	([C)V
    //   1661: invokevirtual 38	java/lang/String:intern	()Ljava/lang/String;
    //   1664: aastore
    //   1665: ldc 126
    //   1667: invokevirtual 30	java/lang/String:toCharArray	()[C
    //   1670: astore 221
    //   1672: aload 221
    //   1674: arraylength
    //   1675: istore 222
    //   1677: iconst_0
    //   1678: istore 223
    //   1680: iload 222
    //   1682: iload 223
    //   1684: if_icmpgt +5721 -> 7405
    //   1687: aload_0
    //   1688: bipush 44
    //   1690: new 24	java/lang/String
    //   1693: dup
    //   1694: aload 221
    //   1696: invokespecial 34	java/lang/String:<init>	([C)V
    //   1699: invokevirtual 38	java/lang/String:intern	()Ljava/lang/String;
    //   1702: aastore
    //   1703: ldc 128
    //   1705: invokevirtual 30	java/lang/String:toCharArray	()[C
    //   1708: astore 226
    //   1710: aload 226
    //   1712: arraylength
    //   1713: istore 227
    //   1715: iconst_0
    //   1716: istore 228
    //   1718: iload 227
    //   1720: iload 228
    //   1722: if_icmpgt +5775 -> 7497
    //   1725: aload_0
    //   1726: bipush 45
    //   1728: new 24	java/lang/String
    //   1731: dup
    //   1732: aload 226
    //   1734: invokespecial 34	java/lang/String:<init>	([C)V
    //   1737: invokevirtual 38	java/lang/String:intern	()Ljava/lang/String;
    //   1740: aastore
    //   1741: ldc 130
    //   1743: invokevirtual 30	java/lang/String:toCharArray	()[C
    //   1746: astore 231
    //   1748: aload 231
    //   1750: arraylength
    //   1751: istore 232
    //   1753: iconst_0
    //   1754: istore 233
    //   1756: iload 232
    //   1758: iload 233
    //   1760: if_icmpgt +5829 -> 7589
    //   1763: aload_0
    //   1764: bipush 46
    //   1766: new 24	java/lang/String
    //   1769: dup
    //   1770: aload 231
    //   1772: invokespecial 34	java/lang/String:<init>	([C)V
    //   1775: invokevirtual 38	java/lang/String:intern	()Ljava/lang/String;
    //   1778: aastore
    //   1779: ldc 132
    //   1781: invokevirtual 30	java/lang/String:toCharArray	()[C
    //   1784: astore 236
    //   1786: aload 236
    //   1788: arraylength
    //   1789: istore 237
    //   1791: iconst_0
    //   1792: istore 238
    //   1794: iload 237
    //   1796: iload 238
    //   1798: if_icmpgt +5883 -> 7681
    //   1801: aload_0
    //   1802: bipush 47
    //   1804: new 24	java/lang/String
    //   1807: dup
    //   1808: aload 236
    //   1810: invokespecial 34	java/lang/String:<init>	([C)V
    //   1813: invokevirtual 38	java/lang/String:intern	()Ljava/lang/String;
    //   1816: aastore
    //   1817: ldc 134
    //   1819: invokevirtual 30	java/lang/String:toCharArray	()[C
    //   1822: astore 241
    //   1824: aload 241
    //   1826: arraylength
    //   1827: istore 242
    //   1829: iconst_0
    //   1830: istore 243
    //   1832: iload 242
    //   1834: iload 243
    //   1836: if_icmpgt +5937 -> 7773
    //   1839: aload_0
    //   1840: bipush 48
    //   1842: new 24	java/lang/String
    //   1845: dup
    //   1846: aload 241
    //   1848: invokespecial 34	java/lang/String:<init>	([C)V
    //   1851: invokevirtual 38	java/lang/String:intern	()Ljava/lang/String;
    //   1854: aastore
    //   1855: ldc 136
    //   1857: invokevirtual 30	java/lang/String:toCharArray	()[C
    //   1860: astore 246
    //   1862: aload 246
    //   1864: arraylength
    //   1865: istore 247
    //   1867: iconst_0
    //   1868: istore 248
    //   1870: iload 247
    //   1872: iload 248
    //   1874: if_icmpgt +5991 -> 7865
    //   1877: aload_0
    //   1878: bipush 49
    //   1880: new 24	java/lang/String
    //   1883: dup
    //   1884: aload 246
    //   1886: invokespecial 34	java/lang/String:<init>	([C)V
    //   1889: invokevirtual 38	java/lang/String:intern	()Ljava/lang/String;
    //   1892: aastore
    //   1893: ldc 138
    //   1895: invokevirtual 30	java/lang/String:toCharArray	()[C
    //   1898: astore 251
    //   1900: aload 251
    //   1902: arraylength
    //   1903: istore 252
    //   1905: iconst_0
    //   1906: istore 253
    //   1908: iload 252
    //   1910: iload 253
    //   1912: if_icmpgt +6045 -> 7957
    //   1915: aload_0
    //   1916: bipush 50
    //   1918: new 24	java/lang/String
    //   1921: dup
    //   1922: aload 251
    //   1924: invokespecial 34	java/lang/String:<init>	([C)V
    //   1927: invokevirtual 38	java/lang/String:intern	()Ljava/lang/String;
    //   1930: aastore
    //   1931: ldc 140
    //   1933: invokevirtual 30	java/lang/String:toCharArray	()[C
    //   1936: wide
    //   1940: wide
    //   1944: arraylength
    //   1945: wide
    //   1949: iconst_0
    //   1950: wide
    //   1954: wide
    //   1958: wide
    //   1962: if_icmpgt +6087 -> 8049
    //   1965: aload_0
    //   1966: bipush 51
    //   1968: new 24	java/lang/String
    //   1971: dup
    //   1972: wide
    //   1976: invokespecial 34	java/lang/String:<init>	([C)V
    //   1979: invokevirtual 38	java/lang/String:intern	()Ljava/lang/String;
    //   1982: aastore
    //   1983: ldc 142
    //   1985: invokevirtual 30	java/lang/String:toCharArray	()[C
    //   1988: wide
    //   1992: wide
    //   1996: arraylength
    //   1997: wide
    //   2001: iconst_0
    //   2002: wide
    //   2006: wide
    //   2010: wide
    //   2014: if_icmpgt +6156 -> 8170
    //   2017: aload_0
    //   2018: bipush 52
    //   2020: new 24	java/lang/String
    //   2023: dup
    //   2024: wide
    //   2028: invokespecial 34	java/lang/String:<init>	([C)V
    //   2031: invokevirtual 38	java/lang/String:intern	()Ljava/lang/String;
    //   2034: aastore
    //   2035: ldc 144
    //   2037: invokevirtual 30	java/lang/String:toCharArray	()[C
    //   2040: wide
    //   2044: wide
    //   2048: arraylength
    //   2049: wide
    //   2053: iconst_0
    //   2054: wide
    //   2058: wide
    //   2062: wide
    //   2066: if_icmpgt +6224 -> 8290
    //   2069: aload_0
    //   2070: bipush 53
    //   2072: new 24	java/lang/String
    //   2075: dup
    //   2076: wide
    //   2080: invokespecial 34	java/lang/String:<init>	([C)V
    //   2083: invokevirtual 38	java/lang/String:intern	()Ljava/lang/String;
    //   2086: aastore
    //   2087: ldc 146
    //   2089: invokevirtual 30	java/lang/String:toCharArray	()[C
    //   2092: wide
    //   2096: wide
    //   2100: arraylength
    //   2101: wide
    //   2105: iconst_0
    //   2106: wide
    //   2110: wide
    //   2114: wide
    //   2118: if_icmpgt +6292 -> 8410
    //   2121: aload_0
    //   2122: bipush 54
    //   2124: new 24	java/lang/String
    //   2127: dup
    //   2128: wide
    //   2132: invokespecial 34	java/lang/String:<init>	([C)V
    //   2135: invokevirtual 38	java/lang/String:intern	()Ljava/lang/String;
    //   2138: aastore
    //   2139: ldc 148
    //   2141: invokevirtual 30	java/lang/String:toCharArray	()[C
    //   2144: wide
    //   2148: wide
    //   2152: arraylength
    //   2153: wide
    //   2157: iconst_0
    //   2158: wide
    //   2162: wide
    //   2166: wide
    //   2170: if_icmpgt +6360 -> 8530
    //   2173: aload_0
    //   2174: bipush 55
    //   2176: new 24	java/lang/String
    //   2179: dup
    //   2180: wide
    //   2184: invokespecial 34	java/lang/String:<init>	([C)V
    //   2187: invokevirtual 38	java/lang/String:intern	()Ljava/lang/String;
    //   2190: aastore
    //   2191: ldc 150
    //   2193: invokevirtual 30	java/lang/String:toCharArray	()[C
    //   2196: wide
    //   2200: wide
    //   2204: arraylength
    //   2205: wide
    //   2209: iconst_0
    //   2210: wide
    //   2214: wide
    //   2218: wide
    //   2222: if_icmpgt +6428 -> 8650
    //   2225: aload_0
    //   2226: bipush 56
    //   2228: new 24	java/lang/String
    //   2231: dup
    //   2232: wide
    //   2236: invokespecial 34	java/lang/String:<init>	([C)V
    //   2239: invokevirtual 38	java/lang/String:intern	()Ljava/lang/String;
    //   2242: aastore
    //   2243: ldc 152
    //   2245: invokevirtual 30	java/lang/String:toCharArray	()[C
    //   2248: wide
    //   2252: wide
    //   2256: arraylength
    //   2257: wide
    //   2261: iconst_0
    //   2262: wide
    //   2266: wide
    //   2270: wide
    //   2274: if_icmpgt +6496 -> 8770
    //   2277: aload_0
    //   2278: bipush 57
    //   2280: new 24	java/lang/String
    //   2283: dup
    //   2284: wide
    //   2288: invokespecial 34	java/lang/String:<init>	([C)V
    //   2291: invokevirtual 38	java/lang/String:intern	()Ljava/lang/String;
    //   2294: aastore
    //   2295: ldc 154
    //   2297: invokevirtual 30	java/lang/String:toCharArray	()[C
    //   2300: wide
    //   2304: wide
    //   2308: arraylength
    //   2309: wide
    //   2313: iconst_0
    //   2314: wide
    //   2318: wide
    //   2322: wide
    //   2326: if_icmpgt +6564 -> 8890
    //   2329: aload_0
    //   2330: bipush 58
    //   2332: new 24	java/lang/String
    //   2335: dup
    //   2336: wide
    //   2340: invokespecial 34	java/lang/String:<init>	([C)V
    //   2343: invokevirtual 38	java/lang/String:intern	()Ljava/lang/String;
    //   2346: aastore
    //   2347: ldc 156
    //   2349: invokevirtual 30	java/lang/String:toCharArray	()[C
    //   2352: wide
    //   2356: wide
    //   2360: arraylength
    //   2361: wide
    //   2365: iconst_0
    //   2366: wide
    //   2370: wide
    //   2374: wide
    //   2378: if_icmpgt +6632 -> 9010
    //   2381: aload_0
    //   2382: bipush 59
    //   2384: new 24	java/lang/String
    //   2387: dup
    //   2388: wide
    //   2392: invokespecial 34	java/lang/String:<init>	([C)V
    //   2395: invokevirtual 38	java/lang/String:intern	()Ljava/lang/String;
    //   2398: aastore
    //   2399: ldc 158
    //   2401: invokevirtual 30	java/lang/String:toCharArray	()[C
    //   2404: wide
    //   2408: wide
    //   2412: arraylength
    //   2413: wide
    //   2417: iconst_0
    //   2418: wide
    //   2422: wide
    //   2426: wide
    //   2430: if_icmpgt +6700 -> 9130
    //   2433: aload_0
    //   2434: bipush 60
    //   2436: new 24	java/lang/String
    //   2439: dup
    //   2440: wide
    //   2444: invokespecial 34	java/lang/String:<init>	([C)V
    //   2447: invokevirtual 38	java/lang/String:intern	()Ljava/lang/String;
    //   2450: aastore
    //   2451: ldc 160
    //   2453: invokevirtual 30	java/lang/String:toCharArray	()[C
    //   2456: wide
    //   2460: wide
    //   2464: arraylength
    //   2465: wide
    //   2469: iconst_0
    //   2470: wide
    //   2474: wide
    //   2478: wide
    //   2482: if_icmpgt +6768 -> 9250
    //   2485: aload_0
    //   2486: bipush 61
    //   2488: new 24	java/lang/String
    //   2491: dup
    //   2492: wide
    //   2496: invokespecial 34	java/lang/String:<init>	([C)V
    //   2499: invokevirtual 38	java/lang/String:intern	()Ljava/lang/String;
    //   2502: aastore
    //   2503: ldc 162
    //   2505: invokevirtual 30	java/lang/String:toCharArray	()[C
    //   2508: wide
    //   2512: wide
    //   2516: arraylength
    //   2517: wide
    //   2521: iconst_0
    //   2522: wide
    //   2526: wide
    //   2530: wide
    //   2534: if_icmpgt +6836 -> 9370
    //   2537: aload_0
    //   2538: bipush 62
    //   2540: new 24	java/lang/String
    //   2543: dup
    //   2544: wide
    //   2548: invokespecial 34	java/lang/String:<init>	([C)V
    //   2551: invokevirtual 38	java/lang/String:intern	()Ljava/lang/String;
    //   2554: aastore
    //   2555: ldc 164
    //   2557: invokevirtual 30	java/lang/String:toCharArray	()[C
    //   2560: wide
    //   2564: wide
    //   2568: arraylength
    //   2569: wide
    //   2573: iconst_0
    //   2574: wide
    //   2578: wide
    //   2582: wide
    //   2586: if_icmpgt +6904 -> 9490
    //   2589: aload_0
    //   2590: bipush 63
    //   2592: new 24	java/lang/String
    //   2595: dup
    //   2596: wide
    //   2600: invokespecial 34	java/lang/String:<init>	([C)V
    //   2603: invokevirtual 38	java/lang/String:intern	()Ljava/lang/String;
    //   2606: aastore
    //   2607: ldc 166
    //   2609: invokevirtual 30	java/lang/String:toCharArray	()[C
    //   2612: wide
    //   2616: wide
    //   2620: arraylength
    //   2621: wide
    //   2625: iconst_0
    //   2626: wide
    //   2630: wide
    //   2634: wide
    //   2638: if_icmpgt +6972 -> 9610
    //   2641: aload_0
    //   2642: bipush 64
    //   2644: new 24	java/lang/String
    //   2647: dup
    //   2648: wide
    //   2652: invokespecial 34	java/lang/String:<init>	([C)V
    //   2655: invokevirtual 38	java/lang/String:intern	()Ljava/lang/String;
    //   2658: aastore
    //   2659: ldc 168
    //   2661: invokevirtual 30	java/lang/String:toCharArray	()[C
    //   2664: wide
    //   2668: wide
    //   2672: arraylength
    //   2673: wide
    //   2677: iconst_0
    //   2678: wide
    //   2682: wide
    //   2686: wide
    //   2690: if_icmpgt +7040 -> 9730
    //   2693: aload_0
    //   2694: bipush 65
    //   2696: new 24	java/lang/String
    //   2699: dup
    //   2700: wide
    //   2704: invokespecial 34	java/lang/String:<init>	([C)V
    //   2707: invokevirtual 38	java/lang/String:intern	()Ljava/lang/String;
    //   2710: aastore
    //   2711: ldc 170
    //   2713: invokevirtual 30	java/lang/String:toCharArray	()[C
    //   2716: wide
    //   2720: wide
    //   2724: arraylength
    //   2725: wide
    //   2729: iconst_0
    //   2730: wide
    //   2734: wide
    //   2738: wide
    //   2742: if_icmpgt +7108 -> 9850
    //   2745: aload_0
    //   2746: bipush 66
    //   2748: new 24	java/lang/String
    //   2751: dup
    //   2752: wide
    //   2756: invokespecial 34	java/lang/String:<init>	([C)V
    //   2759: invokevirtual 38	java/lang/String:intern	()Ljava/lang/String;
    //   2762: aastore
    //   2763: ldc 172
    //   2765: invokevirtual 30	java/lang/String:toCharArray	()[C
    //   2768: wide
    //   2772: wide
    //   2776: arraylength
    //   2777: wide
    //   2781: iconst_0
    //   2782: wide
    //   2786: wide
    //   2790: wide
    //   2794: if_icmpgt +7176 -> 9970
    //   2797: aload_0
    //   2798: bipush 67
    //   2800: new 24	java/lang/String
    //   2803: dup
    //   2804: wide
    //   2808: invokespecial 34	java/lang/String:<init>	([C)V
    //   2811: invokevirtual 38	java/lang/String:intern	()Ljava/lang/String;
    //   2814: aastore
    //   2815: ldc 174
    //   2817: invokevirtual 30	java/lang/String:toCharArray	()[C
    //   2820: wide
    //   2824: wide
    //   2828: arraylength
    //   2829: wide
    //   2833: iconst_0
    //   2834: wide
    //   2838: wide
    //   2842: wide
    //   2846: if_icmpgt +7244 -> 10090
    //   2849: aload_0
    //   2850: bipush 68
    //   2852: new 24	java/lang/String
    //   2855: dup
    //   2856: wide
    //   2860: invokespecial 34	java/lang/String:<init>	([C)V
    //   2863: invokevirtual 38	java/lang/String:intern	()Ljava/lang/String;
    //   2866: aastore
    //   2867: ldc 176
    //   2869: invokevirtual 30	java/lang/String:toCharArray	()[C
    //   2872: wide
    //   2876: wide
    //   2880: arraylength
    //   2881: wide
    //   2885: iconst_0
    //   2886: wide
    //   2890: wide
    //   2894: wide
    //   2898: if_icmpgt +7312 -> 10210
    //   2901: aload_0
    //   2902: bipush 69
    //   2904: new 24	java/lang/String
    //   2907: dup
    //   2908: wide
    //   2912: invokespecial 34	java/lang/String:<init>	([C)V
    //   2915: invokevirtual 38	java/lang/String:intern	()Ljava/lang/String;
    //   2918: aastore
    //   2919: ldc 178
    //   2921: invokevirtual 30	java/lang/String:toCharArray	()[C
    //   2924: wide
    //   2928: wide
    //   2932: arraylength
    //   2933: wide
    //   2937: iconst_0
    //   2938: wide
    //   2942: wide
    //   2946: wide
    //   2950: if_icmpgt +7380 -> 10330
    //   2953: aload_0
    //   2954: bipush 70
    //   2956: new 24	java/lang/String
    //   2959: dup
    //   2960: wide
    //   2964: invokespecial 34	java/lang/String:<init>	([C)V
    //   2967: invokevirtual 38	java/lang/String:intern	()Ljava/lang/String;
    //   2970: aastore
    //   2971: ldc 180
    //   2973: invokevirtual 30	java/lang/String:toCharArray	()[C
    //   2976: wide
    //   2980: wide
    //   2984: arraylength
    //   2985: wide
    //   2989: iconst_0
    //   2990: wide
    //   2994: wide
    //   2998: wide
    //   3002: if_icmpgt +7448 -> 10450
    //   3005: aload_0
    //   3006: bipush 71
    //   3008: new 24	java/lang/String
    //   3011: dup
    //   3012: wide
    //   3016: invokespecial 34	java/lang/String:<init>	([C)V
    //   3019: invokevirtual 38	java/lang/String:intern	()Ljava/lang/String;
    //   3022: aastore
    //   3023: ldc 182
    //   3025: invokevirtual 30	java/lang/String:toCharArray	()[C
    //   3028: wide
    //   3032: wide
    //   3036: arraylength
    //   3037: wide
    //   3041: iconst_0
    //   3042: wide
    //   3046: wide
    //   3050: wide
    //   3054: if_icmpgt +7516 -> 10570
    //   3057: aload_0
    //   3058: bipush 72
    //   3060: new 24	java/lang/String
    //   3063: dup
    //   3064: wide
    //   3068: invokespecial 34	java/lang/String:<init>	([C)V
    //   3071: invokevirtual 38	java/lang/String:intern	()Ljava/lang/String;
    //   3074: aastore
    //   3075: ldc 184
    //   3077: invokevirtual 30	java/lang/String:toCharArray	()[C
    //   3080: wide
    //   3084: wide
    //   3088: arraylength
    //   3089: wide
    //   3093: iconst_0
    //   3094: wide
    //   3098: wide
    //   3102: wide
    //   3106: if_icmpgt +7584 -> 10690
    //   3109: aload_0
    //   3110: bipush 73
    //   3112: new 24	java/lang/String
    //   3115: dup
    //   3116: wide
    //   3120: invokespecial 34	java/lang/String:<init>	([C)V
    //   3123: invokevirtual 38	java/lang/String:intern	()Ljava/lang/String;
    //   3126: aastore
    //   3127: ldc 186
    //   3129: invokevirtual 30	java/lang/String:toCharArray	()[C
    //   3132: wide
    //   3136: wide
    //   3140: arraylength
    //   3141: wide
    //   3145: iconst_0
    //   3146: wide
    //   3150: wide
    //   3154: wide
    //   3158: if_icmpgt +7652 -> 10810
    //   3161: aload_0
    //   3162: bipush 74
    //   3164: new 24	java/lang/String
    //   3167: dup
    //   3168: wide
    //   3172: invokespecial 34	java/lang/String:<init>	([C)V
    //   3175: invokevirtual 38	java/lang/String:intern	()Ljava/lang/String;
    //   3178: aastore
    //   3179: ldc 188
    //   3181: invokevirtual 30	java/lang/String:toCharArray	()[C
    //   3184: wide
    //   3188: wide
    //   3192: arraylength
    //   3193: wide
    //   3197: iconst_0
    //   3198: wide
    //   3202: wide
    //   3206: wide
    //   3210: if_icmpgt +7720 -> 10930
    //   3213: aload_0
    //   3214: bipush 75
    //   3216: new 24	java/lang/String
    //   3219: dup
    //   3220: wide
    //   3224: invokespecial 34	java/lang/String:<init>	([C)V
    //   3227: invokevirtual 38	java/lang/String:intern	()Ljava/lang/String;
    //   3230: aastore
    //   3231: ldc 190
    //   3233: invokevirtual 30	java/lang/String:toCharArray	()[C
    //   3236: wide
    //   3240: wide
    //   3244: arraylength
    //   3245: wide
    //   3249: iconst_0
    //   3250: wide
    //   3254: wide
    //   3258: wide
    //   3262: if_icmpgt +7788 -> 11050
    //   3265: aload_0
    //   3266: bipush 76
    //   3268: new 24	java/lang/String
    //   3271: dup
    //   3272: wide
    //   3276: invokespecial 34	java/lang/String:<init>	([C)V
    //   3279: invokevirtual 38	java/lang/String:intern	()Ljava/lang/String;
    //   3282: aastore
    //   3283: ldc 192
    //   3285: invokevirtual 30	java/lang/String:toCharArray	()[C
    //   3288: wide
    //   3292: wide
    //   3296: arraylength
    //   3297: wide
    //   3301: iconst_0
    //   3302: wide
    //   3306: wide
    //   3310: wide
    //   3314: if_icmpgt +7856 -> 11170
    //   3317: aload_0
    //   3318: bipush 77
    //   3320: new 24	java/lang/String
    //   3323: dup
    //   3324: wide
    //   3328: invokespecial 34	java/lang/String:<init>	([C)V
    //   3331: invokevirtual 38	java/lang/String:intern	()Ljava/lang/String;
    //   3334: aastore
    //   3335: aload_0
    //   3336: putstatic 194	com/whatsapp/j5:z	[Ljava/lang/String;
    //   3339: iconst_0
    //   3340: putstatic 196	com/whatsapp/j5:e	I
    //   3343: iconst_0
    //   3344: putstatic 198	com/whatsapp/j5:h	I
    //   3347: new 200	android/graphics/BitmapFactory$Options
    //   3350: dup
    //   3351: invokespecial 202	android/graphics/BitmapFactory$Options:<init>	()V
    //   3354: putstatic 204	com/whatsapp/j5:i	Landroid/graphics/BitmapFactory$Options;
    //   3357: getstatic 204	com/whatsapp/j5:i	Landroid/graphics/BitmapFactory$Options;
    //   3360: iconst_1
    //   3361: putfield 208	android/graphics/BitmapFactory$Options:inDither	Z
    //   3364: return
    //   3365: aload_1
    //   3366: iload_3
    //   3367: caload
    //   3368: istore 4
    //   3370: iload_3
    //   3371: iconst_5
    //   3372: irem
    //   3373: tableswitch	default:+31 -> 3404, 0:+50->3423, 1:+57->3430, 2:+64->3437, 3:+71->3444
    //   3405: iand
    //   3406: istore 5
    //   3408: aload_1
    //   3409: iload_3
    //   3410: iload 5
    //   3412: iload 4
    //   3414: ixor
    //   3415: i2c
    //   3416: castore
    //   3417: iinc 3 1
    //   3420: goto -3403 -> 17
    //   3423: bipush 6
    //   3425: istore 5
    //   3427: goto -19 -> 3408
    //   3430: bipush 39
    //   3432: istore 5
    //   3434: goto -26 -> 3408
    //   3437: bipush 115
    //   3439: istore 5
    //   3441: goto -33 -> 3408
    //   3444: bipush 69
    //   3446: istore 5
    //   3448: goto -40 -> 3408
    //   3451: aload 6
    //   3453: iload 8
    //   3455: caload
    //   3456: istore 9
    //   3458: iload 8
    //   3460: iconst_5
    //   3461: irem
    //   3462: tableswitch	default:+30 -> 3492, 0:+51->3513, 1:+58->3520, 2:+65->3527, 3:+72->3534
    //   3493: iand
    //   3494: istore 10
    //   3496: aload 6
    //   3498: iload 8
    //   3500: iload 10
    //   3502: iload 9
    //   3504: ixor
    //   3505: i2c
    //   3506: castore
    //   3507: iinc 8 1
    //   3510: goto -3459 -> 51
    //   3513: bipush 6
    //   3515: istore 10
    //   3517: goto -21 -> 3496
    //   3520: bipush 39
    //   3522: istore 10
    //   3524: goto -28 -> 3496
    //   3527: bipush 115
    //   3529: istore 10
    //   3531: goto -35 -> 3496
    //   3534: bipush 69
    //   3536: istore 10
    //   3538: goto -42 -> 3496
    //   3541: aload 11
    //   3543: iload 13
    //   3545: caload
    //   3546: istore 14
    //   3548: iload 13
    //   3550: iconst_5
    //   3551: irem
    //   3552: tableswitch	default:+32 -> 3584, 0:+53->3605, 1:+60->3612, 2:+67->3619, 3:+74->3626
    //   3585: iand
    //   3586: istore 15
    //   3588: aload 11
    //   3590: iload 13
    //   3592: iload 15
    //   3594: iload 14
    //   3596: ixor
    //   3597: i2c
    //   3598: castore
    //   3599: iinc 13 1
    //   3602: goto -3514 -> 88
    //   3605: bipush 6
    //   3607: istore 15
    //   3609: goto -21 -> 3588
    //   3612: bipush 39
    //   3614: istore 15
    //   3616: goto -28 -> 3588
    //   3619: bipush 115
    //   3621: istore 15
    //   3623: goto -35 -> 3588
    //   3626: bipush 69
    //   3628: istore 15
    //   3630: goto -42 -> 3588
    //   3633: aload 16
    //   3635: iload 18
    //   3637: caload
    //   3638: istore 19
    //   3640: iload 18
    //   3642: iconst_5
    //   3643: irem
    //   3644: tableswitch	default:+32 -> 3676, 0:+53->3697, 1:+60->3704, 2:+67->3711, 3:+74->3718
    //   3677: iand
    //   3678: istore 20
    //   3680: aload 16
    //   3682: iload 18
    //   3684: iload 20
    //   3686: iload 19
    //   3688: ixor
    //   3689: i2c
    //   3690: castore
    //   3691: iinc 18 1
    //   3694: goto -3569 -> 125
    //   3697: bipush 6
    //   3699: istore 20
    //   3701: goto -21 -> 3680
    //   3704: bipush 39
    //   3706: istore 20
    //   3708: goto -28 -> 3680
    //   3711: bipush 115
    //   3713: istore 20
    //   3715: goto -35 -> 3680
    //   3718: bipush 69
    //   3720: istore 20
    //   3722: goto -42 -> 3680
    //   3725: aload 21
    //   3727: iload 23
    //   3729: caload
    //   3730: istore 24
    //   3732: iload 23
    //   3734: iconst_5
    //   3735: irem
    //   3736: tableswitch	default:+32 -> 3768, 0:+53->3789, 1:+60->3796, 2:+67->3803, 3:+74->3810
    //   3769: iand
    //   3770: istore 25
    //   3772: aload 21
    //   3774: iload 23
    //   3776: iload 25
    //   3778: iload 24
    //   3780: ixor
    //   3781: i2c
    //   3782: castore
    //   3783: iinc 23 1
    //   3786: goto -3624 -> 162
    //   3789: bipush 6
    //   3791: istore 25
    //   3793: goto -21 -> 3772
    //   3796: bipush 39
    //   3798: istore 25
    //   3800: goto -28 -> 3772
    //   3803: bipush 115
    //   3805: istore 25
    //   3807: goto -35 -> 3772
    //   3810: bipush 69
    //   3812: istore 25
    //   3814: goto -42 -> 3772
    //   3817: aload 26
    //   3819: iload 28
    //   3821: caload
    //   3822: istore 29
    //   3824: iload 28
    //   3826: iconst_5
    //   3827: irem
    //   3828: tableswitch	default:+32 -> 3860, 0:+53->3881, 1:+60->3888, 2:+67->3895, 3:+74->3902
    //   3861: iand
    //   3862: istore 30
    //   3864: aload 26
    //   3866: iload 28
    //   3868: iload 30
    //   3870: iload 29
    //   3872: ixor
    //   3873: i2c
    //   3874: castore
    //   3875: iinc 28 1
    //   3878: goto -3679 -> 199
    //   3881: bipush 6
    //   3883: istore 30
    //   3885: goto -21 -> 3864
    //   3888: bipush 39
    //   3890: istore 30
    //   3892: goto -28 -> 3864
    //   3895: bipush 115
    //   3897: istore 30
    //   3899: goto -35 -> 3864
    //   3902: bipush 69
    //   3904: istore 30
    //   3906: goto -42 -> 3864
    //   3909: aload 31
    //   3911: iload 33
    //   3913: caload
    //   3914: istore 34
    //   3916: iload 33
    //   3918: iconst_5
    //   3919: irem
    //   3920: tableswitch	default:+32 -> 3952, 0:+53->3973, 1:+60->3980, 2:+67->3987, 3:+74->3994
    //   3953: iand
    //   3954: istore 35
    //   3956: aload 31
    //   3958: iload 33
    //   3960: iload 35
    //   3962: iload 34
    //   3964: ixor
    //   3965: i2c
    //   3966: castore
    //   3967: iinc 33 1
    //   3970: goto -3734 -> 236
    //   3973: bipush 6
    //   3975: istore 35
    //   3977: goto -21 -> 3956
    //   3980: bipush 39
    //   3982: istore 35
    //   3984: goto -28 -> 3956
    //   3987: bipush 115
    //   3989: istore 35
    //   3991: goto -35 -> 3956
    //   3994: bipush 69
    //   3996: istore 35
    //   3998: goto -42 -> 3956
    //   4001: aload 36
    //   4003: iload 38
    //   4005: caload
    //   4006: istore 39
    //   4008: iload 38
    //   4010: iconst_5
    //   4011: irem
    //   4012: tableswitch	default:+32 -> 4044, 0:+53->4065, 1:+60->4072, 2:+67->4079, 3:+74->4086
    //   4045: iand
    //   4046: istore 40
    //   4048: aload 36
    //   4050: iload 38
    //   4052: iload 40
    //   4054: iload 39
    //   4056: ixor
    //   4057: i2c
    //   4058: castore
    //   4059: iinc 38 1
    //   4062: goto -3788 -> 274
    //   4065: bipush 6
    //   4067: istore 40
    //   4069: goto -21 -> 4048
    //   4072: bipush 39
    //   4074: istore 40
    //   4076: goto -28 -> 4048
    //   4079: bipush 115
    //   4081: istore 40
    //   4083: goto -35 -> 4048
    //   4086: bipush 69
    //   4088: istore 40
    //   4090: goto -42 -> 4048
    //   4093: aload 41
    //   4095: iload 43
    //   4097: caload
    //   4098: istore 44
    //   4100: iload 43
    //   4102: iconst_5
    //   4103: irem
    //   4104: tableswitch	default:+32 -> 4136, 0:+53->4157, 1:+60->4164, 2:+67->4171, 3:+74->4178
    //   4137: iand
    //   4138: istore 45
    //   4140: aload 41
    //   4142: iload 43
    //   4144: iload 45
    //   4146: iload 44
    //   4148: ixor
    //   4149: i2c
    //   4150: castore
    //   4151: iinc 43 1
    //   4154: goto -3842 -> 312
    //   4157: bipush 6
    //   4159: istore 45
    //   4161: goto -21 -> 4140
    //   4164: bipush 39
    //   4166: istore 45
    //   4168: goto -28 -> 4140
    //   4171: bipush 115
    //   4173: istore 45
    //   4175: goto -35 -> 4140
    //   4178: bipush 69
    //   4180: istore 45
    //   4182: goto -42 -> 4140
    //   4185: aload 46
    //   4187: iload 48
    //   4189: caload
    //   4190: istore 49
    //   4192: iload 48
    //   4194: iconst_5
    //   4195: irem
    //   4196: tableswitch	default:+32 -> 4228, 0:+53->4249, 1:+60->4256, 2:+67->4263, 3:+74->4270
    //   4229: iand
    //   4230: istore 50
    //   4232: aload 46
    //   4234: iload 48
    //   4236: iload 50
    //   4238: iload 49
    //   4240: ixor
    //   4241: i2c
    //   4242: castore
    //   4243: iinc 48 1
    //   4246: goto -3896 -> 350
    //   4249: bipush 6
    //   4251: istore 50
    //   4253: goto -21 -> 4232
    //   4256: bipush 39
    //   4258: istore 50
    //   4260: goto -28 -> 4232
    //   4263: bipush 115
    //   4265: istore 50
    //   4267: goto -35 -> 4232
    //   4270: bipush 69
    //   4272: istore 50
    //   4274: goto -42 -> 4232
    //   4277: aload 51
    //   4279: iload 53
    //   4281: caload
    //   4282: istore 54
    //   4284: iload 53
    //   4286: iconst_5
    //   4287: irem
    //   4288: tableswitch	default:+32 -> 4320, 0:+53->4341, 1:+60->4348, 2:+67->4355, 3:+74->4362
    //   4321: iand
    //   4322: istore 55
    //   4324: aload 51
    //   4326: iload 53
    //   4328: iload 55
    //   4330: iload 54
    //   4332: ixor
    //   4333: i2c
    //   4334: castore
    //   4335: iinc 53 1
    //   4338: goto -3950 -> 388
    //   4341: bipush 6
    //   4343: istore 55
    //   4345: goto -21 -> 4324
    //   4348: bipush 39
    //   4350: istore 55
    //   4352: goto -28 -> 4324
    //   4355: bipush 115
    //   4357: istore 55
    //   4359: goto -35 -> 4324
    //   4362: bipush 69
    //   4364: istore 55
    //   4366: goto -42 -> 4324
    //   4369: aload 56
    //   4371: iload 58
    //   4373: caload
    //   4374: istore 59
    //   4376: iload 58
    //   4378: iconst_5
    //   4379: irem
    //   4380: tableswitch	default:+32 -> 4412, 0:+53->4433, 1:+60->4440, 2:+67->4447, 3:+74->4454
    //   4413: iand
    //   4414: istore 60
    //   4416: aload 56
    //   4418: iload 58
    //   4420: iload 60
    //   4422: iload 59
    //   4424: ixor
    //   4425: i2c
    //   4426: castore
    //   4427: iinc 58 1
    //   4430: goto -4004 -> 426
    //   4433: bipush 6
    //   4435: istore 60
    //   4437: goto -21 -> 4416
    //   4440: bipush 39
    //   4442: istore 60
    //   4444: goto -28 -> 4416
    //   4447: bipush 115
    //   4449: istore 60
    //   4451: goto -35 -> 4416
    //   4454: bipush 69
    //   4456: istore 60
    //   4458: goto -42 -> 4416
    //   4461: aload 61
    //   4463: iload 63
    //   4465: caload
    //   4466: istore 64
    //   4468: iload 63
    //   4470: iconst_5
    //   4471: irem
    //   4472: tableswitch	default:+32 -> 4504, 0:+53->4525, 1:+60->4532, 2:+67->4539, 3:+74->4546
    //   4505: iand
    //   4506: istore 65
    //   4508: aload 61
    //   4510: iload 63
    //   4512: iload 65
    //   4514: iload 64
    //   4516: ixor
    //   4517: i2c
    //   4518: castore
    //   4519: iinc 63 1
    //   4522: goto -4058 -> 464
    //   4525: bipush 6
    //   4527: istore 65
    //   4529: goto -21 -> 4508
    //   4532: bipush 39
    //   4534: istore 65
    //   4536: goto -28 -> 4508
    //   4539: bipush 115
    //   4541: istore 65
    //   4543: goto -35 -> 4508
    //   4546: bipush 69
    //   4548: istore 65
    //   4550: goto -42 -> 4508
    //   4553: aload 66
    //   4555: iload 68
    //   4557: caload
    //   4558: istore 69
    //   4560: iload 68
    //   4562: iconst_5
    //   4563: irem
    //   4564: tableswitch	default:+32 -> 4596, 0:+53->4617, 1:+60->4624, 2:+67->4631, 3:+74->4638
    //   4597: iand
    //   4598: istore 70
    //   4600: aload 66
    //   4602: iload 68
    //   4604: iload 70
    //   4606: iload 69
    //   4608: ixor
    //   4609: i2c
    //   4610: castore
    //   4611: iinc 68 1
    //   4614: goto -4112 -> 502
    //   4617: bipush 6
    //   4619: istore 70
    //   4621: goto -21 -> 4600
    //   4624: bipush 39
    //   4626: istore 70
    //   4628: goto -28 -> 4600
    //   4631: bipush 115
    //   4633: istore 70
    //   4635: goto -35 -> 4600
    //   4638: bipush 69
    //   4640: istore 70
    //   4642: goto -42 -> 4600
    //   4645: aload 71
    //   4647: iload 73
    //   4649: caload
    //   4650: istore 74
    //   4652: iload 73
    //   4654: iconst_5
    //   4655: irem
    //   4656: tableswitch	default:+32 -> 4688, 0:+53->4709, 1:+60->4716, 2:+67->4723, 3:+74->4730
    //   4689: iand
    //   4690: istore 75
    //   4692: aload 71
    //   4694: iload 73
    //   4696: iload 75
    //   4698: iload 74
    //   4700: ixor
    //   4701: i2c
    //   4702: castore
    //   4703: iinc 73 1
    //   4706: goto -4166 -> 540
    //   4709: bipush 6
    //   4711: istore 75
    //   4713: goto -21 -> 4692
    //   4716: bipush 39
    //   4718: istore 75
    //   4720: goto -28 -> 4692
    //   4723: bipush 115
    //   4725: istore 75
    //   4727: goto -35 -> 4692
    //   4730: bipush 69
    //   4732: istore 75
    //   4734: goto -42 -> 4692
    //   4737: aload 76
    //   4739: iload 78
    //   4741: caload
    //   4742: istore 79
    //   4744: iload 78
    //   4746: iconst_5
    //   4747: irem
    //   4748: tableswitch	default:+32 -> 4780, 0:+53->4801, 1:+60->4808, 2:+67->4815, 3:+74->4822
    //   4781: iand
    //   4782: istore 80
    //   4784: aload 76
    //   4786: iload 78
    //   4788: iload 80
    //   4790: iload 79
    //   4792: ixor
    //   4793: i2c
    //   4794: castore
    //   4795: iinc 78 1
    //   4798: goto -4220 -> 578
    //   4801: bipush 6
    //   4803: istore 80
    //   4805: goto -21 -> 4784
    //   4808: bipush 39
    //   4810: istore 80
    //   4812: goto -28 -> 4784
    //   4815: bipush 115
    //   4817: istore 80
    //   4819: goto -35 -> 4784
    //   4822: bipush 69
    //   4824: istore 80
    //   4826: goto -42 -> 4784
    //   4829: aload 81
    //   4831: iload 83
    //   4833: caload
    //   4834: istore 84
    //   4836: iload 83
    //   4838: iconst_5
    //   4839: irem
    //   4840: tableswitch	default:+32 -> 4872, 0:+53->4893, 1:+60->4900, 2:+67->4907, 3:+74->4914
    //   4873: iand
    //   4874: istore 85
    //   4876: aload 81
    //   4878: iload 83
    //   4880: iload 85
    //   4882: iload 84
    //   4884: ixor
    //   4885: i2c
    //   4886: castore
    //   4887: iinc 83 1
    //   4890: goto -4274 -> 616
    //   4893: bipush 6
    //   4895: istore 85
    //   4897: goto -21 -> 4876
    //   4900: bipush 39
    //   4902: istore 85
    //   4904: goto -28 -> 4876
    //   4907: bipush 115
    //   4909: istore 85
    //   4911: goto -35 -> 4876
    //   4914: bipush 69
    //   4916: istore 85
    //   4918: goto -42 -> 4876
    //   4921: aload 86
    //   4923: iload 88
    //   4925: caload
    //   4926: istore 89
    //   4928: iload 88
    //   4930: iconst_5
    //   4931: irem
    //   4932: tableswitch	default:+32 -> 4964, 0:+53->4985, 1:+60->4992, 2:+67->4999, 3:+74->5006
    //   4965: iand
    //   4966: istore 90
    //   4968: aload 86
    //   4970: iload 88
    //   4972: iload 90
    //   4974: iload 89
    //   4976: ixor
    //   4977: i2c
    //   4978: castore
    //   4979: iinc 88 1
    //   4982: goto -4328 -> 654
    //   4985: bipush 6
    //   4987: istore 90
    //   4989: goto -21 -> 4968
    //   4992: bipush 39
    //   4994: istore 90
    //   4996: goto -28 -> 4968
    //   4999: bipush 115
    //   5001: istore 90
    //   5003: goto -35 -> 4968
    //   5006: bipush 69
    //   5008: istore 90
    //   5010: goto -42 -> 4968
    //   5013: aload 91
    //   5015: iload 93
    //   5017: caload
    //   5018: istore 94
    //   5020: iload 93
    //   5022: iconst_5
    //   5023: irem
    //   5024: tableswitch	default:+32 -> 5056, 0:+53->5077, 1:+60->5084, 2:+67->5091, 3:+74->5098
    //   5057: iand
    //   5058: istore 95
    //   5060: aload 91
    //   5062: iload 93
    //   5064: iload 95
    //   5066: iload 94
    //   5068: ixor
    //   5069: i2c
    //   5070: castore
    //   5071: iinc 93 1
    //   5074: goto -4382 -> 692
    //   5077: bipush 6
    //   5079: istore 95
    //   5081: goto -21 -> 5060
    //   5084: bipush 39
    //   5086: istore 95
    //   5088: goto -28 -> 5060
    //   5091: bipush 115
    //   5093: istore 95
    //   5095: goto -35 -> 5060
    //   5098: bipush 69
    //   5100: istore 95
    //   5102: goto -42 -> 5060
    //   5105: aload 96
    //   5107: iload 98
    //   5109: caload
    //   5110: istore 99
    //   5112: iload 98
    //   5114: iconst_5
    //   5115: irem
    //   5116: tableswitch	default:+32 -> 5148, 0:+53->5169, 1:+60->5176, 2:+67->5183, 3:+74->5190
    //   5149: iand
    //   5150: istore 100
    //   5152: aload 96
    //   5154: iload 98
    //   5156: iload 100
    //   5158: iload 99
    //   5160: ixor
    //   5161: i2c
    //   5162: castore
    //   5163: iinc 98 1
    //   5166: goto -4436 -> 730
    //   5169: bipush 6
    //   5171: istore 100
    //   5173: goto -21 -> 5152
    //   5176: bipush 39
    //   5178: istore 100
    //   5180: goto -28 -> 5152
    //   5183: bipush 115
    //   5185: istore 100
    //   5187: goto -35 -> 5152
    //   5190: bipush 69
    //   5192: istore 100
    //   5194: goto -42 -> 5152
    //   5197: aload 101
    //   5199: iload 103
    //   5201: caload
    //   5202: istore 104
    //   5204: iload 103
    //   5206: iconst_5
    //   5207: irem
    //   5208: tableswitch	default:+32 -> 5240, 0:+53->5261, 1:+60->5268, 2:+67->5275, 3:+74->5282
    //   5241: iand
    //   5242: istore 105
    //   5244: aload 101
    //   5246: iload 103
    //   5248: iload 105
    //   5250: iload 104
    //   5252: ixor
    //   5253: i2c
    //   5254: castore
    //   5255: iinc 103 1
    //   5258: goto -4490 -> 768
    //   5261: bipush 6
    //   5263: istore 105
    //   5265: goto -21 -> 5244
    //   5268: bipush 39
    //   5270: istore 105
    //   5272: goto -28 -> 5244
    //   5275: bipush 115
    //   5277: istore 105
    //   5279: goto -35 -> 5244
    //   5282: bipush 69
    //   5284: istore 105
    //   5286: goto -42 -> 5244
    //   5289: aload 106
    //   5291: iload 108
    //   5293: caload
    //   5294: istore 109
    //   5296: iload 108
    //   5298: iconst_5
    //   5299: irem
    //   5300: tableswitch	default:+32 -> 5332, 0:+53->5353, 1:+60->5360, 2:+67->5367, 3:+74->5374
    //   5333: iand
    //   5334: istore 110
    //   5336: aload 106
    //   5338: iload 108
    //   5340: iload 110
    //   5342: iload 109
    //   5344: ixor
    //   5345: i2c
    //   5346: castore
    //   5347: iinc 108 1
    //   5350: goto -4544 -> 806
    //   5353: bipush 6
    //   5355: istore 110
    //   5357: goto -21 -> 5336
    //   5360: bipush 39
    //   5362: istore 110
    //   5364: goto -28 -> 5336
    //   5367: bipush 115
    //   5369: istore 110
    //   5371: goto -35 -> 5336
    //   5374: bipush 69
    //   5376: istore 110
    //   5378: goto -42 -> 5336
    //   5381: aload 111
    //   5383: iload 113
    //   5385: caload
    //   5386: istore 114
    //   5388: iload 113
    //   5390: iconst_5
    //   5391: irem
    //   5392: tableswitch	default:+32 -> 5424, 0:+53->5445, 1:+60->5452, 2:+67->5459, 3:+74->5466
    //   5425: iand
    //   5426: istore 115
    //   5428: aload 111
    //   5430: iload 113
    //   5432: iload 115
    //   5434: iload 114
    //   5436: ixor
    //   5437: i2c
    //   5438: castore
    //   5439: iinc 113 1
    //   5442: goto -4598 -> 844
    //   5445: bipush 6
    //   5447: istore 115
    //   5449: goto -21 -> 5428
    //   5452: bipush 39
    //   5454: istore 115
    //   5456: goto -28 -> 5428
    //   5459: bipush 115
    //   5461: istore 115
    //   5463: goto -35 -> 5428
    //   5466: bipush 69
    //   5468: istore 115
    //   5470: goto -42 -> 5428
    //   5473: aload 116
    //   5475: iload 118
    //   5477: caload
    //   5478: istore 119
    //   5480: iload 118
    //   5482: iconst_5
    //   5483: irem
    //   5484: tableswitch	default:+32 -> 5516, 0:+53->5537, 1:+60->5544, 2:+67->5551, 3:+74->5558
    //   5517: iand
    //   5518: istore 120
    //   5520: aload 116
    //   5522: iload 118
    //   5524: iload 120
    //   5526: iload 119
    //   5528: ixor
    //   5529: i2c
    //   5530: castore
    //   5531: iinc 118 1
    //   5534: goto -4652 -> 882
    //   5537: bipush 6
    //   5539: istore 120
    //   5541: goto -21 -> 5520
    //   5544: bipush 39
    //   5546: istore 120
    //   5548: goto -28 -> 5520
    //   5551: bipush 115
    //   5553: istore 120
    //   5555: goto -35 -> 5520
    //   5558: bipush 69
    //   5560: istore 120
    //   5562: goto -42 -> 5520
    //   5565: aload 121
    //   5567: iload 123
    //   5569: caload
    //   5570: istore 124
    //   5572: iload 123
    //   5574: iconst_5
    //   5575: irem
    //   5576: tableswitch	default:+32 -> 5608, 0:+53->5629, 1:+60->5636, 2:+67->5643, 3:+74->5650
    //   5609: iand
    //   5610: istore 125
    //   5612: aload 121
    //   5614: iload 123
    //   5616: iload 125
    //   5618: iload 124
    //   5620: ixor
    //   5621: i2c
    //   5622: castore
    //   5623: iinc 123 1
    //   5626: goto -4706 -> 920
    //   5629: bipush 6
    //   5631: istore 125
    //   5633: goto -21 -> 5612
    //   5636: bipush 39
    //   5638: istore 125
    //   5640: goto -28 -> 5612
    //   5643: bipush 115
    //   5645: istore 125
    //   5647: goto -35 -> 5612
    //   5650: bipush 69
    //   5652: istore 125
    //   5654: goto -42 -> 5612
    //   5657: aload 126
    //   5659: iload 128
    //   5661: caload
    //   5662: istore 129
    //   5664: iload 128
    //   5666: iconst_5
    //   5667: irem
    //   5668: tableswitch	default:+32 -> 5700, 0:+53->5721, 1:+60->5728, 2:+67->5735, 3:+74->5742
    //   5701: iand
    //   5702: istore 130
    //   5704: aload 126
    //   5706: iload 128
    //   5708: iload 130
    //   5710: iload 129
    //   5712: ixor
    //   5713: i2c
    //   5714: castore
    //   5715: iinc 128 1
    //   5718: goto -4760 -> 958
    //   5721: bipush 6
    //   5723: istore 130
    //   5725: goto -21 -> 5704
    //   5728: bipush 39
    //   5730: istore 130
    //   5732: goto -28 -> 5704
    //   5735: bipush 115
    //   5737: istore 130
    //   5739: goto -35 -> 5704
    //   5742: bipush 69
    //   5744: istore 130
    //   5746: goto -42 -> 5704
    //   5749: aload 131
    //   5751: iload 133
    //   5753: caload
    //   5754: istore 134
    //   5756: iload 133
    //   5758: iconst_5
    //   5759: irem
    //   5760: tableswitch	default:+32 -> 5792, 0:+53->5813, 1:+60->5820, 2:+67->5827, 3:+74->5834
    //   5793: iand
    //   5794: istore 135
    //   5796: aload 131
    //   5798: iload 133
    //   5800: iload 135
    //   5802: iload 134
    //   5804: ixor
    //   5805: i2c
    //   5806: castore
    //   5807: iinc 133 1
    //   5810: goto -4814 -> 996
    //   5813: bipush 6
    //   5815: istore 135
    //   5817: goto -21 -> 5796
    //   5820: bipush 39
    //   5822: istore 135
    //   5824: goto -28 -> 5796
    //   5827: bipush 115
    //   5829: istore 135
    //   5831: goto -35 -> 5796
    //   5834: bipush 69
    //   5836: istore 135
    //   5838: goto -42 -> 5796
    //   5841: aload 136
    //   5843: iload 138
    //   5845: caload
    //   5846: istore 139
    //   5848: iload 138
    //   5850: iconst_5
    //   5851: irem
    //   5852: tableswitch	default:+32 -> 5884, 0:+53->5905, 1:+60->5912, 2:+67->5919, 3:+74->5926
    //   5885: iand
    //   5886: istore 140
    //   5888: aload 136
    //   5890: iload 138
    //   5892: iload 140
    //   5894: iload 139
    //   5896: ixor
    //   5897: i2c
    //   5898: castore
    //   5899: iinc 138 1
    //   5902: goto -4868 -> 1034
    //   5905: bipush 6
    //   5907: istore 140
    //   5909: goto -21 -> 5888
    //   5912: bipush 39
    //   5914: istore 140
    //   5916: goto -28 -> 5888
    //   5919: bipush 115
    //   5921: istore 140
    //   5923: goto -35 -> 5888
    //   5926: bipush 69
    //   5928: istore 140
    //   5930: goto -42 -> 5888
    //   5933: aload 141
    //   5935: iload 143
    //   5937: caload
    //   5938: istore 144
    //   5940: iload 143
    //   5942: iconst_5
    //   5943: irem
    //   5944: tableswitch	default:+32 -> 5976, 0:+53->5997, 1:+60->6004, 2:+67->6011, 3:+74->6018
    //   5977: iand
    //   5978: istore 145
    //   5980: aload 141
    //   5982: iload 143
    //   5984: iload 145
    //   5986: iload 144
    //   5988: ixor
    //   5989: i2c
    //   5990: castore
    //   5991: iinc 143 1
    //   5994: goto -4922 -> 1072
    //   5997: bipush 6
    //   5999: istore 145
    //   6001: goto -21 -> 5980
    //   6004: bipush 39
    //   6006: istore 145
    //   6008: goto -28 -> 5980
    //   6011: bipush 115
    //   6013: istore 145
    //   6015: goto -35 -> 5980
    //   6018: bipush 69
    //   6020: istore 145
    //   6022: goto -42 -> 5980
    //   6025: aload 146
    //   6027: iload 148
    //   6029: caload
    //   6030: istore 149
    //   6032: iload 148
    //   6034: iconst_5
    //   6035: irem
    //   6036: tableswitch	default:+32 -> 6068, 0:+53->6089, 1:+60->6096, 2:+67->6103, 3:+74->6110
    //   6069: iand
    //   6070: istore 150
    //   6072: aload 146
    //   6074: iload 148
    //   6076: iload 150
    //   6078: iload 149
    //   6080: ixor
    //   6081: i2c
    //   6082: castore
    //   6083: iinc 148 1
    //   6086: goto -4976 -> 1110
    //   6089: bipush 6
    //   6091: istore 150
    //   6093: goto -21 -> 6072
    //   6096: bipush 39
    //   6098: istore 150
    //   6100: goto -28 -> 6072
    //   6103: bipush 115
    //   6105: istore 150
    //   6107: goto -35 -> 6072
    //   6110: bipush 69
    //   6112: istore 150
    //   6114: goto -42 -> 6072
    //   6117: aload 151
    //   6119: iload 153
    //   6121: caload
    //   6122: istore 154
    //   6124: iload 153
    //   6126: iconst_5
    //   6127: irem
    //   6128: tableswitch	default:+32 -> 6160, 0:+53->6181, 1:+60->6188, 2:+67->6195, 3:+74->6202
    //   6161: iand
    //   6162: istore 155
    //   6164: aload 151
    //   6166: iload 153
    //   6168: iload 155
    //   6170: iload 154
    //   6172: ixor
    //   6173: i2c
    //   6174: castore
    //   6175: iinc 153 1
    //   6178: goto -5030 -> 1148
    //   6181: bipush 6
    //   6183: istore 155
    //   6185: goto -21 -> 6164
    //   6188: bipush 39
    //   6190: istore 155
    //   6192: goto -28 -> 6164
    //   6195: bipush 115
    //   6197: istore 155
    //   6199: goto -35 -> 6164
    //   6202: bipush 69
    //   6204: istore 155
    //   6206: goto -42 -> 6164
    //   6209: aload 156
    //   6211: iload 158
    //   6213: caload
    //   6214: istore 159
    //   6216: iload 158
    //   6218: iconst_5
    //   6219: irem
    //   6220: tableswitch	default:+32 -> 6252, 0:+53->6273, 1:+60->6280, 2:+67->6287, 3:+74->6294
    //   6253: iand
    //   6254: istore 160
    //   6256: aload 156
    //   6258: iload 158
    //   6260: iload 160
    //   6262: iload 159
    //   6264: ixor
    //   6265: i2c
    //   6266: castore
    //   6267: iinc 158 1
    //   6270: goto -5084 -> 1186
    //   6273: bipush 6
    //   6275: istore 160
    //   6277: goto -21 -> 6256
    //   6280: bipush 39
    //   6282: istore 160
    //   6284: goto -28 -> 6256
    //   6287: bipush 115
    //   6289: istore 160
    //   6291: goto -35 -> 6256
    //   6294: bipush 69
    //   6296: istore 160
    //   6298: goto -42 -> 6256
    //   6301: aload 161
    //   6303: iload 163
    //   6305: caload
    //   6306: istore 164
    //   6308: iload 163
    //   6310: iconst_5
    //   6311: irem
    //   6312: tableswitch	default:+32 -> 6344, 0:+53->6365, 1:+60->6372, 2:+67->6379, 3:+74->6386
    //   6345: iand
    //   6346: istore 165
    //   6348: aload 161
    //   6350: iload 163
    //   6352: iload 165
    //   6354: iload 164
    //   6356: ixor
    //   6357: i2c
    //   6358: castore
    //   6359: iinc 163 1
    //   6362: goto -5138 -> 1224
    //   6365: bipush 6
    //   6367: istore 165
    //   6369: goto -21 -> 6348
    //   6372: bipush 39
    //   6374: istore 165
    //   6376: goto -28 -> 6348
    //   6379: bipush 115
    //   6381: istore 165
    //   6383: goto -35 -> 6348
    //   6386: bipush 69
    //   6388: istore 165
    //   6390: goto -42 -> 6348
    //   6393: aload 166
    //   6395: iload 168
    //   6397: caload
    //   6398: istore 169
    //   6400: iload 168
    //   6402: iconst_5
    //   6403: irem
    //   6404: tableswitch	default:+32 -> 6436, 0:+53->6457, 1:+60->6464, 2:+67->6471, 3:+74->6478
    //   6437: iand
    //   6438: istore 170
    //   6440: aload 166
    //   6442: iload 168
    //   6444: iload 170
    //   6446: iload 169
    //   6448: ixor
    //   6449: i2c
    //   6450: castore
    //   6451: iinc 168 1
    //   6454: goto -5192 -> 1262
    //   6457: bipush 6
    //   6459: istore 170
    //   6461: goto -21 -> 6440
    //   6464: bipush 39
    //   6466: istore 170
    //   6468: goto -28 -> 6440
    //   6471: bipush 115
    //   6473: istore 170
    //   6475: goto -35 -> 6440
    //   6478: bipush 69
    //   6480: istore 170
    //   6482: goto -42 -> 6440
    //   6485: aload 171
    //   6487: iload 173
    //   6489: caload
    //   6490: istore 174
    //   6492: iload 173
    //   6494: iconst_5
    //   6495: irem
    //   6496: tableswitch	default:+32 -> 6528, 0:+53->6549, 1:+60->6556, 2:+67->6563, 3:+74->6570
    //   6529: iand
    //   6530: istore 175
    //   6532: aload 171
    //   6534: iload 173
    //   6536: iload 175
    //   6538: iload 174
    //   6540: ixor
    //   6541: i2c
    //   6542: castore
    //   6543: iinc 173 1
    //   6546: goto -5246 -> 1300
    //   6549: bipush 6
    //   6551: istore 175
    //   6553: goto -21 -> 6532
    //   6556: bipush 39
    //   6558: istore 175
    //   6560: goto -28 -> 6532
    //   6563: bipush 115
    //   6565: istore 175
    //   6567: goto -35 -> 6532
    //   6570: bipush 69
    //   6572: istore 175
    //   6574: goto -42 -> 6532
    //   6577: aload 176
    //   6579: iload 178
    //   6581: caload
    //   6582: istore 179
    //   6584: iload 178
    //   6586: iconst_5
    //   6587: irem
    //   6588: tableswitch	default:+32 -> 6620, 0:+53->6641, 1:+60->6648, 2:+67->6655, 3:+74->6662
    //   6621: iand
    //   6622: istore 180
    //   6624: aload 176
    //   6626: iload 178
    //   6628: iload 180
    //   6630: iload 179
    //   6632: ixor
    //   6633: i2c
    //   6634: castore
    //   6635: iinc 178 1
    //   6638: goto -5300 -> 1338
    //   6641: bipush 6
    //   6643: istore 180
    //   6645: goto -21 -> 6624
    //   6648: bipush 39
    //   6650: istore 180
    //   6652: goto -28 -> 6624
    //   6655: bipush 115
    //   6657: istore 180
    //   6659: goto -35 -> 6624
    //   6662: bipush 69
    //   6664: istore 180
    //   6666: goto -42 -> 6624
    //   6669: aload 181
    //   6671: iload 183
    //   6673: caload
    //   6674: istore 184
    //   6676: iload 183
    //   6678: iconst_5
    //   6679: irem
    //   6680: tableswitch	default:+32 -> 6712, 0:+53->6733, 1:+60->6740, 2:+67->6747, 3:+74->6754
    //   6713: iand
    //   6714: istore 185
    //   6716: aload 181
    //   6718: iload 183
    //   6720: iload 185
    //   6722: iload 184
    //   6724: ixor
    //   6725: i2c
    //   6726: castore
    //   6727: iinc 183 1
    //   6730: goto -5354 -> 1376
    //   6733: bipush 6
    //   6735: istore 185
    //   6737: goto -21 -> 6716
    //   6740: bipush 39
    //   6742: istore 185
    //   6744: goto -28 -> 6716
    //   6747: bipush 115
    //   6749: istore 185
    //   6751: goto -35 -> 6716
    //   6754: bipush 69
    //   6756: istore 185
    //   6758: goto -42 -> 6716
    //   6761: aload 186
    //   6763: iload 188
    //   6765: caload
    //   6766: istore 189
    //   6768: iload 188
    //   6770: iconst_5
    //   6771: irem
    //   6772: tableswitch	default:+32 -> 6804, 0:+53->6825, 1:+60->6832, 2:+67->6839, 3:+74->6846
    //   6805: iand
    //   6806: istore 190
    //   6808: aload 186
    //   6810: iload 188
    //   6812: iload 190
    //   6814: iload 189
    //   6816: ixor
    //   6817: i2c
    //   6818: castore
    //   6819: iinc 188 1
    //   6822: goto -5408 -> 1414
    //   6825: bipush 6
    //   6827: istore 190
    //   6829: goto -21 -> 6808
    //   6832: bipush 39
    //   6834: istore 190
    //   6836: goto -28 -> 6808
    //   6839: bipush 115
    //   6841: istore 190
    //   6843: goto -35 -> 6808
    //   6846: bipush 69
    //   6848: istore 190
    //   6850: goto -42 -> 6808
    //   6853: aload 191
    //   6855: iload 193
    //   6857: caload
    //   6858: istore 194
    //   6860: iload 193
    //   6862: iconst_5
    //   6863: irem
    //   6864: tableswitch	default:+32 -> 6896, 0:+53->6917, 1:+60->6924, 2:+67->6931, 3:+74->6938
    //   6897: iand
    //   6898: istore 195
    //   6900: aload 191
    //   6902: iload 193
    //   6904: iload 195
    //   6906: iload 194
    //   6908: ixor
    //   6909: i2c
    //   6910: castore
    //   6911: iinc 193 1
    //   6914: goto -5462 -> 1452
    //   6917: bipush 6
    //   6919: istore 195
    //   6921: goto -21 -> 6900
    //   6924: bipush 39
    //   6926: istore 195
    //   6928: goto -28 -> 6900
    //   6931: bipush 115
    //   6933: istore 195
    //   6935: goto -35 -> 6900
    //   6938: bipush 69
    //   6940: istore 195
    //   6942: goto -42 -> 6900
    //   6945: aload 196
    //   6947: iload 198
    //   6949: caload
    //   6950: istore 199
    //   6952: iload 198
    //   6954: iconst_5
    //   6955: irem
    //   6956: tableswitch	default:+32 -> 6988, 0:+53->7009, 1:+60->7016, 2:+67->7023, 3:+74->7030
    //   6989: iand
    //   6990: istore 200
    //   6992: aload 196
    //   6994: iload 198
    //   6996: iload 200
    //   6998: iload 199
    //   7000: ixor
    //   7001: i2c
    //   7002: castore
    //   7003: iinc 198 1
    //   7006: goto -5516 -> 1490
    //   7009: bipush 6
    //   7011: istore 200
    //   7013: goto -21 -> 6992
    //   7016: bipush 39
    //   7018: istore 200
    //   7020: goto -28 -> 6992
    //   7023: bipush 115
    //   7025: istore 200
    //   7027: goto -35 -> 6992
    //   7030: bipush 69
    //   7032: istore 200
    //   7034: goto -42 -> 6992
    //   7037: aload 201
    //   7039: iload 203
    //   7041: caload
    //   7042: istore 204
    //   7044: iload 203
    //   7046: iconst_5
    //   7047: irem
    //   7048: tableswitch	default:+32 -> 7080, 0:+53->7101, 1:+60->7108, 2:+67->7115, 3:+74->7122
    //   7081: iand
    //   7082: istore 205
    //   7084: aload 201
    //   7086: iload 203
    //   7088: iload 205
    //   7090: iload 204
    //   7092: ixor
    //   7093: i2c
    //   7094: castore
    //   7095: iinc 203 1
    //   7098: goto -5570 -> 1528
    //   7101: bipush 6
    //   7103: istore 205
    //   7105: goto -21 -> 7084
    //   7108: bipush 39
    //   7110: istore 205
    //   7112: goto -28 -> 7084
    //   7115: bipush 115
    //   7117: istore 205
    //   7119: goto -35 -> 7084
    //   7122: bipush 69
    //   7124: istore 205
    //   7126: goto -42 -> 7084
    //   7129: aload 206
    //   7131: iload 208
    //   7133: caload
    //   7134: istore 209
    //   7136: iload 208
    //   7138: iconst_5
    //   7139: irem
    //   7140: tableswitch	default:+32 -> 7172, 0:+53->7193, 1:+60->7200, 2:+67->7207, 3:+74->7214
    //   7173: iand
    //   7174: istore 210
    //   7176: aload 206
    //   7178: iload 208
    //   7180: iload 210
    //   7182: iload 209
    //   7184: ixor
    //   7185: i2c
    //   7186: castore
    //   7187: iinc 208 1
    //   7190: goto -5624 -> 1566
    //   7193: bipush 6
    //   7195: istore 210
    //   7197: goto -21 -> 7176
    //   7200: bipush 39
    //   7202: istore 210
    //   7204: goto -28 -> 7176
    //   7207: bipush 115
    //   7209: istore 210
    //   7211: goto -35 -> 7176
    //   7214: bipush 69
    //   7216: istore 210
    //   7218: goto -42 -> 7176
    //   7221: aload 211
    //   7223: iload 213
    //   7225: caload
    //   7226: istore 214
    //   7228: iload 213
    //   7230: iconst_5
    //   7231: irem
    //   7232: tableswitch	default:+32 -> 7264, 0:+53->7285, 1:+60->7292, 2:+67->7299, 3:+74->7306
    //   7265: iand
    //   7266: istore 215
    //   7268: aload 211
    //   7270: iload 213
    //   7272: iload 215
    //   7274: iload 214
    //   7276: ixor
    //   7277: i2c
    //   7278: castore
    //   7279: iinc 213 1
    //   7282: goto -5678 -> 1604
    //   7285: bipush 6
    //   7287: istore 215
    //   7289: goto -21 -> 7268
    //   7292: bipush 39
    //   7294: istore 215
    //   7296: goto -28 -> 7268
    //   7299: bipush 115
    //   7301: istore 215
    //   7303: goto -35 -> 7268
    //   7306: bipush 69
    //   7308: istore 215
    //   7310: goto -42 -> 7268
    //   7313: aload 216
    //   7315: iload 218
    //   7317: caload
    //   7318: istore 219
    //   7320: iload 218
    //   7322: iconst_5
    //   7323: irem
    //   7324: tableswitch	default:+32 -> 7356, 0:+53->7377, 1:+60->7384, 2:+67->7391, 3:+74->7398
    //   7357: iand
    //   7358: istore 220
    //   7360: aload 216
    //   7362: iload 218
    //   7364: iload 220
    //   7366: iload 219
    //   7368: ixor
    //   7369: i2c
    //   7370: castore
    //   7371: iinc 218 1
    //   7374: goto -5732 -> 1642
    //   7377: bipush 6
    //   7379: istore 220
    //   7381: goto -21 -> 7360
    //   7384: bipush 39
    //   7386: istore 220
    //   7388: goto -28 -> 7360
    //   7391: bipush 115
    //   7393: istore 220
    //   7395: goto -35 -> 7360
    //   7398: bipush 69
    //   7400: istore 220
    //   7402: goto -42 -> 7360
    //   7405: aload 221
    //   7407: iload 223
    //   7409: caload
    //   7410: istore 224
    //   7412: iload 223
    //   7414: iconst_5
    //   7415: irem
    //   7416: tableswitch	default:+32 -> 7448, 0:+53->7469, 1:+60->7476, 2:+67->7483, 3:+74->7490
    //   7449: iand
    //   7450: istore 225
    //   7452: aload 221
    //   7454: iload 223
    //   7456: iload 225
    //   7458: iload 224
    //   7460: ixor
    //   7461: i2c
    //   7462: castore
    //   7463: iinc 223 1
    //   7466: goto -5786 -> 1680
    //   7469: bipush 6
    //   7471: istore 225
    //   7473: goto -21 -> 7452
    //   7476: bipush 39
    //   7478: istore 225
    //   7480: goto -28 -> 7452
    //   7483: bipush 115
    //   7485: istore 225
    //   7487: goto -35 -> 7452
    //   7490: bipush 69
    //   7492: istore 225
    //   7494: goto -42 -> 7452
    //   7497: aload 226
    //   7499: iload 228
    //   7501: caload
    //   7502: istore 229
    //   7504: iload 228
    //   7506: iconst_5
    //   7507: irem
    //   7508: tableswitch	default:+32 -> 7540, 0:+53->7561, 1:+60->7568, 2:+67->7575, 3:+74->7582
    //   7541: iand
    //   7542: istore 230
    //   7544: aload 226
    //   7546: iload 228
    //   7548: iload 230
    //   7550: iload 229
    //   7552: ixor
    //   7553: i2c
    //   7554: castore
    //   7555: iinc 228 1
    //   7558: goto -5840 -> 1718
    //   7561: bipush 6
    //   7563: istore 230
    //   7565: goto -21 -> 7544
    //   7568: bipush 39
    //   7570: istore 230
    //   7572: goto -28 -> 7544
    //   7575: bipush 115
    //   7577: istore 230
    //   7579: goto -35 -> 7544
    //   7582: bipush 69
    //   7584: istore 230
    //   7586: goto -42 -> 7544
    //   7589: aload 231
    //   7591: iload 233
    //   7593: caload
    //   7594: istore 234
    //   7596: iload 233
    //   7598: iconst_5
    //   7599: irem
    //   7600: tableswitch	default:+32 -> 7632, 0:+53->7653, 1:+60->7660, 2:+67->7667, 3:+74->7674
    //   7633: iand
    //   7634: istore 235
    //   7636: aload 231
    //   7638: iload 233
    //   7640: iload 235
    //   7642: iload 234
    //   7644: ixor
    //   7645: i2c
    //   7646: castore
    //   7647: iinc 233 1
    //   7650: goto -5894 -> 1756
    //   7653: bipush 6
    //   7655: istore 235
    //   7657: goto -21 -> 7636
    //   7660: bipush 39
    //   7662: istore 235
    //   7664: goto -28 -> 7636
    //   7667: bipush 115
    //   7669: istore 235
    //   7671: goto -35 -> 7636
    //   7674: bipush 69
    //   7676: istore 235
    //   7678: goto -42 -> 7636
    //   7681: aload 236
    //   7683: iload 238
    //   7685: caload
    //   7686: istore 239
    //   7688: iload 238
    //   7690: iconst_5
    //   7691: irem
    //   7692: tableswitch	default:+32 -> 7724, 0:+53->7745, 1:+60->7752, 2:+67->7759, 3:+74->7766
    //   7725: iand
    //   7726: istore 240
    //   7728: aload 236
    //   7730: iload 238
    //   7732: iload 240
    //   7734: iload 239
    //   7736: ixor
    //   7737: i2c
    //   7738: castore
    //   7739: iinc 238 1
    //   7742: goto -5948 -> 1794
    //   7745: bipush 6
    //   7747: istore 240
    //   7749: goto -21 -> 7728
    //   7752: bipush 39
    //   7754: istore 240
    //   7756: goto -28 -> 7728
    //   7759: bipush 115
    //   7761: istore 240
    //   7763: goto -35 -> 7728
    //   7766: bipush 69
    //   7768: istore 240
    //   7770: goto -42 -> 7728
    //   7773: aload 241
    //   7775: iload 243
    //   7777: caload
    //   7778: istore 244
    //   7780: iload 243
    //   7782: iconst_5
    //   7783: irem
    //   7784: tableswitch	default:+32 -> 7816, 0:+53->7837, 1:+60->7844, 2:+67->7851, 3:+74->7858
    //   7817: iand
    //   7818: istore 245
    //   7820: aload 241
    //   7822: iload 243
    //   7824: iload 245
    //   7826: iload 244
    //   7828: ixor
    //   7829: i2c
    //   7830: castore
    //   7831: iinc 243 1
    //   7834: goto -6002 -> 1832
    //   7837: bipush 6
    //   7839: istore 245
    //   7841: goto -21 -> 7820
    //   7844: bipush 39
    //   7846: istore 245
    //   7848: goto -28 -> 7820
    //   7851: bipush 115
    //   7853: istore 245
    //   7855: goto -35 -> 7820
    //   7858: bipush 69
    //   7860: istore 245
    //   7862: goto -42 -> 7820
    //   7865: aload 246
    //   7867: iload 248
    //   7869: caload
    //   7870: istore 249
    //   7872: iload 248
    //   7874: iconst_5
    //   7875: irem
    //   7876: tableswitch	default:+32 -> 7908, 0:+53->7929, 1:+60->7936, 2:+67->7943, 3:+74->7950
    //   7909: iand
    //   7910: istore 250
    //   7912: aload 246
    //   7914: iload 248
    //   7916: iload 250
    //   7918: iload 249
    //   7920: ixor
    //   7921: i2c
    //   7922: castore
    //   7923: iinc 248 1
    //   7926: goto -6056 -> 1870
    //   7929: bipush 6
    //   7931: istore 250
    //   7933: goto -21 -> 7912
    //   7936: bipush 39
    //   7938: istore 250
    //   7940: goto -28 -> 7912
    //   7943: bipush 115
    //   7945: istore 250
    //   7947: goto -35 -> 7912
    //   7950: bipush 69
    //   7952: istore 250
    //   7954: goto -42 -> 7912
    //   7957: aload 251
    //   7959: iload 253
    //   7961: caload
    //   7962: istore 254
    //   7964: iload 253
    //   7966: iconst_5
    //   7967: irem
    //   7968: tableswitch	default:+32 -> 8000, 0:+53->8021, 1:+60->8028, 2:+67->8035, 3:+74->8042
    //   8001: iand
    //   8002: istore 255
    //   8004: aload 251
    //   8006: iload 253
    //   8008: iload 255
    //   8010: iload 254
    //   8012: ixor
    //   8013: i2c
    //   8014: castore
    //   8015: iinc 253 1
    //   8018: goto -6110 -> 1908
    //   8021: bipush 6
    //   8023: istore 255
    //   8025: goto -21 -> 8004
    //   8028: bipush 39
    //   8030: istore 255
    //   8032: goto -28 -> 8004
    //   8035: bipush 115
    //   8037: istore 255
    //   8039: goto -35 -> 8004
    //   8042: bipush 69
    //   8044: istore 255
    //   8046: goto -42 -> 8004
    //   8049: wide
    //   8053: wide
    //   8057: caload
    //   8058: wide
    //   8062: wide
    //   8066: iconst_5
    //   8067: irem
    //   8068: tableswitch	default:+32 -> 8100, 0:+66->8134, 1:+75->8143, 2:+84->8152, 3:+93->8161
    //   8101: iand
    //   8102: wide
    //   8106: wide
    //   8110: wide
    //   8114: wide
    //   8118: wide
    //   8122: ixor
    //   8123: i2c
    //   8124: castore
    //   8125: wide
    //   8131: goto -6177 -> 1954
    //   8134: bipush 6
    //   8136: wide
    //   8140: goto -34 -> 8106
    //   8143: bipush 39
    //   8145: wide
    //   8149: goto -43 -> 8106
    //   8152: bipush 115
    //   8154: wide
    //   8158: goto -52 -> 8106
    //   8161: bipush 69
    //   8163: wide
    //   8167: goto -61 -> 8106
    //   8170: wide
    //   8174: wide
    //   8178: caload
    //   8179: wide
    //   8183: wide
    //   8187: iconst_5
    //   8188: irem
    //   8189: tableswitch	default:+31 -> 8220, 0:+65->8254, 1:+74->8263, 2:+83->8272, 3:+92->8281
    //   8221: iand
    //   8222: wide
    //   8226: wide
    //   8230: wide
    //   8234: wide
    //   8238: wide
    //   8242: ixor
    //   8243: i2c
    //   8244: castore
    //   8245: wide
    //   8251: goto -6245 -> 2006
    //   8254: bipush 6
    //   8256: wide
    //   8260: goto -34 -> 8226
    //   8263: bipush 39
    //   8265: wide
    //   8269: goto -43 -> 8226
    //   8272: bipush 115
    //   8274: wide
    //   8278: goto -52 -> 8226
    //   8281: bipush 69
    //   8283: wide
    //   8287: goto -61 -> 8226
    //   8290: wide
    //   8294: wide
    //   8298: caload
    //   8299: wide
    //   8303: wide
    //   8307: iconst_5
    //   8308: irem
    //   8309: tableswitch	default:+31 -> 8340, 0:+65->8374, 1:+74->8383, 2:+83->8392, 3:+92->8401
    //   8341: iand
    //   8342: wide
    //   8346: wide
    //   8350: wide
    //   8354: wide
    //   8358: wide
    //   8362: ixor
    //   8363: i2c
    //   8364: castore
    //   8365: wide
    //   8371: goto -6313 -> 2058
    //   8374: bipush 6
    //   8376: wide
    //   8380: goto -34 -> 8346
    //   8383: bipush 39
    //   8385: wide
    //   8389: goto -43 -> 8346
    //   8392: bipush 115
    //   8394: wide
    //   8398: goto -52 -> 8346
    //   8401: bipush 69
    //   8403: wide
    //   8407: goto -61 -> 8346
    //   8410: wide
    //   8414: wide
    //   8418: caload
    //   8419: wide
    //   8423: wide
    //   8427: iconst_5
    //   8428: irem
    //   8429: tableswitch	default:+31 -> 8460, 0:+65->8494, 1:+74->8503, 2:+83->8512, 3:+92->8521
    //   8461: iand
    //   8462: wide
    //   8466: wide
    //   8470: wide
    //   8474: wide
    //   8478: wide
    //   8482: ixor
    //   8483: i2c
    //   8484: castore
    //   8485: wide
    //   8491: goto -6381 -> 2110
    //   8494: bipush 6
    //   8496: wide
    //   8500: goto -34 -> 8466
    //   8503: bipush 39
    //   8505: wide
    //   8509: goto -43 -> 8466
    //   8512: bipush 115
    //   8514: wide
    //   8518: goto -52 -> 8466
    //   8521: bipush 69
    //   8523: wide
    //   8527: goto -61 -> 8466
    //   8530: wide
    //   8534: wide
    //   8538: caload
    //   8539: wide
    //   8543: wide
    //   8547: iconst_5
    //   8548: irem
    //   8549: tableswitch	default:+31 -> 8580, 0:+65->8614, 1:+74->8623, 2:+83->8632, 3:+92->8641
    //   8581: iand
    //   8582: wide
    //   8586: wide
    //   8590: wide
    //   8594: wide
    //   8598: wide
    //   8602: ixor
    //   8603: i2c
    //   8604: castore
    //   8605: wide
    //   8611: goto -6449 -> 2162
    //   8614: bipush 6
    //   8616: wide
    //   8620: goto -34 -> 8586
    //   8623: bipush 39
    //   8625: wide
    //   8629: goto -43 -> 8586
    //   8632: bipush 115
    //   8634: wide
    //   8638: goto -52 -> 8586
    //   8641: bipush 69
    //   8643: wide
    //   8647: goto -61 -> 8586
    //   8650: wide
    //   8654: wide
    //   8658: caload
    //   8659: wide
    //   8663: wide
    //   8667: iconst_5
    //   8668: irem
    //   8669: tableswitch	default:+31 -> 8700, 0:+65->8734, 1:+74->8743, 2:+83->8752, 3:+92->8761
    //   8701: iand
    //   8702: wide
    //   8706: wide
    //   8710: wide
    //   8714: wide
    //   8718: wide
    //   8722: ixor
    //   8723: i2c
    //   8724: castore
    //   8725: wide
    //   8731: goto -6517 -> 2214
    //   8734: bipush 6
    //   8736: wide
    //   8740: goto -34 -> 8706
    //   8743: bipush 39
    //   8745: wide
    //   8749: goto -43 -> 8706
    //   8752: bipush 115
    //   8754: wide
    //   8758: goto -52 -> 8706
    //   8761: bipush 69
    //   8763: wide
    //   8767: goto -61 -> 8706
    //   8770: wide
    //   8774: wide
    //   8778: caload
    //   8779: wide
    //   8783: wide
    //   8787: iconst_5
    //   8788: irem
    //   8789: tableswitch	default:+31 -> 8820, 0:+65->8854, 1:+74->8863, 2:+83->8872, 3:+92->8881
    //   8821: iand
    //   8822: wide
    //   8826: wide
    //   8830: wide
    //   8834: wide
    //   8838: wide
    //   8842: ixor
    //   8843: i2c
    //   8844: castore
    //   8845: wide
    //   8851: goto -6585 -> 2266
    //   8854: bipush 6
    //   8856: wide
    //   8860: goto -34 -> 8826
    //   8863: bipush 39
    //   8865: wide
    //   8869: goto -43 -> 8826
    //   8872: bipush 115
    //   8874: wide
    //   8878: goto -52 -> 8826
    //   8881: bipush 69
    //   8883: wide
    //   8887: goto -61 -> 8826
    //   8890: wide
    //   8894: wide
    //   8898: caload
    //   8899: wide
    //   8903: wide
    //   8907: iconst_5
    //   8908: irem
    //   8909: tableswitch	default:+31 -> 8940, 0:+65->8974, 1:+74->8983, 2:+83->8992, 3:+92->9001
    //   8941: iand
    //   8942: wide
    //   8946: wide
    //   8950: wide
    //   8954: wide
    //   8958: wide
    //   8962: ixor
    //   8963: i2c
    //   8964: castore
    //   8965: wide
    //   8971: goto -6653 -> 2318
    //   8974: bipush 6
    //   8976: wide
    //   8980: goto -34 -> 8946
    //   8983: bipush 39
    //   8985: wide
    //   8989: goto -43 -> 8946
    //   8992: bipush 115
    //   8994: wide
    //   8998: goto -52 -> 8946
    //   9001: bipush 69
    //   9003: wide
    //   9007: goto -61 -> 8946
    //   9010: wide
    //   9014: wide
    //   9018: caload
    //   9019: wide
    //   9023: wide
    //   9027: iconst_5
    //   9028: irem
    //   9029: tableswitch	default:+31 -> 9060, 0:+65->9094, 1:+74->9103, 2:+83->9112, 3:+92->9121
    //   9061: iand
    //   9062: wide
    //   9066: wide
    //   9070: wide
    //   9074: wide
    //   9078: wide
    //   9082: ixor
    //   9083: i2c
    //   9084: castore
    //   9085: wide
    //   9091: goto -6721 -> 2370
    //   9094: bipush 6
    //   9096: wide
    //   9100: goto -34 -> 9066
    //   9103: bipush 39
    //   9105: wide
    //   9109: goto -43 -> 9066
    //   9112: bipush 115
    //   9114: wide
    //   9118: goto -52 -> 9066
    //   9121: bipush 69
    //   9123: wide
    //   9127: goto -61 -> 9066
    //   9130: wide
    //   9134: wide
    //   9138: caload
    //   9139: wide
    //   9143: wide
    //   9147: iconst_5
    //   9148: irem
    //   9149: tableswitch	default:+31 -> 9180, 0:+65->9214, 1:+74->9223, 2:+83->9232, 3:+92->9241
    //   9181: iand
    //   9182: wide
    //   9186: wide
    //   9190: wide
    //   9194: wide
    //   9198: wide
    //   9202: ixor
    //   9203: i2c
    //   9204: castore
    //   9205: wide
    //   9211: goto -6789 -> 2422
    //   9214: bipush 6
    //   9216: wide
    //   9220: goto -34 -> 9186
    //   9223: bipush 39
    //   9225: wide
    //   9229: goto -43 -> 9186
    //   9232: bipush 115
    //   9234: wide
    //   9238: goto -52 -> 9186
    //   9241: bipush 69
    //   9243: wide
    //   9247: goto -61 -> 9186
    //   9250: wide
    //   9254: wide
    //   9258: caload
    //   9259: wide
    //   9263: wide
    //   9267: iconst_5
    //   9268: irem
    //   9269: tableswitch	default:+31 -> 9300, 0:+65->9334, 1:+74->9343, 2:+83->9352, 3:+92->9361
    //   9301: iand
    //   9302: wide
    //   9306: wide
    //   9310: wide
    //   9314: wide
    //   9318: wide
    //   9322: ixor
    //   9323: i2c
    //   9324: castore
    //   9325: wide
    //   9331: goto -6857 -> 2474
    //   9334: bipush 6
    //   9336: wide
    //   9340: goto -34 -> 9306
    //   9343: bipush 39
    //   9345: wide
    //   9349: goto -43 -> 9306
    //   9352: bipush 115
    //   9354: wide
    //   9358: goto -52 -> 9306
    //   9361: bipush 69
    //   9363: wide
    //   9367: goto -61 -> 9306
    //   9370: wide
    //   9374: wide
    //   9378: caload
    //   9379: wide
    //   9383: wide
    //   9387: iconst_5
    //   9388: irem
    //   9389: tableswitch	default:+31 -> 9420, 0:+65->9454, 1:+74->9463, 2:+83->9472, 3:+92->9481
    //   9421: iand
    //   9422: wide
    //   9426: wide
    //   9430: wide
    //   9434: wide
    //   9438: wide
    //   9442: ixor
    //   9443: i2c
    //   9444: castore
    //   9445: wide
    //   9451: goto -6925 -> 2526
    //   9454: bipush 6
    //   9456: wide
    //   9460: goto -34 -> 9426
    //   9463: bipush 39
    //   9465: wide
    //   9469: goto -43 -> 9426
    //   9472: bipush 115
    //   9474: wide
    //   9478: goto -52 -> 9426
    //   9481: bipush 69
    //   9483: wide
    //   9487: goto -61 -> 9426
    //   9490: wide
    //   9494: wide
    //   9498: caload
    //   9499: wide
    //   9503: wide
    //   9507: iconst_5
    //   9508: irem
    //   9509: tableswitch	default:+31 -> 9540, 0:+65->9574, 1:+74->9583, 2:+83->9592, 3:+92->9601
    //   9541: iand
    //   9542: wide
    //   9546: wide
    //   9550: wide
    //   9554: wide
    //   9558: wide
    //   9562: ixor
    //   9563: i2c
    //   9564: castore
    //   9565: wide
    //   9571: goto -6993 -> 2578
    //   9574: bipush 6
    //   9576: wide
    //   9580: goto -34 -> 9546
    //   9583: bipush 39
    //   9585: wide
    //   9589: goto -43 -> 9546
    //   9592: bipush 115
    //   9594: wide
    //   9598: goto -52 -> 9546
    //   9601: bipush 69
    //   9603: wide
    //   9607: goto -61 -> 9546
    //   9610: wide
    //   9614: wide
    //   9618: caload
    //   9619: wide
    //   9623: wide
    //   9627: iconst_5
    //   9628: irem
    //   9629: tableswitch	default:+31 -> 9660, 0:+65->9694, 1:+74->9703, 2:+83->9712, 3:+92->9721
    //   9661: iand
    //   9662: wide
    //   9666: wide
    //   9670: wide
    //   9674: wide
    //   9678: wide
    //   9682: ixor
    //   9683: i2c
    //   9684: castore
    //   9685: wide
    //   9691: goto -7061 -> 2630
    //   9694: bipush 6
    //   9696: wide
    //   9700: goto -34 -> 9666
    //   9703: bipush 39
    //   9705: wide
    //   9709: goto -43 -> 9666
    //   9712: bipush 115
    //   9714: wide
    //   9718: goto -52 -> 9666
    //   9721: bipush 69
    //   9723: wide
    //   9727: goto -61 -> 9666
    //   9730: wide
    //   9734: wide
    //   9738: caload
    //   9739: wide
    //   9743: wide
    //   9747: iconst_5
    //   9748: irem
    //   9749: tableswitch	default:+31 -> 9780, 0:+65->9814, 1:+74->9823, 2:+83->9832, 3:+92->9841
    //   9781: iand
    //   9782: wide
    //   9786: wide
    //   9790: wide
    //   9794: wide
    //   9798: wide
    //   9802: ixor
    //   9803: i2c
    //   9804: castore
    //   9805: wide
    //   9811: goto -7129 -> 2682
    //   9814: bipush 6
    //   9816: wide
    //   9820: goto -34 -> 9786
    //   9823: bipush 39
    //   9825: wide
    //   9829: goto -43 -> 9786
    //   9832: bipush 115
    //   9834: wide
    //   9838: goto -52 -> 9786
    //   9841: bipush 69
    //   9843: wide
    //   9847: goto -61 -> 9786
    //   9850: wide
    //   9854: wide
    //   9858: caload
    //   9859: wide
    //   9863: wide
    //   9867: iconst_5
    //   9868: irem
    //   9869: tableswitch	default:+31 -> 9900, 0:+65->9934, 1:+74->9943, 2:+83->9952, 3:+92->9961
    //   9901: iand
    //   9902: wide
    //   9906: wide
    //   9910: wide
    //   9914: wide
    //   9918: wide
    //   9922: ixor
    //   9923: i2c
    //   9924: castore
    //   9925: wide
    //   9931: goto -7197 -> 2734
    //   9934: bipush 6
    //   9936: wide
    //   9940: goto -34 -> 9906
    //   9943: bipush 39
    //   9945: wide
    //   9949: goto -43 -> 9906
    //   9952: bipush 115
    //   9954: wide
    //   9958: goto -52 -> 9906
    //   9961: bipush 69
    //   9963: wide
    //   9967: goto -61 -> 9906
    //   9970: wide
    //   9974: wide
    //   9978: caload
    //   9979: wide
    //   9983: wide
    //   9987: iconst_5
    //   9988: irem
    //   9989: tableswitch	default:+31 -> 10020, 0:+65->10054, 1:+74->10063, 2:+83->10072, 3:+92->10081
    //   10021: iand
    //   10022: wide
    //   10026: wide
    //   10030: wide
    //   10034: wide
    //   10038: wide
    //   10042: ixor
    //   10043: i2c
    //   10044: castore
    //   10045: wide
    //   10051: goto -7265 -> 2786
    //   10054: bipush 6
    //   10056: wide
    //   10060: goto -34 -> 10026
    //   10063: bipush 39
    //   10065: wide
    //   10069: goto -43 -> 10026
    //   10072: bipush 115
    //   10074: wide
    //   10078: goto -52 -> 10026
    //   10081: bipush 69
    //   10083: wide
    //   10087: goto -61 -> 10026
    //   10090: wide
    //   10094: wide
    //   10098: caload
    //   10099: wide
    //   10103: wide
    //   10107: iconst_5
    //   10108: irem
    //   10109: tableswitch	default:+31 -> 10140, 0:+65->10174, 1:+74->10183, 2:+83->10192, 3:+92->10201
    //   10141: iand
    //   10142: wide
    //   10146: wide
    //   10150: wide
    //   10154: wide
    //   10158: wide
    //   10162: ixor
    //   10163: i2c
    //   10164: castore
    //   10165: wide
    //   10171: goto -7333 -> 2838
    //   10174: bipush 6
    //   10176: wide
    //   10180: goto -34 -> 10146
    //   10183: bipush 39
    //   10185: wide
    //   10189: goto -43 -> 10146
    //   10192: bipush 115
    //   10194: wide
    //   10198: goto -52 -> 10146
    //   10201: bipush 69
    //   10203: wide
    //   10207: goto -61 -> 10146
    //   10210: wide
    //   10214: wide
    //   10218: caload
    //   10219: wide
    //   10223: wide
    //   10227: iconst_5
    //   10228: irem
    //   10229: tableswitch	default:+31 -> 10260, 0:+65->10294, 1:+74->10303, 2:+83->10312, 3:+92->10321
    //   10261: iand
    //   10262: wide
    //   10266: wide
    //   10270: wide
    //   10274: wide
    //   10278: wide
    //   10282: ixor
    //   10283: i2c
    //   10284: castore
    //   10285: wide
    //   10291: goto -7401 -> 2890
    //   10294: bipush 6
    //   10296: wide
    //   10300: goto -34 -> 10266
    //   10303: bipush 39
    //   10305: wide
    //   10309: goto -43 -> 10266
    //   10312: bipush 115
    //   10314: wide
    //   10318: goto -52 -> 10266
    //   10321: bipush 69
    //   10323: wide
    //   10327: goto -61 -> 10266
    //   10330: wide
    //   10334: wide
    //   10338: caload
    //   10339: wide
    //   10343: wide
    //   10347: iconst_5
    //   10348: irem
    //   10349: tableswitch	default:+31 -> 10380, 0:+65->10414, 1:+74->10423, 2:+83->10432, 3:+92->10441
    //   10381: iand
    //   10382: wide
    //   10386: wide
    //   10390: wide
    //   10394: wide
    //   10398: wide
    //   10402: ixor
    //   10403: i2c
    //   10404: castore
    //   10405: wide
    //   10411: goto -7469 -> 2942
    //   10414: bipush 6
    //   10416: wide
    //   10420: goto -34 -> 10386
    //   10423: bipush 39
    //   10425: wide
    //   10429: goto -43 -> 10386
    //   10432: bipush 115
    //   10434: wide
    //   10438: goto -52 -> 10386
    //   10441: bipush 69
    //   10443: wide
    //   10447: goto -61 -> 10386
    //   10450: wide
    //   10454: wide
    //   10458: caload
    //   10459: wide
    //   10463: wide
    //   10467: iconst_5
    //   10468: irem
    //   10469: tableswitch	default:+31 -> 10500, 0:+65->10534, 1:+74->10543, 2:+83->10552, 3:+92->10561
    //   10501: iand
    //   10502: wide
    //   10506: wide
    //   10510: wide
    //   10514: wide
    //   10518: wide
    //   10522: ixor
    //   10523: i2c
    //   10524: castore
    //   10525: wide
    //   10531: goto -7537 -> 2994
    //   10534: bipush 6
    //   10536: wide
    //   10540: goto -34 -> 10506
    //   10543: bipush 39
    //   10545: wide
    //   10549: goto -43 -> 10506
    //   10552: bipush 115
    //   10554: wide
    //   10558: goto -52 -> 10506
    //   10561: bipush 69
    //   10563: wide
    //   10567: goto -61 -> 10506
    //   10570: wide
    //   10574: wide
    //   10578: caload
    //   10579: wide
    //   10583: wide
    //   10587: iconst_5
    //   10588: irem
    //   10589: tableswitch	default:+31 -> 10620, 0:+65->10654, 1:+74->10663, 2:+83->10672, 3:+92->10681
    //   10621: iand
    //   10622: wide
    //   10626: wide
    //   10630: wide
    //   10634: wide
    //   10638: wide
    //   10642: ixor
    //   10643: i2c
    //   10644: castore
    //   10645: wide
    //   10651: goto -7605 -> 3046
    //   10654: bipush 6
    //   10656: wide
    //   10660: goto -34 -> 10626
    //   10663: bipush 39
    //   10665: wide
    //   10669: goto -43 -> 10626
    //   10672: bipush 115
    //   10674: wide
    //   10678: goto -52 -> 10626
    //   10681: bipush 69
    //   10683: wide
    //   10687: goto -61 -> 10626
    //   10690: wide
    //   10694: wide
    //   10698: caload
    //   10699: wide
    //   10703: wide
    //   10707: iconst_5
    //   10708: irem
    //   10709: tableswitch	default:+31 -> 10740, 0:+65->10774, 1:+74->10783, 2:+83->10792, 3:+92->10801
    //   10741: iand
    //   10742: wide
    //   10746: wide
    //   10750: wide
    //   10754: wide
    //   10758: wide
    //   10762: ixor
    //   10763: i2c
    //   10764: castore
    //   10765: wide
    //   10771: goto -7673 -> 3098
    //   10774: bipush 6
    //   10776: wide
    //   10780: goto -34 -> 10746
    //   10783: bipush 39
    //   10785: wide
    //   10789: goto -43 -> 10746
    //   10792: bipush 115
    //   10794: wide
    //   10798: goto -52 -> 10746
    //   10801: bipush 69
    //   10803: wide
    //   10807: goto -61 -> 10746
    //   10810: wide
    //   10814: wide
    //   10818: caload
    //   10819: wide
    //   10823: wide
    //   10827: iconst_5
    //   10828: irem
    //   10829: tableswitch	default:+31 -> 10860, 0:+65->10894, 1:+74->10903, 2:+83->10912, 3:+92->10921
    //   10861: iand
    //   10862: wide
    //   10866: wide
    //   10870: wide
    //   10874: wide
    //   10878: wide
    //   10882: ixor
    //   10883: i2c
    //   10884: castore
    //   10885: wide
    //   10891: goto -7741 -> 3150
    //   10894: bipush 6
    //   10896: wide
    //   10900: goto -34 -> 10866
    //   10903: bipush 39
    //   10905: wide
    //   10909: goto -43 -> 10866
    //   10912: bipush 115
    //   10914: wide
    //   10918: goto -52 -> 10866
    //   10921: bipush 69
    //   10923: wide
    //   10927: goto -61 -> 10866
    //   10930: wide
    //   10934: wide
    //   10938: caload
    //   10939: wide
    //   10943: wide
    //   10947: iconst_5
    //   10948: irem
    //   10949: tableswitch	default:+31 -> 10980, 0:+65->11014, 1:+74->11023, 2:+83->11032, 3:+92->11041
    //   10981: iand
    //   10982: wide
    //   10986: wide
    //   10990: wide
    //   10994: wide
    //   10998: wide
    //   11002: ixor
    //   11003: i2c
    //   11004: castore
    //   11005: wide
    //   11011: goto -7809 -> 3202
    //   11014: bipush 6
    //   11016: wide
    //   11020: goto -34 -> 10986
    //   11023: bipush 39
    //   11025: wide
    //   11029: goto -43 -> 10986
    //   11032: bipush 115
    //   11034: wide
    //   11038: goto -52 -> 10986
    //   11041: bipush 69
    //   11043: wide
    //   11047: goto -61 -> 10986
    //   11050: wide
    //   11054: wide
    //   11058: caload
    //   11059: wide
    //   11063: wide
    //   11067: iconst_5
    //   11068: irem
    //   11069: tableswitch	default:+31 -> 11100, 0:+65->11134, 1:+74->11143, 2:+83->11152, 3:+92->11161
    //   11101: iand
    //   11102: wide
    //   11106: wide
    //   11110: wide
    //   11114: wide
    //   11118: wide
    //   11122: ixor
    //   11123: i2c
    //   11124: castore
    //   11125: wide
    //   11131: goto -7877 -> 3254
    //   11134: bipush 6
    //   11136: wide
    //   11140: goto -34 -> 11106
    //   11143: bipush 39
    //   11145: wide
    //   11149: goto -43 -> 11106
    //   11152: bipush 115
    //   11154: wide
    //   11158: goto -52 -> 11106
    //   11161: bipush 69
    //   11163: wide
    //   11167: goto -61 -> 11106
    //   11170: wide
    //   11174: wide
    //   11178: caload
    //   11179: wide
    //   11183: wide
    //   11187: iconst_5
    //   11188: irem
    //   11189: tableswitch	default:+31 -> 11220, 0:+65->11254, 1:+74->11263, 2:+83->11272, 3:+92->11281
    //   11221: iand
    //   11222: wide
    //   11226: wide
    //   11230: wide
    //   11234: wide
    //   11238: wide
    //   11242: ixor
    //   11243: i2c
    //   11244: castore
    //   11245: wide
    //   11251: goto -7945 -> 3306
    //   11254: bipush 6
    //   11256: wide
    //   11260: goto -34 -> 11226
    //   11263: bipush 39
    //   11265: wide
    //   11269: goto -43 -> 11226
    //   11272: bipush 115
    //   11274: wide
    //   11278: goto -52 -> 11226
    //   11281: bipush 69
    //   11283: wide
    //   11287: goto -61 -> 11226
  }

  public static int a(int paramInt, Activity paramActivity)
  {
    int j = 0;
    String[] arrayOfString = e(paramInt);
    Cursor localCursor1 = paramActivity.managedQuery(f(paramInt), arrayOfString, "", null, "");
    if (localCursor1 != null)
    {
      int k = 0 + localCursor1.getCount();
      g5.b(z[76] + localCursor1.getCount());
      j = k;
    }
    Cursor localCursor2 = paramActivity.managedQuery(g(paramInt), arrayOfString, "", null, "");
    if (localCursor2 != null)
    {
      j += localCursor2.getCount();
      g5.b(z[77] + localCursor2.getCount());
    }
    return j;
  }

  public static Intent a(int paramInt, List<Intent> paramList)
  {
    int j = g5.n;
    Intent localIntent1;
    switch (paramInt)
    {
    case 2:
    case 3:
    default:
      localIntent1 = null;
    case 1:
    case 4:
    }
    while (true)
    {
      Intent localIntent2 = Intent.createChooser(localIntent1, null);
      ArrayList localArrayList = new ArrayList(paramList.size());
      Iterator localIterator = paramList.iterator();
      do
      {
        if (!localIterator.hasNext())
          break;
        a.a((Intent)localIterator.next(), localArrayList);
      }
      while (j == 0);
      localIntent2.putExtra(z[38], (Parcelable[])localArrayList.toArray(new Intent[0]));
      return localIntent2;
      localIntent1 = new Intent(z[40], MediaStore.Images.Media.INTERNAL_CONTENT_URI);
      localIntent1.setType(z[37]);
      continue;
      localIntent1 = new Intent(z[40], MediaStore.Video.Media.INTERNAL_CONTENT_URI);
      localIntent1.setType(z[39]);
    }
  }

  public static Bitmap a(Bitmap paramBitmap)
  {
    double d1 = 1.0D;
    Bitmap localBitmap2;
    if (paramBitmap == null)
      localBitmap2 = null;
    while (true)
    {
      return localBitmap2;
      if ((paramBitmap.getWidth() > 100) || (paramBitmap.getHeight() > 100))
        d1 = Math.min(paramBitmap.getWidth() / 100.0D, paramBitmap.getHeight() / 100.0D);
      Bitmap localBitmap1 = Bitmap.createScaledBitmap(paramBitmap, (int)Math.ceil(paramBitmap.getWidth() / d1), (int)Math.ceil(paramBitmap.getHeight() / d1), true);
      paramBitmap.recycle();
      g5.b(z[48] + localBitmap1.getHeight() + " " + localBitmap1.getWidth());
      localBitmap2 = Bitmap.createBitmap(localBitmap1, 0, 0, 100, 100);
      localBitmap1.recycle();
    }
  }

  private static Bitmap a(Bitmap paramBitmap, int paramInt, float paramFloat)
  {
    if ((paramBitmap == null) || (paramBitmap.isRecycled()));
    Bitmap localBitmap;
    for (Object localObject = null; ; localObject = localBitmap)
    {
      return localObject;
      localBitmap = Bitmap.createBitmap(paramInt, paramInt, Bitmap.Config.ARGB_8888);
      Canvas localCanvas = new Canvas(localBitmap);
      Paint localPaint = new Paint();
      RectF localRectF = new RectF(0.0F, 0.0F, paramInt, paramInt);
      int j = (paramBitmap.getWidth() - paramBitmap.getHeight()) / 2;
      Rect localRect;
      if (j > 0)
      {
        localRect = new Rect(j, 0, paramBitmap.getWidth() - j, paramBitmap.getHeight());
        if (g5.n == 0);
      }
      else
      {
        localRect = new Rect(0, -j, paramBitmap.getWidth(), j + paramBitmap.getHeight());
      }
      localPaint.setAntiAlias(true);
      localPaint.setDither(true);
      localPaint.setFilterBitmap(true);
      localCanvas.drawARGB(0, 0, 0, 0);
      localPaint.setColor(-1);
      localCanvas.drawRoundRect(localRectF, paramFloat, paramFloat, localPaint);
      localPaint.setXfermode(new PorterDuffXfermode(PorterDuff.Mode.SRC_IN));
      localCanvas.drawBitmap(paramBitmap, localRect, localRectF, localPaint);
    }
  }

  // ERROR //
  public static Bitmap a(Uri paramUri, int paramInt)
  {
    // Byte code:
    //   0: aconst_null
    //   1: astore_2
    //   2: getstatic 429	com/whatsapp/App:ib	Landroid/content/ContentResolver;
    //   5: aload_0
    //   6: invokevirtual 435	android/content/ContentResolver:openInputStream	(Landroid/net/Uri;)Ljava/io/InputStream;
    //   9: astore 9
    //   11: aload 9
    //   13: astore 4
    //   15: new 200	android/graphics/BitmapFactory$Options
    //   18: dup
    //   19: invokespecial 202	android/graphics/BitmapFactory$Options:<init>	()V
    //   22: astore 10
    //   24: aload 10
    //   26: iload_1
    //   27: putfield 438	android/graphics/BitmapFactory$Options:inSampleSize	I
    //   30: aload 10
    //   32: iconst_1
    //   33: putfield 208	android/graphics/BitmapFactory$Options:inDither	Z
    //   36: getstatic 443	android/os/Build$VERSION:SDK_INT	I
    //   39: bipush 10
    //   41: if_icmplt +9 -> 50
    //   44: aload 10
    //   46: iconst_1
    //   47: putfield 446	android/graphics/BitmapFactory$Options:inPreferQualityOverSpeed	Z
    //   50: aload 4
    //   52: aconst_null
    //   53: aload 10
    //   55: invokestatic 452	android/graphics/BitmapFactory:decodeStream	(Ljava/io/InputStream;Landroid/graphics/Rect;Landroid/graphics/BitmapFactory$Options;)Landroid/graphics/Bitmap;
    //   58: astore 11
    //   60: aload 11
    //   62: astore_2
    //   63: aload 4
    //   65: ifnull +8 -> 73
    //   68: aload 4
    //   70: invokevirtual 457	java/io/InputStream:close	()V
    //   73: aload_2
    //   74: areturn
    //   75: astore 12
    //   77: aload 12
    //   79: invokestatic 460	com/whatsapp/g5:d	(Ljava/lang/Throwable;)V
    //   82: goto -9 -> 73
    //   85: astore 7
    //   87: aconst_null
    //   88: astore 4
    //   90: aload 7
    //   92: invokestatic 460	com/whatsapp/g5:d	(Ljava/lang/Throwable;)V
    //   95: aload 4
    //   97: ifnull -24 -> 73
    //   100: aload 4
    //   102: invokevirtual 457	java/io/InputStream:close	()V
    //   105: goto -32 -> 73
    //   108: astore 8
    //   110: aload 8
    //   112: invokestatic 460	com/whatsapp/g5:d	(Ljava/lang/Throwable;)V
    //   115: goto -42 -> 73
    //   118: astore_3
    //   119: aconst_null
    //   120: astore 4
    //   122: aload_3
    //   123: astore 5
    //   125: aload 4
    //   127: ifnull +8 -> 135
    //   130: aload 4
    //   132: invokevirtual 457	java/io/InputStream:close	()V
    //   135: aload 5
    //   137: athrow
    //   138: astore 6
    //   140: aload 6
    //   142: invokestatic 460	com/whatsapp/g5:d	(Ljava/lang/Throwable;)V
    //   145: goto -10 -> 135
    //   148: astore 5
    //   150: goto -25 -> 125
    //   153: astore 7
    //   155: goto -65 -> 90
    //
    // Exception table:
    //   from	to	target	type
    //   68	73	75	java/io/IOException
    //   2	11	85	java/io/FileNotFoundException
    //   100	105	108	java/io/IOException
    //   2	11	118	finally
    //   130	135	138	java/io/IOException
    //   15	60	148	finally
    //   90	95	148	finally
    //   15	60	153	java/io/FileNotFoundException
  }

  public static Bitmap a(Uri paramUri, File paramFile)
    throws FileNotFoundException, IOException, SecurityException, dg, OutOfMemoryError
  {
    Bitmap localBitmap = b(paramUri, paramFile);
    File localFile = paramFile.getParentFile();
    if (localFile != null)
      localFile.mkdirs();
    FileOutputStream localFileOutputStream = new FileOutputStream(paramFile);
    localBitmap.compress(Bitmap.CompressFormat.JPEG, 80, localFileOutputStream);
    localFileOutputStream.close();
    localBitmap.recycle();
    return a(paramUri, paramFile, 100, 100);
  }

  // ERROR //
  public static Bitmap a(Uri paramUri, File paramFile, int paramInt1, int paramInt2)
    throws FileNotFoundException, IOException, dg, OutOfMemoryError
  {
    // Byte code:
    //   0: getstatic 253	com/whatsapp/g5:n	I
    //   3: istore 4
    //   5: aconst_null
    //   6: astore 5
    //   8: aload_0
    //   9: ifnull +19 -> 28
    //   12: aload_0
    //   13: invokevirtual 504	android/net/Uri:toString	()Ljava/lang/String;
    //   16: getstatic 194	com/whatsapp/j5:z	[Ljava/lang/String;
    //   19: bipush 25
    //   21: aaload
    //   22: invokevirtual 508	java/lang/String:contains	(Ljava/lang/CharSequence;)Z
    //   25: ifeq +495 -> 520
    //   28: aload_0
    //   29: ifnull +340 -> 369
    //   32: aload_0
    //   33: invokevirtual 511	android/net/Uri:getPath	()Ljava/lang/String;
    //   36: astore 6
    //   38: aload 6
    //   40: ifnull +435 -> 475
    //   43: new 513	android/media/ExifInterface
    //   46: dup
    //   47: aload 6
    //   49: invokespecial 515	android/media/ExifInterface:<init>	(Ljava/lang/String;)V
    //   52: astore 7
    //   54: aload 7
    //   56: getstatic 194	com/whatsapp/j5:z	[Ljava/lang/String;
    //   59: bipush 12
    //   61: aaload
    //   62: iconst_1
    //   63: invokevirtual 519	android/media/ExifInterface:getAttributeInt	(Ljava/lang/String;I)I
    //   66: istore 8
    //   68: aload 7
    //   70: getstatic 194	com/whatsapp/j5:z	[Ljava/lang/String;
    //   73: bipush 26
    //   75: aaload
    //   76: iconst_0
    //   77: invokevirtual 519	android/media/ExifInterface:getAttributeInt	(Ljava/lang/String;I)I
    //   80: istore 9
    //   82: aload 7
    //   84: getstatic 194	com/whatsapp/j5:z	[Ljava/lang/String;
    //   87: bipush 20
    //   89: aaload
    //   90: iconst_0
    //   91: invokevirtual 519	android/media/ExifInterface:getAttributeInt	(Ljava/lang/String;I)I
    //   94: istore 10
    //   96: new 521	java/io/FileInputStream
    //   99: dup
    //   100: new 471	java/io/File
    //   103: dup
    //   104: aload 6
    //   106: invokespecial 522	java/io/File:<init>	(Ljava/lang/String;)V
    //   109: invokespecial 523	java/io/FileInputStream:<init>	(Ljava/io/File;)V
    //   112: astore 11
    //   114: new 200	android/graphics/BitmapFactory$Options
    //   117: dup
    //   118: invokespecial 202	android/graphics/BitmapFactory$Options:<init>	()V
    //   121: astore 12
    //   123: aload 12
    //   125: iload 9
    //   127: iload_2
    //   128: idiv
    //   129: iload 10
    //   131: iload_2
    //   132: idiv
    //   133: invokestatic 527	java/lang/Math:max	(II)I
    //   136: putfield 438	android/graphics/BitmapFactory$Options:inSampleSize	I
    //   139: aload 12
    //   141: iconst_1
    //   142: putfield 208	android/graphics/BitmapFactory$Options:inDither	Z
    //   145: aload 12
    //   147: iconst_0
    //   148: putfield 530	android/graphics/BitmapFactory$Options:inJustDecodeBounds	Z
    //   151: aload 12
    //   153: iconst_0
    //   154: putfield 533	android/graphics/BitmapFactory$Options:inScaled	Z
    //   157: aload 12
    //   159: getstatic 536	android/graphics/Bitmap$Config:RGB_565	Landroid/graphics/Bitmap$Config;
    //   162: putfield 539	android/graphics/BitmapFactory$Options:inPreferredConfig	Landroid/graphics/Bitmap$Config;
    //   165: getstatic 443	android/os/Build$VERSION:SDK_INT	I
    //   168: bipush 10
    //   170: if_icmplt +9 -> 179
    //   173: aload 12
    //   175: iconst_1
    //   176: putfield 446	android/graphics/BitmapFactory$Options:inPreferQualityOverSpeed	Z
    //   179: new 231	java/lang/StringBuilder
    //   182: dup
    //   183: invokespecial 232	java/lang/StringBuilder:<init>	()V
    //   186: getstatic 194	com/whatsapp/j5:z	[Ljava/lang/String;
    //   189: bipush 13
    //   191: aaload
    //   192: invokevirtual 236	java/lang/StringBuilder:append	(Ljava/lang/String;)Ljava/lang/StringBuilder;
    //   195: aload 6
    //   197: invokevirtual 236	java/lang/StringBuilder:append	(Ljava/lang/String;)Ljava/lang/StringBuilder;
    //   200: getstatic 194	com/whatsapp/j5:z	[Ljava/lang/String;
    //   203: bipush 33
    //   205: aaload
    //   206: invokevirtual 236	java/lang/StringBuilder:append	(Ljava/lang/String;)Ljava/lang/StringBuilder;
    //   209: iload 9
    //   211: invokevirtual 239	java/lang/StringBuilder:append	(I)Ljava/lang/StringBuilder;
    //   214: getstatic 194	com/whatsapp/j5:z	[Ljava/lang/String;
    //   217: bipush 9
    //   219: aaload
    //   220: invokevirtual 236	java/lang/StringBuilder:append	(Ljava/lang/String;)Ljava/lang/StringBuilder;
    //   223: iload 10
    //   225: invokevirtual 239	java/lang/StringBuilder:append	(I)Ljava/lang/StringBuilder;
    //   228: getstatic 194	com/whatsapp/j5:z	[Ljava/lang/String;
    //   231: bipush 18
    //   233: aaload
    //   234: invokevirtual 236	java/lang/StringBuilder:append	(Ljava/lang/String;)Ljava/lang/StringBuilder;
    //   237: iload 8
    //   239: invokevirtual 239	java/lang/StringBuilder:append	(I)Ljava/lang/StringBuilder;
    //   242: getstatic 194	com/whatsapp/j5:z	[Ljava/lang/String;
    //   245: bipush 19
    //   247: aaload
    //   248: invokevirtual 236	java/lang/StringBuilder:append	(Ljava/lang/String;)Ljava/lang/StringBuilder;
    //   251: aload 12
    //   253: getfield 438	android/graphics/BitmapFactory$Options:inSampleSize	I
    //   256: invokevirtual 239	java/lang/StringBuilder:append	(I)Ljava/lang/StringBuilder;
    //   259: invokevirtual 242	java/lang/StringBuilder:toString	()Ljava/lang/String;
    //   262: invokestatic 247	com/whatsapp/g5:b	(Ljava/lang/String;)V
    //   265: iload 9
    //   267: ifne +111 -> 378
    //   270: iload 10
    //   272: ifne +106 -> 378
    //   275: aload 6
    //   277: iconst_1
    //   278: aload 6
    //   280: ldc_w 541
    //   283: invokevirtual 545	java/lang/String:lastIndexOf	(Ljava/lang/String;)I
    //   286: iadd
    //   287: invokevirtual 549	java/lang/String:substring	(I)Ljava/lang/String;
    //   290: astore 25
    //   292: aload 25
    //   294: getstatic 194	com/whatsapp/j5:z	[Ljava/lang/String;
    //   297: bipush 30
    //   299: aaload
    //   300: invokevirtual 553	java/lang/String:equalsIgnoreCase	(Ljava/lang/String;)Z
    //   303: ifne +17 -> 320
    //   306: aload 25
    //   308: getstatic 194	com/whatsapp/j5:z	[Ljava/lang/String;
    //   311: bipush 10
    //   313: aaload
    //   314: invokevirtual 553	java/lang/String:equalsIgnoreCase	(Ljava/lang/String;)Z
    //   317: ifeq +17 -> 334
    //   320: getstatic 194	com/whatsapp/j5:z	[Ljava/lang/String;
    //   323: bipush 11
    //   325: aaload
    //   326: invokestatic 247	com/whatsapp/g5:b	(Ljava/lang/String;)V
    //   329: iload 4
    //   331: ifeq +47 -> 378
    //   334: new 231	java/lang/StringBuilder
    //   337: dup
    //   338: invokespecial 232	java/lang/StringBuilder:<init>	()V
    //   341: getstatic 194	com/whatsapp/j5:z	[Ljava/lang/String;
    //   344: bipush 22
    //   346: aaload
    //   347: invokevirtual 236	java/lang/StringBuilder:append	(Ljava/lang/String;)Ljava/lang/StringBuilder;
    //   350: aload 6
    //   352: invokevirtual 236	java/lang/StringBuilder:append	(Ljava/lang/String;)Ljava/lang/StringBuilder;
    //   355: invokevirtual 242	java/lang/StringBuilder:toString	()Ljava/lang/String;
    //   358: invokestatic 247	com/whatsapp/g5:b	(Ljava/lang/String;)V
    //   361: new 465	com/whatsapp/dg
    //   364: dup
    //   365: invokespecial 554	com/whatsapp/dg:<init>	()V
    //   368: athrow
    //   369: aload_1
    //   370: invokevirtual 557	java/io/File:getAbsolutePath	()Ljava/lang/String;
    //   373: astore 6
    //   375: goto -337 -> 38
    //   378: aload 11
    //   380: aconst_null
    //   381: aload 12
    //   383: invokestatic 452	android/graphics/BitmapFactory:decodeStream	(Ljava/io/InputStream;Landroid/graphics/Rect;Landroid/graphics/BitmapFactory$Options;)Landroid/graphics/Bitmap;
    //   386: astore 14
    //   388: aload 11
    //   390: invokevirtual 457	java/io/InputStream:close	()V
    //   393: iload 8
    //   395: istore 15
    //   397: aload 14
    //   399: astore 5
    //   401: aload 5
    //   403: ifnull +19 -> 422
    //   406: aload 5
    //   408: invokevirtual 320	android/graphics/Bitmap:getWidth	()I
    //   411: ifeq +11 -> 422
    //   414: aload 5
    //   416: invokevirtual 323	android/graphics/Bitmap:getHeight	()I
    //   419: ifne +545 -> 964
    //   422: new 231	java/lang/StringBuilder
    //   425: dup
    //   426: invokespecial 232	java/lang/StringBuilder:<init>	()V
    //   429: getstatic 194	com/whatsapp/j5:z	[Ljava/lang/String;
    //   432: bipush 22
    //   434: aaload
    //   435: invokevirtual 236	java/lang/StringBuilder:append	(Ljava/lang/String;)Ljava/lang/StringBuilder;
    //   438: aload_0
    //   439: invokevirtual 560	java/lang/StringBuilder:append	(Ljava/lang/Object;)Ljava/lang/StringBuilder;
    //   442: invokevirtual 242	java/lang/StringBuilder:toString	()Ljava/lang/String;
    //   445: invokestatic 247	com/whatsapp/g5:b	(Ljava/lang/String;)V
    //   448: new 465	com/whatsapp/dg
    //   451: dup
    //   452: invokespecial 554	com/whatsapp/dg:<init>	()V
    //   455: athrow
    //   456: astore 13
    //   458: getstatic 194	com/whatsapp/j5:z	[Ljava/lang/String;
    //   461: bipush 28
    //   463: aaload
    //   464: invokestatic 562	com/whatsapp/g5:d	(Ljava/lang/String;)V
    //   467: aload 11
    //   469: invokevirtual 457	java/io/InputStream:close	()V
    //   472: aload 13
    //   474: athrow
    //   475: new 231	java/lang/StringBuilder
    //   478: dup
    //   479: invokespecial 232	java/lang/StringBuilder:<init>	()V
    //   482: getstatic 194	com/whatsapp/j5:z	[Ljava/lang/String;
    //   485: bipush 8
    //   487: aaload
    //   488: invokevirtual 236	java/lang/StringBuilder:append	(Ljava/lang/String;)Ljava/lang/StringBuilder;
    //   491: aload_0
    //   492: invokevirtual 560	java/lang/StringBuilder:append	(Ljava/lang/Object;)Ljava/lang/StringBuilder;
    //   495: getstatic 194	com/whatsapp/j5:z	[Ljava/lang/String;
    //   498: bipush 23
    //   500: aaload
    //   501: invokevirtual 236	java/lang/StringBuilder:append	(Ljava/lang/String;)Ljava/lang/StringBuilder;
    //   504: aload_1
    //   505: invokevirtual 560	java/lang/StringBuilder:append	(Ljava/lang/Object;)Ljava/lang/StringBuilder;
    //   508: invokevirtual 242	java/lang/StringBuilder:toString	()Ljava/lang/String;
    //   511: invokestatic 562	com/whatsapp/g5:d	(Ljava/lang/String;)V
    //   514: iconst_0
    //   515: istore 15
    //   517: goto -116 -> 401
    //   520: new 231	java/lang/StringBuilder
    //   523: dup
    //   524: invokespecial 232	java/lang/StringBuilder:<init>	()V
    //   527: getstatic 194	com/whatsapp/j5:z	[Ljava/lang/String;
    //   530: bipush 29
    //   532: aaload
    //   533: invokevirtual 236	java/lang/StringBuilder:append	(Ljava/lang/String;)Ljava/lang/StringBuilder;
    //   536: aload_0
    //   537: invokevirtual 504	android/net/Uri:toString	()Ljava/lang/String;
    //   540: invokevirtual 236	java/lang/StringBuilder:append	(Ljava/lang/String;)Ljava/lang/StringBuilder;
    //   543: invokevirtual 242	java/lang/StringBuilder:toString	()Ljava/lang/String;
    //   546: invokestatic 247	com/whatsapp/g5:b	(Ljava/lang/String;)V
    //   549: getstatic 429	com/whatsapp/App:ib	Landroid/content/ContentResolver;
    //   552: aload_0
    //   553: invokevirtual 435	android/content/ContentResolver:openInputStream	(Landroid/net/Uri;)Ljava/io/InputStream;
    //   556: astore 26
    //   558: aload 26
    //   560: ifnonnull +18 -> 578
    //   563: getstatic 194	com/whatsapp/j5:z	[Ljava/lang/String;
    //   566: bipush 27
    //   568: aaload
    //   569: invokestatic 562	com/whatsapp/g5:d	(Ljava/lang/String;)V
    //   572: aconst_null
    //   573: astore 5
    //   575: aload 5
    //   577: areturn
    //   578: iconst_2
    //   579: anewarray 24	java/lang/String
    //   582: astore 27
    //   584: aload 27
    //   586: iconst_0
    //   587: getstatic 194	com/whatsapp/j5:z	[Ljava/lang/String;
    //   590: bipush 24
    //   592: aaload
    //   593: aastore
    //   594: aload 27
    //   596: iconst_1
    //   597: getstatic 194	com/whatsapp/j5:z	[Ljava/lang/String;
    //   600: bipush 21
    //   602: aaload
    //   603: aastore
    //   604: getstatic 429	com/whatsapp/App:ib	Landroid/content/ContentResolver;
    //   607: aload_0
    //   608: aload 27
    //   610: aconst_null
    //   611: aconst_null
    //   612: aconst_null
    //   613: invokevirtual 565	android/content/ContentResolver:query	(Landroid/net/Uri;[Ljava/lang/String;Ljava/lang/String;[Ljava/lang/String;Ljava/lang/String;)Landroid/database/Cursor;
    //   616: astore 28
    //   618: aload 28
    //   620: ifnull +768 -> 1388
    //   623: aload 28
    //   625: invokeinterface 568 1 0
    //   630: pop
    //   631: aload 28
    //   633: invokeinterface 571 1 0
    //   638: iconst_2
    //   639: if_icmpne +743 -> 1382
    //   642: aload 28
    //   644: iconst_1
    //   645: invokeinterface 575 2 0
    //   650: istore 29
    //   652: iload 4
    //   654: ifeq +12 -> 666
    //   657: getstatic 194	com/whatsapp/j5:z	[Ljava/lang/String;
    //   660: bipush 15
    //   662: aaload
    //   663: invokestatic 562	com/whatsapp/g5:d	(Ljava/lang/String;)V
    //   666: new 231	java/lang/StringBuilder
    //   669: dup
    //   670: invokespecial 232	java/lang/StringBuilder:<init>	()V
    //   673: getstatic 194	com/whatsapp/j5:z	[Ljava/lang/String;
    //   676: bipush 17
    //   678: aaload
    //   679: invokevirtual 236	java/lang/StringBuilder:append	(Ljava/lang/String;)Ljava/lang/StringBuilder;
    //   682: iload 29
    //   684: invokevirtual 239	java/lang/StringBuilder:append	(I)Ljava/lang/StringBuilder;
    //   687: invokevirtual 242	java/lang/StringBuilder:toString	()Ljava/lang/String;
    //   690: invokestatic 247	com/whatsapp/g5:b	(Ljava/lang/String;)V
    //   693: aload 28
    //   695: ifnull +10 -> 705
    //   698: aload 28
    //   700: invokeinterface 576 1 0
    //   705: new 200	android/graphics/BitmapFactory$Options
    //   708: dup
    //   709: invokespecial 202	android/graphics/BitmapFactory$Options:<init>	()V
    //   712: astore 30
    //   714: aload 30
    //   716: iconst_1
    //   717: putfield 530	android/graphics/BitmapFactory$Options:inJustDecodeBounds	Z
    //   720: aload 26
    //   722: aconst_null
    //   723: aload 30
    //   725: invokestatic 452	android/graphics/BitmapFactory:decodeStream	(Ljava/io/InputStream;Landroid/graphics/Rect;Landroid/graphics/BitmapFactory$Options;)Landroid/graphics/Bitmap;
    //   728: pop
    //   729: aload 30
    //   731: aload 30
    //   733: getfield 579	android/graphics/BitmapFactory$Options:outWidth	I
    //   736: iload_2
    //   737: idiv
    //   738: aload 30
    //   740: getfield 582	android/graphics/BitmapFactory$Options:outHeight	I
    //   743: iload_2
    //   744: idiv
    //   745: invokestatic 527	java/lang/Math:max	(II)I
    //   748: putfield 438	android/graphics/BitmapFactory$Options:inSampleSize	I
    //   751: aload 30
    //   753: iconst_1
    //   754: putfield 208	android/graphics/BitmapFactory$Options:inDither	Z
    //   757: aload 30
    //   759: iconst_0
    //   760: putfield 530	android/graphics/BitmapFactory$Options:inJustDecodeBounds	Z
    //   763: aload 30
    //   765: iconst_0
    //   766: putfield 533	android/graphics/BitmapFactory$Options:inScaled	Z
    //   769: aload 30
    //   771: getstatic 536	android/graphics/Bitmap$Config:RGB_565	Landroid/graphics/Bitmap$Config;
    //   774: putfield 539	android/graphics/BitmapFactory$Options:inPreferredConfig	Landroid/graphics/Bitmap$Config;
    //   777: new 231	java/lang/StringBuilder
    //   780: dup
    //   781: invokespecial 232	java/lang/StringBuilder:<init>	()V
    //   784: getstatic 194	com/whatsapp/j5:z	[Ljava/lang/String;
    //   787: bipush 16
    //   789: aaload
    //   790: invokevirtual 236	java/lang/StringBuilder:append	(Ljava/lang/String;)Ljava/lang/StringBuilder;
    //   793: aload 30
    //   795: getfield 579	android/graphics/BitmapFactory$Options:outWidth	I
    //   798: invokevirtual 239	java/lang/StringBuilder:append	(I)Ljava/lang/StringBuilder;
    //   801: getstatic 194	com/whatsapp/j5:z	[Ljava/lang/String;
    //   804: bipush 9
    //   806: aaload
    //   807: invokevirtual 236	java/lang/StringBuilder:append	(Ljava/lang/String;)Ljava/lang/StringBuilder;
    //   810: aload 30
    //   812: getfield 582	android/graphics/BitmapFactory$Options:outHeight	I
    //   815: invokevirtual 239	java/lang/StringBuilder:append	(I)Ljava/lang/StringBuilder;
    //   818: getstatic 194	com/whatsapp/j5:z	[Ljava/lang/String;
    //   821: bipush 19
    //   823: aaload
    //   824: invokevirtual 236	java/lang/StringBuilder:append	(Ljava/lang/String;)Ljava/lang/StringBuilder;
    //   827: aload 30
    //   829: getfield 438	android/graphics/BitmapFactory$Options:inSampleSize	I
    //   832: invokevirtual 239	java/lang/StringBuilder:append	(I)Ljava/lang/StringBuilder;
    //   835: invokevirtual 242	java/lang/StringBuilder:toString	()Ljava/lang/String;
    //   838: invokestatic 247	com/whatsapp/g5:b	(Ljava/lang/String;)V
    //   841: getstatic 443	android/os/Build$VERSION:SDK_INT	I
    //   844: bipush 10
    //   846: if_icmplt +9 -> 855
    //   849: aload 30
    //   851: iconst_1
    //   852: putfield 446	android/graphics/BitmapFactory$Options:inPreferQualityOverSpeed	Z
    //   855: aload 26
    //   857: invokevirtual 457	java/io/InputStream:close	()V
    //   860: getstatic 429	com/whatsapp/App:ib	Landroid/content/ContentResolver;
    //   863: aload_0
    //   864: invokevirtual 435	android/content/ContentResolver:openInputStream	(Landroid/net/Uri;)Ljava/io/InputStream;
    //   867: astore 33
    //   869: aload 33
    //   871: aconst_null
    //   872: aload 30
    //   874: invokestatic 452	android/graphics/BitmapFactory:decodeStream	(Ljava/io/InputStream;Landroid/graphics/Rect;Landroid/graphics/BitmapFactory$Options;)Landroid/graphics/Bitmap;
    //   877: astore 35
    //   879: aload 33
    //   881: invokevirtual 457	java/io/InputStream:close	()V
    //   884: iload 29
    //   886: istore 15
    //   888: aload 35
    //   890: astore 5
    //   892: goto -491 -> 401
    //   895: astore 36
    //   897: aload 28
    //   899: ifnull +10 -> 909
    //   902: aload 28
    //   904: invokeinterface 576 1 0
    //   909: aload 36
    //   911: athrow
    //   912: astore 32
    //   914: new 231	java/lang/StringBuilder
    //   917: dup
    //   918: invokespecial 232	java/lang/StringBuilder:<init>	()V
    //   921: getstatic 194	com/whatsapp/j5:z	[Ljava/lang/String;
    //   924: bipush 14
    //   926: aaload
    //   927: invokevirtual 236	java/lang/StringBuilder:append	(Ljava/lang/String;)Ljava/lang/StringBuilder;
    //   930: getstatic 443	android/os/Build$VERSION:SDK_INT	I
    //   933: invokevirtual 239	java/lang/StringBuilder:append	(I)Ljava/lang/StringBuilder;
    //   936: invokevirtual 242	java/lang/StringBuilder:toString	()Ljava/lang/String;
    //   939: invokestatic 584	com/whatsapp/g5:c	(Ljava/lang/String;)V
    //   942: goto -87 -> 855
    //   945: astore 34
    //   947: getstatic 194	com/whatsapp/j5:z	[Ljava/lang/String;
    //   950: bipush 28
    //   952: aaload
    //   953: invokestatic 562	com/whatsapp/g5:d	(Ljava/lang/String;)V
    //   956: aload 33
    //   958: invokevirtual 457	java/io/InputStream:close	()V
    //   961: aload 34
    //   963: athrow
    //   964: fconst_0
    //   965: fstore 16
    //   967: iload 15
    //   969: lookupswitch	default:+59->1028, 3:+395->1364, 6:+385->1354, 8:+405->1374, 90:+385->1354, 180:+395->1364, 270:+405->1374
    //   1029: iconst_m1
    //   1030: dstore_3
    //   1031: dup
    //   1032: invokespecial 587	android/graphics/Matrix:<init>	()V
    //   1035: astore 17
    //   1037: fload 16
    //   1039: fconst_0
    //   1040: fcmpl
    //   1041: ifle +50 -> 1091
    //   1044: getstatic 194	com/whatsapp/j5:z	[Ljava/lang/String;
    //   1047: bipush 32
    //   1049: aaload
    //   1050: invokestatic 247	com/whatsapp/g5:b	(Ljava/lang/String;)V
    //   1053: aload 17
    //   1055: fload 16
    //   1057: invokevirtual 591	android/graphics/Matrix:setRotate	(F)V
    //   1060: aload 5
    //   1062: iconst_0
    //   1063: iconst_0
    //   1064: aload 5
    //   1066: invokevirtual 320	android/graphics/Bitmap:getWidth	()I
    //   1069: aload 5
    //   1071: invokevirtual 323	android/graphics/Bitmap:getHeight	()I
    //   1074: aload 17
    //   1076: iconst_1
    //   1077: invokestatic 594	android/graphics/Bitmap:createBitmap	(Landroid/graphics/Bitmap;IIIILandroid/graphics/Matrix;Z)Landroid/graphics/Bitmap;
    //   1080: astore 24
    //   1082: aload 5
    //   1084: invokevirtual 342	android/graphics/Bitmap:recycle	()V
    //   1087: aload 24
    //   1089: astore 5
    //   1091: iload_3
    //   1092: ifle +212 -> 1304
    //   1095: aload 5
    //   1097: invokevirtual 320	android/graphics/Bitmap:getWidth	()I
    //   1100: iload_3
    //   1101: if_icmpgt +12 -> 1113
    //   1104: aload 5
    //   1106: invokevirtual 323	android/graphics/Bitmap:getHeight	()I
    //   1109: iload_3
    //   1110: if_icmple +194 -> 1304
    //   1113: new 231	java/lang/StringBuilder
    //   1116: dup
    //   1117: invokespecial 232	java/lang/StringBuilder:<init>	()V
    //   1120: aload 5
    //   1122: invokevirtual 320	android/graphics/Bitmap:getWidth	()I
    //   1125: invokevirtual 239	java/lang/StringBuilder:append	(I)Ljava/lang/StringBuilder;
    //   1128: getstatic 194	com/whatsapp/j5:z	[Ljava/lang/String;
    //   1131: bipush 7
    //   1133: aaload
    //   1134: invokevirtual 236	java/lang/StringBuilder:append	(Ljava/lang/String;)Ljava/lang/StringBuilder;
    //   1137: aload 5
    //   1139: invokevirtual 323	android/graphics/Bitmap:getHeight	()I
    //   1142: invokevirtual 239	java/lang/StringBuilder:append	(I)Ljava/lang/StringBuilder;
    //   1145: invokevirtual 242	java/lang/StringBuilder:toString	()Ljava/lang/String;
    //   1148: invokestatic 247	com/whatsapp/g5:b	(Ljava/lang/String;)V
    //   1151: aload 5
    //   1153: invokevirtual 320	android/graphics/Bitmap:getWidth	()I
    //   1156: i2f
    //   1157: iload_2
    //   1158: i2f
    //   1159: fdiv
    //   1160: aload 5
    //   1162: invokevirtual 323	android/graphics/Bitmap:getHeight	()I
    //   1165: i2f
    //   1166: iload_2
    //   1167: i2f
    //   1168: fdiv
    //   1169: invokestatic 597	java/lang/Math:max	(FF)F
    //   1172: fstore 18
    //   1174: new 376	android/graphics/Rect
    //   1177: dup
    //   1178: iconst_0
    //   1179: iconst_0
    //   1180: aload 5
    //   1182: invokevirtual 320	android/graphics/Bitmap:getWidth	()I
    //   1185: i2f
    //   1186: fload 18
    //   1188: fdiv
    //   1189: f2i
    //   1190: aload 5
    //   1192: invokevirtual 323	android/graphics/Bitmap:getHeight	()I
    //   1195: i2f
    //   1196: fload 18
    //   1198: fdiv
    //   1199: f2i
    //   1200: invokespecial 379	android/graphics/Rect:<init>	(IIII)V
    //   1203: astore 19
    //   1205: new 376	android/graphics/Rect
    //   1208: dup
    //   1209: iconst_0
    //   1210: iconst_0
    //   1211: aload 5
    //   1213: invokevirtual 320	android/graphics/Bitmap:getWidth	()I
    //   1216: aload 5
    //   1218: invokevirtual 323	android/graphics/Bitmap:getHeight	()I
    //   1221: invokespecial 379	android/graphics/Rect:<init>	(IIII)V
    //   1224: astore 20
    //   1226: aload 19
    //   1228: invokevirtual 600	android/graphics/Rect:width	()I
    //   1231: aload 19
    //   1233: invokevirtual 603	android/graphics/Rect:height	()I
    //   1236: getstatic 536	android/graphics/Bitmap$Config:RGB_565	Landroid/graphics/Bitmap$Config;
    //   1239: invokestatic 361	android/graphics/Bitmap:createBitmap	(IILandroid/graphics/Bitmap$Config;)Landroid/graphics/Bitmap;
    //   1242: astore 21
    //   1244: new 363	android/graphics/Canvas
    //   1247: dup
    //   1248: aload 21
    //   1250: invokespecial 366	android/graphics/Canvas:<init>	(Landroid/graphics/Bitmap;)V
    //   1253: astore 22
    //   1255: new 368	android/graphics/Paint
    //   1258: dup
    //   1259: invokespecial 369	android/graphics/Paint:<init>	()V
    //   1262: astore 23
    //   1264: aload 23
    //   1266: iconst_1
    //   1267: invokevirtual 383	android/graphics/Paint:setAntiAlias	(Z)V
    //   1270: aload 23
    //   1272: iconst_1
    //   1273: invokevirtual 389	android/graphics/Paint:setFilterBitmap	(Z)V
    //   1276: aload 23
    //   1278: iconst_1
    //   1279: invokevirtual 386	android/graphics/Paint:setDither	(Z)V
    //   1282: aload 22
    //   1284: aload 5
    //   1286: aload 20
    //   1288: aload 19
    //   1290: aload 23
    //   1292: invokevirtual 606	android/graphics/Canvas:drawBitmap	(Landroid/graphics/Bitmap;Landroid/graphics/Rect;Landroid/graphics/Rect;Landroid/graphics/Paint;)V
    //   1295: aload 5
    //   1297: invokevirtual 342	android/graphics/Bitmap:recycle	()V
    //   1300: aload 21
    //   1302: astore 5
    //   1304: new 231	java/lang/StringBuilder
    //   1307: dup
    //   1308: invokespecial 232	java/lang/StringBuilder:<init>	()V
    //   1311: getstatic 194	com/whatsapp/j5:z	[Ljava/lang/String;
    //   1314: bipush 31
    //   1316: aaload
    //   1317: invokevirtual 236	java/lang/StringBuilder:append	(Ljava/lang/String;)Ljava/lang/StringBuilder;
    //   1320: aload 5
    //   1322: invokevirtual 320	android/graphics/Bitmap:getWidth	()I
    //   1325: invokevirtual 239	java/lang/StringBuilder:append	(I)Ljava/lang/StringBuilder;
    //   1328: getstatic 194	com/whatsapp/j5:z	[Ljava/lang/String;
    //   1331: bipush 7
    //   1333: aaload
    //   1334: invokevirtual 236	java/lang/StringBuilder:append	(Ljava/lang/String;)Ljava/lang/StringBuilder;
    //   1337: aload 5
    //   1339: invokevirtual 323	android/graphics/Bitmap:getHeight	()I
    //   1342: invokevirtual 239	java/lang/StringBuilder:append	(I)Ljava/lang/StringBuilder;
    //   1345: invokevirtual 242	java/lang/StringBuilder:toString	()Ljava/lang/String;
    //   1348: invokestatic 247	com/whatsapp/g5:b	(Ljava/lang/String;)V
    //   1351: goto -776 -> 575
    //   1354: ldc_w 607
    //   1357: fstore 16
    //   1359: iload 4
    //   1361: ifeq -333 -> 1028
    //   1364: ldc_w 608
    //   1367: fstore 16
    //   1369: iload 4
    //   1371: ifeq -343 -> 1028
    //   1374: ldc_w 609
    //   1377: fstore 16
    //   1379: goto -351 -> 1028
    //   1382: iconst_0
    //   1383: istore 29
    //   1385: goto -728 -> 657
    //   1388: iconst_0
    //   1389: istore 29
    //   1391: goto -698 -> 693
    //
    // Exception table:
    //   from	to	target	type
    //   378	393	456	java/lang/OutOfMemoryError
    //   623	693	895	finally
    //   841	855	912	java/lang/NoSuchFieldError
    //   869	884	945	java/lang/OutOfMemoryError
  }

  public static ImageView a(sz paramsz, ImageView paramImageView, Activity paramActivity)
  {
    int j = g5.n;
    float f1 = j4.a(paramActivity).L;
    int k = (int)paramActivity.getResources().getDimension(2131361804);
    Bitmap localBitmap3;
    Canvas localCanvas;
    Paint localPaint;
    RectF localRectF;
    Bitmap localBitmap4;
    switch (paramsz.l)
    {
    case 4:
    default:
    case 1:
      do
      {
        do
        {
          return paramImageView;
          paramImageView.setScaleType(ImageView.ScaleType.CENTER);
          Bitmap localBitmap5 = m5.b(paramsz);
          if (localBitmap5 == null)
            break;
          Bitmap localBitmap6 = a(localBitmap5, k, f1);
          if (localBitmap6 != null)
          {
            paramImageView.setImageBitmap(localBitmap6);
            if (j == 0);
          }
          else
          {
            paramImageView.setImageResource(2130838490);
          }
        }
        while (j == 0);
        paramImageView.setImageResource(2130838490);
      }
      while (j == 0);
    case 5:
      paramImageView.setScaleType(ImageView.ScaleType.CENTER);
      int m = k * 4 / 3;
      localBitmap3 = Bitmap.createBitmap(m, k, Bitmap.Config.ARGB_8888);
      localCanvas = new Canvas(localBitmap3);
      localPaint = new Paint();
      localRectF = new RectF(0.0F, 0.0F, m, k);
      localPaint.setAntiAlias(true);
      localPaint.setDither(true);
      localPaint.setFilterBitmap(true);
      localCanvas.drawARGB(0, 0, 0, 0);
      localPaint.setColor(-1);
      localCanvas.drawRoundRect(localRectF, f1, f1, localPaint);
      localPaint.setXfermode(new PorterDuffXfermode(PorterDuff.Mode.SRC_IN));
      localBitmap4 = m5.b(paramsz);
      if (localBitmap4 == null)
        break;
    case 2:
    case 3:
    }
    while (true)
    {
      Matrix localMatrix = new Matrix();
      float f2 = Math.max(Math.max(1.0F, localRectF.width() / localBitmap4.getWidth()), Math.max(1.0F, localRectF.height() / localBitmap4.getHeight()));
      localMatrix.setScale(f2, f2, localBitmap4.getWidth() / 2, localBitmap4.getHeight() / 2);
      localMatrix.postTranslate((localRectF.width() - localBitmap4.getWidth()) / 2.0F, (localRectF.height() - localBitmap4.getHeight()) / 2.0F);
      localCanvas.drawBitmap(localBitmap4, localMatrix, localPaint);
      localPaint.setXfermode(null);
      localPaint.setColor(1711276032);
      localPaint.setStyle(Paint.Style.STROKE);
      localCanvas.drawRoundRect(localRectF, f1, f1, localPaint);
      int n = (int)(9.333333F * j4.a(paramActivity).d);
      int i1 = n + 2;
      Path localPath = new Path();
      localPath.moveTo(localRectF.left, localRectF.bottom - i1);
      localPath.lineTo(localRectF.right, localRectF.bottom - i1);
      localPath.lineTo(localRectF.right, localRectF.bottom - f1);
      localPath.arcTo(new RectF(localRectF.right - 2.0F * f1, localRectF.bottom - 2.0F * f1, localRectF.right, localRectF.bottom), 0.0F, 90.0F);
      localPath.lineTo(f1 + localRectF.left, localRectF.bottom);
      localPath.arcTo(new RectF(localRectF.left, localRectF.bottom - 2.0F * f1, localRectF.left + 2.0F * f1, localRectF.bottom), 90.0F, 90.0F);
      localPath.lineTo(localRectF.left, localRectF.bottom - i1);
      localPaint.setStyle(Paint.Style.FILL);
      localCanvas.drawPath(localPath, localPaint);
      if (paramsz.c != null)
      {
        String str = App.w.a(paramsz.c, null).d();
        TextPaint localTextPaint = new TextPaint();
        localTextPaint.setAntiAlias(true);
        localTextPaint.setColor(-1);
        localTextPaint.setTextSize(n);
        localTextPaint.setTypeface(Typeface.DEFAULT_BOLD);
        localTextPaint.setTextAlign(Paint.Align.CENTER);
        localCanvas.drawText(TextUtils.ellipsize(str, localTextPaint, localRectF.width() - f1, TextUtils.TruncateAt.END).toString(), localRectF.left + localRectF.width() / 2.0F, localRectF.bottom - (int)Math.ceil(localTextPaint.descent()), localTextPaint);
      }
      paramImageView.setImageBitmap(localBitmap3);
      if (j == 0)
        break;
      paramImageView.setScaleType(ImageView.ScaleType.FIT_CENTER);
      paramImageView.setImageResource(2130837512);
      if (j == 0)
        break;
      paramImageView.setScaleType(ImageView.ScaleType.FIT_CENTER);
      Bitmap localBitmap1 = m5.b(paramsz);
      if (localBitmap1 != null)
      {
        Bitmap localBitmap2 = a(localBitmap1, k, f1);
        if (localBitmap2 != null)
        {
          paramImageView.setImageBitmap(localBitmap2);
          if (j == 0);
        }
        else
        {
          paramImageView.setImageResource(2130837517);
        }
        if (j == 0)
          break;
      }
      paramImageView.setImageResource(2130837517);
      break;
      localBitmap4 = d5.a();
    }
  }

  public static File a(Uri paramUri)
    throws IOException
  {
    File localFile;
    if (paramUri.toString().startsWith(z[49]))
    {
      localFile = new File(paramUri.getPath());
      if (g5.n == 0);
    }
    else
    {
      ContentResolver localContentResolver = App.ib;
      String[] arrayOfString = new String[1];
      arrayOfString[0] = z[24];
      Cursor localCursor = localContentResolver.query(paramUri, arrayOfString, null, null, null);
      if (localCursor == null)
        throw new IOException(z[50]);
      localCursor.moveToFirst();
      localFile = new File(localCursor.getString(0));
      localCursor.close();
    }
    return localFile;
  }

  public static String a(int paramInt)
  {
    long l = System.currentTimeMillis();
    return mh.b(App.bb.jabber_id + Long.toString(l));
  }

  public static void a()
  {
    long l = System.currentTimeMillis();
    e = 0;
    a((byte)2);
    a((byte)3);
    a((byte)1);
    e = 1 + e;
    g5.b(z[45] + e + z[44] + new Date(f) + z[47] + (System.currentTimeMillis() - l) + z[46] + h);
  }

  private static void a(byte paramByte)
  {
    int j = g5.n;
    File localFile1 = new File(App.c, et.a(paramByte));
    File[] arrayOfFile;
    int k;
    if (localFile1.exists())
    {
      arrayOfFile = localFile1.listFiles();
      if (arrayOfFile != null)
      {
        h += arrayOfFile.length;
        k = 0;
      }
    }
    while (true)
    {
      File localFile2;
      String str1;
      String str2;
      if (k < arrayOfFile.length)
      {
        localFile2 = arrayOfFile[k];
        str1 = localFile2.getName();
        if ((str1.contains(c(paramByte))) && (str1.contains(z[5])))
          if (str1.length() > 19)
            str2 = str1.substring(15, 19);
      }
      try
      {
        int m = Integer.parseInt(str2);
        int n = Integer.parseInt(str1.substring(4, 12));
        if ((g == 0) || (g <= n))
          if (g != n)
            break label288;
        label288: for (int i1 = 1; ; i1 = 0)
        {
          g = n;
          if ((m > e) || (localFile2.lastModified() > f))
          {
            if ((i1 == 0) || (e <= m))
              e = m;
            if (localFile2.lastModified() > f)
              f = localFile2.lastModified();
          }
          if (j != 0)
            g5.d(z[3] + str1);
          k++;
          if (j == 0)
            break;
          if (j != 0)
            g5.b(z[4] + paramByte);
          return;
        }
      }
      catch (NumberFormatException localNumberFormatException)
      {
        while (true)
          g5.b(z[6] + str1);
      }
    }
  }

  public static void a(sz paramsz)
  {
    String str1 = App.a(paramsz).getAbsolutePath();
    String str2 = str1.substring(str1.lastIndexOf("."));
    File localFile = App.a(b(paramsz.l) + str2, paramsz.l);
    MediaData localMediaData = (MediaData)paramsz.t;
    localMediaData.file.renameTo(localFile);
    localMediaData.file.delete();
    localMediaData.file = localFile;
  }

  // ERROR //
  public static void a(File paramFile1, File paramFile2)
    throws IOException, FileNotFoundException
  {
    // Byte code:
    //   0: iconst_0
    //   1: istore_2
    //   2: getstatic 253	com/whatsapp/g5:n	I
    //   5: istore_3
    //   6: new 521	java/io/FileInputStream
    //   9: dup
    //   10: aload_0
    //   11: invokespecial 523	java/io/FileInputStream:<init>	(Ljava/io/File;)V
    //   14: astore 4
    //   16: aload_1
    //   17: invokevirtual 475	java/io/File:getParentFile	()Ljava/io/File;
    //   20: astore 6
    //   22: aload 6
    //   24: ifnull +9 -> 33
    //   27: aload 6
    //   29: invokevirtual 478	java/io/File:mkdirs	()Z
    //   32: pop
    //   33: new 480	java/io/FileOutputStream
    //   36: dup
    //   37: aload_1
    //   38: invokespecial 483	java/io/FileOutputStream:<init>	(Ljava/io/File;)V
    //   41: astore 7
    //   43: sipush 4096
    //   46: newarray byte
    //   48: astore 8
    //   50: aload 4
    //   52: aload 8
    //   54: iconst_0
    //   55: aload 8
    //   57: arraylength
    //   58: invokevirtual 910	java/io/InputStream:read	([BII)I
    //   61: istore 9
    //   63: iload 9
    //   65: iflt +22 -> 87
    //   68: aload 7
    //   70: aload 8
    //   72: iconst_0
    //   73: iload 9
    //   75: invokevirtual 914	java/io/OutputStream:write	([BII)V
    //   78: iload_2
    //   79: iload 9
    //   81: iadd
    //   82: istore_2
    //   83: iload_3
    //   84: ifeq -34 -> 50
    //   87: aload 4
    //   89: ifnull +8 -> 97
    //   92: aload 4
    //   94: invokevirtual 457	java/io/InputStream:close	()V
    //   97: return
    //   98: astore 5
    //   100: aconst_null
    //   101: astore 4
    //   103: aload 4
    //   105: ifnull +8 -> 113
    //   108: aload 4
    //   110: invokevirtual 457	java/io/InputStream:close	()V
    //   113: aload 5
    //   115: athrow
    //   116: astore 5
    //   118: goto -15 -> 103
    //
    // Exception table:
    //   from	to	target	type
    //   6	16	98	finally
    //   16	78	116	finally
  }

  public static void a(String paramString, Intent paramIntent, File paramFile)
    throws IOException, FileNotFoundException, dg, OutOfMemoryError
  {
    if (paramIntent == null);
    for (Uri localUri = null; ; localUri = paramIntent.getData())
    {
      a(paramString, localUri, paramFile);
      return;
    }
  }

  public static void a(String paramString, Uri paramUri, File paramFile)
    throws IOException, FileNotFoundException, dg, OutOfMemoryError
  {
    try
    {
      localBitmap = a(paramUri, paramFile);
      if (localBitmap == null)
      {
        g5.d(z[34]);
        App.a(App.Mb.getApplicationContext(), 2131296775, 0);
        return;
      }
    }
    catch (SecurityException localSecurityException)
    {
      while (true)
      {
        Bitmap localBitmap;
        g5.d(z[35] + localSecurityException.getMessage());
        App.a(App.Mb.getApplicationContext(), 2131296778, 0);
        continue;
        MediaData localMediaData = new MediaData();
        localMediaData.file = paramFile;
        ByteArrayOutputStream localByteArrayOutputStream = new ByteArrayOutputStream();
        localBitmap.compress(Bitmap.CompressFormat.JPEG, 80, localByteArrayOutputStream);
        byte[] arrayOfByte = localByteArrayOutputStream.toByteArray();
        localBitmap.recycle();
        App.a(paramString, arrayOfByte, localMediaData, (byte)1);
      }
    }
  }

  // ERROR //
  public static void a(byte[] paramArrayOfByte, File paramFile)
    throws IOException, FileNotFoundException
  {
    // Byte code:
    //   0: aload_0
    //   1: ifnull +32 -> 33
    //   4: new 954	java/io/BufferedOutputStream
    //   7: dup
    //   8: new 480	java/io/FileOutputStream
    //   11: dup
    //   12: aload_1
    //   13: invokespecial 483	java/io/FileOutputStream:<init>	(Ljava/io/File;)V
    //   16: invokespecial 957	java/io/BufferedOutputStream:<init>	(Ljava/io/OutputStream;)V
    //   19: astore_2
    //   20: aload_2
    //   21: aload_0
    //   22: invokevirtual 960	java/io/OutputStream:write	([B)V
    //   25: aload_2
    //   26: ifnull +7 -> 33
    //   29: aload_2
    //   30: invokevirtual 496	java/io/OutputStream:close	()V
    //   33: return
    //   34: astore_3
    //   35: aconst_null
    //   36: astore_2
    //   37: aload_2
    //   38: ifnull +7 -> 45
    //   41: aload_2
    //   42: invokevirtual 496	java/io/OutputStream:close	()V
    //   45: aload_3
    //   46: athrow
    //   47: astore 5
    //   49: goto -16 -> 33
    //   52: astore 4
    //   54: goto -9 -> 45
    //   57: astore_3
    //   58: goto -21 -> 37
    //
    // Exception table:
    //   from	to	target	type
    //   4	20	34	finally
    //   29	33	47	java/io/IOException
    //   41	45	52	java/io/IOException
    //   20	25	57	finally
  }

  public static boolean a(Activity paramActivity, lr paramlr, String paramString1, File paramFile, byte paramByte, String paramString2)
    throws IOException, FileNotFoundException
  {
    int j = g5.n;
    boolean bool;
    if (paramFile.length() > 12582912L)
    {
      g5.c(z[51] + paramFile.length());
      paramlr.a(2131296760);
      bool = false;
      return bool;
    }
    int k = paramFile.getName().lastIndexOf(".");
    String str = "";
    if (k != -1)
      str = paramFile.getName().substring(k);
    File localFile = App.a(paramString2 + str, paramByte);
    g5.d(paramFile.getAbsolutePath());
    MediaData localMediaData = new MediaData();
    a(paramFile, localFile);
    localMediaData.file = localFile;
    if (paramByte == 3);
    while (true)
    {
      try
      {
        while (true)
        {
          MediaMetadataRetriever localMediaMetadataRetriever = new MediaMetadataRetriever();
          try
          {
            localMediaMetadataRetriever.setDataSource(localMediaData.file.getAbsolutePath());
            Bitmap localBitmap3;
            if (Build.VERSION.SDK_INT >= 10)
              localBitmap3 = localMediaMetadataRetriever.getFrameAtTime(0L);
            Bitmap localBitmap2;
            for (localObject1 = localBitmap3; ; localObject1 = localBitmap2)
            {
              if (localObject1 != null)
              {
                g5.b(z[54] + ((Bitmap)localObject1).getWidth() + z[52] + ((Bitmap)localObject1).getHeight());
                localj4 = j4.a(paramActivity);
                if ((((Bitmap)localObject1).getWidth() != localj4.X) || (((Bitmap)localObject1).getHeight() != localj4.X))
                {
                  g5.b(z[53]);
                  if (((Bitmap)localObject1).getWidth() <= ((Bitmap)localObject1).getHeight())
                    break label470;
                  Matrix localMatrix1 = new Matrix();
                  float f1 = localj4.X / ((Bitmap)localObject1).getHeight();
                  localMatrix1.setScale(f1, f1);
                  localObject2 = Bitmap.createBitmap((Bitmap)localObject1, (((Bitmap)localObject1).getWidth() - ((Bitmap)localObject1).getHeight()) / 2, 0, ((Bitmap)localObject1).getHeight(), ((Bitmap)localObject1).getHeight(), localMatrix1, true);
                  ((Bitmap)localObject1).recycle();
                  localObject1 = localObject2;
                }
                ByteArrayOutputStream localByteArrayOutputStream = new ByteArrayOutputStream();
                ((Bitmap)localObject1).compress(Bitmap.CompressFormat.JPEG, 80, localByteArrayOutputStream);
                App.a(paramString1, localByteArrayOutputStream.toByteArray(), localMediaData, paramByte);
                ((Bitmap)localObject1).recycle();
                if (j == 0);
              }
              else
              {
                App.a(paramString1, null, localMediaData, paramByte);
              }
              bool = true;
              break;
              localBitmap2 = a(localMediaMetadataRetriever.captureFrame());
            }
          }
          catch (RuntimeException localRuntimeException)
          {
            while (true)
            {
              j4 localj4;
              g5.d(localRuntimeException);
              Object localObject1 = null;
              continue;
              label470: Matrix localMatrix2 = new Matrix();
              float f2 = localj4.X / ((Bitmap)localObject1).getWidth();
              localMatrix2.setScale(f2, f2);
              Bitmap localBitmap1 = Bitmap.createBitmap((Bitmap)localObject1, 0, (((Bitmap)localObject1).getHeight() - ((Bitmap)localObject1).getWidth()) / 2, ((Bitmap)localObject1).getWidth(), ((Bitmap)localObject1).getWidth(), localMatrix2, true);
              Object localObject2 = localBitmap1;
            }
          }
        }
      }
      catch (UnsatisfiedLinkError localUnsatisfiedLinkError)
      {
        App.a(paramString1, null, localMediaData, paramByte);
        if (j == 0)
          continue;
      }
      App.a(paramString1, null, localMediaData, paramByte);
    }
  }

  public static Bitmap b(Uri paramUri, File paramFile)
    throws FileNotFoundException, IOException, dg, OutOfMemoryError
  {
    return a(paramUri, paramFile, 800, 1000);
  }

  public static File b()
  {
    if (a == null)
    {
      String str = App.Mb.getSharedPreferences(App.Mb.getString(2131296258), 0).getString(z[1], null);
      if (str != null)
        a = new File(str);
    }
    return a;
  }

  public static String b(int paramInt)
  {
    long l = System.currentTimeMillis();
    if (!t4.b(f, l))
      e = 0;
    String str1 = null;
    switch (paramInt)
    {
    default:
    case 1:
    case 2:
    case 3:
    }
    while (true)
    {
      String str2 = new DecimalFormat(z[61]).format(e);
      String str3 = str1 + t4.a() + z[5] + str2;
      f = l;
      e = 1 + e;
      return str3;
      str1 = z[60];
      continue;
      str1 = z[59];
      continue;
      str1 = z[58];
    }
  }

  public static void b(int paramInt, Activity paramActivity)
  {
    int j = g5.n;
    ArrayList localArrayList1 = new ArrayList();
    switch (paramInt)
    {
    case 2:
    case 3:
    default:
      paramActivity.startActivityForResult(a(paramInt, localArrayList1), paramInt);
    case 1:
    case 4:
    case 5:
    }
    while (true)
    {
      return;
      c = a(1, paramActivity);
      Uri localUri = Uri.fromFile(d(1));
      localArrayList1.add(new Intent(z[65]).putExtra(z[75], localUri));
      if (j == 0)
        break;
      d = a(3, paramActivity);
      Intent localIntent3 = new Intent(z[74]);
      localIntent3.putExtra(z[66], 1);
      localIntent3.putExtra(z[72], 12582912L);
      localArrayList1.add(localIntent3);
      if (j == 0)
        break;
      ArrayList localArrayList2 = new ArrayList();
      Intent localIntent1 = h(paramInt).putExtra(z[68], 12582912L);
      List localList1 = App.hb.queryIntentActivities(localIntent1, 0);
      if (localList1 != null)
      {
        Iterator localIterator2 = localList1.iterator();
        do
        {
          if (!localIterator2.hasNext())
            break;
          ResolveInfo localResolveInfo2 = (ResolveInfo)localIterator2.next();
          ActivityInfo localActivityInfo2 = localResolveInfo2.activityInfo;
          String str2 = localActivityInfo2.applicationInfo.packageName;
          g5.b(z[67] + str2 + z[7] + localActivityInfo2.name);
          if ((str2.contains(z[73])) || (str2.contains(z[71])) || (str2.contains(z[70])) || (str2.contains(z[69])))
            localArrayList2.add(new Pair(localResolveInfo2, localIntent1));
        }
        while (j == 0);
      }
      Intent localIntent2 = new Intent(z[64]).setType(z[63]);
      List localList2 = App.hb.queryIntentActivities(localIntent2, 0);
      if (localList2 != null)
      {
        Iterator localIterator1 = localList2.iterator();
        do
        {
          if (!localIterator1.hasNext())
            break;
          ResolveInfo localResolveInfo1 = (ResolveInfo)localIterator1.next();
          ActivityInfo localActivityInfo1 = localResolveInfo1.activityInfo;
          String str1 = localActivityInfo1.applicationInfo.packageName;
          g5.b(z[67] + str1 + z[7] + localActivityInfo1.name);
          localArrayList2.add(new Pair(localResolveInfo1, localIntent2));
        }
        while (j == 0);
      }
      new a(paramActivity, 2131296501, localArrayList2, paramInt).show();
    }
  }

  public static void b(Uri paramUri)
  {
    Intent localIntent = new Intent(z[36]);
    localIntent.setData(paramUri);
    App.Mb.getApplicationContext().sendBroadcast(localIntent);
  }

  public static void b(sz paramsz)
  {
    b(Uri.fromFile(((MediaData)paramsz.t).file));
  }

  private static String c(int paramInt)
  {
    String str;
    switch (paramInt)
    {
    default:
      str = null;
    case 2:
    case 3:
    case 1:
    }
    while (true)
    {
      return str;
      str = z[56];
      continue;
      str = z[57];
      continue;
      str = z[55];
    }
  }

  public static void c()
  {
    int j = g5.n;
    g5.d(z[41] + Debug.getNativeHeapAllocatedSize() / 1024L + z[42]);
    if (MediaGallery.g != null)
    {
      MediaGallery.g.c();
      MediaGallery.g.finish();
    }
    Iterator localIterator = App.wb.keySet().iterator();
    do
    {
      if (!localIterator.hasNext())
        break;
      String str = (String)localIterator.next();
      if ((Conversations.a()) && (!Conversations.b().n.containsKey(str)))
      {
        Bitmap localBitmap = (Bitmap)((SoftReference)App.wb.get(str)).get();
        if (localBitmap != null)
          localBitmap.recycle();
      }
    }
    while (j == 0);
    App.wb.clear();
    App.xb.clear();
    if (Conversations.a())
      Conversations.b().finish();
  }

  private static File d(int paramInt)
  {
    a = App.a(a(paramInt) + z[0], (byte)1);
    SharedPreferences.Editor localEditor = App.Mb.getSharedPreferences(App.Mb.getString(2131296258), 0).edit();
    localEditor.putString(z[1], a.getAbsolutePath());
    if (!localEditor.commit())
      g5.d(z[2]);
    return a;
  }

  private static String[] e(int paramInt)
  {
    String[] arrayOfString;
    if (paramInt == 1)
    {
      arrayOfString = new String[1];
      arrayOfString[0] = z[43];
    }
    while (true)
    {
      return arrayOfString;
      arrayOfString = new String[1];
      arrayOfString[0] = z[43];
    }
  }

  private static Uri f(int paramInt)
  {
    if (paramInt == 1);
    for (Uri localUri = MediaStore.Images.Media.EXTERNAL_CONTENT_URI; ; localUri = MediaStore.Video.Media.EXTERNAL_CONTENT_URI)
      return localUri;
  }

  private static Uri g(int paramInt)
  {
    if (paramInt == 1);
    for (Uri localUri = MediaStore.Images.Media.INTERNAL_CONTENT_URI; ; localUri = MediaStore.Video.Media.INTERNAL_CONTENT_URI)
      return localUri;
  }

  public static Intent h(int paramInt)
  {
    int j = g5.n;
    Intent localIntent = new Intent(z[62]);
    switch (paramInt)
    {
    case 2:
    case 3:
    default:
    case 1:
    case 4:
    case 5:
    }
    while (true)
    {
      return localIntent;
      localIntent.setType(z[37]);
      if (j != 0)
      {
        localIntent.setType(z[39]);
        if (j != 0)
          localIntent.setType(z[63]);
      }
    }
  }
}