// #######################################################
// Decompiled by   : coddec 
// Module          : WhatsApp-18.cod
// Module version  : 2.8.1914
// Class ID        : 4
// ########################################################


package com.whatsapp.client;


abstract public final class ContactStatuses$PhotoSpec extends Object

{

	// @@@@@@@@@@@@@ Fields 
	public byte[] /*byte[]*/  data ; // ofs = 58382 addr = 0)
	public String /*java.lang.String*/  id ; // ofs = 58386 addr = 0)
	public String /*java.lang.String*/  jid ; // ofs = 58390 addr = 0)

	// @@@@@@@@@@@@@ Static routines 

public <init>( com.whatsapp.client.ContactStatuses$PhotoSpec ); // address: 0
	{
	jumpspecial_lib <init>( java.lang.Object )
	}

	// @@@@@@@@@@@@@ Virtual routines 

public final int hashCode( com.whatsapp.client.ContactStatuses$PhotoSpec ); // address: 0
	{
	enter_narrow 
	bipush 31
	istore_1 
	iconst_1 
	istore_2 
	bipush 31
	iload_2 
	imul 
	aload_0_getfield .field_1_1   // get_name_1:  .field_1_1   // get_name_2:  .field_1_1   // get_Name:    .field_1_1   // getName->1:  null   // getName->2:  null   // getName->N:  null   // ofs = -1 ord = 0 addr = 1
	ifnonnull Label12
	iconst_0 
	goto Label14
Label12:
	aload_0_getfield .field_1_1   // get_name_1:  .field_1_1   // get_name_2:  .field_1_1   // get_Name:    .field_1_1   // getName->1:  null   // getName->2:  null   // getName->N:  null   // ofs = -1 ord = 0 addr = 1
	invokevirtual_short .virtual_ // idx=0 pc=1
Label14:
	iadd 
	istore_2 
	bipush 31
	iload_2 
	imul 
	aload_0_getfield .field_2_2   // get_name_1:  .field_2_2   // get_name_2:  .field_2_2   // get_Name:    .field_2_2   // getName->1:  null   // getName->2:  null   // getName->N:  null   // ofs = -1 ord = 0 addr = 2
	ifnonnull Label23
	iconst_0 
	goto Label25
Label23:
	aload_0_getfield .field_2_2   // get_name_1:  .field_2_2   // get_name_2:  .field_2_2   // get_Name:    .field_2_2   // getName->1:  null   // getName->2:  null   // getName->N:  null   // ofs = -1 ord = 0 addr = 2
	invokevirtual_short .virtual_ // idx=0 pc=1
Label25:
	iadd 
	istore_2 
	iload_2 
	ireturn 
	}


public final boolean equals( com.whatsapp.client.ContactStatuses$PhotoSpec, java.lang.Object ); // address: 0
	{
	enter_narrow 
	aload_0 
	aload_1 
	if_acmpne Label6
	iconst_1 
	ireturn 
Label6:
	aload_1 
	ifnonnull Label10
	iconst_0 
	ireturn 
Label10:
	aload_0 
	invokenonvirtual_lib java.lang.Object.getClass // pc=1
	aload_1 
	invokenonvirtual_lib java.lang.Object.getClass // pc=1
	if_acmpeq Label17
	iconst_0 
	ireturn 
Label17:
	aload_1 
	checkcast ContactStatuses$PhotoSpec
	astore_2 
	aload_0_getfield .field_1_1   // get_name_1:  .field_1_1   // get_name_2:  .field_1_1   // get_Name:    .field_1_1   // getName->1:  null   // getName->2:  null   // getName->N:  null   // ofs = -1 ord = 0 addr = 1
	ifnonnull Label27
	aload_2 
	getfield .field_1_1   // get_name_1:  .field_1_1   // get_name_2:  .field_1_1   // get_Name:    .field_1_1   // getName->1:  null   // getName->2:  null   // getName->N:  null   // ofs = -1 ord = 0 addr = 1
	ifnull Label34
	iconst_0 
	ireturn 
Label27:
	aload_0_getfield .field_1_1   // get_name_1:  .field_1_1   // get_name_2:  .field_1_1   // get_Name:    .field_1_1   // getName->1:  null   // getName->2:  null   // getName->N:  null   // ofs = -1 ord = 0 addr = 1
	aload_2 
	getfield .field_1_1   // get_name_1:  .field_1_1   // get_name_2:  .field_1_1   // get_Name:    .field_1_1   // getName->1:  null   // getName->2:  null   // getName->N:  null   // ofs = -1 ord = 0 addr = 1
	invokevirtual_short .equals // idx=1 pc=2
	ifne Label34
	iconst_0 
	ireturn 
Label34:
	aload_0_getfield .field_2_2   // get_name_1:  .field_2_2   // get_name_2:  .field_2_2   // get_Name:    .field_2_2   // getName->1:  null   // getName->2:  null   // getName->N:  null   // ofs = -1 ord = 0 addr = 2
	ifnonnull Label41
	aload_2 
	getfield .field_2_2   // get_name_1:  .field_2_2   // get_name_2:  .field_2_2   // get_Name:    .field_2_2   // getName->1:  null   // getName->2:  null   // getName->N:  null   // ofs = -1 ord = 0 addr = 2
	ifnull Label48
	iconst_0 
	ireturn 
Label41:
	aload_0_getfield .field_2_2   // get_name_1:  .field_2_2   // get_name_2:  .field_2_2   // get_Name:    .field_2_2   // getName->1:  null   // getName->2:  null   // getName->N:  null   // ofs = -1 ord = 0 addr = 2
	aload_2 
	getfield .field_2_2   // get_name_1:  .field_2_2   // get_name_2:  .field_2_2   // get_Name:    .field_2_2   // getName->1:  null   // getName->2:  null   // getName->N:  null   // ofs = -1 ord = 0 addr = 2
	invokevirtual_short .equals // idx=1 pc=2
	ifne Label48
	iconst_0 
	ireturn 
Label48:
	iconst_1 
	ireturn 
	}

}
