// #######################################################
// Decompiled by   : coddec 
// Module          : WhatsApp-49.cod
// Module version  : 2.8.1914
// Class ID        : 0
// ########################################################


package com.whatsapp.client;


abstract final class SqliteMessageStore$1 extends Object
implements Runnable

{

	// @@@@@@@@@@@@@ Fields 
	private final com.whatsapp.client. /*module:WhatsApp-76.class#0*/  field_57352 ; // ofs = 57352 addr = 0)

	// @@@@@@@@@@@@@ Static routines 

<init>( com.whatsapp.client.SqliteMessageStore$1, module:WhatsApp-76.class#0 ); // address: 0
	{
	enter_narrow 
	aload_0 
	invokespecial_lib java.lang.Object.<init> // pc=1
	aload_0 
	aload_1 
	putfield .field_0_   // get_name_1:  .field_0_   // get_name_2:  .field_0_   // get_Name:    .field_0_   // getName->1:  null   // getName->2:  null   // getName->N:  null   // ofs = -1 ord = 0 addr = 0
	return 
	}

	// @@@@@@@@@@@@@ Virtual routines 

public final run( com.whatsapp.client.SqliteMessageStore$1 ); // address: 0
	{
	enter 
	ldc literal_85:"SqliteMessageStore: started async commit thread"
	invokestatic_lib module:WhatsApp-79.class#39.routine_24694(  ) // class#39
	aload_0_getfield .field_0_   // get_name_1:  .field_0_   // get_name_2:  .field_0_   // get_Name:    .field_0_   // getName->1:  null   // getName->2:  null   // getName->N:  null   // ofs = -1 ord = 0 addr = 0
	dup 
	astore_1 
	monitorenter 
	iipush 82800000
	istore_2 
	aload_0_getfield .field_0_   // get_name_1:  .field_0_   // get_name_2:  .field_0_   // get_Name:    .field_0_   // getName->1:  null   // getName->2:  null   // getName->N:  null   // ofs = -1 ord = 0 addr = 0
	getfield .field_26_26   // get_name_1:  .field_26_26   // get_name_2:  .field_26_26   // get_Name:    .field_26_26   // getName->1:  null   // getName->2:  null   // getName->N:  null   // ofs = -1 ord = 0 addr = 26
	invokevirtual long longValue( java.lang.Long ) // pc=1
	lstore 3
	aload_0_getfield .field_0_   // get_name_1:  .field_0_   // get_name_2:  .field_0_   // get_Name:    .field_0_   // getName->1:  null   // getName->2:  null   // getName->N:  null   // ofs = -1 ord = 0 addr = 0
	getfield .field_0_   // get_name_1:  .field_0_   // get_name_2:  .field_0_   // get_Name:    .field_0_   // getName->1:  null   // getName->2:  null   // getName->N:  null   // ofs = -1 ord = 0 addr = 0
	ifnull Label29
	aload_0_getfield .field_0_   // get_name_1:  .field_0_   // get_name_2:  .field_0_   // get_Name:    .field_0_   // getName->1:  null   // getName->2:  null   // getName->N:  null   // ofs = -1 ord = 0 addr = 0
	lgetfield .field_1_1   // get_name_1:  .field_1_1   // get_name_2:  .field_1_1   // get_Name:    .field_1_1   // getName->1:  null   // getName->2:  null   // getName->N:  null   // ofs = -1 ord = 0 addr = 1
	lload 3
	lcmp 
	ifgt Label29
	lload 3
	aload_0_getfield .field_0_   // get_name_1:  .field_0_   // get_name_2:  .field_0_   // get_Name:    .field_0_   // getName->1:  null   // getName->2:  null   // getName->N:  null   // ofs = -1 ord = 0 addr = 0
	lgetfield .field_1_1   // get_name_1:  .field_1_1   // get_name_2:  .field_1_1   // get_Name:    .field_1_1   // getName->1:  null   // getName->2:  null   // getName->N:  null   // ofs = -1 ord = 0 addr = 1
	iipush 82800000
	i2l 
	ladd 
	lcmp 
	ifle Label31
Label29:
	iconst_1 
	goto Label32
Label31:
	iconst_0 
Label32:
	istore_5 
	aload_0_getfield .field_0_   // get_name_1:  .field_0_   // get_name_2:  .field_0_   // get_Name:    .field_0_   // getName->1:  null   // getName->2:  null   // getName->N:  null   // ofs = -1 ord = 0 addr = 0
	lgetfield .field_3_3   // get_name_1:  .field_3_3   // get_name_2:  .field_3_3   // get_Name:    .field_3_3   // getName->1:  null   // getName->2:  null   // getName->N:  null   // ofs = -1 ord = 0 addr = 3
	lload 3
	lcmp 
	ifgt Label46
	lload 3
	aload_0_getfield .field_0_   // get_name_1:  .field_0_   // get_name_2:  .field_0_   // get_Name:    .field_0_   // getName->1:  null   // getName->2:  null   // getName->N:  null   // ofs = -1 ord = 0 addr = 0
	lgetfield .field_3_3   // get_name_1:  .field_3_3   // get_name_2:  .field_3_3   // get_Name:    .field_3_3   // getName->1:  null   // getName->2:  null   // getName->N:  null   // ofs = -1 ord = 0 addr = 3
	iipush 3600000
	i2l 
	ladd 
	lcmp 
	ifle Label48
Label46:
	iconst_1 
	goto Label49
Label48:
	iconst_0 
Label49:
	istore_6 
	iload_5 
	ifeq Label62
	iload_6 
	ifeq Label62
	ldc literal_86:"SqliteMessageStore: database periodic reconnect starting"
	invokestatic_lib module:WhatsApp-79.class#39.routine_24694(  ) // class#39
	aload_0_getfield .field_0_   // get_name_1:  .field_0_   // get_name_2:  .field_0_   // get_Name:    .field_0_   // getName->1:  null   // getName->2:  null   // getName->N:  null   // ofs = -1 ord = 0 addr = 0
	invokenonvirtual_lib .routine_994 // pc=1
	aload_0_getfield .field_0_   // get_name_1:  .field_0_   // get_name_2:  .field_0_   // get_Name:    .field_0_   // getName->1:  null   // getName->2:  null   // getName->N:  null   // ofs = -1 ord = 0 addr = 0
	invokenonvirtual_lib .routine_132 // pc=1
	ldc literal_87:"SqliteMessageStore: database periodic reconnect complete"
	invokestatic_lib module:WhatsApp-79.class#39.routine_24694(  ) // class#39
Label62:
	aload_1 
	monitorexit 
	goto Label70
	astore_7 
	aload_1 
	monitorexit 
	aload_7 
	athrow 
Label70:
	aload_0_getfield .field_0_   // get_name_1:  .field_0_   // get_name_2:  .field_0_   // get_Name:    .field_0_   // getName->1:  null   // getName->2:  null   // getName->N:  null   // ofs = -1 ord = 0 addr = 0
	getfield .field_28_28   // get_name_1:  .field_28_28   // get_name_2:  .field_28_28   // get_Name:    .field_28_28   // getName->1:  null   // getName->2:  null   // getName->N:  null   // ofs = -1 ord = 0 addr = 28
	dup 
	astore 9
	monitorenter 
	aload_0_getfield .field_0_   // get_name_1:  .field_0_   // get_name_2:  .field_0_   // get_Name:    .field_0_   // getName->1:  null   // getName->2:  null   // getName->N:  null   // ofs = -1 ord = 0 addr = 0
	getfield .field_27_27   // get_name_1:  .field_27_27   // get_name_2:  .field_27_27   // get_Name:    .field_27_27   // getName->1:  null   // getName->2:  null   // getName->N:  null   // ofs = -1 ord = 0 addr = 27
	astore 8
	aload 9
	monitorexit 
	goto Label86
	astore 10
	aload 9
	monitorexit 
	aload 10
	athrow 
Label86:
	invokestatic_lib long currentTimeMillis(  ) // System
	lstore 9
	aload 8
	ifnull Label104
	lload 9
	aload 8
	invokevirtual long longValue( java.lang.Long ) // pc=1
	lcmp 
	ifle Label96
	goto Label104
Label96:
	aload 8
	invokevirtual long longValue( java.lang.Long ) // pc=1
	lload 9
	lsub 
	invokestatic_lib sleep( long ) // Thread
	goto Label70
	astore 11
	goto Label70
Label104:
	aload_0_getfield .field_0_   // get_name_1:  .field_0_   // get_name_2:  .field_0_   // get_Name:    .field_0_   // getName->1:  null   // getName->2:  null   // getName->N:  null   // ofs = -1 ord = 0 addr = 0
	getfield .field_28_28   // get_name_1:  .field_28_28   // get_name_2:  .field_28_28   // get_Name:    .field_28_28   // getName->1:  null   // getName->2:  null   // getName->N:  null   // ofs = -1 ord = 0 addr = 28
	dup 
	astore 8
	monitorenter 
	aload_0_getfield .field_0_   // get_name_1:  .field_0_   // get_name_2:  .field_0_   // get_Name:    .field_0_   // getName->1:  null   // getName->2:  null   // getName->N:  null   // ofs = -1 ord = 0 addr = 0
	getfield .field_35_35   // get_name_1:  .field_35_35   // get_name_2:  .field_35_35   // get_Name:    .field_35_35   // getName->1:  null   // getName->2:  null   // getName->N:  null   // ofs = -1 ord = 0 addr = 35
	invokevirtual boolean isEmpty( java.util.Vector ) // pc=1
	ifeq Label143
	aload_0_getfield .field_0_   // get_name_1:  .field_0_   // get_name_2:  .field_0_   // get_Name:    .field_0_   // getName->1:  null   // getName->2:  null   // getName->N:  null   // ofs = -1 ord = 0 addr = 0
	getfield .field_29_29   // get_name_1:  .field_29_29   // get_name_2:  .field_29_29   // get_Name:    .field_29_29   // getName->1:  null   // getName->2:  null   // getName->N:  null   // ofs = -1 ord = 0 addr = 29
	invokevirtual boolean isEmpty( java.util.Vector ) // pc=1
	ifeq Label143
	aload_0_getfield .field_0_   // get_name_1:  .field_0_   // get_name_2:  .field_0_   // get_Name:    .field_0_   // getName->1:  null   // getName->2:  null   // getName->N:  null   // ofs = -1 ord = 0 addr = 0
	getfield .field_30_30   // get_name_1:  .field_30_30   // get_name_2:  .field_30_30   // get_Name:    .field_30_30   // getName->1:  null   // getName->2:  null   // getName->N:  null   // ofs = -1 ord = 0 addr = 30
	invokevirtual boolean isEmpty( java.util.Hashtable ) // pc=1
	ifeq Label143
	aload_0_getfield .field_0_   // get_name_1:  .field_0_   // get_name_2:  .field_0_   // get_Name:    .field_0_   // getName->1:  null   // getName->2:  null   // getName->N:  null   // ofs = -1 ord = 0 addr = 0
	getfield .field_31_31   // get_name_1:  .field_31_31   // get_name_2:  .field_31_31   // get_Name:    .field_31_31   // getName->1:  null   // getName->2:  null   // getName->N:  null   // ofs = -1 ord = 0 addr = 31
	invokevirtual boolean isEmpty( java.util.Hashtable ) // pc=1
	ifeq Label143
	aload_0_getfield .field_0_   // get_name_1:  .field_0_   // get_name_2:  .field_0_   // get_Name:    .field_0_   // getName->1:  null   // getName->2:  null   // getName->N:  null   // ofs = -1 ord = 0 addr = 0
	getfield .field_32_32   // get_name_1:  .field_32_32   // get_name_2:  .field_32_32   // get_Name:    .field_32_32   // getName->1:  null   // getName->2:  null   // getName->N:  null   // ofs = -1 ord = 0 addr = 32
	invokevirtual boolean isEmpty( java.util.Hashtable ) // pc=1
	ifeq Label143
	aload_0_getfield .field_0_   // get_name_1:  .field_0_   // get_name_2:  .field_0_   // get_Name:    .field_0_   // getName->1:  null   // getName->2:  null   // getName->N:  null   // ofs = -1 ord = 0 addr = 0
	getfield .field_33_33   // get_name_1:  .field_33_33   // get_name_2:  .field_33_33   // get_Name:    .field_33_33   // getName->1:  null   // getName->2:  null   // getName->N:  null   // ofs = -1 ord = 0 addr = 33
	invokevirtual boolean isEmpty( java.util.Hashtable ) // pc=1
	ifeq Label143
	aload_0_getfield .field_0_   // get_name_1:  .field_0_   // get_name_2:  .field_0_   // get_Name:    .field_0_   // getName->1:  null   // getName->2:  null   // getName->N:  null   // ofs = -1 ord = 0 addr = 0
	getfield .field_34_34   // get_name_1:  .field_34_34   // get_name_2:  .field_34_34   // get_Name:    .field_34_34   // getName->1:  null   // getName->2:  null   // getName->N:  null   // ofs = -1 ord = 0 addr = 34
	invokevirtual boolean isEmpty( java.util.Vector ) // pc=1
	ifeq Label143
	aload_0_getfield .field_0_   // get_name_1:  .field_0_   // get_name_2:  .field_0_   // get_Name:    .field_0_   // getName->1:  null   // getName->2:  null   // getName->N:  null   // ofs = -1 ord = 0 addr = 0
	aconst_null 
	putfield .field_26_26   // get_name_1:  .field_26_26   // get_name_2:  .field_26_26   // get_Name:    .field_26_26   // getName->1:  null   // getName->2:  null   // getName->N:  null   // ofs = -1 ord = 0 addr = 26
	aload 8
	monitorexit 
	goto_w Label356
Label143:
	aload_0_getfield .field_0_   // get_name_1:  .field_0_   // get_name_2:  .field_0_   // get_Name:    .field_0_   // getName->1:  null   // getName->2:  null   // getName->N:  null   // ofs = -1 ord = 0 addr = 0
	getfield .field_35_35   // get_name_1:  .field_35_35   // get_name_2:  .field_35_35   // get_Name:    .field_35_35   // getName->1:  null   // getName->2:  null   // getName->N:  null   // ofs = -1 ord = 0 addr = 35
	astore_1 
	aload_0_getfield .field_0_   // get_name_1:  .field_0_   // get_name_2:  .field_0_   // get_Name:    .field_0_   // getName->1:  null   // getName->2:  null   // getName->N:  null   // ofs = -1 ord = 0 addr = 0
	getfield .field_29_29   // get_name_1:  .field_29_29   // get_name_2:  .field_29_29   // get_Name:    .field_29_29   // getName->1:  null   // getName->2:  null   // getName->N:  null   // ofs = -1 ord = 0 addr = 29
	astore_2 
	aload_0_getfield .field_0_   // get_name_1:  .field_0_   // get_name_2:  .field_0_   // get_Name:    .field_0_   // getName->1:  null   // getName->2:  null   // getName->N:  null   // ofs = -1 ord = 0 addr = 0
	getfield .field_30_30   // get_name_1:  .field_30_30   // get_name_2:  .field_30_30   // get_Name:    .field_30_30   // getName->1:  null   // getName->2:  null   // getName->N:  null   // ofs = -1 ord = 0 addr = 30
	astore_3 
	aload_0_getfield .field_0_   // get_name_1:  .field_0_   // get_name_2:  .field_0_   // get_Name:    .field_0_   // getName->1:  null   // getName->2:  null   // getName->N:  null   // ofs = -1 ord = 0 addr = 0
	getfield .field_31_31   // get_name_1:  .field_31_31   // get_name_2:  .field_31_31   // get_Name:    .field_31_31   // getName->1:  null   // getName->2:  null   // getName->N:  null   // ofs = -1 ord = 0 addr = 31
	astore_4 
	aload_0_getfield .field_0_   // get_name_1:  .field_0_   // get_name_2:  .field_0_   // get_Name:    .field_0_   // getName->1:  null   // getName->2:  null   // getName->N:  null   // ofs = -1 ord = 0 addr = 0
	getfield .field_32_32   // get_name_1:  .field_32_32   // get_name_2:  .field_32_32   // get_Name:    .field_32_32   // getName->1:  null   // getName->2:  null   // getName->N:  null   // ofs = -1 ord = 0 addr = 32
	astore_5 
	aload_0_getfield .field_0_   // get_name_1:  .field_0_   // get_name_2:  .field_0_   // get_Name:    .field_0_   // getName->1:  null   // getName->2:  null   // getName->N:  null   // ofs = -1 ord = 0 addr = 0
	getfield .field_33_33   // get_name_1:  .field_33_33   // get_name_2:  .field_33_33   // get_Name:    .field_33_33   // getName->1:  null   // getName->2:  null   // getName->N:  null   // ofs = -1 ord = 0 addr = 33
	astore_6 
	aload_0_getfield .field_0_   // get_name_1:  .field_0_   // get_name_2:  .field_0_   // get_Name:    .field_0_   // getName->1:  null   // getName->2:  null   // getName->N:  null   // ofs = -1 ord = 0 addr = 0
	getfield .field_34_34   // get_name_1:  .field_34_34   // get_name_2:  .field_34_34   // get_Name:    .field_34_34   // getName->1:  null   // getName->2:  null   // getName->N:  null   // ofs = -1 ord = 0 addr = 34
	astore_7 
	aload_0_getfield .field_0_   // get_name_1:  .field_0_   // get_name_2:  .field_0_   // get_Name:    .field_0_   // getName->1:  null   // getName->2:  null   // getName->N:  null   // ofs = -1 ord = 0 addr = 0
	new_lib Runnable//java.lang.Runnable java.lang.Runnable java.lang.Runnable
	dup 
	invokespecial_lib java.util.Vector.<init> // pc=1
	putfield .field_35_35   // get_name_1:  .field_35_35   // get_name_2:  .field_35_35   // get_Name:    .field_35_35   // getName->1:  null   // getName->2:  null   // getName->N:  null   // ofs = -1 ord = 0 addr = 35
	aload_0_getfield .field_0_   // get_name_1:  .field_0_   // get_name_2:  .field_0_   // get_Name:    .field_0_   // getName->1:  null   // getName->2:  null   // getName->N:  null   // ofs = -1 ord = 0 addr = 0
	new_lib Runnable//java.lang.Runnable java.lang.Runnable java.lang.Runnable
	dup 
	invokespecial_lib java.util.Vector.<init> // pc=1
	putfield .field_29_29   // get_name_1:  .field_29_29   // get_name_2:  .field_29_29   // get_Name:    .field_29_29   // getName->1:  null   // getName->2:  null   // getName->N:  null   // ofs = -1 ord = 0 addr = 29
	aload_0_getfield .field_0_   // get_name_1:  .field_0_   // get_name_2:  .field_0_   // get_Name:    .field_0_   // getName->1:  null   // getName->2:  null   // getName->N:  null   // ofs = -1 ord = 0 addr = 0
	new_lib java.util.Hashtable//java.util.Hashtable java.util.Hashtable java.util.Hashtable
	dup 
	invokespecial_lib java.util.Hashtable.<init> // pc=1
	putfield .field_30_30   // get_name_1:  .field_30_30   // get_name_2:  .field_30_30   // get_Name:    .field_30_30   // getName->1:  null   // getName->2:  null   // getName->N:  null   // ofs = -1 ord = 0 addr = 30
	aload_0_getfield .field_0_   // get_name_1:  .field_0_   // get_name_2:  .field_0_   // get_Name:    .field_0_   // getName->1:  null   // getName->2:  null   // getName->N:  null   // ofs = -1 ord = 0 addr = 0
	new_lib java.util.Hashtable//java.util.Hashtable java.util.Hashtable java.util.Hashtable
	dup 
	invokespecial_lib java.util.Hashtable.<init> // pc=1
	putfield .field_31_31   // get_name_1:  .field_31_31   // get_name_2:  .field_31_31   // get_Name:    .field_31_31   // getName->1:  null   // getName->2:  null   // getName->N:  null   // ofs = -1 ord = 0 addr = 31
	aload_0_getfield .field_0_   // get_name_1:  .field_0_   // get_name_2:  .field_0_   // get_Name:    .field_0_   // getName->1:  null   // getName->2:  null   // getName->N:  null   // ofs = -1 ord = 0 addr = 0
	new_lib java.util.Hashtable//java.util.Hashtable java.util.Hashtable java.util.Hashtable
	dup 
	invokespecial_lib java.util.Hashtable.<init> // pc=1
	putfield .field_32_32   // get_name_1:  .field_32_32   // get_name_2:  .field_32_32   // get_Name:    .field_32_32   // getName->1:  null   // getName->2:  null   // getName->N:  null   // ofs = -1 ord = 0 addr = 32
	aload_0_getfield .field_0_   // get_name_1:  .field_0_   // get_name_2:  .field_0_   // get_Name:    .field_0_   // getName->1:  null   // getName->2:  null   // getName->N:  null   // ofs = -1 ord = 0 addr = 0
	new_lib java.util.Hashtable//java.util.Hashtable java.util.Hashtable java.util.Hashtable
	dup 
	invokespecial_lib java.util.Hashtable.<init> // pc=1
	putfield .field_33_33   // get_name_1:  .field_33_33   // get_name_2:  .field_33_33   // get_Name:    .field_33_33   // getName->1:  null   // getName->2:  null   // getName->N:  null   // ofs = -1 ord = 0 addr = 33
	aload_0_getfield .field_0_   // get_name_1:  .field_0_   // get_name_2:  .field_0_   // get_Name:    .field_0_   // getName->1:  null   // getName->2:  null   // getName->N:  null   // ofs = -1 ord = 0 addr = 0
	new_lib Runnable//java.lang.Runnable java.lang.Runnable java.lang.Runnable
	dup 
	invokespecial_lib java.util.Vector.<init> // pc=1
	putfield .field_34_34   // get_name_1:  .field_34_34   // get_name_2:  .field_34_34   // get_Name:    .field_34_34   // getName->1:  null   // getName->2:  null   // getName->N:  null   // ofs = -1 ord = 0 addr = 34
	aload 8
	monitorexit 
	goto Label207
	astore 12
	aload 8
	monitorexit 
	aload 12
	athrow 
Label207:
	lipush -4528648054740815433
	ldc literal_88:"Start sqlite batch commit cycle"
	invokenonvirtual_lib java.lang.String.getBytes // pc=1
	invokestatic_lib boolean logEvent( long, byte[] ) // EventLogger
	pop 
	invokestatic_lib long currentTimeMillis(  ) // System
	lstore 8
	lipush -4528648054740815433
	new_lib Long//java.lang.Long java.lang.Long java.lang.Long
	dup 
	ldc literal_89:"Delete chat history: "
	invokespecial_lib java.lang.StringBuffer.<init> // pc=2
	aload_1 
	invokevirtual int size( java.util.Vector ) // pc=1
	invokevirtual java.lang.StringBuffer append( java.lang.StringBuffer, int ) // pc=2
	invokevirtual_short .toString // idx=2 pc=1
	invokenonvirtual_lib java.lang.String.getBytes // pc=1
	invokestatic_lib boolean logEvent( long, byte[] ) // EventLogger
	pop 
	aload_0_getfield .field_0_   // get_name_1:  .field_0_   // get_name_2:  .field_0_   // get_Name:    .field_0_   // getName->1:  null   // getName->2:  null   // getName->N:  null   // ofs = -1 ord = 0 addr = 0
	aload_1 
	invokespecial_lib .routine_7350 // pc=2
	lipush -4528648054740815433
	new_lib Long//java.lang.Long java.lang.Long java.lang.Long
	dup 
	ldc literal_90:"Commit messages: "
	invokespecial_lib java.lang.StringBuffer.<init> // pc=2
	aload_2 
	invokevirtual int size( java.util.Vector ) // pc=1
	invokevirtual java.lang.StringBuffer append( java.lang.StringBuffer, int ) // pc=2
	invokevirtual_short .toString // idx=2 pc=1
	invokenonvirtual_lib java.lang.String.getBytes // pc=1
	invokestatic_lib boolean logEvent( long, byte[] ) // EventLogger
	pop 
	aload_0_getfield .field_0_   // get_name_1:  .field_0_   // get_name_2:  .field_0_   // get_Name:    .field_0_   // getName->1:  null   // getName->2:  null   // getName->N:  null   // ofs = -1 ord = 0 addr = 0
	aload_2 
	invokespecial_lib .routine_10511 // pc=2
	lipush -4528648054740815433
	new_lib Long//java.lang.Long java.lang.Long java.lang.Long
	dup 
	ldc literal_91:"Mark messages received: "
	invokespecial_lib java.lang.StringBuffer.<init> // pc=2
	aload_3 
	invokevirtual int size( java.util.Hashtable ) // pc=1
	invokevirtual java.lang.StringBuffer append( java.lang.StringBuffer, int ) // pc=2
	invokevirtual_short .toString // idx=2 pc=1
	invokenonvirtual_lib java.lang.String.getBytes // pc=1
	invokestatic_lib boolean logEvent( long, byte[] ) // EventLogger
	pop 
	aload_0_getfield .field_0_   // get_name_1:  .field_0_   // get_name_2:  .field_0_   // get_Name:    .field_0_   // getName->1:  null   // getName->2:  null   // getName->N:  null   // ofs = -1 ord = 0 addr = 0
	aload_3 
	invokespecial_lib .routine_5020 // pc=2
	lipush -4528648054740815433
	new_lib Long//java.lang.Long java.lang.Long java.lang.Long
	dup 
	ldc literal_92:"Update last seen status: "
	invokespecial_lib java.lang.StringBuffer.<init> // pc=2
	aload_4 
	invokevirtual int size( java.util.Hashtable ) // pc=1
	invokevirtual java.lang.StringBuffer append( java.lang.StringBuffer, int ) // pc=2
	invokevirtual_short .toString // idx=2 pc=1
	invokenonvirtual_lib java.lang.String.getBytes // pc=1
	invokestatic_lib boolean logEvent( long, byte[] ) // EventLogger
	pop 
	aload_0_getfield .field_0_   // get_name_1:  .field_0_   // get_name_2:  .field_0_   // get_Name:    .field_0_   // getName->1:  null   // getName->2:  null   // getName->N:  null   // ofs = -1 ord = 0 addr = 0
	aload_4 
	invokespecial_lib .routine_10888 // pc=2
	lipush -4528648054740815433
	new_lib Long//java.lang.Long java.lang.Long java.lang.Long
	dup 
	ldc literal_93:"Update participants: "
	invokespecial_lib java.lang.StringBuffer.<init> // pc=2
	aload_5 
	invokevirtual int size( java.util.Hashtable ) // pc=1
	invokevirtual java.lang.StringBuffer append( java.lang.StringBuffer, int ) // pc=2
	invokevirtual_short .toString // idx=2 pc=1
	invokenonvirtual_lib java.lang.String.getBytes // pc=1
	invokestatic_lib boolean logEvent( long, byte[] ) // EventLogger
	pop 
	aload_0_getfield .field_0_   // get_name_1:  .field_0_   // get_name_2:  .field_0_   // get_Name:    .field_0_   // getName->1:  null   // getName->2:  null   // getName->N:  null   // ofs = -1 ord = 0 addr = 0
	aload_5 
	invokespecial_lib .routine_11079 // pc=2
	lipush -4528648054740815433
	new_lib Long//java.lang.Long java.lang.Long java.lang.Long
	dup 
	ldc literal_94:"Update group photo: "
	invokespecial_lib java.lang.StringBuffer.<init> // pc=2
	aload_6 
	invokevirtual int size( java.util.Hashtable ) // pc=1
	invokevirtual java.lang.StringBuffer append( java.lang.StringBuffer, int ) // pc=2
	invokevirtual_short .toString // idx=2 pc=1
	invokenonvirtual_lib java.lang.String.getBytes // pc=1
	invokestatic_lib boolean logEvent( long, byte[] ) // EventLogger
	pop 
	aload_0_getfield .field_0_   // get_name_1:  .field_0_   // get_name_2:  .field_0_   // get_Name:    .field_0_   // getName->1:  null   // getName->2:  null   // getName->N:  null   // ofs = -1 ord = 0 addr = 0
	aload_6 
	invokespecial_lib .routine_11233 // pc=2
	lipush -4528648054740815433
	new_lib Long//java.lang.Long java.lang.Long java.lang.Long
	dup 
	ldc literal_95:"Delete messages: "
	invokespecial_lib java.lang.StringBuffer.<init> // pc=2
	aload_7 
	invokevirtual int size( java.util.Vector ) // pc=1
	invokevirtual java.lang.StringBuffer append( java.lang.StringBuffer, int ) // pc=2
	invokevirtual_short .toString // idx=2 pc=1
	invokenonvirtual_lib java.lang.String.getBytes // pc=1
	invokestatic_lib boolean logEvent( long, byte[] ) // EventLogger
	pop 
	aload_0_getfield .field_0_   // get_name_1:  .field_0_   // get_name_2:  .field_0_   // get_Name:    .field_0_   // getName->1:  null   // getName->2:  null   // getName->N:  null   // ofs = -1 ord = 0 addr = 0
	aload_7 
	invokespecial_lib .routine_11556 // pc=2
	lipush -4528648054740815433
	new_lib Long//java.lang.Long java.lang.Long java.lang.Long
	dup 
	ldc literal_96:"End sqlite batch commit cycle. Total time "
	invokespecial_lib java.lang.StringBuffer.<init> // pc=2
	invokestatic_lib long currentTimeMillis(  ) // System
	lload 8
	lsub 
	invokevirtual java.lang.StringBuffer append( java.lang.StringBuffer, long ) // pc=3
	ldc literal_97:"ms"
	invokevirtual java.lang.StringBuffer append( java.lang.StringBuffer, java.lang.String ) // pc=2
	invokevirtual_short .toString // idx=2 pc=1
	invokenonvirtual_lib java.lang.String.getBytes // pc=1
	invokestatic_lib boolean logEvent( long, byte[] ) // EventLogger
	pop 
	goto_w Label70
	astore_1 
	aload_0_getfield .field_0_   // get_name_1:  .field_0_   // get_name_2:  .field_0_   // get_Name:    .field_0_   // getName->1:  null   // getName->2:  null   // getName->N:  null   // ofs = -1 ord = 0 addr = 0
	aload_1 
	ldc literal_98:"asyncCommitThread.run"
	invokespecial_lib .routine_4234 // pc=3
	aload_0_getfield .field_0_   // get_name_1:  .field_0_   // get_name_2:  .field_0_   // get_Name:    .field_0_   // getName->1:  null   // getName->2:  null   // getName->N:  null   // ofs = -1 ord = 0 addr = 0
	getfield .field_28_28   // get_name_1:  .field_28_28   // get_name_2:  .field_28_28   // get_Name:    .field_28_28   // getName->1:  null   // getName->2:  null   // getName->N:  null   // ofs = -1 ord = 0 addr = 28
	dup 
	astore_2 
	monitorenter 
	aload_0_getfield .field_0_   // get_name_1:  .field_0_   // get_name_2:  .field_0_   // get_Name:    .field_0_   // getName->1:  null   // getName->2:  null   // getName->N:  null   // ofs = -1 ord = 0 addr = 0
	aconst_null 
	putfield .field_26_26   // get_name_1:  .field_26_26   // get_name_2:  .field_26_26   // get_Name:    .field_26_26   // getName->1:  null   // getName->2:  null   // getName->N:  null   // ofs = -1 ord = 0 addr = 26
	aload_2 
	monitorexit 
	return 
	astore 13
	aload_2 
	monitorexit 
	aload 13
	athrow 
Label356:
	return 
	}

}
