// #######################################################
// Decompiled by   : coddec 
// Module          : WhatsApp-16.cod
// Module version  : 2.8.1914
// Class ID        : 1
// ########################################################


package com.whatsapp.client;


abstract final class ChatsTabButton$17 extends Object
implements Runnable

{

	// @@@@@@@@@@@@@ Fields 
	private final com.whatsapp.client.ChatsTabButton /*com.whatsapp.client.ChatsTabButton*/  field_59458 ; // ofs = 59458 addr = 0)

	// @@@@@@@@@@@@@ Static routines 

<init>( com.whatsapp.client.ChatsTabButton$17, com.whatsapp.client.ChatsTabButton ); // address: 0
	{
	enter_narrow 
	aload_0 
	invokespecial_lib java.lang.Object.<init> // pc=1
	aload_0 
	aload_1 
	putfield .field_0_   // get_name_1:  .field_0_   // get_name_2:  .field_0_   // get_Name:    .field_0_   // getName->1:  null   // getName->2:  null   // getName->N:  null   // ofs = -1 ord = 0 addr = 0
	return 
	}

	// @@@@@@@@@@@@@ Virtual routines 

public final run( com.whatsapp.client.ChatsTabButton$17 ); // address: 0
	{
	enter 
	aload_0_getfield .field_0_   // get_name_1:  .field_0_   // get_name_2:  .field_0_   // get_Name:    .field_0_   // getName->1:  null   // getName->2:  null   // getName->N:  null   // ofs = -1 ord = 0 addr = 0
	getfield _selected   // get_name_1:  _selected   // get_name_2:  _selected   // get_Name:    _selected   // getName->1:  _selected   // getName->2:  _selected   // getName->N:  _selected   // ofs = -1 ord = 0 addr = -1
	ifne Label7
	aload_0_getfield .field_0_   // get_name_1:  .field_0_   // get_name_2:  .field_0_   // get_Name:    .field_0_   // getName->1:  null   // getName->2:  null   // getName->N:  null   // ofs = -1 ord = 0 addr = 0
	invokespecial_lib .routine_3972 // pc=1
	return 
Label7:
	aload_0_getfield .field_0_   // get_name_1:  .field_0_   // get_name_2:  .field_0_   // get_Name:    .field_0_   // getName->1:  null   // getName->2:  null   // getName->N:  null   // ofs = -1 ord = 0 addr = 0
	invokestatic_lib com.whatsapp.client.ChatsTabButton.routine_7958(  ) // ChatsTabButton
	pop 
	aload_0_getfield .field_0_   // get_name_1:  .field_0_   // get_name_2:  .field_0_   // get_Name:    .field_0_   // getName->1:  null   // getName->2:  null   // getName->N:  null   // ofs = -1 ord = 0 addr = 0
	getfield _currentFrame   // get_name_1:  _currentFrame   // get_name_2:  _currentFrame   // get_Name:    _currentFrame   // getName->1:  _currentFrame   // getName->2:  _currentFrame   // getName->N:  _currentFrame   // ofs = -1 ord = 0 addr = -1
	bipush 6
	if_icmplt Label17
	aload_0_getfield .field_0_   // get_name_1:  .field_0_   // get_name_2:  .field_0_   // get_Name:    .field_0_   // getName->1:  null   // getName->2:  null   // getName->N:  null   // ofs = -1 ord = 0 addr = 0
	iconst_0 
	putfield _currentFrame   // get_name_1:  _currentFrame   // get_name_2:  _currentFrame   // get_Name:    _currentFrame   // getName->1:  _currentFrame   // getName->2:  _currentFrame   // getName->N:  _currentFrame   // ofs = -1 ord = 0 addr = -1
Label17:
	aload_0_getfield .field_0_   // get_name_1:  .field_0_   // get_name_2:  .field_0_   // get_Name:    .field_0_   // getName->1:  null   // getName->2:  null   // getName->N:  null   // ofs = -1 ord = 0 addr = 0
	getfield _parentScr   // get_name_1:  _parentScr   // get_name_2:  _parentScr   // get_Name:    _parentScr   // getName->1:  _parentScr   // getName->2:  _parentScr   // getName->N:  _parentScr   // ofs = -1 ord = 1 addr = -1
	invokenonvirtual_lib .routine_4993 // pc=1
	istore_1 
	iconst_0 
	istore_2 
Label23:
	iload_2 
	iload_1 
	if_icmpge Label47
	aload_0_getfield .field_0_   // get_name_1:  .field_0_   // get_name_2:  .field_0_   // get_Name:    .field_0_   // getName->1:  null   // getName->2:  null   // getName->N:  null   // ofs = -1 ord = 0 addr = 0
	getfield _parentScr   // get_name_1:  _parentScr   // get_name_2:  _parentScr   // get_Name:    _parentScr   // getName->1:  _parentScr   // getName->2:  _parentScr   // getName->N:  _parentScr   // ofs = -1 ord = 1 addr = -1
	iload_2 
	invokenonvirtual_lib .routine_4975 // pc=2
	astore_3 
	aload_3 
	checkcastbranch_lib 
	astore_4 
	aload_4 
	getfield .field_8_8   // get_name_1:  .field_8_8   // get_name_2:  .field_8_8   // get_Name:    .field_8_8   // getName->1:  null   // getName->2:  null   // getName->N:  null   // ofs = -1 ord = 0 addr = 8
	ifnull Label45
	aload_4 
	getfield .field_8_8   // get_name_1:  .field_8_8   // get_name_2:  .field_8_8   // get_Name:    .field_8_8   // getName->1:  null   // getName->2:  null   // getName->N:  null   // ofs = -1 ord = 0 addr = 8
	getfield .field_4_4   // get_name_1:  .field_4_4   // get_name_2:  .field_4_4   // get_Name:    .field_4_4   // getName->1:  null   // getName->2:  null   // getName->N:  null   // ofs = -1 ord = 0 addr = 4
	ifeq Label45
	aload_0_getfield .field_0_   // get_name_1:  .field_0_   // get_name_2:  .field_0_   // get_Name:    .field_0_   // getName->1:  null   // getName->2:  null   // getName->N:  null   // ofs = -1 ord = 0 addr = 0
	getfield _parentScr   // get_name_1:  _parentScr   // get_name_2:  _parentScr   // get_Name:    _parentScr   // getName->1:  _parentScr   // getName->2:  _parentScr   // getName->N:  _parentScr   // ofs = -1 ord = 1 addr = -1
	iload_2 
	invokenonvirtual_lib .routine_4957 // pc=2
Label45:
	iinc 2 1
	goto Label23
Label47:
	return 
	}

}
