package com.whatsapp;

import android.text.TextUtils;
import java.io.File;
import java.util.ArrayList;
import java.util.Arrays;
import org.json.JSONArray;
import org.json.JSONException;
import org.json.JSONObject;

public class d8
{
  private static final File e;
  private static final String[] z;
  public ArrayList<w7> a;
  public int b;
  private String c;
  private String d;

  static
  {
    String[] arrayOfString = new String[22];
    char[] arrayOfChar1 = "Po��!Z\024ZI\002N\002O\0014\030".toCharArray();
    int i = arrayOfChar1.length;
    int j = 0;
    char[] arrayOfChar2;
    int i1;
    char[] arrayOfChar3;
    int i5;
    char[] arrayOfChar4;
    int i9;
    char[] arrayOfChar5;
    int i13;
    char[] arrayOfChar6;
    int i17;
    char[] arrayOfChar7;
    int i21;
    char[] arrayOfChar8;
    int i25;
    char[] arrayOfChar9;
    int i29;
    char[] arrayOfChar10;
    int i33;
    char[] arrayOfChar11;
    int i37;
    char[] arrayOfChar12;
    int i41;
    char[] arrayOfChar13;
    int i45;
    char[] arrayOfChar14;
    int i49;
    char[] arrayOfChar15;
    int i53;
    char[] arrayOfChar16;
    int i57;
    char[] arrayOfChar17;
    int i61;
    char[] arrayOfChar18;
    int i65;
    char[] arrayOfChar19;
    int i69;
    char[] arrayOfChar20;
    int i73;
    char[] arrayOfChar21;
    int i77;
    char[] arrayOfChar22;
    int i81;
    if (i <= j)
    {
      arrayOfString[0] = new String(arrayOfChar1).intern();
      arrayOfChar2 = "P}\007#V\024ZT".toCharArray();
      int n = arrayOfChar2.length;
      i1 = 0;
      if (n <= i1)
      {
        arrayOfString[1] = new String(arrayOfChar2).intern();
        arrayOfChar3 = "Q\n\025>M\032O\007lU\004A\035".toCharArray();
        int i4 = arrayOfChar3.length;
        i5 = 0;
        if (i4 > i5)
          break label1033;
        arrayOfString[2] = new String(arrayOfChar3).intern();
        arrayOfChar4 = "6J\006=K".toCharArray();
        int i8 = arrayOfChar4.length;
        i9 = 0;
        if (i8 > i9)
          break label1125;
        arrayOfString[3] = new String(arrayOfChar4).intern();
        arrayOfChar5 = "4A\036<J\031G\0200K\036A\035qY\026G\0374[[\016��%^\003[��l".toCharArray();
        int i12 = arrayOfChar5.length;
        i13 = 0;
        if (i12 > i13)
          break label1217;
        arrayOfString[4] = new String(arrayOfChar5).intern();
        arrayOfChar6 = "&[\026#F".toCharArray();
        int i16 = arrayOfChar6.length;
        i17 = 0;
        if (i16 > i17)
          break label1309;
        arrayOfString[5] = new String(arrayOfChar6).intern();
        arrayOfChar7 = "6[\0079P\005G\t0K\036A\035".toCharArray();
        int i20 = arrayOfChar7.length;
        i21 = 0;
        if (i20 > i21)
          break label1401;
        arrayOfString[6] = new String(arrayOfChar7).intern();
        arrayOfChar8 = "\037Z\007!LM\001\\0O\036��\0270K\026C\022#T\022Z]0E\002\\\026\\\030C\\\025^\003O]0L\037V\\\023V\031I\\\002Z\026\\\0209\020>C\0226ZH".toCharArray();
        int i24 = arrayOfChar8.length;
        i25 = 0;
        if (i24 > i25)
          break label1493;
        arrayOfString[7] = new String(arrayOfChar8).intern();
        arrayOfChar9 = "\"z5|\007".toCharArray();
        int i28 = arrayOfChar9.length;
        i29 = 0;
        if (i28 > i29)
          break label1585;
        arrayOfString[8] = new String(arrayOfChar9).intern();
        arrayOfChar10 = "5O��8\\W`6)\f%\0375\"h4\0279\007i=h `S:a+\037\0169v=\035h3kF0\017\017\032'ai:a7\003W9@\037+j\031l\022\007\f=a\020+\017A`6)\f%\0375\"h4\0279\007i=h `S:a+\037\0169v=\035h3kF0\017\017\032'ai:a7\003W9@\037+j\031l\022\007\f=a\020+\017J".toCharArray();
        int i32 = arrayOfChar10.length;
        i33 = 0;
        if (i32 > i33)
          break label1677;
        arrayOfString[9] = new String(arrayOfChar10).intern();
        arrayOfChar11 = "Q\n\007>OJ".toCharArray();
        int i36 = arrayOfChar11.length;
        i37 = 0;
        if (i36 > i37)
          break label1769;
        arrayOfString[10] = new String(arrayOfChar11).intern();
        arrayOfChar12 = ">C\0226Z1G\037%Z\005]".toCharArray();
        int i40 = arrayOfChar12.length;
        i41 = 0;
        if (i40 > i41)
          break label1861;
        arrayOfString[11] = new String(arrayOfChar12).intern();
        arrayOfChar13 = "\005K��$S\003]]=Z\031I\0079\027^\016Nq".toCharArray();
        int i44 = arrayOfChar13.length;
        i45 = 0;
        if (i44 > i45)
          break label1953;
        arrayOfString[12] = new String(arrayOfChar13).intern();
        arrayOfChar14 = "#F\006<]\031O\032=".toCharArray();
        int i48 = arrayOfChar14.length;
        i49 = 0;
        if (i48 > i49)
          break label2045;
        arrayOfString[13] = new String(arrayOfChar14).intern();
        arrayOfChar15 = "(q\0354G\003".toCharArray();
        int i52 = arrayOfChar15.length;
        i53 = 0;
        if (i52 > i53)
          break label2137;
        arrayOfString[14] = new String(arrayOfChar15).intern();
        arrayOfChar16 = "WG\0360X\022]".toCharArray();
        int i56 = arrayOfChar16.length;
        i57 = 0;
        if (i56 > i57)
          break label2229;
        arrayOfString[15] = new String(arrayOfChar16).intern();
        arrayOfChar17 = " G\027%W".toCharArray();
        int i60 = arrayOfChar17.length;
        i61 = 0;
        if (i60 > i61)
          break label2321;
        arrayOfString[16] = new String(arrayOfChar17).intern();
        arrayOfChar18 = ":K\0278^\"\\\037".toCharArray();
        int i64 = arrayOfChar18.length;
        i65 = 0;
        if (i64 > i65)
          break label2413;
        arrayOfString[17] = new String(arrayOfChar18).intern();
        arrayOfChar19 = "1G\0374l\036T\026".toCharArray();
        int i68 = arrayOfChar19.length;
        i69 = 0;
        if (i68 > i69)
          break label2505;
        arrayOfString[18] = new String(arrayOfChar19).intern();
        arrayOfChar20 = "?K\0326W\003".toCharArray();
        int i72 = arrayOfChar20.length;
        i73 = 0;
        if (i72 > i73)
          break label2597;
        arrayOfString[19] = new String(arrayOfChar20).intern();
        arrayOfChar21 = "\005K��$S\003]".toCharArray();
        int i76 = arrayOfChar21.length;
        i77 = 0;
        if (i76 > i77)
          break label2689;
        arrayOfString[20] = new String(arrayOfChar21).intern();
        arrayOfChar22 = "5G\0356".toCharArray();
        int i80 = arrayOfChar22.length;
        i81 = 0;
        if (i80 > i81)
          break label2781;
        arrayOfString[21] = new String(arrayOfChar22).intern();
        z = arrayOfString;
        e = new File(App.Mb.getCacheDir(), z[21]);
      }
    }
    else
    {
      int k = arrayOfChar1[j];
      int m;
      switch (j % 5)
      {
      default:
        m = 63;
      case 0:
      case 1:
      case 2:
      case 3:
      }
      while (true)
      {
        arrayOfChar1[j] = (char)(m ^ k);
        j++;
        break;
        m = 119;
        continue;
        m = 46;
        continue;
        m = 115;
        continue;
        m = 81;
      }
    }
    int i2 = arrayOfChar2[i1];
    int i3;
    switch (i1 % 5)
    {
    default:
      i3 = 63;
    case 0:
    case 1:
    case 2:
    case 3:
    }
    while (true)
    {
      arrayOfChar2[i1] = (char)(i3 ^ i2);
      i1++;
      break;
      i3 = 119;
      continue;
      i3 = 46;
      continue;
      i3 = 115;
      continue;
      i3 = 81;
    }
    label1033: int i6 = arrayOfChar3[i5];
    int i7;
    switch (i5 % 5)
    {
    default:
      i7 = 63;
    case 0:
    case 1:
    case 2:
    case 3:
    }
    while (true)
    {
      arrayOfChar3[i5] = (char)(i7 ^ i6);
      i5++;
      break;
      i7 = 119;
      continue;
      i7 = 46;
      continue;
      i7 = 115;
      continue;
      i7 = 81;
    }
    label1125: int i10 = arrayOfChar4[i9];
    int i11;
    switch (i9 % 5)
    {
    default:
      i11 = 63;
    case 0:
    case 1:
    case 2:
    case 3:
    }
    while (true)
    {
      arrayOfChar4[i9] = (char)(i11 ^ i10);
      i9++;
      break;
      i11 = 119;
      continue;
      i11 = 46;
      continue;
      i11 = 115;
      continue;
      i11 = 81;
    }
    label1217: int i14 = arrayOfChar5[i13];
    int i15;
    switch (i13 % 5)
    {
    default:
      i15 = 63;
    case 0:
    case 1:
    case 2:
    case 3:
    }
    while (true)
    {
      arrayOfChar5[i13] = (char)(i15 ^ i14);
      i13++;
      break;
      i15 = 119;
      continue;
      i15 = 46;
      continue;
      i15 = 115;
      continue;
      i15 = 81;
    }
    label1309: int i18 = arrayOfChar6[i17];
    int i19;
    switch (i17 % 5)
    {
    default:
      i19 = 63;
    case 0:
    case 1:
    case 2:
    case 3:
    }
    while (true)
    {
      arrayOfChar6[i17] = (char)(i19 ^ i18);
      i17++;
      break;
      i19 = 119;
      continue;
      i19 = 46;
      continue;
      i19 = 115;
      continue;
      i19 = 81;
    }
    label1401: int i22 = arrayOfChar7[i21];
    int i23;
    switch (i21 % 5)
    {
    default:
      i23 = 63;
    case 0:
    case 1:
    case 2:
    case 3:
    }
    while (true)
    {
      arrayOfChar7[i21] = (char)(i23 ^ i22);
      i21++;
      break;
      i23 = 119;
      continue;
      i23 = 46;
      continue;
      i23 = 115;
      continue;
      i23 = 81;
    }
    label1493: int i26 = arrayOfChar8[i25];
    int i27;
    switch (i25 % 5)
    {
    default:
      i27 = 63;
    case 0:
    case 1:
    case 2:
    case 3:
    }
    while (true)
    {
      arrayOfChar8[i25] = (char)(i27 ^ i26);
      i25++;
      break;
      i27 = 119;
      continue;
      i27 = 46;
      continue;
      i27 = 115;
      continue;
      i27 = 81;
    }
    label1585: int i30 = arrayOfChar9[i29];
    int i31;
    switch (i29 % 5)
    {
    default:
      i31 = 63;
    case 0:
    case 1:
    case 2:
    case 3:
    }
    while (true)
    {
      arrayOfChar9[i29] = (char)(i31 ^ i30);
      i29++;
      break;
      i31 = 119;
      continue;
      i31 = 46;
      continue;
      i31 = 115;
      continue;
      i31 = 81;
    }
    label1677: int i34 = arrayOfChar10[i33];
    int i35;
    switch (i33 % 5)
    {
    default:
      i35 = 63;
    case 0:
    case 1:
    case 2:
    case 3:
    }
    while (true)
    {
      arrayOfChar10[i33] = (char)(i35 ^ i34);
      i33++;
      break;
      i35 = 119;
      continue;
      i35 = 46;
      continue;
      i35 = 115;
      continue;
      i35 = 81;
    }
    label1769: int i38 = arrayOfChar11[i37];
    int i39;
    switch (i37 % 5)
    {
    default:
      i39 = 63;
    case 0:
    case 1:
    case 2:
    case 3:
    }
    while (true)
    {
      arrayOfChar11[i37] = (char)(i39 ^ i38);
      i37++;
      break;
      i39 = 119;
      continue;
      i39 = 46;
      continue;
      i39 = 115;
      continue;
      i39 = 81;
    }
    label1861: int i42 = arrayOfChar12[i41];
    int i43;
    switch (i41 % 5)
    {
    default:
      i43 = 63;
    case 0:
    case 1:
    case 2:
    case 3:
    }
    while (true)
    {
      arrayOfChar12[i41] = (char)(i43 ^ i42);
      i41++;
      break;
      i43 = 119;
      continue;
      i43 = 46;
      continue;
      i43 = 115;
      continue;
      i43 = 81;
    }
    label1953: int i46 = arrayOfChar13[i45];
    int i47;
    switch (i45 % 5)
    {
    default:
      i47 = 63;
    case 0:
    case 1:
    case 2:
    case 3:
    }
    while (true)
    {
      arrayOfChar13[i45] = (char)(i47 ^ i46);
      i45++;
      break;
      i47 = 119;
      continue;
      i47 = 46;
      continue;
      i47 = 115;
      continue;
      i47 = 81;
    }
    label2045: int i50 = arrayOfChar14[i49];
    int i51;
    switch (i49 % 5)
    {
    default:
      i51 = 63;
    case 0:
    case 1:
    case 2:
    case 3:
    }
    while (true)
    {
      arrayOfChar14[i49] = (char)(i51 ^ i50);
      i49++;
      break;
      i51 = 119;
      continue;
      i51 = 46;
      continue;
      i51 = 115;
      continue;
      i51 = 81;
    }
    label2137: int i54 = arrayOfChar15[i53];
    int i55;
    switch (i53 % 5)
    {
    default:
      i55 = 63;
    case 0:
    case 1:
    case 2:
    case 3:
    }
    while (true)
    {
      arrayOfChar15[i53] = (char)(i55 ^ i54);
      i53++;
      break;
      i55 = 119;
      continue;
      i55 = 46;
      continue;
      i55 = 115;
      continue;
      i55 = 81;
    }
    label2229: int i58 = arrayOfChar16[i57];
    int i59;
    switch (i57 % 5)
    {
    default:
      i59 = 63;
    case 0:
    case 1:
    case 2:
    case 3:
    }
    while (true)
    {
      arrayOfChar16[i57] = (char)(i59 ^ i58);
      i57++;
      break;
      i59 = 119;
      continue;
      i59 = 46;
      continue;
      i59 = 115;
      continue;
      i59 = 81;
    }
    label2321: int i62 = arrayOfChar17[i61];
    int i63;
    switch (i61 % 5)
    {
    default:
      i63 = 63;
    case 0:
    case 1:
    case 2:
    case 3:
    }
    while (true)
    {
      arrayOfChar17[i61] = (char)(i63 ^ i62);
      i61++;
      break;
      i63 = 119;
      continue;
      i63 = 46;
      continue;
      i63 = 115;
      continue;
      i63 = 81;
    }
    label2413: int i66 = arrayOfChar18[i65];
    int i67;
    switch (i65 % 5)
    {
    default:
      i67 = 63;
    case 0:
    case 1:
    case 2:
    case 3:
    }
    while (true)
    {
      arrayOfChar18[i65] = (char)(i67 ^ i66);
      i65++;
      break;
      i67 = 119;
      continue;
      i67 = 46;
      continue;
      i67 = 115;
      continue;
      i67 = 81;
    }
    label2505: int i70 = arrayOfChar19[i69];
    int i71;
    switch (i69 % 5)
    {
    default:
      i71 = 63;
    case 0:
    case 1:
    case 2:
    case 3:
    }
    while (true)
    {
      arrayOfChar19[i69] = (char)(i71 ^ i70);
      i69++;
      break;
      i71 = 119;
      continue;
      i71 = 46;
      continue;
      i71 = 115;
      continue;
      i71 = 81;
    }
    label2597: int i74 = arrayOfChar20[i73];
    int i75;
    switch (i73 % 5)
    {
    default:
      i75 = 63;
    case 0:
    case 1:
    case 2:
    case 3:
    }
    while (true)
    {
      arrayOfChar20[i73] = (char)(i75 ^ i74);
      i73++;
      break;
      i75 = 119;
      continue;
      i75 = 46;
      continue;
      i75 = 115;
      continue;
      i75 = 81;
    }
    label2689: int i78 = arrayOfChar21[i77];
    int i79;
    switch (i77 % 5)
    {
    default:
      i79 = 63;
    case 0:
    case 1:
    case 2:
    case 3:
    }
    while (true)
    {
      arrayOfChar21[i77] = (char)(i79 ^ i78);
      i77++;
      break;
      i79 = 119;
      continue;
      i79 = 46;
      continue;
      i79 = 115;
      continue;
      i79 = 81;
    }
    label2781: int i82 = arrayOfChar22[i81];
    int i83;
    switch (i81 % 5)
    {
    default:
      i83 = 63;
    case 0:
    case 1:
    case 2:
    case 3:
    }
    while (true)
    {
      arrayOfChar22[i81] = (char)(i83 ^ i82);
      i81++;
      break;
      i83 = 119;
      continue;
      i83 = 46;
      continue;
      i83 = 115;
      continue;
      i83 = 81;
    }
  }

  public d8(int paramInt, String paramString)
  {
    this.b = paramInt;
    this.c = paramString;
    e.mkdirs();
  }

  public d8(String paramString)
  {
    this(50, paramString);
  }

  public static void a()
  {
    boolean bool = DialogToastListActivity.f;
    File[] arrayOfFile = e.listFiles();
    if (arrayOfFile != null)
    {
      Arrays.sort(arrayOfFile, new e8());
      int i = 0;
      do
      {
        if (i >= arrayOfFile.length)
          break;
        File localFile = arrayOfFile[i];
        if ((i <= -16 + arrayOfFile.length) || (86400000L + localFile.lastModified() <= System.currentTimeMillis()))
          localFile.delete();
        i++;
      }
      while (!bool);
    }
  }

  private void a(JSONObject paramJSONObject)
    throws JSONException
  {
    JSONArray localJSONArray1 = null;
    boolean bool = DialogToastListActivity.f;
    this.d = null;
    while (true)
    {
      JSONArray localJSONArray2;
      int i;
      try
      {
        JSONObject localJSONObject3 = paramJSONObject.getJSONObject("d");
        if (localJSONObject3 != null)
        {
          localJSONArray1 = localJSONObject3.getJSONArray(z[20]);
          this.d = localJSONObject3.optString(z[14]);
        }
        localJSONArray2 = localJSONArray1;
        if (localJSONArray2 == null)
          return;
      }
      catch (JSONException localJSONException1)
      {
        localJSONArray2 = localJSONArray1;
        continue;
        g5.b(z[12] + localJSONArray2.length());
        i = 0;
      }
      label101: if (i < localJSONArray2.length());
      try
      {
        w7 localw7 = new w7();
        JSONObject localJSONObject1 = localJSONArray2.getJSONObject(i);
        localw7.b = localJSONObject1.getString(z[17]);
        localw7.c = localJSONObject1.getInt(z[18]);
        localw7.d = localJSONObject1.getInt(z[16]);
        localw7.e = localJSONObject1.getInt(z[19]);
        JSONObject localJSONObject2 = localJSONObject1.getJSONObject(z[13]);
        if (localJSONObject2 != null)
          localw7.a = localJSONObject2.getString(z[17]);
        if ((localw7.d >= 300) && (localw7.e >= 300) && (localw7.c <= 512000))
          this.a.add(localw7);
        label269: i++;
        if (!bool)
          break label101;
        g5.b(this.a.size() + z[15]);
      }
      catch (JSONException localJSONException2)
      {
        break label269;
      }
    }
  }

  // ERROR //
  public java.util.List<w7> b()
    throws java.io.IOException, JSONException
  {
    // Byte code:
    //   0: aconst_null
    //   1: astore_1
    //   2: invokestatic 229	com/whatsapp/d8:a	()V
    //   5: aload_0
    //   6: new 213	java/util/ArrayList
    //   9: dup
    //   10: invokespecial 230	java/util/ArrayList:<init>	()V
    //   13: putfield 211	com/whatsapp/d8:a	Ljava/util/ArrayList;
    //   16: new 213	java/util/ArrayList
    //   19: dup
    //   20: invokespecial 230	java/util/ArrayList:<init>	()V
    //   23: astore_2
    //   24: aload_2
    //   25: new 232	org/apache/http/message/BasicNameValuePair
    //   28: dup
    //   29: getstatic 78	com/whatsapp/d8:z	[Ljava/lang/String;
    //   32: iconst_5
    //   33: aaload
    //   34: new 164	java/lang/StringBuilder
    //   37: dup
    //   38: invokespecial 165	java/lang/StringBuilder:<init>	()V
    //   41: ldc 234
    //   43: invokevirtual 169	java/lang/StringBuilder:append	(Ljava/lang/String;)Ljava/lang/StringBuilder;
    //   46: aload_0
    //   47: getfield 102	com/whatsapp/d8:c	Ljava/lang/String;
    //   50: invokevirtual 237	java/lang/String:trim	()Ljava/lang/String;
    //   53: invokevirtual 169	java/lang/StringBuilder:append	(Ljava/lang/String;)Ljava/lang/StringBuilder;
    //   56: ldc 234
    //   58: invokevirtual 169	java/lang/StringBuilder:append	(Ljava/lang/String;)Ljava/lang/StringBuilder;
    //   61: invokevirtual 181	java/lang/StringBuilder:toString	()Ljava/lang/String;
    //   64: invokespecial 240	org/apache/http/message/BasicNameValuePair:<init>	(Ljava/lang/String;Ljava/lang/String;)V
    //   67: invokeinterface 243 2 0
    //   72: pop
    //   73: aload_2
    //   74: new 232	org/apache/http/message/BasicNameValuePair
    //   77: dup
    //   78: getstatic 78	com/whatsapp/d8:z	[Ljava/lang/String;
    //   81: iconst_3
    //   82: aaload
    //   83: getstatic 78	com/whatsapp/d8:z	[Ljava/lang/String;
    //   86: iconst_1
    //   87: aaload
    //   88: invokespecial 240	org/apache/http/message/BasicNameValuePair:<init>	(Ljava/lang/String;Ljava/lang/String;)V
    //   91: invokeinterface 243 2 0
    //   96: pop
    //   97: aload_2
    //   98: new 232	org/apache/http/message/BasicNameValuePair
    //   101: dup
    //   102: getstatic 78	com/whatsapp/d8:z	[Ljava/lang/String;
    //   105: bipush 11
    //   107: aaload
    //   108: getstatic 78	com/whatsapp/d8:z	[Ljava/lang/String;
    //   111: iconst_0
    //   112: aaload
    //   113: invokespecial 240	org/apache/http/message/BasicNameValuePair:<init>	(Ljava/lang/String;Ljava/lang/String;)V
    //   116: invokeinterface 243 2 0
    //   121: pop
    //   122: aload_0
    //   123: getfield 147	com/whatsapp/d8:d	Ljava/lang/String;
    //   126: invokestatic 249	android/text/TextUtils:isEmpty	(Ljava/lang/CharSequence;)Z
    //   129: ifeq +162 -> 291
    //   132: new 164	java/lang/StringBuilder
    //   135: dup
    //   136: invokespecial 165	java/lang/StringBuilder:<init>	()V
    //   139: getstatic 78	com/whatsapp/d8:z	[Ljava/lang/String;
    //   142: bipush 7
    //   144: aaload
    //   145: invokevirtual 169	java/lang/StringBuilder:append	(Ljava/lang/String;)Ljava/lang/StringBuilder;
    //   148: aload_2
    //   149: getstatic 78	com/whatsapp/d8:z	[Ljava/lang/String;
    //   152: bipush 8
    //   154: aaload
    //   155: invokestatic 255	org/apache/http/client/utils/URLEncodedUtils:format	(Ljava/util/List;Ljava/lang/String;)Ljava/lang/String;
    //   158: invokevirtual 169	java/lang/StringBuilder:append	(Ljava/lang/String;)Ljava/lang/StringBuilder;
    //   161: getstatic 78	com/whatsapp/d8:z	[Ljava/lang/String;
    //   164: bipush 10
    //   166: aaload
    //   167: invokevirtual 169	java/lang/StringBuilder:append	(Ljava/lang/String;)Ljava/lang/StringBuilder;
    //   170: aload_0
    //   171: getfield 100	com/whatsapp/d8:b	I
    //   174: invokevirtual 178	java/lang/StringBuilder:append	(I)Ljava/lang/StringBuilder;
    //   177: invokevirtual 181	java/lang/StringBuilder:toString	()Ljava/lang/String;
    //   180: astore 6
    //   182: aload 6
    //   184: invokestatic 259	com/whatsapp/mh:b	(Ljava/lang/String;)Ljava/lang/String;
    //   187: astore 7
    //   189: new 80	java/io/File
    //   192: dup
    //   193: getstatic 95	com/whatsapp/d8:e	Ljava/io/File;
    //   196: aload 7
    //   198: invokevirtual 260	java/lang/String:toString	()Ljava/lang/String;
    //   201: invokespecial 93	java/io/File:<init>	(Ljava/io/File;Ljava/lang/String;)V
    //   204: astore 8
    //   206: aload 8
    //   208: invokevirtual 263	java/io/File:exists	()Z
    //   211: ifeq +175 -> 386
    //   214: ldc2_w 129
    //   217: aload 8
    //   219: invokevirtual 134	java/io/File:lastModified	()J
    //   222: ladd
    //   223: invokestatic 139	java/lang/System:currentTimeMillis	()J
    //   226: lcmp
    //   227: ifle +159 -> 386
    //   230: new 265	java/io/ObjectInputStream
    //   233: dup
    //   234: new 267	java/io/FileInputStream
    //   237: dup
    //   238: aload 8
    //   240: invokespecial 270	java/io/FileInputStream:<init>	(Ljava/io/File;)V
    //   243: invokespecial 273	java/io/ObjectInputStream:<init>	(Ljava/io/InputStream;)V
    //   246: astore 24
    //   248: aload 24
    //   250: invokevirtual 277	java/io/ObjectInputStream:readObject	()Ljava/lang/Object;
    //   253: checkcast 20	java/lang/String
    //   256: astore 20
    //   258: aload 24
    //   260: ifnull +8 -> 268
    //   263: aload 24
    //   265: invokevirtual 280	java/io/ObjectInputStream:close	()V
    //   268: aload 20
    //   270: ifnull +16 -> 286
    //   273: aload_0
    //   274: new 150	org/json/JSONObject
    //   277: dup
    //   278: aload 20
    //   280: invokespecial 282	org/json/JSONObject:<init>	(Ljava/lang/String;)V
    //   283: invokespecial 284	com/whatsapp/d8:a	(Lorg/json/JSONObject;)V
    //   286: aload_0
    //   287: getfield 211	com/whatsapp/d8:a	Ljava/util/ArrayList;
    //   290: areturn
    //   291: aload_0
    //   292: getfield 147	com/whatsapp/d8:d	Ljava/lang/String;
    //   295: astore 6
    //   297: goto -115 -> 182
    //   300: astore 25
    //   302: aconst_null
    //   303: astore 24
    //   305: aload 25
    //   307: invokestatic 287	com/whatsapp/g5:d	(Ljava/lang/Throwable;)V
    //   310: aload 24
    //   312: ifnull +403 -> 715
    //   315: aload 24
    //   317: invokevirtual 280	java/io/ObjectInputStream:close	()V
    //   320: aconst_null
    //   321: astore 20
    //   323: goto -55 -> 268
    //   326: astore 28
    //   328: aconst_null
    //   329: astore 20
    //   331: goto -63 -> 268
    //   334: astore 29
    //   336: aconst_null
    //   337: astore 24
    //   339: aload 29
    //   341: invokestatic 287	com/whatsapp/g5:d	(Ljava/lang/Throwable;)V
    //   344: aload 24
    //   346: ifnull +369 -> 715
    //   349: aload 24
    //   351: invokevirtual 280	java/io/ObjectInputStream:close	()V
    //   354: aconst_null
    //   355: astore 20
    //   357: goto -89 -> 268
    //   360: astore 30
    //   362: aconst_null
    //   363: astore 20
    //   365: goto -97 -> 268
    //   368: astore 26
    //   370: aconst_null
    //   371: astore 24
    //   373: aload 24
    //   375: ifnull +8 -> 383
    //   378: aload 24
    //   380: invokevirtual 280	java/io/ObjectInputStream:close	()V
    //   383: aload 26
    //   385: athrow
    //   386: aload 8
    //   388: invokevirtual 142	java/io/File:delete	()Z
    //   391: pop
    //   392: new 289	org/apache/http/client/methods/HttpGet
    //   395: dup
    //   396: new 164	java/lang/StringBuilder
    //   399: dup
    //   400: invokespecial 165	java/lang/StringBuilder:<init>	()V
    //   403: aload 6
    //   405: invokevirtual 169	java/lang/StringBuilder:append	(Ljava/lang/String;)Ljava/lang/StringBuilder;
    //   408: getstatic 78	com/whatsapp/d8:z	[Ljava/lang/String;
    //   411: iconst_2
    //   412: aaload
    //   413: invokevirtual 169	java/lang/StringBuilder:append	(Ljava/lang/String;)Ljava/lang/StringBuilder;
    //   416: invokevirtual 181	java/lang/StringBuilder:toString	()Ljava/lang/String;
    //   419: invokespecial 290	org/apache/http/client/methods/HttpGet:<init>	(Ljava/lang/String;)V
    //   422: astore 10
    //   424: aload 10
    //   426: getstatic 78	com/whatsapp/d8:z	[Ljava/lang/String;
    //   429: bipush 6
    //   431: aaload
    //   432: getstatic 78	com/whatsapp/d8:z	[Ljava/lang/String;
    //   435: bipush 9
    //   437: aaload
    //   438: invokevirtual 293	org/apache/http/client/methods/HttpGet:addHeader	(Ljava/lang/String;Ljava/lang/String;)V
    //   441: new 295	org/apache/http/params/BasicHttpParams
    //   444: dup
    //   445: invokespecial 296	org/apache/http/params/BasicHttpParams:<init>	()V
    //   448: astore 11
    //   450: aload 11
    //   452: sipush 15000
    //   455: invokestatic 302	org/apache/http/params/HttpConnectionParams:setConnectionTimeout	(Lorg/apache/http/params/HttpParams;I)V
    //   458: aload 11
    //   460: sipush 30000
    //   463: invokestatic 305	org/apache/http/params/HttpConnectionParams:setSoTimeout	(Lorg/apache/http/params/HttpParams;I)V
    //   466: aload 11
    //   468: getstatic 308	com/whatsapp/App:n	Ljava/lang/String;
    //   471: invokestatic 314	org/apache/http/params/HttpProtocolParams:setUserAgent	(Lorg/apache/http/params/HttpParams;Ljava/lang/String;)V
    //   474: new 316	org/apache/http/impl/client/DefaultHttpClient
    //   477: dup
    //   478: aload 11
    //   480: invokespecial 319	org/apache/http/impl/client/DefaultHttpClient:<init>	(Lorg/apache/http/params/HttpParams;)V
    //   483: aload 10
    //   485: invokevirtual 323	org/apache/http/impl/client/DefaultHttpClient:execute	(Lorg/apache/http/client/methods/HttpUriRequest;)Lorg/apache/http/HttpResponse;
    //   488: astore 12
    //   490: aload 12
    //   492: invokeinterface 329 1 0
    //   497: invokeinterface 334 1 0
    //   502: istore 13
    //   504: iload 13
    //   506: sipush 200
    //   509: if_icmpne +116 -> 625
    //   512: aload 12
    //   514: invokeinterface 338 1 0
    //   519: invokestatic 343	org/apache/http/util/EntityUtils:toString	(Lorg/apache/http/HttpEntity;)Ljava/lang/String;
    //   522: astore 14
    //   524: new 345	java/io/ObjectOutputStream
    //   527: dup
    //   528: new 347	java/io/FileOutputStream
    //   531: dup
    //   532: aload 8
    //   534: invokespecial 348	java/io/FileOutputStream:<init>	(Ljava/io/File;)V
    //   537: invokespecial 351	java/io/ObjectOutputStream:<init>	(Ljava/io/OutputStream;)V
    //   540: astore 15
    //   542: aload 15
    //   544: aload 14
    //   546: invokevirtual 355	java/io/ObjectOutputStream:writeObject	(Ljava/lang/Object;)V
    //   549: aload 15
    //   551: ifnull +8 -> 559
    //   554: aload 15
    //   556: invokevirtual 356	java/io/ObjectOutputStream:close	()V
    //   559: aload 14
    //   561: astore 20
    //   563: goto -295 -> 268
    //   566: astore 16
    //   568: aload 16
    //   570: invokestatic 287	com/whatsapp/g5:d	(Ljava/lang/Throwable;)V
    //   573: aload_1
    //   574: ifnull -15 -> 559
    //   577: aload_1
    //   578: invokevirtual 356	java/io/ObjectOutputStream:close	()V
    //   581: goto -22 -> 559
    //   584: astore 19
    //   586: goto -27 -> 559
    //   589: astore 21
    //   591: aload 21
    //   593: invokestatic 287	com/whatsapp/g5:d	(Ljava/lang/Throwable;)V
    //   596: aload_1
    //   597: ifnull -38 -> 559
    //   600: aload_1
    //   601: invokevirtual 356	java/io/ObjectOutputStream:close	()V
    //   604: goto -45 -> 559
    //   607: astore 22
    //   609: goto -50 -> 559
    //   612: astore 17
    //   614: aload_1
    //   615: ifnull +7 -> 622
    //   618: aload_1
    //   619: invokevirtual 356	java/io/ObjectOutputStream:close	()V
    //   622: aload 17
    //   624: athrow
    //   625: new 223	java/io/IOException
    //   628: dup
    //   629: new 164	java/lang/StringBuilder
    //   632: dup
    //   633: invokespecial 165	java/lang/StringBuilder:<init>	()V
    //   636: getstatic 78	com/whatsapp/d8:z	[Ljava/lang/String;
    //   639: iconst_4
    //   640: aaload
    //   641: invokevirtual 169	java/lang/StringBuilder:append	(Ljava/lang/String;)Ljava/lang/StringBuilder;
    //   644: iload 13
    //   646: invokevirtual 178	java/lang/StringBuilder:append	(I)Ljava/lang/StringBuilder;
    //   649: invokevirtual 181	java/lang/StringBuilder:toString	()Ljava/lang/String;
    //   652: invokespecial 357	java/io/IOException:<init>	(Ljava/lang/String;)V
    //   655: athrow
    //   656: astore 31
    //   658: goto -390 -> 268
    //   661: astore 27
    //   663: goto -280 -> 383
    //   666: astore 23
    //   668: goto -109 -> 559
    //   671: astore 18
    //   673: goto -51 -> 622
    //   676: astore 17
    //   678: aload 15
    //   680: astore_1
    //   681: goto -67 -> 614
    //   684: astore 21
    //   686: aload 15
    //   688: astore_1
    //   689: goto -98 -> 591
    //   692: astore 16
    //   694: aload 15
    //   696: astore_1
    //   697: goto -129 -> 568
    //   700: astore 26
    //   702: goto -329 -> 373
    //   705: astore 29
    //   707: goto -368 -> 339
    //   710: astore 25
    //   712: goto -407 -> 305
    //   715: aconst_null
    //   716: astore 20
    //   718: goto -450 -> 268
    //
    // Exception table:
    //   from	to	target	type
    //   230	248	300	java/io/IOException
    //   315	320	326	java/io/IOException
    //   230	248	334	java/lang/ClassNotFoundException
    //   349	354	360	java/io/IOException
    //   230	248	368	finally
    //   524	542	566	java/io/FileNotFoundException
    //   577	581	584	java/io/IOException
    //   524	542	589	java/io/IOException
    //   600	604	607	java/io/IOException
    //   524	542	612	finally
    //   568	573	612	finally
    //   591	596	612	finally
    //   263	268	656	java/io/IOException
    //   378	383	661	java/io/IOException
    //   554	559	666	java/io/IOException
    //   618	622	671	java/io/IOException
    //   542	549	676	finally
    //   542	549	684	java/io/IOException
    //   542	549	692	java/io/FileNotFoundException
    //   248	258	700	finally
    //   305	310	700	finally
    //   339	344	700	finally
    //   248	258	705	java/lang/ClassNotFoundException
    //   248	258	710	java/io/IOException
  }

  public boolean c()
  {
    if (!TextUtils.isEmpty(this.d));
    for (boolean bool = true; ; bool = false)
      return bool;
  }

  public String d()
  {
    return this.c;
  }
}

/* Location:           C:\Users\Jaap\Downloads\Code\WhatsApp-2.8.4278_dex2jar.jar
 * Qualified Name:     com.whatsapp.d8
 * JD-Core Version:    0.6.1
 */