package com.whatsapp;

import android.app.Activity;
import android.content.ContentResolver;
import android.content.Intent;
import android.graphics.Bitmap.CompressFormat;
import android.graphics.BitmapFactory;
import android.graphics.BitmapFactory.Options;
import android.net.Uri;
import android.os.Parcelable;
import android.provider.MediaStore.Images.Media;
import com.whatsapp.wallpaper.CropImage;
import java.io.File;
import java.io.IOException;
import java.io.InputStream;
import java.util.ArrayList;

public class iz
{
  private static final String[] z;

  static
  {
    String[] arrayOfString = new String[33];
    char[] arrayOfChar1 = "<E+N".toCharArray();
    int i = arrayOfChar1.length;
    int j = 0;
    char[] arrayOfChar2;
    int i1;
    char[] arrayOfChar3;
    int i5;
    char[] arrayOfChar4;
    int i9;
    char[] arrayOfChar5;
    int i13;
    char[] arrayOfChar6;
    int i17;
    char[] arrayOfChar7;
    int i21;
    char[] arrayOfChar8;
    int i25;
    char[] arrayOfChar9;
    int i29;
    char[] arrayOfChar10;
    int i33;
    char[] arrayOfChar11;
    int i37;
    char[] arrayOfChar12;
    int i41;
    char[] arrayOfChar13;
    int i45;
    char[] arrayOfChar14;
    int i49;
    char[] arrayOfChar15;
    int i53;
    char[] arrayOfChar16;
    int i57;
    char[] arrayOfChar17;
    int i61;
    char[] arrayOfChar18;
    int i65;
    char[] arrayOfChar19;
    int i69;
    char[] arrayOfChar20;
    int i73;
    char[] arrayOfChar21;
    int i77;
    char[] arrayOfChar22;
    int i81;
    char[] arrayOfChar23;
    int i85;
    char[] arrayOfChar24;
    int i89;
    char[] arrayOfChar25;
    int i93;
    char[] arrayOfChar26;
    int i97;
    char[] arrayOfChar27;
    int i101;
    char[] arrayOfChar28;
    int i105;
    char[] arrayOfChar29;
    int i109;
    char[] arrayOfChar30;
    int i113;
    char[] arrayOfChar31;
    int i117;
    char[] arrayOfChar32;
    int i121;
    char[] arrayOfChar33;
    int i125;
    if (i <= j)
    {
      arrayOfString[0] = new String(arrayOfChar1).intern();
      arrayOfChar2 = "8Z4\\:$M2T5'\007(_=,X3U''\0078[=&G/\0327-K4^6h\\3O>*".toCharArray();
      int n = arrayOfChar2.length;
      i1 = 0;
      if (n <= i1)
      {
        arrayOfString[1] = new String(arrayOfChar2).intern();
        arrayOfChar3 = "8Z4\\:$M2T5'\007(_=,X3U''".toCharArray();
        int i4 = arrayOfChar3.length;
        i5 = 0;
        if (i4 > i5)
          break label1429;
        arrayOfString[2] = new String(arrayOfChar3).intern();
        arrayOfChar4 = "8Z4\\:$M2T5'\007(_=,X3U''\0078[=&G/\032 )^>\032' ]6X".toCharArray();
        int i8 = arrayOfChar4.length;
        i9 = 0;
        if (i8 > i9)
          break label1521;
        arrayOfString[3] = new String(arrayOfChar4).intern();
        arrayOfChar5 = "<E+S".toCharArray();
        int i12 = arrayOfChar5.length;
        i13 = 0;
        if (i12 > i13)
          break label1613;
        arrayOfString[4] = new String(arrayOfChar5).intern();
        arrayOfChar6 = "']/J&<n4H>)\\".toCharArray();
        int i16 = arrayOfChar6.length;
        i17 = 0;
        if (i16 > i17)
          break label1705;
        arrayOfString[5] = new String(arrayOfChar6).intern();
        arrayOfChar7 = "']/J&<".toCharArray();
        int i20 = arrayOfChar7.length;
        i21 = 0;
        if (i20 > i21)
          break label1797;
        arrayOfString[6] = new String(arrayOfChar7).intern();
        arrayOfChar8 = "']/J&<p".toCharArray();
        int i24 = arrayOfChar8.length;
        i25 = 0;
        if (i24 > i25)
          break label1889;
        arrayOfString[7] = new String(arrayOfChar8).intern();
        arrayOfChar9 = "']/J&<q".toCharArray();
        int i28 = arrayOfChar9.length;
        i29 = 0;
        if (i28 > i29)
          break label1981;
        arrayOfString[8] = new String(arrayOfChar9).intern();
        arrayOfChar10 = ")[+_0<p".toCharArray();
        int i32 = arrayOfChar10.length;
        i33 = 0;
        if (i32 > i33)
          break label2073;
        arrayOfString[9] = new String(arrayOfChar10).intern();
        arrayOfChar11 = ")[+_0<q".toCharArray();
        int i36 = arrayOfChar11.length;
        i37 = 0;
        if (i36 > i37)
          break label2165;
        arrayOfString[10] = new String(arrayOfChar11).intern();
        arrayOfChar12 = "%A5y!'X".toCharArray();
        int i40 = arrayOfChar12.length;
        i41 = 0;
        if (i40 > i41)
          break label2257;
        arrayOfString[11] = new String(arrayOfChar12).intern();
        arrayOfChar13 = ";K:V6".toCharArray();
        int i44 = arrayOfChar13.length;
        i45 = 0;
        if (i44 > i45)
          break label2349;
        arrayOfString[12] = new String(arrayOfChar13).intern();
        arrayOfChar14 = "%I#|:$M\bS)-".toCharArray();
        int i48 = arrayOfChar14.length;
        i49 = 0;
        if (i48 > i49)
          break label2441;
        arrayOfString[13] = new String(arrayOfChar14).intern();
        arrayOfChar15 = ";K:V6\035X\022\\\035-M?_7".toCharArray();
        int i52 = arrayOfChar15.length;
        i53 = 0;
        if (i52 > i53)
          break label2533;
        arrayOfString[14] = new String(arrayOfChar15).intern();
        arrayOfChar16 = "+Z4J\0211g.N#=\\\bS)-".toCharArray();
        int i56 = arrayOfChar16.length;
        i57 = 0;
        if (i56 > i57)
          break label2625;
        arrayOfString[15] = new String(arrayOfChar16).intern();
        arrayOfChar17 = "<E+J".toCharArray();
        int i60 = arrayOfChar17.length;
        i61 = 0;
        if (i60 > i61)
          break label2717;
        arrayOfString[16] = new String(arrayOfChar17).intern();
        arrayOfChar18 = "!Gv_!:G)".toCharArray();
        int i64 = arrayOfChar18.length;
        i65 = 0;
        if (i64 > i65)
          break label2809;
        arrayOfString[17] = new String(arrayOfChar18).intern();
        arrayOfChar19 = "&GvI#)K>".toCharArray();
        int i68 = arrayOfChar19.length;
        i69 = 0;
        if (i68 > i69)
          break label2901;
        arrayOfString[18] = new String(arrayOfChar19).intern();
        arrayOfChar20 = "8Z4\\:$M2T5'\007:Y'!^2N*:M(\025='\005(J2+M".toCharArray();
        int i72 = arrayOfChar20.length;
        i73 = 0;
        if (i72 > i73)
          break label2993;
        arrayOfString[19] = new String(arrayOfChar20).intern();
        arrayOfChar21 = "8Z4\\:$M2T5'\007:Y'!^2N*:M(\0255)A7\025='\\v[~!E:]6".toCharArray();
        int i76 = arrayOfChar21.length;
        i77 = 0;
        if (i76 > i77)
          break label3085;
        arrayOfString[20] = new String(arrayOfChar21).intern();
        arrayOfChar22 = "8Z4\\:$M2T5'\007:Y'!^2N*:M(\0255)A7\025?'I?\027:%I<_".toCharArray();
        int i80 = arrayOfChar22.length;
        i81 = 0;
        if (i80 > i81)
          break label3177;
        arrayOfString[21] = new String(arrayOfChar22).intern();
        arrayOfChar23 = "8Z4\\:$M2T5'\007:Y'!^2N*:M(\025<'Ev_!:G)".toCharArray();
        int i84 = arrayOfChar23.length;
        i85 = 0;
        if (i84 > i85)
          break label3269;
        arrayOfString[22] = new String(arrayOfChar23).intern();
        arrayOfChar24 = "&G/\0272eA6[4-".toCharArray();
        int i88 = arrayOfChar24.length;
        i89 = 0;
        if (i88 > i89)
          break label3361;
        arrayOfString[23] = new String(arrayOfChar24).intern();
        arrayOfChar25 = "-Z)U!eG4W".toCharArray();
        int i92 = arrayOfChar25.length;
        i93 = 0;
        if (i92 > i93)
          break label3453;
        arrayOfString[24] = new String(arrayOfChar25).intern();
        arrayOfChar26 = "9]>H*".toCharArray();
        int i96 = arrayOfChar26.length;
        i97 = 0;
        if (i96 > i97)
          break label3545;
        arrayOfString[25] = new String(arrayOfChar26).intern();
        arrayOfChar27 = ")F?H<!LuS=<M5N}-P/H2fa\025s\007\001i\027e\032\006|\036t\007\033".toCharArray();
        int i100 = arrayOfChar27.length;
        i101 = 0;
        if (i100 > i101)
          break label3637;
        arrayOfString[26] = new String(arrayOfChar27).intern();
        arrayOfChar28 = ")F?H<!LuS=<M5N})K/S<&\006\013s\020\003".toCharArray();
        int i104 = arrayOfChar28.length;
        i105 = 0;
        if (i104 > i105)
          break label3729;
        arrayOfString[27] = new String(arrayOfChar28).intern();
        arrayOfChar29 = ")F?H<!LuW6,A:\0242+\\2U=fa\026{\024\rw\030{\003\034}\t".toCharArray();
        int i108 = arrayOfChar29.length;
        i109 = 0;
        if (i108 > i109)
          break label3821;
        arrayOfString[28] = new String(arrayOfChar29).intern();
        arrayOfChar30 = "+G6\024$ I/I28XuS=<M5N})K/S<&\006\t��\r|\004j\001\007n\022v\026\027x\023u\007\007".toCharArray();
        int i112 = arrayOfChar30.length;
        i113 = 0;
        if (i112 > i113)
          break label3913;
        arrayOfString[29] = new String(arrayOfChar30).intern();
        arrayOfChar31 = "!E:]6g\002".toCharArray();
        int i116 = arrayOfChar31.length;
        i117 = 0;
        if (i116 > i117)
          break label4005;
        arrayOfString[30] = new String(arrayOfChar31).intern();
        arrayOfChar32 = "+G6\024$ I/I28XuS=<M5N})K/S<&\006\b\022\032k\023e\003��g\017u".toCharArray();
        int i120 = arrayOfChar32.length;
        i121 = 0;
        if (i120 > i121)
          break label4097;
        arrayOfString[31] = new String(arrayOfChar32).intern();
        arrayOfChar33 = "+G6\024$ I/I28XuS=<M5N})K/S<&\006\t��\r|\004}\001\007}\013e\003��g\017u".toCharArray();
        int i124 = arrayOfChar33.length;
        i125 = 0;
        if (i124 > i125)
          break label4189;
        arrayOfString[32] = new String(arrayOfChar33).intern();
        z = arrayOfString;
      }
    }
    else
    {
      int k = arrayOfChar1[j];
      int m;
      switch (j % 5)
      {
      default:
        m = 83;
      case 0:
      case 1:
      case 2:
      case 3:
      }
      while (true)
      {
        arrayOfChar1[j] = (char)(m ^ k);
        j++;
        break;
        m = 72;
        continue;
        m = 40;
        continue;
        m = 91;
        continue;
        m = 58;
      }
    }
    int i2 = arrayOfChar2[i1];
    int i3;
    switch (i1 % 5)
    {
    default:
      i3 = 83;
    case 0:
    case 1:
    case 2:
    case 3:
    }
    while (true)
    {
      arrayOfChar2[i1] = (char)(i3 ^ i2);
      i1++;
      break;
      i3 = 72;
      continue;
      i3 = 40;
      continue;
      i3 = 91;
      continue;
      i3 = 58;
    }
    label1429: int i6 = arrayOfChar3[i5];
    int i7;
    switch (i5 % 5)
    {
    default:
      i7 = 83;
    case 0:
    case 1:
    case 2:
    case 3:
    }
    while (true)
    {
      arrayOfChar3[i5] = (char)(i7 ^ i6);
      i5++;
      break;
      i7 = 72;
      continue;
      i7 = 40;
      continue;
      i7 = 91;
      continue;
      i7 = 58;
    }
    label1521: int i10 = arrayOfChar4[i9];
    int i11;
    switch (i9 % 5)
    {
    default:
      i11 = 83;
    case 0:
    case 1:
    case 2:
    case 3:
    }
    while (true)
    {
      arrayOfChar4[i9] = (char)(i11 ^ i10);
      i9++;
      break;
      i11 = 72;
      continue;
      i11 = 40;
      continue;
      i11 = 91;
      continue;
      i11 = 58;
    }
    label1613: int i14 = arrayOfChar5[i13];
    int i15;
    switch (i13 % 5)
    {
    default:
      i15 = 83;
    case 0:
    case 1:
    case 2:
    case 3:
    }
    while (true)
    {
      arrayOfChar5[i13] = (char)(i15 ^ i14);
      i13++;
      break;
      i15 = 72;
      continue;
      i15 = 40;
      continue;
      i15 = 91;
      continue;
      i15 = 58;
    }
    label1705: int i18 = arrayOfChar6[i17];
    int i19;
    switch (i17 % 5)
    {
    default:
      i19 = 83;
    case 0:
    case 1:
    case 2:
    case 3:
    }
    while (true)
    {
      arrayOfChar6[i17] = (char)(i19 ^ i18);
      i17++;
      break;
      i19 = 72;
      continue;
      i19 = 40;
      continue;
      i19 = 91;
      continue;
      i19 = 58;
    }
    label1797: int i22 = arrayOfChar7[i21];
    int i23;
    switch (i21 % 5)
    {
    default:
      i23 = 83;
    case 0:
    case 1:
    case 2:
    case 3:
    }
    while (true)
    {
      arrayOfChar7[i21] = (char)(i23 ^ i22);
      i21++;
      break;
      i23 = 72;
      continue;
      i23 = 40;
      continue;
      i23 = 91;
      continue;
      i23 = 58;
    }
    label1889: int i26 = arrayOfChar8[i25];
    int i27;
    switch (i25 % 5)
    {
    default:
      i27 = 83;
    case 0:
    case 1:
    case 2:
    case 3:
    }
    while (true)
    {
      arrayOfChar8[i25] = (char)(i27 ^ i26);
      i25++;
      break;
      i27 = 72;
      continue;
      i27 = 40;
      continue;
      i27 = 91;
      continue;
      i27 = 58;
    }
    label1981: int i30 = arrayOfChar9[i29];
    int i31;
    switch (i29 % 5)
    {
    default:
      i31 = 83;
    case 0:
    case 1:
    case 2:
    case 3:
    }
    while (true)
    {
      arrayOfChar9[i29] = (char)(i31 ^ i30);
      i29++;
      break;
      i31 = 72;
      continue;
      i31 = 40;
      continue;
      i31 = 91;
      continue;
      i31 = 58;
    }
    label2073: int i34 = arrayOfChar10[i33];
    int i35;
    switch (i33 % 5)
    {
    default:
      i35 = 83;
    case 0:
    case 1:
    case 2:
    case 3:
    }
    while (true)
    {
      arrayOfChar10[i33] = (char)(i35 ^ i34);
      i33++;
      break;
      i35 = 72;
      continue;
      i35 = 40;
      continue;
      i35 = 91;
      continue;
      i35 = 58;
    }
    label2165: int i38 = arrayOfChar11[i37];
    int i39;
    switch (i37 % 5)
    {
    default:
      i39 = 83;
    case 0:
    case 1:
    case 2:
    case 3:
    }
    while (true)
    {
      arrayOfChar11[i37] = (char)(i39 ^ i38);
      i37++;
      break;
      i39 = 72;
      continue;
      i39 = 40;
      continue;
      i39 = 91;
      continue;
      i39 = 58;
    }
    label2257: int i42 = arrayOfChar12[i41];
    int i43;
    switch (i41 % 5)
    {
    default:
      i43 = 83;
    case 0:
    case 1:
    case 2:
    case 3:
    }
    while (true)
    {
      arrayOfChar12[i41] = (char)(i43 ^ i42);
      i41++;
      break;
      i43 = 72;
      continue;
      i43 = 40;
      continue;
      i43 = 91;
      continue;
      i43 = 58;
    }
    label2349: int i46 = arrayOfChar13[i45];
    int i47;
    switch (i45 % 5)
    {
    default:
      i47 = 83;
    case 0:
    case 1:
    case 2:
    case 3:
    }
    while (true)
    {
      arrayOfChar13[i45] = (char)(i47 ^ i46);
      i45++;
      break;
      i47 = 72;
      continue;
      i47 = 40;
      continue;
      i47 = 91;
      continue;
      i47 = 58;
    }
    label2441: int i50 = arrayOfChar14[i49];
    int i51;
    switch (i49 % 5)
    {
    default:
      i51 = 83;
    case 0:
    case 1:
    case 2:
    case 3:
    }
    while (true)
    {
      arrayOfChar14[i49] = (char)(i51 ^ i50);
      i49++;
      break;
      i51 = 72;
      continue;
      i51 = 40;
      continue;
      i51 = 91;
      continue;
      i51 = 58;
    }
    label2533: int i54 = arrayOfChar15[i53];
    int i55;
    switch (i53 % 5)
    {
    default:
      i55 = 83;
    case 0:
    case 1:
    case 2:
    case 3:
    }
    while (true)
    {
      arrayOfChar15[i53] = (char)(i55 ^ i54);
      i53++;
      break;
      i55 = 72;
      continue;
      i55 = 40;
      continue;
      i55 = 91;
      continue;
      i55 = 58;
    }
    label2625: int i58 = arrayOfChar16[i57];
    int i59;
    switch (i57 % 5)
    {
    default:
      i59 = 83;
    case 0:
    case 1:
    case 2:
    case 3:
    }
    while (true)
    {
      arrayOfChar16[i57] = (char)(i59 ^ i58);
      i57++;
      break;
      i59 = 72;
      continue;
      i59 = 40;
      continue;
      i59 = 91;
      continue;
      i59 = 58;
    }
    label2717: int i62 = arrayOfChar17[i61];
    int i63;
    switch (i61 % 5)
    {
    default:
      i63 = 83;
    case 0:
    case 1:
    case 2:
    case 3:
    }
    while (true)
    {
      arrayOfChar17[i61] = (char)(i63 ^ i62);
      i61++;
      break;
      i63 = 72;
      continue;
      i63 = 40;
      continue;
      i63 = 91;
      continue;
      i63 = 58;
    }
    label2809: int i66 = arrayOfChar18[i65];
    int i67;
    switch (i65 % 5)
    {
    default:
      i67 = 83;
    case 0:
    case 1:
    case 2:
    case 3:
    }
    while (true)
    {
      arrayOfChar18[i65] = (char)(i67 ^ i66);
      i65++;
      break;
      i67 = 72;
      continue;
      i67 = 40;
      continue;
      i67 = 91;
      continue;
      i67 = 58;
    }
    label2901: int i70 = arrayOfChar19[i69];
    int i71;
    switch (i69 % 5)
    {
    default:
      i71 = 83;
    case 0:
    case 1:
    case 2:
    case 3:
    }
    while (true)
    {
      arrayOfChar19[i69] = (char)(i71 ^ i70);
      i69++;
      break;
      i71 = 72;
      continue;
      i71 = 40;
      continue;
      i71 = 91;
      continue;
      i71 = 58;
    }
    label2993: int i74 = arrayOfChar20[i73];
    int i75;
    switch (i73 % 5)
    {
    default:
      i75 = 83;
    case 0:
    case 1:
    case 2:
    case 3:
    }
    while (true)
    {
      arrayOfChar20[i73] = (char)(i75 ^ i74);
      i73++;
      break;
      i75 = 72;
      continue;
      i75 = 40;
      continue;
      i75 = 91;
      continue;
      i75 = 58;
    }
    label3085: int i78 = arrayOfChar21[i77];
    int i79;
    switch (i77 % 5)
    {
    default:
      i79 = 83;
    case 0:
    case 1:
    case 2:
    case 3:
    }
    while (true)
    {
      arrayOfChar21[i77] = (char)(i79 ^ i78);
      i77++;
      break;
      i79 = 72;
      continue;
      i79 = 40;
      continue;
      i79 = 91;
      continue;
      i79 = 58;
    }
    label3177: int i82 = arrayOfChar22[i81];
    int i83;
    switch (i81 % 5)
    {
    default:
      i83 = 83;
    case 0:
    case 1:
    case 2:
    case 3:
    }
    while (true)
    {
      arrayOfChar22[i81] = (char)(i83 ^ i82);
      i81++;
      break;
      i83 = 72;
      continue;
      i83 = 40;
      continue;
      i83 = 91;
      continue;
      i83 = 58;
    }
    label3269: int i86 = arrayOfChar23[i85];
    int i87;
    switch (i85 % 5)
    {
    default:
      i87 = 83;
    case 0:
    case 1:
    case 2:
    case 3:
    }
    while (true)
    {
      arrayOfChar23[i85] = (char)(i87 ^ i86);
      i85++;
      break;
      i87 = 72;
      continue;
      i87 = 40;
      continue;
      i87 = 91;
      continue;
      i87 = 58;
    }
    label3361: int i90 = arrayOfChar24[i89];
    int i91;
    switch (i89 % 5)
    {
    default:
      i91 = 83;
    case 0:
    case 1:
    case 2:
    case 3:
    }
    while (true)
    {
      arrayOfChar24[i89] = (char)(i91 ^ i90);
      i89++;
      break;
      i91 = 72;
      continue;
      i91 = 40;
      continue;
      i91 = 91;
      continue;
      i91 = 58;
    }
    label3453: int i94 = arrayOfChar25[i93];
    int i95;
    switch (i93 % 5)
    {
    default:
      i95 = 83;
    case 0:
    case 1:
    case 2:
    case 3:
    }
    while (true)
    {
      arrayOfChar25[i93] = (char)(i95 ^ i94);
      i93++;
      break;
      i95 = 72;
      continue;
      i95 = 40;
      continue;
      i95 = 91;
      continue;
      i95 = 58;
    }
    label3545: int i98 = arrayOfChar26[i97];
    int i99;
    switch (i97 % 5)
    {
    default:
      i99 = 83;
    case 0:
    case 1:
    case 2:
    case 3:
    }
    while (true)
    {
      arrayOfChar26[i97] = (char)(i99 ^ i98);
      i97++;
      break;
      i99 = 72;
      continue;
      i99 = 40;
      continue;
      i99 = 91;
      continue;
      i99 = 58;
    }
    label3637: int i102 = arrayOfChar27[i101];
    int i103;
    switch (i101 % 5)
    {
    default:
      i103 = 83;
    case 0:
    case 1:
    case 2:
    case 3:
    }
    while (true)
    {
      arrayOfChar27[i101] = (char)(i103 ^ i102);
      i101++;
      break;
      i103 = 72;
      continue;
      i103 = 40;
      continue;
      i103 = 91;
      continue;
      i103 = 58;
    }
    label3729: int i106 = arrayOfChar28[i105];
    int i107;
    switch (i105 % 5)
    {
    default:
      i107 = 83;
    case 0:
    case 1:
    case 2:
    case 3:
    }
    while (true)
    {
      arrayOfChar28[i105] = (char)(i107 ^ i106);
      i105++;
      break;
      i107 = 72;
      continue;
      i107 = 40;
      continue;
      i107 = 91;
      continue;
      i107 = 58;
    }
    label3821: int i110 = arrayOfChar29[i109];
    int i111;
    switch (i109 % 5)
    {
    default:
      i111 = 83;
    case 0:
    case 1:
    case 2:
    case 3:
    }
    while (true)
    {
      arrayOfChar29[i109] = (char)(i111 ^ i110);
      i109++;
      break;
      i111 = 72;
      continue;
      i111 = 40;
      continue;
      i111 = 91;
      continue;
      i111 = 58;
    }
    label3913: int i114 = arrayOfChar30[i113];
    int i115;
    switch (i113 % 5)
    {
    default:
      i115 = 83;
    case 0:
    case 1:
    case 2:
    case 3:
    }
    while (true)
    {
      arrayOfChar30[i113] = (char)(i115 ^ i114);
      i113++;
      break;
      i115 = 72;
      continue;
      i115 = 40;
      continue;
      i115 = 91;
      continue;
      i115 = 58;
    }
    label4005: int i118 = arrayOfChar31[i117];
    int i119;
    switch (i117 % 5)
    {
    default:
      i119 = 83;
    case 0:
    case 1:
    case 2:
    case 3:
    }
    while (true)
    {
      arrayOfChar31[i117] = (char)(i119 ^ i118);
      i117++;
      break;
      i119 = 72;
      continue;
      i119 = 40;
      continue;
      i119 = 91;
      continue;
      i119 = 58;
    }
    label4097: int i122 = arrayOfChar32[i121];
    int i123;
    switch (i121 % 5)
    {
    default:
      i123 = 83;
    case 0:
    case 1:
    case 2:
    case 3:
    }
    while (true)
    {
      arrayOfChar32[i121] = (char)(i123 ^ i122);
      i121++;
      break;
      i123 = 72;
      continue;
      i123 = 40;
      continue;
      i123 = 91;
      continue;
      i123 = 58;
    }
    label4189: int i126 = arrayOfChar33[i125];
    int i127;
    switch (i125 % 5)
    {
    default:
      i127 = 83;
    case 0:
    case 1:
    case 2:
    case 3:
    }
    while (true)
    {
      arrayOfChar33[i125] = (char)(i127 ^ i126);
      i125++;
      break;
      i127 = 72;
      continue;
      i127 = 40;
      continue;
      i127 = 91;
      continue;
      i127 = 58;
    }
  }

  public static File a()
  {
    return App.c(z[4]);
  }

  public static void a(Intent paramIntent, lr paramlr)
  {
    boolean bool = DialogToastListActivity.f;
    if (paramIntent.getBooleanExtra(z[24], false))
    {
      g5.d(z[22]);
      App.a(paramlr, App.Mb.getString(2131296980));
      if (!bool);
    }
    else if (paramIntent.getBooleanExtra(z[18], false))
    {
      g5.d(z[19]);
      App.a(paramlr, App.Mb.getString(2131296987));
      if (!bool);
    }
    else if (paramIntent.getBooleanExtra(z[17], false))
    {
      g5.d(z[21]);
      App.a(paramlr, App.Mb.getString(2131296988));
      if (!bool);
    }
    else if (paramIntent.getBooleanExtra(z[23], false))
    {
      g5.d(z[20]);
      App.a(paramlr, App.Mb.getString(2131296982));
    }
  }

  public static void a(Intent paramIntent, zq paramzq, Activity paramActivity, int paramInt, lr paramlr)
  {
    Uri localUri = null;
    if (paramIntent != null)
      localUri = paramIntent.getData();
    if ((localUri == null) && (a().exists()))
      localUri = Uri.fromFile(a());
    b().delete();
    if (localUri != null)
    {
      try
      {
        InputStream localInputStream = App.ib.openInputStream(localUri);
        BitmapFactory.Options localOptions = new BitmapFactory.Options();
        localOptions.inJustDecodeBounds = true;
        BitmapFactory.decodeStream(localInputStream, null, localOptions);
        localInputStream.close();
        if ((localOptions.outWidth <= 0) || (localOptions.outHeight <= 0))
        {
          paramlr.a(2131296982);
        }
        else if ((localOptions.outWidth < 192) || (localOptions.outHeight < 192))
        {
          String str = App.Z.a(2131427340, 192);
          Object[] arrayOfObject = new Object[1];
          arrayOfObject[0] = Integer.valueOf(192);
          paramlr.c(String.format(str, arrayOfObject));
        }
      }
      catch (IOException localIOException)
      {
        paramlr.a(2131296988);
      }
      Intent localIntent = new Intent(paramActivity, CropImage.class);
      localIntent.putExtra(z[7], 640);
      localIntent.putExtra(z[8], 640);
      localIntent.putExtra(z[11], 192);
      localIntent.putExtra(z[9], 1);
      localIntent.putExtra(z[10], 1);
      localIntent.putExtra(z[12], true);
      localIntent.putExtra(z[14], false);
      localIntent.putExtra(z[15], false);
      localIntent.putExtra(z[13], 61440);
      localIntent.setData(localUri);
      localIntent.putExtra(z[6], Uri.fromFile(b()));
      localIntent.putExtra(z[5], Bitmap.CompressFormat.JPEG.toString());
      paramActivity.startActivityForResult(localIntent, paramInt);
      if (!DialogToastListActivity.f);
    }
    else
    {
      paramlr.a(2131296982);
    }
  }

  public static void a(zq paramzq, Activity paramActivity, int paramInt)
  {
    boolean bool = DialogToastListActivity.f;
    Intent localIntent1 = new Intent(z[27], MediaStore.Images.Media.INTERNAL_CONTENT_URI);
    localIntent1.setType(z[30]);
    a().delete();
    Uri localUri = Uri.fromFile(a());
    Intent localIntent2 = new Intent(z[28]).putExtra(z[6], localUri);
    Intent localIntent3 = new Intent(z[31]).putExtra(z[6], localUri).putExtra(z[25], paramzq.h);
    String str;
    if (paramzq.o())
    {
      localIntent4 = new Intent(z[32], null);
      str = paramActivity.getString(2131296632);
      if (!bool);
    }
    else
    {
      localIntent4 = new Intent(z[29], null);
      str = paramActivity.getString(2131296633);
    }
    ArrayList localArrayList = new ArrayList();
    if (paramzq.h().exists())
    {
      a.a(localIntent1, localArrayList);
      a.a(localIntent2, localArrayList);
      if (paramzq.o())
      {
        localArrayList.add(localIntent3);
        if (!bool);
      }
    }
    else
    {
      if (paramzq.o())
      {
        a.a(localIntent1, localArrayList);
        a.a(localIntent2, localArrayList);
        if (!bool)
          break label312;
      }
      a.a(localIntent1, localArrayList);
    }
    label312: for (Intent localIntent4 = localIntent2; ; localIntent4 = localIntent3)
    {
      Intent localIntent5 = Intent.createChooser(localIntent4, str);
      if (!localArrayList.isEmpty())
        localIntent5.putExtra(z[26], (Parcelable[])localArrayList.toArray(new Intent[0]));
      paramActivity.startActivityForResult(localIntent5, paramInt);
      return;
    }
  }

  // ERROR //
  public static boolean a(zq paramzq, Activity paramActivity)
  {
    // Byte code:
    //   0: invokestatic 322	com/whatsapp/App:sb	()Z
    //   3: ifeq +455 -> 458
    //   6: invokestatic 156	com/whatsapp/iz:b	()Ljava/io/File;
    //   9: astore 5
    //   11: new 324	java/io/FileInputStream
    //   14: dup
    //   15: aload 5
    //   17: invokespecial 327	java/io/FileInputStream:<init>	(Ljava/io/File;)V
    //   20: astore 6
    //   22: aload 5
    //   24: invokevirtual 331	java/io/File:length	()J
    //   27: l2i
    //   28: newarray byte
    //   30: astore 7
    //   32: aload 6
    //   34: aload 7
    //   36: invokevirtual 335	java/io/FileInputStream:read	([B)I
    //   39: pop
    //   40: new 171	android/graphics/BitmapFactory$Options
    //   43: dup
    //   44: invokespecial 173	android/graphics/BitmapFactory$Options:<init>	()V
    //   47: astore 9
    //   49: aload 9
    //   51: iconst_1
    //   52: putfield 176	android/graphics/BitmapFactory$Options:inJustDecodeBounds	Z
    //   55: aload 7
    //   57: iconst_0
    //   58: aload 7
    //   60: arraylength
    //   61: aload 9
    //   63: invokestatic 339	android/graphics/BitmapFactory:decodeByteArray	([BIILandroid/graphics/BitmapFactory$Options;)Landroid/graphics/Bitmap;
    //   66: pop
    //   67: aload 9
    //   69: aload 9
    //   71: getfield 191	android/graphics/BitmapFactory$Options:outWidth	I
    //   74: aload 9
    //   76: getfield 194	android/graphics/BitmapFactory$Options:outHeight	I
    //   79: invokestatic 345	java/lang/Math:min	(II)I
    //   82: bipush 96
    //   84: idiv
    //   85: putfield 348	android/graphics/BitmapFactory$Options:inSampleSize	I
    //   88: aload 9
    //   90: iconst_0
    //   91: putfield 176	android/graphics/BitmapFactory$Options:inJustDecodeBounds	Z
    //   94: aload 9
    //   96: iconst_0
    //   97: putfield 351	android/graphics/BitmapFactory$Options:inScaled	Z
    //   100: aload 9
    //   102: iconst_1
    //   103: putfield 354	android/graphics/BitmapFactory$Options:inDither	Z
    //   106: getstatic 359	android/os/Build$VERSION:SDK_INT	I
    //   109: bipush 10
    //   111: if_icmplt +9 -> 120
    //   114: aload 9
    //   116: iconst_1
    //   117: putfield 362	android/graphics/BitmapFactory$Options:inPreferQualityOverSpeed	Z
    //   120: aload 7
    //   122: iconst_0
    //   123: aload 7
    //   125: arraylength
    //   126: aload 9
    //   128: invokestatic 339	android/graphics/BitmapFactory:decodeByteArray	([BIILandroid/graphics/BitmapFactory$Options;)Landroid/graphics/Bitmap;
    //   131: astore 11
    //   133: aload 11
    //   135: ifnull +213 -> 348
    //   138: aload 11
    //   140: invokevirtual 368	android/graphics/Bitmap:getConfig	()Landroid/graphics/Bitmap$Config;
    //   143: astore 12
    //   145: aload 12
    //   147: ifnonnull +8 -> 155
    //   150: getstatic 374	android/graphics/Bitmap$Config:ARGB_8888	Landroid/graphics/Bitmap$Config;
    //   153: astore 12
    //   155: bipush 96
    //   157: bipush 96
    //   159: aload 12
    //   161: invokestatic 378	android/graphics/Bitmap:createBitmap	(IILandroid/graphics/Bitmap$Config;)Landroid/graphics/Bitmap;
    //   164: astore 13
    //   166: new 380	android/graphics/Canvas
    //   169: dup
    //   170: aload 13
    //   172: invokespecial 383	android/graphics/Canvas:<init>	(Landroid/graphics/Bitmap;)V
    //   175: astore 14
    //   177: new 385	android/graphics/Paint
    //   180: dup
    //   181: invokespecial 386	android/graphics/Paint:<init>	()V
    //   184: astore 15
    //   186: aload 15
    //   188: iconst_1
    //   189: invokevirtual 390	android/graphics/Paint:setAntiAlias	(Z)V
    //   192: aload 15
    //   194: iconst_1
    //   195: invokevirtual 393	android/graphics/Paint:setFilterBitmap	(Z)V
    //   198: aload 15
    //   200: iconst_1
    //   201: invokevirtual 396	android/graphics/Paint:setDither	(Z)V
    //   204: aload 14
    //   206: aload 11
    //   208: new 398	android/graphics/Rect
    //   211: dup
    //   212: iconst_0
    //   213: iconst_0
    //   214: aload 11
    //   216: invokevirtual 402	android/graphics/Bitmap:getWidth	()I
    //   219: aload 11
    //   221: invokevirtual 405	android/graphics/Bitmap:getHeight	()I
    //   224: invokespecial 408	android/graphics/Rect:<init>	(IIII)V
    //   227: new 398	android/graphics/Rect
    //   230: dup
    //   231: iconst_0
    //   232: iconst_0
    //   233: bipush 96
    //   235: bipush 96
    //   237: invokespecial 408	android/graphics/Rect:<init>	(IIII)V
    //   240: aload 15
    //   242: invokevirtual 412	android/graphics/Canvas:drawBitmap	(Landroid/graphics/Bitmap;Landroid/graphics/Rect;Landroid/graphics/Rect;Landroid/graphics/Paint;)V
    //   245: aload 11
    //   247: invokevirtual 415	android/graphics/Bitmap:recycle	()V
    //   250: new 417	java/io/FileOutputStream
    //   253: dup
    //   254: invokestatic 419	com/whatsapp/iz:c	()Ljava/io/File;
    //   257: invokespecial 420	java/io/FileOutputStream:<init>	(Ljava/io/File;)V
    //   260: astore 16
    //   262: aload 16
    //   264: ifnull +16 -> 280
    //   267: aload 13
    //   269: getstatic 246	android/graphics/Bitmap$CompressFormat:JPEG	Landroid/graphics/Bitmap$CompressFormat;
    //   272: bipush 75
    //   274: aload 16
    //   276: invokevirtual 424	android/graphics/Bitmap:compress	(Landroid/graphics/Bitmap$CompressFormat;ILjava/io/OutputStream;)Z
    //   279: pop
    //   280: aload 16
    //   282: invokestatic 429	com/whatsapp/d5:a	(Ljava/io/Closeable;)V
    //   285: aload 13
    //   287: invokevirtual 415	android/graphics/Bitmap:recycle	()V
    //   290: invokestatic 419	com/whatsapp/iz:c	()Ljava/io/File;
    //   293: astore 17
    //   295: new 324	java/io/FileInputStream
    //   298: dup
    //   299: aload 17
    //   301: invokespecial 327	java/io/FileInputStream:<init>	(Ljava/io/File;)V
    //   304: astore 18
    //   306: aload 17
    //   308: invokevirtual 331	java/io/File:length	()J
    //   311: l2i
    //   312: newarray byte
    //   314: astore 19
    //   316: aload 18
    //   318: aload 19
    //   320: invokevirtual 335	java/io/FileInputStream:read	([B)I
    //   323: pop
    //   324: new 431	com/whatsapp/hz
    //   327: dup
    //   328: aload_0
    //   329: getfield 433	com/whatsapp/zq:b	Ljava/lang/String;
    //   332: aload 7
    //   334: aload 19
    //   336: invokespecial 436	com/whatsapp/hz:<init>	(Ljava/lang/String;[B[B)V
    //   339: invokestatic 439	com/whatsapp/App:a	(Lcom/whatsapp/hz;)V
    //   342: getstatic 105	com/whatsapp/DialogToastListActivity:f	Z
    //   345: ifeq +129 -> 474
    //   348: aload_1
    //   349: invokevirtual 443	android/app/Activity:getBaseContext	()Landroid/content/Context;
    //   352: ldc 131
    //   354: iconst_0
    //   355: invokestatic 446	com/whatsapp/App:a	(Landroid/content/Context;II)V
    //   358: getstatic 90	com/whatsapp/iz:z	[Ljava/lang/String;
    //   361: iconst_1
    //   362: aaload
    //   363: invokestatic 117	com/whatsapp/g5:d	(Ljava/lang/String;)V
    //   366: iconst_0
    //   367: istore_2
    //   368: iload_2
    //   369: ireturn
    //   370: astore 21
    //   372: aconst_null
    //   373: astore 16
    //   375: getstatic 90	com/whatsapp/iz:z	[Ljava/lang/String;
    //   378: iconst_3
    //   379: aaload
    //   380: aload 21
    //   382: invokestatic 449	com/whatsapp/g5:b	(Ljava/lang/String;Ljava/lang/Throwable;)V
    //   385: aload 16
    //   387: invokestatic 429	com/whatsapp/d5:a	(Ljava/io/Closeable;)V
    //   390: goto -105 -> 285
    //   393: astore 4
    //   395: aload_1
    //   396: invokevirtual 443	android/app/Activity:getBaseContext	()Landroid/content/Context;
    //   399: ldc 131
    //   401: iconst_0
    //   402: invokestatic 446	com/whatsapp/App:a	(Landroid/content/Context;II)V
    //   405: getstatic 90	com/whatsapp/iz:z	[Ljava/lang/String;
    //   408: iconst_2
    //   409: aaload
    //   410: aload 4
    //   412: invokestatic 449	com/whatsapp/g5:b	(Ljava/lang/String;Ljava/lang/Throwable;)V
    //   415: iconst_0
    //   416: istore_2
    //   417: goto -49 -> 368
    //   420: astore 22
    //   422: aconst_null
    //   423: astore 16
    //   425: aload 16
    //   427: invokestatic 429	com/whatsapp/d5:a	(Ljava/io/Closeable;)V
    //   430: aload 22
    //   432: athrow
    //   433: astore_3
    //   434: aload_1
    //   435: invokevirtual 443	android/app/Activity:getBaseContext	()Landroid/content/Context;
    //   438: ldc 131
    //   440: iconst_0
    //   441: invokestatic 446	com/whatsapp/App:a	(Landroid/content/Context;II)V
    //   444: getstatic 90	com/whatsapp/iz:z	[Ljava/lang/String;
    //   447: iconst_2
    //   448: aaload
    //   449: aload_3
    //   450: invokestatic 449	com/whatsapp/g5:b	(Ljava/lang/String;Ljava/lang/Throwable;)V
    //   453: iconst_0
    //   454: istore_2
    //   455: goto -87 -> 368
    //   458: aload_1
    //   459: invokevirtual 443	android/app/Activity:getBaseContext	()Landroid/content/Context;
    //   462: ldc_w 450
    //   465: iconst_0
    //   466: invokestatic 446	com/whatsapp/App:a	(Landroid/content/Context;II)V
    //   469: iconst_0
    //   470: istore_2
    //   471: goto -103 -> 368
    //   474: iconst_1
    //   475: istore_2
    //   476: goto -108 -> 368
    //   479: astore 22
    //   481: goto -56 -> 425
    //   484: astore 21
    //   486: goto -111 -> 375
    //
    // Exception table:
    //   from	to	target	type
    //   250	262	370	java/io/IOException
    //   6	250	393	java/io/FileNotFoundException
    //   280	366	393	java/io/FileNotFoundException
    //   385	390	393	java/io/FileNotFoundException
    //   425	433	393	java/io/FileNotFoundException
    //   250	262	420	finally
    //   6	250	433	java/io/IOException
    //   280	366	433	java/io/IOException
    //   385	390	433	java/io/IOException
    //   425	433	433	java/io/IOException
    //   267	280	479	finally
    //   375	385	479	finally
    //   267	280	484	java/io/IOException
  }

  public static File b()
  {
    return App.c(z[16]);
  }

  public static void b(zq paramzq, Activity paramActivity)
  {
    App.a(new hz(paramzq.b, null, null));
  }

  public static File c()
  {
    return App.c(z[0]);
  }
}

/* Location:           C:\Users\Jaap\Downloads\Code\WhatsApp-2.8.4278_dex2jar.jar
 * Qualified Name:     com.whatsapp.iz
 * JD-Core Version:    0.6.1
 */