package com.whatsapp;

import android.content.Context;
import android.net.Uri;
import java.io.File;
import java.io.IOException;

public class k4
{
  private static String a;
  private static String b;
  private static String c;
  private static String d;
  private static volatile boolean e;
  private static final String[] z;

  static
  {
    String[] arrayOfString = new String[16];
    char[] arrayOfChar1 = " \026ibPmN\"sE%X,`NfS\"s��iS6{Dd\03377DoP&cE*X,`NfS\"s\001".toCharArray();
    int i = arrayOfChar1.length;
    int j = 0;
    char[] arrayOfChar2;
    int i1;
    char[] arrayOfChar3;
    int i5;
    char[] arrayOfChar4;
    int i9;
    char[] arrayOfChar5;
    int i13;
    char[] arrayOfChar6;
    int i17;
    char[] arrayOfChar7;
    int i21;
    char[] arrayOfChar8;
    int i25;
    char[] arrayOfChar9;
    int i29;
    char[] arrayOfChar10;
    int i33;
    char[] arrayOfChar11;
    int i37;
    char[] arrayOfChar12;
    int i41;
    char[] arrayOfChar13;
    int i45;
    char[] arrayOfChar14;
    int i49;
    char[] arrayOfChar15;
    int i53;
    char[] arrayOfChar16;
    int i57;
    if (i <= j)
    {
      arrayOfString[0] = new String(arrayOfChar1).intern();
      arrayOfChar2 = " \026ibPmN\"sE%X,`NfS\"s\017nS4yLe]'7CeI/sN-HcsEfY7r��nS4yLe]'6".toCharArray();
      int n = arrayOfChar2.length;
      i1 = 0;
      if (n <= i1)
      {
        arrayOfString[1] = new String(arrayOfChar2).intern();
        arrayOfChar3 = " \026ibPmN\"sE%X,`NfS\"s\017nS4yLe]'7CeI/sN-HceEd].r��nS4yLe]'6".toCharArray();
        int i4 = arrayOfChar3.length;
        i5 = 0;
        if (i4 > i5)
          break label785;
        arrayOfString[2] = new String(arrayOfChar3).intern();
        arrayOfChar4 = " \026ibPmN\"sE%U-dTkP/7CeI/sN-HcsEfY7r��nS4yLe]'6".toCharArray();
        int i8 = arrayOfChar4.length;
        i9 = 0;
        if (i8 > i9)
          break label877;
        arrayOfString[3] = new String(arrayOfChar4).intern();
        arrayOfChar5 = "]T\"cSKL39AzW".toCharArray();
        int i12 = arrayOfChar5.length;
        i13 = 0;
        if (i12 > i13)
          break label969;
        arrayOfString[4] = new String(arrayOfChar5).intern();
        arrayOfChar6 = "]T\"cSKL39DeK-{OkX".toCharArray();
        int i16 = arrayOfChar6.length;
        i17 = 0;
        if (i16 > i17)
          break label1061;
        arrayOfString[5] = new String(arrayOfChar6).intern();
        arrayOfChar7 = "]T\"cSKL39Uz[1vDo".toCharArray();
        int i20 = arrayOfChar7.length;
        i21 = 0;
        if (i20 > i21)
          break label1153;
        arrayOfString[6] = new String(arrayOfChar7).intern();
        arrayOfChar8 = " \026ibPmN\"sE%U-dTkP/7CeI/sN-HcsEfY7r��cR0cAfPb".toCharArray();
        int i24 = arrayOfChar8.length;
        i25 = 0;
        if (i24 > i25)
          break label1245;
        arrayOfString[7] = new String(arrayOfChar8).intern();
        arrayOfChar9 = " \026ibPmN\"sE%X,`NfS\"s��iS6{Dd\03377RoR\"zE*X,`NfS\"s\001".toCharArray();
        int i28 = arrayOfChar9.length;
        i29 = 0;
        if (i28 > i29)
          break label1337;
        arrayOfString[8] = new String(arrayOfChar9).intern();
        arrayOfChar10 = "g]1|E~\006l8DoH\"~Ly\003*s\035iS.9Wb]7dAzL".toCharArray();
        int i32 = arrayOfChar10.length;
        i33 = 0;
        if (i32 > i33)
          break label1429;
        arrayOfString[9] = new String(arrayOfChar10).intern();
        arrayOfChar11 = "]T\"cSKL39CaO6z".toCharArray();
        int i36 = arrayOfChar11.length;
        i37 = 0;
        if (i36 > i37)
          break label1521;
        arrayOfString[10] = new String(arrayOfChar11).intern();
        arrayOfChar12 = "]T\"cSKL39VoN0~Od".toCharArray();
        int i40 = arrayOfChar12.length;
        i41 = 0;
        if (i40 > i41)
          break label1613;
        arrayOfString[11] = new String(arrayOfChar12).intern();
        arrayOfChar13 = "L$eAnYldON r��".toCharArray();
        int i44 = arrayOfChar13.length;
        i45 = 0;
        if (i44 > i45)
          break label1705;
        arrayOfString[12] = new String(arrayOfChar13).intern();
        arrayOfChar14 = "bH7g\032%\0234`W$K+vTy]3g\016iS.8AdX1xIn\023".toCharArray();
        int i48 = arrayOfChar14.length;
        i49 = 0;
        if (i48 > i49)
          break label1797;
        arrayOfString[13] = new String(arrayOfChar14).intern();
        arrayOfChar15 = "]T\"cSKL39H~Q/".toCharArray();
        int i52 = arrayOfChar15.length;
        i53 = 0;
        if (i52 > i53)
          break label1889;
        arrayOfString[14] = new String(arrayOfChar15).intern();
        arrayOfChar16 = "L$eAnYldEdH*yEf\023%vIf".toCharArray();
        int i56 = arrayOfChar16.length;
        i57 = 0;
        if (i56 > i57)
          break label1981;
        arrayOfString[15] = new String(arrayOfChar16).intern();
        z = arrayOfString;
        e = false;
      }
    }
    else
    {
      int k = arrayOfChar1[j];
      int m;
      switch (j % 5)
      {
      default:
        m = 32;
      case 0:
      case 1:
      case 2:
      case 3:
      }
      while (true)
      {
        arrayOfChar1[j] = (char)(m ^ k);
        j++;
        break;
        m = 10;
        continue;
        m = 60;
        continue;
        m = 67;
        continue;
        m = 23;
      }
    }
    int i2 = arrayOfChar2[i1];
    int i3;
    switch (i1 % 5)
    {
    default:
      i3 = 32;
    case 0:
    case 1:
    case 2:
    case 3:
    }
    while (true)
    {
      arrayOfChar2[i1] = (char)(i3 ^ i2);
      i1++;
      break;
      i3 = 10;
      continue;
      i3 = 60;
      continue;
      i3 = 67;
      continue;
      i3 = 23;
    }
    label785: int i6 = arrayOfChar3[i5];
    int i7;
    switch (i5 % 5)
    {
    default:
      i7 = 32;
    case 0:
    case 1:
    case 2:
    case 3:
    }
    while (true)
    {
      arrayOfChar3[i5] = (char)(i7 ^ i6);
      i5++;
      break;
      i7 = 10;
      continue;
      i7 = 60;
      continue;
      i7 = 67;
      continue;
      i7 = 23;
    }
    label877: int i10 = arrayOfChar4[i9];
    int i11;
    switch (i9 % 5)
    {
    default:
      i11 = 32;
    case 0:
    case 1:
    case 2:
    case 3:
    }
    while (true)
    {
      arrayOfChar4[i9] = (char)(i11 ^ i10);
      i9++;
      break;
      i11 = 10;
      continue;
      i11 = 60;
      continue;
      i11 = 67;
      continue;
      i11 = 23;
    }
    label969: int i14 = arrayOfChar5[i13];
    int i15;
    switch (i13 % 5)
    {
    default:
      i15 = 32;
    case 0:
    case 1:
    case 2:
    case 3:
    }
    while (true)
    {
      arrayOfChar5[i13] = (char)(i15 ^ i14);
      i13++;
      break;
      i15 = 10;
      continue;
      i15 = 60;
      continue;
      i15 = 67;
      continue;
      i15 = 23;
    }
    label1061: int i18 = arrayOfChar6[i17];
    int i19;
    switch (i17 % 5)
    {
    default:
      i19 = 32;
    case 0:
    case 1:
    case 2:
    case 3:
    }
    while (true)
    {
      arrayOfChar6[i17] = (char)(i19 ^ i18);
      i17++;
      break;
      i19 = 10;
      continue;
      i19 = 60;
      continue;
      i19 = 67;
      continue;
      i19 = 23;
    }
    label1153: int i22 = arrayOfChar7[i21];
    int i23;
    switch (i21 % 5)
    {
    default:
      i23 = 32;
    case 0:
    case 1:
    case 2:
    case 3:
    }
    while (true)
    {
      arrayOfChar7[i21] = (char)(i23 ^ i22);
      i21++;
      break;
      i23 = 10;
      continue;
      i23 = 60;
      continue;
      i23 = 67;
      continue;
      i23 = 23;
    }
    label1245: int i26 = arrayOfChar8[i25];
    int i27;
    switch (i25 % 5)
    {
    default:
      i27 = 32;
    case 0:
    case 1:
    case 2:
    case 3:
    }
    while (true)
    {
      arrayOfChar8[i25] = (char)(i27 ^ i26);
      i25++;
      break;
      i27 = 10;
      continue;
      i27 = 60;
      continue;
      i27 = 67;
      continue;
      i27 = 23;
    }
    label1337: int i30 = arrayOfChar9[i29];
    int i31;
    switch (i29 % 5)
    {
    default:
      i31 = 32;
    case 0:
    case 1:
    case 2:
    case 3:
    }
    while (true)
    {
      arrayOfChar9[i29] = (char)(i31 ^ i30);
      i29++;
      break;
      i31 = 10;
      continue;
      i31 = 60;
      continue;
      i31 = 67;
      continue;
      i31 = 23;
    }
    label1429: int i34 = arrayOfChar10[i33];
    int i35;
    switch (i33 % 5)
    {
    default:
      i35 = 32;
    case 0:
    case 1:
    case 2:
    case 3:
    }
    while (true)
    {
      arrayOfChar10[i33] = (char)(i35 ^ i34);
      i33++;
      break;
      i35 = 10;
      continue;
      i35 = 60;
      continue;
      i35 = 67;
      continue;
      i35 = 23;
    }
    label1521: int i38 = arrayOfChar11[i37];
    int i39;
    switch (i37 % 5)
    {
    default:
      i39 = 32;
    case 0:
    case 1:
    case 2:
    case 3:
    }
    while (true)
    {
      arrayOfChar11[i37] = (char)(i39 ^ i38);
      i37++;
      break;
      i39 = 10;
      continue;
      i39 = 60;
      continue;
      i39 = 67;
      continue;
      i39 = 23;
    }
    label1613: int i42 = arrayOfChar12[i41];
    int i43;
    switch (i41 % 5)
    {
    default:
      i43 = 32;
    case 0:
    case 1:
    case 2:
    case 3:
    }
    while (true)
    {
      arrayOfChar12[i41] = (char)(i43 ^ i42);
      i41++;
      break;
      i43 = 10;
      continue;
      i43 = 60;
      continue;
      i43 = 67;
      continue;
      i43 = 23;
    }
    label1705: int i46 = arrayOfChar13[i45];
    int i47;
    switch (i45 % 5)
    {
    default:
      i47 = 32;
    case 0:
    case 1:
    case 2:
    case 3:
    }
    while (true)
    {
      arrayOfChar13[i45] = (char)(i47 ^ i46);
      i45++;
      break;
      i47 = 10;
      continue;
      i47 = 60;
      continue;
      i47 = 67;
      continue;
      i47 = 23;
    }
    label1797: int i50 = arrayOfChar14[i49];
    int i51;
    switch (i49 % 5)
    {
    default:
      i51 = 32;
    case 0:
    case 1:
    case 2:
    case 3:
    }
    while (true)
    {
      arrayOfChar14[i49] = (char)(i51 ^ i50);
      i49++;
      break;
      i51 = 10;
      continue;
      i51 = 60;
      continue;
      i51 = 67;
      continue;
      i51 = 23;
    }
    label1889: int i54 = arrayOfChar15[i53];
    int i55;
    switch (i53 % 5)
    {
    default:
      i55 = 32;
    case 0:
    case 1:
    case 2:
    case 3:
    }
    while (true)
    {
      arrayOfChar15[i53] = (char)(i55 ^ i54);
      i53++;
      break;
      i55 = 10;
      continue;
      i55 = 60;
      continue;
      i55 = 67;
      continue;
      i55 = 23;
    }
    label1981: int i58 = arrayOfChar16[i57];
    int i59;
    switch (i57 % 5)
    {
    default:
      i59 = 32;
    case 0:
    case 1:
    case 2:
    case 3:
    }
    while (true)
    {
      arrayOfChar16[i57] = (char)(i59 ^ i58);
      i57++;
      break;
      i59 = 10;
      continue;
      i59 = 60;
      continue;
      i59 = 67;
      continue;
      i59 = 23;
    }
  }

  // ERROR //
  private static long a(File paramFile)
  {
    // Byte code:
    //   0: getstatic 73	com/whatsapp/DialogToastListActivity:f	Z
    //   3: istore_1
    //   4: sipush 4096
    //   7: newarray byte
    //   9: astore 9
    //   11: new 75	java/util/zip/CRC32
    //   14: dup
    //   15: invokespecial 77	java/util/zip/CRC32:<init>	()V
    //   18: astore 10
    //   20: new 79	java/io/FileInputStream
    //   23: dup
    //   24: aload_0
    //   25: invokespecial 82	java/io/FileInputStream:<init>	(Ljava/io/File;)V
    //   28: astore_3
    //   29: aload_3
    //   30: aload 9
    //   32: iconst_0
    //   33: aload 9
    //   35: arraylength
    //   36: invokevirtual 86	java/io/FileInputStream:read	([BII)I
    //   39: istore 11
    //   41: iload 11
    //   43: iflt +17 -> 60
    //   46: aload 10
    //   48: aload 9
    //   50: iconst_0
    //   51: iload 11
    //   53: invokevirtual 90	java/util/zip/CRC32:update	([BII)V
    //   56: iload_1
    //   57: ifeq -28 -> 29
    //   60: aload 10
    //   62: invokevirtual 94	java/util/zip/CRC32:getValue	()J
    //   65: lstore 12
    //   67: lload 12
    //   69: lstore 6
    //   71: aload_3
    //   72: ifnull +7 -> 79
    //   75: aload_3
    //   76: invokevirtual 97	java/io/FileInputStream:close	()V
    //   79: lload 6
    //   81: lreturn
    //   82: astore 5
    //   84: aconst_null
    //   85: astore_3
    //   86: aload 5
    //   88: invokestatic 102	com/whatsapp/g5:d	(Ljava/lang/Throwable;)V
    //   91: lconst_0
    //   92: lstore 6
    //   94: aload_3
    //   95: ifnull -16 -> 79
    //   98: aload_3
    //   99: invokevirtual 97	java/io/FileInputStream:close	()V
    //   102: goto -23 -> 79
    //   105: astore 8
    //   107: goto -28 -> 79
    //   110: astore_2
    //   111: aconst_null
    //   112: astore_3
    //   113: aload_3
    //   114: ifnull +7 -> 121
    //   117: aload_3
    //   118: invokevirtual 97	java/io/FileInputStream:close	()V
    //   121: aload_2
    //   122: athrow
    //   123: astore 14
    //   125: goto -46 -> 79
    //   128: astore 4
    //   130: goto -9 -> 121
    //   133: astore_2
    //   134: goto -21 -> 113
    //   137: astore 5
    //   139: goto -53 -> 86
    //
    // Exception table:
    //   from	to	target	type
    //   4	29	82	java/io/IOException
    //   98	102	105	java/io/IOException
    //   4	29	110	finally
    //   75	79	123	java/io/IOException
    //   117	121	128	java/io/IOException
    //   29	67	133	finally
    //   86	91	133	finally
    //   29	67	137	java/io/IOException
  }

  public static Uri a()
  {
    if (!e);
    for (Uri localUri = Uri.parse(z[9]); ; localUri = Uri.parse(a))
      return localUri;
  }

  public static void a(Context paramContext, String paramString)
  {
    if (!e);
    while (true)
    {
      return;
      if (paramContext != null)
        new Thread(new l4(paramString)).start();
    }
  }

  // ERROR //
  private static void a(String paramString, File paramFile)
  {
    // Byte code:
    //   0: aconst_null
    //   1: astore_2
    //   2: getstatic 73	com/whatsapp/DialogToastListActivity:f	Z
    //   5: istore_3
    //   6: sipush 4096
    //   9: newarray byte
    //   11: astore 10
    //   13: new 128	org/apache/http/params/BasicHttpParams
    //   16: dup
    //   17: invokespecial 129	org/apache/http/params/BasicHttpParams:<init>	()V
    //   20: astore 11
    //   22: aload 11
    //   24: sipush 15000
    //   27: invokestatic 135	org/apache/http/params/HttpConnectionParams:setConnectionTimeout	(Lorg/apache/http/params/HttpParams;I)V
    //   30: aload 11
    //   32: sipush 30000
    //   35: invokestatic 138	org/apache/http/params/HttpConnectionParams:setSoTimeout	(Lorg/apache/http/params/HttpParams;I)V
    //   38: aload 11
    //   40: getstatic 143	com/whatsapp/App:n	Ljava/lang/String;
    //   43: invokestatic 149	org/apache/http/params/HttpProtocolParams:setUserAgent	(Lorg/apache/http/params/HttpParams;Ljava/lang/String;)V
    //   46: new 151	org/apache/http/impl/client/DefaultHttpClient
    //   49: dup
    //   50: aload 11
    //   52: invokespecial 154	org/apache/http/impl/client/DefaultHttpClient:<init>	(Lorg/apache/http/params/HttpParams;)V
    //   55: new 156	org/apache/http/client/methods/HttpGet
    //   58: dup
    //   59: aload_0
    //   60: invokespecial 157	org/apache/http/client/methods/HttpGet:<init>	(Ljava/lang/String;)V
    //   63: invokevirtual 161	org/apache/http/impl/client/DefaultHttpClient:execute	(Lorg/apache/http/client/methods/HttpUriRequest;)Lorg/apache/http/HttpResponse;
    //   66: invokeinterface 167 1 0
    //   71: invokeinterface 173 1 0
    //   76: astore 12
    //   78: aload 12
    //   80: astore 8
    //   82: new 175	java/io/FileOutputStream
    //   85: dup
    //   86: aload_1
    //   87: invokespecial 176	java/io/FileOutputStream:<init>	(Ljava/io/File;)V
    //   90: astore 5
    //   92: aload 8
    //   94: aload 10
    //   96: iconst_0
    //   97: aload 10
    //   99: arraylength
    //   100: invokevirtual 179	java/io/InputStream:read	([BII)I
    //   103: istore 13
    //   105: iload 13
    //   107: iflt +17 -> 124
    //   110: aload 5
    //   112: aload 10
    //   114: iconst_0
    //   115: iload 13
    //   117: invokevirtual 184	java/io/OutputStream:write	([BII)V
    //   120: iload_3
    //   121: ifeq -29 -> 92
    //   124: aload 5
    //   126: invokevirtual 187	java/io/OutputStream:flush	()V
    //   129: iconst_0
    //   130: ifeq +7 -> 137
    //   133: aconst_null
    //   134: invokevirtual 188	java/io/OutputStream:close	()V
    //   137: aload 8
    //   139: ifnull +8 -> 147
    //   142: aload 8
    //   144: invokevirtual 189	java/io/InputStream:close	()V
    //   147: return
    //   148: astore 7
    //   150: aconst_null
    //   151: astore 8
    //   153: aload 7
    //   155: invokestatic 102	com/whatsapp/g5:d	(Ljava/lang/Throwable;)V
    //   158: aload_2
    //   159: ifnull +7 -> 166
    //   162: aload_2
    //   163: invokevirtual 188	java/io/OutputStream:close	()V
    //   166: aload 8
    //   168: ifnull -21 -> 147
    //   171: aload 8
    //   173: invokevirtual 189	java/io/InputStream:close	()V
    //   176: goto -29 -> 147
    //   179: astore 9
    //   181: goto -34 -> 147
    //   184: astore 4
    //   186: aconst_null
    //   187: astore 5
    //   189: aload 5
    //   191: ifnull +8 -> 199
    //   194: aload 5
    //   196: invokevirtual 188	java/io/OutputStream:close	()V
    //   199: aload_2
    //   200: ifnull +7 -> 207
    //   203: aload_2
    //   204: invokevirtual 189	java/io/InputStream:close	()V
    //   207: aload 4
    //   209: athrow
    //   210: astore 6
    //   212: goto -5 -> 207
    //   215: astore 4
    //   217: aconst_null
    //   218: astore 5
    //   220: aload 8
    //   222: astore_2
    //   223: goto -34 -> 189
    //   226: astore 4
    //   228: aload 8
    //   230: astore_2
    //   231: goto -42 -> 189
    //   234: astore 4
    //   236: aload_2
    //   237: astore 5
    //   239: aload 8
    //   241: astore_2
    //   242: goto -53 -> 189
    //   245: astore 7
    //   247: goto -94 -> 153
    //   250: astore 7
    //   252: aload 5
    //   254: astore_2
    //   255: goto -102 -> 153
    //   258: astore 14
    //   260: goto -113 -> 147
    //
    // Exception table:
    //   from	to	target	type
    //   6	78	148	java/io/IOException
    //   162	176	179	java/io/IOException
    //   6	78	184	finally
    //   194	207	210	java/io/IOException
    //   82	92	215	finally
    //   92	129	226	finally
    //   153	158	234	finally
    //   82	92	245	java/io/IOException
    //   92	129	250	java/io/IOException
    //   133	147	258	java/io/IOException
  }

  public static boolean a(String paramString)
  {
    boolean bool = false;
    if (paramString == null);
    while (true)
    {
      return bool;
      if (paramString.length() >= 1)
        if (e)
        {
          bool = true;
        }
        else
        {
          String str = z[13] + paramString.substring(-1 + paramString.length()) + "/";
          g5.b(z[12] + str);
          a = str + z[4];
          b = str + z[10];
          c = str + z[11];
          d = str + z[14];
          e = true;
          bool = true;
        }
    }
  }

  public static Uri b()
  {
    if (!e);
    for (Uri localUri = null; ; localUri = Uri.parse(d))
      return localUri;
  }

  // ERROR //
  private static String b(String paramString)
  {
    // Byte code:
    //   0: getstatic 73	com/whatsapp/DialogToastListActivity:f	Z
    //   3: istore_1
    //   4: new 128	org/apache/http/params/BasicHttpParams
    //   7: dup
    //   8: invokespecial 129	org/apache/http/params/BasicHttpParams:<init>	()V
    //   11: astore_2
    //   12: aload_2
    //   13: sipush 15000
    //   16: invokestatic 135	org/apache/http/params/HttpConnectionParams:setConnectionTimeout	(Lorg/apache/http/params/HttpParams;I)V
    //   19: aload_2
    //   20: sipush 30000
    //   23: invokestatic 138	org/apache/http/params/HttpConnectionParams:setSoTimeout	(Lorg/apache/http/params/HttpParams;I)V
    //   26: aload_2
    //   27: getstatic 143	com/whatsapp/App:n	Ljava/lang/String;
    //   30: invokestatic 149	org/apache/http/params/HttpProtocolParams:setUserAgent	(Lorg/apache/http/params/HttpParams;Ljava/lang/String;)V
    //   33: new 151	org/apache/http/impl/client/DefaultHttpClient
    //   36: dup
    //   37: aload_2
    //   38: invokespecial 154	org/apache/http/impl/client/DefaultHttpClient:<init>	(Lorg/apache/http/params/HttpParams;)V
    //   41: new 156	org/apache/http/client/methods/HttpGet
    //   44: dup
    //   45: aload_0
    //   46: invokespecial 157	org/apache/http/client/methods/HttpGet:<init>	(Ljava/lang/String;)V
    //   49: invokevirtual 161	org/apache/http/impl/client/DefaultHttpClient:execute	(Lorg/apache/http/client/methods/HttpUriRequest;)Lorg/apache/http/HttpResponse;
    //   52: invokeinterface 167 1 0
    //   57: invokeinterface 173 1 0
    //   62: astore 10
    //   64: aload 10
    //   66: astore 4
    //   68: new 196	java/lang/StringBuilder
    //   71: dup
    //   72: invokespecial 197	java/lang/StringBuilder:<init>	()V
    //   75: astore 11
    //   77: aload 4
    //   79: invokevirtual 221	java/io/InputStream:read	()I
    //   82: istore 13
    //   84: iload 13
    //   86: iflt +16 -> 102
    //   89: aload 11
    //   91: iload 13
    //   93: i2c
    //   94: invokevirtual 224	java/lang/StringBuilder:append	(C)Ljava/lang/StringBuilder;
    //   97: pop
    //   98: iload_1
    //   99: ifeq -22 -> 77
    //   102: aload 4
    //   104: invokevirtual 189	java/io/InputStream:close	()V
    //   107: aload 11
    //   109: invokevirtual 210	java/lang/StringBuilder:toString	()Ljava/lang/String;
    //   112: astore 14
    //   114: aload 14
    //   116: astore 8
    //   118: aload 4
    //   120: ifnull +8 -> 128
    //   123: aload 4
    //   125: invokevirtual 189	java/io/InputStream:close	()V
    //   128: aload 8
    //   130: areturn
    //   131: astore 7
    //   133: aconst_null
    //   134: astore 4
    //   136: ldc 226
    //   138: astore 8
    //   140: aload 4
    //   142: ifnull -14 -> 128
    //   145: aload 4
    //   147: invokevirtual 189	java/io/InputStream:close	()V
    //   150: goto -22 -> 128
    //   153: astore 9
    //   155: goto -27 -> 128
    //   158: astore_3
    //   159: aconst_null
    //   160: astore 4
    //   162: aload_3
    //   163: astore 5
    //   165: aload 4
    //   167: ifnull +8 -> 175
    //   170: aload 4
    //   172: invokevirtual 189	java/io/InputStream:close	()V
    //   175: aload 5
    //   177: athrow
    //   178: astore 15
    //   180: goto -52 -> 128
    //   183: astore 6
    //   185: goto -10 -> 175
    //   188: astore 5
    //   190: goto -25 -> 165
    //   193: astore 12
    //   195: goto -59 -> 136
    //
    // Exception table:
    //   from	to	target	type
    //   4	64	131	java/io/IOException
    //   145	150	153	java/io/IOException
    //   4	64	158	finally
    //   123	128	178	java/io/IOException
    //   170	175	183	java/io/IOException
    //   68	114	188	finally
    //   136	140	188	finally
    //   68	114	193	java/io/IOException
  }

  public static Uri c()
  {
    File localFile1 = App.c;
    File localFile2 = new File(localFile1, z[4]);
    if ((new File(localFile1, z[6]).delete()) && (localFile2.exists()));
    for (Uri localUri = Uri.fromFile(localFile2); ; localUri = null)
      return localUri;
  }

  public static void d()
  {
    File localFile = new File(App.c, z[6]);
    try
    {
      localFile.createNewFile();
      return;
    }
    catch (IOException localIOException)
    {
      while (true)
        g5.d(z[15]);
    }
  }

  private static String e()
  {
    return b(c).trim();
  }

  private static long f()
  {
    String str = b(b).trim();
    try
    {
      long l2 = Long.parseLong(str);
      l1 = l2;
      return l1;
    }
    catch (NumberFormatException localNumberFormatException)
    {
      while (true)
      {
        g5.b(str, localNumberFormatException);
        long l1 = -1L;
      }
    }
  }

  private static void g()
  {
    File localFile1 = App.c;
    File localFile2 = new File(localFile1, z[5]);
    File localFile3 = new File(localFile1, z[4]);
    new File(localFile1, z[6]);
    long l = f();
    if (localFile3.exists())
      if (l == a(localFile3))
      {
        if ((localFile2.exists()) && (!localFile2.delete()))
          g5.c(z[3]);
        d();
      }
    while (true)
    {
      return;
      if (!localFile3.delete())
        g5.c(z[7]);
      if (localFile2.exists())
      {
        if (l == a(localFile2))
        {
          if (!localFile2.renameTo(localFile3))
            g5.c(z[8]);
          d();
        }
        else if (!localFile2.delete())
        {
          g5.c(z[0]);
        }
      }
      else
      {
        a(a, localFile2);
        if (localFile2.exists())
          if (l == a(localFile2))
          {
            if (!localFile2.renameTo(localFile3))
              g5.c(z[2]);
            d();
          }
          else if (!localFile2.delete())
          {
            g5.c(z[1]);
          }
      }
    }
  }

  public static void h()
  {
    boolean bool1 = true;
    File localFile1 = App.c;
    File localFile2 = new File(localFile1, z[5]);
    boolean bool2;
    if (localFile2.exists())
    {
      if (localFile2.delete() == bool1)
      {
        bool2 = bool1;
        g5.b(bool2);
      }
    }
    else
      if (!new File(localFile1, z[6]).exists())
        break label70;
    label70: File localFile3;
    do
    {
      return;
      bool2 = false;
      break;
      localFile3 = new File(localFile1, z[4]);
    }
    while (!localFile3.exists());
    if (localFile3.delete() == bool1);
    while (true)
    {
      g5.b(bool1);
      break;
      bool1 = false;
    }
  }

  static String i()
  {
    return e();
  }

  static void j()
  {
    g();
  }
}

/* Location:           C:\Users\Jaap\Downloads\Code\WhatsApp-2.8.4278_dex2jar.jar
 * Qualified Name:     com.whatsapp.k4
 * JD-Core Version:    0.6.1
 */