package com.whatsapp;

import android.os.Handler;

class s9 extends Thread
{
  private static final String[] z;
  Handler a;
  boolean b = false;
  boolean c = false;
  int d = 0;
  final RegisterName e;

  static
  {
    String[] arrayOfString = new String[9];
    char[] arrayOfChar1 = "(\002S o.\002F'}7\002\033.y4HQ;n5\025".toCharArray();
    int i = arrayOfChar1.length;
    int j = 0;
    char[] arrayOfChar2;
    int i1;
    char[] arrayOfChar3;
    int i5;
    char[] arrayOfChar4;
    int i9;
    char[] arrayOfChar5;
    int i13;
    char[] arrayOfChar6;
    int i17;
    char[] arrayOfChar7;
    int i21;
    char[] arrayOfChar8;
    int i25;
    char[] arrayOfChar9;
    int i29;
    if (i <= j)
    {
      arrayOfString[0] = new String(arrayOfChar1).intern();
      arrayOfChar2 = ")\036Z*3(\002S o.\002F\026o#\tW\026~;\023W!".toCharArray();
      int n = arrayOfChar2.length;
      i1 = 0;
      if (n <= i1)
      {
        arrayOfString[1] = new String(arrayOfChar2).intern();
        arrayOfChar3 = "(\002S o.\002F'}7\002\033!h.\027\033,n(\bF".toCharArray();
        int i4 = arrayOfChar3.length;
        i5 = 0;
        if (i4 > i5)
          break label517;
        arrayOfString[2] = new String(arrayOfChar3).intern();
        arrayOfChar4 = "(\002S o.\002F'}7\002\033,n(\bF".toCharArray();
        int i8 = arrayOfChar4.length;
        i9 = 0;
        if (i8 > i9)
          break label609;
        arrayOfString[3] = new String(arrayOfChar4).intern();
        arrayOfChar5 = "(\002S o.\002F'}7\002\033 su\002F;s(".toCharArray();
        int i12 = arrayOfChar5.length;
        i13 = 0;
        if (i12 > i13)
          break label701;
        arrayOfString[4] = new String(arrayOfChar5).intern();
        arrayOfChar6 = "(\002S o.\002F'}7\002\0331q6\027U;o?\025\033,n(\bF".toCharArray();
        int i16 = arrayOfChar6.length;
        i17 = 0;
        if (i16 > i17)
          break label793;
        arrayOfString[5] = new String(arrayOfChar6).intern();
        arrayOfChar7 = "zO".toCharArray();
        int i20 = arrayOfChar7.length;
        i21 = 0;
        if (i20 > i21)
          break label885;
        arrayOfString[6] = new String(arrayOfChar7).intern();
        arrayOfChar8 = "z\025Q/i)\002P".toCharArray();
        int i24 = arrayOfChar8.length;
        i25 = 0;
        if (i24 > i25)
          break label977;
        arrayOfString[7] = new String(arrayOfChar8).intern();
        arrayOfChar9 = "(\002S o.\002F'}7\002\033*s4\023U*h)HW&i4\023\024".toCharArray();
        int i28 = arrayOfChar9.length;
        i29 = 0;
        if (i28 > i29)
          break label1069;
        arrayOfString[8] = new String(arrayOfChar9).intern();
        z = arrayOfString;
      }
    }
    else
    {
      int k = arrayOfChar1[j];
      int m;
      switch (j % 5)
      {
      default:
        m = 28;
      case 0:
      case 1:
      case 2:
      case 3:
      }
      while (true)
      {
        arrayOfChar1[j] = (char)(m ^ k);
        j++;
        break;
        m = 90;
        continue;
        m = 103;
        continue;
        m = 52;
        continue;
        m = 73;
      }
    }
    int i2 = arrayOfChar2[i1];
    int i3;
    switch (i1 % 5)
    {
    default:
      i3 = 28;
    case 0:
    case 1:
    case 2:
    case 3:
    }
    while (true)
    {
      arrayOfChar2[i1] = (char)(i3 ^ i2);
      i1++;
      break;
      i3 = 90;
      continue;
      i3 = 103;
      continue;
      i3 = 52;
      continue;
      i3 = 73;
    }
    label517: int i6 = arrayOfChar3[i5];
    int i7;
    switch (i5 % 5)
    {
    default:
      i7 = 28;
    case 0:
    case 1:
    case 2:
    case 3:
    }
    while (true)
    {
      arrayOfChar3[i5] = (char)(i7 ^ i6);
      i5++;
      break;
      i7 = 90;
      continue;
      i7 = 103;
      continue;
      i7 = 52;
      continue;
      i7 = 73;
    }
    label609: int i10 = arrayOfChar4[i9];
    int i11;
    switch (i9 % 5)
    {
    default:
      i11 = 28;
    case 0:
    case 1:
    case 2:
    case 3:
    }
    while (true)
    {
      arrayOfChar4[i9] = (char)(i11 ^ i10);
      i9++;
      break;
      i11 = 90;
      continue;
      i11 = 103;
      continue;
      i11 = 52;
      continue;
      i11 = 73;
    }
    label701: int i14 = arrayOfChar5[i13];
    int i15;
    switch (i13 % 5)
    {
    default:
      i15 = 28;
    case 0:
    case 1:
    case 2:
    case 3:
    }
    while (true)
    {
      arrayOfChar5[i13] = (char)(i15 ^ i14);
      i13++;
      break;
      i15 = 90;
      continue;
      i15 = 103;
      continue;
      i15 = 52;
      continue;
      i15 = 73;
    }
    label793: int i18 = arrayOfChar6[i17];
    int i19;
    switch (i17 % 5)
    {
    default:
      i19 = 28;
    case 0:
    case 1:
    case 2:
    case 3:
    }
    while (true)
    {
      arrayOfChar6[i17] = (char)(i19 ^ i18);
      i17++;
      break;
      i19 = 90;
      continue;
      i19 = 103;
      continue;
      i19 = 52;
      continue;
      i19 = 73;
    }
    label885: int i22 = arrayOfChar7[i21];
    int i23;
    switch (i21 % 5)
    {
    default:
      i23 = 28;
    case 0:
    case 1:
    case 2:
    case 3:
    }
    while (true)
    {
      arrayOfChar7[i21] = (char)(i23 ^ i22);
      i21++;
      break;
      i23 = 90;
      continue;
      i23 = 103;
      continue;
      i23 = 52;
      continue;
      i23 = 73;
    }
    label977: int i26 = arrayOfChar8[i25];
    int i27;
    switch (i25 % 5)
    {
    default:
      i27 = 28;
    case 0:
    case 1:
    case 2:
    case 3:
    }
    while (true)
    {
      arrayOfChar8[i25] = (char)(i27 ^ i26);
      i25++;
      break;
      i27 = 90;
      continue;
      i27 = 103;
      continue;
      i27 = 52;
      continue;
      i27 = 73;
    }
    label1069: int i30 = arrayOfChar9[i29];
    int i31;
    switch (i29 % 5)
    {
    default:
      i31 = 28;
    case 0:
    case 1:
    case 2:
    case 3:
    }
    while (true)
    {
      arrayOfChar9[i29] = (char)(i31 ^ i30);
      i29++;
      break;
      i31 = 90;
      continue;
      i31 = 103;
      continue;
      i31 = 52;
      continue;
      i31 = 73;
    }
  }

  s9(RegisterName paramRegisterName, Handler paramHandler)
  {
    this.a = paramHandler;
    start();
  }

  public void a()
  {
    if (this.a != null)
    {
      this.a.removeMessages(0);
      this.a = null;
    }
  }

  public void a(Handler paramHandler)
  {
    if (this.b)
      paramHandler.sendEmptyMessage(0);
    this.a = paramHandler;
  }

  // ERROR //
  public void run()
  {
    // Byte code:
    //   0: getstatic 94	com/whatsapp/DialogToastListActivity:f	Z
    //   3: istore_1
    //   4: iconst_1
    //   5: putstatic 98	com/whatsapp/tp:a	Z
    //   8: new 100	java/util/HashMap
    //   11: dup
    //   12: invokespecial 101	java/util/HashMap:<init>	()V
    //   15: astore 15
    //   17: getstatic 107	com/whatsapp/App:w	Lcom/whatsapp/qp;
    //   20: invokevirtual 112	com/whatsapp/qp:e	()I
    //   23: istore 16
    //   25: sipush 1001
    //   28: istore 17
    //   30: iconst_2
    //   31: invokestatic 115	com/whatsapp/tp:c	(I)Ljava/lang/Integer;
    //   34: invokevirtual 120	java/lang/Integer:intValue	()I
    //   37: istore 36
    //   39: iload 36
    //   41: istore 17
    //   43: aload_0
    //   44: getfield 54	com/whatsapp/s9:e	Lcom/whatsapp/RegisterName;
    //   47: astore 19
    //   49: iload 17
    //   51: sipush 1000
    //   54: if_icmpgt +550 -> 604
    //   57: iconst_1
    //   58: istore 20
    //   60: aload 19
    //   62: iload 20
    //   64: invokestatic 123	com/whatsapp/App:a	(Landroid/content/Context;Z)V
    //   67: new 125	java/lang/StringBuilder
    //   70: dup
    //   71: invokespecial 126	java/lang/StringBuilder:<init>	()V
    //   74: getstatic 51	com/whatsapp/s9:z	[Ljava/lang/String;
    //   77: bipush 8
    //   79: aaload
    //   80: invokevirtual 130	java/lang/StringBuilder:append	(Ljava/lang/String;)Ljava/lang/StringBuilder;
    //   83: iload 17
    //   85: invokevirtual 133	java/lang/StringBuilder:append	(I)Ljava/lang/StringBuilder;
    //   88: getstatic 51	com/whatsapp/s9:z	[Ljava/lang/String;
    //   91: bipush 6
    //   93: aaload
    //   94: invokevirtual 130	java/lang/StringBuilder:append	(Ljava/lang/String;)Ljava/lang/StringBuilder;
    //   97: aload_0
    //   98: getfield 54	com/whatsapp/s9:e	Lcom/whatsapp/RegisterName;
    //   101: invokestatic 137	com/whatsapp/App:i	(Landroid/content/Context;)Z
    //   104: invokevirtual 140	java/lang/StringBuilder:append	(Z)Ljava/lang/StringBuilder;
    //   107: ldc 142
    //   109: invokevirtual 130	java/lang/StringBuilder:append	(Ljava/lang/String;)Ljava/lang/StringBuilder;
    //   112: invokevirtual 145	java/lang/StringBuilder:toString	()Ljava/lang/String;
    //   115: invokestatic 150	com/whatsapp/g5:b	(Ljava/lang/String;)V
    //   118: aload 15
    //   120: getstatic 154	com/whatsapp/App:ib	Landroid/content/ContentResolver;
    //   123: invokestatic 157	com/whatsapp/tp:a	(Ljava/util/HashMap;Landroid/content/ContentResolver;)Z
    //   126: pop
    //   127: aload 15
    //   129: invokevirtual 161	java/util/HashMap:values	()Ljava/util/Collection;
    //   132: getstatic 51	com/whatsapp/s9:z	[Ljava/lang/String;
    //   135: iconst_1
    //   136: aaload
    //   137: invokestatic 166	com/whatsapp/zq:a	(Ljava/util/Collection;Ljava/lang/String;)V
    //   140: getstatic 170	com/whatsapp/App:bb	Lcom/whatsapp/App$Me;
    //   143: aload 15
    //   145: invokestatic 175	com/whatsapp/yp:a	(Lcom/whatsapp/App$Me;Ljava/util/HashMap;)V
    //   148: getstatic 107	com/whatsapp/App:w	Lcom/whatsapp/qp;
    //   151: aload 15
    //   153: aconst_null
    //   154: invokevirtual 178	com/whatsapp/qp:a	(Ljava/util/HashMap;Landroid/database/sqlite/SQLiteTransactionListener;)V
    //   157: getstatic 182	com/whatsapp/App:lc	Lcom/whatsapp/g;
    //   160: iconst_1
    //   161: invokevirtual 187	com/whatsapp/g:b	(Z)V
    //   164: getstatic 191	com/whatsapp/App:Mb	Lcom/whatsapp/App;
    //   167: invokestatic 197	java/lang/System:currentTimeMillis	()J
    //   170: invokevirtual 200	com/whatsapp/App:b	(J)V
    //   173: invokestatic 204	com/whatsapp/accountsync/PerformSyncManager:b	()V
    //   176: new 206	com/whatsapp/t9
    //   179: dup
    //   180: aload_0
    //   181: invokespecial 209	com/whatsapp/t9:<init>	(Lcom/whatsapp/s9;)V
    //   184: astore 22
    //   186: aload 22
    //   188: iconst_1
    //   189: invokevirtual 212	java/lang/Thread:setPriority	(I)V
    //   192: aload 22
    //   194: invokevirtual 213	java/lang/Thread:start	()V
    //   197: new 215	com/whatsapp/u9
    //   200: dup
    //   201: aload_0
    //   202: invokespecial 216	com/whatsapp/u9:<init>	(Lcom/whatsapp/s9;)V
    //   205: astore 23
    //   207: aload 23
    //   209: iconst_1
    //   210: invokevirtual 212	java/lang/Thread:setPriority	(I)V
    //   213: aload 23
    //   215: invokevirtual 213	java/lang/Thread:start	()V
    //   218: aload 23
    //   220: invokevirtual 219	java/lang/Thread:join	()V
    //   223: aload 15
    //   225: invokevirtual 161	java/util/HashMap:values	()Ljava/util/Collection;
    //   228: invokeinterface 225 1 0
    //   233: astore 24
    //   235: iconst_0
    //   236: istore 25
    //   238: aload 24
    //   240: invokeinterface 231 1 0
    //   245: ifeq +79 -> 324
    //   248: aload 24
    //   250: invokeinterface 235 1 0
    //   255: checkcast 237	java/util/LinkedList
    //   258: invokevirtual 238	java/util/LinkedList:iterator	()Ljava/util/Iterator;
    //   261: astore 33
    //   263: aload 33
    //   265: invokeinterface 231 1 0
    //   270: ifeq +539 -> 809
    //   273: aload 33
    //   275: invokeinterface 235 1 0
    //   280: checkcast 163	com/whatsapp/zq
    //   283: astore 35
    //   285: aload 35
    //   287: getfield 241	com/whatsapp/zq:k	Z
    //   290: ifeq +512 -> 802
    //   293: aload 35
    //   295: getfield 244	com/whatsapp/zq:b	Ljava/lang/String;
    //   298: iconst_0
    //   299: iconst_2
    //   300: invokestatic 247	com/whatsapp/App:a	(Ljava/lang/String;II)V
    //   303: iload 25
    //   305: iconst_1
    //   306: iadd
    //   307: istore 34
    //   309: iload 34
    //   311: sipush 250
    //   314: if_icmple +502 -> 816
    //   317: iload_1
    //   318: ifeq +502 -> 820
    //   321: goto +495 -> 816
    //   324: aload 15
    //   326: invokevirtual 250	java/util/HashMap:clear	()V
    //   329: getstatic 107	com/whatsapp/App:w	Lcom/whatsapp/qp;
    //   332: invokevirtual 253	com/whatsapp/qp:i	()Ljava/util/ArrayList;
    //   335: invokevirtual 256	java/util/ArrayList:iterator	()Ljava/util/Iterator;
    //   338: astore 26
    //   340: aload 26
    //   342: invokeinterface 231 1 0
    //   347: ifeq +36 -> 383
    //   350: aload 26
    //   352: invokeinterface 235 1 0
    //   357: checkcast 163	com/whatsapp/zq
    //   360: astore 32
    //   362: aload 32
    //   364: invokevirtual 259	com/whatsapp/zq:p	()Z
    //   367: ifne +472 -> 839
    //   370: aload 32
    //   372: getfield 244	com/whatsapp/zq:b	Ljava/lang/String;
    //   375: iconst_0
    //   376: iconst_2
    //   377: invokestatic 247	com/whatsapp/App:a	(Ljava/lang/String;II)V
    //   380: goto +459 -> 839
    //   383: aload_0
    //   384: getfield 54	com/whatsapp/s9:e	Lcom/whatsapp/RegisterName;
    //   387: invokestatic 264	com/whatsapp/RegisterName:b	(Lcom/whatsapp/RegisterName;)Lcom/whatsapp/zq;
    //   390: getfield 267	com/whatsapp/zq:o	I
    //   393: ifne +453 -> 846
    //   396: aload_0
    //   397: getfield 54	com/whatsapp/s9:e	Lcom/whatsapp/RegisterName;
    //   400: invokestatic 264	com/whatsapp/RegisterName:b	(Lcom/whatsapp/RegisterName;)Lcom/whatsapp/zq;
    //   403: getfield 244	com/whatsapp/zq:b	Ljava/lang/String;
    //   406: iconst_0
    //   407: iconst_1
    //   408: invokestatic 247	com/whatsapp/App:a	(Ljava/lang/String;II)V
    //   411: goto +435 -> 846
    //   414: getstatic 271	com/whatsapp/App:U	Lcom/whatsapp/c5;
    //   417: invokevirtual 275	com/whatsapp/c5:b	()Z
    //   420: istore 28
    //   422: iload 28
    //   424: ifne +37 -> 461
    //   427: iload 27
    //   429: sipush 20000
    //   432: if_icmpge +29 -> 461
    //   435: wide
    //   441: ldc2_w 276
    //   444: invokestatic 280	java/lang/Thread:sleep	(J)V
    //   447: goto -33 -> 414
    //   450: astore 31
    //   452: aload 31
    //   454: invokevirtual 283	java/lang/InterruptedException:printStackTrace	()V
    //   457: iload_1
    //   458: ifeq -44 -> 414
    //   461: iload 16
    //   463: invokestatic 285	com/whatsapp/g:a	(I)V
    //   466: getstatic 288	com/whatsapp/App:Ib	Landroid/os/Handler;
    //   469: iconst_1
    //   470: invokevirtual 78	android/os/Handler:sendEmptyMessage	(I)Z
    //   473: pop
    //   474: aload_0
    //   475: iconst_1
    //   476: putfield 60	com/whatsapp/s9:c	Z
    //   479: aload_0
    //   480: getfield 54	com/whatsapp/s9:e	Lcom/whatsapp/RegisterName;
    //   483: iconst_3
    //   484: invokestatic 291	com/whatsapp/App:a	(Landroid/content/Context;I)V
    //   487: aload_0
    //   488: iconst_1
    //   489: putfield 58	com/whatsapp/s9:b	Z
    //   492: aload_0
    //   493: getfield 64	com/whatsapp/s9:a	Landroid/os/Handler;
    //   496: ifnull +12 -> 508
    //   499: aload_0
    //   500: getfield 64	com/whatsapp/s9:a	Landroid/os/Handler;
    //   503: iconst_0
    //   504: invokevirtual 78	android/os/Handler:sendEmptyMessage	(I)Z
    //   507: pop
    //   508: iconst_0
    //   509: putstatic 98	com/whatsapp/tp:a	Z
    //   512: return
    //   513: astore 18
    //   515: getstatic 51	com/whatsapp/s9:z	[Ljava/lang/String;
    //   518: iconst_3
    //   519: aaload
    //   520: aload 18
    //   522: invokestatic 294	com/whatsapp/g5:b	(Ljava/lang/String;Ljava/lang/Throwable;)V
    //   525: goto -482 -> 43
    //   528: astore 12
    //   530: aload 12
    //   532: invokevirtual 295	java/io/IOException:toString	()Ljava/lang/String;
    //   535: astore 13
    //   537: aload 13
    //   539: ifnull +26 -> 565
    //   542: aload 13
    //   544: getstatic 51	com/whatsapp/s9:z	[Ljava/lang/String;
    //   547: bipush 7
    //   549: aaload
    //   550: invokevirtual 299	java/lang/String:contains	(Ljava/lang/CharSequence;)Z
    //   553: ifeq +12 -> 565
    //   556: aload_0
    //   557: iconst_3
    //   558: putfield 62	com/whatsapp/s9:d	I
    //   561: iload_1
    //   562: ifeq +8 -> 570
    //   565: aload_0
    //   566: iconst_1
    //   567: putfield 62	com/whatsapp/s9:d	I
    //   570: getstatic 51	com/whatsapp/s9:z	[Ljava/lang/String;
    //   573: iconst_4
    //   574: aaload
    //   575: aload 12
    //   577: invokestatic 294	com/whatsapp/g5:b	(Ljava/lang/String;Ljava/lang/Throwable;)V
    //   580: aload_0
    //   581: iconst_1
    //   582: putfield 58	com/whatsapp/s9:b	Z
    //   585: aload_0
    //   586: getfield 64	com/whatsapp/s9:a	Landroid/os/Handler;
    //   589: ifnull -81 -> 508
    //   592: aload_0
    //   593: getfield 64	com/whatsapp/s9:a	Landroid/os/Handler;
    //   596: iconst_0
    //   597: invokevirtual 78	android/os/Handler:sendEmptyMessage	(I)Z
    //   600: pop
    //   601: goto -93 -> 508
    //   604: iconst_0
    //   605: istore 20
    //   607: goto -547 -> 60
    //   610: astore 10
    //   612: aload_0
    //   613: iconst_1
    //   614: putfield 62	com/whatsapp/s9:d	I
    //   617: getstatic 51	com/whatsapp/s9:z	[Ljava/lang/String;
    //   620: iconst_5
    //   621: aaload
    //   622: aload 10
    //   624: invokestatic 294	com/whatsapp/g5:b	(Ljava/lang/String;Ljava/lang/Throwable;)V
    //   627: aload_0
    //   628: iconst_1
    //   629: putfield 58	com/whatsapp/s9:b	Z
    //   632: aload_0
    //   633: getfield 64	com/whatsapp/s9:a	Landroid/os/Handler;
    //   636: ifnull -128 -> 508
    //   639: aload_0
    //   640: getfield 64	com/whatsapp/s9:a	Landroid/os/Handler;
    //   643: iconst_0
    //   644: invokevirtual 78	android/os/Handler:sendEmptyMessage	(I)Z
    //   647: pop
    //   648: goto -140 -> 508
    //   651: astore 8
    //   653: aload_0
    //   654: iconst_3
    //   655: putfield 62	com/whatsapp/s9:d	I
    //   658: getstatic 51	com/whatsapp/s9:z	[Ljava/lang/String;
    //   661: iconst_2
    //   662: aaload
    //   663: aload 8
    //   665: invokestatic 294	com/whatsapp/g5:b	(Ljava/lang/String;Ljava/lang/Throwable;)V
    //   668: aload_0
    //   669: iconst_1
    //   670: putfield 58	com/whatsapp/s9:b	Z
    //   673: aload_0
    //   674: getfield 64	com/whatsapp/s9:a	Landroid/os/Handler;
    //   677: ifnull -169 -> 508
    //   680: aload_0
    //   681: getfield 64	com/whatsapp/s9:a	Landroid/os/Handler;
    //   684: iconst_0
    //   685: invokevirtual 78	android/os/Handler:sendEmptyMessage	(I)Z
    //   688: pop
    //   689: goto -181 -> 508
    //   692: astore 6
    //   694: aload_0
    //   695: iconst_3
    //   696: putfield 62	com/whatsapp/s9:d	I
    //   699: getstatic 51	com/whatsapp/s9:z	[Ljava/lang/String;
    //   702: iconst_0
    //   703: aaload
    //   704: aload 6
    //   706: invokestatic 294	com/whatsapp/g5:b	(Ljava/lang/String;Ljava/lang/Throwable;)V
    //   709: aload_0
    //   710: iconst_1
    //   711: putfield 58	com/whatsapp/s9:b	Z
    //   714: aload_0
    //   715: getfield 64	com/whatsapp/s9:a	Landroid/os/Handler;
    //   718: ifnull -210 -> 508
    //   721: aload_0
    //   722: getfield 64	com/whatsapp/s9:a	Landroid/os/Handler;
    //   725: iconst_0
    //   726: invokevirtual 78	android/os/Handler:sendEmptyMessage	(I)Z
    //   729: pop
    //   730: goto -222 -> 508
    //   733: astore 4
    //   735: aload_0
    //   736: iconst_1
    //   737: putfield 58	com/whatsapp/s9:b	Z
    //   740: aload_0
    //   741: getfield 64	com/whatsapp/s9:a	Landroid/os/Handler;
    //   744: ifnull +12 -> 756
    //   747: aload_0
    //   748: getfield 64	com/whatsapp/s9:a	Landroid/os/Handler;
    //   751: iconst_0
    //   752: invokevirtual 78	android/os/Handler:sendEmptyMessage	(I)Z
    //   755: pop
    //   756: iconst_0
    //   757: putstatic 98	com/whatsapp/tp:a	Z
    //   760: aload 4
    //   762: athrow
    //   763: astore_2
    //   764: aload_0
    //   765: iconst_1
    //   766: putfield 58	com/whatsapp/s9:b	Z
    //   769: aload_0
    //   770: getfield 64	com/whatsapp/s9:a	Landroid/os/Handler;
    //   773: ifnull -265 -> 508
    //   776: aload_0
    //   777: getfield 64	com/whatsapp/s9:a	Landroid/os/Handler;
    //   780: iconst_0
    //   781: invokevirtual 78	android/os/Handler:sendEmptyMessage	(I)Z
    //   784: pop
    //   785: goto -277 -> 508
    //   788: iload 34
    //   790: istore 25
    //   792: goto -554 -> 238
    //   795: iload 34
    //   797: istore 25
    //   799: goto -536 -> 263
    //   802: iload 25
    //   804: istore 34
    //   806: goto +10 -> 816
    //   809: iload 25
    //   811: istore 34
    //   813: goto +7 -> 820
    //   816: iload_1
    //   817: ifeq -22 -> 795
    //   820: iload 34
    //   822: sipush 250
    //   825: if_icmple +7 -> 832
    //   828: iload_1
    //   829: ifeq -505 -> 324
    //   832: iload_1
    //   833: ifeq -45 -> 788
    //   836: goto -512 -> 324
    //   839: iload_1
    //   840: ifeq -500 -> 340
    //   843: goto -460 -> 383
    //   846: iconst_0
    //   847: istore 27
    //   849: goto -435 -> 414
    //
    // Exception table:
    //   from	to	target	type
    //   441	447	450	java/lang/InterruptedException
    //   30	39	513	java/lang/Exception
    //   4	25	528	java/io/IOException
    //   30	39	528	java/io/IOException
    //   43	422	528	java/io/IOException
    //   441	447	528	java/io/IOException
    //   452	487	528	java/io/IOException
    //   515	525	528	java/io/IOException
    //   4	25	610	org/xmlpull/v1/XmlPullParserException
    //   30	39	610	org/xmlpull/v1/XmlPullParserException
    //   43	422	610	org/xmlpull/v1/XmlPullParserException
    //   441	447	610	org/xmlpull/v1/XmlPullParserException
    //   452	487	610	org/xmlpull/v1/XmlPullParserException
    //   515	525	610	org/xmlpull/v1/XmlPullParserException
    //   4	25	651	org/apache/http/HttpException
    //   30	39	651	org/apache/http/HttpException
    //   43	422	651	org/apache/http/HttpException
    //   441	447	651	org/apache/http/HttpException
    //   452	487	651	org/apache/http/HttpException
    //   515	525	651	org/apache/http/HttpException
    //   4	25	692	java/lang/Exception
    //   43	422	692	java/lang/Exception
    //   441	447	692	java/lang/Exception
    //   452	487	692	java/lang/Exception
    //   515	525	692	java/lang/Exception
    //   4	25	733	finally
    //   30	39	733	finally
    //   43	422	733	finally
    //   441	447	733	finally
    //   452	487	733	finally
    //   515	525	733	finally
    //   530	580	733	finally
    //   612	627	733	finally
    //   653	668	733	finally
    //   694	709	733	finally
    //   4	25	763	java/lang/InterruptedException
    //   30	39	763	java/lang/InterruptedException
    //   43	422	763	java/lang/InterruptedException
    //   452	487	763	java/lang/InterruptedException
    //   515	525	763	java/lang/InterruptedException
  }
}

/* Location:           C:\Users\Jaap\Downloads\Code\WhatsApp-2.8.4278_dex2jar.jar
 * Qualified Name:     com.whatsapp.s9
 * JD-Core Version:    0.6.1
 */