package com.whatsapp;

import android.app.AlertDialog.Builder;
import android.app.Dialog;
import android.app.NotificationManager;
import android.app.PendingIntent;
import android.app.ProgressDialog;
import android.content.BroadcastReceiver;
import android.content.Intent;
import android.content.IntentFilter;
import android.content.SharedPreferences;
import android.content.SharedPreferences.Editor;
import android.os.Bundle;
import android.os.CountDownTimer;
import android.telephony.ServiceState;
import android.telephony.SmsManager;
import android.telephony.TelephonyManager;
import android.text.InputFilter;
import android.text.InputFilter.LengthFilter;
import android.text.SpannableStringBuilder;
import android.view.Menu;
import android.view.MenuItem;
import android.view.View;
import android.view.inputmethod.InputMethodManager;
import android.widget.Button;
import android.widget.EditText;
import android.widget.ProgressBar;
import android.widget.RelativeLayout;
import android.widget.TextView;
import java.io.IOException;
import java.util.Arrays;
import java.util.List;
import java.util.Random;

public class VerifySms extends VerifyNumber
{
  private static String A;
  private static short B;
  private static String C;
  private static boolean O;
  private static final String[] ab;
  private static int q;
  private static int r;
  private static CountDownTimer s;
  private static long t;
  private static long u;
  private static BroadcastReceiver v;
  private static BroadcastReceiver w;
  private static BroadcastReceiver x;
  private static String y;
  private static String z;
  private String D;
  private String E;
  private ProgressBar F;
  private TextView G;
  private TextView H;
  private EditText I;
  private Button J;
  private Button K;
  private long L;
  private long M;
  private long N;
  private String P = ab[2];
  private boolean Q = false;
  private CountDownTimer R;
  private CountDownTimer S = null;
  private long T = 1L;
  private long U = 60000L;
  boolean V = false;
  ProgressDialog W;
  BroadcastReceiver X = new VerifySms.1(this);
  BroadcastReceiver Y = new VerifySms.2(this);
  BroadcastReceiver Z = new VerifySms.3(this);

  // ERROR //
  static
  {
    // Byte code:
    //   0: bipush 69
    //   2: anewarray 54	java/lang/String
    //   5: astore_0
    //   6: ldc 56
    //   8: invokevirtual 60	java/lang/String:toCharArray	()[C
    //   11: astore_1
    //   12: aload_1
    //   13: arraylength
    //   14: istore_2
    //   15: iconst_0
    //   16: istore_3
    //   17: iload_2
    //   18: iload_3
    //   19: if_icmpgt +2910 -> 2929
    //   22: aload_0
    //   23: iconst_0
    //   24: new 54	java/lang/String
    //   27: dup
    //   28: aload_1
    //   29: invokespecial 64	java/lang/String:<init>	([C)V
    //   32: invokevirtual 68	java/lang/String:intern	()Ljava/lang/String;
    //   35: aastore
    //   36: ldc 70
    //   38: invokevirtual 60	java/lang/String:toCharArray	()[C
    //   41: astore 6
    //   43: aload 6
    //   45: arraylength
    //   46: istore 7
    //   48: iconst_0
    //   49: istore 8
    //   51: iload 7
    //   53: iload 8
    //   55: if_icmpgt +2960 -> 3015
    //   58: aload_0
    //   59: iconst_1
    //   60: new 54	java/lang/String
    //   63: dup
    //   64: aload 6
    //   66: invokespecial 64	java/lang/String:<init>	([C)V
    //   69: invokevirtual 68	java/lang/String:intern	()Ljava/lang/String;
    //   72: aastore
    //   73: ldc 72
    //   75: invokevirtual 60	java/lang/String:toCharArray	()[C
    //   78: astore 11
    //   80: aload 11
    //   82: arraylength
    //   83: istore 12
    //   85: iconst_0
    //   86: istore 13
    //   88: iload 12
    //   90: iload 13
    //   92: if_icmpgt +3013 -> 3105
    //   95: aload_0
    //   96: iconst_2
    //   97: new 54	java/lang/String
    //   100: dup
    //   101: aload 11
    //   103: invokespecial 64	java/lang/String:<init>	([C)V
    //   106: invokevirtual 68	java/lang/String:intern	()Ljava/lang/String;
    //   109: aastore
    //   110: ldc 74
    //   112: invokevirtual 60	java/lang/String:toCharArray	()[C
    //   115: astore 16
    //   117: aload 16
    //   119: arraylength
    //   120: istore 17
    //   122: iconst_0
    //   123: istore 18
    //   125: iload 17
    //   127: iload 18
    //   129: if_icmpgt +3068 -> 3197
    //   132: aload_0
    //   133: iconst_3
    //   134: new 54	java/lang/String
    //   137: dup
    //   138: aload 16
    //   140: invokespecial 64	java/lang/String:<init>	([C)V
    //   143: invokevirtual 68	java/lang/String:intern	()Ljava/lang/String;
    //   146: aastore
    //   147: ldc 76
    //   149: invokevirtual 60	java/lang/String:toCharArray	()[C
    //   152: astore 21
    //   154: aload 21
    //   156: arraylength
    //   157: istore 22
    //   159: iconst_0
    //   160: istore 23
    //   162: iload 22
    //   164: iload 23
    //   166: if_icmpgt +3123 -> 3289
    //   169: aload_0
    //   170: iconst_4
    //   171: new 54	java/lang/String
    //   174: dup
    //   175: aload 21
    //   177: invokespecial 64	java/lang/String:<init>	([C)V
    //   180: invokevirtual 68	java/lang/String:intern	()Ljava/lang/String;
    //   183: aastore
    //   184: ldc 78
    //   186: invokevirtual 60	java/lang/String:toCharArray	()[C
    //   189: astore 26
    //   191: aload 26
    //   193: arraylength
    //   194: istore 27
    //   196: iconst_0
    //   197: istore 28
    //   199: iload 27
    //   201: iload 28
    //   203: if_icmpgt +3178 -> 3381
    //   206: aload_0
    //   207: iconst_5
    //   208: new 54	java/lang/String
    //   211: dup
    //   212: aload 26
    //   214: invokespecial 64	java/lang/String:<init>	([C)V
    //   217: invokevirtual 68	java/lang/String:intern	()Ljava/lang/String;
    //   220: aastore
    //   221: ldc 80
    //   223: invokevirtual 60	java/lang/String:toCharArray	()[C
    //   226: astore 31
    //   228: aload 31
    //   230: arraylength
    //   231: istore 32
    //   233: iconst_0
    //   234: istore 33
    //   236: iload 32
    //   238: iload 33
    //   240: if_icmpgt +3233 -> 3473
    //   243: aload_0
    //   244: bipush 6
    //   246: new 54	java/lang/String
    //   249: dup
    //   250: aload 31
    //   252: invokespecial 64	java/lang/String:<init>	([C)V
    //   255: invokevirtual 68	java/lang/String:intern	()Ljava/lang/String;
    //   258: aastore
    //   259: ldc 82
    //   261: invokevirtual 60	java/lang/String:toCharArray	()[C
    //   264: astore 36
    //   266: aload 36
    //   268: arraylength
    //   269: istore 37
    //   271: iconst_0
    //   272: istore 38
    //   274: iload 37
    //   276: iload 38
    //   278: if_icmpgt +3287 -> 3565
    //   281: aload_0
    //   282: bipush 7
    //   284: new 54	java/lang/String
    //   287: dup
    //   288: aload 36
    //   290: invokespecial 64	java/lang/String:<init>	([C)V
    //   293: invokevirtual 68	java/lang/String:intern	()Ljava/lang/String;
    //   296: aastore
    //   297: ldc 84
    //   299: invokevirtual 60	java/lang/String:toCharArray	()[C
    //   302: astore 41
    //   304: aload 41
    //   306: arraylength
    //   307: istore 42
    //   309: iconst_0
    //   310: istore 43
    //   312: iload 42
    //   314: iload 43
    //   316: if_icmpgt +3341 -> 3657
    //   319: aload_0
    //   320: bipush 8
    //   322: new 54	java/lang/String
    //   325: dup
    //   326: aload 41
    //   328: invokespecial 64	java/lang/String:<init>	([C)V
    //   331: invokevirtual 68	java/lang/String:intern	()Ljava/lang/String;
    //   334: aastore
    //   335: ldc 86
    //   337: invokevirtual 60	java/lang/String:toCharArray	()[C
    //   340: astore 46
    //   342: aload 46
    //   344: arraylength
    //   345: istore 47
    //   347: iconst_0
    //   348: istore 48
    //   350: iload 47
    //   352: iload 48
    //   354: if_icmpgt +3395 -> 3749
    //   357: aload_0
    //   358: bipush 9
    //   360: new 54	java/lang/String
    //   363: dup
    //   364: aload 46
    //   366: invokespecial 64	java/lang/String:<init>	([C)V
    //   369: invokevirtual 68	java/lang/String:intern	()Ljava/lang/String;
    //   372: aastore
    //   373: ldc 88
    //   375: invokevirtual 60	java/lang/String:toCharArray	()[C
    //   378: astore 51
    //   380: aload 51
    //   382: arraylength
    //   383: istore 52
    //   385: iconst_0
    //   386: istore 53
    //   388: iload 52
    //   390: iload 53
    //   392: if_icmpgt +3449 -> 3841
    //   395: aload_0
    //   396: bipush 10
    //   398: new 54	java/lang/String
    //   401: dup
    //   402: aload 51
    //   404: invokespecial 64	java/lang/String:<init>	([C)V
    //   407: invokevirtual 68	java/lang/String:intern	()Ljava/lang/String;
    //   410: aastore
    //   411: ldc 90
    //   413: invokevirtual 60	java/lang/String:toCharArray	()[C
    //   416: astore 56
    //   418: aload 56
    //   420: arraylength
    //   421: istore 57
    //   423: iconst_0
    //   424: istore 58
    //   426: iload 57
    //   428: iload 58
    //   430: if_icmpgt +3503 -> 3933
    //   433: aload_0
    //   434: bipush 11
    //   436: new 54	java/lang/String
    //   439: dup
    //   440: aload 56
    //   442: invokespecial 64	java/lang/String:<init>	([C)V
    //   445: invokevirtual 68	java/lang/String:intern	()Ljava/lang/String;
    //   448: aastore
    //   449: ldc 92
    //   451: invokevirtual 60	java/lang/String:toCharArray	()[C
    //   454: astore 61
    //   456: aload 61
    //   458: arraylength
    //   459: istore 62
    //   461: iconst_0
    //   462: istore 63
    //   464: iload 62
    //   466: iload 63
    //   468: if_icmpgt +3557 -> 4025
    //   471: aload_0
    //   472: bipush 12
    //   474: new 54	java/lang/String
    //   477: dup
    //   478: aload 61
    //   480: invokespecial 64	java/lang/String:<init>	([C)V
    //   483: invokevirtual 68	java/lang/String:intern	()Ljava/lang/String;
    //   486: aastore
    //   487: ldc 94
    //   489: invokevirtual 60	java/lang/String:toCharArray	()[C
    //   492: astore 66
    //   494: aload 66
    //   496: arraylength
    //   497: istore 67
    //   499: iconst_0
    //   500: istore 68
    //   502: iload 67
    //   504: iload 68
    //   506: if_icmpgt +3611 -> 4117
    //   509: aload_0
    //   510: bipush 13
    //   512: new 54	java/lang/String
    //   515: dup
    //   516: aload 66
    //   518: invokespecial 64	java/lang/String:<init>	([C)V
    //   521: invokevirtual 68	java/lang/String:intern	()Ljava/lang/String;
    //   524: aastore
    //   525: ldc 96
    //   527: invokevirtual 60	java/lang/String:toCharArray	()[C
    //   530: astore 71
    //   532: aload 71
    //   534: arraylength
    //   535: istore 72
    //   537: iconst_0
    //   538: istore 73
    //   540: iload 72
    //   542: iload 73
    //   544: if_icmpgt +3665 -> 4209
    //   547: aload_0
    //   548: bipush 14
    //   550: new 54	java/lang/String
    //   553: dup
    //   554: aload 71
    //   556: invokespecial 64	java/lang/String:<init>	([C)V
    //   559: invokevirtual 68	java/lang/String:intern	()Ljava/lang/String;
    //   562: aastore
    //   563: ldc 98
    //   565: invokevirtual 60	java/lang/String:toCharArray	()[C
    //   568: astore 76
    //   570: aload 76
    //   572: arraylength
    //   573: istore 77
    //   575: iconst_0
    //   576: istore 78
    //   578: iload 77
    //   580: iload 78
    //   582: if_icmpgt +3719 -> 4301
    //   585: aload_0
    //   586: bipush 15
    //   588: new 54	java/lang/String
    //   591: dup
    //   592: aload 76
    //   594: invokespecial 64	java/lang/String:<init>	([C)V
    //   597: invokevirtual 68	java/lang/String:intern	()Ljava/lang/String;
    //   600: aastore
    //   601: ldc 100
    //   603: invokevirtual 60	java/lang/String:toCharArray	()[C
    //   606: astore 81
    //   608: aload 81
    //   610: arraylength
    //   611: istore 82
    //   613: iconst_0
    //   614: istore 83
    //   616: iload 82
    //   618: iload 83
    //   620: if_icmpgt +3773 -> 4393
    //   623: aload_0
    //   624: bipush 16
    //   626: new 54	java/lang/String
    //   629: dup
    //   630: aload 81
    //   632: invokespecial 64	java/lang/String:<init>	([C)V
    //   635: invokevirtual 68	java/lang/String:intern	()Ljava/lang/String;
    //   638: aastore
    //   639: ldc 102
    //   641: invokevirtual 60	java/lang/String:toCharArray	()[C
    //   644: astore 86
    //   646: aload 86
    //   648: arraylength
    //   649: istore 87
    //   651: iconst_0
    //   652: istore 88
    //   654: iload 87
    //   656: iload 88
    //   658: if_icmpgt +3827 -> 4485
    //   661: aload_0
    //   662: bipush 17
    //   664: new 54	java/lang/String
    //   667: dup
    //   668: aload 86
    //   670: invokespecial 64	java/lang/String:<init>	([C)V
    //   673: invokevirtual 68	java/lang/String:intern	()Ljava/lang/String;
    //   676: aastore
    //   677: ldc 104
    //   679: invokevirtual 60	java/lang/String:toCharArray	()[C
    //   682: astore 91
    //   684: aload 91
    //   686: arraylength
    //   687: istore 92
    //   689: iconst_0
    //   690: istore 93
    //   692: iload 92
    //   694: iload 93
    //   696: if_icmpgt +3881 -> 4577
    //   699: aload_0
    //   700: bipush 18
    //   702: new 54	java/lang/String
    //   705: dup
    //   706: aload 91
    //   708: invokespecial 64	java/lang/String:<init>	([C)V
    //   711: invokevirtual 68	java/lang/String:intern	()Ljava/lang/String;
    //   714: aastore
    //   715: ldc 106
    //   717: invokevirtual 60	java/lang/String:toCharArray	()[C
    //   720: astore 96
    //   722: aload 96
    //   724: arraylength
    //   725: istore 97
    //   727: iconst_0
    //   728: istore 98
    //   730: iload 97
    //   732: iload 98
    //   734: if_icmpgt +3935 -> 4669
    //   737: aload_0
    //   738: bipush 19
    //   740: new 54	java/lang/String
    //   743: dup
    //   744: aload 96
    //   746: invokespecial 64	java/lang/String:<init>	([C)V
    //   749: invokevirtual 68	java/lang/String:intern	()Ljava/lang/String;
    //   752: aastore
    //   753: ldc 108
    //   755: invokevirtual 60	java/lang/String:toCharArray	()[C
    //   758: astore 101
    //   760: aload 101
    //   762: arraylength
    //   763: istore 102
    //   765: iconst_0
    //   766: istore 103
    //   768: iload 102
    //   770: iload 103
    //   772: if_icmpgt +3989 -> 4761
    //   775: aload_0
    //   776: bipush 20
    //   778: new 54	java/lang/String
    //   781: dup
    //   782: aload 101
    //   784: invokespecial 64	java/lang/String:<init>	([C)V
    //   787: invokevirtual 68	java/lang/String:intern	()Ljava/lang/String;
    //   790: aastore
    //   791: ldc 110
    //   793: invokevirtual 60	java/lang/String:toCharArray	()[C
    //   796: astore 106
    //   798: aload 106
    //   800: arraylength
    //   801: istore 107
    //   803: iconst_0
    //   804: istore 108
    //   806: iload 107
    //   808: iload 108
    //   810: if_icmpgt +4043 -> 4853
    //   813: aload_0
    //   814: bipush 21
    //   816: new 54	java/lang/String
    //   819: dup
    //   820: aload 106
    //   822: invokespecial 64	java/lang/String:<init>	([C)V
    //   825: invokevirtual 68	java/lang/String:intern	()Ljava/lang/String;
    //   828: aastore
    //   829: ldc 112
    //   831: invokevirtual 60	java/lang/String:toCharArray	()[C
    //   834: astore 111
    //   836: aload 111
    //   838: arraylength
    //   839: istore 112
    //   841: iconst_0
    //   842: istore 113
    //   844: iload 112
    //   846: iload 113
    //   848: if_icmpgt +4097 -> 4945
    //   851: aload_0
    //   852: bipush 22
    //   854: new 54	java/lang/String
    //   857: dup
    //   858: aload 111
    //   860: invokespecial 64	java/lang/String:<init>	([C)V
    //   863: invokevirtual 68	java/lang/String:intern	()Ljava/lang/String;
    //   866: aastore
    //   867: ldc 114
    //   869: invokevirtual 60	java/lang/String:toCharArray	()[C
    //   872: astore 116
    //   874: aload 116
    //   876: arraylength
    //   877: istore 117
    //   879: iconst_0
    //   880: istore 118
    //   882: iload 117
    //   884: iload 118
    //   886: if_icmpgt +4151 -> 5037
    //   889: aload_0
    //   890: bipush 23
    //   892: new 54	java/lang/String
    //   895: dup
    //   896: aload 116
    //   898: invokespecial 64	java/lang/String:<init>	([C)V
    //   901: invokevirtual 68	java/lang/String:intern	()Ljava/lang/String;
    //   904: aastore
    //   905: ldc 116
    //   907: invokevirtual 60	java/lang/String:toCharArray	()[C
    //   910: astore 121
    //   912: aload 121
    //   914: arraylength
    //   915: istore 122
    //   917: iconst_0
    //   918: istore 123
    //   920: iload 122
    //   922: iload 123
    //   924: if_icmpgt +4205 -> 5129
    //   927: aload_0
    //   928: bipush 24
    //   930: new 54	java/lang/String
    //   933: dup
    //   934: aload 121
    //   936: invokespecial 64	java/lang/String:<init>	([C)V
    //   939: invokevirtual 68	java/lang/String:intern	()Ljava/lang/String;
    //   942: aastore
    //   943: ldc 118
    //   945: invokevirtual 60	java/lang/String:toCharArray	()[C
    //   948: astore 126
    //   950: aload 126
    //   952: arraylength
    //   953: istore 127
    //   955: iconst_0
    //   956: istore 128
    //   958: iload 127
    //   960: iload 128
    //   962: if_icmpgt +4259 -> 5221
    //   965: aload_0
    //   966: bipush 25
    //   968: new 54	java/lang/String
    //   971: dup
    //   972: aload 126
    //   974: invokespecial 64	java/lang/String:<init>	([C)V
    //   977: invokevirtual 68	java/lang/String:intern	()Ljava/lang/String;
    //   980: aastore
    //   981: ldc 120
    //   983: invokevirtual 60	java/lang/String:toCharArray	()[C
    //   986: astore 131
    //   988: aload 131
    //   990: arraylength
    //   991: istore 132
    //   993: iconst_0
    //   994: istore 133
    //   996: iload 132
    //   998: iload 133
    //   1000: if_icmpgt +4313 -> 5313
    //   1003: aload_0
    //   1004: bipush 26
    //   1006: new 54	java/lang/String
    //   1009: dup
    //   1010: aload 131
    //   1012: invokespecial 64	java/lang/String:<init>	([C)V
    //   1015: invokevirtual 68	java/lang/String:intern	()Ljava/lang/String;
    //   1018: aastore
    //   1019: ldc 122
    //   1021: invokevirtual 60	java/lang/String:toCharArray	()[C
    //   1024: astore 136
    //   1026: aload 136
    //   1028: arraylength
    //   1029: istore 137
    //   1031: iconst_0
    //   1032: istore 138
    //   1034: iload 137
    //   1036: iload 138
    //   1038: if_icmpgt +4367 -> 5405
    //   1041: aload_0
    //   1042: bipush 27
    //   1044: new 54	java/lang/String
    //   1047: dup
    //   1048: aload 136
    //   1050: invokespecial 64	java/lang/String:<init>	([C)V
    //   1053: invokevirtual 68	java/lang/String:intern	()Ljava/lang/String;
    //   1056: aastore
    //   1057: ldc 124
    //   1059: invokevirtual 60	java/lang/String:toCharArray	()[C
    //   1062: astore 141
    //   1064: aload 141
    //   1066: arraylength
    //   1067: istore 142
    //   1069: iconst_0
    //   1070: istore 143
    //   1072: iload 142
    //   1074: iload 143
    //   1076: if_icmpgt +4421 -> 5497
    //   1079: aload_0
    //   1080: bipush 28
    //   1082: new 54	java/lang/String
    //   1085: dup
    //   1086: aload 141
    //   1088: invokespecial 64	java/lang/String:<init>	([C)V
    //   1091: invokevirtual 68	java/lang/String:intern	()Ljava/lang/String;
    //   1094: aastore
    //   1095: ldc 126
    //   1097: invokevirtual 60	java/lang/String:toCharArray	()[C
    //   1100: astore 146
    //   1102: aload 146
    //   1104: arraylength
    //   1105: istore 147
    //   1107: iconst_0
    //   1108: istore 148
    //   1110: iload 147
    //   1112: iload 148
    //   1114: if_icmpgt +4475 -> 5589
    //   1117: aload_0
    //   1118: bipush 29
    //   1120: new 54	java/lang/String
    //   1123: dup
    //   1124: aload 146
    //   1126: invokespecial 64	java/lang/String:<init>	([C)V
    //   1129: invokevirtual 68	java/lang/String:intern	()Ljava/lang/String;
    //   1132: aastore
    //   1133: ldc 128
    //   1135: invokevirtual 60	java/lang/String:toCharArray	()[C
    //   1138: astore 151
    //   1140: aload 151
    //   1142: arraylength
    //   1143: istore 152
    //   1145: iconst_0
    //   1146: istore 153
    //   1148: iload 152
    //   1150: iload 153
    //   1152: if_icmpgt +4529 -> 5681
    //   1155: aload_0
    //   1156: bipush 30
    //   1158: new 54	java/lang/String
    //   1161: dup
    //   1162: aload 151
    //   1164: invokespecial 64	java/lang/String:<init>	([C)V
    //   1167: invokevirtual 68	java/lang/String:intern	()Ljava/lang/String;
    //   1170: aastore
    //   1171: ldc 130
    //   1173: invokevirtual 60	java/lang/String:toCharArray	()[C
    //   1176: astore 156
    //   1178: aload 156
    //   1180: arraylength
    //   1181: istore 157
    //   1183: iconst_0
    //   1184: istore 158
    //   1186: iload 157
    //   1188: iload 158
    //   1190: if_icmpgt +4583 -> 5773
    //   1193: aload_0
    //   1194: bipush 31
    //   1196: new 54	java/lang/String
    //   1199: dup
    //   1200: aload 156
    //   1202: invokespecial 64	java/lang/String:<init>	([C)V
    //   1205: invokevirtual 68	java/lang/String:intern	()Ljava/lang/String;
    //   1208: aastore
    //   1209: ldc 132
    //   1211: invokevirtual 60	java/lang/String:toCharArray	()[C
    //   1214: astore 161
    //   1216: aload 161
    //   1218: arraylength
    //   1219: istore 162
    //   1221: iconst_0
    //   1222: istore 163
    //   1224: iload 162
    //   1226: iload 163
    //   1228: if_icmpgt +4637 -> 5865
    //   1231: aload_0
    //   1232: bipush 32
    //   1234: new 54	java/lang/String
    //   1237: dup
    //   1238: aload 161
    //   1240: invokespecial 64	java/lang/String:<init>	([C)V
    //   1243: invokevirtual 68	java/lang/String:intern	()Ljava/lang/String;
    //   1246: aastore
    //   1247: ldc 134
    //   1249: invokevirtual 60	java/lang/String:toCharArray	()[C
    //   1252: astore 166
    //   1254: aload 166
    //   1256: arraylength
    //   1257: istore 167
    //   1259: iconst_0
    //   1260: istore 168
    //   1262: iload 167
    //   1264: iload 168
    //   1266: if_icmpgt +4691 -> 5957
    //   1269: aload_0
    //   1270: bipush 33
    //   1272: new 54	java/lang/String
    //   1275: dup
    //   1276: aload 166
    //   1278: invokespecial 64	java/lang/String:<init>	([C)V
    //   1281: invokevirtual 68	java/lang/String:intern	()Ljava/lang/String;
    //   1284: aastore
    //   1285: ldc 136
    //   1287: invokevirtual 60	java/lang/String:toCharArray	()[C
    //   1290: astore 171
    //   1292: aload 171
    //   1294: arraylength
    //   1295: istore 172
    //   1297: iconst_0
    //   1298: istore 173
    //   1300: iload 172
    //   1302: iload 173
    //   1304: if_icmpgt +4745 -> 6049
    //   1307: aload_0
    //   1308: bipush 34
    //   1310: new 54	java/lang/String
    //   1313: dup
    //   1314: aload 171
    //   1316: invokespecial 64	java/lang/String:<init>	([C)V
    //   1319: invokevirtual 68	java/lang/String:intern	()Ljava/lang/String;
    //   1322: aastore
    //   1323: ldc 138
    //   1325: invokevirtual 60	java/lang/String:toCharArray	()[C
    //   1328: astore 176
    //   1330: aload 176
    //   1332: arraylength
    //   1333: istore 177
    //   1335: iconst_0
    //   1336: istore 178
    //   1338: iload 177
    //   1340: iload 178
    //   1342: if_icmpgt +4799 -> 6141
    //   1345: aload_0
    //   1346: bipush 35
    //   1348: new 54	java/lang/String
    //   1351: dup
    //   1352: aload 176
    //   1354: invokespecial 64	java/lang/String:<init>	([C)V
    //   1357: invokevirtual 68	java/lang/String:intern	()Ljava/lang/String;
    //   1360: aastore
    //   1361: ldc 140
    //   1363: invokevirtual 60	java/lang/String:toCharArray	()[C
    //   1366: astore 181
    //   1368: aload 181
    //   1370: arraylength
    //   1371: istore 182
    //   1373: iconst_0
    //   1374: istore 183
    //   1376: iload 182
    //   1378: iload 183
    //   1380: if_icmpgt +4853 -> 6233
    //   1383: aload_0
    //   1384: bipush 36
    //   1386: new 54	java/lang/String
    //   1389: dup
    //   1390: aload 181
    //   1392: invokespecial 64	java/lang/String:<init>	([C)V
    //   1395: invokevirtual 68	java/lang/String:intern	()Ljava/lang/String;
    //   1398: aastore
    //   1399: ldc 142
    //   1401: invokevirtual 60	java/lang/String:toCharArray	()[C
    //   1404: astore 186
    //   1406: aload 186
    //   1408: arraylength
    //   1409: istore 187
    //   1411: iconst_0
    //   1412: istore 188
    //   1414: iload 187
    //   1416: iload 188
    //   1418: if_icmpgt +4907 -> 6325
    //   1421: aload_0
    //   1422: bipush 37
    //   1424: new 54	java/lang/String
    //   1427: dup
    //   1428: aload 186
    //   1430: invokespecial 64	java/lang/String:<init>	([C)V
    //   1433: invokevirtual 68	java/lang/String:intern	()Ljava/lang/String;
    //   1436: aastore
    //   1437: ldc 144
    //   1439: invokevirtual 60	java/lang/String:toCharArray	()[C
    //   1442: astore 191
    //   1444: aload 191
    //   1446: arraylength
    //   1447: istore 192
    //   1449: iconst_0
    //   1450: istore 193
    //   1452: iload 192
    //   1454: iload 193
    //   1456: if_icmpgt +4961 -> 6417
    //   1459: aload_0
    //   1460: bipush 38
    //   1462: new 54	java/lang/String
    //   1465: dup
    //   1466: aload 191
    //   1468: invokespecial 64	java/lang/String:<init>	([C)V
    //   1471: invokevirtual 68	java/lang/String:intern	()Ljava/lang/String;
    //   1474: aastore
    //   1475: ldc 146
    //   1477: invokevirtual 60	java/lang/String:toCharArray	()[C
    //   1480: astore 196
    //   1482: aload 196
    //   1484: arraylength
    //   1485: istore 197
    //   1487: iconst_0
    //   1488: istore 198
    //   1490: iload 197
    //   1492: iload 198
    //   1494: if_icmpgt +5015 -> 6509
    //   1497: aload_0
    //   1498: bipush 39
    //   1500: new 54	java/lang/String
    //   1503: dup
    //   1504: aload 196
    //   1506: invokespecial 64	java/lang/String:<init>	([C)V
    //   1509: invokevirtual 68	java/lang/String:intern	()Ljava/lang/String;
    //   1512: aastore
    //   1513: ldc 148
    //   1515: invokevirtual 60	java/lang/String:toCharArray	()[C
    //   1518: astore 201
    //   1520: aload 201
    //   1522: arraylength
    //   1523: istore 202
    //   1525: iconst_0
    //   1526: istore 203
    //   1528: iload 202
    //   1530: iload 203
    //   1532: if_icmpgt +5069 -> 6601
    //   1535: aload_0
    //   1536: bipush 40
    //   1538: new 54	java/lang/String
    //   1541: dup
    //   1542: aload 201
    //   1544: invokespecial 64	java/lang/String:<init>	([C)V
    //   1547: invokevirtual 68	java/lang/String:intern	()Ljava/lang/String;
    //   1550: aastore
    //   1551: ldc 150
    //   1553: invokevirtual 60	java/lang/String:toCharArray	()[C
    //   1556: astore 206
    //   1558: aload 206
    //   1560: arraylength
    //   1561: istore 207
    //   1563: iconst_0
    //   1564: istore 208
    //   1566: iload 207
    //   1568: iload 208
    //   1570: if_icmpgt +5123 -> 6693
    //   1573: aload_0
    //   1574: bipush 41
    //   1576: new 54	java/lang/String
    //   1579: dup
    //   1580: aload 206
    //   1582: invokespecial 64	java/lang/String:<init>	([C)V
    //   1585: invokevirtual 68	java/lang/String:intern	()Ljava/lang/String;
    //   1588: aastore
    //   1589: ldc 152
    //   1591: invokevirtual 60	java/lang/String:toCharArray	()[C
    //   1594: astore 211
    //   1596: aload 211
    //   1598: arraylength
    //   1599: istore 212
    //   1601: iconst_0
    //   1602: istore 213
    //   1604: iload 212
    //   1606: iload 213
    //   1608: if_icmpgt +5177 -> 6785
    //   1611: aload_0
    //   1612: bipush 42
    //   1614: new 54	java/lang/String
    //   1617: dup
    //   1618: aload 211
    //   1620: invokespecial 64	java/lang/String:<init>	([C)V
    //   1623: invokevirtual 68	java/lang/String:intern	()Ljava/lang/String;
    //   1626: aastore
    //   1627: ldc 154
    //   1629: invokevirtual 60	java/lang/String:toCharArray	()[C
    //   1632: astore 216
    //   1634: aload 216
    //   1636: arraylength
    //   1637: istore 217
    //   1639: iconst_0
    //   1640: istore 218
    //   1642: iload 217
    //   1644: iload 218
    //   1646: if_icmpgt +5231 -> 6877
    //   1649: aload_0
    //   1650: bipush 43
    //   1652: new 54	java/lang/String
    //   1655: dup
    //   1656: aload 216
    //   1658: invokespecial 64	java/lang/String:<init>	([C)V
    //   1661: invokevirtual 68	java/lang/String:intern	()Ljava/lang/String;
    //   1664: aastore
    //   1665: ldc 156
    //   1667: invokevirtual 60	java/lang/String:toCharArray	()[C
    //   1670: astore 221
    //   1672: aload 221
    //   1674: arraylength
    //   1675: istore 222
    //   1677: iconst_0
    //   1678: istore 223
    //   1680: iload 222
    //   1682: iload 223
    //   1684: if_icmpgt +5285 -> 6969
    //   1687: aload_0
    //   1688: bipush 44
    //   1690: new 54	java/lang/String
    //   1693: dup
    //   1694: aload 221
    //   1696: invokespecial 64	java/lang/String:<init>	([C)V
    //   1699: invokevirtual 68	java/lang/String:intern	()Ljava/lang/String;
    //   1702: aastore
    //   1703: ldc 158
    //   1705: invokevirtual 60	java/lang/String:toCharArray	()[C
    //   1708: astore 226
    //   1710: aload 226
    //   1712: arraylength
    //   1713: istore 227
    //   1715: iconst_0
    //   1716: istore 228
    //   1718: iload 227
    //   1720: iload 228
    //   1722: if_icmpgt +5339 -> 7061
    //   1725: aload_0
    //   1726: bipush 45
    //   1728: new 54	java/lang/String
    //   1731: dup
    //   1732: aload 226
    //   1734: invokespecial 64	java/lang/String:<init>	([C)V
    //   1737: invokevirtual 68	java/lang/String:intern	()Ljava/lang/String;
    //   1740: aastore
    //   1741: ldc 160
    //   1743: invokevirtual 60	java/lang/String:toCharArray	()[C
    //   1746: astore 231
    //   1748: aload 231
    //   1750: arraylength
    //   1751: istore 232
    //   1753: iconst_0
    //   1754: istore 233
    //   1756: iload 232
    //   1758: iload 233
    //   1760: if_icmpgt +5393 -> 7153
    //   1763: aload_0
    //   1764: bipush 46
    //   1766: new 54	java/lang/String
    //   1769: dup
    //   1770: aload 231
    //   1772: invokespecial 64	java/lang/String:<init>	([C)V
    //   1775: invokevirtual 68	java/lang/String:intern	()Ljava/lang/String;
    //   1778: aastore
    //   1779: ldc 162
    //   1781: invokevirtual 60	java/lang/String:toCharArray	()[C
    //   1784: astore 236
    //   1786: aload 236
    //   1788: arraylength
    //   1789: istore 237
    //   1791: iconst_0
    //   1792: istore 238
    //   1794: iload 237
    //   1796: iload 238
    //   1798: if_icmpgt +5447 -> 7245
    //   1801: aload_0
    //   1802: bipush 47
    //   1804: new 54	java/lang/String
    //   1807: dup
    //   1808: aload 236
    //   1810: invokespecial 64	java/lang/String:<init>	([C)V
    //   1813: invokevirtual 68	java/lang/String:intern	()Ljava/lang/String;
    //   1816: aastore
    //   1817: ldc 164
    //   1819: invokevirtual 60	java/lang/String:toCharArray	()[C
    //   1822: astore 241
    //   1824: aload 241
    //   1826: arraylength
    //   1827: istore 242
    //   1829: iconst_0
    //   1830: istore 243
    //   1832: iload 242
    //   1834: iload 243
    //   1836: if_icmpgt +5501 -> 7337
    //   1839: aload_0
    //   1840: bipush 48
    //   1842: new 54	java/lang/String
    //   1845: dup
    //   1846: aload 241
    //   1848: invokespecial 64	java/lang/String:<init>	([C)V
    //   1851: invokevirtual 68	java/lang/String:intern	()Ljava/lang/String;
    //   1854: aastore
    //   1855: ldc 166
    //   1857: invokevirtual 60	java/lang/String:toCharArray	()[C
    //   1860: astore 246
    //   1862: aload 246
    //   1864: arraylength
    //   1865: istore 247
    //   1867: iconst_0
    //   1868: istore 248
    //   1870: iload 247
    //   1872: iload 248
    //   1874: if_icmpgt +5555 -> 7429
    //   1877: aload_0
    //   1878: bipush 49
    //   1880: new 54	java/lang/String
    //   1883: dup
    //   1884: aload 246
    //   1886: invokespecial 64	java/lang/String:<init>	([C)V
    //   1889: invokevirtual 68	java/lang/String:intern	()Ljava/lang/String;
    //   1892: aastore
    //   1893: ldc 168
    //   1895: invokevirtual 60	java/lang/String:toCharArray	()[C
    //   1898: astore 251
    //   1900: aload 251
    //   1902: arraylength
    //   1903: istore 252
    //   1905: iconst_0
    //   1906: istore 253
    //   1908: iload 252
    //   1910: iload 253
    //   1912: if_icmpgt +5609 -> 7521
    //   1915: aload_0
    //   1916: bipush 50
    //   1918: new 54	java/lang/String
    //   1921: dup
    //   1922: aload 251
    //   1924: invokespecial 64	java/lang/String:<init>	([C)V
    //   1927: invokevirtual 68	java/lang/String:intern	()Ljava/lang/String;
    //   1930: aastore
    //   1931: ldc 170
    //   1933: invokevirtual 60	java/lang/String:toCharArray	()[C
    //   1936: wide
    //   1940: wide
    //   1944: arraylength
    //   1945: wide
    //   1949: iconst_0
    //   1950: wide
    //   1954: wide
    //   1958: wide
    //   1962: if_icmpgt +5651 -> 7613
    //   1965: aload_0
    //   1966: bipush 51
    //   1968: new 54	java/lang/String
    //   1971: dup
    //   1972: wide
    //   1976: invokespecial 64	java/lang/String:<init>	([C)V
    //   1979: invokevirtual 68	java/lang/String:intern	()Ljava/lang/String;
    //   1982: aastore
    //   1983: ldc 172
    //   1985: invokevirtual 60	java/lang/String:toCharArray	()[C
    //   1988: wide
    //   1992: wide
    //   1996: arraylength
    //   1997: wide
    //   2001: iconst_0
    //   2002: wide
    //   2006: wide
    //   2010: wide
    //   2014: if_icmpgt +5720 -> 7734
    //   2017: aload_0
    //   2018: bipush 52
    //   2020: new 54	java/lang/String
    //   2023: dup
    //   2024: wide
    //   2028: invokespecial 64	java/lang/String:<init>	([C)V
    //   2031: invokevirtual 68	java/lang/String:intern	()Ljava/lang/String;
    //   2034: aastore
    //   2035: ldc 174
    //   2037: invokevirtual 60	java/lang/String:toCharArray	()[C
    //   2040: wide
    //   2044: wide
    //   2048: arraylength
    //   2049: wide
    //   2053: iconst_0
    //   2054: wide
    //   2058: wide
    //   2062: wide
    //   2066: if_icmpgt +5788 -> 7854
    //   2069: aload_0
    //   2070: bipush 53
    //   2072: new 54	java/lang/String
    //   2075: dup
    //   2076: wide
    //   2080: invokespecial 64	java/lang/String:<init>	([C)V
    //   2083: invokevirtual 68	java/lang/String:intern	()Ljava/lang/String;
    //   2086: aastore
    //   2087: ldc 176
    //   2089: invokevirtual 60	java/lang/String:toCharArray	()[C
    //   2092: wide
    //   2096: wide
    //   2100: arraylength
    //   2101: wide
    //   2105: iconst_0
    //   2106: wide
    //   2110: wide
    //   2114: wide
    //   2118: if_icmpgt +5856 -> 7974
    //   2121: aload_0
    //   2122: bipush 54
    //   2124: new 54	java/lang/String
    //   2127: dup
    //   2128: wide
    //   2132: invokespecial 64	java/lang/String:<init>	([C)V
    //   2135: invokevirtual 68	java/lang/String:intern	()Ljava/lang/String;
    //   2138: aastore
    //   2139: ldc 178
    //   2141: invokevirtual 60	java/lang/String:toCharArray	()[C
    //   2144: wide
    //   2148: wide
    //   2152: arraylength
    //   2153: wide
    //   2157: iconst_0
    //   2158: wide
    //   2162: wide
    //   2166: wide
    //   2170: if_icmpgt +5924 -> 8094
    //   2173: aload_0
    //   2174: bipush 55
    //   2176: new 54	java/lang/String
    //   2179: dup
    //   2180: wide
    //   2184: invokespecial 64	java/lang/String:<init>	([C)V
    //   2187: invokevirtual 68	java/lang/String:intern	()Ljava/lang/String;
    //   2190: aastore
    //   2191: ldc 180
    //   2193: invokevirtual 60	java/lang/String:toCharArray	()[C
    //   2196: wide
    //   2200: wide
    //   2204: arraylength
    //   2205: wide
    //   2209: iconst_0
    //   2210: wide
    //   2214: wide
    //   2218: wide
    //   2222: if_icmpgt +5992 -> 8214
    //   2225: aload_0
    //   2226: bipush 56
    //   2228: new 54	java/lang/String
    //   2231: dup
    //   2232: wide
    //   2236: invokespecial 64	java/lang/String:<init>	([C)V
    //   2239: invokevirtual 68	java/lang/String:intern	()Ljava/lang/String;
    //   2242: aastore
    //   2243: ldc 182
    //   2245: invokevirtual 60	java/lang/String:toCharArray	()[C
    //   2248: wide
    //   2252: wide
    //   2256: arraylength
    //   2257: wide
    //   2261: iconst_0
    //   2262: wide
    //   2266: wide
    //   2270: wide
    //   2274: if_icmpgt +6060 -> 8334
    //   2277: aload_0
    //   2278: bipush 57
    //   2280: new 54	java/lang/String
    //   2283: dup
    //   2284: wide
    //   2288: invokespecial 64	java/lang/String:<init>	([C)V
    //   2291: invokevirtual 68	java/lang/String:intern	()Ljava/lang/String;
    //   2294: aastore
    //   2295: ldc 184
    //   2297: invokevirtual 60	java/lang/String:toCharArray	()[C
    //   2300: wide
    //   2304: wide
    //   2308: arraylength
    //   2309: wide
    //   2313: iconst_0
    //   2314: wide
    //   2318: wide
    //   2322: wide
    //   2326: if_icmpgt +6128 -> 8454
    //   2329: aload_0
    //   2330: bipush 58
    //   2332: new 54	java/lang/String
    //   2335: dup
    //   2336: wide
    //   2340: invokespecial 64	java/lang/String:<init>	([C)V
    //   2343: invokevirtual 68	java/lang/String:intern	()Ljava/lang/String;
    //   2346: aastore
    //   2347: ldc 186
    //   2349: invokevirtual 60	java/lang/String:toCharArray	()[C
    //   2352: wide
    //   2356: wide
    //   2360: arraylength
    //   2361: wide
    //   2365: iconst_0
    //   2366: wide
    //   2370: wide
    //   2374: wide
    //   2378: if_icmpgt +6196 -> 8574
    //   2381: aload_0
    //   2382: bipush 59
    //   2384: new 54	java/lang/String
    //   2387: dup
    //   2388: wide
    //   2392: invokespecial 64	java/lang/String:<init>	([C)V
    //   2395: invokevirtual 68	java/lang/String:intern	()Ljava/lang/String;
    //   2398: aastore
    //   2399: ldc 188
    //   2401: invokevirtual 60	java/lang/String:toCharArray	()[C
    //   2404: wide
    //   2408: wide
    //   2412: arraylength
    //   2413: wide
    //   2417: iconst_0
    //   2418: wide
    //   2422: wide
    //   2426: wide
    //   2430: if_icmpgt +6264 -> 8694
    //   2433: aload_0
    //   2434: bipush 60
    //   2436: new 54	java/lang/String
    //   2439: dup
    //   2440: wide
    //   2444: invokespecial 64	java/lang/String:<init>	([C)V
    //   2447: invokevirtual 68	java/lang/String:intern	()Ljava/lang/String;
    //   2450: aastore
    //   2451: ldc 190
    //   2453: invokevirtual 60	java/lang/String:toCharArray	()[C
    //   2456: wide
    //   2460: wide
    //   2464: arraylength
    //   2465: wide
    //   2469: iconst_0
    //   2470: wide
    //   2474: wide
    //   2478: wide
    //   2482: if_icmpgt +6332 -> 8814
    //   2485: aload_0
    //   2486: bipush 61
    //   2488: new 54	java/lang/String
    //   2491: dup
    //   2492: wide
    //   2496: invokespecial 64	java/lang/String:<init>	([C)V
    //   2499: invokevirtual 68	java/lang/String:intern	()Ljava/lang/String;
    //   2502: aastore
    //   2503: ldc 192
    //   2505: invokevirtual 60	java/lang/String:toCharArray	()[C
    //   2508: wide
    //   2512: wide
    //   2516: arraylength
    //   2517: wide
    //   2521: iconst_0
    //   2522: wide
    //   2526: wide
    //   2530: wide
    //   2534: if_icmpgt +6400 -> 8934
    //   2537: aload_0
    //   2538: bipush 62
    //   2540: new 54	java/lang/String
    //   2543: dup
    //   2544: wide
    //   2548: invokespecial 64	java/lang/String:<init>	([C)V
    //   2551: invokevirtual 68	java/lang/String:intern	()Ljava/lang/String;
    //   2554: aastore
    //   2555: ldc 194
    //   2557: invokevirtual 60	java/lang/String:toCharArray	()[C
    //   2560: wide
    //   2564: wide
    //   2568: arraylength
    //   2569: wide
    //   2573: iconst_0
    //   2574: wide
    //   2578: wide
    //   2582: wide
    //   2586: if_icmpgt +6468 -> 9054
    //   2589: aload_0
    //   2590: bipush 63
    //   2592: new 54	java/lang/String
    //   2595: dup
    //   2596: wide
    //   2600: invokespecial 64	java/lang/String:<init>	([C)V
    //   2603: invokevirtual 68	java/lang/String:intern	()Ljava/lang/String;
    //   2606: aastore
    //   2607: ldc 196
    //   2609: invokevirtual 60	java/lang/String:toCharArray	()[C
    //   2612: wide
    //   2616: wide
    //   2620: arraylength
    //   2621: wide
    //   2625: iconst_0
    //   2626: wide
    //   2630: wide
    //   2634: wide
    //   2638: if_icmpgt +6536 -> 9174
    //   2641: aload_0
    //   2642: bipush 64
    //   2644: new 54	java/lang/String
    //   2647: dup
    //   2648: wide
    //   2652: invokespecial 64	java/lang/String:<init>	([C)V
    //   2655: invokevirtual 68	java/lang/String:intern	()Ljava/lang/String;
    //   2658: aastore
    //   2659: ldc 198
    //   2661: invokevirtual 60	java/lang/String:toCharArray	()[C
    //   2664: wide
    //   2668: wide
    //   2672: arraylength
    //   2673: wide
    //   2677: iconst_0
    //   2678: wide
    //   2682: wide
    //   2686: wide
    //   2690: if_icmpgt +6604 -> 9294
    //   2693: aload_0
    //   2694: bipush 65
    //   2696: new 54	java/lang/String
    //   2699: dup
    //   2700: wide
    //   2704: invokespecial 64	java/lang/String:<init>	([C)V
    //   2707: invokevirtual 68	java/lang/String:intern	()Ljava/lang/String;
    //   2710: aastore
    //   2711: ldc 200
    //   2713: invokevirtual 60	java/lang/String:toCharArray	()[C
    //   2716: wide
    //   2720: wide
    //   2724: arraylength
    //   2725: wide
    //   2729: iconst_0
    //   2730: wide
    //   2734: wide
    //   2738: wide
    //   2742: if_icmpgt +6672 -> 9414
    //   2745: aload_0
    //   2746: bipush 66
    //   2748: new 54	java/lang/String
    //   2751: dup
    //   2752: wide
    //   2756: invokespecial 64	java/lang/String:<init>	([C)V
    //   2759: invokevirtual 68	java/lang/String:intern	()Ljava/lang/String;
    //   2762: aastore
    //   2763: ldc 202
    //   2765: invokevirtual 60	java/lang/String:toCharArray	()[C
    //   2768: wide
    //   2772: wide
    //   2776: arraylength
    //   2777: wide
    //   2781: iconst_0
    //   2782: wide
    //   2786: wide
    //   2790: wide
    //   2794: if_icmpgt +6740 -> 9534
    //   2797: aload_0
    //   2798: bipush 67
    //   2800: new 54	java/lang/String
    //   2803: dup
    //   2804: wide
    //   2808: invokespecial 64	java/lang/String:<init>	([C)V
    //   2811: invokevirtual 68	java/lang/String:intern	()Ljava/lang/String;
    //   2814: aastore
    //   2815: ldc 204
    //   2817: invokevirtual 60	java/lang/String:toCharArray	()[C
    //   2820: wide
    //   2824: wide
    //   2828: arraylength
    //   2829: wide
    //   2833: iconst_0
    //   2834: wide
    //   2838: wide
    //   2842: wide
    //   2846: if_icmpgt +6808 -> 9654
    //   2849: aload_0
    //   2850: bipush 68
    //   2852: new 54	java/lang/String
    //   2855: dup
    //   2856: wide
    //   2860: invokespecial 64	java/lang/String:<init>	([C)V
    //   2863: invokevirtual 68	java/lang/String:intern	()Ljava/lang/String;
    //   2866: aastore
    //   2867: aload_0
    //   2868: putstatic 206	com/whatsapp/VerifySms:ab	[Ljava/lang/String;
    //   2871: bipush 10
    //   2873: putstatic 208	com/whatsapp/VerifySms:q	I
    //   2876: iconst_0
    //   2877: putstatic 210	com/whatsapp/VerifySms:r	I
    //   2880: aconst_null
    //   2881: putstatic 212	com/whatsapp/VerifySms:s	Landroid/os/CountDownTimer;
    //   2884: ldc2_w 213
    //   2887: putstatic 216	com/whatsapp/VerifySms:t	J
    //   2890: lconst_0
    //   2891: putstatic 218	com/whatsapp/VerifySms:u	J
    //   2894: aconst_null
    //   2895: putstatic 220	com/whatsapp/VerifySms:v	Landroid/content/BroadcastReceiver;
    //   2898: aconst_null
    //   2899: putstatic 222	com/whatsapp/VerifySms:w	Landroid/content/BroadcastReceiver;
    //   2902: aconst_null
    //   2903: putstatic 224	com/whatsapp/VerifySms:x	Landroid/content/BroadcastReceiver;
    //   2906: aconst_null
    //   2907: putstatic 226	com/whatsapp/VerifySms:y	Ljava/lang/String;
    //   2910: ldc 228
    //   2912: putstatic 230	com/whatsapp/VerifySms:z	Ljava/lang/String;
    //   2915: ldc 228
    //   2917: putstatic 232	com/whatsapp/VerifySms:A	Ljava/lang/String;
    //   2920: aconst_null
    //   2921: putstatic 234	com/whatsapp/VerifySms:C	Ljava/lang/String;
    //   2924: iconst_0
    //   2925: putstatic 236	com/whatsapp/VerifySms:O	Z
    //   2928: return
    //   2929: aload_1
    //   2930: iload_3
    //   2931: caload
    //   2932: istore 4
    //   2934: iload_3
    //   2935: iconst_5
    //   2936: irem
    //   2937: tableswitch	default:+31 -> 2968, 0:+50->2987, 1:+57->2994, 2:+64->3001, 3:+71->3008
    //   2969: ldc2_w 13829
    //   2972: aload_1
    //   2973: iload_3
    //   2974: iload 5
    //   2976: iload 4
    //   2978: ixor
    //   2979: i2c
    //   2980: castore
    //   2981: iinc 3 1
    //   2984: goto -2967 -> 17
    //   2987: bipush 109
    //   2989: istore 5
    //   2991: goto -19 -> 2972
    //   2994: bipush 90
    //   2996: istore 5
    //   2998: goto -26 -> 2972
    //   3001: bipush 9
    //   3003: istore 5
    //   3005: goto -33 -> 2972
    //   3008: bipush 117
    //   3010: istore 5
    //   3012: goto -40 -> 2972
    //   3015: aload 6
    //   3017: iload 8
    //   3019: caload
    //   3020: istore 9
    //   3022: iload 8
    //   3024: iconst_5
    //   3025: irem
    //   3026: tableswitch	default:+30 -> 3056, 0:+51->3077, 1:+58->3084, 2:+65->3091, 3:+72->3098
    //   3057: ldc2_w 13834
    //   3060: aload 6
    //   3062: iload 8
    //   3064: iload 10
    //   3066: iload 9
    //   3068: ixor
    //   3069: i2c
    //   3070: castore
    //   3071: iinc 8 1
    //   3074: goto -3023 -> 51
    //   3077: bipush 109
    //   3079: istore 10
    //   3081: goto -21 -> 3060
    //   3084: bipush 90
    //   3086: istore 10
    //   3088: goto -28 -> 3060
    //   3091: bipush 9
    //   3093: istore 10
    //   3095: goto -35 -> 3060
    //   3098: bipush 117
    //   3100: istore 10
    //   3102: goto -42 -> 3060
    //   3105: aload 11
    //   3107: iload 13
    //   3109: caload
    //   3110: istore 14
    //   3112: iload 13
    //   3114: iconst_5
    //   3115: irem
    //   3116: tableswitch	default:+32 -> 3148, 0:+53->3169, 1:+60->3176, 2:+67->3183, 3:+74->3190
    //   3149: ldc2_w 13839
    //   3152: aload 11
    //   3154: iload 13
    //   3156: iload 15
    //   3158: iload 14
    //   3160: ixor
    //   3161: i2c
    //   3162: castore
    //   3163: iinc 13 1
    //   3166: goto -3078 -> 88
    //   3169: bipush 109
    //   3171: istore 15
    //   3173: goto -21 -> 3152
    //   3176: bipush 90
    //   3178: istore 15
    //   3180: goto -28 -> 3152
    //   3183: bipush 9
    //   3185: istore 15
    //   3187: goto -35 -> 3152
    //   3190: bipush 117
    //   3192: istore 15
    //   3194: goto -42 -> 3152
    //   3197: aload 16
    //   3199: iload 18
    //   3201: caload
    //   3202: istore 19
    //   3204: iload 18
    //   3206: iconst_5
    //   3207: irem
    //   3208: tableswitch	default:+32 -> 3240, 0:+53->3261, 1:+60->3268, 2:+67->3275, 3:+74->3282
    //   3241: ldc2_w 13844
    //   3244: aload 16
    //   3246: iload 18
    //   3248: iload 20
    //   3250: iload 19
    //   3252: ixor
    //   3253: i2c
    //   3254: castore
    //   3255: iinc 18 1
    //   3258: goto -3133 -> 125
    //   3261: bipush 109
    //   3263: istore 20
    //   3265: goto -21 -> 3244
    //   3268: bipush 90
    //   3270: istore 20
    //   3272: goto -28 -> 3244
    //   3275: bipush 9
    //   3277: istore 20
    //   3279: goto -35 -> 3244
    //   3282: bipush 117
    //   3284: istore 20
    //   3286: goto -42 -> 3244
    //   3289: aload 21
    //   3291: iload 23
    //   3293: caload
    //   3294: istore 24
    //   3296: iload 23
    //   3298: iconst_5
    //   3299: irem
    //   3300: tableswitch	default:+32 -> 3332, 0:+53->3353, 1:+60->3360, 2:+67->3367, 3:+74->3374
    //   3333: ldc2_w 13849
    //   3336: aload 21
    //   3338: iload 23
    //   3340: iload 25
    //   3342: iload 24
    //   3344: ixor
    //   3345: i2c
    //   3346: castore
    //   3347: iinc 23 1
    //   3350: goto -3188 -> 162
    //   3353: bipush 109
    //   3355: istore 25
    //   3357: goto -21 -> 3336
    //   3360: bipush 90
    //   3362: istore 25
    //   3364: goto -28 -> 3336
    //   3367: bipush 9
    //   3369: istore 25
    //   3371: goto -35 -> 3336
    //   3374: bipush 117
    //   3376: istore 25
    //   3378: goto -42 -> 3336
    //   3381: aload 26
    //   3383: iload 28
    //   3385: caload
    //   3386: istore 29
    //   3388: iload 28
    //   3390: iconst_5
    //   3391: irem
    //   3392: tableswitch	default:+32 -> 3424, 0:+53->3445, 1:+60->3452, 2:+67->3459, 3:+74->3466
    //   3425: ldc2_w 13854
    //   3428: aload 26
    //   3430: iload 28
    //   3432: iload 30
    //   3434: iload 29
    //   3436: ixor
    //   3437: i2c
    //   3438: castore
    //   3439: iinc 28 1
    //   3442: goto -3243 -> 199
    //   3445: bipush 109
    //   3447: istore 30
    //   3449: goto -21 -> 3428
    //   3452: bipush 90
    //   3454: istore 30
    //   3456: goto -28 -> 3428
    //   3459: bipush 9
    //   3461: istore 30
    //   3463: goto -35 -> 3428
    //   3466: bipush 117
    //   3468: istore 30
    //   3470: goto -42 -> 3428
    //   3473: aload 31
    //   3475: iload 33
    //   3477: caload
    //   3478: istore 34
    //   3480: iload 33
    //   3482: iconst_5
    //   3483: irem
    //   3484: tableswitch	default:+32 -> 3516, 0:+53->3537, 1:+60->3544, 2:+67->3551, 3:+74->3558
    //   3517: ldc2_w 13859
    //   3520: aload 31
    //   3522: iload 33
    //   3524: iload 35
    //   3526: iload 34
    //   3528: ixor
    //   3529: i2c
    //   3530: castore
    //   3531: iinc 33 1
    //   3534: goto -3298 -> 236
    //   3537: bipush 109
    //   3539: istore 35
    //   3541: goto -21 -> 3520
    //   3544: bipush 90
    //   3546: istore 35
    //   3548: goto -28 -> 3520
    //   3551: bipush 9
    //   3553: istore 35
    //   3555: goto -35 -> 3520
    //   3558: bipush 117
    //   3560: istore 35
    //   3562: goto -42 -> 3520
    //   3565: aload 36
    //   3567: iload 38
    //   3569: caload
    //   3570: istore 39
    //   3572: iload 38
    //   3574: iconst_5
    //   3575: irem
    //   3576: tableswitch	default:+32 -> 3608, 0:+53->3629, 1:+60->3636, 2:+67->3643, 3:+74->3650
    //   3609: ldc2_w 13864
    //   3612: aload 36
    //   3614: iload 38
    //   3616: iload 40
    //   3618: iload 39
    //   3620: ixor
    //   3621: i2c
    //   3622: castore
    //   3623: iinc 38 1
    //   3626: goto -3352 -> 274
    //   3629: bipush 109
    //   3631: istore 40
    //   3633: goto -21 -> 3612
    //   3636: bipush 90
    //   3638: istore 40
    //   3640: goto -28 -> 3612
    //   3643: bipush 9
    //   3645: istore 40
    //   3647: goto -35 -> 3612
    //   3650: bipush 117
    //   3652: istore 40
    //   3654: goto -42 -> 3612
    //   3657: aload 41
    //   3659: iload 43
    //   3661: caload
    //   3662: istore 44
    //   3664: iload 43
    //   3666: iconst_5
    //   3667: irem
    //   3668: tableswitch	default:+32 -> 3700, 0:+53->3721, 1:+60->3728, 2:+67->3735, 3:+74->3742
    //   3701: ldc2_w 13869
    //   3704: aload 41
    //   3706: iload 43
    //   3708: iload 45
    //   3710: iload 44
    //   3712: ixor
    //   3713: i2c
    //   3714: castore
    //   3715: iinc 43 1
    //   3718: goto -3406 -> 312
    //   3721: bipush 109
    //   3723: istore 45
    //   3725: goto -21 -> 3704
    //   3728: bipush 90
    //   3730: istore 45
    //   3732: goto -28 -> 3704
    //   3735: bipush 9
    //   3737: istore 45
    //   3739: goto -35 -> 3704
    //   3742: bipush 117
    //   3744: istore 45
    //   3746: goto -42 -> 3704
    //   3749: aload 46
    //   3751: iload 48
    //   3753: caload
    //   3754: istore 49
    //   3756: iload 48
    //   3758: iconst_5
    //   3759: irem
    //   3760: tableswitch	default:+32 -> 3792, 0:+53->3813, 1:+60->3820, 2:+67->3827, 3:+74->3834
    //   3793: ldc2_w 13874
    //   3796: aload 46
    //   3798: iload 48
    //   3800: iload 50
    //   3802: iload 49
    //   3804: ixor
    //   3805: i2c
    //   3806: castore
    //   3807: iinc 48 1
    //   3810: goto -3460 -> 350
    //   3813: bipush 109
    //   3815: istore 50
    //   3817: goto -21 -> 3796
    //   3820: bipush 90
    //   3822: istore 50
    //   3824: goto -28 -> 3796
    //   3827: bipush 9
    //   3829: istore 50
    //   3831: goto -35 -> 3796
    //   3834: bipush 117
    //   3836: istore 50
    //   3838: goto -42 -> 3796
    //   3841: aload 51
    //   3843: iload 53
    //   3845: caload
    //   3846: istore 54
    //   3848: iload 53
    //   3850: iconst_5
    //   3851: irem
    //   3852: tableswitch	default:+32 -> 3884, 0:+53->3905, 1:+60->3912, 2:+67->3919, 3:+74->3926
    //   3885: ldc2_w 13879
    //   3888: aload 51
    //   3890: iload 53
    //   3892: iload 55
    //   3894: iload 54
    //   3896: ixor
    //   3897: i2c
    //   3898: castore
    //   3899: iinc 53 1
    //   3902: goto -3514 -> 388
    //   3905: bipush 109
    //   3907: istore 55
    //   3909: goto -21 -> 3888
    //   3912: bipush 90
    //   3914: istore 55
    //   3916: goto -28 -> 3888
    //   3919: bipush 9
    //   3921: istore 55
    //   3923: goto -35 -> 3888
    //   3926: bipush 117
    //   3928: istore 55
    //   3930: goto -42 -> 3888
    //   3933: aload 56
    //   3935: iload 58
    //   3937: caload
    //   3938: istore 59
    //   3940: iload 58
    //   3942: iconst_5
    //   3943: irem
    //   3944: tableswitch	default:+32 -> 3976, 0:+53->3997, 1:+60->4004, 2:+67->4011, 3:+74->4018
    //   3977: ldc2_w 13884
    //   3980: aload 56
    //   3982: iload 58
    //   3984: iload 60
    //   3986: iload 59
    //   3988: ixor
    //   3989: i2c
    //   3990: castore
    //   3991: iinc 58 1
    //   3994: goto -3568 -> 426
    //   3997: bipush 109
    //   3999: istore 60
    //   4001: goto -21 -> 3980
    //   4004: bipush 90
    //   4006: istore 60
    //   4008: goto -28 -> 3980
    //   4011: bipush 9
    //   4013: istore 60
    //   4015: goto -35 -> 3980
    //   4018: bipush 117
    //   4020: istore 60
    //   4022: goto -42 -> 3980
    //   4025: aload 61
    //   4027: iload 63
    //   4029: caload
    //   4030: istore 64
    //   4032: iload 63
    //   4034: iconst_5
    //   4035: irem
    //   4036: tableswitch	default:+32 -> 4068, 0:+53->4089, 1:+60->4096, 2:+67->4103, 3:+74->4110
    //   4069: ldc2_w 13889
    //   4072: aload 61
    //   4074: iload 63
    //   4076: iload 65
    //   4078: iload 64
    //   4080: ixor
    //   4081: i2c
    //   4082: castore
    //   4083: iinc 63 1
    //   4086: goto -3622 -> 464
    //   4089: bipush 109
    //   4091: istore 65
    //   4093: goto -21 -> 4072
    //   4096: bipush 90
    //   4098: istore 65
    //   4100: goto -28 -> 4072
    //   4103: bipush 9
    //   4105: istore 65
    //   4107: goto -35 -> 4072
    //   4110: bipush 117
    //   4112: istore 65
    //   4114: goto -42 -> 4072
    //   4117: aload 66
    //   4119: iload 68
    //   4121: caload
    //   4122: istore 69
    //   4124: iload 68
    //   4126: iconst_5
    //   4127: irem
    //   4128: tableswitch	default:+32 -> 4160, 0:+53->4181, 1:+60->4188, 2:+67->4195, 3:+74->4202
    //   4161: ldc2_w 13894
    //   4164: aload 66
    //   4166: iload 68
    //   4168: iload 70
    //   4170: iload 69
    //   4172: ixor
    //   4173: i2c
    //   4174: castore
    //   4175: iinc 68 1
    //   4178: goto -3676 -> 502
    //   4181: bipush 109
    //   4183: istore 70
    //   4185: goto -21 -> 4164
    //   4188: bipush 90
    //   4190: istore 70
    //   4192: goto -28 -> 4164
    //   4195: bipush 9
    //   4197: istore 70
    //   4199: goto -35 -> 4164
    //   4202: bipush 117
    //   4204: istore 70
    //   4206: goto -42 -> 4164
    //   4209: aload 71
    //   4211: iload 73
    //   4213: caload
    //   4214: istore 74
    //   4216: iload 73
    //   4218: iconst_5
    //   4219: irem
    //   4220: tableswitch	default:+32 -> 4252, 0:+53->4273, 1:+60->4280, 2:+67->4287, 3:+74->4294
    //   4253: ldc2_w 13899
    //   4256: aload 71
    //   4258: iload 73
    //   4260: iload 75
    //   4262: iload 74
    //   4264: ixor
    //   4265: i2c
    //   4266: castore
    //   4267: iinc 73 1
    //   4270: goto -3730 -> 540
    //   4273: bipush 109
    //   4275: istore 75
    //   4277: goto -21 -> 4256
    //   4280: bipush 90
    //   4282: istore 75
    //   4284: goto -28 -> 4256
    //   4287: bipush 9
    //   4289: istore 75
    //   4291: goto -35 -> 4256
    //   4294: bipush 117
    //   4296: istore 75
    //   4298: goto -42 -> 4256
    //   4301: aload 76
    //   4303: iload 78
    //   4305: caload
    //   4306: istore 79
    //   4308: iload 78
    //   4310: iconst_5
    //   4311: irem
    //   4312: tableswitch	default:+32 -> 4344, 0:+53->4365, 1:+60->4372, 2:+67->4379, 3:+74->4386
    //   4345: ldc2_w 13904
    //   4348: aload 76
    //   4350: iload 78
    //   4352: iload 80
    //   4354: iload 79
    //   4356: ixor
    //   4357: i2c
    //   4358: castore
    //   4359: iinc 78 1
    //   4362: goto -3784 -> 578
    //   4365: bipush 109
    //   4367: istore 80
    //   4369: goto -21 -> 4348
    //   4372: bipush 90
    //   4374: istore 80
    //   4376: goto -28 -> 4348
    //   4379: bipush 9
    //   4381: istore 80
    //   4383: goto -35 -> 4348
    //   4386: bipush 117
    //   4388: istore 80
    //   4390: goto -42 -> 4348
    //   4393: aload 81
    //   4395: iload 83
    //   4397: caload
    //   4398: istore 84
    //   4400: iload 83
    //   4402: iconst_5
    //   4403: irem
    //   4404: tableswitch	default:+32 -> 4436, 0:+53->4457, 1:+60->4464, 2:+67->4471, 3:+74->4478
    //   4437: ldc2_w 13909
    //   4440: aload 81
    //   4442: iload 83
    //   4444: iload 85
    //   4446: iload 84
    //   4448: ixor
    //   4449: i2c
    //   4450: castore
    //   4451: iinc 83 1
    //   4454: goto -3838 -> 616
    //   4457: bipush 109
    //   4459: istore 85
    //   4461: goto -21 -> 4440
    //   4464: bipush 90
    //   4466: istore 85
    //   4468: goto -28 -> 4440
    //   4471: bipush 9
    //   4473: istore 85
    //   4475: goto -35 -> 4440
    //   4478: bipush 117
    //   4480: istore 85
    //   4482: goto -42 -> 4440
    //   4485: aload 86
    //   4487: iload 88
    //   4489: caload
    //   4490: istore 89
    //   4492: iload 88
    //   4494: iconst_5
    //   4495: irem
    //   4496: tableswitch	default:+32 -> 4528, 0:+53->4549, 1:+60->4556, 2:+67->4563, 3:+74->4570
    //   4529: ldc2_w 13914
    //   4532: aload 86
    //   4534: iload 88
    //   4536: iload 90
    //   4538: iload 89
    //   4540: ixor
    //   4541: i2c
    //   4542: castore
    //   4543: iinc 88 1
    //   4546: goto -3892 -> 654
    //   4549: bipush 109
    //   4551: istore 90
    //   4553: goto -21 -> 4532
    //   4556: bipush 90
    //   4558: istore 90
    //   4560: goto -28 -> 4532
    //   4563: bipush 9
    //   4565: istore 90
    //   4567: goto -35 -> 4532
    //   4570: bipush 117
    //   4572: istore 90
    //   4574: goto -42 -> 4532
    //   4577: aload 91
    //   4579: iload 93
    //   4581: caload
    //   4582: istore 94
    //   4584: iload 93
    //   4586: iconst_5
    //   4587: irem
    //   4588: tableswitch	default:+32 -> 4620, 0:+53->4641, 1:+60->4648, 2:+67->4655, 3:+74->4662
    //   4621: ldc2_w 13919
    //   4624: aload 91
    //   4626: iload 93
    //   4628: iload 95
    //   4630: iload 94
    //   4632: ixor
    //   4633: i2c
    //   4634: castore
    //   4635: iinc 93 1
    //   4638: goto -3946 -> 692
    //   4641: bipush 109
    //   4643: istore 95
    //   4645: goto -21 -> 4624
    //   4648: bipush 90
    //   4650: istore 95
    //   4652: goto -28 -> 4624
    //   4655: bipush 9
    //   4657: istore 95
    //   4659: goto -35 -> 4624
    //   4662: bipush 117
    //   4664: istore 95
    //   4666: goto -42 -> 4624
    //   4669: aload 96
    //   4671: iload 98
    //   4673: caload
    //   4674: istore 99
    //   4676: iload 98
    //   4678: iconst_5
    //   4679: irem
    //   4680: tableswitch	default:+32 -> 4712, 0:+53->4733, 1:+60->4740, 2:+67->4747, 3:+74->4754
    //   4713: ldc2_w 13924
    //   4716: aload 96
    //   4718: iload 98
    //   4720: iload 100
    //   4722: iload 99
    //   4724: ixor
    //   4725: i2c
    //   4726: castore
    //   4727: iinc 98 1
    //   4730: goto -4000 -> 730
    //   4733: bipush 109
    //   4735: istore 100
    //   4737: goto -21 -> 4716
    //   4740: bipush 90
    //   4742: istore 100
    //   4744: goto -28 -> 4716
    //   4747: bipush 9
    //   4749: istore 100
    //   4751: goto -35 -> 4716
    //   4754: bipush 117
    //   4756: istore 100
    //   4758: goto -42 -> 4716
    //   4761: aload 101
    //   4763: iload 103
    //   4765: caload
    //   4766: istore 104
    //   4768: iload 103
    //   4770: iconst_5
    //   4771: irem
    //   4772: tableswitch	default:+32 -> 4804, 0:+53->4825, 1:+60->4832, 2:+67->4839, 3:+74->4846
    //   4805: ldc2_w 13929
    //   4808: aload 101
    //   4810: iload 103
    //   4812: iload 105
    //   4814: iload 104
    //   4816: ixor
    //   4817: i2c
    //   4818: castore
    //   4819: iinc 103 1
    //   4822: goto -4054 -> 768
    //   4825: bipush 109
    //   4827: istore 105
    //   4829: goto -21 -> 4808
    //   4832: bipush 90
    //   4834: istore 105
    //   4836: goto -28 -> 4808
    //   4839: bipush 9
    //   4841: istore 105
    //   4843: goto -35 -> 4808
    //   4846: bipush 117
    //   4848: istore 105
    //   4850: goto -42 -> 4808
    //   4853: aload 106
    //   4855: iload 108
    //   4857: caload
    //   4858: istore 109
    //   4860: iload 108
    //   4862: iconst_5
    //   4863: irem
    //   4864: tableswitch	default:+32 -> 4896, 0:+53->4917, 1:+60->4924, 2:+67->4931, 3:+74->4938
    //   4897: ldc2_w 13934
    //   4900: aload 106
    //   4902: iload 108
    //   4904: iload 110
    //   4906: iload 109
    //   4908: ixor
    //   4909: i2c
    //   4910: castore
    //   4911: iinc 108 1
    //   4914: goto -4108 -> 806
    //   4917: bipush 109
    //   4919: istore 110
    //   4921: goto -21 -> 4900
    //   4924: bipush 90
    //   4926: istore 110
    //   4928: goto -28 -> 4900
    //   4931: bipush 9
    //   4933: istore 110
    //   4935: goto -35 -> 4900
    //   4938: bipush 117
    //   4940: istore 110
    //   4942: goto -42 -> 4900
    //   4945: aload 111
    //   4947: iload 113
    //   4949: caload
    //   4950: istore 114
    //   4952: iload 113
    //   4954: iconst_5
    //   4955: irem
    //   4956: tableswitch	default:+32 -> 4988, 0:+53->5009, 1:+60->5016, 2:+67->5023, 3:+74->5030
    //   4989: ldc2_w 13939
    //   4992: aload 111
    //   4994: iload 113
    //   4996: iload 115
    //   4998: iload 114
    //   5000: ixor
    //   5001: i2c
    //   5002: castore
    //   5003: iinc 113 1
    //   5006: goto -4162 -> 844
    //   5009: bipush 109
    //   5011: istore 115
    //   5013: goto -21 -> 4992
    //   5016: bipush 90
    //   5018: istore 115
    //   5020: goto -28 -> 4992
    //   5023: bipush 9
    //   5025: istore 115
    //   5027: goto -35 -> 4992
    //   5030: bipush 117
    //   5032: istore 115
    //   5034: goto -42 -> 4992
    //   5037: aload 116
    //   5039: iload 118
    //   5041: caload
    //   5042: istore 119
    //   5044: iload 118
    //   5046: iconst_5
    //   5047: irem
    //   5048: tableswitch	default:+32 -> 5080, 0:+53->5101, 1:+60->5108, 2:+67->5115, 3:+74->5122
    //   5081: ldc2_w 13944
    //   5084: aload 116
    //   5086: iload 118
    //   5088: iload 120
    //   5090: iload 119
    //   5092: ixor
    //   5093: i2c
    //   5094: castore
    //   5095: iinc 118 1
    //   5098: goto -4216 -> 882
    //   5101: bipush 109
    //   5103: istore 120
    //   5105: goto -21 -> 5084
    //   5108: bipush 90
    //   5110: istore 120
    //   5112: goto -28 -> 5084
    //   5115: bipush 9
    //   5117: istore 120
    //   5119: goto -35 -> 5084
    //   5122: bipush 117
    //   5124: istore 120
    //   5126: goto -42 -> 5084
    //   5129: aload 121
    //   5131: iload 123
    //   5133: caload
    //   5134: istore 124
    //   5136: iload 123
    //   5138: iconst_5
    //   5139: irem
    //   5140: tableswitch	default:+32 -> 5172, 0:+53->5193, 1:+60->5200, 2:+67->5207, 3:+74->5214
    //   5173: ldc2_w 13949
    //   5176: aload 121
    //   5178: iload 123
    //   5180: iload 125
    //   5182: iload 124
    //   5184: ixor
    //   5185: i2c
    //   5186: castore
    //   5187: iinc 123 1
    //   5190: goto -4270 -> 920
    //   5193: bipush 109
    //   5195: istore 125
    //   5197: goto -21 -> 5176
    //   5200: bipush 90
    //   5202: istore 125
    //   5204: goto -28 -> 5176
    //   5207: bipush 9
    //   5209: istore 125
    //   5211: goto -35 -> 5176
    //   5214: bipush 117
    //   5216: istore 125
    //   5218: goto -42 -> 5176
    //   5221: aload 126
    //   5223: iload 128
    //   5225: caload
    //   5226: istore 129
    //   5228: iload 128
    //   5230: iconst_5
    //   5231: irem
    //   5232: tableswitch	default:+32 -> 5264, 0:+53->5285, 1:+60->5292, 2:+67->5299, 3:+74->5306
    //   5265: ldc2_w 13954
    //   5268: aload 126
    //   5270: iload 128
    //   5272: iload 130
    //   5274: iload 129
    //   5276: ixor
    //   5277: i2c
    //   5278: castore
    //   5279: iinc 128 1
    //   5282: goto -4324 -> 958
    //   5285: bipush 109
    //   5287: istore 130
    //   5289: goto -21 -> 5268
    //   5292: bipush 90
    //   5294: istore 130
    //   5296: goto -28 -> 5268
    //   5299: bipush 9
    //   5301: istore 130
    //   5303: goto -35 -> 5268
    //   5306: bipush 117
    //   5308: istore 130
    //   5310: goto -42 -> 5268
    //   5313: aload 131
    //   5315: iload 133
    //   5317: caload
    //   5318: istore 134
    //   5320: iload 133
    //   5322: iconst_5
    //   5323: irem
    //   5324: tableswitch	default:+32 -> 5356, 0:+53->5377, 1:+60->5384, 2:+67->5391, 3:+74->5398
    //   5357: ldc2_w 13959
    //   5360: aload 131
    //   5362: iload 133
    //   5364: iload 135
    //   5366: iload 134
    //   5368: ixor
    //   5369: i2c
    //   5370: castore
    //   5371: iinc 133 1
    //   5374: goto -4378 -> 996
    //   5377: bipush 109
    //   5379: istore 135
    //   5381: goto -21 -> 5360
    //   5384: bipush 90
    //   5386: istore 135
    //   5388: goto -28 -> 5360
    //   5391: bipush 9
    //   5393: istore 135
    //   5395: goto -35 -> 5360
    //   5398: bipush 117
    //   5400: istore 135
    //   5402: goto -42 -> 5360
    //   5405: aload 136
    //   5407: iload 138
    //   5409: caload
    //   5410: istore 139
    //   5412: iload 138
    //   5414: iconst_5
    //   5415: irem
    //   5416: tableswitch	default:+32 -> 5448, 0:+53->5469, 1:+60->5476, 2:+67->5483, 3:+74->5490
    //   5449: ldc2_w 13964
    //   5452: aload 136
    //   5454: iload 138
    //   5456: iload 140
    //   5458: iload 139
    //   5460: ixor
    //   5461: i2c
    //   5462: castore
    //   5463: iinc 138 1
    //   5466: goto -4432 -> 1034
    //   5469: bipush 109
    //   5471: istore 140
    //   5473: goto -21 -> 5452
    //   5476: bipush 90
    //   5478: istore 140
    //   5480: goto -28 -> 5452
    //   5483: bipush 9
    //   5485: istore 140
    //   5487: goto -35 -> 5452
    //   5490: bipush 117
    //   5492: istore 140
    //   5494: goto -42 -> 5452
    //   5497: aload 141
    //   5499: iload 143
    //   5501: caload
    //   5502: istore 144
    //   5504: iload 143
    //   5506: iconst_5
    //   5507: irem
    //   5508: tableswitch	default:+32 -> 5540, 0:+53->5561, 1:+60->5568, 2:+67->5575, 3:+74->5582
    //   5541: ldc2_w 13969
    //   5544: aload 141
    //   5546: iload 143
    //   5548: iload 145
    //   5550: iload 144
    //   5552: ixor
    //   5553: i2c
    //   5554: castore
    //   5555: iinc 143 1
    //   5558: goto -4486 -> 1072
    //   5561: bipush 109
    //   5563: istore 145
    //   5565: goto -21 -> 5544
    //   5568: bipush 90
    //   5570: istore 145
    //   5572: goto -28 -> 5544
    //   5575: bipush 9
    //   5577: istore 145
    //   5579: goto -35 -> 5544
    //   5582: bipush 117
    //   5584: istore 145
    //   5586: goto -42 -> 5544
    //   5589: aload 146
    //   5591: iload 148
    //   5593: caload
    //   5594: istore 149
    //   5596: iload 148
    //   5598: iconst_5
    //   5599: irem
    //   5600: tableswitch	default:+32 -> 5632, 0:+53->5653, 1:+60->5660, 2:+67->5667, 3:+74->5674
    //   5633: ldc2_w 13974
    //   5636: aload 146
    //   5638: iload 148
    //   5640: iload 150
    //   5642: iload 149
    //   5644: ixor
    //   5645: i2c
    //   5646: castore
    //   5647: iinc 148 1
    //   5650: goto -4540 -> 1110
    //   5653: bipush 109
    //   5655: istore 150
    //   5657: goto -21 -> 5636
    //   5660: bipush 90
    //   5662: istore 150
    //   5664: goto -28 -> 5636
    //   5667: bipush 9
    //   5669: istore 150
    //   5671: goto -35 -> 5636
    //   5674: bipush 117
    //   5676: istore 150
    //   5678: goto -42 -> 5636
    //   5681: aload 151
    //   5683: iload 153
    //   5685: caload
    //   5686: istore 154
    //   5688: iload 153
    //   5690: iconst_5
    //   5691: irem
    //   5692: tableswitch	default:+32 -> 5724, 0:+53->5745, 1:+60->5752, 2:+67->5759, 3:+74->5766
    //   5725: ldc2_w 13979
    //   5728: aload 151
    //   5730: iload 153
    //   5732: iload 155
    //   5734: iload 154
    //   5736: ixor
    //   5737: i2c
    //   5738: castore
    //   5739: iinc 153 1
    //   5742: goto -4594 -> 1148
    //   5745: bipush 109
    //   5747: istore 155
    //   5749: goto -21 -> 5728
    //   5752: bipush 90
    //   5754: istore 155
    //   5756: goto -28 -> 5728
    //   5759: bipush 9
    //   5761: istore 155
    //   5763: goto -35 -> 5728
    //   5766: bipush 117
    //   5768: istore 155
    //   5770: goto -42 -> 5728
    //   5773: aload 156
    //   5775: iload 158
    //   5777: caload
    //   5778: istore 159
    //   5780: iload 158
    //   5782: iconst_5
    //   5783: irem
    //   5784: tableswitch	default:+32 -> 5816, 0:+53->5837, 1:+60->5844, 2:+67->5851, 3:+74->5858
    //   5817: ldc2_w 13984
    //   5820: aload 156
    //   5822: iload 158
    //   5824: iload 160
    //   5826: iload 159
    //   5828: ixor
    //   5829: i2c
    //   5830: castore
    //   5831: iinc 158 1
    //   5834: goto -4648 -> 1186
    //   5837: bipush 109
    //   5839: istore 160
    //   5841: goto -21 -> 5820
    //   5844: bipush 90
    //   5846: istore 160
    //   5848: goto -28 -> 5820
    //   5851: bipush 9
    //   5853: istore 160
    //   5855: goto -35 -> 5820
    //   5858: bipush 117
    //   5860: istore 160
    //   5862: goto -42 -> 5820
    //   5865: aload 161
    //   5867: iload 163
    //   5869: caload
    //   5870: istore 164
    //   5872: iload 163
    //   5874: iconst_5
    //   5875: irem
    //   5876: tableswitch	default:+32 -> 5908, 0:+53->5929, 1:+60->5936, 2:+67->5943, 3:+74->5950
    //   5909: ldc2_w 13989
    //   5912: aload 161
    //   5914: iload 163
    //   5916: iload 165
    //   5918: iload 164
    //   5920: ixor
    //   5921: i2c
    //   5922: castore
    //   5923: iinc 163 1
    //   5926: goto -4702 -> 1224
    //   5929: bipush 109
    //   5931: istore 165
    //   5933: goto -21 -> 5912
    //   5936: bipush 90
    //   5938: istore 165
    //   5940: goto -28 -> 5912
    //   5943: bipush 9
    //   5945: istore 165
    //   5947: goto -35 -> 5912
    //   5950: bipush 117
    //   5952: istore 165
    //   5954: goto -42 -> 5912
    //   5957: aload 166
    //   5959: iload 168
    //   5961: caload
    //   5962: istore 169
    //   5964: iload 168
    //   5966: iconst_5
    //   5967: irem
    //   5968: tableswitch	default:+32 -> 6000, 0:+53->6021, 1:+60->6028, 2:+67->6035, 3:+74->6042
    //   6001: ldc2_w 13994
    //   6004: aload 166
    //   6006: iload 168
    //   6008: iload 170
    //   6010: iload 169
    //   6012: ixor
    //   6013: i2c
    //   6014: castore
    //   6015: iinc 168 1
    //   6018: goto -4756 -> 1262
    //   6021: bipush 109
    //   6023: istore 170
    //   6025: goto -21 -> 6004
    //   6028: bipush 90
    //   6030: istore 170
    //   6032: goto -28 -> 6004
    //   6035: bipush 9
    //   6037: istore 170
    //   6039: goto -35 -> 6004
    //   6042: bipush 117
    //   6044: istore 170
    //   6046: goto -42 -> 6004
    //   6049: aload 171
    //   6051: iload 173
    //   6053: caload
    //   6054: istore 174
    //   6056: iload 173
    //   6058: iconst_5
    //   6059: irem
    //   6060: tableswitch	default:+32 -> 6092, 0:+53->6113, 1:+60->6120, 2:+67->6127, 3:+74->6134
    //   6093: ldc2_w 13999
    //   6096: aload 171
    //   6098: iload 173
    //   6100: iload 175
    //   6102: iload 174
    //   6104: ixor
    //   6105: i2c
    //   6106: castore
    //   6107: iinc 173 1
    //   6110: goto -4810 -> 1300
    //   6113: bipush 109
    //   6115: istore 175
    //   6117: goto -21 -> 6096
    //   6120: bipush 90
    //   6122: istore 175
    //   6124: goto -28 -> 6096
    //   6127: bipush 9
    //   6129: istore 175
    //   6131: goto -35 -> 6096
    //   6134: bipush 117
    //   6136: istore 175
    //   6138: goto -42 -> 6096
    //   6141: aload 176
    //   6143: iload 178
    //   6145: caload
    //   6146: istore 179
    //   6148: iload 178
    //   6150: iconst_5
    //   6151: irem
    //   6152: tableswitch	default:+32 -> 6184, 0:+53->6205, 1:+60->6212, 2:+67->6219, 3:+74->6226
    //   6185: ldc2_w 14004
    //   6188: aload 176
    //   6190: iload 178
    //   6192: iload 180
    //   6194: iload 179
    //   6196: ixor
    //   6197: i2c
    //   6198: castore
    //   6199: iinc 178 1
    //   6202: goto -4864 -> 1338
    //   6205: bipush 109
    //   6207: istore 180
    //   6209: goto -21 -> 6188
    //   6212: bipush 90
    //   6214: istore 180
    //   6216: goto -28 -> 6188
    //   6219: bipush 9
    //   6221: istore 180
    //   6223: goto -35 -> 6188
    //   6226: bipush 117
    //   6228: istore 180
    //   6230: goto -42 -> 6188
    //   6233: aload 181
    //   6235: iload 183
    //   6237: caload
    //   6238: istore 184
    //   6240: iload 183
    //   6242: iconst_5
    //   6243: irem
    //   6244: tableswitch	default:+32 -> 6276, 0:+53->6297, 1:+60->6304, 2:+67->6311, 3:+74->6318
    //   6277: ldc2_w 14009
    //   6280: aload 181
    //   6282: iload 183
    //   6284: iload 185
    //   6286: iload 184
    //   6288: ixor
    //   6289: i2c
    //   6290: castore
    //   6291: iinc 183 1
    //   6294: goto -4918 -> 1376
    //   6297: bipush 109
    //   6299: istore 185
    //   6301: goto -21 -> 6280
    //   6304: bipush 90
    //   6306: istore 185
    //   6308: goto -28 -> 6280
    //   6311: bipush 9
    //   6313: istore 185
    //   6315: goto -35 -> 6280
    //   6318: bipush 117
    //   6320: istore 185
    //   6322: goto -42 -> 6280
    //   6325: aload 186
    //   6327: iload 188
    //   6329: caload
    //   6330: istore 189
    //   6332: iload 188
    //   6334: iconst_5
    //   6335: irem
    //   6336: tableswitch	default:+32 -> 6368, 0:+53->6389, 1:+60->6396, 2:+67->6403, 3:+74->6410
    //   6369: ldc2_w 14014
    //   6372: aload 186
    //   6374: iload 188
    //   6376: iload 190
    //   6378: iload 189
    //   6380: ixor
    //   6381: i2c
    //   6382: castore
    //   6383: iinc 188 1
    //   6386: goto -4972 -> 1414
    //   6389: bipush 109
    //   6391: istore 190
    //   6393: goto -21 -> 6372
    //   6396: bipush 90
    //   6398: istore 190
    //   6400: goto -28 -> 6372
    //   6403: bipush 9
    //   6405: istore 190
    //   6407: goto -35 -> 6372
    //   6410: bipush 117
    //   6412: istore 190
    //   6414: goto -42 -> 6372
    //   6417: aload 191
    //   6419: iload 193
    //   6421: caload
    //   6422: istore 194
    //   6424: iload 193
    //   6426: iconst_5
    //   6427: irem
    //   6428: tableswitch	default:+32 -> 6460, 0:+53->6481, 1:+60->6488, 2:+67->6495, 3:+74->6502
    //   6461: ldc2_w 14019
    //   6464: aload 191
    //   6466: iload 193
    //   6468: iload 195
    //   6470: iload 194
    //   6472: ixor
    //   6473: i2c
    //   6474: castore
    //   6475: iinc 193 1
    //   6478: goto -5026 -> 1452
    //   6481: bipush 109
    //   6483: istore 195
    //   6485: goto -21 -> 6464
    //   6488: bipush 90
    //   6490: istore 195
    //   6492: goto -28 -> 6464
    //   6495: bipush 9
    //   6497: istore 195
    //   6499: goto -35 -> 6464
    //   6502: bipush 117
    //   6504: istore 195
    //   6506: goto -42 -> 6464
    //   6509: aload 196
    //   6511: iload 198
    //   6513: caload
    //   6514: istore 199
    //   6516: iload 198
    //   6518: iconst_5
    //   6519: irem
    //   6520: tableswitch	default:+32 -> 6552, 0:+53->6573, 1:+60->6580, 2:+67->6587, 3:+74->6594
    //   6553: ldc2_w 14024
    //   6556: aload 196
    //   6558: iload 198
    //   6560: iload 200
    //   6562: iload 199
    //   6564: ixor
    //   6565: i2c
    //   6566: castore
    //   6567: iinc 198 1
    //   6570: goto -5080 -> 1490
    //   6573: bipush 109
    //   6575: istore 200
    //   6577: goto -21 -> 6556
    //   6580: bipush 90
    //   6582: istore 200
    //   6584: goto -28 -> 6556
    //   6587: bipush 9
    //   6589: istore 200
    //   6591: goto -35 -> 6556
    //   6594: bipush 117
    //   6596: istore 200
    //   6598: goto -42 -> 6556
    //   6601: aload 201
    //   6603: iload 203
    //   6605: caload
    //   6606: istore 204
    //   6608: iload 203
    //   6610: iconst_5
    //   6611: irem
    //   6612: tableswitch	default:+32 -> 6644, 0:+53->6665, 1:+60->6672, 2:+67->6679, 3:+74->6686
    //   6645: ldc2_w 14029
    //   6648: aload 201
    //   6650: iload 203
    //   6652: iload 205
    //   6654: iload 204
    //   6656: ixor
    //   6657: i2c
    //   6658: castore
    //   6659: iinc 203 1
    //   6662: goto -5134 -> 1528
    //   6665: bipush 109
    //   6667: istore 205
    //   6669: goto -21 -> 6648
    //   6672: bipush 90
    //   6674: istore 205
    //   6676: goto -28 -> 6648
    //   6679: bipush 9
    //   6681: istore 205
    //   6683: goto -35 -> 6648
    //   6686: bipush 117
    //   6688: istore 205
    //   6690: goto -42 -> 6648
    //   6693: aload 206
    //   6695: iload 208
    //   6697: caload
    //   6698: istore 209
    //   6700: iload 208
    //   6702: iconst_5
    //   6703: irem
    //   6704: tableswitch	default:+32 -> 6736, 0:+53->6757, 1:+60->6764, 2:+67->6771, 3:+74->6778
    //   6737: ldc2_w 14034
    //   6740: aload 206
    //   6742: iload 208
    //   6744: iload 210
    //   6746: iload 209
    //   6748: ixor
    //   6749: i2c
    //   6750: castore
    //   6751: iinc 208 1
    //   6754: goto -5188 -> 1566
    //   6757: bipush 109
    //   6759: istore 210
    //   6761: goto -21 -> 6740
    //   6764: bipush 90
    //   6766: istore 210
    //   6768: goto -28 -> 6740
    //   6771: bipush 9
    //   6773: istore 210
    //   6775: goto -35 -> 6740
    //   6778: bipush 117
    //   6780: istore 210
    //   6782: goto -42 -> 6740
    //   6785: aload 211
    //   6787: iload 213
    //   6789: caload
    //   6790: istore 214
    //   6792: iload 213
    //   6794: iconst_5
    //   6795: irem
    //   6796: tableswitch	default:+32 -> 6828, 0:+53->6849, 1:+60->6856, 2:+67->6863, 3:+74->6870
    //   6829: ldc2_w 14039
    //   6832: aload 211
    //   6834: iload 213
    //   6836: iload 215
    //   6838: iload 214
    //   6840: ixor
    //   6841: i2c
    //   6842: castore
    //   6843: iinc 213 1
    //   6846: goto -5242 -> 1604
    //   6849: bipush 109
    //   6851: istore 215
    //   6853: goto -21 -> 6832
    //   6856: bipush 90
    //   6858: istore 215
    //   6860: goto -28 -> 6832
    //   6863: bipush 9
    //   6865: istore 215
    //   6867: goto -35 -> 6832
    //   6870: bipush 117
    //   6872: istore 215
    //   6874: goto -42 -> 6832
    //   6877: aload 216
    //   6879: iload 218
    //   6881: caload
    //   6882: istore 219
    //   6884: iload 218
    //   6886: iconst_5
    //   6887: irem
    //   6888: tableswitch	default:+32 -> 6920, 0:+53->6941, 1:+60->6948, 2:+67->6955, 3:+74->6962
    //   6921: ldc2_w 14044
    //   6924: aload 216
    //   6926: iload 218
    //   6928: iload 220
    //   6930: iload 219
    //   6932: ixor
    //   6933: i2c
    //   6934: castore
    //   6935: iinc 218 1
    //   6938: goto -5296 -> 1642
    //   6941: bipush 109
    //   6943: istore 220
    //   6945: goto -21 -> 6924
    //   6948: bipush 90
    //   6950: istore 220
    //   6952: goto -28 -> 6924
    //   6955: bipush 9
    //   6957: istore 220
    //   6959: goto -35 -> 6924
    //   6962: bipush 117
    //   6964: istore 220
    //   6966: goto -42 -> 6924
    //   6969: aload 221
    //   6971: iload 223
    //   6973: caload
    //   6974: istore 224
    //   6976: iload 223
    //   6978: iconst_5
    //   6979: irem
    //   6980: tableswitch	default:+32 -> 7012, 0:+53->7033, 1:+60->7040, 2:+67->7047, 3:+74->7054
    //   7013: ldc2_w 14049
    //   7016: aload 221
    //   7018: iload 223
    //   7020: iload 225
    //   7022: iload 224
    //   7024: ixor
    //   7025: i2c
    //   7026: castore
    //   7027: iinc 223 1
    //   7030: goto -5350 -> 1680
    //   7033: bipush 109
    //   7035: istore 225
    //   7037: goto -21 -> 7016
    //   7040: bipush 90
    //   7042: istore 225
    //   7044: goto -28 -> 7016
    //   7047: bipush 9
    //   7049: istore 225
    //   7051: goto -35 -> 7016
    //   7054: bipush 117
    //   7056: istore 225
    //   7058: goto -42 -> 7016
    //   7061: aload 226
    //   7063: iload 228
    //   7065: caload
    //   7066: istore 229
    //   7068: iload 228
    //   7070: iconst_5
    //   7071: irem
    //   7072: tableswitch	default:+32 -> 7104, 0:+53->7125, 1:+60->7132, 2:+67->7139, 3:+74->7146
    //   7105: ldc2_w 14054
    //   7108: aload 226
    //   7110: iload 228
    //   7112: iload 230
    //   7114: iload 229
    //   7116: ixor
    //   7117: i2c
    //   7118: castore
    //   7119: iinc 228 1
    //   7122: goto -5404 -> 1718
    //   7125: bipush 109
    //   7127: istore 230
    //   7129: goto -21 -> 7108
    //   7132: bipush 90
    //   7134: istore 230
    //   7136: goto -28 -> 7108
    //   7139: bipush 9
    //   7141: istore 230
    //   7143: goto -35 -> 7108
    //   7146: bipush 117
    //   7148: istore 230
    //   7150: goto -42 -> 7108
    //   7153: aload 231
    //   7155: iload 233
    //   7157: caload
    //   7158: istore 234
    //   7160: iload 233
    //   7162: iconst_5
    //   7163: irem
    //   7164: tableswitch	default:+32 -> 7196, 0:+53->7217, 1:+60->7224, 2:+67->7231, 3:+74->7238
    //   7197: ldc2_w 14059
    //   7200: aload 231
    //   7202: iload 233
    //   7204: iload 235
    //   7206: iload 234
    //   7208: ixor
    //   7209: i2c
    //   7210: castore
    //   7211: iinc 233 1
    //   7214: goto -5458 -> 1756
    //   7217: bipush 109
    //   7219: istore 235
    //   7221: goto -21 -> 7200
    //   7224: bipush 90
    //   7226: istore 235
    //   7228: goto -28 -> 7200
    //   7231: bipush 9
    //   7233: istore 235
    //   7235: goto -35 -> 7200
    //   7238: bipush 117
    //   7240: istore 235
    //   7242: goto -42 -> 7200
    //   7245: aload 236
    //   7247: iload 238
    //   7249: caload
    //   7250: istore 239
    //   7252: iload 238
    //   7254: iconst_5
    //   7255: irem
    //   7256: tableswitch	default:+32 -> 7288, 0:+53->7309, 1:+60->7316, 2:+67->7323, 3:+74->7330
    //   7289: ldc2_w 14064
    //   7292: aload 236
    //   7294: iload 238
    //   7296: iload 240
    //   7298: iload 239
    //   7300: ixor
    //   7301: i2c
    //   7302: castore
    //   7303: iinc 238 1
    //   7306: goto -5512 -> 1794
    //   7309: bipush 109
    //   7311: istore 240
    //   7313: goto -21 -> 7292
    //   7316: bipush 90
    //   7318: istore 240
    //   7320: goto -28 -> 7292
    //   7323: bipush 9
    //   7325: istore 240
    //   7327: goto -35 -> 7292
    //   7330: bipush 117
    //   7332: istore 240
    //   7334: goto -42 -> 7292
    //   7337: aload 241
    //   7339: iload 243
    //   7341: caload
    //   7342: istore 244
    //   7344: iload 243
    //   7346: iconst_5
    //   7347: irem
    //   7348: tableswitch	default:+32 -> 7380, 0:+53->7401, 1:+60->7408, 2:+67->7415, 3:+74->7422
    //   7381: ldc2_w 14069
    //   7384: aload 241
    //   7386: iload 243
    //   7388: iload 245
    //   7390: iload 244
    //   7392: ixor
    //   7393: i2c
    //   7394: castore
    //   7395: iinc 243 1
    //   7398: goto -5566 -> 1832
    //   7401: bipush 109
    //   7403: istore 245
    //   7405: goto -21 -> 7384
    //   7408: bipush 90
    //   7410: istore 245
    //   7412: goto -28 -> 7384
    //   7415: bipush 9
    //   7417: istore 245
    //   7419: goto -35 -> 7384
    //   7422: bipush 117
    //   7424: istore 245
    //   7426: goto -42 -> 7384
    //   7429: aload 246
    //   7431: iload 248
    //   7433: caload
    //   7434: istore 249
    //   7436: iload 248
    //   7438: iconst_5
    //   7439: irem
    //   7440: tableswitch	default:+32 -> 7472, 0:+53->7493, 1:+60->7500, 2:+67->7507, 3:+74->7514
    //   7473: ldc2_w 14074
    //   7476: aload 246
    //   7478: iload 248
    //   7480: iload 250
    //   7482: iload 249
    //   7484: ixor
    //   7485: i2c
    //   7486: castore
    //   7487: iinc 248 1
    //   7490: goto -5620 -> 1870
    //   7493: bipush 109
    //   7495: istore 250
    //   7497: goto -21 -> 7476
    //   7500: bipush 90
    //   7502: istore 250
    //   7504: goto -28 -> 7476
    //   7507: bipush 9
    //   7509: istore 250
    //   7511: goto -35 -> 7476
    //   7514: bipush 117
    //   7516: istore 250
    //   7518: goto -42 -> 7476
    //   7521: aload 251
    //   7523: iload 253
    //   7525: caload
    //   7526: istore 254
    //   7528: iload 253
    //   7530: iconst_5
    //   7531: irem
    //   7532: tableswitch	default:+32 -> 7564, 0:+53->7585, 1:+60->7592, 2:+67->7599, 3:+74->7606
    //   7565: ldc2_w 14079
    //   7568: aload 251
    //   7570: iload 253
    //   7572: iload 255
    //   7574: iload 254
    //   7576: ixor
    //   7577: i2c
    //   7578: castore
    //   7579: iinc 253 1
    //   7582: goto -5674 -> 1908
    //   7585: bipush 109
    //   7587: istore 255
    //   7589: goto -21 -> 7568
    //   7592: bipush 90
    //   7594: istore 255
    //   7596: goto -28 -> 7568
    //   7599: bipush 9
    //   7601: istore 255
    //   7603: goto -35 -> 7568
    //   7606: bipush 117
    //   7608: istore 255
    //   7610: goto -42 -> 7568
    //   7613: wide
    //   7617: wide
    //   7621: caload
    //   7622: wide
    //   7626: wide
    //   7630: iconst_5
    //   7631: irem
    //   7632: tableswitch	default:+32 -> 7664, 0:+66->7698, 1:+75->7707, 2:+84->7716, 3:+93->7725
    //   7665: ldc2_w -15306
    //   7668: aconst_null
    //   7669: iconst_1
    //   7670: wide
    //   7674: wide
    //   7678: wide
    //   7682: wide
    //   7686: ixor
    //   7687: i2c
    //   7688: castore
    //   7689: wide
    //   7695: goto -5741 -> 1954
    //   7698: bipush 109
    //   7700: wide
    //   7704: goto -34 -> 7670
    //   7707: bipush 90
    //   7709: wide
    //   7713: goto -43 -> 7670
    //   7716: bipush 9
    //   7718: wide
    //   7722: goto -52 -> 7670
    //   7725: bipush 117
    //   7727: wide
    //   7731: goto -61 -> 7670
    //   7734: wide
    //   7738: wide
    //   7742: caload
    //   7743: wide
    //   7747: wide
    //   7751: iconst_5
    //   7752: irem
    //   7753: tableswitch	default:+31 -> 7784, 0:+65->7818, 1:+74->7827, 2:+83->7836, 3:+92->7845
    //   7785: ldc2_w -15306
    //   7788: aconst_null
    //   7789: lconst_0
    //   7790: wide
    //   7794: wide
    //   7798: wide
    //   7802: wide
    //   7806: ixor
    //   7807: i2c
    //   7808: castore
    //   7809: wide
    //   7815: goto -5809 -> 2006
    //   7818: bipush 109
    //   7820: wide
    //   7824: goto -34 -> 7790
    //   7827: bipush 90
    //   7829: wide
    //   7833: goto -43 -> 7790
    //   7836: bipush 9
    //   7838: wide
    //   7842: goto -52 -> 7790
    //   7845: bipush 117
    //   7847: wide
    //   7851: goto -61 -> 7790
    //   7854: wide
    //   7858: wide
    //   7862: caload
    //   7863: wide
    //   7867: wide
    //   7871: iconst_5
    //   7872: irem
    //   7873: tableswitch	default:+31 -> 7904, 0:+65->7938, 1:+74->7947, 2:+83->7956, 3:+92->7965
    //   7905: ldc2_w -15306
    //   7908: aconst_null
    //   7909: dconst_0
    //   7910: wide
    //   7914: wide
    //   7918: wide
    //   7922: wide
    //   7926: ixor
    //   7927: i2c
    //   7928: castore
    //   7929: wide
    //   7935: goto -5877 -> 2058
    //   7938: bipush 109
    //   7940: wide
    //   7944: goto -34 -> 7910
    //   7947: bipush 90
    //   7949: wide
    //   7953: goto -43 -> 7910
    //   7956: bipush 9
    //   7958: wide
    //   7962: goto -52 -> 7910
    //   7965: bipush 117
    //   7967: wide
    //   7971: goto -61 -> 7910
    //   7974: wide
    //   7978: wide
    //   7982: caload
    //   7983: wide
    //   7987: wide
    //   7991: iconst_5
    //   7992: irem
    //   7993: tableswitch	default:+31 -> 8024, 0:+65->8058, 1:+74->8067, 2:+83->8076, 3:+92->8085
    //   8025: ldc2_w -15306
    //   8028: aconst_null
    //   8029: ldc_w -15335
    //   8032: aconst_null
    //   8033: dconst_1
    //   8034: wide
    //   8038: wide
    //   8042: wide
    //   8046: ixor
    //   8047: i2c
    //   8048: castore
    //   8049: wide
    //   8055: goto -5945 -> 2110
    //   8058: bipush 109
    //   8060: wide
    //   8064: goto -34 -> 8030
    //   8067: bipush 90
    //   8069: wide
    //   8073: goto -43 -> 8030
    //   8076: bipush 9
    //   8078: wide
    //   8082: goto -52 -> 8030
    //   8085: bipush 117
    //   8087: wide
    //   8091: goto -61 -> 8030
    //   8094: wide
    //   8098: wide
    //   8102: caload
    //   8103: wide
    //   8107: wide
    //   8111: iconst_5
    //   8112: irem
    //   8113: tableswitch	default:+31 -> 8144, 0:+65->8178, 1:+74->8187, 2:+83->8196, 3:+92->8205
    //   8145: ldc2_w -15306
    //   8148: aconst_null
    //   8149: dload 196
    //   8151: aload 1
    //   8153: ldc2_w -15339
    //   8156: aconst_null
    //   8157: lload 196
    //   8159: iload 1
    //   8161: dload 196
    //   8163: iload 1
    //   8165: fload 130
    //   8167: i2c
    //   8168: castore
    //   8169: wide
    //   8175: goto -6013 -> 2162
    //   8178: bipush 109
    //   8180: wide
    //   8184: goto -34 -> 8150
    //   8187: bipush 90
    //   8189: wide
    //   8193: goto -43 -> 8150
    //   8196: bipush 9
    //   8198: wide
    //   8202: goto -52 -> 8150
    //   8205: bipush 117
    //   8207: wide
    //   8211: goto -61 -> 8150
    //   8214: wide
    //   8218: wide
    //   8222: caload
    //   8223: wide
    //   8227: wide
    //   8231: iconst_5
    //   8232: irem
    //   8233: tableswitch	default:+31 -> 8264, 0:+65->8298, 1:+74->8307, 2:+83->8316, 3:+92->8325
    //   8265: ldc2_w -15306
    //   8268: aconst_null
    //   8269: iload_3
    //   8270: wide
    //   8274: wide
    //   8278: wide
    //   8282: wide
    //   8286: ixor
    //   8287: i2c
    //   8288: castore
    //   8289: wide
    //   8295: goto -6081 -> 2214
    //   8298: bipush 109
    //   8300: wide
    //   8304: goto -34 -> 8270
    //   8307: bipush 90
    //   8309: wide
    //   8313: goto -43 -> 8270
    //   8316: bipush 9
    //   8318: wide
    //   8322: goto -52 -> 8270
    //   8325: bipush 117
    //   8327: wide
    //   8331: goto -61 -> 8270
    //   8334: wide
    //   8338: wide
    //   8342: caload
    //   8343: wide
    //   8347: wide
    //   8351: iconst_5
    //   8352: irem
    //   8353: tableswitch	default:+31 -> 8384, 0:+65->8418, 1:+74->8427, 2:+83->8436, 3:+92->8445
    //   8385: ldc2_w -15306
    //   8388: aconst_null
    //   8389: fload_0
    //   8390: wide
    //   8394: wide
    //   8398: wide
    //   8402: wide
    //   8406: ixor
    //   8407: i2c
    //   8408: castore
    //   8409: wide
    //   8415: goto -6149 -> 2266
    //   8418: bipush 109
    //   8420: wide
    //   8424: goto -34 -> 8390
    //   8427: bipush 90
    //   8429: wide
    //   8433: goto -43 -> 8390
    //   8436: bipush 9
    //   8438: wide
    //   8442: goto -52 -> 8390
    //   8445: bipush 117
    //   8447: wide
    //   8451: goto -61 -> 8390
    //   8454: wide
    //   8458: wide
    //   8462: caload
    //   8463: wide
    //   8467: wide
    //   8471: iconst_5
    //   8472: irem
    //   8473: tableswitch	default:+31 -> 8504, 0:+65->8538, 1:+74->8547, 2:+83->8556, 3:+92->8565
    //   8505: ldc2_w -15306
    //   8508: aconst_null
    //   8509: dload_1
    //   8510: wide
    //   8514: wide
    //   8518: wide
    //   8522: wide
    //   8526: ixor
    //   8527: i2c
    //   8528: castore
    //   8529: wide
    //   8535: goto -6217 -> 2318
    //   8538: bipush 109
    //   8540: wide
    //   8544: goto -34 -> 8510
    //   8547: bipush 90
    //   8549: wide
    //   8553: goto -43 -> 8510
    //   8556: bipush 9
    //   8558: wide
    //   8562: goto -52 -> 8510
    //   8565: bipush 117
    //   8567: wide
    //   8571: goto -61 -> 8510
    //   8574: wide
    //   8578: wide
    //   8582: caload
    //   8583: wide
    //   8587: wide
    //   8591: iconst_5
    //   8592: irem
    //   8593: tableswitch	default:+31 -> 8624, 0:+65->8658, 1:+74->8667, 2:+83->8676, 3:+92->8685
    //   8625: ldc2_w -15306
    //   8628: aconst_null
    //   8629: aload_2
    //   8630: wide
    //   8634: wide
    //   8638: wide
    //   8642: wide
    //   8646: ixor
    //   8647: i2c
    //   8648: castore
    //   8649: wide
    //   8655: goto -6285 -> 2370
    //   8658: bipush 109
    //   8660: wide
    //   8664: goto -34 -> 8630
    //   8667: bipush 90
    //   8669: wide
    //   8673: goto -43 -> 8630
    //   8676: bipush 9
    //   8678: wide
    //   8682: goto -52 -> 8630
    //   8685: bipush 117
    //   8687: wide
    //   8691: goto -61 -> 8630
    //   8694: wide
    //   8698: wide
    //   8702: caload
    //   8703: wide
    //   8707: wide
    //   8711: iconst_5
    //   8712: irem
    //   8713: tableswitch	default:+31 -> 8744, 0:+65->8778, 1:+74->8787, 2:+83->8796, 3:+92->8805
    //   8745: ldc2_w -15306
    //   8748: aconst_null
    //   8749: daload
    //   8750: wide
    //   8754: wide
    //   8758: wide
    //   8762: wide
    //   8766: ixor
    //   8767: i2c
    //   8768: castore
    //   8769: wide
    //   8775: goto -6353 -> 2422
    //   8778: bipush 109
    //   8780: wide
    //   8784: goto -34 -> 8750
    //   8787: bipush 90
    //   8789: wide
    //   8793: goto -43 -> 8750
    //   8796: bipush 9
    //   8798: wide
    //   8802: goto -52 -> 8750
    //   8805: bipush 117
    //   8807: wide
    //   8811: goto -61 -> 8750
    //   8814: wide
    //   8818: wide
    //   8822: caload
    //   8823: wide
    //   8827: wide
    //   8831: iconst_5
    //   8832: irem
    //   8833: tableswitch	default:+31 -> 8864, 0:+65->8898, 1:+74->8907, 2:+83->8916, 3:+92->8925
    //   8865: ldc2_w -15306
    //   8868: aconst_null
    //   8869: istore 196
    //   8871: aload 1
    //   8873: aaload
    //   8874: wide
    //   8878: wide
    //   8882: wide
    //   8886: ixor
    //   8887: i2c
    //   8888: castore
    //   8889: wide
    //   8895: goto -6421 -> 2474
    //   8898: bipush 109
    //   8900: wide
    //   8904: goto -34 -> 8870
    //   8907: bipush 90
    //   8909: wide
    //   8913: goto -43 -> 8870
    //   8916: bipush 9
    //   8918: wide
    //   8922: goto -52 -> 8870
    //   8925: bipush 117
    //   8927: wide
    //   8931: goto -61 -> 8870
    //   8934: wide
    //   8938: wide
    //   8942: caload
    //   8943: wide
    //   8947: wide
    //   8951: iconst_5
    //   8952: irem
    //   8953: tableswitch	default:+31 -> 8984, 0:+65->9018, 1:+74->9027, 2:+83->9036, 3:+92->9045
    //   8985: ldc2_w -15306
    //   8988: aconst_null
    //   8989: istore_0
    //   8990: wide
    //   8994: wide
    //   8998: wide
    //   9002: wide
    //   9006: ixor
    //   9007: i2c
    //   9008: castore
    //   9009: wide
    //   9015: goto -6489 -> 2526
    //   9018: bipush 109
    //   9020: wide
    //   9024: goto -34 -> 8990
    //   9027: bipush 90
    //   9029: wide
    //   9033: goto -43 -> 8990
    //   9036: bipush 9
    //   9038: wide
    //   9042: goto -52 -> 8990
    //   9045: bipush 117
    //   9047: wide
    //   9051: goto -61 -> 8990
    //   9054: wide
    //   9058: wide
    //   9062: caload
    //   9063: wide
    //   9067: wide
    //   9071: iconst_5
    //   9072: irem
    //   9073: tableswitch	default:+31 -> 9104, 0:+65->9138, 1:+74->9147, 2:+83->9156, 3:+92->9165
    //   9105: ldc2_w -15306
    //   9108: aconst_null
    //   9109: lstore_1
    //   9110: wide
    //   9114: wide
    //   9118: wide
    //   9122: wide
    //   9126: ixor
    //   9127: i2c
    //   9128: castore
    //   9129: wide
    //   9135: goto -6557 -> 2578
    //   9138: bipush 109
    //   9140: wide
    //   9144: goto -34 -> 9110
    //   9147: bipush 90
    //   9149: wide
    //   9153: goto -43 -> 9110
    //   9156: bipush 9
    //   9158: wide
    //   9162: goto -52 -> 9110
    //   9165: bipush 117
    //   9167: wide
    //   9171: goto -61 -> 9110
    //   9174: wide
    //   9178: wide
    //   9182: caload
    //   9183: wide
    //   9187: wide
    //   9191: iconst_5
    //   9192: irem
    //   9193: tableswitch	default:+31 -> 9224, 0:+65->9258, 1:+74->9267, 2:+83->9276, 3:+92->9285
    //   9225: ldc2_w -15306
    //   9228: aconst_null
    //   9229: fstore_2
    //   9230: wide
    //   9234: wide
    //   9238: wide
    //   9242: wide
    //   9246: ixor
    //   9247: i2c
    //   9248: castore
    //   9249: wide
    //   9255: goto -6625 -> 2630
    //   9258: bipush 109
    //   9260: wide
    //   9264: goto -34 -> 9230
    //   9267: bipush 90
    //   9269: wide
    //   9273: goto -43 -> 9230
    //   9276: bipush 9
    //   9278: wide
    //   9282: goto -52 -> 9230
    //   9285: bipush 117
    //   9287: wide
    //   9291: goto -61 -> 9230
    //   9294: wide
    //   9298: wide
    //   9302: caload
    //   9303: wide
    //   9307: wide
    //   9311: iconst_5
    //   9312: irem
    //   9313: tableswitch	default:+31 -> 9344, 0:+65->9378, 1:+74->9387, 2:+83->9396, 3:+92->9405
    //   9345: ldc2_w -15306
    //   9348: aconst_null
    //   9349: dstore_3
    //   9350: wide
    //   9354: wide
    //   9358: wide
    //   9362: wide
    //   9366: ixor
    //   9367: i2c
    //   9368: castore
    //   9369: wide
    //   9375: goto -6693 -> 2682
    //   9378: bipush 109
    //   9380: wide
    //   9384: goto -34 -> 9350
    //   9387: bipush 90
    //   9389: wide
    //   9393: goto -43 -> 9350
    //   9396: bipush 9
    //   9398: wide
    //   9402: goto -52 -> 9350
    //   9405: bipush 117
    //   9407: wide
    //   9411: goto -61 -> 9350
    //   9414: wide
    //   9418: wide
    //   9422: caload
    //   9423: wide
    //   9427: wide
    //   9431: iconst_5
    //   9432: irem
    //   9433: tableswitch	default:+31 -> 9464, 0:+65->9498, 1:+74->9507, 2:+83->9516, 3:+92->9525
    //   9465: ldc2_w -15306
    //   9468: aconst_null
    //   9469: iastore
    //   9470: wide
    //   9474: wide
    //   9478: wide
    //   9482: wide
    //   9486: ixor
    //   9487: i2c
    //   9488: castore
    //   9489: wide
    //   9495: goto -6761 -> 2734
    //   9498: bipush 109
    //   9500: wide
    //   9504: goto -34 -> 9470
    //   9507: bipush 90
    //   9509: wide
    //   9513: goto -43 -> 9470
    //   9516: bipush 9
    //   9518: wide
    //   9522: goto -52 -> 9470
    //   9525: bipush 117
    //   9527: wide
    //   9531: goto -61 -> 9470
    //   9534: wide
    //   9538: wide
    //   9542: caload
    //   9543: wide
    //   9547: wide
    //   9551: iconst_5
    //   9552: irem
    //   9553: tableswitch	default:+31 -> 9584, 0:+65->9618, 1:+74->9627, 2:+83->9636, 3:+92->9645
    //   9585: ldc2_w -15306
    //   9588: aconst_null
    //   9589: bastore
    //   9590: wide
    //   9594: wide
    //   9598: wide
    //   9602: wide
    //   9606: ixor
    //   9607: i2c
    //   9608: castore
    //   9609: wide
    //   9615: goto -6829 -> 2786
    //   9618: bipush 109
    //   9620: wide
    //   9624: goto -34 -> 9590
    //   9627: bipush 90
    //   9629: wide
    //   9633: goto -43 -> 9590
    //   9636: bipush 9
    //   9638: wide
    //   9642: goto -52 -> 9590
    //   9645: bipush 117
    //   9647: wide
    //   9651: goto -61 -> 9590
    //   9654: wide
    //   9658: wide
    //   9662: caload
    //   9663: wide
    //   9667: wide
    //   9671: iconst_5
    //   9672: irem
    //   9673: tableswitch	default:+31 -> 9704, 0:+65->9738, 1:+74->9747, 2:+83->9756, 3:+92->9765
    //   9705: ldc2_w -15306
    //   9708: aconst_null
    //   9709: dup
    //   9710: wide
    //   9714: wide
    //   9718: wide
    //   9722: wide
    //   9726: ixor
    //   9727: i2c
    //   9728: castore
    //   9729: wide
    //   9735: goto -6897 -> 2838
    //   9738: bipush 109
    //   9740: wide
    //   9744: goto -34 -> 9710
    //   9747: bipush 90
    //   9749: wide
    //   9753: goto -43 -> 9710
    //   9756: bipush 9
    //   9758: wide
    //   9762: goto -52 -> 9710
    //   9765: bipush 117
    //   9767: wide
    //   9771: goto -61 -> 9710
  }

  static int A()
  {
    return q;
  }

  static int a(int paramInt)
  {
    r = paramInt;
    return paramInt;
  }

  static long a(VerifySms paramVerifySms, long paramLong)
  {
    paramVerifySms.M = paramLong;
    return paramLong;
  }

  private void a(long paramLong)
  {
    if (this.S != null)
    {
      this.S.cancel();
      this.S = null;
    }
    this.I.setEnabled(false);
    View localView = findViewById(2131558785);
    localView.setVisibility(0);
    ProgressBar localProgressBar = (ProgressBar)findViewById(2131558786);
    localProgressBar.setVisibility(0);
    this.S = new jc(this, paramLong, 1000L, localProgressBar, paramLong, localView).start();
  }

  private void a(SmsManager paramSmsManager, String paramString)
  {
    TextView localTextView = this.G;
    StringBuilder localStringBuilder = new StringBuilder();
    Object[] arrayOfObject = new Object[2];
    arrayOfObject[0] = Integer.valueOf(1);
    arrayOfObject[1] = Integer.valueOf(2);
    localTextView.setText(getString(2131296372, arrayOfObject) + " ");
    r = 1;
    m();
    PendingIntent localPendingIntent = PendingIntent.getBroadcast(this, 0, new Intent(ab[46]), 0);
    try
    {
      if (App.f == 2)
      {
        String str = c(this.D, this.E);
        if (str == null)
          str = y;
        paramSmsManager.sendDataMessage(str, null, B, paramString.getBytes(), localPendingIntent, null);
        if (!DialogToastListActivity.f);
      }
      else
      {
        paramSmsManager.sendDataMessage(y, null, B, paramString.getBytes(), localPendingIntent, null);
      }
      g5.b(ab[45] + System.currentTimeMillis());
      return;
    }
    catch (Exception localException)
    {
      while (true)
      {
        g5.b(ab[44]);
        e(ab[47]);
        d();
      }
    }
  }

  static void a(VerifySms paramVerifySms)
  {
    paramVerifySms.k();
  }

  static void a(VerifySms paramVerifySms, boolean paramBoolean)
  {
    paramVerifySms.a(paramBoolean);
  }

  private void a(boolean paramBoolean)
  {
    App.a(this, this.D, this.E);
    r = 0;
    l();
    if ((paramBoolean) && (this.l))
    {
      a();
      if (!DialogToastListActivity.f);
    }
    else
    {
      App.a(this, 2);
      startActivity(new Intent(this, RegisterName.class));
    }
    finish();
  }

  static boolean a(VerifySms paramVerifySms, String paramString)
  {
    return paramVerifySms.a(paramString);
  }

  private boolean a(String paramString)
  {
    boolean bool1 = false;
    boolean bool2 = DialogToastListActivity.f;
    int i;
    if ((paramString != null) && (paramString.length() == 3))
    {
      i = 0;
      if (i >= paramString.length())
        break label51;
      if (Character.isDigit(paramString.charAt(i)))
        break label44;
    }
    while (true)
    {
      return bool1;
      label44: i++;
      if (!bool2)
        break;
      label51: bool1 = true;
    }
  }

  private void b(long paramLong)
  {
    if (this.R != null)
    {
      this.R.cancel();
      this.R = null;
    }
    this.J.setEnabled(false);
    this.R = new kc(this, paramLong, 1000L).start();
  }

  static void b(VerifySms paramVerifySms)
  {
    paramVerifySms.d();
  }

  static void b(VerifySms paramVerifySms, long paramLong)
  {
    paramVerifySms.b(paramLong);
  }

  static boolean b(boolean paramBoolean)
  {
    O = paramBoolean;
    return paramBoolean;
  }

  static long c(long paramLong)
  {
    u = paramLong;
    return paramLong;
  }

  private static String c(String paramString1, String paramString2)
  {
    String str1 = null;
    if ((paramString1 == null) || (paramString2 == null));
    while (true)
    {
      return str1;
      if (ab[5].equals(paramString1))
      {
        String str2 = App.db.getNetworkCountryIso();
        if (str2 != null)
          try
          {
            String str3 = jp.d(str2);
            if (ab[5].equals(str3))
              break label84;
            g5.b(ab[3]);
            str1 = y;
          }
          catch (IOException localIOException)
          {
            g5.b(ab[4], localIOException);
          }
        else
          label84: str1 = d(paramString2);
      }
      else
      {
        str1 = y;
      }
    }
  }

  static void c(VerifySms paramVerifySms)
  {
    paramVerifySms.l();
  }

  static void c(VerifySms paramVerifySms, long paramLong)
  {
    paramVerifySms.a(paramLong);
  }

  static long d(VerifySms paramVerifySms, long paramLong)
  {
    paramVerifySms.T = paramLong;
    return paramLong;
  }

  static String d(VerifySms paramVerifySms)
  {
    return paramVerifySms.D;
  }

  private static String d(String paramString)
  {
    int i = 2;
    boolean bool = DialogToastListActivity.f;
    if ((paramString == null) || (paramString.length() < 10))
      g5.c(ab[23] + paramString);
    String str2;
    for (String str1 = null; ; str1 = null)
    {
      return str1;
      if (paramString.startsWith("9"))
      {
        str2 = paramString.substring(1, paramString.length());
        if (!bool);
      }
      else
      {
        str2 = paramString;
      }
      if (str2.length() == 10)
        break;
      g5.c(ab[17] + paramString);
    }
    int j = '' + str2.charAt(i);
    int k = '' + str2.charAt(3);
    String[] arrayOfString = new String[9];
    arrayOfString[0] = ab[27];
    arrayOfString[1] = ab[21];
    arrayOfString[i] = ab[18];
    arrayOfString[3] = ab[26];
    arrayOfString[4] = ab[11];
    arrayOfString[5] = ab[22];
    arrayOfString[6] = ab[15];
    arrayOfString[7] = ab[25];
    arrayOfString[8] = ab[6];
    int m;
    if ((!str2.startsWith(ab[28])) || (bool))
    {
      if (str2.startsWith(ab[14]))
      {
        if (k != i)
          break label703;
        m = 4;
        label281: if (!bool)
          break label770;
      }
      if (str2.startsWith(ab[12]))
      {
        if (j != 7)
          break label709;
        m = 3;
        label309: if (!bool)
          break label770;
      }
      if (str2.startsWith(ab[7]))
      {
        if ((k < 6) || (k > 8))
          break label715;
        m = 4;
        label344: if (!bool)
          break label770;
      }
      if (str2.startsWith(ab[19]))
      {
        if (k != i)
          break label721;
        m = 4;
        label371: if (!bool)
          break label770;
      }
      if (str2.startsWith(ab[16]))
      {
        if ((k < 5) || (k > 8))
          break label727;
        m = 4;
        label405: if (!bool)
          break label770;
      }
      if (str2.startsWith(ab[20]))
      {
        if (((k < 4) || (k > 6)) && (k != 8))
          break label733;
        m = 4;
        label446: if (!bool)
          break label770;
      }
      if (str2.startsWith(ab[8]))
      {
        if ((k < i) || (k > 4))
          break label739;
        m = 4;
        label479: if (!bool)
          break label770;
      }
      if (str2.startsWith(ab[24]))
      {
        if ((k < i) || (k > 5))
          break label745;
        i = 4;
        label511: if (!bool);
      }
      else if (str2.startsWith(ab[13]))
      {
        if ((k < 4) || (k > 8))
          break label750;
        i = 4;
        label544: if (!bool);
      }
      else if (str2.startsWith(ab[10]))
      {
        if ((k < 5) || (k > 8))
          break label755;
        i = 4;
        label577: if (!bool);
      }
      else if (str2.startsWith(ab[29]))
      {
        if ((k < 4) || (k > 7))
          break label760;
        i = 4;
        label610: if (!bool);
      }
      else
      {
        if ((Arrays.asList(arrayOfString).contains(str2.substring(0, 3))) && (!bool))
          break label765;
        i = 4;
      }
    }
    while (true)
    {
      str1 = ab[30] + str2.substring(i, str2.length());
      g5.b(ab[9] + str1);
      break;
      label703: m = 3;
      break label281;
      label709: m = 4;
      break label309;
      label715: m = 3;
      break label344;
      label721: m = 3;
      break label371;
      label727: m = 3;
      break label405;
      label733: m = 3;
      break label446;
      label739: m = 3;
      break label479;
      label745: i = 3;
      break label511;
      label750: i = 3;
      break label544;
      label755: i = 3;
      break label577;
      label760: i = 3;
      break label610;
      label765: i = 3;
      continue;
      label770: i = m;
    }
  }

  private void d()
  {
    k();
    this.N = 300000L;
    TextView localTextView = this.G;
    StringBuilder localStringBuilder = new StringBuilder();
    Object[] arrayOfObject = new Object[2];
    arrayOfObject[0] = Integer.valueOf(2);
    arrayOfObject[1] = Integer.valueOf(2);
    localTextView.setText(getString(2131296372, arrayOfObject) + " ");
    t();
  }

  static long e(VerifySms paramVerifySms, long paramLong)
  {
    paramVerifySms.U = paramLong;
    return paramLong;
  }

  static String e(VerifySms paramVerifySms)
  {
    return paramVerifySms.E;
  }

  private void e()
  {
    r = 0;
    l();
    App.a(this, 1);
    this.P = ab[2];
    Intent localIntent = new Intent(this, RegisterPhone.class);
    localIntent.putExtra(ab[55], true);
    startActivity(localIntent);
    finish();
  }

  static long f(VerifySms paramVerifySms)
  {
    return paramVerifySms.N;
  }

  private void f()
  {
    if (d())
    {
      registerReceiver(this.X, new IntentFilter(ab[46]));
      v = this.X;
      IntentFilter localIntentFilter = new IntentFilter(ab[57]);
      localIntentFilter.addDataScheme(ab[56]);
      localIntentFilter.addDataAuthority("*", Short.toString(B));
      registerReceiver(this.Z, localIntentFilter);
      x = this.Z;
    }
  }

  static long g(VerifySms paramVerifySms)
  {
    return paramVerifySms.M;
  }

  private void g()
  {
    if (v != null)
    {
      unregisterReceiver(v);
      v = null;
    }
    if (x != null)
    {
      unregisterReceiver(x);
      x = null;
    }
  }

  static long h(VerifySms paramVerifySms)
  {
    return paramVerifySms.L;
  }

  private void h()
  {
    if (w == null)
    {
      registerReceiver(this.Y, new IntentFilter(ab[0]));
      w = this.Y;
    }
  }

  static ProgressBar i(VerifySms paramVerifySms)
  {
    return paramVerifySms.F;
  }

  private void i()
  {
    if (w != null)
    {
      unregisterReceiver(w);
      w = null;
    }
  }

  static TextView j(VerifySms paramVerifySms)
  {
    return paramVerifySms.H;
  }

  private void j()
  {
    if (v != null)
    {
      unregisterReceiver(v);
      v = null;
    }
    if (w != null)
    {
      unregisterReceiver(w);
      w = null;
    }
    if (x != null)
    {
      unregisterReceiver(x);
      x = null;
    }
  }

  private void k()
  {
    if (s != null)
    {
      s.cancel();
      s = null;
    }
  }

  static void k(VerifySms paramVerifySms)
  {
    paramVerifySms.o();
  }

  static EditText l(VerifySms paramVerifySms)
  {
    return paramVerifySms.I;
  }

  private void l()
  {
    SharedPreferences.Editor localEditor = getPreferences(0).edit();
    localEditor.putInt(ab[41], r);
    if (!localEditor.commit())
      g5.c(ab[49]);
  }

  static Button m(VerifySms paramVerifySms)
  {
    return paramVerifySms.J;
  }

  private void m()
  {
    long l = t;
    if (s != null)
    {
      l = u;
      s.cancel();
      s = null;
    }
    s = new ic(this, l, 1000L).start();
  }

  private void n()
  {
    String str = a(this.D, this.E);
    ((TextView)findViewById(2131558773)).setText(str);
    this.F.setVisibility(0);
    this.G.setVisibility(0);
    this.H.setVisibility(0);
    this.J.setVisibility(8);
    ((RelativeLayout)findViewById(2131558774)).setVisibility(8);
    ((RelativeLayout)findViewById(2131558782)).setVisibility(8);
    ((TextView)findViewById(2131558770)).setVisibility(0);
    ((TextView)findViewById(2131558777)).setText(2131296371);
    ((TextView)findViewById(2131558778)).setText("");
    ((TextView)findViewById(2131558778)).setVisibility(8);
    ((TextView)findViewById(2131558779)).setText("");
    ((TextView)findViewById(2131558779)).setVisibility(8);
    ((TextView)findViewById(2131558776)).setVisibility(8);
    ((RelativeLayout)findViewById(2131558771)).setVisibility(0);
  }

  static void n(VerifySms paramVerifySms)
  {
    paramVerifySms.e();
  }

  private void o()
  {
    String str1 = a(this.D, this.E);
    String str2 = getString(2131296376);
    Object[] arrayOfObject = new Object[2];
    arrayOfObject[0] = getString(2131296378);
    arrayOfObject[1] = Integer.valueOf(3);
    String str3 = getString(2131296377, arrayOfObject);
    SpannableStringBuilder localSpannableStringBuilder = c(str1, str1);
    ((TextView)findViewById(2131558777)).setText(str2);
    ((TextView)findViewById(2131558778)).setText(localSpannableStringBuilder);
    ((TextView)findViewById(2131558778)).setVisibility(0);
    ((TextView)findViewById(2131558779)).setText(str3);
    ((TextView)findViewById(2131558779)).setVisibility(0);
    this.F.setVisibility(8);
    this.G.setVisibility(8);
    this.H.setVisibility(8);
    this.J.setVisibility(0);
    ((RelativeLayout)findViewById(2131558774)).setVisibility(0);
    ((TextView)findViewById(2131558770)).setVisibility(8);
    ((TextView)findViewById(2131558776)).setVisibility(0);
    ((RelativeLayout)findViewById(2131558771)).setVisibility(8);
    u();
  }

  static void o(VerifySms paramVerifySms)
  {
    paramVerifySms.p();
  }

  private void p()
  {
    this.Q = true;
    String str1 = a(this.D, this.E);
    String str2 = getString(2131296405);
    String str3 = getString(2131296406);
    SpannableStringBuilder localSpannableStringBuilder = c(str1, str1);
    ((TextView)findViewById(2131558777)).setText(str2);
    ((TextView)findViewById(2131558778)).setText(localSpannableStringBuilder);
    ((TextView)findViewById(2131558778)).setVisibility(0);
    ((TextView)findViewById(2131558779)).setText(str3);
    ((TextView)findViewById(2131558779)).setVisibility(0);
    this.F.setVisibility(8);
    this.G.setVisibility(8);
    this.H.setVisibility(8);
    ((RelativeLayout)findViewById(2131558774)).setVisibility(0);
    ((TextView)findViewById(2131558770)).setVisibility(8);
    ((RelativeLayout)findViewById(2131558771)).setVisibility(8);
  }

  static void p(VerifySms paramVerifySms)
  {
    paramVerifySms.m();
  }

  private void q()
  {
    if (this.Q)
    {
      super.a(ab[40]);
      if (!DialogToastListActivity.f);
    }
    else
    {
      super.a(this.P);
    }
  }

  static void q(VerifySms paramVerifySms)
  {
    paramVerifySms.h();
  }

  private void r()
  {
    String str = App.db.getNetworkOperator();
    if (!ab[48].equals(str));
    while (true)
    {
      B = (short)(16000 + new Random().nextInt(100));
      do
      {
        return;
        B = 0;
      }
      while (!DialogToastListActivity.f);
    }
  }

  static void r(VerifySms paramVerifySms)
  {
    paramVerifySms.i();
  }

  private void s()
  {
    boolean bool = DialogToastListActivity.f;
    ((InputMethodManager)getSystemService(ab[63])).toggleSoftInput(0, 0);
    StringBuilder localStringBuilder = new StringBuilder().append(ab[61]);
    String str1;
    String str2;
    SmsManager localSmsManager;
    if (mh.c())
    {
      str1 = A;
      str2 = str1 + ab[58];
      localSmsManager = SmsManager.getDefault();
      y = b(this.D, this.E);
      g5.b(ab[62] + y);
      switch (r)
      {
      default:
      case 0:
      case 5:
      }
    }
    while (true)
    {
      g5.d(ab[59] + r);
      label222: label253: 
      do
      {
        do
        {
          do
          {
            do
            {
              return;
              str1 = z;
              break;
              this.M = 0L;
              this.N = 0L;
              if ((!d()) || (C == null))
                break label222;
              this.L = 600000L;
              a(localSmsManager, str2);
            }
            while (!bool);
            if (!e())
              break label253;
            this.G.setText("");
            this.L = 300000L;
            t();
          }
          while (!bool);
          g5.d(ab[60]);
          e();
        }
        while (!bool);
        this.G.setText("");
        this.L = 300000L;
        t();
      }
      while (!bool);
    }
  }

  static void s(VerifySms paramVerifySms)
  {
    paramVerifySms.u();
  }

  static long t(VerifySms paramVerifySms)
  {
    return paramVerifySms.T;
  }

  private void t()
  {
    g5.b(ab[64]);
    g();
    C = null;
    App.a(App.Mb, b(C));
    new cc(this).execute(new String[0]);
  }

  static long u(VerifySms paramVerifySms)
  {
    return paramVerifySms.U;
  }

  private void u()
  {
    boolean bool = DialogToastListActivity.f;
    switch (r)
    {
    case 4:
    case 5:
    case 6:
    case 7:
    case 8:
    case 9:
    default:
    case 10:
    case 13:
    case 3:
    case 11:
    case 12:
    }
    while (true)
    {
      g5.d(ab[66] + r);
      ((RelativeLayout)findViewById(2131558782)).setVisibility(0);
      this.J.setText(getString(2131296378));
      this.P = ab[65];
      do
      {
        do
        {
          do
          {
            do
            {
              return;
              this.I.setText("");
              ((RelativeLayout)findViewById(2131558782)).setVisibility(0);
              this.J.setText(getString(2131296378));
            }
            while (!bool);
            this.I.setText("");
            ((RelativeLayout)findViewById(2131558782)).setVisibility(8);
            this.J.setText(getString(2131296378));
          }
          while (!bool);
          ((RelativeLayout)findViewById(2131558782)).setVisibility(0);
          this.J.setText(getString(2131296484));
          this.P = ab[65];
        }
        while (!bool);
        ((RelativeLayout)findViewById(2131558782)).setVisibility(8);
        this.J.setVisibility(8);
      }
      while (!bool);
    }
  }

  static String v()
  {
    return y;
  }

  static String w()
  {
    return z;
  }

  static long x()
  {
    return t;
  }

  static int y()
  {
    return r;
  }

  static int z()
  {
    int i = -1 + q;
    q = i;
    return i;
  }

  protected void a(ServiceState paramServiceState)
  {
    View localView = findViewById(2131558769);
    if (this.k);
    for (int i = 0; ; i = 8)
    {
      localView.setVisibility(i);
      return;
    }
  }

  public void onBackPressed()
  {
  }

  public void onCreate(Bundle paramBundle)
  {
    boolean bool = DialogToastListActivity.f;
    g5.b(ab[35]);
    super.onCreate(paramBundle);
    setContentView(2130903127);
    int i = App.c(this);
    if (i != 4)
    {
      g5.d(ab[31] + i);
      startActivity(new Intent(this, Main.class));
      finish();
    }
    while (true)
    {
      return;
      this.Q = false;
      r();
      if (getIntent().getExtras() != null)
      {
        if (getIntent().getBooleanExtra(ab[36], false))
        {
          r = 5;
          l();
        }
        if ((getIntent().getBooleanExtra(ab[34], this.k)) || (this.k))
        {
          g5.b(ab[33]);
          findViewById(2131558769).setVisibility(0);
        }
      }
      SharedPreferences localSharedPreferences = getSharedPreferences(getString(2131296258), 0);
      this.D = localSharedPreferences.getString(ab[32], null);
      this.E = localSharedPreferences.getString(ab[39], null);
      if ((this.D == null) || (this.E == null))
      {
        g5.c(ab[38]);
        e();
      }
      else
      {
        if ((d()) && (z.length() == 0))
        {
          String str = ab[37];
          int j = str.length();
          Random localRandom = new Random();
          int k = 0;
          do
          {
            if (k >= 32)
              break;
            z += str.charAt(localRandom.nextInt(j));
            A += str.charAt(localRandom.nextInt(j));
            k++;
          }
          while (!bool);
        }
        App.db.listen(this.p, -1);
        this.F = ((ProgressBar)findViewById(2131558492));
        this.G = ((TextView)findViewById(2131558781));
        this.H = ((TextView)findViewById(2131558780));
        this.I = ((EditText)findViewById(2131558784));
        this.I.addTextChangedListener(new h7(this));
        this.J = ((Button)findViewById(2131558788));
        this.J.setOnClickListener(new i7(this));
        this.K = ((Button)findViewById(2131558789));
        Button localButton = this.K;
        Object[] arrayOfObject = new Object[1];
        arrayOfObject[0] = ("" + a(this.D, this.E) + "");
        localButton.setText(getString(2131296380, arrayOfObject));
        this.K.setOnClickListener(new j7(this));
        n();
        f();
      }
    }
  }

  protected Dialog onCreateDialog(int paramInt)
  {
    Object localObject;
    switch (paramInt)
    {
    case 5:
    case 6:
    case 8:
    case 10:
    case 11:
    case 12:
    case 13:
    case 14:
    case 15:
    case 16:
    case 17:
    case 18:
    case 19:
    case 20:
    default:
      localObject = super.onCreateDialog(paramInt);
    case 7:
    case 21:
    case 30:
    case 22:
    case 23:
    case 4:
    case 9:
    case 24:
    case 25:
    case 26:
    case 27:
    case 28:
    case 29:
    }
    while (true)
    {
      return localObject;
      localObject = new AlertDialog.Builder(this).setTitle(2131296269).setMessage(2131296384).setNeutralButton(2131296270, new k7(this)).create();
      continue;
      AlertDialog.Builder localBuilder5 = new AlertDialog.Builder(this);
      Object[] arrayOfObject5 = new Object[1];
      arrayOfObject5[0] = getString(2131296328);
      localObject = localBuilder5.setMessage(getString(2131296333, arrayOfObject5)).setNeutralButton(2131296270, new l7(this)).create();
      continue;
      localObject = new AlertDialog.Builder(this).setMessage(2131296390).setNeutralButton(2131296270, new m7(this)).create();
      continue;
      localObject = new AlertDialog.Builder(this).setMessage(2131296396).setNeutralButton(2131296270, new x6(this)).create();
      continue;
      AlertDialog.Builder localBuilder4 = new AlertDialog.Builder(this);
      Object[] arrayOfObject4 = new Object[1];
      if (ab[68].equals(App.m));
      for (String str = getString(2131296398); ; str = getString(2131296399))
      {
        arrayOfObject4[0] = str;
        localObject = localBuilder4.setMessage(getString(2131296397, arrayOfObject4)).setNeutralButton(2131296270, new y6(this)).create();
        break;
      }
      localObject = new AlertDialog.Builder(this).setTitle(2131296269).setMessage(2131296385).setNeutralButton(2131296270, new z6(this)).create();
      continue;
      localObject = new ProgressDialog(this);
      ((ProgressDialog)localObject).setMessage(getString(2131296335));
      ((ProgressDialog)localObject).setIndeterminate(true);
      ((ProgressDialog)localObject).setCancelable(false);
      this.W = ((ProgressDialog)localObject);
      continue;
      localObject = new ProgressDialog(this);
      ((ProgressDialog)localObject).setMessage(getString(2131296352));
      ((ProgressDialog)localObject).setIndeterminate(true);
      ((ProgressDialog)localObject).setCancelable(false);
      this.W = ((ProgressDialog)localObject);
      continue;
      localObject = new ProgressDialog(this);
      ((ProgressDialog)localObject).setMessage(getString(2131296351));
      ((ProgressDialog)localObject).setIndeterminate(true);
      ((ProgressDialog)localObject).setCancelable(false);
      this.W = ((ProgressDialog)localObject);
      continue;
      localObject = new AlertDialog.Builder(this).setMessage(2131296389).setPositiveButton(2131296336, new b7(this)).setNeutralButton(2131296268, new a7(this)).create();
      continue;
      AlertDialog.Builder localBuilder3 = new AlertDialog.Builder(this);
      Object[] arrayOfObject3 = new Object[1];
      arrayOfObject3[0] = getString(2131296446);
      localObject = localBuilder3.setMessage(getString(2131296403, arrayOfObject3)).setPositiveButton(2131296336, new d7(this)).setNeutralButton(2131296268, new c7(this)).create();
      continue;
      EditText localEditText = new EditText(this);
      InputFilter[] arrayOfInputFilter = new InputFilter[1];
      arrayOfInputFilter[0] = new InputFilter.LengthFilter(3);
      localEditText.setInputType(2);
      localEditText.setFilters(arrayOfInputFilter);
      localEditText.setGravity(17);
      AlertDialog.Builder localBuilder2 = new AlertDialog.Builder(this).setTitle(2131296347);
      Object[] arrayOfObject2 = new Object[1];
      arrayOfObject2[0] = Integer.valueOf(3);
      localObject = localBuilder2.setMessage(getString(2131296348, arrayOfObject2)).setView(localEditText).setPositiveButton(2131296270, new f7(this, localEditText)).setNegativeButton(2131296268, new e7(this)).create();
      continue;
      AlertDialog.Builder localBuilder1 = new AlertDialog.Builder(this);
      Object[] arrayOfObject1 = new Object[1];
      arrayOfObject1[0] = Integer.valueOf(3);
      localObject = localBuilder1.setMessage(getString(2131296353, arrayOfObject1)).setNeutralButton(2131296270, new g7(this)).create();
    }
  }

  public boolean onCreateOptionsMenu(Menu paramMenu)
  {
    paramMenu.add(0, 0, 0, 2131296336).setIcon(2130838470);
    return true;
  }

  protected void onDestroy()
  {
    g5.b(ab[1]);
    App.db.listen(this.p, 0);
    this.V = true;
    j();
    if (s != null)
    {
      s.cancel();
      s = null;
    }
    if (this.S != null)
    {
      this.S.cancel();
      this.S = null;
    }
    if (this.R != null)
    {
      this.R.cancel();
      this.R = null;
    }
    super.onDestroy();
  }

  protected void onNewIntent(Intent paramIntent)
  {
    boolean bool = DialogToastListActivity.f;
    super.onNewIntent(paramIntent);
    switch (paramIntent.getIntExtra(ab[67], 0))
    {
    default:
    case 7:
    case 4:
    case 21:
    case 23:
    case 22:
    }
    while (true)
    {
      return;
      showDialog(7);
      if (bool)
      {
        showDialog(4);
        if (bool)
        {
          showDialog(21);
          if (bool)
          {
            showDialog(23);
            if (bool)
              showDialog(22);
          }
        }
      }
    }
  }

  public boolean onOptionsItemSelected(MenuItem paramMenuItem)
  {
    boolean bool = true;
    switch (paramMenuItem.getItemId())
    {
    default:
      bool = false;
    case 0:
    case 1:
    }
    while (true)
    {
      return bool;
      q();
      continue;
      showDialog(28);
    }
  }

  public void onPause()
  {
    super.onPause();
    g5.b(ab[42] + r);
    SharedPreferences.Editor localEditor = getPreferences(0).edit();
    localEditor.putInt(ab[41], r);
    if (!localEditor.commit())
      g5.c(ab[43]);
    App.a(App.Mb, b(C));
  }

  public boolean onPrepareOptionsMenu(Menu paramMenu)
  {
    if ((O) && (paramMenu.findItem(1) == null))
      paramMenu.add(0, 1, 0, 2131296382).setIcon(2130838495);
    return true;
  }

  public void onResume()
  {
    boolean bool = DialogToastListActivity.f;
    super.onResume();
    r = getPreferences(0).getInt(ab[41], 0);
    C = c(App.e(App.Mb));
    if ((this.D == null) || (this.E == null))
    {
      g5.c(ab[52]);
      e();
      return;
    }
    App.a(this, 4);
    if ((!e()) && (r == 0))
    {
      g5.b(ab[54]);
      r = 3;
      l();
    }
    g5.b(ab[50] + r);
    switch (r)
    {
    default:
    case 0:
    case 5:
    case 3:
    case 10:
    case 11:
    case 13:
    case 1:
    case 2:
    case 7:
    case 6:
    case 4:
    case 8:
    case 9:
    case 12:
    }
    while (true)
    {
      g5.c(ab[51]);
      do
      {
        do
        {
          do
          {
            do
            {
              do
              {
                do
                {
                  do
                  {
                    do
                    {
                      do
                      {
                        App.gb.cancel(1);
                        break;
                        n();
                        s();
                      }
                      while (!bool);
                      o();
                    }
                    while ((!bool) || (s != null));
                    g5.b(ab[53]);
                    e();
                  }
                  while (!bool);
                  showDialog(7);
                }
                while (!bool);
                showDialog(4);
              }
              while (!bool);
              showDialog(21);
            }
            while (!bool);
            showDialog(23);
          }
          while (!bool);
          showDialog(22);
        }
        while (!bool);
        p();
      }
      while (!bool);
    }
  }
}

/* Location:           C:\Users\Jaap\Downloads\Code\WhatsApp-2.8.4278_dex2jar.jar
 * Qualified Name:     com.whatsapp.VerifySms
 * JD-Core Version:    0.6.1
 */