package com.whatsapp;

import android.util.Pair;
import java.io.IOException;
import java.io.InputStreamReader;
import java.security.MessageDigest;
import java.security.NoSuchAlgorithmException;
import java.util.ArrayList;
import java.util.Collection;
import java.util.HashMap;
import java.util.Iterator;
import java.util.LinkedList;
import java.util.List;
import java.util.Set;
import java.util.regex.Matcher;
import java.util.regex.Pattern;
import org.apache.http.Header;
import org.apache.http.HttpEntity;
import org.apache.http.HttpException;
import org.apache.http.HttpResponse;
import org.apache.http.StatusLine;
import org.apache.http.client.entity.UrlEncodedFormEntity;
import org.apache.http.client.methods.HttpGet;
import org.apache.http.client.utils.URLEncodedUtils;
import org.apache.http.impl.client.DefaultHttpClient;
import org.apache.http.message.BasicNameValuePair;
import org.apache.http.params.BasicHttpParams;
import org.apache.http.params.HttpConnectionParams;
import org.apache.http.params.HttpProtocolParams;
import org.apache.http.protocol.RequestExpectContinue;
import org.xmlpull.v1.XmlPullParserException;
import zb;

public class yp
{
  private static jz a;
  private static final String[] z;

  // ERROR //
  static
  {
    // Byte code:
    //   0: bipush 101
    //   2: anewarray 12	java/lang/String
    //   5: astore_0
    //   6: ldc 14
    //   8: invokevirtual 18	java/lang/String:toCharArray	()[C
    //   11: astore_1
    //   12: aload_1
    //   13: arraylength
    //   14: istore_2
    //   15: iconst_0
    //   16: istore_3
    //   17: iload_2
    //   18: iload_3
    //   19: if_icmpgt +4521 -> 4540
    //   22: aload_0
    //   23: iconst_0
    //   24: new 12	java/lang/String
    //   27: dup
    //   28: aload_1
    //   29: invokespecial 22	java/lang/String:<init>	([C)V
    //   32: invokevirtual 26	java/lang/String:intern	()Ljava/lang/String;
    //   35: aastore
    //   36: ldc 28
    //   38: invokevirtual 18	java/lang/String:toCharArray	()[C
    //   41: astore 6
    //   43: aload 6
    //   45: arraylength
    //   46: istore 7
    //   48: iconst_0
    //   49: istore 8
    //   51: iload 7
    //   53: iload 8
    //   55: if_icmpgt +4572 -> 4627
    //   58: aload_0
    //   59: iconst_1
    //   60: new 12	java/lang/String
    //   63: dup
    //   64: aload 6
    //   66: invokespecial 22	java/lang/String:<init>	([C)V
    //   69: invokevirtual 26	java/lang/String:intern	()Ljava/lang/String;
    //   72: aastore
    //   73: ldc 30
    //   75: invokevirtual 18	java/lang/String:toCharArray	()[C
    //   78: astore 11
    //   80: aload 11
    //   82: arraylength
    //   83: istore 12
    //   85: iconst_0
    //   86: istore 13
    //   88: iload 12
    //   90: iload 13
    //   92: if_icmpgt +4625 -> 4717
    //   95: aload_0
    //   96: iconst_2
    //   97: new 12	java/lang/String
    //   100: dup
    //   101: aload 11
    //   103: invokespecial 22	java/lang/String:<init>	([C)V
    //   106: invokevirtual 26	java/lang/String:intern	()Ljava/lang/String;
    //   109: aastore
    //   110: ldc 32
    //   112: invokevirtual 18	java/lang/String:toCharArray	()[C
    //   115: astore 16
    //   117: aload 16
    //   119: arraylength
    //   120: istore 17
    //   122: iconst_0
    //   123: istore 18
    //   125: iload 17
    //   127: iload 18
    //   129: if_icmpgt +4680 -> 4809
    //   132: aload_0
    //   133: iconst_3
    //   134: new 12	java/lang/String
    //   137: dup
    //   138: aload 16
    //   140: invokespecial 22	java/lang/String:<init>	([C)V
    //   143: invokevirtual 26	java/lang/String:intern	()Ljava/lang/String;
    //   146: aastore
    //   147: ldc 34
    //   149: invokevirtual 18	java/lang/String:toCharArray	()[C
    //   152: astore 21
    //   154: aload 21
    //   156: arraylength
    //   157: istore 22
    //   159: iconst_0
    //   160: istore 23
    //   162: iload 22
    //   164: iload 23
    //   166: if_icmpgt +4735 -> 4901
    //   169: aload_0
    //   170: iconst_4
    //   171: new 12	java/lang/String
    //   174: dup
    //   175: aload 21
    //   177: invokespecial 22	java/lang/String:<init>	([C)V
    //   180: invokevirtual 26	java/lang/String:intern	()Ljava/lang/String;
    //   183: aastore
    //   184: ldc 36
    //   186: invokevirtual 18	java/lang/String:toCharArray	()[C
    //   189: astore 26
    //   191: aload 26
    //   193: arraylength
    //   194: istore 27
    //   196: iconst_0
    //   197: istore 28
    //   199: iload 27
    //   201: iload 28
    //   203: if_icmpgt +4790 -> 4993
    //   206: aload_0
    //   207: iconst_5
    //   208: new 12	java/lang/String
    //   211: dup
    //   212: aload 26
    //   214: invokespecial 22	java/lang/String:<init>	([C)V
    //   217: invokevirtual 26	java/lang/String:intern	()Ljava/lang/String;
    //   220: aastore
    //   221: ldc 38
    //   223: invokevirtual 18	java/lang/String:toCharArray	()[C
    //   226: astore 31
    //   228: aload 31
    //   230: arraylength
    //   231: istore 32
    //   233: iconst_0
    //   234: istore 33
    //   236: iload 32
    //   238: iload 33
    //   240: if_icmpgt +4845 -> 5085
    //   243: aload_0
    //   244: bipush 6
    //   246: new 12	java/lang/String
    //   249: dup
    //   250: aload 31
    //   252: invokespecial 22	java/lang/String:<init>	([C)V
    //   255: invokevirtual 26	java/lang/String:intern	()Ljava/lang/String;
    //   258: aastore
    //   259: ldc 40
    //   261: invokevirtual 18	java/lang/String:toCharArray	()[C
    //   264: astore 36
    //   266: aload 36
    //   268: arraylength
    //   269: istore 37
    //   271: iconst_0
    //   272: istore 38
    //   274: iload 37
    //   276: iload 38
    //   278: if_icmpgt +4899 -> 5177
    //   281: aload_0
    //   282: bipush 7
    //   284: new 12	java/lang/String
    //   287: dup
    //   288: aload 36
    //   290: invokespecial 22	java/lang/String:<init>	([C)V
    //   293: invokevirtual 26	java/lang/String:intern	()Ljava/lang/String;
    //   296: aastore
    //   297: ldc 42
    //   299: invokevirtual 18	java/lang/String:toCharArray	()[C
    //   302: astore 41
    //   304: aload 41
    //   306: arraylength
    //   307: istore 42
    //   309: iconst_0
    //   310: istore 43
    //   312: iload 42
    //   314: iload 43
    //   316: if_icmpgt +4953 -> 5269
    //   319: aload_0
    //   320: bipush 8
    //   322: new 12	java/lang/String
    //   325: dup
    //   326: aload 41
    //   328: invokespecial 22	java/lang/String:<init>	([C)V
    //   331: invokevirtual 26	java/lang/String:intern	()Ljava/lang/String;
    //   334: aastore
    //   335: ldc 44
    //   337: invokevirtual 18	java/lang/String:toCharArray	()[C
    //   340: astore 46
    //   342: aload 46
    //   344: arraylength
    //   345: istore 47
    //   347: iconst_0
    //   348: istore 48
    //   350: iload 47
    //   352: iload 48
    //   354: if_icmpgt +5007 -> 5361
    //   357: aload_0
    //   358: bipush 9
    //   360: new 12	java/lang/String
    //   363: dup
    //   364: aload 46
    //   366: invokespecial 22	java/lang/String:<init>	([C)V
    //   369: invokevirtual 26	java/lang/String:intern	()Ljava/lang/String;
    //   372: aastore
    //   373: ldc 46
    //   375: invokevirtual 18	java/lang/String:toCharArray	()[C
    //   378: astore 51
    //   380: aload 51
    //   382: arraylength
    //   383: istore 52
    //   385: iconst_0
    //   386: istore 53
    //   388: iload 52
    //   390: iload 53
    //   392: if_icmpgt +5061 -> 5453
    //   395: aload_0
    //   396: bipush 10
    //   398: new 12	java/lang/String
    //   401: dup
    //   402: aload 51
    //   404: invokespecial 22	java/lang/String:<init>	([C)V
    //   407: invokevirtual 26	java/lang/String:intern	()Ljava/lang/String;
    //   410: aastore
    //   411: ldc 48
    //   413: invokevirtual 18	java/lang/String:toCharArray	()[C
    //   416: astore 56
    //   418: aload 56
    //   420: arraylength
    //   421: istore 57
    //   423: iconst_0
    //   424: istore 58
    //   426: iload 57
    //   428: iload 58
    //   430: if_icmpgt +5115 -> 5545
    //   433: aload_0
    //   434: bipush 11
    //   436: new 12	java/lang/String
    //   439: dup
    //   440: aload 56
    //   442: invokespecial 22	java/lang/String:<init>	([C)V
    //   445: invokevirtual 26	java/lang/String:intern	()Ljava/lang/String;
    //   448: aastore
    //   449: ldc 50
    //   451: invokevirtual 18	java/lang/String:toCharArray	()[C
    //   454: astore 61
    //   456: aload 61
    //   458: arraylength
    //   459: istore 62
    //   461: iconst_0
    //   462: istore 63
    //   464: iload 62
    //   466: iload 63
    //   468: if_icmpgt +5169 -> 5637
    //   471: aload_0
    //   472: bipush 12
    //   474: new 12	java/lang/String
    //   477: dup
    //   478: aload 61
    //   480: invokespecial 22	java/lang/String:<init>	([C)V
    //   483: invokevirtual 26	java/lang/String:intern	()Ljava/lang/String;
    //   486: aastore
    //   487: ldc 52
    //   489: invokevirtual 18	java/lang/String:toCharArray	()[C
    //   492: astore 66
    //   494: aload 66
    //   496: arraylength
    //   497: istore 67
    //   499: iconst_0
    //   500: istore 68
    //   502: iload 67
    //   504: iload 68
    //   506: if_icmpgt +5223 -> 5729
    //   509: aload_0
    //   510: bipush 13
    //   512: new 12	java/lang/String
    //   515: dup
    //   516: aload 66
    //   518: invokespecial 22	java/lang/String:<init>	([C)V
    //   521: invokevirtual 26	java/lang/String:intern	()Ljava/lang/String;
    //   524: aastore
    //   525: ldc 54
    //   527: invokevirtual 18	java/lang/String:toCharArray	()[C
    //   530: astore 71
    //   532: aload 71
    //   534: arraylength
    //   535: istore 72
    //   537: iconst_0
    //   538: istore 73
    //   540: iload 72
    //   542: iload 73
    //   544: if_icmpgt +5277 -> 5821
    //   547: aload_0
    //   548: bipush 14
    //   550: new 12	java/lang/String
    //   553: dup
    //   554: aload 71
    //   556: invokespecial 22	java/lang/String:<init>	([C)V
    //   559: invokevirtual 26	java/lang/String:intern	()Ljava/lang/String;
    //   562: aastore
    //   563: ldc 56
    //   565: invokevirtual 18	java/lang/String:toCharArray	()[C
    //   568: astore 76
    //   570: aload 76
    //   572: arraylength
    //   573: istore 77
    //   575: iconst_0
    //   576: istore 78
    //   578: iload 77
    //   580: iload 78
    //   582: if_icmpgt +5331 -> 5913
    //   585: aload_0
    //   586: bipush 15
    //   588: new 12	java/lang/String
    //   591: dup
    //   592: aload 76
    //   594: invokespecial 22	java/lang/String:<init>	([C)V
    //   597: invokevirtual 26	java/lang/String:intern	()Ljava/lang/String;
    //   600: aastore
    //   601: ldc 58
    //   603: invokevirtual 18	java/lang/String:toCharArray	()[C
    //   606: astore 81
    //   608: aload 81
    //   610: arraylength
    //   611: istore 82
    //   613: iconst_0
    //   614: istore 83
    //   616: iload 82
    //   618: iload 83
    //   620: if_icmpgt +5385 -> 6005
    //   623: aload_0
    //   624: bipush 16
    //   626: new 12	java/lang/String
    //   629: dup
    //   630: aload 81
    //   632: invokespecial 22	java/lang/String:<init>	([C)V
    //   635: invokevirtual 26	java/lang/String:intern	()Ljava/lang/String;
    //   638: aastore
    //   639: ldc 60
    //   641: invokevirtual 18	java/lang/String:toCharArray	()[C
    //   644: astore 86
    //   646: aload 86
    //   648: arraylength
    //   649: istore 87
    //   651: iconst_0
    //   652: istore 88
    //   654: iload 87
    //   656: iload 88
    //   658: if_icmpgt +5439 -> 6097
    //   661: aload_0
    //   662: bipush 17
    //   664: new 12	java/lang/String
    //   667: dup
    //   668: aload 86
    //   670: invokespecial 22	java/lang/String:<init>	([C)V
    //   673: invokevirtual 26	java/lang/String:intern	()Ljava/lang/String;
    //   676: aastore
    //   677: ldc 62
    //   679: invokevirtual 18	java/lang/String:toCharArray	()[C
    //   682: astore 91
    //   684: aload 91
    //   686: arraylength
    //   687: istore 92
    //   689: iconst_0
    //   690: istore 93
    //   692: iload 92
    //   694: iload 93
    //   696: if_icmpgt +5493 -> 6189
    //   699: aload_0
    //   700: bipush 18
    //   702: new 12	java/lang/String
    //   705: dup
    //   706: aload 91
    //   708: invokespecial 22	java/lang/String:<init>	([C)V
    //   711: invokevirtual 26	java/lang/String:intern	()Ljava/lang/String;
    //   714: aastore
    //   715: ldc 64
    //   717: invokevirtual 18	java/lang/String:toCharArray	()[C
    //   720: astore 96
    //   722: aload 96
    //   724: arraylength
    //   725: istore 97
    //   727: iconst_0
    //   728: istore 98
    //   730: iload 97
    //   732: iload 98
    //   734: if_icmpgt +5547 -> 6281
    //   737: aload_0
    //   738: bipush 19
    //   740: new 12	java/lang/String
    //   743: dup
    //   744: aload 96
    //   746: invokespecial 22	java/lang/String:<init>	([C)V
    //   749: invokevirtual 26	java/lang/String:intern	()Ljava/lang/String;
    //   752: aastore
    //   753: ldc 66
    //   755: invokevirtual 18	java/lang/String:toCharArray	()[C
    //   758: astore 101
    //   760: aload 101
    //   762: arraylength
    //   763: istore 102
    //   765: iconst_0
    //   766: istore 103
    //   768: iload 102
    //   770: iload 103
    //   772: if_icmpgt +5601 -> 6373
    //   775: aload_0
    //   776: bipush 20
    //   778: new 12	java/lang/String
    //   781: dup
    //   782: aload 101
    //   784: invokespecial 22	java/lang/String:<init>	([C)V
    //   787: invokevirtual 26	java/lang/String:intern	()Ljava/lang/String;
    //   790: aastore
    //   791: ldc 68
    //   793: invokevirtual 18	java/lang/String:toCharArray	()[C
    //   796: astore 106
    //   798: aload 106
    //   800: arraylength
    //   801: istore 107
    //   803: iconst_0
    //   804: istore 108
    //   806: iload 107
    //   808: iload 108
    //   810: if_icmpgt +5655 -> 6465
    //   813: aload_0
    //   814: bipush 21
    //   816: new 12	java/lang/String
    //   819: dup
    //   820: aload 106
    //   822: invokespecial 22	java/lang/String:<init>	([C)V
    //   825: invokevirtual 26	java/lang/String:intern	()Ljava/lang/String;
    //   828: aastore
    //   829: ldc 70
    //   831: invokevirtual 18	java/lang/String:toCharArray	()[C
    //   834: astore 111
    //   836: aload 111
    //   838: arraylength
    //   839: istore 112
    //   841: iconst_0
    //   842: istore 113
    //   844: iload 112
    //   846: iload 113
    //   848: if_icmpgt +5709 -> 6557
    //   851: aload_0
    //   852: bipush 22
    //   854: new 12	java/lang/String
    //   857: dup
    //   858: aload 111
    //   860: invokespecial 22	java/lang/String:<init>	([C)V
    //   863: invokevirtual 26	java/lang/String:intern	()Ljava/lang/String;
    //   866: aastore
    //   867: ldc 72
    //   869: invokevirtual 18	java/lang/String:toCharArray	()[C
    //   872: astore 116
    //   874: aload 116
    //   876: arraylength
    //   877: istore 117
    //   879: iconst_0
    //   880: istore 118
    //   882: iload 117
    //   884: iload 118
    //   886: if_icmpgt +5763 -> 6649
    //   889: aload_0
    //   890: bipush 23
    //   892: new 12	java/lang/String
    //   895: dup
    //   896: aload 116
    //   898: invokespecial 22	java/lang/String:<init>	([C)V
    //   901: invokevirtual 26	java/lang/String:intern	()Ljava/lang/String;
    //   904: aastore
    //   905: ldc 74
    //   907: invokevirtual 18	java/lang/String:toCharArray	()[C
    //   910: astore 121
    //   912: aload 121
    //   914: arraylength
    //   915: istore 122
    //   917: iconst_0
    //   918: istore 123
    //   920: iload 122
    //   922: iload 123
    //   924: if_icmpgt +5817 -> 6741
    //   927: aload_0
    //   928: bipush 24
    //   930: new 12	java/lang/String
    //   933: dup
    //   934: aload 121
    //   936: invokespecial 22	java/lang/String:<init>	([C)V
    //   939: invokevirtual 26	java/lang/String:intern	()Ljava/lang/String;
    //   942: aastore
    //   943: ldc 76
    //   945: invokevirtual 18	java/lang/String:toCharArray	()[C
    //   948: astore 126
    //   950: aload 126
    //   952: arraylength
    //   953: istore 127
    //   955: iconst_0
    //   956: istore 128
    //   958: iload 127
    //   960: iload 128
    //   962: if_icmpgt +5871 -> 6833
    //   965: aload_0
    //   966: bipush 25
    //   968: new 12	java/lang/String
    //   971: dup
    //   972: aload 126
    //   974: invokespecial 22	java/lang/String:<init>	([C)V
    //   977: invokevirtual 26	java/lang/String:intern	()Ljava/lang/String;
    //   980: aastore
    //   981: ldc 78
    //   983: invokevirtual 18	java/lang/String:toCharArray	()[C
    //   986: astore 131
    //   988: aload 131
    //   990: arraylength
    //   991: istore 132
    //   993: iconst_0
    //   994: istore 133
    //   996: iload 132
    //   998: iload 133
    //   1000: if_icmpgt +5925 -> 6925
    //   1003: aload_0
    //   1004: bipush 26
    //   1006: new 12	java/lang/String
    //   1009: dup
    //   1010: aload 131
    //   1012: invokespecial 22	java/lang/String:<init>	([C)V
    //   1015: invokevirtual 26	java/lang/String:intern	()Ljava/lang/String;
    //   1018: aastore
    //   1019: ldc 80
    //   1021: invokevirtual 18	java/lang/String:toCharArray	()[C
    //   1024: astore 136
    //   1026: aload 136
    //   1028: arraylength
    //   1029: istore 137
    //   1031: iconst_0
    //   1032: istore 138
    //   1034: iload 137
    //   1036: iload 138
    //   1038: if_icmpgt +5979 -> 7017
    //   1041: aload_0
    //   1042: bipush 27
    //   1044: new 12	java/lang/String
    //   1047: dup
    //   1048: aload 136
    //   1050: invokespecial 22	java/lang/String:<init>	([C)V
    //   1053: invokevirtual 26	java/lang/String:intern	()Ljava/lang/String;
    //   1056: aastore
    //   1057: ldc 82
    //   1059: invokevirtual 18	java/lang/String:toCharArray	()[C
    //   1062: astore 141
    //   1064: aload 141
    //   1066: arraylength
    //   1067: istore 142
    //   1069: iconst_0
    //   1070: istore 143
    //   1072: iload 142
    //   1074: iload 143
    //   1076: if_icmpgt +6033 -> 7109
    //   1079: aload_0
    //   1080: bipush 28
    //   1082: new 12	java/lang/String
    //   1085: dup
    //   1086: aload 141
    //   1088: invokespecial 22	java/lang/String:<init>	([C)V
    //   1091: invokevirtual 26	java/lang/String:intern	()Ljava/lang/String;
    //   1094: aastore
    //   1095: ldc 84
    //   1097: invokevirtual 18	java/lang/String:toCharArray	()[C
    //   1100: astore 146
    //   1102: aload 146
    //   1104: arraylength
    //   1105: istore 147
    //   1107: iconst_0
    //   1108: istore 148
    //   1110: iload 147
    //   1112: iload 148
    //   1114: if_icmpgt +6087 -> 7201
    //   1117: aload_0
    //   1118: bipush 29
    //   1120: new 12	java/lang/String
    //   1123: dup
    //   1124: aload 146
    //   1126: invokespecial 22	java/lang/String:<init>	([C)V
    //   1129: invokevirtual 26	java/lang/String:intern	()Ljava/lang/String;
    //   1132: aastore
    //   1133: ldc 86
    //   1135: invokevirtual 18	java/lang/String:toCharArray	()[C
    //   1138: astore 151
    //   1140: aload 151
    //   1142: arraylength
    //   1143: istore 152
    //   1145: iconst_0
    //   1146: istore 153
    //   1148: iload 152
    //   1150: iload 153
    //   1152: if_icmpgt +6141 -> 7293
    //   1155: aload_0
    //   1156: bipush 30
    //   1158: new 12	java/lang/String
    //   1161: dup
    //   1162: aload 151
    //   1164: invokespecial 22	java/lang/String:<init>	([C)V
    //   1167: invokevirtual 26	java/lang/String:intern	()Ljava/lang/String;
    //   1170: aastore
    //   1171: ldc 88
    //   1173: invokevirtual 18	java/lang/String:toCharArray	()[C
    //   1176: astore 156
    //   1178: aload 156
    //   1180: arraylength
    //   1181: istore 157
    //   1183: iconst_0
    //   1184: istore 158
    //   1186: iload 157
    //   1188: iload 158
    //   1190: if_icmpgt +6195 -> 7385
    //   1193: aload_0
    //   1194: bipush 31
    //   1196: new 12	java/lang/String
    //   1199: dup
    //   1200: aload 156
    //   1202: invokespecial 22	java/lang/String:<init>	([C)V
    //   1205: invokevirtual 26	java/lang/String:intern	()Ljava/lang/String;
    //   1208: aastore
    //   1209: ldc 90
    //   1211: invokevirtual 18	java/lang/String:toCharArray	()[C
    //   1214: astore 161
    //   1216: aload 161
    //   1218: arraylength
    //   1219: istore 162
    //   1221: iconst_0
    //   1222: istore 163
    //   1224: iload 162
    //   1226: iload 163
    //   1228: if_icmpgt +6249 -> 7477
    //   1231: aload_0
    //   1232: bipush 32
    //   1234: new 12	java/lang/String
    //   1237: dup
    //   1238: aload 161
    //   1240: invokespecial 22	java/lang/String:<init>	([C)V
    //   1243: invokevirtual 26	java/lang/String:intern	()Ljava/lang/String;
    //   1246: aastore
    //   1247: ldc 92
    //   1249: invokevirtual 18	java/lang/String:toCharArray	()[C
    //   1252: astore 166
    //   1254: aload 166
    //   1256: arraylength
    //   1257: istore 167
    //   1259: iconst_0
    //   1260: istore 168
    //   1262: iload 167
    //   1264: iload 168
    //   1266: if_icmpgt +6303 -> 7569
    //   1269: aload_0
    //   1270: bipush 33
    //   1272: new 12	java/lang/String
    //   1275: dup
    //   1276: aload 166
    //   1278: invokespecial 22	java/lang/String:<init>	([C)V
    //   1281: invokevirtual 26	java/lang/String:intern	()Ljava/lang/String;
    //   1284: aastore
    //   1285: ldc 94
    //   1287: invokevirtual 18	java/lang/String:toCharArray	()[C
    //   1290: astore 171
    //   1292: aload 171
    //   1294: arraylength
    //   1295: istore 172
    //   1297: iconst_0
    //   1298: istore 173
    //   1300: iload 172
    //   1302: iload 173
    //   1304: if_icmpgt +6357 -> 7661
    //   1307: aload_0
    //   1308: bipush 34
    //   1310: new 12	java/lang/String
    //   1313: dup
    //   1314: aload 171
    //   1316: invokespecial 22	java/lang/String:<init>	([C)V
    //   1319: invokevirtual 26	java/lang/String:intern	()Ljava/lang/String;
    //   1322: aastore
    //   1323: ldc 96
    //   1325: invokevirtual 18	java/lang/String:toCharArray	()[C
    //   1328: astore 176
    //   1330: aload 176
    //   1332: arraylength
    //   1333: istore 177
    //   1335: iconst_0
    //   1336: istore 178
    //   1338: iload 177
    //   1340: iload 178
    //   1342: if_icmpgt +6411 -> 7753
    //   1345: aload_0
    //   1346: bipush 35
    //   1348: new 12	java/lang/String
    //   1351: dup
    //   1352: aload 176
    //   1354: invokespecial 22	java/lang/String:<init>	([C)V
    //   1357: invokevirtual 26	java/lang/String:intern	()Ljava/lang/String;
    //   1360: aastore
    //   1361: ldc 98
    //   1363: invokevirtual 18	java/lang/String:toCharArray	()[C
    //   1366: astore 181
    //   1368: aload 181
    //   1370: arraylength
    //   1371: istore 182
    //   1373: iconst_0
    //   1374: istore 183
    //   1376: iload 182
    //   1378: iload 183
    //   1380: if_icmpgt +6465 -> 7845
    //   1383: aload_0
    //   1384: bipush 36
    //   1386: new 12	java/lang/String
    //   1389: dup
    //   1390: aload 181
    //   1392: invokespecial 22	java/lang/String:<init>	([C)V
    //   1395: invokevirtual 26	java/lang/String:intern	()Ljava/lang/String;
    //   1398: aastore
    //   1399: ldc 100
    //   1401: invokevirtual 18	java/lang/String:toCharArray	()[C
    //   1404: astore 186
    //   1406: aload 186
    //   1408: arraylength
    //   1409: istore 187
    //   1411: iconst_0
    //   1412: istore 188
    //   1414: iload 187
    //   1416: iload 188
    //   1418: if_icmpgt +6519 -> 7937
    //   1421: aload_0
    //   1422: bipush 37
    //   1424: new 12	java/lang/String
    //   1427: dup
    //   1428: aload 186
    //   1430: invokespecial 22	java/lang/String:<init>	([C)V
    //   1433: invokevirtual 26	java/lang/String:intern	()Ljava/lang/String;
    //   1436: aastore
    //   1437: ldc 102
    //   1439: invokevirtual 18	java/lang/String:toCharArray	()[C
    //   1442: astore 191
    //   1444: aload 191
    //   1446: arraylength
    //   1447: istore 192
    //   1449: iconst_0
    //   1450: istore 193
    //   1452: iload 192
    //   1454: iload 193
    //   1456: if_icmpgt +6573 -> 8029
    //   1459: aload_0
    //   1460: bipush 38
    //   1462: new 12	java/lang/String
    //   1465: dup
    //   1466: aload 191
    //   1468: invokespecial 22	java/lang/String:<init>	([C)V
    //   1471: invokevirtual 26	java/lang/String:intern	()Ljava/lang/String;
    //   1474: aastore
    //   1475: ldc 104
    //   1477: invokevirtual 18	java/lang/String:toCharArray	()[C
    //   1480: astore 196
    //   1482: aload 196
    //   1484: arraylength
    //   1485: istore 197
    //   1487: iconst_0
    //   1488: istore 198
    //   1490: iload 197
    //   1492: iload 198
    //   1494: if_icmpgt +6627 -> 8121
    //   1497: aload_0
    //   1498: bipush 39
    //   1500: new 12	java/lang/String
    //   1503: dup
    //   1504: aload 196
    //   1506: invokespecial 22	java/lang/String:<init>	([C)V
    //   1509: invokevirtual 26	java/lang/String:intern	()Ljava/lang/String;
    //   1512: aastore
    //   1513: ldc 106
    //   1515: invokevirtual 18	java/lang/String:toCharArray	()[C
    //   1518: astore 201
    //   1520: aload 201
    //   1522: arraylength
    //   1523: istore 202
    //   1525: iconst_0
    //   1526: istore 203
    //   1528: iload 202
    //   1530: iload 203
    //   1532: if_icmpgt +6681 -> 8213
    //   1535: aload_0
    //   1536: bipush 40
    //   1538: new 12	java/lang/String
    //   1541: dup
    //   1542: aload 201
    //   1544: invokespecial 22	java/lang/String:<init>	([C)V
    //   1547: invokevirtual 26	java/lang/String:intern	()Ljava/lang/String;
    //   1550: aastore
    //   1551: ldc 108
    //   1553: invokevirtual 18	java/lang/String:toCharArray	()[C
    //   1556: astore 206
    //   1558: aload 206
    //   1560: arraylength
    //   1561: istore 207
    //   1563: iconst_0
    //   1564: istore 208
    //   1566: iload 207
    //   1568: iload 208
    //   1570: if_icmpgt +6735 -> 8305
    //   1573: aload_0
    //   1574: bipush 41
    //   1576: new 12	java/lang/String
    //   1579: dup
    //   1580: aload 206
    //   1582: invokespecial 22	java/lang/String:<init>	([C)V
    //   1585: invokevirtual 26	java/lang/String:intern	()Ljava/lang/String;
    //   1588: aastore
    //   1589: ldc 110
    //   1591: invokevirtual 18	java/lang/String:toCharArray	()[C
    //   1594: astore 211
    //   1596: aload 211
    //   1598: arraylength
    //   1599: istore 212
    //   1601: iconst_0
    //   1602: istore 213
    //   1604: iload 212
    //   1606: iload 213
    //   1608: if_icmpgt +6789 -> 8397
    //   1611: aload_0
    //   1612: bipush 42
    //   1614: new 12	java/lang/String
    //   1617: dup
    //   1618: aload 211
    //   1620: invokespecial 22	java/lang/String:<init>	([C)V
    //   1623: invokevirtual 26	java/lang/String:intern	()Ljava/lang/String;
    //   1626: aastore
    //   1627: ldc 112
    //   1629: invokevirtual 18	java/lang/String:toCharArray	()[C
    //   1632: astore 216
    //   1634: aload 216
    //   1636: arraylength
    //   1637: istore 217
    //   1639: iconst_0
    //   1640: istore 218
    //   1642: iload 217
    //   1644: iload 218
    //   1646: if_icmpgt +6843 -> 8489
    //   1649: aload_0
    //   1650: bipush 43
    //   1652: new 12	java/lang/String
    //   1655: dup
    //   1656: aload 216
    //   1658: invokespecial 22	java/lang/String:<init>	([C)V
    //   1661: invokevirtual 26	java/lang/String:intern	()Ljava/lang/String;
    //   1664: aastore
    //   1665: ldc 114
    //   1667: invokevirtual 18	java/lang/String:toCharArray	()[C
    //   1670: astore 221
    //   1672: aload 221
    //   1674: arraylength
    //   1675: istore 222
    //   1677: iconst_0
    //   1678: istore 223
    //   1680: iload 222
    //   1682: iload 223
    //   1684: if_icmpgt +6897 -> 8581
    //   1687: aload_0
    //   1688: bipush 44
    //   1690: new 12	java/lang/String
    //   1693: dup
    //   1694: aload 221
    //   1696: invokespecial 22	java/lang/String:<init>	([C)V
    //   1699: invokevirtual 26	java/lang/String:intern	()Ljava/lang/String;
    //   1702: aastore
    //   1703: ldc 116
    //   1705: invokevirtual 18	java/lang/String:toCharArray	()[C
    //   1708: astore 226
    //   1710: aload 226
    //   1712: arraylength
    //   1713: istore 227
    //   1715: iconst_0
    //   1716: istore 228
    //   1718: iload 227
    //   1720: iload 228
    //   1722: if_icmpgt +6951 -> 8673
    //   1725: aload_0
    //   1726: bipush 45
    //   1728: new 12	java/lang/String
    //   1731: dup
    //   1732: aload 226
    //   1734: invokespecial 22	java/lang/String:<init>	([C)V
    //   1737: invokevirtual 26	java/lang/String:intern	()Ljava/lang/String;
    //   1740: aastore
    //   1741: ldc 118
    //   1743: invokevirtual 18	java/lang/String:toCharArray	()[C
    //   1746: astore 231
    //   1748: aload 231
    //   1750: arraylength
    //   1751: istore 232
    //   1753: iconst_0
    //   1754: istore 233
    //   1756: iload 232
    //   1758: iload 233
    //   1760: if_icmpgt +7005 -> 8765
    //   1763: aload_0
    //   1764: bipush 46
    //   1766: new 12	java/lang/String
    //   1769: dup
    //   1770: aload 231
    //   1772: invokespecial 22	java/lang/String:<init>	([C)V
    //   1775: invokevirtual 26	java/lang/String:intern	()Ljava/lang/String;
    //   1778: aastore
    //   1779: ldc 120
    //   1781: invokevirtual 18	java/lang/String:toCharArray	()[C
    //   1784: astore 236
    //   1786: aload 236
    //   1788: arraylength
    //   1789: istore 237
    //   1791: iconst_0
    //   1792: istore 238
    //   1794: iload 237
    //   1796: iload 238
    //   1798: if_icmpgt +7059 -> 8857
    //   1801: aload_0
    //   1802: bipush 47
    //   1804: new 12	java/lang/String
    //   1807: dup
    //   1808: aload 236
    //   1810: invokespecial 22	java/lang/String:<init>	([C)V
    //   1813: invokevirtual 26	java/lang/String:intern	()Ljava/lang/String;
    //   1816: aastore
    //   1817: ldc 122
    //   1819: invokevirtual 18	java/lang/String:toCharArray	()[C
    //   1822: astore 241
    //   1824: aload 241
    //   1826: arraylength
    //   1827: istore 242
    //   1829: iconst_0
    //   1830: istore 243
    //   1832: iload 242
    //   1834: iload 243
    //   1836: if_icmpgt +7113 -> 8949
    //   1839: aload_0
    //   1840: bipush 48
    //   1842: new 12	java/lang/String
    //   1845: dup
    //   1846: aload 241
    //   1848: invokespecial 22	java/lang/String:<init>	([C)V
    //   1851: invokevirtual 26	java/lang/String:intern	()Ljava/lang/String;
    //   1854: aastore
    //   1855: ldc 124
    //   1857: invokevirtual 18	java/lang/String:toCharArray	()[C
    //   1860: astore 246
    //   1862: aload 246
    //   1864: arraylength
    //   1865: istore 247
    //   1867: iconst_0
    //   1868: istore 248
    //   1870: iload 247
    //   1872: iload 248
    //   1874: if_icmpgt +7167 -> 9041
    //   1877: aload_0
    //   1878: bipush 49
    //   1880: new 12	java/lang/String
    //   1883: dup
    //   1884: aload 246
    //   1886: invokespecial 22	java/lang/String:<init>	([C)V
    //   1889: invokevirtual 26	java/lang/String:intern	()Ljava/lang/String;
    //   1892: aastore
    //   1893: ldc 126
    //   1895: invokevirtual 18	java/lang/String:toCharArray	()[C
    //   1898: astore 251
    //   1900: aload 251
    //   1902: arraylength
    //   1903: istore 252
    //   1905: iconst_0
    //   1906: istore 253
    //   1908: iload 252
    //   1910: iload 253
    //   1912: if_icmpgt +7221 -> 9133
    //   1915: aload_0
    //   1916: bipush 50
    //   1918: new 12	java/lang/String
    //   1921: dup
    //   1922: aload 251
    //   1924: invokespecial 22	java/lang/String:<init>	([C)V
    //   1927: invokevirtual 26	java/lang/String:intern	()Ljava/lang/String;
    //   1930: aastore
    //   1931: ldc 128
    //   1933: invokevirtual 18	java/lang/String:toCharArray	()[C
    //   1936: wide
    //   1940: wide
    //   1944: arraylength
    //   1945: wide
    //   1949: iconst_0
    //   1950: wide
    //   1954: wide
    //   1958: wide
    //   1962: if_icmpgt +7263 -> 9225
    //   1965: aload_0
    //   1966: bipush 51
    //   1968: new 12	java/lang/String
    //   1971: dup
    //   1972: wide
    //   1976: invokespecial 22	java/lang/String:<init>	([C)V
    //   1979: invokevirtual 26	java/lang/String:intern	()Ljava/lang/String;
    //   1982: aastore
    //   1983: ldc 130
    //   1985: invokevirtual 18	java/lang/String:toCharArray	()[C
    //   1988: wide
    //   1992: wide
    //   1996: arraylength
    //   1997: wide
    //   2001: iconst_0
    //   2002: wide
    //   2006: wide
    //   2010: wide
    //   2014: if_icmpgt +7332 -> 9346
    //   2017: aload_0
    //   2018: bipush 52
    //   2020: new 12	java/lang/String
    //   2023: dup
    //   2024: wide
    //   2028: invokespecial 22	java/lang/String:<init>	([C)V
    //   2031: invokevirtual 26	java/lang/String:intern	()Ljava/lang/String;
    //   2034: aastore
    //   2035: ldc 132
    //   2037: invokevirtual 18	java/lang/String:toCharArray	()[C
    //   2040: wide
    //   2044: wide
    //   2048: arraylength
    //   2049: wide
    //   2053: iconst_0
    //   2054: wide
    //   2058: wide
    //   2062: wide
    //   2066: if_icmpgt +7400 -> 9466
    //   2069: aload_0
    //   2070: bipush 53
    //   2072: new 12	java/lang/String
    //   2075: dup
    //   2076: wide
    //   2080: invokespecial 22	java/lang/String:<init>	([C)V
    //   2083: invokevirtual 26	java/lang/String:intern	()Ljava/lang/String;
    //   2086: aastore
    //   2087: ldc 134
    //   2089: invokevirtual 18	java/lang/String:toCharArray	()[C
    //   2092: wide
    //   2096: wide
    //   2100: arraylength
    //   2101: wide
    //   2105: iconst_0
    //   2106: wide
    //   2110: wide
    //   2114: wide
    //   2118: if_icmpgt +7468 -> 9586
    //   2121: aload_0
    //   2122: bipush 54
    //   2124: new 12	java/lang/String
    //   2127: dup
    //   2128: wide
    //   2132: invokespecial 22	java/lang/String:<init>	([C)V
    //   2135: invokevirtual 26	java/lang/String:intern	()Ljava/lang/String;
    //   2138: aastore
    //   2139: ldc 136
    //   2141: invokevirtual 18	java/lang/String:toCharArray	()[C
    //   2144: wide
    //   2148: wide
    //   2152: arraylength
    //   2153: wide
    //   2157: iconst_0
    //   2158: wide
    //   2162: wide
    //   2166: wide
    //   2170: if_icmpgt +7536 -> 9706
    //   2173: aload_0
    //   2174: bipush 55
    //   2176: new 12	java/lang/String
    //   2179: dup
    //   2180: wide
    //   2184: invokespecial 22	java/lang/String:<init>	([C)V
    //   2187: invokevirtual 26	java/lang/String:intern	()Ljava/lang/String;
    //   2190: aastore
    //   2191: ldc 138
    //   2193: invokevirtual 18	java/lang/String:toCharArray	()[C
    //   2196: wide
    //   2200: wide
    //   2204: arraylength
    //   2205: wide
    //   2209: iconst_0
    //   2210: wide
    //   2214: wide
    //   2218: wide
    //   2222: if_icmpgt +7604 -> 9826
    //   2225: aload_0
    //   2226: bipush 56
    //   2228: new 12	java/lang/String
    //   2231: dup
    //   2232: wide
    //   2236: invokespecial 22	java/lang/String:<init>	([C)V
    //   2239: invokevirtual 26	java/lang/String:intern	()Ljava/lang/String;
    //   2242: aastore
    //   2243: ldc 140
    //   2245: invokevirtual 18	java/lang/String:toCharArray	()[C
    //   2248: wide
    //   2252: wide
    //   2256: arraylength
    //   2257: wide
    //   2261: iconst_0
    //   2262: wide
    //   2266: wide
    //   2270: wide
    //   2274: if_icmpgt +7672 -> 9946
    //   2277: aload_0
    //   2278: bipush 57
    //   2280: new 12	java/lang/String
    //   2283: dup
    //   2284: wide
    //   2288: invokespecial 22	java/lang/String:<init>	([C)V
    //   2291: invokevirtual 26	java/lang/String:intern	()Ljava/lang/String;
    //   2294: aastore
    //   2295: ldc 142
    //   2297: invokevirtual 18	java/lang/String:toCharArray	()[C
    //   2300: wide
    //   2304: wide
    //   2308: arraylength
    //   2309: wide
    //   2313: iconst_0
    //   2314: wide
    //   2318: wide
    //   2322: wide
    //   2326: if_icmpgt +7740 -> 10066
    //   2329: aload_0
    //   2330: bipush 58
    //   2332: new 12	java/lang/String
    //   2335: dup
    //   2336: wide
    //   2340: invokespecial 22	java/lang/String:<init>	([C)V
    //   2343: invokevirtual 26	java/lang/String:intern	()Ljava/lang/String;
    //   2346: aastore
    //   2347: ldc 144
    //   2349: invokevirtual 18	java/lang/String:toCharArray	()[C
    //   2352: wide
    //   2356: wide
    //   2360: arraylength
    //   2361: wide
    //   2365: iconst_0
    //   2366: wide
    //   2370: wide
    //   2374: wide
    //   2378: if_icmpgt +7808 -> 10186
    //   2381: aload_0
    //   2382: bipush 59
    //   2384: new 12	java/lang/String
    //   2387: dup
    //   2388: wide
    //   2392: invokespecial 22	java/lang/String:<init>	([C)V
    //   2395: invokevirtual 26	java/lang/String:intern	()Ljava/lang/String;
    //   2398: aastore
    //   2399: ldc 146
    //   2401: invokevirtual 18	java/lang/String:toCharArray	()[C
    //   2404: wide
    //   2408: wide
    //   2412: arraylength
    //   2413: wide
    //   2417: iconst_0
    //   2418: wide
    //   2422: wide
    //   2426: wide
    //   2430: if_icmpgt +7876 -> 10306
    //   2433: aload_0
    //   2434: bipush 60
    //   2436: new 12	java/lang/String
    //   2439: dup
    //   2440: wide
    //   2444: invokespecial 22	java/lang/String:<init>	([C)V
    //   2447: invokevirtual 26	java/lang/String:intern	()Ljava/lang/String;
    //   2450: aastore
    //   2451: ldc 148
    //   2453: invokevirtual 18	java/lang/String:toCharArray	()[C
    //   2456: wide
    //   2460: wide
    //   2464: arraylength
    //   2465: wide
    //   2469: iconst_0
    //   2470: wide
    //   2474: wide
    //   2478: wide
    //   2482: if_icmpgt +7944 -> 10426
    //   2485: aload_0
    //   2486: bipush 61
    //   2488: new 12	java/lang/String
    //   2491: dup
    //   2492: wide
    //   2496: invokespecial 22	java/lang/String:<init>	([C)V
    //   2499: invokevirtual 26	java/lang/String:intern	()Ljava/lang/String;
    //   2502: aastore
    //   2503: ldc 150
    //   2505: invokevirtual 18	java/lang/String:toCharArray	()[C
    //   2508: wide
    //   2512: wide
    //   2516: arraylength
    //   2517: wide
    //   2521: iconst_0
    //   2522: wide
    //   2526: wide
    //   2530: wide
    //   2534: if_icmpgt +8012 -> 10546
    //   2537: aload_0
    //   2538: bipush 62
    //   2540: new 12	java/lang/String
    //   2543: dup
    //   2544: wide
    //   2548: invokespecial 22	java/lang/String:<init>	([C)V
    //   2551: invokevirtual 26	java/lang/String:intern	()Ljava/lang/String;
    //   2554: aastore
    //   2555: ldc 152
    //   2557: invokevirtual 18	java/lang/String:toCharArray	()[C
    //   2560: wide
    //   2564: wide
    //   2568: arraylength
    //   2569: wide
    //   2573: iconst_0
    //   2574: wide
    //   2578: wide
    //   2582: wide
    //   2586: if_icmpgt +8080 -> 10666
    //   2589: aload_0
    //   2590: bipush 63
    //   2592: new 12	java/lang/String
    //   2595: dup
    //   2596: wide
    //   2600: invokespecial 22	java/lang/String:<init>	([C)V
    //   2603: invokevirtual 26	java/lang/String:intern	()Ljava/lang/String;
    //   2606: aastore
    //   2607: ldc 154
    //   2609: invokevirtual 18	java/lang/String:toCharArray	()[C
    //   2612: wide
    //   2616: wide
    //   2620: arraylength
    //   2621: wide
    //   2625: iconst_0
    //   2626: wide
    //   2630: wide
    //   2634: wide
    //   2638: if_icmpgt +8148 -> 10786
    //   2641: aload_0
    //   2642: bipush 64
    //   2644: new 12	java/lang/String
    //   2647: dup
    //   2648: wide
    //   2652: invokespecial 22	java/lang/String:<init>	([C)V
    //   2655: invokevirtual 26	java/lang/String:intern	()Ljava/lang/String;
    //   2658: aastore
    //   2659: ldc 156
    //   2661: invokevirtual 18	java/lang/String:toCharArray	()[C
    //   2664: wide
    //   2668: wide
    //   2672: arraylength
    //   2673: wide
    //   2677: iconst_0
    //   2678: wide
    //   2682: wide
    //   2686: wide
    //   2690: if_icmpgt +8216 -> 10906
    //   2693: aload_0
    //   2694: bipush 65
    //   2696: new 12	java/lang/String
    //   2699: dup
    //   2700: wide
    //   2704: invokespecial 22	java/lang/String:<init>	([C)V
    //   2707: invokevirtual 26	java/lang/String:intern	()Ljava/lang/String;
    //   2710: aastore
    //   2711: ldc 158
    //   2713: invokevirtual 18	java/lang/String:toCharArray	()[C
    //   2716: wide
    //   2720: wide
    //   2724: arraylength
    //   2725: wide
    //   2729: iconst_0
    //   2730: wide
    //   2734: wide
    //   2738: wide
    //   2742: if_icmpgt +8284 -> 11026
    //   2745: aload_0
    //   2746: bipush 66
    //   2748: new 12	java/lang/String
    //   2751: dup
    //   2752: wide
    //   2756: invokespecial 22	java/lang/String:<init>	([C)V
    //   2759: invokevirtual 26	java/lang/String:intern	()Ljava/lang/String;
    //   2762: aastore
    //   2763: ldc 160
    //   2765: invokevirtual 18	java/lang/String:toCharArray	()[C
    //   2768: wide
    //   2772: wide
    //   2776: arraylength
    //   2777: wide
    //   2781: iconst_0
    //   2782: wide
    //   2786: wide
    //   2790: wide
    //   2794: if_icmpgt +8352 -> 11146
    //   2797: aload_0
    //   2798: bipush 67
    //   2800: new 12	java/lang/String
    //   2803: dup
    //   2804: wide
    //   2808: invokespecial 22	java/lang/String:<init>	([C)V
    //   2811: invokevirtual 26	java/lang/String:intern	()Ljava/lang/String;
    //   2814: aastore
    //   2815: ldc 162
    //   2817: invokevirtual 18	java/lang/String:toCharArray	()[C
    //   2820: wide
    //   2824: wide
    //   2828: arraylength
    //   2829: wide
    //   2833: iconst_0
    //   2834: wide
    //   2838: wide
    //   2842: wide
    //   2846: if_icmpgt +8420 -> 11266
    //   2849: aload_0
    //   2850: bipush 68
    //   2852: new 12	java/lang/String
    //   2855: dup
    //   2856: wide
    //   2860: invokespecial 22	java/lang/String:<init>	([C)V
    //   2863: invokevirtual 26	java/lang/String:intern	()Ljava/lang/String;
    //   2866: aastore
    //   2867: ldc 164
    //   2869: invokevirtual 18	java/lang/String:toCharArray	()[C
    //   2872: wide
    //   2876: wide
    //   2880: arraylength
    //   2881: wide
    //   2885: iconst_0
    //   2886: wide
    //   2890: wide
    //   2894: wide
    //   2898: if_icmpgt +8488 -> 11386
    //   2901: aload_0
    //   2902: bipush 69
    //   2904: new 12	java/lang/String
    //   2907: dup
    //   2908: wide
    //   2912: invokespecial 22	java/lang/String:<init>	([C)V
    //   2915: invokevirtual 26	java/lang/String:intern	()Ljava/lang/String;
    //   2918: aastore
    //   2919: ldc 166
    //   2921: invokevirtual 18	java/lang/String:toCharArray	()[C
    //   2924: wide
    //   2928: wide
    //   2932: arraylength
    //   2933: wide
    //   2937: iconst_0
    //   2938: wide
    //   2942: wide
    //   2946: wide
    //   2950: if_icmpgt +8556 -> 11506
    //   2953: aload_0
    //   2954: bipush 70
    //   2956: new 12	java/lang/String
    //   2959: dup
    //   2960: wide
    //   2964: invokespecial 22	java/lang/String:<init>	([C)V
    //   2967: invokevirtual 26	java/lang/String:intern	()Ljava/lang/String;
    //   2970: aastore
    //   2971: ldc 168
    //   2973: invokevirtual 18	java/lang/String:toCharArray	()[C
    //   2976: wide
    //   2980: wide
    //   2984: arraylength
    //   2985: wide
    //   2989: iconst_0
    //   2990: wide
    //   2994: wide
    //   2998: wide
    //   3002: if_icmpgt +8624 -> 11626
    //   3005: aload_0
    //   3006: bipush 71
    //   3008: new 12	java/lang/String
    //   3011: dup
    //   3012: wide
    //   3016: invokespecial 22	java/lang/String:<init>	([C)V
    //   3019: invokevirtual 26	java/lang/String:intern	()Ljava/lang/String;
    //   3022: aastore
    //   3023: ldc 170
    //   3025: invokevirtual 18	java/lang/String:toCharArray	()[C
    //   3028: wide
    //   3032: wide
    //   3036: arraylength
    //   3037: wide
    //   3041: iconst_0
    //   3042: wide
    //   3046: wide
    //   3050: wide
    //   3054: if_icmpgt +8692 -> 11746
    //   3057: aload_0
    //   3058: bipush 72
    //   3060: new 12	java/lang/String
    //   3063: dup
    //   3064: wide
    //   3068: invokespecial 22	java/lang/String:<init>	([C)V
    //   3071: invokevirtual 26	java/lang/String:intern	()Ljava/lang/String;
    //   3074: aastore
    //   3075: ldc 172
    //   3077: invokevirtual 18	java/lang/String:toCharArray	()[C
    //   3080: wide
    //   3084: wide
    //   3088: arraylength
    //   3089: wide
    //   3093: iconst_0
    //   3094: wide
    //   3098: wide
    //   3102: wide
    //   3106: if_icmpgt +8760 -> 11866
    //   3109: aload_0
    //   3110: bipush 73
    //   3112: new 12	java/lang/String
    //   3115: dup
    //   3116: wide
    //   3120: invokespecial 22	java/lang/String:<init>	([C)V
    //   3123: invokevirtual 26	java/lang/String:intern	()Ljava/lang/String;
    //   3126: aastore
    //   3127: ldc 174
    //   3129: invokevirtual 18	java/lang/String:toCharArray	()[C
    //   3132: wide
    //   3136: wide
    //   3140: arraylength
    //   3141: wide
    //   3145: iconst_0
    //   3146: wide
    //   3150: wide
    //   3154: wide
    //   3158: if_icmpgt +8828 -> 11986
    //   3161: aload_0
    //   3162: bipush 74
    //   3164: new 12	java/lang/String
    //   3167: dup
    //   3168: wide
    //   3172: invokespecial 22	java/lang/String:<init>	([C)V
    //   3175: invokevirtual 26	java/lang/String:intern	()Ljava/lang/String;
    //   3178: aastore
    //   3179: ldc 176
    //   3181: invokevirtual 18	java/lang/String:toCharArray	()[C
    //   3184: wide
    //   3188: wide
    //   3192: arraylength
    //   3193: wide
    //   3197: iconst_0
    //   3198: wide
    //   3202: wide
    //   3206: wide
    //   3210: if_icmpgt +8896 -> 12106
    //   3213: aload_0
    //   3214: bipush 75
    //   3216: new 12	java/lang/String
    //   3219: dup
    //   3220: wide
    //   3224: invokespecial 22	java/lang/String:<init>	([C)V
    //   3227: invokevirtual 26	java/lang/String:intern	()Ljava/lang/String;
    //   3230: aastore
    //   3231: ldc 178
    //   3233: invokevirtual 18	java/lang/String:toCharArray	()[C
    //   3236: wide
    //   3240: wide
    //   3244: arraylength
    //   3245: wide
    //   3249: iconst_0
    //   3250: wide
    //   3254: wide
    //   3258: wide
    //   3262: if_icmpgt +8964 -> 12226
    //   3265: aload_0
    //   3266: bipush 76
    //   3268: new 12	java/lang/String
    //   3271: dup
    //   3272: wide
    //   3276: invokespecial 22	java/lang/String:<init>	([C)V
    //   3279: invokevirtual 26	java/lang/String:intern	()Ljava/lang/String;
    //   3282: aastore
    //   3283: ldc 180
    //   3285: invokevirtual 18	java/lang/String:toCharArray	()[C
    //   3288: wide
    //   3292: wide
    //   3296: arraylength
    //   3297: wide
    //   3301: iconst_0
    //   3302: wide
    //   3306: wide
    //   3310: wide
    //   3314: if_icmpgt +9032 -> 12346
    //   3317: aload_0
    //   3318: bipush 77
    //   3320: new 12	java/lang/String
    //   3323: dup
    //   3324: wide
    //   3328: invokespecial 22	java/lang/String:<init>	([C)V
    //   3331: invokevirtual 26	java/lang/String:intern	()Ljava/lang/String;
    //   3334: aastore
    //   3335: ldc 182
    //   3337: invokevirtual 18	java/lang/String:toCharArray	()[C
    //   3340: wide
    //   3344: wide
    //   3348: arraylength
    //   3349: wide
    //   3353: iconst_0
    //   3354: wide
    //   3358: wide
    //   3362: wide
    //   3366: if_icmpgt +9100 -> 12466
    //   3369: aload_0
    //   3370: bipush 78
    //   3372: new 12	java/lang/String
    //   3375: dup
    //   3376: wide
    //   3380: invokespecial 22	java/lang/String:<init>	([C)V
    //   3383: invokevirtual 26	java/lang/String:intern	()Ljava/lang/String;
    //   3386: aastore
    //   3387: ldc 184
    //   3389: invokevirtual 18	java/lang/String:toCharArray	()[C
    //   3392: wide
    //   3396: wide
    //   3400: arraylength
    //   3401: wide
    //   3405: iconst_0
    //   3406: wide
    //   3410: wide
    //   3414: wide
    //   3418: if_icmpgt +9168 -> 12586
    //   3421: aload_0
    //   3422: bipush 79
    //   3424: new 12	java/lang/String
    //   3427: dup
    //   3428: wide
    //   3432: invokespecial 22	java/lang/String:<init>	([C)V
    //   3435: invokevirtual 26	java/lang/String:intern	()Ljava/lang/String;
    //   3438: aastore
    //   3439: ldc 186
    //   3441: invokevirtual 18	java/lang/String:toCharArray	()[C
    //   3444: wide
    //   3448: wide
    //   3452: arraylength
    //   3453: wide
    //   3457: iconst_0
    //   3458: wide
    //   3462: wide
    //   3466: wide
    //   3470: if_icmpgt +9236 -> 12706
    //   3473: aload_0
    //   3474: bipush 80
    //   3476: new 12	java/lang/String
    //   3479: dup
    //   3480: wide
    //   3484: invokespecial 22	java/lang/String:<init>	([C)V
    //   3487: invokevirtual 26	java/lang/String:intern	()Ljava/lang/String;
    //   3490: aastore
    //   3491: ldc 188
    //   3493: invokevirtual 18	java/lang/String:toCharArray	()[C
    //   3496: wide
    //   3500: wide
    //   3504: arraylength
    //   3505: wide
    //   3509: iconst_0
    //   3510: wide
    //   3514: wide
    //   3518: wide
    //   3522: if_icmpgt +9304 -> 12826
    //   3525: aload_0
    //   3526: bipush 81
    //   3528: new 12	java/lang/String
    //   3531: dup
    //   3532: wide
    //   3536: invokespecial 22	java/lang/String:<init>	([C)V
    //   3539: invokevirtual 26	java/lang/String:intern	()Ljava/lang/String;
    //   3542: aastore
    //   3543: ldc 190
    //   3545: invokevirtual 18	java/lang/String:toCharArray	()[C
    //   3548: wide
    //   3552: wide
    //   3556: arraylength
    //   3557: wide
    //   3561: iconst_0
    //   3562: wide
    //   3566: wide
    //   3570: wide
    //   3574: if_icmpgt +9372 -> 12946
    //   3577: aload_0
    //   3578: bipush 82
    //   3580: new 12	java/lang/String
    //   3583: dup
    //   3584: wide
    //   3588: invokespecial 22	java/lang/String:<init>	([C)V
    //   3591: invokevirtual 26	java/lang/String:intern	()Ljava/lang/String;
    //   3594: aastore
    //   3595: ldc 192
    //   3597: invokevirtual 18	java/lang/String:toCharArray	()[C
    //   3600: wide
    //   3604: wide
    //   3608: arraylength
    //   3609: wide
    //   3613: iconst_0
    //   3614: wide
    //   3618: wide
    //   3622: wide
    //   3626: if_icmpgt +9440 -> 13066
    //   3629: aload_0
    //   3630: bipush 83
    //   3632: new 12	java/lang/String
    //   3635: dup
    //   3636: wide
    //   3640: invokespecial 22	java/lang/String:<init>	([C)V
    //   3643: invokevirtual 26	java/lang/String:intern	()Ljava/lang/String;
    //   3646: aastore
    //   3647: ldc 194
    //   3649: invokevirtual 18	java/lang/String:toCharArray	()[C
    //   3652: wide
    //   3656: wide
    //   3660: arraylength
    //   3661: wide
    //   3665: iconst_0
    //   3666: wide
    //   3670: wide
    //   3674: wide
    //   3678: if_icmpgt +9508 -> 13186
    //   3681: aload_0
    //   3682: bipush 84
    //   3684: new 12	java/lang/String
    //   3687: dup
    //   3688: wide
    //   3692: invokespecial 22	java/lang/String:<init>	([C)V
    //   3695: invokevirtual 26	java/lang/String:intern	()Ljava/lang/String;
    //   3698: aastore
    //   3699: ldc 196
    //   3701: invokevirtual 18	java/lang/String:toCharArray	()[C
    //   3704: wide
    //   3708: wide
    //   3712: arraylength
    //   3713: wide
    //   3717: iconst_0
    //   3718: wide
    //   3722: wide
    //   3726: wide
    //   3730: if_icmpgt +9576 -> 13306
    //   3733: aload_0
    //   3734: bipush 85
    //   3736: new 12	java/lang/String
    //   3739: dup
    //   3740: wide
    //   3744: invokespecial 22	java/lang/String:<init>	([C)V
    //   3747: invokevirtual 26	java/lang/String:intern	()Ljava/lang/String;
    //   3750: aastore
    //   3751: ldc 198
    //   3753: invokevirtual 18	java/lang/String:toCharArray	()[C
    //   3756: wide
    //   3760: wide
    //   3764: arraylength
    //   3765: wide
    //   3769: iconst_0
    //   3770: wide
    //   3774: wide
    //   3778: wide
    //   3782: if_icmpgt +9644 -> 13426
    //   3785: aload_0
    //   3786: bipush 86
    //   3788: new 12	java/lang/String
    //   3791: dup
    //   3792: wide
    //   3796: invokespecial 22	java/lang/String:<init>	([C)V
    //   3799: invokevirtual 26	java/lang/String:intern	()Ljava/lang/String;
    //   3802: aastore
    //   3803: ldc 200
    //   3805: invokevirtual 18	java/lang/String:toCharArray	()[C
    //   3808: wide
    //   3812: wide
    //   3816: arraylength
    //   3817: wide
    //   3821: iconst_0
    //   3822: wide
    //   3826: wide
    //   3830: wide
    //   3834: if_icmpgt +9712 -> 13546
    //   3837: aload_0
    //   3838: bipush 87
    //   3840: new 12	java/lang/String
    //   3843: dup
    //   3844: wide
    //   3848: invokespecial 22	java/lang/String:<init>	([C)V
    //   3851: invokevirtual 26	java/lang/String:intern	()Ljava/lang/String;
    //   3854: aastore
    //   3855: ldc 202
    //   3857: invokevirtual 18	java/lang/String:toCharArray	()[C
    //   3860: wide
    //   3864: wide
    //   3868: arraylength
    //   3869: wide
    //   3873: iconst_0
    //   3874: wide
    //   3878: wide
    //   3882: wide
    //   3886: if_icmpgt +9780 -> 13666
    //   3889: aload_0
    //   3890: bipush 88
    //   3892: new 12	java/lang/String
    //   3895: dup
    //   3896: wide
    //   3900: invokespecial 22	java/lang/String:<init>	([C)V
    //   3903: invokevirtual 26	java/lang/String:intern	()Ljava/lang/String;
    //   3906: aastore
    //   3907: ldc 204
    //   3909: invokevirtual 18	java/lang/String:toCharArray	()[C
    //   3912: wide
    //   3916: wide
    //   3920: arraylength
    //   3921: wide
    //   3925: iconst_0
    //   3926: wide
    //   3930: wide
    //   3934: wide
    //   3938: if_icmpgt +9848 -> 13786
    //   3941: aload_0
    //   3942: bipush 89
    //   3944: new 12	java/lang/String
    //   3947: dup
    //   3948: wide
    //   3952: invokespecial 22	java/lang/String:<init>	([C)V
    //   3955: invokevirtual 26	java/lang/String:intern	()Ljava/lang/String;
    //   3958: aastore
    //   3959: ldc 206
    //   3961: invokevirtual 18	java/lang/String:toCharArray	()[C
    //   3964: wide
    //   3968: wide
    //   3972: arraylength
    //   3973: wide
    //   3977: iconst_0
    //   3978: wide
    //   3982: wide
    //   3986: wide
    //   3990: if_icmpgt +9916 -> 13906
    //   3993: aload_0
    //   3994: bipush 90
    //   3996: new 12	java/lang/String
    //   3999: dup
    //   4000: wide
    //   4004: invokespecial 22	java/lang/String:<init>	([C)V
    //   4007: invokevirtual 26	java/lang/String:intern	()Ljava/lang/String;
    //   4010: aastore
    //   4011: ldc 208
    //   4013: invokevirtual 18	java/lang/String:toCharArray	()[C
    //   4016: wide
    //   4020: wide
    //   4024: arraylength
    //   4025: wide
    //   4029: iconst_0
    //   4030: wide
    //   4034: wide
    //   4038: wide
    //   4042: if_icmpgt +9984 -> 14026
    //   4045: aload_0
    //   4046: bipush 91
    //   4048: new 12	java/lang/String
    //   4051: dup
    //   4052: wide
    //   4056: invokespecial 22	java/lang/String:<init>	([C)V
    //   4059: invokevirtual 26	java/lang/String:intern	()Ljava/lang/String;
    //   4062: aastore
    //   4063: ldc 210
    //   4065: invokevirtual 18	java/lang/String:toCharArray	()[C
    //   4068: wide
    //   4072: wide
    //   4076: arraylength
    //   4077: wide
    //   4081: iconst_0
    //   4082: wide
    //   4086: wide
    //   4090: wide
    //   4094: if_icmpgt +10052 -> 14146
    //   4097: aload_0
    //   4098: bipush 92
    //   4100: new 12	java/lang/String
    //   4103: dup
    //   4104: wide
    //   4108: invokespecial 22	java/lang/String:<init>	([C)V
    //   4111: invokevirtual 26	java/lang/String:intern	()Ljava/lang/String;
    //   4114: aastore
    //   4115: ldc 212
    //   4117: invokevirtual 18	java/lang/String:toCharArray	()[C
    //   4120: wide
    //   4124: wide
    //   4128: arraylength
    //   4129: wide
    //   4133: iconst_0
    //   4134: wide
    //   4138: wide
    //   4142: wide
    //   4146: if_icmpgt +10120 -> 14266
    //   4149: aload_0
    //   4150: bipush 93
    //   4152: new 12	java/lang/String
    //   4155: dup
    //   4156: wide
    //   4160: invokespecial 22	java/lang/String:<init>	([C)V
    //   4163: invokevirtual 26	java/lang/String:intern	()Ljava/lang/String;
    //   4166: aastore
    //   4167: ldc 214
    //   4169: invokevirtual 18	java/lang/String:toCharArray	()[C
    //   4172: wide
    //   4176: wide
    //   4180: arraylength
    //   4181: wide
    //   4185: iconst_0
    //   4186: wide
    //   4190: wide
    //   4194: wide
    //   4198: if_icmpgt +10188 -> 14386
    //   4201: aload_0
    //   4202: bipush 94
    //   4204: new 12	java/lang/String
    //   4207: dup
    //   4208: wide
    //   4212: invokespecial 22	java/lang/String:<init>	([C)V
    //   4215: invokevirtual 26	java/lang/String:intern	()Ljava/lang/String;
    //   4218: aastore
    //   4219: ldc 216
    //   4221: invokevirtual 18	java/lang/String:toCharArray	()[C
    //   4224: wide
    //   4228: wide
    //   4232: arraylength
    //   4233: wide
    //   4237: iconst_0
    //   4238: wide
    //   4242: wide
    //   4246: wide
    //   4250: if_icmpgt +10256 -> 14506
    //   4253: aload_0
    //   4254: bipush 95
    //   4256: new 12	java/lang/String
    //   4259: dup
    //   4260: wide
    //   4264: invokespecial 22	java/lang/String:<init>	([C)V
    //   4267: invokevirtual 26	java/lang/String:intern	()Ljava/lang/String;
    //   4270: aastore
    //   4271: ldc 218
    //   4273: invokevirtual 18	java/lang/String:toCharArray	()[C
    //   4276: wide
    //   4280: wide
    //   4284: arraylength
    //   4285: wide
    //   4289: iconst_0
    //   4290: wide
    //   4294: wide
    //   4298: wide
    //   4302: if_icmpgt +10324 -> 14626
    //   4305: aload_0
    //   4306: bipush 96
    //   4308: new 12	java/lang/String
    //   4311: dup
    //   4312: wide
    //   4316: invokespecial 22	java/lang/String:<init>	([C)V
    //   4319: invokevirtual 26	java/lang/String:intern	()Ljava/lang/String;
    //   4322: aastore
    //   4323: ldc 220
    //   4325: invokevirtual 18	java/lang/String:toCharArray	()[C
    //   4328: wide
    //   4332: wide
    //   4336: arraylength
    //   4337: wide
    //   4341: iconst_0
    //   4342: wide
    //   4346: wide
    //   4350: wide
    //   4354: if_icmpgt +10392 -> 14746
    //   4357: aload_0
    //   4358: bipush 97
    //   4360: new 12	java/lang/String
    //   4363: dup
    //   4364: wide
    //   4368: invokespecial 22	java/lang/String:<init>	([C)V
    //   4371: invokevirtual 26	java/lang/String:intern	()Ljava/lang/String;
    //   4374: aastore
    //   4375: ldc 222
    //   4377: invokevirtual 18	java/lang/String:toCharArray	()[C
    //   4380: wide
    //   4384: wide
    //   4388: arraylength
    //   4389: wide
    //   4393: iconst_0
    //   4394: wide
    //   4398: wide
    //   4402: wide
    //   4406: if_icmpgt +10460 -> 14866
    //   4409: aload_0
    //   4410: bipush 98
    //   4412: new 12	java/lang/String
    //   4415: dup
    //   4416: wide
    //   4420: invokespecial 22	java/lang/String:<init>	([C)V
    //   4423: invokevirtual 26	java/lang/String:intern	()Ljava/lang/String;
    //   4426: aastore
    //   4427: ldc 224
    //   4429: invokevirtual 18	java/lang/String:toCharArray	()[C
    //   4432: wide
    //   4436: wide
    //   4440: arraylength
    //   4441: wide
    //   4445: iconst_0
    //   4446: wide
    //   4450: wide
    //   4454: wide
    //   4458: if_icmpgt +10528 -> 14986
    //   4461: aload_0
    //   4462: bipush 99
    //   4464: new 12	java/lang/String
    //   4467: dup
    //   4468: wide
    //   4472: invokespecial 22	java/lang/String:<init>	([C)V
    //   4475: invokevirtual 26	java/lang/String:intern	()Ljava/lang/String;
    //   4478: aastore
    //   4479: ldc 226
    //   4481: invokevirtual 18	java/lang/String:toCharArray	()[C
    //   4484: wide
    //   4488: wide
    //   4492: arraylength
    //   4493: wide
    //   4497: iconst_0
    //   4498: wide
    //   4502: wide
    //   4506: wide
    //   4510: if_icmpgt +10596 -> 15106
    //   4513: aload_0
    //   4514: bipush 100
    //   4516: new 12	java/lang/String
    //   4519: dup
    //   4520: wide
    //   4524: invokespecial 22	java/lang/String:<init>	([C)V
    //   4527: invokevirtual 26	java/lang/String:intern	()Ljava/lang/String;
    //   4530: aastore
    //   4531: aload_0
    //   4532: putstatic 228	com/whatsapp/yp:z	[Ljava/lang/String;
    //   4535: aconst_null
    //   4536: putstatic 230	com/whatsapp/yp:a	Lcom/whatsapp/jz;
    //   4539: return
    //   4540: aload_1
    //   4541: iload_3
    //   4542: caload
    //   4543: istore 4
    //   4545: iload_3
    //   4546: iconst_5
    //   4547: irem
    //   4548: tableswitch	default:+32 -> 4580, 0:+51->4599, 1:+58->4606, 2:+65->4613, 3:+72->4620
    //   4581: aastore
    //   4582: istore 5
    //   4584: aload_1
    //   4585: iload_3
    //   4586: iload 5
    //   4588: iload 4
    //   4590: ixor
    //   4591: i2c
    //   4592: castore
    //   4593: iinc 3 1
    //   4596: goto -4579 -> 17
    //   4599: bipush 11
    //   4601: istore 5
    //   4603: goto -19 -> 4584
    //   4606: bipush 34
    //   4608: istore 5
    //   4610: goto -26 -> 4584
    //   4613: bipush 95
    //   4615: istore 5
    //   4617: goto -33 -> 4584
    //   4620: bipush 10
    //   4622: istore 5
    //   4624: goto -40 -> 4584
    //   4627: aload 6
    //   4629: iload 8
    //   4631: caload
    //   4632: istore 9
    //   4634: iload 8
    //   4636: iconst_5
    //   4637: irem
    //   4638: tableswitch	default:+30 -> 4668, 0:+51->4689, 1:+58->4696, 2:+65->4703, 3:+72->4710
    //   4669: aastore
    //   4670: istore 10
    //   4672: aload 6
    //   4674: iload 8
    //   4676: iload 10
    //   4678: iload 9
    //   4680: ixor
    //   4681: i2c
    //   4682: castore
    //   4683: iinc 8 1
    //   4686: goto -4635 -> 51
    //   4689: bipush 11
    //   4691: istore 10
    //   4693: goto -21 -> 4672
    //   4696: bipush 34
    //   4698: istore 10
    //   4700: goto -28 -> 4672
    //   4703: bipush 95
    //   4705: istore 10
    //   4707: goto -35 -> 4672
    //   4710: bipush 10
    //   4712: istore 10
    //   4714: goto -42 -> 4672
    //   4717: aload 11
    //   4719: iload 13
    //   4721: caload
    //   4722: istore 14
    //   4724: iload 13
    //   4726: iconst_5
    //   4727: irem
    //   4728: tableswitch	default:+32 -> 4760, 0:+53->4781, 1:+60->4788, 2:+67->4795, 3:+74->4802
    //   4761: aastore
    //   4762: istore 15
    //   4764: aload 11
    //   4766: iload 13
    //   4768: iload 15
    //   4770: iload 14
    //   4772: ixor
    //   4773: i2c
    //   4774: castore
    //   4775: iinc 13 1
    //   4778: goto -4690 -> 88
    //   4781: bipush 11
    //   4783: istore 15
    //   4785: goto -21 -> 4764
    //   4788: bipush 34
    //   4790: istore 15
    //   4792: goto -28 -> 4764
    //   4795: bipush 95
    //   4797: istore 15
    //   4799: goto -35 -> 4764
    //   4802: bipush 10
    //   4804: istore 15
    //   4806: goto -42 -> 4764
    //   4809: aload 16
    //   4811: iload 18
    //   4813: caload
    //   4814: istore 19
    //   4816: iload 18
    //   4818: iconst_5
    //   4819: irem
    //   4820: tableswitch	default:+32 -> 4852, 0:+53->4873, 1:+60->4880, 2:+67->4887, 3:+74->4894
    //   4853: aastore
    //   4854: istore 20
    //   4856: aload 16
    //   4858: iload 18
    //   4860: iload 20
    //   4862: iload 19
    //   4864: ixor
    //   4865: i2c
    //   4866: castore
    //   4867: iinc 18 1
    //   4870: goto -4745 -> 125
    //   4873: bipush 11
    //   4875: istore 20
    //   4877: goto -21 -> 4856
    //   4880: bipush 34
    //   4882: istore 20
    //   4884: goto -28 -> 4856
    //   4887: bipush 95
    //   4889: istore 20
    //   4891: goto -35 -> 4856
    //   4894: bipush 10
    //   4896: istore 20
    //   4898: goto -42 -> 4856
    //   4901: aload 21
    //   4903: iload 23
    //   4905: caload
    //   4906: istore 24
    //   4908: iload 23
    //   4910: iconst_5
    //   4911: irem
    //   4912: tableswitch	default:+32 -> 4944, 0:+53->4965, 1:+60->4972, 2:+67->4979, 3:+74->4986
    //   4945: aastore
    //   4946: istore 25
    //   4948: aload 21
    //   4950: iload 23
    //   4952: iload 25
    //   4954: iload 24
    //   4956: ixor
    //   4957: i2c
    //   4958: castore
    //   4959: iinc 23 1
    //   4962: goto -4800 -> 162
    //   4965: bipush 11
    //   4967: istore 25
    //   4969: goto -21 -> 4948
    //   4972: bipush 34
    //   4974: istore 25
    //   4976: goto -28 -> 4948
    //   4979: bipush 95
    //   4981: istore 25
    //   4983: goto -35 -> 4948
    //   4986: bipush 10
    //   4988: istore 25
    //   4990: goto -42 -> 4948
    //   4993: aload 26
    //   4995: iload 28
    //   4997: caload
    //   4998: istore 29
    //   5000: iload 28
    //   5002: iconst_5
    //   5003: irem
    //   5004: tableswitch	default:+32 -> 5036, 0:+53->5057, 1:+60->5064, 2:+67->5071, 3:+74->5078
    //   5037: aastore
    //   5038: istore 30
    //   5040: aload 26
    //   5042: iload 28
    //   5044: iload 30
    //   5046: iload 29
    //   5048: ixor
    //   5049: i2c
    //   5050: castore
    //   5051: iinc 28 1
    //   5054: goto -4855 -> 199
    //   5057: bipush 11
    //   5059: istore 30
    //   5061: goto -21 -> 5040
    //   5064: bipush 34
    //   5066: istore 30
    //   5068: goto -28 -> 5040
    //   5071: bipush 95
    //   5073: istore 30
    //   5075: goto -35 -> 5040
    //   5078: bipush 10
    //   5080: istore 30
    //   5082: goto -42 -> 5040
    //   5085: aload 31
    //   5087: iload 33
    //   5089: caload
    //   5090: istore 34
    //   5092: iload 33
    //   5094: iconst_5
    //   5095: irem
    //   5096: tableswitch	default:+32 -> 5128, 0:+53->5149, 1:+60->5156, 2:+67->5163, 3:+74->5170
    //   5129: aastore
    //   5130: istore 35
    //   5132: aload 31
    //   5134: iload 33
    //   5136: iload 35
    //   5138: iload 34
    //   5140: ixor
    //   5141: i2c
    //   5142: castore
    //   5143: iinc 33 1
    //   5146: goto -4910 -> 236
    //   5149: bipush 11
    //   5151: istore 35
    //   5153: goto -21 -> 5132
    //   5156: bipush 34
    //   5158: istore 35
    //   5160: goto -28 -> 5132
    //   5163: bipush 95
    //   5165: istore 35
    //   5167: goto -35 -> 5132
    //   5170: bipush 10
    //   5172: istore 35
    //   5174: goto -42 -> 5132
    //   5177: aload 36
    //   5179: iload 38
    //   5181: caload
    //   5182: istore 39
    //   5184: iload 38
    //   5186: iconst_5
    //   5187: irem
    //   5188: tableswitch	default:+32 -> 5220, 0:+53->5241, 1:+60->5248, 2:+67->5255, 3:+74->5262
    //   5221: aastore
    //   5222: istore 40
    //   5224: aload 36
    //   5226: iload 38
    //   5228: iload 40
    //   5230: iload 39
    //   5232: ixor
    //   5233: i2c
    //   5234: castore
    //   5235: iinc 38 1
    //   5238: goto -4964 -> 274
    //   5241: bipush 11
    //   5243: istore 40
    //   5245: goto -21 -> 5224
    //   5248: bipush 34
    //   5250: istore 40
    //   5252: goto -28 -> 5224
    //   5255: bipush 95
    //   5257: istore 40
    //   5259: goto -35 -> 5224
    //   5262: bipush 10
    //   5264: istore 40
    //   5266: goto -42 -> 5224
    //   5269: aload 41
    //   5271: iload 43
    //   5273: caload
    //   5274: istore 44
    //   5276: iload 43
    //   5278: iconst_5
    //   5279: irem
    //   5280: tableswitch	default:+32 -> 5312, 0:+53->5333, 1:+60->5340, 2:+67->5347, 3:+74->5354
    //   5313: aastore
    //   5314: istore 45
    //   5316: aload 41
    //   5318: iload 43
    //   5320: iload 45
    //   5322: iload 44
    //   5324: ixor
    //   5325: i2c
    //   5326: castore
    //   5327: iinc 43 1
    //   5330: goto -5018 -> 312
    //   5333: bipush 11
    //   5335: istore 45
    //   5337: goto -21 -> 5316
    //   5340: bipush 34
    //   5342: istore 45
    //   5344: goto -28 -> 5316
    //   5347: bipush 95
    //   5349: istore 45
    //   5351: goto -35 -> 5316
    //   5354: bipush 10
    //   5356: istore 45
    //   5358: goto -42 -> 5316
    //   5361: aload 46
    //   5363: iload 48
    //   5365: caload
    //   5366: istore 49
    //   5368: iload 48
    //   5370: iconst_5
    //   5371: irem
    //   5372: tableswitch	default:+32 -> 5404, 0:+53->5425, 1:+60->5432, 2:+67->5439, 3:+74->5446
    //   5405: aastore
    //   5406: istore 50
    //   5408: aload 46
    //   5410: iload 48
    //   5412: iload 50
    //   5414: iload 49
    //   5416: ixor
    //   5417: i2c
    //   5418: castore
    //   5419: iinc 48 1
    //   5422: goto -5072 -> 350
    //   5425: bipush 11
    //   5427: istore 50
    //   5429: goto -21 -> 5408
    //   5432: bipush 34
    //   5434: istore 50
    //   5436: goto -28 -> 5408
    //   5439: bipush 95
    //   5441: istore 50
    //   5443: goto -35 -> 5408
    //   5446: bipush 10
    //   5448: istore 50
    //   5450: goto -42 -> 5408
    //   5453: aload 51
    //   5455: iload 53
    //   5457: caload
    //   5458: istore 54
    //   5460: iload 53
    //   5462: iconst_5
    //   5463: irem
    //   5464: tableswitch	default:+32 -> 5496, 0:+53->5517, 1:+60->5524, 2:+67->5531, 3:+74->5538
    //   5497: aastore
    //   5498: istore 55
    //   5500: aload 51
    //   5502: iload 53
    //   5504: iload 55
    //   5506: iload 54
    //   5508: ixor
    //   5509: i2c
    //   5510: castore
    //   5511: iinc 53 1
    //   5514: goto -5126 -> 388
    //   5517: bipush 11
    //   5519: istore 55
    //   5521: goto -21 -> 5500
    //   5524: bipush 34
    //   5526: istore 55
    //   5528: goto -28 -> 5500
    //   5531: bipush 95
    //   5533: istore 55
    //   5535: goto -35 -> 5500
    //   5538: bipush 10
    //   5540: istore 55
    //   5542: goto -42 -> 5500
    //   5545: aload 56
    //   5547: iload 58
    //   5549: caload
    //   5550: istore 59
    //   5552: iload 58
    //   5554: iconst_5
    //   5555: irem
    //   5556: tableswitch	default:+32 -> 5588, 0:+53->5609, 1:+60->5616, 2:+67->5623, 3:+74->5630
    //   5589: aastore
    //   5590: istore 60
    //   5592: aload 56
    //   5594: iload 58
    //   5596: iload 60
    //   5598: iload 59
    //   5600: ixor
    //   5601: i2c
    //   5602: castore
    //   5603: iinc 58 1
    //   5606: goto -5180 -> 426
    //   5609: bipush 11
    //   5611: istore 60
    //   5613: goto -21 -> 5592
    //   5616: bipush 34
    //   5618: istore 60
    //   5620: goto -28 -> 5592
    //   5623: bipush 95
    //   5625: istore 60
    //   5627: goto -35 -> 5592
    //   5630: bipush 10
    //   5632: istore 60
    //   5634: goto -42 -> 5592
    //   5637: aload 61
    //   5639: iload 63
    //   5641: caload
    //   5642: istore 64
    //   5644: iload 63
    //   5646: iconst_5
    //   5647: irem
    //   5648: tableswitch	default:+32 -> 5680, 0:+53->5701, 1:+60->5708, 2:+67->5715, 3:+74->5722
    //   5681: aastore
    //   5682: istore 65
    //   5684: aload 61
    //   5686: iload 63
    //   5688: iload 65
    //   5690: iload 64
    //   5692: ixor
    //   5693: i2c
    //   5694: castore
    //   5695: iinc 63 1
    //   5698: goto -5234 -> 464
    //   5701: bipush 11
    //   5703: istore 65
    //   5705: goto -21 -> 5684
    //   5708: bipush 34
    //   5710: istore 65
    //   5712: goto -28 -> 5684
    //   5715: bipush 95
    //   5717: istore 65
    //   5719: goto -35 -> 5684
    //   5722: bipush 10
    //   5724: istore 65
    //   5726: goto -42 -> 5684
    //   5729: aload 66
    //   5731: iload 68
    //   5733: caload
    //   5734: istore 69
    //   5736: iload 68
    //   5738: iconst_5
    //   5739: irem
    //   5740: tableswitch	default:+32 -> 5772, 0:+53->5793, 1:+60->5800, 2:+67->5807, 3:+74->5814
    //   5773: aastore
    //   5774: istore 70
    //   5776: aload 66
    //   5778: iload 68
    //   5780: iload 70
    //   5782: iload 69
    //   5784: ixor
    //   5785: i2c
    //   5786: castore
    //   5787: iinc 68 1
    //   5790: goto -5288 -> 502
    //   5793: bipush 11
    //   5795: istore 70
    //   5797: goto -21 -> 5776
    //   5800: bipush 34
    //   5802: istore 70
    //   5804: goto -28 -> 5776
    //   5807: bipush 95
    //   5809: istore 70
    //   5811: goto -35 -> 5776
    //   5814: bipush 10
    //   5816: istore 70
    //   5818: goto -42 -> 5776
    //   5821: aload 71
    //   5823: iload 73
    //   5825: caload
    //   5826: istore 74
    //   5828: iload 73
    //   5830: iconst_5
    //   5831: irem
    //   5832: tableswitch	default:+32 -> 5864, 0:+53->5885, 1:+60->5892, 2:+67->5899, 3:+74->5906
    //   5865: aastore
    //   5866: istore 75
    //   5868: aload 71
    //   5870: iload 73
    //   5872: iload 75
    //   5874: iload 74
    //   5876: ixor
    //   5877: i2c
    //   5878: castore
    //   5879: iinc 73 1
    //   5882: goto -5342 -> 540
    //   5885: bipush 11
    //   5887: istore 75
    //   5889: goto -21 -> 5868
    //   5892: bipush 34
    //   5894: istore 75
    //   5896: goto -28 -> 5868
    //   5899: bipush 95
    //   5901: istore 75
    //   5903: goto -35 -> 5868
    //   5906: bipush 10
    //   5908: istore 75
    //   5910: goto -42 -> 5868
    //   5913: aload 76
    //   5915: iload 78
    //   5917: caload
    //   5918: istore 79
    //   5920: iload 78
    //   5922: iconst_5
    //   5923: irem
    //   5924: tableswitch	default:+32 -> 5956, 0:+53->5977, 1:+60->5984, 2:+67->5991, 3:+74->5998
    //   5957: aastore
    //   5958: istore 80
    //   5960: aload 76
    //   5962: iload 78
    //   5964: iload 80
    //   5966: iload 79
    //   5968: ixor
    //   5969: i2c
    //   5970: castore
    //   5971: iinc 78 1
    //   5974: goto -5396 -> 578
    //   5977: bipush 11
    //   5979: istore 80
    //   5981: goto -21 -> 5960
    //   5984: bipush 34
    //   5986: istore 80
    //   5988: goto -28 -> 5960
    //   5991: bipush 95
    //   5993: istore 80
    //   5995: goto -35 -> 5960
    //   5998: bipush 10
    //   6000: istore 80
    //   6002: goto -42 -> 5960
    //   6005: aload 81
    //   6007: iload 83
    //   6009: caload
    //   6010: istore 84
    //   6012: iload 83
    //   6014: iconst_5
    //   6015: irem
    //   6016: tableswitch	default:+32 -> 6048, 0:+53->6069, 1:+60->6076, 2:+67->6083, 3:+74->6090
    //   6049: aastore
    //   6050: istore 85
    //   6052: aload 81
    //   6054: iload 83
    //   6056: iload 85
    //   6058: iload 84
    //   6060: ixor
    //   6061: i2c
    //   6062: castore
    //   6063: iinc 83 1
    //   6066: goto -5450 -> 616
    //   6069: bipush 11
    //   6071: istore 85
    //   6073: goto -21 -> 6052
    //   6076: bipush 34
    //   6078: istore 85
    //   6080: goto -28 -> 6052
    //   6083: bipush 95
    //   6085: istore 85
    //   6087: goto -35 -> 6052
    //   6090: bipush 10
    //   6092: istore 85
    //   6094: goto -42 -> 6052
    //   6097: aload 86
    //   6099: iload 88
    //   6101: caload
    //   6102: istore 89
    //   6104: iload 88
    //   6106: iconst_5
    //   6107: irem
    //   6108: tableswitch	default:+32 -> 6140, 0:+53->6161, 1:+60->6168, 2:+67->6175, 3:+74->6182
    //   6141: aastore
    //   6142: istore 90
    //   6144: aload 86
    //   6146: iload 88
    //   6148: iload 90
    //   6150: iload 89
    //   6152: ixor
    //   6153: i2c
    //   6154: castore
    //   6155: iinc 88 1
    //   6158: goto -5504 -> 654
    //   6161: bipush 11
    //   6163: istore 90
    //   6165: goto -21 -> 6144
    //   6168: bipush 34
    //   6170: istore 90
    //   6172: goto -28 -> 6144
    //   6175: bipush 95
    //   6177: istore 90
    //   6179: goto -35 -> 6144
    //   6182: bipush 10
    //   6184: istore 90
    //   6186: goto -42 -> 6144
    //   6189: aload 91
    //   6191: iload 93
    //   6193: caload
    //   6194: istore 94
    //   6196: iload 93
    //   6198: iconst_5
    //   6199: irem
    //   6200: tableswitch	default:+32 -> 6232, 0:+53->6253, 1:+60->6260, 2:+67->6267, 3:+74->6274
    //   6233: aastore
    //   6234: istore 95
    //   6236: aload 91
    //   6238: iload 93
    //   6240: iload 95
    //   6242: iload 94
    //   6244: ixor
    //   6245: i2c
    //   6246: castore
    //   6247: iinc 93 1
    //   6250: goto -5558 -> 692
    //   6253: bipush 11
    //   6255: istore 95
    //   6257: goto -21 -> 6236
    //   6260: bipush 34
    //   6262: istore 95
    //   6264: goto -28 -> 6236
    //   6267: bipush 95
    //   6269: istore 95
    //   6271: goto -35 -> 6236
    //   6274: bipush 10
    //   6276: istore 95
    //   6278: goto -42 -> 6236
    //   6281: aload 96
    //   6283: iload 98
    //   6285: caload
    //   6286: istore 99
    //   6288: iload 98
    //   6290: iconst_5
    //   6291: irem
    //   6292: tableswitch	default:+32 -> 6324, 0:+53->6345, 1:+60->6352, 2:+67->6359, 3:+74->6366
    //   6325: aastore
    //   6326: istore 100
    //   6328: aload 96
    //   6330: iload 98
    //   6332: iload 100
    //   6334: iload 99
    //   6336: ixor
    //   6337: i2c
    //   6338: castore
    //   6339: iinc 98 1
    //   6342: goto -5612 -> 730
    //   6345: bipush 11
    //   6347: istore 100
    //   6349: goto -21 -> 6328
    //   6352: bipush 34
    //   6354: istore 100
    //   6356: goto -28 -> 6328
    //   6359: bipush 95
    //   6361: istore 100
    //   6363: goto -35 -> 6328
    //   6366: bipush 10
    //   6368: istore 100
    //   6370: goto -42 -> 6328
    //   6373: aload 101
    //   6375: iload 103
    //   6377: caload
    //   6378: istore 104
    //   6380: iload 103
    //   6382: iconst_5
    //   6383: irem
    //   6384: tableswitch	default:+32 -> 6416, 0:+53->6437, 1:+60->6444, 2:+67->6451, 3:+74->6458
    //   6417: aastore
    //   6418: istore 105
    //   6420: aload 101
    //   6422: iload 103
    //   6424: iload 105
    //   6426: iload 104
    //   6428: ixor
    //   6429: i2c
    //   6430: castore
    //   6431: iinc 103 1
    //   6434: goto -5666 -> 768
    //   6437: bipush 11
    //   6439: istore 105
    //   6441: goto -21 -> 6420
    //   6444: bipush 34
    //   6446: istore 105
    //   6448: goto -28 -> 6420
    //   6451: bipush 95
    //   6453: istore 105
    //   6455: goto -35 -> 6420
    //   6458: bipush 10
    //   6460: istore 105
    //   6462: goto -42 -> 6420
    //   6465: aload 106
    //   6467: iload 108
    //   6469: caload
    //   6470: istore 109
    //   6472: iload 108
    //   6474: iconst_5
    //   6475: irem
    //   6476: tableswitch	default:+32 -> 6508, 0:+53->6529, 1:+60->6536, 2:+67->6543, 3:+74->6550
    //   6509: aastore
    //   6510: istore 110
    //   6512: aload 106
    //   6514: iload 108
    //   6516: iload 110
    //   6518: iload 109
    //   6520: ixor
    //   6521: i2c
    //   6522: castore
    //   6523: iinc 108 1
    //   6526: goto -5720 -> 806
    //   6529: bipush 11
    //   6531: istore 110
    //   6533: goto -21 -> 6512
    //   6536: bipush 34
    //   6538: istore 110
    //   6540: goto -28 -> 6512
    //   6543: bipush 95
    //   6545: istore 110
    //   6547: goto -35 -> 6512
    //   6550: bipush 10
    //   6552: istore 110
    //   6554: goto -42 -> 6512
    //   6557: aload 111
    //   6559: iload 113
    //   6561: caload
    //   6562: istore 114
    //   6564: iload 113
    //   6566: iconst_5
    //   6567: irem
    //   6568: tableswitch	default:+32 -> 6600, 0:+53->6621, 1:+60->6628, 2:+67->6635, 3:+74->6642
    //   6601: aastore
    //   6602: istore 115
    //   6604: aload 111
    //   6606: iload 113
    //   6608: iload 115
    //   6610: iload 114
    //   6612: ixor
    //   6613: i2c
    //   6614: castore
    //   6615: iinc 113 1
    //   6618: goto -5774 -> 844
    //   6621: bipush 11
    //   6623: istore 115
    //   6625: goto -21 -> 6604
    //   6628: bipush 34
    //   6630: istore 115
    //   6632: goto -28 -> 6604
    //   6635: bipush 95
    //   6637: istore 115
    //   6639: goto -35 -> 6604
    //   6642: bipush 10
    //   6644: istore 115
    //   6646: goto -42 -> 6604
    //   6649: aload 116
    //   6651: iload 118
    //   6653: caload
    //   6654: istore 119
    //   6656: iload 118
    //   6658: iconst_5
    //   6659: irem
    //   6660: tableswitch	default:+32 -> 6692, 0:+53->6713, 1:+60->6720, 2:+67->6727, 3:+74->6734
    //   6693: aastore
    //   6694: istore 120
    //   6696: aload 116
    //   6698: iload 118
    //   6700: iload 120
    //   6702: iload 119
    //   6704: ixor
    //   6705: i2c
    //   6706: castore
    //   6707: iinc 118 1
    //   6710: goto -5828 -> 882
    //   6713: bipush 11
    //   6715: istore 120
    //   6717: goto -21 -> 6696
    //   6720: bipush 34
    //   6722: istore 120
    //   6724: goto -28 -> 6696
    //   6727: bipush 95
    //   6729: istore 120
    //   6731: goto -35 -> 6696
    //   6734: bipush 10
    //   6736: istore 120
    //   6738: goto -42 -> 6696
    //   6741: aload 121
    //   6743: iload 123
    //   6745: caload
    //   6746: istore 124
    //   6748: iload 123
    //   6750: iconst_5
    //   6751: irem
    //   6752: tableswitch	default:+32 -> 6784, 0:+53->6805, 1:+60->6812, 2:+67->6819, 3:+74->6826
    //   6785: aastore
    //   6786: istore 125
    //   6788: aload 121
    //   6790: iload 123
    //   6792: iload 125
    //   6794: iload 124
    //   6796: ixor
    //   6797: i2c
    //   6798: castore
    //   6799: iinc 123 1
    //   6802: goto -5882 -> 920
    //   6805: bipush 11
    //   6807: istore 125
    //   6809: goto -21 -> 6788
    //   6812: bipush 34
    //   6814: istore 125
    //   6816: goto -28 -> 6788
    //   6819: bipush 95
    //   6821: istore 125
    //   6823: goto -35 -> 6788
    //   6826: bipush 10
    //   6828: istore 125
    //   6830: goto -42 -> 6788
    //   6833: aload 126
    //   6835: iload 128
    //   6837: caload
    //   6838: istore 129
    //   6840: iload 128
    //   6842: iconst_5
    //   6843: irem
    //   6844: tableswitch	default:+32 -> 6876, 0:+53->6897, 1:+60->6904, 2:+67->6911, 3:+74->6918
    //   6877: aastore
    //   6878: istore 130
    //   6880: aload 126
    //   6882: iload 128
    //   6884: iload 130
    //   6886: iload 129
    //   6888: ixor
    //   6889: i2c
    //   6890: castore
    //   6891: iinc 128 1
    //   6894: goto -5936 -> 958
    //   6897: bipush 11
    //   6899: istore 130
    //   6901: goto -21 -> 6880
    //   6904: bipush 34
    //   6906: istore 130
    //   6908: goto -28 -> 6880
    //   6911: bipush 95
    //   6913: istore 130
    //   6915: goto -35 -> 6880
    //   6918: bipush 10
    //   6920: istore 130
    //   6922: goto -42 -> 6880
    //   6925: aload 131
    //   6927: iload 133
    //   6929: caload
    //   6930: istore 134
    //   6932: iload 133
    //   6934: iconst_5
    //   6935: irem
    //   6936: tableswitch	default:+32 -> 6968, 0:+53->6989, 1:+60->6996, 2:+67->7003, 3:+74->7010
    //   6969: aastore
    //   6970: istore 135
    //   6972: aload 131
    //   6974: iload 133
    //   6976: iload 135
    //   6978: iload 134
    //   6980: ixor
    //   6981: i2c
    //   6982: castore
    //   6983: iinc 133 1
    //   6986: goto -5990 -> 996
    //   6989: bipush 11
    //   6991: istore 135
    //   6993: goto -21 -> 6972
    //   6996: bipush 34
    //   6998: istore 135
    //   7000: goto -28 -> 6972
    //   7003: bipush 95
    //   7005: istore 135
    //   7007: goto -35 -> 6972
    //   7010: bipush 10
    //   7012: istore 135
    //   7014: goto -42 -> 6972
    //   7017: aload 136
    //   7019: iload 138
    //   7021: caload
    //   7022: istore 139
    //   7024: iload 138
    //   7026: iconst_5
    //   7027: irem
    //   7028: tableswitch	default:+32 -> 7060, 0:+53->7081, 1:+60->7088, 2:+67->7095, 3:+74->7102
    //   7061: aastore
    //   7062: istore 140
    //   7064: aload 136
    //   7066: iload 138
    //   7068: iload 140
    //   7070: iload 139
    //   7072: ixor
    //   7073: i2c
    //   7074: castore
    //   7075: iinc 138 1
    //   7078: goto -6044 -> 1034
    //   7081: bipush 11
    //   7083: istore 140
    //   7085: goto -21 -> 7064
    //   7088: bipush 34
    //   7090: istore 140
    //   7092: goto -28 -> 7064
    //   7095: bipush 95
    //   7097: istore 140
    //   7099: goto -35 -> 7064
    //   7102: bipush 10
    //   7104: istore 140
    //   7106: goto -42 -> 7064
    //   7109: aload 141
    //   7111: iload 143
    //   7113: caload
    //   7114: istore 144
    //   7116: iload 143
    //   7118: iconst_5
    //   7119: irem
    //   7120: tableswitch	default:+32 -> 7152, 0:+53->7173, 1:+60->7180, 2:+67->7187, 3:+74->7194
    //   7153: aastore
    //   7154: istore 145
    //   7156: aload 141
    //   7158: iload 143
    //   7160: iload 145
    //   7162: iload 144
    //   7164: ixor
    //   7165: i2c
    //   7166: castore
    //   7167: iinc 143 1
    //   7170: goto -6098 -> 1072
    //   7173: bipush 11
    //   7175: istore 145
    //   7177: goto -21 -> 7156
    //   7180: bipush 34
    //   7182: istore 145
    //   7184: goto -28 -> 7156
    //   7187: bipush 95
    //   7189: istore 145
    //   7191: goto -35 -> 7156
    //   7194: bipush 10
    //   7196: istore 145
    //   7198: goto -42 -> 7156
    //   7201: aload 146
    //   7203: iload 148
    //   7205: caload
    //   7206: istore 149
    //   7208: iload 148
    //   7210: iconst_5
    //   7211: irem
    //   7212: tableswitch	default:+32 -> 7244, 0:+53->7265, 1:+60->7272, 2:+67->7279, 3:+74->7286
    //   7245: aastore
    //   7246: istore 150
    //   7248: aload 146
    //   7250: iload 148
    //   7252: iload 150
    //   7254: iload 149
    //   7256: ixor
    //   7257: i2c
    //   7258: castore
    //   7259: iinc 148 1
    //   7262: goto -6152 -> 1110
    //   7265: bipush 11
    //   7267: istore 150
    //   7269: goto -21 -> 7248
    //   7272: bipush 34
    //   7274: istore 150
    //   7276: goto -28 -> 7248
    //   7279: bipush 95
    //   7281: istore 150
    //   7283: goto -35 -> 7248
    //   7286: bipush 10
    //   7288: istore 150
    //   7290: goto -42 -> 7248
    //   7293: aload 151
    //   7295: iload 153
    //   7297: caload
    //   7298: istore 154
    //   7300: iload 153
    //   7302: iconst_5
    //   7303: irem
    //   7304: tableswitch	default:+32 -> 7336, 0:+53->7357, 1:+60->7364, 2:+67->7371, 3:+74->7378
    //   7337: aastore
    //   7338: istore 155
    //   7340: aload 151
    //   7342: iload 153
    //   7344: iload 155
    //   7346: iload 154
    //   7348: ixor
    //   7349: i2c
    //   7350: castore
    //   7351: iinc 153 1
    //   7354: goto -6206 -> 1148
    //   7357: bipush 11
    //   7359: istore 155
    //   7361: goto -21 -> 7340
    //   7364: bipush 34
    //   7366: istore 155
    //   7368: goto -28 -> 7340
    //   7371: bipush 95
    //   7373: istore 155
    //   7375: goto -35 -> 7340
    //   7378: bipush 10
    //   7380: istore 155
    //   7382: goto -42 -> 7340
    //   7385: aload 156
    //   7387: iload 158
    //   7389: caload
    //   7390: istore 159
    //   7392: iload 158
    //   7394: iconst_5
    //   7395: irem
    //   7396: tableswitch	default:+32 -> 7428, 0:+53->7449, 1:+60->7456, 2:+67->7463, 3:+74->7470
    //   7429: aastore
    //   7430: istore 160
    //   7432: aload 156
    //   7434: iload 158
    //   7436: iload 160
    //   7438: iload 159
    //   7440: ixor
    //   7441: i2c
    //   7442: castore
    //   7443: iinc 158 1
    //   7446: goto -6260 -> 1186
    //   7449: bipush 11
    //   7451: istore 160
    //   7453: goto -21 -> 7432
    //   7456: bipush 34
    //   7458: istore 160
    //   7460: goto -28 -> 7432
    //   7463: bipush 95
    //   7465: istore 160
    //   7467: goto -35 -> 7432
    //   7470: bipush 10
    //   7472: istore 160
    //   7474: goto -42 -> 7432
    //   7477: aload 161
    //   7479: iload 163
    //   7481: caload
    //   7482: istore 164
    //   7484: iload 163
    //   7486: iconst_5
    //   7487: irem
    //   7488: tableswitch	default:+32 -> 7520, 0:+53->7541, 1:+60->7548, 2:+67->7555, 3:+74->7562
    //   7521: aastore
    //   7522: istore 165
    //   7524: aload 161
    //   7526: iload 163
    //   7528: iload 165
    //   7530: iload 164
    //   7532: ixor
    //   7533: i2c
    //   7534: castore
    //   7535: iinc 163 1
    //   7538: goto -6314 -> 1224
    //   7541: bipush 11
    //   7543: istore 165
    //   7545: goto -21 -> 7524
    //   7548: bipush 34
    //   7550: istore 165
    //   7552: goto -28 -> 7524
    //   7555: bipush 95
    //   7557: istore 165
    //   7559: goto -35 -> 7524
    //   7562: bipush 10
    //   7564: istore 165
    //   7566: goto -42 -> 7524
    //   7569: aload 166
    //   7571: iload 168
    //   7573: caload
    //   7574: istore 169
    //   7576: iload 168
    //   7578: iconst_5
    //   7579: irem
    //   7580: tableswitch	default:+32 -> 7612, 0:+53->7633, 1:+60->7640, 2:+67->7647, 3:+74->7654
    //   7613: aastore
    //   7614: istore 170
    //   7616: aload 166
    //   7618: iload 168
    //   7620: iload 170
    //   7622: iload 169
    //   7624: ixor
    //   7625: i2c
    //   7626: castore
    //   7627: iinc 168 1
    //   7630: goto -6368 -> 1262
    //   7633: bipush 11
    //   7635: istore 170
    //   7637: goto -21 -> 7616
    //   7640: bipush 34
    //   7642: istore 170
    //   7644: goto -28 -> 7616
    //   7647: bipush 95
    //   7649: istore 170
    //   7651: goto -35 -> 7616
    //   7654: bipush 10
    //   7656: istore 170
    //   7658: goto -42 -> 7616
    //   7661: aload 171
    //   7663: iload 173
    //   7665: caload
    //   7666: istore 174
    //   7668: iload 173
    //   7670: iconst_5
    //   7671: irem
    //   7672: tableswitch	default:+32 -> 7704, 0:+53->7725, 1:+60->7732, 2:+67->7739, 3:+74->7746
    //   7705: aastore
    //   7706: istore 175
    //   7708: aload 171
    //   7710: iload 173
    //   7712: iload 175
    //   7714: iload 174
    //   7716: ixor
    //   7717: i2c
    //   7718: castore
    //   7719: iinc 173 1
    //   7722: goto -6422 -> 1300
    //   7725: bipush 11
    //   7727: istore 175
    //   7729: goto -21 -> 7708
    //   7732: bipush 34
    //   7734: istore 175
    //   7736: goto -28 -> 7708
    //   7739: bipush 95
    //   7741: istore 175
    //   7743: goto -35 -> 7708
    //   7746: bipush 10
    //   7748: istore 175
    //   7750: goto -42 -> 7708
    //   7753: aload 176
    //   7755: iload 178
    //   7757: caload
    //   7758: istore 179
    //   7760: iload 178
    //   7762: iconst_5
    //   7763: irem
    //   7764: tableswitch	default:+32 -> 7796, 0:+53->7817, 1:+60->7824, 2:+67->7831, 3:+74->7838
    //   7797: aastore
    //   7798: istore 180
    //   7800: aload 176
    //   7802: iload 178
    //   7804: iload 180
    //   7806: iload 179
    //   7808: ixor
    //   7809: i2c
    //   7810: castore
    //   7811: iinc 178 1
    //   7814: goto -6476 -> 1338
    //   7817: bipush 11
    //   7819: istore 180
    //   7821: goto -21 -> 7800
    //   7824: bipush 34
    //   7826: istore 180
    //   7828: goto -28 -> 7800
    //   7831: bipush 95
    //   7833: istore 180
    //   7835: goto -35 -> 7800
    //   7838: bipush 10
    //   7840: istore 180
    //   7842: goto -42 -> 7800
    //   7845: aload 181
    //   7847: iload 183
    //   7849: caload
    //   7850: istore 184
    //   7852: iload 183
    //   7854: iconst_5
    //   7855: irem
    //   7856: tableswitch	default:+32 -> 7888, 0:+53->7909, 1:+60->7916, 2:+67->7923, 3:+74->7930
    //   7889: aastore
    //   7890: istore 185
    //   7892: aload 181
    //   7894: iload 183
    //   7896: iload 185
    //   7898: iload 184
    //   7900: ixor
    //   7901: i2c
    //   7902: castore
    //   7903: iinc 183 1
    //   7906: goto -6530 -> 1376
    //   7909: bipush 11
    //   7911: istore 185
    //   7913: goto -21 -> 7892
    //   7916: bipush 34
    //   7918: istore 185
    //   7920: goto -28 -> 7892
    //   7923: bipush 95
    //   7925: istore 185
    //   7927: goto -35 -> 7892
    //   7930: bipush 10
    //   7932: istore 185
    //   7934: goto -42 -> 7892
    //   7937: aload 186
    //   7939: iload 188
    //   7941: caload
    //   7942: istore 189
    //   7944: iload 188
    //   7946: iconst_5
    //   7947: irem
    //   7948: tableswitch	default:+32 -> 7980, 0:+53->8001, 1:+60->8008, 2:+67->8015, 3:+74->8022
    //   7981: aastore
    //   7982: istore 190
    //   7984: aload 186
    //   7986: iload 188
    //   7988: iload 190
    //   7990: iload 189
    //   7992: ixor
    //   7993: i2c
    //   7994: castore
    //   7995: iinc 188 1
    //   7998: goto -6584 -> 1414
    //   8001: bipush 11
    //   8003: istore 190
    //   8005: goto -21 -> 7984
    //   8008: bipush 34
    //   8010: istore 190
    //   8012: goto -28 -> 7984
    //   8015: bipush 95
    //   8017: istore 190
    //   8019: goto -35 -> 7984
    //   8022: bipush 10
    //   8024: istore 190
    //   8026: goto -42 -> 7984
    //   8029: aload 191
    //   8031: iload 193
    //   8033: caload
    //   8034: istore 194
    //   8036: iload 193
    //   8038: iconst_5
    //   8039: irem
    //   8040: tableswitch	default:+32 -> 8072, 0:+53->8093, 1:+60->8100, 2:+67->8107, 3:+74->8114
    //   8073: aastore
    //   8074: istore 195
    //   8076: aload 191
    //   8078: iload 193
    //   8080: iload 195
    //   8082: iload 194
    //   8084: ixor
    //   8085: i2c
    //   8086: castore
    //   8087: iinc 193 1
    //   8090: goto -6638 -> 1452
    //   8093: bipush 11
    //   8095: istore 195
    //   8097: goto -21 -> 8076
    //   8100: bipush 34
    //   8102: istore 195
    //   8104: goto -28 -> 8076
    //   8107: bipush 95
    //   8109: istore 195
    //   8111: goto -35 -> 8076
    //   8114: bipush 10
    //   8116: istore 195
    //   8118: goto -42 -> 8076
    //   8121: aload 196
    //   8123: iload 198
    //   8125: caload
    //   8126: istore 199
    //   8128: iload 198
    //   8130: iconst_5
    //   8131: irem
    //   8132: tableswitch	default:+32 -> 8164, 0:+53->8185, 1:+60->8192, 2:+67->8199, 3:+74->8206
    //   8165: aastore
    //   8166: istore 200
    //   8168: aload 196
    //   8170: iload 198
    //   8172: iload 200
    //   8174: iload 199
    //   8176: ixor
    //   8177: i2c
    //   8178: castore
    //   8179: iinc 198 1
    //   8182: goto -6692 -> 1490
    //   8185: bipush 11
    //   8187: istore 200
    //   8189: goto -21 -> 8168
    //   8192: bipush 34
    //   8194: istore 200
    //   8196: goto -28 -> 8168
    //   8199: bipush 95
    //   8201: istore 200
    //   8203: goto -35 -> 8168
    //   8206: bipush 10
    //   8208: istore 200
    //   8210: goto -42 -> 8168
    //   8213: aload 201
    //   8215: iload 203
    //   8217: caload
    //   8218: istore 204
    //   8220: iload 203
    //   8222: iconst_5
    //   8223: irem
    //   8224: tableswitch	default:+32 -> 8256, 0:+53->8277, 1:+60->8284, 2:+67->8291, 3:+74->8298
    //   8257: aastore
    //   8258: istore 205
    //   8260: aload 201
    //   8262: iload 203
    //   8264: iload 205
    //   8266: iload 204
    //   8268: ixor
    //   8269: i2c
    //   8270: castore
    //   8271: iinc 203 1
    //   8274: goto -6746 -> 1528
    //   8277: bipush 11
    //   8279: istore 205
    //   8281: goto -21 -> 8260
    //   8284: bipush 34
    //   8286: istore 205
    //   8288: goto -28 -> 8260
    //   8291: bipush 95
    //   8293: istore 205
    //   8295: goto -35 -> 8260
    //   8298: bipush 10
    //   8300: istore 205
    //   8302: goto -42 -> 8260
    //   8305: aload 206
    //   8307: iload 208
    //   8309: caload
    //   8310: istore 209
    //   8312: iload 208
    //   8314: iconst_5
    //   8315: irem
    //   8316: tableswitch	default:+32 -> 8348, 0:+53->8369, 1:+60->8376, 2:+67->8383, 3:+74->8390
    //   8349: aastore
    //   8350: istore 210
    //   8352: aload 206
    //   8354: iload 208
    //   8356: iload 210
    //   8358: iload 209
    //   8360: ixor
    //   8361: i2c
    //   8362: castore
    //   8363: iinc 208 1
    //   8366: goto -6800 -> 1566
    //   8369: bipush 11
    //   8371: istore 210
    //   8373: goto -21 -> 8352
    //   8376: bipush 34
    //   8378: istore 210
    //   8380: goto -28 -> 8352
    //   8383: bipush 95
    //   8385: istore 210
    //   8387: goto -35 -> 8352
    //   8390: bipush 10
    //   8392: istore 210
    //   8394: goto -42 -> 8352
    //   8397: aload 211
    //   8399: iload 213
    //   8401: caload
    //   8402: istore 214
    //   8404: iload 213
    //   8406: iconst_5
    //   8407: irem
    //   8408: tableswitch	default:+32 -> 8440, 0:+53->8461, 1:+60->8468, 2:+67->8475, 3:+74->8482
    //   8441: aastore
    //   8442: istore 215
    //   8444: aload 211
    //   8446: iload 213
    //   8448: iload 215
    //   8450: iload 214
    //   8452: ixor
    //   8453: i2c
    //   8454: castore
    //   8455: iinc 213 1
    //   8458: goto -6854 -> 1604
    //   8461: bipush 11
    //   8463: istore 215
    //   8465: goto -21 -> 8444
    //   8468: bipush 34
    //   8470: istore 215
    //   8472: goto -28 -> 8444
    //   8475: bipush 95
    //   8477: istore 215
    //   8479: goto -35 -> 8444
    //   8482: bipush 10
    //   8484: istore 215
    //   8486: goto -42 -> 8444
    //   8489: aload 216
    //   8491: iload 218
    //   8493: caload
    //   8494: istore 219
    //   8496: iload 218
    //   8498: iconst_5
    //   8499: irem
    //   8500: tableswitch	default:+32 -> 8532, 0:+53->8553, 1:+60->8560, 2:+67->8567, 3:+74->8574
    //   8533: aastore
    //   8534: istore 220
    //   8536: aload 216
    //   8538: iload 218
    //   8540: iload 220
    //   8542: iload 219
    //   8544: ixor
    //   8545: i2c
    //   8546: castore
    //   8547: iinc 218 1
    //   8550: goto -6908 -> 1642
    //   8553: bipush 11
    //   8555: istore 220
    //   8557: goto -21 -> 8536
    //   8560: bipush 34
    //   8562: istore 220
    //   8564: goto -28 -> 8536
    //   8567: bipush 95
    //   8569: istore 220
    //   8571: goto -35 -> 8536
    //   8574: bipush 10
    //   8576: istore 220
    //   8578: goto -42 -> 8536
    //   8581: aload 221
    //   8583: iload 223
    //   8585: caload
    //   8586: istore 224
    //   8588: iload 223
    //   8590: iconst_5
    //   8591: irem
    //   8592: tableswitch	default:+32 -> 8624, 0:+53->8645, 1:+60->8652, 2:+67->8659, 3:+74->8666
    //   8625: aastore
    //   8626: istore 225
    //   8628: aload 221
    //   8630: iload 223
    //   8632: iload 225
    //   8634: iload 224
    //   8636: ixor
    //   8637: i2c
    //   8638: castore
    //   8639: iinc 223 1
    //   8642: goto -6962 -> 1680
    //   8645: bipush 11
    //   8647: istore 225
    //   8649: goto -21 -> 8628
    //   8652: bipush 34
    //   8654: istore 225
    //   8656: goto -28 -> 8628
    //   8659: bipush 95
    //   8661: istore 225
    //   8663: goto -35 -> 8628
    //   8666: bipush 10
    //   8668: istore 225
    //   8670: goto -42 -> 8628
    //   8673: aload 226
    //   8675: iload 228
    //   8677: caload
    //   8678: istore 229
    //   8680: iload 228
    //   8682: iconst_5
    //   8683: irem
    //   8684: tableswitch	default:+32 -> 8716, 0:+53->8737, 1:+60->8744, 2:+67->8751, 3:+74->8758
    //   8717: aastore
    //   8718: istore 230
    //   8720: aload 226
    //   8722: iload 228
    //   8724: iload 230
    //   8726: iload 229
    //   8728: ixor
    //   8729: i2c
    //   8730: castore
    //   8731: iinc 228 1
    //   8734: goto -7016 -> 1718
    //   8737: bipush 11
    //   8739: istore 230
    //   8741: goto -21 -> 8720
    //   8744: bipush 34
    //   8746: istore 230
    //   8748: goto -28 -> 8720
    //   8751: bipush 95
    //   8753: istore 230
    //   8755: goto -35 -> 8720
    //   8758: bipush 10
    //   8760: istore 230
    //   8762: goto -42 -> 8720
    //   8765: aload 231
    //   8767: iload 233
    //   8769: caload
    //   8770: istore 234
    //   8772: iload 233
    //   8774: iconst_5
    //   8775: irem
    //   8776: tableswitch	default:+32 -> 8808, 0:+53->8829, 1:+60->8836, 2:+67->8843, 3:+74->8850
    //   8809: aastore
    //   8810: istore 235
    //   8812: aload 231
    //   8814: iload 233
    //   8816: iload 235
    //   8818: iload 234
    //   8820: ixor
    //   8821: i2c
    //   8822: castore
    //   8823: iinc 233 1
    //   8826: goto -7070 -> 1756
    //   8829: bipush 11
    //   8831: istore 235
    //   8833: goto -21 -> 8812
    //   8836: bipush 34
    //   8838: istore 235
    //   8840: goto -28 -> 8812
    //   8843: bipush 95
    //   8845: istore 235
    //   8847: goto -35 -> 8812
    //   8850: bipush 10
    //   8852: istore 235
    //   8854: goto -42 -> 8812
    //   8857: aload 236
    //   8859: iload 238
    //   8861: caload
    //   8862: istore 239
    //   8864: iload 238
    //   8866: iconst_5
    //   8867: irem
    //   8868: tableswitch	default:+32 -> 8900, 0:+53->8921, 1:+60->8928, 2:+67->8935, 3:+74->8942
    //   8901: aastore
    //   8902: istore 240
    //   8904: aload 236
    //   8906: iload 238
    //   8908: iload 240
    //   8910: iload 239
    //   8912: ixor
    //   8913: i2c
    //   8914: castore
    //   8915: iinc 238 1
    //   8918: goto -7124 -> 1794
    //   8921: bipush 11
    //   8923: istore 240
    //   8925: goto -21 -> 8904
    //   8928: bipush 34
    //   8930: istore 240
    //   8932: goto -28 -> 8904
    //   8935: bipush 95
    //   8937: istore 240
    //   8939: goto -35 -> 8904
    //   8942: bipush 10
    //   8944: istore 240
    //   8946: goto -42 -> 8904
    //   8949: aload 241
    //   8951: iload 243
    //   8953: caload
    //   8954: istore 244
    //   8956: iload 243
    //   8958: iconst_5
    //   8959: irem
    //   8960: tableswitch	default:+32 -> 8992, 0:+53->9013, 1:+60->9020, 2:+67->9027, 3:+74->9034
    //   8993: aastore
    //   8994: istore 245
    //   8996: aload 241
    //   8998: iload 243
    //   9000: iload 245
    //   9002: iload 244
    //   9004: ixor
    //   9005: i2c
    //   9006: castore
    //   9007: iinc 243 1
    //   9010: goto -7178 -> 1832
    //   9013: bipush 11
    //   9015: istore 245
    //   9017: goto -21 -> 8996
    //   9020: bipush 34
    //   9022: istore 245
    //   9024: goto -28 -> 8996
    //   9027: bipush 95
    //   9029: istore 245
    //   9031: goto -35 -> 8996
    //   9034: bipush 10
    //   9036: istore 245
    //   9038: goto -42 -> 8996
    //   9041: aload 246
    //   9043: iload 248
    //   9045: caload
    //   9046: istore 249
    //   9048: iload 248
    //   9050: iconst_5
    //   9051: irem
    //   9052: tableswitch	default:+32 -> 9084, 0:+53->9105, 1:+60->9112, 2:+67->9119, 3:+74->9126
    //   9085: aastore
    //   9086: istore 250
    //   9088: aload 246
    //   9090: iload 248
    //   9092: iload 250
    //   9094: iload 249
    //   9096: ixor
    //   9097: i2c
    //   9098: castore
    //   9099: iinc 248 1
    //   9102: goto -7232 -> 1870
    //   9105: bipush 11
    //   9107: istore 250
    //   9109: goto -21 -> 9088
    //   9112: bipush 34
    //   9114: istore 250
    //   9116: goto -28 -> 9088
    //   9119: bipush 95
    //   9121: istore 250
    //   9123: goto -35 -> 9088
    //   9126: bipush 10
    //   9128: istore 250
    //   9130: goto -42 -> 9088
    //   9133: aload 251
    //   9135: iload 253
    //   9137: caload
    //   9138: istore 254
    //   9140: iload 253
    //   9142: iconst_5
    //   9143: irem
    //   9144: tableswitch	default:+32 -> 9176, 0:+53->9197, 1:+60->9204, 2:+67->9211, 3:+74->9218
    //   9177: aastore
    //   9178: istore 255
    //   9180: aload 251
    //   9182: iload 253
    //   9184: iload 255
    //   9186: iload 254
    //   9188: ixor
    //   9189: i2c
    //   9190: castore
    //   9191: iinc 253 1
    //   9194: goto -7286 -> 1908
    //   9197: bipush 11
    //   9199: istore 255
    //   9201: goto -21 -> 9180
    //   9204: bipush 34
    //   9206: istore 255
    //   9208: goto -28 -> 9180
    //   9211: bipush 95
    //   9213: istore 255
    //   9215: goto -35 -> 9180
    //   9218: bipush 10
    //   9220: istore 255
    //   9222: goto -42 -> 9180
    //   9225: wide
    //   9229: wide
    //   9233: caload
    //   9234: wide
    //   9238: wide
    //   9242: iconst_5
    //   9243: irem
    //   9244: tableswitch	default:+32 -> 9276, 0:+66->9310, 1:+75->9319, 2:+84->9328, 3:+93->9337
    //   9277: aastore
    //   9278: wide
    //   9282: wide
    //   9286: wide
    //   9290: wide
    //   9294: wide
    //   9298: ixor
    //   9299: i2c
    //   9300: castore
    //   9301: wide
    //   9307: goto -7353 -> 1954
    //   9310: bipush 11
    //   9312: wide
    //   9316: goto -34 -> 9282
    //   9319: bipush 34
    //   9321: wide
    //   9325: goto -43 -> 9282
    //   9328: bipush 95
    //   9330: wide
    //   9334: goto -52 -> 9282
    //   9337: bipush 10
    //   9339: wide
    //   9343: goto -61 -> 9282
    //   9346: wide
    //   9350: wide
    //   9354: caload
    //   9355: wide
    //   9359: wide
    //   9363: iconst_5
    //   9364: irem
    //   9365: tableswitch	default:+31 -> 9396, 0:+65->9430, 1:+74->9439, 2:+83->9448, 3:+92->9457
    //   9397: aastore
    //   9398: wide
    //   9402: wide
    //   9406: wide
    //   9410: wide
    //   9414: wide
    //   9418: ixor
    //   9419: i2c
    //   9420: castore
    //   9421: wide
    //   9427: goto -7421 -> 2006
    //   9430: bipush 11
    //   9432: wide
    //   9436: goto -34 -> 9402
    //   9439: bipush 34
    //   9441: wide
    //   9445: goto -43 -> 9402
    //   9448: bipush 95
    //   9450: wide
    //   9454: goto -52 -> 9402
    //   9457: bipush 10
    //   9459: wide
    //   9463: goto -61 -> 9402
    //   9466: wide
    //   9470: wide
    //   9474: caload
    //   9475: wide
    //   9479: wide
    //   9483: iconst_5
    //   9484: irem
    //   9485: tableswitch	default:+31 -> 9516, 0:+65->9550, 1:+74->9559, 2:+83->9568, 3:+92->9577
    //   9517: aastore
    //   9518: wide
    //   9522: wide
    //   9526: wide
    //   9530: wide
    //   9534: wide
    //   9538: ixor
    //   9539: i2c
    //   9540: castore
    //   9541: wide
    //   9547: goto -7489 -> 2058
    //   9550: bipush 11
    //   9552: wide
    //   9556: goto -34 -> 9522
    //   9559: bipush 34
    //   9561: wide
    //   9565: goto -43 -> 9522
    //   9568: bipush 95
    //   9570: wide
    //   9574: goto -52 -> 9522
    //   9577: bipush 10
    //   9579: wide
    //   9583: goto -61 -> 9522
    //   9586: wide
    //   9590: wide
    //   9594: caload
    //   9595: wide
    //   9599: wide
    //   9603: iconst_5
    //   9604: irem
    //   9605: tableswitch	default:+31 -> 9636, 0:+65->9670, 1:+74->9679, 2:+83->9688, 3:+92->9697
    //   9637: aastore
    //   9638: wide
    //   9642: wide
    //   9646: wide
    //   9650: wide
    //   9654: wide
    //   9658: ixor
    //   9659: i2c
    //   9660: castore
    //   9661: wide
    //   9667: goto -7557 -> 2110
    //   9670: bipush 11
    //   9672: wide
    //   9676: goto -34 -> 9642
    //   9679: bipush 34
    //   9681: wide
    //   9685: goto -43 -> 9642
    //   9688: bipush 95
    //   9690: wide
    //   9694: goto -52 -> 9642
    //   9697: bipush 10
    //   9699: wide
    //   9703: goto -61 -> 9642
    //   9706: wide
    //   9710: wide
    //   9714: caload
    //   9715: wide
    //   9719: wide
    //   9723: iconst_5
    //   9724: irem
    //   9725: tableswitch	default:+31 -> 9756, 0:+65->9790, 1:+74->9799, 2:+83->9808, 3:+92->9817
    //   9757: aastore
    //   9758: wide
    //   9762: wide
    //   9766: wide
    //   9770: wide
    //   9774: wide
    //   9778: ixor
    //   9779: i2c
    //   9780: castore
    //   9781: wide
    //   9787: goto -7625 -> 2162
    //   9790: bipush 11
    //   9792: wide
    //   9796: goto -34 -> 9762
    //   9799: bipush 34
    //   9801: wide
    //   9805: goto -43 -> 9762
    //   9808: bipush 95
    //   9810: wide
    //   9814: goto -52 -> 9762
    //   9817: bipush 10
    //   9819: wide
    //   9823: goto -61 -> 9762
    //   9826: wide
    //   9830: wide
    //   9834: caload
    //   9835: wide
    //   9839: wide
    //   9843: iconst_5
    //   9844: irem
    //   9845: tableswitch	default:+31 -> 9876, 0:+65->9910, 1:+74->9919, 2:+83->9928, 3:+92->9937
    //   9877: aastore
    //   9878: wide
    //   9882: wide
    //   9886: wide
    //   9890: wide
    //   9894: wide
    //   9898: ixor
    //   9899: i2c
    //   9900: castore
    //   9901: wide
    //   9907: goto -7693 -> 2214
    //   9910: bipush 11
    //   9912: wide
    //   9916: goto -34 -> 9882
    //   9919: bipush 34
    //   9921: wide
    //   9925: goto -43 -> 9882
    //   9928: bipush 95
    //   9930: wide
    //   9934: goto -52 -> 9882
    //   9937: bipush 10
    //   9939: wide
    //   9943: goto -61 -> 9882
    //   9946: wide
    //   9950: wide
    //   9954: caload
    //   9955: wide
    //   9959: wide
    //   9963: iconst_5
    //   9964: irem
    //   9965: tableswitch	default:+31 -> 9996, 0:+65->10030, 1:+74->10039, 2:+83->10048, 3:+92->10057
    //   9997: aastore
    //   9998: wide
    //   10002: wide
    //   10006: wide
    //   10010: wide
    //   10014: wide
    //   10018: ixor
    //   10019: i2c
    //   10020: castore
    //   10021: wide
    //   10027: goto -7761 -> 2266
    //   10030: bipush 11
    //   10032: wide
    //   10036: goto -34 -> 10002
    //   10039: bipush 34
    //   10041: wide
    //   10045: goto -43 -> 10002
    //   10048: bipush 95
    //   10050: wide
    //   10054: goto -52 -> 10002
    //   10057: bipush 10
    //   10059: wide
    //   10063: goto -61 -> 10002
    //   10066: wide
    //   10070: wide
    //   10074: caload
    //   10075: wide
    //   10079: wide
    //   10083: iconst_5
    //   10084: irem
    //   10085: tableswitch	default:+31 -> 10116, 0:+65->10150, 1:+74->10159, 2:+83->10168, 3:+92->10177
    //   10117: aastore
    //   10118: wide
    //   10122: wide
    //   10126: wide
    //   10130: wide
    //   10134: wide
    //   10138: ixor
    //   10139: i2c
    //   10140: castore
    //   10141: wide
    //   10147: goto -7829 -> 2318
    //   10150: bipush 11
    //   10152: wide
    //   10156: goto -34 -> 10122
    //   10159: bipush 34
    //   10161: wide
    //   10165: goto -43 -> 10122
    //   10168: bipush 95
    //   10170: wide
    //   10174: goto -52 -> 10122
    //   10177: bipush 10
    //   10179: wide
    //   10183: goto -61 -> 10122
    //   10186: wide
    //   10190: wide
    //   10194: caload
    //   10195: wide
    //   10199: wide
    //   10203: iconst_5
    //   10204: irem
    //   10205: tableswitch	default:+31 -> 10236, 0:+65->10270, 1:+74->10279, 2:+83->10288, 3:+92->10297
    //   10237: aastore
    //   10238: wide
    //   10242: wide
    //   10246: wide
    //   10250: wide
    //   10254: wide
    //   10258: ixor
    //   10259: i2c
    //   10260: castore
    //   10261: wide
    //   10267: goto -7897 -> 2370
    //   10270: bipush 11
    //   10272: wide
    //   10276: goto -34 -> 10242
    //   10279: bipush 34
    //   10281: wide
    //   10285: goto -43 -> 10242
    //   10288: bipush 95
    //   10290: wide
    //   10294: goto -52 -> 10242
    //   10297: bipush 10
    //   10299: wide
    //   10303: goto -61 -> 10242
    //   10306: wide
    //   10310: wide
    //   10314: caload
    //   10315: wide
    //   10319: wide
    //   10323: iconst_5
    //   10324: irem
    //   10325: tableswitch	default:+31 -> 10356, 0:+65->10390, 1:+74->10399, 2:+83->10408, 3:+92->10417
    //   10357: aastore
    //   10358: wide
    //   10362: wide
    //   10366: wide
    //   10370: wide
    //   10374: wide
    //   10378: ixor
    //   10379: i2c
    //   10380: castore
    //   10381: wide
    //   10387: goto -7965 -> 2422
    //   10390: bipush 11
    //   10392: wide
    //   10396: goto -34 -> 10362
    //   10399: bipush 34
    //   10401: wide
    //   10405: goto -43 -> 10362
    //   10408: bipush 95
    //   10410: wide
    //   10414: goto -52 -> 10362
    //   10417: bipush 10
    //   10419: wide
    //   10423: goto -61 -> 10362
    //   10426: wide
    //   10430: wide
    //   10434: caload
    //   10435: wide
    //   10439: wide
    //   10443: iconst_5
    //   10444: irem
    //   10445: tableswitch	default:+31 -> 10476, 0:+65->10510, 1:+74->10519, 2:+83->10528, 3:+92->10537
    //   10477: aastore
    //   10478: wide
    //   10482: wide
    //   10486: wide
    //   10490: wide
    //   10494: wide
    //   10498: ixor
    //   10499: i2c
    //   10500: castore
    //   10501: wide
    //   10507: goto -8033 -> 2474
    //   10510: bipush 11
    //   10512: wide
    //   10516: goto -34 -> 10482
    //   10519: bipush 34
    //   10521: wide
    //   10525: goto -43 -> 10482
    //   10528: bipush 95
    //   10530: wide
    //   10534: goto -52 -> 10482
    //   10537: bipush 10
    //   10539: wide
    //   10543: goto -61 -> 10482
    //   10546: wide
    //   10550: wide
    //   10554: caload
    //   10555: wide
    //   10559: wide
    //   10563: iconst_5
    //   10564: irem
    //   10565: tableswitch	default:+31 -> 10596, 0:+65->10630, 1:+74->10639, 2:+83->10648, 3:+92->10657
    //   10597: aastore
    //   10598: wide
    //   10602: wide
    //   10606: wide
    //   10610: wide
    //   10614: wide
    //   10618: ixor
    //   10619: i2c
    //   10620: castore
    //   10621: wide
    //   10627: goto -8101 -> 2526
    //   10630: bipush 11
    //   10632: wide
    //   10636: goto -34 -> 10602
    //   10639: bipush 34
    //   10641: wide
    //   10645: goto -43 -> 10602
    //   10648: bipush 95
    //   10650: wide
    //   10654: goto -52 -> 10602
    //   10657: bipush 10
    //   10659: wide
    //   10663: goto -61 -> 10602
    //   10666: wide
    //   10670: wide
    //   10674: caload
    //   10675: wide
    //   10679: wide
    //   10683: iconst_5
    //   10684: irem
    //   10685: tableswitch	default:+31 -> 10716, 0:+65->10750, 1:+74->10759, 2:+83->10768, 3:+92->10777
    //   10717: aastore
    //   10718: wide
    //   10722: wide
    //   10726: wide
    //   10730: wide
    //   10734: wide
    //   10738: ixor
    //   10739: i2c
    //   10740: castore
    //   10741: wide
    //   10747: goto -8169 -> 2578
    //   10750: bipush 11
    //   10752: wide
    //   10756: goto -34 -> 10722
    //   10759: bipush 34
    //   10761: wide
    //   10765: goto -43 -> 10722
    //   10768: bipush 95
    //   10770: wide
    //   10774: goto -52 -> 10722
    //   10777: bipush 10
    //   10779: wide
    //   10783: goto -61 -> 10722
    //   10786: wide
    //   10790: wide
    //   10794: caload
    //   10795: wide
    //   10799: wide
    //   10803: iconst_5
    //   10804: irem
    //   10805: tableswitch	default:+31 -> 10836, 0:+65->10870, 1:+74->10879, 2:+83->10888, 3:+92->10897
    //   10837: aastore
    //   10838: wide
    //   10842: wide
    //   10846: wide
    //   10850: wide
    //   10854: wide
    //   10858: ixor
    //   10859: i2c
    //   10860: castore
    //   10861: wide
    //   10867: goto -8237 -> 2630
    //   10870: bipush 11
    //   10872: wide
    //   10876: goto -34 -> 10842
    //   10879: bipush 34
    //   10881: wide
    //   10885: goto -43 -> 10842
    //   10888: bipush 95
    //   10890: wide
    //   10894: goto -52 -> 10842
    //   10897: bipush 10
    //   10899: wide
    //   10903: goto -61 -> 10842
    //   10906: wide
    //   10910: wide
    //   10914: caload
    //   10915: wide
    //   10919: wide
    //   10923: iconst_5
    //   10924: irem
    //   10925: tableswitch	default:+31 -> 10956, 0:+65->10990, 1:+74->10999, 2:+83->11008, 3:+92->11017
    //   10957: aastore
    //   10958: wide
    //   10962: wide
    //   10966: wide
    //   10970: wide
    //   10974: wide
    //   10978: ixor
    //   10979: i2c
    //   10980: castore
    //   10981: wide
    //   10987: goto -8305 -> 2682
    //   10990: bipush 11
    //   10992: wide
    //   10996: goto -34 -> 10962
    //   10999: bipush 34
    //   11001: wide
    //   11005: goto -43 -> 10962
    //   11008: bipush 95
    //   11010: wide
    //   11014: goto -52 -> 10962
    //   11017: bipush 10
    //   11019: wide
    //   11023: goto -61 -> 10962
    //   11026: wide
    //   11030: wide
    //   11034: caload
    //   11035: wide
    //   11039: wide
    //   11043: iconst_5
    //   11044: irem
    //   11045: tableswitch	default:+31 -> 11076, 0:+65->11110, 1:+74->11119, 2:+83->11128, 3:+92->11137
    //   11077: aastore
    //   11078: wide
    //   11082: wide
    //   11086: wide
    //   11090: wide
    //   11094: wide
    //   11098: ixor
    //   11099: i2c
    //   11100: castore
    //   11101: wide
    //   11107: goto -8373 -> 2734
    //   11110: bipush 11
    //   11112: wide
    //   11116: goto -34 -> 11082
    //   11119: bipush 34
    //   11121: wide
    //   11125: goto -43 -> 11082
    //   11128: bipush 95
    //   11130: wide
    //   11134: goto -52 -> 11082
    //   11137: bipush 10
    //   11139: wide
    //   11143: goto -61 -> 11082
    //   11146: wide
    //   11150: wide
    //   11154: caload
    //   11155: wide
    //   11159: wide
    //   11163: iconst_5
    //   11164: irem
    //   11165: tableswitch	default:+31 -> 11196, 0:+65->11230, 1:+74->11239, 2:+83->11248, 3:+92->11257
    //   11197: aastore
    //   11198: wide
    //   11202: wide
    //   11206: wide
    //   11210: wide
    //   11214: wide
    //   11218: ixor
    //   11219: i2c
    //   11220: castore
    //   11221: wide
    //   11227: goto -8441 -> 2786
    //   11230: bipush 11
    //   11232: wide
    //   11236: goto -34 -> 11202
    //   11239: bipush 34
    //   11241: wide
    //   11245: goto -43 -> 11202
    //   11248: bipush 95
    //   11250: wide
    //   11254: goto -52 -> 11202
    //   11257: bipush 10
    //   11259: wide
    //   11263: goto -61 -> 11202
    //   11266: wide
    //   11270: wide
    //   11274: caload
    //   11275: wide
    //   11279: wide
    //   11283: iconst_5
    //   11284: irem
    //   11285: tableswitch	default:+31 -> 11316, 0:+65->11350, 1:+74->11359, 2:+83->11368, 3:+92->11377
    //   11317: aastore
    //   11318: wide
    //   11322: wide
    //   11326: wide
    //   11330: wide
    //   11334: wide
    //   11338: ixor
    //   11339: i2c
    //   11340: castore
    //   11341: wide
    //   11347: goto -8509 -> 2838
    //   11350: bipush 11
    //   11352: wide
    //   11356: goto -34 -> 11322
    //   11359: bipush 34
    //   11361: wide
    //   11365: goto -43 -> 11322
    //   11368: bipush 95
    //   11370: wide
    //   11374: goto -52 -> 11322
    //   11377: bipush 10
    //   11379: wide
    //   11383: goto -61 -> 11322
    //   11386: wide
    //   11390: wide
    //   11394: caload
    //   11395: wide
    //   11399: wide
    //   11403: iconst_5
    //   11404: irem
    //   11405: tableswitch	default:+31 -> 11436, 0:+65->11470, 1:+74->11479, 2:+83->11488, 3:+92->11497
    //   11437: aastore
    //   11438: wide
    //   11442: wide
    //   11446: wide
    //   11450: wide
    //   11454: wide
    //   11458: ixor
    //   11459: i2c
    //   11460: castore
    //   11461: wide
    //   11467: goto -8577 -> 2890
    //   11470: bipush 11
    //   11472: wide
    //   11476: goto -34 -> 11442
    //   11479: bipush 34
    //   11481: wide
    //   11485: goto -43 -> 11442
    //   11488: bipush 95
    //   11490: wide
    //   11494: goto -52 -> 11442
    //   11497: bipush 10
    //   11499: wide
    //   11503: goto -61 -> 11442
    //   11506: wide
    //   11510: wide
    //   11514: caload
    //   11515: wide
    //   11519: wide
    //   11523: iconst_5
    //   11524: irem
    //   11525: tableswitch	default:+31 -> 11556, 0:+65->11590, 1:+74->11599, 2:+83->11608, 3:+92->11617
    //   11557: aastore
    //   11558: wide
    //   11562: wide
    //   11566: wide
    //   11570: wide
    //   11574: wide
    //   11578: ixor
    //   11579: i2c
    //   11580: castore
    //   11581: wide
    //   11587: goto -8645 -> 2942
    //   11590: bipush 11
    //   11592: wide
    //   11596: goto -34 -> 11562
    //   11599: bipush 34
    //   11601: wide
    //   11605: goto -43 -> 11562
    //   11608: bipush 95
    //   11610: wide
    //   11614: goto -52 -> 11562
    //   11617: bipush 10
    //   11619: wide
    //   11623: goto -61 -> 11562
    //   11626: wide
    //   11630: wide
    //   11634: caload
    //   11635: wide
    //   11639: wide
    //   11643: iconst_5
    //   11644: irem
    //   11645: tableswitch	default:+31 -> 11676, 0:+65->11710, 1:+74->11719, 2:+83->11728, 3:+92->11737
    //   11677: aastore
    //   11678: wide
    //   11682: wide
    //   11686: wide
    //   11690: wide
    //   11694: wide
    //   11698: ixor
    //   11699: i2c
    //   11700: castore
    //   11701: wide
    //   11707: goto -8713 -> 2994
    //   11710: bipush 11
    //   11712: wide
    //   11716: goto -34 -> 11682
    //   11719: bipush 34
    //   11721: wide
    //   11725: goto -43 -> 11682
    //   11728: bipush 95
    //   11730: wide
    //   11734: goto -52 -> 11682
    //   11737: bipush 10
    //   11739: wide
    //   11743: goto -61 -> 11682
    //   11746: wide
    //   11750: wide
    //   11754: caload
    //   11755: wide
    //   11759: wide
    //   11763: iconst_5
    //   11764: irem
    //   11765: tableswitch	default:+31 -> 11796, 0:+65->11830, 1:+74->11839, 2:+83->11848, 3:+92->11857
    //   11797: aastore
    //   11798: wide
    //   11802: wide
    //   11806: wide
    //   11810: wide
    //   11814: wide
    //   11818: ixor
    //   11819: i2c
    //   11820: castore
    //   11821: wide
    //   11827: goto -8781 -> 3046
    //   11830: bipush 11
    //   11832: wide
    //   11836: goto -34 -> 11802
    //   11839: bipush 34
    //   11841: wide
    //   11845: goto -43 -> 11802
    //   11848: bipush 95
    //   11850: wide
    //   11854: goto -52 -> 11802
    //   11857: bipush 10
    //   11859: wide
    //   11863: goto -61 -> 11802
    //   11866: wide
    //   11870: wide
    //   11874: caload
    //   11875: wide
    //   11879: wide
    //   11883: iconst_5
    //   11884: irem
    //   11885: tableswitch	default:+31 -> 11916, 0:+65->11950, 1:+74->11959, 2:+83->11968, 3:+92->11977
    //   11917: aastore
    //   11918: wide
    //   11922: wide
    //   11926: wide
    //   11930: wide
    //   11934: wide
    //   11938: ixor
    //   11939: i2c
    //   11940: castore
    //   11941: wide
    //   11947: goto -8849 -> 3098
    //   11950: bipush 11
    //   11952: wide
    //   11956: goto -34 -> 11922
    //   11959: bipush 34
    //   11961: wide
    //   11965: goto -43 -> 11922
    //   11968: bipush 95
    //   11970: wide
    //   11974: goto -52 -> 11922
    //   11977: bipush 10
    //   11979: wide
    //   11983: goto -61 -> 11922
    //   11986: wide
    //   11990: wide
    //   11994: caload
    //   11995: wide
    //   11999: wide
    //   12003: iconst_5
    //   12004: irem
    //   12005: tableswitch	default:+31 -> 12036, 0:+65->12070, 1:+74->12079, 2:+83->12088, 3:+92->12097
    //   12037: aastore
    //   12038: wide
    //   12042: wide
    //   12046: wide
    //   12050: wide
    //   12054: wide
    //   12058: ixor
    //   12059: i2c
    //   12060: castore
    //   12061: wide
    //   12067: goto -8917 -> 3150
    //   12070: bipush 11
    //   12072: wide
    //   12076: goto -34 -> 12042
    //   12079: bipush 34
    //   12081: wide
    //   12085: goto -43 -> 12042
    //   12088: bipush 95
    //   12090: wide
    //   12094: goto -52 -> 12042
    //   12097: bipush 10
    //   12099: wide
    //   12103: goto -61 -> 12042
    //   12106: wide
    //   12110: wide
    //   12114: caload
    //   12115: wide
    //   12119: wide
    //   12123: iconst_5
    //   12124: irem
    //   12125: tableswitch	default:+31 -> 12156, 0:+65->12190, 1:+74->12199, 2:+83->12208, 3:+92->12217
    //   12157: aastore
    //   12158: wide
    //   12162: wide
    //   12166: wide
    //   12170: wide
    //   12174: wide
    //   12178: ixor
    //   12179: i2c
    //   12180: castore
    //   12181: wide
    //   12187: goto -8985 -> 3202
    //   12190: bipush 11
    //   12192: wide
    //   12196: goto -34 -> 12162
    //   12199: bipush 34
    //   12201: wide
    //   12205: goto -43 -> 12162
    //   12208: bipush 95
    //   12210: wide
    //   12214: goto -52 -> 12162
    //   12217: bipush 10
    //   12219: wide
    //   12223: goto -61 -> 12162
    //   12226: wide
    //   12230: wide
    //   12234: caload
    //   12235: wide
    //   12239: wide
    //   12243: iconst_5
    //   12244: irem
    //   12245: tableswitch	default:+31 -> 12276, 0:+65->12310, 1:+74->12319, 2:+83->12328, 3:+92->12337
    //   12277: aastore
    //   12278: wide
    //   12282: wide
    //   12286: wide
    //   12290: wide
    //   12294: wide
    //   12298: ixor
    //   12299: i2c
    //   12300: castore
    //   12301: wide
    //   12307: goto -9053 -> 3254
    //   12310: bipush 11
    //   12312: wide
    //   12316: goto -34 -> 12282
    //   12319: bipush 34
    //   12321: wide
    //   12325: goto -43 -> 12282
    //   12328: bipush 95
    //   12330: wide
    //   12334: goto -52 -> 12282
    //   12337: bipush 10
    //   12339: wide
    //   12343: goto -61 -> 12282
    //   12346: wide
    //   12350: wide
    //   12354: caload
    //   12355: wide
    //   12359: wide
    //   12363: iconst_5
    //   12364: irem
    //   12365: tableswitch	default:+31 -> 12396, 0:+65->12430, 1:+74->12439, 2:+83->12448, 3:+92->12457
    //   12397: aastore
    //   12398: wide
    //   12402: wide
    //   12406: wide
    //   12410: wide
    //   12414: wide
    //   12418: ixor
    //   12419: i2c
    //   12420: castore
    //   12421: wide
    //   12427: goto -9121 -> 3306
    //   12430: bipush 11
    //   12432: wide
    //   12436: goto -34 -> 12402
    //   12439: bipush 34
    //   12441: wide
    //   12445: goto -43 -> 12402
    //   12448: bipush 95
    //   12450: wide
    //   12454: goto -52 -> 12402
    //   12457: bipush 10
    //   12459: wide
    //   12463: goto -61 -> 12402
    //   12466: wide
    //   12470: wide
    //   12474: caload
    //   12475: wide
    //   12479: wide
    //   12483: iconst_5
    //   12484: irem
    //   12485: tableswitch	default:+31 -> 12516, 0:+65->12550, 1:+74->12559, 2:+83->12568, 3:+92->12577
    //   12517: aastore
    //   12518: wide
    //   12522: wide
    //   12526: wide
    //   12530: wide
    //   12534: wide
    //   12538: ixor
    //   12539: i2c
    //   12540: castore
    //   12541: wide
    //   12547: goto -9189 -> 3358
    //   12550: bipush 11
    //   12552: wide
    //   12556: goto -34 -> 12522
    //   12559: bipush 34
    //   12561: wide
    //   12565: goto -43 -> 12522
    //   12568: bipush 95
    //   12570: wide
    //   12574: goto -52 -> 12522
    //   12577: bipush 10
    //   12579: wide
    //   12583: goto -61 -> 12522
    //   12586: wide
    //   12590: wide
    //   12594: caload
    //   12595: wide
    //   12599: wide
    //   12603: iconst_5
    //   12604: irem
    //   12605: tableswitch	default:+31 -> 12636, 0:+65->12670, 1:+74->12679, 2:+83->12688, 3:+92->12697
    //   12637: aastore
    //   12638: wide
    //   12642: wide
    //   12646: wide
    //   12650: wide
    //   12654: wide
    //   12658: ixor
    //   12659: i2c
    //   12660: castore
    //   12661: wide
    //   12667: goto -9257 -> 3410
    //   12670: bipush 11
    //   12672: wide
    //   12676: goto -34 -> 12642
    //   12679: bipush 34
    //   12681: wide
    //   12685: goto -43 -> 12642
    //   12688: bipush 95
    //   12690: wide
    //   12694: goto -52 -> 12642
    //   12697: bipush 10
    //   12699: wide
    //   12703: goto -61 -> 12642
    //   12706: wide
    //   12710: wide
    //   12714: caload
    //   12715: wide
    //   12719: wide
    //   12723: iconst_5
    //   12724: irem
    //   12725: tableswitch	default:+31 -> 12756, 0:+65->12790, 1:+74->12799, 2:+83->12808, 3:+92->12817
    //   12757: aastore
    //   12758: wide
    //   12762: wide
    //   12766: wide
    //   12770: wide
    //   12774: wide
    //   12778: ixor
    //   12779: i2c
    //   12780: castore
    //   12781: wide
    //   12787: goto -9325 -> 3462
    //   12790: bipush 11
    //   12792: wide
    //   12796: goto -34 -> 12762
    //   12799: bipush 34
    //   12801: wide
    //   12805: goto -43 -> 12762
    //   12808: bipush 95
    //   12810: wide
    //   12814: goto -52 -> 12762
    //   12817: bipush 10
    //   12819: wide
    //   12823: goto -61 -> 12762
    //   12826: wide
    //   12830: wide
    //   12834: caload
    //   12835: wide
    //   12839: wide
    //   12843: iconst_5
    //   12844: irem
    //   12845: tableswitch	default:+31 -> 12876, 0:+65->12910, 1:+74->12919, 2:+83->12928, 3:+92->12937
    //   12877: aastore
    //   12878: wide
    //   12882: wide
    //   12886: wide
    //   12890: wide
    //   12894: wide
    //   12898: ixor
    //   12899: i2c
    //   12900: castore
    //   12901: wide
    //   12907: goto -9393 -> 3514
    //   12910: bipush 11
    //   12912: wide
    //   12916: goto -34 -> 12882
    //   12919: bipush 34
    //   12921: wide
    //   12925: goto -43 -> 12882
    //   12928: bipush 95
    //   12930: wide
    //   12934: goto -52 -> 12882
    //   12937: bipush 10
    //   12939: wide
    //   12943: goto -61 -> 12882
    //   12946: wide
    //   12950: wide
    //   12954: caload
    //   12955: wide
    //   12959: wide
    //   12963: iconst_5
    //   12964: irem
    //   12965: tableswitch	default:+31 -> 12996, 0:+65->13030, 1:+74->13039, 2:+83->13048, 3:+92->13057
    //   12997: aastore
    //   12998: wide
    //   13002: wide
    //   13006: wide
    //   13010: wide
    //   13014: wide
    //   13018: ixor
    //   13019: i2c
    //   13020: castore
    //   13021: wide
    //   13027: goto -9461 -> 3566
    //   13030: bipush 11
    //   13032: wide
    //   13036: goto -34 -> 13002
    //   13039: bipush 34
    //   13041: wide
    //   13045: goto -43 -> 13002
    //   13048: bipush 95
    //   13050: wide
    //   13054: goto -52 -> 13002
    //   13057: bipush 10
    //   13059: wide
    //   13063: goto -61 -> 13002
    //   13066: wide
    //   13070: wide
    //   13074: caload
    //   13075: wide
    //   13079: wide
    //   13083: iconst_5
    //   13084: irem
    //   13085: tableswitch	default:+31 -> 13116, 0:+65->13150, 1:+74->13159, 2:+83->13168, 3:+92->13177
    //   13117: aastore
    //   13118: wide
    //   13122: wide
    //   13126: wide
    //   13130: wide
    //   13134: wide
    //   13138: ixor
    //   13139: i2c
    //   13140: castore
    //   13141: wide
    //   13147: goto -9529 -> 3618
    //   13150: bipush 11
    //   13152: wide
    //   13156: goto -34 -> 13122
    //   13159: bipush 34
    //   13161: wide
    //   13165: goto -43 -> 13122
    //   13168: bipush 95
    //   13170: wide
    //   13174: goto -52 -> 13122
    //   13177: bipush 10
    //   13179: wide
    //   13183: goto -61 -> 13122
    //   13186: wide
    //   13190: wide
    //   13194: caload
    //   13195: wide
    //   13199: wide
    //   13203: iconst_5
    //   13204: irem
    //   13205: tableswitch	default:+31 -> 13236, 0:+65->13270, 1:+74->13279, 2:+83->13288, 3:+92->13297
    //   13237: aastore
    //   13238: wide
    //   13242: wide
    //   13246: wide
    //   13250: wide
    //   13254: wide
    //   13258: ixor
    //   13259: i2c
    //   13260: castore
    //   13261: wide
    //   13267: goto -9597 -> 3670
    //   13270: bipush 11
    //   13272: wide
    //   13276: goto -34 -> 13242
    //   13279: bipush 34
    //   13281: wide
    //   13285: goto -43 -> 13242
    //   13288: bipush 95
    //   13290: wide
    //   13294: goto -52 -> 13242
    //   13297: bipush 10
    //   13299: wide
    //   13303: goto -61 -> 13242
    //   13306: wide
    //   13310: wide
    //   13314: caload
    //   13315: wide
    //   13319: wide
    //   13323: iconst_5
    //   13324: irem
    //   13325: tableswitch	default:+31 -> 13356, 0:+65->13390, 1:+74->13399, 2:+83->13408, 3:+92->13417
    //   13357: aastore
    //   13358: wide
    //   13362: wide
    //   13366: wide
    //   13370: wide
    //   13374: wide
    //   13378: ixor
    //   13379: i2c
    //   13380: castore
    //   13381: wide
    //   13387: goto -9665 -> 3722
    //   13390: bipush 11
    //   13392: wide
    //   13396: goto -34 -> 13362
    //   13399: bipush 34
    //   13401: wide
    //   13405: goto -43 -> 13362
    //   13408: bipush 95
    //   13410: wide
    //   13414: goto -52 -> 13362
    //   13417: bipush 10
    //   13419: wide
    //   13423: goto -61 -> 13362
    //   13426: wide
    //   13430: wide
    //   13434: caload
    //   13435: wide
    //   13439: wide
    //   13443: iconst_5
    //   13444: irem
    //   13445: tableswitch	default:+31 -> 13476, 0:+65->13510, 1:+74->13519, 2:+83->13528, 3:+92->13537
    //   13477: aastore
    //   13478: wide
    //   13482: wide
    //   13486: wide
    //   13490: wide
    //   13494: wide
    //   13498: ixor
    //   13499: i2c
    //   13500: castore
    //   13501: wide
    //   13507: goto -9733 -> 3774
    //   13510: bipush 11
    //   13512: wide
    //   13516: goto -34 -> 13482
    //   13519: bipush 34
    //   13521: wide
    //   13525: goto -43 -> 13482
    //   13528: bipush 95
    //   13530: wide
    //   13534: goto -52 -> 13482
    //   13537: bipush 10
    //   13539: wide
    //   13543: goto -61 -> 13482
    //   13546: wide
    //   13550: wide
    //   13554: caload
    //   13555: wide
    //   13559: wide
    //   13563: iconst_5
    //   13564: irem
    //   13565: tableswitch	default:+31 -> 13596, 0:+65->13630, 1:+74->13639, 2:+83->13648, 3:+92->13657
    //   13597: aastore
    //   13598: wide
    //   13602: wide
    //   13606: wide
    //   13610: wide
    //   13614: wide
    //   13618: ixor
    //   13619: i2c
    //   13620: castore
    //   13621: wide
    //   13627: goto -9801 -> 3826
    //   13630: bipush 11
    //   13632: wide
    //   13636: goto -34 -> 13602
    //   13639: bipush 34
    //   13641: wide
    //   13645: goto -43 -> 13602
    //   13648: bipush 95
    //   13650: wide
    //   13654: goto -52 -> 13602
    //   13657: bipush 10
    //   13659: wide
    //   13663: goto -61 -> 13602
    //   13666: wide
    //   13670: wide
    //   13674: caload
    //   13675: wide
    //   13679: wide
    //   13683: iconst_5
    //   13684: irem
    //   13685: tableswitch	default:+31 -> 13716, 0:+65->13750, 1:+74->13759, 2:+83->13768, 3:+92->13777
    //   13717: aastore
    //   13718: wide
    //   13722: wide
    //   13726: wide
    //   13730: wide
    //   13734: wide
    //   13738: ixor
    //   13739: i2c
    //   13740: castore
    //   13741: wide
    //   13747: goto -9869 -> 3878
    //   13750: bipush 11
    //   13752: wide
    //   13756: goto -34 -> 13722
    //   13759: bipush 34
    //   13761: wide
    //   13765: goto -43 -> 13722
    //   13768: bipush 95
    //   13770: wide
    //   13774: goto -52 -> 13722
    //   13777: bipush 10
    //   13779: wide
    //   13783: goto -61 -> 13722
    //   13786: wide
    //   13790: wide
    //   13794: caload
    //   13795: wide
    //   13799: wide
    //   13803: iconst_5
    //   13804: irem
    //   13805: tableswitch	default:+31 -> 13836, 0:+65->13870, 1:+74->13879, 2:+83->13888, 3:+92->13897
    //   13837: aastore
    //   13838: wide
    //   13842: wide
    //   13846: wide
    //   13850: wide
    //   13854: wide
    //   13858: ixor
    //   13859: i2c
    //   13860: castore
    //   13861: wide
    //   13867: goto -9937 -> 3930
    //   13870: bipush 11
    //   13872: wide
    //   13876: goto -34 -> 13842
    //   13879: bipush 34
    //   13881: wide
    //   13885: goto -43 -> 13842
    //   13888: bipush 95
    //   13890: wide
    //   13894: goto -52 -> 13842
    //   13897: bipush 10
    //   13899: wide
    //   13903: goto -61 -> 13842
    //   13906: wide
    //   13910: wide
    //   13914: caload
    //   13915: wide
    //   13919: wide
    //   13923: iconst_5
    //   13924: irem
    //   13925: tableswitch	default:+31 -> 13956, 0:+65->13990, 1:+74->13999, 2:+83->14008, 3:+92->14017
    //   13957: aastore
    //   13958: wide
    //   13962: wide
    //   13966: wide
    //   13970: wide
    //   13974: wide
    //   13978: ixor
    //   13979: i2c
    //   13980: castore
    //   13981: wide
    //   13987: goto -10005 -> 3982
    //   13990: bipush 11
    //   13992: wide
    //   13996: goto -34 -> 13962
    //   13999: bipush 34
    //   14001: wide
    //   14005: goto -43 -> 13962
    //   14008: bipush 95
    //   14010: wide
    //   14014: goto -52 -> 13962
    //   14017: bipush 10
    //   14019: wide
    //   14023: goto -61 -> 13962
    //   14026: wide
    //   14030: wide
    //   14034: caload
    //   14035: wide
    //   14039: wide
    //   14043: iconst_5
    //   14044: irem
    //   14045: tableswitch	default:+31 -> 14076, 0:+65->14110, 1:+74->14119, 2:+83->14128, 3:+92->14137
    //   14077: aastore
    //   14078: wide
    //   14082: wide
    //   14086: wide
    //   14090: wide
    //   14094: wide
    //   14098: ixor
    //   14099: i2c
    //   14100: castore
    //   14101: wide
    //   14107: goto -10073 -> 4034
    //   14110: bipush 11
    //   14112: wide
    //   14116: goto -34 -> 14082
    //   14119: bipush 34
    //   14121: wide
    //   14125: goto -43 -> 14082
    //   14128: bipush 95
    //   14130: wide
    //   14134: goto -52 -> 14082
    //   14137: bipush 10
    //   14139: wide
    //   14143: goto -61 -> 14082
    //   14146: wide
    //   14150: wide
    //   14154: caload
    //   14155: wide
    //   14159: wide
    //   14163: iconst_5
    //   14164: irem
    //   14165: tableswitch	default:+31 -> 14196, 0:+65->14230, 1:+74->14239, 2:+83->14248, 3:+92->14257
    //   14197: aastore
    //   14198: wide
    //   14202: wide
    //   14206: wide
    //   14210: wide
    //   14214: wide
    //   14218: ixor
    //   14219: i2c
    //   14220: castore
    //   14221: wide
    //   14227: goto -10141 -> 4086
    //   14230: bipush 11
    //   14232: wide
    //   14236: goto -34 -> 14202
    //   14239: bipush 34
    //   14241: wide
    //   14245: goto -43 -> 14202
    //   14248: bipush 95
    //   14250: wide
    //   14254: goto -52 -> 14202
    //   14257: bipush 10
    //   14259: wide
    //   14263: goto -61 -> 14202
    //   14266: wide
    //   14270: wide
    //   14274: caload
    //   14275: wide
    //   14279: wide
    //   14283: iconst_5
    //   14284: irem
    //   14285: tableswitch	default:+31 -> 14316, 0:+65->14350, 1:+74->14359, 2:+83->14368, 3:+92->14377
    //   14317: aastore
    //   14318: wide
    //   14322: wide
    //   14326: wide
    //   14330: wide
    //   14334: wide
    //   14338: ixor
    //   14339: i2c
    //   14340: castore
    //   14341: wide
    //   14347: goto -10209 -> 4138
    //   14350: bipush 11
    //   14352: wide
    //   14356: goto -34 -> 14322
    //   14359: bipush 34
    //   14361: wide
    //   14365: goto -43 -> 14322
    //   14368: bipush 95
    //   14370: wide
    //   14374: goto -52 -> 14322
    //   14377: bipush 10
    //   14379: wide
    //   14383: goto -61 -> 14322
    //   14386: wide
    //   14390: wide
    //   14394: caload
    //   14395: wide
    //   14399: wide
    //   14403: iconst_5
    //   14404: irem
    //   14405: tableswitch	default:+31 -> 14436, 0:+65->14470, 1:+74->14479, 2:+83->14488, 3:+92->14497
    //   14437: aastore
    //   14438: wide
    //   14442: wide
    //   14446: wide
    //   14450: wide
    //   14454: wide
    //   14458: ixor
    //   14459: i2c
    //   14460: castore
    //   14461: wide
    //   14467: goto -10277 -> 4190
    //   14470: bipush 11
    //   14472: wide
    //   14476: goto -34 -> 14442
    //   14479: bipush 34
    //   14481: wide
    //   14485: goto -43 -> 14442
    //   14488: bipush 95
    //   14490: wide
    //   14494: goto -52 -> 14442
    //   14497: bipush 10
    //   14499: wide
    //   14503: goto -61 -> 14442
    //   14506: wide
    //   14510: wide
    //   14514: caload
    //   14515: wide
    //   14519: wide
    //   14523: iconst_5
    //   14524: irem
    //   14525: tableswitch	default:+31 -> 14556, 0:+65->14590, 1:+74->14599, 2:+83->14608, 3:+92->14617
    //   14557: aastore
    //   14558: wide
    //   14562: wide
    //   14566: wide
    //   14570: wide
    //   14574: wide
    //   14578: ixor
    //   14579: i2c
    //   14580: castore
    //   14581: wide
    //   14587: goto -10345 -> 4242
    //   14590: bipush 11
    //   14592: wide
    //   14596: goto -34 -> 14562
    //   14599: bipush 34
    //   14601: wide
    //   14605: goto -43 -> 14562
    //   14608: bipush 95
    //   14610: wide
    //   14614: goto -52 -> 14562
    //   14617: bipush 10
    //   14619: wide
    //   14623: goto -61 -> 14562
    //   14626: wide
    //   14630: wide
    //   14634: caload
    //   14635: wide
    //   14639: wide
    //   14643: iconst_5
    //   14644: irem
    //   14645: tableswitch	default:+31 -> 14676, 0:+65->14710, 1:+74->14719, 2:+83->14728, 3:+92->14737
    //   14677: aastore
    //   14678: wide
    //   14682: wide
    //   14686: wide
    //   14690: wide
    //   14694: wide
    //   14698: ixor
    //   14699: i2c
    //   14700: castore
    //   14701: wide
    //   14707: goto -10413 -> 4294
    //   14710: bipush 11
    //   14712: wide
    //   14716: goto -34 -> 14682
    //   14719: bipush 34
    //   14721: wide
    //   14725: goto -43 -> 14682
    //   14728: bipush 95
    //   14730: wide
    //   14734: goto -52 -> 14682
    //   14737: bipush 10
    //   14739: wide
    //   14743: goto -61 -> 14682
    //   14746: wide
    //   14750: wide
    //   14754: caload
    //   14755: wide
    //   14759: wide
    //   14763: iconst_5
    //   14764: irem
    //   14765: tableswitch	default:+31 -> 14796, 0:+65->14830, 1:+74->14839, 2:+83->14848, 3:+92->14857
    //   14797: aastore
    //   14798: wide
    //   14802: wide
    //   14806: wide
    //   14810: wide
    //   14814: wide
    //   14818: ixor
    //   14819: i2c
    //   14820: castore
    //   14821: wide
    //   14827: goto -10481 -> 4346
    //   14830: bipush 11
    //   14832: wide
    //   14836: goto -34 -> 14802
    //   14839: bipush 34
    //   14841: wide
    //   14845: goto -43 -> 14802
    //   14848: bipush 95
    //   14850: wide
    //   14854: goto -52 -> 14802
    //   14857: bipush 10
    //   14859: wide
    //   14863: goto -61 -> 14802
    //   14866: wide
    //   14870: wide
    //   14874: caload
    //   14875: wide
    //   14879: wide
    //   14883: iconst_5
    //   14884: irem
    //   14885: tableswitch	default:+31 -> 14916, 0:+65->14950, 1:+74->14959, 2:+83->14968, 3:+92->14977
    //   14917: aastore
    //   14918: wide
    //   14922: wide
    //   14926: wide
    //   14930: wide
    //   14934: wide
    //   14938: ixor
    //   14939: i2c
    //   14940: castore
    //   14941: wide
    //   14947: goto -10549 -> 4398
    //   14950: bipush 11
    //   14952: wide
    //   14956: goto -34 -> 14922
    //   14959: bipush 34
    //   14961: wide
    //   14965: goto -43 -> 14922
    //   14968: bipush 95
    //   14970: wide
    //   14974: goto -52 -> 14922
    //   14977: bipush 10
    //   14979: wide
    //   14983: goto -61 -> 14922
    //   14986: wide
    //   14990: wide
    //   14994: caload
    //   14995: wide
    //   14999: wide
    //   15003: iconst_5
    //   15004: irem
    //   15005: tableswitch	default:+31 -> 15036, 0:+65->15070, 1:+74->15079, 2:+83->15088, 3:+92->15097
    //   15037: aastore
    //   15038: wide
    //   15042: wide
    //   15046: wide
    //   15050: wide
    //   15054: wide
    //   15058: ixor
    //   15059: i2c
    //   15060: castore
    //   15061: wide
    //   15067: goto -10617 -> 4450
    //   15070: bipush 11
    //   15072: wide
    //   15076: goto -34 -> 15042
    //   15079: bipush 34
    //   15081: wide
    //   15085: goto -43 -> 15042
    //   15088: bipush 95
    //   15090: wide
    //   15094: goto -52 -> 15042
    //   15097: bipush 10
    //   15099: wide
    //   15103: goto -61 -> 15042
    //   15106: wide
    //   15110: wide
    //   15114: caload
    //   15115: wide
    //   15119: wide
    //   15123: iconst_5
    //   15124: irem
    //   15125: tableswitch	default:+31 -> 15156, 0:+65->15190, 1:+74->15199, 2:+83->15208, 3:+92->15217
    //   15157: aastore
    //   15158: wide
    //   15162: wide
    //   15166: wide
    //   15170: wide
    //   15174: wide
    //   15178: ixor
    //   15179: i2c
    //   15180: castore
    //   15181: wide
    //   15187: goto -10685 -> 4502
    //   15190: bipush 11
    //   15192: wide
    //   15196: goto -34 -> 15162
    //   15199: bipush 34
    //   15201: wide
    //   15205: goto -43 -> 15162
    //   15208: bipush 95
    //   15210: wide
    //   15214: goto -52 -> 15162
    //   15217: bipush 10
    //   15219: wide
    //   15223: goto -61 -> 15162
  }

  public static aq a(String paramString1, String paramString2, String paramString3, String paramString4, String paramString5, String paramString6, String paramString7, String paramString8, String paramString9, String paramString10, String paramString11, String paramString12)
    throws IOException, HttpException, XmlPullParserException, Exception
  {
    int i = yq.e;
    boolean bool1;
    boolean bool2;
    label24: boolean bool3;
    label36: boolean bool4;
    label48: boolean bool5;
    label61: boolean bool6;
    if (paramString1 != null)
    {
      bool1 = true;
      g5.b(bool1);
      if (paramString2 == null)
        break label180;
      bool2 = true;
      g5.b(bool2);
      if (paramString3 == null)
        break label186;
      bool3 = true;
      g5.b(bool3);
      if (paramString4 == null)
        break label192;
      bool4 = true;
      g5.b(bool4);
      if (paramString5 == null)
        break label198;
      bool5 = true;
      g5.b(bool5);
      if (paramString6 == null)
        break label204;
      bool6 = true;
      label74: g5.b(bool6);
      if (paramString7 == null)
        break label210;
    }
    label180: label186: label192: label198: label204: label210: for (boolean bool7 = true; ; bool7 = false)
    {
      g5.b(bool7);
      if ((paramString9.equals(z[0])) || (paramString9.equals(z[19])) || (paramString9.equals(z[40])))
        break label216;
      g5.d(z[34] + paramString9);
      throw new IllegalArgumentException(z[25]);
      bool1 = false;
      break;
      bool2 = false;
      break label24;
      bool3 = false;
      break label36;
      bool4 = false;
      break label48;
      bool5 = false;
      break label61;
      bool6 = false;
      break label74;
    }
    label216: if (paramString11 != null);
    HttpResponse localHttpResponse;
    for (boolean bool8 = true; ; bool8 = false)
    {
      g5.b(bool8);
      ArrayList localArrayList = new ArrayList();
      localArrayList.add(new BasicNameValuePair(z[28], paramString1));
      localArrayList.add(new BasicNameValuePair(z[18], paramString2));
      localArrayList.add(new BasicNameValuePair(z[36], paramString3));
      localArrayList.add(new BasicNameValuePair(z[5], paramString4));
      localArrayList.add(new BasicNameValuePair(z[12], paramString5));
      localArrayList.add(new BasicNameValuePair(z[11], paramString6));
      localArrayList.add(new BasicNameValuePair(z[9], paramString7));
      if (paramString8 != null)
        localArrayList.add(new BasicNameValuePair(z[37], paramString8));
      localArrayList.add(new BasicNameValuePair(z[25], paramString9));
      localArrayList.add(new BasicNameValuePair(z[14], paramString10));
      localArrayList.add(new BasicNameValuePair(z[16], paramString11));
      if (paramString12 != null)
        localArrayList.add(new BasicNameValuePair(z[31], paramString12));
      String str1 = URLEncodedUtils.format(localArrayList, z[10]);
      localHttpResponse = dq.b(f8.h + "?" + str1);
      if (localHttpResponse != null)
        break;
      throw new IOException(z[39]);
    }
    int j = localHttpResponse.getStatusLine().getStatusCode();
    aq localaq;
    if (j != 200)
    {
      g5.d(z[4] + j);
      localaq = new aq(uf.c);
    }
    while (true)
    {
      return localaq;
      uf localuf = uf.c;
      zb localzb = new zb();
      localzb.setInput(new InputStreamReader(localHttpResponse.getEntity().getContent()));
      localzb.nextTag();
      localzb.require(2, null, z[7]);
      localzb.nextTag();
      localzb.require(2, null, z[30]);
      String str2 = localzb.getAttributeValue(null, z[35]);
      String str3 = localzb.getAttributeValue(null, z[13]);
      if (str2 == null)
      {
        g5.d(z[27]);
        if (i != 0)
          App.wc = 1 + App.wc;
      }
      else if (str2.equals(z[3]))
      {
        if (str3 == null)
        {
          g5.c(z[21]);
          localuf = uf.c;
          if (i == 0);
        }
        else
        {
          localuf = uf.a;
          if (i == 0);
        }
      }
      else if (str2.equals(z[26]))
      {
        if (str3 == null)
        {
          g5.c(z[24]);
          localuf = uf.c;
          if (i == 0);
        }
        else
        {
          localuf = uf.b;
          if (i == 0);
        }
      }
      else if (str2.equals(z[23]))
      {
        if (str3 == null)
        {
          g5.c(z[6]);
          localuf = uf.c;
          if (i == 0);
        }
        else
        {
          localuf = uf.e;
          if (i == 0);
        }
      }
      else if (str2.equals(z[20]))
      {
        localuf = uf.f;
        if (i == 0);
      }
      else if (str2.equals(z[15]))
      {
        localuf = uf.g;
        if (i == 0);
      }
      else if (str2.equals(z[33]))
      {
        localuf = uf.h;
        if (i == 0);
      }
      else if (str2.equals(z[2]))
      {
        localuf = uf.i;
        if (i == 0);
      }
      else if (str2.equals(z[1]))
      {
        g5.d(z[29] + str3);
        localuf = uf.j;
        if (i == 0);
      }
      else if (str2.equals(z[8]))
      {
        g5.d(z[17]);
        localuf = uf.c;
        if (i == 0);
      }
      else if (str2.equals(z[32]))
      {
        g5.d(z[38]);
        localuf = uf.k;
        if (i == 0);
      }
      else
      {
        g5.d(z[22] + str2 + " " + str3);
      }
      localzb.nextTag();
      localzb.require(3, null, z[30]);
      localzb.nextTag();
      localzb.require(3, null, z[7]);
      if ((localuf == uf.b) || (localuf == uf.e) || (localuf == uf.a))
        localaq = new aq(localuf, str3);
      else
        localaq = new aq(localuf);
    }
  }

  public static zp a(String paramString1, String paramString2, String paramString3, String paramString4)
    throws IOException, HttpException, XmlPullParserException, Exception
  {
    boolean bool1 = true;
    boolean bool2;
    if ((paramString2 != null) && (paramString2.length() > 0))
    {
      bool2 = bool1;
      g5.b(bool2);
      if ((paramString3 == null) || (paramString3.length() <= 0))
        break label210;
    }
    HttpResponse localHttpResponse;
    while (true)
    {
      g5.b(bool1);
      ArrayList localArrayList = new ArrayList();
      localArrayList.add(new BasicNameValuePair(z[28], paramString1));
      localArrayList.add(new BasicNameValuePair(z[36], paramString2));
      localArrayList.add(new BasicNameValuePair(z[76], paramString3));
      if (paramString4 != null)
        localArrayList.add(new BasicNameValuePair(z[31], paramString4));
      String str1 = URLEncodedUtils.format(localArrayList, z[10]);
      localHttpResponse = dq.b(f8.g + "?" + str1);
      if (localHttpResponse != null)
        break label216;
      throw new IOException(z[39]);
      bool2 = false;
      break;
      label210: bool1 = false;
    }
    label216: int i = localHttpResponse.getStatusLine().getStatusCode();
    if (i != 200)
    {
      g5.d(z[47] + i);
      throw new IOException(z[48] + i);
    }
    zb localzb = new zb();
    localzb.setInput(new InputStreamReader(localHttpResponse.getEntity().getContent()));
    localzb.nextTag();
    localzb.require(2, null, z[54]);
    localzb.nextTag();
    localzb.require(2, null, z[30]);
    String str2 = localzb.getAttributeValue(null, z[35]);
    String str3 = localzb.getAttributeValue(null, z[13]);
    if (str2 == null)
    {
      g5.d(z[50]);
      throw new IOException(z[53]);
    }
    zp localzp;
    if (str2.equals(z[52]))
    {
      if (str3 == null)
      {
        g5.d(z[49]);
        throw new IOException(z[51]);
      }
      localzp = new zp(tf.a, str3);
      localzb.nextTag();
      localzb.require(3, null, z[30]);
      localzb.nextTag();
      localzb.require(3, null, z[54]);
    }
    while (true)
    {
      return localzp;
      if (z[78].equals(str2))
      {
        if (z[75].equals(str3))
        {
          localzp = new zp(tf.b, sf.b);
          break;
        }
        localzp = new zp(tf.b, sf.a);
        break;
      }
      g5.d(z[77] + str2);
      localzp = new zp(tf.b, sf.a);
    }
  }

  public static String a(String paramString1, String paramString2)
    throws IOException, HttpException, XmlPullParserException, Exception
  {
    if ((paramString2 != null) && (paramString2.length() > 0));
    HttpResponse localHttpResponse;
    for (boolean bool = true; ; bool = false)
    {
      g5.b(bool);
      ArrayList localArrayList = new ArrayList();
      localArrayList.add(new BasicNameValuePair(z[28], paramString1));
      localArrayList.add(new BasicNameValuePair(z[36], paramString2));
      localArrayList.add(new BasicNameValuePair("d", "1"));
      String str1 = URLEncodedUtils.format(localArrayList, z[10]);
      localHttpResponse = dq.b(f8.g + "?" + str1);
      if (localHttpResponse != null)
        break;
      throw new IOException(z[39]);
    }
    int i = localHttpResponse.getStatusLine().getStatusCode();
    if (i != 200)
    {
      g5.d(z[47] + i);
      throw new IOException(z[48] + i);
    }
    zb localzb = new zb();
    localzb.setInput(new InputStreamReader(localHttpResponse.getEntity().getContent()));
    localzb.nextTag();
    localzb.require(2, null, z[54]);
    localzb.nextTag();
    localzb.require(2, null, z[30]);
    String str2 = localzb.getAttributeValue(null, z[35]);
    String str3 = localzb.getAttributeValue(null, z[13]);
    if (str2 == null)
    {
      g5.d(z[50]);
      throw new IOException(z[53]);
    }
    if ((str2.equals(z[52])) && (str3 == null))
    {
      g5.d(z[49]);
      throw new IOException(z[51]);
    }
    localzb.nextTag();
    localzb.require(3, null, z[30]);
    localzb.nextTag();
    localzb.require(3, null, z[54]);
    return str3;
  }

  private static String a(String paramString1, String paramString2, String paramString3)
    throws IOException
  {
    return y0.a(paramString3, y0.e(), z[94], paramString1, z[95], z[96], paramString2, b());
  }

  public static HashMap<String, bq> a()
    throws IOException
  {
    int i = yq.e;
    HashMap localHashMap1 = new HashMap();
    HttpGet localHttpGet = new HttpGet(f8.j);
    BasicHttpParams localBasicHttpParams = new BasicHttpParams();
    HttpConnectionParams.setConnectionTimeout(localBasicHttpParams, 15000);
    HttpConnectionParams.setSoTimeout(localBasicHttpParams, 30000);
    HttpProtocolParams.setUserAgent(localBasicHttpParams, App.n);
    DefaultHttpClient localDefaultHttpClient = new DefaultHttpClient(localBasicHttpParams);
    localDefaultHttpClient.removeRequestInterceptorByClass(RequestExpectContinue.class);
    HttpResponse localHttpResponse = localDefaultHttpClient.execute(localHttpGet);
    int j = localHttpResponse.getStatusLine().getStatusCode();
    HashMap localHashMap2;
    if (j != 200)
    {
      g5.d(z[97] + j);
      localHashMap2 = localHashMap1;
      return localHashMap2;
    }
    e5 locale5 = new e5(new InputStreamReader(localHttpResponse.getEntity().getContent(), z[10]));
    locale5.c();
    label172: String str1;
    if (locale5.e())
    {
      str1 = locale5.h();
      locale5.c();
      if (!z[100].equals(locale5.h()))
        break label351;
    }
    label351: for (String str2 = (locale5.j() + "").toLowerCase(); ; str2 = null)
    {
      if (z[99].equals(locale5.h()));
      for (String str3 = locale5.i(); ; str3 = null)
      {
        if ((locale5.e()) && (z[98].equals(locale5.h())));
        for (String str4 = locale5.i(); ; str4 = null)
        {
          locale5.d();
          if (str1 != null)
            localHashMap1.put(str1, new bq(str2, str3, str4));
          if (i == 0)
            break label172;
          locale5.d();
          localHashMap2 = localHashMap1;
          break;
        }
      }
    }
  }

  public static void a(App.Me paramMe)
    throws IOException, HttpException, XmlPullParserException, Exception
  {
    int i = yq.e;
    long l = System.currentTimeMillis();
    ArrayList localArrayList = new ArrayList();
    localArrayList.add(new BasicNameValuePair(z[43], paramMe.number));
    localArrayList.add(new BasicNameValuePair("t", "w"));
    localArrayList.add(new BasicNameValuePair(z[44], z[42]));
    UrlEncodedFormEntity localUrlEncodedFormEntity = new UrlEncodedFormEntity(localArrayList, z[10]);
    eq localeq = eq.b(f8.b);
    localeq.a(localUrlEncodedFormEntity);
    a(localeq);
    localeq.a(2);
    HttpResponse localHttpResponse = localeq.a();
    if (localHttpResponse == null)
      throw new IOException(z[39]);
    int j = localHttpResponse.getStatusLine().getStatusCode();
    if (j != 200)
      throw new IOException(z[45] + j);
    e5 locale5 = new e5(new InputStreamReader(new lf(localHttpResponse.getEntity().getContent(), 2), z[10]));
    while (true)
    {
      try
      {
        locale5.c();
        if ("c".equals(locale5.h()))
        {
          locale5.a();
          locale5.c();
          if (locale5.e())
          {
            if ("s".equals(locale5.h()))
            {
              if (locale5.f() != ag.i)
              {
                App.a = locale5.i();
                if (i == 0)
                  break label429;
              }
              App.a = null;
              locale5.l();
              if (i == 0)
                break label429;
            }
            locale5.l();
            break label429;
          }
          locale5.d();
          locale5.b();
          if (i == 0);
        }
        else
        {
          throw new IOException(z[46]);
        }
      }
      finally
      {
        locale5.close();
      }
      locale5.d();
      locale5.close();
      g5.b(z[41] + (System.currentTimeMillis() - l));
      return;
      label429: if (i == 0);
    }
  }

  public static void a(App.Me paramMe, zq paramzq, vp paramvp)
    throws IOException, HttpException, XmlPullParserException, Exception
  {
    int i = yq.e;
    long l = System.currentTimeMillis();
    ArrayList localArrayList = new ArrayList();
    localArrayList.add(new BasicNameValuePair("t", "w"));
    localArrayList.add(new BasicNameValuePair(z[44], z[42]));
    if (paramzq.g == null)
      return;
    localArrayList.add(new BasicNameValuePair(z[43], paramzq.g.b));
    UrlEncodedFormEntity localUrlEncodedFormEntity = new UrlEncodedFormEntity(localArrayList, z[10]);
    eq localeq = eq.b(f8.b);
    localeq.a(localUrlEncodedFormEntity);
    a(localeq);
    localeq.a(2);
    HttpResponse localHttpResponse = localeq.a();
    if (localHttpResponse == null)
      throw new IOException(z[39]);
    int j = localHttpResponse.getStatusLine().getStatusCode();
    if (j != 200)
      throw new IOException(z[45] + j);
    e5 locale5 = new e5(new InputStreamReader(new lf(localHttpResponse.getEntity().getContent(), 2), z[10]));
    while (true)
    {
      String str2;
      String str3;
      try
      {
        locale5.c();
        if (!"c".equals(locale5.h()))
          break label579;
        locale5.a();
        String str1 = null;
        str2 = null;
        str3 = null;
        bool = false;
        locale5.c();
        if (locale5.e())
        {
          String str5 = locale5.h();
          if ("p".equals(str5))
          {
            str1 = locale5.i();
            if (i == 0)
              break label679;
          }
          if ("n".equals(str5))
          {
            str2 = locale5.i();
            if (i == 0)
              break label679;
          }
          if (("s".equals(str5)) && (locale5.f() != ag.i))
          {
            str3 = locale5.i();
            if (i == 0)
              break label679;
          }
          if ("t".equals(str5))
          {
            locale5.l();
            if (i == 0)
              break label679;
          }
          if ("w".equals(str5))
          {
            if (locale5.k() == 1)
            {
              bool = true;
              break label672;
            }
          }
          else
          {
            g5.c(z[90] + str5);
            locale5.l();
            break label679;
          }
        }
        else
        {
          locale5.d();
          if ((str1 != null) && (str2 != null))
            break label526;
          throw new IOException(z[46]);
        }
      }
      finally
      {
        locale5.close();
      }
      boolean bool = false;
      break label672;
      label526: String str4 = str2 + z[68];
      paramzq.c = str3;
      paramzq.k = bool;
      paramzq.b = str4;
      locale5.b();
      if (i != 0)
        label579: throw new IOException(z[46]);
      locale5.d();
      locale5.close();
      if (paramzq.k)
        App.w.f(paramzq, null);
      App.b(App.Mb.getApplicationContext(), 1 + App.h(App.Mb.getApplicationContext()));
      g5.b(z[91] + (System.currentTimeMillis() - l));
      break;
      label672: if (i == 0)
        label679: if (i == 0);
    }
  }

  public static void a(App.Me paramMe, ArrayList<zq> paramArrayList, vp paramvp)
    throws IOException, HttpException, XmlPullParserException, Exception
  {
    int i = yq.e;
    if (paramArrayList.isEmpty())
      return;
    long l = System.currentTimeMillis();
    ArrayList localArrayList1 = new ArrayList();
    localArrayList1.add(new BasicNameValuePair("t", "w"));
    localArrayList1.add(new BasicNameValuePair(z[44], z[42]));
    Iterator localIterator1 = paramArrayList.iterator();
    do
    {
      if (!localIterator1.hasNext())
        break;
      zq localzq2 = (zq)localIterator1.next();
      localArrayList1.add(new BasicNameValuePair(z[43], localzq2.g.b));
    }
    while (i == 0);
    UrlEncodedFormEntity localUrlEncodedFormEntity = new UrlEncodedFormEntity(localArrayList1, z[10]);
    eq localeq = eq.b(f8.b);
    localeq.a(2);
    localeq.a(localUrlEncodedFormEntity);
    a(localeq);
    HttpResponse localHttpResponse = localeq.a();
    if (localHttpResponse == null)
      throw new IOException(z[39]);
    int j = localHttpResponse.getStatusLine().getStatusCode();
    if (j != 200)
      throw new IOException(z[45] + j);
    int k = 0;
    int m = 0;
    ArrayList localArrayList2 = new ArrayList();
    e5 locale5 = new e5(new InputStreamReader(new lf(localHttpResponse.getEntity().getContent(), 2), z[10]));
    label339: String str1;
    label502: boolean bool2;
    label537: String str4;
    String str5;
    try
    {
      locale5.c();
      if (!"c".equals(locale5.h()))
        break label731;
      locale5.a();
      if (!locale5.e())
        break label722;
      str1 = null;
      String str2 = null;
      String str3 = null;
      bool1 = false;
      locale5.c();
      if (locale5.e())
      {
        String str7 = locale5.h();
        if ("p".equals(str7))
        {
          str1 = locale5.i();
          if (i == 0)
            break label910;
        }
        if ("n".equals(str7))
        {
          str2 = locale5.i();
          if (i == 0)
            break label910;
        }
        if (("s".equals(str7)) && (locale5.f() != ag.i))
        {
          str3 = locale5.i();
          if (i == 0)
            break label910;
        }
        if ("t".equals(str7))
        {
          locale5.l();
          if (i == 0)
            break label910;
        }
        if ("w".equals(str7))
        {
          if (locale5.k() == 1)
          {
            bool1 = true;
            break label903;
          }
        }
        else
        {
          g5.c(z[93] + str7);
          locale5.l();
          break label910;
        }
      }
      else
      {
        bool2 = bool1;
        str4 = str2;
        str5 = str3;
        locale5.d();
        if ((str1 != null) && (str4 != null))
          break label594;
        throw new IOException(z[46]);
      }
    }
    finally
    {
      locale5.close();
    }
    boolean bool1 = false;
    break label903;
    label594: String str6 = str4 + z[68];
    Iterator localIterator2 = paramArrayList.iterator();
    int n = k;
    int i1 = m;
    label634: if (localIterator2.hasNext())
    {
      zq localzq1 = (zq)localIterator2.next();
      if (str1.equals(localzq1.g.b))
      {
        localzq1.b = str6;
        localzq1.k = bool2;
        localzq1.c = str5;
        n++;
        localArrayList2.add(localzq1);
        if (bool2)
        {
          m = i1 + 1;
          k = n;
          break label917;
        }
      }
    }
    while (true)
    {
      label722: locale5.b();
      if (i != 0)
        label731: throw new IOException(z[46]);
      locale5.d();
      locale5.close();
      if (!localArrayList2.isEmpty())
        App.w.c(localArrayList2, null);
      paramvp.a(localArrayList2.size());
      localArrayList2.clear();
      App.b(App.Mb.getApplicationContext(), 1 + App.h(App.Mb.getApplicationContext()));
      g5.b(z[92] + (System.currentTimeMillis() - l) + z[67] + k + z[62] + m);
      break;
      label903: label910: label917: 
      do
      {
        n = k;
        i1 = m;
        break label634;
        m = i1;
        k = n;
        continue;
        m = i1;
        k = n;
        break label921;
        if (i != 0)
          break label502;
        if (i == 0)
          break;
        break label537;
      }
      while (i == 0);
      label921: if (i == 0)
        break label339;
    }
  }

  public static void a(App.Me paramMe, HashMap<String, LinkedList<zq>> paramHashMap)
    throws IOException, HttpException, XmlPullParserException, Exception
  {
    int i = yq.e;
    long l = System.currentTimeMillis();
    ArrayList localArrayList = new ArrayList();
    localArrayList.add(new BasicNameValuePair("t", "c"));
    localArrayList.add(new BasicNameValuePair(z[44], z[42]));
    if (paramHashMap.size() == 0)
    {
      localArrayList.add(new BasicNameValuePair(z[43], ""));
      if (i == 0);
    }
    else
    {
      Iterator localIterator1 = paramHashMap.keySet().iterator();
      do
      {
        if (!localIterator1.hasNext())
          break;
        String str8 = (String)localIterator1.next();
        localArrayList.add(new BasicNameValuePair(z[43], str8));
      }
      while (i == 0);
    }
    UrlEncodedFormEntity localUrlEncodedFormEntity = new UrlEncodedFormEntity(localArrayList, z[10]);
    eq localeq = eq.b(f8.b);
    localeq.a(2);
    localeq.a(localUrlEncodedFormEntity);
    a(localeq);
    HttpResponse localHttpResponse = localeq.a();
    if (localHttpResponse == null)
      throw new IOException(z[39]);
    int j = localHttpResponse.getStatusLine().getStatusCode();
    if (j != 200)
      throw new IOException(z[45] + j);
    int k = 0;
    int m = 0;
    StringBuilder localStringBuilder = new StringBuilder();
    localStringBuilder.append(z[71]);
    e5 locale5 = new e5(new InputStreamReader(new lf(localHttpResponse.getEntity().getContent(), 2), z[10]));
    String str1;
    label539: label588: boolean bool2;
    String str4;
    String str5;
    try
    {
      locale5.c();
      if (!"c".equals(locale5.h()))
        break label804;
      locale5.a();
      if (!locale5.e())
        break label966;
      str1 = null;
      String str2 = null;
      String str3 = null;
      bool1 = false;
      locale5.c();
      if (locale5.e())
      {
        String str7 = locale5.h();
        if ("p".equals(str7))
        {
          str1 = locale5.i();
          if (i == 0)
            break label984;
        }
        if ("n".equals(str7))
        {
          str2 = locale5.i();
          if (i == 0)
            break label984;
        }
        if (("s".equals(str7)) && (locale5.f() != ag.i))
        {
          str3 = locale5.i();
          if (i == 0)
            break label984;
        }
        if ("t".equals(str7))
        {
          locale5.l();
          if (i == 0)
            break label984;
        }
        if ("w".equals(str7))
        {
          if (locale5.k() == 1)
          {
            bool1 = true;
            break label977;
          }
        }
        else
        {
          g5.c(z[72] + str7 + z[64] + str1);
          locale5.l();
          break label984;
        }
      }
      else
      {
        bool2 = bool1;
        str4 = str2;
        str5 = str3;
        locale5.d();
        if ((str1 != null) && (str4 != null))
          break label645;
        throw new IOException(z[46]);
      }
    }
    finally
    {
      locale5.close();
    }
    boolean bool1 = false;
    break label977;
    label645: String str6 = str4 + z[68];
    LinkedList localLinkedList = (LinkedList)paramHashMap.get(str1);
    label694: int n;
    if (localLinkedList != null)
    {
      Iterator localIterator2 = localLinkedList.iterator();
      if (localIterator2.hasNext())
      {
        zq localzq = (zq)localIterator2.next();
        localzq.b = str6;
        localzq.k = bool2;
        localzq.c = str5;
        k++;
        if (localzq.k)
        {
          localStringBuilder.append(localzq);
          n = m + 1;
          break label991;
          label765: g5.b(z[74] + str1);
          break label1006;
        }
      }
    }
    while (true)
    {
      label795: locale5.b();
      if (i != 0)
        label804: throw new IOException(z[46]);
      locale5.d();
      locale5.close();
      App.b(App.Mb.getApplicationContext(), 1 + App.h(App.Mb.getApplicationContext()));
      int i1;
      g5.b(z[73] + (System.currentTimeMillis() - l) + z[67] + i1 + z[62] + n);
      if (App.wc != 0)
        yq.e = i + 1;
      return;
      label966: label977: label984: label991: label999: label1006: 
      do
      {
        k = i1;
        m = n;
        break;
        do
        {
          m = n;
          break label694;
          n = m;
          continue;
          n = m;
          i1 = k;
          break label999;
          n = m;
          i1 = k;
          break label765;
          n = m;
          i1 = k;
          break label795;
          if (i != 0)
            break label539;
          if (i == 0)
            break;
          break label588;
        }
        while (i == 0);
        i1 = k;
        if (i != 0)
          break label765;
      }
      while (i == 0);
    }
  }

  public static void a(App.Me paramMe, HashMap<String, zq> paramHashMap, vp paramvp, boolean paramBoolean)
    throws IOException, HttpException, XmlPullParserException, Exception
  {
    int i = yq.e;
    if (paramHashMap.isEmpty())
      return;
    long l = System.currentTimeMillis();
    ArrayList localArrayList1 = new ArrayList();
    if (paramBoolean);
    HttpResponse localHttpResponse;
    for (String str1 = "c"; ; str1 = "w")
    {
      localArrayList1.add(new BasicNameValuePair("t", str1));
      localArrayList1.add(new BasicNameValuePair(z[44], z[66]));
      Iterator localIterator1 = paramHashMap.values().iterator();
      do
      {
        if (!localIterator1.hasNext())
          break;
        zq localzq5 = (zq)localIterator1.next();
        localArrayList1.add(new BasicNameValuePair(z[43], localzq5.g.b));
      }
      while (i == 0);
      UrlEncodedFormEntity localUrlEncodedFormEntity = new UrlEncodedFormEntity(localArrayList1, z[10]);
      eq localeq = eq.b(f8.b);
      localeq.a(2);
      localeq.a(localUrlEncodedFormEntity);
      a(localeq);
      localHttpResponse = localeq.a();
      if (localHttpResponse != null)
        break;
      throw new IOException(z[39]);
    }
    int j = localHttpResponse.getStatusLine().getStatusCode();
    if (j != 200)
      throw new IOException(z[45] + j);
    int k = 0;
    int m = 0;
    ArrayList localArrayList2 = new ArrayList();
    HashMap localHashMap = new HashMap();
    ArrayList localArrayList3 = new ArrayList();
    e5 locale5 = new e5(new InputStreamReader(new lf(localHttpResponse.getEntity().getContent(), 2), z[10]));
    label547: label596: boolean bool2;
    String str6;
    String str8;
    label657: String str9;
    zq localzq3;
    do
    {
      String str7;
      try
      {
        locale5.c();
        if (!"c".equals(locale5.h()))
          break;
        locale5.a();
        if (!locale5.e())
          break label1396;
        String str3 = null;
        String str4 = null;
        String str5 = null;
        bool1 = false;
        locale5.c();
        if (locale5.e())
        {
          String str10 = locale5.h();
          if ("p".equals(str10))
          {
            str3 = locale5.i();
            if (i == 0)
              break label1422;
          }
          if ("n".equals(str10))
          {
            str4 = locale5.i();
            if (i == 0)
              break label1422;
          }
          if (("s".equals(str10)) && (locale5.f() != ag.i))
          {
            str5 = locale5.i();
            if (i == 0)
              break label1422;
          }
          if ("t".equals(str10))
          {
            locale5.l();
            if (i == 0)
              break label1422;
          }
          if ("w".equals(str10))
          {
            if (locale5.k() == 1)
            {
              bool1 = true;
              break label1414;
            }
          }
          else
          {
            g5.c(z[65] + str10 + z[64] + str3);
            locale5.l();
            break label1422;
          }
        }
        else
        {
          bool2 = bool1;
          str6 = str5;
          str7 = str4;
          str8 = str3;
          locale5.d();
          if ((str8 != null) && (str7 != null))
            break label657;
          throw new IOException(z[46]);
        }
      }
      finally
      {
        locale5.close();
      }
      boolean bool1 = false;
      break label1414;
      str9 = str7 + z[68];
      localzq3 = (zq)paramHashMap.remove(str9);
      if (localzq3 == null)
        break label1385;
      if (!str8.equals(localzq3.g.b))
        break label1403;
    }
    while ((!localzq3.k) && (!bool2) && (str6 == null) && (i == 0));
    label855: int i3;
    int n;
    int i4;
    int i5;
    if ((localzq3.k != bool2) || ((str6 != null) && (localzq3.c != null) && (!localzq3.c.equalsIgnoreCase(str6))) || ((str6 == null) && (localzq3.c != null)) || ((str6 != null) && (localzq3.c == null)))
    {
      localzq3.k = bool2;
      localzq3.c = str6;
      localArrayList2.add(localzq3);
      m++;
      g5.b(z[61] + localzq3);
      break label1430;
      zq localzq4 = new zq(str8, 0L, "", 0, "");
      localzq4.b = str9;
      localzq4.c = str6;
      localzq4.k = bool2;
      localHashMap.put(str8, localzq4);
      n = i3;
      i5 = i4;
      break label1456;
    }
    while (true)
    {
      label916: locale5.b();
      locale5.d();
      locale5.close();
      Iterator localIterator2 = paramHashMap.values().iterator();
      int i1 = n;
      label946: int i2;
      if (localIterator2.hasNext())
      {
        zq localzq1 = (zq)localIterator2.next();
        if (localHashMap.containsKey(localzq1.g.b))
        {
          zq localzq2 = (zq)localHashMap.remove(localzq1.g.b);
          String str2 = localzq1.b;
          localzq1.b = localzq2.b;
          localzq1.k = localzq2.k;
          localzq1.c = localzq2.c;
          localArrayList3.add(Pair.create(str2, localzq1));
          i1++;
          g5.b(z[60] + localzq1);
          if (i == 0);
        }
        else if (localzq1.k)
        {
          localzq1.k = false;
          localzq1.c = null;
          localArrayList2.add(localzq1);
          i1++;
          g5.b(z[59] + localzq1);
        }
        i2 = i1;
        if (i == 0);
      }
      while (true)
      {
        if (localHashMap.size() > 0)
          g5.c(z[58] + localHashMap.size());
        if (!localArrayList2.isEmpty())
          App.w.b(localArrayList2, null);
        paramvp.a(localArrayList2.size());
        localArrayList2.clear();
        if (!localArrayList3.isEmpty())
          App.w.b(localArrayList3);
        paramvp.a(localArrayList3.size());
        localArrayList3.clear();
        App.b(App.Mb.getApplicationContext(), 1 + App.h(App.Mb.getApplicationContext()));
        g5.b(z[63] + (System.currentTimeMillis() - l) + z[67] + k + z[62] + i2);
        break;
        throw new IOException(z[46]);
        i1 = i2;
        break label946;
        i2 = i1;
      }
      label1385: label1396: label1403: 
      do
      {
        m = n;
        k = i5;
        break;
        int i6;
        do
        {
          i5 = i6;
          break label1456;
          i3 = m;
          i4 = k;
          break label855;
          n = m;
          break label916;
          n = m;
          i5 = k;
          break label1456;
          if (i != 0)
            break label547;
          if (i == 0)
            break;
          break label596;
          n = m;
          i6 = k + 1;
        }
        while (i == 0);
        i3 = n;
        i4 = i6;
        break label855;
      }
      while (i == 0);
      label1414: label1422: label1430: label1456: k = i5;
    }
  }

  private static void a(eq parameq)
    throws IOException, Exception
  {
    String str1 = App.bb.jabber_id;
    String str2 = App.cb;
    String str3 = b(str1, str2);
    if (str3 == null)
      throw new IOException(z[55]);
    String str4 = a(str1, str2, str3);
    parameq.a(z[57], z[56] + str4);
  }

  public static cq b(String paramString1, String paramString2, String paramString3, String paramString4)
    throws IOException, XmlPullParserException, Exception
  {
    boolean bool1 = true;
    int i = yq.e;
    boolean bool2;
    boolean bool3;
    label29: boolean bool4;
    label42: label51: HttpResponse localHttpResponse;
    cq localcq;
    if (paramString1 != null)
    {
      bool2 = bool1;
      g5.b(bool2);
      if (paramString2 == null)
        break label249;
      bool3 = bool1;
      g5.b(bool3);
      if (paramString3 == null)
        break label255;
      bool4 = bool1;
      g5.b(bool4);
      if (paramString4 == null)
        break label261;
      g5.b(bool1);
      ArrayList localArrayList = new ArrayList();
      localArrayList.add(new BasicNameValuePair(z[28], paramString1));
      localArrayList.add(new BasicNameValuePair(z[36], paramString2));
      localArrayList.add(new BasicNameValuePair(z[76], paramString3));
      localArrayList.add(new BasicNameValuePair(z[7], paramString4));
      String str1 = URLEncodedUtils.format(localArrayList, z[10]);
      try
      {
        localHttpResponse = dq.b(f8.i + "?" + str1);
        if (localHttpResponse == null)
          throw new IOException(z[39]);
      }
      catch (HttpException localHttpException)
      {
        g5.d(z[82]);
        localcq = new cq(wf.c);
      }
    }
    while (true)
    {
      return localcq;
      bool2 = false;
      break;
      label249: bool3 = false;
      break label29;
      label255: bool4 = false;
      break label42;
      label261: bool1 = false;
      break label51;
      int j = localHttpResponse.getStatusLine().getStatusCode();
      if (j == 200)
        break label331;
      g5.d(z[79] + j);
      localcq = new cq(wf.c);
    }
    label331: wf localwf1 = wf.c;
    zb localzb = new zb();
    localzb.setInput(new InputStreamReader(localHttpResponse.getEntity().getContent()));
    localzb.nextTag();
    localzb.require(2, null, z[86]);
    localzb.nextTag();
    localzb.require(2, null, z[30]);
    String str2 = localzb.getAttributeValue(null, z[35]);
    String str3 = localzb.getAttributeValue(null, z[13]);
    String str4 = localzb.getAttributeValue(null, z[80]);
    if (str2 == null)
    {
      g5.d(z[84]);
      if (i == 0);
    }
    else if (str2.equals(z[52]))
    {
      localwf1 = wf.a;
      if (i == 0);
    }
    else if (str2.equals(z[83]))
    {
      localwf1 = wf.b;
      if (i == 0);
    }
    else if (str2.equals(z[78]))
    {
      if (!z[75].equals(str3))
        break label720;
      localwf1 = wf.h;
      break label725;
    }
    while (true)
    {
      if (str2.equals(z[81]))
      {
        localwf1 = wf.e;
        if (i == 0);
      }
      else if (str2.equals(z[85]))
      {
        localwf1 = wf.f;
        if (i == 0);
      }
      else if (str2.equals(z[87]))
      {
        localwf1 = wf.g;
        if (i == 0);
      }
      else
      {
        g5.d(z[22] + str2 + " " + str3);
      }
      label720: label725: 
      do
      {
        wf localwf2 = localwf1;
        localzb.nextTag();
        localzb.require(3, null, z[30]);
        localzb.nextTag();
        localzb.require(3, null, z[86]);
        localcq = new cq(localwf2, str4);
        break;
        localwf1 = wf.c;
      }
      while (i == 0);
    }
  }

  private static i1 b()
  {
    jz localjz;
    if (a != null)
      localjz = a;
    while (true)
    {
      return localjz;
      try
      {
        a = new jz(MessageDigest.getInstance(z[70]));
        localjz = a;
      }
      catch (NoSuchAlgorithmException localNoSuchAlgorithmException)
      {
      }
    }
    throw new InternalError(z[69]);
  }

  private static String b(String paramString1, String paramString2)
    throws IOException, Exception
  {
    int i = yq.e;
    String str1 = a(paramString1, paramString2, "0");
    eq localeq = eq.b(f8.a);
    localeq.a(z[57], z[56] + str1);
    localeq.a(2);
    HttpResponse localHttpResponse = localeq.a();
    if (localHttpResponse == null)
      throw new IOException(z[39]);
    int j = localHttpResponse.getStatusLine().getStatusCode();
    if (j != 200)
      throw new IOException(z[45] + j);
    Header[] arrayOfHeader = localHttpResponse.getHeaders(z[88]);
    Pattern localPattern = Pattern.compile(z[89]);
    int k = 0;
    Matcher localMatcher;
    if (k < arrayOfHeader.length)
    {
      localMatcher = localPattern.matcher(arrayOfHeader[k].getValue());
      if (!localMatcher.find());
    }
    for (String str2 = localMatcher.group(1); ; str2 = null)
    {
      return str2;
      k++;
      if (i == 0)
        break;
    }
  }
}

/* Location:           C:\Users\Jaap\Downloads\Code\WhatsApp-2.8.4278_dex2jar.jar
 * Qualified Name:     com.whatsapp.yp
 * JD-Core Version:    0.6.1
 */