// #######################################################
// Decompiled by   : coddec 
// Module          : WhatsApp-7.cod
// Module version  : 2.7.3204
// Class ID        : 18
// ########################################################


package com.whatsapp.client;


abstract final class AuthVoiceScreen$7$1 extends Object
implements Runnable

{

	// @@@@@@@@@@@@@ Fields 
	private final String /*java.lang.String*/  field_55456 ; // ofs = 55456 addr = 0)
	private final com.whatsapp.client.AuthVoiceScreen$7 /*com.whatsapp.client.AuthVoiceScreen$7*/  this$1 ; // ofs = 55460 addr = 0)

	// @@@@@@@@@@@@@ Static routines 

<init>( com.whatsapp.client.AuthVoiceScreen$7$1, com.whatsapp.client.AuthVoiceScreen$7, java.lang.String ); // address: 0
	{
	enter_narrow 
	aload_0 
	invokespecial_lib java.lang.Object.<init> // pc=1
	aload_0 
	aload_1 
	putfield .field_1_1   // get_name_1:  .field_1_1   // get_name_2:  .field_1_1   // get_Name:    .field_1_1   // getName->1:  null   // getName->2:  null   // getName->N:  null   // ofs = -1 ord = 0 addr = 1
	aload_0 
	aload_2 
	putfield .field_0_   // get_name_1:  .field_0_   // get_name_2:  .field_0_   // get_Name:    .field_0_   // getName->1:  null   // getName->2:  null   // getName->N:  null   // ofs = -1 ord = 0 addr = 0
	return 
	}

	// @@@@@@@@@@@@@ Virtual routines 

public final run( com.whatsapp.client.AuthVoiceScreen$7$1 ); // address: 0
	{
	enter 
	aload_0_getfield .field_0_   // get_name_1:  .field_0_   // get_name_2:  .field_0_   // get_Name:    .field_0_   // getName->1:  null   // getName->2:  null   // getName->N:  null   // ofs = -1 ord = 0 addr = 0
	ldc literal_54:"ok"
	invokevirtual_short .equals // idx=1 pc=2
	ifeq Label9
	aload_0_getfield .field_1_1   // get_name_1:  .field_1_1   // get_name_2:  .field_1_1   // get_Name:    .field_1_1   // getName->1:  null   // getName->2:  null   // getName->N:  null   // ofs = -1 ord = 0 addr = 1
	getfield .field_1_1   // get_name_1:  .field_1_1   // get_name_2:  .field_1_1   // get_Name:    .field_1_1   // getName->1:  null   // getName->2:  null   // getName->N:  null   // ofs = -1 ord = 0 addr = 1
	invokespecial com.whatsapp.client.AuthVoiceScreen.transitionOut // pc=1
	return 
Label9:
	aload_0_getfield .field_1_1   // get_name_1:  .field_1_1   // get_name_2:  .field_1_1   // get_Name:    .field_1_1   // getName->1:  null   // getName->2:  null   // getName->N:  null   // ofs = -1 ord = 0 addr = 1
	getfield .field_1_1   // get_name_1:  .field_1_1   // get_name_2:  .field_1_1   // get_Name:    .field_1_1   // getName->1:  null   // getName->2:  null   // getName->N:  null   // ofs = -1 ord = 0 addr = 1
	getfield _codeEditField   // get_name_1:  _codeEditField   // get_name_2:  _codeEditField   // get_Name:    _codeEditField   // getName->1:  _codeEditField   // getName->2:  _codeEditField   // getName->N:  _codeEditField   // ofs = 54942 ord = 5 addr = 0
	invokevirtual net.rim.device.api.ui.text.TextFilter getFilter( net.rim.device.api.ui.component.BasicEditField ) // pc=1
	astore_1 
	aload_0_getfield .field_1_1   // get_name_1:  .field_1_1   // get_name_2:  .field_1_1   // get_Name:    .field_1_1   // getName->1:  null   // getName->2:  null   // getName->N:  null   // ofs = -1 ord = 0 addr = 1
	getfield .field_1_1   // get_name_1:  .field_1_1   // get_name_2:  .field_1_1   // get_Name:    .field_1_1   // getName->1:  null   // getName->2:  null   // getName->N:  null   // ofs = -1 ord = 0 addr = 1
	getfield _codeEditField   // get_name_1:  _codeEditField   // get_name_2:  _codeEditField   // get_Name:    _codeEditField   // getName->1:  _codeEditField   // getName->2:  _codeEditField   // getName->N:  _codeEditField   // ofs = 54942 ord = 5 addr = 0
	aconst_null 
	invokevirtual setFilter( net.rim.device.api.ui.component.BasicEditField, net.rim.device.api.ui.text.TextFilter ) // pc=2
	aload_0_getfield .field_0_   // get_name_1:  .field_0_   // get_name_2:  .field_0_   // get_Name:    .field_0_   // getName->1:  null   // getName->2:  null   // getName->N:  null   // ofs = -1 ord = 0 addr = 0
	ldc literal_53:"mismatch"
	invokevirtual_short .equals // idx=1 pc=2
	ifeq Label32
	aload_0_getfield .field_1_1   // get_name_1:  .field_1_1   // get_name_2:  .field_1_1   // get_Name:    .field_1_1   // getName->1:  null   // getName->2:  null   // getName->N:  null   // ofs = -1 ord = 0 addr = 1
	getfield .field_1_1   // get_name_1:  .field_1_1   // get_name_2:  .field_1_1   // get_Name:    .field_1_1   // getName->1:  null   // getName->2:  null   // getName->N:  null   // ofs = -1 ord = 0 addr = 1
	getfield _codeEditField   // get_name_1:  _codeEditField   // get_name_2:  _codeEditField   // get_Name:    _codeEditField   // getName->1:  _codeEditField   // getName->2:  _codeEditField   // getName->N:  _codeEditField   // ofs = 54942 ord = 5 addr = 0
	sipush 823
	aload_0_getfield .field_1_1   // get_name_1:  .field_1_1   // get_name_2:  .field_1_1   // get_Name:    .field_1_1   // getName->1:  null   // getName->2:  null   // getName->N:  null   // ofs = -1 ord = 0 addr = 1
	getfield .field_0_   // get_name_1:  .field_0_   // get_name_2:  .field_0_   // get_Name:    .field_0_   // getName->1:  null   // getName->2:  null   // getName->N:  null   // ofs = -1 ord = 0 addr = 0
	invokestatic_lib module:WhatsApp-27.class#28.routine_5809(  ) // class#28
	invokevirtual setText( net.rim.device.api.ui.component.BasicEditField, java.lang.String ) // pc=2
	goto Label37
Label32:
	aload_0_getfield .field_1_1   // get_name_1:  .field_1_1   // get_name_2:  .field_1_1   // get_Name:    .field_1_1   // getName->1:  null   // getName->2:  null   // getName->N:  null   // ofs = -1 ord = 0 addr = 1
	getfield .field_1_1   // get_name_1:  .field_1_1   // get_name_2:  .field_1_1   // get_Name:    .field_1_1   // getName->1:  null   // getName->2:  null   // getName->N:  null   // ofs = -1 ord = 0 addr = 1
	getfield _codeEditField   // get_name_1:  _codeEditField   // get_name_2:  _codeEditField   // get_Name:    _codeEditField   // getName->1:  _codeEditField   // getName->2:  _codeEditField   // getName->N:  _codeEditField   // ofs = 54942 ord = 5 addr = 0
	aload_0_getfield .field_0_   // get_name_1:  .field_0_   // get_name_2:  .field_0_   // get_Name:    .field_0_   // getName->1:  null   // getName->2:  null   // getName->N:  null   // ofs = -1 ord = 0 addr = 0
	invokevirtual setText( net.rim.device.api.ui.component.BasicEditField, java.lang.String ) // pc=2
Label37:
	invokestatic_lib com.whatsapp.client.UiApp.routine_6246(  ) // UiApp
	new AuthVoiceScreen$7$1$1
	dup 
	aload_0 
	aload_1 
	invokespecial com.whatsapp.client.AuthVoiceScreen$7$1$1.<init> // pc=3
	aload_0_getfield .field_1_1   // get_name_1:  .field_1_1   // get_name_2:  .field_1_1   // get_Name:    .field_1_1   // getName->1:  null   // getName->2:  null   // getName->N:  null   // ofs = -1 ord = 0 addr = 1
	getfield .field_1_1   // get_name_1:  .field_1_1   // get_name_2:  .field_1_1   // get_Name:    .field_1_1   // getName->1:  null   // getName->2:  null   // getName->N:  null   // ofs = -1 ord = 0 addr = 1
	getfield _nextWait   // get_name_1:  _nextWait   // get_name_2:  _nextWait   // get_Name:    _nextWait   // getName->1:  _nextWait   // getName->2:  _nextWait   // getName->N:  _nextWait   // ofs = 54958 ord = 9 addr = 0
	i2l 
	iconst_0 
	invokevirtual int invokeLater( net.rim.device.api.system.Application, java.lang.Runnable, long, boolean ) // pc=5
	pop 
	aload_0_getfield .field_1_1   // get_name_1:  .field_1_1   // get_name_2:  .field_1_1   // get_Name:    .field_1_1   // getName->1:  null   // getName->2:  null   // getName->N:  null   // ofs = -1 ord = 0 addr = 1
	getfield .field_1_1   // get_name_1:  .field_1_1   // get_name_2:  .field_1_1   // get_Name:    .field_1_1   // getName->1:  null   // getName->2:  null   // getName->N:  null   // ofs = -1 ord = 0 addr = 1
	aload_0_getfield .field_1_1   // get_name_1:  .field_1_1   // get_name_2:  .field_1_1   // get_Name:    .field_1_1   // getName->1:  null   // getName->2:  null   // getName->N:  null   // ofs = -1 ord = 0 addr = 1
	getfield .field_1_1   // get_name_1:  .field_1_1   // get_name_2:  .field_1_1   // get_Name:    .field_1_1   // getName->1:  null   // getName->2:  null   // getName->N:  null   // ofs = -1 ord = 0 addr = 1
	getfield _nextWait   // get_name_1:  _nextWait   // get_name_2:  _nextWait   // get_Name:    _nextWait   // getName->1:  _nextWait   // getName->2:  _nextWait   // getName->N:  _nextWait   // ofs = 54958 ord = 9 addr = 0
	bipush 3
	imul 
	bipush 2
	idiv 
	putfield _nextWait   // get_name_1:  _nextWait   // get_name_2:  _nextWait   // get_Name:    _nextWait   // getName->1:  _nextWait   // getName->2:  _nextWait   // getName->N:  _nextWait   // ofs = 54958 ord = 9 addr = 0
	return 
	}

}
