// #######################################################
// Decompiled by   : coddec 
// Module          : WhatsApp-1.cod
// Module version  : 2.8.1914
// Class ID        : 22
// ########################################################


package com.whatsapp.client;


abstract final class App$26 extends Object
implements Runnable

{

	// @@@@@@@@@@@@@ Fields 
	private final com.whatsapp.client.FunXMPP$Connection /*module:WhatsApp-27.class#0*/  field_55544 ; // ofs = 55544 addr = 0)
	private final com.whatsapp.client.App /*com.whatsapp.client.App*/  this$0 ; // ofs = 55548 addr = 0)

	// @@@@@@@@@@@@@ Static routines 

<init>( com.whatsapp.client.App$26, com.whatsapp.client.App, module:WhatsApp-27.class#0 ); // address: 0
	{
	enter_narrow 
	aload_0 
	invokespecial_lib java.lang.Object.<init> // pc=1
	aload_0 
	aload_1 
	putfield .field_1_1   // get_name_1:  .field_1_1   // get_name_2:  .field_1_1   // get_Name:    .field_1_1   // getName->1:  null   // getName->2:  null   // getName->N:  null   // ofs = -1 ord = 0 addr = 1
	aload_0 
	aload_2 
	putfield .field_0_   // get_name_1:  .field_0_   // get_name_2:  .field_0_   // get_Name:    .field_0_   // getName->1:  null   // getName->2:  null   // getName->N:  null   // ofs = -1 ord = 0 addr = 0
	return 
	}

	// @@@@@@@@@@@@@ Virtual routines 

public final run( com.whatsapp.client.App$26 ); // address: 0
	{
	enter 
	invokestatic_lib module:WhatsApp-12.class#2.routine_2805(  ) // class#2
	astore_1 
	invokestatic_lib long currentTimeMillis(  ) // System
	lstore 3
Label5:
	aload_1 
	invokeinterface interfacemethodref_8 // pc=1 guess=10
	ifne Label9
	goto_w Label67
Label9:
	aload_0_getfield .field_1_1   // get_name_1:  .field_1_1   // get_name_2:  .field_1_1   // get_Name:    .field_1_1   // getName->1:  null   // getName->2:  null   // getName->N:  null   // ofs = -1 ord = 0 addr = 1
	invokenonvirtual_lib .routine_939 // pc=1
	aload_1 
	invokeinterface interfacemethodref_9 // pc=1 guess=11
	checkcast_lib com.whatsapp.client.FunXMPP$FMessage//module:WhatsApp-26.class#23 module:WhatsApp-26.class#23 module:WhatsApp-26.class#23
	astore_2 
	new_lib String//java.lang.String java.lang.String java.lang.String
	dup 
	ldc literal_99:"offline send attempt for messg w key id "
	invokespecial_lib java.lang.StringBuffer.<init> // pc=2
	aload_2 
	getfield .field_1_1   // get_name_1:  .field_1_1   // get_name_2:  .field_1_1   // get_Name:    .field_1_1   // getName->1:  null   // getName->2:  null   // getName->N:  null   // ofs = -1 ord = 0 addr = 1
	getfield .field_2_2   // get_name_1:  .field_2_2   // get_name_2:  .field_2_2   // get_Name:    .field_2_2   // getName->1:  null   // getName->2:  null   // getName->N:  null   // ofs = -1 ord = 0 addr = 2
	invokevirtual java.lang.StringBuffer append( java.lang.StringBuffer, java.lang.String ) // pc=2
	invokevirtual_short .toString // idx=2 pc=1
	invokestatic_lib module:WhatsApp-79.class#39.routine_24694(  ) // class#39
	aload_2 
	getfield .field_1_1   // get_name_1:  .field_1_1   // get_name_2:  .field_1_1   // get_Name:    .field_1_1   // getName->1:  null   // getName->2:  null   // getName->N:  null   // ofs = -1 ord = 0 addr = 1
	getfield .field_0_   // get_name_1:  .field_0_   // get_name_2:  .field_0_   // get_Name:    .field_0_   // getName->1:  null   // getName->2:  null   // getName->N:  null   // ofs = -1 ord = 0 addr = 0
	astore_5 
	aload_5 
	ifnull Label39
	aload_5 
	getstatic_lib module:WhatsApp-19.class#0.static_63 // class#0
	invokenonvirtual_lib java.lang.String.endsWith // pc=2
	ifne Label39
	aload_5 
	getstatic_lib module:WhatsApp-19.class#0.static_64 // class#0
	invokenonvirtual_lib java.lang.String.endsWith // pc=2
	ifeq Label45
Label39:
	aload_0_getfield .field_1_1   // get_name_1:  .field_1_1   // get_name_2:  .field_1_1   // get_Name:    .field_1_1   // getName->1:  null   // getName->2:  null   // getName->N:  null   // ofs = -1 ord = 0 addr = 1
	aload_2 
	getfield .field_1_1   // get_name_1:  .field_1_1   // get_name_2:  .field_1_1   // get_Name:    .field_1_1   // getName->1:  null   // getName->2:  null   // getName->N:  null   // ofs = -1 ord = 0 addr = 1
	sipush 500
	invokenonvirtual_lib .routine_5319 // pc=3
	goto Label5
Label45:
	lload 3
	aload_2 
	lgetfield .field_8_8   // get_name_1:  .field_8_8   // get_name_2:  .field_8_8   // get_Name:    .field_8_8   // getName->1:  null   // getName->2:  null   // getName->N:  null   // ofs = -1 ord = 0 addr = 8
	lsub 
	invokestatic_lib long abs( long ) // Math
	iipush 86400000
	i2l 
	lcmp 
	ifle Label60
	aload_0_getfield .field_1_1   // get_name_1:  .field_1_1   // get_name_2:  .field_1_1   // get_Name:    .field_1_1   // getName->1:  null   // getName->2:  null   // getName->N:  null   // ofs = -1 ord = 0 addr = 1
	aload_2 
	getfield .field_1_1   // get_name_1:  .field_1_1   // get_name_2:  .field_1_1   // get_Name:    .field_1_1   // getName->1:  null   // getName->2:  null   // getName->N:  null   // ofs = -1 ord = 0 addr = 1
	sipush 408
	invokenonvirtual_lib .routine_5319 // pc=3
	goto_w Label5
Label60:
	aload_0_getfield .field_0_   // get_name_1:  .field_0_   // get_name_2:  .field_0_   // get_Name:    .field_0_   // getName->1:  null   // getName->2:  null   // getName->N:  null   // ofs = -1 ord = 0 addr = 0
	ifnull Label66
	aload_0_getfield .field_0_   // get_name_1:  .field_0_   // get_name_2:  .field_0_   // get_Name:    .field_0_   // getName->1:  null   // getName->2:  null   // getName->N:  null   // ofs = -1 ord = 0 addr = 0
	aload_2 
	invokenonvirtual_lib .routine_1258 // pc=2
	goto_w Label5
Label66:
	return 
Label67:
	aload_0_getfield .field_1_1   // get_name_1:  .field_1_1   // get_name_2:  .field_1_1   // get_Name:    .field_1_1   // getName->1:  null   // getName->2:  null   // getName->N:  null   // ofs = -1 ord = 0 addr = 1
	getfield _chatState   // get_name_1:  _chatState   // get_name_2:  _chatState   // get_Name:    _chatState   // getName->1:  _chatState   // getName->2:  _chatState   // getName->N:  _chatState   // ofs = -1 ord = 1 addr = -1
	getfield .field_31_31   // get_name_1:  .field_31_31   // get_name_2:  .field_31_31   // get_Name:    .field_31_31   // getName->1:  null   // getName->2:  null   // getName->N:  null   // ofs = -1 ord = 0 addr = 31
	invokenonvirtual_lib .routine_1777 // pc=1
	ifeq Label92
	aload_0_getfield .field_1_1   // get_name_1:  .field_1_1   // get_name_2:  .field_1_1   // get_Name:    .field_1_1   // getName->1:  null   // getName->2:  null   // getName->N:  null   // ofs = -1 ord = 0 addr = 1
	getfield _chatState   // get_name_1:  _chatState   // get_name_2:  _chatState   // get_Name:    _chatState   // getName->1:  _chatState   // getName->2:  _chatState   // getName->N:  _chatState   // ofs = -1 ord = 1 addr = -1
	getfield .field_31_31   // get_name_1:  .field_31_31   // get_name_2:  .field_31_31   // get_Name:    .field_31_31   // getName->1:  null   // getName->2:  null   // getName->N:  null   // ofs = -1 ord = 0 addr = 31
	invokenonvirtual_lib .routine_1766 // pc=1
	ifne Label92
	aload_0_getfield .field_0_   // get_name_1:  .field_0_   // get_name_2:  .field_0_   // get_Name:    .field_0_   // getName->1:  null   // getName->2:  null   // getName->N:  null   // ofs = -1 ord = 0 addr = 0
	ifnull Label92
	aload_0_getfield .field_0_   // get_name_1:  .field_0_   // get_name_2:  .field_0_   // get_Name:    .field_0_   // getName->1:  null   // getName->2:  null   // getName->N:  null   // ofs = -1 ord = 0 addr = 0
	aload_0_getfield .field_1_1   // get_name_1:  .field_1_1   // get_name_2:  .field_1_1   // get_Name:    .field_1_1   // getName->1:  null   // getName->2:  null   // getName->N:  null   // ofs = -1 ord = 0 addr = 1
	getfield _chatState   // get_name_1:  _chatState   // get_name_2:  _chatState   // get_Name:    _chatState   // getName->1:  _chatState   // getName->2:  _chatState   // getName->N:  _chatState   // ofs = -1 ord = 1 addr = -1
	getfield .field_31_31   // get_name_1:  .field_31_31   // get_name_2:  .field_31_31   // get_Name:    .field_31_31   // getName->1:  null   // getName->2:  null   // getName->N:  null   // ofs = -1 ord = 0 addr = 31
	invokenonvirtual_lib .routine_2194 // pc=1
	new App$26$1
	dup 
	aload_0 
	invokespecial com.whatsapp.client.App$26$1.<init> // pc=2
	aconst_null 
	invokenonvirtual_lib .routine_3238 // pc=4
	return 
	astore_1 
Label92:
	return 
	}

}
