// #######################################################
// Decompiled by   : coddec 
// Module          : WhatsApp-59.cod
// Module version  : 2.8.1914
// Class ID        : 2
// ########################################################


package com.whatsapp.util;


abstract public final class Queue extends Object

{

	// @@@@@@@@@@@@@ Fields 
	private com.whatsapp.util.Queue$Node /*com.whatsapp.util.Queue$Node*/  field_58378 ; // ofs = 58378 addr = 0)
	private com.whatsapp.util.Queue$Node /*com.whatsapp.util.Queue$Node*/  field_58382 ; // ofs = 58382 addr = 0)
	private int /*int*/  field_58386 ; // ofs = 58386 addr = 0)

	// @@@@@@@@@@@@@ Static routines 

public <init>( com.whatsapp.util.Queue ); // address: 0
	{
	enter_narrow 
	aload_0 
	invokespecial_lib java.lang.Object.<init> // pc=1
	aload_0 
	aconst_null 
	putfield .field_0_   // get_name_1:  .field_0_   // get_name_2:  .field_0_   // get_Name:    .field_0_   // getName->1:  null   // getName->2:  null   // getName->N:  null   // ofs = -1 ord = 0 addr = 0
	aload_0 
	aconst_null 
	putfield .field_1_1   // get_name_1:  .field_1_1   // get_name_2:  .field_1_1   // get_Name:    .field_1_1   // getName->1:  null   // getName->2:  null   // getName->N:  null   // ofs = -1 ord = 0 addr = 1
	aload_0 
	iconst_0 
	putfield .field_2_2   // get_name_1:  .field_2_2   // get_name_2:  .field_2_2   // get_Name:    .field_2_2   // getName->1:  null   // getName->2:  null   // getName->N:  null   // ofs = -1 ord = 0 addr = 2
	return 
	}

	// @@@@@@@@@@@@@ Non-virtual routines 

public final add( com.whatsapp.util.Queue, java.lang.Object ); // address: 0
	{
	enter_narrow 
	aload_1 
	ifnonnull Label7
	new_lib NullPointerException//java.lang.NullPointerException java.lang.NullPointerException java.lang.NullPointerException
	dup 
	invokespecial_lib java.lang.NullPointerException.<init> // pc=1
	athrow 
Label7:
	new Queue$Node
	dup 
	aconst_null 
	invokespecial com.whatsapp.util.Queue$Node.<init> // pc=2
	astore_2 
	aload_2 
	aload_1 
	putfield .field_0_   // get_name_1:  .field_0_   // get_name_2:  .field_0_   // get_Name:    .field_0_   // getName->1:  null   // getName->2:  null   // getName->N:  null   // ofs = -1 ord = 0 addr = 0
	aload_2 
	aconst_null 
	putfield .field_1_1   // get_name_1:  .field_1_1   // get_name_2:  .field_1_1   // get_Name:    .field_1_1   // getName->1:  null   // getName->2:  null   // getName->N:  null   // ofs = -1 ord = 0 addr = 1
	aload_0_getfield .field_0_   // get_name_1:  .field_0_   // get_name_2:  .field_0_   // get_Name:    .field_0_   // getName->1:  null   // getName->2:  null   // getName->N:  null   // ofs = -1 ord = 0 addr = 0
	ifnonnull Label27
	aload_0 
	aload_2 
	putfield .field_0_   // get_name_1:  .field_0_   // get_name_2:  .field_0_   // get_Name:    .field_0_   // getName->1:  null   // getName->2:  null   // getName->N:  null   // ofs = -1 ord = 0 addr = 0
	aload_0 
	aload_0_getfield .field_0_   // get_name_1:  .field_0_   // get_name_2:  .field_0_   // get_Name:    .field_0_   // getName->1:  null   // getName->2:  null   // getName->N:  null   // ofs = -1 ord = 0 addr = 0
	putfield .field_1_1   // get_name_1:  .field_1_1   // get_name_2:  .field_1_1   // get_Name:    .field_1_1   // getName->1:  null   // getName->2:  null   // getName->N:  null   // ofs = -1 ord = 0 addr = 1
	goto Label34
Label27:
	aload_0_getfield .field_1_1   // get_name_1:  .field_1_1   // get_name_2:  .field_1_1   // get_Name:    .field_1_1   // getName->1:  null   // getName->2:  null   // getName->N:  null   // ofs = -1 ord = 0 addr = 1
	aload_2 
	putfield .field_1_1   // get_name_1:  .field_1_1   // get_name_2:  .field_1_1   // get_Name:    .field_1_1   // getName->1:  null   // getName->2:  null   // getName->N:  null   // ofs = -1 ord = 0 addr = 1
	aload_0 
	aload_0_getfield .field_1_1   // get_name_1:  .field_1_1   // get_name_2:  .field_1_1   // get_Name:    .field_1_1   // getName->1:  null   // getName->2:  null   // getName->N:  null   // ofs = -1 ord = 0 addr = 1
	getfield .field_1_1   // get_name_1:  .field_1_1   // get_name_2:  .field_1_1   // get_Name:    .field_1_1   // getName->1:  null   // getName->2:  null   // getName->N:  null   // ofs = -1 ord = 0 addr = 1
	putfield .field_1_1   // get_name_1:  .field_1_1   // get_name_2:  .field_1_1   // get_Name:    .field_1_1   // getName->1:  null   // getName->2:  null   // getName->N:  null   // ofs = -1 ord = 0 addr = 1
Label34:
	aload_0 
	aload_0_getfield .field_2_2   // get_name_1:  .field_2_2   // get_name_2:  .field_2_2   // get_Name:    .field_2_2   // getName->1:  null   // getName->2:  null   // getName->N:  null   // ofs = -1 ord = 0 addr = 2
	iconst_1 
	iadd 
	putfield .field_2_2   // get_name_1:  .field_2_2   // get_name_2:  .field_2_2   // get_Name:    .field_2_2   // getName->1:  null   // getName->2:  null   // getName->N:  null   // ofs = -1 ord = 0 addr = 2
	return 
	}


public final java.lang.Object element( com.whatsapp.util.Queue ); // address: 0
	{
	enter_narrow 
	aload_0_getfield .field_0_   // get_name_1:  .field_0_   // get_name_2:  .field_0_   // get_Name:    .field_0_   // getName->1:  null   // getName->2:  null   // getName->N:  null   // ofs = -1 ord = 0 addr = 0
	ifnonnull Label5
	aconst_null 
	areturn 
Label5:
	aload_0_getfield .field_0_   // get_name_1:  .field_0_   // get_name_2:  .field_0_   // get_Name:    .field_0_   // getName->1:  null   // getName->2:  null   // getName->N:  null   // ofs = -1 ord = 0 addr = 0
	getfield .field_0_   // get_name_1:  .field_0_   // get_name_2:  .field_0_   // get_Name:    .field_0_   // getName->1:  null   // getName->2:  null   // getName->N:  null   // ofs = -1 ord = 0 addr = 0
	areturn 
	}


public final java.util.Enumeration elements( com.whatsapp.util.Queue ); // address: 0
	{
	enter_narrow 
	new Queue$QueueEnumeration
	dup 
	aload_0_getfield .field_0_   // get_name_1:  .field_0_   // get_name_2:  .field_0_   // get_Name:    .field_0_   // getName->1:  null   // getName->2:  null   // getName->N:  null   // ofs = -1 ord = 0 addr = 0
	invokespecial com.whatsapp.util.Queue$QueueEnumeration.<init> // pc=2
	areturn 
	}


public final java.lang.Object remove( com.whatsapp.util.Queue ); // address: 0
	{
	enter_narrow 
	aload_0_getfield .field_0_   // get_name_1:  .field_0_   // get_name_2:  .field_0_   // get_Name:    .field_0_   // getName->1:  null   // getName->2:  null   // getName->N:  null   // ofs = -1 ord = 0 addr = 0
	ifnonnull Label7
	new_lib java.util.NoSuchElementException//java.util.NoSuchElementException java.util.NoSuchElementException java.util.NoSuchElementException
	dup 
	invokespecial_lib java.util.NoSuchElementException.<init> // pc=1
	athrow 
Label7:
	aload_0_getfield .field_0_   // get_name_1:  .field_0_   // get_name_2:  .field_0_   // get_Name:    .field_0_   // getName->1:  null   // getName->2:  null   // getName->N:  null   // ofs = -1 ord = 0 addr = 0
	getfield .field_0_   // get_name_1:  .field_0_   // get_name_2:  .field_0_   // get_Name:    .field_0_   // getName->1:  null   // getName->2:  null   // getName->N:  null   // ofs = -1 ord = 0 addr = 0
	astore_1 
	aload_0_getfield .field_0_   // get_name_1:  .field_0_   // get_name_2:  .field_0_   // get_Name:    .field_0_   // getName->1:  null   // getName->2:  null   // getName->N:  null   // ofs = -1 ord = 0 addr = 0
	aconst_null 
	putfield .field_0_   // get_name_1:  .field_0_   // get_name_2:  .field_0_   // get_Name:    .field_0_   // getName->1:  null   // getName->2:  null   // getName->N:  null   // ofs = -1 ord = 0 addr = 0
	aload_0 
	aload_0_getfield .field_0_   // get_name_1:  .field_0_   // get_name_2:  .field_0_   // get_Name:    .field_0_   // getName->1:  null   // getName->2:  null   // getName->N:  null   // ofs = -1 ord = 0 addr = 0
	getfield .field_1_1   // get_name_1:  .field_1_1   // get_name_2:  .field_1_1   // get_Name:    .field_1_1   // getName->1:  null   // getName->2:  null   // getName->N:  null   // ofs = -1 ord = 0 addr = 1
	putfield .field_0_   // get_name_1:  .field_0_   // get_name_2:  .field_0_   // get_Name:    .field_0_   // getName->1:  null   // getName->2:  null   // getName->N:  null   // ofs = -1 ord = 0 addr = 0
	aload_0 
	aload_0_getfield .field_2_2   // get_name_1:  .field_2_2   // get_name_2:  .field_2_2   // get_Name:    .field_2_2   // getName->1:  null   // getName->2:  null   // getName->N:  null   // ofs = -1 ord = 0 addr = 2
	iconst_1 
	isub 
	putfield .field_2_2   // get_name_1:  .field_2_2   // get_name_2:  .field_2_2   // get_Name:    .field_2_2   // getName->1:  null   // getName->2:  null   // getName->N:  null   // ofs = -1 ord = 0 addr = 2
	aload_1 
	areturn 
	}


public final boolean isEmpty( com.whatsapp.util.Queue ); // address: 0
	{
	enter_narrow 
	aload_0_getfield .field_0_   // get_name_1:  .field_0_   // get_name_2:  .field_0_   // get_Name:    .field_0_   // getName->1:  null   // getName->2:  null   // getName->N:  null   // ofs = -1 ord = 0 addr = 0
	ifnonnull Label5
	iconst_1 
	ireturn 
Label5:
	iconst_0 
	ireturn 
	}


public final int size( com.whatsapp.util.Queue ); // address: 0
	{
	ireturn_field .field_2_2   // get_name_1:  .field_2_2   // get_name_2:  .field_2_2   // get_Name:    .field_2_2   // getName->1:  null   // getName->2:  null   // getName->N:  null   // ofs = -1 ord = 0 addr = 2
	}


public final copyInto( com.whatsapp.util.Queue, java.lang.Object[] ); // address: 0
	{
	enter 
	aload_0_getfield .field_0_   // get_name_1:  .field_0_   // get_name_2:  .field_0_   // get_Name:    .field_0_   // getName->1:  null   // getName->2:  null   // getName->N:  null   // ofs = -1 ord = 0 addr = 0
	ifnonnull Label4
	return 
Label4:
	iconst_0 
	istore_2 
	aload_0_getfield .field_0_   // get_name_1:  .field_0_   // get_name_2:  .field_0_   // get_Name:    .field_0_   // getName->1:  null   // getName->2:  null   // getName->N:  null   // ofs = -1 ord = 0 addr = 0
	astore_3 
Label8:
	iload_2 
	aload_0_getfield .field_2_2   // get_name_1:  .field_2_2   // get_name_2:  .field_2_2   // get_Name:    .field_2_2   // getName->1:  null   // getName->2:  null   // getName->N:  null   // ofs = -1 ord = 0 addr = 2
	if_icmpge Label21
	aload_1 
	iload_2 
	iinc 2 1
	aload_3 
	getfield .field_0_   // get_name_1:  .field_0_   // get_name_2:  .field_0_   // get_Name:    .field_0_   // getName->1:  null   // getName->2:  null   // getName->N:  null   // ofs = -1 ord = 0 addr = 0
	aastore 
	aload_3 
	getfield .field_1_1   // get_name_1:  .field_1_1   // get_name_2:  .field_1_1   // get_Name:    .field_1_1   // getName->1:  null   // getName->2:  null   // getName->N:  null   // ofs = -1 ord = 0 addr = 1
	astore_3 
	goto Label8
Label21:
	return 
	}

}
