// #######################################################
// Decompiled by   : coddec 
// Module          : WhatsApp-27.cod
// Module version  : 2.8.1914
// Class ID        : 1
// ########################################################


package com.whatsapp.client;


abstract public final class FunXMPP$FMessage$Builder extends Object

{

	// @@@@@@@@@@@@@ Fields 
	private com.whatsapp.client.FunXMPP$FMessage /*module:WhatsApp-26.class#23*/  field_55408 ; // ofs = 55408 addr = 0)
	private String /*java.lang.String*/  field_55412 ; // ofs = 55412 addr = 0)
	private String /*java.lang.String*/  field_55416 ; // ofs = 55416 addr = 0)
	private Boolean /*java.lang.Boolean*/  field_55420 ; // ofs = 55420 addr = 0)
	private String /*java.lang.String*/  field_55424 ; // ofs = 55424 addr = 0)
	private Boolean /*java.lang.Boolean*/  field_55428 ; // ofs = 55428 addr = 0)
	private String /*java.lang.String*/  field_55432 ; // ofs = 55432 addr = 0)
	private byte[] /*byte[]*/  field_55436 ; // ofs = 55436 addr = 0)
	private Integer /*java.lang.Integer*/  field_55440 ; // ofs = 55440 addr = 0)
	private Long /*java.lang.Long*/  field_55444 ; // ofs = 55444 addr = 0)
	private Boolean /*java.lang.Boolean*/  field_55448 ; // ofs = 55448 addr = 0)
	private Byte /*java.lang.Byte*/  field_55452 ; // ofs = 55452 addr = 0)
	private Long /*java.lang.Long*/  field_55456 ; // ofs = 55456 addr = 0)
	private Integer /*java.lang.Integer*/  field_55460 ; // ofs = 55460 addr = 0)
	private String /*java.lang.String*/  field_55464 ; // ofs = 55464 addr = 0)
	private String /*java.lang.String*/  field_55468 ; // ofs = 55468 addr = 0)
	private Double /*java.lang.Double*/  field_55472 ; // ofs = 55472 addr = 0)
	private Double /*java.lang.Double*/  field_55476 ; // ofs = 55476 addr = 0)
	private String /*java.lang.String*/  field_55480 ; // ofs = 55480 addr = 0)

	// @@@@@@@@@@@@@ Static routines 

public <init>( com.whatsapp.client.FunXMPP$FMessage$Builder ); // address: 0
	{
	jumpspecial_lib <init>( java.lang.Object )
	}

	// @@@@@@@@@@@@@ Non-virtual routines 

public final com.whatsapp.client.FunXMPP$FMessage$Builder key( com.whatsapp.client.FunXMPP$FMessage$Builder, module:WhatsApp-26.class#24 ); // address: 0
	{
	enter_narrow 
	aload_0 
	aload_1 
	getfield .field_0_   // get_name_1:  .field_0_   // get_name_2:  .field_0_   // get_Name:    .field_0_   // getName->1:  null   // getName->2:  null   // getName->N:  null   // ofs = -1 ord = 0 addr = 0
	putfield .field_1_1   // get_name_1:  .field_1_1   // get_name_2:  .field_1_1   // get_Name:    .field_1_1   // getName->1:  null   // getName->2:  null   // getName->N:  null   // ofs = -1 ord = 0 addr = 1
	aload_0 
	aload_1 
	getfield .field_1_1   // get_name_1:  .field_1_1   // get_name_2:  .field_1_1   // get_Name:    .field_1_1   // getName->1:  null   // getName->2:  null   // getName->N:  null   // ofs = -1 ord = 0 addr = 1
	ifeq Label11
	getstatic_lib TRUE // Boolean
	goto Label12
Label11:
	getstatic_lib FALSE // Boolean
Label12:
	putfield .field_3_3   // get_name_1:  .field_3_3   // get_name_2:  .field_3_3   // get_Name:    .field_3_3   // getName->1:  null   // getName->2:  null   // getName->N:  null   // ofs = -1 ord = 0 addr = 3
	aload_0 
	aload_1 
	getfield .field_2_2   // get_name_1:  .field_2_2   // get_name_2:  .field_2_2   // get_Name:    .field_2_2   // getName->1:  null   // getName->2:  null   // getName->N:  null   // ofs = -1 ord = 0 addr = 2
	putfield .field_4_4   // get_name_1:  .field_4_4   // get_name_2:  .field_4_4   // get_Name:    .field_4_4   // getName->1:  null   // getName->2:  null   // getName->N:  null   // ofs = -1 ord = 0 addr = 4
	aload_0 
	areturn 
	}


public final com.whatsapp.client.FunXMPP$FMessage$Builder remote_resource( com.whatsapp.client.FunXMPP$FMessage$Builder, java.lang.String ); // address: 0
	{
	enter_narrow 
	aload_0 
	aload_1 
	putfield .field_2_2   // get_name_1:  .field_2_2   // get_name_2:  .field_2_2   // get_Name:    .field_2_2   // getName->1:  null   // getName->2:  null   // getName->N:  null   // ofs = -1 ord = 0 addr = 2
	aload_0 
	areturn 
	}


public final com.whatsapp.client.FunXMPP$FMessage$Builder wants_receipt( com.whatsapp.client.FunXMPP$FMessage$Builder, boolean ); // address: 0
	{
	enter_narrow 
	aload_0 
	iload_1 
	ifeq Label6
	getstatic_lib TRUE // Boolean
	goto Label7
Label6:
	getstatic_lib FALSE // Boolean
Label7:
	putfield .field_5_5   // get_name_1:  .field_5_5   // get_name_2:  .field_5_5   // get_Name:    .field_5_5   // getName->1:  null   // getName->2:  null   // getName->N:  null   // ofs = -1 ord = 0 addr = 5
	aload_0 
	areturn 
	}


public final com.whatsapp.client.FunXMPP$FMessage$Builder data( com.whatsapp.client.FunXMPP$FMessage$Builder, java.lang.String ); // address: 0
	{
	enter_narrow 
	aload_0 
	aload_1 
	putfield .field_6_6   // get_name_1:  .field_6_6   // get_name_2:  .field_6_6   // get_Name:    .field_6_6   // getName->1:  null   // getName->2:  null   // getName->N:  null   // ofs = -1 ord = 0 addr = 6
	aload_0 
	areturn 
	}


public final com.whatsapp.client.FunXMPP$FMessage$Builder dataBytes( com.whatsapp.client.FunXMPP$FMessage$Builder, byte[] ); // address: 0
	{
	enter_narrow 
	aload_0 
	aload_1 
	putfield .field_7_7   // get_name_1:  .field_7_7   // get_name_2:  .field_7_7   // get_Name:    .field_7_7   // getName->1:  null   // getName->2:  null   // getName->N:  null   // ofs = -1 ord = 0 addr = 7
	aload_0 
	areturn 
	}


public final com.whatsapp.client.FunXMPP$FMessage$Builder encoding( com.whatsapp.client.FunXMPP$FMessage$Builder, int ); // address: 0
	{
	enter 
	aload_0 
	new_lib Integer//java.lang.Integer java.lang.Integer java.lang.Integer
	dup 
	iload_1 
	invokespecial_lib java.lang.Integer.<init> // pc=2
	putfield .field_8_8   // get_name_1:  .field_8_8   // get_name_2:  .field_8_8   // get_Name:    .field_8_8   // getName->1:  null   // getName->2:  null   // getName->N:  null   // ofs = -1 ord = 0 addr = 8
	aload_0 
	areturn 
	}


public final com.whatsapp.client.FunXMPP$FMessage$Builder offline( com.whatsapp.client.FunXMPP$FMessage$Builder, java.lang.Boolean ); // address: 0
	{
	enter_narrow 
	aload_0 
	aload_1 
	putfield .field_10_10   // get_name_1:  .field_10_10   // get_name_2:  .field_10_10   // get_Name:    .field_10_10   // getName->1:  null   // getName->2:  null   // getName->N:  null   // ofs = -1 ord = 0 addr = 10
	aload_0 
	areturn 
	}


public final com.whatsapp.client.FunXMPP$FMessage$Builder timestamp( com.whatsapp.client.FunXMPP$FMessage$Builder, long ); // address: 0
	{
	enter 
	aload_0 
	new_lib Long//java.lang.Long java.lang.Long java.lang.Long
	dup 
	lload 1
	invokespecial_lib java.lang.Long.<init> // pc=3
	putfield .field_9_9   // get_name_1:  .field_9_9   // get_name_2:  .field_9_9   // get_Name:    .field_9_9   // getName->1:  null   // getName->2:  null   // getName->N:  null   // ofs = -1 ord = 0 addr = 9
	aload_0 
	areturn 
	}


public final com.whatsapp.client.FunXMPP$FMessage$Builder media_wa_type( com.whatsapp.client.FunXMPP$FMessage$Builder, byte ); // address: 0
	{
	enter 
	aload_0 
	new_lib Byte//java.lang.Byte java.lang.Byte java.lang.Byte
	dup 
	iload_1 
	invokespecial_lib java.lang.Byte.<init> // pc=2
	putfield .field_11_11   // get_name_1:  .field_11_11   // get_name_2:  .field_11_11   // get_Name:    .field_11_11   // getName->1:  null   // getName->2:  null   // getName->N:  null   // ofs = -1 ord = 0 addr = 11
	aload_0 
	areturn 
	}


public final java.lang.Byte media_wa_type( com.whatsapp.client.FunXMPP$FMessage$Builder ); // address: 0
	{
	areturn_field .field_11_11   // get_name_1:  .field_11_11   // get_name_2:  .field_11_11   // get_Name:    .field_11_11   // getName->1:  null   // getName->2:  null   // getName->N:  null   // ofs = -1 ord = 0 addr = 11
	}


public final com.whatsapp.client.FunXMPP$FMessage$Builder media_size( com.whatsapp.client.FunXMPP$FMessage$Builder, long ); // address: 0
	{
	enter 
	aload_0 
	new_lib Long//java.lang.Long java.lang.Long java.lang.Long
	dup 
	lload 1
	invokespecial_lib java.lang.Long.<init> // pc=3
	putfield .field_12_12   // get_name_1:  .field_12_12   // get_name_2:  .field_12_12   // get_Name:    .field_12_12   // getName->1:  null   // getName->2:  null   // getName->N:  null   // ofs = -1 ord = 0 addr = 12
	aload_0 
	areturn 
	}


public final com.whatsapp.client.FunXMPP$FMessage$Builder media_duration_seconds( com.whatsapp.client.FunXMPP$FMessage$Builder, int ); // address: 0
	{
	enter 
	aload_0 
	new_lib Integer//java.lang.Integer java.lang.Integer java.lang.Integer
	dup 
	iload_1 
	invokespecial_lib java.lang.Integer.<init> // pc=2
	putfield .field_13_13   // get_name_1:  .field_13_13   // get_name_2:  .field_13_13   // get_Name:    .field_13_13   // getName->1:  null   // getName->2:  null   // getName->N:  null   // ofs = -1 ord = 0 addr = 13
	aload_0 
	areturn 
	}


public final com.whatsapp.client.FunXMPP$FMessage$Builder media_url( com.whatsapp.client.FunXMPP$FMessage$Builder, java.lang.String ); // address: 0
	{
	enter_narrow 
	aload_0 
	aload_1 
	putfield .field_14_14   // get_name_1:  .field_14_14   // get_name_2:  .field_14_14   // get_Name:    .field_14_14   // getName->1:  null   // getName->2:  null   // getName->N:  null   // ofs = -1 ord = 0 addr = 14
	aload_0 
	areturn 
	}


public final com.whatsapp.client.FunXMPP$FMessage$Builder media_name( com.whatsapp.client.FunXMPP$FMessage$Builder, java.lang.String ); // address: 0
	{
	enter_narrow 
	aload_0 
	aload_1 
	putfield .field_15_15   // get_name_1:  .field_15_15   // get_name_2:  .field_15_15   // get_Name:    .field_15_15   // getName->1:  null   // getName->2:  null   // getName->N:  null   // ofs = -1 ord = 0 addr = 15
	aload_0 
	areturn 
	}


public final com.whatsapp.client.FunXMPP$FMessage$Builder latitude( com.whatsapp.client.FunXMPP$FMessage$Builder, java.lang.Double ); // address: 0
	{
	enter_narrow 
	aload_0 
	aload_1 
	putfield .field_16_16   // get_name_1:  .field_16_16   // get_name_2:  .field_16_16   // get_Name:    .field_16_16   // getName->1:  null   // getName->2:  null   // getName->N:  null   // ofs = -1 ord = 0 addr = 16
	aload_0 
	areturn 
	}


public final com.whatsapp.client.FunXMPP$FMessage$Builder longitude( com.whatsapp.client.FunXMPP$FMessage$Builder, java.lang.Double ); // address: 0
	{
	enter_narrow 
	aload_0 
	aload_1 
	putfield .field_17_17   // get_name_1:  .field_17_17   // get_name_2:  .field_17_17   // get_Name:    .field_17_17   // getName->1:  null   // getName->2:  null   // getName->N:  null   // ofs = -1 ord = 0 addr = 17
	aload_0 
	areturn 
	}


public final com.whatsapp.client.FunXMPP$FMessage$Builder from_name( com.whatsapp.client.FunXMPP$FMessage$Builder, java.lang.String ); // address: 0
	{
	enter_narrow 
	aload_0 
	aload_1 
	putfield .field_18_18   // get_name_1:  .field_18_18   // get_name_2:  .field_18_18   // get_Name:    .field_18_18   // getName->1:  null   // getName->2:  null   // getName->N:  null   // ofs = -1 ord = 0 addr = 18
	aload_0 
	areturn 
	}


public final com.whatsapp.client.FunXMPP$FMessage$Builder newIncomingInstance( com.whatsapp.client.FunXMPP$FMessage$Builder ); // address: 0
	{
	enter 
	aload_0_getfield .field_1_1   // get_name_1:  .field_1_1   // get_name_2:  .field_1_1   // get_Name:    .field_1_1   // getName->1:  null   // getName->2:  null   // getName->N:  null   // ofs = -1 ord = 0 addr = 1
	ifnull Label7
	aload_0_getfield .field_3_3   // get_name_1:  .field_3_3   // get_name_2:  .field_3_3   // get_Name:    .field_3_3   // getName->1:  null   // getName->2:  null   // getName->N:  null   // ofs = -1 ord = 0 addr = 3
	ifnull Label7
	aload_0_getfield .field_4_4   // get_name_1:  .field_4_4   // get_name_2:  .field_4_4   // get_Name:    .field_4_4   // getName->1:  null   // getName->2:  null   // getName->N:  null   // ofs = -1 ord = 0 addr = 4
	ifnonnull Label12
Label7:
	new_lib UnsupportedOperationException//java.lang.UnsupportedOperationException java.lang.UnsupportedOperationException java.lang.UnsupportedOperationException
	dup 
	ldc literal_245:"missing required property before instantiating new incoming message"
	invokespecial_lib java.lang.UnsupportedOperationException.<init> // pc=2
	athrow 
Label12:
	aload_0 
	new_lib com.whatsapp.client.FunXMPP$FMessage//module:WhatsApp-26.class#23 module:WhatsApp-26.class#23 module:WhatsApp-26.class#23
	dup 
	new_lib com.whatsapp.client.FunXMPP$FMessage$Key//module:WhatsApp-26.class#24 module:WhatsApp-26.class#24 module:WhatsApp-26.class#24
	dup 
	aload_0_getfield .field_1_1   // get_name_1:  .field_1_1   // get_name_2:  .field_1_1   // get_Name:    .field_1_1   // getName->1:  null   // getName->2:  null   // getName->N:  null   // ofs = -1 ord = 0 addr = 1
	aload_0_getfield .field_3_3   // get_name_1:  .field_3_3   // get_name_2:  .field_3_3   // get_Name:    .field_3_3   // getName->1:  null   // getName->2:  null   // getName->N:  null   // ofs = -1 ord = 0 addr = 3
	invokevirtual boolean booleanValue( java.lang.Boolean ) // pc=1
	aload_0_getfield .field_4_4   // get_name_1:  .field_4_4   // get_name_2:  .field_4_4   // get_Name:    .field_4_4   // getName->1:  null   // getName->2:  null   // getName->N:  null   // ofs = -1 ord = 0 addr = 4
	invokespecial_lib .routine_6840 // pc=4
	invokespecial_lib .routine_6221 // pc=2
	putfield .field_0_   // get_name_1:  .field_0_   // get_name_2:  .field_0_   // get_Name:    .field_0_   // getName->1:  null   // getName->2:  null   // getName->N:  null   // ofs = -1 ord = 0 addr = 0
	aload_0 
	areturn 
	}


public final module:WhatsApp-26.class#23 build( com.whatsapp.client.FunXMPP$FMessage$Builder ); // address: 0
	{
	enter 
	aload_0_getfield .field_0_   // get_name_1:  .field_0_   // get_name_2:  .field_0_   // get_Name:    .field_0_   // getName->1:  null   // getName->2:  null   // getName->N:  null   // ofs = -1 ord = 0 addr = 0
	ifnonnull Label5
	aconst_null 
	areturn 
Label5:
	aload_0_getfield .field_1_1   // get_name_1:  .field_1_1   // get_name_2:  .field_1_1   // get_Name:    .field_1_1   // getName->1:  null   // getName->2:  null   // getName->N:  null   // ofs = -1 ord = 0 addr = 1
	ifnull Label20
	aload_0_getfield .field_3_3   // get_name_1:  .field_3_3   // get_name_2:  .field_3_3   // get_Name:    .field_3_3   // getName->1:  null   // getName->2:  null   // getName->N:  null   // ofs = -1 ord = 0 addr = 3
	ifnull Label20
	aload_0_getfield .field_4_4   // get_name_1:  .field_4_4   // get_name_2:  .field_4_4   // get_Name:    .field_4_4   // getName->1:  null   // getName->2:  null   // getName->N:  null   // ofs = -1 ord = 0 addr = 4
	ifnull Label20
	aload_0_getfield .field_0_   // get_name_1:  .field_0_   // get_name_2:  .field_0_   // get_Name:    .field_0_   // getName->1:  null   // getName->2:  null   // getName->N:  null   // ofs = -1 ord = 0 addr = 0
	new_lib com.whatsapp.client.FunXMPP$FMessage$Key//module:WhatsApp-26.class#24 module:WhatsApp-26.class#24 module:WhatsApp-26.class#24
	dup 
	aload_0_getfield .field_1_1   // get_name_1:  .field_1_1   // get_name_2:  .field_1_1   // get_Name:    .field_1_1   // getName->1:  null   // getName->2:  null   // getName->N:  null   // ofs = -1 ord = 0 addr = 1
	aload_0_getfield .field_3_3   // get_name_1:  .field_3_3   // get_name_2:  .field_3_3   // get_Name:    .field_3_3   // getName->1:  null   // getName->2:  null   // getName->N:  null   // ofs = -1 ord = 0 addr = 3
	invokevirtual boolean booleanValue( java.lang.Boolean ) // pc=1
	aload_0_getfield .field_4_4   // get_name_1:  .field_4_4   // get_name_2:  .field_4_4   // get_Name:    .field_4_4   // getName->1:  null   // getName->2:  null   // getName->N:  null   // ofs = -1 ord = 0 addr = 4
	invokespecial_lib .routine_6840 // pc=4
	putfield .field_1_1   // get_name_1:  .field_1_1   // get_name_2:  .field_1_1   // get_Name:    .field_1_1   // getName->1:  null   // getName->2:  null   // getName->N:  null   // ofs = -1 ord = 0 addr = 1
Label20:
	aload_0_getfield .field_2_2   // get_name_1:  .field_2_2   // get_name_2:  .field_2_2   // get_Name:    .field_2_2   // getName->1:  null   // getName->2:  null   // getName->N:  null   // ofs = -1 ord = 0 addr = 2
	ifnull Label25
	aload_0_getfield .field_0_   // get_name_1:  .field_0_   // get_name_2:  .field_0_   // get_Name:    .field_0_   // getName->1:  null   // getName->2:  null   // getName->N:  null   // ofs = -1 ord = 0 addr = 0
	aload_0_getfield .field_2_2   // get_name_1:  .field_2_2   // get_name_2:  .field_2_2   // get_Name:    .field_2_2   // getName->1:  null   // getName->2:  null   // getName->N:  null   // ofs = -1 ord = 0 addr = 2
	putfield .field_2_2   // get_name_1:  .field_2_2   // get_name_2:  .field_2_2   // get_Name:    .field_2_2   // getName->1:  null   // getName->2:  null   // getName->N:  null   // ofs = -1 ord = 0 addr = 2
Label25:
	aload_0_getfield .field_5_5   // get_name_1:  .field_5_5   // get_name_2:  .field_5_5   // get_Name:    .field_5_5   // getName->1:  null   // getName->2:  null   // getName->N:  null   // ofs = -1 ord = 0 addr = 5
	ifnull Label31
	aload_0_getfield .field_0_   // get_name_1:  .field_0_   // get_name_2:  .field_0_   // get_Name:    .field_0_   // getName->1:  null   // getName->2:  null   // getName->N:  null   // ofs = -1 ord = 0 addr = 0
	aload_0_getfield .field_5_5   // get_name_1:  .field_5_5   // get_name_2:  .field_5_5   // get_Name:    .field_5_5   // getName->1:  null   // getName->2:  null   // getName->N:  null   // ofs = -1 ord = 0 addr = 5
	invokevirtual boolean booleanValue( java.lang.Boolean ) // pc=1
	putfield .field_4_4   // get_name_1:  .field_4_4   // get_name_2:  .field_4_4   // get_Name:    .field_4_4   // getName->1:  null   // getName->2:  null   // getName->N:  null   // ofs = -1 ord = 0 addr = 4
Label31:
	aload_0_getfield .field_6_6   // get_name_1:  .field_6_6   // get_name_2:  .field_6_6   // get_Name:    .field_6_6   // getName->1:  null   // getName->2:  null   // getName->N:  null   // ofs = -1 ord = 0 addr = 6
	ifnull Label36
	aload_0_getfield .field_0_   // get_name_1:  .field_0_   // get_name_2:  .field_0_   // get_Name:    .field_0_   // getName->1:  null   // getName->2:  null   // getName->N:  null   // ofs = -1 ord = 0 addr = 0
	aload_0_getfield .field_6_6   // get_name_1:  .field_6_6   // get_name_2:  .field_6_6   // get_Name:    .field_6_6   // getName->1:  null   // getName->2:  null   // getName->N:  null   // ofs = -1 ord = 0 addr = 6
	invokenonvirtual_lib .routine_6057 // pc=2
Label36:
	aload_0_getfield .field_7_7   // get_name_1:  .field_7_7   // get_name_2:  .field_7_7   // get_Name:    .field_7_7   // getName->1:  null   // getName->2:  null   // getName->N:  null   // ofs = -1 ord = 0 addr = 7
	ifnull Label41
	aload_0_getfield .field_0_   // get_name_1:  .field_0_   // get_name_2:  .field_0_   // get_Name:    .field_0_   // getName->1:  null   // getName->2:  null   // getName->N:  null   // ofs = -1 ord = 0 addr = 0
	aload_0_getfield .field_7_7   // get_name_1:  .field_7_7   // get_name_2:  .field_7_7   // get_Name:    .field_7_7   // getName->1:  null   // getName->2:  null   // getName->N:  null   // ofs = -1 ord = 0 addr = 7
	invokenonvirtual_lib .routine_6076 // pc=2
Label41:
	aload_0_getfield .field_8_8   // get_name_1:  .field_8_8   // get_name_2:  .field_8_8   // get_Name:    .field_8_8   // getName->1:  null   // getName->2:  null   // getName->N:  null   // ofs = -1 ord = 0 addr = 8
	ifnull Label47
	aload_0_getfield .field_0_   // get_name_1:  .field_0_   // get_name_2:  .field_0_   // get_Name:    .field_0_   // getName->1:  null   // getName->2:  null   // getName->N:  null   // ofs = -1 ord = 0 addr = 0
	aload_0_getfield .field_8_8   // get_name_1:  .field_8_8   // get_name_2:  .field_8_8   // get_Name:    .field_8_8   // getName->1:  null   // getName->2:  null   // getName->N:  null   // ofs = -1 ord = 0 addr = 8
	invokevirtual int intValue( java.lang.Integer ) // pc=1
	putfield .field_7_7   // get_name_1:  .field_7_7   // get_name_2:  .field_7_7   // get_Name:    .field_7_7   // getName->1:  null   // getName->2:  null   // getName->N:  null   // ofs = -1 ord = 0 addr = 7
Label47:
	aload_0_getfield .field_9_9   // get_name_1:  .field_9_9   // get_name_2:  .field_9_9   // get_Name:    .field_9_9   // getName->1:  null   // getName->2:  null   // getName->N:  null   // ofs = -1 ord = 0 addr = 9
	ifnull Label53
	aload_0_getfield .field_0_   // get_name_1:  .field_0_   // get_name_2:  .field_0_   // get_Name:    .field_0_   // getName->1:  null   // getName->2:  null   // getName->N:  null   // ofs = -1 ord = 0 addr = 0
	aload_0_getfield .field_9_9   // get_name_1:  .field_9_9   // get_name_2:  .field_9_9   // get_Name:    .field_9_9   // getName->1:  null   // getName->2:  null   // getName->N:  null   // ofs = -1 ord = 0 addr = 9
	invokevirtual long longValue( java.lang.Long ) // pc=1
	lputfield .field_8_8   // get_name_1:  .field_8_8   // get_name_2:  .field_8_8   // get_Name:    .field_8_8   // getName->1:  null   // getName->2:  null   // getName->N:  null   // ofs = -1 ord = 0 addr = 8
Label53:
	aload_0_getfield .field_10_10   // get_name_1:  .field_10_10   // get_name_2:  .field_10_10   // get_Name:    .field_10_10   // getName->1:  null   // getName->2:  null   // getName->N:  null   // ofs = -1 ord = 0 addr = 10
	ifnull Label59
	aload_0_getfield .field_0_   // get_name_1:  .field_0_   // get_name_2:  .field_0_   // get_Name:    .field_0_   // getName->1:  null   // getName->2:  null   // getName->N:  null   // ofs = -1 ord = 0 addr = 0
	aload_0_getfield .field_10_10   // get_name_1:  .field_10_10   // get_name_2:  .field_10_10   // get_Name:    .field_10_10   // getName->1:  null   // getName->2:  null   // getName->N:  null   // ofs = -1 ord = 0 addr = 10
	invokevirtual boolean booleanValue( java.lang.Boolean ) // pc=1
	putfield .field_24_24   // get_name_1:  .field_24_24   // get_name_2:  .field_24_24   // get_Name:    .field_24_24   // getName->1:  null   // getName->2:  null   // getName->N:  null   // ofs = -1 ord = 0 addr = 24
Label59:
	aload_0_getfield .field_11_11   // get_name_1:  .field_11_11   // get_name_2:  .field_11_11   // get_Name:    .field_11_11   // getName->1:  null   // getName->2:  null   // getName->N:  null   // ofs = -1 ord = 0 addr = 11
	ifnull Label65
	aload_0_getfield .field_0_   // get_name_1:  .field_0_   // get_name_2:  .field_0_   // get_Name:    .field_0_   // getName->1:  null   // getName->2:  null   // getName->N:  null   // ofs = -1 ord = 0 addr = 0
	aload_0_getfield .field_11_11   // get_name_1:  .field_11_11   // get_name_2:  .field_11_11   // get_Name:    .field_11_11   // getName->1:  null   // getName->2:  null   // getName->N:  null   // ofs = -1 ord = 0 addr = 11
	invokevirtual byte byteValue( java.lang.Byte ) // pc=1
	putfield .field_12_12   // get_name_1:  .field_12_12   // get_name_2:  .field_12_12   // get_Name:    .field_12_12   // getName->1:  null   // getName->2:  null   // getName->N:  null   // ofs = -1 ord = 0 addr = 12
Label65:
	aload_0_getfield .field_12_12   // get_name_1:  .field_12_12   // get_name_2:  .field_12_12   // get_Name:    .field_12_12   // getName->1:  null   // getName->2:  null   // getName->N:  null   // ofs = -1 ord = 0 addr = 12
	ifnull Label71
	aload_0_getfield .field_0_   // get_name_1:  .field_0_   // get_name_2:  .field_0_   // get_Name:    .field_0_   // getName->1:  null   // getName->2:  null   // getName->N:  null   // ofs = -1 ord = 0 addr = 0
	aload_0_getfield .field_12_12   // get_name_1:  .field_12_12   // get_name_2:  .field_12_12   // get_Name:    .field_12_12   // getName->1:  null   // getName->2:  null   // getName->N:  null   // ofs = -1 ord = 0 addr = 12
	invokevirtual long longValue( java.lang.Long ) // pc=1
	lputfield .field_13_13   // get_name_1:  .field_13_13   // get_name_2:  .field_13_13   // get_Name:    .field_13_13   // getName->1:  null   // getName->2:  null   // getName->N:  null   // ofs = -1 ord = 0 addr = 13
Label71:
	aload_0_getfield .field_13_13   // get_name_1:  .field_13_13   // get_name_2:  .field_13_13   // get_Name:    .field_13_13   // getName->1:  null   // getName->2:  null   // getName->N:  null   // ofs = -1 ord = 0 addr = 13
	ifnull Label77
	aload_0_getfield .field_0_   // get_name_1:  .field_0_   // get_name_2:  .field_0_   // get_Name:    .field_0_   // getName->1:  null   // getName->2:  null   // getName->N:  null   // ofs = -1 ord = 0 addr = 0
	aload_0_getfield .field_13_13   // get_name_1:  .field_13_13   // get_name_2:  .field_13_13   // get_Name:    .field_13_13   // getName->1:  null   // getName->2:  null   // getName->N:  null   // ofs = -1 ord = 0 addr = 13
	invokevirtual int intValue( java.lang.Integer ) // pc=1
	putfield .field_15_15   // get_name_1:  .field_15_15   // get_name_2:  .field_15_15   // get_Name:    .field_15_15   // getName->1:  null   // getName->2:  null   // getName->N:  null   // ofs = -1 ord = 0 addr = 15
Label77:
	aload_0_getfield .field_14_14   // get_name_1:  .field_14_14   // get_name_2:  .field_14_14   // get_Name:    .field_14_14   // getName->1:  null   // getName->2:  null   // getName->N:  null   // ofs = -1 ord = 0 addr = 14
	ifnull Label82
	aload_0_getfield .field_0_   // get_name_1:  .field_0_   // get_name_2:  .field_0_   // get_Name:    .field_0_   // getName->1:  null   // getName->2:  null   // getName->N:  null   // ofs = -1 ord = 0 addr = 0
	aload_0_getfield .field_14_14   // get_name_1:  .field_14_14   // get_name_2:  .field_14_14   // get_Name:    .field_14_14   // getName->1:  null   // getName->2:  null   // getName->N:  null   // ofs = -1 ord = 0 addr = 14
	putfield .field_10_10   // get_name_1:  .field_10_10   // get_name_2:  .field_10_10   // get_Name:    .field_10_10   // getName->1:  null   // getName->2:  null   // getName->N:  null   // ofs = -1 ord = 0 addr = 10
Label82:
	aload_0_getfield .field_15_15   // get_name_1:  .field_15_15   // get_name_2:  .field_15_15   // get_Name:    .field_15_15   // getName->1:  null   // getName->2:  null   // getName->N:  null   // ofs = -1 ord = 0 addr = 15
	ifnull Label87
	aload_0_getfield .field_0_   // get_name_1:  .field_0_   // get_name_2:  .field_0_   // get_Name:    .field_0_   // getName->1:  null   // getName->2:  null   // getName->N:  null   // ofs = -1 ord = 0 addr = 0
	aload_0_getfield .field_15_15   // get_name_1:  .field_15_15   // get_name_2:  .field_15_15   // get_Name:    .field_15_15   // getName->1:  null   // getName->2:  null   // getName->N:  null   // ofs = -1 ord = 0 addr = 15
	putfield .field_16_16   // get_name_1:  .field_16_16   // get_name_2:  .field_16_16   // get_Name:    .field_16_16   // getName->1:  null   // getName->2:  null   // getName->N:  null   // ofs = -1 ord = 0 addr = 16
Label87:
	aload_0_getfield .field_16_16   // get_name_1:  .field_16_16   // get_name_2:  .field_16_16   // get_Name:    .field_16_16   // getName->1:  null   // getName->2:  null   // getName->N:  null   // ofs = -1 ord = 0 addr = 16
	ifnull Label93
	aload_0_getfield .field_0_   // get_name_1:  .field_0_   // get_name_2:  .field_0_   // get_Name:    .field_0_   // getName->1:  null   // getName->2:  null   // getName->N:  null   // ofs = -1 ord = 0 addr = 0
	aload_0_getfield .field_16_16   // get_name_1:  .field_16_16   // get_name_2:  .field_16_16   // get_Name:    .field_16_16   // getName->1:  null   // getName->2:  null   // getName->N:  null   // ofs = -1 ord = 0 addr = 16
	invokevirtual double doubleValue( java.lang.Double ) // pc=1
	lputfield .field_17_17   // get_name_1:  .field_17_17   // get_name_2:  .field_17_17   // get_Name:    .field_17_17   // getName->1:  null   // getName->2:  null   // getName->N:  null   // ofs = -1 ord = 0 addr = 17
Label93:
	aload_0_getfield .field_17_17   // get_name_1:  .field_17_17   // get_name_2:  .field_17_17   // get_Name:    .field_17_17   // getName->1:  null   // getName->2:  null   // getName->N:  null   // ofs = -1 ord = 0 addr = 17
	ifnull Label99
	aload_0_getfield .field_0_   // get_name_1:  .field_0_   // get_name_2:  .field_0_   // get_Name:    .field_0_   // getName->1:  null   // getName->2:  null   // getName->N:  null   // ofs = -1 ord = 0 addr = 0
	aload_0_getfield .field_17_17   // get_name_1:  .field_17_17   // get_name_2:  .field_17_17   // get_Name:    .field_17_17   // getName->1:  null   // getName->2:  null   // getName->N:  null   // ofs = -1 ord = 0 addr = 17
	invokevirtual double doubleValue( java.lang.Double ) // pc=1
	lputfield .field_19_19   // get_name_1:  .field_19_19   // get_name_2:  .field_19_19   // get_Name:    .field_19_19   // getName->1:  null   // getName->2:  null   // getName->N:  null   // ofs = -1 ord = 0 addr = 19
Label99:
	aload_0_getfield .field_18_18   // get_name_1:  .field_18_18   // get_name_2:  .field_18_18   // get_Name:    .field_18_18   // getName->1:  null   // getName->2:  null   // getName->N:  null   // ofs = -1 ord = 0 addr = 18
	ifnull Label104
	aload_0_getfield .field_0_   // get_name_1:  .field_0_   // get_name_2:  .field_0_   // get_Name:    .field_0_   // getName->1:  null   // getName->2:  null   // getName->N:  null   // ofs = -1 ord = 0 addr = 0
	aload_0_getfield .field_18_18   // get_name_1:  .field_18_18   // get_name_2:  .field_18_18   // get_Name:    .field_18_18   // getName->1:  null   // getName->2:  null   // getName->N:  null   // ofs = -1 ord = 0 addr = 18
	putfield .field_21_21   // get_name_1:  .field_21_21   // get_name_2:  .field_21_21   // get_Name:    .field_21_21   // getName->1:  null   // getName->2:  null   // getName->N:  null   // ofs = -1 ord = 0 addr = 21
Label104:
	aload_0_getfield .field_0_   // get_name_1:  .field_0_   // get_name_2:  .field_0_   // get_Name:    .field_0_   // getName->1:  null   // getName->2:  null   // getName->N:  null   // ofs = -1 ord = 0 addr = 0
	areturn 
	}

}
