// #######################################################
// Decompiled by   : coddec 
// Module          : WhatsApp-7.cod
// Module version  : 2.7.3204
// Class ID        : 19
// ########################################################


package com.whatsapp.client;


abstract final class AuthVoiceScreen$7$1$1 extends Object
implements Runnable

{

	// @@@@@@@@@@@@@ Fields 
	private final net.rim.device.api.ui.text.TextFilter /*net.rim.device.api.ui.text.TextFilter*/  field_55512 ; // ofs = 55512 addr = 0)
	private final com.whatsapp.client.AuthVoiceScreen$7$1 /*com.whatsapp.client.AuthVoiceScreen$7$1*/  field_55516 ; // ofs = 55516 addr = 0)

	// @@@@@@@@@@@@@ Static routines 

<init>( com.whatsapp.client.AuthVoiceScreen$7$1$1, com.whatsapp.client.AuthVoiceScreen$7$1, net.rim.device.api.ui.text.TextFilter ); // address: 0
	{
	enter_narrow 
	aload_0 
	invokespecial_lib java.lang.Object.<init> // pc=1
	aload_0 
	aload_1 
	putfield .field_1_1   // get_name_1:  .field_1_1   // get_name_2:  .field_1_1   // get_Name:    .field_1_1   // getName->1:  null   // getName->2:  null   // getName->N:  null   // ofs = -1 ord = 0 addr = 1
	aload_0 
	aload_2 
	putfield .field_0_   // get_name_1:  .field_0_   // get_name_2:  .field_0_   // get_Name:    .field_0_   // getName->1:  null   // getName->2:  null   // getName->N:  null   // ofs = -1 ord = 0 addr = 0
	return 
	}

	// @@@@@@@@@@@@@ Virtual routines 

public final run( com.whatsapp.client.AuthVoiceScreen$7$1$1 ); // address: 0
	{
	enter_narrow 
	aload_0_getfield .field_1_1   // get_name_1:  .field_1_1   // get_name_2:  .field_1_1   // get_Name:    .field_1_1   // getName->1:  null   // getName->2:  null   // getName->N:  null   // ofs = -1 ord = 0 addr = 1
	getfield .field_1_1   // get_name_1:  .field_1_1   // get_name_2:  .field_1_1   // get_Name:    .field_1_1   // getName->1:  null   // getName->2:  null   // getName->N:  null   // ofs = -1 ord = 0 addr = 1
	getfield .field_1_1   // get_name_1:  .field_1_1   // get_name_2:  .field_1_1   // get_Name:    .field_1_1   // getName->1:  null   // getName->2:  null   // getName->N:  null   // ofs = -1 ord = 0 addr = 1
	getfield _codeEditField   // get_name_1:  _codeEditField   // get_name_2:  _codeEditField   // get_Name:    _codeEditField   // getName->1:  _codeEditField   // getName->2:  _codeEditField   // getName->N:  _codeEditField   // ofs = 54942 ord = 5 addr = 0
	getstatic_lib module:WhatsApp-12.class#0.static_156 // class#0
	invokevirtual setText( net.rim.device.api.ui.component.BasicEditField, java.lang.String ) // pc=2
	aload_0_getfield .field_1_1   // get_name_1:  .field_1_1   // get_name_2:  .field_1_1   // get_Name:    .field_1_1   // getName->1:  null   // getName->2:  null   // getName->N:  null   // ofs = -1 ord = 0 addr = 1
	getfield .field_1_1   // get_name_1:  .field_1_1   // get_name_2:  .field_1_1   // get_Name:    .field_1_1   // getName->1:  null   // getName->2:  null   // getName->N:  null   // ofs = -1 ord = 0 addr = 1
	getfield .field_1_1   // get_name_1:  .field_1_1   // get_name_2:  .field_1_1   // get_Name:    .field_1_1   // getName->1:  null   // getName->2:  null   // getName->N:  null   // ofs = -1 ord = 0 addr = 1
	getfield _codeEditField   // get_name_1:  _codeEditField   // get_name_2:  _codeEditField   // get_Name:    _codeEditField   // getName->1:  _codeEditField   // getName->2:  _codeEditField   // getName->N:  _codeEditField   // ofs = 54942 ord = 5 addr = 0
	bipush 3
	invokevirtual setMaxSize( net.rim.device.api.ui.component.BasicEditField, int ) // pc=2
	aload_0_getfield .field_1_1   // get_name_1:  .field_1_1   // get_name_2:  .field_1_1   // get_Name:    .field_1_1   // getName->1:  null   // getName->2:  null   // getName->N:  null   // ofs = -1 ord = 0 addr = 1
	getfield .field_1_1   // get_name_1:  .field_1_1   // get_name_2:  .field_1_1   // get_Name:    .field_1_1   // getName->1:  null   // getName->2:  null   // getName->N:  null   // ofs = -1 ord = 0 addr = 1
	getfield .field_1_1   // get_name_1:  .field_1_1   // get_name_2:  .field_1_1   // get_Name:    .field_1_1   // getName->1:  null   // getName->2:  null   // getName->N:  null   // ofs = -1 ord = 0 addr = 1
	getfield _codeEditField   // get_name_1:  _codeEditField   // get_name_2:  _codeEditField   // get_Name:    _codeEditField   // getName->1:  _codeEditField   // getName->2:  _codeEditField   // getName->N:  _codeEditField   // ofs = 54942 ord = 5 addr = 0
	aload_0_getfield .field_0_   // get_name_1:  .field_0_   // get_name_2:  .field_0_   // get_Name:    .field_0_   // getName->1:  null   // getName->2:  null   // getName->N:  null   // ofs = -1 ord = 0 addr = 0
	invokevirtual setFilter( net.rim.device.api.ui.component.BasicEditField, net.rim.device.api.ui.text.TextFilter ) // pc=2
	aload_0_getfield .field_1_1   // get_name_1:  .field_1_1   // get_name_2:  .field_1_1   // get_Name:    .field_1_1   // getName->1:  null   // getName->2:  null   // getName->N:  null   // ofs = -1 ord = 0 addr = 1
	getfield .field_1_1   // get_name_1:  .field_1_1   // get_name_2:  .field_1_1   // get_Name:    .field_1_1   // getName->1:  null   // getName->2:  null   // getName->N:  null   // ofs = -1 ord = 0 addr = 1
	getfield .field_1_1   // get_name_1:  .field_1_1   // get_name_2:  .field_1_1   // get_Name:    .field_1_1   // getName->1:  null   // getName->2:  null   // getName->N:  null   // ofs = -1 ord = 0 addr = 1
	invokespecial com.whatsapp.client.AuthVoiceScreen.showCallButton // pc=1
	aload_0_getfield .field_1_1   // get_name_1:  .field_1_1   // get_name_2:  .field_1_1   // get_Name:    .field_1_1   // getName->1:  null   // getName->2:  null   // getName->N:  null   // ofs = -1 ord = 0 addr = 1
	getfield .field_1_1   // get_name_1:  .field_1_1   // get_name_2:  .field_1_1   // get_Name:    .field_1_1   // getName->1:  null   // getName->2:  null   // getName->N:  null   // ofs = -1 ord = 0 addr = 1
	getfield .field_1_1   // get_name_1:  .field_1_1   // get_name_2:  .field_1_1   // get_Name:    .field_1_1   // getName->1:  null   // getName->2:  null   // getName->N:  null   // ofs = -1 ord = 0 addr = 1
	getfield _codeEditField   // get_name_1:  _codeEditField   // get_name_2:  _codeEditField   // get_Name:    _codeEditField   // getName->1:  _codeEditField   // getName->2:  _codeEditField   // getName->N:  _codeEditField   // ofs = 54942 ord = 5 addr = 0
	iconst_1 
	invokevirtual setEditable( net.rim.device.api.ui.Field, boolean ) // pc=2
	return 
	}

}
