// #######################################################
// Decompiled by   : coddec 
// Module          : WhatsApp-13.cod
// Module version  : 2.8.1914
// Class ID        : 1
// ########################################################


package com.whatsapp.client;


abstract public final class ChatableNumber$NameComparator extends Object
implements net.rim.device.api.util.Comparator

{

	// @@@@@@@@@@@@@ Fields 
	private com.whatsapp.client. /*module:WhatsApp-18.class#0*/  field_60352 ; // ofs = 60352 addr = 0)
	private java.util.Hashtable /*java.util.Hashtable*/  field_60356 ; // ofs = 60356 addr = 0)

	// @@@@@@@@@@@@@ Static routines 

public <init>( com.whatsapp.client.ChatableNumber$NameComparator ); // address: 0
	{
	enter_narrow 
	aload_0 
	invokespecial_lib java.lang.Object.<init> // pc=1
	aload_0 
	invokestatic_lib module:WhatsApp-18.class#0.routine_2419(  ) // class#0
	putfield .field_0_   // get_name_1:  .field_0_   // get_name_2:  .field_0_   // get_Name:    .field_0_   // getName->1:  null   // getName->2:  null   // getName->N:  null   // ofs = -1 ord = 0 addr = 0
	aload_0 
	new_lib java.util.Hashtable//java.util.Hashtable java.util.Hashtable java.util.Hashtable
	dup 
	invokespecial_lib java.util.Hashtable.<init> // pc=1
	putfield .field_1_1   // get_name_1:  .field_1_1   // get_name_2:  .field_1_1   // get_Name:    .field_1_1   // getName->1:  null   // getName->2:  null   // getName->N:  null   // ofs = -1 ord = 0 addr = 1
	return 
	}

	// @@@@@@@@@@@@@ Virtual routines 

public final int compare( com.whatsapp.client.ChatableNumber$NameComparator, java.lang.Object, java.lang.Object ); // address: 0
	{
	enter 
	aload_1 
	checkcast_lib com.whatsapp.client.ChatableNumber//module:WhatsApp-12.class#30 module:WhatsApp-12.class#30 module:WhatsApp-12.class#30
	getfield .field_0_   // get_name_1:  .field_0_   // get_name_2:  .field_0_   // get_Name:    .field_0_   // getName->1:  null   // getName->2:  null   // getName->N:  null   // ofs = -1 ord = 0 addr = 0
	astore_3 
	aload_2 
	checkcast_lib com.whatsapp.client.ChatableNumber//module:WhatsApp-12.class#30 module:WhatsApp-12.class#30 module:WhatsApp-12.class#30
	getfield .field_0_   // get_name_1:  .field_0_   // get_name_2:  .field_0_   // get_Name:    .field_0_   // getName->1:  null   // getName->2:  null   // getName->N:  null   // ofs = -1 ord = 0 addr = 0
	astore_4 
	aload_0_getfield .field_1_1   // get_name_1:  .field_1_1   // get_name_2:  .field_1_1   // get_Name:    .field_1_1   // getName->1:  null   // getName->2:  null   // getName->N:  null   // ofs = -1 ord = 0 addr = 1
	aload_3 
	invokevirtual java.lang.Object get( java.util.Hashtable, java.lang.Object ) // pc=2
	checkcast_lib String//java.lang.String java.lang.String java.lang.String
	astore_5 
	aload_5 
	ifnonnull Label26
	aload_3 
	aload_0_getfield .field_0_   // get_name_1:  .field_0_   // get_name_2:  .field_0_   // get_Name:    .field_0_   // getName->1:  null   // getName->2:  null   // getName->N:  null   // ofs = -1 ord = 0 addr = 0
	getfield .field_6_6   // get_name_1:  .field_6_6   // get_name_2:  .field_6_6   // get_Name:    .field_6_6   // getName->1:  null   // getName->2:  null   // getName->N:  null   // ofs = -1 ord = 0 addr = 6
	invokenonvirtual_lib .routine_8839 // pc=2
	astore_5 
	aload_0_getfield .field_1_1   // get_name_1:  .field_1_1   // get_name_2:  .field_1_1   // get_Name:    .field_1_1   // getName->1:  null   // getName->2:  null   // getName->N:  null   // ofs = -1 ord = 0 addr = 1
	aload_3 
	aload_5 
	invokevirtual java.lang.Object put( java.util.Hashtable, java.lang.Object, java.lang.Object ) // pc=3
	pop 
Label26:
	aload_0_getfield .field_1_1   // get_name_1:  .field_1_1   // get_name_2:  .field_1_1   // get_Name:    .field_1_1   // getName->1:  null   // getName->2:  null   // getName->N:  null   // ofs = -1 ord = 0 addr = 1
	aload_4 
	invokevirtual java.lang.Object get( java.util.Hashtable, java.lang.Object ) // pc=2
	checkcast_lib String//java.lang.String java.lang.String java.lang.String
	astore_6 
	aload_6 
	ifnonnull Label43
	aload_3 
	aload_0_getfield .field_0_   // get_name_1:  .field_0_   // get_name_2:  .field_0_   // get_Name:    .field_0_   // getName->1:  null   // getName->2:  null   // getName->N:  null   // ofs = -1 ord = 0 addr = 0
	getfield .field_6_6   // get_name_1:  .field_6_6   // get_name_2:  .field_6_6   // get_Name:    .field_6_6   // getName->1:  null   // getName->2:  null   // getName->N:  null   // ofs = -1 ord = 0 addr = 6
	invokenonvirtual_lib .routine_8839 // pc=2
	astore_6 
	aload_0_getfield .field_1_1   // get_name_1:  .field_1_1   // get_name_2:  .field_1_1   // get_Name:    .field_1_1   // getName->1:  null   // getName->2:  null   // getName->N:  null   // ofs = -1 ord = 0 addr = 1
	aload_4 
	aload_6 
	invokevirtual java.lang.Object put( java.util.Hashtable, java.lang.Object, java.lang.Object ) // pc=3
	pop 
Label43:
	aload_5 
	aload_6 
	invokestatic_lib int compareToIgnoreCase( java.lang.String, java.lang.String ) // StringUtilities
	ireturn 
	}

}
