// #######################################################
// Decompiled by   : coddec 
// Module          : WhatsApp-25.cod
// Module version  : 2.7.3204
// Class ID        : 7
// ########################################################


package com.whatsapp.client;


abstract final class NewChatScreen$27 extends Object
implements Runnable

{

	// @@@@@@@@@@@@@ Fields 
	private final java.util.Vector /*java.util.Vector*/  field_53568 ; // ofs = 53568 addr = 0)
	private final java.util.Vector /*java.util.Vector*/  field_53572 ; // ofs = 53572 addr = 0)
	private final Runnable /*java.lang.Runnable*/  field_53576 ; // ofs = 53576 addr = 0)
	private final boolean /*boolean*/  field_53580 ; // ofs = 53580 addr = 0)
	private final boolean /*boolean*/  field_53584 ; // ofs = 53584 addr = 0)
	private final com.whatsapp.client.NewChatScreen /*com.whatsapp.client.NewChatScreen*/  field_53588 ; // ofs = 53588 addr = 0)

	// @@@@@@@@@@@@@ Static routines 

<init>( com.whatsapp.client.NewChatScreen$27, com.whatsapp.client.NewChatScreen, java.util.Vector, java.util.Vector, java.lang.Runnable, boolean, boolean ); // address: 0
	{
	enter 
	aload_0 
	invokespecial_lib java.lang.Object.<init> // pc=1
	aload_0 
	aload_1 
	putfield .field_5_5   // get_name_1:  .field_5_5   // get_name_2:  .field_5_5   // get_Name:    .field_5_5   // getName->1:  null   // getName->2:  null   // getName->N:  null   // ofs = -1 ord = 0 addr = 5
	aload_0 
	aload_2 
	putfield .field_0_   // get_name_1:  .field_0_   // get_name_2:  .field_0_   // get_Name:    .field_0_   // getName->1:  null   // getName->2:  null   // getName->N:  null   // ofs = -1 ord = 0 addr = 0
	aload_0 
	aload_3 
	putfield .field_1_1   // get_name_1:  .field_1_1   // get_name_2:  .field_1_1   // get_Name:    .field_1_1   // getName->1:  null   // getName->2:  null   // getName->N:  null   // ofs = -1 ord = 0 addr = 1
	aload_0 
	aload_4 
	putfield .field_2_2   // get_name_1:  .field_2_2   // get_name_2:  .field_2_2   // get_Name:    .field_2_2   // getName->1:  null   // getName->2:  null   // getName->N:  null   // ofs = -1 ord = 0 addr = 2
	aload_0 
	iload_5 
	putfield .field_3_3   // get_name_1:  .field_3_3   // get_name_2:  .field_3_3   // get_Name:    .field_3_3   // getName->1:  null   // getName->2:  null   // getName->N:  null   // ofs = -1 ord = 0 addr = 3
	aload_0 
	iload_6 
	putfield .field_4_4   // get_name_1:  .field_4_4   // get_name_2:  .field_4_4   // get_Name:    .field_4_4   // getName->1:  null   // getName->2:  null   // getName->N:  null   // ofs = -1 ord = 0 addr = 4
	return 
	}

	// @@@@@@@@@@@@@ Virtual routines 

public final run( com.whatsapp.client.NewChatScreen$27 ); // address: 0
	{
	enter 
	aload_0_getfield .field_5_5   // get_name_1:  .field_5_5   // get_name_2:  .field_5_5   // get_Name:    .field_5_5   // getName->1:  null   // getName->2:  null   // getName->N:  null   // ofs = -1 ord = 0 addr = 5
	aload_0_getfield .field_0_   // get_name_1:  .field_0_   // get_name_2:  .field_0_   // get_Name:    .field_0_   // getName->1:  null   // getName->2:  null   // getName->N:  null   // ofs = -1 ord = 0 addr = 0
	aload_0_getfield .field_1_1   // get_name_1:  .field_1_1   // get_name_2:  .field_1_1   // get_Name:    .field_1_1   // getName->1:  null   // getName->2:  null   // getName->N:  null   // ofs = -1 ord = 0 addr = 1
	aload_0_getfield .field_2_2   // get_name_1:  .field_2_2   // get_name_2:  .field_2_2   // get_Name:    .field_2_2   // getName->1:  null   // getName->2:  null   // getName->N:  null   // ofs = -1 ord = 0 addr = 2
	aload_0_getfield .field_3_3   // get_name_1:  .field_3_3   // get_name_2:  .field_3_3   // get_Name:    .field_3_3   // getName->1:  null   // getName->2:  null   // getName->N:  null   // ofs = -1 ord = 0 addr = 3
	aload_0_getfield .field_4_4   // get_name_1:  .field_4_4   // get_name_2:  .field_4_4   // get_Name:    .field_4_4   // getName->1:  null   // getName->2:  null   // getName->N:  null   // ofs = -1 ord = 0 addr = 4
	invokespecial com.whatsapp.client.NewChatScreen.paintChatsInBatchFinalUI // pc=6
	return 
	}

}
