// #######################################################
// Decompiled by   : coddec 
// Module          : WhatsApp-25.cod
// Module version  : 2.7.3204
// Class ID        : 10
// ########################################################


package com.whatsapp.client;


abstract final class NewChatScreen$4 extends Object
implements Runnable

{

	// @@@@@@@@@@@@@ Fields 
	private final com.whatsapp.client.NewChatScreen /*com.whatsapp.client.NewChatScreen*/  field_53752 ; // ofs = 53752 addr = 0)

	// @@@@@@@@@@@@@ Static routines 

<init>( com.whatsapp.client.NewChatScreen$4, com.whatsapp.client.NewChatScreen ); // address: 0
	{
	enter_narrow 
	aload_0 
	invokespecial_lib java.lang.Object.<init> // pc=1
	aload_0 
	aload_1 
	putfield .field_0_   // get_name_1:  .field_0_   // get_name_2:  .field_0_   // get_Name:    .field_0_   // getName->1:  null   // getName->2:  null   // getName->N:  null   // ofs = -1 ord = 0 addr = 0
	return 
	}

	// @@@@@@@@@@@@@ Virtual routines 

public final run( com.whatsapp.client.NewChatScreen$4 ); // address: 0
	{
	enter 
	aload_0_getfield .field_0_   // get_name_1:  .field_0_   // get_name_2:  .field_0_   // get_Name:    .field_0_   // getName->1:  null   // getName->2:  null   // getName->N:  null   // ofs = -1 ord = 0 addr = 0
	invokespecial com.whatsapp.client.NewChatScreen.getFocusChatLine // pc=1
	getfield _fmsg   // get_name_1:  _fmsg   // get_name_2:  _fmsg   // get_Name:    _fmsg   // getName->1:  _fmsg   // getName->2:  _fmsg   // getName->N:  _fmsg   // ofs = -1 ord = 0 addr = -1
	getfield .field_2_2   // get_name_1:  .field_2_2   // get_name_2:  .field_2_2   // get_Name:    .field_2_2   // getName->1:  null   // getName->2:  null   // getName->N:  null   // ofs = -1 ord = 0 addr = 2
	astore_1 
	invokestatic_lib module:WhatsApp-13.class#5.routine_9622(  ) // class#5
	getfield .field_1_1   // get_name_1:  .field_1_1   // get_name_2:  .field_1_1   // get_Name:    .field_1_1   // getName->1:  null   // getName->2:  null   // getName->N:  null   // ofs = -1 ord = 0 addr = 1
	aload_1 
	invokevirtual java.lang.Object get( java.util.Hashtable, java.lang.Object ) // pc=2
	checkcast_lib //module:WhatsApp-13.class#4 module:WhatsApp-13.class#4 module:WhatsApp-13.class#4
	astore_2 
	aload_2 
	ifnull Label38
	invokestatic_lib net.rim.device.api.system.RuntimeStore getRuntimeStore(  ) // RuntimeStore
	lipush 8535665252065932813
	invokevirtual java.lang.Object get( net.rim.device.api.system.RuntimeStore, long ) // pc=3
	checkcast_lib //module:WhatsApp-13.class#1 module:WhatsApp-13.class#1 module:WhatsApp-13.class#1
	astore_3 
	aload_3 
	getfield .field_3_3   // get_name_1:  .field_3_3   // get_name_2:  .field_3_3   // get_Name:    .field_3_3   // getName->1:  null   // getName->2:  null   // getName->N:  null   // ofs = -1 ord = 0 addr = 3
	aload_2 
	getfield .field_4_4   // get_name_1:  .field_4_4   // get_name_2:  .field_4_4   // get_Name:    .field_4_4   // getName->1:  null   // getName->2:  null   // getName->N:  null   // ofs = -1 ord = 0 addr = 4
	invokevirtual java.lang.Object get( java.util.Hashtable, java.lang.Object ) // pc=2
	checkcast_lib com.whatsapp.client.ContactInfoDetails//module:WhatsApp.class#11 module:WhatsApp.class#11 module:WhatsApp.class#11
	astore_4 
	aload_4 
	ifnull Label38
	new_lib //module:WhatsApp-13.class#0 module:WhatsApp-13.class#0 module:WhatsApp-13.class#0
	dup 
	aload_4 
	invokespecial_lib .routine_3417 // pc=2
	astore_5 
	invokestatic_lib com.whatsapp.client.UiApp.routine_6246(  ) // UiApp
	astore_6 
	aload_6 
	aload_5 
	invokevirtual pushScreen( net.rim.device.api.ui.UiApplication, net.rim.device.api.ui.Screen ) // pc=2
Label38:
	return 
	}

}
