import android.provider.ContactsContract.CommonDataKinds.Email;
import android.provider.ContactsContract.CommonDataKinds.Phone;
import android.provider.ContactsContract.CommonDataKinds.StructuredPostal;
import com.whatsapp.App;
import com.whatsapp.g5;
import com.whatsapp.jp;
import java.io.IOException;
import java.util.HashMap;
import java.util.HashSet;
import java.util.Iterator;
import java.util.List;
import java.util.Map;
import java.util.Set;

public class m
{
  private static final HashSet<String> d;
  private static final HashSet<String> e;
  private static final String[] z;
  private String a;
  private StringBuilder b;
  private int c = 0;

  // ERROR //
  static
  {
    // Byte code:
    //   0: bipush 64
    //   2: anewarray 20	java/lang/String
    //   5: astore_0
    //   6: ldc 22
    //   8: invokevirtual 26	java/lang/String:toCharArray	()[C
    //   11: astore_1
    //   12: aload_1
    //   13: arraylength
    //   14: istore_2
    //   15: iconst_0
    //   16: istore_3
    //   17: iload_2
    //   18: iload_3
    //   19: if_icmpgt +2971 -> 2990
    //   22: aload_0
    //   23: iconst_0
    //   24: new 20	java/lang/String
    //   27: dup
    //   28: aload_1
    //   29: invokespecial 30	java/lang/String:<init>	([C)V
    //   32: invokevirtual 34	java/lang/String:intern	()Ljava/lang/String;
    //   35: aastore
    //   36: ldc 36
    //   38: invokevirtual 26	java/lang/String:toCharArray	()[C
    //   41: astore 6
    //   43: aload 6
    //   45: arraylength
    //   46: istore 7
    //   48: iconst_0
    //   49: istore 8
    //   51: iload 7
    //   53: iload 8
    //   55: if_icmpgt +3020 -> 3075
    //   58: aload_0
    //   59: iconst_1
    //   60: new 20	java/lang/String
    //   63: dup
    //   64: aload 6
    //   66: invokespecial 30	java/lang/String:<init>	([C)V
    //   69: invokevirtual 34	java/lang/String:intern	()Ljava/lang/String;
    //   72: aastore
    //   73: ldc 38
    //   75: invokevirtual 26	java/lang/String:toCharArray	()[C
    //   78: astore 11
    //   80: aload 11
    //   82: arraylength
    //   83: istore 12
    //   85: iconst_0
    //   86: istore 13
    //   88: iload 12
    //   90: iload 13
    //   92: if_icmpgt +3073 -> 3165
    //   95: aload_0
    //   96: iconst_2
    //   97: new 20	java/lang/String
    //   100: dup
    //   101: aload 11
    //   103: invokespecial 30	java/lang/String:<init>	([C)V
    //   106: invokevirtual 34	java/lang/String:intern	()Ljava/lang/String;
    //   109: aastore
    //   110: ldc 40
    //   112: invokevirtual 26	java/lang/String:toCharArray	()[C
    //   115: astore 16
    //   117: aload 16
    //   119: arraylength
    //   120: istore 17
    //   122: iconst_0
    //   123: istore 18
    //   125: iload 17
    //   127: iload 18
    //   129: if_icmpgt +3128 -> 3257
    //   132: aload_0
    //   133: iconst_3
    //   134: new 20	java/lang/String
    //   137: dup
    //   138: aload 16
    //   140: invokespecial 30	java/lang/String:<init>	([C)V
    //   143: invokevirtual 34	java/lang/String:intern	()Ljava/lang/String;
    //   146: aastore
    //   147: ldc 42
    //   149: invokevirtual 26	java/lang/String:toCharArray	()[C
    //   152: astore 21
    //   154: aload 21
    //   156: arraylength
    //   157: istore 22
    //   159: iconst_0
    //   160: istore 23
    //   162: iload 22
    //   164: iload 23
    //   166: if_icmpgt +3183 -> 3349
    //   169: aload_0
    //   170: iconst_4
    //   171: new 20	java/lang/String
    //   174: dup
    //   175: aload 21
    //   177: invokespecial 30	java/lang/String:<init>	([C)V
    //   180: invokevirtual 34	java/lang/String:intern	()Ljava/lang/String;
    //   183: aastore
    //   184: ldc 44
    //   186: invokevirtual 26	java/lang/String:toCharArray	()[C
    //   189: astore 26
    //   191: aload 26
    //   193: arraylength
    //   194: istore 27
    //   196: iconst_0
    //   197: istore 28
    //   199: iload 27
    //   201: iload 28
    //   203: if_icmpgt +3238 -> 3441
    //   206: aload_0
    //   207: iconst_5
    //   208: new 20	java/lang/String
    //   211: dup
    //   212: aload 26
    //   214: invokespecial 30	java/lang/String:<init>	([C)V
    //   217: invokevirtual 34	java/lang/String:intern	()Ljava/lang/String;
    //   220: aastore
    //   221: ldc 46
    //   223: invokevirtual 26	java/lang/String:toCharArray	()[C
    //   226: astore 31
    //   228: aload 31
    //   230: arraylength
    //   231: istore 32
    //   233: iconst_0
    //   234: istore 33
    //   236: iload 32
    //   238: iload 33
    //   240: if_icmpgt +3293 -> 3533
    //   243: aload_0
    //   244: bipush 6
    //   246: new 20	java/lang/String
    //   249: dup
    //   250: aload 31
    //   252: invokespecial 30	java/lang/String:<init>	([C)V
    //   255: invokevirtual 34	java/lang/String:intern	()Ljava/lang/String;
    //   258: aastore
    //   259: ldc 48
    //   261: invokevirtual 26	java/lang/String:toCharArray	()[C
    //   264: astore 36
    //   266: aload 36
    //   268: arraylength
    //   269: istore 37
    //   271: iconst_0
    //   272: istore 38
    //   274: iload 37
    //   276: iload 38
    //   278: if_icmpgt +3347 -> 3625
    //   281: aload_0
    //   282: bipush 7
    //   284: new 20	java/lang/String
    //   287: dup
    //   288: aload 36
    //   290: invokespecial 30	java/lang/String:<init>	([C)V
    //   293: invokevirtual 34	java/lang/String:intern	()Ljava/lang/String;
    //   296: aastore
    //   297: ldc 50
    //   299: invokevirtual 26	java/lang/String:toCharArray	()[C
    //   302: astore 41
    //   304: aload 41
    //   306: arraylength
    //   307: istore 42
    //   309: iconst_0
    //   310: istore 43
    //   312: iload 42
    //   314: iload 43
    //   316: if_icmpgt +3401 -> 3717
    //   319: aload_0
    //   320: bipush 8
    //   322: new 20	java/lang/String
    //   325: dup
    //   326: aload 41
    //   328: invokespecial 30	java/lang/String:<init>	([C)V
    //   331: invokevirtual 34	java/lang/String:intern	()Ljava/lang/String;
    //   334: aastore
    //   335: ldc 52
    //   337: invokevirtual 26	java/lang/String:toCharArray	()[C
    //   340: astore 46
    //   342: aload 46
    //   344: arraylength
    //   345: istore 47
    //   347: iconst_0
    //   348: istore 48
    //   350: iload 47
    //   352: iload 48
    //   354: if_icmpgt +3455 -> 3809
    //   357: aload_0
    //   358: bipush 9
    //   360: new 20	java/lang/String
    //   363: dup
    //   364: aload 46
    //   366: invokespecial 30	java/lang/String:<init>	([C)V
    //   369: invokevirtual 34	java/lang/String:intern	()Ljava/lang/String;
    //   372: aastore
    //   373: ldc 54
    //   375: invokevirtual 26	java/lang/String:toCharArray	()[C
    //   378: astore 51
    //   380: aload 51
    //   382: arraylength
    //   383: istore 52
    //   385: iconst_0
    //   386: istore 53
    //   388: iload 52
    //   390: iload 53
    //   392: if_icmpgt +3509 -> 3901
    //   395: aload_0
    //   396: bipush 10
    //   398: new 20	java/lang/String
    //   401: dup
    //   402: aload 51
    //   404: invokespecial 30	java/lang/String:<init>	([C)V
    //   407: invokevirtual 34	java/lang/String:intern	()Ljava/lang/String;
    //   410: aastore
    //   411: ldc 56
    //   413: invokevirtual 26	java/lang/String:toCharArray	()[C
    //   416: astore 56
    //   418: aload 56
    //   420: arraylength
    //   421: istore 57
    //   423: iconst_0
    //   424: istore 58
    //   426: iload 57
    //   428: iload 58
    //   430: if_icmpgt +3563 -> 3993
    //   433: aload_0
    //   434: bipush 11
    //   436: new 20	java/lang/String
    //   439: dup
    //   440: aload 56
    //   442: invokespecial 30	java/lang/String:<init>	([C)V
    //   445: invokevirtual 34	java/lang/String:intern	()Ljava/lang/String;
    //   448: aastore
    //   449: ldc 58
    //   451: invokevirtual 26	java/lang/String:toCharArray	()[C
    //   454: astore 61
    //   456: aload 61
    //   458: arraylength
    //   459: istore 62
    //   461: iconst_0
    //   462: istore 63
    //   464: iload 62
    //   466: iload 63
    //   468: if_icmpgt +3617 -> 4085
    //   471: aload_0
    //   472: bipush 12
    //   474: new 20	java/lang/String
    //   477: dup
    //   478: aload 61
    //   480: invokespecial 30	java/lang/String:<init>	([C)V
    //   483: invokevirtual 34	java/lang/String:intern	()Ljava/lang/String;
    //   486: aastore
    //   487: ldc 60
    //   489: invokevirtual 26	java/lang/String:toCharArray	()[C
    //   492: astore 66
    //   494: aload 66
    //   496: arraylength
    //   497: istore 67
    //   499: iconst_0
    //   500: istore 68
    //   502: iload 67
    //   504: iload 68
    //   506: if_icmpgt +3671 -> 4177
    //   509: aload_0
    //   510: bipush 13
    //   512: new 20	java/lang/String
    //   515: dup
    //   516: aload 66
    //   518: invokespecial 30	java/lang/String:<init>	([C)V
    //   521: invokevirtual 34	java/lang/String:intern	()Ljava/lang/String;
    //   524: aastore
    //   525: ldc 62
    //   527: invokevirtual 26	java/lang/String:toCharArray	()[C
    //   530: astore 71
    //   532: aload 71
    //   534: arraylength
    //   535: istore 72
    //   537: iconst_0
    //   538: istore 73
    //   540: iload 72
    //   542: iload 73
    //   544: if_icmpgt +3725 -> 4269
    //   547: aload_0
    //   548: bipush 14
    //   550: new 20	java/lang/String
    //   553: dup
    //   554: aload 71
    //   556: invokespecial 30	java/lang/String:<init>	([C)V
    //   559: invokevirtual 34	java/lang/String:intern	()Ljava/lang/String;
    //   562: aastore
    //   563: ldc 64
    //   565: invokevirtual 26	java/lang/String:toCharArray	()[C
    //   568: astore 76
    //   570: aload 76
    //   572: arraylength
    //   573: istore 77
    //   575: iconst_0
    //   576: istore 78
    //   578: iload 77
    //   580: iload 78
    //   582: if_icmpgt +3779 -> 4361
    //   585: aload_0
    //   586: bipush 15
    //   588: new 20	java/lang/String
    //   591: dup
    //   592: aload 76
    //   594: invokespecial 30	java/lang/String:<init>	([C)V
    //   597: invokevirtual 34	java/lang/String:intern	()Ljava/lang/String;
    //   600: aastore
    //   601: ldc 66
    //   603: invokevirtual 26	java/lang/String:toCharArray	()[C
    //   606: astore 81
    //   608: aload 81
    //   610: arraylength
    //   611: istore 82
    //   613: iconst_0
    //   614: istore 83
    //   616: iload 82
    //   618: iload 83
    //   620: if_icmpgt +3833 -> 4453
    //   623: aload_0
    //   624: bipush 16
    //   626: new 20	java/lang/String
    //   629: dup
    //   630: aload 81
    //   632: invokespecial 30	java/lang/String:<init>	([C)V
    //   635: invokevirtual 34	java/lang/String:intern	()Ljava/lang/String;
    //   638: aastore
    //   639: ldc 68
    //   641: invokevirtual 26	java/lang/String:toCharArray	()[C
    //   644: astore 86
    //   646: aload 86
    //   648: arraylength
    //   649: istore 87
    //   651: iconst_0
    //   652: istore 88
    //   654: iload 87
    //   656: iload 88
    //   658: if_icmpgt +3887 -> 4545
    //   661: aload_0
    //   662: bipush 17
    //   664: new 20	java/lang/String
    //   667: dup
    //   668: aload 86
    //   670: invokespecial 30	java/lang/String:<init>	([C)V
    //   673: invokevirtual 34	java/lang/String:intern	()Ljava/lang/String;
    //   676: aastore
    //   677: ldc 70
    //   679: invokevirtual 26	java/lang/String:toCharArray	()[C
    //   682: astore 91
    //   684: aload 91
    //   686: arraylength
    //   687: istore 92
    //   689: iconst_0
    //   690: istore 93
    //   692: iload 92
    //   694: iload 93
    //   696: if_icmpgt +3941 -> 4637
    //   699: aload_0
    //   700: bipush 18
    //   702: new 20	java/lang/String
    //   705: dup
    //   706: aload 91
    //   708: invokespecial 30	java/lang/String:<init>	([C)V
    //   711: invokevirtual 34	java/lang/String:intern	()Ljava/lang/String;
    //   714: aastore
    //   715: ldc 72
    //   717: invokevirtual 26	java/lang/String:toCharArray	()[C
    //   720: astore 96
    //   722: aload 96
    //   724: arraylength
    //   725: istore 97
    //   727: iconst_0
    //   728: istore 98
    //   730: iload 97
    //   732: iload 98
    //   734: if_icmpgt +3995 -> 4729
    //   737: aload_0
    //   738: bipush 19
    //   740: new 20	java/lang/String
    //   743: dup
    //   744: aload 96
    //   746: invokespecial 30	java/lang/String:<init>	([C)V
    //   749: invokevirtual 34	java/lang/String:intern	()Ljava/lang/String;
    //   752: aastore
    //   753: ldc 74
    //   755: invokevirtual 26	java/lang/String:toCharArray	()[C
    //   758: astore 101
    //   760: aload 101
    //   762: arraylength
    //   763: istore 102
    //   765: iconst_0
    //   766: istore 103
    //   768: iload 102
    //   770: iload 103
    //   772: if_icmpgt +4049 -> 4821
    //   775: aload_0
    //   776: bipush 20
    //   778: new 20	java/lang/String
    //   781: dup
    //   782: aload 101
    //   784: invokespecial 30	java/lang/String:<init>	([C)V
    //   787: invokevirtual 34	java/lang/String:intern	()Ljava/lang/String;
    //   790: aastore
    //   791: ldc 76
    //   793: invokevirtual 26	java/lang/String:toCharArray	()[C
    //   796: astore 106
    //   798: aload 106
    //   800: arraylength
    //   801: istore 107
    //   803: iconst_0
    //   804: istore 108
    //   806: iload 107
    //   808: iload 108
    //   810: if_icmpgt +4103 -> 4913
    //   813: aload_0
    //   814: bipush 21
    //   816: new 20	java/lang/String
    //   819: dup
    //   820: aload 106
    //   822: invokespecial 30	java/lang/String:<init>	([C)V
    //   825: invokevirtual 34	java/lang/String:intern	()Ljava/lang/String;
    //   828: aastore
    //   829: ldc 78
    //   831: invokevirtual 26	java/lang/String:toCharArray	()[C
    //   834: astore 111
    //   836: aload 111
    //   838: arraylength
    //   839: istore 112
    //   841: iconst_0
    //   842: istore 113
    //   844: iload 112
    //   846: iload 113
    //   848: if_icmpgt +4157 -> 5005
    //   851: aload_0
    //   852: bipush 22
    //   854: new 20	java/lang/String
    //   857: dup
    //   858: aload 111
    //   860: invokespecial 30	java/lang/String:<init>	([C)V
    //   863: invokevirtual 34	java/lang/String:intern	()Ljava/lang/String;
    //   866: aastore
    //   867: ldc 80
    //   869: invokevirtual 26	java/lang/String:toCharArray	()[C
    //   872: astore 116
    //   874: aload 116
    //   876: arraylength
    //   877: istore 117
    //   879: iconst_0
    //   880: istore 118
    //   882: iload 117
    //   884: iload 118
    //   886: if_icmpgt +4211 -> 5097
    //   889: aload_0
    //   890: bipush 23
    //   892: new 20	java/lang/String
    //   895: dup
    //   896: aload 116
    //   898: invokespecial 30	java/lang/String:<init>	([C)V
    //   901: invokevirtual 34	java/lang/String:intern	()Ljava/lang/String;
    //   904: aastore
    //   905: ldc 82
    //   907: invokevirtual 26	java/lang/String:toCharArray	()[C
    //   910: astore 121
    //   912: aload 121
    //   914: arraylength
    //   915: istore 122
    //   917: iconst_0
    //   918: istore 123
    //   920: iload 122
    //   922: iload 123
    //   924: if_icmpgt +4265 -> 5189
    //   927: aload_0
    //   928: bipush 24
    //   930: new 20	java/lang/String
    //   933: dup
    //   934: aload 121
    //   936: invokespecial 30	java/lang/String:<init>	([C)V
    //   939: invokevirtual 34	java/lang/String:intern	()Ljava/lang/String;
    //   942: aastore
    //   943: ldc 84
    //   945: invokevirtual 26	java/lang/String:toCharArray	()[C
    //   948: astore 126
    //   950: aload 126
    //   952: arraylength
    //   953: istore 127
    //   955: iconst_0
    //   956: istore 128
    //   958: iload 127
    //   960: iload 128
    //   962: if_icmpgt +4319 -> 5281
    //   965: aload_0
    //   966: bipush 25
    //   968: new 20	java/lang/String
    //   971: dup
    //   972: aload 126
    //   974: invokespecial 30	java/lang/String:<init>	([C)V
    //   977: invokevirtual 34	java/lang/String:intern	()Ljava/lang/String;
    //   980: aastore
    //   981: ldc 86
    //   983: invokevirtual 26	java/lang/String:toCharArray	()[C
    //   986: astore 131
    //   988: aload 131
    //   990: arraylength
    //   991: istore 132
    //   993: iconst_0
    //   994: istore 133
    //   996: iload 132
    //   998: iload 133
    //   1000: if_icmpgt +4373 -> 5373
    //   1003: aload_0
    //   1004: bipush 26
    //   1006: new 20	java/lang/String
    //   1009: dup
    //   1010: aload 131
    //   1012: invokespecial 30	java/lang/String:<init>	([C)V
    //   1015: invokevirtual 34	java/lang/String:intern	()Ljava/lang/String;
    //   1018: aastore
    //   1019: ldc 88
    //   1021: invokevirtual 26	java/lang/String:toCharArray	()[C
    //   1024: astore 136
    //   1026: aload 136
    //   1028: arraylength
    //   1029: istore 137
    //   1031: iconst_0
    //   1032: istore 138
    //   1034: iload 137
    //   1036: iload 138
    //   1038: if_icmpgt +4427 -> 5465
    //   1041: aload_0
    //   1042: bipush 27
    //   1044: new 20	java/lang/String
    //   1047: dup
    //   1048: aload 136
    //   1050: invokespecial 30	java/lang/String:<init>	([C)V
    //   1053: invokevirtual 34	java/lang/String:intern	()Ljava/lang/String;
    //   1056: aastore
    //   1057: ldc 90
    //   1059: invokevirtual 26	java/lang/String:toCharArray	()[C
    //   1062: astore 141
    //   1064: aload 141
    //   1066: arraylength
    //   1067: istore 142
    //   1069: iconst_0
    //   1070: istore 143
    //   1072: iload 142
    //   1074: iload 143
    //   1076: if_icmpgt +4481 -> 5557
    //   1079: aload_0
    //   1080: bipush 28
    //   1082: new 20	java/lang/String
    //   1085: dup
    //   1086: aload 141
    //   1088: invokespecial 30	java/lang/String:<init>	([C)V
    //   1091: invokevirtual 34	java/lang/String:intern	()Ljava/lang/String;
    //   1094: aastore
    //   1095: ldc 92
    //   1097: invokevirtual 26	java/lang/String:toCharArray	()[C
    //   1100: astore 146
    //   1102: aload 146
    //   1104: arraylength
    //   1105: istore 147
    //   1107: iconst_0
    //   1108: istore 148
    //   1110: iload 147
    //   1112: iload 148
    //   1114: if_icmpgt +4535 -> 5649
    //   1117: aload_0
    //   1118: bipush 29
    //   1120: new 20	java/lang/String
    //   1123: dup
    //   1124: aload 146
    //   1126: invokespecial 30	java/lang/String:<init>	([C)V
    //   1129: invokevirtual 34	java/lang/String:intern	()Ljava/lang/String;
    //   1132: aastore
    //   1133: ldc 94
    //   1135: invokevirtual 26	java/lang/String:toCharArray	()[C
    //   1138: astore 151
    //   1140: aload 151
    //   1142: arraylength
    //   1143: istore 152
    //   1145: iconst_0
    //   1146: istore 153
    //   1148: iload 152
    //   1150: iload 153
    //   1152: if_icmpgt +4589 -> 5741
    //   1155: aload_0
    //   1156: bipush 30
    //   1158: new 20	java/lang/String
    //   1161: dup
    //   1162: aload 151
    //   1164: invokespecial 30	java/lang/String:<init>	([C)V
    //   1167: invokevirtual 34	java/lang/String:intern	()Ljava/lang/String;
    //   1170: aastore
    //   1171: ldc 96
    //   1173: invokevirtual 26	java/lang/String:toCharArray	()[C
    //   1176: astore 156
    //   1178: aload 156
    //   1180: arraylength
    //   1181: istore 157
    //   1183: iconst_0
    //   1184: istore 158
    //   1186: iload 157
    //   1188: iload 158
    //   1190: if_icmpgt +4643 -> 5833
    //   1193: aload_0
    //   1194: bipush 31
    //   1196: new 20	java/lang/String
    //   1199: dup
    //   1200: aload 156
    //   1202: invokespecial 30	java/lang/String:<init>	([C)V
    //   1205: invokevirtual 34	java/lang/String:intern	()Ljava/lang/String;
    //   1208: aastore
    //   1209: ldc 98
    //   1211: invokevirtual 26	java/lang/String:toCharArray	()[C
    //   1214: astore 161
    //   1216: aload 161
    //   1218: arraylength
    //   1219: istore 162
    //   1221: iconst_0
    //   1222: istore 163
    //   1224: iload 162
    //   1226: iload 163
    //   1228: if_icmpgt +4697 -> 5925
    //   1231: aload_0
    //   1232: bipush 32
    //   1234: new 20	java/lang/String
    //   1237: dup
    //   1238: aload 161
    //   1240: invokespecial 30	java/lang/String:<init>	([C)V
    //   1243: invokevirtual 34	java/lang/String:intern	()Ljava/lang/String;
    //   1246: aastore
    //   1247: ldc 100
    //   1249: invokevirtual 26	java/lang/String:toCharArray	()[C
    //   1252: astore 166
    //   1254: aload 166
    //   1256: arraylength
    //   1257: istore 167
    //   1259: iconst_0
    //   1260: istore 168
    //   1262: iload 167
    //   1264: iload 168
    //   1266: if_icmpgt +4751 -> 6017
    //   1269: aload_0
    //   1270: bipush 33
    //   1272: new 20	java/lang/String
    //   1275: dup
    //   1276: aload 166
    //   1278: invokespecial 30	java/lang/String:<init>	([C)V
    //   1281: invokevirtual 34	java/lang/String:intern	()Ljava/lang/String;
    //   1284: aastore
    //   1285: ldc 102
    //   1287: invokevirtual 26	java/lang/String:toCharArray	()[C
    //   1290: astore 171
    //   1292: aload 171
    //   1294: arraylength
    //   1295: istore 172
    //   1297: iconst_0
    //   1298: istore 173
    //   1300: iload 172
    //   1302: iload 173
    //   1304: if_icmpgt +4805 -> 6109
    //   1307: aload_0
    //   1308: bipush 34
    //   1310: new 20	java/lang/String
    //   1313: dup
    //   1314: aload 171
    //   1316: invokespecial 30	java/lang/String:<init>	([C)V
    //   1319: invokevirtual 34	java/lang/String:intern	()Ljava/lang/String;
    //   1322: aastore
    //   1323: ldc 104
    //   1325: invokevirtual 26	java/lang/String:toCharArray	()[C
    //   1328: astore 176
    //   1330: aload 176
    //   1332: arraylength
    //   1333: istore 177
    //   1335: iconst_0
    //   1336: istore 178
    //   1338: iload 177
    //   1340: iload 178
    //   1342: if_icmpgt +4859 -> 6201
    //   1345: aload_0
    //   1346: bipush 35
    //   1348: new 20	java/lang/String
    //   1351: dup
    //   1352: aload 176
    //   1354: invokespecial 30	java/lang/String:<init>	([C)V
    //   1357: invokevirtual 34	java/lang/String:intern	()Ljava/lang/String;
    //   1360: aastore
    //   1361: ldc 106
    //   1363: invokevirtual 26	java/lang/String:toCharArray	()[C
    //   1366: astore 181
    //   1368: aload 181
    //   1370: arraylength
    //   1371: istore 182
    //   1373: iconst_0
    //   1374: istore 183
    //   1376: iload 182
    //   1378: iload 183
    //   1380: if_icmpgt +4913 -> 6293
    //   1383: aload_0
    //   1384: bipush 36
    //   1386: new 20	java/lang/String
    //   1389: dup
    //   1390: aload 181
    //   1392: invokespecial 30	java/lang/String:<init>	([C)V
    //   1395: invokevirtual 34	java/lang/String:intern	()Ljava/lang/String;
    //   1398: aastore
    //   1399: ldc 108
    //   1401: invokevirtual 26	java/lang/String:toCharArray	()[C
    //   1404: astore 186
    //   1406: aload 186
    //   1408: arraylength
    //   1409: istore 187
    //   1411: iconst_0
    //   1412: istore 188
    //   1414: iload 187
    //   1416: iload 188
    //   1418: if_icmpgt +4967 -> 6385
    //   1421: aload_0
    //   1422: bipush 37
    //   1424: new 20	java/lang/String
    //   1427: dup
    //   1428: aload 186
    //   1430: invokespecial 30	java/lang/String:<init>	([C)V
    //   1433: invokevirtual 34	java/lang/String:intern	()Ljava/lang/String;
    //   1436: aastore
    //   1437: ldc 110
    //   1439: invokevirtual 26	java/lang/String:toCharArray	()[C
    //   1442: astore 191
    //   1444: aload 191
    //   1446: arraylength
    //   1447: istore 192
    //   1449: iconst_0
    //   1450: istore 193
    //   1452: iload 192
    //   1454: iload 193
    //   1456: if_icmpgt +5021 -> 6477
    //   1459: aload_0
    //   1460: bipush 38
    //   1462: new 20	java/lang/String
    //   1465: dup
    //   1466: aload 191
    //   1468: invokespecial 30	java/lang/String:<init>	([C)V
    //   1471: invokevirtual 34	java/lang/String:intern	()Ljava/lang/String;
    //   1474: aastore
    //   1475: ldc 112
    //   1477: invokevirtual 26	java/lang/String:toCharArray	()[C
    //   1480: astore 196
    //   1482: aload 196
    //   1484: arraylength
    //   1485: istore 197
    //   1487: iconst_0
    //   1488: istore 198
    //   1490: iload 197
    //   1492: iload 198
    //   1494: if_icmpgt +5075 -> 6569
    //   1497: aload_0
    //   1498: bipush 39
    //   1500: new 20	java/lang/String
    //   1503: dup
    //   1504: aload 196
    //   1506: invokespecial 30	java/lang/String:<init>	([C)V
    //   1509: invokevirtual 34	java/lang/String:intern	()Ljava/lang/String;
    //   1512: aastore
    //   1513: ldc 114
    //   1515: invokevirtual 26	java/lang/String:toCharArray	()[C
    //   1518: astore 201
    //   1520: aload 201
    //   1522: arraylength
    //   1523: istore 202
    //   1525: iconst_0
    //   1526: istore 203
    //   1528: iload 202
    //   1530: iload 203
    //   1532: if_icmpgt +5129 -> 6661
    //   1535: aload_0
    //   1536: bipush 40
    //   1538: new 20	java/lang/String
    //   1541: dup
    //   1542: aload 201
    //   1544: invokespecial 30	java/lang/String:<init>	([C)V
    //   1547: invokevirtual 34	java/lang/String:intern	()Ljava/lang/String;
    //   1550: aastore
    //   1551: ldc 116
    //   1553: invokevirtual 26	java/lang/String:toCharArray	()[C
    //   1556: astore 206
    //   1558: aload 206
    //   1560: arraylength
    //   1561: istore 207
    //   1563: iconst_0
    //   1564: istore 208
    //   1566: iload 207
    //   1568: iload 208
    //   1570: if_icmpgt +5183 -> 6753
    //   1573: aload_0
    //   1574: bipush 41
    //   1576: new 20	java/lang/String
    //   1579: dup
    //   1580: aload 206
    //   1582: invokespecial 30	java/lang/String:<init>	([C)V
    //   1585: invokevirtual 34	java/lang/String:intern	()Ljava/lang/String;
    //   1588: aastore
    //   1589: ldc 118
    //   1591: invokevirtual 26	java/lang/String:toCharArray	()[C
    //   1594: astore 211
    //   1596: aload 211
    //   1598: arraylength
    //   1599: istore 212
    //   1601: iconst_0
    //   1602: istore 213
    //   1604: iload 212
    //   1606: iload 213
    //   1608: if_icmpgt +5237 -> 6845
    //   1611: aload_0
    //   1612: bipush 42
    //   1614: new 20	java/lang/String
    //   1617: dup
    //   1618: aload 211
    //   1620: invokespecial 30	java/lang/String:<init>	([C)V
    //   1623: invokevirtual 34	java/lang/String:intern	()Ljava/lang/String;
    //   1626: aastore
    //   1627: ldc 120
    //   1629: invokevirtual 26	java/lang/String:toCharArray	()[C
    //   1632: astore 216
    //   1634: aload 216
    //   1636: arraylength
    //   1637: istore 217
    //   1639: iconst_0
    //   1640: istore 218
    //   1642: iload 217
    //   1644: iload 218
    //   1646: if_icmpgt +5291 -> 6937
    //   1649: aload_0
    //   1650: bipush 43
    //   1652: new 20	java/lang/String
    //   1655: dup
    //   1656: aload 216
    //   1658: invokespecial 30	java/lang/String:<init>	([C)V
    //   1661: invokevirtual 34	java/lang/String:intern	()Ljava/lang/String;
    //   1664: aastore
    //   1665: ldc 122
    //   1667: invokevirtual 26	java/lang/String:toCharArray	()[C
    //   1670: astore 221
    //   1672: aload 221
    //   1674: arraylength
    //   1675: istore 222
    //   1677: iconst_0
    //   1678: istore 223
    //   1680: iload 222
    //   1682: iload 223
    //   1684: if_icmpgt +5345 -> 7029
    //   1687: aload_0
    //   1688: bipush 44
    //   1690: new 20	java/lang/String
    //   1693: dup
    //   1694: aload 221
    //   1696: invokespecial 30	java/lang/String:<init>	([C)V
    //   1699: invokevirtual 34	java/lang/String:intern	()Ljava/lang/String;
    //   1702: aastore
    //   1703: ldc 124
    //   1705: invokevirtual 26	java/lang/String:toCharArray	()[C
    //   1708: astore 226
    //   1710: aload 226
    //   1712: arraylength
    //   1713: istore 227
    //   1715: iconst_0
    //   1716: istore 228
    //   1718: iload 227
    //   1720: iload 228
    //   1722: if_icmpgt +5399 -> 7121
    //   1725: aload_0
    //   1726: bipush 45
    //   1728: new 20	java/lang/String
    //   1731: dup
    //   1732: aload 226
    //   1734: invokespecial 30	java/lang/String:<init>	([C)V
    //   1737: invokevirtual 34	java/lang/String:intern	()Ljava/lang/String;
    //   1740: aastore
    //   1741: ldc 126
    //   1743: invokevirtual 26	java/lang/String:toCharArray	()[C
    //   1746: astore 231
    //   1748: aload 231
    //   1750: arraylength
    //   1751: istore 232
    //   1753: iconst_0
    //   1754: istore 233
    //   1756: iload 232
    //   1758: iload 233
    //   1760: if_icmpgt +5453 -> 7213
    //   1763: aload_0
    //   1764: bipush 46
    //   1766: new 20	java/lang/String
    //   1769: dup
    //   1770: aload 231
    //   1772: invokespecial 30	java/lang/String:<init>	([C)V
    //   1775: invokevirtual 34	java/lang/String:intern	()Ljava/lang/String;
    //   1778: aastore
    //   1779: ldc 128
    //   1781: invokevirtual 26	java/lang/String:toCharArray	()[C
    //   1784: astore 236
    //   1786: aload 236
    //   1788: arraylength
    //   1789: istore 237
    //   1791: iconst_0
    //   1792: istore 238
    //   1794: iload 237
    //   1796: iload 238
    //   1798: if_icmpgt +5507 -> 7305
    //   1801: aload_0
    //   1802: bipush 47
    //   1804: new 20	java/lang/String
    //   1807: dup
    //   1808: aload 236
    //   1810: invokespecial 30	java/lang/String:<init>	([C)V
    //   1813: invokevirtual 34	java/lang/String:intern	()Ljava/lang/String;
    //   1816: aastore
    //   1817: ldc 130
    //   1819: invokevirtual 26	java/lang/String:toCharArray	()[C
    //   1822: astore 241
    //   1824: aload 241
    //   1826: arraylength
    //   1827: istore 242
    //   1829: iconst_0
    //   1830: istore 243
    //   1832: iload 242
    //   1834: iload 243
    //   1836: if_icmpgt +5561 -> 7397
    //   1839: aload_0
    //   1840: bipush 48
    //   1842: new 20	java/lang/String
    //   1845: dup
    //   1846: aload 241
    //   1848: invokespecial 30	java/lang/String:<init>	([C)V
    //   1851: invokevirtual 34	java/lang/String:intern	()Ljava/lang/String;
    //   1854: aastore
    //   1855: ldc 132
    //   1857: invokevirtual 26	java/lang/String:toCharArray	()[C
    //   1860: astore 246
    //   1862: aload 246
    //   1864: arraylength
    //   1865: istore 247
    //   1867: iconst_0
    //   1868: istore 248
    //   1870: iload 247
    //   1872: iload 248
    //   1874: if_icmpgt +5615 -> 7489
    //   1877: aload_0
    //   1878: bipush 49
    //   1880: new 20	java/lang/String
    //   1883: dup
    //   1884: aload 246
    //   1886: invokespecial 30	java/lang/String:<init>	([C)V
    //   1889: invokevirtual 34	java/lang/String:intern	()Ljava/lang/String;
    //   1892: aastore
    //   1893: ldc 134
    //   1895: invokevirtual 26	java/lang/String:toCharArray	()[C
    //   1898: astore 251
    //   1900: aload 251
    //   1902: arraylength
    //   1903: istore 252
    //   1905: iconst_0
    //   1906: istore 253
    //   1908: iload 252
    //   1910: iload 253
    //   1912: if_icmpgt +5669 -> 7581
    //   1915: aload_0
    //   1916: bipush 50
    //   1918: new 20	java/lang/String
    //   1921: dup
    //   1922: aload 251
    //   1924: invokespecial 30	java/lang/String:<init>	([C)V
    //   1927: invokevirtual 34	java/lang/String:intern	()Ljava/lang/String;
    //   1930: aastore
    //   1931: ldc 136
    //   1933: invokevirtual 26	java/lang/String:toCharArray	()[C
    //   1936: wide
    //   1940: wide
    //   1944: arraylength
    //   1945: wide
    //   1949: iconst_0
    //   1950: wide
    //   1954: wide
    //   1958: wide
    //   1962: if_icmpgt +5711 -> 7673
    //   1965: aload_0
    //   1966: bipush 51
    //   1968: new 20	java/lang/String
    //   1971: dup
    //   1972: wide
    //   1976: invokespecial 30	java/lang/String:<init>	([C)V
    //   1979: invokevirtual 34	java/lang/String:intern	()Ljava/lang/String;
    //   1982: aastore
    //   1983: ldc 138
    //   1985: invokevirtual 26	java/lang/String:toCharArray	()[C
    //   1988: wide
    //   1992: wide
    //   1996: arraylength
    //   1997: wide
    //   2001: iconst_0
    //   2002: wide
    //   2006: wide
    //   2010: wide
    //   2014: if_icmpgt +5780 -> 7794
    //   2017: aload_0
    //   2018: bipush 52
    //   2020: new 20	java/lang/String
    //   2023: dup
    //   2024: wide
    //   2028: invokespecial 30	java/lang/String:<init>	([C)V
    //   2031: invokevirtual 34	java/lang/String:intern	()Ljava/lang/String;
    //   2034: aastore
    //   2035: ldc 140
    //   2037: invokevirtual 26	java/lang/String:toCharArray	()[C
    //   2040: wide
    //   2044: wide
    //   2048: arraylength
    //   2049: wide
    //   2053: iconst_0
    //   2054: wide
    //   2058: wide
    //   2062: wide
    //   2066: if_icmpgt +5848 -> 7914
    //   2069: aload_0
    //   2070: bipush 53
    //   2072: new 20	java/lang/String
    //   2075: dup
    //   2076: wide
    //   2080: invokespecial 30	java/lang/String:<init>	([C)V
    //   2083: invokevirtual 34	java/lang/String:intern	()Ljava/lang/String;
    //   2086: aastore
    //   2087: ldc 142
    //   2089: invokevirtual 26	java/lang/String:toCharArray	()[C
    //   2092: wide
    //   2096: wide
    //   2100: arraylength
    //   2101: wide
    //   2105: iconst_0
    //   2106: wide
    //   2110: wide
    //   2114: wide
    //   2118: if_icmpgt +5916 -> 8034
    //   2121: aload_0
    //   2122: bipush 54
    //   2124: new 20	java/lang/String
    //   2127: dup
    //   2128: wide
    //   2132: invokespecial 30	java/lang/String:<init>	([C)V
    //   2135: invokevirtual 34	java/lang/String:intern	()Ljava/lang/String;
    //   2138: aastore
    //   2139: ldc 144
    //   2141: invokevirtual 26	java/lang/String:toCharArray	()[C
    //   2144: wide
    //   2148: wide
    //   2152: arraylength
    //   2153: wide
    //   2157: iconst_0
    //   2158: wide
    //   2162: wide
    //   2166: wide
    //   2170: if_icmpgt +5984 -> 8154
    //   2173: aload_0
    //   2174: bipush 55
    //   2176: new 20	java/lang/String
    //   2179: dup
    //   2180: wide
    //   2184: invokespecial 30	java/lang/String:<init>	([C)V
    //   2187: invokevirtual 34	java/lang/String:intern	()Ljava/lang/String;
    //   2190: aastore
    //   2191: ldc 146
    //   2193: invokevirtual 26	java/lang/String:toCharArray	()[C
    //   2196: wide
    //   2200: wide
    //   2204: arraylength
    //   2205: wide
    //   2209: iconst_0
    //   2210: wide
    //   2214: wide
    //   2218: wide
    //   2222: if_icmpgt +6052 -> 8274
    //   2225: aload_0
    //   2226: bipush 56
    //   2228: new 20	java/lang/String
    //   2231: dup
    //   2232: wide
    //   2236: invokespecial 30	java/lang/String:<init>	([C)V
    //   2239: invokevirtual 34	java/lang/String:intern	()Ljava/lang/String;
    //   2242: aastore
    //   2243: ldc 148
    //   2245: invokevirtual 26	java/lang/String:toCharArray	()[C
    //   2248: wide
    //   2252: wide
    //   2256: arraylength
    //   2257: wide
    //   2261: iconst_0
    //   2262: wide
    //   2266: wide
    //   2270: wide
    //   2274: if_icmpgt +6120 -> 8394
    //   2277: aload_0
    //   2278: bipush 57
    //   2280: new 20	java/lang/String
    //   2283: dup
    //   2284: wide
    //   2288: invokespecial 30	java/lang/String:<init>	([C)V
    //   2291: invokevirtual 34	java/lang/String:intern	()Ljava/lang/String;
    //   2294: aastore
    //   2295: ldc 150
    //   2297: invokevirtual 26	java/lang/String:toCharArray	()[C
    //   2300: wide
    //   2304: wide
    //   2308: arraylength
    //   2309: wide
    //   2313: iconst_0
    //   2314: wide
    //   2318: wide
    //   2322: wide
    //   2326: if_icmpgt +6188 -> 8514
    //   2329: aload_0
    //   2330: bipush 58
    //   2332: new 20	java/lang/String
    //   2335: dup
    //   2336: wide
    //   2340: invokespecial 30	java/lang/String:<init>	([C)V
    //   2343: invokevirtual 34	java/lang/String:intern	()Ljava/lang/String;
    //   2346: aastore
    //   2347: ldc 152
    //   2349: invokevirtual 26	java/lang/String:toCharArray	()[C
    //   2352: wide
    //   2356: wide
    //   2360: arraylength
    //   2361: wide
    //   2365: iconst_0
    //   2366: wide
    //   2370: wide
    //   2374: wide
    //   2378: if_icmpgt +6256 -> 8634
    //   2381: aload_0
    //   2382: bipush 59
    //   2384: new 20	java/lang/String
    //   2387: dup
    //   2388: wide
    //   2392: invokespecial 30	java/lang/String:<init>	([C)V
    //   2395: invokevirtual 34	java/lang/String:intern	()Ljava/lang/String;
    //   2398: aastore
    //   2399: ldc 154
    //   2401: invokevirtual 26	java/lang/String:toCharArray	()[C
    //   2404: wide
    //   2408: wide
    //   2412: arraylength
    //   2413: wide
    //   2417: iconst_0
    //   2418: wide
    //   2422: wide
    //   2426: wide
    //   2430: if_icmpgt +6324 -> 8754
    //   2433: aload_0
    //   2434: bipush 60
    //   2436: new 20	java/lang/String
    //   2439: dup
    //   2440: wide
    //   2444: invokespecial 30	java/lang/String:<init>	([C)V
    //   2447: invokevirtual 34	java/lang/String:intern	()Ljava/lang/String;
    //   2450: aastore
    //   2451: ldc 156
    //   2453: invokevirtual 26	java/lang/String:toCharArray	()[C
    //   2456: wide
    //   2460: wide
    //   2464: arraylength
    //   2465: wide
    //   2469: iconst_0
    //   2470: wide
    //   2474: wide
    //   2478: wide
    //   2482: if_icmpgt +6392 -> 8874
    //   2485: aload_0
    //   2486: bipush 61
    //   2488: new 20	java/lang/String
    //   2491: dup
    //   2492: wide
    //   2496: invokespecial 30	java/lang/String:<init>	([C)V
    //   2499: invokevirtual 34	java/lang/String:intern	()Ljava/lang/String;
    //   2502: aastore
    //   2503: ldc 158
    //   2505: invokevirtual 26	java/lang/String:toCharArray	()[C
    //   2508: wide
    //   2512: wide
    //   2516: arraylength
    //   2517: wide
    //   2521: iconst_0
    //   2522: wide
    //   2526: wide
    //   2530: wide
    //   2534: if_icmpgt +6460 -> 8994
    //   2537: aload_0
    //   2538: bipush 62
    //   2540: new 20	java/lang/String
    //   2543: dup
    //   2544: wide
    //   2548: invokespecial 30	java/lang/String:<init>	([C)V
    //   2551: invokevirtual 34	java/lang/String:intern	()Ljava/lang/String;
    //   2554: aastore
    //   2555: ldc 160
    //   2557: invokevirtual 26	java/lang/String:toCharArray	()[C
    //   2560: wide
    //   2564: wide
    //   2568: arraylength
    //   2569: wide
    //   2573: iconst_0
    //   2574: wide
    //   2578: wide
    //   2582: wide
    //   2586: if_icmpgt +6528 -> 9114
    //   2589: aload_0
    //   2590: bipush 63
    //   2592: new 20	java/lang/String
    //   2595: dup
    //   2596: wide
    //   2600: invokespecial 30	java/lang/String:<init>	([C)V
    //   2603: invokevirtual 34	java/lang/String:intern	()Ljava/lang/String;
    //   2606: aastore
    //   2607: aload_0
    //   2608: putstatic 162	m:z	[Ljava/lang/String;
    //   2611: bipush 13
    //   2613: anewarray 20	java/lang/String
    //   2616: wide
    //   2620: wide
    //   2624: iconst_0
    //   2625: getstatic 162	m:z	[Ljava/lang/String;
    //   2628: bipush 52
    //   2630: aaload
    //   2631: aastore
    //   2632: wide
    //   2636: iconst_1
    //   2637: getstatic 162	m:z	[Ljava/lang/String;
    //   2640: bipush 40
    //   2642: aaload
    //   2643: aastore
    //   2644: wide
    //   2648: iconst_2
    //   2649: getstatic 162	m:z	[Ljava/lang/String;
    //   2652: bipush 42
    //   2654: aaload
    //   2655: aastore
    //   2656: wide
    //   2660: iconst_3
    //   2661: getstatic 162	m:z	[Ljava/lang/String;
    //   2664: bipush 43
    //   2666: aaload
    //   2667: aastore
    //   2668: wide
    //   2672: iconst_4
    //   2673: getstatic 162	m:z	[Ljava/lang/String;
    //   2676: bipush 48
    //   2678: aaload
    //   2679: aastore
    //   2680: wide
    //   2684: iconst_5
    //   2685: getstatic 162	m:z	[Ljava/lang/String;
    //   2688: bipush 44
    //   2690: aaload
    //   2691: aastore
    //   2692: wide
    //   2696: bipush 6
    //   2698: getstatic 162	m:z	[Ljava/lang/String;
    //   2701: bipush 11
    //   2703: aaload
    //   2704: aastore
    //   2705: wide
    //   2709: bipush 7
    //   2711: getstatic 162	m:z	[Ljava/lang/String;
    //   2714: bipush 61
    //   2716: aaload
    //   2717: aastore
    //   2718: wide
    //   2722: bipush 8
    //   2724: getstatic 162	m:z	[Ljava/lang/String;
    //   2727: bipush 63
    //   2729: aaload
    //   2730: aastore
    //   2731: wide
    //   2735: bipush 9
    //   2737: getstatic 162	m:z	[Ljava/lang/String;
    //   2740: bipush 62
    //   2742: aaload
    //   2743: aastore
    //   2744: wide
    //   2748: bipush 10
    //   2750: getstatic 162	m:z	[Ljava/lang/String;
    //   2753: bipush 56
    //   2755: aaload
    //   2756: aastore
    //   2757: wide
    //   2761: bipush 11
    //   2763: getstatic 162	m:z	[Ljava/lang/String;
    //   2766: bipush 45
    //   2768: aaload
    //   2769: aastore
    //   2770: wide
    //   2774: bipush 12
    //   2776: getstatic 162	m:z	[Ljava/lang/String;
    //   2779: bipush 60
    //   2781: aaload
    //   2782: aastore
    //   2783: new 164	java/util/HashSet
    //   2786: dup
    //   2787: wide
    //   2791: invokestatic 170	java/util/Arrays:asList	([Ljava/lang/Object;)Ljava/util/List;
    //   2794: invokespecial 173	java/util/HashSet:<init>	(Ljava/util/Collection;)V
    //   2797: putstatic 175	m:d	Ljava/util/HashSet;
    //   2800: bipush 13
    //   2802: anewarray 20	java/lang/String
    //   2805: wide
    //   2809: wide
    //   2813: iconst_0
    //   2814: getstatic 162	m:z	[Ljava/lang/String;
    //   2817: bipush 41
    //   2819: aaload
    //   2820: aastore
    //   2821: wide
    //   2825: iconst_1
    //   2826: getstatic 162	m:z	[Ljava/lang/String;
    //   2829: bipush 54
    //   2831: aaload
    //   2832: aastore
    //   2833: wide
    //   2837: iconst_2
    //   2838: getstatic 162	m:z	[Ljava/lang/String;
    //   2841: bipush 46
    //   2843: aaload
    //   2844: aastore
    //   2845: wide
    //   2849: iconst_3
    //   2850: getstatic 162	m:z	[Ljava/lang/String;
    //   2853: bipush 59
    //   2855: aaload
    //   2856: aastore
    //   2857: wide
    //   2861: iconst_4
    //   2862: getstatic 162	m:z	[Ljava/lang/String;
    //   2865: bipush 58
    //   2867: aaload
    //   2868: aastore
    //   2869: wide
    //   2873: iconst_5
    //   2874: getstatic 162	m:z	[Ljava/lang/String;
    //   2877: bipush 55
    //   2879: aaload
    //   2880: aastore
    //   2881: wide
    //   2885: bipush 6
    //   2887: getstatic 162	m:z	[Ljava/lang/String;
    //   2890: bipush 52
    //   2892: aaload
    //   2893: aastore
    //   2894: wide
    //   2898: bipush 7
    //   2900: getstatic 162	m:z	[Ljava/lang/String;
    //   2903: bipush 51
    //   2905: aaload
    //   2906: aastore
    //   2907: wide
    //   2911: bipush 8
    //   2913: getstatic 162	m:z	[Ljava/lang/String;
    //   2916: bipush 49
    //   2918: aaload
    //   2919: aastore
    //   2920: wide
    //   2924: bipush 9
    //   2926: getstatic 162	m:z	[Ljava/lang/String;
    //   2929: bipush 57
    //   2931: aaload
    //   2932: aastore
    //   2933: wide
    //   2937: bipush 10
    //   2939: getstatic 162	m:z	[Ljava/lang/String;
    //   2942: bipush 53
    //   2944: aaload
    //   2945: aastore
    //   2946: wide
    //   2950: bipush 11
    //   2952: getstatic 162	m:z	[Ljava/lang/String;
    //   2955: bipush 50
    //   2957: aaload
    //   2958: aastore
    //   2959: wide
    //   2963: bipush 12
    //   2965: getstatic 162	m:z	[Ljava/lang/String;
    //   2968: bipush 47
    //   2970: aaload
    //   2971: aastore
    //   2972: new 164	java/util/HashSet
    //   2975: dup
    //   2976: wide
    //   2980: invokestatic 170	java/util/Arrays:asList	([Ljava/lang/Object;)Ljava/util/List;
    //   2983: invokespecial 173	java/util/HashSet:<init>	(Ljava/util/Collection;)V
    //   2986: putstatic 177	m:e	Ljava/util/HashSet;
    //   2989: return
    //   2990: aload_1
    //   2991: iload_3
    //   2992: caload
    //   2993: istore 4
    //   2995: iload_3
    //   2996: iconst_5
    //   2997: irem
    //   2998: tableswitch	default:+30 -> 3028, 0:+49->3047, 1:+56->3054, 2:+63->3061, 3:+70->3068
    //   3029: daload
    //   3030: istore 5
    //   3032: aload_1
    //   3033: iload_3
    //   3034: iload 5
    //   3036: iload 4
    //   3038: ixor
    //   3039: i2c
    //   3040: castore
    //   3041: iinc 3 1
    //   3044: goto -3027 -> 17
    //   3047: bipush 120
    //   3049: istore 5
    //   3051: goto -19 -> 3032
    //   3054: bipush 104
    //   3056: istore 5
    //   3058: goto -26 -> 3032
    //   3061: bipush 58
    //   3063: istore 5
    //   3065: goto -33 -> 3032
    //   3068: bipush 64
    //   3070: istore 5
    //   3072: goto -40 -> 3032
    //   3075: aload 6
    //   3077: iload 8
    //   3079: caload
    //   3080: istore 9
    //   3082: iload 8
    //   3084: iconst_5
    //   3085: irem
    //   3086: tableswitch	default:+30 -> 3116, 0:+51->3137, 1:+58->3144, 2:+65->3151, 3:+72->3158
    //   3117: daload
    //   3118: istore 10
    //   3120: aload 6
    //   3122: iload 8
    //   3124: iload 10
    //   3126: iload 9
    //   3128: ixor
    //   3129: i2c
    //   3130: castore
    //   3131: iinc 8 1
    //   3134: goto -3083 -> 51
    //   3137: bipush 120
    //   3139: istore 10
    //   3141: goto -21 -> 3120
    //   3144: bipush 104
    //   3146: istore 10
    //   3148: goto -28 -> 3120
    //   3151: bipush 58
    //   3153: istore 10
    //   3155: goto -35 -> 3120
    //   3158: bipush 64
    //   3160: istore 10
    //   3162: goto -42 -> 3120
    //   3165: aload 11
    //   3167: iload 13
    //   3169: caload
    //   3170: istore 14
    //   3172: iload 13
    //   3174: iconst_5
    //   3175: irem
    //   3176: tableswitch	default:+32 -> 3208, 0:+53->3229, 1:+60->3236, 2:+67->3243, 3:+74->3250
    //   3209: daload
    //   3210: istore 15
    //   3212: aload 11
    //   3214: iload 13
    //   3216: iload 15
    //   3218: iload 14
    //   3220: ixor
    //   3221: i2c
    //   3222: castore
    //   3223: iinc 13 1
    //   3226: goto -3138 -> 88
    //   3229: bipush 120
    //   3231: istore 15
    //   3233: goto -21 -> 3212
    //   3236: bipush 104
    //   3238: istore 15
    //   3240: goto -28 -> 3212
    //   3243: bipush 58
    //   3245: istore 15
    //   3247: goto -35 -> 3212
    //   3250: bipush 64
    //   3252: istore 15
    //   3254: goto -42 -> 3212
    //   3257: aload 16
    //   3259: iload 18
    //   3261: caload
    //   3262: istore 19
    //   3264: iload 18
    //   3266: iconst_5
    //   3267: irem
    //   3268: tableswitch	default:+32 -> 3300, 0:+53->3321, 1:+60->3328, 2:+67->3335, 3:+74->3342
    //   3301: daload
    //   3302: istore 20
    //   3304: aload 16
    //   3306: iload 18
    //   3308: iload 20
    //   3310: iload 19
    //   3312: ixor
    //   3313: i2c
    //   3314: castore
    //   3315: iinc 18 1
    //   3318: goto -3193 -> 125
    //   3321: bipush 120
    //   3323: istore 20
    //   3325: goto -21 -> 3304
    //   3328: bipush 104
    //   3330: istore 20
    //   3332: goto -28 -> 3304
    //   3335: bipush 58
    //   3337: istore 20
    //   3339: goto -35 -> 3304
    //   3342: bipush 64
    //   3344: istore 20
    //   3346: goto -42 -> 3304
    //   3349: aload 21
    //   3351: iload 23
    //   3353: caload
    //   3354: istore 24
    //   3356: iload 23
    //   3358: iconst_5
    //   3359: irem
    //   3360: tableswitch	default:+32 -> 3392, 0:+53->3413, 1:+60->3420, 2:+67->3427, 3:+74->3434
    //   3393: daload
    //   3394: istore 25
    //   3396: aload 21
    //   3398: iload 23
    //   3400: iload 25
    //   3402: iload 24
    //   3404: ixor
    //   3405: i2c
    //   3406: castore
    //   3407: iinc 23 1
    //   3410: goto -3248 -> 162
    //   3413: bipush 120
    //   3415: istore 25
    //   3417: goto -21 -> 3396
    //   3420: bipush 104
    //   3422: istore 25
    //   3424: goto -28 -> 3396
    //   3427: bipush 58
    //   3429: istore 25
    //   3431: goto -35 -> 3396
    //   3434: bipush 64
    //   3436: istore 25
    //   3438: goto -42 -> 3396
    //   3441: aload 26
    //   3443: iload 28
    //   3445: caload
    //   3446: istore 29
    //   3448: iload 28
    //   3450: iconst_5
    //   3451: irem
    //   3452: tableswitch	default:+32 -> 3484, 0:+53->3505, 1:+60->3512, 2:+67->3519, 3:+74->3526
    //   3485: daload
    //   3486: istore 30
    //   3488: aload 26
    //   3490: iload 28
    //   3492: iload 30
    //   3494: iload 29
    //   3496: ixor
    //   3497: i2c
    //   3498: castore
    //   3499: iinc 28 1
    //   3502: goto -3303 -> 199
    //   3505: bipush 120
    //   3507: istore 30
    //   3509: goto -21 -> 3488
    //   3512: bipush 104
    //   3514: istore 30
    //   3516: goto -28 -> 3488
    //   3519: bipush 58
    //   3521: istore 30
    //   3523: goto -35 -> 3488
    //   3526: bipush 64
    //   3528: istore 30
    //   3530: goto -42 -> 3488
    //   3533: aload 31
    //   3535: iload 33
    //   3537: caload
    //   3538: istore 34
    //   3540: iload 33
    //   3542: iconst_5
    //   3543: irem
    //   3544: tableswitch	default:+32 -> 3576, 0:+53->3597, 1:+60->3604, 2:+67->3611, 3:+74->3618
    //   3577: daload
    //   3578: istore 35
    //   3580: aload 31
    //   3582: iload 33
    //   3584: iload 35
    //   3586: iload 34
    //   3588: ixor
    //   3589: i2c
    //   3590: castore
    //   3591: iinc 33 1
    //   3594: goto -3358 -> 236
    //   3597: bipush 120
    //   3599: istore 35
    //   3601: goto -21 -> 3580
    //   3604: bipush 104
    //   3606: istore 35
    //   3608: goto -28 -> 3580
    //   3611: bipush 58
    //   3613: istore 35
    //   3615: goto -35 -> 3580
    //   3618: bipush 64
    //   3620: istore 35
    //   3622: goto -42 -> 3580
    //   3625: aload 36
    //   3627: iload 38
    //   3629: caload
    //   3630: istore 39
    //   3632: iload 38
    //   3634: iconst_5
    //   3635: irem
    //   3636: tableswitch	default:+32 -> 3668, 0:+53->3689, 1:+60->3696, 2:+67->3703, 3:+74->3710
    //   3669: daload
    //   3670: istore 40
    //   3672: aload 36
    //   3674: iload 38
    //   3676: iload 40
    //   3678: iload 39
    //   3680: ixor
    //   3681: i2c
    //   3682: castore
    //   3683: iinc 38 1
    //   3686: goto -3412 -> 274
    //   3689: bipush 120
    //   3691: istore 40
    //   3693: goto -21 -> 3672
    //   3696: bipush 104
    //   3698: istore 40
    //   3700: goto -28 -> 3672
    //   3703: bipush 58
    //   3705: istore 40
    //   3707: goto -35 -> 3672
    //   3710: bipush 64
    //   3712: istore 40
    //   3714: goto -42 -> 3672
    //   3717: aload 41
    //   3719: iload 43
    //   3721: caload
    //   3722: istore 44
    //   3724: iload 43
    //   3726: iconst_5
    //   3727: irem
    //   3728: tableswitch	default:+32 -> 3760, 0:+53->3781, 1:+60->3788, 2:+67->3795, 3:+74->3802
    //   3761: daload
    //   3762: istore 45
    //   3764: aload 41
    //   3766: iload 43
    //   3768: iload 45
    //   3770: iload 44
    //   3772: ixor
    //   3773: i2c
    //   3774: castore
    //   3775: iinc 43 1
    //   3778: goto -3466 -> 312
    //   3781: bipush 120
    //   3783: istore 45
    //   3785: goto -21 -> 3764
    //   3788: bipush 104
    //   3790: istore 45
    //   3792: goto -28 -> 3764
    //   3795: bipush 58
    //   3797: istore 45
    //   3799: goto -35 -> 3764
    //   3802: bipush 64
    //   3804: istore 45
    //   3806: goto -42 -> 3764
    //   3809: aload 46
    //   3811: iload 48
    //   3813: caload
    //   3814: istore 49
    //   3816: iload 48
    //   3818: iconst_5
    //   3819: irem
    //   3820: tableswitch	default:+32 -> 3852, 0:+53->3873, 1:+60->3880, 2:+67->3887, 3:+74->3894
    //   3853: daload
    //   3854: istore 50
    //   3856: aload 46
    //   3858: iload 48
    //   3860: iload 50
    //   3862: iload 49
    //   3864: ixor
    //   3865: i2c
    //   3866: castore
    //   3867: iinc 48 1
    //   3870: goto -3520 -> 350
    //   3873: bipush 120
    //   3875: istore 50
    //   3877: goto -21 -> 3856
    //   3880: bipush 104
    //   3882: istore 50
    //   3884: goto -28 -> 3856
    //   3887: bipush 58
    //   3889: istore 50
    //   3891: goto -35 -> 3856
    //   3894: bipush 64
    //   3896: istore 50
    //   3898: goto -42 -> 3856
    //   3901: aload 51
    //   3903: iload 53
    //   3905: caload
    //   3906: istore 54
    //   3908: iload 53
    //   3910: iconst_5
    //   3911: irem
    //   3912: tableswitch	default:+32 -> 3944, 0:+53->3965, 1:+60->3972, 2:+67->3979, 3:+74->3986
    //   3945: daload
    //   3946: istore 55
    //   3948: aload 51
    //   3950: iload 53
    //   3952: iload 55
    //   3954: iload 54
    //   3956: ixor
    //   3957: i2c
    //   3958: castore
    //   3959: iinc 53 1
    //   3962: goto -3574 -> 388
    //   3965: bipush 120
    //   3967: istore 55
    //   3969: goto -21 -> 3948
    //   3972: bipush 104
    //   3974: istore 55
    //   3976: goto -28 -> 3948
    //   3979: bipush 58
    //   3981: istore 55
    //   3983: goto -35 -> 3948
    //   3986: bipush 64
    //   3988: istore 55
    //   3990: goto -42 -> 3948
    //   3993: aload 56
    //   3995: iload 58
    //   3997: caload
    //   3998: istore 59
    //   4000: iload 58
    //   4002: iconst_5
    //   4003: irem
    //   4004: tableswitch	default:+32 -> 4036, 0:+53->4057, 1:+60->4064, 2:+67->4071, 3:+74->4078
    //   4037: daload
    //   4038: istore 60
    //   4040: aload 56
    //   4042: iload 58
    //   4044: iload 60
    //   4046: iload 59
    //   4048: ixor
    //   4049: i2c
    //   4050: castore
    //   4051: iinc 58 1
    //   4054: goto -3628 -> 426
    //   4057: bipush 120
    //   4059: istore 60
    //   4061: goto -21 -> 4040
    //   4064: bipush 104
    //   4066: istore 60
    //   4068: goto -28 -> 4040
    //   4071: bipush 58
    //   4073: istore 60
    //   4075: goto -35 -> 4040
    //   4078: bipush 64
    //   4080: istore 60
    //   4082: goto -42 -> 4040
    //   4085: aload 61
    //   4087: iload 63
    //   4089: caload
    //   4090: istore 64
    //   4092: iload 63
    //   4094: iconst_5
    //   4095: irem
    //   4096: tableswitch	default:+32 -> 4128, 0:+53->4149, 1:+60->4156, 2:+67->4163, 3:+74->4170
    //   4129: daload
    //   4130: istore 65
    //   4132: aload 61
    //   4134: iload 63
    //   4136: iload 65
    //   4138: iload 64
    //   4140: ixor
    //   4141: i2c
    //   4142: castore
    //   4143: iinc 63 1
    //   4146: goto -3682 -> 464
    //   4149: bipush 120
    //   4151: istore 65
    //   4153: goto -21 -> 4132
    //   4156: bipush 104
    //   4158: istore 65
    //   4160: goto -28 -> 4132
    //   4163: bipush 58
    //   4165: istore 65
    //   4167: goto -35 -> 4132
    //   4170: bipush 64
    //   4172: istore 65
    //   4174: goto -42 -> 4132
    //   4177: aload 66
    //   4179: iload 68
    //   4181: caload
    //   4182: istore 69
    //   4184: iload 68
    //   4186: iconst_5
    //   4187: irem
    //   4188: tableswitch	default:+32 -> 4220, 0:+53->4241, 1:+60->4248, 2:+67->4255, 3:+74->4262
    //   4221: daload
    //   4222: istore 70
    //   4224: aload 66
    //   4226: iload 68
    //   4228: iload 70
    //   4230: iload 69
    //   4232: ixor
    //   4233: i2c
    //   4234: castore
    //   4235: iinc 68 1
    //   4238: goto -3736 -> 502
    //   4241: bipush 120
    //   4243: istore 70
    //   4245: goto -21 -> 4224
    //   4248: bipush 104
    //   4250: istore 70
    //   4252: goto -28 -> 4224
    //   4255: bipush 58
    //   4257: istore 70
    //   4259: goto -35 -> 4224
    //   4262: bipush 64
    //   4264: istore 70
    //   4266: goto -42 -> 4224
    //   4269: aload 71
    //   4271: iload 73
    //   4273: caload
    //   4274: istore 74
    //   4276: iload 73
    //   4278: iconst_5
    //   4279: irem
    //   4280: tableswitch	default:+32 -> 4312, 0:+53->4333, 1:+60->4340, 2:+67->4347, 3:+74->4354
    //   4313: daload
    //   4314: istore 75
    //   4316: aload 71
    //   4318: iload 73
    //   4320: iload 75
    //   4322: iload 74
    //   4324: ixor
    //   4325: i2c
    //   4326: castore
    //   4327: iinc 73 1
    //   4330: goto -3790 -> 540
    //   4333: bipush 120
    //   4335: istore 75
    //   4337: goto -21 -> 4316
    //   4340: bipush 104
    //   4342: istore 75
    //   4344: goto -28 -> 4316
    //   4347: bipush 58
    //   4349: istore 75
    //   4351: goto -35 -> 4316
    //   4354: bipush 64
    //   4356: istore 75
    //   4358: goto -42 -> 4316
    //   4361: aload 76
    //   4363: iload 78
    //   4365: caload
    //   4366: istore 79
    //   4368: iload 78
    //   4370: iconst_5
    //   4371: irem
    //   4372: tableswitch	default:+32 -> 4404, 0:+53->4425, 1:+60->4432, 2:+67->4439, 3:+74->4446
    //   4405: daload
    //   4406: istore 80
    //   4408: aload 76
    //   4410: iload 78
    //   4412: iload 80
    //   4414: iload 79
    //   4416: ixor
    //   4417: i2c
    //   4418: castore
    //   4419: iinc 78 1
    //   4422: goto -3844 -> 578
    //   4425: bipush 120
    //   4427: istore 80
    //   4429: goto -21 -> 4408
    //   4432: bipush 104
    //   4434: istore 80
    //   4436: goto -28 -> 4408
    //   4439: bipush 58
    //   4441: istore 80
    //   4443: goto -35 -> 4408
    //   4446: bipush 64
    //   4448: istore 80
    //   4450: goto -42 -> 4408
    //   4453: aload 81
    //   4455: iload 83
    //   4457: caload
    //   4458: istore 84
    //   4460: iload 83
    //   4462: iconst_5
    //   4463: irem
    //   4464: tableswitch	default:+32 -> 4496, 0:+53->4517, 1:+60->4524, 2:+67->4531, 3:+74->4538
    //   4497: daload
    //   4498: istore 85
    //   4500: aload 81
    //   4502: iload 83
    //   4504: iload 85
    //   4506: iload 84
    //   4508: ixor
    //   4509: i2c
    //   4510: castore
    //   4511: iinc 83 1
    //   4514: goto -3898 -> 616
    //   4517: bipush 120
    //   4519: istore 85
    //   4521: goto -21 -> 4500
    //   4524: bipush 104
    //   4526: istore 85
    //   4528: goto -28 -> 4500
    //   4531: bipush 58
    //   4533: istore 85
    //   4535: goto -35 -> 4500
    //   4538: bipush 64
    //   4540: istore 85
    //   4542: goto -42 -> 4500
    //   4545: aload 86
    //   4547: iload 88
    //   4549: caload
    //   4550: istore 89
    //   4552: iload 88
    //   4554: iconst_5
    //   4555: irem
    //   4556: tableswitch	default:+32 -> 4588, 0:+53->4609, 1:+60->4616, 2:+67->4623, 3:+74->4630
    //   4589: daload
    //   4590: istore 90
    //   4592: aload 86
    //   4594: iload 88
    //   4596: iload 90
    //   4598: iload 89
    //   4600: ixor
    //   4601: i2c
    //   4602: castore
    //   4603: iinc 88 1
    //   4606: goto -3952 -> 654
    //   4609: bipush 120
    //   4611: istore 90
    //   4613: goto -21 -> 4592
    //   4616: bipush 104
    //   4618: istore 90
    //   4620: goto -28 -> 4592
    //   4623: bipush 58
    //   4625: istore 90
    //   4627: goto -35 -> 4592
    //   4630: bipush 64
    //   4632: istore 90
    //   4634: goto -42 -> 4592
    //   4637: aload 91
    //   4639: iload 93
    //   4641: caload
    //   4642: istore 94
    //   4644: iload 93
    //   4646: iconst_5
    //   4647: irem
    //   4648: tableswitch	default:+32 -> 4680, 0:+53->4701, 1:+60->4708, 2:+67->4715, 3:+74->4722
    //   4681: daload
    //   4682: istore 95
    //   4684: aload 91
    //   4686: iload 93
    //   4688: iload 95
    //   4690: iload 94
    //   4692: ixor
    //   4693: i2c
    //   4694: castore
    //   4695: iinc 93 1
    //   4698: goto -4006 -> 692
    //   4701: bipush 120
    //   4703: istore 95
    //   4705: goto -21 -> 4684
    //   4708: bipush 104
    //   4710: istore 95
    //   4712: goto -28 -> 4684
    //   4715: bipush 58
    //   4717: istore 95
    //   4719: goto -35 -> 4684
    //   4722: bipush 64
    //   4724: istore 95
    //   4726: goto -42 -> 4684
    //   4729: aload 96
    //   4731: iload 98
    //   4733: caload
    //   4734: istore 99
    //   4736: iload 98
    //   4738: iconst_5
    //   4739: irem
    //   4740: tableswitch	default:+32 -> 4772, 0:+53->4793, 1:+60->4800, 2:+67->4807, 3:+74->4814
    //   4773: daload
    //   4774: istore 100
    //   4776: aload 96
    //   4778: iload 98
    //   4780: iload 100
    //   4782: iload 99
    //   4784: ixor
    //   4785: i2c
    //   4786: castore
    //   4787: iinc 98 1
    //   4790: goto -4060 -> 730
    //   4793: bipush 120
    //   4795: istore 100
    //   4797: goto -21 -> 4776
    //   4800: bipush 104
    //   4802: istore 100
    //   4804: goto -28 -> 4776
    //   4807: bipush 58
    //   4809: istore 100
    //   4811: goto -35 -> 4776
    //   4814: bipush 64
    //   4816: istore 100
    //   4818: goto -42 -> 4776
    //   4821: aload 101
    //   4823: iload 103
    //   4825: caload
    //   4826: istore 104
    //   4828: iload 103
    //   4830: iconst_5
    //   4831: irem
    //   4832: tableswitch	default:+32 -> 4864, 0:+53->4885, 1:+60->4892, 2:+67->4899, 3:+74->4906
    //   4865: daload
    //   4866: istore 105
    //   4868: aload 101
    //   4870: iload 103
    //   4872: iload 105
    //   4874: iload 104
    //   4876: ixor
    //   4877: i2c
    //   4878: castore
    //   4879: iinc 103 1
    //   4882: goto -4114 -> 768
    //   4885: bipush 120
    //   4887: istore 105
    //   4889: goto -21 -> 4868
    //   4892: bipush 104
    //   4894: istore 105
    //   4896: goto -28 -> 4868
    //   4899: bipush 58
    //   4901: istore 105
    //   4903: goto -35 -> 4868
    //   4906: bipush 64
    //   4908: istore 105
    //   4910: goto -42 -> 4868
    //   4913: aload 106
    //   4915: iload 108
    //   4917: caload
    //   4918: istore 109
    //   4920: iload 108
    //   4922: iconst_5
    //   4923: irem
    //   4924: tableswitch	default:+32 -> 4956, 0:+53->4977, 1:+60->4984, 2:+67->4991, 3:+74->4998
    //   4957: daload
    //   4958: istore 110
    //   4960: aload 106
    //   4962: iload 108
    //   4964: iload 110
    //   4966: iload 109
    //   4968: ixor
    //   4969: i2c
    //   4970: castore
    //   4971: iinc 108 1
    //   4974: goto -4168 -> 806
    //   4977: bipush 120
    //   4979: istore 110
    //   4981: goto -21 -> 4960
    //   4984: bipush 104
    //   4986: istore 110
    //   4988: goto -28 -> 4960
    //   4991: bipush 58
    //   4993: istore 110
    //   4995: goto -35 -> 4960
    //   4998: bipush 64
    //   5000: istore 110
    //   5002: goto -42 -> 4960
    //   5005: aload 111
    //   5007: iload 113
    //   5009: caload
    //   5010: istore 114
    //   5012: iload 113
    //   5014: iconst_5
    //   5015: irem
    //   5016: tableswitch	default:+32 -> 5048, 0:+53->5069, 1:+60->5076, 2:+67->5083, 3:+74->5090
    //   5049: daload
    //   5050: istore 115
    //   5052: aload 111
    //   5054: iload 113
    //   5056: iload 115
    //   5058: iload 114
    //   5060: ixor
    //   5061: i2c
    //   5062: castore
    //   5063: iinc 113 1
    //   5066: goto -4222 -> 844
    //   5069: bipush 120
    //   5071: istore 115
    //   5073: goto -21 -> 5052
    //   5076: bipush 104
    //   5078: istore 115
    //   5080: goto -28 -> 5052
    //   5083: bipush 58
    //   5085: istore 115
    //   5087: goto -35 -> 5052
    //   5090: bipush 64
    //   5092: istore 115
    //   5094: goto -42 -> 5052
    //   5097: aload 116
    //   5099: iload 118
    //   5101: caload
    //   5102: istore 119
    //   5104: iload 118
    //   5106: iconst_5
    //   5107: irem
    //   5108: tableswitch	default:+32 -> 5140, 0:+53->5161, 1:+60->5168, 2:+67->5175, 3:+74->5182
    //   5141: daload
    //   5142: istore 120
    //   5144: aload 116
    //   5146: iload 118
    //   5148: iload 120
    //   5150: iload 119
    //   5152: ixor
    //   5153: i2c
    //   5154: castore
    //   5155: iinc 118 1
    //   5158: goto -4276 -> 882
    //   5161: bipush 120
    //   5163: istore 120
    //   5165: goto -21 -> 5144
    //   5168: bipush 104
    //   5170: istore 120
    //   5172: goto -28 -> 5144
    //   5175: bipush 58
    //   5177: istore 120
    //   5179: goto -35 -> 5144
    //   5182: bipush 64
    //   5184: istore 120
    //   5186: goto -42 -> 5144
    //   5189: aload 121
    //   5191: iload 123
    //   5193: caload
    //   5194: istore 124
    //   5196: iload 123
    //   5198: iconst_5
    //   5199: irem
    //   5200: tableswitch	default:+32 -> 5232, 0:+53->5253, 1:+60->5260, 2:+67->5267, 3:+74->5274
    //   5233: daload
    //   5234: istore 125
    //   5236: aload 121
    //   5238: iload 123
    //   5240: iload 125
    //   5242: iload 124
    //   5244: ixor
    //   5245: i2c
    //   5246: castore
    //   5247: iinc 123 1
    //   5250: goto -4330 -> 920
    //   5253: bipush 120
    //   5255: istore 125
    //   5257: goto -21 -> 5236
    //   5260: bipush 104
    //   5262: istore 125
    //   5264: goto -28 -> 5236
    //   5267: bipush 58
    //   5269: istore 125
    //   5271: goto -35 -> 5236
    //   5274: bipush 64
    //   5276: istore 125
    //   5278: goto -42 -> 5236
    //   5281: aload 126
    //   5283: iload 128
    //   5285: caload
    //   5286: istore 129
    //   5288: iload 128
    //   5290: iconst_5
    //   5291: irem
    //   5292: tableswitch	default:+32 -> 5324, 0:+53->5345, 1:+60->5352, 2:+67->5359, 3:+74->5366
    //   5325: daload
    //   5326: istore 130
    //   5328: aload 126
    //   5330: iload 128
    //   5332: iload 130
    //   5334: iload 129
    //   5336: ixor
    //   5337: i2c
    //   5338: castore
    //   5339: iinc 128 1
    //   5342: goto -4384 -> 958
    //   5345: bipush 120
    //   5347: istore 130
    //   5349: goto -21 -> 5328
    //   5352: bipush 104
    //   5354: istore 130
    //   5356: goto -28 -> 5328
    //   5359: bipush 58
    //   5361: istore 130
    //   5363: goto -35 -> 5328
    //   5366: bipush 64
    //   5368: istore 130
    //   5370: goto -42 -> 5328
    //   5373: aload 131
    //   5375: iload 133
    //   5377: caload
    //   5378: istore 134
    //   5380: iload 133
    //   5382: iconst_5
    //   5383: irem
    //   5384: tableswitch	default:+32 -> 5416, 0:+53->5437, 1:+60->5444, 2:+67->5451, 3:+74->5458
    //   5417: daload
    //   5418: istore 135
    //   5420: aload 131
    //   5422: iload 133
    //   5424: iload 135
    //   5426: iload 134
    //   5428: ixor
    //   5429: i2c
    //   5430: castore
    //   5431: iinc 133 1
    //   5434: goto -4438 -> 996
    //   5437: bipush 120
    //   5439: istore 135
    //   5441: goto -21 -> 5420
    //   5444: bipush 104
    //   5446: istore 135
    //   5448: goto -28 -> 5420
    //   5451: bipush 58
    //   5453: istore 135
    //   5455: goto -35 -> 5420
    //   5458: bipush 64
    //   5460: istore 135
    //   5462: goto -42 -> 5420
    //   5465: aload 136
    //   5467: iload 138
    //   5469: caload
    //   5470: istore 139
    //   5472: iload 138
    //   5474: iconst_5
    //   5475: irem
    //   5476: tableswitch	default:+32 -> 5508, 0:+53->5529, 1:+60->5536, 2:+67->5543, 3:+74->5550
    //   5509: daload
    //   5510: istore 140
    //   5512: aload 136
    //   5514: iload 138
    //   5516: iload 140
    //   5518: iload 139
    //   5520: ixor
    //   5521: i2c
    //   5522: castore
    //   5523: iinc 138 1
    //   5526: goto -4492 -> 1034
    //   5529: bipush 120
    //   5531: istore 140
    //   5533: goto -21 -> 5512
    //   5536: bipush 104
    //   5538: istore 140
    //   5540: goto -28 -> 5512
    //   5543: bipush 58
    //   5545: istore 140
    //   5547: goto -35 -> 5512
    //   5550: bipush 64
    //   5552: istore 140
    //   5554: goto -42 -> 5512
    //   5557: aload 141
    //   5559: iload 143
    //   5561: caload
    //   5562: istore 144
    //   5564: iload 143
    //   5566: iconst_5
    //   5567: irem
    //   5568: tableswitch	default:+32 -> 5600, 0:+53->5621, 1:+60->5628, 2:+67->5635, 3:+74->5642
    //   5601: daload
    //   5602: istore 145
    //   5604: aload 141
    //   5606: iload 143
    //   5608: iload 145
    //   5610: iload 144
    //   5612: ixor
    //   5613: i2c
    //   5614: castore
    //   5615: iinc 143 1
    //   5618: goto -4546 -> 1072
    //   5621: bipush 120
    //   5623: istore 145
    //   5625: goto -21 -> 5604
    //   5628: bipush 104
    //   5630: istore 145
    //   5632: goto -28 -> 5604
    //   5635: bipush 58
    //   5637: istore 145
    //   5639: goto -35 -> 5604
    //   5642: bipush 64
    //   5644: istore 145
    //   5646: goto -42 -> 5604
    //   5649: aload 146
    //   5651: iload 148
    //   5653: caload
    //   5654: istore 149
    //   5656: iload 148
    //   5658: iconst_5
    //   5659: irem
    //   5660: tableswitch	default:+32 -> 5692, 0:+53->5713, 1:+60->5720, 2:+67->5727, 3:+74->5734
    //   5693: daload
    //   5694: istore 150
    //   5696: aload 146
    //   5698: iload 148
    //   5700: iload 150
    //   5702: iload 149
    //   5704: ixor
    //   5705: i2c
    //   5706: castore
    //   5707: iinc 148 1
    //   5710: goto -4600 -> 1110
    //   5713: bipush 120
    //   5715: istore 150
    //   5717: goto -21 -> 5696
    //   5720: bipush 104
    //   5722: istore 150
    //   5724: goto -28 -> 5696
    //   5727: bipush 58
    //   5729: istore 150
    //   5731: goto -35 -> 5696
    //   5734: bipush 64
    //   5736: istore 150
    //   5738: goto -42 -> 5696
    //   5741: aload 151
    //   5743: iload 153
    //   5745: caload
    //   5746: istore 154
    //   5748: iload 153
    //   5750: iconst_5
    //   5751: irem
    //   5752: tableswitch	default:+32 -> 5784, 0:+53->5805, 1:+60->5812, 2:+67->5819, 3:+74->5826
    //   5785: daload
    //   5786: istore 155
    //   5788: aload 151
    //   5790: iload 153
    //   5792: iload 155
    //   5794: iload 154
    //   5796: ixor
    //   5797: i2c
    //   5798: castore
    //   5799: iinc 153 1
    //   5802: goto -4654 -> 1148
    //   5805: bipush 120
    //   5807: istore 155
    //   5809: goto -21 -> 5788
    //   5812: bipush 104
    //   5814: istore 155
    //   5816: goto -28 -> 5788
    //   5819: bipush 58
    //   5821: istore 155
    //   5823: goto -35 -> 5788
    //   5826: bipush 64
    //   5828: istore 155
    //   5830: goto -42 -> 5788
    //   5833: aload 156
    //   5835: iload 158
    //   5837: caload
    //   5838: istore 159
    //   5840: iload 158
    //   5842: iconst_5
    //   5843: irem
    //   5844: tableswitch	default:+32 -> 5876, 0:+53->5897, 1:+60->5904, 2:+67->5911, 3:+74->5918
    //   5877: daload
    //   5878: istore 160
    //   5880: aload 156
    //   5882: iload 158
    //   5884: iload 160
    //   5886: iload 159
    //   5888: ixor
    //   5889: i2c
    //   5890: castore
    //   5891: iinc 158 1
    //   5894: goto -4708 -> 1186
    //   5897: bipush 120
    //   5899: istore 160
    //   5901: goto -21 -> 5880
    //   5904: bipush 104
    //   5906: istore 160
    //   5908: goto -28 -> 5880
    //   5911: bipush 58
    //   5913: istore 160
    //   5915: goto -35 -> 5880
    //   5918: bipush 64
    //   5920: istore 160
    //   5922: goto -42 -> 5880
    //   5925: aload 161
    //   5927: iload 163
    //   5929: caload
    //   5930: istore 164
    //   5932: iload 163
    //   5934: iconst_5
    //   5935: irem
    //   5936: tableswitch	default:+32 -> 5968, 0:+53->5989, 1:+60->5996, 2:+67->6003, 3:+74->6010
    //   5969: daload
    //   5970: istore 165
    //   5972: aload 161
    //   5974: iload 163
    //   5976: iload 165
    //   5978: iload 164
    //   5980: ixor
    //   5981: i2c
    //   5982: castore
    //   5983: iinc 163 1
    //   5986: goto -4762 -> 1224
    //   5989: bipush 120
    //   5991: istore 165
    //   5993: goto -21 -> 5972
    //   5996: bipush 104
    //   5998: istore 165
    //   6000: goto -28 -> 5972
    //   6003: bipush 58
    //   6005: istore 165
    //   6007: goto -35 -> 5972
    //   6010: bipush 64
    //   6012: istore 165
    //   6014: goto -42 -> 5972
    //   6017: aload 166
    //   6019: iload 168
    //   6021: caload
    //   6022: istore 169
    //   6024: iload 168
    //   6026: iconst_5
    //   6027: irem
    //   6028: tableswitch	default:+32 -> 6060, 0:+53->6081, 1:+60->6088, 2:+67->6095, 3:+74->6102
    //   6061: daload
    //   6062: istore 170
    //   6064: aload 166
    //   6066: iload 168
    //   6068: iload 170
    //   6070: iload 169
    //   6072: ixor
    //   6073: i2c
    //   6074: castore
    //   6075: iinc 168 1
    //   6078: goto -4816 -> 1262
    //   6081: bipush 120
    //   6083: istore 170
    //   6085: goto -21 -> 6064
    //   6088: bipush 104
    //   6090: istore 170
    //   6092: goto -28 -> 6064
    //   6095: bipush 58
    //   6097: istore 170
    //   6099: goto -35 -> 6064
    //   6102: bipush 64
    //   6104: istore 170
    //   6106: goto -42 -> 6064
    //   6109: aload 171
    //   6111: iload 173
    //   6113: caload
    //   6114: istore 174
    //   6116: iload 173
    //   6118: iconst_5
    //   6119: irem
    //   6120: tableswitch	default:+32 -> 6152, 0:+53->6173, 1:+60->6180, 2:+67->6187, 3:+74->6194
    //   6153: daload
    //   6154: istore 175
    //   6156: aload 171
    //   6158: iload 173
    //   6160: iload 175
    //   6162: iload 174
    //   6164: ixor
    //   6165: i2c
    //   6166: castore
    //   6167: iinc 173 1
    //   6170: goto -4870 -> 1300
    //   6173: bipush 120
    //   6175: istore 175
    //   6177: goto -21 -> 6156
    //   6180: bipush 104
    //   6182: istore 175
    //   6184: goto -28 -> 6156
    //   6187: bipush 58
    //   6189: istore 175
    //   6191: goto -35 -> 6156
    //   6194: bipush 64
    //   6196: istore 175
    //   6198: goto -42 -> 6156
    //   6201: aload 176
    //   6203: iload 178
    //   6205: caload
    //   6206: istore 179
    //   6208: iload 178
    //   6210: iconst_5
    //   6211: irem
    //   6212: tableswitch	default:+32 -> 6244, 0:+53->6265, 1:+60->6272, 2:+67->6279, 3:+74->6286
    //   6245: daload
    //   6246: istore 180
    //   6248: aload 176
    //   6250: iload 178
    //   6252: iload 180
    //   6254: iload 179
    //   6256: ixor
    //   6257: i2c
    //   6258: castore
    //   6259: iinc 178 1
    //   6262: goto -4924 -> 1338
    //   6265: bipush 120
    //   6267: istore 180
    //   6269: goto -21 -> 6248
    //   6272: bipush 104
    //   6274: istore 180
    //   6276: goto -28 -> 6248
    //   6279: bipush 58
    //   6281: istore 180
    //   6283: goto -35 -> 6248
    //   6286: bipush 64
    //   6288: istore 180
    //   6290: goto -42 -> 6248
    //   6293: aload 181
    //   6295: iload 183
    //   6297: caload
    //   6298: istore 184
    //   6300: iload 183
    //   6302: iconst_5
    //   6303: irem
    //   6304: tableswitch	default:+32 -> 6336, 0:+53->6357, 1:+60->6364, 2:+67->6371, 3:+74->6378
    //   6337: daload
    //   6338: istore 185
    //   6340: aload 181
    //   6342: iload 183
    //   6344: iload 185
    //   6346: iload 184
    //   6348: ixor
    //   6349: i2c
    //   6350: castore
    //   6351: iinc 183 1
    //   6354: goto -4978 -> 1376
    //   6357: bipush 120
    //   6359: istore 185
    //   6361: goto -21 -> 6340
    //   6364: bipush 104
    //   6366: istore 185
    //   6368: goto -28 -> 6340
    //   6371: bipush 58
    //   6373: istore 185
    //   6375: goto -35 -> 6340
    //   6378: bipush 64
    //   6380: istore 185
    //   6382: goto -42 -> 6340
    //   6385: aload 186
    //   6387: iload 188
    //   6389: caload
    //   6390: istore 189
    //   6392: iload 188
    //   6394: iconst_5
    //   6395: irem
    //   6396: tableswitch	default:+32 -> 6428, 0:+53->6449, 1:+60->6456, 2:+67->6463, 3:+74->6470
    //   6429: daload
    //   6430: istore 190
    //   6432: aload 186
    //   6434: iload 188
    //   6436: iload 190
    //   6438: iload 189
    //   6440: ixor
    //   6441: i2c
    //   6442: castore
    //   6443: iinc 188 1
    //   6446: goto -5032 -> 1414
    //   6449: bipush 120
    //   6451: istore 190
    //   6453: goto -21 -> 6432
    //   6456: bipush 104
    //   6458: istore 190
    //   6460: goto -28 -> 6432
    //   6463: bipush 58
    //   6465: istore 190
    //   6467: goto -35 -> 6432
    //   6470: bipush 64
    //   6472: istore 190
    //   6474: goto -42 -> 6432
    //   6477: aload 191
    //   6479: iload 193
    //   6481: caload
    //   6482: istore 194
    //   6484: iload 193
    //   6486: iconst_5
    //   6487: irem
    //   6488: tableswitch	default:+32 -> 6520, 0:+53->6541, 1:+60->6548, 2:+67->6555, 3:+74->6562
    //   6521: daload
    //   6522: istore 195
    //   6524: aload 191
    //   6526: iload 193
    //   6528: iload 195
    //   6530: iload 194
    //   6532: ixor
    //   6533: i2c
    //   6534: castore
    //   6535: iinc 193 1
    //   6538: goto -5086 -> 1452
    //   6541: bipush 120
    //   6543: istore 195
    //   6545: goto -21 -> 6524
    //   6548: bipush 104
    //   6550: istore 195
    //   6552: goto -28 -> 6524
    //   6555: bipush 58
    //   6557: istore 195
    //   6559: goto -35 -> 6524
    //   6562: bipush 64
    //   6564: istore 195
    //   6566: goto -42 -> 6524
    //   6569: aload 196
    //   6571: iload 198
    //   6573: caload
    //   6574: istore 199
    //   6576: iload 198
    //   6578: iconst_5
    //   6579: irem
    //   6580: tableswitch	default:+32 -> 6612, 0:+53->6633, 1:+60->6640, 2:+67->6647, 3:+74->6654
    //   6613: daload
    //   6614: istore 200
    //   6616: aload 196
    //   6618: iload 198
    //   6620: iload 200
    //   6622: iload 199
    //   6624: ixor
    //   6625: i2c
    //   6626: castore
    //   6627: iinc 198 1
    //   6630: goto -5140 -> 1490
    //   6633: bipush 120
    //   6635: istore 200
    //   6637: goto -21 -> 6616
    //   6640: bipush 104
    //   6642: istore 200
    //   6644: goto -28 -> 6616
    //   6647: bipush 58
    //   6649: istore 200
    //   6651: goto -35 -> 6616
    //   6654: bipush 64
    //   6656: istore 200
    //   6658: goto -42 -> 6616
    //   6661: aload 201
    //   6663: iload 203
    //   6665: caload
    //   6666: istore 204
    //   6668: iload 203
    //   6670: iconst_5
    //   6671: irem
    //   6672: tableswitch	default:+32 -> 6704, 0:+53->6725, 1:+60->6732, 2:+67->6739, 3:+74->6746
    //   6705: daload
    //   6706: istore 205
    //   6708: aload 201
    //   6710: iload 203
    //   6712: iload 205
    //   6714: iload 204
    //   6716: ixor
    //   6717: i2c
    //   6718: castore
    //   6719: iinc 203 1
    //   6722: goto -5194 -> 1528
    //   6725: bipush 120
    //   6727: istore 205
    //   6729: goto -21 -> 6708
    //   6732: bipush 104
    //   6734: istore 205
    //   6736: goto -28 -> 6708
    //   6739: bipush 58
    //   6741: istore 205
    //   6743: goto -35 -> 6708
    //   6746: bipush 64
    //   6748: istore 205
    //   6750: goto -42 -> 6708
    //   6753: aload 206
    //   6755: iload 208
    //   6757: caload
    //   6758: istore 209
    //   6760: iload 208
    //   6762: iconst_5
    //   6763: irem
    //   6764: tableswitch	default:+32 -> 6796, 0:+53->6817, 1:+60->6824, 2:+67->6831, 3:+74->6838
    //   6797: daload
    //   6798: istore 210
    //   6800: aload 206
    //   6802: iload 208
    //   6804: iload 210
    //   6806: iload 209
    //   6808: ixor
    //   6809: i2c
    //   6810: castore
    //   6811: iinc 208 1
    //   6814: goto -5248 -> 1566
    //   6817: bipush 120
    //   6819: istore 210
    //   6821: goto -21 -> 6800
    //   6824: bipush 104
    //   6826: istore 210
    //   6828: goto -28 -> 6800
    //   6831: bipush 58
    //   6833: istore 210
    //   6835: goto -35 -> 6800
    //   6838: bipush 64
    //   6840: istore 210
    //   6842: goto -42 -> 6800
    //   6845: aload 211
    //   6847: iload 213
    //   6849: caload
    //   6850: istore 214
    //   6852: iload 213
    //   6854: iconst_5
    //   6855: irem
    //   6856: tableswitch	default:+32 -> 6888, 0:+53->6909, 1:+60->6916, 2:+67->6923, 3:+74->6930
    //   6889: daload
    //   6890: istore 215
    //   6892: aload 211
    //   6894: iload 213
    //   6896: iload 215
    //   6898: iload 214
    //   6900: ixor
    //   6901: i2c
    //   6902: castore
    //   6903: iinc 213 1
    //   6906: goto -5302 -> 1604
    //   6909: bipush 120
    //   6911: istore 215
    //   6913: goto -21 -> 6892
    //   6916: bipush 104
    //   6918: istore 215
    //   6920: goto -28 -> 6892
    //   6923: bipush 58
    //   6925: istore 215
    //   6927: goto -35 -> 6892
    //   6930: bipush 64
    //   6932: istore 215
    //   6934: goto -42 -> 6892
    //   6937: aload 216
    //   6939: iload 218
    //   6941: caload
    //   6942: istore 219
    //   6944: iload 218
    //   6946: iconst_5
    //   6947: irem
    //   6948: tableswitch	default:+32 -> 6980, 0:+53->7001, 1:+60->7008, 2:+67->7015, 3:+74->7022
    //   6981: daload
    //   6982: istore 220
    //   6984: aload 216
    //   6986: iload 218
    //   6988: iload 220
    //   6990: iload 219
    //   6992: ixor
    //   6993: i2c
    //   6994: castore
    //   6995: iinc 218 1
    //   6998: goto -5356 -> 1642
    //   7001: bipush 120
    //   7003: istore 220
    //   7005: goto -21 -> 6984
    //   7008: bipush 104
    //   7010: istore 220
    //   7012: goto -28 -> 6984
    //   7015: bipush 58
    //   7017: istore 220
    //   7019: goto -35 -> 6984
    //   7022: bipush 64
    //   7024: istore 220
    //   7026: goto -42 -> 6984
    //   7029: aload 221
    //   7031: iload 223
    //   7033: caload
    //   7034: istore 224
    //   7036: iload 223
    //   7038: iconst_5
    //   7039: irem
    //   7040: tableswitch	default:+32 -> 7072, 0:+53->7093, 1:+60->7100, 2:+67->7107, 3:+74->7114
    //   7073: daload
    //   7074: istore 225
    //   7076: aload 221
    //   7078: iload 223
    //   7080: iload 225
    //   7082: iload 224
    //   7084: ixor
    //   7085: i2c
    //   7086: castore
    //   7087: iinc 223 1
    //   7090: goto -5410 -> 1680
    //   7093: bipush 120
    //   7095: istore 225
    //   7097: goto -21 -> 7076
    //   7100: bipush 104
    //   7102: istore 225
    //   7104: goto -28 -> 7076
    //   7107: bipush 58
    //   7109: istore 225
    //   7111: goto -35 -> 7076
    //   7114: bipush 64
    //   7116: istore 225
    //   7118: goto -42 -> 7076
    //   7121: aload 226
    //   7123: iload 228
    //   7125: caload
    //   7126: istore 229
    //   7128: iload 228
    //   7130: iconst_5
    //   7131: irem
    //   7132: tableswitch	default:+32 -> 7164, 0:+53->7185, 1:+60->7192, 2:+67->7199, 3:+74->7206
    //   7165: daload
    //   7166: istore 230
    //   7168: aload 226
    //   7170: iload 228
    //   7172: iload 230
    //   7174: iload 229
    //   7176: ixor
    //   7177: i2c
    //   7178: castore
    //   7179: iinc 228 1
    //   7182: goto -5464 -> 1718
    //   7185: bipush 120
    //   7187: istore 230
    //   7189: goto -21 -> 7168
    //   7192: bipush 104
    //   7194: istore 230
    //   7196: goto -28 -> 7168
    //   7199: bipush 58
    //   7201: istore 230
    //   7203: goto -35 -> 7168
    //   7206: bipush 64
    //   7208: istore 230
    //   7210: goto -42 -> 7168
    //   7213: aload 231
    //   7215: iload 233
    //   7217: caload
    //   7218: istore 234
    //   7220: iload 233
    //   7222: iconst_5
    //   7223: irem
    //   7224: tableswitch	default:+32 -> 7256, 0:+53->7277, 1:+60->7284, 2:+67->7291, 3:+74->7298
    //   7257: daload
    //   7258: istore 235
    //   7260: aload 231
    //   7262: iload 233
    //   7264: iload 235
    //   7266: iload 234
    //   7268: ixor
    //   7269: i2c
    //   7270: castore
    //   7271: iinc 233 1
    //   7274: goto -5518 -> 1756
    //   7277: bipush 120
    //   7279: istore 235
    //   7281: goto -21 -> 7260
    //   7284: bipush 104
    //   7286: istore 235
    //   7288: goto -28 -> 7260
    //   7291: bipush 58
    //   7293: istore 235
    //   7295: goto -35 -> 7260
    //   7298: bipush 64
    //   7300: istore 235
    //   7302: goto -42 -> 7260
    //   7305: aload 236
    //   7307: iload 238
    //   7309: caload
    //   7310: istore 239
    //   7312: iload 238
    //   7314: iconst_5
    //   7315: irem
    //   7316: tableswitch	default:+32 -> 7348, 0:+53->7369, 1:+60->7376, 2:+67->7383, 3:+74->7390
    //   7349: daload
    //   7350: istore 240
    //   7352: aload 236
    //   7354: iload 238
    //   7356: iload 240
    //   7358: iload 239
    //   7360: ixor
    //   7361: i2c
    //   7362: castore
    //   7363: iinc 238 1
    //   7366: goto -5572 -> 1794
    //   7369: bipush 120
    //   7371: istore 240
    //   7373: goto -21 -> 7352
    //   7376: bipush 104
    //   7378: istore 240
    //   7380: goto -28 -> 7352
    //   7383: bipush 58
    //   7385: istore 240
    //   7387: goto -35 -> 7352
    //   7390: bipush 64
    //   7392: istore 240
    //   7394: goto -42 -> 7352
    //   7397: aload 241
    //   7399: iload 243
    //   7401: caload
    //   7402: istore 244
    //   7404: iload 243
    //   7406: iconst_5
    //   7407: irem
    //   7408: tableswitch	default:+32 -> 7440, 0:+53->7461, 1:+60->7468, 2:+67->7475, 3:+74->7482
    //   7441: daload
    //   7442: istore 245
    //   7444: aload 241
    //   7446: iload 243
    //   7448: iload 245
    //   7450: iload 244
    //   7452: ixor
    //   7453: i2c
    //   7454: castore
    //   7455: iinc 243 1
    //   7458: goto -5626 -> 1832
    //   7461: bipush 120
    //   7463: istore 245
    //   7465: goto -21 -> 7444
    //   7468: bipush 104
    //   7470: istore 245
    //   7472: goto -28 -> 7444
    //   7475: bipush 58
    //   7477: istore 245
    //   7479: goto -35 -> 7444
    //   7482: bipush 64
    //   7484: istore 245
    //   7486: goto -42 -> 7444
    //   7489: aload 246
    //   7491: iload 248
    //   7493: caload
    //   7494: istore 249
    //   7496: iload 248
    //   7498: iconst_5
    //   7499: irem
    //   7500: tableswitch	default:+32 -> 7532, 0:+53->7553, 1:+60->7560, 2:+67->7567, 3:+74->7574
    //   7533: daload
    //   7534: istore 250
    //   7536: aload 246
    //   7538: iload 248
    //   7540: iload 250
    //   7542: iload 249
    //   7544: ixor
    //   7545: i2c
    //   7546: castore
    //   7547: iinc 248 1
    //   7550: goto -5680 -> 1870
    //   7553: bipush 120
    //   7555: istore 250
    //   7557: goto -21 -> 7536
    //   7560: bipush 104
    //   7562: istore 250
    //   7564: goto -28 -> 7536
    //   7567: bipush 58
    //   7569: istore 250
    //   7571: goto -35 -> 7536
    //   7574: bipush 64
    //   7576: istore 250
    //   7578: goto -42 -> 7536
    //   7581: aload 251
    //   7583: iload 253
    //   7585: caload
    //   7586: istore 254
    //   7588: iload 253
    //   7590: iconst_5
    //   7591: irem
    //   7592: tableswitch	default:+32 -> 7624, 0:+53->7645, 1:+60->7652, 2:+67->7659, 3:+74->7666
    //   7625: daload
    //   7626: istore 255
    //   7628: aload 251
    //   7630: iload 253
    //   7632: iload 255
    //   7634: iload 254
    //   7636: ixor
    //   7637: i2c
    //   7638: castore
    //   7639: iinc 253 1
    //   7642: goto -5734 -> 1908
    //   7645: bipush 120
    //   7647: istore 255
    //   7649: goto -21 -> 7628
    //   7652: bipush 104
    //   7654: istore 255
    //   7656: goto -28 -> 7628
    //   7659: bipush 58
    //   7661: istore 255
    //   7663: goto -35 -> 7628
    //   7666: bipush 64
    //   7668: istore 255
    //   7670: goto -42 -> 7628
    //   7673: wide
    //   7677: wide
    //   7681: caload
    //   7682: wide
    //   7686: wide
    //   7690: iconst_5
    //   7691: irem
    //   7692: tableswitch	default:+32 -> 7724, 0:+66->7758, 1:+75->7767, 2:+84->7776, 3:+93->7785
    //   7725: daload
    //   7726: wide
    //   7730: wide
    //   7734: wide
    //   7738: wide
    //   7742: wide
    //   7746: ixor
    //   7747: i2c
    //   7748: castore
    //   7749: wide
    //   7755: goto -5801 -> 1954
    //   7758: bipush 120
    //   7760: wide
    //   7764: goto -34 -> 7730
    //   7767: bipush 104
    //   7769: wide
    //   7773: goto -43 -> 7730
    //   7776: bipush 58
    //   7778: wide
    //   7782: goto -52 -> 7730
    //   7785: bipush 64
    //   7787: wide
    //   7791: goto -61 -> 7730
    //   7794: wide
    //   7798: wide
    //   7802: caload
    //   7803: wide
    //   7807: wide
    //   7811: iconst_5
    //   7812: irem
    //   7813: tableswitch	default:+31 -> 7844, 0:+65->7878, 1:+74->7887, 2:+83->7896, 3:+92->7905
    //   7845: daload
    //   7846: wide
    //   7850: wide
    //   7854: wide
    //   7858: wide
    //   7862: wide
    //   7866: ixor
    //   7867: i2c
    //   7868: castore
    //   7869: wide
    //   7875: goto -5869 -> 2006
    //   7878: bipush 120
    //   7880: wide
    //   7884: goto -34 -> 7850
    //   7887: bipush 104
    //   7889: wide
    //   7893: goto -43 -> 7850
    //   7896: bipush 58
    //   7898: wide
    //   7902: goto -52 -> 7850
    //   7905: bipush 64
    //   7907: wide
    //   7911: goto -61 -> 7850
    //   7914: wide
    //   7918: wide
    //   7922: caload
    //   7923: wide
    //   7927: wide
    //   7931: iconst_5
    //   7932: irem
    //   7933: tableswitch	default:+31 -> 7964, 0:+65->7998, 1:+74->8007, 2:+83->8016, 3:+92->8025
    //   7965: daload
    //   7966: wide
    //   7970: wide
    //   7974: wide
    //   7978: wide
    //   7982: wide
    //   7986: ixor
    //   7987: i2c
    //   7988: castore
    //   7989: wide
    //   7995: goto -5937 -> 2058
    //   7998: bipush 120
    //   8000: wide
    //   8004: goto -34 -> 7970
    //   8007: bipush 104
    //   8009: wide
    //   8013: goto -43 -> 7970
    //   8016: bipush 58
    //   8018: wide
    //   8022: goto -52 -> 7970
    //   8025: bipush 64
    //   8027: wide
    //   8031: goto -61 -> 7970
    //   8034: wide
    //   8038: wide
    //   8042: caload
    //   8043: wide
    //   8047: wide
    //   8051: iconst_5
    //   8052: irem
    //   8053: tableswitch	default:+31 -> 8084, 0:+65->8118, 1:+74->8127, 2:+83->8136, 3:+92->8145
    //   8085: daload
    //   8086: wide
    //   8090: wide
    //   8094: wide
    //   8098: wide
    //   8102: wide
    //   8106: ixor
    //   8107: i2c
    //   8108: castore
    //   8109: wide
    //   8115: goto -6005 -> 2110
    //   8118: bipush 120
    //   8120: wide
    //   8124: goto -34 -> 8090
    //   8127: bipush 104
    //   8129: wide
    //   8133: goto -43 -> 8090
    //   8136: bipush 58
    //   8138: wide
    //   8142: goto -52 -> 8090
    //   8145: bipush 64
    //   8147: wide
    //   8151: goto -61 -> 8090
    //   8154: wide
    //   8158: wide
    //   8162: caload
    //   8163: wide
    //   8167: wide
    //   8171: iconst_5
    //   8172: irem
    //   8173: tableswitch	default:+31 -> 8204, 0:+65->8238, 1:+74->8247, 2:+83->8256, 3:+92->8265
    //   8205: daload
    //   8206: wide
    //   8210: wide
    //   8214: wide
    //   8218: wide
    //   8222: wide
    //   8226: ixor
    //   8227: i2c
    //   8228: castore
    //   8229: wide
    //   8235: goto -6073 -> 2162
    //   8238: bipush 120
    //   8240: wide
    //   8244: goto -34 -> 8210
    //   8247: bipush 104
    //   8249: wide
    //   8253: goto -43 -> 8210
    //   8256: bipush 58
    //   8258: wide
    //   8262: goto -52 -> 8210
    //   8265: bipush 64
    //   8267: wide
    //   8271: goto -61 -> 8210
    //   8274: wide
    //   8278: wide
    //   8282: caload
    //   8283: wide
    //   8287: wide
    //   8291: iconst_5
    //   8292: irem
    //   8293: tableswitch	default:+31 -> 8324, 0:+65->8358, 1:+74->8367, 2:+83->8376, 3:+92->8385
    //   8325: daload
    //   8326: wide
    //   8330: wide
    //   8334: wide
    //   8338: wide
    //   8342: wide
    //   8346: ixor
    //   8347: i2c
    //   8348: castore
    //   8349: wide
    //   8355: goto -6141 -> 2214
    //   8358: bipush 120
    //   8360: wide
    //   8364: goto -34 -> 8330
    //   8367: bipush 104
    //   8369: wide
    //   8373: goto -43 -> 8330
    //   8376: bipush 58
    //   8378: wide
    //   8382: goto -52 -> 8330
    //   8385: bipush 64
    //   8387: wide
    //   8391: goto -61 -> 8330
    //   8394: wide
    //   8398: wide
    //   8402: caload
    //   8403: wide
    //   8407: wide
    //   8411: iconst_5
    //   8412: irem
    //   8413: tableswitch	default:+31 -> 8444, 0:+65->8478, 1:+74->8487, 2:+83->8496, 3:+92->8505
    //   8445: daload
    //   8446: wide
    //   8450: wide
    //   8454: wide
    //   8458: wide
    //   8462: wide
    //   8466: ixor
    //   8467: i2c
    //   8468: castore
    //   8469: wide
    //   8475: goto -6209 -> 2266
    //   8478: bipush 120
    //   8480: wide
    //   8484: goto -34 -> 8450
    //   8487: bipush 104
    //   8489: wide
    //   8493: goto -43 -> 8450
    //   8496: bipush 58
    //   8498: wide
    //   8502: goto -52 -> 8450
    //   8505: bipush 64
    //   8507: wide
    //   8511: goto -61 -> 8450
    //   8514: wide
    //   8518: wide
    //   8522: caload
    //   8523: wide
    //   8527: wide
    //   8531: iconst_5
    //   8532: irem
    //   8533: tableswitch	default:+31 -> 8564, 0:+65->8598, 1:+74->8607, 2:+83->8616, 3:+92->8625
    //   8565: daload
    //   8566: wide
    //   8570: wide
    //   8574: wide
    //   8578: wide
    //   8582: wide
    //   8586: ixor
    //   8587: i2c
    //   8588: castore
    //   8589: wide
    //   8595: goto -6277 -> 2318
    //   8598: bipush 120
    //   8600: wide
    //   8604: goto -34 -> 8570
    //   8607: bipush 104
    //   8609: wide
    //   8613: goto -43 -> 8570
    //   8616: bipush 58
    //   8618: wide
    //   8622: goto -52 -> 8570
    //   8625: bipush 64
    //   8627: wide
    //   8631: goto -61 -> 8570
    //   8634: wide
    //   8638: wide
    //   8642: caload
    //   8643: wide
    //   8647: wide
    //   8651: iconst_5
    //   8652: irem
    //   8653: tableswitch	default:+31 -> 8684, 0:+65->8718, 1:+74->8727, 2:+83->8736, 3:+92->8745
    //   8685: daload
    //   8686: wide
    //   8690: wide
    //   8694: wide
    //   8698: wide
    //   8702: wide
    //   8706: ixor
    //   8707: i2c
    //   8708: castore
    //   8709: wide
    //   8715: goto -6345 -> 2370
    //   8718: bipush 120
    //   8720: wide
    //   8724: goto -34 -> 8690
    //   8727: bipush 104
    //   8729: wide
    //   8733: goto -43 -> 8690
    //   8736: bipush 58
    //   8738: wide
    //   8742: goto -52 -> 8690
    //   8745: bipush 64
    //   8747: wide
    //   8751: goto -61 -> 8690
    //   8754: wide
    //   8758: wide
    //   8762: caload
    //   8763: wide
    //   8767: wide
    //   8771: iconst_5
    //   8772: irem
    //   8773: tableswitch	default:+31 -> 8804, 0:+65->8838, 1:+74->8847, 2:+83->8856, 3:+92->8865
    //   8805: daload
    //   8806: wide
    //   8810: wide
    //   8814: wide
    //   8818: wide
    //   8822: wide
    //   8826: ixor
    //   8827: i2c
    //   8828: castore
    //   8829: wide
    //   8835: goto -6413 -> 2422
    //   8838: bipush 120
    //   8840: wide
    //   8844: goto -34 -> 8810
    //   8847: bipush 104
    //   8849: wide
    //   8853: goto -43 -> 8810
    //   8856: bipush 58
    //   8858: wide
    //   8862: goto -52 -> 8810
    //   8865: bipush 64
    //   8867: wide
    //   8871: goto -61 -> 8810
    //   8874: wide
    //   8878: wide
    //   8882: caload
    //   8883: wide
    //   8887: wide
    //   8891: iconst_5
    //   8892: irem
    //   8893: tableswitch	default:+31 -> 8924, 0:+65->8958, 1:+74->8967, 2:+83->8976, 3:+92->8985
    //   8925: daload
    //   8926: wide
    //   8930: wide
    //   8934: wide
    //   8938: wide
    //   8942: wide
    //   8946: ixor
    //   8947: i2c
    //   8948: castore
    //   8949: wide
    //   8955: goto -6481 -> 2474
    //   8958: bipush 120
    //   8960: wide
    //   8964: goto -34 -> 8930
    //   8967: bipush 104
    //   8969: wide
    //   8973: goto -43 -> 8930
    //   8976: bipush 58
    //   8978: wide
    //   8982: goto -52 -> 8930
    //   8985: bipush 64
    //   8987: wide
    //   8991: goto -61 -> 8930
    //   8994: wide
    //   8998: wide
    //   9002: caload
    //   9003: wide
    //   9007: wide
    //   9011: iconst_5
    //   9012: irem
    //   9013: tableswitch	default:+31 -> 9044, 0:+65->9078, 1:+74->9087, 2:+83->9096, 3:+92->9105
    //   9045: daload
    //   9046: wide
    //   9050: wide
    //   9054: wide
    //   9058: wide
    //   9062: wide
    //   9066: ixor
    //   9067: i2c
    //   9068: castore
    //   9069: wide
    //   9075: goto -6549 -> 2526
    //   9078: bipush 120
    //   9080: wide
    //   9084: goto -34 -> 9050
    //   9087: bipush 104
    //   9089: wide
    //   9093: goto -43 -> 9050
    //   9096: bipush 58
    //   9098: wide
    //   9102: goto -52 -> 9050
    //   9105: bipush 64
    //   9107: wide
    //   9111: goto -61 -> 9050
    //   9114: wide
    //   9118: wide
    //   9122: caload
    //   9123: wide
    //   9127: wide
    //   9131: iconst_5
    //   9132: irem
    //   9133: tableswitch	default:+31 -> 9164, 0:+65->9198, 1:+74->9207, 2:+83->9216, 3:+92->9225
    //   9165: daload
    //   9166: wide
    //   9170: wide
    //   9174: wide
    //   9178: wide
    //   9182: wide
    //   9186: ixor
    //   9187: i2c
    //   9188: castore
    //   9189: wide
    //   9195: goto -6617 -> 2578
    //   9198: bipush 120
    //   9200: wide
    //   9204: goto -34 -> 9170
    //   9207: bipush 104
    //   9209: wide
    //   9213: goto -43 -> 9170
    //   9216: bipush 58
    //   9218: wide
    //   9222: goto -52 -> 9170
    //   9225: bipush 64
    //   9227: wide
    //   9231: goto -61 -> 9170
  }

  private String a(String paramString, int paramInt)
  {
    String str1 = null;
    boolean bool = b.a;
    if (paramString.endsWith(z[14]))
    {
      paramString = paramString.substring(0, -2 + paramString.length());
      if (!bool);
    }
    else if (paramString.endsWith("\n"))
    {
      paramString = paramString.substring(0, -1 + paramString.length());
      if (!bool)
        break label67;
    }
    while (true)
    {
      return str1;
      label67: String str2 = paramString.replaceAll(z[14], "\n");
      if (paramInt == 1)
        str1 = str2.replaceAll("\n", z[13]);
      else if (paramInt == 2)
        str1 = str2.replaceAll("\n", z[15]);
    }
  }

  private void a(g paramg)
  {
    boolean bool = b.a;
    if (paramg.k != null)
    {
      Iterator localIterator = paramg.k.keySet().iterator();
      do
      {
        if (!localIterator.hasNext())
          break;
        String str = (String)localIterator.next();
        if (g.a.containsKey(str))
        {
          e locale = (e)((List)paramg.k.get(str)).get(0);
          this.b.append(str).append(";");
          if ((locale.e != null) && (locale.e.size() > 0))
          {
            this.b.append(z[0]).append(locale.e.toArray()[0]).append(":");
            if (!bool);
          }
          else
          {
            this.b.append(z[1]).append(":");
          }
          this.b.append(locale.b).append(this.a);
        }
      }
      while (!bool);
    }
  }

  private void a(i parami, int paramInt)
  {
    boolean bool = b.a;
    z[11];
    if (!a(parami.c))
      if (parami.b == 0)
      {
        g5.a(z[12] + parami);
        this.c = (1 + this.c);
        this.b.append(z[7]).append(this.c).append(z[6]).append(parami.c).append(this.a);
        this.b.append(z[7]).append(this.c).append(z[8]).append(parami.e).append(this.a);
        if (!bool);
      }
      else
      {
        String str = App.Mb.getString(ContactsContract.CommonDataKinds.Email.getTypeLabelResource(parami.b));
        if (paramInt == 1)
        {
          this.b.append(z[10]);
          if (!bool);
        }
        else
        {
          this.b.append(z[9]);
        }
        this.b.append(str).append(":").append(parami.c).append(this.a);
      }
  }

  private void a(j paramj)
  {
    boolean bool = b.a;
    g5.a(z[3] + paramj);
    this.b.append(z[2]);
    if (paramj.c != null)
    {
      this.b.append(paramj.c).append(";");
      if (!bool);
    }
    else
    {
      this.b.append(";");
    }
    if (paramj.b != null)
    {
      this.b.append(paramj.b).append(";");
      if (!bool);
    }
    else
    {
      this.b.append(";");
    }
    if (paramj.d != null)
    {
      this.b.append(paramj.d).append(";");
      if (!bool);
    }
    else
    {
      this.b.append(";");
    }
    if (paramj.e != null)
    {
      this.b.append(paramj.e).append(";");
      if (!bool);
    }
    else
    {
      this.b.append(";");
    }
    if (paramj.f != null)
      this.b.append(paramj.f);
    this.b.append(this.a);
    this.b.append(z[4]).append(paramj.a).append(this.a);
  }

  private void a(List<l> paramList, int paramInt)
  {
    boolean bool = b.a;
    Iterator localIterator = paramList.iterator();
    do
    {
      if (!localIterator.hasNext())
        break;
      l locall = (l)localIterator.next();
      if (!a(locall.b))
        if (locall.a == 0)
        {
          this.c = (1 + this.c);
          this.b.append(z[7]).append(this.c).append(z[32]).append(locall.b).append(this.a);
          this.b.append(z[7]).append(this.c).append(z[8]).append(locall.c).append(this.a);
          if (!bool);
        }
        else
        {
          String str = App.Mb.getString(ContactsContract.CommonDataKinds.Phone.getTypeLabelResource(locall.a));
          if ((paramInt == 2) && (str.indexOf(";") != -1))
            str = str.replace(";", ",");
          if (paramInt == 1)
          {
            this.b.append(z[31]);
            if (!bool);
          }
          else
          {
            this.b.append(z[30]);
          }
          this.b.append(str).append(":").append(locall.b).append(this.a);
        }
    }
    while (!bool);
  }

  private void a(byte[] paramArrayOfByte, String paramString, int paramInt)
    throws b
  {
    this.b.append(z[5]).append(new String(wb.a(paramArrayOfByte))).append(this.a);
  }

  private boolean a(String paramString)
  {
    if ((paramString == null) || (paramString.trim().equals("")));
    for (boolean bool = true; ; bool = false)
      return bool;
  }

  private void b(i parami, int paramInt)
  {
    boolean bool = b.a;
    this.c = (1 + this.c);
    if (parami.d != null)
    {
      g5.a(z[35] + parami);
      if (parami.b == 0)
      {
        this.b.append(z[7]).append(this.c).append(z[34]).append(parami.d.a()).append(this.a);
        this.b.append(z[7]).append(this.c).append(z[36]);
        if (parami.d.e == null);
      }
    }
    try
    {
      this.b.append(jp.e(parami.d.e).toLowerCase());
      this.b.append(this.a);
      this.b.append(z[7]).append(this.c).append(z[8]).append(parami.e).append(this.a);
      if (bool)
      {
        String str = App.Mb.getString(ContactsContract.CommonDataKinds.StructuredPostal.getTypeLabelResource(parami.b));
        this.b.append(z[7]).append(this.c).append(z[33]).append(str).append(z[37]).append(parami.d.a()).append(this.a);
        this.b.append(z[7]).append(this.c).append(z[36]);
        if (parami.d.e == null);
      }
    }
    catch (IOException localIOException2)
    {
      try
      {
        this.b.append(jp.e(parami.d.e).toLowerCase());
        this.b.append(this.a);
        if (bool)
          g5.d(z[38]);
        return;
        localIOException2 = localIOException2;
        g5.b(z[39], localIOException2);
      }
      catch (IOException localIOException1)
      {
        while (true)
          g5.b(z[39], localIOException1);
      }
    }
  }

  private void b(List<i> paramList, int paramInt)
  {
    boolean bool = b.a;
    Iterator localIterator = paramList.iterator();
    do
    {
      if (!localIterator.hasNext())
        break;
      i locali = (i)localIterator.next();
      if (locali.a == ContactsContract.CommonDataKinds.Email.class)
      {
        a(locali, paramInt);
        if (!bool);
      }
      else if (locali.a == ContactsContract.CommonDataKinds.StructuredPostal.class)
      {
        b(locali, paramInt);
      }
    }
    while (!bool);
  }

  public String a(g paramg, int paramInt)
    throws b
  {
    boolean bool1 = b.a;
    this.b = new StringBuilder();
    if ((paramg.c != null) && (paramg.c.a == null))
      paramg.c.a = "";
    if (paramInt == 1)
    {
      this.a = "\n";
      if (!bool1);
    }
    else if (paramInt == 2)
    {
      this.a = "\n";
      if (!bool1);
    }
    else
    {
      throw new b(z[29]);
    }
    this.b.append(z[23]).append(this.a);
    if (paramInt == 1)
    {
      this.b.append(z[27]).append(this.a);
      if (!bool1);
    }
    else
    {
      this.b.append(z[26]).append(this.a);
    }
    if (paramg.c != null)
      a(paramg.c);
    if ((paramg.k != null) && (paramg.k.containsKey(z[24])))
      this.b.append(z[21]).append(((e)((List)paramg.k.get(z[24])).get(0)).b).append(this.a);
    if (paramg.c != null)
    {
      if (paramg.c.g != null)
        this.b.append(z[16]).append(paramg.c.g).append(this.a);
      if (paramg.c.h != null)
        this.b.append(z[25]).append(paramg.c.h).append(this.a);
    }
    if ((paramg.j != null) && (paramg.j.size() > 0))
    {
      String str2 = ((k)paramg.j.get(0)).b;
      String str3 = ((k)paramg.j.get(0)).c;
      if (str2 != null)
        this.b.append(z[17]).append(str2).append(this.a);
      if (str3 != null)
        this.b.append(z[28]).append(str3).append(this.a);
    }
    if ((paramg.e.size() > 0) && (!a((String)paramg.e.get(0))))
      this.b.append(z[18]).append(a((String)paramg.e.get(0), paramInt)).append(this.a);
    if (paramg.h != null)
      a(paramg.h, paramInt);
    if (paramg.i != null)
      b(paramg.i, paramInt);
    if ((paramg.k != null) && (paramg.k.containsKey(z[20])))
      this.b.append(z[22]).append(((e)((List)paramg.k.get(z[20])).get(0)).b).append(this.a);
    a(paramg);
    if (paramg.f != null)
      a(paramg.f, paramg.g, paramInt);
    this.b.append(z[19]);
    String str1 = this.b.toString();
    if (App.wc != 0)
      if (!bool1)
        break label712;
    label712: for (boolean bool2 = false; ; bool2 = true)
    {
      b.a = bool2;
      return str1;
    }
  }
}