package com.whatsapp;

import android.location.Location;
import java.util.HashSet;
import java.util.Set;
import org.json.JSONArray;
import org.json.JSONException;
import org.json.JSONObject;

public class fy
{
  private static final String[] z;
  public String a;
  public String b;
  public String c;
  public String d;
  public double e;
  public double f;
  public String g;
  public String h;
  public String i;
  public String j;
  public String k;
  public Set<String> l;
  public boolean m;
  public double n;
  private Location o;
  public int p;

  static
  {
    String[] arrayOfString = new String[24];
    char[] arrayOfChar1 = "I~a_\033^ud_".toCharArray();
    int i1 = arrayOfChar1.length;
    int i2 = 0;
    char[] arrayOfChar2;
    int i6;
    char[] arrayOfChar3;
    int i10;
    char[] arrayOfChar4;
    int i14;
    char[] arrayOfChar5;
    int i18;
    char[] arrayOfChar6;
    int i22;
    char[] arrayOfChar7;
    int i26;
    char[] arrayOfChar8;
    int i30;
    char[] arrayOfChar9;
    int i34;
    char[] arrayOfChar10;
    int i38;
    char[] arrayOfChar11;
    int i42;
    char[] arrayOfChar12;
    int i46;
    char[] arrayOfChar13;
    int i50;
    char[] arrayOfChar14;
    int i54;
    char[] arrayOfChar15;
    int i58;
    char[] arrayOfChar16;
    int i62;
    char[] arrayOfChar17;
    int i66;
    char[] arrayOfChar18;
    int i70;
    char[] arrayOfChar19;
    int i74;
    char[] arrayOfChar20;
    int i78;
    char[] arrayOfChar21;
    int i82;
    char[] arrayOfChar22;
    int i86;
    char[] arrayOfChar23;
    int i90;
    char[] arrayOfChar24;
    int i94;
    if (i1 <= i2)
    {
      arrayOfString[0] = new String(arrayOfChar1).intern();
      arrayOfChar2 = "RxhT".toCharArray();
      int i5 = arrayOfChar2.length;
      i6 = 0;
      if (i5 <= i6)
      {
        arrayOfString[1] = new String(arrayOfChar2).intern();
        arrayOfChar3 = "\027;RT��O~c\032:Ozs_\032".toCharArray();
        int i9 = arrayOfChar3.length;
        i10 = 0;
        if (i9 > i10)
          break label1085;
        arrayOfString[2] = new String(arrayOfChar3).intern();
        arrayOfChar4 = "Obw_\032".toCharArray();
        int i13 = arrayOfChar4.length;
        i14 = 0;
        if (i13 > i14)
          break label1177;
        arrayOfString[3] = new String(arrayOfChar4).intern();
        arrayOfChar5 = "R".toCharArray();
        int i17 = arrayOfChar5.length;
        i18 = 0;
        if (i17 > i18)
          break label1269;
        arrayOfString[4] = new String(arrayOfChar5).intern();
        arrayOfChar6 = "Wu`".toCharArray();
        int i21 = arrayOfChar6.length;
        i22 = 0;
        if (i21 > i22)
          break label1361;
        arrayOfString[5] = new String(arrayOfChar6).intern();
        arrayOfChar7 = "Wtd[\035Rti".toCharArray();
        int i25 = arrayOfChar7.length;
        i26 = 0;
        if (i25 > i26)
          break label1453;
        arrayOfString[6] = new String(arrayOfChar7).intern();
        arrayOfChar8 = "IzsS\007\\".toCharArray();
        int i29 = arrayOfChar8.length;
        i30 = 0;
        if (i29 > i30)
          break label1545;
        arrayOfString[7] = new String(arrayOfChar8).intern();
        arrayOfChar9 = "Uzj_".toCharArray();
        int i33 = arrayOfChar9.length;
        i34 = 0;
        if (i33 > i34)
          break label1637;
        arrayOfString[8] = new String(arrayOfChar9).intern();
        arrayOfChar10 = "\\~hW\fOi~".toCharArray();
        int i37 = arrayOfChar10.length;
        i38 = 0;
        if (i37 > i38)
          break label1729;
        arrayOfString[9] = new String(arrayOfChar10).intern();
        arrayOfChar11 = "MrdS\007Ro~".toCharArray();
        int i41 = arrayOfChar11.length;
        i42 = 0;
        if (i41 > i42)
          break label1821;
        arrayOfString[10] = new String(arrayOfChar11).intern();
        arrayOfChar12 = "]tuW\bOob^6ZcH\fHh".toCharArray();
        int i45 = arrayOfChar12.length;
        i46 = 0;
        if (i45 > i46)
          break label1913;
        arrayOfString[11] = new String(arrayOfChar12).intern();
        arrayOfChar13 = "]tuW\bOob^6KshT\fdurW\013^i".toCharArray();
        int i49 = arrayOfChar13.length;
        i50 = 0;
        if (i49 > i50)
          break label2005;
        arrayOfString[12] = new String(arrayOfChar13).intern();
        arrayOfChar14 = "Nik".toCharArray();
        int i53 = arrayOfChar14.length;
        i54 = 0;
        if (i53 > i54)
          break label2097;
        arrayOfString[13] = new String(arrayOfChar14).intern();
        arrayOfChar15 = "Wzs".toCharArray();
        int i57 = arrayOfChar15.length;
        i58 = 0;
        if (i57 > i58)
          break label2189;
        arrayOfString[14] = new String(arrayOfChar15).intern();
        arrayOfChar16 = "I~tO\005O".toCharArray();
        int i61 = arrayOfChar16.length;
        i62 = 0;
        if (i61 > i62)
          break label2281;
        arrayOfString[15] = new String(arrayOfChar16).intern();
        arrayOfChar17 = "tP".toCharArray();
        int i65 = arrayOfChar17.length;
        i66 = 0;
        if (i65 > i66)
          break label2373;
        arrayOfString[16] = new String(arrayOfChar17).intern();
        arrayOfChar18 = "HofN\034H".toCharArray();
        int i69 = arrayOfChar18.length;
        i70 = 0;
        if (i69 > i70)
          break label2465;
        arrayOfString[17] = new String(arrayOfChar18).intern();
        arrayOfChar19 = "HofN\f".toCharArray();
        int i73 = arrayOfChar19.length;
        i74 = 0;
        if (i73 > i74)
          break label2557;
        arrayOfString[18] = new String(arrayOfChar19).intern();
        arrayOfChar20 = "ZcH\fHh".toCharArray();
        int i77 = arrayOfChar20.length;
        i78 = 0;
        if (i77 > i78)
          break label2649;
        arrayOfString[19] = new String(arrayOfChar20).intern();
        arrayOfChar21 = "\027;".toCharArray();
        int i81 = arrayOfChar21.length;
        i82 = 0;
        if (i81 > i82)
          break label2741;
        arrayOfString[20] = new String(arrayOfChar21).intern();
        arrayOfChar22 = "KttN\bWXh^\f".toCharArray();
        int i85 = arrayOfChar22.length;
        i86 = 0;
        if (i85 > i86)
          break label2833;
        arrayOfString[21] = new String(arrayOfChar22).intern();
        arrayOfChar23 = "SosJ\032\0014(\\\006NitK\034Zib\024\nTv(LF".toCharArray();
        int i89 = arrayOfChar23.length;
        i90 = 0;
        if (i89 > i90)
          break label2925;
        arrayOfString[22] = new String(arrayOfChar23).intern();
        arrayOfChar24 = "XrsC".toCharArray();
        int i93 = arrayOfChar24.length;
        i94 = 0;
        if (i93 > i94)
          break label3017;
        arrayOfString[23] = new String(arrayOfChar24).intern();
        z = arrayOfString;
      }
    }
    else
    {
      int i3 = arrayOfChar1[i2];
      int i4;
      switch (i2 % 5)
      {
      default:
        i4 = 105;
      case 0:
      case 1:
      case 2:
      case 3:
      }
      while (true)
      {
        arrayOfChar1[i2] = (char)(i4 ^ i3);
        i2++;
        break;
        i4 = 59;
        continue;
        i4 = 27;
        continue;
        i4 = 7;
        continue;
        i4 = 58;
      }
    }
    int i7 = arrayOfChar2[i6];
    int i8;
    switch (i6 % 5)
    {
    default:
      i8 = 105;
    case 0:
    case 1:
    case 2:
    case 3:
    }
    while (true)
    {
      arrayOfChar2[i6] = (char)(i8 ^ i7);
      i6++;
      break;
      i8 = 59;
      continue;
      i8 = 27;
      continue;
      i8 = 7;
      continue;
      i8 = 58;
    }
    label1085: int i11 = arrayOfChar3[i10];
    int i12;
    switch (i10 % 5)
    {
    default:
      i12 = 105;
    case 0:
    case 1:
    case 2:
    case 3:
    }
    while (true)
    {
      arrayOfChar3[i10] = (char)(i12 ^ i11);
      i10++;
      break;
      i12 = 59;
      continue;
      i12 = 27;
      continue;
      i12 = 7;
      continue;
      i12 = 58;
    }
    label1177: int i15 = arrayOfChar4[i14];
    int i16;
    switch (i14 % 5)
    {
    default:
      i16 = 105;
    case 0:
    case 1:
    case 2:
    case 3:
    }
    while (true)
    {
      arrayOfChar4[i14] = (char)(i16 ^ i15);
      i14++;
      break;
      i16 = 59;
      continue;
      i16 = 27;
      continue;
      i16 = 7;
      continue;
      i16 = 58;
    }
    label1269: int i19 = arrayOfChar5[i18];
    int i20;
    switch (i18 % 5)
    {
    default:
      i20 = 105;
    case 0:
    case 1:
    case 2:
    case 3:
    }
    while (true)
    {
      arrayOfChar5[i18] = (char)(i20 ^ i19);
      i18++;
      break;
      i20 = 59;
      continue;
      i20 = 27;
      continue;
      i20 = 7;
      continue;
      i20 = 58;
    }
    label1361: int i23 = arrayOfChar6[i22];
    int i24;
    switch (i22 % 5)
    {
    default:
      i24 = 105;
    case 0:
    case 1:
    case 2:
    case 3:
    }
    while (true)
    {
      arrayOfChar6[i22] = (char)(i24 ^ i23);
      i22++;
      break;
      i24 = 59;
      continue;
      i24 = 27;
      continue;
      i24 = 7;
      continue;
      i24 = 58;
    }
    label1453: int i27 = arrayOfChar7[i26];
    int i28;
    switch (i26 % 5)
    {
    default:
      i28 = 105;
    case 0:
    case 1:
    case 2:
    case 3:
    }
    while (true)
    {
      arrayOfChar7[i26] = (char)(i28 ^ i27);
      i26++;
      break;
      i28 = 59;
      continue;
      i28 = 27;
      continue;
      i28 = 7;
      continue;
      i28 = 58;
    }
    label1545: int i31 = arrayOfChar8[i30];
    int i32;
    switch (i30 % 5)
    {
    default:
      i32 = 105;
    case 0:
    case 1:
    case 2:
    case 3:
    }
    while (true)
    {
      arrayOfChar8[i30] = (char)(i32 ^ i31);
      i30++;
      break;
      i32 = 59;
      continue;
      i32 = 27;
      continue;
      i32 = 7;
      continue;
      i32 = 58;
    }
    label1637: int i35 = arrayOfChar9[i34];
    int i36;
    switch (i34 % 5)
    {
    default:
      i36 = 105;
    case 0:
    case 1:
    case 2:
    case 3:
    }
    while (true)
    {
      arrayOfChar9[i34] = (char)(i36 ^ i35);
      i34++;
      break;
      i36 = 59;
      continue;
      i36 = 27;
      continue;
      i36 = 7;
      continue;
      i36 = 58;
    }
    label1729: int i39 = arrayOfChar10[i38];
    int i40;
    switch (i38 % 5)
    {
    default:
      i40 = 105;
    case 0:
    case 1:
    case 2:
    case 3:
    }
    while (true)
    {
      arrayOfChar10[i38] = (char)(i40 ^ i39);
      i38++;
      break;
      i40 = 59;
      continue;
      i40 = 27;
      continue;
      i40 = 7;
      continue;
      i40 = 58;
    }
    label1821: int i43 = arrayOfChar11[i42];
    int i44;
    switch (i42 % 5)
    {
    default:
      i44 = 105;
    case 0:
    case 1:
    case 2:
    case 3:
    }
    while (true)
    {
      arrayOfChar11[i42] = (char)(i44 ^ i43);
      i42++;
      break;
      i44 = 59;
      continue;
      i44 = 27;
      continue;
      i44 = 7;
      continue;
      i44 = 58;
    }
    label1913: int i47 = arrayOfChar12[i46];
    int i48;
    switch (i46 % 5)
    {
    default:
      i48 = 105;
    case 0:
    case 1:
    case 2:
    case 3:
    }
    while (true)
    {
      arrayOfChar12[i46] = (char)(i48 ^ i47);
      i46++;
      break;
      i48 = 59;
      continue;
      i48 = 27;
      continue;
      i48 = 7;
      continue;
      i48 = 58;
    }
    label2005: int i51 = arrayOfChar13[i50];
    int i52;
    switch (i50 % 5)
    {
    default:
      i52 = 105;
    case 0:
    case 1:
    case 2:
    case 3:
    }
    while (true)
    {
      arrayOfChar13[i50] = (char)(i52 ^ i51);
      i50++;
      break;
      i52 = 59;
      continue;
      i52 = 27;
      continue;
      i52 = 7;
      continue;
      i52 = 58;
    }
    label2097: int i55 = arrayOfChar14[i54];
    int i56;
    switch (i54 % 5)
    {
    default:
      i56 = 105;
    case 0:
    case 1:
    case 2:
    case 3:
    }
    while (true)
    {
      arrayOfChar14[i54] = (char)(i56 ^ i55);
      i54++;
      break;
      i56 = 59;
      continue;
      i56 = 27;
      continue;
      i56 = 7;
      continue;
      i56 = 58;
    }
    label2189: int i59 = arrayOfChar15[i58];
    int i60;
    switch (i58 % 5)
    {
    default:
      i60 = 105;
    case 0:
    case 1:
    case 2:
    case 3:
    }
    while (true)
    {
      arrayOfChar15[i58] = (char)(i60 ^ i59);
      i58++;
      break;
      i60 = 59;
      continue;
      i60 = 27;
      continue;
      i60 = 7;
      continue;
      i60 = 58;
    }
    label2281: int i63 = arrayOfChar16[i62];
    int i64;
    switch (i62 % 5)
    {
    default:
      i64 = 105;
    case 0:
    case 1:
    case 2:
    case 3:
    }
    while (true)
    {
      arrayOfChar16[i62] = (char)(i64 ^ i63);
      i62++;
      break;
      i64 = 59;
      continue;
      i64 = 27;
      continue;
      i64 = 7;
      continue;
      i64 = 58;
    }
    label2373: int i67 = arrayOfChar17[i66];
    int i68;
    switch (i66 % 5)
    {
    default:
      i68 = 105;
    case 0:
    case 1:
    case 2:
    case 3:
    }
    while (true)
    {
      arrayOfChar17[i66] = (char)(i68 ^ i67);
      i66++;
      break;
      i68 = 59;
      continue;
      i68 = 27;
      continue;
      i68 = 7;
      continue;
      i68 = 58;
    }
    label2465: int i71 = arrayOfChar18[i70];
    int i72;
    switch (i70 % 5)
    {
    default:
      i72 = 105;
    case 0:
    case 1:
    case 2:
    case 3:
    }
    while (true)
    {
      arrayOfChar18[i70] = (char)(i72 ^ i71);
      i70++;
      break;
      i72 = 59;
      continue;
      i72 = 27;
      continue;
      i72 = 7;
      continue;
      i72 = 58;
    }
    label2557: int i75 = arrayOfChar19[i74];
    int i76;
    switch (i74 % 5)
    {
    default:
      i76 = 105;
    case 0:
    case 1:
    case 2:
    case 3:
    }
    while (true)
    {
      arrayOfChar19[i74] = (char)(i76 ^ i75);
      i74++;
      break;
      i76 = 59;
      continue;
      i76 = 27;
      continue;
      i76 = 7;
      continue;
      i76 = 58;
    }
    label2649: int i79 = arrayOfChar20[i78];
    int i80;
    switch (i78 % 5)
    {
    default:
      i80 = 105;
    case 0:
    case 1:
    case 2:
    case 3:
    }
    while (true)
    {
      arrayOfChar20[i78] = (char)(i80 ^ i79);
      i78++;
      break;
      i80 = 59;
      continue;
      i80 = 27;
      continue;
      i80 = 7;
      continue;
      i80 = 58;
    }
    label2741: int i83 = arrayOfChar21[i82];
    int i84;
    switch (i82 % 5)
    {
    default:
      i84 = 105;
    case 0:
    case 1:
    case 2:
    case 3:
    }
    while (true)
    {
      arrayOfChar21[i82] = (char)(i84 ^ i83);
      i82++;
      break;
      i84 = 59;
      continue;
      i84 = 27;
      continue;
      i84 = 7;
      continue;
      i84 = 58;
    }
    label2833: int i87 = arrayOfChar22[i86];
    int i88;
    switch (i86 % 5)
    {
    default:
      i88 = 105;
    case 0:
    case 1:
    case 2:
    case 3:
    }
    while (true)
    {
      arrayOfChar22[i86] = (char)(i88 ^ i87);
      i86++;
      break;
      i88 = 59;
      continue;
      i88 = 27;
      continue;
      i88 = 7;
      continue;
      i88 = 58;
    }
    label2925: int i91 = arrayOfChar23[i90];
    int i92;
    switch (i90 % 5)
    {
    default:
      i92 = 105;
    case 0:
    case 1:
    case 2:
    case 3:
    }
    while (true)
    {
      arrayOfChar23[i90] = (char)(i92 ^ i91);
      i90++;
      break;
      i92 = 59;
      continue;
      i92 = 27;
      continue;
      i92 = 7;
      continue;
      i92 = 58;
    }
    label3017: int i95 = arrayOfChar24[i94];
    int i96;
    switch (i94 % 5)
    {
    default:
      i96 = 105;
    case 0:
    case 1:
    case 2:
    case 3:
    }
    while (true)
    {
      arrayOfChar24[i94] = (char)(i96 ^ i95);
      i94++;
      break;
      i96 = 59;
      continue;
      i96 = 27;
      continue;
      i96 = 7;
      continue;
      i96 = 58;
    }
  }

  // ERROR //
  public void a()
  {
    // Byte code:
    //   0: aload_0
    //   1: monitorenter
    //   2: aload_0
    //   3: getfield 103	com/whatsapp/fy:m	Z
    //   6: istore_2
    //   7: iload_2
    //   8: ifeq +6 -> 14
    //   11: aload_0
    //   12: monitorexit
    //   13: return
    //   14: aload_0
    //   15: getfield 105	com/whatsapp/fy:p	I
    //   18: iconst_1
    //   19: if_icmpne -8 -> 11
    //   22: new 107	org/apache/http/params/BasicHttpParams
    //   25: dup
    //   26: invokespecial 108	org/apache/http/params/BasicHttpParams:<init>	()V
    //   29: astore_3
    //   30: aload_3
    //   31: sipush 15000
    //   34: invokestatic 114	org/apache/http/params/HttpConnectionParams:setConnectionTimeout	(Lorg/apache/http/params/HttpParams;I)V
    //   37: aload_3
    //   38: sipush 30000
    //   41: invokestatic 117	org/apache/http/params/HttpConnectionParams:setSoTimeout	(Lorg/apache/http/params/HttpParams;I)V
    //   44: aload_3
    //   45: getstatic 121	com/whatsapp/App:n	Ljava/lang/String;
    //   48: invokestatic 127	org/apache/http/params/HttpProtocolParams:setUserAgent	(Lorg/apache/http/params/HttpParams;Ljava/lang/String;)V
    //   51: new 129	org/apache/http/impl/client/DefaultHttpClient
    //   54: dup
    //   55: aload_3
    //   56: invokespecial 132	org/apache/http/impl/client/DefaultHttpClient:<init>	(Lorg/apache/http/params/HttpParams;)V
    //   59: astore 4
    //   61: new 134	org/apache/http/client/methods/HttpGet
    //   64: dup
    //   65: new 136	java/lang/StringBuilder
    //   68: dup
    //   69: invokespecial 137	java/lang/StringBuilder:<init>	()V
    //   72: getstatic 141	com/whatsapp/f8:p	Ljava/lang/String;
    //   75: invokevirtual 145	java/lang/StringBuilder:append	(Ljava/lang/String;)Ljava/lang/StringBuilder;
    //   78: aload_0
    //   79: getfield 147	com/whatsapp/fy:c	Ljava/lang/String;
    //   82: invokevirtual 145	java/lang/StringBuilder:append	(Ljava/lang/String;)Ljava/lang/StringBuilder;
    //   85: invokevirtual 150	java/lang/StringBuilder:toString	()Ljava/lang/String;
    //   88: invokespecial 153	org/apache/http/client/methods/HttpGet:<init>	(Ljava/lang/String;)V
    //   91: astore 5
    //   93: aload 4
    //   95: aload 5
    //   97: invokevirtual 157	org/apache/http/impl/client/DefaultHttpClient:execute	(Lorg/apache/http/client/methods/HttpUriRequest;)Lorg/apache/http/HttpResponse;
    //   100: astore 8
    //   102: aload 8
    //   104: invokeinterface 163 1 0
    //   109: invokeinterface 169 1 0
    //   114: sipush 200
    //   117: if_icmpne -106 -> 11
    //   120: new 171	org/json/JSONObject
    //   123: dup
    //   124: aload 8
    //   126: invokeinterface 175 1 0
    //   131: invokestatic 180	org/apache/http/util/EntityUtils:toString	(Lorg/apache/http/HttpEntity;)Ljava/lang/String;
    //   134: invokespecial 181	org/json/JSONObject:<init>	(Ljava/lang/String;)V
    //   137: astore 9
    //   139: aload 9
    //   141: getstatic 95	com/whatsapp/fy:z	[Ljava/lang/String;
    //   144: bipush 17
    //   146: aaload
    //   147: invokevirtual 185	org/json/JSONObject:getString	(Ljava/lang/String;)Ljava/lang/String;
    //   150: astore 10
    //   152: getstatic 95	com/whatsapp/fy:z	[Ljava/lang/String;
    //   155: bipush 16
    //   157: aaload
    //   158: aload 10
    //   160: invokevirtual 189	java/lang/String:equals	(Ljava/lang/Object;)Z
    //   163: ifeq -152 -> 11
    //   166: aload 9
    //   168: getstatic 95	com/whatsapp/fy:z	[Ljava/lang/String;
    //   171: bipush 15
    //   173: aaload
    //   174: invokevirtual 193	org/json/JSONObject:getJSONObject	(Ljava/lang/String;)Lorg/json/JSONObject;
    //   177: astore 11
    //   179: aload 11
    //   181: ifnull -170 -> 11
    //   184: aload_0
    //   185: aload 11
    //   187: iconst_1
    //   188: invokevirtual 196	com/whatsapp/fy:a	(Lorg/json/JSONObject;Z)V
    //   191: aload_0
    //   192: iconst_1
    //   193: putfield 103	com/whatsapp/fy:m	Z
    //   196: goto -185 -> 11
    //   199: astore 7
    //   201: aload 7
    //   203: invokestatic 201	com/whatsapp/g5:d	(Ljava/lang/Throwable;)V
    //   206: goto -195 -> 11
    //   209: astore_1
    //   210: aload_0
    //   211: monitorexit
    //   212: aload_1
    //   213: athrow
    //   214: astore 6
    //   216: aload 6
    //   218: invokestatic 201	com/whatsapp/g5:d	(Ljava/lang/Throwable;)V
    //   221: goto -210 -> 11
    //
    // Exception table:
    //   from	to	target	type
    //   93	196	199	java/io/IOException
    //   2	7	209	finally
    //   14	93	209	finally
    //   93	196	209	finally
    //   201	206	209	finally
    //   216	221	209	finally
    //   93	196	214	org/json/JSONException
  }

  public void a(JSONObject paramJSONObject, boolean paramBoolean)
    throws JSONException
  {
    int i1 = 0;
    boolean bool = DialogToastListActivity.f;
    this.p = 1;
    this.a = paramJSONObject.getString(z[8]);
    this.c = paramJSONObject.optString(z[0]);
    this.d = paramJSONObject.optString(z[4]);
    this.b = paramJSONObject.optString(z[10]);
    this.l = new HashSet();
    JSONArray localJSONArray = paramJSONObject.optJSONArray(z[3]);
    if (localJSONArray != null)
      do
      {
        if (i1 >= localJSONArray.length())
          break;
        this.l.add(localJSONArray.getString(i1));
        i1++;
      }
      while (!bool);
    JSONObject localJSONObject1 = paramJSONObject.getJSONObject(z[9]);
    if (localJSONObject1 != null)
    {
      JSONObject localJSONObject2 = localJSONObject1.getJSONObject(z[6]);
      if (localJSONObject2 != null)
      {
        this.e = localJSONObject2.getDouble(z[14]);
        this.f = localJSONObject2.getDouble(z[5]);
      }
    }
    this.k = paramJSONObject.optString(z[1]);
    if (paramBoolean)
    {
      this.g = paramJSONObject.optString(z[13]);
      this.h = paramJSONObject.optString(z[12]);
      this.i = paramJSONObject.optString(z[11]);
      this.j = paramJSONObject.optString(z[7]);
      if (this.i != null)
        this.i = this.i.replace(z[2], "");
      this.m = true;
    }
  }

  public Location b()
  {
    if (this.o == null)
    {
      this.o = new Location("");
      this.o.setLatitude(this.e);
      this.o.setLongitude(this.f);
    }
    return this.o;
  }

  public void b(JSONObject paramJSONObject, boolean paramBoolean)
    throws JSONException
  {
    this.p = 2;
    this.a = paramJSONObject.getString(z[8]);
    this.g = paramJSONObject.optString(z[13]);
    this.c = paramJSONObject.optString(z[4]);
    if ((this.g == null) || ("".equals(this.g)))
      this.g = (z[22] + this.c);
    JSONObject localJSONObject = paramJSONObject.getJSONObject(z[6]);
    if (localJSONObject != null)
    {
      this.e = localJSONObject.optDouble(z[14]);
      this.f = localJSONObject.optDouble(z[5]);
      this.i = localJSONObject.optString(z[19]);
      this.b = this.i;
      String str1 = localJSONObject.optString(z[23]);
      if ((str1 != null) && (!"".equals(str1)))
      {
        if ((this.i != null) && (!"".equals(this.i)))
          this.i += z[20];
        this.i += str1;
      }
      String str2 = localJSONObject.optString(z[18]);
      if ((str2 != null) && (!"".equals(str2)))
      {
        if ((this.i != null) && (!"".equals(this.i)))
          this.i += z[20];
        this.i += str2;
      }
      String str3 = localJSONObject.optString(z[21]);
      if ((str3 != null) && (!"".equals(str3)))
      {
        if ((this.i != null) && (!"".equals(this.i)))
          this.i += " ";
        this.i += str3;
      }
      this.m = true;
    }
  }
}

/* Location:           C:\Users\Jaap\Downloads\Code\WhatsApp-2.8.4278_dex2jar.jar
 * Qualified Name:     com.whatsapp.fy
 * JD-Core Version:    0.6.1
 */