package com.whatsapp;

import android.os.AsyncTask;

public class ub extends AsyncTask<String, Void, uf>
{
  private static final String[] z;
  String a = z[15];
  String b = z[14];
  String c;
  final RegisterPhone d;

  static
  {
    String[] arrayOfString = new String[19];
    char[] arrayOfChar1 = ">\037Z!jt\t]4st\016".toCharArray();
    int i = arrayOfChar1.length;
    int j = 0;
    char[] arrayOfChar2;
    int i1;
    char[] arrayOfChar3;
    int i5;
    char[] arrayOfChar4;
    int i9;
    char[] arrayOfChar5;
    int i13;
    char[] arrayOfChar6;
    int i17;
    char[] arrayOfChar7;
    int i21;
    char[] arrayOfChar8;
    int i25;
    char[] arrayOfChar9;
    int i29;
    char[] arrayOfChar10;
    int i33;
    char[] arrayOfChar11;
    int i37;
    char[] arrayOfChar12;
    int i41;
    char[] arrayOfChar13;
    int i45;
    char[] arrayOfChar14;
    int i49;
    char[] arrayOfChar15;
    int i53;
    char[] arrayOfChar16;
    int i57;
    char[] arrayOfChar17;
    int i61;
    char[] arrayOfChar18;
    int i65;
    char[] arrayOfChar19;
    int i69;
    if (i <= j)
    {
      arrayOfString[0] = new String(arrayOfChar1).intern();
      arrayOfChar2 = ">\bU67a\013F3wt\036Q ".toCharArray();
      int n = arrayOfChar2.length;
      i1 = 0;
      if (n <= i1)
      {
        arrayOfString[1] = new String(arrayOfChar2).intern();
        arrayOfChar3 = ">\034Q ix\005Zn~\005\031=vu".toCharArray();
        int i4 = arrayOfChar3.length;
        i5 = 0;
        if (i4 > i5)
          break label897;
        arrayOfString[2] = new String(arrayOfChar3).intern();
        arrayOfChar4 = "b\017X47b\017Z67\005@jt\030Y;ne\017P".toCharArray();
        int i8 = arrayOfChar4.length;
        i9 = 0;
        if (i8 > i9)
          break label989;
        arrayOfString[3] = new String(arrayOfChar4).intern();
        arrayOfChar5 = ">\037Z!oa\032[ nt\016\031\"vp\036R=h|".toCharArray();
        int i12 = arrayOfChar5.length;
        i13 = 0;
        if (i12 > i13)
          break label1081;
        arrayOfString[4] = new String(arrayOfChar5).intern();
        arrayOfChar6 = ">\004[&7a\017F?se\036Q6".toCharArray();
        int i16 = arrayOfChar6.length;
        i17 = 0;
        if (i16 > i17)
          break label1173;
        arrayOfString[5] = new String(arrayOfChar6).intern();
        arrayOfChar7 = ">\bX=yz\017P".toCharArray();
        int i20 = arrayOfChar7.length;
        i21 = 0;
        if (i20 > i21)
          break label1265;
        arrayOfString[6] = new String(arrayOfChar7).intern();
        arrayOfChar8 = "b\017X47b\017Z67e\005[wp\004Mnc\003Q!".toCharArray();
        int i24 = arrayOfChar8.length;
        i25 = 0;
        if (i24 > i25)
          break label1357;
        arrayOfString[7] = new String(arrayOfChar8).intern();
        arrayOfChar9 = ">\036[=7c\017W7te".toCharArray();
        int i28 = arrayOfChar9.length;
        i29 = 0;
        if (i28 > i29)
          break label1449;
        arrayOfString[8] = new String(arrayOfChar9).intern();
        arrayOfChar10 = "c\017S;ie\017F}jy\005Z75c\017E'b\036\033".toCharArray();
        int i32 = arrayOfChar10.length;
        i33 = 0;
        if (i32 > i33)
          break label1541;
        arrayOfString[9] = new String(arrayOfChar10).intern();
        arrayOfChar11 = "s\013Prjp\030U?e\017F".toCharArray();
        int i36 = arrayOfChar11.length;
        i37 = 0;
        if (i36 > i37)
          break label1633;
        arrayOfString[10] = new String(arrayOfChar11).intern();
        arrayOfChar12 = ">\036[=7|\013Z+7e\030]7i".toCharArray();
        int i40 = arrayOfChar12.length;
        i41 = 0;
        if (i40 > i41)
          break label1725;
        arrayOfString[11] = new String(arrayOfChar12).intern();
        arrayOfChar13 = ">\036[=7c\017W7teE@;wtGZ=n<\003Z&".toCharArray();
        int i44 = arrayOfChar13.length;
        i45 = 0;
        if (i44 > i45)
          break label1817;
        arrayOfString[12] = new String(arrayOfChar13).intern();
        arrayOfChar14 = "|\013F9e".toCharArray();
        int i48 = arrayOfChar14.length;
        i49 = 0;
        if (i48 > i49)
          break label1909;
        arrayOfString[13] = new String(arrayOfChar14).intern();
        arrayOfChar15 = "b\f".toCharArray();
        int i52 = arrayOfChar15.length;
        i53 = 0;
        if (i52 > i53)
          break label2001;
        arrayOfString[14] = new String(arrayOfChar15).intern();
        arrayOfChar16 = "b\017X4".toCharArray();
        int i56 = arrayOfChar16.length;
        i57 = 0;
        if (i56 > i57)
          break label2093;
        arrayOfString[15] = new String(arrayOfChar16).intern();
        arrayOfChar17 = "c\017R'it\016".toCharArray();
        int i60 = arrayOfChar17.length;
        i61 = 0;
        if (i60 > i61)
          break label2185;
        arrayOfString[16] = new String(arrayOfChar17).intern();
        arrayOfChar18 = ">\017F ucJ".toCharArray();
        int i64 = arrayOfChar18.length;
        i65 = 0;
        if (i64 > i65)
          break label2277;
        arrayOfString[17] = new String(arrayOfChar18).intern();
        arrayOfChar19 = ">\003[7hc\005Fr".toCharArray();
        int i68 = arrayOfChar19.length;
        i69 = 0;
        if (i68 > i69)
          break label2369;
        arrayOfString[18] = new String(arrayOfChar19).intern();
        z = arrayOfString;
      }
    }
    else
    {
      int k = arrayOfChar1[j];
      int m;
      switch (j % 5)
      {
      default:
        m = 26;
      case 0:
      case 1:
      case 2:
      case 3:
      }
      while (true)
      {
        arrayOfChar1[j] = (char)(m ^ k);
        j++;
        break;
        m = 17;
        continue;
        m = 106;
        continue;
        m = 52;
        continue;
        m = 82;
      }
    }
    int i2 = arrayOfChar2[i1];
    int i3;
    switch (i1 % 5)
    {
    default:
      i3 = 26;
    case 0:
    case 1:
    case 2:
    case 3:
    }
    while (true)
    {
      arrayOfChar2[i1] = (char)(i3 ^ i2);
      i1++;
      break;
      i3 = 17;
      continue;
      i3 = 106;
      continue;
      i3 = 52;
      continue;
      i3 = 82;
    }
    label897: int i6 = arrayOfChar3[i5];
    int i7;
    switch (i5 % 5)
    {
    default:
      i7 = 26;
    case 0:
    case 1:
    case 2:
    case 3:
    }
    while (true)
    {
      arrayOfChar3[i5] = (char)(i7 ^ i6);
      i5++;
      break;
      i7 = 17;
      continue;
      i7 = 106;
      continue;
      i7 = 52;
      continue;
      i7 = 82;
    }
    label989: int i10 = arrayOfChar4[i9];
    int i11;
    switch (i9 % 5)
    {
    default:
      i11 = 26;
    case 0:
    case 1:
    case 2:
    case 3:
    }
    while (true)
    {
      arrayOfChar4[i9] = (char)(i11 ^ i10);
      i9++;
      break;
      i11 = 17;
      continue;
      i11 = 106;
      continue;
      i11 = 52;
      continue;
      i11 = 82;
    }
    label1081: int i14 = arrayOfChar5[i13];
    int i15;
    switch (i13 % 5)
    {
    default:
      i15 = 26;
    case 0:
    case 1:
    case 2:
    case 3:
    }
    while (true)
    {
      arrayOfChar5[i13] = (char)(i15 ^ i14);
      i13++;
      break;
      i15 = 17;
      continue;
      i15 = 106;
      continue;
      i15 = 52;
      continue;
      i15 = 82;
    }
    label1173: int i18 = arrayOfChar6[i17];
    int i19;
    switch (i17 % 5)
    {
    default:
      i19 = 26;
    case 0:
    case 1:
    case 2:
    case 3:
    }
    while (true)
    {
      arrayOfChar6[i17] = (char)(i19 ^ i18);
      i17++;
      break;
      i19 = 17;
      continue;
      i19 = 106;
      continue;
      i19 = 52;
      continue;
      i19 = 82;
    }
    label1265: int i22 = arrayOfChar7[i21];
    int i23;
    switch (i21 % 5)
    {
    default:
      i23 = 26;
    case 0:
    case 1:
    case 2:
    case 3:
    }
    while (true)
    {
      arrayOfChar7[i21] = (char)(i23 ^ i22);
      i21++;
      break;
      i23 = 17;
      continue;
      i23 = 106;
      continue;
      i23 = 52;
      continue;
      i23 = 82;
    }
    label1357: int i26 = arrayOfChar8[i25];
    int i27;
    switch (i25 % 5)
    {
    default:
      i27 = 26;
    case 0:
    case 1:
    case 2:
    case 3:
    }
    while (true)
    {
      arrayOfChar8[i25] = (char)(i27 ^ i26);
      i25++;
      break;
      i27 = 17;
      continue;
      i27 = 106;
      continue;
      i27 = 52;
      continue;
      i27 = 82;
    }
    label1449: int i30 = arrayOfChar9[i29];
    int i31;
    switch (i29 % 5)
    {
    default:
      i31 = 26;
    case 0:
    case 1:
    case 2:
    case 3:
    }
    while (true)
    {
      arrayOfChar9[i29] = (char)(i31 ^ i30);
      i29++;
      break;
      i31 = 17;
      continue;
      i31 = 106;
      continue;
      i31 = 52;
      continue;
      i31 = 82;
    }
    label1541: int i34 = arrayOfChar10[i33];
    int i35;
    switch (i33 % 5)
    {
    default:
      i35 = 26;
    case 0:
    case 1:
    case 2:
    case 3:
    }
    while (true)
    {
      arrayOfChar10[i33] = (char)(i35 ^ i34);
      i33++;
      break;
      i35 = 17;
      continue;
      i35 = 106;
      continue;
      i35 = 52;
      continue;
      i35 = 82;
    }
    label1633: int i38 = arrayOfChar11[i37];
    int i39;
    switch (i37 % 5)
    {
    default:
      i39 = 26;
    case 0:
    case 1:
    case 2:
    case 3:
    }
    while (true)
    {
      arrayOfChar11[i37] = (char)(i39 ^ i38);
      i37++;
      break;
      i39 = 17;
      continue;
      i39 = 106;
      continue;
      i39 = 52;
      continue;
      i39 = 82;
    }
    label1725: int i42 = arrayOfChar12[i41];
    int i43;
    switch (i41 % 5)
    {
    default:
      i43 = 26;
    case 0:
    case 1:
    case 2:
    case 3:
    }
    while (true)
    {
      arrayOfChar12[i41] = (char)(i43 ^ i42);
      i41++;
      break;
      i43 = 17;
      continue;
      i43 = 106;
      continue;
      i43 = 52;
      continue;
      i43 = 82;
    }
    label1817: int i46 = arrayOfChar13[i45];
    int i47;
    switch (i45 % 5)
    {
    default:
      i47 = 26;
    case 0:
    case 1:
    case 2:
    case 3:
    }
    while (true)
    {
      arrayOfChar13[i45] = (char)(i47 ^ i46);
      i45++;
      break;
      i47 = 17;
      continue;
      i47 = 106;
      continue;
      i47 = 52;
      continue;
      i47 = 82;
    }
    label1909: int i50 = arrayOfChar14[i49];
    int i51;
    switch (i49 % 5)
    {
    default:
      i51 = 26;
    case 0:
    case 1:
    case 2:
    case 3:
    }
    while (true)
    {
      arrayOfChar14[i49] = (char)(i51 ^ i50);
      i49++;
      break;
      i51 = 17;
      continue;
      i51 = 106;
      continue;
      i51 = 52;
      continue;
      i51 = 82;
    }
    label2001: int i54 = arrayOfChar15[i53];
    int i55;
    switch (i53 % 5)
    {
    default:
      i55 = 26;
    case 0:
    case 1:
    case 2:
    case 3:
    }
    while (true)
    {
      arrayOfChar15[i53] = (char)(i55 ^ i54);
      i53++;
      break;
      i55 = 17;
      continue;
      i55 = 106;
      continue;
      i55 = 52;
      continue;
      i55 = 82;
    }
    label2093: int i58 = arrayOfChar16[i57];
    int i59;
    switch (i57 % 5)
    {
    default:
      i59 = 26;
    case 0:
    case 1:
    case 2:
    case 3:
    }
    while (true)
    {
      arrayOfChar16[i57] = (char)(i59 ^ i58);
      i57++;
      break;
      i59 = 17;
      continue;
      i59 = 106;
      continue;
      i59 = 52;
      continue;
      i59 = 82;
    }
    label2185: int i62 = arrayOfChar17[i61];
    int i63;
    switch (i61 % 5)
    {
    default:
      i63 = 26;
    case 0:
    case 1:
    case 2:
    case 3:
    }
    while (true)
    {
      arrayOfChar17[i61] = (char)(i63 ^ i62);
      i61++;
      break;
      i63 = 17;
      continue;
      i63 = 106;
      continue;
      i63 = 52;
      continue;
      i63 = 82;
    }
    label2277: int i66 = arrayOfChar18[i65];
    int i67;
    switch (i65 % 5)
    {
    default:
      i67 = 26;
    case 0:
    case 1:
    case 2:
    case 3:
    }
    while (true)
    {
      arrayOfChar18[i65] = (char)(i67 ^ i66);
      i65++;
      break;
      i67 = 17;
      continue;
      i67 = 106;
      continue;
      i67 = 52;
      continue;
      i67 = 82;
    }
    label2369: int i70 = arrayOfChar19[i69];
    int i71;
    switch (i69 % 5)
    {
    default:
      i71 = 26;
    case 0:
    case 1:
    case 2:
    case 3:
    }
    while (true)
    {
      arrayOfChar19[i69] = (char)(i71 ^ i70);
      i69++;
      break;
      i71 = 17;
      continue;
      i71 = 106;
      continue;
      i71 = 52;
      continue;
      i71 = 82;
    }
  }

  protected ub(RegisterPhone paramRegisterPhone)
  {
  }

  // ERROR //
  protected uf a(String[] paramArrayOfString)
  {
    // Byte code:
    //   0: getstatic 88	com/whatsapp/uf:c	Lcom/whatsapp/uf;
    //   3: astore_2
    //   4: invokestatic 93	com/whatsapp/RegisterPhone:m	()Ljava/lang/String;
    //   7: invokestatic 96	com/whatsapp/RegisterPhone:n	()Ljava/lang/String;
    //   10: aload_0
    //   11: getfield 72	com/whatsapp/ub:d	Lcom/whatsapp/RegisterPhone;
    //   14: invokevirtual 100	com/whatsapp/RegisterPhone:getResources	()Landroid/content/res/Resources;
    //   17: invokevirtual 106	android/content/res/Resources:getConfiguration	()Landroid/content/res/Configuration;
    //   20: getfield 112	android/content/res/Configuration:locale	Ljava/util/Locale;
    //   23: aload_0
    //   24: getfield 76	com/whatsapp/ub:a	Ljava/lang/String;
    //   27: getstatic 117	com/whatsapp/VerifyNumber:j	Ljava/lang/String;
    //   30: invokestatic 120	com/whatsapp/VerifyNumber:a	(Ljava/lang/String;Ljava/lang/String;Ljava/util/Locale;Ljava/lang/String;Ljava/lang/String;)Lcom/whatsapp/aq;
    //   33: astore 8
    //   35: aload 8
    //   37: getfield 124	com/whatsapp/aq:a	Lcom/whatsapp/uf;
    //   40: astore 4
    //   42: aload_0
    //   43: aload 8
    //   45: getfield 125	com/whatsapp/aq:b	Ljava/lang/String;
    //   48: putfield 127	com/whatsapp/ub:c	Ljava/lang/String;
    //   51: aload 4
    //   53: areturn
    //   54: astore 6
    //   56: aload 6
    //   58: invokevirtual 130	java/io/IOException:toString	()Ljava/lang/String;
    //   61: astore 7
    //   63: new 132	java/lang/StringBuilder
    //   66: dup
    //   67: invokespecial 133	java/lang/StringBuilder:<init>	()V
    //   70: getstatic 69	com/whatsapp/ub:z	[Ljava/lang/String;
    //   73: bipush 9
    //   75: aaload
    //   76: invokevirtual 137	java/lang/StringBuilder:append	(Ljava/lang/String;)Ljava/lang/StringBuilder;
    //   79: aload_0
    //   80: getfield 78	com/whatsapp/ub:b	Ljava/lang/String;
    //   83: invokevirtual 137	java/lang/StringBuilder:append	(Ljava/lang/String;)Ljava/lang/StringBuilder;
    //   86: getstatic 69	com/whatsapp/ub:z	[Ljava/lang/String;
    //   89: bipush 18
    //   91: aaload
    //   92: invokevirtual 137	java/lang/StringBuilder:append	(Ljava/lang/String;)Ljava/lang/StringBuilder;
    //   95: aload 7
    //   97: invokevirtual 137	java/lang/StringBuilder:append	(Ljava/lang/String;)Ljava/lang/StringBuilder;
    //   100: invokevirtual 138	java/lang/StringBuilder:toString	()Ljava/lang/String;
    //   103: invokestatic 143	com/whatsapp/g5:d	(Ljava/lang/String;)V
    //   106: aload 7
    //   108: ifnull +28 -> 136
    //   111: aload 7
    //   113: getstatic 69	com/whatsapp/ub:z	[Ljava/lang/String;
    //   116: bipush 16
    //   118: aaload
    //   119: invokevirtual 147	java/lang/String:contains	(Ljava/lang/CharSequence;)Z
    //   122: ifeq +14 -> 136
    //   125: getstatic 88	com/whatsapp/uf:c	Lcom/whatsapp/uf;
    //   128: astore 4
    //   130: getstatic 153	com/whatsapp/DialogToastListActivity:f	Z
    //   133: ifeq -82 -> 51
    //   136: getstatic 155	com/whatsapp/uf:d	Lcom/whatsapp/uf;
    //   139: astore 4
    //   141: goto -90 -> 51
    //   144: astore_3
    //   145: aload_2
    //   146: astore 4
    //   148: aload_3
    //   149: astore 5
    //   151: new 132	java/lang/StringBuilder
    //   154: dup
    //   155: invokespecial 133	java/lang/StringBuilder:<init>	()V
    //   158: getstatic 69	com/whatsapp/ub:z	[Ljava/lang/String;
    //   161: bipush 9
    //   163: aaload
    //   164: invokevirtual 137	java/lang/StringBuilder:append	(Ljava/lang/String;)Ljava/lang/StringBuilder;
    //   167: aload_0
    //   168: getfield 78	com/whatsapp/ub:b	Ljava/lang/String;
    //   171: invokevirtual 137	java/lang/StringBuilder:append	(Ljava/lang/String;)Ljava/lang/StringBuilder;
    //   174: getstatic 69	com/whatsapp/ub:z	[Ljava/lang/String;
    //   177: bipush 17
    //   179: aaload
    //   180: invokevirtual 137	java/lang/StringBuilder:append	(Ljava/lang/String;)Ljava/lang/StringBuilder;
    //   183: invokevirtual 138	java/lang/StringBuilder:toString	()Ljava/lang/String;
    //   186: aload 5
    //   188: invokestatic 158	com/whatsapp/g5:b	(Ljava/lang/String;Ljava/lang/Throwable;)V
    //   191: goto -140 -> 51
    //   194: astore 5
    //   196: goto -45 -> 151
    //
    // Exception table:
    //   from	to	target	type
    //   4	42	54	java/io/IOException
    //   42	51	54	java/io/IOException
    //   4	42	144	java/lang/Exception
    //   42	51	194	java/lang/Exception
  }

  protected void a(uf paramuf)
  {
    boolean bool1 = DialogToastListActivity.f;
    this.d.e("");
    this.d.removeDialog(9);
    RegisterPhone.a(14);
    RegisterPhone.a(this.d);
    boolean bool2;
    String str;
    if (paramuf == uf.b)
    {
      if (this.c == null)
        break label898;
      bool2 = true;
      g5.b(bool2);
      RegisterPhone.f(this.c);
      App.a(App.Mb, VerifyNumber.b(RegisterPhone.p()));
      RegisterPhone.a(15);
      RegisterPhone.a(this.d);
      if ((!this.d.l) && (!this.d.isFinishing()))
      {
        this.d.showDialog(21);
        if (!bool1);
      }
    }
    else if (paramuf != uf.a)
    {
      RegisterPhone.a(14);
      RegisterPhone.a(this.d);
      if (paramuf == uf.i)
      {
        g5.b(z[9] + this.b + z[5]);
        RegisterPhone.f(null);
        App.a(App.Mb, VerifyNumber.b(RegisterPhone.p()));
        RegisterPhone.a(15);
        RegisterPhone.a(this.d);
        this.d.y = true;
        VerifyNumber.j = z[3];
        RegisterPhone.b(this.d, true);
        if ((!this.d.l) && (!this.d.isFinishing()))
        {
          this.d.showDialog(21);
          if (!bool1);
        }
      }
      else if (paramuf == uf.c)
      {
        g5.c(z[9] + this.b + z[0]);
        if ((!this.d.l) && (!this.d.isFinishing()))
        {
          this.d.showDialog(109);
          if (!bool1);
        }
      }
      else if (paramuf == uf.f)
      {
        g5.c(z[9] + this.b + z[11]);
        RegisterPhone.f(null);
        App.a(App.Mb, VerifyNumber.b(RegisterPhone.p()));
        RegisterPhone.a(15);
        RegisterPhone.a(this.d);
        this.d.y = true;
        VerifyNumber.j = z[7];
        RegisterPhone.b(this.d, true);
        if ((!this.d.l) && (!this.d.isFinishing()))
        {
          this.d.showDialog(21);
          if (!bool1);
        }
      }
      else if (paramuf == uf.d)
      {
        RegisterPhone localRegisterPhone5 = this.d;
        RegisterPhone localRegisterPhone6 = this.d;
        Object[] arrayOfObject3 = new Object[1];
        arrayOfObject3[0] = this.d.getString(2131296328);
        localRegisterPhone5.f(localRegisterPhone6.getString(2131296333, arrayOfObject3));
        if (!bool1);
      }
      else if (paramuf == uf.j)
      {
        g5.d(z[9] + this.b + z[1]);
        App.d(z[10]);
        if ((!this.d.l) && (!this.d.isFinishing()))
        {
          this.d.showDialog(22);
          if (!bool1);
        }
      }
      else if (paramuf == uf.h)
      {
        g5.c(z[9] + this.b + z[4]);
        this.d.d(2131296396);
        if (!bool1);
      }
      else if (paramuf == uf.g)
      {
        g5.c(z[9] + this.b + z[2]);
        RegisterPhone localRegisterPhone3 = this.d;
        RegisterPhone localRegisterPhone4 = this.d;
        Object[] arrayOfObject2 = new Object[1];
        if (!z[13].equals(App.m))
          break label904;
        str = this.d.getString(2131296398);
        arrayOfObject2[0] = str;
        localRegisterPhone3.f(localRegisterPhone4.getString(2131296397, arrayOfObject2));
        if (!bool1);
      }
      else
      {
        if (paramuf != uf.e)
          break label980;
        g5.c(z[9] + this.b + z[8]);
      }
    }
    while (true)
    {
      try
      {
        long l = 60000L * Integer.parseInt(this.c);
        RegisterPhone localRegisterPhone1 = this.d;
        RegisterPhone localRegisterPhone2 = this.d;
        Object[] arrayOfObject1 = new Object[1];
        arrayOfObject1[0] = t4.a(l);
        localRegisterPhone1.f(localRegisterPhone2.getString(2131296400, arrayOfObject1));
        return;
        label898: bool2 = false;
        break;
        label904: str = this.d.getString(2131296399);
      }
      catch (NumberFormatException localNumberFormatException)
      {
        g5.c(z[9] + this.b + z[12]);
        this.d.f(this.d.getString(2131296402));
        if (!bool1)
          continue;
      }
      label980: if (paramuf == uf.k)
      {
        g5.d(z[9] + this.b + z[6]);
        this.d.e(23);
      }
    }
  }

  protected void onPreExecute()
  {
    RegisterPhone.f(null);
    if (!this.d.isFinishing())
      this.d.showDialog(9);
  }
}

/* Location:           C:\Users\Jaap\Downloads\Code\WhatsApp-2.8.4278_dex2jar.jar
 * Qualified Name:     com.whatsapp.ub
 * JD-Core Version:    0.6.1
 */