// #######################################################
// Decompiled by   : coddec 
// Module          : WhatsApp-47.cod
// Module version  : 2.8.1914
// Class ID        : 15
// ########################################################


package com.whatsapp.client;


abstract final class SafeApplicationMessageFolder$1 extends Object
implements Runnable

{

	// @@@@@@@@@@@@@ Fields 
	private final com.whatsapp.client.SafeApplicationMessageFolder /*module:WhatsApp-48.class#0*/  field_55492 ; // ofs = 55492 addr = 0)

	// @@@@@@@@@@@@@ Static routines 

<init>( com.whatsapp.client.SafeApplicationMessageFolder$1, module:WhatsApp-48.class#0 ); // address: 0
	{
	enter_narrow 
	aload_0 
	invokespecial_lib java.lang.Object.<init> // pc=1
	aload_0 
	aload_1 
	putfield .field_0_   // get_name_1:  .field_0_   // get_name_2:  .field_0_   // get_Name:    .field_0_   // getName->1:  null   // getName->2:  null   // getName->N:  null   // ofs = -1 ord = 0 addr = 0
	return 
	}

	// @@@@@@@@@@@@@ Virtual routines 

public final run( com.whatsapp.client.SafeApplicationMessageFolder$1 ); // address: 0
	{
	enter 
Label1:
	aload_0_getfield .field_0_   // get_name_1:  .field_0_   // get_name_2:  .field_0_   // get_Name:    .field_0_   // getName->1:  null   // getName->2:  null   // getName->N:  null   // ofs = -1 ord = 0 addr = 0
	getfield .field_1_1   // get_name_1:  .field_1_1   // get_name_2:  .field_1_1   // get_Name:    .field_1_1   // getName->1:  null   // getName->2:  null   // getName->N:  null   // ofs = -1 ord = 0 addr = 1
	dup 
	astore_4 
	monitorenter 
	aload_0_getfield .field_0_   // get_name_1:  .field_0_   // get_name_2:  .field_0_   // get_Name:    .field_0_   // getName->1:  null   // getName->2:  null   // getName->N:  null   // ofs = -1 ord = 0 addr = 0
	getfield .field_4_4   // get_name_1:  .field_4_4   // get_name_2:  .field_4_4   // get_Name:    .field_4_4   // getName->1:  null   // getName->2:  null   // getName->N:  null   // ofs = -1 ord = 0 addr = 4
	invokevirtual boolean isEmpty( java.util.Vector ) // pc=1
	ifeq Label24
	aload_0_getfield .field_0_   // get_name_1:  .field_0_   // get_name_2:  .field_0_   // get_Name:    .field_0_   // getName->1:  null   // getName->2:  null   // getName->N:  null   // ofs = -1 ord = 0 addr = 0
	getfield .field_3_3   // get_name_1:  .field_3_3   // get_name_2:  .field_3_3   // get_Name:    .field_3_3   // getName->1:  null   // getName->2:  null   // getName->N:  null   // ofs = -1 ord = 0 addr = 3
	invokevirtual boolean isEmpty( java.util.Vector ) // pc=1
	ifeq Label24
	aload_0_getfield .field_0_   // get_name_1:  .field_0_   // get_name_2:  .field_0_   // get_Name:    .field_0_   // getName->1:  null   // getName->2:  null   // getName->N:  null   // ofs = -1 ord = 0 addr = 0
	getfield .field_5_5   // get_name_1:  .field_5_5   // get_name_2:  .field_5_5   // get_Name:    .field_5_5   // getName->1:  null   // getName->2:  null   // getName->N:  null   // ofs = -1 ord = 0 addr = 5
	invokevirtual boolean isEmpty( java.util.Vector ) // pc=1
	ifeq Label24
	aload_0_getfield .field_0_   // get_name_1:  .field_0_   // get_name_2:  .field_0_   // get_Name:    .field_0_   // getName->1:  null   // getName->2:  null   // getName->N:  null   // ofs = -1 ord = 0 addr = 0
	aconst_null 
	putfield .field_2_2   // get_name_1:  .field_2_2   // get_name_2:  .field_2_2   // get_Name:    .field_2_2   // getName->1:  null   // getName->2:  null   // getName->N:  null   // ofs = -1 ord = 0 addr = 2
	aload_4 
	monitorexit 
	goto Label83
Label24:
	aload_0_getfield .field_0_   // get_name_1:  .field_0_   // get_name_2:  .field_0_   // get_Name:    .field_0_   // getName->1:  null   // getName->2:  null   // getName->N:  null   // ofs = -1 ord = 0 addr = 0
	getfield .field_4_4   // get_name_1:  .field_4_4   // get_name_2:  .field_4_4   // get_Name:    .field_4_4   // getName->1:  null   // getName->2:  null   // getName->N:  null   // ofs = -1 ord = 0 addr = 4
	astore_1 
	aload_0_getfield .field_0_   // get_name_1:  .field_0_   // get_name_2:  .field_0_   // get_Name:    .field_0_   // getName->1:  null   // getName->2:  null   // getName->N:  null   // ofs = -1 ord = 0 addr = 0
	getfield .field_3_3   // get_name_1:  .field_3_3   // get_name_2:  .field_3_3   // get_Name:    .field_3_3   // getName->1:  null   // getName->2:  null   // getName->N:  null   // ofs = -1 ord = 0 addr = 3
	astore_2 
	aload_0_getfield .field_0_   // get_name_1:  .field_0_   // get_name_2:  .field_0_   // get_Name:    .field_0_   // getName->1:  null   // getName->2:  null   // getName->N:  null   // ofs = -1 ord = 0 addr = 0
	getfield .field_5_5   // get_name_1:  .field_5_5   // get_name_2:  .field_5_5   // get_Name:    .field_5_5   // getName->1:  null   // getName->2:  null   // getName->N:  null   // ofs = -1 ord = 0 addr = 5
	astore_3 
	aload_0_getfield .field_0_   // get_name_1:  .field_0_   // get_name_2:  .field_0_   // get_Name:    .field_0_   // getName->1:  null   // getName->2:  null   // getName->N:  null   // ofs = -1 ord = 0 addr = 0
	new_lib net.rim.device.api.ui.component.BasicEditField//net.rim.device.api.ui.component.BasicEditField net.rim.device.api.ui.component.BasicEditField net.rim.device.api.ui.component.BasicEditField
	dup 
	invokespecial_lib java.util.Vector.<init> // pc=1
	putfield .field_4_4   // get_name_1:  .field_4_4   // get_name_2:  .field_4_4   // get_Name:    .field_4_4   // getName->1:  null   // getName->2:  null   // getName->N:  null   // ofs = -1 ord = 0 addr = 4
	aload_0_getfield .field_0_   // get_name_1:  .field_0_   // get_name_2:  .field_0_   // get_Name:    .field_0_   // getName->1:  null   // getName->2:  null   // getName->N:  null   // ofs = -1 ord = 0 addr = 0
	new_lib net.rim.device.api.ui.component.BasicEditField//net.rim.device.api.ui.component.BasicEditField net.rim.device.api.ui.component.BasicEditField net.rim.device.api.ui.component.BasicEditField
	dup 
	invokespecial_lib java.util.Vector.<init> // pc=1
	putfield .field_3_3   // get_name_1:  .field_3_3   // get_name_2:  .field_3_3   // get_Name:    .field_3_3   // getName->1:  null   // getName->2:  null   // getName->N:  null   // ofs = -1 ord = 0 addr = 3
	aload_0_getfield .field_0_   // get_name_1:  .field_0_   // get_name_2:  .field_0_   // get_Name:    .field_0_   // getName->1:  null   // getName->2:  null   // getName->N:  null   // ofs = -1 ord = 0 addr = 0
	new_lib net.rim.device.api.ui.component.BasicEditField//net.rim.device.api.ui.component.BasicEditField net.rim.device.api.ui.component.BasicEditField net.rim.device.api.ui.component.BasicEditField
	dup 
	invokespecial_lib java.util.Vector.<init> // pc=1
	putfield .field_5_5   // get_name_1:  .field_5_5   // get_name_2:  .field_5_5   // get_Name:    .field_5_5   // getName->1:  null   // getName->2:  null   // getName->N:  null   // ofs = -1 ord = 0 addr = 5
	aload_4 
	monitorexit 
	goto Label56
	astore_5 
	aload_4 
	monitorexit 
	aload_5 
	athrow 
Label56:
	aload_0_getfield .field_0_   // get_name_1:  .field_0_   // get_name_2:  .field_0_   // get_Name:    .field_0_   // getName->1:  null   // getName->2:  null   // getName->N:  null   // ofs = -1 ord = 0 addr = 0
	aload_1 
	invokespecial_lib .routine_434 // pc=2
	aload_0_getfield .field_0_   // get_name_1:  .field_0_   // get_name_2:  .field_0_   // get_Name:    .field_0_   // getName->1:  null   // getName->2:  null   // getName->N:  null   // ofs = -1 ord = 0 addr = 0
	aload_2 
	invokespecial_lib .routine_311 // pc=2
	aload_0_getfield .field_0_   // get_name_1:  .field_0_   // get_name_2:  .field_0_   // get_Name:    .field_0_   // getName->1:  null   // getName->2:  null   // getName->N:  null   // ofs = -1 ord = 0 addr = 0
	aload_3 
	invokespecial_lib .routine_192 // pc=2
	goto_w Label1
	astore_1 
	aload_0_getfield .field_0_   // get_name_1:  .field_0_   // get_name_2:  .field_0_   // get_Name:    .field_0_   // getName->1:  null   // getName->2:  null   // getName->N:  null   // ofs = -1 ord = 0 addr = 0
	getfield .field_1_1   // get_name_1:  .field_1_1   // get_name_2:  .field_1_1   // get_Name:    .field_1_1   // getName->1:  null   // getName->2:  null   // getName->N:  null   // ofs = -1 ord = 0 addr = 1
	dup 
	astore_2 
	monitorenter 
	aload_0_getfield .field_0_   // get_name_1:  .field_0_   // get_name_2:  .field_0_   // get_Name:    .field_0_   // getName->1:  null   // getName->2:  null   // getName->N:  null   // ofs = -1 ord = 0 addr = 0
	aconst_null 
	putfield .field_2_2   // get_name_1:  .field_2_2   // get_name_2:  .field_2_2   // get_Name:    .field_2_2   // getName->1:  null   // getName->2:  null   // getName->N:  null   // ofs = -1 ord = 0 addr = 2
	aload_2 
	monitorexit 
	return 
	astore_6 
	aload_2 
	monitorexit 
	aload_6 
	athrow 
Label83:
	return 
	}

}
