// #######################################################
// Decompiled by   : coddec 
// Module          : WhatsApp-36.cod
// Module version  : 2.7.3204
// Class ID        : 11
// ########################################################


package com.whatsapp.client.it.yup.xml;


abstract public final class KXmlParser extends Object
implements com.whatsapp.client.org.xmlpull.v1.XmlPullParser

{
	// @@@@@@@@@@@@@ Static fields 
	private static String /*java.lang.String*/  field_54250 ; // ofs = 54250 addr = 25)
	private static String /*java.lang.String*/  field_54256 ; // ofs = 54256 addr = 26)

	// @@@@@@@@@@@@@ Fields 
	private Object /*java.lang.Object*/  field_54126 ; // ofs = 54126 addr = 0)
	private String /*java.lang.String*/  field_54130 ; // ofs = 54130 addr = 0)
	private Boolean /*java.lang.Boolean*/  field_54134 ; // ofs = 54134 addr = 0)
	private boolean /*boolean*/  field_54138 ; // ofs = 54138 addr = 0)
	private boolean /*boolean*/  field_54142 ; // ofs = 54142 addr = 0)
	private java.util.Hashtable /*java.util.Hashtable*/  field_54146 ; // ofs = 54146 addr = 0)
	private int /*int*/  field_54150 ; // ofs = 54150 addr = 0)
	private String /*java.lang.String[]*/  field_54154 ; // ofs = 54154 addr = 0)
	private String /*java.lang.String[]*/  field_54158 ; // ofs = 54158 addr = 0)
	private int[] /*int[]*/  field_54162 ; // ofs = 54162 addr = 0)
	private java.io.Reader /*java.io.Reader*/  field_54166 ; // ofs = 54166 addr = 0)
	private String /*java.lang.String*/  field_54170 ; // ofs = 54170 addr = 0)
	private int /*int*/  field_54174 ; // ofs = 54174 addr = 0)
	private int /*int*/  field_54178 ; // ofs = 54178 addr = 0)
	private char[] /*char[]*/  field_54182 ; // ofs = 54182 addr = 0)
	private int /*int*/  field_54186 ; // ofs = 54186 addr = 0)
	private int /*int*/  field_54190 ; // ofs = 54190 addr = 0)
	private boolean /*boolean*/  field_54194 ; // ofs = 54194 addr = 0)
	private String /*java.lang.String*/  field_54198 ; // ofs = 54198 addr = 0)
	private String /*java.lang.String*/  field_54202 ; // ofs = 54202 addr = 0)
	private String /*java.lang.String*/  field_54206 ; // ofs = 54206 addr = 0)
	private boolean /*boolean*/  field_54210 ; // ofs = 54210 addr = 0)
	private int /*int*/  field_54214 ; // ofs = 54214 addr = 0)
	private String /*java.lang.String[]*/  field_54218 ; // ofs = 54218 addr = 0)
	private int /*int*/  field_54222 ; // ofs = 54222 addr = 0)
	private String /*java.lang.String*/  field_54226 ; // ofs = 54226 addr = 0)
	private int[] /*int[]*/  field_54230 ; // ofs = 54230 addr = 0)
	private int /*int*/  field_54234 ; // ofs = 54234 addr = 0)
	private boolean /*boolean*/  field_54238 ; // ofs = 54238 addr = 0)
	private boolean /*boolean*/  field_54242 ; // ofs = 54242 addr = 0)
	private boolean /*boolean*/  field_54246 ; // ofs = 54246 addr = 0)

	// @@@@@@@@@@@@@ Static routines 

public <init>( com.whatsapp.client.it.yup.xml.KXmlParser ); // address: 0
	{
	enter_narrow 
	aload_0 
	invokespecial_lib java.lang.Object.<init> // pc=1
	aload_0 
	bipush 16
	newarray_object_lib String//java.lang.String java.lang.String java.lang.String
	putfield .field_7_7   // get_name_1:  .field_7_7   // get_name_2:  .field_7_7   // get_Name:    .field_7_7   // getName->1:  null   // getName->2:  null   // getName->N:  null   // ofs = -1 ord = 0 addr = 7
	aload_0 
	bipush 8
	newarray_object_lib String//java.lang.String java.lang.String java.lang.String
	putfield .field_8_8   // get_name_1:  .field_8_8   // get_name_2:  .field_8_8   // get_Name:    .field_8_8   // getName->1:  null   // getName->2:  null   // getName->N:  null   // ofs = -1 ord = 0 addr = 8
	aload_0 
	bipush 4
	newarray 5
	putfield .field_9_9   // get_name_1:  .field_9_9   // get_name_2:  .field_9_9   // get_Name:    .field_9_9   // getName->1:  null   // getName->2:  null   // getName->N:  null   // ofs = -1 ord = 0 addr = 9
	aload_0 
	aconst_null 
	putfield .field_10_10   // get_name_1:  .field_10_10   // get_name_2:  .field_10_10   // get_Name:    .field_10_10   // getName->1:  null   // getName->2:  null   // getName->N:  null   // ofs = -1 ord = 0 addr = 10
	aload_0 
	sipush 128
	newarray 3
	putfield .field_14_14   // get_name_1:  .field_14_14   // get_name_2:  .field_14_14   // get_Name:    .field_14_14   // getName->1:  null   // getName->2:  null   // getName->N:  null   // ofs = -1 ord = 0 addr = 14
	aload_0 
	bipush 16
	newarray_object_lib String//java.lang.String java.lang.String java.lang.String
	putfield .field_23_23   // get_name_1:  .field_23_23   // get_name_2:  .field_23_23   // get_Name:    .field_23_23   // getName->1:  null   // getName->2:  null   // getName->N:  null   // ofs = -1 ord = 0 addr = 23
	aload_0 
	iconst_0 
	putfield .field_24_24   // get_name_1:  .field_24_24   // get_name_2:  .field_24_24   // get_Name:    .field_24_24   // getName->1:  null   // getName->2:  null   // getName->N:  null   // ofs = -1 ord = 0 addr = 24
	aload_0 
	bipush 2
	newarray 5
	putfield .field_26_26   // get_name_1:  .field_26_26   // get_name_2:  .field_26_26   // get_Name:    .field_26_26   // getName->1:  null   // getName->2:  null   // getName->N:  null   // ofs = -1 ord = 0 addr = 26
	return 
	}


static final <clinit>(  ); // address: 0
	{
	enter 
	synch_static KXmlParser
	clinit_wait 
	ldc literal_652:"Unexpected EOF"
	putstatic com.whatsapp.client.it.yup.xml.KXmlParser.field_54250 // KXmlParser
	ldc literal_653:"Wrong event type"
	putstatic com.whatsapp.client.it.yup.xml.KXmlParser.field_54256 // KXmlParser
	clinit_return 
	}

	// @@@@@@@@@@@@@ Non-virtual routines 

private final boolean com.whatsapp.client.it.yup.xml.KXmlParser.routine_2994( com.whatsapp.client.it.yup.xml.KXmlParser ); // address: 0
	{
	enter 
	iconst_0 
	istore_1 
	iconst_0 
	istore_2 
Label5:
	iload_2 
	aload_0_getfield .field_22_22   // get_name_1:  .field_22_22   // get_name_2:  .field_22_22   // get_Name:    .field_22_22   // getName->1:  null   // getName->2:  null   // getName->N:  null   // ofs = -1 ord = 0 addr = 22
	bipush 2
	ishl 
	if_icmplt Label11
	goto_w Label117
Label11:
	aload_0_getfield .field_23_23   // get_name_1:  .field_23_23   // get_name_2:  .field_23_23   // get_Name:    .field_23_23   // getName->1:  null   // getName->2:  null   // getName->N:  null   // ofs = -1 ord = 0 addr = 23
	iload_2 
	bipush 2
	iadd 
	aaload 
	astore_3 
	aload_3 
	bipush 58
	invokenonvirtual_lib java.lang.String.indexOf // pc=2
	istore_4 
	iload_4 
	bipush -1
	if_icmpeq Label36
	aload_3 
	iconst_0 
	iload_4 
	invokenonvirtual_lib java.lang.String.substring // pc=3
	astore_5 
	aload_3 
	iload_4 
	iconst_1 
	iadd 
	invokenonvirtual_lib java.lang.String.substring // pc=2
	astore_3 
	goto Label44
Label36:
	aload_3 
	ldc literal_587:"xmlns"
	invokevirtual_short .equals // idx=1 pc=2
	ifeq Label115
	aload_3 
	astore_5 
	aconst_null 
	astore_3 
Label44:
	aload_5 
	ldc literal_587:"xmlns"
	invokevirtual_short .equals // idx=1 pc=2
	ifne Label51
	iconst_1 
	istore_1 
	goto Label115
Label51:
	aload_0_getfield .field_9_9   // get_name_1:  .field_9_9   // get_name_2:  .field_9_9   // get_Name:    .field_9_9   // getName->1:  null   // getName->2:  null   // getName->N:  null   // ofs = -1 ord = 0 addr = 9
	aload_0_getfield .field_6_6   // get_name_1:  .field_6_6   // get_name_2:  .field_6_6   // get_Name:    .field_6_6   // getName->1:  null   // getName->2:  null   // getName->N:  null   // ofs = -1 ord = 0 addr = 6
	dup2 
	iaload 
	dup_x2 
	iconst_1 
	iadd 
	iastore 
	iconst_1 
	ishl 
	istore_6 
	aload_0 
	aload_0 
	aload_0_getfield .field_8_8   // get_name_1:  .field_8_8   // get_name_2:  .field_8_8   // get_Name:    .field_8_8   // getName->1:  null   // getName->2:  null   // getName->N:  null   // ofs = -1 ord = 0 addr = 8
	iload_6 
	bipush 2
	iadd 
	invokespecial com.whatsapp.client.it.yup.xml.KXmlParser.routine_3499 // pc=3
	putfield .field_8_8   // get_name_1:  .field_8_8   // get_name_2:  .field_8_8   // get_Name:    .field_8_8   // getName->1:  null   // getName->2:  null   // getName->N:  null   // ofs = -1 ord = 0 addr = 8
	aload_0_getfield .field_8_8   // get_name_1:  .field_8_8   // get_name_2:  .field_8_8   // get_Name:    .field_8_8   // getName->1:  null   // getName->2:  null   // getName->N:  null   // ofs = -1 ord = 0 addr = 8
	iload_6 
	aload_3 
	aastore 
	aload_0_getfield .field_8_8   // get_name_1:  .field_8_8   // get_name_2:  .field_8_8   // get_Name:    .field_8_8   // getName->1:  null   // getName->2:  null   // getName->N:  null   // ofs = -1 ord = 0 addr = 8
	iload_6 
	iconst_1 
	iadd 
	aload_0_getfield .field_23_23   // get_name_1:  .field_23_23   // get_name_2:  .field_23_23   // get_Name:    .field_23_23   // getName->1:  null   // getName->2:  null   // getName->N:  null   // ofs = -1 ord = 0 addr = 23
	iload_2 
	bipush 3
	iadd 
	aaload 
	aastore 
	aload_3 
	ifnull Label97
	aload_0_getfield .field_23_23   // get_name_1:  .field_23_23   // get_name_2:  .field_23_23   // get_Name:    .field_23_23   // getName->1:  null   // getName->2:  null   // getName->N:  null   // ofs = -1 ord = 0 addr = 23
	iload_2 
	bipush 3
	iadd 
	aaload 
	ldc_nullstr 
	invokevirtual_short .equals // idx=1 pc=2
	ifeq Label97
	aload_0 
	ldc literal_613:"illegal empty namespace"
	invokespecial com.whatsapp.client.it.yup.xml.KXmlParser.routine_3542 // pc=2
Label97:
	aload_0_getfield .field_23_23   // get_name_1:  .field_23_23   // get_name_2:  .field_23_23   // get_Name:    .field_23_23   // getName->1:  null   // getName->2:  null   // getName->N:  null   // ofs = -1 ord = 0 addr = 23
	iload_2 
	bipush 4
	iadd 
	aload_0_getfield .field_23_23   // get_name_1:  .field_23_23   // get_name_2:  .field_23_23   // get_Name:    .field_23_23   // getName->1:  null   // getName->2:  null   // getName->N:  null   // ofs = -1 ord = 0 addr = 23
	iload_2 
	aload_0 
	aload_0_getfield .field_22_22   // get_name_1:  .field_22_22   // get_name_2:  .field_22_22   // get_Name:    .field_22_22   // getName->1:  null   // getName->2:  null   // getName->N:  null   // ofs = -1 ord = 0 addr = 22
	iconst_1 
	isub 
	dup_x1 
	putfield .field_22_22   // get_name_1:  .field_22_22   // get_name_2:  .field_22_22   // get_Name:    .field_22_22   // getName->1:  null   // getName->2:  null   // getName->N:  null   // ofs = -1 ord = 0 addr = 22
	bipush 2
	ishl 
	iload_2 
	isub 
	invokestatic_lib arraycopy( java.lang.Object, int, java.lang.Object, int, int ) // System
	iinc 2 -4
Label115:
	iinc 2 4
	goto_w Label5
Label117:
	iload_1 
	ifne Label120
	goto_w Label213
Label120:
	aload_0_getfield .field_22_22   // get_name_1:  .field_22_22   // get_name_2:  .field_22_22   // get_Name:    .field_22_22   // getName->1:  null   // getName->2:  null   // getName->N:  null   // ofs = -1 ord = 0 addr = 22
	bipush 2
	ishl 
	bipush 4
	isub 
	istore_2 
Label126:
	iload_2 
	ifge Label129
	goto_w Label213
Label129:
	aload_0_getfield .field_23_23   // get_name_1:  .field_23_23   // get_name_2:  .field_23_23   // get_Name:    .field_23_23   // getName->1:  null   // getName->2:  null   // getName->N:  null   // ofs = -1 ord = 0 addr = 23
	iload_2 
	bipush 2
	iadd 
	aaload 
	astore_3 
	aload_3 
	bipush 58
	invokenonvirtual_lib java.lang.String.indexOf // pc=2
	istore_4 
	iload_4 
	ifne Label158
	aload_0_getfield .field_4_4   // get_name_1:  .field_4_4   // get_name_2:  .field_4_4   // get_Name:    .field_4_4   // getName->1:  null   // getName->2:  null   // getName->N:  null   // ofs = -1 ord = 0 addr = 4
	ifne Label158
	new_lib net.rim.device.api.ui.UiApplication//net.rim.device.api.ui.UiApplication net.rim.device.api.ui.UiApplication net.rim.device.api.ui.UiApplication
	dup 
	new_lib Object//java.lang.Object java.lang.Object java.lang.Object
	dup 
	ldc literal_614:"illegal attribute name: "
	invokespecial_lib java.lang.StringBuffer.<init> // pc=2
	aload_3 
	invokevirtual java.lang.StringBuffer append( java.lang.StringBuffer, java.lang.String ) // pc=2
	ldc literal_615:" at "
	invokevirtual java.lang.StringBuffer append( java.lang.StringBuffer, java.lang.String ) // pc=2
	aload_0 
	invokevirtual java.lang.StringBuffer append( java.lang.StringBuffer, java.lang.Object ) // pc=2
	invokevirtual_short .toString // idx=2 pc=1
	invokespecial_lib java.lang.RuntimeException.<init> // pc=2
	athrow 
Label158:
	iload_4 
	bipush -1
	if_icmpeq Label211
	aload_3 
	iconst_0 
	iload_4 
	invokenonvirtual_lib java.lang.String.substring // pc=3
	astore_5 
	aload_3 
	iload_4 
	iconst_1 
	iadd 
	invokenonvirtual_lib java.lang.String.substring // pc=2
	astore_3 
	aload_0 
	aload_5 
	invokevirtual_short .virtual_4 // idx=4 pc=2
	astore_6 
	aload_6 
	ifnonnull Label195
	aload_0_getfield .field_4_4   // get_name_1:  .field_4_4   // get_name_2:  .field_4_4   // get_Name:    .field_4_4   // getName->1:  null   // getName->2:  null   // getName->N:  null   // ofs = -1 ord = 0 addr = 4
	ifne Label195
	new_lib net.rim.device.api.ui.UiApplication//net.rim.device.api.ui.UiApplication net.rim.device.api.ui.UiApplication net.rim.device.api.ui.UiApplication
	dup 
	new_lib Object//java.lang.Object java.lang.Object java.lang.Object
	dup 
	ldc literal_616:"Undefined Prefix: "
	invokespecial_lib java.lang.StringBuffer.<init> // pc=2
	aload_5 
	invokevirtual java.lang.StringBuffer append( java.lang.StringBuffer, java.lang.String ) // pc=2
	ldc literal_599:" in "
	invokevirtual java.lang.StringBuffer append( java.lang.StringBuffer, java.lang.String ) // pc=2
	aload_0 
	invokevirtual java.lang.StringBuffer append( java.lang.StringBuffer, java.lang.Object ) // pc=2
	invokevirtual_short .toString // idx=2 pc=1
	invokespecial_lib java.lang.RuntimeException.<init> // pc=2
	athrow 
Label195:
	aload_0_getfield .field_23_23   // get_name_1:  .field_23_23   // get_name_2:  .field_23_23   // get_Name:    .field_23_23   // getName->1:  null   // getName->2:  null   // getName->N:  null   // ofs = -1 ord = 0 addr = 23
	iload_2 
	aload_6 
	aastore 
	aload_0_getfield .field_23_23   // get_name_1:  .field_23_23   // get_name_2:  .field_23_23   // get_Name:    .field_23_23   // getName->1:  null   // getName->2:  null   // getName->N:  null   // ofs = -1 ord = 0 addr = 23
	iload_2 
	iconst_1 
	iadd 
	aload_5 
	aastore 
	aload_0_getfield .field_23_23   // get_name_1:  .field_23_23   // get_name_2:  .field_23_23   // get_Name:    .field_23_23   // getName->1:  null   // getName->2:  null   // getName->N:  null   // ofs = -1 ord = 0 addr = 23
	iload_2 
	bipush 2
	iadd 
	aload_3 
	aastore 
Label211:
	iinc 2 -4
	goto_w Label126
Label213:
	aload_0_getfield .field_20_20   // get_name_1:  .field_20_20   // get_name_2:  .field_20_20   // get_Name:    .field_20_20   // getName->1:  null   // getName->2:  null   // getName->N:  null   // ofs = -1 ord = 0 addr = 20
	bipush 58
	invokenonvirtual_lib java.lang.String.indexOf // pc=2
	istore_2 
	iload_2 
	ifne Label228
	aload_0 
	new_lib Object//java.lang.Object java.lang.Object java.lang.Object
	dup 
	ldc literal_617:"illegal tag name: "
	invokespecial_lib java.lang.StringBuffer.<init> // pc=2
	aload_0_getfield .field_20_20   // get_name_1:  .field_20_20   // get_name_2:  .field_20_20   // get_Name:    .field_20_20   // getName->1:  null   // getName->2:  null   // getName->N:  null   // ofs = -1 ord = 0 addr = 20
	invokevirtual java.lang.StringBuffer append( java.lang.StringBuffer, java.lang.String ) // pc=2
	invokevirtual_short .toString // idx=2 pc=1
	invokespecial com.whatsapp.client.it.yup.xml.KXmlParser.routine_3542 // pc=2
Label228:
	iload_2 
	bipush -1
	if_icmpeq Label244
	aload_0 
	aload_0_getfield .field_20_20   // get_name_1:  .field_20_20   // get_name_2:  .field_20_20   // get_Name:    .field_20_20   // getName->1:  null   // getName->2:  null   // getName->N:  null   // ofs = -1 ord = 0 addr = 20
	iconst_0 
	iload_2 
	invokenonvirtual_lib java.lang.String.substring // pc=3
	putfield .field_19_19   // get_name_1:  .field_19_19   // get_name_2:  .field_19_19   // get_Name:    .field_19_19   // getName->1:  null   // getName->2:  null   // getName->N:  null   // ofs = -1 ord = 0 addr = 19
	aload_0 
	aload_0_getfield .field_20_20   // get_name_1:  .field_20_20   // get_name_2:  .field_20_20   // get_Name:    .field_20_20   // getName->1:  null   // getName->2:  null   // getName->N:  null   // ofs = -1 ord = 0 addr = 20
	iload_2 
	iconst_1 
	iadd 
	invokenonvirtual_lib java.lang.String.substring // pc=2
	putfield .field_20_20   // get_name_1:  .field_20_20   // get_name_2:  .field_20_20   // get_Name:    .field_20_20   // getName->1:  null   // getName->2:  null   // getName->N:  null   // ofs = -1 ord = 0 addr = 20
Label244:
	aload_0 
	aload_0 
	aload_0_getfield .field_19_19   // get_name_1:  .field_19_19   // get_name_2:  .field_19_19   // get_Name:    .field_19_19   // getName->1:  null   // getName->2:  null   // getName->N:  null   // ofs = -1 ord = 0 addr = 19
	invokevirtual_short .virtual_4 // idx=4 pc=2
	putfield .field_18_18   // get_name_1:  .field_18_18   // get_name_2:  .field_18_18   // get_Name:    .field_18_18   // getName->1:  null   // getName->2:  null   // getName->N:  null   // ofs = -1 ord = 0 addr = 18
	aload_0_getfield .field_18_18   // get_name_1:  .field_18_18   // get_name_2:  .field_18_18   // get_Name:    .field_18_18   // getName->1:  null   // getName->2:  null   // getName->N:  null   // ofs = -1 ord = 0 addr = 18
	ifnonnull Label265
	aload_0_getfield .field_19_19   // get_name_1:  .field_19_19   // get_name_2:  .field_19_19   // get_Name:    .field_19_19   // getName->1:  null   // getName->2:  null   // getName->N:  null   // ofs = -1 ord = 0 addr = 19
	ifnull Label262
	aload_0 
	new_lib Object//java.lang.Object java.lang.Object java.lang.Object
	dup 
	ldc literal_618:"undefined prefix: "
	invokespecial_lib java.lang.StringBuffer.<init> // pc=2
	aload_0_getfield .field_19_19   // get_name_1:  .field_19_19   // get_name_2:  .field_19_19   // get_Name:    .field_19_19   // getName->1:  null   // getName->2:  null   // getName->N:  null   // ofs = -1 ord = 0 addr = 19
	invokevirtual java.lang.StringBuffer append( java.lang.StringBuffer, java.lang.String ) // pc=2
	invokevirtual_short .toString // idx=2 pc=1
	invokespecial com.whatsapp.client.it.yup.xml.KXmlParser.routine_3542 // pc=2
Label262:
	aload_0 
	ldc_nullstr 
	putfield .field_18_18   // get_name_1:  .field_18_18   // get_name_2:  .field_18_18   // get_Name:    .field_18_18   // getName->1:  null   // getName->2:  null   // getName->N:  null   // ofs = -1 ord = 0 addr = 18
Label265:
	iload_1 
	ireturn 
	}


private final java.lang.String[] com.whatsapp.client.it.yup.xml.KXmlParser.routine_3499( com.whatsapp.client.it.yup.xml.KXmlParser, java.lang.String[], int ); // address: 0
	{
	enter 
	aload_1 
	arraylength 
	iload_2 
	if_icmplt Label7
	aload_1 
	areturn 
Label7:
	iload_2 
	bipush 16
	iadd 
	newarray_object_lib String//java.lang.String java.lang.String java.lang.String
	astore_3 
	aload_1 
	iconst_0 
	aload_3 
	iconst_0 
	aload_1 
	arraylength 
	invokestatic_lib arraycopy( java.lang.Object, int, java.lang.Object, int, int ) // System
	aload_3 
	areturn 
	}


private final com.whatsapp.client.it.yup.xml.KXmlParser.routine_3542( com.whatsapp.client.it.yup.xml.KXmlParser, java.lang.String ); // address: 0
	{
	enter 
	aload_0_getfield .field_4_4   // get_name_1:  .field_4_4   // get_name_2:  .field_4_4   // get_Name:    .field_4_4   // getName->1:  null   // getName->2:  null   // getName->N:  null   // ofs = -1 ord = 0 addr = 4
	ifeq Label15
	aload_0_getfield .field_25_25   // get_name_1:  .field_25_25   // get_name_2:  .field_25_25   // get_Name:    .field_25_25   // getName->1:  null   // getName->2:  null   // getName->N:  null   // ofs = -1 ord = 0 addr = 25
	ifnonnull Label18
	aload_0 
	new_lib Object//java.lang.Object java.lang.Object java.lang.Object
	dup 
	ldc literal_619:"ERR: "
	invokespecial_lib java.lang.StringBuffer.<init> // pc=2
	aload_1 
	invokevirtual java.lang.StringBuffer append( java.lang.StringBuffer, java.lang.String ) // pc=2
	invokevirtual_short .toString // idx=2 pc=1
	putfield .field_25_25   // get_name_1:  .field_25_25   // get_name_2:  .field_25_25   // get_Name:    .field_25_25   // getName->1:  null   // getName->2:  null   // getName->N:  null   // ofs = -1 ord = 0 addr = 25
	return 
Label15:
	aload_0 
	aload_1 
	invokespecial com.whatsapp.client.it.yup.xml.KXmlParser.routine_3595 // pc=2
Label18:
	return 
	}


private final com.whatsapp.client.it.yup.xml.KXmlParser.routine_3595( com.whatsapp.client.it.yup.xml.KXmlParser, java.lang.String ); // address: 0
	{
	enter 
	new_lib com.whatsapp.client.org.xmlpull.v1.XmlPullParserException//module:WhatsApp-37.class#21 module:WhatsApp-37.class#21 module:WhatsApp-37.class#21
	dup 
	aload_1 
	stringlength 
	bipush 100
	if_icmpge Label9
	aload_1 
	goto Label20
Label9:
	new_lib Object//java.lang.Object java.lang.Object java.lang.Object
	dup 
	invokespecial_lib java.lang.StringBuffer.<init> // pc=1
	aload_1 
	iconst_0 
	bipush 100
	invokenonvirtual_lib java.lang.String.substring // pc=3
	invokevirtual java.lang.StringBuffer append( java.lang.StringBuffer, java.lang.String ) // pc=2
	ldc literal_620:"?"
	invokevirtual java.lang.StringBuffer append( java.lang.StringBuffer, java.lang.String ) // pc=2
	invokevirtual_short .toString // idx=2 pc=1
Label20:
	aload_0 
	aconst_null 
	invokespecial_lib .routine_7952 // pc=4
	athrow 
	}


private final com.whatsapp.client.it.yup.xml.KXmlParser.routine_3666( com.whatsapp.client.it.yup.xml.KXmlParser ); // address: 0
	{
	enter 
	aload_0_getfield .field_10_10   // get_name_1:  .field_10_10   // get_name_2:  .field_10_10   // get_Name:    .field_10_10   // getName->1:  null   // getName->2:  null   // getName->N:  null   // ofs = -1 ord = 0 addr = 10
	ifnonnull Label6
	aload_0 
	ldc literal_621:"No Input specified"
	invokespecial com.whatsapp.client.it.yup.xml.KXmlParser.routine_3595 // pc=2
Label6:
	aload_0_getfield .field_16_16   // get_name_1:  .field_16_16   // get_name_2:  .field_16_16   // get_Name:    .field_16_16   // getName->1:  null   // getName->2:  null   // getName->N:  null   // ofs = -1 ord = 0 addr = 16
	bipush 3
	if_icmpne Label14
	aload_0 
	aload_0_getfield .field_6_6   // get_name_1:  .field_6_6   // get_name_2:  .field_6_6   // get_Name:    .field_6_6   // getName->1:  null   // getName->2:  null   // getName->N:  null   // ofs = -1 ord = 0 addr = 6
	iconst_1 
	isub 
	putfield .field_6_6   // get_name_1:  .field_6_6   // get_name_2:  .field_6_6   // get_Name:    .field_6_6   // getName->1:  null   // getName->2:  null   // getName->N:  null   // ofs = -1 ord = 0 addr = 6
Label14:
	aload_0 
	bipush -1
	putfield .field_22_22   // get_name_1:  .field_22_22   // get_name_2:  .field_22_22   // get_Name:    .field_22_22   // getName->1:  null   // getName->2:  null   // getName->N:  null   // ofs = -1 ord = 0 addr = 22
	aload_0_getfield .field_21_21   // get_name_1:  .field_21_21   // get_name_2:  .field_21_21   // get_Name:    .field_21_21   // getName->1:  null   // getName->2:  null   // getName->N:  null   // ofs = -1 ord = 0 addr = 21
	ifeq Label26
	aload_0 
	iconst_0 
	putfield .field_21_21   // get_name_1:  .field_21_21   // get_name_2:  .field_21_21   // get_Name:    .field_21_21   // getName->1:  null   // getName->2:  null   // getName->N:  null   // ofs = -1 ord = 0 addr = 21
	aload_0 
	bipush 3
	putfield .field_16_16   // get_name_1:  .field_16_16   // get_name_2:  .field_16_16   // get_Name:    .field_16_16   // getName->1:  null   // getName->2:  null   // getName->N:  null   // ofs = -1 ord = 0 addr = 16
	return 
Label26:
	aload_0_getfield .field_25_25   // get_name_1:  .field_25_25   // get_name_2:  .field_25_25   // get_Name:    .field_25_25   // getName->1:  null   // getName->2:  null   // getName->N:  null   // ofs = -1 ord = 0 addr = 25
	ifnull Label48
	iconst_0 
	istore_1 
Label30:
	iload_1 
	aload_0_getfield .field_25_25   // get_name_1:  .field_25_25   // get_name_2:  .field_25_25   // get_Name:    .field_25_25   // getName->1:  null   // getName->2:  null   // getName->N:  null   // ofs = -1 ord = 0 addr = 25
	stringlength 
	if_icmpge Label41
	aload_0 
	aload_0_getfield .field_25_25   // get_name_1:  .field_25_25   // get_name_2:  .field_25_25   // get_Name:    .field_25_25   // getName->1:  null   // getName->2:  null   // getName->N:  null   // ofs = -1 ord = 0 addr = 25
	iload_1 
	stringaload 
	invokespecial com.whatsapp.client.it.yup.xml.KXmlParser.routine_5030 // pc=2
	iinc 1 1
	goto Label30
Label41:
	aload_0 
	aconst_null 
	putfield .field_25_25   // get_name_1:  .field_25_25   // get_name_2:  .field_25_25   // get_Name:    .field_25_25   // getName->1:  null   // getName->2:  null   // getName->N:  null   // ofs = -1 ord = 0 addr = 25
	aload_0 
	bipush 9
	putfield .field_16_16   // get_name_1:  .field_16_16   // get_name_2:  .field_16_16   // get_Name:    .field_16_16   // getName->1:  null   // getName->2:  null   // getName->N:  null   // ofs = -1 ord = 0 addr = 16
	return 
Label48:
	aload_0_getfield .field_4_4   // get_name_1:  .field_4_4   // get_name_2:  .field_4_4   // get_Name:    .field_4_4   // getName->1:  null   // getName->2:  null   // getName->N:  null   // ofs = -1 ord = 0 addr = 4
	ifeq Label109
	aload_0_getfield .field_24_24   // get_name_1:  .field_24_24   // get_name_2:  .field_24_24   // get_Name:    .field_24_24   // getName->1:  null   // getName->2:  null   // getName->N:  null   // ofs = -1 ord = 0 addr = 24
	ifgt Label59
	aload_0 
	iconst_0 
	invokespecial com.whatsapp.client.it.yup.xml.KXmlParser.routine_6164 // pc=2
	bipush -1
	if_icmpne Label109
	aload_0_getfield .field_6_6   // get_name_1:  .field_6_6   // get_name_2:  .field_6_6   // get_Name:    .field_6_6   // getName->1:  null   // getName->2:  null   // getName->N:  null   // ofs = -1 ord = 0 addr = 6
	ifle Label109
Label59:
	aload_0_getfield .field_6_6   // get_name_1:  .field_6_6   // get_name_2:  .field_6_6   // get_Name:    .field_6_6   // getName->1:  null   // getName->2:  null   // getName->N:  null   // ofs = -1 ord = 0 addr = 6
	iconst_1 
	isub 
	bipush 2
	ishl 
	istore_1 
	aload_0 
	bipush 3
	putfield .field_16_16   // get_name_1:  .field_16_16   // get_name_2:  .field_16_16   // get_Name:    .field_16_16   // getName->1:  null   // getName->2:  null   // getName->N:  null   // ofs = -1 ord = 0 addr = 16
	aload_0 
	aload_0_getfield .field_7_7   // get_name_1:  .field_7_7   // get_name_2:  .field_7_7   // get_Name:    .field_7_7   // getName->1:  null   // getName->2:  null   // getName->N:  null   // ofs = -1 ord = 0 addr = 7
	iload_1 
	aaload 
	putfield .field_18_18   // get_name_1:  .field_18_18   // get_name_2:  .field_18_18   // get_Name:    .field_18_18   // getName->1:  null   // getName->2:  null   // getName->N:  null   // ofs = -1 ord = 0 addr = 18
	aload_0 
	aload_0_getfield .field_7_7   // get_name_1:  .field_7_7   // get_name_2:  .field_7_7   // get_Name:    .field_7_7   // getName->1:  null   // getName->2:  null   // getName->N:  null   // ofs = -1 ord = 0 addr = 7
	iload_1 
	iconst_1 
	iadd 
	aaload 
	putfield .field_19_19   // get_name_1:  .field_19_19   // get_name_2:  .field_19_19   // get_Name:    .field_19_19   // getName->1:  null   // getName->2:  null   // getName->N:  null   // ofs = -1 ord = 0 addr = 19
	aload_0 
	aload_0_getfield .field_7_7   // get_name_1:  .field_7_7   // get_name_2:  .field_7_7   // get_Name:    .field_7_7   // getName->1:  null   // getName->2:  null   // getName->N:  null   // ofs = -1 ord = 0 addr = 7
	iload_1 
	bipush 2
	iadd 
	aaload 
	putfield .field_20_20   // get_name_1:  .field_20_20   // get_name_2:  .field_20_20   // get_Name:    .field_20_20   // getName->1:  null   // getName->2:  null   // getName->N:  null   // ofs = -1 ord = 0 addr = 20
	aload_0_getfield .field_24_24   // get_name_1:  .field_24_24   // get_name_2:  .field_24_24   // get_Name:    .field_24_24   // getName->1:  null   // getName->2:  null   // getName->N:  null   // ofs = -1 ord = 0 addr = 24
	iconst_1 
	if_icmpeq Label101
	aload_0 
	new_lib Object//java.lang.Object java.lang.Object java.lang.Object
	dup 
	ldc literal_622:"missing end tag /"
	invokespecial_lib java.lang.StringBuffer.<init> // pc=2
	aload_0_getfield .field_20_20   // get_name_1:  .field_20_20   // get_name_2:  .field_20_20   // get_Name:    .field_20_20   // getName->1:  null   // getName->2:  null   // getName->N:  null   // ofs = -1 ord = 0 addr = 20
	invokevirtual java.lang.StringBuffer append( java.lang.StringBuffer, java.lang.String ) // pc=2
	ldc literal_623:" inserted"
	invokevirtual java.lang.StringBuffer append( java.lang.StringBuffer, java.lang.String ) // pc=2
	invokevirtual_short .toString // idx=2 pc=1
	putfield .field_25_25   // get_name_1:  .field_25_25   // get_name_2:  .field_25_25   // get_Name:    .field_25_25   // getName->1:  null   // getName->2:  null   // getName->N:  null   // ofs = -1 ord = 0 addr = 25
Label101:
	aload_0_getfield .field_24_24   // get_name_1:  .field_24_24   // get_name_2:  .field_24_24   // get_Name:    .field_24_24   // getName->1:  null   // getName->2:  null   // getName->N:  null   // ofs = -1 ord = 0 addr = 24
	ifle Label108
	aload_0 
	aload_0_getfield .field_24_24   // get_name_1:  .field_24_24   // get_name_2:  .field_24_24   // get_Name:    .field_24_24   // getName->1:  null   // getName->2:  null   // getName->N:  null   // ofs = -1 ord = 0 addr = 24
	iconst_1 
	isub 
	putfield .field_24_24   // get_name_1:  .field_24_24   // get_name_2:  .field_24_24   // get_Name:    .field_24_24   // getName->1:  null   // getName->2:  null   // getName->N:  null   // ofs = -1 ord = 0 addr = 24
Label108:
	return 
Label109:
	aload_0 
	aconst_null 
	putfield .field_19_19   // get_name_1:  .field_19_19   // get_name_2:  .field_19_19   // get_Name:    .field_19_19   // getName->1:  null   // getName->2:  null   // getName->N:  null   // ofs = -1 ord = 0 addr = 19
	aload_0 
	aconst_null 
	putfield .field_20_20   // get_name_1:  .field_20_20   // get_name_2:  .field_20_20   // get_Name:    .field_20_20   // getName->1:  null   // getName->2:  null   // getName->N:  null   // ofs = -1 ord = 0 addr = 20
	aload_0 
	aconst_null 
	putfield .field_18_18   // get_name_1:  .field_18_18   // get_name_2:  .field_18_18   // get_Name:    .field_18_18   // getName->1:  null   // getName->2:  null   // getName->N:  null   // ofs = -1 ord = 0 addr = 18
	aload_0 
	aload_0 
	invokespecial com.whatsapp.client.it.yup.xml.KXmlParser.routine_4919 // pc=1
	putfield .field_16_16   // get_name_1:  .field_16_16   // get_name_2:  .field_16_16   // get_Name:    .field_16_16   // getName->1:  null   // getName->2:  null   // getName->N:  null   // ofs = -1 ord = 0 addr = 16
	aload_0_getfield .field_16_16   // get_name_1:  .field_16_16   // get_name_2:  .field_16_16   // get_Name:    .field_16_16   // getName->1:  null   // getName->2:  null   // getName->N:  null   // ofs = -1 ord = 0 addr = 16
	tableswitch  :
		
		
		
		
		
		
		

Label124:
	aload_0 
	invokespecial com.whatsapp.client.it.yup.xml.KXmlParser.routine_5583 // pc=1
	return 
Label127:
	aload_0 
	iconst_0 
	invokespecial com.whatsapp.client.it.yup.xml.KXmlParser.routine_5115 // pc=2
	return 
Label131:
	aload_0 
	invokespecial com.whatsapp.client.it.yup.xml.KXmlParser.routine_4715 // pc=1
	return 
Label134:
	return 
Label135:
	aload_0 
	bipush 60
	aload_0_getfield .field_30_30   // get_name_1:  .field_30_30   // get_name_2:  .field_30_30   // get_Name:    .field_30_30   // getName->1:  null   // getName->2:  null   // getName->N:  null   // ofs = -1 ord = 0 addr = 30
	ifne Label141
	iconst_1 
	goto Label142
Label141:
	iconst_0 
Label142:
	invokespecial com.whatsapp.client.it.yup.xml.KXmlParser.routine_5871 // pc=3
	aload_0_getfield .field_6_6   // get_name_1:  .field_6_6   // get_name_2:  .field_6_6   // get_Name:    .field_6_6   // getName->1:  null   // getName->2:  null   // getName->N:  null   // ofs = -1 ord = 0 addr = 6
	ifne Label150
	aload_0_getfield .field_17_17   // get_name_1:  .field_17_17   // get_name_2:  .field_17_17   // get_Name:    .field_17_17   // getName->1:  null   // getName->2:  null   // getName->N:  null   // ofs = -1 ord = 0 addr = 17
	ifeq Label150
	aload_0 
	bipush 7
	putfield .field_16_16   // get_name_1:  .field_16_16   // get_name_2:  .field_16_16   // get_Name:    .field_16_16   // getName->1:  null   // getName->2:  null   // getName->N:  null   // ofs = -1 ord = 0 addr = 16
Label150:
	return 
Label151:
	aload_0 
	aload_0 
	aload_0_getfield .field_30_30   // get_name_1:  .field_30_30   // get_name_2:  .field_30_30   // get_Name:    .field_30_30   // getName->1:  null   // getName->2:  null   // getName->N:  null   // ofs = -1 ord = 0 addr = 30
	invokespecial com.whatsapp.client.it.yup.xml.KXmlParser.routine_3986 // pc=2
	putfield .field_16_16   // get_name_1:  .field_16_16   // get_name_2:  .field_16_16   // get_Name:    .field_16_16   // getName->1:  null   // getName->2:  null   // getName->N:  null   // ofs = -1 ord = 0 addr = 16
	aload_0_getfield .field_16_16   // get_name_1:  .field_16_16   // get_name_2:  .field_16_16   // get_Name:    .field_16_16   // getName->1:  null   // getName->2:  null   // getName->N:  null   // ofs = -1 ord = 0 addr = 16
	sipush 998
	if_icmpne Label160
	goto_w Label14
Label160:
	return 
	}


private final int com.whatsapp.client.it.yup.xml.KXmlParser.routine_3986( com.whatsapp.client.it.yup.xml.KXmlParser, boolean ); // address: 0
	{
	enter 
	ldc_nullstr 
	astore_2 
	iconst_0 
	istore_5 
	aload_0 
	invokespecial com.whatsapp.client.it.yup.xml.KXmlParser.routine_6087 // pc=1
	pop 
	aload_0 
	invokespecial com.whatsapp.client.it.yup.xml.KXmlParser.routine_6087 // pc=1
	istore_6 
	iload_6 
	bipush 63
	if_icmpeq Label15
	goto_w Label190
Label15:
	aload_0 
	iconst_0 
	invokespecial com.whatsapp.client.it.yup.xml.KXmlParser.routine_6164 // pc=2
	bipush 120
	if_icmpeq Label26
	aload_0 
	iconst_0 
	invokespecial com.whatsapp.client.it.yup.xml.KXmlParser.routine_6164 // pc=2
	bipush 88
	if_icmpeq Label26
	goto_w Label185
Label26:
	aload_0 
	iconst_1 
	invokespecial com.whatsapp.client.it.yup.xml.KXmlParser.routine_6164 // pc=2
	bipush 109
	if_icmpeq Label37
	aload_0 
	iconst_1 
	invokespecial com.whatsapp.client.it.yup.xml.KXmlParser.routine_6164 // pc=2
	bipush 77
	if_icmpeq Label37
	goto_w Label185
Label37:
	iload_1 
	ifeq Label49
	aload_0 
	aload_0 
	iconst_0 
	invokespecial com.whatsapp.client.it.yup.xml.KXmlParser.routine_6164 // pc=2
	invokespecial com.whatsapp.client.it.yup.xml.KXmlParser.routine_5030 // pc=2
	aload_0 
	aload_0 
	iconst_1 
	invokespecial com.whatsapp.client.it.yup.xml.KXmlParser.routine_6164 // pc=2
	invokespecial com.whatsapp.client.it.yup.xml.KXmlParser.routine_5030 // pc=2
Label49:
	aload_0 
	invokespecial com.whatsapp.client.it.yup.xml.KXmlParser.routine_6087 // pc=1
	pop 
	aload_0 
	invokespecial com.whatsapp.client.it.yup.xml.KXmlParser.routine_6087 // pc=1
	pop 
	aload_0 
	iconst_0 
	invokespecial com.whatsapp.client.it.yup.xml.KXmlParser.routine_6164 // pc=2
	bipush 108
	if_icmpeq Label66
	aload_0 
	iconst_0 
	invokespecial com.whatsapp.client.it.yup.xml.KXmlParser.routine_6164 // pc=2
	bipush 76
	if_icmpeq Label66
	goto_w Label185
Label66:
	aload_0 
	iconst_1 
	invokespecial com.whatsapp.client.it.yup.xml.KXmlParser.routine_6164 // pc=2
	bipush 32
	if_icmple Label72
	goto_w Label185
Label72:
	aload_0_getfield .field_12_12   // get_name_1:  .field_12_12   // get_name_2:  .field_12_12   // get_Name:    .field_12_12   // getName->1:  null   // getName->2:  null   // getName->N:  null   // ofs = -1 ord = 0 addr = 12
	iconst_1 
	if_icmpne Label78
	aload_0_getfield .field_13_13   // get_name_1:  .field_13_13   // get_name_2:  .field_13_13   // get_Name:    .field_13_13   // getName->1:  null   // getName->2:  null   // getName->N:  null   // ofs = -1 ord = 0 addr = 13
	bipush 4
	if_icmple Label81
Label78:
	aload_0 
	ldc literal_624:"PI must not start with xml"
	invokespecial com.whatsapp.client.it.yup.xml.KXmlParser.routine_3542 // pc=2
Label81:
	aload_0 
	iconst_1 
	invokespecial com.whatsapp.client.it.yup.xml.KXmlParser.routine_5115 // pc=2
	aload_0_getfield .field_22_22   // get_name_1:  .field_22_22   // get_name_2:  .field_22_22   // get_Name:    .field_22_22   // getName->1:  null   // getName->2:  null   // getName->N:  null   // ofs = -1 ord = 0 addr = 22
	iconst_1 
	if_icmplt Label93
	ldc literal_625:"version"
	aload_0_getfield .field_23_23   // get_name_1:  .field_23_23   // get_name_2:  .field_23_23   // get_Name:    .field_23_23   // getName->1:  null   // getName->2:  null   // getName->N:  null   // ofs = -1 ord = 0 addr = 23
	bipush 2
	aaload 
	invokevirtual_short .equals // idx=1 pc=2
	ifne Label96
Label93:
	aload_0 
	ldc literal_626:"version expected"
	invokespecial com.whatsapp.client.it.yup.xml.KXmlParser.routine_3542 // pc=2
Label96:
	aload_0 
	aload_0_getfield .field_23_23   // get_name_1:  .field_23_23   // get_name_2:  .field_23_23   // get_Name:    .field_23_23   // getName->1:  null   // getName->2:  null   // getName->N:  null   // ofs = -1 ord = 0 addr = 23
	bipush 3
	aaload 
	putfield .field_1_1   // get_name_1:  .field_1_1   // get_name_2:  .field_1_1   // get_Name:    .field_1_1   // getName->1:  null   // getName->2:  null   // getName->N:  null   // ofs = -1 ord = 0 addr = 1
	iconst_1 
	istore_7 
	iload_7 
	aload_0_getfield .field_22_22   // get_name_1:  .field_22_22   // get_name_2:  .field_22_22   // get_Name:    .field_22_22   // getName->1:  null   // getName->2:  null   // getName->N:  null   // ofs = -1 ord = 0 addr = 22
	if_icmpge Label118
	ldc literal_627:"encoding"
	aload_0_getfield .field_23_23   // get_name_1:  .field_23_23   // get_name_2:  .field_23_23   // get_Name:    .field_23_23   // getName->1:  null   // getName->2:  null   // getName->N:  null   // ofs = -1 ord = 0 addr = 23
	bipush 6
	aaload 
	invokevirtual_short .equals // idx=1 pc=2
	ifeq Label118
	aload_0 
	aload_0_getfield .field_23_23   // get_name_1:  .field_23_23   // get_name_2:  .field_23_23   // get_Name:    .field_23_23   // getName->1:  null   // getName->2:  null   // getName->N:  null   // ofs = -1 ord = 0 addr = 23
	bipush 7
	aaload 
	putfield .field_11_11   // get_name_1:  .field_11_11   // get_name_2:  .field_11_11   // get_Name:    .field_11_11   // getName->1:  null   // getName->2:  null   // getName->N:  null   // ofs = -1 ord = 0 addr = 11
	iinc 7 1
Label118:
	iload_7 
	aload_0_getfield .field_22_22   // get_name_1:  .field_22_22   // get_name_2:  .field_22_22   // get_Name:    .field_22_22   // getName->1:  null   // getName->2:  null   // getName->N:  null   // ofs = -1 ord = 0 addr = 22
	if_icmpge Label171
	ldc literal_628:"standalone"
	aload_0_getfield .field_23_23   // get_name_1:  .field_23_23   // get_name_2:  .field_23_23   // get_Name:    .field_23_23   // getName->1:  null   // getName->2:  null   // getName->N:  null   // ofs = -1 ord = 0 addr = 23
	bipush 4
	iload_7 
	imul 
	bipush 2
	iadd 
	aaload 
	invokevirtual_short .equals // idx=1 pc=2
	ifeq Label171
	aload_0_getfield .field_23_23   // get_name_1:  .field_23_23   // get_name_2:  .field_23_23   // get_Name:    .field_23_23   // getName->1:  null   // getName->2:  null   // getName->N:  null   // ofs = -1 ord = 0 addr = 23
	bipush 3
	bipush 4
	iload_7 
	imul 
	iadd 
	aaload 
	astore 8
	ldc literal_629:"yes"
	aload 8
	invokevirtual_short .equals // idx=1 pc=2
	ifeq Label150
	aload_0 
	new_lib Throwable//java.lang.Throwable java.lang.Throwable java.lang.Throwable
	dup 
	iconst_1 
	invokespecial_lib java.lang.Boolean.<init> // pc=2
	putfield .field_2_2   // get_name_1:  .field_2_2   // get_name_2:  .field_2_2   // get_Name:    .field_2_2   // getName->1:  null   // getName->2:  null   // getName->N:  null   // ofs = -1 ord = 0 addr = 2
	goto Label170
Label150:
	ldc literal_630:"no"
	aload 8
	invokevirtual_short .equals // idx=1 pc=2
	ifeq Label161
	aload_0 
	new_lib Throwable//java.lang.Throwable java.lang.Throwable java.lang.Throwable
	dup 
	iconst_0 
	invokespecial_lib java.lang.Boolean.<init> // pc=2
	putfield .field_2_2   // get_name_1:  .field_2_2   // get_name_2:  .field_2_2   // get_Name:    .field_2_2   // getName->1:  null   // getName->2:  null   // getName->N:  null   // ofs = -1 ord = 0 addr = 2
	goto Label170
Label161:
	aload_0 
	new_lib Object//java.lang.Object java.lang.Object java.lang.Object
	dup 
	ldc literal_631:"illegal standalone value: "
	invokespecial_lib java.lang.StringBuffer.<init> // pc=2
	aload 8
	invokevirtual java.lang.StringBuffer append( java.lang.StringBuffer, java.lang.String ) // pc=2
	invokevirtual_short .toString // idx=2 pc=1
	invokespecial com.whatsapp.client.it.yup.xml.KXmlParser.routine_3542 // pc=2
Label170:
	iinc 7 1
Label171:
	iload_7 
	aload_0_getfield .field_22_22   // get_name_1:  .field_22_22   // get_name_2:  .field_22_22   // get_Name:    .field_22_22   // getName->1:  null   // getName->2:  null   // getName->N:  null   // ofs = -1 ord = 0 addr = 22
	if_icmpeq Label177
	aload_0 
	ldc literal_632:"illegal xmldecl"
	invokespecial com.whatsapp.client.it.yup.xml.KXmlParser.routine_3542 // pc=2
Label177:
	aload_0 
	iconst_1 
	putfield .field_17_17   // get_name_1:  .field_17_17   // get_name_2:  .field_17_17   // get_Name:    .field_17_17   // getName->1:  null   // getName->2:  null   // getName->N:  null   // ofs = -1 ord = 0 addr = 17
	aload_0 
	iconst_0 
	putfield .field_15_15   // get_name_1:  .field_15_15   // get_name_2:  .field_15_15   // get_Name:    .field_15_15   // getName->1:  null   // getName->2:  null   // getName->N:  null   // ofs = -1 ord = 0 addr = 15
	sipush 998
	ireturn 
Label185:
	bipush 63
	istore_3 
	bipush 8
	istore_4 
	goto Label237
Label190:
	iload_6 
	bipush 33
	if_icmpne Label226
	aload_0 
	iconst_0 
	invokespecial com.whatsapp.client.it.yup.xml.KXmlParser.routine_6164 // pc=2
	bipush 45
	if_icmpne Label205
	bipush 9
	istore_4 
	ldc literal_633:"--"
	astore_2 
	bipush 45
	istore_3 
	goto Label237
Label205:
	aload_0 
	iconst_0 
	invokespecial com.whatsapp.client.it.yup.xml.KXmlParser.routine_6164 // pc=2
	bipush 91
	if_icmpne Label219
	bipush 5
	istore_4 
	ldc literal_634:"[CDATA["
	astore_2 
	bipush 93
	istore_3 
	iconst_1 
	istore_1 
	goto Label237
Label219:
	bipush 10
	istore_4 
	ldc literal_635:"DOCTYPE"
	astore_2 
	bipush -1
	istore_3 
	goto Label237
Label226:
	aload_0 
	new_lib Object//java.lang.Object java.lang.Object java.lang.Object
	dup 
	ldc literal_636:"illegal: <"
	invokespecial_lib java.lang.StringBuffer.<init> // pc=2
	iload_6 
	invokevirtual java.lang.StringBuffer append( java.lang.StringBuffer, int ) // pc=2
	invokevirtual_short .toString // idx=2 pc=1
	invokespecial com.whatsapp.client.it.yup.xml.KXmlParser.routine_3542 // pc=2
	bipush 9
	ireturn 
Label237:
	iconst_0 
	istore_7 
Label239:
	iload_7 
	aload_2 
	stringlength 
	if_icmpge Label250
	aload_0 
	aload_2 
	iload_7 
	stringaload 
	invokespecial com.whatsapp.client.it.yup.xml.KXmlParser.routine_6017 // pc=2
	iinc 7 1
	goto Label239
Label250:
	iload_4 
	bipush 10
	if_icmpne Label257
	aload_0 
	iload_1 
	invokespecial com.whatsapp.client.it.yup.xml.KXmlParser.routine_4615 // pc=2
	goto Label318
Label257:
	aload_0 
	invokespecial com.whatsapp.client.it.yup.xml.KXmlParser.routine_6087 // pc=1
	istore_6 
	iload_6 
	bipush -1
	if_icmpne Label268
	aload_0 
	getstatic com.whatsapp.client.it.yup.xml.KXmlParser.field_54250 // KXmlParser
	invokespecial com.whatsapp.client.it.yup.xml.KXmlParser.routine_3542 // pc=2
	bipush 9
	ireturn 
Label268:
	iload_1 
	ifeq Label273
	aload_0 
	iload_6 
	invokespecial com.whatsapp.client.it.yup.xml.KXmlParser.routine_5030 // pc=2
Label273:
	iload_3 
	bipush 63
	if_icmpeq Label279
	iload_6 
	iload_3 
	if_icmpne Label290
Label279:
	aload_0 
	iconst_0 
	invokespecial com.whatsapp.client.it.yup.xml.KXmlParser.routine_6164 // pc=2
	iload_3 
	if_icmpne Label290
	aload_0 
	iconst_1 
	invokespecial com.whatsapp.client.it.yup.xml.KXmlParser.routine_6164 // pc=2
	bipush 62
	if_icmpne Label290
	goto Label293
Label290:
	iload_6 
	istore_5 
	goto Label257
Label293:
	iload_3 
	bipush 45
	if_icmpne Label302
	iload_5 
	bipush 45
	if_icmpne Label302
	aload_0 
	ldc literal_637:"illegal comment delimiter: --->"
	invokespecial com.whatsapp.client.it.yup.xml.KXmlParser.routine_3542 // pc=2
Label302:
	aload_0 
	invokespecial com.whatsapp.client.it.yup.xml.KXmlParser.routine_6087 // pc=1
	pop 
	aload_0 
	invokespecial com.whatsapp.client.it.yup.xml.KXmlParser.routine_6087 // pc=1
	pop 
	iload_1 
	ifeq Label318
	iload_3 
	bipush 63
	if_icmpeq Label318
	aload_0 
	aload_0_getfield .field_15_15   // get_name_1:  .field_15_15   // get_name_2:  .field_15_15   // get_Name:    .field_15_15   // getName->1:  null   // getName->2:  null   // getName->N:  null   // ofs = -1 ord = 0 addr = 15
	iconst_1 
	isub 
	putfield .field_15_15   // get_name_1:  .field_15_15   // get_name_2:  .field_15_15   // get_Name:    .field_15_15   // getName->1:  null   // getName->2:  null   // getName->N:  null   // ofs = -1 ord = 0 addr = 15
Label318:
	iload_4 
	ireturn 
	}


private final com.whatsapp.client.it.yup.xml.KXmlParser.routine_4615( com.whatsapp.client.it.yup.xml.KXmlParser, boolean ); // address: 0
	{
	enter 
	iconst_1 
	istore_2 
	iconst_0 
	istore_3 
Label5:
	aload_0 
	invokespecial com.whatsapp.client.it.yup.xml.KXmlParser.routine_6087 // pc=1
	istore_4 
	iload_4 
Label10:
	aload_0 
	getstatic com.whatsapp.client.it.yup.xml.KXmlParser.field_54250 // KXmlParser
	invokespecial com.whatsapp.client.it.yup.xml.KXmlParser.routine_3542 // pc=2
	return 
Label14:
	iload_3 
	ifne Label18
	iconst_1 
	goto Label19
Label18:
	iconst_0 
Label19:
	istore_3 
	goto Label31
Label21:
	iload_3 
	ifne Label31
	iinc 2 1
	goto Label31
Label25:
	iload_3 
	ifne Label31
	iinc 2 -1
	iload_2 
	ifne Label31
	return 
Label31:
	iload_1 
	ifeq Label5
	aload_0 
	iload_4 
	invokespecial com.whatsapp.client.it.yup.xml.KXmlParser.routine_5030 // pc=2
	goto Label5
	}


private final com.whatsapp.client.it.yup.xml.KXmlParser.routine_4715( com.whatsapp.client.it.yup.xml.KXmlParser ); // address: 0
	{
	enter 
	aload_0 
	invokespecial com.whatsapp.client.it.yup.xml.KXmlParser.routine_6087 // pc=1
	pop 
	aload_0 
	invokespecial com.whatsapp.client.it.yup.xml.KXmlParser.routine_6087 // pc=1
	pop 
	aload_0 
	aload_0 
	invokespecial com.whatsapp.client.it.yup.xml.KXmlParser.routine_6262 // pc=1
	putfield .field_20_20   // get_name_1:  .field_20_20   // get_name_2:  .field_20_20   // get_Name:    .field_20_20   // getName->1:  null   // getName->2:  null   // getName->N:  null   // ofs = -1 ord = 0 addr = 20
	aload_0 
	invokespecial com.whatsapp.client.it.yup.xml.KXmlParser.routine_6420 // pc=1
	aload_0 
	bipush 62
	invokespecial com.whatsapp.client.it.yup.xml.KXmlParser.routine_6017 // pc=2
	aload_0_getfield .field_6_6   // get_name_1:  .field_6_6   // get_name_2:  .field_6_6   // get_Name:    .field_6_6   // getName->1:  null   // getName->2:  null   // getName->N:  null   // ofs = -1 ord = 0 addr = 6
	iconst_1 
	isub 
	bipush 2
	ishl 
	istore_1 
	aload_0_getfield .field_6_6   // get_name_1:  .field_6_6   // get_name_2:  .field_6_6   // get_Name:    .field_6_6   // getName->1:  null   // getName->2:  null   // getName->N:  null   // ofs = -1 ord = 0 addr = 6
	ifne Label31
	aload_0 
	ldc literal_638:"element stack empty"
	invokespecial com.whatsapp.client.it.yup.xml.KXmlParser.routine_3542 // pc=2
	aload_0 
	bipush 9
	putfield .field_16_16   // get_name_1:  .field_16_16   // get_name_2:  .field_16_16   // get_Name:    .field_16_16   // getName->1:  null   // getName->2:  null   // getName->N:  null   // ofs = -1 ord = 0 addr = 16
	return 
Label31:
	aload_0_getfield .field_20_20   // get_name_1:  .field_20_20   // get_name_2:  .field_20_20   // get_Name:    .field_20_20   // getName->1:  null   // getName->2:  null   // getName->N:  null   // ofs = -1 ord = 0 addr = 20
	aload_0_getfield .field_7_7   // get_name_1:  .field_7_7   // get_name_2:  .field_7_7   // get_Name:    .field_7_7   // getName->1:  null   // getName->2:  null   // getName->N:  null   // ofs = -1 ord = 0 addr = 7
	iload_1 
	bipush 3
	iadd 
	aaload 
	invokevirtual_short .equals // idx=1 pc=2
	ifne Label86
	aload_0 
	new_lib Object//java.lang.Object java.lang.Object java.lang.Object
	dup 
	ldc literal_639:"expected: /"
	invokespecial_lib java.lang.StringBuffer.<init> // pc=2
	aload_0_getfield .field_7_7   // get_name_1:  .field_7_7   // get_name_2:  .field_7_7   // get_Name:    .field_7_7   // getName->1:  null   // getName->2:  null   // getName->N:  null   // ofs = -1 ord = 0 addr = 7
	iload_1 
	bipush 3
	iadd 
	aaload 
	invokevirtual java.lang.StringBuffer append( java.lang.StringBuffer, java.lang.String ) // pc=2
	ldc literal_640:" read: "
	invokevirtual java.lang.StringBuffer append( java.lang.StringBuffer, java.lang.String ) // pc=2
	aload_0_getfield .field_20_20   // get_name_1:  .field_20_20   // get_name_2:  .field_20_20   // get_Name:    .field_20_20   // getName->1:  null   // getName->2:  null   // getName->N:  null   // ofs = -1 ord = 0 addr = 20
	invokevirtual java.lang.StringBuffer append( java.lang.StringBuffer, java.lang.String ) // pc=2
	invokevirtual_short .toString // idx=2 pc=1
	invokespecial com.whatsapp.client.it.yup.xml.KXmlParser.routine_3542 // pc=2
	iload_1 
	istore_2 
Label58:
	iload_2 
	iflt Label77
	aload_0_getfield .field_20_20   // get_name_1:  .field_20_20   // get_name_2:  .field_20_20   // get_Name:    .field_20_20   // getName->1:  null   // getName->2:  null   // getName->N:  null   // ofs = -1 ord = 0 addr = 20
	invokenonvirtual_lib java.lang.String.toLowerCase // pc=1
	aload_0_getfield .field_7_7   // get_name_1:  .field_7_7   // get_name_2:  .field_7_7   // get_Name:    .field_7_7   // getName->1:  null   // getName->2:  null   // getName->N:  null   // ofs = -1 ord = 0 addr = 7
	iload_2 
	bipush 3
	iadd 
	aaload 
	invokenonvirtual_lib java.lang.String.toLowerCase // pc=1
	invokevirtual_short .equals // idx=1 pc=2
	ifne Label77
	aload_0 
	aload_0_getfield .field_24_24   // get_name_1:  .field_24_24   // get_name_2:  .field_24_24   // get_Name:    .field_24_24   // getName->1:  null   // getName->2:  null   // getName->N:  null   // ofs = -1 ord = 0 addr = 24
	iconst_1 
	iadd 
	putfield .field_24_24   // get_name_1:  .field_24_24   // get_name_2:  .field_24_24   // get_Name:    .field_24_24   // getName->1:  null   // getName->2:  null   // getName->N:  null   // ofs = -1 ord = 0 addr = 24
	iinc 2 -4
	goto Label58
Label77:
	iload_2 
	ifge Label86
	aload_0 
	iconst_0 
	putfield .field_24_24   // get_name_1:  .field_24_24   // get_name_2:  .field_24_24   // get_Name:    .field_24_24   // getName->1:  null   // getName->2:  null   // getName->N:  null   // ofs = -1 ord = 0 addr = 24
	aload_0 
	bipush 9
	putfield .field_16_16   // get_name_1:  .field_16_16   // get_name_2:  .field_16_16   // get_Name:    .field_16_16   // getName->1:  null   // getName->2:  null   // getName->N:  null   // ofs = -1 ord = 0 addr = 16
	return 
Label86:
	aload_0 
	aload_0_getfield .field_7_7   // get_name_1:  .field_7_7   // get_name_2:  .field_7_7   // get_Name:    .field_7_7   // getName->1:  null   // getName->2:  null   // getName->N:  null   // ofs = -1 ord = 0 addr = 7
	iload_1 
	aaload 
	putfield .field_18_18   // get_name_1:  .field_18_18   // get_name_2:  .field_18_18   // get_Name:    .field_18_18   // getName->1:  null   // getName->2:  null   // getName->N:  null   // ofs = -1 ord = 0 addr = 18
	aload_0 
	aload_0_getfield .field_7_7   // get_name_1:  .field_7_7   // get_name_2:  .field_7_7   // get_Name:    .field_7_7   // getName->1:  null   // getName->2:  null   // getName->N:  null   // ofs = -1 ord = 0 addr = 7
	iload_1 
	iconst_1 
	iadd 
	aaload 
	putfield .field_19_19   // get_name_1:  .field_19_19   // get_name_2:  .field_19_19   // get_Name:    .field_19_19   // getName->1:  null   // getName->2:  null   // getName->N:  null   // ofs = -1 ord = 0 addr = 19
	aload_0 
	aload_0_getfield .field_7_7   // get_name_1:  .field_7_7   // get_name_2:  .field_7_7   // get_Name:    .field_7_7   // getName->1:  null   // getName->2:  null   // getName->N:  null   // ofs = -1 ord = 0 addr = 7
	iload_1 
	bipush 2
	iadd 
	aaload 
	putfield .field_20_20   // get_name_1:  .field_20_20   // get_name_2:  .field_20_20   // get_Name:    .field_20_20   // getName->1:  null   // getName->2:  null   // getName->N:  null   // ofs = -1 ord = 0 addr = 20
	return 
	}


private final int com.whatsapp.client.it.yup.xml.KXmlParser.routine_4919( com.whatsapp.client.it.yup.xml.KXmlParser ); // address: 0
	{
	enter_narrow 
	aload_0 
	iconst_0 
	invokespecial com.whatsapp.client.it.yup.xml.KXmlParser.routine_6164 // pc=2
Label5:
	iconst_1 
	ireturn 
Label7:
	bipush 6
	ireturn 
Label9:
	aload_0 
	iconst_1 
	invokespecial com.whatsapp.client.it.yup.xml.KXmlParser.routine_6164 // pc=2
Label13:
	bipush 3
	ireturn 
Label15:
	sipush 999
	ireturn 
Label17:
	bipush 2
	ireturn 
Label19:
	bipush 4
	ireturn 
	}


private final java.lang.String com.whatsapp.client.it.yup.xml.KXmlParser.routine_4998( com.whatsapp.client.it.yup.xml.KXmlParser, int ); // address: 0
	{
	enter 
	new_lib String//java.lang.String java.lang.String java.lang.String
	dup 
	aload_0_getfield .field_14_14   // get_name_1:  .field_14_14   // get_name_2:  .field_14_14   // get_Name:    .field_14_14   // getName->1:  null   // getName->2:  null   // getName->N:  null   // ofs = -1 ord = 0 addr = 14
	iload_1 
	aload_0_getfield .field_15_15   // get_name_1:  .field_15_15   // get_name_2:  .field_15_15   // get_Name:    .field_15_15   // getName->1:  null   // getName->2:  null   // getName->N:  null   // ofs = -1 ord = 0 addr = 15
	iload_1 
	isub 
	invokespecial_lib java.lang.String.<init> // pc=4
	areturn 
	}


private final com.whatsapp.client.it.yup.xml.KXmlParser.routine_5030( com.whatsapp.client.it.yup.xml.KXmlParser, int ); // address: 0
	{
	enter 
	aload_0 
	aload_0_getfield .field_17_17   // get_name_1:  .field_17_17   // get_name_2:  .field_17_17   // get_Name:    .field_17_17   // getName->1:  null   // getName->2:  null   // getName->N:  null   // ofs = -1 ord = 0 addr = 17
	iload_1 
	bipush 32
	if_icmpgt Label8
	iconst_1 
	goto Label9
Label8:
	iconst_0 
Label9:
	iand 
	putfield .field_17_17   // get_name_1:  .field_17_17   // get_name_2:  .field_17_17   // get_Name:    .field_17_17   // getName->1:  null   // getName->2:  null   // getName->N:  null   // ofs = -1 ord = 0 addr = 17
	aload_0_getfield .field_15_15   // get_name_1:  .field_15_15   // get_name_2:  .field_15_15   // get_Name:    .field_15_15   // getName->1:  null   // getName->2:  null   // getName->N:  null   // ofs = -1 ord = 0 addr = 15
	aload_0_getfield .field_14_14   // get_name_1:  .field_14_14   // get_name_2:  .field_14_14   // get_Name:    .field_14_14   // getName->1:  null   // getName->2:  null   // getName->N:  null   // ofs = -1 ord = 0 addr = 14
	arraylength 
	if_icmpne Label33
	aload_0_getfield .field_15_15   // get_name_1:  .field_15_15   // get_name_2:  .field_15_15   // get_Name:    .field_15_15   // getName->1:  null   // getName->2:  null   // getName->N:  null   // ofs = -1 ord = 0 addr = 15
	bipush 4
	imul 
	bipush 3
	idiv 
	bipush 4
	iadd 
	newarray 3
	astore_2 
	aload_0_getfield .field_14_14   // get_name_1:  .field_14_14   // get_name_2:  .field_14_14   // get_Name:    .field_14_14   // getName->1:  null   // getName->2:  null   // getName->N:  null   // ofs = -1 ord = 0 addr = 14
	iconst_0 
	aload_2 
	iconst_0 
	aload_0_getfield .field_15_15   // get_name_1:  .field_15_15   // get_name_2:  .field_15_15   // get_Name:    .field_15_15   // getName->1:  null   // getName->2:  null   // getName->N:  null   // ofs = -1 ord = 0 addr = 15
	invokestatic_lib arraycopy( java.lang.Object, int, java.lang.Object, int, int ) // System
	aload_0 
	aload_2 
	putfield .field_14_14   // get_name_1:  .field_14_14   // get_name_2:  .field_14_14   // get_Name:    .field_14_14   // getName->1:  null   // getName->2:  null   // getName->N:  null   // ofs = -1 ord = 0 addr = 14
Label33:
	aload_0_getfield .field_14_14   // get_name_1:  .field_14_14   // get_name_2:  .field_14_14   // get_Name:    .field_14_14   // getName->1:  null   // getName->2:  null   // getName->N:  null   // ofs = -1 ord = 0 addr = 14
	aload_0 
	aload_0_getfield .field_15_15   // get_name_1:  .field_15_15   // get_name_2:  .field_15_15   // get_Name:    .field_15_15   // getName->1:  null   // getName->2:  null   // getName->N:  null   // ofs = -1 ord = 0 addr = 15
	dup_x1 
	iconst_1 
	iadd 
	putfield .field_15_15   // get_name_1:  .field_15_15   // get_name_2:  .field_15_15   // get_Name:    .field_15_15   // getName->1:  null   // getName->2:  null   // getName->N:  null   // ofs = -1 ord = 0 addr = 15
	iload_1 
	i2c 
	castore 
	return 
	}


private final com.whatsapp.client.it.yup.xml.KXmlParser.routine_5115( com.whatsapp.client.it.yup.xml.KXmlParser, boolean ); // address: 0
	{
	enter 
	iload_1 
	ifne Label6
	aload_0 
	invokespecial com.whatsapp.client.it.yup.xml.KXmlParser.routine_6087 // pc=1
	pop 
Label6:
	aload_0 
	aload_0 
	invokespecial com.whatsapp.client.it.yup.xml.KXmlParser.routine_6262 // pc=1
	putfield .field_20_20   // get_name_1:  .field_20_20   // get_name_2:  .field_20_20   // get_Name:    .field_20_20   // getName->1:  null   // getName->2:  null   // getName->N:  null   // ofs = -1 ord = 0 addr = 20
	aload_0 
	iconst_0 
	putfield .field_22_22   // get_name_1:  .field_22_22   // get_name_2:  .field_22_22   // get_Name:    .field_22_22   // getName->1:  null   // getName->2:  null   // getName->N:  null   // ofs = -1 ord = 0 addr = 22
Label13:
	aload_0 
	invokespecial com.whatsapp.client.it.yup.xml.KXmlParser.routine_6420 // pc=1
	aload_0 
	iconst_0 
	invokespecial com.whatsapp.client.it.yup.xml.KXmlParser.routine_6164 // pc=2
	istore_2 
	iload_1 
	ifeq Label31
	iload_2 
	bipush 63
	if_icmpne Label55
	aload_0 
	invokespecial com.whatsapp.client.it.yup.xml.KXmlParser.routine_6087 // pc=1
	pop 
	aload_0 
	bipush 62
	invokespecial com.whatsapp.client.it.yup.xml.KXmlParser.routine_6017 // pc=2
	return 
Label31:
	iload_2 
	bipush 47
	if_icmpne Label46
	aload_0 
	iconst_1 
	putfield .field_21_21   // get_name_1:  .field_21_21   // get_name_2:  .field_21_21   // get_Name:    .field_21_21   // getName->1:  null   // getName->2:  null   // getName->N:  null   // ofs = -1 ord = 0 addr = 21
	aload_0 
	invokespecial com.whatsapp.client.it.yup.xml.KXmlParser.routine_6087 // pc=1
	pop 
	aload_0 
	invokespecial com.whatsapp.client.it.yup.xml.KXmlParser.routine_6420 // pc=1
	aload_0 
	bipush 62
	invokespecial com.whatsapp.client.it.yup.xml.KXmlParser.routine_6017 // pc=2
	goto_w Label172
Label46:
	iload_2 
	bipush 62
	if_icmpne Label55
	iload_1 
	ifne Label55
	aload_0 
	invokespecial com.whatsapp.client.it.yup.xml.KXmlParser.routine_6087 // pc=1
	pop 
	goto_w Label172
Label55:
	iload_2 
	bipush -1
	if_icmpne Label62
	aload_0 
	getstatic com.whatsapp.client.it.yup.xml.KXmlParser.field_54250 // KXmlParser
	invokespecial com.whatsapp.client.it.yup.xml.KXmlParser.routine_3542 // pc=2
	return 
Label62:
	aload_0 
	invokespecial com.whatsapp.client.it.yup.xml.KXmlParser.routine_6262 // pc=1
	astore_3 
	aload_3 
	stringlength 
	ifne Label72
	aload_0 
	ldc literal_641:"attr name expected"
	invokespecial com.whatsapp.client.it.yup.xml.KXmlParser.routine_3542 // pc=2
	goto_w Label172
Label72:
	aload_0 
	aload_0_getfield .field_22_22   // get_name_1:  .field_22_22   // get_name_2:  .field_22_22   // get_Name:    .field_22_22   // getName->1:  null   // getName->2:  null   // getName->N:  null   // ofs = -1 ord = 0 addr = 22
	dup_x1 
	iconst_1 
	iadd 
	putfield .field_22_22   // get_name_1:  .field_22_22   // get_name_2:  .field_22_22   // get_Name:    .field_22_22   // getName->1:  null   // getName->2:  null   // getName->N:  null   // ofs = -1 ord = 0 addr = 22
	bipush 2
	ishl 
	istore_4 
	aload_0 
	aload_0 
	aload_0_getfield .field_23_23   // get_name_1:  .field_23_23   // get_name_2:  .field_23_23   // get_Name:    .field_23_23   // getName->1:  null   // getName->2:  null   // getName->N:  null   // ofs = -1 ord = 0 addr = 23
	iload_4 
	bipush 4
	iadd 
	invokespecial com.whatsapp.client.it.yup.xml.KXmlParser.routine_3499 // pc=3
	putfield .field_23_23   // get_name_1:  .field_23_23   // get_name_2:  .field_23_23   // get_Name:    .field_23_23   // getName->1:  null   // getName->2:  null   // getName->N:  null   // ofs = -1 ord = 0 addr = 23
	aload_0_getfield .field_23_23   // get_name_1:  .field_23_23   // get_name_2:  .field_23_23   // get_Name:    .field_23_23   // getName->1:  null   // getName->2:  null   // getName->N:  null   // ofs = -1 ord = 0 addr = 23
	iload_4 
	iinc 4 1
	ldc_nullstr 
	aastore 
	aload_0_getfield .field_23_23   // get_name_1:  .field_23_23   // get_name_2:  .field_23_23   // get_Name:    .field_23_23   // getName->1:  null   // getName->2:  null   // getName->N:  null   // ofs = -1 ord = 0 addr = 23
	iload_4 
	iinc 4 1
	aconst_null 
	aastore 
	aload_0_getfield .field_23_23   // get_name_1:  .field_23_23   // get_name_2:  .field_23_23   // get_Name:    .field_23_23   // getName->1:  null   // getName->2:  null   // getName->N:  null   // ofs = -1 ord = 0 addr = 23
	iload_4 
	iinc 4 1
	aload_3 
	aastore 
	aload_0 
	invokespecial com.whatsapp.client.it.yup.xml.KXmlParser.routine_6420 // pc=1
	aload_0 
	iconst_0 
	invokespecial com.whatsapp.client.it.yup.xml.KXmlParser.routine_6164 // pc=2
	bipush 61
	if_icmpeq Label125
	aload_0 
	new_lib Object//java.lang.Object java.lang.Object java.lang.Object
	dup 
	ldc literal_642:"Attr.value missing f. "
	invokespecial_lib java.lang.StringBuffer.<init> // pc=2
	aload_3 
	invokevirtual java.lang.StringBuffer append( java.lang.StringBuffer, java.lang.String ) // pc=2
	invokevirtual_short .toString // idx=2 pc=1
	invokespecial com.whatsapp.client.it.yup.xml.KXmlParser.routine_3542 // pc=2
	aload_0_getfield .field_23_23   // get_name_1:  .field_23_23   // get_name_2:  .field_23_23   // get_Name:    .field_23_23   // getName->1:  null   // getName->2:  null   // getName->N:  null   // ofs = -1 ord = 0 addr = 23
	iload_4 
	ldc literal_643:"1"
	aastore 
	goto_w Label13
Label125:
	aload_0 
	bipush 61
	invokespecial com.whatsapp.client.it.yup.xml.KXmlParser.routine_6017 // pc=2
	aload_0 
	invokespecial com.whatsapp.client.it.yup.xml.KXmlParser.routine_6420 // pc=1
	aload_0 
	iconst_0 
	invokespecial com.whatsapp.client.it.yup.xml.KXmlParser.routine_6164 // pc=2
	istore_5 
	iload_5 
	bipush 39
	if_icmpeq Label146
	iload_5 
	bipush 34
	if_icmpeq Label146
	aload_0 
	ldc literal_644:"attr value delimiter missing!"
	invokespecial com.whatsapp.client.it.yup.xml.KXmlParser.routine_3542 // pc=2
	bipush 32
	istore_5 
	goto Label149
Label146:
	aload_0 
	invokespecial com.whatsapp.client.it.yup.xml.KXmlParser.routine_6087 // pc=1
	pop 
Label149:
	aload_0_getfield .field_15_15   // get_name_1:  .field_15_15   // get_name_2:  .field_15_15   // get_Name:    .field_15_15   // getName->1:  null   // getName->2:  null   // getName->N:  null   // ofs = -1 ord = 0 addr = 15
	istore_6 
	aload_0 
	iload_5 
	iconst_1 
	invokespecial com.whatsapp.client.it.yup.xml.KXmlParser.routine_5871 // pc=3
	aload_0_getfield .field_23_23   // get_name_1:  .field_23_23   // get_name_2:  .field_23_23   // get_Name:    .field_23_23   // getName->1:  null   // getName->2:  null   // getName->N:  null   // ofs = -1 ord = 0 addr = 23
	iload_4 
	aload_0 
	iload_6 
	invokespecial com.whatsapp.client.it.yup.xml.KXmlParser.routine_4998 // pc=2
	aastore 
	aload_0 
	iload_6 
	putfield .field_15_15   // get_name_1:  .field_15_15   // get_name_2:  .field_15_15   // get_Name:    .field_15_15   // getName->1:  null   // getName->2:  null   // getName->N:  null   // ofs = -1 ord = 0 addr = 15
	iload_5 
	bipush 32
	if_icmpne Label168
	goto_w Label13
Label168:
	aload_0 
	invokespecial com.whatsapp.client.it.yup.xml.KXmlParser.routine_6087 // pc=1
	pop 
	goto_w Label13
Label172:
	aload_0 
	aload_0_getfield .field_6_6   // get_name_1:  .field_6_6   // get_name_2:  .field_6_6   // get_Name:    .field_6_6   // getName->1:  null   // getName->2:  null   // getName->N:  null   // ofs = -1 ord = 0 addr = 6
	dup_x1 
	iconst_1 
	iadd 
	putfield .field_6_6   // get_name_1:  .field_6_6   // get_name_2:  .field_6_6   // get_Name:    .field_6_6   // getName->1:  null   // getName->2:  null   // getName->N:  null   // ofs = -1 ord = 0 addr = 6
	bipush 2
	ishl 
	istore_2 
	aload_0 
	aload_0 
	aload_0_getfield .field_7_7   // get_name_1:  .field_7_7   // get_name_2:  .field_7_7   // get_Name:    .field_7_7   // getName->1:  null   // getName->2:  null   // getName->N:  null   // ofs = -1 ord = 0 addr = 7
	iload_2 
	bipush 4
	iadd 
	invokespecial com.whatsapp.client.it.yup.xml.KXmlParser.routine_3499 // pc=3
	putfield .field_7_7   // get_name_1:  .field_7_7   // get_name_2:  .field_7_7   // get_Name:    .field_7_7   // getName->1:  null   // getName->2:  null   // getName->N:  null   // ofs = -1 ord = 0 addr = 7
	aload_0_getfield .field_7_7   // get_name_1:  .field_7_7   // get_name_2:  .field_7_7   // get_Name:    .field_7_7   // getName->1:  null   // getName->2:  null   // getName->N:  null   // ofs = -1 ord = 0 addr = 7
	iload_2 
	bipush 3
	iadd 
	aload_0_getfield .field_20_20   // get_name_1:  .field_20_20   // get_name_2:  .field_20_20   // get_Name:    .field_20_20   // getName->1:  null   // getName->2:  null   // getName->N:  null   // ofs = -1 ord = 0 addr = 20
	aastore 
	aload_0_getfield .field_6_6   // get_name_1:  .field_6_6   // get_name_2:  .field_6_6   // get_Name:    .field_6_6   // getName->1:  null   // getName->2:  null   // getName->N:  null   // ofs = -1 ord = 0 addr = 6
	aload_0_getfield .field_9_9   // get_name_1:  .field_9_9   // get_name_2:  .field_9_9   // get_Name:    .field_9_9   // getName->1:  null   // getName->2:  null   // getName->N:  null   // ofs = -1 ord = 0 addr = 9
	arraylength 
	if_icmplt Label214
	aload_0_getfield .field_6_6   // get_name_1:  .field_6_6   // get_name_2:  .field_6_6   // get_Name:    .field_6_6   // getName->1:  null   // getName->2:  null   // getName->N:  null   // ofs = -1 ord = 0 addr = 6
	bipush 4
	iadd 
	newarray 5
	astore_3 
	aload_0_getfield .field_9_9   // get_name_1:  .field_9_9   // get_name_2:  .field_9_9   // get_Name:    .field_9_9   // getName->1:  null   // getName->2:  null   // getName->N:  null   // ofs = -1 ord = 0 addr = 9
	iconst_0 
	aload_3 
	iconst_0 
	aload_0_getfield .field_9_9   // get_name_1:  .field_9_9   // get_name_2:  .field_9_9   // get_Name:    .field_9_9   // getName->1:  null   // getName->2:  null   // getName->N:  null   // ofs = -1 ord = 0 addr = 9
	arraylength 
	invokestatic_lib arraycopy( java.lang.Object, int, java.lang.Object, int, int ) // System
	aload_0 
	aload_3 
	putfield .field_9_9   // get_name_1:  .field_9_9   // get_name_2:  .field_9_9   // get_Name:    .field_9_9   // getName->1:  null   // getName->2:  null   // getName->N:  null   // ofs = -1 ord = 0 addr = 9
Label214:
	aload_0_getfield .field_9_9   // get_name_1:  .field_9_9   // get_name_2:  .field_9_9   // get_Name:    .field_9_9   // getName->1:  null   // getName->2:  null   // getName->N:  null   // ofs = -1 ord = 0 addr = 9
	aload_0_getfield .field_6_6   // get_name_1:  .field_6_6   // get_name_2:  .field_6_6   // get_Name:    .field_6_6   // getName->1:  null   // getName->2:  null   // getName->N:  null   // ofs = -1 ord = 0 addr = 6
	aload_0_getfield .field_9_9   // get_name_1:  .field_9_9   // get_name_2:  .field_9_9   // get_Name:    .field_9_9   // getName->1:  null   // getName->2:  null   // getName->N:  null   // ofs = -1 ord = 0 addr = 9
	aload_0_getfield .field_6_6   // get_name_1:  .field_6_6   // get_name_2:  .field_6_6   // get_Name:    .field_6_6   // getName->1:  null   // getName->2:  null   // getName->N:  null   // ofs = -1 ord = 0 addr = 6
	iconst_1 
	isub 
	iaload 
	iastore 
	aload_0_getfield .field_3_3   // get_name_1:  .field_3_3   // get_name_2:  .field_3_3   // get_Name:    .field_3_3   // getName->1:  null   // getName->2:  null   // getName->N:  null   // ofs = -1 ord = 0 addr = 3
	ifeq Label228
	aload_0 
	invokespecial com.whatsapp.client.it.yup.xml.KXmlParser.routine_2994 // pc=1
	pop 
	goto Label231
Label228:
	aload_0 
	ldc_nullstr 
	putfield .field_18_18   // get_name_1:  .field_18_18   // get_name_2:  .field_18_18   // get_Name:    .field_18_18   // getName->1:  null   // getName->2:  null   // getName->N:  null   // ofs = -1 ord = 0 addr = 18
Label231:
	aload_0_getfield .field_7_7   // get_name_1:  .field_7_7   // get_name_2:  .field_7_7   // get_Name:    .field_7_7   // getName->1:  null   // getName->2:  null   // getName->N:  null   // ofs = -1 ord = 0 addr = 7
	iload_2 
	aload_0_getfield .field_18_18   // get_name_1:  .field_18_18   // get_name_2:  .field_18_18   // get_Name:    .field_18_18   // getName->1:  null   // getName->2:  null   // getName->N:  null   // ofs = -1 ord = 0 addr = 18
	aastore 
	aload_0_getfield .field_7_7   // get_name_1:  .field_7_7   // get_name_2:  .field_7_7   // get_Name:    .field_7_7   // getName->1:  null   // getName->2:  null   // getName->N:  null   // ofs = -1 ord = 0 addr = 7
	iload_2 
	iconst_1 
	iadd 
	aload_0_getfield .field_19_19   // get_name_1:  .field_19_19   // get_name_2:  .field_19_19   // get_Name:    .field_19_19   // getName->1:  null   // getName->2:  null   // getName->N:  null   // ofs = -1 ord = 0 addr = 19
	aastore 
	aload_0_getfield .field_7_7   // get_name_1:  .field_7_7   // get_name_2:  .field_7_7   // get_Name:    .field_7_7   // getName->1:  null   // getName->2:  null   // getName->N:  null   // ofs = -1 ord = 0 addr = 7
	iload_2 
	bipush 2
	iadd 
	aload_0_getfield .field_20_20   // get_name_1:  .field_20_20   // get_name_2:  .field_20_20   // get_Name:    .field_20_20   // getName->1:  null   // getName->2:  null   // getName->N:  null   // ofs = -1 ord = 0 addr = 20
	aastore 
	return 
	}


private final com.whatsapp.client.it.yup.xml.KXmlParser.routine_5583( com.whatsapp.client.it.yup.xml.KXmlParser ); // address: 0
	{
	enter 
	aload_0 
	aload_0 
	invokespecial com.whatsapp.client.it.yup.xml.KXmlParser.routine_6087 // pc=1
	invokespecial com.whatsapp.client.it.yup.xml.KXmlParser.routine_5030 // pc=2
	aload_0_getfield .field_15_15   // get_name_1:  .field_15_15   // get_name_2:  .field_15_15   // get_Name:    .field_15_15   // getName->1:  null   // getName->2:  null   // getName->N:  null   // ofs = -1 ord = 0 addr = 15
	istore_1 
Label7:
	aload_0 
	invokespecial com.whatsapp.client.it.yup.xml.KXmlParser.routine_6087 // pc=1
	istore_2 
	iload_2 
	bipush 59
	if_icmpne Label14
	goto Label60
Label14:
	iload_2 
	sipush 128
	if_icmpge Label56
	iload_2 
	bipush 48
	if_icmplt Label23
	iload_2 
	bipush 57
	if_icmple Label56
Label23:
	iload_2 
	bipush 97
	if_icmplt Label29
	iload_2 
	bipush 122
	if_icmple Label56
Label29:
	iload_2 
	bipush 65
	if_icmplt Label35
	iload_2 
	bipush 90
	if_icmple Label56
Label35:
	iload_2 
	bipush 95
	if_icmpeq Label56
	iload_2 
	bipush 45
	if_icmpeq Label56
	iload_2 
	bipush 35
	if_icmpeq Label56
	aload_0_getfield .field_4_4   // get_name_1:  .field_4_4   // get_name_2:  .field_4_4   // get_Name:    .field_4_4   // getName->1:  null   // getName->2:  null   // getName->N:  null   // ofs = -1 ord = 0 addr = 4
	ifne Label49
	aload_0 
	ldc literal_645:"unterminated entity ref"
	invokespecial com.whatsapp.client.it.yup.xml.KXmlParser.routine_3542 // pc=2
Label49:
	iload_2 
	bipush -1
	if_icmpeq Label55
	aload_0 
	iload_2 
	invokespecial com.whatsapp.client.it.yup.xml.KXmlParser.routine_5030 // pc=2
Label55:
	return 
Label56:
	aload_0 
	iload_2 
	invokespecial com.whatsapp.client.it.yup.xml.KXmlParser.routine_5030 // pc=2
	goto Label7
Label60:
	aload_0 
	iload_1 
	invokespecial com.whatsapp.client.it.yup.xml.KXmlParser.routine_4998 // pc=2
	astore_2 
	aload_0 
	iload_1 
	iconst_1 
	isub 
	putfield .field_15_15   // get_name_1:  .field_15_15   // get_name_2:  .field_15_15   // get_Name:    .field_15_15   // getName->1:  null   // getName->2:  null   // getName->N:  null   // ofs = -1 ord = 0 addr = 15
	aload_0_getfield .field_30_30   // get_name_1:  .field_30_30   // get_name_2:  .field_30_30   // get_Name:    .field_30_30   // getName->1:  null   // getName->2:  null   // getName->N:  null   // ofs = -1 ord = 0 addr = 30
	ifeq Label77
	aload_0_getfield .field_16_16   // get_name_1:  .field_16_16   // get_name_2:  .field_16_16   // get_Name:    .field_16_16   // getName->1:  null   // getName->2:  null   // getName->N:  null   // ofs = -1 ord = 0 addr = 16
	bipush 6
	if_icmpne Label77
	aload_0 
	aload_2 
	putfield .field_20_20   // get_name_1:  .field_20_20   // get_name_2:  .field_20_20   // get_Name:    .field_20_20   // getName->1:  null   // getName->2:  null   // getName->N:  null   // ofs = -1 ord = 0 addr = 20
Label77:
	aload_2 
	iconst_0 
	stringaload 
	bipush 35
	if_icmpne Label102
	aload_2 
	iconst_1 
	stringaload 
	bipush 120
	if_icmpne Label93
	aload_2 
	bipush 2
	invokenonvirtual_lib java.lang.String.substring // pc=2
	bipush 16
	invokestatic_lib int parseInt( java.lang.String, int ) // Integer
	goto Label97
Label93:
	aload_2 
	iconst_1 
	invokenonvirtual_lib java.lang.String.substring // pc=2
	invokestatic_lib int parseInt( java.lang.String ) // Integer
Label97:
	istore_3 
	aload_0 
	iload_3 
	invokespecial com.whatsapp.client.it.yup.xml.KXmlParser.routine_5030 // pc=2
	return 
Label102:
	aload_0_getfield .field_5_5   // get_name_1:  .field_5_5   // get_name_2:  .field_5_5   // get_Name:    .field_5_5   // getName->1:  null   // getName->2:  null   // getName->N:  null   // ofs = -1 ord = 0 addr = 5
	aload_2 
	invokevirtual java.lang.Object get( java.util.Hashtable, java.lang.Object ) // pc=2
	checkcast_lib String//java.lang.String java.lang.String java.lang.String
	astore_3 
	aload_0 
	aload_3 
	ifnonnull Label112
	iconst_1 
	goto Label113
Label112:
	iconst_0 
Label113:
	putfield .field_29_29   // get_name_1:  .field_29_29   // get_name_2:  .field_29_29   // get_Name:    .field_29_29   // getName->1:  null   // getName->2:  null   // getName->N:  null   // ofs = -1 ord = 0 addr = 29
	aload_0_getfield .field_29_29   // get_name_1:  .field_29_29   // get_name_2:  .field_29_29   // get_Name:    .field_29_29   // getName->1:  null   // getName->2:  null   // getName->N:  null   // ofs = -1 ord = 0 addr = 29
	ifeq Label130
	aload_0_getfield .field_30_30   // get_name_1:  .field_30_30   // get_name_2:  .field_30_30   // get_Name:    .field_30_30   // getName->1:  null   // getName->2:  null   // getName->N:  null   // ofs = -1 ord = 0 addr = 30
	ifne Label143
	aload_0 
	new_lib Object//java.lang.Object java.lang.Object java.lang.Object
	dup 
	ldc literal_646:"unresolved: &"
	invokespecial_lib java.lang.StringBuffer.<init> // pc=2
	aload_2 
	invokevirtual java.lang.StringBuffer append( java.lang.StringBuffer, java.lang.String ) // pc=2
	ldc literal_647:";"
	invokevirtual java.lang.StringBuffer append( java.lang.StringBuffer, java.lang.String ) // pc=2
	invokevirtual_short .toString // idx=2 pc=1
	invokespecial com.whatsapp.client.it.yup.xml.KXmlParser.routine_3542 // pc=2
	return 
Label130:
	iconst_0 
	istore_4 
Label132:
	iload_4 
	aload_3 
	stringlength 
	if_icmpge Label143
	aload_0 
	aload_3 
	iload_4 
	stringaload 
	invokespecial com.whatsapp.client.it.yup.xml.KXmlParser.routine_5030 // pc=2
	iinc 4 1
	goto Label132
Label143:
	return 
	}


private final com.whatsapp.client.it.yup.xml.KXmlParser.routine_5871( com.whatsapp.client.it.yup.xml.KXmlParser, int, boolean ); // address: 0
	{
	enter 
	aload_0 
	iconst_0 
	invokespecial com.whatsapp.client.it.yup.xml.KXmlParser.routine_6164 // pc=2
	istore_3 
	iconst_0 
	istore_4 
Label7:
	iload_3 
	bipush -1
	if_icmpeq Label73
	iload_3 
	iload_1 
	if_icmpeq Label73
	iload_1 
	bipush 32
	if_icmpne Label23
	iload_3 
	bipush 32
	if_icmple Label73
	iload_3 
	bipush 62
	if_icmpne Label23
	return 
Label23:
	iload_3 
	bipush 38
	if_icmpne Label32
	iload_2 
	ifne Label29
	return 
Label29:
	aload_0 
	invokespecial com.whatsapp.client.it.yup.xml.KXmlParser.routine_5583 // pc=1
	goto Label49
Label32:
	iload_3 
	bipush 10
	if_icmpne Label45
	aload_0_getfield .field_16_16   // get_name_1:  .field_16_16   // get_name_2:  .field_16_16   // get_Name:    .field_16_16   // getName->1:  null   // getName->2:  null   // getName->N:  null   // ofs = -1 ord = 0 addr = 16
	bipush 2
	if_icmpne Label45
	aload_0 
	invokespecial com.whatsapp.client.it.yup.xml.KXmlParser.routine_6087 // pc=1
	pop 
	aload_0 
	bipush 32
	invokespecial com.whatsapp.client.it.yup.xml.KXmlParser.routine_5030 // pc=2
	goto Label49
Label45:
	aload_0 
	aload_0 
	invokespecial com.whatsapp.client.it.yup.xml.KXmlParser.routine_6087 // pc=1
	invokespecial com.whatsapp.client.it.yup.xml.KXmlParser.routine_5030 // pc=2
Label49:
	iload_3 
	bipush 62
	if_icmpne Label61
	iload_4 
	bipush 2
	if_icmplt Label61
	iload_1 
	bipush 93
	if_icmpeq Label61
	aload_0 
	ldc literal_648:"Illegal: ]]>"
	invokespecial com.whatsapp.client.it.yup.xml.KXmlParser.routine_3542 // pc=2
Label61:
	iload_3 
	bipush 93
	if_icmpne Label66
	iinc 4 1
	goto Label68
Label66:
	iconst_0 
	istore_4 
Label68:
	aload_0 
	iconst_0 
	invokespecial com.whatsapp.client.it.yup.xml.KXmlParser.routine_6164 // pc=2
	istore_3 
	goto Label7
Label73:
	return 
	}


private final com.whatsapp.client.it.yup.xml.KXmlParser.routine_6017( com.whatsapp.client.it.yup.xml.KXmlParser, char ); // address: 0
	{
	enter 
	aload_0 
	invokespecial com.whatsapp.client.it.yup.xml.KXmlParser.routine_6087 // pc=1
	istore_2 
	iload_2 
	iload_1 
	if_icmpeq Label23
	aload_0 
	new_lib Object//java.lang.Object java.lang.Object java.lang.Object
	dup 
	ldc literal_649:"expected: '"
	invokespecial_lib java.lang.StringBuffer.<init> // pc=2
	iload_1 
	invokevirtual java.lang.StringBuffer append( java.lang.StringBuffer, char ) // pc=2
	ldc literal_650:"' actual: '"
	invokevirtual java.lang.StringBuffer append( java.lang.StringBuffer, java.lang.String ) // pc=2
	iload_2 
	i2c 
	invokevirtual java.lang.StringBuffer append( java.lang.StringBuffer, char ) // pc=2
	ldc literal_595:"'"
	invokevirtual java.lang.StringBuffer append( java.lang.StringBuffer, java.lang.String ) // pc=2
	invokevirtual_short .toString // idx=2 pc=1
	invokespecial com.whatsapp.client.it.yup.xml.KXmlParser.routine_3542 // pc=2
Label23:
	return 
	}


private final int com.whatsapp.client.it.yup.xml.KXmlParser.routine_6087( com.whatsapp.client.it.yup.xml.KXmlParser ); // address: 0
	{
	enter 
	aload_0_getfield .field_27_27   // get_name_1:  .field_27_27   // get_name_2:  .field_27_27   // get_Name:    .field_27_27   // getName->1:  null   // getName->2:  null   // getName->N:  null   // ofs = -1 ord = 0 addr = 27
	ifne Label8
	aload_0 
	iconst_0 
	invokespecial com.whatsapp.client.it.yup.xml.KXmlParser.routine_6164 // pc=2
	istore_1 
	goto Label18
Label8:
	aload_0_getfield .field_26_26   // get_name_1:  .field_26_26   // get_name_2:  .field_26_26   // get_Name:    .field_26_26   // getName->1:  null   // getName->2:  null   // getName->N:  null   // ofs = -1 ord = 0 addr = 26
	iconst_0 
	iaload 
	istore_1 
	aload_0_getfield .field_26_26   // get_name_1:  .field_26_26   // get_name_2:  .field_26_26   // get_Name:    .field_26_26   // getName->1:  null   // getName->2:  null   // getName->N:  null   // ofs = -1 ord = 0 addr = 26
	iconst_0 
	aload_0_getfield .field_26_26   // get_name_1:  .field_26_26   // get_name_2:  .field_26_26   // get_Name:    .field_26_26   // getName->1:  null   // getName->2:  null   // getName->N:  null   // ofs = -1 ord = 0 addr = 26
	iconst_1 
	iaload 
	iastore 
Label18:
	aload_0 
	aload_0_getfield .field_27_27   // get_name_1:  .field_27_27   // get_name_2:  .field_27_27   // get_Name:    .field_27_27   // getName->1:  null   // getName->2:  null   // getName->N:  null   // ofs = -1 ord = 0 addr = 27
	iconst_1 
	isub 
	putfield .field_27_27   // get_name_1:  .field_27_27   // get_name_2:  .field_27_27   // get_Name:    .field_27_27   // getName->1:  null   // getName->2:  null   // getName->N:  null   // ofs = -1 ord = 0 addr = 27
	aload_0 
	aload_0_getfield .field_13_13   // get_name_1:  .field_13_13   // get_name_2:  .field_13_13   // get_Name:    .field_13_13   // getName->1:  null   // getName->2:  null   // getName->N:  null   // ofs = -1 ord = 0 addr = 13
	iconst_1 
	iadd 
	putfield .field_13_13   // get_name_1:  .field_13_13   // get_name_2:  .field_13_13   // get_Name:    .field_13_13   // getName->1:  null   // getName->2:  null   // getName->N:  null   // ofs = -1 ord = 0 addr = 13
	iload_1 
	bipush 10
	if_icmpne Label39
	aload_0 
	aload_0_getfield .field_12_12   // get_name_1:  .field_12_12   // get_name_2:  .field_12_12   // get_Name:    .field_12_12   // getName->1:  null   // getName->2:  null   // getName->N:  null   // ofs = -1 ord = 0 addr = 12
	iconst_1 
	iadd 
	putfield .field_12_12   // get_name_1:  .field_12_12   // get_name_2:  .field_12_12   // get_Name:    .field_12_12   // getName->1:  null   // getName->2:  null   // getName->N:  null   // ofs = -1 ord = 0 addr = 12
	aload_0 
	iconst_1 
	putfield .field_13_13   // get_name_1:  .field_13_13   // get_name_2:  .field_13_13   // get_Name:    .field_13_13   // getName->1:  null   // getName->2:  null   // getName->N:  null   // ofs = -1 ord = 0 addr = 13
Label39:
	iload_1 
	ireturn 
	}


private final int com.whatsapp.client.it.yup.xml.KXmlParser.routine_6164( com.whatsapp.client.it.yup.xml.KXmlParser, int ); // address: 0
	{
	enter 
Label1:
	iload_1 
	aload_0_getfield .field_27_27   // get_name_1:  .field_27_27   // get_name_2:  .field_27_27   // get_Name:    .field_27_27   // getName->1:  null   // getName->2:  null   // getName->N:  null   // ofs = -1 ord = 0 addr = 27
	if_icmplt Label51
	aload_0_getfield .field_10_10   // get_name_1:  .field_10_10   // get_name_2:  .field_10_10   // get_Name:    .field_10_10   // getName->1:  null   // getName->2:  null   // getName->N:  null   // ofs = -1 ord = 0 addr = 10
	invokevirtual int read( java.io.Reader ) // pc=1
	istore_2 
	iload_2 
	bipush 13
	if_icmpne Label23
	aload_0 
	iconst_1 
	putfield .field_28_28   // get_name_1:  .field_28_28   // get_name_2:  .field_28_28   // get_Name:    .field_28_28   // getName->1:  null   // getName->2:  null   // getName->N:  null   // ofs = -1 ord = 0 addr = 28
	aload_0_getfield .field_26_26   // get_name_1:  .field_26_26   // get_name_2:  .field_26_26   // get_Name:    .field_26_26   // getName->1:  null   // getName->2:  null   // getName->N:  null   // ofs = -1 ord = 0 addr = 26
	aload_0 
	aload_0_getfield .field_27_27   // get_name_1:  .field_27_27   // get_name_2:  .field_27_27   // get_Name:    .field_27_27   // getName->1:  null   // getName->2:  null   // getName->N:  null   // ofs = -1 ord = 0 addr = 27
	dup_x1 
	iconst_1 
	iadd 
	putfield .field_27_27   // get_name_1:  .field_27_27   // get_name_2:  .field_27_27   // get_Name:    .field_27_27   // getName->1:  null   // getName->2:  null   // getName->N:  null   // ofs = -1 ord = 0 addr = 27
	bipush 10
	iastore 
	goto Label1
Label23:
	iload_2 
	bipush 10
	if_icmpne Label38
	aload_0_getfield .field_28_28   // get_name_1:  .field_28_28   // get_name_2:  .field_28_28   // get_Name:    .field_28_28   // getName->1:  null   // getName->2:  null   // getName->N:  null   // ofs = -1 ord = 0 addr = 28
	ifne Label47
	aload_0_getfield .field_26_26   // get_name_1:  .field_26_26   // get_name_2:  .field_26_26   // get_Name:    .field_26_26   // getName->1:  null   // getName->2:  null   // getName->N:  null   // ofs = -1 ord = 0 addr = 26
	aload_0 
	aload_0_getfield .field_27_27   // get_name_1:  .field_27_27   // get_name_2:  .field_27_27   // get_Name:    .field_27_27   // getName->1:  null   // getName->2:  null   // getName->N:  null   // ofs = -1 ord = 0 addr = 27
	dup_x1 
	iconst_1 
	iadd 
	putfield .field_27_27   // get_name_1:  .field_27_27   // get_name_2:  .field_27_27   // get_Name:    .field_27_27   // getName->1:  null   // getName->2:  null   // getName->N:  null   // ofs = -1 ord = 0 addr = 27
	bipush 10
	iastore 
	goto Label47
Label38:
	aload_0_getfield .field_26_26   // get_name_1:  .field_26_26   // get_name_2:  .field_26_26   // get_Name:    .field_26_26   // getName->1:  null   // getName->2:  null   // getName->N:  null   // ofs = -1 ord = 0 addr = 26
	aload_0 
	aload_0_getfield .field_27_27   // get_name_1:  .field_27_27   // get_name_2:  .field_27_27   // get_Name:    .field_27_27   // getName->1:  null   // getName->2:  null   // getName->N:  null   // ofs = -1 ord = 0 addr = 27
	dup_x1 
	iconst_1 
	iadd 
	putfield .field_27_27   // get_name_1:  .field_27_27   // get_name_2:  .field_27_27   // get_Name:    .field_27_27   // getName->1:  null   // getName->2:  null   // getName->N:  null   // ofs = -1 ord = 0 addr = 27
	iload_2 
	iastore 
Label47:
	aload_0 
	iconst_0 
	putfield .field_28_28   // get_name_1:  .field_28_28   // get_name_2:  .field_28_28   // get_Name:    .field_28_28   // getName->1:  null   // getName->2:  null   // getName->N:  null   // ofs = -1 ord = 0 addr = 28
	goto Label1
Label51:
	aload_0_getfield .field_26_26   // get_name_1:  .field_26_26   // get_name_2:  .field_26_26   // get_Name:    .field_26_26   // getName->1:  null   // getName->2:  null   // getName->N:  null   // ofs = -1 ord = 0 addr = 26
	iload_1 
	iaload 
	ireturn 
	}


private final java.lang.String com.whatsapp.client.it.yup.xml.KXmlParser.routine_6262( com.whatsapp.client.it.yup.xml.KXmlParser ); // address: 0
	{
	enter 
	aload_0_getfield .field_15_15   // get_name_1:  .field_15_15   // get_name_2:  .field_15_15   // get_Name:    .field_15_15   // getName->1:  null   // getName->2:  null   // getName->N:  null   // ofs = -1 ord = 0 addr = 15
	istore_1 
	aload_0 
	iconst_0 
	invokespecial com.whatsapp.client.it.yup.xml.KXmlParser.routine_6164 // pc=2
	istore_2 
	iload_2 
	bipush 97
	if_icmplt Label13
	iload_2 
	bipush 122
	if_icmple Label33
Label13:
	iload_2 
	bipush 65
	if_icmplt Label19
	iload_2 
	bipush 90
	if_icmple Label33
Label19:
	iload_2 
	bipush 95
	if_icmpeq Label33
	iload_2 
	bipush 58
	if_icmpeq Label33
	iload_2 
	sipush 192
	if_icmpge Label33
	aload_0_getfield .field_4_4   // get_name_1:  .field_4_4   // get_name_2:  .field_4_4   // get_Name:    .field_4_4   // getName->1:  null   // getName->2:  null   // getName->N:  null   // ofs = -1 ord = 0 addr = 4
	ifne Label33
	aload_0 
	ldc literal_651:"name expected"
	invokespecial com.whatsapp.client.it.yup.xml.KXmlParser.routine_3542 // pc=2
Label33:
	aload_0 
	aload_0 
	invokespecial com.whatsapp.client.it.yup.xml.KXmlParser.routine_6087 // pc=1
	invokespecial com.whatsapp.client.it.yup.xml.KXmlParser.routine_5030 // pc=2
	aload_0 
	iconst_0 
	invokespecial com.whatsapp.client.it.yup.xml.KXmlParser.routine_6164 // pc=2
	istore_2 
	iload_2 
	bipush 97
	if_icmplt Label47
	iload_2 
	bipush 122
	if_icmple Label33
Label47:
	iload_2 
	bipush 65
	if_icmplt Label53
	iload_2 
	bipush 90
	if_icmple Label33
Label53:
	iload_2 
	bipush 48
	if_icmplt Label59
	iload_2 
	bipush 57
	if_icmple Label33
Label59:
	iload_2 
	bipush 95
	if_icmpeq Label33
	iload_2 
	bipush 45
	if_icmpeq Label33
	iload_2 
	bipush 58
	if_icmpeq Label33
	iload_2 
	bipush 46
	if_icmpeq Label33
	iload_2 
	sipush 183
	if_icmpge Label33
	aload_0 
	iload_1 
	invokespecial com.whatsapp.client.it.yup.xml.KXmlParser.routine_4998 // pc=2
	astore_3 
	aload_0 
	iload_1 
	putfield .field_15_15   // get_name_1:  .field_15_15   // get_name_2:  .field_15_15   // get_Name:    .field_15_15   // getName->1:  null   // getName->2:  null   // getName->N:  null   // ofs = -1 ord = 0 addr = 15
	aload_3 
	areturn 
	}


private final com.whatsapp.client.it.yup.xml.KXmlParser.routine_6420( com.whatsapp.client.it.yup.xml.KXmlParser ); // address: 0
	{
	enter_narrow 
Label1:
	aload_0 
	iconst_0 
	invokespecial com.whatsapp.client.it.yup.xml.KXmlParser.routine_6164 // pc=2
	istore_1 
	iload_1 
	bipush 32
	if_icmpgt Label16
	iload_1 
	bipush -1
	if_icmpne Label12
	return 
Label12:
	aload_0 
	invokespecial com.whatsapp.client.it.yup.xml.KXmlParser.routine_6087 // pc=1
	pop 
	goto Label1
Label16:
	return 
	}

	// @@@@@@@@@@@@@ Virtual routines 

public final int getNamespaceCount( com.whatsapp.client.it.yup.xml.KXmlParser, int ); // address: 0
	{
	enter_narrow 
	iload_1 
	aload_0_getfield .field_6_6   // get_name_1:  .field_6_6   // get_name_2:  .field_6_6   // get_Name:    .field_6_6   // getName->1:  null   // getName->2:  null   // getName->N:  null   // ofs = -1 ord = 0 addr = 6
	if_icmple Label8
	new_lib RuntimeException//java.lang.RuntimeException java.lang.RuntimeException java.lang.RuntimeException
	dup 
	invokespecial_lib java.lang.IndexOutOfBoundsException.<init> // pc=1
	athrow 
Label8:
	aload_0_getfield .field_9_9   // get_name_1:  .field_9_9   // get_name_2:  .field_9_9   // get_Name:    .field_9_9   // getName->1:  null   // getName->2:  null   // getName->N:  null   // ofs = -1 ord = 0 addr = 9
	iload_1 
	iaload 
	ireturn 
	}


public final java.lang.String getNamespace( com.whatsapp.client.it.yup.xml.KXmlParser, java.lang.String ); // address: 0
	{
	enter_narrow 
	ldc literal_585:"xml"
	aload_1 
	invokevirtual_short .equals // idx=1 pc=2
	ifeq Label7
	ldc literal_586:"http://www.w3.org/XML/1998/namespace"
	areturn 
Label7:
	ldc literal_587:"xmlns"
	aload_1 
	invokevirtual_short .equals // idx=1 pc=2
	ifeq Label13
	ldc literal_588:"http://www.w3.org/2000/xmlns/"
	areturn 
Label13:
	aload_0 
	aload_0_getfield .field_6_6   // get_name_1:  .field_6_6   // get_name_2:  .field_6_6   // get_Name:    .field_6_6   // getName->1:  null   // getName->2:  null   // getName->N:  null   // ofs = -1 ord = 0 addr = 6
	invokevirtual_short .virtual_3 // idx=3 pc=2
	iconst_1 
	ishl 
	bipush 2
	isub 
	istore_2 
Label21:
	iload_2 
	iflt Label49
	aload_1 
	ifnonnull Label35
	aload_0_getfield .field_8_8   // get_name_1:  .field_8_8   // get_name_2:  .field_8_8   // get_Name:    .field_8_8   // getName->1:  null   // getName->2:  null   // getName->N:  null   // ofs = -1 ord = 0 addr = 8
	iload_2 
	aaload 
	ifnonnull Label47
	aload_0_getfield .field_8_8   // get_name_1:  .field_8_8   // get_name_2:  .field_8_8   // get_Name:    .field_8_8   // getName->1:  null   // getName->2:  null   // getName->N:  null   // ofs = -1 ord = 0 addr = 8
	iload_2 
	iconst_1 
	iadd 
	aaload 
	areturn 
Label35:
	aload_1 
	aload_0_getfield .field_8_8   // get_name_1:  .field_8_8   // get_name_2:  .field_8_8   // get_Name:    .field_8_8   // getName->1:  null   // getName->2:  null   // getName->N:  null   // ofs = -1 ord = 0 addr = 8
	iload_2 
	aaload 
	invokevirtual_short .equals // idx=1 pc=2
	ifeq Label47
	aload_0_getfield .field_8_8   // get_name_1:  .field_8_8   // get_name_2:  .field_8_8   // get_Name:    .field_8_8   // getName->1:  null   // getName->2:  null   // getName->N:  null   // ofs = -1 ord = 0 addr = 8
	iload_2 
	iconst_1 
	iadd 
	aaload 
	areturn 
Label47:
	iinc 2 -2
	goto Label21
Label49:
	aconst_null 
	areturn 
	}


public final java.lang.String getPositionDescription( com.whatsapp.client.it.yup.xml.KXmlParser ); // address: 0
	{
	enter 
	new_lib Object//java.lang.Object java.lang.Object java.lang.Object
	dup 
	aload_0_getfield .field_16_16   // get_name_1:  .field_16_16   // get_name_2:  .field_16_16   // get_Name:    .field_16_16   // getName->1:  null   // getName->2:  null   // getName->N:  null   // ofs = -1 ord = 0 addr = 16
	getstatic_lib module:WhatsApp-37.class#20.static_55 // class#20
	arraylength 
	if_icmpge Label11
	getstatic_lib module:WhatsApp-37.class#20.static_55 // class#20
	aload_0_getfield .field_16_16   // get_name_1:  .field_16_16   // get_name_2:  .field_16_16   // get_Name:    .field_16_16   // getName->1:  null   // getName->2:  null   // getName->N:  null   // ofs = -1 ord = 0 addr = 16
	aaload 
	goto Label12
Label11:
	ldc literal_589:"unknown"
Label12:
	invokespecial_lib java.lang.StringBuffer.<init> // pc=2
	astore_1 
	aload_1 
	bipush 32
	invokevirtual java.lang.StringBuffer append( java.lang.StringBuffer, char ) // pc=2
	pop 
	aload_0_getfield .field_16_16   // get_name_1:  .field_16_16   // get_name_2:  .field_16_16   // get_Name:    .field_16_16   // getName->1:  null   // getName->2:  null   // getName->N:  null   // ofs = -1 ord = 0 addr = 16
	bipush 2
	if_icmpeq Label25
	aload_0_getfield .field_16_16   // get_name_1:  .field_16_16   // get_name_2:  .field_16_16   // get_Name:    .field_16_16   // getName->1:  null   // getName->2:  null   // getName->N:  null   // ofs = -1 ord = 0 addr = 16
	bipush 3
	if_icmpeq Label25
	goto_w Label136
Label25:
	aload_0_getfield .field_21_21   // get_name_1:  .field_21_21   // get_name_2:  .field_21_21   // get_Name:    .field_21_21   // getName->1:  null   // getName->2:  null   // getName->N:  null   // ofs = -1 ord = 0 addr = 21
	ifeq Label31
	aload_1 
	ldc literal_590:"(empty) "
	invokevirtual java.lang.StringBuffer append( java.lang.StringBuffer, java.lang.String ) // pc=2
	pop 
Label31:
	aload_1 
	bipush 60
	invokevirtual java.lang.StringBuffer append( java.lang.StringBuffer, char ) // pc=2
	pop 
	aload_0_getfield .field_16_16   // get_name_1:  .field_16_16   // get_name_2:  .field_16_16   // get_Name:    .field_16_16   // getName->1:  null   // getName->2:  null   // getName->N:  null   // ofs = -1 ord = 0 addr = 16
	bipush 3
	if_icmpne Label42
	aload_1 
	bipush 47
	invokevirtual java.lang.StringBuffer append( java.lang.StringBuffer, char ) // pc=2
	pop 
Label42:
	aload_0_getfield .field_19_19   // get_name_1:  .field_19_19   // get_name_2:  .field_19_19   // get_Name:    .field_19_19   // getName->1:  null   // getName->2:  null   // getName->N:  null   // ofs = -1 ord = 0 addr = 19
	ifnull Label60
	aload_1 
	new_lib Object//java.lang.Object java.lang.Object java.lang.Object
	dup 
	ldc literal_591:"{"
	invokespecial_lib java.lang.StringBuffer.<init> // pc=2
	aload_0_getfield .field_18_18   // get_name_1:  .field_18_18   // get_name_2:  .field_18_18   // get_Name:    .field_18_18   // getName->1:  null   // getName->2:  null   // getName->N:  null   // ofs = -1 ord = 0 addr = 18
	invokevirtual java.lang.StringBuffer append( java.lang.StringBuffer, java.lang.String ) // pc=2
	ldc literal_592:"}"
	invokevirtual java.lang.StringBuffer append( java.lang.StringBuffer, java.lang.String ) // pc=2
	aload_0_getfield .field_19_19   // get_name_1:  .field_19_19   // get_name_2:  .field_19_19   // get_Name:    .field_19_19   // getName->1:  null   // getName->2:  null   // getName->N:  null   // ofs = -1 ord = 0 addr = 19
	invokevirtual java.lang.StringBuffer append( java.lang.StringBuffer, java.lang.String ) // pc=2
	ldc literal_593:":"
	invokevirtual java.lang.StringBuffer append( java.lang.StringBuffer, java.lang.String ) // pc=2
	invokevirtual_short .toString // idx=2 pc=1
	invokevirtual java.lang.StringBuffer append( java.lang.StringBuffer, java.lang.String ) // pc=2
	pop 
Label60:
	aload_1 
	aload_0_getfield .field_20_20   // get_name_1:  .field_20_20   // get_name_2:  .field_20_20   // get_Name:    .field_20_20   // getName->1:  null   // getName->2:  null   // getName->N:  null   // ofs = -1 ord = 0 addr = 20
	invokevirtual java.lang.StringBuffer append( java.lang.StringBuffer, java.lang.String ) // pc=2
	pop 
	aload_0_getfield .field_22_22   // get_name_1:  .field_22_22   // get_name_2:  .field_22_22   // get_Name:    .field_22_22   // getName->1:  null   // getName->2:  null   // getName->N:  null   // ofs = -1 ord = 0 addr = 22
	bipush 2
	ishl 
	istore_2 
	iconst_0 
	istore_3 
Label70:
	iload_3 
	iload_2 
	if_icmplt Label74
	goto_w Label131
Label74:
	aload_1 
	bipush 32
	invokevirtual java.lang.StringBuffer append( java.lang.StringBuffer, char ) // pc=2
	pop 
	aload_0_getfield .field_23_23   // get_name_1:  .field_23_23   // get_name_2:  .field_23_23   // get_Name:    .field_23_23   // getName->1:  null   // getName->2:  null   // getName->N:  null   // ofs = -1 ord = 0 addr = 23
	iload_3 
	iconst_1 
	iadd 
	aaload 
	ifnull Label106
	aload_1 
	new_lib Object//java.lang.Object java.lang.Object java.lang.Object
	dup 
	ldc literal_591:"{"
	invokespecial_lib java.lang.StringBuffer.<init> // pc=2
	aload_0_getfield .field_23_23   // get_name_1:  .field_23_23   // get_name_2:  .field_23_23   // get_Name:    .field_23_23   // getName->1:  null   // getName->2:  null   // getName->N:  null   // ofs = -1 ord = 0 addr = 23
	iload_3 
	aaload 
	invokevirtual java.lang.StringBuffer append( java.lang.StringBuffer, java.lang.String ) // pc=2
	ldc literal_592:"}"
	invokevirtual java.lang.StringBuffer append( java.lang.StringBuffer, java.lang.String ) // pc=2
	aload_0_getfield .field_23_23   // get_name_1:  .field_23_23   // get_name_2:  .field_23_23   // get_Name:    .field_23_23   // getName->1:  null   // getName->2:  null   // getName->N:  null   // ofs = -1 ord = 0 addr = 23
	iload_3 
	iconst_1 
	iadd 
	aaload 
	invokevirtual java.lang.StringBuffer append( java.lang.StringBuffer, java.lang.String ) // pc=2
	ldc literal_593:":"
	invokevirtual java.lang.StringBuffer append( java.lang.StringBuffer, java.lang.String ) // pc=2
	invokevirtual_short .toString // idx=2 pc=1
	invokevirtual java.lang.StringBuffer append( java.lang.StringBuffer, java.lang.String ) // pc=2
	pop 
Label106:
	aload_1 
	new_lib Object//java.lang.Object java.lang.Object java.lang.Object
	dup 
	invokespecial_lib java.lang.StringBuffer.<init> // pc=1
	aload_0_getfield .field_23_23   // get_name_1:  .field_23_23   // get_name_2:  .field_23_23   // get_Name:    .field_23_23   // getName->1:  null   // getName->2:  null   // getName->N:  null   // ofs = -1 ord = 0 addr = 23
	iload_3 
	bipush 2
	iadd 
	aaload 
	invokevirtual java.lang.StringBuffer append( java.lang.StringBuffer, java.lang.String ) // pc=2
	ldc literal_594:"='"
	invokevirtual java.lang.StringBuffer append( java.lang.StringBuffer, java.lang.String ) // pc=2
	aload_0_getfield .field_23_23   // get_name_1:  .field_23_23   // get_name_2:  .field_23_23   // get_Name:    .field_23_23   // getName->1:  null   // getName->2:  null   // getName->N:  null   // ofs = -1 ord = 0 addr = 23
	iload_3 
	bipush 3
	iadd 
	aaload 
	invokevirtual java.lang.StringBuffer append( java.lang.StringBuffer, java.lang.String ) // pc=2
	ldc literal_595:"'"
	invokevirtual java.lang.StringBuffer append( java.lang.StringBuffer, java.lang.String ) // pc=2
	invokevirtual_short .toString // idx=2 pc=1
	invokevirtual java.lang.StringBuffer append( java.lang.StringBuffer, java.lang.String ) // pc=2
	pop 
	iinc 3 4
	goto_w Label70
Label131:
	aload_1 
	bipush 62
	invokevirtual java.lang.StringBuffer append( java.lang.StringBuffer, char ) // pc=2
	pop 
	goto Label179
Label136:
	aload_0_getfield .field_16_16   // get_name_1:  .field_16_16   // get_name_2:  .field_16_16   // get_Name:    .field_16_16   // getName->1:  null   // getName->2:  null   // getName->N:  null   // ofs = -1 ord = 0 addr = 16
	bipush 7
	if_icmpne Label140
	goto Label179
Label140:
	aload_0_getfield .field_16_16   // get_name_1:  .field_16_16   // get_name_2:  .field_16_16   // get_Name:    .field_16_16   // getName->1:  null   // getName->2:  null   // getName->N:  null   // ofs = -1 ord = 0 addr = 16
	bipush 4
	if_icmpeq Label149
	aload_1 
	aload_0 
	invokevirtual_short .virtual_9 // idx=9 pc=1
	invokevirtual java.lang.StringBuffer append( java.lang.StringBuffer, java.lang.String ) // pc=2
	pop 
	goto Label179
Label149:
	aload_0_getfield .field_17_17   // get_name_1:  .field_17_17   // get_name_2:  .field_17_17   // get_Name:    .field_17_17   // getName->1:  null   // getName->2:  null   // getName->N:  null   // ofs = -1 ord = 0 addr = 17
	ifeq Label156
	aload_1 
	ldc literal_596:"(whitespace)"
	invokevirtual java.lang.StringBuffer append( java.lang.StringBuffer, java.lang.String ) // pc=2
	pop 
	goto Label179
Label156:
	aload_0 
	invokevirtual_short .virtual_9 // idx=9 pc=1
	astore_2 
	aload_2 
	stringlength 
	bipush 16
	if_icmple Label175
	new_lib Object//java.lang.Object java.lang.Object java.lang.Object
	dup 
	invokespecial_lib java.lang.StringBuffer.<init> // pc=1
	aload_2 
	iconst_0 
	bipush 16
	invokenonvirtual_lib java.lang.String.substring // pc=3
	invokevirtual java.lang.StringBuffer append( java.lang.StringBuffer, java.lang.String ) // pc=2
	ldc literal_597:"..."
	invokevirtual java.lang.StringBuffer append( java.lang.StringBuffer, java.lang.String ) // pc=2
	invokevirtual_short .toString // idx=2 pc=1
	astore_2 
Label175:
	aload_1 
	aload_2 
	invokevirtual java.lang.StringBuffer append( java.lang.StringBuffer, java.lang.String ) // pc=2
	pop 
Label179:
	aload_1 
	new_lib Object//java.lang.Object java.lang.Object java.lang.Object
	dup 
	ldc literal_598:"@"
	invokespecial_lib java.lang.StringBuffer.<init> // pc=2
	aload_0_getfield .field_12_12   // get_name_1:  .field_12_12   // get_name_2:  .field_12_12   // get_Name:    .field_12_12   // getName->1:  null   // getName->2:  null   // getName->N:  null   // ofs = -1 ord = 0 addr = 12
	invokevirtual java.lang.StringBuffer append( java.lang.StringBuffer, int ) // pc=2
	ldc literal_593:":"
	invokevirtual java.lang.StringBuffer append( java.lang.StringBuffer, java.lang.String ) // pc=2
	aload_0_getfield .field_13_13   // get_name_1:  .field_13_13   // get_name_2:  .field_13_13   // get_Name:    .field_13_13   // getName->1:  null   // getName->2:  null   // getName->N:  null   // ofs = -1 ord = 0 addr = 13
	invokevirtual java.lang.StringBuffer append( java.lang.StringBuffer, int ) // pc=2
	invokevirtual_short .toString // idx=2 pc=1
	invokevirtual java.lang.StringBuffer append( java.lang.StringBuffer, java.lang.String ) // pc=2
	pop 
	aload_0_getfield .field_0_   // get_name_1:  .field_0_   // get_name_2:  .field_0_   // get_Name:    .field_0_   // getName->1:  null   // getName->2:  null   // getName->N:  null   // ofs = -1 ord = 0 addr = 0
	ifnull Label204
	aload_1 
	ldc literal_599:" in "
	invokevirtual java.lang.StringBuffer append( java.lang.StringBuffer, java.lang.String ) // pc=2
	pop 
	aload_1 
	aload_0_getfield .field_0_   // get_name_1:  .field_0_   // get_name_2:  .field_0_   // get_Name:    .field_0_   // getName->1:  null   // getName->2:  null   // getName->N:  null   // ofs = -1 ord = 0 addr = 0
	invokevirtual java.lang.StringBuffer append( java.lang.StringBuffer, java.lang.Object ) // pc=2
	pop 
	goto Label215
Label204:
	aload_0_getfield .field_10_10   // get_name_1:  .field_10_10   // get_name_2:  .field_10_10   // get_Name:    .field_10_10   // getName->1:  null   // getName->2:  null   // getName->N:  null   // ofs = -1 ord = 0 addr = 10
	ifnull Label215
	aload_1 
	ldc literal_599:" in "
	invokevirtual java.lang.StringBuffer append( java.lang.StringBuffer, java.lang.String ) // pc=2
	pop 
	aload_1 
	aload_0_getfield .field_10_10   // get_name_1:  .field_10_10   // get_name_2:  .field_10_10   // get_Name:    .field_10_10   // getName->1:  null   // getName->2:  null   // getName->N:  null   // ofs = -1 ord = 0 addr = 10
	invokevirtual_short .toString // idx=2 pc=1
	invokevirtual java.lang.StringBuffer append( java.lang.StringBuffer, java.lang.String ) // pc=2
	pop 
Label215:
	aload_1 
	invokevirtual_short .toString // idx=2 pc=1
	areturn 
	}


public final int getLineNumber( com.whatsapp.client.it.yup.xml.KXmlParser ); // address: 0
	{
	ireturn_field .field_12_12   // get_name_1:  .field_12_12   // get_name_2:  .field_12_12   // get_Name:    .field_12_12   // getName->1:  null   // getName->2:  null   // getName->N:  null   // ofs = -1 ord = 0 addr = 12
	}


public final int getColumnNumber( com.whatsapp.client.it.yup.xml.KXmlParser ); // address: 0
	{
	ireturn_field .field_13_13   // get_name_1:  .field_13_13   // get_name_2:  .field_13_13   // get_Name:    .field_13_13   // getName->1:  null   // getName->2:  null   // getName->N:  null   // ofs = -1 ord = 0 addr = 13
	}


public final boolean isWhitespace( com.whatsapp.client.it.yup.xml.KXmlParser ); // address: 0
	{
	enter_narrow 
	aload_0_getfield .field_16_16   // get_name_1:  .field_16_16   // get_name_2:  .field_16_16   // get_Name:    .field_16_16   // getName->1:  null   // getName->2:  null   // getName->N:  null   // ofs = -1 ord = 0 addr = 16
	bipush 4
	if_icmpeq Label13
	aload_0_getfield .field_16_16   // get_name_1:  .field_16_16   // get_name_2:  .field_16_16   // get_Name:    .field_16_16   // getName->1:  null   // getName->2:  null   // getName->N:  null   // ofs = -1 ord = 0 addr = 16
	bipush 7
	if_icmpeq Label13
	aload_0_getfield .field_16_16   // get_name_1:  .field_16_16   // get_name_2:  .field_16_16   // get_Name:    .field_16_16   // getName->1:  null   // getName->2:  null   // getName->N:  null   // ofs = -1 ord = 0 addr = 16
	bipush 5
	if_icmpeq Label13
	aload_0 
	getstatic com.whatsapp.client.it.yup.xml.KXmlParser.field_54256 // KXmlParser
	invokespecial com.whatsapp.client.it.yup.xml.KXmlParser.routine_3595 // pc=2
Label13:
	aload_0_getfield .field_17_17   // get_name_1:  .field_17_17   // get_name_2:  .field_17_17   // get_Name:    .field_17_17   // getName->1:  null   // getName->2:  null   // getName->N:  null   // ofs = -1 ord = 0 addr = 17
	ireturn 
	}


public final java.lang.String getText( com.whatsapp.client.it.yup.xml.KXmlParser ); // address: 0
	{
	enter_narrow 
	aload_0_getfield .field_16_16   // get_name_1:  .field_16_16   // get_name_2:  .field_16_16   // get_Name:    .field_16_16   // getName->1:  null   // getName->2:  null   // getName->N:  null   // ofs = -1 ord = 0 addr = 16
	bipush 4
	if_icmplt Label9
	aload_0_getfield .field_16_16   // get_name_1:  .field_16_16   // get_name_2:  .field_16_16   // get_Name:    .field_16_16   // getName->1:  null   // getName->2:  null   // getName->N:  null   // ofs = -1 ord = 0 addr = 16
	bipush 6
	if_icmpne Label11
	aload_0_getfield .field_29_29   // get_name_1:  .field_29_29   // get_name_2:  .field_29_29   // get_Name:    .field_29_29   // getName->1:  null   // getName->2:  null   // getName->N:  null   // ofs = -1 ord = 0 addr = 29
	ifeq Label11
Label9:
	aconst_null 
	areturn 
Label11:
	aload_0 
	iconst_0 
	invokespecial com.whatsapp.client.it.yup.xml.KXmlParser.routine_4998 // pc=2
	areturn 
	}


public final java.lang.String getNamespace( com.whatsapp.client.it.yup.xml.KXmlParser ); // address: 0
	{
	areturn_field .field_18_18   // get_name_1:  .field_18_18   // get_name_2:  .field_18_18   // get_Name:    .field_18_18   // getName->1:  null   // getName->2:  null   // getName->N:  null   // ofs = -1 ord = 0 addr = 18
	}


public final java.lang.String getName( com.whatsapp.client.it.yup.xml.KXmlParser ); // address: 0
	{
	areturn_field .field_20_20   // get_name_1:  .field_20_20   // get_name_2:  .field_20_20   // get_Name:    .field_20_20   // getName->1:  null   // getName->2:  null   // getName->N:  null   // ofs = -1 ord = 0 addr = 20
	}


public final int getAttributeCount( com.whatsapp.client.it.yup.xml.KXmlParser ); // address: 0
	{
	ireturn_field .field_22_22   // get_name_1:  .field_22_22   // get_name_2:  .field_22_22   // get_Name:    .field_22_22   // getName->1:  null   // getName->2:  null   // getName->N:  null   // ofs = -1 ord = 0 addr = 22
	}


public final java.lang.String getAttributeName( com.whatsapp.client.it.yup.xml.KXmlParser, int ); // address: 0
	{
	enter_narrow 
	iload_1 
	aload_0_getfield .field_22_22   // get_name_1:  .field_22_22   // get_name_2:  .field_22_22   // get_Name:    .field_22_22   // getName->1:  null   // getName->2:  null   // getName->N:  null   // ofs = -1 ord = 0 addr = 22
	if_icmplt Label8
	new_lib RuntimeException//java.lang.RuntimeException java.lang.RuntimeException java.lang.RuntimeException
	dup 
	invokespecial_lib java.lang.IndexOutOfBoundsException.<init> // pc=1
	athrow 
Label8:
	aload_0_getfield .field_23_23   // get_name_1:  .field_23_23   // get_name_2:  .field_23_23   // get_Name:    .field_23_23   // getName->1:  null   // getName->2:  null   // getName->N:  null   // ofs = -1 ord = 0 addr = 23
	iload_1 
	bipush 2
	ishl 
	bipush 2
	iadd 
	aaload 
	areturn 
	}


public final java.lang.String getAttributeValue( com.whatsapp.client.it.yup.xml.KXmlParser, int ); // address: 0
	{
	enter_narrow 
	iload_1 
	aload_0_getfield .field_22_22   // get_name_1:  .field_22_22   // get_name_2:  .field_22_22   // get_Name:    .field_22_22   // getName->1:  null   // getName->2:  null   // getName->N:  null   // ofs = -1 ord = 0 addr = 22
	if_icmplt Label8
	new_lib RuntimeException//java.lang.RuntimeException java.lang.RuntimeException java.lang.RuntimeException
	dup 
	invokespecial_lib java.lang.IndexOutOfBoundsException.<init> // pc=1
	athrow 
Label8:
	aload_0_getfield .field_23_23   // get_name_1:  .field_23_23   // get_name_2:  .field_23_23   // get_Name:    .field_23_23   // getName->1:  null   // getName->2:  null   // getName->N:  null   // ofs = -1 ord = 0 addr = 23
	iload_1 
	bipush 2
	ishl 
	bipush 3
	iadd 
	aaload 
	areturn 
	}


public final java.lang.String getAttributeValue( com.whatsapp.client.it.yup.xml.KXmlParser, java.lang.String, java.lang.String ); // address: 0
	{
	enter 
	aload_0_getfield .field_22_22   // get_name_1:  .field_22_22   // get_name_2:  .field_22_22   // get_Name:    .field_22_22   // getName->1:  null   // getName->2:  null   // getName->N:  null   // ofs = -1 ord = 0 addr = 22
	bipush 2
	ishl 
	bipush 4
	isub 
	istore_3 
Label7:
	iload_3 
	iflt Label33
	aload_0_getfield .field_23_23   // get_name_1:  .field_23_23   // get_name_2:  .field_23_23   // get_Name:    .field_23_23   // getName->1:  null   // getName->2:  null   // getName->N:  null   // ofs = -1 ord = 0 addr = 23
	iload_3 
	bipush 2
	iadd 
	aaload 
	aload_2 
	invokevirtual_short .equals // idx=1 pc=2
	ifeq Label31
	aload_1 
	ifnull Label25
	aload_0_getfield .field_23_23   // get_name_1:  .field_23_23   // get_name_2:  .field_23_23   // get_Name:    .field_23_23   // getName->1:  null   // getName->2:  null   // getName->N:  null   // ofs = -1 ord = 0 addr = 23
	iload_3 
	aaload 
	aload_1 
	invokevirtual_short .equals // idx=1 pc=2
	ifeq Label31
Label25:
	aload_0_getfield .field_23_23   // get_name_1:  .field_23_23   // get_name_2:  .field_23_23   // get_Name:    .field_23_23   // getName->1:  null   // getName->2:  null   // getName->N:  null   // ofs = -1 ord = 0 addr = 23
	iload_3 
	bipush 3
	iadd 
	aaload 
	areturn 
Label31:
	iinc 3 -4
	goto Label7
Label33:
	aconst_null 
	areturn 
	}


public final int getEventType( com.whatsapp.client.it.yup.xml.KXmlParser ); // address: 0
	{
	ireturn_field .field_16_16   // get_name_1:  .field_16_16   // get_name_2:  .field_16_16   // get_Name:    .field_16_16   // getName->1:  null   // getName->2:  null   // getName->N:  null   // ofs = -1 ord = 0 addr = 16
	}


public final int next( com.whatsapp.client.it.yup.xml.KXmlParser ); // address: 0
	{
	enter_narrow 
	aload_0 
	iconst_0 
	putfield .field_15_15   // get_name_1:  .field_15_15   // get_name_2:  .field_15_15   // get_Name:    .field_15_15   // getName->1:  null   // getName->2:  null   // getName->N:  null   // ofs = -1 ord = 0 addr = 15
	aload_0 
	iconst_1 
	putfield .field_17_17   // get_name_1:  .field_17_17   // get_name_2:  .field_17_17   // get_Name:    .field_17_17   // getName->1:  null   // getName->2:  null   // getName->N:  null   // ofs = -1 ord = 0 addr = 17
	sipush 9999
	istore_1 
	aload_0 
	iconst_0 
	putfield .field_30_30   // get_name_1:  .field_30_30   // get_name_2:  .field_30_30   // get_Name:    .field_30_30   // getName->1:  null   // getName->2:  null   // getName->N:  null   // ofs = -1 ord = 0 addr = 30
Label12:
	aload_0 
	invokespecial com.whatsapp.client.it.yup.xml.KXmlParser.routine_3666 // pc=1
	aload_0_getfield .field_16_16   // get_name_1:  .field_16_16   // get_name_2:  .field_16_16   // get_Name:    .field_16_16   // getName->1:  null   // getName->2:  null   // getName->N:  null   // ofs = -1 ord = 0 addr = 16
	iload_1 
	if_icmpge Label19
	aload_0_getfield .field_16_16   // get_name_1:  .field_16_16   // get_name_2:  .field_16_16   // get_Name:    .field_16_16   // getName->1:  null   // getName->2:  null   // getName->N:  null   // ofs = -1 ord = 0 addr = 16
	istore_1 
Label19:
	iload_1 
	bipush 6
	if_icmpgt Label12
	iload_1 
	bipush 4
	if_icmplt Label29
	aload_0 
	invokespecial com.whatsapp.client.it.yup.xml.KXmlParser.routine_4919 // pc=1
	bipush 4
	if_icmpge Label12
Label29:
	aload_0 
	iload_1 
	putfield .field_16_16   // get_name_1:  .field_16_16   // get_name_2:  .field_16_16   // get_Name:    .field_16_16   // getName->1:  null   // getName->2:  null   // getName->N:  null   // ofs = -1 ord = 0 addr = 16
	aload_0_getfield .field_16_16   // get_name_1:  .field_16_16   // get_name_2:  .field_16_16   // get_Name:    .field_16_16   // getName->1:  null   // getName->2:  null   // getName->N:  null   // ofs = -1 ord = 0 addr = 16
	bipush 4
	if_icmple Label38
	aload_0 
	bipush 4
	putfield .field_16_16   // get_name_1:  .field_16_16   // get_name_2:  .field_16_16   // get_Name:    .field_16_16   // getName->1:  null   // getName->2:  null   // getName->N:  null   // ofs = -1 ord = 0 addr = 16
Label38:
	aload_0_getfield .field_16_16   // get_name_1:  .field_16_16   // get_name_2:  .field_16_16   // get_Name:    .field_16_16   // getName->1:  null   // getName->2:  null   // getName->N:  null   // ofs = -1 ord = 0 addr = 16
	ireturn 
	}


public final int nextToken( com.whatsapp.client.it.yup.xml.KXmlParser ); // address: 0
	{
	enter_narrow 
	aload_0 
	iconst_1 
	putfield .field_17_17   // get_name_1:  .field_17_17   // get_name_2:  .field_17_17   // get_Name:    .field_17_17   // getName->1:  null   // getName->2:  null   // getName->N:  null   // ofs = -1 ord = 0 addr = 17
	aload_0 
	iconst_0 
	putfield .field_15_15   // get_name_1:  .field_15_15   // get_name_2:  .field_15_15   // get_Name:    .field_15_15   // getName->1:  null   // getName->2:  null   // getName->N:  null   // ofs = -1 ord = 0 addr = 15
	aload_0 
	iconst_1 
	putfield .field_30_30   // get_name_1:  .field_30_30   // get_name_2:  .field_30_30   // get_Name:    .field_30_30   // getName->1:  null   // getName->2:  null   // getName->N:  null   // ofs = -1 ord = 0 addr = 30
	aload_0 
	invokespecial com.whatsapp.client.it.yup.xml.KXmlParser.routine_3666 // pc=1
	aload_0_getfield .field_16_16   // get_name_1:  .field_16_16   // get_name_2:  .field_16_16   // get_Name:    .field_16_16   // getName->1:  null   // getName->2:  null   // getName->N:  null   // ofs = -1 ord = 0 addr = 16
	ireturn 
	}


public final int nextTag( com.whatsapp.client.it.yup.xml.KXmlParser ); // address: 0
	{
	enter_narrow 
	aload_0 
	invokevirtual_short .virtual_17 // idx=17 pc=1
	pop 
	aload_0_getfield .field_16_16   // get_name_1:  .field_16_16   // get_name_2:  .field_16_16   // get_Name:    .field_16_16   // getName->1:  null   // getName->2:  null   // getName->N:  null   // ofs = -1 ord = 0 addr = 16
	bipush 4
	if_icmpne Label12
	aload_0_getfield .field_17_17   // get_name_1:  .field_17_17   // get_name_2:  .field_17_17   // get_Name:    .field_17_17   // getName->1:  null   // getName->2:  null   // getName->N:  null   // ofs = -1 ord = 0 addr = 17
	ifeq Label12
	aload_0 
	invokevirtual_short .virtual_17 // idx=17 pc=1
	pop 
Label12:
	aload_0_getfield .field_16_16   // get_name_1:  .field_16_16   // get_name_2:  .field_16_16   // get_Name:    .field_16_16   // getName->1:  null   // getName->2:  null   // getName->N:  null   // ofs = -1 ord = 0 addr = 16
	bipush 3
	if_icmpeq Label21
	aload_0_getfield .field_16_16   // get_name_1:  .field_16_16   // get_name_2:  .field_16_16   // get_Name:    .field_16_16   // getName->1:  null   // getName->2:  null   // getName->N:  null   // ofs = -1 ord = 0 addr = 16
	bipush 2
	if_icmpeq Label21
	aload_0 
	ldc literal_600:"unexpected type"
	invokespecial com.whatsapp.client.it.yup.xml.KXmlParser.routine_3595 // pc=2
Label21:
	aload_0_getfield .field_16_16   // get_name_1:  .field_16_16   // get_name_2:  .field_16_16   // get_Name:    .field_16_16   // getName->1:  null   // getName->2:  null   // getName->N:  null   // ofs = -1 ord = 0 addr = 16
	ireturn 
	}


public final require( com.whatsapp.client.it.yup.xml.KXmlParser, int, java.lang.String, java.lang.String ); // address: 0
	{
	enter 
	iload_1 
	aload_0_getfield .field_16_16   // get_name_1:  .field_16_16   // get_name_2:  .field_16_16   // get_Name:    .field_16_16   // getName->1:  null   // getName->2:  null   // getName->N:  null   // ofs = -1 ord = 0 addr = 16
	if_icmpne Label18
	aload_2 
	ifnull Label11
	aload_2 
	aload_0 
	invokevirtual_short .virtual_10 // idx=10 pc=1
	invokevirtual_short .equals // idx=1 pc=2
	ifeq Label18
Label11:
	aload_3 
	ifnull Label37
	aload_3 
	aload_0 
	invokevirtual_short .virtual_11 // idx=11 pc=1
	invokevirtual_short .equals // idx=1 pc=2
	ifne Label37
Label18:
	aload_0 
	new_lib Object//java.lang.Object java.lang.Object java.lang.Object
	dup 
	ldc literal_601:"expected: "
	invokespecial_lib java.lang.StringBuffer.<init> // pc=2
	getstatic_lib module:WhatsApp-37.class#20.static_55 // class#20
	iload_1 
	aaload 
	invokevirtual java.lang.StringBuffer append( java.lang.StringBuffer, java.lang.String ) // pc=2
	ldc literal_602:" {"
	invokevirtual java.lang.StringBuffer append( java.lang.StringBuffer, java.lang.String ) // pc=2
	aload_2 
	invokevirtual java.lang.StringBuffer append( java.lang.StringBuffer, java.lang.String ) // pc=2
	ldc literal_592:"}"
	invokevirtual java.lang.StringBuffer append( java.lang.StringBuffer, java.lang.String ) // pc=2
	aload_3 
	invokevirtual java.lang.StringBuffer append( java.lang.StringBuffer, java.lang.String ) // pc=2
	invokevirtual_short .toString // idx=2 pc=1
	invokespecial com.whatsapp.client.it.yup.xml.KXmlParser.routine_3595 // pc=2
Label37:
	return 
	}


public final setInput( com.whatsapp.client.it.yup.xml.KXmlParser, java.io.Reader ); // address: 0
	{
	enter_narrow 
	aload_0 
	aload_1 
	putfield .field_10_10   // get_name_1:  .field_10_10   // get_name_2:  .field_10_10   // get_Name:    .field_10_10   // getName->1:  null   // getName->2:  null   // getName->N:  null   // ofs = -1 ord = 0 addr = 10
	aload_0 
	ldc literal_603:"utf-8"
	putfield .field_11_11   // get_name_1:  .field_11_11   // get_name_2:  .field_11_11   // get_Name:    .field_11_11   // getName->1:  null   // getName->2:  null   // getName->N:  null   // ofs = -1 ord = 0 addr = 11
	aload_0 
	iconst_1 
	putfield .field_12_12   // get_name_1:  .field_12_12   // get_name_2:  .field_12_12   // get_Name:    .field_12_12   // getName->1:  null   // getName->2:  null   // getName->N:  null   // ofs = -1 ord = 0 addr = 12
	aload_0 
	iconst_0 
	putfield .field_13_13   // get_name_1:  .field_13_13   // get_name_2:  .field_13_13   // get_Name:    .field_13_13   // getName->1:  null   // getName->2:  null   // getName->N:  null   // ofs = -1 ord = 0 addr = 13
	aload_0 
	iconst_0 
	putfield .field_16_16   // get_name_1:  .field_16_16   // get_name_2:  .field_16_16   // get_Name:    .field_16_16   // getName->1:  null   // getName->2:  null   // getName->N:  null   // ofs = -1 ord = 0 addr = 16
	aload_0 
	aconst_null 
	putfield .field_20_20   // get_name_1:  .field_20_20   // get_name_2:  .field_20_20   // get_Name:    .field_20_20   // getName->1:  null   // getName->2:  null   // getName->N:  null   // ofs = -1 ord = 0 addr = 20
	aload_0 
	aconst_null 
	putfield .field_18_18   // get_name_1:  .field_18_18   // get_name_2:  .field_18_18   // get_Name:    .field_18_18   // getName->1:  null   // getName->2:  null   // getName->N:  null   // ofs = -1 ord = 0 addr = 18
	aload_0 
	iconst_0 
	putfield .field_21_21   // get_name_1:  .field_21_21   // get_name_2:  .field_21_21   // get_Name:    .field_21_21   // getName->1:  null   // getName->2:  null   // getName->N:  null   // ofs = -1 ord = 0 addr = 21
	aload_0 
	bipush -1
	putfield .field_22_22   // get_name_1:  .field_22_22   // get_name_2:  .field_22_22   // get_Name:    .field_22_22   // getName->1:  null   // getName->2:  null   // getName->N:  null   // ofs = -1 ord = 0 addr = 22
	aload_0 
	aconst_null 
	putfield .field_1_1   // get_name_1:  .field_1_1   // get_name_2:  .field_1_1   // get_Name:    .field_1_1   // getName->1:  null   // getName->2:  null   // getName->N:  null   // ofs = -1 ord = 0 addr = 1
	aload_0 
	aconst_null 
	putfield .field_2_2   // get_name_1:  .field_2_2   // get_name_2:  .field_2_2   // get_Name:    .field_2_2   // getName->1:  null   // getName->2:  null   // getName->N:  null   // ofs = -1 ord = 0 addr = 2
	aload_0 
	iconst_0 
	putfield .field_27_27   // get_name_1:  .field_27_27   // get_name_2:  .field_27_27   // get_Name:    .field_27_27   // getName->1:  null   // getName->2:  null   // getName->N:  null   // ofs = -1 ord = 0 addr = 27
	aload_0 
	iconst_0 
	putfield .field_6_6   // get_name_1:  .field_6_6   // get_name_2:  .field_6_6   // get_Name:    .field_6_6   // getName->1:  null   // getName->2:  null   // getName->N:  null   // ofs = -1 ord = 0 addr = 6
	aload_0 
	new_lib java.util.Hashtable//java.util.Hashtable java.util.Hashtable java.util.Hashtable
	dup 
	invokespecial_lib java.util.Hashtable.<init> // pc=1
	putfield .field_5_5   // get_name_1:  .field_5_5   // get_name_2:  .field_5_5   // get_Name:    .field_5_5   // getName->1:  null   // getName->2:  null   // getName->N:  null   // ofs = -1 ord = 0 addr = 5
	aload_0_getfield .field_5_5   // get_name_1:  .field_5_5   // get_name_2:  .field_5_5   // get_Name:    .field_5_5   // getName->1:  null   // getName->2:  null   // getName->N:  null   // ofs = -1 ord = 0 addr = 5
	ldc literal_604:"amp"
	ldc literal_605:"&"
	invokevirtual java.lang.Object put( java.util.Hashtable, java.lang.Object, java.lang.Object ) // pc=3
	pop 
	aload_0_getfield .field_5_5   // get_name_1:  .field_5_5   // get_name_2:  .field_5_5   // get_Name:    .field_5_5   // getName->1:  null   // getName->2:  null   // getName->N:  null   // ofs = -1 ord = 0 addr = 5
	ldc literal_606:"apos"
	ldc literal_595:"'"
	invokevirtual java.lang.Object put( java.util.Hashtable, java.lang.Object, java.lang.Object ) // pc=3
	pop 
	aload_0_getfield .field_5_5   // get_name_1:  .field_5_5   // get_name_2:  .field_5_5   // get_Name:    .field_5_5   // getName->1:  null   // getName->2:  null   // getName->N:  null   // ofs = -1 ord = 0 addr = 5
	ldc literal_607:"gt"
	ldc literal_608:">"
	invokevirtual java.lang.Object put( java.util.Hashtable, java.lang.Object, java.lang.Object ) // pc=3
	pop 
	aload_0_getfield .field_5_5   // get_name_1:  .field_5_5   // get_name_2:  .field_5_5   // get_Name:    .field_5_5   // getName->1:  null   // getName->2:  null   // getName->N:  null   // ofs = -1 ord = 0 addr = 5
	ldc literal_609:"lt"
	ldc literal_610:"<"
	invokevirtual java.lang.Object put( java.util.Hashtable, java.lang.Object, java.lang.Object ) // pc=3
	pop 
	aload_0_getfield .field_5_5   // get_name_1:  .field_5_5   // get_name_2:  .field_5_5   // get_Name:    .field_5_5   // getName->1:  null   // getName->2:  null   // getName->N:  null   // ofs = -1 ord = 0 addr = 5
	ldc literal_611:"quot"
	ldc literal_612:"""
	invokevirtual java.lang.Object put( java.util.Hashtable, java.lang.Object, java.lang.Object ) // pc=3
	pop 
	return 
	}

}
