// #######################################################
// Decompiled by   : coddec 
// Module          : WhatsApp-28.cod
// Module version  : 2.7.3204
// Class ID        : 12
// ########################################################


package com.whatsapp.client;


abstract final class SettingsTabButton$7 extends Object
implements Runnable

{

	// @@@@@@@@@@@@@ Fields 
	private final com.whatsapp.client.UiApp /*com.whatsapp.client.UiApp*/  field_54316 ; // ofs = 54316 addr = 0)
	private final net.rim.device.api.ui.Screen /*net.rim.device.api.ui.Screen*/  field_54320 ; // ofs = 54320 addr = 0)
	private final com.whatsapp.client.SettingsTabButton /*com.whatsapp.client.SettingsTabButton*/  field_54324 ; // ofs = 54324 addr = 0)

	// @@@@@@@@@@@@@ Static routines 

<init>( com.whatsapp.client.SettingsTabButton$7, com.whatsapp.client.SettingsTabButton, com.whatsapp.client.UiApp, net.rim.device.api.ui.Screen ); // address: 0
	{
	enter 
	aload_0 
	invokespecial_lib java.lang.Object.<init> // pc=1
	aload_0 
	aload_1 
	putfield .field_2_2   // get_name_1:  .field_2_2   // get_name_2:  .field_2_2   // get_Name:    .field_2_2   // getName->1:  null   // getName->2:  null   // getName->N:  null   // ofs = -1 ord = 0 addr = 2
	aload_0 
	aload_2 
	putfield .field_0_   // get_name_1:  .field_0_   // get_name_2:  .field_0_   // get_Name:    .field_0_   // getName->1:  null   // getName->2:  null   // getName->N:  null   // ofs = -1 ord = 0 addr = 0
	aload_0 
	aload_3 
	putfield .field_1_1   // get_name_1:  .field_1_1   // get_name_2:  .field_1_1   // get_Name:    .field_1_1   // getName->1:  null   // getName->2:  null   // getName->N:  null   // ofs = -1 ord = 0 addr = 1
	return 
	}

	// @@@@@@@@@@@@@ Virtual routines 

public final run( com.whatsapp.client.SettingsTabButton$7 ); // address: 0
	{
	enter 
	aload_0_getfield .field_0_   // get_name_1:  .field_0_   // get_name_2:  .field_0_   // get_Name:    .field_0_   // getName->1:  null   // getName->2:  null   // getName->N:  null   // ofs = -1 ord = 0 addr = 0
	invokevirtual net.rim.device.api.ui.UiEngineInstance getUiEngineInstance( net.rim.device.api.ui.UiApplication ) // pc=1
	aload_0_getfield .field_1_1   // get_name_1:  .field_1_1   // get_name_2:  .field_1_1   // get_Name:    .field_1_1   // getName->1:  null   // getName->2:  null   // getName->N:  null   // ofs = -1 ord = 0 addr = 1
	aconst_null 
	bipush 7
	aconst_null 
	invokevirtual setTransition( net.rim.device.api.ui.UiEngineInstance, net.rim.device.api.ui.Screen, net.rim.device.api.ui.Screen, int, net.rim.device.api.ui.TransitionContext ) // pc=5
	aload_0_getfield .field_0_   // get_name_1:  .field_0_   // get_name_2:  .field_0_   // get_Name:    .field_0_   // getName->1:  null   // getName->2:  null   // getName->N:  null   // ofs = -1 ord = 0 addr = 0
	invokevirtual net.rim.device.api.ui.UiEngineInstance getUiEngineInstance( net.rim.device.api.ui.UiApplication ) // pc=1
	aconst_null 
	aload_0_getfield .field_1_1   // get_name_1:  .field_1_1   // get_name_2:  .field_1_1   // get_Name:    .field_1_1   // getName->1:  null   // getName->2:  null   // getName->N:  null   // ofs = -1 ord = 0 addr = 1
	bipush 56
	aconst_null 
	invokevirtual setTransition( net.rim.device.api.ui.UiEngineInstance, net.rim.device.api.ui.Screen, net.rim.device.api.ui.Screen, int, net.rim.device.api.ui.TransitionContext ) // pc=5
	return 
	}

}
