// #######################################################
// Decompiled by   : coddec 
// Module          : WhatsApp-30.cod
// Module version  : 2.7.3204
// Class ID        : 1
// ########################################################


package com.whatsapp.client;


abstract final class SyncManager$SyncRunner extends Object
implements Runnable

{

	// @@@@@@@@@@@@@ Fields 
	private int /*int*/  field_52922 ; // ofs = 52922 addr = 0)
	private String /*java.lang.String*/  field_52926 ; // ofs = 52926 addr = 0)
	private String /*java.lang.String*/  field_52930 ; // ofs = 52930 addr = 0)
	private java.util.Hashtable /*java.util.Hashtable*/  field_52934 ; // ofs = 52934 addr = 0)
	private String /*java.lang.String*/  field_52938 ; // ofs = 52938 addr = 0)
	private String /*java.lang.String*/  field_52942 ; // ofs = 52942 addr = 0)
	private String /*java.lang.String*/  field_52946 ; // ofs = 52946 addr = 0)
	private final com.whatsapp.client.SyncManager /*module:WhatsApp-29.class#2*/  field_52950 ; // ofs = 52950 addr = 0)

	// @@@@@@@@@@@@@ Static routines 

<init>( com.whatsapp.client.SyncManager$SyncRunner, module:WhatsApp-29.class#2, int, java.lang.String, java.lang.String, java.util.Hashtable ); // address: 0
	{
	enter 
	aload_0 
	aload_1 
	iload_2 
	aload_3 
	aload_4 
	aload_5 
	aconst_null 
	aconst_null 
	aconst_null 
	invokespecial com.whatsapp.client.SyncManager$SyncRunner.<init> // pc=9
	return 
	}


<init>( com.whatsapp.client.SyncManager$SyncRunner, module:WhatsApp-29.class#2, int, java.lang.String, java.lang.String, java.util.Hashtable, java.lang.String, java.lang.String, java.lang.String ); // address: 0
	{
	enter 
	aload_0 
	invokespecial_lib java.lang.Object.<init> // pc=1
	aload_0 
	aload_1 
	putfield .field_7_7   // get_name_1:  .field_7_7   // get_name_2:  .field_7_7   // get_Name:    .field_7_7   // getName->1:  null   // getName->2:  null   // getName->N:  null   // ofs = -1 ord = 0 addr = 7
	aload_0 
	iload_2 
	putfield .field_0_   // get_name_1:  .field_0_   // get_name_2:  .field_0_   // get_Name:    .field_0_   // getName->1:  null   // getName->2:  null   // getName->N:  null   // ofs = -1 ord = 0 addr = 0
	aload_0 
	aload_3 
	putfield .field_1_1   // get_name_1:  .field_1_1   // get_name_2:  .field_1_1   // get_Name:    .field_1_1   // getName->1:  null   // getName->2:  null   // getName->N:  null   // ofs = -1 ord = 0 addr = 1
	aload_0 
	aload_4 
	putfield .field_2_2   // get_name_1:  .field_2_2   // get_name_2:  .field_2_2   // get_Name:    .field_2_2   // getName->1:  null   // getName->2:  null   // getName->N:  null   // ofs = -1 ord = 0 addr = 2
	aload_0 
	aload_5 
	putfield .field_3_3   // get_name_1:  .field_3_3   // get_name_2:  .field_3_3   // get_Name:    .field_3_3   // getName->1:  null   // getName->2:  null   // getName->N:  null   // ofs = -1 ord = 0 addr = 3
	aload_0 
	aload_6 
	putfield .field_4_4   // get_name_1:  .field_4_4   // get_name_2:  .field_4_4   // get_Name:    .field_4_4   // getName->1:  null   // getName->2:  null   // getName->N:  null   // ofs = -1 ord = 0 addr = 4
	aload_0 
	aload_7 
	putfield .field_5_5   // get_name_1:  .field_5_5   // get_name_2:  .field_5_5   // get_Name:    .field_5_5   // getName->1:  null   // getName->2:  null   // getName->N:  null   // ofs = -1 ord = 0 addr = 5
	aload_0 
	aload 8
	putfield .field_6_6   // get_name_1:  .field_6_6   // get_name_2:  .field_6_6   // get_Name:    .field_6_6   // getName->1:  null   // getName->2:  null   // getName->N:  null   // ofs = -1 ord = 0 addr = 6
	return 
	}

	// @@@@@@@@@@@@@ Non-virtual routines 

private final com.whatsapp.client.SyncManager$SyncRunner.routine_4233( com.whatsapp.client.SyncManager$SyncRunner, int ); // address: 0
	{
	enter 
	new_lib java.util.Hashtable//java.util.Hashtable java.util.Hashtable java.util.Hashtable
	dup 
	invokespecial_lib java.util.Hashtable.<init> // pc=1
	astore_2 
	aload_2 
	getstatic_lib module:WhatsApp-12.class#0.static_138 // class#0
	new_lib javax.microedition.io.OutputConnection//javax.microedition.io.OutputConnection javax.microedition.io.OutputConnection javax.microedition.io.OutputConnection
	dup 
	aload_0 
	iload_1 
	invokespecial com.whatsapp.client.SyncManager$SyncRunner.routine_4607 // pc=2
	invokespecial_lib java.lang.Throwable.<init> // pc=2
	invokevirtual java.lang.Object put( java.util.Hashtable, java.lang.Object, java.lang.Object ) // pc=3
	pop 
	aload_0_getfield .field_7_7   // get_name_1:  .field_7_7   // get_name_2:  .field_7_7   // get_Name:    .field_7_7   // getName->1:  null   // getName->2:  null   // getName->N:  null   // ofs = -1 ord = 0 addr = 7
	aload_0_getfield .field_0_   // get_name_1:  .field_0_   // get_name_2:  .field_0_   // get_Name:    .field_0_   // getName->1:  null   // getName->2:  null   // getName->N:  null   // ofs = -1 ord = 0 addr = 0
	aload_0_getfield .field_3_3   // get_name_1:  .field_3_3   // get_name_2:  .field_3_3   // get_Name:    .field_3_3   // getName->1:  null   // getName->2:  null   // getName->N:  null   // ofs = -1 ord = 0 addr = 3
	aload_2 
	invokespecial_lib .routine_9173 // pc=4
	return 
	}


private final java.lang.String com.whatsapp.client.SyncManager$SyncRunner.routine_4297( com.whatsapp.client.SyncManager$SyncRunner ); // address: 0
	{
	enter 
	ldc literal_71:"00000001"
	astore_1 
	new_lib Object//java.lang.Object java.lang.Object java.lang.Object
	dup 
	invokespecial_lib java.lang.StringBuffer.<init> // pc=1
	getstatic_lib module:WhatsApp-12.class#0.static_174 // class#0
	invokevirtual java.lang.StringBuffer append( java.lang.StringBuffer, java.lang.String ) // pc=2
	aload_0_getfield .field_6_6   // get_name_1:  .field_6_6   // get_name_2:  .field_6_6   // get_Name:    .field_6_6   // getName->1:  null   // getName->2:  null   // getName->N:  null   // ofs = -1 ord = 0 addr = 6
	invokevirtual java.lang.StringBuffer append( java.lang.StringBuffer, java.lang.String ) // pc=2
	invokevirtual_short .toString // idx=2 pc=1
	astore_2 
	new_lib Object//java.lang.Object java.lang.Object java.lang.Object
	dup 
	getstatic_lib module:WhatsApp-12.class#0.static_168 // class#0
	invokestatic_lib module:WhatsApp-32.class#2.routine_1796(  ) // class#2
	invokespecial_lib java.lang.StringBuffer.<init> // pc=2
	astore_3 
	aload_3 
	aload_0_getfield .field_2_2   // get_name_1:  .field_2_2   // get_name_2:  .field_2_2   // get_Name:    .field_2_2   // getName->1:  null   // getName->2:  null   // getName->N:  null   // ofs = -1 ord = 0 addr = 2
	invokevirtual java.lang.StringBuffer append( java.lang.StringBuffer, java.lang.String ) // pc=2
	pop 
	aload_3 
	invokevirtual_short .toString // idx=2 pc=1
	bipush 3
	iconst_1 
	invokestatic_lib javax.microedition.io.Connection open( java.lang.String, int, boolean ) // Connector
	checkcast_lib net.rim.device.api.util.SimpleSortingVector//net.rim.device.api.util.SimpleSortingVector net.rim.device.api.util.SimpleSortingVector net.rim.device.api.util.SimpleSortingVector
	astore_4 
	aload_4 
	getstatic_lib module:WhatsApp-12.class#0.static_55 // class#0
	invokestatic_lib module:WhatsApp-32.class#2.routine_3892(  ) // class#2
	invokeinterface interfacemethodref_5 // pc=3 guess=8
	ldc literal_72:"0"
	invokestatic_lib module:WhatsApp-17.class#25.routine_4234(  ) // class#25
	aload_1 
	aload_0_getfield .field_4_4   // get_name_1:  .field_4_4   // get_name_2:  .field_4_4   // get_Name:    .field_4_4   // getName->1:  null   // getName->2:  null   // getName->N:  null   // ofs = -1 ord = 0 addr = 4
	aload_0_getfield .field_6_6   // get_name_1:  .field_6_6   // get_name_2:  .field_6_6   // get_Name:    .field_6_6   // getName->1:  null   // getName->2:  null   // getName->N:  null   // ofs = -1 ord = 0 addr = 6
	aload_2 
	aload_0_getfield .field_5_5   // get_name_1:  .field_5_5   // get_name_2:  .field_5_5   // get_Name:    .field_5_5   // getName->1:  null   // getName->2:  null   // getName->N:  null   // ofs = -1 ord = 0 addr = 5
	new_lib com.whatsapp.client.FunXMPPRunner$BBDigest//module:WhatsApp-18.class#4 module:WhatsApp-18.class#4 module:WhatsApp-18.class#4
	dup 
	invokespecial_lib .routine_4767 // pc=1
	invokestatic_lib module:WhatsApp-17.class#25.routine_4412(  ) // class#25
	astore_5 
	aload_4 
	getstatic_lib module:WhatsApp-12.class#0.static_56 // class#0
	new_lib Object//java.lang.Object java.lang.Object java.lang.Object
	dup 
	invokespecial_lib java.lang.StringBuffer.<init> // pc=1
	getstatic_lib module:WhatsApp-12.class#0.static_173 // class#0
	invokevirtual java.lang.StringBuffer append( java.lang.StringBuffer, java.lang.String ) // pc=2
	aload_5 
	invokevirtual java.lang.StringBuffer append( java.lang.StringBuffer, java.lang.String ) // pc=2
	invokevirtual_short .toString // idx=2 pc=1
	invokeinterface interfacemethodref_5 // pc=3 guess=8
	aload_4 
	getstatic_lib module:WhatsApp-12.class#0.static_58 // class#0
	getstatic_lib module:WhatsApp-12.class#0.static_59 // class#0
	invokeinterface interfacemethodref_5 // pc=3 guess=8
	aload_4 
	getstatic_lib module:WhatsApp-12.class#0.static_53 // class#0
	getstatic_lib module:WhatsApp-12.class#0.static_54 // class#0
	invokeinterface interfacemethodref_5 // pc=3 guess=8
	aload_4 
	ldc literal_73:"GET"
	invokeinterface interfacemethodref_6 // pc=2 guess=9
	aload_4 
	invokeinterface interfacemethodref_8 // pc=1 guess=10
	istore_6 
	iload_6 
	sipush 401
	if_icmpeq Label78
	aload_0 
	iload_6 
	invokespecial com.whatsapp.client.SyncManager$SyncRunner.routine_4233 // pc=2
	aconst_null 
	areturn 
Label78:
	aload_4 
	getstatic_lib module:WhatsApp-12.class#0.static_60 // class#0
	invokeinterface interfacemethodref_10 // pc=2 guess=11
	astore_7 
	aload_7 
	invokestatic_lib module:WhatsApp-17.class#25.routine_4275(  ) // class#25
	astore 8
	new_lib Object//java.lang.Object java.lang.Object java.lang.Object
	dup 
	invokespecial_lib java.lang.StringBuffer.<init> // pc=1
	getstatic_lib module:WhatsApp-12.class#0.static_173 // class#0
	invokevirtual java.lang.StringBuffer append( java.lang.StringBuffer, java.lang.String ) // pc=2
	aload 8
	invokestatic_lib module:WhatsApp-17.class#25.routine_4234(  ) // class#25
	aload_1 
	aload_0_getfield .field_4_4   // get_name_1:  .field_4_4   // get_name_2:  .field_4_4   // get_Name:    .field_4_4   // getName->1:  null   // getName->2:  null   // getName->N:  null   // ofs = -1 ord = 0 addr = 4
	aload_0_getfield .field_6_6   // get_name_1:  .field_6_6   // get_name_2:  .field_6_6   // get_Name:    .field_6_6   // getName->1:  null   // getName->2:  null   // getName->N:  null   // ofs = -1 ord = 0 addr = 6
	aload_2 
	aload_0_getfield .field_5_5   // get_name_1:  .field_5_5   // get_name_2:  .field_5_5   // get_Name:    .field_5_5   // getName->1:  null   // getName->2:  null   // getName->N:  null   // ofs = -1 ord = 0 addr = 5
	new_lib com.whatsapp.client.FunXMPPRunner$BBDigest//module:WhatsApp-18.class#4 module:WhatsApp-18.class#4 module:WhatsApp-18.class#4
	dup 
	invokespecial_lib .routine_4767 // pc=1
	invokestatic_lib module:WhatsApp-17.class#25.routine_4412(  ) // class#25
	invokevirtual java.lang.StringBuffer append( java.lang.StringBuffer, java.lang.String ) // pc=2
	invokevirtual_short .toString // idx=2 pc=1
	areturn 
	}


private final java.lang.String com.whatsapp.client.SyncManager$SyncRunner.routine_4607( com.whatsapp.client.SyncManager$SyncRunner, int ); // address: 0
	{
	enter_narrow 
	new_lib Object//java.lang.Object java.lang.Object java.lang.Object
	dup 
	ldc literal_74:"HTTP Response ["
	invokespecial_lib java.lang.StringBuffer.<init> // pc=2
	iload_1 
	invokevirtual java.lang.StringBuffer append( java.lang.StringBuffer, int ) // pc=2
	ldc literal_75:"]"
	invokevirtual java.lang.StringBuffer append( java.lang.StringBuffer, java.lang.String ) // pc=2
	invokevirtual_short .toString // idx=2 pc=1
	areturn 
	}

	// @@@@@@@@@@@@@ Virtual routines 

public final run( com.whatsapp.client.SyncManager$SyncRunner ); // address: 0
	{
	enter 
	aload_0_getfield .field_0_   // get_name_1:  .field_0_   // get_name_2:  .field_0_   // get_Name:    .field_0_   // getName->1:  null   // getName->2:  null   // getName->N:  null   // ofs = -1 ord = 0 addr = 0
	bipush 6
	if_icmpne Label12
	invokestatic_lib com.whatsapp.client.App.routine_10054(  ) // App
	getfield _firstSyncFails   // get_name_1:  _firstSyncFails   // get_name_2:  _firstSyncFails   // get_Name:    _firstSyncFails   // getName->1:  _firstSyncFails   // getName->2:  _firstSyncFails   // getName->N:  _firstSyncFails   // ofs = -1 ord = 0 addr = -1
	iconst_1 
	iadd 
	sipush 1000
	imul 
	i2l 
	invokestatic_lib sleep( long ) // Thread
Label12:
	getstatic_lib module:WhatsApp-29.class#2.static_7 // class#2
	invokenonvirtual_lib .routine_8038 // pc=1
	aconst_null 
	astore_1 
	aconst_null 
	astore_2 
	aconst_null 
	astore_3 
	aconst_null 
	astore_4 
	invokestatic_lib module:WhatsApp-32.class#2.routine_3892(  ) // class#2
	astore_5 
	aload_0_getfield .field_0_   // get_name_1:  .field_0_   // get_name_2:  .field_0_   // get_Name:    .field_0_   // getName->1:  null   // getName->2:  null   // getName->N:  null   // ofs = -1 ord = 0 addr = 0
	putstatic_lib module:WhatsApp-29.class#2.static_8 // class#2
	new_lib Object//java.lang.Object java.lang.Object java.lang.Object
	dup 
	aload_0_getfield .field_1_1   // get_name_1:  .field_1_1   // get_name_2:  .field_1_1   // get_Name:    .field_1_1   // getName->1:  null   // getName->2:  null   // getName->N:  null   // ofs = -1 ord = 0 addr = 1
	invokespecial_lib java.lang.StringBuffer.<init> // pc=2
	astore_6 
	aload_6 
	aload_0_getfield .field_2_2   // get_name_1:  .field_2_2   // get_name_2:  .field_2_2   // get_Name:    .field_2_2   // getName->1:  null   // getName->2:  null   // getName->N:  null   // ofs = -1 ord = 0 addr = 2
	invokevirtual java.lang.StringBuffer append( java.lang.StringBuffer, java.lang.String ) // pc=2
	pop 
	aload_6 
	invokevirtual_short .toString // idx=2 pc=1
	astore_7 
	aconst_null 
	astore_6 
	aload_0_getfield .field_0_   // get_name_1:  .field_0_   // get_name_2:  .field_0_   // get_Name:    .field_0_   // getName->1:  null   // getName->2:  null   // getName->N:  null   // ofs = -1 ord = 0 addr = 0
	tableswitch  :
		
		
		
		
		
		
		
		
		

Label42:
	aconst_null 
	astore 8
	invokestatic_lib module:WhatsApp-26.class#11.routine_3571(  ) // class#11
	astore 9
	aload 9
	invokenonvirtual_lib .routine_2951 // pc=1
	astore 10
	aload 9
	invokenonvirtual_lib .routine_3069 // pc=1
	astore 11
	invokestatic_lib module:WhatsApp-13.class#5.routine_9622(  ) // class#5
	astore 12
	aload 12
	getfield .field_0_   // get_name_1:  .field_0_   // get_name_2:  .field_0_   // get_Name:    .field_0_   // getName->1:  null   // getName->2:  null   // getName->N:  null   // ofs = -1 ord = 0 addr = 0
	astore 13
	new SyncManager$UTF8URLEncoder
	dup 
	aconst_null 
	invokespecial com.whatsapp.client.SyncManager$UTF8URLEncoder.<init> // pc=2
	astore 14
	aload 14
	ldc literal_54:"v"
	ldc literal_55:"3"
	invokenonvirtual com.whatsapp.client.SyncManager$UTF8URLEncoder.append // pc=3
	aload 14
	ldc literal_56:"cc"
	aload 11
	getfield .field_0_   // get_name_1:  .field_0_   // get_name_2:  .field_0_   // get_Name:    .field_0_   // getName->1:  null   // getName->2:  null   // getName->N:  null   // ofs = -1 ord = 0 addr = 0
	invokestatic_lib java.lang.String valueOf( int ) // String
	invokenonvirtual com.whatsapp.client.SyncManager$UTF8URLEncoder.append // pc=3
	aload 14
	ldc literal_57:"me"
	aload 11
	getfield .field_2_2   // get_name_1:  .field_2_2   // get_name_2:  .field_2_2   // get_Name:    .field_2_2   // getName->1:  null   // getName->2:  null   // getName->N:  null   // ofs = -1 ord = 0 addr = 2
	invokenonvirtual com.whatsapp.client.SyncManager$UTF8URLEncoder.append // pc=3
	invokestatic_lib net.rim.device.api.system.RuntimeStore getRuntimeStore(  ) // RuntimeStore
	lipush 8535665252065932813
	invokevirtual java.lang.Object get( net.rim.device.api.system.RuntimeStore, long ) // pc=3
	checkcast_lib //module:WhatsApp-13.class#1 module:WhatsApp-13.class#1 module:WhatsApp-13.class#1
	astore 15
	aconst_null 
	astore 16
	aload_0_getfield .field_0_   // get_name_1:  .field_0_   // get_name_2:  .field_0_   // get_Name:    .field_0_   // getName->1:  null   // getName->2:  null   // getName->N:  null   // ofs = -1 ord = 0 addr = 0
	tableswitch  :
		
		
		
		
		

Label86:
	invokestatic_lib module:WhatsApp-10.class#29.routine_5442(  ) // class#29
	astore 17
	aload 17
	getfield .field_8_8   // get_name_1:  .field_8_8   // get_name_2:  .field_8_8   // get_Name:    .field_8_8   // getName->1:  null   // getName->2:  null   // getName->N:  null   // ofs = -1 ord = 0 addr = 8
	bipush 4
	iand 
	ifle Label97
	aload 14
	ldc literal_58:"qh"
	ldc literal_59:"1"
	invokenonvirtual com.whatsapp.client.SyncManager$UTF8URLEncoder.append // pc=3
Label97:
	aload 15
	invokenonvirtual_lib .routine_4597 // pc=1
	iconst_1 
	isub 
	istore 18
Label102:
	iload 18
	ifge Label105
	goto_w Label175
Label105:
	aload 15
	iload 18
	invokenonvirtual_lib .routine_3878 // pc=2
	invokenonvirtual_lib .routine_6881 // pc=1
	astore 19
	iconst_0 
	istore 20
Label112:
	iload 20
	aload 19
	arraylength 
	if_icmpge Label128
	aload 19
	iload 20
	aaload 
	astore 16
	aload 16
	ifnull Label126
	aload 14
	ldc literal_60:"u[]"
	aload 16
	invokenonvirtual com.whatsapp.client.SyncManager$UTF8URLEncoder.appendXMLCheck // pc=3
Label126:
	iinc 20 1
	goto Label112
Label128:
	iinc 18 -1
	goto Label102
Label130:
	aload_0_getfield .field_3_3   // get_name_1:  .field_3_3   // get_name_2:  .field_3_3   // get_Name:    .field_3_3   // getName->1:  null   // getName->2:  null   // getName->N:  null   // ofs = -1 ord = 0 addr = 3
	ifnull Label158
	aload_0_getfield .field_3_3   // get_name_1:  .field_3_3   // get_name_2:  .field_3_3   // get_Name:    .field_3_3   // getName->1:  null   // getName->2:  null   // getName->N:  null   // ofs = -1 ord = 0 addr = 3
	getstatic_lib module:WhatsApp-12.class#0.static_141 // class#0
	invokevirtual java.lang.Object get( java.util.Hashtable, java.lang.Object ) // pc=2
	checkcast_lib com.whatsapp.client.ContactInfoDetails//module:WhatsApp.class#11 module:WhatsApp.class#11 module:WhatsApp.class#11
	astore 8
	aload 8
	invokenonvirtual_lib .routine_6881 // pc=1
	astore 17
	iconst_0 
	istore 18
Label142:
	iload 18
	aload 17
	arraylength 
	if_icmpge Label175
	aload 17
	iload 18
	aaload 
	astore 19
	aload 19
	ifnull Label156
	aload 14
	ldc literal_60:"u[]"
	aload 19
	invokenonvirtual com.whatsapp.client.SyncManager$UTF8URLEncoder.appendXMLCheck // pc=3
Label156:
	iinc 18 1
	goto Label142
Label158:
	aload 13
	invokevirtual java.util.Enumeration keys( java.util.Hashtable ) // pc=1
	astore 17
Label161:
	aload 17
	invokeinterface interfacemethodref_2 // pc=1 guess=0
	ifeq Label175
	aload 17
	invokeinterface interfacemethodref_3 // pc=1 guess=1
	checkcast_lib net.rim.device.api.ui.MenuItem//net.rim.device.api.ui.MenuItem net.rim.device.api.ui.MenuItem net.rim.device.api.ui.MenuItem
	astore 16
	aload 16
	ifnull Label161
	aload 14
	ldc literal_60:"u[]"
	aload 16
	invokenonvirtual com.whatsapp.client.SyncManager$UTF8URLEncoder.appendXMLCheck // pc=3
	goto Label161
Label175:
	aload 14
	ldc literal_60:"u[]"
	aload 11
	getfield .field_2_2   // get_name_1:  .field_2_2   // get_name_2:  .field_2_2   // get_Name:    .field_2_2   // getName->1:  null   // getName->2:  null   // getName->N:  null   // ofs = -1 ord = 0 addr = 2
	invokenonvirtual com.whatsapp.client.SyncManager$UTF8URLEncoder.append // pc=3
	aload 14
	ldc literal_61:"bb"
	ldc literal_59:"1"
	invokenonvirtual com.whatsapp.client.SyncManager$UTF8URLEncoder.append // pc=3
	aload 10
	invokenonvirtual_lib .routine_2170 // pc=1
	ifne Label191
	aload 14
	ldc literal_62:"bbfr"
	ldc literal_59:"1"
	invokenonvirtual com.whatsapp.client.SyncManager$UTF8URLEncoder.append // pc=3
Label191:
	aconst_null 
	astore 17
	aload_0_getfield .field_4_4   // get_name_1:  .field_4_4   // get_name_2:  .field_4_4   // get_Name:    .field_4_4   // getName->1:  null   // getName->2:  null   // getName->N:  null   // ofs = -1 ord = 0 addr = 4
	ifnull Label237
	aload_0 
	invokespecial com.whatsapp.client.SyncManager$SyncRunner.routine_4297 // pc=1
	astore 17
	aload 17
	ifnonnull Label237
	aload_3 
	ifnull Label208
	aload_3 
	invokevirtual close( java.io.InputStream ) // pc=1
	goto Label206
	astore 36
Label206:
	aconst_null 
	astore_3 
Label208:
	aload_4 
	ifnull Label216
	aload_4 
	invokevirtual close( java.io.OutputStream ) // pc=1
	goto Label214
	astore 36
Label214:
	aconst_null 
	astore_4 
Label216:
	aload_1 
	ifnull Label224
	aload_1 
	invokeinterface interfacemethodref_4 // pc=1 guess=2
	goto Label222
	astore 36
Label222:
	aconst_null 
	astore_1 
Label224:
	aload_2 
	ifnull Label232
	aload_2 
	invokeinterface interfacemethodref_4 // pc=1 guess=2
	goto Label230
	astore 36
Label230:
	aconst_null 
	astore_2 
Label232:
	bipush -1
	putstatic_lib module:WhatsApp-29.class#2.static_8 // class#2
	getstatic_lib module:WhatsApp-29.class#2.static_7 // class#2
	invokenonvirtual_lib .routine_8184 // pc=1
	return 
Label237:
	aload 14
	invokenonvirtual com.whatsapp.client.SyncManager$UTF8URLEncoder.getBytes // pc=1
	astore 18
	aconst_null 
	astore 14
	aload_7 
	bipush 3
	iconst_1 
	invokestatic_lib javax.microedition.io.Connection open( java.lang.String, int, boolean ) // Connector
	checkcast_lib net.rim.device.api.util.SimpleSortingVector//net.rim.device.api.util.SimpleSortingVector net.rim.device.api.util.SimpleSortingVector net.rim.device.api.util.SimpleSortingVector
	astore_1 
	aload_1 
	getstatic_lib module:WhatsApp-12.class#0.static_55 // class#0
	aload_5 
	invokeinterface interfacemethodref_5 // pc=3 guess=3
	aload 17
	ifnull Label258
	aload_1 
	getstatic_lib module:WhatsApp-12.class#0.static_56 // class#0
	aload 17
	invokeinterface interfacemethodref_5 // pc=3 guess=3
Label258:
	aload_1 
	getstatic_lib module:WhatsApp-12.class#0.static_58 // class#0
	getstatic_lib module:WhatsApp-12.class#0.static_59 // class#0
	invokeinterface interfacemethodref_5 // pc=3 guess=3
	aload_1 
	getstatic_lib module:WhatsApp-12.class#0.static_53 // class#0
	getstatic_lib module:WhatsApp-12.class#0.static_54 // class#0
	invokeinterface interfacemethodref_5 // pc=3 guess=3
	aload_1 
	ldc literal_63:"POST"
	invokeinterface interfacemethodref_6 // pc=2 guess=4
	aload 18
	ifnull Label274
	aload 18
	arraylength 
	goto Label275
Label274:
	iconst_0 
Label275:
	istore 19
	aload_1 
	getstatic_lib module:WhatsApp-12.class#0.static_52 // class#0
	iload 19
	invokestatic_lib java.lang.String toString( int ) // Integer
	invokeinterface interfacemethodref_5 // pc=3 guess=3
	aload_1 
	invokeinterface interfacemethodref_7 // pc=1 guess=5
	astore_4 
	aload_4 
	aload 18
	invokevirtual write( java.io.OutputStream, byte[] ) // pc=2
	aload_4 
	invokevirtual flush( java.io.OutputStream ) // pc=1
	invokestatic_lib module:WhatsApp-10.class#29.routine_5442(  ) // class#29
	getfield .field_38_38   // get_name_1:  .field_38_38   // get_name_2:  .field_38_38   // get_Name:    .field_38_38   // getName->1:  null   // getName->2:  null   // getName->N:  null   // ofs = -1 ord = 0 addr = 38
	aload 18
	arraylength 
	i2l 
	bipush 2
	invokenonvirtual_lib .routine_10296 // pc=4
	aconst_null 
	astore 18
	aload_1 
	invokeinterface interfacemethodref_8 // pc=1 guess=6
	istore 20
	iload 20
	sipush 200
	if_icmpeq Label344
	aload_0 
	iload 20
	invokespecial com.whatsapp.client.SyncManager$SyncRunner.routine_4233 // pc=2
	aload_3 
	ifnull Label315
	aload_3 
	invokevirtual close( java.io.InputStream ) // pc=1
	goto Label313
	astore 36
Label313:
	aconst_null 
	astore_3 
Label315:
	aload_4 
	ifnull Label323
	aload_4 
	invokevirtual close( java.io.OutputStream ) // pc=1
	goto Label321
	astore 36
Label321:
	aconst_null 
	astore_4 
Label323:
	aload_1 
	ifnull Label331
	aload_1 
	invokeinterface interfacemethodref_4 // pc=1 guess=2
	goto Label329
	astore 36
Label329:
	aconst_null 
	astore_1 
Label331:
	aload_2 
	ifnull Label339
	aload_2 
	invokeinterface interfacemethodref_4 // pc=1 guess=2
	goto Label337
	astore 36
Label337:
	aconst_null 
	astore_2 
Label339:
	bipush -1
	putstatic_lib module:WhatsApp-29.class#2.static_8 // class#2
	getstatic_lib module:WhatsApp-29.class#2.static_7 // class#2
	invokenonvirtual_lib .routine_8184 // pc=1
	return 
Label344:
	aload 10
	invokenonvirtual_lib .routine_2170 // pc=1
	ifne Label358
	aload 9
	invokenonvirtual_lib .routine_2951 // pc=1
	invokestatic_lib java.lang.Object expandGroup( java.lang.Object ) // ObjectGroup
	checkcast_lib com.whatsapp.client.ApplicationHashData//module:WhatsApp.class#9 module:WhatsApp.class#9 module:WhatsApp.class#9
	astore 10
	aload 10
	iconst_1 
	invokenonvirtual_lib .routine_2190 // pc=2
	aload 9
	aload 10
	invokestatic_lib module:WhatsApp.class#9.routine_3363(  ) // class#9
Label358:
	aload_1 
	invokeinterface interfacemethodref_9 // pc=1 guess=7
	astore_3 
	new_lib com.whatsapp.client.it.yup.xml.KXmlParser//module:WhatsApp-35.class#12 module:WhatsApp-35.class#12 module:WhatsApp-35.class#12
	dup 
	invokespecial_lib .routine_7345 // pc=1
	astore 21
	new_lib com.whatsapp.client.FunXMPPRunner$MeteredInputStream//module:WhatsApp-17.class#35 module:WhatsApp-17.class#35 module:WhatsApp-17.class#35
	dup 
	aload_3 
	bipush 2
	invokestatic_lib module:WhatsApp-10.class#29.routine_5442(  ) // class#29
	invokespecial_lib .routine_7832 // pc=4
	astore 22
	new_lib javax.microedition.io.HttpConnection//javax.microedition.io.HttpConnection javax.microedition.io.HttpConnection javax.microedition.io.HttpConnection
	dup 
	aload 22
	invokespecial_lib java.io.InputStreamReader.<init> // pc=2
	astore 23
	aload 21
	aload 23
	invokevirtual_short .virtual_21 // idx=21 pc=2
	aload 21
	invokevirtual_short .virtual_19 // idx=19 pc=1
	pop 
	aload 21
	bipush 2
	aconst_null 
	ldc literal_64:"statusreport"
	invokevirtual_short .virtual_20 // idx=20 pc=4
	aload 21
	invokevirtual_short .virtual_19 // idx=19 pc=1
	pop 
	aload 9
	invokenonvirtual_lib .routine_3246 // pc=1
	astore 29
	aload 29
	getfield .field_1_1   // get_name_1:  .field_1_1   // get_name_2:  .field_1_1   // get_Name:    .field_1_1   // getName->1:  null   // getName->2:  null   // getName->N:  null   // ofs = -1 ord = 0 addr = 1
	invokevirtual boolean isEmpty( java.util.Vector ) // pc=1
	istore 30
Label398:
	aload 21
	invokevirtual_short .virtual_16 // idx=16 pc=1
	bipush 3
	if_icmpne Label403
	goto_w Label522
Label403:
	aload 21
	bipush 2
	aconst_null 
	ldc literal_65:"s"
	invokevirtual_short .virtual_20 // idx=20 pc=4
	aload 21
	aconst_null 
	ldc literal_66:"p"
	invokevirtual_short .virtual_15 // idx=15 pc=3
	astore 24
	aload 21
	aconst_null 
	ldc literal_67:"t"
	invokevirtual_short .virtual_15 // idx=15 pc=3
	invokestatic_lib long parseLong( java.lang.String ) // Long
	lstore 27
	goto Label424
	astore 31
	bipush -1
	i2l 
	lstore 27
Label424:
	aload 21
	aconst_null 
	ldc literal_68:"jid"
	invokevirtual_short .virtual_15 // idx=15 pc=3
	astore 25
	aload 21
	aconst_null 
	ldc literal_69:"u"
	invokevirtual_short .virtual_15 // idx=15 pc=3
	astore 26
	aload 21
	invokevirtual_short .virtual_18 // idx=18 pc=1
	pop 
	aload 26
	ifnull Label448
	aload 26
	ldc literal_59:"1"
	invokevirtual_short .equals // idx=1 pc=2
	ifeq Label448
	aload 12
	aload 25
	aload 24
	invokenonvirtual_lib .routine_9538 // pc=3
	goto_w Label513
Label448:
	aconst_null 
	astore 31
	aload 21
	invokevirtual_short .virtual_16 // idx=16 pc=1
	bipush 5
	if_icmpne Label472
	aload 21
	bipush 5
	aconst_null 
	aconst_null 
	invokevirtual_short .virtual_20 // idx=20 pc=4
	aload 21
	invokevirtual_short .virtual_9 // idx=9 pc=1
	astore 31
	new_lib net.rim.device.api.ui.MenuItem//net.rim.device.api.ui.MenuItem net.rim.device.api.ui.MenuItem net.rim.device.api.ui.MenuItem
	dup 
	aload 31
	invokenonvirtual_lib java.lang.String.getBytes // pc=1
	getstatic_lib module:WhatsApp-12.class#0.static_2 // class#0
	invokespecial_lib java.lang.String.<init> // pc=3
	astore 31
	aload 21
	invokevirtual_short .virtual_19 // idx=19 pc=1
	pop 
Label472:
	aload 12
	aload 31
	lload 27
	aload 25
	aload 24
	invokenonvirtual_lib .routine_9435 // pc=6
	istore 32
	iload 32
	ifeq Label485
	aload 25
	invokestatic_lib module:WhatsApp-10.class#4.routine_2364(  ) // class#4
	goto Label485
	astore 33
Label485:
	aload 24
	aload 11
	getfield .field_2_2   // get_name_1:  .field_2_2   // get_name_2:  .field_2_2   // get_Name:    .field_2_2   // getName->1:  null   // getName->2:  null   // getName->N:  null   // ofs = -1 ord = 0 addr = 2
	invokevirtual_short .equals // idx=1 pc=2
	ifne Label507
	aload 15
	getfield .field_3_3   // get_name_1:  .field_3_3   // get_name_2:  .field_3_3   // get_Name:    .field_3_3   // getName->1:  null   // getName->2:  null   // getName->N:  null   // ofs = -1 ord = 0 addr = 3
	aload 24
	invokevirtual java.lang.Object get( java.util.Hashtable, java.lang.Object ) // pc=2
	checkcast_lib com.whatsapp.client.ContactInfoDetails//module:WhatsApp.class#11 module:WhatsApp.class#11 module:WhatsApp.class#11
	astore 33
	aload 33
	ifnull Label513
	aload 29
	new_lib com.whatsapp.client.UIDPhone//module:WhatsApp.class#15 module:WhatsApp.class#15 module:WhatsApp.class#15
	dup 
	aload 33
	getfield .field_0_   // get_name_1:  .field_0_   // get_name_2:  .field_0_   // get_Name:    .field_0_   // getName->1:  null   // getName->2:  null   // getName->N:  null   // ofs = -1 ord = 0 addr = 0
	aload 24
	invokespecial_lib .routine_10070 // pc=3
	invokenonvirtual_lib .routine_9217 // pc=2
	goto Label513
Label507:
	aload 12
	aload 25
	putfield .field_3_3   // get_name_1:  .field_3_3   // get_name_2:  .field_3_3   // get_Name:    .field_3_3   // getName->1:  null   // getName->2:  null   // getName->N:  null   // ofs = -1 ord = 0 addr = 3
	aload 12
	aload 31
	putfield .field_4_4   // get_name_1:  .field_4_4   // get_name_2:  .field_4_4   // get_Name:    .field_4_4   // getName->1:  null   // getName->2:  null   // getName->N:  null   // ofs = -1 ord = 0 addr = 4
Label513:
	aload 21
	bipush 3
	aconst_null 
	ldc literal_65:"s"
	invokevirtual_short .virtual_20 // idx=20 pc=4
	aload 21
	invokevirtual_short .virtual_19 // idx=19 pc=1
	pop 
	goto_w Label398
Label522:
	aload_0_getfield .field_0_   // get_name_1:  .field_0_   // get_name_2:  .field_0_   // get_Name:    .field_0_   // getName->1:  null   // getName->2:  null   // getName->N:  null   // ofs = -1 ord = 0 addr = 0
	bipush 4
	if_icmpeq Label528
	aload_0_getfield .field_0_   // get_name_1:  .field_0_   // get_name_2:  .field_0_   // get_Name:    .field_0_   // getName->1:  null   // getName->2:  null   // getName->N:  null   // ofs = -1 ord = 0 addr = 0
	bipush 6
	if_icmpne Label531
Label528:
	aload 29
	aload 15
	invokenonvirtual_lib .routine_9502 // pc=2
Label531:
	iload 30
	ifeq Label536
	aload 29
	aload 15
	invokenonvirtual_lib .routine_9402 // pc=2
Label536:
	aload 9
	aload 29
	invokenonvirtual_lib .routine_3288 // pc=2
	aload_0_getfield .field_0_   // get_name_1:  .field_0_   // get_name_2:  .field_0_   // get_Name:    .field_0_   // getName->1:  null   // getName->2:  null   // getName->N:  null   // ofs = -1 ord = 0 addr = 0
	tableswitch  :
		
		
		
		
		

Label541:
	invokestatic_lib com.whatsapp.client.App.routine_10054(  ) // App
	invokestatic_lib long currentTimeMillis(  ) // System
	invokenonvirtual_lib .routine_535 // pc=3
	lipush 5596369375448698592
	invokestatic_lib module:WhatsApp-32.class#2.routine_5867(  ) // class#2
	pop 
	goto Label586
Label548:
	lipush 5596369375448698592
	invokestatic_lib module:WhatsApp-32.class#2.routine_5867(  ) // class#2
	pop 
	goto Label586
Label552:
	invokestatic_lib com.whatsapp.client.App.routine_10054(  ) // App
	invokestatic_lib long currentTimeMillis(  ) // System
	invokenonvirtual_lib .routine_535 // pc=3
	lipush -1952900490994291821
	invokestatic_lib module:WhatsApp-32.class#2.routine_5867(  ) // class#2
	pop 
	invokestatic_lib module:WhatsApp-10.class#29.routine_5442(  ) // class#29
	astore 31
	aload 31
	getfield .field_8_8   // get_name_1:  .field_8_8   // get_name_2:  .field_8_8   // get_Name:    .field_8_8   // getName->1:  null   // getName->2:  null   // getName->N:  null   // ofs = -1 ord = 0 addr = 8
	bipush 4
	iand 
	ifne Label586
	aload 31
	dup 
	getfield .field_8_8   // get_name_1:  .field_8_8   // get_name_2:  .field_8_8   // get_Name:    .field_8_8   // getName->1:  null   // getName->2:  null   // getName->N:  null   // ofs = -1 ord = 0 addr = 8
	bipush 4
	ior 
	putfield .field_8_8   // get_name_1:  .field_8_8   // get_name_2:  .field_8_8   // get_Name:    .field_8_8   // getName->1:  null   // getName->2:  null   // getName->N:  null   // ofs = -1 ord = 0 addr = 8
	aload 31
	iconst_0 
	invokenonvirtual_lib .routine_4794 // pc=2
	pop 
	aload 31
	invokenonvirtual_lib .routine_5253 // pc=1
	goto Label586
Label578:
	invokestatic_lib long currentTimeMillis(  ) // System
	lstore 31
	invokestatic_lib com.whatsapp.client.App.routine_10054(  ) // App
	lload 31
	invokenonvirtual_lib .routine_427 // pc=3
	lipush -4120904274618440631
	invokestatic_lib module:WhatsApp-32.class#2.routine_5867(  ) // class#2
	pop 
Label586:
	invokestatic_lib long currentTimeMillis(  ) // System
	lstore 21
	goto_w Label811
Label589:
	getstatic_lib module:WhatsApp-12.class#0.static_156 // class#0
	astore 8
	aload_0_getfield .field_0_   // get_name_1:  .field_0_   // get_name_2:  .field_0_   // get_Name:    .field_0_   // getName->1:  null   // getName->2:  null   // getName->N:  null   // ofs = -1 ord = 0 addr = 0
	bipush 3
	if_icmpne Label605
	aload_0_getfield .field_3_3   // get_name_1:  .field_3_3   // get_name_2:  .field_3_3   // get_Name:    .field_3_3   // getName->1:  null   // getName->2:  null   // getName->N:  null   // ofs = -1 ord = 0 addr = 3
	ifnull Label605
	aload_0_getfield .field_3_3   // get_name_1:  .field_3_3   // get_name_2:  .field_3_3   // get_Name:    .field_3_3   // getName->1:  null   // getName->2:  null   // getName->N:  null   // ofs = -1 ord = 0 addr = 3
	getstatic_lib module:WhatsApp-12.class#0.static_141 // class#0
	invokevirtual boolean containsKey( java.util.Hashtable, java.lang.Object ) // pc=2
	ifeq Label605
	aload_0_getfield .field_3_3   // get_name_1:  .field_3_3   // get_name_2:  .field_3_3   // get_Name:    .field_3_3   // getName->1:  null   // getName->2:  null   // getName->N:  null   // ofs = -1 ord = 0 addr = 3
	getstatic_lib module:WhatsApp-12.class#0.static_141 // class#0
	invokevirtual java.lang.Object get( java.util.Hashtable, java.lang.Object ) // pc=2
	checkcast_lib net.rim.device.api.ui.MenuItem//net.rim.device.api.ui.MenuItem net.rim.device.api.ui.MenuItem net.rim.device.api.ui.MenuItem
	astore 8
Label605:
	invokestatic_lib module:WhatsApp-26.class#11.routine_3571(  ) // class#11
	astore 9
	aload 9
	invokenonvirtual_lib .routine_3069 // pc=1
	astore 10
	aload 10
	getfield .field_0_   // get_name_1:  .field_0_   // get_name_2:  .field_0_   // get_Name:    .field_0_   // getName->1:  null   // getName->2:  null   // getName->N:  null   // ofs = -1 ord = 0 addr = 0
	istore 11
	aload 10
	getfield .field_2_2   // get_name_1:  .field_2_2   // get_name_2:  .field_2_2   // get_Name:    .field_2_2   // getName->1:  null   // getName->2:  null   // getName->N:  null   // ofs = -1 ord = 0 addr = 2
	astore 12
	new_lib net.rim.blackberry.api.browser.URLEncodedPostData//net.rim.blackberry.api.browser.URLEncodedPostData net.rim.blackberry.api.browser.URLEncodedPostData net.rim.blackberry.api.browser.URLEncodedPostData
	dup 
	getstatic_lib module:WhatsApp-12.class#0.static_2 // class#0
	iconst_0 
	invokespecial_lib net.rim.blackberry.api.browser.URLEncodedPostData.<init> // pc=3
	astore 13
	aload 13
	ldc literal_54:"v"
	ldc literal_59:"1"
	invokevirtual append( net.rim.blackberry.api.browser.URLEncodedPostData, java.lang.String, java.lang.String ) // pc=3
	aload 13
	ldc literal_56:"cc"
	iload 11
	invokestatic_lib java.lang.String valueOf( int ) // String
	invokevirtual append( net.rim.blackberry.api.browser.URLEncodedPostData, java.lang.String, java.lang.String ) // pc=3
	aload_0_getfield .field_0_   // get_name_1:  .field_0_   // get_name_2:  .field_0_   // get_Name:    .field_0_   // getName->1:  null   // getName->2:  null   // getName->N:  null   // ofs = -1 ord = 0 addr = 0
	ifne Label637
	aload 13
	ldc literal_70:"clear"
	ldc literal_59:"1"
	invokevirtual append( net.rim.blackberry.api.browser.URLEncodedPostData, java.lang.String, java.lang.String ) // pc=3
Label637:
	aload 13
	ldc literal_57:"me"
	new_lib Object//java.lang.Object java.lang.Object java.lang.Object
	dup 
	invokespecial_lib java.lang.StringBuffer.<init> // pc=1
	bipush 43
	invokestatic_lib java.lang.String valueOf( char ) // String
	invokevirtual java.lang.StringBuffer append( java.lang.StringBuffer, java.lang.String ) // pc=2
	iload 11
	invokestatic_lib java.lang.String valueOf( int ) // String
	invokevirtual java.lang.StringBuffer append( java.lang.StringBuffer, java.lang.String ) // pc=2
	aload 12
	invokevirtual java.lang.StringBuffer append( java.lang.StringBuffer, java.lang.String ) // pc=2
	invokevirtual_short .toString // idx=2 pc=1
	invokevirtual append( net.rim.blackberry.api.browser.URLEncodedPostData, java.lang.String, java.lang.String ) // pc=3
	aload 13
	ldc literal_65:"s"
	aload 8
	invokevirtual append( net.rim.blackberry.api.browser.URLEncodedPostData, java.lang.String, java.lang.String ) // pc=3
	aload 13
	invokevirtual byte[] getBytes( net.rim.blackberry.api.browser.URLEncodedPostData ) // pc=1
	astore 14
	aconst_null 
	astore 13
	aload_7 
	bipush 3
	iconst_1 
	invokestatic_lib javax.microedition.io.Connection open( java.lang.String, int, boolean ) // Connector
	checkcast_lib net.rim.device.api.util.SimpleSortingVector//net.rim.device.api.util.SimpleSortingVector net.rim.device.api.util.SimpleSortingVector net.rim.device.api.util.SimpleSortingVector
	astore_1 
	aload_1 
	getstatic_lib module:WhatsApp-12.class#0.static_55 // class#0
	aload_5 
	invokeinterface interfacemethodref_5 // pc=3 guess=3
	aload_1 
	getstatic_lib module:WhatsApp-12.class#0.static_58 // class#0
	getstatic_lib module:WhatsApp-12.class#0.static_59 // class#0
	invokeinterface interfacemethodref_5 // pc=3 guess=3
	aload_1 
	getstatic_lib module:WhatsApp-12.class#0.static_53 // class#0
	getstatic_lib module:WhatsApp-12.class#0.static_54 // class#0
	invokeinterface interfacemethodref_5 // pc=3 guess=3
	aload_1 
	ldc literal_63:"POST"
	invokeinterface interfacemethodref_6 // pc=2 guess=4
	aload 14
	ifnull Label687
	aload 14
	arraylength 
	goto Label688
Label687:
	iconst_0 
Label688:
	istore 15
	aload_1 
	getstatic_lib module:WhatsApp-12.class#0.static_52 // class#0
	iload 15
	invokestatic_lib java.lang.String toString( int ) // Integer
	invokeinterface interfacemethodref_5 // pc=3 guess=3
	aload_1 
	invokeinterface interfacemethodref_7 // pc=1 guess=5
	astore_4 
	aload_4 
	aload 14
	invokevirtual write( java.io.OutputStream, byte[] ) // pc=2
	aload_4 
	invokevirtual flush( java.io.OutputStream ) // pc=1
	aconst_null 
	astore 14
	aload_1 
	invokeinterface interfacemethodref_8 // pc=1 guess=6
	istore 16
	iload 16
	sipush 200
	if_icmpeq Label711
	goto_w Label769
Label711:
	aload 9
	invokenonvirtual_lib .routine_2951 // pc=1
	invokestatic_lib java.lang.Object expandGroup( java.lang.Object ) // ObjectGroup
	checkcast_lib com.whatsapp.client.ApplicationHashData//module:WhatsApp.class#9 module:WhatsApp.class#9 module:WhatsApp.class#9
	astore 17
	aload 17
	invokestatic_lib long currentTimeMillis(  ) // System
	invokenonvirtual_lib .routine_2005 // pc=3
	aload 10
	invokestatic_lib createGroup( java.lang.Object ) // ObjectGroup
	aload 9
	aload 17
	invokenonvirtual_lib .routine_3032 // pc=2
	goto Label726
	astore 17
Label726:
	invokestatic_lib module:WhatsApp-13.class#5.routine_9622(  ) // class#5
	astore 17
	aload 17
	getfield .field_0_   // get_name_1:  .field_0_   // get_name_2:  .field_0_   // get_Name:    .field_0_   // getName->1:  null   // getName->2:  null   // getName->N:  null   // ofs = -1 ord = 0 addr = 0
	astore 18
	aload 17
	aload 8
	putfield .field_4_4   // get_name_1:  .field_4_4   // get_name_2:  .field_4_4   // get_Name:    .field_4_4   // getName->1:  null   // getName->2:  null   // getName->N:  null   // ofs = -1 ord = 0 addr = 4
	aload_0_getfield .field_0_   // get_name_1:  .field_0_   // get_name_2:  .field_0_   // get_Name:    .field_0_   // getName->1:  null   // getName->2:  null   // getName->N:  null   // ofs = -1 ord = 0 addr = 0
Label736:
	new_lib //module:WhatsApp-13.class#4 module:WhatsApp-13.class#4 module:WhatsApp-13.class#4
	dup 
	sipush 605
	invokestatic_lib module:WhatsApp-27.class#28.routine_5758(  ) // class#28
	iconst_0 
	i2l 
	invokespecial_lib .routine_9334 // pc=4
	astore 19
	aload 18
	aload 12
	aload 19
	invokevirtual java.lang.Object put( java.util.Hashtable, java.lang.Object, java.lang.Object ) // pc=3
	pop 
	lipush -8471386065305298206
	invokestatic_lib module:WhatsApp-32.class#2.routine_5867(  ) // class#2
	pop 
	goto_w Label809
Label753:
	new_lib //module:WhatsApp-13.class#4 module:WhatsApp-13.class#4 module:WhatsApp-13.class#4
	dup 
	aload 8
	iconst_0 
	i2l 
	invokespecial_lib .routine_9334 // pc=4
	astore 19
	aload 18
	aload 12
	aload 19
	invokevirtual java.lang.Object put( java.util.Hashtable, java.lang.Object, java.lang.Object ) // pc=3
	pop 
	lipush 1862839069620204345
	invokestatic_lib module:WhatsApp-32.class#2.routine_5867(  ) // class#2
	pop 
	goto Label809
Label769:
	aload_0 
	iload 16
	invokespecial com.whatsapp.client.SyncManager$SyncRunner.routine_4233 // pc=2
	aload_3 
	ifnull Label780
	aload_3 
	invokevirtual close( java.io.InputStream ) // pc=1
	goto Label778
	astore 36
Label778:
	aconst_null 
	astore_3 
Label780:
	aload_4 
	ifnull Label788
	aload_4 
	invokevirtual close( java.io.OutputStream ) // pc=1
	goto Label786
	astore 36
Label786:
	aconst_null 
	astore_4 
Label788:
	aload_1 
	ifnull Label796
	aload_1 
	invokeinterface interfacemethodref_4 // pc=1 guess=2
	goto Label794
	astore 36
Label794:
	aconst_null 
	astore_1 
Label796:
	aload_2 
	ifnull Label804
	aload_2 
	invokeinterface interfacemethodref_4 // pc=1 guess=2
	goto Label802
	astore 36
Label802:
	aconst_null 
	astore_2 
Label804:
	bipush -1
	putstatic_lib module:WhatsApp-29.class#2.static_8 // class#2
	getstatic_lib module:WhatsApp-29.class#2.static_7 // class#2
	invokenonvirtual_lib .routine_8184 // pc=1
	return 
Label809:
	invokestatic_lib long currentTimeMillis(  ) // System
	lstore 17
Label811:
	aload_3 
	ifnull Label819
	aload_3 
	invokevirtual close( java.io.InputStream ) // pc=1
	goto Label817
	astore 36
Label817:
	aconst_null 
	astore_3 
Label819:
	aload_4 
	ifnull Label827
	aload_4 
	invokevirtual close( java.io.OutputStream ) // pc=1
	goto Label825
	astore 36
Label825:
	aconst_null 
	astore_4 
Label827:
	aload_1 
	ifnull Label835
	aload_1 
	invokeinterface interfacemethodref_4 // pc=1 guess=2
	goto Label833
	astore 36
Label833:
	aconst_null 
	astore_1 
Label835:
	aload_2 
	ifnull Label843
	aload_2 
	invokeinterface interfacemethodref_4 // pc=1 guess=2
	goto Label841
	astore 36
Label841:
	aconst_null 
	astore_2 
Label843:
	bipush -1
	putstatic_lib module:WhatsApp-29.class#2.static_8 // class#2
	getstatic_lib module:WhatsApp-29.class#2.static_7 // class#2
	invokenonvirtual_lib .routine_8184 // pc=1
	goto_w Label940
	astore_6 
	new_lib java.util.Hashtable//java.util.Hashtable java.util.Hashtable java.util.Hashtable
	dup 
	invokespecial_lib java.util.Hashtable.<init> // pc=1
	astore_7 
	aload_7 
	getstatic_lib module:WhatsApp-12.class#0.static_138 // class#0
	aload_6 
	invokevirtual java.lang.Object put( java.util.Hashtable, java.lang.Object, java.lang.Object ) // pc=3
	pop 
	aload_0_getfield .field_7_7   // get_name_1:  .field_7_7   // get_name_2:  .field_7_7   // get_Name:    .field_7_7   // getName->1:  null   // getName->2:  null   // getName->N:  null   // ofs = -1 ord = 0 addr = 7
	aload_0_getfield .field_0_   // get_name_1:  .field_0_   // get_name_2:  .field_0_   // get_Name:    .field_0_   // getName->1:  null   // getName->2:  null   // getName->N:  null   // ofs = -1 ord = 0 addr = 0
	aload_0_getfield .field_3_3   // get_name_1:  .field_3_3   // get_name_2:  .field_3_3   // get_Name:    .field_3_3   // getName->1:  null   // getName->2:  null   // getName->N:  null   // ofs = -1 ord = 0 addr = 3
	aload_7 
	invokespecial_lib .routine_9173 // pc=4
	aload_3 
	ifnull Label871
	aload_3 
	invokevirtual close( java.io.InputStream ) // pc=1
	goto Label869
	astore 36
Label869:
	aconst_null 
	astore_3 
Label871:
	aload_4 
	ifnull Label879
	aload_4 
	invokevirtual close( java.io.OutputStream ) // pc=1
	goto Label877
	astore 36
Label877:
	aconst_null 
	astore_4 
Label879:
	aload_1 
	ifnull Label887
	aload_1 
	invokeinterface interfacemethodref_4 // pc=1 guess=2
	goto Label885
	astore 36
Label885:
	aconst_null 
	astore_1 
Label887:
	aload_2 
	ifnull Label895
	aload_2 
	invokeinterface interfacemethodref_4 // pc=1 guess=2
	goto Label893
	astore 36
Label893:
	aconst_null 
	astore_2 
Label895:
	bipush -1
	putstatic_lib module:WhatsApp-29.class#2.static_8 // class#2
	getstatic_lib module:WhatsApp-29.class#2.static_7 // class#2
	invokenonvirtual_lib .routine_8184 // pc=1
	goto Label940
	astore 34
	aload_3 
	ifnull Label909
	aload_3 
	invokevirtual close( java.io.InputStream ) // pc=1
	goto Label907
	astore 36
Label907:
	aconst_null 
	astore_3 
Label909:
	aload_4 
	ifnull Label917
	aload_4 
	invokevirtual close( java.io.OutputStream ) // pc=1
	goto Label915
	astore 36
Label915:
	aconst_null 
	astore_4 
Label917:
	aload_1 
	ifnull Label925
	aload_1 
	invokeinterface interfacemethodref_4 // pc=1 guess=2
	goto Label923
	astore 36
Label923:
	aconst_null 
	astore_1 
Label925:
	aload_2 
	ifnull Label933
	aload_2 
	invokeinterface interfacemethodref_4 // pc=1 guess=2
	goto Label931
	astore 36
Label931:
	aconst_null 
	astore_2 
Label933:
	bipush -1
	putstatic_lib module:WhatsApp-29.class#2.static_8 // class#2
	getstatic_lib module:WhatsApp-29.class#2.static_7 // class#2
	invokenonvirtual_lib .routine_8184 // pc=1
	aload 34
	athrow 
	astore_1 
Label940:
	return 
	}

}
