// #######################################################
// Decompiled by   : coddec 
// Module          : WhatsApp-12.cod
// Module version  : 2.7.6550
// Class ID        : 41
// ########################################################


package com.whatsapp.client;


abstract final class ContactStatuses extends Object

{

	// @@@@@@@@@@@@@ Fields 

	// @@@@@@@@@@@@@ Static routines 

<init>( com.whatsapp.client.ContactStatuses ); // address: 0
	{
	enter 
	aload_0 
	invokespecial_lib java.lang.Object.<init> // pc=1
	aload_0 
	new_lib java.util.Hashtable//java.util.Hashtable java.util.Hashtable java.util.Hashtable
	dup 
	bipush 25
	invokespecial_lib java.util.Hashtable.<init> // pc=2
	putfield .field_0_   // get_name_1:  .field_0_   // get_name_2:  .field_0_   // get_Name:    .field_0_   // getName->1:  null   // getName->2:  null   // getName->N:  null   // ofs = -1 ord = 0 addr = 0
	aload_0 
	new_lib java.util.Hashtable//java.util.Hashtable java.util.Hashtable java.util.Hashtable
	dup 
	bipush 25
	invokespecial_lib java.util.Hashtable.<init> // pc=2
	putfield .field_1_1   // get_name_1:  .field_1_1   // get_name_2:  .field_1_1   // get_Name:    .field_1_1   // getName->1:  null   // getName->2:  null   // getName->N:  null   // ofs = -1 ord = 0 addr = 1
	aload_0 
	new_lib java.util.Hashtable//java.util.Hashtable java.util.Hashtable java.util.Hashtable
	dup 
	bipush 100
	invokespecial_lib java.util.Hashtable.<init> // pc=2
	putfield .field_2_2   // get_name_1:  .field_2_2   // get_name_2:  .field_2_2   // get_Name:    .field_2_2   // getName->1:  null   // getName->2:  null   // getName->N:  null   // ofs = -1 ord = 0 addr = 2
	return 
	}


static public final com.whatsapp.client.ContactStatuses getInstance(  ); // address: 0
	{
	enter_narrow 
	invokestatic_lib net.rim.device.api.system.RuntimeStore getRuntimeStore(  ) // RuntimeStore
	astore_0 
	aload_0 
	lipush 179229773001380596
	invokevirtual java.lang.Object get( net.rim.device.api.system.RuntimeStore, long ) // pc=3
	checkcast ContactStatuses
	astore_1 
	aload_1 
	areturn 
	}


static public final java.util.Hashtable getStatuses(  ); // address: 0
	{
	enter_narrow 
	invokestatic_lib net.rim.device.api.system.RuntimeStore getRuntimeStore(  ) // RuntimeStore
	astore_0 
	aload_0 
	lipush 179229773001380596
	invokevirtual java.lang.Object get( net.rim.device.api.system.RuntimeStore, long ) // pc=3
	checkcast ContactStatuses
	astore_1 
	aload_1 
	getfield .field_0_   // get_name_1:  .field_0_   // get_name_2:  .field_0_   // get_Name:    .field_0_   // getName->1:  null   // getName->2:  null   // getName->N:  null   // ofs = -1 ord = 0 addr = 0
	areturn 
	}

	// @@@@@@@@@@@@@ Non-virtual routines 

public final put( com.whatsapp.client.ContactStatuses, java.lang.String, com.whatsapp.client.ContactStatusDetails ); // address: 0
	{
	enter_narrow 
	aload_0_getfield .field_0_   // get_name_1:  .field_0_   // get_name_2:  .field_0_   // get_Name:    .field_0_   // getName->1:  null   // getName->2:  null   // getName->N:  null   // ofs = -1 ord = 0 addr = 0
	aload_1 
	aload_2 
	invokevirtual java.lang.Object put( java.util.Hashtable, java.lang.Object, java.lang.Object ) // pc=3
	pop 
	aload_2 
	getfield .field_3_3   // get_name_1:  .field_3_3   // get_name_2:  .field_3_3   // get_Name:    .field_3_3   // getName->1:  null   // getName->2:  null   // getName->N:  null   // ofs = -1 ord = 0 addr = 3
	ifnull Label15
	aload_0_getfield .field_1_1   // get_name_1:  .field_1_1   // get_name_2:  .field_1_1   // get_Name:    .field_1_1   // getName->1:  null   // getName->2:  null   // getName->N:  null   // ofs = -1 ord = 0 addr = 1
	aload_2 
	getfield .field_3_3   // get_name_1:  .field_3_3   // get_name_2:  .field_3_3   // get_Name:    .field_3_3   // getName->1:  null   // getName->2:  null   // getName->N:  null   // ofs = -1 ord = 0 addr = 3
	aload_2 
	invokevirtual java.lang.Object put( java.util.Hashtable, java.lang.Object, java.lang.Object ) // pc=3
	pop 
Label15:
	return 
	}


public final boolean putDetails( com.whatsapp.client.ContactStatuses, java.lang.String, long, java.lang.String, java.lang.String ); // address: 0
	{
	enter 
	aload_0_getfield .field_0_   // get_name_1:  .field_0_   // get_name_2:  .field_0_   // get_Name:    .field_0_   // getName->1:  null   // getName->2:  null   // getName->N:  null   // ofs = -1 ord = 0 addr = 0
	aload_5 
	invokevirtual java.lang.Object get( java.util.Hashtable, java.lang.Object ) // pc=2
	checkcast ContactStatusDetails
	astore_6 
	aload_6 
	ifnull Label19
	aload_6 
	aload_1 
	putfield .field_0_   // get_name_1:  .field_0_   // get_name_2:  .field_0_   // get_Name:    .field_0_   // getName->1:  null   // getName->2:  null   // getName->N:  null   // ofs = -1 ord = 0 addr = 0
	aload_6 
	lload 2
	invokenonvirtual com.whatsapp.client.ContactStatusDetails.setTimeSinceSet // pc=3
	aload_6 
	aload_4 
	putfield .field_3_3   // get_name_1:  .field_3_3   // get_name_2:  .field_3_3   // get_Name:    .field_3_3   // getName->1:  null   // getName->2:  null   // getName->N:  null   // ofs = -1 ord = 0 addr = 3
	iconst_0 
	ireturn 
Label19:
	new ContactStatusDetails
	dup 
	aload_1 
	lload 2
	aload_4 
	aload_5 
	invokespecial com.whatsapp.client.ContactStatusDetails.<init> // pc=6
	astore_6 
	aload_0 
	aload_5 
	aload_6 
	invokenonvirtual com.whatsapp.client.ContactStatuses.put // pc=3
	iconst_1 
	ireturn 
	}


public final remove( com.whatsapp.client.ContactStatuses, com.whatsapp.client.ContactStatusDetails ); // address: 0
	{
	enter_narrow 
	aload_1 
	getfield .field_4_4   // get_name_1:  .field_4_4   // get_name_2:  .field_4_4   // get_Name:    .field_4_4   // getName->1:  null   // getName->2:  null   // getName->N:  null   // ofs = -1 ord = 0 addr = 4
	ifnull Label9
	aload_0_getfield .field_0_   // get_name_1:  .field_0_   // get_name_2:  .field_0_   // get_Name:    .field_0_   // getName->1:  null   // getName->2:  null   // getName->N:  null   // ofs = -1 ord = 0 addr = 0
	aload_1 
	getfield .field_4_4   // get_name_1:  .field_4_4   // get_name_2:  .field_4_4   // get_Name:    .field_4_4   // getName->1:  null   // getName->2:  null   // getName->N:  null   // ofs = -1 ord = 0 addr = 4
	invokevirtual java.lang.Object remove( java.util.Hashtable, java.lang.Object ) // pc=2
	pop 
Label9:
	aload_1 
	getfield .field_3_3   // get_name_1:  .field_3_3   // get_name_2:  .field_3_3   // get_Name:    .field_3_3   // getName->1:  null   // getName->2:  null   // getName->N:  null   // ofs = -1 ord = 0 addr = 3
	ifnull Label17
	aload_0_getfield .field_1_1   // get_name_1:  .field_1_1   // get_name_2:  .field_1_1   // get_Name:    .field_1_1   // getName->1:  null   // getName->2:  null   // getName->N:  null   // ofs = -1 ord = 0 addr = 1
	aload_1 
	getfield .field_3_3   // get_name_1:  .field_3_3   // get_name_2:  .field_3_3   // get_Name:    .field_3_3   // getName->1:  null   // getName->2:  null   // getName->N:  null   // ofs = -1 ord = 0 addr = 3
	invokevirtual java.lang.Object remove( java.util.Hashtable, java.lang.Object ) // pc=2
	pop 
Label17:
	return 
	}


public final putHoldout( com.whatsapp.client.ContactStatuses, java.lang.String, java.lang.String ); // address: 0
	{
	enter_narrow 
	aload_0_getfield .field_2_2   // get_name_1:  .field_2_2   // get_name_2:  .field_2_2   // get_Name:    .field_2_2   // getName->1:  null   // getName->2:  null   // getName->N:  null   // ofs = -1 ord = 0 addr = 2
	aload_1 
	aload_2 
	invokevirtual java.lang.Object put( java.util.Hashtable, java.lang.Object, java.lang.Object ) // pc=3
	pop 
	return 
	}

}
