// #######################################################
// Decompiled by   : coddec 
// Module          : WhatsApp-37.cod
// Module version  : 2.7.3204
// Class ID        : 3
// ########################################################


package com.whatsapp.field;


abstract final class ChatBorder$BitmapCacheKey extends Object

{

	// @@@@@@@@@@@@@ Fields 
	private final boolean /*boolean*/  field_52896 ; // ofs = 52896 addr = 0)
	private final int /*int*/  field_52900 ; // ofs = 52900 addr = 0)
	private final int /*int*/  field_52904 ; // ofs = 52904 addr = 0)
	private final int /*int*/  field_52908 ; // ofs = 52908 addr = 0)
	private int /*int*/  field_52912 ; // ofs = 52912 addr = 0)

	// @@@@@@@@@@@@@ Static routines 

public <init>( com.whatsapp.field.ChatBorder$BitmapCacheKey, boolean, int, int, int, int ); // address: 0
	{
	enter 
	aload_0 
	invokespecial_lib java.lang.Object.<init> // pc=1
	aload_0 
	iload_1 
	putfield .field_0_   // get_name_1:  .field_0_   // get_name_2:  .field_0_   // get_Name:    .field_0_   // getName->1:  null   // getName->2:  null   // getName->N:  null   // ofs = -1 ord = 0 addr = 0
	aload_0 
	iload_2 
	putfield .field_1_1   // get_name_1:  .field_1_1   // get_name_2:  .field_1_1   // get_Name:    .field_1_1   // getName->1:  null   // getName->2:  null   // getName->N:  null   // ofs = -1 ord = 0 addr = 1
	aload_0 
	iload_3 
	putfield .field_2_2   // get_name_1:  .field_2_2   // get_name_2:  .field_2_2   // get_Name:    .field_2_2   // getName->1:  null   // getName->2:  null   // getName->N:  null   // ofs = -1 ord = 0 addr = 2
	aload_0 
	iload_4 
	putfield .field_3_3   // get_name_1:  .field_3_3   // get_name_2:  .field_3_3   // get_Name:    .field_3_3   // getName->1:  null   // getName->2:  null   // getName->N:  null   // ofs = -1 ord = 0 addr = 3
	aload_0 
	iload_5 
	putfield .field_4_4   // get_name_1:  .field_4_4   // get_name_2:  .field_4_4   // get_Name:    .field_4_4   // getName->1:  null   // getName->2:  null   // getName->N:  null   // ofs = -1 ord = 0 addr = 4
	return 
	}

	// @@@@@@@@@@@@@ Non-virtual routines 

public final int getFieldHeight( com.whatsapp.field.ChatBorder$BitmapCacheKey ); // address: 0
	{
	ireturn_field .field_4_4   // get_name_1:  .field_4_4   // get_name_2:  .field_4_4   // get_Name:    .field_4_4   // getName->1:  null   // getName->2:  null   // getName->N:  null   // ofs = -1 ord = 0 addr = 4
	}


public final setFieldHeight( com.whatsapp.field.ChatBorder$BitmapCacheKey, int ); // address: 0
	{
	putfield_return .field_4_4   // get_name_1:  .field_4_4   // get_name_2:  .field_4_4   // get_Name:    .field_4_4   // getName->1:  null   // getName->2:  null   // getName->N:  null   // ofs = -1 ord = 0 addr = 4
	}

	// @@@@@@@@@@@@@ Virtual routines 

public final int hashCode( com.whatsapp.field.ChatBorder$BitmapCacheKey ); // address: 0
	{
	enter_narrow 
	bipush 31
	istore_1 
	iconst_1 
	istore_2 
	bipush 31
	iload_2 
	imul 
	aload_0_getfield .field_3_3   // get_name_1:  .field_3_3   // get_name_2:  .field_3_3   // get_Name:    .field_3_3   // getName->1:  null   // getName->2:  null   // getName->N:  null   // ofs = -1 ord = 0 addr = 3
	iadd 
	istore_2 
	bipush 31
	iload_2 
	imul 
	aload_0_getfield .field_2_2   // get_name_1:  .field_2_2   // get_name_2:  .field_2_2   // get_Name:    .field_2_2   // getName->1:  null   // getName->2:  null   // getName->N:  null   // ofs = -1 ord = 0 addr = 2
	iadd 
	istore_2 
	bipush 31
	iload_2 
	imul 
	aload_0_getfield .field_4_4   // get_name_1:  .field_4_4   // get_name_2:  .field_4_4   // get_Name:    .field_4_4   // getName->1:  null   // getName->2:  null   // getName->N:  null   // ofs = -1 ord = 0 addr = 4
	iadd 
	istore_2 
	bipush 31
	iload_2 
	imul 
	aload_0_getfield .field_0_   // get_name_1:  .field_0_   // get_name_2:  .field_0_   // get_Name:    .field_0_   // getName->1:  null   // getName->2:  null   // getName->N:  null   // ofs = -1 ord = 0 addr = 0
	ifeq Label30
	sipush 1231
	goto Label31
Label30:
	sipush 1237
Label31:
	iadd 
	istore_2 
	bipush 31
	iload_2 
	imul 
	aload_0_getfield .field_1_1   // get_name_1:  .field_1_1   // get_name_2:  .field_1_1   // get_Name:    .field_1_1   // getName->1:  null   // getName->2:  null   // getName->N:  null   // ofs = -1 ord = 0 addr = 1
	iadd 
	istore_2 
	iload_2 
	ireturn 
	}


public final boolean equals( com.whatsapp.field.ChatBorder$BitmapCacheKey, java.lang.Object ); // address: 0
	{
	enter_narrow 
	aload_0 
	aload_1 
	if_acmpne Label6
	iconst_1 
	ireturn 
Label6:
	aload_1 
	ifnonnull Label10
	iconst_0 
	ireturn 
Label10:
	aload_0 
	invokenonvirtual_lib java.lang.Object.getClass // pc=1
	aload_1 
	invokenonvirtual_lib java.lang.Object.getClass // pc=1
	if_acmpeq Label17
	iconst_0 
	ireturn 
Label17:
	aload_1 
	checkcast ChatBorder$BitmapCacheKey
	astore_2 
	aload_0_getfield .field_3_3   // get_name_1:  .field_3_3   // get_name_2:  .field_3_3   // get_Name:    .field_3_3   // getName->1:  null   // getName->2:  null   // getName->N:  null   // ofs = -1 ord = 0 addr = 3
	aload_2 
	getfield .field_3_3   // get_name_1:  .field_3_3   // get_name_2:  .field_3_3   // get_Name:    .field_3_3   // getName->1:  null   // getName->2:  null   // getName->N:  null   // ofs = -1 ord = 0 addr = 3
	if_icmpeq Label26
	iconst_0 
	ireturn 
Label26:
	aload_0_getfield .field_2_2   // get_name_1:  .field_2_2   // get_name_2:  .field_2_2   // get_Name:    .field_2_2   // getName->1:  null   // getName->2:  null   // getName->N:  null   // ofs = -1 ord = 0 addr = 2
	aload_2 
	getfield .field_2_2   // get_name_1:  .field_2_2   // get_name_2:  .field_2_2   // get_Name:    .field_2_2   // getName->1:  null   // getName->2:  null   // getName->N:  null   // ofs = -1 ord = 0 addr = 2
	if_icmpeq Label32
	iconst_0 
	ireturn 
Label32:
	aload_0_getfield .field_4_4   // get_name_1:  .field_4_4   // get_name_2:  .field_4_4   // get_Name:    .field_4_4   // getName->1:  null   // getName->2:  null   // getName->N:  null   // ofs = -1 ord = 0 addr = 4
	aload_2 
	getfield .field_4_4   // get_name_1:  .field_4_4   // get_name_2:  .field_4_4   // get_Name:    .field_4_4   // getName->1:  null   // getName->2:  null   // getName->N:  null   // ofs = -1 ord = 0 addr = 4
	if_icmpeq Label38
	iconst_0 
	ireturn 
Label38:
	aload_0_getfield .field_0_   // get_name_1:  .field_0_   // get_name_2:  .field_0_   // get_Name:    .field_0_   // getName->1:  null   // getName->2:  null   // getName->N:  null   // ofs = -1 ord = 0 addr = 0
	aload_2 
	getfield .field_0_   // get_name_1:  .field_0_   // get_name_2:  .field_0_   // get_Name:    .field_0_   // getName->1:  null   // getName->2:  null   // getName->N:  null   // ofs = -1 ord = 0 addr = 0
	if_icmpeq Label44
	iconst_0 
	ireturn 
Label44:
	aload_0_getfield .field_1_1   // get_name_1:  .field_1_1   // get_name_2:  .field_1_1   // get_Name:    .field_1_1   // getName->1:  null   // getName->2:  null   // getName->N:  null   // ofs = -1 ord = 0 addr = 1
	aload_2 
	getfield .field_1_1   // get_name_1:  .field_1_1   // get_name_2:  .field_1_1   // get_Name:    .field_1_1   // getName->1:  null   // getName->2:  null   // getName->N:  null   // ofs = -1 ord = 0 addr = 1
	if_icmpeq Label50
	iconst_0 
	ireturn 
Label50:
	iconst_1 
	ireturn 
	}

}
