// #######################################################
// Decompiled by   : coddec 
// Module          : WhatsApp-37.cod
// Module version  : 2.7.3204
// Class ID        : 11
// ########################################################


package com.whatsapp.field;


abstract final class MediaFullBrowserField$1$1 extends Object
implements Runnable

{

	// @@@@@@@@@@@@@ Fields 
	private final java.util.Hashtable /*java.util.Hashtable*/  field_53400 ; // ofs = 53400 addr = 0)
	private final java.util.Hashtable /*java.util.Hashtable[]*/  field_53404 ; // ofs = 53404 addr = 0)
	private final com.whatsapp.field.MediaFullBrowserField$1 /*com.whatsapp.field.MediaFullBrowserField$1*/  field_53408 ; // ofs = 53408 addr = 0)

	// @@@@@@@@@@@@@ Static routines 

<init>( com.whatsapp.field.MediaFullBrowserField$1$1, com.whatsapp.field.MediaFullBrowserField$1, java.util.Hashtable, java.util.Hashtable[] ); // address: 0
	{
	enter 
	aload_0 
	invokespecial_lib java.lang.Object.<init> // pc=1
	aload_0 
	aload_1 
	putfield .field_2_2   // get_name_1:  .field_2_2   // get_name_2:  .field_2_2   // get_Name:    .field_2_2   // getName->1:  null   // getName->2:  null   // getName->N:  null   // ofs = -1 ord = 0 addr = 2
	aload_0 
	aload_2 
	putfield .field_0_   // get_name_1:  .field_0_   // get_name_2:  .field_0_   // get_Name:    .field_0_   // getName->1:  null   // getName->2:  null   // getName->N:  null   // ofs = -1 ord = 0 addr = 0
	aload_0 
	aload_3 
	putfield .field_1_1   // get_name_1:  .field_1_1   // get_name_2:  .field_1_1   // get_Name:    .field_1_1   // getName->1:  null   // getName->2:  null   // getName->N:  null   // ofs = -1 ord = 0 addr = 1
	return 
	}

	// @@@@@@@@@@@@@ Virtual routines 

public final run( com.whatsapp.field.MediaFullBrowserField$1$1 ); // address: 0
	{
	enter_narrow 
	aload_0_getfield .field_2_2   // get_name_1:  .field_2_2   // get_name_2:  .field_2_2   // get_Name:    .field_2_2   // getName->1:  null   // getName->2:  null   // getName->N:  null   // ofs = -1 ord = 0 addr = 2
	getfield .field_0_   // get_name_1:  .field_0_   // get_name_2:  .field_0_   // get_Name:    .field_0_   // getName->1:  null   // getName->2:  null   // getName->N:  null   // ofs = -1 ord = 0 addr = 0
	invokevirtual net.rim.device.api.ui.Screen getScreen( net.rim.device.api.ui.Field ) // pc=1
	invokevirtual boolean isDisplayed( net.rim.device.api.ui.Screen ) // pc=1
	ifne Label12
	aload_0_getfield .field_2_2   // get_name_1:  .field_2_2   // get_name_2:  .field_2_2   // get_Name:    .field_2_2   // getName->1:  null   // getName->2:  null   // getName->N:  null   // ofs = -1 ord = 0 addr = 2
	getfield .field_0_   // get_name_1:  .field_0_   // get_name_2:  .field_0_   // get_Name:    .field_0_   // getName->1:  null   // getName->2:  null   // getName->N:  null   // ofs = -1 ord = 0 addr = 0
	getfield _worklist   // get_name_1:  _worklist   // get_name_2:  _worklist   // get_Name:    _worklist   // getName->1:  _worklist   // getName->2:  _worklist   // getName->N:  _worklist   // ofs = -1 ord = 2 addr = -1
	invokevirtual clear( java.util.Hashtable ) // pc=1
	aload_0_getfield .field_0_   // get_name_1:  .field_0_   // get_name_2:  .field_0_   // get_Name:    .field_0_   // getName->1:  null   // getName->2:  null   // getName->N:  null   // ofs = -1 ord = 0 addr = 0
	invokevirtual clear( java.util.Hashtable ) // pc=1
Label12:
	aload_0_getfield .field_2_2   // get_name_1:  .field_2_2   // get_name_2:  .field_2_2   // get_Name:    .field_2_2   // getName->1:  null   // getName->2:  null   // getName->N:  null   // ofs = -1 ord = 0 addr = 2
	getfield .field_0_   // get_name_1:  .field_0_   // get_name_2:  .field_0_   // get_Name:    .field_0_   // getName->1:  null   // getName->2:  null   // getName->N:  null   // ofs = -1 ord = 0 addr = 0
	getfield _worklist   // get_name_1:  _worklist   // get_name_2:  _worklist   // get_Name:    _worklist   // getName->1:  _worklist   // getName->2:  _worklist   // getName->N:  _worklist   // ofs = -1 ord = 2 addr = -1
	invokevirtual boolean isEmpty( java.util.Hashtable ) // pc=1
	ifeq Label24
	aload_0_getfield .field_0_   // get_name_1:  .field_0_   // get_name_2:  .field_0_   // get_Name:    .field_0_   // getName->1:  null   // getName->2:  null   // getName->N:  null   // ofs = -1 ord = 0 addr = 0
	invokevirtual boolean isEmpty( java.util.Hashtable ) // pc=1
	ifeq Label24
	aload_0_getfield .field_2_2   // get_name_1:  .field_2_2   // get_name_2:  .field_2_2   // get_Name:    .field_2_2   // getName->1:  null   // getName->2:  null   // getName->N:  null   // ofs = -1 ord = 0 addr = 2
	getfield .field_0_   // get_name_1:  .field_0_   // get_name_2:  .field_0_   // get_Name:    .field_0_   // getName->1:  null   // getName->2:  null   // getName->N:  null   // ofs = -1 ord = 0 addr = 0
	iconst_0 
	putfield _workerRunning   // get_name_1:  _workerRunning   // get_name_2:  _workerRunning   // get_Name:    _workerRunning   // getName->1:  _workerRunning   // getName->2:  _workerRunning   // getName->N:  _workerRunning   // ofs = -1 ord = 3 addr = -1
Label24:
	aload_0_getfield .field_1_1   // get_name_1:  .field_1_1   // get_name_2:  .field_1_1   // get_Name:    .field_1_1   // getName->1:  null   // getName->2:  null   // getName->N:  null   // ofs = -1 ord = 0 addr = 1
	iconst_0 
	aload_0_getfield .field_2_2   // get_name_1:  .field_2_2   // get_name_2:  .field_2_2   // get_Name:    .field_2_2   // getName->1:  null   // getName->2:  null   // getName->N:  null   // ofs = -1 ord = 0 addr = 2
	getfield .field_0_   // get_name_1:  .field_0_   // get_name_2:  .field_0_   // get_Name:    .field_0_   // getName->1:  null   // getName->2:  null   // getName->N:  null   // ofs = -1 ord = 0 addr = 0
	getfield _worklist   // get_name_1:  _worklist   // get_name_2:  _worklist   // get_Name:    _worklist   // getName->1:  _worklist   // getName->2:  _worklist   // getName->N:  _worklist   // ofs = -1 ord = 2 addr = -1
	aastore 
	aload_0_getfield .field_2_2   // get_name_1:  .field_2_2   // get_name_2:  .field_2_2   // get_Name:    .field_2_2   // getName->1:  null   // getName->2:  null   // getName->N:  null   // ofs = -1 ord = 0 addr = 2
	getfield .field_0_   // get_name_1:  .field_0_   // get_name_2:  .field_0_   // get_Name:    .field_0_   // getName->1:  null   // getName->2:  null   // getName->N:  null   // ofs = -1 ord = 0 addr = 0
	new_lib java.util.Hashtable//java.util.Hashtable java.util.Hashtable java.util.Hashtable
	dup 
	invokespecial_lib java.util.Hashtable.<init> // pc=1
	putfield _worklist   // get_name_1:  _worklist   // get_name_2:  _worklist   // get_Name:    _worklist   // getName->1:  _worklist   // getName->2:  _worklist   // getName->N:  _worklist   // ofs = -1 ord = 2 addr = -1
	return 
	}

}
