// #######################################################
// Decompiled by   : coddec 
// Module          : WhatsApp-18.cod
// Module version  : 2.7.3204
// Class ID        : 5
// ########################################################


package com.whatsapp.client;


abstract public final class FunXMPPRunner$BBParser extends Object
implements com.whatsapp.client.

{
	// @@@@@@@@@@@@@ Static fields 


	// @@@@@@@@@@@@@ Static routines 

public <init>( com.whatsapp.client.FunXMPPRunner$BBParser ); // address: 0
	{
	jumpspecial_lib <init>( java.lang.Object )
	}


static final <clinit>(  ); // address: 0
	{
	enter 
	synch_static FunXMPPRunner$BBParser
	clinit_wait 
	ldc literal_69:"GMT"
	invokestatic_lib java.util.TimeZone getTimeZone( java.lang.String ) // TimeZone
	putstatic tz // FunXMPPRunner$BBParser
	clinit_return 
	}

	// @@@@@@@@@@@@@ Virtual routines 

public final java.util.Date parse( com.whatsapp.client.FunXMPPRunner$BBParser, java.lang.String ); // address: 0
	{
	enter 
	aload_1 
	stringlength 
	bipush 17
	if_icmpge Label9
	new_lib net.rim.device.api.system.ApplicationDescriptor//net.rim.device.api.system.ApplicationDescriptor net.rim.device.api.system.ApplicationDescriptor net.rim.device.api.system.ApplicationDescriptor
	dup 
	invokespecial_lib java.util.Date.<init> // pc=1
	areturn 
Label9:
	getstatic tz // FunXMPPRunner$BBParser
	invokestatic_lib java.util.Calendar getInstance( java.util.TimeZone ) // Calendar
	astore_2 
	aload_2 
	iconst_1 
	aload_1 
	iconst_0 
	bipush 4
	invokenonvirtual_lib java.lang.String.substring // pc=3
	invokestatic_lib int parseInt( java.lang.String ) // Integer
	invokevirtual set( java.util.Calendar, int, int ) // pc=3
	aload_2 
	bipush 2
	aload_1 
	bipush 4
	bipush 6
	invokenonvirtual_lib java.lang.String.substring // pc=3
	invokestatic_lib int parseInt( java.lang.String ) // Integer
	iconst_1 
	isub 
	invokevirtual set( java.util.Calendar, int, int ) // pc=3
	aload_2 
	bipush 5
	aload_1 
	bipush 6
	bipush 8
	invokenonvirtual_lib java.lang.String.substring // pc=3
	invokestatic_lib int parseInt( java.lang.String ) // Integer
	invokevirtual set( java.util.Calendar, int, int ) // pc=3
	aload_2 
	bipush 11
	aload_1 
	bipush 9
	bipush 11
	invokenonvirtual_lib java.lang.String.substring // pc=3
	invokestatic_lib int parseInt( java.lang.String ) // Integer
	invokevirtual set( java.util.Calendar, int, int ) // pc=3
	aload_2 
	bipush 12
	aload_1 
	bipush 12
	bipush 14
	invokenonvirtual_lib java.lang.String.substring // pc=3
	invokestatic_lib int parseInt( java.lang.String ) // Integer
	invokevirtual set( java.util.Calendar, int, int ) // pc=3
	aload_2 
	bipush 13
	aload_1 
	bipush 15
	bipush 17
	invokenonvirtual_lib java.lang.String.substring // pc=3
	invokestatic_lib int parseInt( java.lang.String ) // Integer
	invokevirtual set( java.util.Calendar, int, int ) // pc=3
	aload_2 
	invokevirtual java.util.Date getTime( java.util.Calendar ) // pc=1
	areturn 
	}

}
