// #######################################################
// Decompiled by   : coddec 
// Module          : WhatsApp.cod
// Module version  : 2.7.3204
// Class ID        : 14
// ########################################################


package com.whatsapp.client;


abstract public final class PrivacyBlockList extends Object
implements net.rim.device.api.util.Persistable

{

	// @@@@@@@@@@@@@ Fields 
	protected java.util.Hashtable /*java.util.Hashtable*/  _jids ; // ofs = 55214 addr = 0)
	protected java.util.Hashtable /*java.util.Hashtable*/  _names ; // ofs = 55218 addr = 0)
	public boolean /*boolean*/  _dirty ; // ofs = 55222 addr = 0)

	// @@@@@@@@@@@@@ Static routines 

public <init>( com.whatsapp.client.PrivacyBlockList ); // address: 0
	{
	enter_narrow 
	aload_0 
	invokespecial_lib java.lang.Object.<init> // pc=1
	aload_0 
	new_lib net.rim.device.api.system.Application//net.rim.device.api.system.Application net.rim.device.api.system.Application net.rim.device.api.system.Application
	dup 
	invokespecial_lib java.util.Hashtable.<init> // pc=1
	putfield .field_0_   // get_name_1:  .field_0_   // get_name_2:  .field_0_   // get_Name:    .field_0_   // getName->1:  null   // getName->2:  null   // getName->N:  null   // ofs = -1 ord = 0 addr = 0
	aload_0 
	new_lib net.rim.device.api.system.Application//net.rim.device.api.system.Application net.rim.device.api.system.Application net.rim.device.api.system.Application
	dup 
	invokespecial_lib java.util.Hashtable.<init> // pc=1
	putfield .field_1_1   // get_name_1:  .field_1_1   // get_name_2:  .field_1_1   // get_Name:    .field_1_1   // getName->1:  null   // getName->2:  null   // getName->N:  null   // ofs = -1 ord = 0 addr = 1
	aload_0 
	iconst_0 
	putfield .field_2_2   // get_name_1:  .field_2_2   // get_name_2:  .field_2_2   // get_Name:    .field_2_2   // getName->1:  null   // getName->2:  null   // getName->N:  null   // ofs = -1 ord = 0 addr = 2
	return 
	}

	// @@@@@@@@@@@@@ Virtual routines 

public final clearFromServer( com.whatsapp.client.PrivacyBlockList ); // address: 0
	{
	enter_narrow 
	aload_0_getfield .field_0_   // get_name_1:  .field_0_   // get_name_2:  .field_0_   // get_Name:    .field_0_   // getName->1:  null   // getName->2:  null   // getName->N:  null   // ofs = -1 ord = 0 addr = 0
	invokevirtual clear( java.util.Hashtable ) // pc=1
	aload_0 
	iconst_0 
	putfield .field_2_2   // get_name_1:  .field_2_2   // get_name_2:  .field_2_2   // get_Name:    .field_2_2   // getName->1:  null   // getName->2:  null   // getName->N:  null   // ofs = -1 ord = 0 addr = 2
	return 
	}


public final putFromServer( com.whatsapp.client.PrivacyBlockList, java.lang.String ); // address: 0
	{
	enter_narrow 
	aload_0_getfield .field_0_   // get_name_1:  .field_0_   // get_name_2:  .field_0_   // get_Name:    .field_0_   // getName->1:  null   // getName->2:  null   // getName->N:  null   // ofs = -1 ord = 0 addr = 0
	aload_1 
	aload_1 
	invokevirtual java.lang.Object put( java.util.Hashtable, java.lang.Object, java.lang.Object ) // pc=3
	pop 
	aload_0_getfield .field_1_1   // get_name_1:  .field_1_1   // get_name_2:  .field_1_1   // get_Name:    .field_1_1   // getName->1:  null   // getName->2:  null   // getName->N:  null   // ofs = -1 ord = 0 addr = 1
	aload_1 
	invokevirtual java.lang.Object get( java.util.Hashtable, java.lang.Object ) // pc=2
	ifnonnull Label18
	aload_1 
	invokestatic_lib module:WhatsApp-9.class#15.routine_8159(  ) // class#15
	astore_2 
	aload_0_getfield .field_1_1   // get_name_1:  .field_1_1   // get_name_2:  .field_1_1   // get_Name:    .field_1_1   // getName->1:  null   // getName->2:  null   // getName->N:  null   // ofs = -1 ord = 0 addr = 1
	aload_1 
	aload_2 
	invokevirtual java.lang.Object put( java.util.Hashtable, java.lang.Object, java.lang.Object ) // pc=3
	pop 
Label18:
	return 
	}


public final put( com.whatsapp.client.PrivacyBlockList, java.lang.String ); // address: 0
	{
	enter_narrow 
	aload_0 
	aload_1 
	invokenonvirtual com.whatsapp.client.PrivacyBlockList.putFromServer // pc=2
	aload_0 
	iconst_1 
	putfield .field_2_2   // get_name_1:  .field_2_2   // get_name_2:  .field_2_2   // get_Name:    .field_2_2   // getName->1:  null   // getName->2:  null   // getName->N:  null   // ofs = -1 ord = 0 addr = 2
	return 
	}


public final remove( com.whatsapp.client.PrivacyBlockList, java.lang.String ); // address: 0
	{
	enter_narrow 
	aload_0_getfield .field_0_   // get_name_1:  .field_0_   // get_name_2:  .field_0_   // get_Name:    .field_0_   // getName->1:  null   // getName->2:  null   // getName->N:  null   // ofs = -1 ord = 0 addr = 0
	aload_1 
	invokevirtual java.lang.Object remove( java.util.Hashtable, java.lang.Object ) // pc=2
	pop 
	aload_0 
	iconst_1 
	putfield .field_2_2   // get_name_1:  .field_2_2   // get_name_2:  .field_2_2   // get_Name:    .field_2_2   // getName->1:  null   // getName->2:  null   // getName->N:  null   // ofs = -1 ord = 0 addr = 2
	return 
	}


public final replace( com.whatsapp.client.PrivacyBlockList, java.util.Vector ); // address: 0
	{
	enter 
	aload_0_getfield .field_0_   // get_name_1:  .field_0_   // get_name_2:  .field_0_   // get_Name:    .field_0_   // getName->1:  null   // getName->2:  null   // getName->N:  null   // ofs = -1 ord = 0 addr = 0
	invokevirtual clear( java.util.Hashtable ) // pc=1
	iconst_0 
	istore_2 
Label5:
	iload_2 
	aload_1 
	invokevirtual int size( java.util.Vector ) // pc=1
	if_icmpge Label21
	aload_1 
	iload_2 
	invokevirtual java.lang.Object elementAt( java.util.Vector, int ) // pc=2
	checkcast_lib String//java.lang.String java.lang.String java.lang.String
	astore_3 
	aload_0_getfield .field_0_   // get_name_1:  .field_0_   // get_name_2:  .field_0_   // get_Name:    .field_0_   // getName->1:  null   // getName->2:  null   // getName->N:  null   // ofs = -1 ord = 0 addr = 0
	aload_3 
	aload_3 
	invokevirtual java.lang.Object put( java.util.Hashtable, java.lang.Object, java.lang.Object ) // pc=3
	pop 
	iinc 2 1
	goto Label5
Label21:
	aload_0 
	iconst_1 
	putfield .field_2_2   // get_name_1:  .field_2_2   // get_name_2:  .field_2_2   // get_Name:    .field_2_2   // getName->1:  null   // getName->2:  null   // getName->N:  null   // ofs = -1 ord = 0 addr = 2
	return 
	}


public final boolean isBlocked( com.whatsapp.client.PrivacyBlockList, java.lang.String ); // address: 0
	{
	enter_narrow 
	aload_0_getfield .field_0_   // get_name_1:  .field_0_   // get_name_2:  .field_0_   // get_Name:    .field_0_   // getName->1:  null   // getName->2:  null   // getName->N:  null   // ofs = -1 ord = 0 addr = 0
	aload_1 
	invokevirtual java.lang.Object get( java.util.Hashtable, java.lang.Object ) // pc=2
	ifnull Label7
	iconst_1 
	ireturn 
Label7:
	iconst_0 
	ireturn 
	}


public final java.util.Hashtable getHash( com.whatsapp.client.PrivacyBlockList ); // address: 0
	{
	areturn_field .field_0_   // get_name_1:  .field_0_   // get_name_2:  .field_0_   // get_Name:    .field_0_   // getName->1:  null   // getName->2:  null   // getName->N:  null   // ofs = -1 ord = 0 addr = 0
	}

}
